{
  "type": "Feature",
  "properties": {
    "gn:admin1_code":"27.0",
    "gn:asciiname":"Huyva",
    "gn:country_code":"UA",
    "gn:dem":217,
    "gn:feature_class":"P",
    "gn:feature_code":"PPL",
    "gn:name":"Huyva",
    "gn:population":0,
    "gn:timezone":"Europe/Kiev",
    "iso:country":"UA",
    "name:ukr_x_preferred":[
        "Huyva"
    ],
    "name:ukr_x_variant":[
        "\u0413\u0443\u0439\u0432\u0430"
    ],
    "name:und_x_variant":[
        "Khutor Guyva"
    ],
    "wof:name":"Huyva",
    "wof:placetype":"locality"
},
  "geometry": {"coordinates":[28.65778,50.21213],"type":"Point"}
}