{
  "type": "Feature",
  "properties": {
    "gn:admin1_code":"9.0",
    "gn:asciiname":"Lysohirka",
    "gn:country_code":"UA",
    "gn:dem":270,
    "gn:feature_class":"P",
    "gn:feature_code":"PPL",
    "gn:name":"Lysohirka",
    "gn:population":0,
    "gn:timezone":"Europe/Kiev",
    "iso:country":"UA",
    "name:und_x_variant":[
        "Lisogorka",
        "Lysogorka",
        "Lysohirka"
    ],
    "wof:name":"Lysohirka",
    "wof:placetype":"locality"
},
  "geometry": {"coordinates":[26.66749,48.99959000000001],"type":"Point"}
}