{
  "type": "Feature",
  "properties": {
    "gn:admin1_code":"19.0",
    "gn:asciiname":"Boyarka",
    "gn:country_code":"UA",
    "gn:dem":209,
    "gn:feature_class":"P",
    "gn:feature_code":"PPL",
    "gn:name":"Boyarka",
    "gn:population":0,
    "gn:timezone":"Europe/Kiev",
    "iso:country":"UA",
    "name:ara_x_preferred":[
        "\u0628\u0648\u064a\u0627\u0631\u0643\u0627"
    ],
    "name:azb_x_preferred":[
        "\u0628\u0648\u06cc\u0627\u0631\u06a9\u0627"
    ],
    "name:bel_x_preferred":[
        "\u0411\u043e\u044f\u0440\u043a\u0430"
    ],
    "name:ceb_x_preferred":[
        "Boyarka"
    ],
    "name:ces_x_preferred":[
        "Bojarka"
    ],
    "name:crh_x_preferred":[
        "Boyarka"
    ],
    "name:deu_x_preferred":[
        "Bojarka"
    ],
    "name:fas_x_preferred":[
        "\u0628\u0648\u06cc\u0627\u0631\u06a9\u0627"
    ],
    "name:fra_x_preferred":[
        "Bo\u00efarka"
    ],
    "name:hsb_x_preferred":[
        "Bojarka"
    ],
    "name:hye_x_preferred":[
        "\u0532\u0578\u0575\u0561\u0580\u056f\u0561"
    ],
    "name:ita_x_preferred":[
        "Bojarka"
    ],
    "name:kat_x_preferred":[
        "\u10d1\u10dd\u10d8\u10d0\u10e0\u10d9\u10d0"
    ],
    "name:lit_x_preferred":[
        "Bojarka"
    ],
    "name:nno_x_preferred":[
        "Bojarka"
    ],
    "name:pol_x_preferred":[
        "Bojarka"
    ],
    "name:ron_x_preferred":[
        "Boiarka"
    ],
    "name:rus_x_preferred":[
        "\u0411\u043e\u044f\u0440\u043a\u0430"
    ],
    "name:sah_x_preferred":[
        "\u0411\u043e\u044f\u0440\u043a\u0430"
    ],
    "name:srp_x_preferred":[
        "\u0411\u043e\u0458\u0430\u0440\u043a\u0430"
    ],
    "name:ukr_x_preferred":[
        "Boyarka"
    ],
    "name:ukr_x_variant":[
        "\u0411\u043e\u044f\u0440\u043a\u0430"
    ],
    "name:vie_x_preferred":[
        "Boyarka"
    ],
    "name:vie_x_variant":[
        "Boiarka"
    ],
    "name:zho_cn_x_preferred":[
        "\u535a\u4e9a\u5c14\u5361"
    ],
    "name:zho_tw_x_preferred":[
        "\u535a\u4e9e\u5361"
    ],
    "name:zho_x_preferred":[
        "\u535a\u4e9e\u723e\u5361"
    ],
    "wof:name":"Boyarka",
    "wof:placetype":"locality"
},
  "geometry": {"coordinates":[26.20925,50.61922],"type":"Point"}
}