{
  "type": "Feature",
  "properties": {
    "gn:admin1_code":"19.0",
    "gn:asciiname":"Boyarka",
    "gn:country_code":"UA",
    "gn:dem":209,
    "gn:feature_class":"P",
    "gn:feature_code":"PPL",
    "gn:name":"Boyarka",
    "gn:population":0,
    "gn:timezone":"Europe/Kiev",
    "iso:country":"UA",
    "name:ukr_x_preferred":[
        "Boyarka"
    ],
    "name:ukr_x_variant":[
        "\u0411\u043e\u044f\u0440\u043a\u0430"
    ],
    "wof:name":"Boyarka",
    "wof:placetype":"locality"
},
  "geometry": {"coordinates":[26.20925,50.61922],"type":"Point"}
}