{
  "type": "Feature",
  "properties": {
    "gn:admin1_code":"4.0",
    "gn:asciiname":"Verbove",
    "gn:country_code":"UA",
    "gn:dem":112,
    "gn:feature_class":"P",
    "gn:feature_code":"PPL",
    "gn:name":"Verbove",
    "gn:population":0,
    "gn:timezone":"Europe/Kiev",
    "iso:country":"UA",
    "name:ukr_x_preferred":[
        "Verbove"
    ],
    "name:ukr_x_variant":[
        "\u0412\u0435\u0440\u0431\u043e\u0432\u0435"
    ],
    "name:und_x_variant":[
        "Verbovka",
        "Verbovaya Vtoraya"
    ],
    "wof:name":"Verbove",
    "wof:placetype":"locality"
},
  "geometry": {"coordinates":[36.38388,47.87719],"type":"Point"}
}