{
  "type": "Feature",
  "properties": {
    "gn:admin1_code":"10.0",
    "gn:asciiname":"Yasynuvatka",
    "gn:country_code":"UA",
    "gn:dem":117,
    "gn:feature_class":"P",
    "gn:feature_code":"PPL",
    "gn:name":"Yasynuvatka",
    "gn:population":0,
    "gn:timezone":"Europe/Kiev",
    "iso:country":"UA",
    "name:ukr_x_preferred":[
        "Yasynuvatka"
    ],
    "name:ukr_x_variant":[
        "\u042f\u0441\u0438\u043d\u0443\u0432\u0430\u0442\u043a\u0430"
    ],
    "wof:name":"Yasynuvatka",
    "wof:placetype":"locality"
},
  "geometry": {"coordinates":[33.82076,48.84023],"type":"Point"}
}