{
  "type": "Feature",
  "properties": {
    "gn:admin1_code":"2.0",
    "gn:asciiname":"Khatylova Huta",
    "gn:country_code":"UA",
    "gn:dem":107,
    "gn:feature_class":"P",
    "gn:feature_code":"PPL",
    "gn:name":"Khatylova Huta",
    "gn:population":0,
    "gn:timezone":"Europe/Kiev",
    "iso:country":"UA",
    "name:ukr_x_preferred":[
        "Khatylova Huta"
    ],
    "name:ukr_x_variant":[
        "\u0425\u0430\u0442\u0438\u043b\u043e\u0432\u0430 \u0413\u0443\u0442\u0430"
    ],
    "name:und_x_variant":[
        "Khatilova Guta"
    ],
    "wof:name":"Khatylova Huta",
    "wof:placetype":"locality"
},
  "geometry": {"coordinates":[30.6937,51.30564],"type":"Point"}
}