{
  "type": "Feature",
  "properties": {
    "gn:admin1_code":"27.0",
    "gn:asciiname":"Hordiyivka",
    "gn:country_code":"UA",
    "gn:dem":278,
    "gn:feature_class":"P",
    "gn:feature_code":"PPL",
    "gn:name":"Hordiyivka",
    "gn:population":0,
    "gn:timezone":"Europe/Kiev",
    "iso:country":"UA",
    "name:ukr_x_preferred":[
        "Hordiyivka"
    ],
    "name:ukr_x_variant":[
        "\u0413\u043e\u0440\u0434\u0456\u0457\u0432\u043a\u0430"
    ],
    "name:und_x_variant":[
        "Gordeyevka"
    ],
    "wof:name":"Hordiyivka",
    "wof:placetype":"locality"
},
  "geometry": {"coordinates":[27.86696,50.05494],"type":"Point"}
}