{
  "type": "Feature",
  "properties": {
    "iso:country":"UA",
    "name:bel_x_preferred":[
        "\u0420\u0430\u043a\u0430 \u0423\u0431\u0430\u0440\u0446\u044c"
    ],
    "name:bel_x_variant":[
        "\u0423\u0431\u0430\u0440\u0446\u044c"
    ],
    "name:ceb_x_preferred":[
        "Ubort'"
    ],
    "name:ces_x_preferred":[
        "Ubor\u0165"
    ],
    "name:deu_x_preferred":[
        "Ubort"
    ],
    "name:deu_x_variant":[
        "Uhlja"
    ],
    "name:eng_x_preferred":[
        "Uglia"
    ],
    "name:epo_x_preferred":[
        "Uhlja"
    ],
    "name:est_x_preferred":[
        "Uglja"
    ],
    "name:fra_x_preferred":[
        "Oubort"
    ],
    "name:heb_x_preferred":[
        "\u05d0\u05d5\u05d4\u05dc\u05d9\u05d4"
    ],
    "name:hun_x_preferred":[
        "Uborty"
    ],
    "name:hun_x_variant":[
        "Uglya"
    ],
    "name:hye_x_preferred":[
        "\u0548\u0582\u0562\u0578\u0580\u057f"
    ],
    "name:hye_x_variant":[
        "\u0548\u0582\u0563\u056c\u0575\u0561"
    ],
    "name:lit_x_preferred":[
        "Ubort\u0117"
    ],
    "name:nld_x_preferred":[
        "Uglya"
    ],
    "name:nno_x_preferred":[
        "Ubort"
    ],
    "name:pol_x_preferred":[
        "Ubor\u0107"
    ],
    "name:ron_x_preferred":[
        "Uhlea"
    ],
    "name:rus_x_preferred":[
        "\u0423\u0431\u043e\u0440\u0442\u044c"
    ],
    "name:rus_x_variant":[
        "\u0423\u0433\u043b\u044f"
    ],
    "name:srp_x_preferred":[
        "\u0423\u0431\u043e\u0440\u0442"
    ],
    "name:swe_x_preferred":[
        "Ubarts"
    ],
    "name:ukr_x_preferred":[
        "\u0423\u0431\u043e\u0440\u0442\u044c"
    ],
    "name:ukr_x_variant":[
        "Uhlya",
        "\u0423\u0433\u043b\u044f"
    ],
    "name:unk_x_variant":[
        "Uglya"
    ],
    "name:zho_x_preferred":[
        "\u70cf\u535a\u723e\u5b63\u6cb3"
    ],
    "name:zho_x_variant":[
        "\u70cf\u683c\u5229\u4e9e"
    ],
    "qs:a0":"\u0423\u043a\u0440\u0430\u0457\u043d\u0430",
    "qs:a1":"*\u0417\u0430\u043a\u0430\u0440\u043f\u0430\u0442\u0441\u044c\u043a\u0430",
    "qs:a1_alt":"Zakarpats'ka",
    "qs:a1r":"0",
    "qs:a2":"\u0422\u044f\u0447\u0456\u0432\u0441\u044c\u043a\u0438\u0439",
    "qs:a2_alt":"Tiachivs'kyi",
    "qs:adm0":"\u0423\u043a\u0440\u0430\u0457\u043d\u0430",
    "qs:la_lc":"*",
    "qs:level":"locality",
    "qs:loc":"\u0423\u0433\u043b\u044f",
    "qs:loc_alt":"Uhlia",
    "qs:pop":0,
    "qs:type":"buffered point",
    "wd:wordcount":605,
    "wof:name":"\u0423\u0433\u043b\u044f",
    "wof:placetype":"locality"
},
  "geometry": {"coordinates":[23.628664,48.150184],"type":"Point"}
}