{
  "type": "Feature",
  "properties": {
    "gn:admin1_code":"14.0",
    "gn:asciiname":"Batyr",
    "gn:country_code":"UA",
    "gn:dem":204,
    "gn:feature_class":"P",
    "gn:feature_code":"PPL",
    "gn:name":"Batyr",
    "gn:population":0,
    "gn:timezone":"Europe/Zaporozhye",
    "iso:country":"UA",
    "name:epo_x_preferred":[
        "Batyr"
    ],
    "name:fra_x_preferred":[
        "Batyr"
    ],
    "name:kaz_x_preferred":[
        "\u0411\u0430\u0442\u044b\u0440"
    ],
    "name:lit_x_preferred":[
        "Batyras"
    ],
    "name:rus_x_preferred":[
        "\u0411\u0430\u0442\u044b\u0440"
    ],
    "name:ukr_x_preferred":[
        "Batyr"
    ],
    "name:ukr_x_variant":[
        "\u0411\u0430\u0442\u0438\u0440",
        "\u0421\u043b\u043e\u043d \u0411\u0430\u0442\u0438\u0440"
    ],
    "wof:name":"Batyr",
    "wof:placetype":"locality"
},
  "geometry": {"coordinates":[39.70029,48.17142],"type":"Point"}
}