{
  "type": "Feature",
  "properties": {
    "gn:admin1_code":"23.0",
    "gn:asciiname":"Druzhne",
    "gn:country_code":"UA",
    "gn:dem":269,
    "gn:feature_class":"P",
    "gn:feature_code":"PPL",
    "gn:name":"Druzhne",
    "gn:population":0,
    "gn:timezone":"Europe/Kiev",
    "iso:country":"UA",
    "name:rus_x_historical":[
        "\u041e\u0432\u0435\u0447\u0430\u0447\u0435"
    ],
    "name:rus_x_preferred":[
        "\u041e\u0432\u0435\u0447\u0430\u0447\u0435"
    ],
    "name:ukr_x_historical":[
        "\u041e\u0432\u0435\u0447\u0430\u0447\u0435"
    ],
    "name:ukr_x_preferred":[
        "\u041e\u0432\u0435\u0447\u0430\u0447\u0435"
    ],
    "name:ukr_x_variant":[
        "\u0414\u0440\u0443\u0436\u043d\u0435"
    ],
    "name:und_x_variant":[
        "Ovechache"
    ],
    "wof:name":"Druzhne",
    "wof:placetype":"locality"
},
  "geometry": {"coordinates":[28.81667,49.46667],"type":"Point"}
}