{
  "type": "Feature",
  "properties": {
    "gn:admin1_code":"9.0",
    "gn:asciiname":"Ripky",
    "gn:country_code":"UA",
    "gn:dem":270,
    "gn:feature_class":"P",
    "gn:feature_code":"PPL",
    "gn:name":"Ripky",
    "gn:population":0,
    "gn:timezone":"Europe/Kiev",
    "iso:country":"UA",
    "name:ukr_x_preferred":[
        "Ripky"
    ],
    "name:ukr_x_variant":[
        "\u0420\u0456\u043f\u043a\u0438"
    ],
    "name:und_x_variant":[
        "Ripki",
        "Repki"
    ],
    "wof:name":"Ripky",
    "wof:placetype":"locality"
},
  "geometry": {"coordinates":[26.89587,50.05099000000001],"type":"Point"}
}