{
  "type": "Feature",
  "properties": {
    "gn:admin1_code":"9.0",
    "gn:asciiname":"Ripky",
    "gn:country_code":"UA",
    "gn:dem":270,
    "gn:feature_class":"P",
    "gn:feature_code":"PPL",
    "gn:name":"Ripky",
    "gn:population":0,
    "gn:timezone":"Europe/Kiev",
    "iso:country":"UA",
    "name:bel_x_preferred":[
        "\u0420\u044b\u043f\u043a\u044b"
    ],
    "name:ceb_x_preferred":[
        "Ripky"
    ],
    "name:crh_x_preferred":[
        "Ripk\u0131"
    ],
    "name:deu_x_preferred":[
        "Ripky"
    ],
    "name:fin_x_preferred":[
        "Ripky"
    ],
    "name:hye_x_preferred":[
        "\u054c\u0565\u057a\u056f\u056b"
    ],
    "name:pol_x_preferred":[
        "Ripky"
    ],
    "name:ron_x_preferred":[
        "Ripk\u00ee"
    ],
    "name:rus_x_preferred":[
        "\u0420\u0435\u043f\u043a\u0438"
    ],
    "name:sah_x_preferred":[
        "\u0420\u0435\u043f\u043a\u0438"
    ],
    "name:ukr_x_preferred":[
        "Ripky"
    ],
    "name:ukr_x_variant":[
        "\u0420\u0456\u043f\u043a\u0438"
    ],
    "name:und_x_variant":[
        "Ripki",
        "Repki"
    ],
    "name:zho_x_preferred":[
        "\u91cc\u666e\u57fa"
    ],
    "wof:name":"Ripky",
    "wof:placetype":"locality"
},
  "geometry": {"coordinates":[26.89587,50.05099000000001],"type":"Point"}
}