{
  "type": "Feature",
  "properties": {
    "gn:admin1_code":"8.0",
    "gn:asciiname":"Perekop",
    "gn:country_code":"UA",
    "gn:dem":12,
    "gn:feature_class":"P",
    "gn:feature_code":"PPL",
    "gn:name":"Perekop",
    "gn:population":0,
    "gn:timezone":"Europe/Kiev",
    "iso:country":"UA",
    "name:aze_x_preferred":[
        "Or Qap\u0131"
    ],
    "name:bul_x_preferred":[
        "\u041f\u0435\u0440\u0435\u043a\u043e\u043f"
    ],
    "name:cat_x_preferred":[
        "Perekop"
    ],
    "name:ceb_x_preferred":[
        "Perekop"
    ],
    "name:crh_x_preferred":[
        "Or Qap\u0131"
    ],
    "name:deu_x_preferred":[
        "Perekop"
    ],
    "name:ell_x_preferred":[
        "\u03a0\u03b5\u03c1\u03b5\u03ba\u03cc\u03c0"
    ],
    "name:est_x_preferred":[
        "Perekop"
    ],
    "name:fra_x_preferred":[
        "Perekop"
    ],
    "name:hye_x_preferred":[
        "\u054a\u0565\u0580\u0565\u056f\u0578\u057a"
    ],
    "name:jpn_x_preferred":[
        "\u30da\u30ec\u30b3\u30fc\u30d7"
    ],
    "name:nor_x_preferred":[
        "Perekop"
    ],
    "name:pol_x_preferred":[
        "Perekop"
    ],
    "name:ron_x_preferred":[
        "Perekop"
    ],
    "name:rus_x_preferred":[
        "\u041f\u0435\u0440\u0435\u043a\u043e\u043f"
    ],
    "name:spa_x_preferred":[
        "Perekop"
    ],
    "name:swe_x_preferred":[
        "Perekop"
    ],
    "name:tat_x_preferred":[
        "Ur Qapqa"
    ],
    "name:tur_x_preferred":[
        "Perekop"
    ],
    "name:ukr_x_preferred":[
        "Perekop"
    ],
    "name:ukr_x_variant":[
        "\u041f\u0435\u0440\u0435\u043a\u043e\u043f"
    ],
    "name:urd_x_preferred":[
        "\u067e\u06cc\u0631\u06cc\u06a9\u0648\u067e"
    ],
    "wof:name":"Perekop",
    "wof:placetype":"locality"
},
  "geometry": {"coordinates":[35.02471,46.31582],"type":"Point"}
}