{
  "type": "Feature",
  "properties": {
    "gn:admin1_code":"8.0",
    "gn:asciiname":"Perekop",
    "gn:country_code":"UA",
    "gn:dem":12,
    "gn:feature_class":"P",
    "gn:feature_code":"PPL",
    "gn:name":"Perekop",
    "gn:population":0,
    "gn:timezone":"Europe/Kiev",
    "iso:country":"UA",
    "name:ukr_x_preferred":[
        "Perekop"
    ],
    "name:ukr_x_variant":[
        "\u041f\u0435\u0440\u0435\u043a\u043e\u043f"
    ],
    "wof:name":"Perekop",
    "wof:placetype":"locality"
},
  "geometry": {"coordinates":[35.02471,46.31582],"type":"Point"}
}