{
  "type": "Feature",
  "properties": {
    "gn:admin1_code":"7.0",
    "gn:asciiname":"Golubovka",
    "gn:country_code":"UA",
    "gn:dem":138,
    "gn:feature_class":"P",
    "gn:feature_code":"PPL",
    "gn:name":"Golubovka",
    "gn:population":0,
    "gn:timezone":"Europe/Kiev",
    "iso:country":"UA",
    "wof:name":"Golubovka",
    "wof:placetype":"locality"
},
  "geometry": {"coordinates":[37.49083,49.44361],"type":"Point"}
}