{
  "type": "Feature",
  "properties": {
    "gn:admin1_code":"8.0",
    "gn:asciiname":"Prydniprovs'ke",
    "gn:country_code":"UA",
    "gn:dem":18,
    "gn:feature_class":"P",
    "gn:feature_code":"PPL",
    "gn:name":"Prydniprovs\u2019ke",
    "gn:population":0,
    "gn:timezone":"Europe/Kiev",
    "iso:country":"UA",
    "name:ukr_x_preferred":[
        "Prydniprovs\u2019ke"
    ],
    "name:ukr_x_variant":[
        "\u041f\u0440\u0438\u0434\u043d\u0456\u043f\u0440\u043e\u0432\u0441\u044c\u043a\u0435"
    ],
    "name:und_x_variant":[
        "Pridneprovskoye"
    ],
    "wof:name":"Prydniprovs'ke",
    "wof:placetype":"locality"
},
  "geometry": {"coordinates":[32.79482,46.679],"type":"Point"}
}