{
  "type": "Feature",
  "properties": {
    "gn:admin1_code":"13.0",
    "gn:asciiname":"Sulymivka",
    "gn:country_code":"UA",
    "gn:dem":103,
    "gn:feature_class":"P",
    "gn:feature_code":"PPL",
    "gn:name":"Sulymivka",
    "gn:population":0,
    "gn:timezone":"Europe/Kiev",
    "iso:country":"UA",
    "name:ukr_x_preferred":[
        "Sulymivka"
    ],
    "name:ukr_x_variant":[
        "\u0421\u0443\u043b\u0438\u043c\u0456\u0432\u043a\u0430"
    ],
    "name:und_x_variant":[
        "Sulimovka"
    ],
    "wof:name":"Sulymivka",
    "wof:placetype":"locality"
},
  "geometry": {"coordinates":[31.19369,50.39666],"type":"Point"}
}