{
  "type": "Feature",
  "properties": {
    "gn:admin1_code":"24.0",
    "gn:asciiname":"Zapokovnoye",
    "gn:country_code":"UA",
    "gn:dem":152,
    "gn:feature_class":"P",
    "gn:feature_code":"PPL",
    "gn:name":"Zapokovnoye",
    "gn:population":0,
    "gn:timezone":"Europe/Kiev",
    "iso:country":"UA",
    "name:rus_x_preferred":[
        "\u0417\u0430\u043f\u043e\u043a\u043e\u0432\u043d\u043e\u0435"
    ],
    "name:und_x_variant":[
        "Zapokive",
        "Zapokov\u2019ye",
        "Zapokovnoye"
    ],
    "wof:name":"Zapokovnoye",
    "wof:placetype":"locality"
},
  "geometry": {"coordinates":[24.41667,51.85],"type":"Point"}
}