{
  "type": "Feature",
  "properties": {
    "gn:admin1_code":"2.0",
    "gn:asciiname":"Rozl'oty",
    "gn:country_code":"UA",
    "gn:dem":128,
    "gn:feature_class":"P",
    "gn:feature_code":"PPL",
    "gn:name":"Rozl\u2019oty",
    "gn:population":0,
    "gn:timezone":"Europe/Kiev",
    "iso:country":"UA",
    "name:eng_x_preferred":[
        "Razl\u00ebty"
    ],
    "name:rus_x_preferred":[
        "\u0420\u0430\u0437\u043b\u0435\u0442\u044b"
    ],
    "name:rus_x_variant":[
        "Rozl\u00ebty"
    ],
    "name:ukr_x_preferred":[
        "Rozl\u2019oty"
    ],
    "name:ukr_x_variant":[
        "\u0420\u043e\u0437\u043b\u044c\u043e\u0442\u0438"
    ],
    "wof:name":"Rozl'oty",
    "wof:placetype":"locality"
},
  "geometry": {"coordinates":[33.14009,51.70684],"type":"Point"}
}