{
  "type": "Feature",
  "properties": {
    "gn:admin1_code":"2.0",
    "gn:asciiname":"Kovpinka",
    "gn:country_code":"UA",
    "gn:dem":136,
    "gn:feature_class":"P",
    "gn:feature_code":"PPL",
    "gn:name":"Kovpinka",
    "gn:population":0,
    "gn:timezone":"Europe/Kiev",
    "iso:country":"UA",
    "name:ukr_x_preferred":[
        "Kovpynka"
    ],
    "name:ukr_x_variant":[
        "\u041a\u043e\u0432\u043f\u0438\u043d\u043a\u0430",
        "Kolpinka",
        "Kalpina"
    ],
    "name:und_x_variant":[
        "Kovpinka"
    ],
    "wof:name":"Kovpinka",
    "wof:placetype":"locality"
},
  "geometry": {"coordinates":[33.26081,52.21773],"type":"Point"}
}