{
  "type": "Feature",
  "properties": {
    "gn:admin1_code":"6.0",
    "gn:asciiname":"Lukvytsya",
    "gn:country_code":"UA",
    "gn:dem":594,
    "gn:feature_class":"P",
    "gn:feature_code":"PPL",
    "gn:name":"Lukvytsya",
    "gn:population":0,
    "gn:timezone":"Europe/Kiev",
    "iso:country":"UA",
    "name:ukr_x_preferred":[
        "Lukvytsya"
    ],
    "name:ukr_x_variant":[
        "\u041b\u0443\u043a\u0432\u0438\u0446\u044f"
    ],
    "name:und_x_variant":[
        "Prislup",
        "Pristup",
        "Lukvitsa",
        "Lukvycja"
    ],
    "wof:name":"Lukvytsya",
    "wof:placetype":"locality"
},
  "geometry": {"coordinates":[24.25322,48.74263],"type":"Point"}
}