{
  "type": "Feature",
  "properties": {
    "gn:admin1_code":"24.0",
    "gn:asciiname":"Pidhaytsi",
    "gn:country_code":"UA",
    "gn:dem":218,
    "gn:feature_class":"P",
    "gn:feature_code":"PPL",
    "gn:name":"Pidhaytsi",
    "gn:population":0,
    "gn:timezone":"Europe/Kiev",
    "iso:country":"UA",
    "name:ukr_x_preferred":[
        "Pidhaytsi"
    ],
    "name:ukr_x_variant":[
        "\u041f\u0456\u0434\u0433\u0430\u0439\u0446\u0456"
    ],
    "name:und_x_variant":[
        "Podhajce",
        "Podgaytse"
    ],
    "wof:name":"Pidhaytsi",
    "wof:placetype":"locality"
},
  "geometry": {"coordinates":[24.47406,50.80182],"type":"Point"}
}