{
  "type": "Feature",
  "properties": {
    "iso:country":"UA",
    "name:eng_x_preferred":[
        "Monastyrishche"
    ],
    "name:rus_x_preferred":[
        "\u041c\u043e\u043d\u0430\u0441\u0442\u044b\u0440\u0438\u0449\u0435"
    ],
    "name:ukr_x_preferred":[
        "Monastyryshche"
    ],
    "name:ukr_x_variant":[
        "\u041c\u043e\u043d\u0430\u0441\u0442\u0438\u0440\u0438\u0449\u0435"
    ],
    "qs:a0":"\u0423\u043a\u0440\u0430\u0457\u043d\u0430",
    "qs:a1":"*\u0427\u0435\u0440\u043d\u0456\u0433\u0456\u0432\u0441\u044c\u043a\u0430",
    "qs:a1_alt":"Chernihivs'ka",
    "qs:a1r":"0",
    "qs:a2":"\u0406\u0447\u043d\u044f\u043d\u0441\u044c\u043a\u0438\u0439",
    "qs:a2_alt":"Ichnians'kyi",
    "qs:adm0":"\u0423\u043a\u0440\u0430\u0457\u043d\u0430",
    "qs:la_lc":"*",
    "qs:level":"locality",
    "qs:loc":"\u041c\u043e\u043d\u0430\u0441\u0442\u0438\u0440\u0438\u0449\u0435",
    "qs:loc_alt":"Monastyrysche",
    "qs:pop":0,
    "qs:type":"buffered point",
    "wd:wordcount":34,
    "wof:name":"\u041c\u043e\u043d\u0430\u0441\u0442\u0438\u0440\u0438\u0449\u0435",
    "wof:placetype":"locality"
},
  "geometry": {"coordinates":[32.154216,50.812464],"type":"Point"}
}