{
  "type": "Feature",
  "properties": {
    "gn:admin1_code":"23.0",
    "gn:asciiname":"Verbova",
    "gn:country_code":"UA",
    "gn:dem":233,
    "gn:feature_class":"P",
    "gn:feature_code":"PPL",
    "gn:name":"Verbova",
    "gn:population":0,
    "gn:timezone":"Europe/Kiev",
    "iso:country":"UA",
    "name:ukr_x_preferred":[
        "\u0412\u0435\u0440\u0431\u043e\u0432\u0430"
    ],
    "name:und_x_variant":[
        "Verbovaya"
    ],
    "wof:name":"Verbova",
    "wof:placetype":"locality"
},
  "geometry": {"coordinates":[28.74532,48.50476],"type":"Point"}
}