{
  "type": "Feature",
  "properties": {
    "iso:country":"UA",
    "name:ara_x_preferred":[
        "\u0641\u064a\u0644\u064a\u0643\u064a \u0633\u0648\u0631\u0648\u062a\u0634\u064a\u0646\u062a\u0633\u064a"
    ],
    "name:ceb_x_preferred":[
        "Velyki Sorochyntsi"
    ],
    "name:ces_x_preferred":[
        "Velyki Soro\u010dynci"
    ],
    "name:dan_x_preferred":[
        "Velikije Sorotjintsy"
    ],
    "name:deu_x_preferred":[
        "Welyki Sorotschynzi"
    ],
    "name:eng_x_preferred":[
        "Velyki Sorochyntsi"
    ],
    "name:fas_x_preferred":[
        "\u0648\u0644\u06cc\u06a9\u06cc \u0633\u0631\u0686\u06cc\u0646\u062a\u0633\u06cc"
    ],
    "name:fra_x_preferred":[
        "Velyki Sorotchintsy"
    ],
    "name:fra_x_variant":[
        "Velyki Sorochyntsi"
    ],
    "name:hye_x_preferred":[
        "\u054e\u0565\u056c\u056b\u056f\u056b\u0565 \u054d\u0578\u0580\u0578\u0579\u056b\u0576\u0581\u056b"
    ],
    "name:ita_x_preferred":[
        "Velyki Soro\u010dynci"
    ],
    "name:jpn_x_preferred":[
        "\u30f4\u30a7\u30eb\u30a3\u30fc\u30ad\u30fb\u30bd\u30ed\u30fc\u30c1\u30f3\u30c4\u30a3"
    ],
    "name:kat_x_preferred":[
        "\u10d5\u10d4\u10da\u10d8\u10d9\u10d8\u10d4-\u10e1\u10dd\u10e0\u10dd\u10e9\u10d8\u10dc\u10ea\u10d8"
    ],
    "name:lav_x_preferred":[
        "Veliki Soro\u010dinci"
    ],
    "name:nld_x_preferred":[
        "Velyki Sorochyntsi"
    ],
    "name:pol_x_preferred":[
        "Wielkie Soroczy\u0144ce"
    ],
    "name:ron_x_preferred":[
        "Vel\u00eeki Soroci\u00een\u021bi"
    ],
    "name:rus_x_preferred":[
        "\u0412\u0435\u043b\u0438\u043a\u0438\u0435 \u0421\u043e\u0440\u043e\u0447\u0438\u043d\u0446\u044b"
    ],
    "name:slv_x_preferred":[
        "Veliki Soro\u010dnici"
    ],
    "name:ukr_x_preferred":[
        "\u0412\u0435\u043b\u0438\u043a\u0456 \u0421\u043e\u0440\u043e\u0447\u0438\u043d\u0446\u0456"
    ],
    "name:zho_x_preferred":[
        "\u5927\u7d22\u7f85\u6b3d\u9f4a"
    ],
    "qs:a0":"\u0423\u043a\u0440\u0430\u0457\u043d\u0430",
    "qs:a1":"*\u041f\u043e\u043b\u0442\u0430\u0432\u0441\u044c\u043a\u0430",
    "qs:a1_alt":"Poltavs'ka",
    "qs:a1r":"0",
    "qs:a2":"\u041c\u0438\u0440\u0433\u043e\u0440\u043e\u0434\u0441\u044c\u043a\u0438\u0439",
    "qs:a2_alt":"Myrhorods'kyi",
    "qs:adm0":"\u0423\u043a\u0440\u0430\u0457\u043d\u0430",
    "qs:la_lc":"*",
    "qs:level":"locality",
    "qs:loc":"\u0412\u0435\u043b\u0438\u043a\u0456 \u0421\u043e\u0440\u043e\u0447\u0438\u043d\u0446\u0456",
    "qs:loc_alt":"Velyki Sorochyntsi",
    "qs:pop":0,
    "qs:type":"buffered point",
    "wd:wordcount":641,
    "wof:name":"\u0412\u0435\u043b\u0438\u043a\u0456 \u0421\u043e\u0440\u043e\u0447\u0438\u043d\u0446\u0456",
    "wof:placetype":"locality"
},
  "geometry": {"coordinates":[33.948437,50.01532],"type":"Point"}
}