{
  "type": "Feature",
  "properties": {
    "gn:admin1_code":"15.0",
    "gn:asciiname":"Okulki",
    "gn:cc2":"UA",
    "gn:country_code":"UA",
    "gn:dem":232,
    "gn:feature_class":"P",
    "gn:feature_code":"PPL",
    "gn:name":"Okulki",
    "gn:population":0,
    "gn:timezone":"Europe/Kiev",
    "iso:country":"UA",
    "name:und_x_variant":[
        "Okolki",
        "Okulki"
    ],
    "wof:name":"Okulki",
    "wof:placetype":"locality"
},
  "geometry": {"coordinates":[23.48333,49.76667],"type":"Point"}
}