{
  "type": "Feature",
  "properties": {
    "gn:admin1_code":"14.0",
    "gn:asciiname":"Pidhorivka",
    "gn:country_code":"UA",
    "gn:dem":60,
    "gn:feature_class":"P",
    "gn:feature_code":"PPL",
    "gn:name":"Pidhorivka",
    "gn:population":0,
    "gn:timezone":"Europe/Zaporozhye",
    "iso:country":"UA",
    "name:eng_x_preferred":[
        "Podgorovka"
    ],
    "name:rus_x_preferred":[
        "\u041f\u043e\u0434\u0433\u043e\u0440\u043e\u0432\u043a\u0430"
    ],
    "name:ukr_x_preferred":[
        "Pidhorivka"
    ],
    "name:und_x_variant":[
        "Podzorovka"
    ],
    "wof:name":"Pidhorivka",
    "wof:placetype":"locality"
},
  "geometry": {"coordinates":[38.88652,49.30803],"type":"Point"}
}