{
  "type": "Feature",
  "properties": {
    "gn:admin1_code":"15.0",
    "gn:asciiname":"Verbizh",
    "gn:country_code":"UA",
    "gn:dem":257,
    "gn:feature_class":"P",
    "gn:feature_code":"PPL",
    "gn:name":"Verbizh",
    "gn:population":0,
    "gn:timezone":"Europe/Kiev",
    "iso:country":"UA",
    "name:ukr_x_preferred":[
        "Verbizh"
    ],
    "name:ukr_x_variant":[
        "\u0412\u0435\u0440\u0431\u0456\u0436"
    ],
    "wof:name":"Verbizh",
    "wof:placetype":"locality"
},
  "geometry": {"coordinates":[23.8951,49.54617],"type":"Point"}
}