{
  "type": "Feature",
  "properties": {
    "gn:admin1_code":"24.0",
    "gn:asciiname":"Pirvanche",
    "gn:country_code":"UA",
    "gn:dem":226,
    "gn:feature_class":"P",
    "gn:feature_code":"PPL",
    "gn:name":"Pirvanche",
    "gn:population":0,
    "gn:timezone":"Europe/Kiev",
    "iso:country":"UA",
    "name:ukr_x_preferred":[
        "Pirvanche"
    ],
    "name:ukr_x_variant":[
        "\u041f\u0456\u0440\u0432\u0430\u043d\u0447\u0435"
    ],
    "name:und_x_variant":[
        "Porvan\u2019che"
    ],
    "wof:name":"Pirvanche",
    "wof:placetype":"locality"
},
  "geometry": {"coordinates":[24.70259,50.50265],"type":"Point"}
}