{
  "type": "Feature",
  "properties": {
    "gn:admin1_code":"4.0",
    "gn:asciiname":"Dibrivka",
    "gn:country_code":"UA",
    "gn:dem":136,
    "gn:feature_class":"P",
    "gn:feature_code":"PPL",
    "gn:name":"Dibrivka",
    "gn:population":0,
    "gn:timezone":"Europe/Kiev",
    "iso:country":"UA",
    "name:ukr_x_preferred":[
        "Dibrivka"
    ],
    "name:ukr_x_variant":[
        "\u0414\u0456\u0431\u0440\u0456\u0432\u043a\u0430"
    ],
    "name:und_x_variant":[
        "Dibrovka"
    ],
    "wof:name":"Dibrivka",
    "wof:placetype":"locality"
},
  "geometry": {"coordinates":[35.78127999999999,48.21292],"type":"Point"}
}