{
  "type": "Feature",
  "properties": {
    "gn:admin1_code":"15.0",
    "gn:asciiname":"Sykhiv",
    "gn:country_code":"UA",
    "gn:dem":294,
    "gn:feature_class":"P",
    "gn:feature_code":"PPL",
    "gn:name":"Sykhiv",
    "gn:population":0,
    "gn:timezone":"Europe/Kiev",
    "iso:country":"UA",
    "name:rus_x_preferred":[
        "\u0421\u044b\u0445\u043e\u0432"
    ],
    "name:ukr_x_preferred":[
        "\u0421\u0438\u0445\u0456\u0432"
    ],
    "name:und_x_variant":[
        "Sykhov"
    ],
    "wof:name":"Sykhiv",
    "wof:placetype":"locality"
},
  "geometry": {"coordinates":[24.03069,49.21306],"type":"Point"}
}