{
  "type": "Feature",
  "properties": {
    "gn:admin1_code":"22.0",
    "gn:asciiname":"Vorobeyevka",
    "gn:country_code":"UA",
    "gn:dem":302,
    "gn:feature_class":"P",
    "gn:feature_code":"PPL",
    "gn:name":"Vorobeyevka",
    "gn:population":0,
    "gn:timezone":"Europe/Kiev",
    "iso:country":"UA",
    "name:und_x_variant":[
        "Vorobiyuvka",
        "Vorobeyevka"
    ],
    "wof:name":"Vorobeyevka",
    "wof:placetype":"locality"
},
  "geometry": {"coordinates":[26.18757,49.62008],"type":"Point"}
}