{
  "type": "Feature",
  "properties": {
    "gn:admin1_code":"15.0",
    "gn:asciiname":"Podgaychiki",
    "gn:country_code":"UA",
    "gn:dem":278,
    "gn:feature_class":"P",
    "gn:feature_code":"PPL",
    "gn:name":"Podgaychiki",
    "gn:population":0,
    "gn:timezone":"Europe/Kiev",
    "iso:country":"UA",
    "wof:name":"Podgaychiki",
    "wof:placetype":"locality"
},
  "geometry": {"coordinates":[23.51244,49.6475],"type":"Point"}
}