{
  "type": "Feature",
  "properties": {
    "iso:country":"UA",
    "name:deu_x_preferred":[
        "Kusmyn"
    ],
    "name:eng_x_preferred":[
        "Kuzmyn"
    ],
    "name:hye_x_preferred":[
        "\u053f\u0578\u0582\u0566\u0574\u056b\u0576"
    ],
    "name:ron_x_preferred":[
        "Kuzm\u00een"
    ],
    "name:rus_x_preferred":[
        "\u041a\u0443\u0437\u044c\u043c\u0438\u043d"
    ],
    "name:slv_x_preferred":[
        "Kuzmin"
    ],
    "name:ukr_x_preferred":[
        "Kuz\u2019myn"
    ],
    "name:ukr_x_variant":[
        "\u041a\u0443\u0437\u044c\u043c\u0438\u043d"
    ],
    "name:und_x_variant":[
        "Kuz\u2019min"
    ],
    "name:zho_x_preferred":[
        "\u5eab\u6fdf\u660e"
    ],
    "qs:a0":"\u0423\u043a\u0440\u0430\u0457\u043d\u0430",
    "qs:a1":"*\u0425\u043c\u0435\u043b\u044c\u043d\u0438\u0446\u044c\u043a\u0430",
    "qs:a1_alt":"Khmel'nyts'ka",
    "qs:a1r":"0",
    "qs:a2":"\u041a\u0440\u0430\u0441\u0438\u043b\u0456\u0432\u0441\u044c\u043a\u0438\u0439",
    "qs:a2_alt":"Krasylivs'kyi",
    "qs:adm0":"\u0423\u043a\u0440\u0430\u0457\u043d\u0430",
    "qs:la_lc":"*",
    "qs:level":"locality",
    "qs:loc":"\u041a\u0443\u0437\u044c\u043c\u0438\u043d",
    "qs:loc_alt":"Kuz'myn",
    "qs:pop":0,
    "qs:type":"buffered point",
    "wd:wordcount":355,
    "wof:name":"\u041a\u0443\u0437\u044c\u043c\u0438\u043d",
    "wof:placetype":"locality"
},
  "geometry": {"coordinates":[27.083705,49.692406],"type":"Point"}
}