{
  "type": "Feature",
  "properties": {
    "gn:admin1_code":"8.0",
    "gn:asciiname":"Anatolivka",
    "gn:country_code":"UA",
    "gn:dem":71,
    "gn:feature_class":"P",
    "gn:feature_code":"PPL",
    "gn:name":"Anatolivka",
    "gn:population":0,
    "gn:timezone":"Europe/Kiev",
    "iso:country":"UA",
    "name:ukr_x_preferred":[
        "Anatolivka"
    ],
    "name:ukr_x_variant":[
        "\u0410\u043d\u0430\u0442\u043e\u043b\u0456\u0432\u043a\u0430"
    ],
    "name:und_x_variant":[
        "Anatolevka",
        "Anatol\u2019yevka"
    ],
    "wof:name":"Anatolivka",
    "wof:placetype":"locality"
},
  "geometry": {"coordinates":[34.49215,47.0773],"type":"Point"}
}