{
  "type": "Feature",
  "properties": {
    "gn:admin1_code":"7.0",
    "gn:asciiname":"Ryabushkin",
    "gn:country_code":"UA",
    "gn:dem":162,
    "gn:feature_class":"P",
    "gn:feature_code":"PPL",
    "gn:name":"Ryabushkin",
    "gn:population":0,
    "gn:timezone":"Europe/Kiev",
    "iso:country":"UA",
    "wof:name":"Ryabushkin",
    "wof:placetype":"locality"
},
  "geometry": {"coordinates":[37.28222,50.20278],"type":"Point"}
}