{
  "type": "Feature",
  "properties": {
    "gn:admin1_code":"7.0",
    "gn:asciiname":"Stroyivka",
    "gn:country_code":"UA",
    "gn:dem":179,
    "gn:feature_class":"P",
    "gn:feature_code":"PPL",
    "gn:name":"Stroyivka",
    "gn:population":0,
    "gn:timezone":"Europe/Kiev",
    "iso:country":"UA",
    "name:rus_x_preferred":[
        "\u0421\u0442\u0440\u043e\u0435\u0432\u043a\u0430"
    ],
    "name:ukr_x_preferred":[
        "Stroyivka"
    ],
    "name:ukr_x_variant":[
        "\u0421\u0442\u0440\u043e\u0457\u0432\u043a\u0430"
    ],
    "name:und_x_variant":[
        "Stroyevka"
    ],
    "wof:name":"Stroyivka",
    "wof:placetype":"locality"
},
  "geometry": {"coordinates":[37.87777,50.04276],"type":"Point"}
}