{
  "type": "Feature",
  "properties": {
    "gn:admin1_code":"14.0",
    "gn:asciiname":"Makogonovka",
    "gn:country_code":"UA",
    "gn:dem":79,
    "gn:feature_class":"P",
    "gn:feature_code":"PPL",
    "gn:name":"Makogonovka",
    "gn:population":0,
    "gn:timezone":"Europe/Zaporozhye",
    "iso:country":"UA",
    "wof:name":"Makogonovka",
    "wof:placetype":"locality"
},
  "geometry": {"coordinates":[37.97056,49.20611],"type":"Point"}
}