{
  "type": "Feature",
  "properties": {
    "gn:admin1_code":"22.0",
    "gn:asciiname":"Narayuv Ves'",
    "gn:country_code":"UA",
    "gn:dem":298,
    "gn:feature_class":"P",
    "gn:feature_code":"PPL",
    "gn:name":"Narayuv Ves\u2019",
    "gn:population":0,
    "gn:timezone":"Europe/Kiev",
    "iso:country":"UA",
    "wof:name":"Narayuv Ves'",
    "wof:placetype":"locality"
},
  "geometry": {"coordinates":[24.78333,49.51667],"type":"Point"}
}