{
  "type": "Feature",
  "properties": {
    "gn:admin1_code":"15.0",
    "gn:asciiname":"Stronevichi",
    "gn:country_code":"UA",
    "gn:dem":233,
    "gn:feature_class":"P",
    "gn:feature_code":"PPL",
    "gn:name":"Stronevichi",
    "gn:population":0,
    "gn:timezone":"Europe/Kiev",
    "iso:country":"UA",
    "name:und_x_variant":[
        "Strunevichi",
        "Stronevitse",
        "Stronevichi"
    ],
    "wof:name":"Stronevichi",
    "wof:placetype":"locality"
},
  "geometry": {"coordinates":[22.90219,49.69697],"type":"Point"}
}