{
  "type": "Feature",
  "properties": {
    "iso:country":"UA",
    "name:eng_x_preferred":[
        "Vil'khivka"
    ],
    "name:epo_x_preferred":[
        "Vilj\u0125ivka"
    ],
    "name:heb_x_preferred":[
        "\u05d5\u05d9\u05dc\u05d7\u05d9\u05d1\u05e7\u05d4"
    ],
    "name:hun_x_preferred":[
        "\u00d6lyv\u00f6s"
    ],
    "name:hye_x_preferred":[
        "\u0555\u056c\u056d\u0578\u057e\u056f\u0561"
    ],
    "name:nld_x_preferred":[
        "\u00d6lyv\u00f6s"
    ],
    "name:ron_x_preferred":[
        "Vilhivka"
    ],
    "name:rus_x_preferred":[
        "Vil\u2019khovka"
    ],
    "name:rus_x_variant":[
        "\u041e\u043b\u044c\u0445\u043e\u0432\u043a\u0430"
    ],
    "name:ukr_x_preferred":[
        "Vil\u2019khivka"
    ],
    "name:ukr_x_variant":[
        "\u0412\u0456\u043b\u044c\u0445\u0456\u0432\u043a\u0430"
    ],
    "name:und_x_variant":[
        "Ol\u2019khovka"
    ],
    "name:zho_x_preferred":[
        "\u7dad\u5229\u5e0c\u592b\u5361"
    ],
    "qs:a0":"\u0423\u043a\u0440\u0430\u0457\u043d\u0430",
    "qs:a1":"*\u0417\u0430\u043a\u0430\u0440\u043f\u0430\u0442\u0441\u044c\u043a\u0430",
    "qs:a1_alt":"Zakarpats'ka",
    "qs:a1r":"0",
    "qs:a2":"\u0406\u0440\u0448\u0430\u0432\u0441\u044c\u043a\u0438\u0439",
    "qs:a2_alt":"Irshavs'kyi",
    "qs:adm0":"\u0423\u043a\u0440\u0430\u0457\u043d\u0430",
    "qs:la_lc":"*",
    "qs:level":"locality",
    "qs:loc":"\u0412\u0456\u043b\u044c\u0445\u0456\u0432\u043a\u0430",
    "qs:loc_alt":"Vil'khivka",
    "qs:pop":0,
    "qs:type":"buffered point",
    "wof:name":"\u0412\u0456\u043b\u044c\u0445\u0456\u0432\u043a\u0430",
    "wof:placetype":"locality"
},
  "geometry": {"coordinates":[23.070637,48.268817],"type":"Point"}
}