{
  "type": "Feature",
  "properties": {
    "gn:admin1_code":"17.0",
    "gn:asciiname":"Maloploske",
    "gn:country_code":"UA",
    "gn:dem":81,
    "gn:feature_class":"P",
    "gn:feature_code":"PPL",
    "gn:name":"Maloploske",
    "gn:population":0,
    "gn:timezone":"Europe/Kiev",
    "iso:country":"UA",
    "name:ukr_x_preferred":[
        "Maloploske"
    ],
    "name:ukr_x_variant":[
        "\u041c\u0430\u043b\u043e\u043f\u043b\u043e\u0441\u043a\u0435"
    ],
    "name:und_x_variant":[
        "Maloye Ploskoye",
        "Maloploskoye"
    ],
    "wof:name":"Maloploske",
    "wof:placetype":"locality"
},
  "geometry": {"coordinates":[29.74151,47.01259],"type":"Point"}
}