{
  "type": "Feature",
  "properties": {
    "gn:admin1_code":"2.0",
    "gn:asciiname":"Novopetrivs'ke",
    "gn:country_code":"UA",
    "gn:dem":172,
    "gn:feature_class":"P",
    "gn:feature_code":"PPL",
    "gn:name":"Novopetrivs\u2019ke",
    "gn:population":0,
    "gn:timezone":"Europe/Kiev",
    "iso:country":"UA",
    "name:ukr_x_preferred":[
        "Novopetrivs\u2019ke"
    ],
    "name:ukr_x_variant":[
        "\u041d\u043e\u0432\u043e\u043f\u0435\u0442\u0440\u0456\u0432\u0441\u044c\u043a\u0435"
    ],
    "name:und_x_variant":[
        "Novopetrovskoye"
    ],
    "wof:name":"Novopetrivs'ke",
    "wof:placetype":"locality"
},
  "geometry": {"coordinates":[33.04320999999999,50.83103],"type":"Point"}
}