{
  "type": "Feature",
  "properties": {
    "gn:admin1_code":"27.0",
    "gn:asciiname":"Smoldyriv",
    "gn:country_code":"UA",
    "gn:dem":216,
    "gn:feature_class":"P",
    "gn:feature_code":"PPL",
    "gn:name":"Smoldyriv",
    "gn:population":0,
    "gn:timezone":"Europe/Kiev",
    "iso:country":"UA",
    "name:ukr_x_preferred":[
        "Smoldyriv"
    ],
    "name:ukr_x_variant":[
        "\u0421\u043c\u043e\u043b\u0434\u0438\u0440\u0456\u0432"
    ],
    "name:und_x_variant":[
        "Smoldyrev"
    ],
    "wof:name":"Smoldyriv",
    "wof:placetype":"locality"
},
  "geometry": {"coordinates":[27.59924,50.42298],"type":"Point"}
}