{
  "type": "Feature",
  "properties": {
    "gn:admin1_code":"15.0",
    "gn:asciiname":"Gaye",
    "gn:country_code":"UA",
    "gn:dem":256,
    "gn:feature_class":"P",
    "gn:feature_code":"PPL",
    "gn:name":"Gaye",
    "gn:population":0,
    "gn:timezone":"Europe/Kiev",
    "iso:country":"UA",
    "name:cat_x_preferred":[
        "Gaye"
    ],
    "name:ceb_x_preferred":[
        "Gaye"
    ],
    "name:eus_x_preferred":[
        "Gaye"
    ],
    "name:fra_x_preferred":[
        "Gaye"
    ],
    "name:hun_x_preferred":[
        "Gaye"
    ],
    "name:ita_x_preferred":[
        "Gaye"
    ],
    "name:lat_x_preferred":[
        "Gaye"
    ],
    "name:mlg_x_preferred":[
        "Gaye"
    ],
    "name:msa_x_preferred":[
        "Gaye"
    ],
    "name:nld_x_preferred":[
        "Gaye"
    ],
    "name:oci_x_preferred":[
        "Gaye"
    ],
    "name:pol_x_preferred":[
        "Gaye"
    ],
    "name:ron_x_preferred":[
        "Gaye"
    ],
    "name:slk_x_preferred":[
        "Gaye"
    ],
    "name:spa_x_preferred":[
        "Gaye"
    ],
    "name:swe_x_preferred":[
        "Gaye"
    ],
    "name:ukr_x_preferred":[
        "\u0413\u0435"
    ],
    "name:vie_x_preferred":[
        "Gaye"
    ],
    "name:vol_x_preferred":[
        "Gaye"
    ],
    "name:war_x_preferred":[
        "Gaye"
    ],
    "wof:name":"Gaye",
    "wof:placetype":"locality"
},
  "geometry": {"coordinates":[24.26575,49.76586],"type":"Point"}
}