{
  "type": "Feature",
  "properties": {
    "iso:country":"UA",
    "name:eng_x_preferred":[
        "Raygorodka"
    ],
    "name:ger_x_preferred":[
        "Rajhorodka"
    ],
    "name:lav_x_preferred":[
        "Rajhorodka"
    ],
    "name:rum_x_preferred":[
        "Raihorodka"
    ],
    "name:rus_x_preferred":[
        "\u0420\u0430\u0439\u0433\u043e\u0440\u043e\u0434\u043a\u0430"
    ],
    "name:ukr_x_preferred":[
        "\u0420\u0430\u0439\u0433\u043e\u0440\u043e\u0434\u043a\u0430"
    ],
    "name:unk_x_variant":[
        "Raygorodka"
    ],
    "qs:a0":"\u0423\u043a\u0440\u0430\u0457\u043d\u0430",
    "qs:a1":"*\u041b\u0443\u0433\u0430\u043d\u0441\u044c\u043a\u0430",
    "qs:a1_alt":"Luhans'ka",
    "qs:a1r":"0",
    "qs:a2":"\u041d\u043e\u0432\u043e\u0430\u0439\u0434\u0430\u0440\u0441\u044c\u043a\u0438\u0439",
    "qs:a2_alt":"Novoaidars'kyi",
    "qs:adm0":"\u0423\u043a\u0440\u0430\u0457\u043d\u0430",
    "qs:la_lc":"*",
    "qs:level":"locality",
    "qs:loc":"\u0420\u0430\u0439\u0433\u043e\u0440\u043e\u0434\u043a\u0430",
    "qs:loc_alt":"Raihorodka",
    "qs:pop":0,
    "qs:type":"buffered point",
    "wof:name":"\u0420\u0430\u0439\u0433\u043e\u0440\u043e\u0434\u043a\u0430",
    "wof:placetype":"locality"
},
  "geometry": {"coordinates":[39.092039,48.807183],"type":"Point"}
}