{
  "type": "Feature",
  "properties": {
    "gn:admin1_code":"6.0",
    "gn:asciiname":"Pshenychnyky",
    "gn:country_code":"UA",
    "gn:dem":536,
    "gn:feature_class":"P",
    "gn:feature_code":"PPL",
    "gn:name":"Pshenychnyky",
    "gn:population":0,
    "gn:timezone":"Europe/Kiev",
    "iso:country":"UA",
    "name:ukr_x_preferred":[
        "Pshenychnyky"
    ],
    "name:ukr_x_variant":[
        "\u041f\u0448\u0435\u043d\u0438\u0447\u043d\u0438\u043a\u0438"
    ],
    "name:und_x_variant":[
        "Pshenichniki"
    ],
    "wof:name":"Pshenychnyky",
    "wof:placetype":"locality"
},
  "geometry": {"coordinates":[23.8671,48.89442],"type":"Point"}
}