{
  "type": "Feature",
  "properties": {
    "gn:admin1_code":"10",
    "gn:asciiname":"Davydovka",
    "gn:country_code":"UA",
    "gn:dem":128,
    "gn:feature_class":"P",
    "gn:feature_code":"PPL",
    "gn:name":"Davydovka",
    "gn:population":0,
    "gn:timezone":"Europe/Kiev",
    "iso:country":"UA",
    "name:ukr_x_preferred":[
        "\u0414\u0430\u0432\u0438\u0434\u0456\u0432\u043a\u0430"
    ],
    "wof:name":"Davydovka",
    "wof:placetype":"locality"
},
  "geometry": {"coordinates":[30.53169,48.46621],"type":"Point"}
}