{
  "type": "Feature",
  "properties": {
    "gn:admin1_code":"17.0",
    "gn:asciiname":"Kalantayivka",
    "gn:country_code":"UA",
    "gn:dem":91,
    "gn:feature_class":"P",
    "gn:feature_code":"PPL",
    "gn:name":"Kalantayivka",
    "gn:population":0,
    "gn:timezone":"Europe/Kiev",
    "iso:country":"UA",
    "name:ukr_x_preferred":[
        "Kalantayivka"
    ],
    "name:ukr_x_variant":[
        "\u041a\u0430\u043b\u0430\u043d\u0442\u0430\u0457\u0432\u043a\u0430"
    ],
    "name:und_x_variant":[
        "Kolontaivka",
        "Kalantayevka"
    ],
    "wof:name":"Kalantayivka",
    "wof:placetype":"locality"
},
  "geometry": {"coordinates":[30.27977000000001,46.7208],"type":"Point"}
}