{
  "type": "Feature",
  "properties": {
    "gn:admin1_code":"5.0",
    "gn:asciiname":"Bilosarays'ka Kosa",
    "gn:country_code":"UA",
    "gn:dem":1,
    "gn:feature_class":"P",
    "gn:feature_code":"PPL",
    "gn:name":"Bilosarays\u2019ka Kosa",
    "gn:population":0,
    "gn:timezone":"Europe/Kiev",
    "iso:country":"UA",
    "name:eng_x_preferred":[
        "Bilosarays'ka Kosa"
    ],
    "name:rus_x_preferred":[
        "\u0411\u0435\u043b\u043e\u0441\u0430\u0440\u0430\u0439\u0441\u043a\u0430\u044f \u041a\u043e\u0441\u0430"
    ],
    "name:ukr_x_preferred":[
        "\u0411\u0456\u043b\u043e\u0441\u0430\u0440\u0430\u0439\u0441\u044c\u043a\u0430 \u041a\u043e\u0441\u0430"
    ],
    "name:und_x_variant":[
        "Belosarayskaya Kosa",
        "Belosarayka",
        "Bilosarays\u2019ka Kosa"
    ],
    "wof:name":"Bilosarays'ka Kosa",
    "wof:placetype":"locality"
},
  "geometry": {"coordinates":[37.3467,46.90298],"type":"Point"}
}