{
  "type": "Feature",
  "properties": {
    "gn:admin1_code":"27.0",
    "gn:asciiname":"Khodachky",
    "gn:country_code":"UA",
    "gn:dem":186,
    "gn:feature_class":"P",
    "gn:feature_code":"PPL",
    "gn:name":"Khodachky",
    "gn:population":0,
    "gn:timezone":"Europe/Kiev",
    "iso:country":"UA",
    "name:ukr_x_preferred":[
        "Khodachky"
    ],
    "name:ukr_x_variant":[
        "\u0425\u043e\u0434\u0430\u0447\u043a\u0438"
    ],
    "name:und_x_variant":[
        "Khodachki"
    ],
    "wof:name":"Khodachky",
    "wof:placetype":"locality"
},
  "geometry": {"coordinates":[28.62822,50.89621],"type":"Point"}
}