{
  "type": "Feature",
  "properties": {
    "gn:admin1_code":"25.0",
    "gn:asciiname":"Zahorb",
    "gn:country_code":"UA",
    "gn:dem":575,
    "gn:feature_class":"P",
    "gn:feature_code":"PPL",
    "gn:name":"Zahorb",
    "gn:population":0,
    "gn:timezone":"Europe/Uzhgorod",
    "iso:country":"UA",
    "name:ukr_x_preferred":[
        "Zahorb"
    ],
    "name:ukr_x_variant":[
        "\u0417\u0430\u0433\u043e\u0440\u0431"
    ],
    "name:und_x_variant":[
        "Zagorb"
    ],
    "wof:name":"Zahorb",
    "wof:placetype":"locality"
},
  "geometry": {"coordinates":[22.66587,49.01628],"type":"Point"}
}