{
  "type": "Feature",
  "properties": {
    "gn:population":15646,
    "iso:country":"UA",
    "name:bel_x_preferred":[
        "\u041d\u043e\u0432\u044b\u0439 \u0411\u0443\u0433"
    ],
    "name:bel_x_variant":[
        "\u041d\u043e\u0432\u044b \u0411\u0443\u0433"
    ],
    "name:bul_x_preferred":[
        "\u041d\u043e\u0432\u0438 \u0411\u0443\u0433"
    ],
    "name:ceb_x_preferred":[
        "Novyy Buh"
    ],
    "name:crh_x_preferred":[
        "Nov\u0131y Bug"
    ],
    "name:deu_x_preferred":[
        "Nowyj Buh"
    ],
    "name:eng_x_preferred":[
        "Novyi Buh"
    ],
    "name:fas_x_preferred":[
        "\u0646\u0648\u0648\u06cc\u06cc \u0628\u0648\u0647"
    ],
    "name:fra_x_preferred":[
        "Novy\u00ef Bouh"
    ],
    "name:heb_x_preferred":[
        "\u05e0\u05d5\u05d1\u05d9 \u05d1\u05d5\u05d4"
    ],
    "name:hsb_x_preferred":[
        "Nowyj Buh"
    ],
    "name:hye_x_preferred":[
        "\u0546\u0578\u057e\u056b \u0532\u0578\u0582\u0563"
    ],
    "name:hye_x_variant":[
        "\u0546\u0578\u057e\u056b\u0575 \u0532\u0578\u0582\u0563"
    ],
    "name:ita_x_preferred":[
        "Novyj Buh"
    ],
    "name:jpn_x_preferred":[
        "\u30ce\u30fc\u30f4\u30a3\u30a4\u30fb\u30d6\u30d5"
    ],
    "name:kat_x_preferred":[
        "\u10dc\u10dd\u10d5\u10d8-\u10d1\u10e3\u10d2\u10d8"
    ],
    "name:lav_x_preferred":[
        "Novijbuha"
    ],
    "name:nno_x_preferred":[
        "Novyj Buh"
    ],
    "name:pol_x_preferred":[
        "Nowy Boh"
    ],
    "name:ron_x_preferred":[
        "Nov\u00eei Buh"
    ],
    "name:rus_x_preferred":[
        "\u041d\u043e\u0432\u044b\u0439 \u0411\u0443\u0433"
    ],
    "name:rus_x_variant":[
        "\u041d\u043e\u0432\u0438\u0439 \u0411\u0443\u0433"
    ],
    "name:sco_x_preferred":[
        "Novyi Buh"
    ],
    "name:tat_x_preferred":[
        "\u041d\u043e\u0432\u044b\u0439-\u0411\u0443\u04bb"
    ],
    "name:ukr_x_preferred":[
        "\u041d\u043e\u0432\u0438\u0439 \u0411\u0443\u0433"
    ],
    "name:und_x_variant":[
        "Novi Bug"
    ],
    "name:vie_x_preferred":[
        "Novyi Buh"
    ],
    "name:zho_x_preferred":[
        "\u8afe\u7dad\u5e03\u683c"
    ],
    "qs:a0":"\u0423\u043a\u0440\u0430\u0457\u043d\u0430",
    "qs:a1":"*\u041c\u0438\u043a\u043e\u043b\u0430\u0457\u0432\u0441\u044c\u043a\u0430",
    "qs:a1_alt":"Mykolaivs'ka",
    "qs:a1r":"0",
    "qs:a2":"\u041d\u043e\u0432\u043e\u0431\u0443\u0437\u044c\u043a\u0438\u0439",
    "qs:a2_alt":"Novobuz'kyi",
    "qs:adm0":"\u0423\u043a\u0440\u0430\u0457\u043d\u0430",
    "qs:la_lc":"*",
    "qs:level":"locality",
    "qs:loc":"\u041d\u043e\u0432\u0438\u0439 \u0411\u0443\u0433",
    "qs:loc_alt":"Novyi Buh",
    "qs:pop":0,
    "qs:type":"buffered point",
    "wd:wordcount":84,
    "wof:name":"\u041d\u043e\u0432\u0438\u0439 \u0411\u0443\u0433",
    "wof:placetype":"locality",
    "wof:population":15646
},
  "geometry": {"coordinates":[32.520632,47.685708],"type":"Point"}
}