{
  "type": "Feature",
  "properties": {
    "gn:gn_country":"UA",
    "gn:gn_fcode":"PPL",
    "gn:gn_pop":462,
    "gn:population":466,
    "iso:country":"UA",
    "name:chi_x_preferred":[
        "\u6c83\u65af\u970d\u5fb7"
    ],
    "name:dut_x_preferred":[
        "Voskhod"
    ],
    "name:eng_x_preferred":[
        "Voskhod"
    ],
    "name:epo_x_preferred":[
        "Vos\u0125odo"
    ],
    "name:rus_x_preferred":[
        "\u0412\u043e\u0441\u0445\u043e\u0434"
    ],
    "name:ukr_x_preferred":[
        "\u0412\u043e\u0441\u0445\u043e\u0434"
    ],
    "qs_pg:aaroncc":"UA",
    "qs_pg:gn_country":"UA",
    "qs_pg:gn_fcode":"PPL",
    "qs_pg:gn_pop":462,
    "qs_pg:name":"Voskhod",
    "qs_pg:photos_9r":0,
    "qs_pg:photos_sr":0,
    "qs_pg:pop_sr":2,
    "qs_pg:qs_pg_placetype":"locality",
    "wof:name":"Voskhod",
    "wof:placetype":"locality",
    "wof:population":466
},
  "geometry": {"coordinates":[34.21694,44.51726],"type":"Point"}
}