{
  "type": "Feature",
  "properties": {
    "gn:population":10920,
    "iso:country":"UA",
    "name:ceb_x_preferred":[
        "Shyroke"
    ],
    "name:crh_x_preferred":[
        "\u015e\u0131roke"
    ],
    "name:deu_x_preferred":[
        "Schyroke"
    ],
    "name:eng_x_preferred":[
        "Shyroke"
    ],
    "name:fra_x_preferred":[
        "Chyroke"
    ],
    "name:hye_x_preferred":[
        "\u0547\u056b\u0580\u0578\u056f\u0578\u0565"
    ],
    "name:lav_x_preferred":[
        "\u0160iroke"
    ],
    "name:pol_x_preferred":[
        "Szyroke"
    ],
    "name:ron_x_preferred":[
        "\u0218\u00eeroke"
    ],
    "name:rus_x_preferred":[
        "\u0428\u0438\u0440\u043e\u043a\u0435"
    ],
    "name:rus_x_variant":[
        "\u0428\u0438\u0440\u043e\u043a\u043e\u0435"
    ],
    "name:ukr_x_preferred":[
        "\u0428\u0438\u0440\u043e\u043a\u0435"
    ],
    "name:unk_x_variant":[
        "Shirokoye"
    ],
    "name:zho_x_preferred":[
        "\u5e0c\u7f85\u514b"
    ],
    "qs:a0":"\u0423\u043a\u0440\u0430\u0457\u043d\u0430",
    "qs:a1":"*\u0414\u043d\u0456\u043f\u0440\u043e\u043f\u0435\u0442\u0440\u043e\u0432\u0441\u044c\u043a\u0430",
    "qs:a1_alt":"Dnipropetrovs'ka",
    "qs:a1r":"0",
    "qs:a2":"\u0428\u0438\u0440\u043e\u043a\u0456\u0432\u0441\u044c\u043a\u0438\u0439",
    "qs:a2_alt":"Shyrokivs'kyi",
    "qs:adm0":"\u0423\u043a\u0440\u0430\u0457\u043d\u0430",
    "qs:la_lc":"*",
    "qs:level":"locality",
    "qs:loc":"\u0428\u0438\u0440\u043e\u043a\u0435",
    "qs:loc_alt":"Shyroke",
    "qs:pop":0,
    "qs:type":"buffered point",
    "wof:name":"\u0428\u0438\u0440\u043e\u043a\u0435",
    "wof:placetype":"locality",
    "wof:population":10920
},
  "geometry": {"coordinates":[33.266328,47.691439],"type":"Point"}
}