{
  "type": "Feature",
  "properties": {
    "gn:admin1_code":"09",
    "gn:asciiname":"Holubcha",
    "gn:country_code":"UA",
    "gn:dem":288,
    "gn:feature_class":"P",
    "gn:feature_code":"PPL",
    "gn:name":"Holubcha",
    "gn:population":0,
    "gn:timezone":"Europe/Kiev",
    "iso:country":"UA",
    "name:ukr_x_preferred":[
        "Holubcha"
    ],
    "name:ukr_x_variant":[
        "\u0413\u043e\u043b\u0443\u0431\u0447\u0430"
    ],
    "wof:name":"Holubcha",
    "wof:placetype":"locality"
},
  "geometry": {"coordinates":[27.34011,49.93131],"type":"Point"}
}