{
  "type": "Feature",
  "properties": {
    "gn:admin1_code":"4.0",
    "gn:asciiname":"Zatyshne",
    "gn:country_code":"UA",
    "gn:dem":144,
    "gn:feature_class":"P",
    "gn:feature_code":"PPL",
    "gn:name":"Zatyshne",
    "gn:population":0,
    "gn:timezone":"Europe/Kiev",
    "iso:country":"UA",
    "name:ukr_x_preferred":[
        "Zatyshne"
    ],
    "name:ukr_x_variant":[
        "\u0417\u0430\u0442\u0438\u0448\u043d\u0435"
    ],
    "wof:name":"Zatyshne",
    "wof:placetype":"locality"
},
  "geometry": {"coordinates":[34.24432,48.2057],"type":"Point"}
}