{
  "type": "Feature",
  "properties": {
    "gn:admin1_code":"4.0",
    "gn:asciiname":"Chervonyy Mayak",
    "gn:country_code":"UA",
    "gn:dem":66,
    "gn:feature_class":"P",
    "gn:feature_code":"PPL",
    "gn:name":"Chervonyy Mayak",
    "gn:population":0,
    "gn:timezone":"Europe/Kiev",
    "iso:country":"UA",
    "name:ukr_x_preferred":[
        "Chervonyy Mayak"
    ],
    "name:ukr_x_variant":[
        "\u0427\u0435\u0440\u0432\u043e\u043d\u0438\u0439 \u041c\u0430\u044f\u043a"
    ],
    "wof:name":"Chervonyy Mayak",
    "wof:placetype":"locality"
},
  "geometry": {"coordinates":[34.66324,48.25085],"type":"Point"}
}