{
  "type": "Feature",
  "properties": {
    "gn:admin1_code":"11.0",
    "gn:admin2_code":"700018",
    "gn:admin3_code":"11152972.0",
    "gn:asciiname":"Kirsanovka",
    "gn:country_code":"UA",
    "gn:dem":15,
    "gn:elevation":"13.0",
    "gn:feature_class":"P",
    "gn:feature_code":"PPL",
    "gn:name":"Kirsanovka",
    "gn:population":299,
    "gn:timezone":"Europe/Simferopol",
    "iso:country":"UA",
    "name:eng_x_preferred":[
        "Kirsanovka"
    ],
    "name:rus_x_historical":[
        "\u0411\u0438\u0439\u0433\u0430\u0437\u044b\u0301"
    ],
    "name:rus_x_preferred":[
        "\u041a\u0438\u0440\u0441\u0430\u043d\u043e\u0432\u043a\u0430"
    ],
    "name:rus_x_variant":[
        "\u0411\u0438\u0439\u0433\u0430\u0437\u044b\u0301"
    ],
    "name:ukr_x_preferred":[
        "\u041a\u0438\u0440\u0441\u0430\u043d\u0456\u0432\u043a\u0430"
    ],
    "wof:name":"Kirsanovka",
    "wof:placetype":"locality",
    "wof:population":299
},
  "geometry": {"coordinates":[34.81402,45.49329],"type":"Point"}
}