{
  "type": "Feature",
  "properties": {
    "gn:admin1_code":"18.0",
    "gn:asciiname":"Myrony",
    "gn:country_code":"UA",
    "gn:dem":86,
    "gn:feature_class":"P",
    "gn:feature_code":"PPL",
    "gn:name":"Myrony",
    "gn:population":0,
    "gn:timezone":"Europe/Kiev",
    "iso:country":"UA",
    "name:ukr_x_preferred":[
        "Myrony"
    ],
    "name:ukr_x_variant":[
        "\u041c\u0438\u0440\u043e\u043d\u0438"
    ],
    "wof:name":"Myrony",
    "wof:placetype":"locality"
},
  "geometry": {"coordinates":[32.77769,49.62264],"type":"Point"}
}