{
  "type": "Feature",
  "properties": {
    "gn:admin1_code":"4.0",
    "gn:asciiname":"Panasivka",
    "gn:country_code":"UA",
    "gn:dem":97,
    "gn:feature_class":"P",
    "gn:feature_code":"PPL",
    "gn:name":"Panasivka",
    "gn:population":0,
    "gn:timezone":"Europe/Kiev",
    "iso:country":"UA",
    "name:rus_x_preferred":[
        "Afanas\u2019yevka"
    ],
    "name:rus_x_variant":[
        "\u041f\u0430\u043d\u0430\u0441\u043e\u0432\u043a\u0430"
    ],
    "name:ukr_x_preferred":[
        "Panasivka"
    ],
    "name:ukr_x_variant":[
        "\u041f\u0430\u043d\u0430\u0441\u0456\u0432\u043a\u0430"
    ],
    "name:und_x_variant":[
        "Panasovka"
    ],
    "wof:name":"Panasivka",
    "wof:placetype":"locality"
},
  "geometry": {"coordinates":[35.54087,48.95116],"type":"Point"}
}