{
  "type": "Feature",
  "properties": {
    "gn:population":6889,
    "iso:country":"UA",
    "name:crh_x_preferred":[
        "Piskivka"
    ],
    "name:deu_x_preferred":[
        "Piskiwka"
    ],
    "name:eng_x_preferred":[
        "Piskivka"
    ],
    "name:ron_x_preferred":[
        "Piskivka"
    ],
    "name:rus_x_preferred":[
        "\u041f\u0435\u0441\u043a\u043e\u0432\u043a\u0430"
    ],
    "name:rus_x_variant":[
        "\u041f\u0456\u0441\u043a\u0456\u0432\u043a\u0430"
    ],
    "name:sah_x_preferred":[
        "\u041f\u0435\u0441\u043a\u043e\u0432\u043a\u0430"
    ],
    "name:sco_x_preferred":[
        "Piskivka"
    ],
    "name:ukr_x_preferred":[
        "\u041f\u0456\u0441\u043a\u0456\u0432\u043a\u0430"
    ],
    "name:unk_x_variant":[
        "Peskovka"
    ],
    "name:zho_x_preferred":[
        "\u76ae\u65af\u57fa\u592b\u5361"
    ],
    "qs:a0":"\u0423\u043a\u0440\u0430\u0457\u043d\u0430",
    "qs:a1":"*\u041a\u0438\u0457\u0432\u0441\u044c\u043a\u0430",
    "qs:a1_alt":"Kyivs'ka",
    "qs:a1r":"0",
    "qs:a2":"\u0411\u043e\u0440\u043e\u0434\u044f\u043d\u0441\u044c\u043a\u0438\u0439",
    "qs:a2_alt":"Borodians'kyi",
    "qs:adm0":"\u0423\u043a\u0440\u0430\u0457\u043d\u0430",
    "qs:la_lc":"*",
    "qs:level":"locality",
    "qs:loc":"\u041f\u0456\u0441\u043a\u0456\u0432\u043a\u0430",
    "qs:loc_alt":"Piskivka",
    "qs:pop":0,
    "qs:type":"buffered point",
    "wd:wordcount":73,
    "wof:name":"\u041f\u0456\u0441\u043a\u0456\u0432\u043a\u0430",
    "wof:placetype":"locality",
    "wof:population":6889
},
  "geometry": {"coordinates":[29.583606,50.694005],"type":"Point"}
}