{
  "type": "Feature",
  "properties": {
    "gn:admin1_code":"19.0",
    "gn:asciiname":"Uhlyshche",
    "gn:country_code":"UA",
    "gn:dem":173,
    "gn:feature_class":"P",
    "gn:feature_code":"PPL",
    "gn:name":"Uhlyshche",
    "gn:population":0,
    "gn:timezone":"Europe/Kiev",
    "iso:country":"UA",
    "name:ukr_x_preferred":[
        "Uhlyshche"
    ],
    "name:ukr_x_variant":[
        "\u0423\u0433\u043b\u0438\u0449\u0435"
    ],
    "name:und_x_variant":[
        "Uglishche"
    ],
    "wof:name":"Uhlyshche",
    "wof:placetype":"locality"
},
  "geometry": {"coordinates":[26.04885,50.82703],"type":"Point"}
}