{
  "type": "Feature",
  "properties": {
    "gn:admin1_code":"15.0",
    "gn:asciiname":"Koropets",
    "gn:country_code":"UA",
    "gn:dem":326,
    "gn:feature_class":"P",
    "gn:feature_code":"PPL",
    "gn:name":"Koropets",
    "gn:population":0,
    "gn:timezone":"Europe/Kiev",
    "iso:country":"UA",
    "name:bel_x_preferred":[
        "\u041a\u0430\u0440\u0430\u043f\u044d\u0446\u044c"
    ],
    "name:crh_x_preferred":[
        "Koropets"
    ],
    "name:deu_x_preferred":[
        "Koropez"
    ],
    "name:fra_x_preferred":[
        "Koropets"
    ],
    "name:pol_x_preferred":[
        "Koropiec"
    ],
    "name:ron_x_preferred":[
        "Korope\u021b"
    ],
    "name:rus_x_preferred":[
        "\u041a\u043e\u0440\u043e\u043f\u0435\u0446"
    ],
    "name:szl_x_preferred":[
        "Koropjec"
    ],
    "name:ukr_x_preferred":[
        "\u041a\u043e\u0440\u043e\u043f\u0435\u0446\u044c"
    ],
    "name:zho_x_preferred":[
        "\u79d1\u7f85\u4f69\u9f4a"
    ],
    "wof:name":"Koropets",
    "wof:placetype":"locality"
},
  "geometry": {"coordinates":[24.88675,49.6704],"type":"Point"}
}