{
  "type": "Feature",
  "properties": {
    "gn:admin1_code":"15.0",
    "gn:asciiname":"Koropets",
    "gn:country_code":"UA",
    "gn:dem":326,
    "gn:feature_class":"P",
    "gn:feature_code":"PPL",
    "gn:name":"Koropets",
    "gn:population":0,
    "gn:timezone":"Europe/Kiev",
    "iso:country":"UA",
    "wof:name":"Koropets",
    "wof:placetype":"locality"
},
  "geometry": {"coordinates":[24.88675,49.6704],"type":"Point"}
}