{
  "type": "Feature",
  "properties": {
    "gn:admin1_code":"23.0",
    "gn:asciiname":"Dubovaya",
    "gn:country_code":"UA",
    "gn:dem":348,
    "gn:feature_class":"P",
    "gn:feature_code":"PPL",
    "gn:name":"Dubovaya",
    "gn:population":0,
    "gn:timezone":"Europe/Kiev",
    "iso:country":"UA",
    "name:che_x_preferred":[
        "\u0414\u0443\u0431\u043e\u0432\u0438"
    ],
    "name:rus_x_preferred":[
        "\u0414\u0443\u0431\u043e\u0432\u0430\u044f"
    ],
    "wof:name":"Dubovaya",
    "wof:placetype":"locality"
},
  "geometry": {"coordinates":[27.92426,49.20673],"type":"Point"}
}