{
  "type": "Feature",
  "properties": {
    "gn:admin1_code":"21.0",
    "gn:asciiname":"Kovtunove",
    "gn:country_code":"UA",
    "gn:dem":148,
    "gn:feature_class":"P",
    "gn:feature_code":"PPL",
    "gn:name":"Kovtunove",
    "gn:population":0,
    "gn:timezone":"Europe/Kiev",
    "iso:country":"UA",
    "name:ukr_x_preferred":[
        "Kovtunove"
    ],
    "name:ukr_x_variant":[
        "\u041a\u043e\u0432\u0442\u0443\u043d\u043e\u0432\u0435"
    ],
    "name:und_x_variant":[
        "Kovtunovo"
    ],
    "wof:name":"Kovtunove",
    "wof:placetype":"locality"
},
  "geometry": {"coordinates":[33.40984,51.84105],"type":"Point"}
}