{
  "type": "Feature",
  "properties": {
    "gn:population":23679,
    "iso:country":"UA",
    "name:ara_x_preferred":[
        "\u0645\u0627\u0631\u064a\u0641\u0627"
    ],
    "name:arm_x_preferred":[
        "\u0544\u0565\u0580\u0565\u0586\u0561"
    ],
    "name:bel_x_variant":[
        "\u041c\u044d\u0440\u044d\u0444\u0430"
    ],
    "name:ces_x_preferred":[
        "Merefa"
    ],
    "name:chi_x_preferred":[
        "\u6885\u5217\u6cd5"
    ],
    "name:crh_x_preferred":[
        "Merefa"
    ],
    "name:cze_x_preferred":[
        "Merefa"
    ],
    "name:deu_x_preferred":[
        "Merefa"
    ],
    "name:dut_x_preferred":[
        "Merefa"
    ],
    "name:eng_x_preferred":[
        "Merefa"
    ],
    "name:fas_x_preferred":[
        "\u0645\u0631\u0641\u0627"
    ],
    "name:fra_x_preferred":[
        "Merefa"
    ],
    "name:fre_x_preferred":[
        "Merefa"
    ],
    "name:geo_x_preferred":[
        "\u10db\u10d4\u10e0\u10d4\u10e4\u10d0"
    ],
    "name:ger_x_preferred":[
        "Merefa"
    ],
    "name:hsb_x_preferred":[
        "Merefa"
    ],
    "name:hye_x_preferred":[
        "\u0544\u0565\u0580\u0565\u0586\u0561"
    ],
    "name:ita_x_preferred":[
        "Merefa"
    ],
    "name:kat_x_preferred":[
        "\u10db\u10d4\u10e0\u10d4\u10e4\u10d0"
    ],
    "name:lit_x_preferred":[
        "Merefa"
    ],
    "name:nno_x_preferred":[
        "Merefa"
    ],
    "name:per_x_preferred":[
        "\u0645\u0631\u0641\u0627"
    ],
    "name:pol_x_preferred":[
        "Merefa"
    ],
    "name:por_x_preferred":[
        "Merefa"
    ],
    "name:ron_x_preferred":[
        "Merefa"
    ],
    "name:rum_x_preferred":[
        "Merefa"
    ],
    "name:rus_x_preferred":[
        "\u041c\u0435\u0440\u0435\u0444\u0430"
    ],
    "name:srp_x_preferred":[
        "\u041c\u0435\u0440\u0435\u0444\u0430"
    ],
    "name:tat_x_preferred":[
        "\u041c\u0435\u0440\u0435\u0444\u0430"
    ],
    "name:ukr_x_preferred":[
        "\u041c\u0435\u0440\u0435\u0444\u0430"
    ],
    "name:unk_x_variant":[
        "Meref"
    ],
    "name:vie_x_preferred":[
        "Merefa"
    ],
    "name:zho_x_preferred":[
        "\u6885\u5217\u6cd5"
    ],
    "qs:a0":"\u0423\u043a\u0440\u0430\u0457\u043d\u0430",
    "qs:a1":"*\u0425\u0430\u0440\u043a\u0456\u0432\u0441\u044c\u043a\u0430",
    "qs:a1_alt":"Kharkivs'ka",
    "qs:a1r":"0",
    "qs:a2":"\u0425\u0430\u0440\u043a\u0456\u0432\u0441\u044c\u043a\u0438\u0439",
    "qs:a2_alt":"Kharkivs'kyi",
    "qs:adm0":"\u0423\u043a\u0440\u0430\u0457\u043d\u0430",
    "qs:la_lc":"*",
    "qs:level":"locality",
    "qs:loc":"\u041c\u0435\u0440\u0435\u0444\u0430",
    "qs:loc_alt":"Merefa",
    "qs:pop":0,
    "qs:type":"buffered point",
    "wd:wordcount":58,
    "wof:name":"\u041c\u0435\u0440\u0435\u0444\u0430",
    "wof:placetype":"locality",
    "wof:population":23679
},
  "geometry": {"coordinates":[36.052448,49.80733],"type":"Point"}
}