{
  "type": "Feature",
  "properties": {
    "gn:admin1_code":"26.0",
    "gn:asciiname":"Yavornyts'ke",
    "gn:country_code":"UA",
    "gn:dem":131,
    "gn:feature_class":"P",
    "gn:feature_code":"PPL",
    "gn:name":"Yavornyts\u2019ke",
    "gn:population":0,
    "gn:timezone":"Europe/Kiev",
    "iso:country":"UA",
    "name:ukr_x_preferred":[
        "Yavornyts\u2019ke"
    ],
    "name:ukr_x_variant":[
        "\u042f\u0432\u043e\u0440\u043d\u0438\u0446\u044c\u043a\u0435"
    ],
    "wof:name":"Yavornyts'ke",
    "wof:placetype":"locality"
},
  "geometry": {"coordinates":[34.86009,48.04031],"type":"Point"}
}