{
  "type": "Feature",
  "properties": {
    "gn:admin1_code":"18.0",
    "gn:asciiname":"Novaya Kochubeyevka",
    "gn:cc2":"UA",
    "gn:country_code":"UA",
    "gn:dem":115,
    "gn:feature_class":"P",
    "gn:feature_code":"PPL",
    "gn:name":"Novaya Kochubeyevka",
    "gn:population":0,
    "gn:timezone":"Europe/Kiev",
    "iso:country":"UA",
    "name:und_x_variant":[
        "Kotschubejewka",
        "Novo-Kochubeyevka",
        "Kochubeyevka",
        "Novaya Kochubeyevka"
    ],
    "wof:name":"Novaya Kochubeyevka",
    "wof:placetype":"locality"
},
  "geometry": {"coordinates":[34.95386,49.75976],"type":"Point"}
}