{
  "type": "Feature",
  "properties": {
    "iso:country":"UA",
    "name:unk_x_variant":[
        "Ostrynya"
    ],
    "qs:a0":"\u0423\u043a\u0440\u0430\u0457\u043d\u0430",
    "qs:a1":"*\u0422\u0435\u0440\u043d\u043e\u043f\u0456\u043b\u044c\u0441\u044c\u043a\u0430",
    "qs:a1_alt":"Ternopil's'ka",
    "qs:a1r":"0",
    "qs:a2":"\u041c\u043e\u043d\u0430\u0441\u0442\u0438\u0440\u0438\u0441\u044c\u043a\u0438\u0439",
    "qs:a2_alt":"Monastyrys'kyi",
    "qs:adm0":"\u0423\u043a\u0440\u0430\u0457\u043d\u0430",
    "qs:la_lc":"*",
    "qs:level":"locality",
    "qs:loc":"\u0412\u0456\u0441\u0442\u0440\u044f",
    "qs:loc_alt":"Vistria",
    "qs:pop":0,
    "qs:type":"buffered point",
    "wof:name":"\u0412\u0456\u0441\u0442\u0440\u044f",
    "wof:placetype":"locality"
},
  "geometry": {"coordinates":[25.133865,48.928803],"type":"Point"}
}