{
  "type": "Feature",
  "properties": {
    "iso:country":"UA",
    "name:ara_x_preferred":[
        "\u0641\u064a\u0644\u064a\u0643\u064a \u0628\u064a\u0631\u0643\u064a"
    ],
    "name:bel_x_preferred":[
        "\u0412\u044d\u043b\u044b\u043a\u0456 \u0411\u0456\u0440\u043a\u044b"
    ],
    "name:ceb_x_preferred":[
        "Velikiye Borki"
    ],
    "name:crh_x_preferred":[
        "Vel\u0131ki Birk\u0131"
    ],
    "name:deu_x_preferred":[
        "Welyki Birky"
    ],
    "name:eng_x_preferred":[
        "Velyki Birky"
    ],
    "name:fra_x_preferred":[
        "Velyki Birky"
    ],
    "name:ita_x_preferred":[
        "Velyki Birky"
    ],
    "name:nld_x_preferred":[
        "Velyki Birky"
    ],
    "name:pol_x_preferred":[
        "Borki Wielkie"
    ],
    "name:ron_x_preferred":[
        "Vel\u00eeki Birk\u00ee"
    ],
    "name:rus_x_preferred":[
        "\u0412\u0435\u043b\u0438\u043a\u0438\u0435 \u0411\u043e\u0440\u043a\u0438"
    ],
    "name:spa_x_preferred":[
        "Velyki Birky"
    ],
    "name:ukr_x_preferred":[
        "\u0412\u0435\u043b\u0438\u043a\u0456 \u0411\u0456\u0440\u043a\u0438"
    ],
    "name:zho_x_preferred":[
        "\u5927\u6bd4\u723e\u57fa"
    ],
    "qs:a0":"\u0423\u043a\u0440\u0430\u0457\u043d\u0430",
    "qs:a1":"*\u0422\u0435\u0440\u043d\u043e\u043f\u0456\u043b\u044c\u0441\u044c\u043a\u0430",
    "qs:a1_alt":"Ternopil's'ka",
    "qs:a1r":"0",
    "qs:a2":"\u0422\u0435\u0440\u043d\u043e\u043f\u0456\u043b\u044c\u0441\u044c\u043a\u0438\u0439",
    "qs:a2_alt":"Ternopil's'kyi",
    "qs:adm0":"\u0423\u043a\u0440\u0430\u0457\u043d\u0430",
    "qs:la_lc":"*",
    "qs:level":"locality",
    "qs:loc":"\u0412\u0435\u043b\u0438\u043a\u0456 \u0411\u0456\u0440\u043a\u0438",
    "qs:loc_alt":"Velyki Birky",
    "qs:pop":0,
    "qs:type":"buffered point",
    "wd:wordcount":1977,
    "wof:name":"\u0412\u0435\u043b\u0438\u043a\u0456 \u0411\u0456\u0440\u043a\u0438",
    "wof:placetype":"locality"
},
  "geometry": {"coordinates":[25.748939,49.52469],"type":"Point"}
}