{
  "type": "Feature",
  "properties": {
    "gn:admin1_code":"24.0",
    "gn:asciiname":"Zoryane",
    "gn:country_code":"UA",
    "gn:dem":156,
    "gn:feature_class":"P",
    "gn:feature_code":"PPL",
    "gn:name":"Zoryane",
    "gn:population":0,
    "gn:timezone":"Europe/Kiev",
    "iso:country":"UA",
    "name:ukr_x_preferred":[
        "Zoryane"
    ],
    "name:ukr_x_variant":[
        "\u0417\u043e\u0440\u044f\u043d\u0435"
    ],
    "name:und_x_variant":[
        "Zoryanoye"
    ],
    "wof:name":"Zoryane",
    "wof:placetype":"locality"
},
  "geometry": {"coordinates":[24.644,51.64508],"type":"Point"}
}