{
  "type": "Feature",
  "properties": {
    "gn:admin1_code":"1.0",
    "gn:asciiname":"Matviyivka",
    "gn:country_code":"UA",
    "gn:dem":209,
    "gn:feature_class":"P",
    "gn:feature_code":"PPL",
    "gn:name":"Matviyivka",
    "gn:population":0,
    "gn:timezone":"Europe/Kiev",
    "iso:country":"UA",
    "name:ukr_x_preferred":[
        "Matviyivka"
    ],
    "name:ukr_x_variant":[
        "\u041c\u0430\u0442\u0432\u0456\u0457\u0432\u043a\u0430"
    ],
    "wof:name":"Matviyivka",
    "wof:placetype":"locality"
},
  "geometry": {"coordinates":[32.43652,49.07203],"type":"Point"}
}