{
  "type": "Feature",
  "properties": {
    "gn:admin1_code":"23.0",
    "gn:asciiname":"Zavadovka",
    "gn:country_code":"UA",
    "gn:dem":163,
    "gn:feature_class":"P",
    "gn:feature_code":"PPL",
    "gn:name":"Zavadovka",
    "gn:population":0,
    "gn:timezone":"Europe/Kiev",
    "iso:country":"UA",
    "wof:name":"Zavadovka",
    "wof:placetype":"locality"
},
  "geometry": {"coordinates":[29.54659,48.51291],"type":"Point"}
}