{
  "type": "Feature",
  "properties": {
    "iso:country":"UA",
    "name:bel_x_preferred":[
        "\u041d\u0430\u0432\u0430\u0442\u0440\u043e\u0456\u0446\u043a\u044d"
    ],
    "name:bul_x_preferred":[
        "\u041d\u043e\u0432\u043e\u0442\u0440\u043e\u0438\u0446\u043a\u0435"
    ],
    "name:ces_x_preferred":[
        "Novotrojicke"
    ],
    "name:che_x_preferred":[
        "\u041d\u043e\u0432\u043e\u0442\u0440\u043e\u0438\u0446\u043a\u043e\u0435"
    ],
    "name:crh_x_preferred":[
        "Sar\u0131 Bulat"
    ],
    "name:deu_x_preferred":[
        "Nowotrojizke"
    ],
    "name:eng_x_preferred":[
        "Novotroitske"
    ],
    "name:fin_x_preferred":[
        "Novotrojitske"
    ],
    "name:fra_x_preferred":[
        "Novotro\u00eftsk\u00e9"
    ],
    "name:lav_x_preferred":[
        "Novotrojicke"
    ],
    "name:pol_x_preferred":[
        "Nowotroji\u0107ke"
    ],
    "name:ron_x_preferred":[
        "Novotroii\u021bke"
    ],
    "name:rus_x_preferred":[
        "\u041d\u043e\u0432\u043e\u0442\u0440\u043e\u0438\u0446\u043a\u043e\u0435"
    ],
    "name:spa_x_preferred":[
        "Novotroitske"
    ],
    "name:swe_x_preferred":[
        "Novotrojitske"
    ],
    "name:ukr_x_preferred":[
        "\u041d\u043e\u0432\u043e\u0442\u0440\u043e\u0457\u0446\u044c\u043a\u0435"
    ],
    "name:und_x_variant":[
        "Novotroitskoye"
    ],
    "name:uzb_x_preferred":[
        "Novotroitske"
    ],
    "name:zho_x_preferred":[
        "\u65b0\u7279\u7f85\u4f0a\u9f4a\u514b"
    ],
    "name:zho_x_variant":[
        "\u65b0\u7279\u7f57\u4f0a\u9f50\u514b"
    ],
    "qs:a0":"\u0423\u043a\u0440\u0430\u0457\u043d\u0430",
    "qs:a1":"*\u0425\u0435\u0440\u0441\u043e\u043d\u0441\u044c\u043a\u0430",
    "qs:a1_alt":"Khersons'ka",
    "qs:a1r":"0",
    "qs:a2":"\u041d\u043e\u0432\u043e\u0442\u0440\u043e\u0457\u0446\u044c\u043a\u0438\u0439",
    "qs:a2_alt":"Novotroits'kyi",
    "qs:adm0":"\u0423\u043a\u0440\u0430\u0457\u043d\u0430",
    "qs:la_lc":"*",
    "qs:level":"locality",
    "qs:loc":"\u041d\u043e\u0432\u043e\u0442\u0440\u043e\u0457\u0446\u044c\u043a\u0435",
    "qs:loc_alt":"Novotroits'ke",
    "qs:pop":0,
    "qs:type":"buffered point",
    "wd:wordcount":79,
    "wof:name":"\u041d\u043e\u0432\u043e\u0442\u0440\u043e\u0457\u0446\u044c\u043a\u0435",
    "wof:placetype":"locality"
},
  "geometry": {"coordinates":[34.339073,46.353003],"type":"Point"}
}