{
  "type": "Feature",
  "properties": {
    "gn:admin1_code":"4.0",
    "gn:asciiname":"Samars'ke",
    "gn:country_code":"UA",
    "gn:dem":84,
    "gn:feature_class":"P",
    "gn:feature_code":"PPL",
    "gn:name":"Samars\u2019ke",
    "gn:population":0,
    "gn:timezone":"Europe/Kiev",
    "iso:country":"UA",
    "name:ukr_x_preferred":[
        "Samars\u2019ke"
    ],
    "name:ukr_x_variant":[
        "\u0421\u0430\u043c\u0430\u0440\u0441\u044c\u043a\u0435"
    ],
    "name:und_x_variant":[
        "Ivanovka",
        "Samarskoye"
    ],
    "wof:name":"Samars'ke",
    "wof:placetype":"locality"
},
  "geometry": {"coordinates":[36.45999000000001,48.48268],"type":"Point"}
}