{
  "type": "Feature",
  "properties": {
    "gn:admin1_code":"21.0",
    "gn:asciiname":"Yakovenkove",
    "gn:country_code":"UA",
    "gn:dem":149,
    "gn:feature_class":"P",
    "gn:feature_code":"PPL",
    "gn:name":"Yakovenkove",
    "gn:population":0,
    "gn:timezone":"Europe/Kiev",
    "iso:country":"UA",
    "name:ukr_x_preferred":[
        "Yakovenkove"
    ],
    "name:ukr_x_variant":[
        "\u042f\u043a\u043e\u0432\u0435\u043d\u043a\u043e\u0432\u0435"
    ],
    "name:und_x_variant":[
        "Yakovenkovo"
    ],
    "wof:name":"Yakovenkove",
    "wof:placetype":"locality"
},
  "geometry": {"coordinates":[33.63567,50.72224],"type":"Point"}
}