{
  "type": "Feature",
  "properties": {
    "gn:admin1_code":"2.0",
    "gn:asciiname":"Mykhaylove",
    "gn:country_code":"UA",
    "gn:dem":158,
    "gn:feature_class":"P",
    "gn:feature_code":"PPL",
    "gn:name":"Mykhaylove",
    "gn:population":0,
    "gn:timezone":"Europe/Kiev",
    "iso:country":"UA",
    "name:ukr_x_preferred":[
        "Mykhaylove"
    ],
    "name:ukr_x_variant":[
        "\u041c\u0438\u0445\u0430\u0439\u043b\u043e\u0432\u0435"
    ],
    "name:und_x_variant":[
        "Mikhaylovka"
    ],
    "wof:name":"Mykhaylove",
    "wof:placetype":"locality"
},
  "geometry": {"coordinates":[32.54923,52.26107],"type":"Point"}
}