{
  "type": "Feature",
  "properties": {
    "gn:admin1_code":"3.0",
    "gn:asciiname":"Lustun",
    "gn:country_code":"UA",
    "gn:dem":844,
    "gn:feature_class":"P",
    "gn:feature_code":"PPL",
    "gn:name":"Lustun",
    "gn:population":0,
    "gn:timezone":"Europe/Kiev",
    "iso:country":"UA",
    "wof:name":"Lustun",
    "wof:placetype":"locality"
},
  "geometry": {"coordinates":[25.1706,47.91992],"type":"Point"}
}