{
  "type": "Feature",
  "properties": {
    "gn:admin1_code":"21.0",
    "gn:asciiname":"Trudove",
    "gn:country_code":"UA",
    "gn:dem":166,
    "gn:feature_class":"P",
    "gn:feature_code":"PPL",
    "gn:name":"Trudove",
    "gn:population":0,
    "gn:timezone":"Europe/Kiev",
    "iso:country":"UA",
    "name:ukr_x_preferred":[
        "Trudove"
    ],
    "name:ukr_x_variant":[
        "\u0422\u0440\u0443\u0434\u043e\u0432\u0435"
    ],
    "name:und_x_variant":[
        "Trudovoye"
    ],
    "wof:name":"Trudove",
    "wof:placetype":"locality"
},
  "geometry": {"coordinates":[33.81092,51.38262],"type":"Point"}
}