{
  "type": "Feature",
  "properties": {
    "gn:admin1_code":"6.0",
    "gn:asciiname":"Pilyavshchyzna",
    "gn:cc2":"UA",
    "gn:country_code":"UA",
    "gn:dem":274,
    "gn:feature_class":"P",
    "gn:feature_code":"PPL",
    "gn:name":"Pilyavshchyzna",
    "gn:population":0,
    "gn:timezone":"Europe/Kiev",
    "iso:country":"UA",
    "name:und_x_variant":[
        "Pilyavshchina",
        "Pilyavshchyzna"
    ],
    "wof:name":"Pilyavshchyzna",
    "wof:placetype":"locality"
},
  "geometry": {"coordinates":[25.01667,48.85],"type":"Point"}
}