{
  "type": "Feature",
  "properties": {
    "gn:admin1_code":"17.0",
    "gn:asciiname":"Budyachky",
    "gn:country_code":"UA",
    "gn:dem":83,
    "gn:feature_class":"P",
    "gn:feature_code":"PPL",
    "gn:name":"Budyachky",
    "gn:population":0,
    "gn:timezone":"Europe/Kiev",
    "iso:country":"UA",
    "name:ukr_x_preferred":[
        "Budyachky"
    ],
    "name:ukr_x_variant":[
        "\u0411\u0443\u0434\u044f\u0447\u043a\u0438"
    ],
    "name:und_x_variant":[
        "Budyachki"
    ],
    "wof:name":"Budyachky",
    "wof:placetype":"locality"
},
  "geometry": {"coordinates":[30.35396,46.69745],"type":"Point"}
}