{
  "type": "Feature",
  "properties": {
    "iso:country":"UA",
    "name:bel_x_preferred":[
        "\u041a\u0430\u043b\u0430\u043c\u044b\u0439\u0441\u043a\u0456 \u0440\u0430\u0451\u043d"
    ],
    "name:ceb_x_preferred":[
        "Kolomyys'kyy Rayon"
    ],
    "name:dan_x_preferred":[
        "Kolomyja Rajon"
    ],
    "name:deu_x_preferred":[
        "Rajon Kolomyja"
    ],
    "name:eng_x_preferred":[
        "Kolomyia Raion"
    ],
    "name:fin_x_preferred":[
        "Kolomyjan piiri"
    ],
    "name:hun_x_preferred":[
        "Kolomijai j\u00e1r\u00e1s"
    ],
    "name:hye_x_preferred":[
        "\u053f\u0578\u056c\u0578\u0574\u056b\u0575\u0561\u0575\u056b \u0577\u0580\u057b\u0561\u0576"
    ],
    "name:kat_x_preferred":[
        "\u10d9\u10dd\u10da\u10dd\u10db\u10d8\u10d8\u10e1 \u10e0\u10d0\u10d8\u10dd\u10dc\u10d8"
    ],
    "name:lav_x_preferred":[
        "Kolomijas rajons"
    ],
    "name:nan_x_preferred":[
        "Kolomyia Ko\u0101n"
    ],
    "name:pol_x_preferred":[
        "Rejon ko\u0142omyjski"
    ],
    "name:ron_x_preferred":[
        "Raionul Colomeea"
    ],
    "name:rus_x_preferred":[
        "\u041a\u043e\u043b\u043e\u043c\u044b\u0439\u0441\u043a\u0438\u0439 \u0440\u0430\u0439\u043e\u043d"
    ],
    "name:sco_x_preferred":[
        "Kolomyia Raion"
    ],
    "name:ukr_x_preferred":[
        "\u041a\u043e\u043b\u043e\u043c\u0438\u0439\u0441\u044c\u043a\u0438\u0439 \u0440\u0430\u0439\u043e\u043d"
    ],
    "name:vie_x_preferred":[
        "Kolomyia"
    ],
    "name:zho_x_preferred":[
        "\u79d1\u6d1b\u6885\u4e9e\u5340"
    ],
    "qs:a0":"\u0423\u043a\u0440\u0430\u0457\u043d\u0430",
    "qs:a1":"*\u0425\u043c\u0435\u043b\u044c\u043d\u0438\u0446\u044c\u043a\u0430",
    "qs:a1_alt":"Khmel'nyts'ka",
    "qs:a1r":"0",
    "qs:a2":"\u041a\u0430\u043c'\u044f\u043d\u0435\u0446\u044c-\u041f\u043e\u0434\u0456\u043b\u044c\u0441\u044c\u043a\u0438\u0439",
    "qs:a2_alt":"Kamyanets'-Podil's'kyi",
    "qs:adm0":"\u0423\u043a\u0440\u0430\u0457\u043d\u0430",
    "qs:la_lc":"*",
    "qs:level":"locality",
    "qs:loc":"\u0413\u043e\u043b\u043e\u0441\u043a\u0456\u0432",
    "qs:loc_alt":"Holoskiv",
    "qs:pop":0,
    "qs:type":"buffered point",
    "wd:wordcount":266,
    "wof:name":"\u0413\u043e\u043b\u043e\u0441\u043a\u0456\u0432",
    "wof:placetype":"locality"
},
  "geometry": {"coordinates":[26.552306,48.742327],"type":"Point"}
}