{
  "type": "Feature",
  "properties": {
    "iso:country":"UA",
    "name:bel_x_preferred":[
        "\u041c\u0443\u043a\u0430\u0447\u044d\u045e\u0441\u043a\u0456 \u0440\u0430\u0451\u043d"
    ],
    "name:ceb_x_preferred":[
        "Mukachevo Raion"
    ],
    "name:ces_x_preferred":[
        "Muka\u010devsk\u00fd raj\u00f3n"
    ],
    "name:deu_x_preferred":[
        "Rajon Mukatschewe"
    ],
    "name:eng_x_preferred":[
        "Mukacheve Raion"
    ],
    "name:fra_x_preferred":[
        "Unit\u00e9 administrative en Ukraine"
    ],
    "name:hun_x_preferred":[
        "Munk\u00e1csi j\u00e1r\u00e1s"
    ],
    "name:hye_x_preferred":[
        "\u0544\u0578\u0582\u056f\u0561\u0579\u0587\u0578\u0575\u056b \u0577\u0580\u057b\u0561\u0576"
    ],
    "name:kat_x_preferred":[
        "\u10db\u10e3\u10d9\u10d0\u10e9\u10d4\u10d5\u10dd\u10e1 \u10e0\u10d0\u10d8\u10dd\u10dc\u10d8"
    ],
    "name:lav_x_preferred":[
        "Muka\u010deves rajons"
    ],
    "name:nld_x_preferred":[
        "Moekatsjeve"
    ],
    "name:pol_x_preferred":[
        "Rejon mukaczewski"
    ],
    "name:ron_x_preferred":[
        "Raionul Muncaci"
    ],
    "name:rue_x_preferred":[
        "\u041c\u0443\u043a\u0430\u0447\u0456\u0432\u0441\u043a\u044b\u0439 \u0440\u0430\u0439\u043e\u043d"
    ],
    "name:rus_x_preferred":[
        "\u041c\u0443\u043a\u0430\u0447\u0435\u0432\u0441\u043a\u0438\u0439 \u0440\u0430\u0439\u043e\u043d"
    ],
    "name:sco_x_preferred":[
        "Mukacheve Raion"
    ],
    "name:slk_x_preferred":[
        "Muka\u010devsk\u00fd raj\u00f3n"
    ],
    "name:ukr_x_preferred":[
        "Verkhnya Vyznytsya"
    ],
    "name:ukr_x_variant":[
        "\u0412\u0435\u0440\u0445\u043d\u044f \u0412\u0438\u0437\u043d\u0438\u0446\u044f",
        "\u041c\u0443\u043a\u0430\u0447\u0456\u0432\u0441\u044c\u043a\u0438\u0439 \u0440\u0430\u0439\u043e\u043d"
    ],
    "name:unk_x_variant":[
        "Verkhnyaya Viznitsa"
    ],
    "name:vie_x_preferred":[
        "Mukachevo"
    ],
    "name:zho_x_preferred":[
        "\u7a46\u5361\u5207\u6c83\u5340"
    ],
    "qs:a0":"\u0423\u043a\u0440\u0430\u0457\u043d\u0430",
    "qs:a1":"*\u0417\u0430\u043a\u0430\u0440\u043f\u0430\u0442\u0441\u044c\u043a\u0430",
    "qs:a1_alt":"Zakarpats'ka",
    "qs:a1r":"0",
    "qs:a2":"\u041c\u0443\u043a\u0430\u0447\u0456\u0432\u0441\u044c\u043a\u0438\u0439",
    "qs:a2_alt":"Mukachivs'kyi",
    "qs:adm0":"\u0423\u043a\u0440\u0430\u0457\u043d\u0430",
    "qs:la_lc":"*",
    "qs:level":"locality",
    "qs:loc":"\u0412\u0435\u0440\u0445\u043d\u044f \u0412\u0438\u0437\u043d\u0438\u0446\u044f",
    "qs:loc_alt":"Verkhnia Vyznytsia",
    "qs:pop":0,
    "qs:type":"buffered point",
    "wd:wordcount":84,
    "wof:name":"\u0412\u0435\u0440\u0445\u043d\u044f \u0412\u0438\u0437\u043d\u0438\u0446\u044f",
    "wof:placetype":"locality"
},
  "geometry": {"coordinates":[22.742134,48.532066],"type":"Point"}
}