{
  "type": "Feature",
  "properties": {
    "gn:admin1_code":"7.0",
    "gn:asciiname":"Karnaukhivka",
    "gn:country_code":"UA",
    "gn:dem":115,
    "gn:feature_class":"P",
    "gn:feature_code":"PPL",
    "gn:name":"Karnaukhivka",
    "gn:population":0,
    "gn:timezone":"Europe/Kiev",
    "iso:country":"UA",
    "name:ukr_x_preferred":[
        "Karnaukhivka"
    ],
    "name:und_x_variant":[
        "Karnaukhovka"
    ],
    "wof:name":"Karnaukhivka",
    "wof:placetype":"locality"
},
  "geometry": {"coordinates":[37.0415,49.03508],"type":"Point"}
}