{
  "type": "Feature",
  "properties": {
    "gn:admin1_code":"21.0",
    "gn:asciiname":"Perelisky",
    "gn:country_code":"UA",
    "gn:dem":130,
    "gn:feature_class":"P",
    "gn:feature_code":"PPL",
    "gn:name":"Perelisky",
    "gn:population":0,
    "gn:timezone":"Europe/Kiev",
    "iso:country":"UA",
    "name:deu_x_preferred":[
        "Pereleski"
    ],
    "name:hye_x_preferred":[
        "\u054a\u0565\u0580\u0565\u056c\u0565\u057d\u056f\u056b"
    ],
    "name:rus_x_preferred":[
        "\u041f\u0435\u0440\u0435\u043b\u0435\u0441\u043a\u0438"
    ],
    "name:ukr_x_preferred":[
        "Perelisky"
    ],
    "name:ukr_x_variant":[
        "\u041f\u0435\u0440\u0435\u043b\u0456\u0441\u043a\u0438"
    ],
    "wof:name":"Perelisky",
    "wof:placetype":"locality"
},
  "geometry": {"coordinates":[34.72598,50.64316],"type":"Point"}
}