{
  "type": "Feature",
  "properties": {
    "gn:admin1_code":"26.0",
    "gn:asciiname":"Olenivka",
    "gn:country_code":"UA",
    "gn:dem":25,
    "gn:feature_class":"P",
    "gn:feature_code":"PPL",
    "gn:name":"Olenivka",
    "gn:population":0,
    "gn:timezone":"Europe/Zaporozhye",
    "iso:country":"UA",
    "name:deu_x_preferred":[
        "Oleniwka"
    ],
    "name:est_x_preferred":[
        "Olenivka"
    ],
    "name:rus_x_preferred":[
        "Yel\u00ebnovka"
    ],
    "name:rus_x_variant":[
        "\u041e\u043b\u0435\u043d\u043e\u0432\u043a\u0430"
    ],
    "name:ukr_x_preferred":[
        "Olenivka"
    ],
    "name:ukr_x_variant":[
        "\u041e\u043b\u0435\u043d\u0456\u0432\u043a\u0430"
    ],
    "name:und_x_variant":[
        "Olenovka"
    ],
    "wof:name":"Olenivka",
    "wof:placetype":"locality"
},
  "geometry": {"coordinates":[35.57445,46.94552],"type":"Point"}
}