{
  "type": "Feature",
  "properties": {
    "gn:admin1_code":"15.0",
    "gn:asciiname":"Novoyavorivs'k",
    "gn:country_code":"UA",
    "gn:dem":297,
    "gn:feature_class":"P",
    "gn:feature_code":"PPL",
    "gn:name":"Novoyavorivs'k",
    "gn:population":28807,
    "gn:timezone":"Europe/Kiev",
    "iso:country":"UA",
    "name:azb_x_preferred":[
        "\u0646\u0648\u0648\u06cc\u0627\u0648\u0648\u0631\u06cc\u0641\u0633\u06a9\u0647"
    ],
    "name:bel_x_preferred":[
        "\u041d\u0430\u0432\u0430\u044f\u0432\u0430\u0440\u044b\u045e\u0441\u043a"
    ],
    "name:ceb_x_preferred":[
        "Novoyavorivs'k"
    ],
    "name:ces_x_preferred":[
        "Novojavorivsk"
    ],
    "name:crh_x_preferred":[
        "Novoyavorivsk"
    ],
    "name:deu_x_preferred":[
        "Nowojaworiwsk"
    ],
    "name:fas_x_preferred":[
        "\u0646\u0648\u0648\u06cc\u0627\u0648\u0648\u0631\u06cc\u0641\u0633\u06a9\u0647"
    ],
    "name:fra_x_preferred":[
        "Novo\u00efavorivsk"
    ],
    "name:hsb_x_preferred":[
        "Nowojaworiwsk"
    ],
    "name:hye_x_preferred":[
        "\u0546\u0578\u057e\u0578\u0575\u0561\u057e\u0578\u0580\u0578\u057e\u057d\u056f"
    ],
    "name:ita_x_preferred":[
        "Novojavorivs'k"
    ],
    "name:kat_x_preferred":[
        "\u10dc\u10dd\u10d5\u10dd\u10d8\u10d0\u10d5\u10dd\u10e0\u10dd\u10d5\u10e1\u10d9\u10d8"
    ],
    "name:lav_x_preferred":[
        "Novojavorivska"
    ],
    "name:nno_x_preferred":[
        "Novojavorivsk"
    ],
    "name:pol_x_preferred":[
        "Nowojaworowsk"
    ],
    "name:ron_x_preferred":[
        "Novoiavorivsk"
    ],
    "name:rus_x_preferred":[
        "\u041d\u043e\u0432\u043e\u044f\u0432\u043e\u0440\u043e\u0432\u0441\u043a"
    ],
    "name:srp_x_preferred":[
        "\u041d\u043e\u0432\u043e\u0458\u0430\u0432\u043e\u0440\u0438\u0432\u0441\u043a"
    ],
    "name:swe_x_preferred":[
        "Novojavorivsk"
    ],
    "name:ukr_x_preferred":[
        "\u041d\u043e\u0432\u043e\u044f\u0432\u043e\u0440\u0456\u0432\u0441\u044c\u043a"
    ],
    "name:vie_x_preferred":[
        "Novoiavorivske"
    ],
    "name:zho_x_preferred":[
        "\u65b0\u4e9e\u6c83\u91cc\u592b\u897f\u514b"
    ],
    "wof:name":"Novoyavorivs'k",
    "wof:placetype":"locality",
    "wof:population":28807
},
  "geometry": {"coordinates":[23.57357,49.93023],"type":"Point"}
}