{
  "type": "Feature",
  "properties": {
    "gn:admin1_code":"9.0",
    "gn:asciiname":"Fashchevka",
    "gn:country_code":"UA",
    "gn:dem":270,
    "gn:feature_class":"P",
    "gn:feature_code":"PPL",
    "gn:name":"Fashch\u00ebvka",
    "gn:population":0,
    "gn:timezone":"Europe/Kiev",
    "iso:country":"UA",
    "name:und_x_variant":[
        "Fashchuvka",
        "Fashch\u00ebvka"
    ],
    "wof:name":"Fashchevka",
    "wof:placetype":"locality"
},
  "geometry": {"coordinates":[26.22305,49.38491],"type":"Point"}
}