{
  "type": "Feature",
  "properties": {
    "iso:country":"UA",
    "name:crh_x_preferred":[
        "\u00dcsk\u00fct"
    ],
    "name:eng_x_preferred":[
        "Privetnoye"
    ],
    "name:eng_x_variant":[
        "Privitne",
        "Uskut",
        "Pryvitne"
    ],
    "name:hye_x_preferred":[
        "\u054a\u0580\u056b\u057e\u0565\u057f\u0576\u0578\u0565"
    ],
    "name:ron_x_preferred":[
        "Pr\u00eevitne"
    ],
    "name:rus_x_historical":[
        "\u0423\u0441\u043a\u0443\u0301\u0442"
    ],
    "name:rus_x_preferred":[
        "\u0423\u0441\u043a\u0443\u0301\u0442"
    ],
    "name:rus_x_variant":[
        "\u041f\u0440\u0438\u0432\u0435\u0442\u043d\u043e\u0435"
    ],
    "name:ukr_x_preferred":[
        "\u041f\u0440\u0438\u0432\u0456\u0442\u043d\u0435"
    ],
    "qs:a0":"\u0423\u043a\u0440\u0430\u0457\u043d\u0430",
    "qs:a1":"*\u041a\u0440\u0438\u043c",
    "qs:a1_alt":"Krym",
    "qs:a1r":"0",
    "qs:a2":"\u0410\u043b\u0443\u0448\u0442\u0430",
    "qs:a2_alt":"Alushta",
    "qs:adm0":"\u0423\u043a\u0440\u0430\u0457\u043d\u0430",
    "qs:la_lc":"*",
    "qs:level":"locality",
    "qs:loc":"\u041f\u0440\u0438\u0432\u0456\u0442\u043d\u0435",
    "qs:loc_alt":"Pryvitne",
    "qs:pop":0,
    "qs:type":"buffered point",
    "wd:wordcount":93,
    "wof:lang":[
        "eng"
    ],
    "wof:name":"\u041f\u0440\u0438\u0432\u0456\u0442\u043d\u0435",
    "wof:placetype":"locality"
},
  "geometry": {"coordinates":[34.673729,44.830179],"type":"Point"}
}