{
  "type": "Feature",
  "properties": {
    "gn:admin1_code":"16.0",
    "gn:asciiname":"Khutor Novo-Dmitrovka",
    "gn:cc2":"UA",
    "gn:country_code":"UA",
    "gn:dem":89,
    "gn:feature_class":"P",
    "gn:feature_code":"PPL",
    "gn:name":"Khutor Novo-Dmitrovka",
    "gn:population":0,
    "gn:timezone":"Europe/Kiev",
    "iso:country":"UA",
    "name:und_x_variant":[
        "Novo Dmitrovka",
        "Khutor Novo-Dmitrovka"
    ],
    "wof:name":"Khutor Novo-Dmitrovka",
    "wof:placetype":"locality"
},
  "geometry": {"coordinates":[32.03333,47.75],"type":"Point"}
}