{
  "type": "Feature",
  "properties": {
    "gn:admin1_code":"5.0",
    "gn:asciiname":"Novoselivka Druha",
    "gn:country_code":"UA",
    "gn:dem":138,
    "gn:feature_class":"P",
    "gn:feature_code":"PPL",
    "gn:name":"Novoselivka Druha",
    "gn:population":0,
    "gn:timezone":"Europe/Kiev",
    "iso:country":"UA",
    "name:ukr_x_preferred":[
        "Novoselivka Druha"
    ],
    "name:ukr_x_variant":[
        "\u041d\u043e\u0432\u043e\u0441\u0435\u043b\u0456\u0432\u043a\u0430 \u0414\u0440\u0443\u0433\u0430"
    ],
    "wof:name":"Novoselivka Druha",
    "wof:placetype":"locality"
},
  "geometry": {"coordinates":[37.75686,47.38135],"type":"Point"}
}