{
  "type": "Feature",
  "properties": {
    "gn:admin1_code":"6.0",
    "gn:asciiname":"Zaprutse",
    "gn:country_code":"UA",
    "gn:dem":202,
    "gn:feature_class":"P",
    "gn:feature_code":"PPL",
    "gn:name":"Zaprutse",
    "gn:population":0,
    "gn:timezone":"Europe/Kiev",
    "iso:country":"UA",
    "name:und_x_variant":[
        "Zarech\u2019ye",
        "Zaprutse"
    ],
    "wof:name":"Zaprutse",
    "wof:placetype":"locality"
},
  "geometry": {"coordinates":[25.58498,48.42297],"type":"Point"}
}