{
  "type": "Feature",
  "properties": {
    "gn:admin1_code":"5.0",
    "gn:asciiname":"Novoromanivka",
    "gn:country_code":"UA",
    "gn:dem":108,
    "gn:feature_class":"P",
    "gn:feature_code":"PPL",
    "gn:name":"Novoromanivka",
    "gn:population":0,
    "gn:timezone":"Europe/Kiev",
    "iso:country":"UA",
    "name:ukr_x_preferred":[
        "Novoromanivka"
    ],
    "name:ukr_x_variant":[
        "\u041d\u043e\u0432\u043e\u0440\u043e\u043c\u0430\u043d\u0456\u0432\u043a\u0430"
    ],
    "name:und_x_variant":[
        "Novaya Romanovka",
        "Novoromanovka"
    ],
    "wof:name":"Novoromanivka",
    "wof:placetype":"locality"
},
  "geometry": {"coordinates":[37.1775,47.22058],"type":"Point"}
}