{
  "type": "Feature",
  "properties": {
    "gn:admin1_code":"15.0",
    "gn:asciiname":"Bilyy Kamin'",
    "gn:country_code":"UA",
    "gn:dem":243,
    "gn:feature_class":"P",
    "gn:feature_code":"PPL",
    "gn:name":"Bilyy Kamin\u2019",
    "gn:population":0,
    "gn:timezone":"Europe/Kiev",
    "iso:country":"UA",
    "name:pol_x_preferred":[
        "Bia\u0142y Kamie\u0144"
    ],
    "name:ukr_x_preferred":[
        "Bilyy Kamin\u2019"
    ],
    "name:ukr_x_variant":[
        "\u0411\u0456\u043b\u0438\u0439 \u041a\u0430\u043c\u0456\u043d\u044c"
    ],
    "name:und_x_variant":[
        "Byaly Kamen\u2019",
        "Belyy Kamen\u2019",
        "Bilkamin"
    ],
    "wof:name":"Bilyy Kamin'",
    "wof:placetype":"locality"
},
  "geometry": {"coordinates":[24.83277,49.89769],"type":"Point"}
}