{
  "type": "Feature",
  "properties": {
    "gn:admin1_code":"11.0",
    "gn:admin2_code":"704383",
    "gn:admin3_code":"11152920.0",
    "gn:asciiname":"Shcherbakovo",
    "gn:country_code":"UA",
    "gn:dem":32,
    "gn:elevation":"33.0",
    "gn:feature_class":"P",
    "gn:feature_code":"PPL",
    "gn:name":"Shcherbakovo",
    "gn:population":614,
    "gn:timezone":"Europe/Simferopol",
    "iso:country":"UA",
    "name:eng_x_preferred":[
        "Shcherbakovo"
    ],
    "name:rus_x_historical":[
        "\u041c\u0443\u0440\u0437\u0430\u043b\u043b\u0430\u0440-\u041a\u0435\u043c\u0435\u043b\u044c\u0447\u0438"
    ],
    "name:rus_x_preferred":[
        "\u0429\u0435\u0440\u0431\u0430\u043a\u043e\u0432\u043e"
    ],
    "name:rus_x_variant":[
        "\u041c\u0443\u0440\u0437\u0430\u043b\u043b\u0430\u0440-\u041a\u0435\u043c\u0435\u043b\u044c\u0447\u0438"
    ],
    "name:ukr_x_preferred":[
        "\u0429\u0435\u0440\u0431\u0430\u043a\u043e\u0432\u0435"
    ],
    "wof:name":"Shcherbakovo",
    "wof:placetype":"locality",
    "wof:population":614
},
  "geometry": {"coordinates":[34.35008,45.48329],"type":"Point"}
}