{
  "type": "Feature",
  "properties": {
    "gn:admin1_code":"9.0",
    "gn:asciiname":"Khrolyn",
    "gn:country_code":"UA",
    "gn:dem":267,
    "gn:feature_class":"P",
    "gn:feature_code":"PPL",
    "gn:name":"Khrolyn",
    "gn:population":0,
    "gn:timezone":"Europe/Kiev",
    "iso:country":"UA",
    "name:ukr_x_preferred":[
        "Khrolyn"
    ],
    "name:ukr_x_variant":[
        "\u0425\u0440\u043e\u043b\u0438\u043d"
    ],
    "name:und_x_variant":[
        "Chrolin",
        "Khrolin"
    ],
    "wof:name":"Khrolyn",
    "wof:placetype":"locality"
},
  "geometry": {"coordinates":[27.24824000000001,50.15384],"type":"Point"}
}