{
  "type": "Feature",
  "properties": {
    "iso:country":"UA",
    "name:deu_x_preferred":[
        "Nowotscherwone"
    ],
    "name:eng_x_preferred":[
        "Novochervonoye"
    ],
    "name:eng_x_variant":[
        "Novochervone"
    ],
    "name:lav_x_preferred":[
        "Novo\u010dervone"
    ],
    "name:ron_x_preferred":[
        "Novocervone"
    ],
    "name:rus_x_preferred":[
        "\u041d\u043e\u0432\u043e\u0447\u0435\u0440\u0432\u043e\u043d\u043e\u0435"
    ],
    "name:ukr_x_preferred":[
        "Novochervone"
    ],
    "name:ukr_x_variant":[
        "\u041d\u043e\u0432\u043e\u0447\u0435\u0440\u0432\u043e\u043d\u0435"
    ],
    "name:und_x_variant":[
        "Novo-Krasnoye"
    ],
    "name:zho_x_preferred":[
        "\u65b0\u5207\u723e\u6c83\u6d85"
    ],
    "qs:a0":"\u0423\u043a\u0440\u0430\u0457\u043d\u0430",
    "qs:a1":"*\u041b\u0443\u0433\u0430\u043d\u0441\u044c\u043a\u0430",
    "qs:a1_alt":"Luhans'ka",
    "qs:a1r":"0",
    "qs:a2":"\u0422\u0440\u043e\u0457\u0446\u044c\u043a\u0438\u0439",
    "qs:a2_alt":"Troits'kyi",
    "qs:adm0":"\u0423\u043a\u0440\u0430\u0457\u043d\u0430",
    "qs:la_lc":"*",
    "qs:level":"locality",
    "qs:loc":"\u041d\u043e\u0432\u043e\u0447\u0435\u0440\u0432\u043e\u043d\u0435",
    "qs:loc_alt":"Novochervone",
    "qs:pop":0,
    "qs:type":"buffered point",
    "wof:name":"\u041d\u043e\u0432\u043e\u0447\u0435\u0440\u0432\u043e\u043d\u0435",
    "wof:placetype":"locality"
},
  "geometry": {"coordinates":[38.31117,49.627949],"type":"Point"}
}