{
  "type": "Feature",
  "properties": {
    "gn:admin1_code":"2.0",
    "gn:asciiname":"Bezykiv",
    "gn:country_code":"UA",
    "gn:dem":139,
    "gn:feature_class":"P",
    "gn:feature_code":"PPL",
    "gn:name":"Bezykiv",
    "gn:population":0,
    "gn:timezone":"Europe/Kiev",
    "iso:country":"UA",
    "name:ukr_x_preferred":[
        "Bezykiv"
    ],
    "name:ukr_x_variant":[
        "\u0411\u0435\u0437\u0438\u043a\u0456\u0432"
    ],
    "name:und_x_variant":[
        "Bezikov"
    ],
    "wof:name":"Bezykiv",
    "wof:placetype":"locality"
},
  "geometry": {"coordinates":[31.33886,51.81211],"type":"Point"}
}