{
  "type": "Feature",
  "properties": {
    "gn:admin1_code":"17.0",
    "gn:asciiname":"Radisne",
    "gn:country_code":"UA",
    "gn:dem":64,
    "gn:feature_class":"P",
    "gn:feature_code":"PPL",
    "gn:name":"Radisne",
    "gn:population":0,
    "gn:timezone":"Europe/Kiev",
    "iso:country":"UA",
    "name:ukr_x_preferred":[
        "Zhovtneva Revolyutsiya"
    ],
    "name:ukr_x_variant":[
        "\u0416\u043e\u0432\u0442\u043d\u0435\u0432\u0430 \u0420\u0435\u0432\u043e\u043b\u044e\u0446\u0456\u044f",
        "Radisne",
        "\u0420\u0430\u0434\u0456\u0441\u043d\u0435"
    ],
    "name:und_x_variant":[
        "Zhovtenvaya Revolyutsiya"
    ],
    "wof:name":"Radisne",
    "wof:placetype":"locality"
},
  "geometry": {"coordinates":[30.57195,46.49154],"type":"Point"}
}