{
  "type": "Feature",
  "properties": {
    "gn:admin1_code":"7.0",
    "gn:asciiname":"Novomykhaylivka",
    "gn:country_code":"UA",
    "gn:dem":158,
    "gn:feature_class":"P",
    "gn:feature_code":"PPL",
    "gn:name":"Novomykhaylivka",
    "gn:population":0,
    "gn:timezone":"Europe/Kiev",
    "iso:country":"UA",
    "name:rus_x_preferred":[
        "\u041d\u043e\u0432\u043e\u043c\u0438\u0445\u0430\u0439\u043b\u043e\u0432\u043a\u0430"
    ],
    "name:ukr_x_preferred":[
        "Novomykhaylivka"
    ],
    "name:ukr_x_variant":[
        "\u041d\u043e\u0432\u043e\u043c\u0438\u0445\u0430\u0439\u043b\u0456\u0432\u043a\u0430"
    ],
    "name:und_x_variant":[
        "Mikhaylovka",
        "Novaya Mikhaylovka",
        "Novomikhaylovka"
    ],
    "wof:name":"Novomykhaylivka",
    "wof:placetype":"locality"
},
  "geometry": {"coordinates":[35.96695,49.22603],"type":"Point"}
}