{
  "type": "Feature",
  "properties": {
    "iso:country":"UA",
    "name:eng_x_preferred":[
        "Tsvitne"
    ],
    "name:rus_x_preferred":[
        "\u0426\u0432\u0435\u0442\u043d\u043e\u0435"
    ],
    "name:ukr_x_preferred":[
        "\u0426\u0432\u0456\u0442\u043d\u0435"
    ],
    "name:unk_x_variant":[
        "Tsvetna"
    ],
    "qs:a0":"\u0423\u043a\u0440\u0430\u0457\u043d\u0430",
    "qs:a1":"*\u041a\u0456\u0440\u043e\u0432\u043e\u0433\u0440\u0430\u0434\u0441\u044c\u043a\u0430",
    "qs:a1_alt":"Kirovohrads'ka",
    "qs:a1r":"0",
    "qs:a2":"\u041e\u043b\u0435\u043a\u0441\u0430\u043d\u0434\u0440\u0456\u0432\u0441\u044c\u043a\u0438\u0439",
    "qs:a2_alt":"Oleksandrivs'kyi",
    "qs:adm0":"\u0423\u043a\u0440\u0430\u0457\u043d\u0430",
    "qs:la_lc":"*",
    "qs:level":"locality",
    "qs:loc":"\u0426\u0432\u0456\u0442\u043d\u0435",
    "qs:loc_alt":"Tsvitne",
    "qs:pop":0,
    "qs:type":"buffered point",
    "wof:name":"\u0426\u0432\u0456\u0442\u043d\u0435",
    "wof:placetype":"locality"
},
  "geometry": {"coordinates":[32.485736,48.959077],"type":"Point"}
}