{
  "type": "Feature",
  "properties": {
    "gn:admin1_code":"2.0",
    "gn:asciiname":"Stanove",
    "gn:country_code":"UA",
    "gn:dem":127,
    "gn:feature_class":"P",
    "gn:feature_code":"PPL",
    "gn:name":"Stanove",
    "gn:population":0,
    "gn:timezone":"Europe/Kiev",
    "iso:country":"UA",
    "name:ukr_x_preferred":[
        "Stanove"
    ],
    "name:ukr_x_variant":[
        "\u0421\u0442\u0430\u043d\u043e\u0432\u0435"
    ],
    "name:und_x_variant":[
        "Stanovoye"
    ],
    "wof:name":"Stanove",
    "wof:placetype":"locality"
},
  "geometry": {"coordinates":[32.78243,51.55282],"type":"Point"}
}