{
  "type": "Feature",
  "properties": {
    "gn:admin1_code":"7.0",
    "gn:asciiname":"Vovchyy Yar",
    "gn:country_code":"UA",
    "gn:dem":169,
    "gn:feature_class":"P",
    "gn:feature_code":"PPL",
    "gn:name":"Vovchyy Yar",
    "gn:population":0,
    "gn:timezone":"Europe/Kiev",
    "iso:country":"UA",
    "name:ukr_x_preferred":[
        "Vovchyy Yar"
    ],
    "name:ukr_x_variant":[
        "\u0412\u043e\u0432\u0447\u0438\u0439 \u042f\u0440"
    ],
    "name:und_x_variant":[
        "Volchiy Yar"
    ],
    "wof:name":"Vovchyy Yar",
    "wof:placetype":"locality"
},
  "geometry": {"coordinates":[37.40806,49.90667],"type":"Point"}
}