{
  "type": "Feature",
  "properties": {
    "gn:admin1_code":"27.0",
    "gn:asciiname":"Novaya Zirka",
    "gn:country_code":"UA",
    "gn:dem":271,
    "gn:feature_class":"P",
    "gn:feature_code":"PPL",
    "gn:name":"Novaya Zirka",
    "gn:population":0,
    "gn:timezone":"Europe/Kiev",
    "iso:country":"UA",
    "wof:name":"Novaya Zirka",
    "wof:placetype":"locality"
},
  "geometry": {"coordinates":[27.95,50.05],"type":"Point"}
}