{
  "type": "Feature",
  "properties": {
    "gn:admin1_code":"27.0",
    "gn:asciiname":"Zubivshchyna",
    "gn:country_code":"UA",
    "gn:dem":179,
    "gn:feature_class":"P",
    "gn:feature_code":"PPL",
    "gn:name":"Zubivshchyna",
    "gn:population":0,
    "gn:timezone":"Europe/Kiev",
    "iso:country":"UA",
    "name:ukr_x_preferred":[
        "Zubivshchyna"
    ],
    "name:ukr_x_variant":[
        "\u0417\u0443\u0431\u0456\u0432\u0449\u0438\u043d\u0430"
    ],
    "name:und_x_variant":[
        "Zubovshchina"
    ],
    "wof:name":"Zubivshchyna",
    "wof:placetype":"locality"
},
  "geometry": {"coordinates":[28.81672,50.96034],"type":"Point"}
}