{
  "type": "Feature",
  "properties": {
    "gn:admin1_code":"17.0",
    "gn:asciiname":"Vodyane",
    "gn:country_code":"UA",
    "gn:dem":94,
    "gn:feature_class":"P",
    "gn:feature_code":"PPL",
    "gn:name":"Vodyane",
    "gn:population":0,
    "gn:timezone":"Europe/Kiev",
    "iso:country":"UA",
    "name:ukr_x_preferred":[
        "Vodyane"
    ],
    "name:und_x_variant":[
        "Vodyanoye",
        "Vodyana"
    ],
    "wof:name":"Vodyane",
    "wof:placetype":"locality"
},
  "geometry": {"coordinates":[29.8572,47.13481],"type":"Point"}
}