{
  "type": "Feature",
  "properties": {
    "gn:admin1_code":"18.0",
    "gn:asciiname":"Halahurivka",
    "gn:country_code":"UA",
    "gn:dem":118,
    "gn:feature_class":"P",
    "gn:feature_code":"PPL",
    "gn:name":"Halahurivka",
    "gn:population":0,
    "gn:timezone":"Europe/Kiev",
    "iso:country":"UA",
    "name:ukr_x_preferred":[
        "Halahurivka"
    ],
    "name:ukr_x_variant":[
        "\u0413\u0430\u043b\u0430\u0433\u0443\u0440\u0456\u0432\u043a\u0430"
    ],
    "name:und_x_variant":[
        "Galagurovka"
    ],
    "wof:name":"Halahurivka",
    "wof:placetype":"locality"
},
  "geometry": {"coordinates":[34.15623,49.20136],"type":"Point"}
}