{
  "type": "Feature",
  "properties": {
    "gn:admin1_code":"6.0",
    "gn:asciiname":"Lyubizhnya",
    "gn:country_code":"UA",
    "gn:dem":543,
    "gn:feature_class":"P",
    "gn:feature_code":"PPL",
    "gn:name":"Lyubizhnya",
    "gn:population":0,
    "gn:timezone":"Europe/Kiev",
    "iso:country":"UA",
    "wof:name":"Lyubizhnya",
    "wof:placetype":"locality"
},
  "geometry": {"coordinates":[24.56667,48.55],"type":"Point"}
}