{
  "type": "Feature",
  "properties": {
    "gn:admin1_code":"17.0",
    "gn:asciiname":"Chystovodne",
    "gn:country_code":"UA",
    "gn:dem":98,
    "gn:feature_class":"P",
    "gn:feature_code":"PPL",
    "gn:name":"Chystovodne",
    "gn:population":0,
    "gn:timezone":"Europe/Kiev",
    "iso:country":"UA",
    "name:und_x_variant":[
        "Suyunduk",
        "Chistovodnoye",
        "Suiunduc",
        "Chystovodne"
    ],
    "wof:name":"Chystovodne",
    "wof:placetype":"locality"
},
  "geometry": {"coordinates":[29.75955,46.44001],"type":"Point"}
}