{
  "type": "Feature",
  "properties": {
    "gn:admin1_code":"22.0",
    "gn:asciiname":"Golovchintsy",
    "gn:country_code":"UA",
    "gn:dem":277,
    "gn:feature_class":"P",
    "gn:feature_code":"PPL",
    "gn:name":"Golovchintsy",
    "gn:population":0,
    "gn:timezone":"Europe/Kiev",
    "iso:country":"UA",
    "name:und_x_variant":[
        "Golovchyn\u2019tse"
    ],
    "wof:name":"Golovchintsy",
    "wof:placetype":"locality"
},
  "geometry": {"coordinates":[25.73137,48.8236],"type":"Point"}
}