{
  "type": "Feature",
  "properties": {
    "gn:admin1_code":"8.0",
    "gn:asciiname":"Sokolohirne",
    "gn:country_code":"UA",
    "gn:dem":23,
    "gn:feature_class":"P",
    "gn:feature_code":"PPL",
    "gn:name":"Sokolohirne",
    "gn:population":0,
    "gn:timezone":"Europe/Zaporozhye",
    "iso:country":"UA",
    "name:rus_x_preferred":[
        "\u0421\u043e\u043a\u043e\u043b\u043e\u0433\u043e\u0440\u043d\u043e\u0435"
    ],
    "name:ukr_x_preferred":[
        "\u0421\u043e\u043a\u043e\u043b\u043e\u0433\u0456\u0440\u043d\u0435"
    ],
    "name:und_x_variant":[
        "Sokologornoye",
        "Sokotowgornoje",
        "Sokolohirne"
    ],
    "wof:name":"Sokolohirne",
    "wof:placetype":"locality"
},
  "geometry": {"coordinates":[34.94653,46.50142],"type":"Point"}
}