{
  "type": "Feature",
  "properties": {
    "gn:admin1_code":"21.0",
    "gn:asciiname":"Pomirky",
    "gn:country_code":"UA",
    "gn:dem":167,
    "gn:feature_class":"P",
    "gn:feature_code":"PPL",
    "gn:name":"Pomirky",
    "gn:population":0,
    "gn:timezone":"Europe/Kiev",
    "iso:country":"UA",
    "name:ukr_x_preferred":[
        "Pomirky"
    ],
    "name:ukr_x_variant":[
        "\u041f\u043e\u043c\u0456\u0440\u043a\u0438"
    ],
    "name:und_x_variant":[
        "Pomerki"
    ],
    "wof:name":"Pomirky",
    "wof:placetype":"locality"
},
  "geometry": {"coordinates":[34.12357,50.70072],"type":"Point"}
}