{
  "type": "Feature",
  "properties": {
    "gn:admin1_code":"18.0",
    "gn:asciiname":"Sinne",
    "gn:country_code":"UA",
    "gn:dem":66,
    "gn:feature_class":"P",
    "gn:feature_code":"PPL",
    "gn:name":"Sinne",
    "gn:population":0,
    "gn:timezone":"Europe/Kiev",
    "iso:country":"UA",
    "name:ukr_x_preferred":[
        "Sinne"
    ],
    "name:ukr_x_variant":[
        "\u0421\u0456\u043d\u043d\u0435"
    ],
    "wof:name":"Sinne",
    "wof:placetype":"locality"
},
  "geometry": {"coordinates":[34.30528,48.96184],"type":"Point"}
}