{
  "type": "Feature",
  "properties": {
    "gn:admin1_code":"14.0",
    "gn:asciiname":"Orikhivka",
    "gn:country_code":"UA",
    "gn:dem":213,
    "gn:feature_class":"P",
    "gn:feature_code":"PPL",
    "gn:name":"Orikhivka",
    "gn:population":0,
    "gn:timezone":"Europe/Zaporozhye",
    "iso:country":"UA",
    "name:eng_x_preferred":[
        "Orekhovka"
    ],
    "name:rus_x_preferred":[
        "\u041e\u0440\u0435\u0445\u043e\u0432\u043a\u0430"
    ],
    "name:ukr_x_preferred":[
        "Orikhivka"
    ],
    "name:ukr_x_variant":[
        "\u041e\u0440\u0456\u0445\u0456\u0432\u043a\u0430"
    ],
    "name:und_x_variant":[
        "Orekhovo"
    ],
    "wof:name":"Orikhivka",
    "wof:placetype":"locality"
},
  "geometry": {"coordinates":[39.20306,48.29083],"type":"Point"}
}