{
  "type": "Feature",
  "properties": {
    "gn:admin1_code":"19.0",
    "gn:asciiname":"Prykladnyky",
    "gn:country_code":"UA",
    "gn:dem":138,
    "gn:feature_class":"P",
    "gn:feature_code":"PPL",
    "gn:name":"Prykladnyky",
    "gn:population":0,
    "gn:timezone":"Europe/Kiev",
    "iso:country":"UA",
    "name:ukr_x_preferred":[
        "Prykladnyky"
    ],
    "name:ukr_x_variant":[
        "\u041f\u0440\u0438\u043a\u043b\u0430\u0434\u043d\u0438\u043a\u0438"
    ],
    "name:und_x_variant":[
        "Prikladniki"
    ],
    "wof:name":"Prykladnyky",
    "wof:placetype":"locality"
},
  "geometry": {"coordinates":[25.8443,51.91625],"type":"Point"}
}