{
  "type": "Feature",
  "properties": {
    "gn:admin1_code":"15.0",
    "gn:asciiname":"Bunov",
    "gn:country_code":"UA",
    "gn:dem":245,
    "gn:feature_class":"P",
    "gn:feature_code":"PPL",
    "gn:name":"Bunov",
    "gn:population":0,
    "gn:timezone":"Europe/Kiev",
    "iso:country":"UA",
    "name:und_x_variant":[
        "Buniv",
        "Bonuv",
        "Bunov"
    ],
    "wof:name":"Bunov",
    "wof:placetype":"locality"
},
  "geometry": {"coordinates":[23.26518,49.89362],"type":"Point"}
}