{
  "type": "Feature",
  "properties": {
    "gn:gn_country":"UA",
    "gn:gn_fcode":"PPL",
    "gn:gn_pop":23900,
    "gn:population":23900,
    "iso:country":"UA",
    "name:arm_x_preferred":[
        "\u0534\u0578\u056f\u0578\u0582\u0579\u0561\u0587\u057d\u056f"
    ],
    "name:cat_x_preferred":[
        "Dokutx\u00e0ievsk"
    ],
    "name:chi_x_preferred":[
        "\u591a\u5eab\u6070\u8036\u592b"
    ],
    "name:cze_x_preferred":[
        "Doku\u010dajivsk"
    ],
    "name:dut_x_preferred":[
        "Dokuchaevsk"
    ],
    "name:eng_x_preferred":[
        "Dokuchayevsk"
    ],
    "name:est_x_preferred":[
        "Dokut\u0161ajevsk"
    ],
    "name:fre_x_preferred":[
        "Dokoutcha\u00efevsk"
    ],
    "name:geo_x_preferred":[
        "\u10d3\u10dd\u10d9\u10e3\u10e9\u10d0\u10d4\u10d5\u10e1\u10d9\u10d8"
    ],
    "name:ger_x_preferred":[
        "Dokutschajewsk"
    ],
    "name:hsb_x_preferred":[
        "Doku\u010dajewsk"
    ],
    "name:ita_x_preferred":[
        "Doku\u010dajevs'k"
    ],
    "name:lav_x_preferred":[
        "Doku\u010dajevska"
    ],
    "name:nno_x_preferred":[
        "Dokutsjajevsk"
    ],
    "name:nob_x_preferred":[
        "Dokutsjajevsk"
    ],
    "name:per_x_preferred":[
        "\u062f\u0648\u06a9\u0648\u0686\u0627\u06cc\u0641\u0633\u06a9"
    ],
    "name:pol_x_preferred":[
        "Dokuczajewsk"
    ],
    "name:rum_x_preferred":[
        "Dokuceaievsk"
    ],
    "name:rus_x_preferred":[
        "\u0414\u043e\u043a\u0443\u0447\u0430\u0435\u0432\u0441\u043a"
    ],
    "name:sco_x_preferred":[
        "Dokuchaievsk"
    ],
    "name:srp_x_preferred":[
        "\u0414\u043e\u043a\u0443\u0447\u0430\u0458\u0435\u0432\u0441\u043a"
    ],
    "name:tat_x_preferred":[
        "\u0414\u043e\u043a\u0443\u0447\u0430\u0435\u0432\u0441\u043a"
    ],
    "name:ukr_x_preferred":[
        "Dokuchayevs\u2019k"
    ],
    "name:ukr_x_variant":[
        "\u0414\u043e\u043a\u0443\u0447\u0430\u0454\u0432\u0441\u044c\u043a"
    ],
    "name:unk_x_variant":[
        "Yelenovskiy Kar\u2019yer"
    ],
    "name:vie_x_preferred":[
        "Dokuchaievsk"
    ],
    "qs_pg:aaroncc":"UA",
    "qs_pg:gn_country":"UA",
    "qs_pg:gn_fcode":"PPL",
    "qs_pg:gn_pop":23900,
    "qs_pg:name":"Dokuchayevsk",
    "qs_pg:name_adm0":"Ukraine",
    "qs_pg:name_adm1":"Donets\u00b4ka Oblast\u00b4",
    "qs_pg:photos_9k":1,
    "qs_pg:photos_9r":1,
    "qs_pg:photos_all":1,
    "qs_pg:photos_sr":0,
    "qs_pg:pop_sr":7,
    "qs_pg:qs_pg_placetype":"locality",
    "qs_pg:qs_pg_placetype_gp":"Town",
    "qs_pg:woe_adm0":23424976,
    "woe:adm0_id":23424976,
    "woe:name_adm0":"Ukraine",
    "woe:name_adm1":"Donets\u00b4ka Oblast\u00b4",
    "woe:placetype":"Town",
    "wof:name":"Dokuchayevsk",
    "wof:placetype":"locality",
    "wof:population":23900
},
  "geometry": {"coordinates":[37.67384,47.74773],"type":"Point"}
}