{
  "type": "Feature",
  "properties": {
    "gn:admin1_code":"15.0",
    "gn:asciiname":"Podlese",
    "gn:country_code":"UA",
    "gn:dem":243,
    "gn:feature_class":"P",
    "gn:feature_code":"PPL",
    "gn:name":"Podlese",
    "gn:population":0,
    "gn:timezone":"Europe/Kiev",
    "iso:country":"UA",
    "name:und_x_variant":[
        "Podles\u2019ye",
        "Podlese"
    ],
    "wof:name":"Podlese",
    "wof:placetype":"locality"
},
  "geometry": {"coordinates":[23.72443,50.14583],"type":"Point"}
}