{
  "type": "Feature",
  "properties": {
    "gn:admin1_code":"18.0",
    "gn:asciiname":"Stepivka",
    "gn:country_code":"UA",
    "gn:dem":69,
    "gn:feature_class":"P",
    "gn:feature_code":"PPL",
    "gn:name":"Stepivka",
    "gn:population":0,
    "gn:timezone":"Europe/Kiev",
    "iso:country":"UA",
    "name:ukr_x_preferred":[
        "Stepivka"
    ],
    "name:ukr_x_variant":[
        "\u0421\u0442\u0435\u043f\u0456\u0432\u043a\u0430"
    ],
    "wof:name":"Stepivka",
    "wof:placetype":"locality"
},
  "geometry": {"coordinates":[33.64638,49.20879],"type":"Point"}
}