{
  "type": "Feature",
  "properties": {
    "gn:admin1_code":"18.0",
    "gn:asciiname":"Chapayeve",
    "gn:country_code":"UA",
    "gn:dem":84,
    "gn:feature_class":"P",
    "gn:feature_code":"PPL",
    "gn:name":"Chapayeve",
    "gn:population":0,
    "gn:timezone":"Europe/Kiev",
    "iso:country":"UA",
    "name:ukr_x_preferred":[
        "Chapayeve"
    ],
    "name:ukr_x_variant":[
        "\u0427\u0430\u043f\u0430\u0454\u0432\u0435"
    ],
    "wof:name":"Chapayeve",
    "wof:placetype":"locality"
},
  "geometry": {"coordinates":[34.42451,49.23421],"type":"Point"}
}