{
  "type": "Feature",
  "properties": {
    "gn:country":"UA",
    "gn:fcode":"PPL",
    "gn:population":5126,
    "iso:country":"UA",
    "name:bel_x_preferred":[
        "\u041f\u044d\u0447\u044d\u043d\u0456\u0436\u044b\u043d"
    ],
    "name:ceb_x_preferred":[
        "Pechenizhyn"
    ],
    "name:ces_x_preferred":[
        "Pe\u010deni\u017eyn"
    ],
    "name:che_x_preferred":[
        "\u041f\u0435\u0447\u0435\u043d\u0435\u0436\u0438\u043d"
    ],
    "name:crh_x_preferred":[
        "Pe\u00e7enij\u0131n"
    ],
    "name:deu_x_preferred":[
        "Petschenischyn"
    ],
    "name:eng_x_preferred":[
        "Pechenizhyn"
    ],
    "name:fra_x_preferred":[
        "Petchenijyn"
    ],
    "name:heb_x_preferred":[
        "\u05e4\u05e6'\u05e0\u05d9\u05d6'\u05d9\u05df"
    ],
    "name:mdf_x_preferred":[
        "\u041f\u044d\u0447\u044d\u043d\u0438\u0436\u044b\u043d"
    ],
    "name:pol_x_preferred":[
        "Peczeni\u017cyn"
    ],
    "name:ron_x_preferred":[
        "Pecenij\u00een"
    ],
    "name:rus_x_preferred":[
        "\u041f\u0435\u0447\u0435\u043d\u0456\u0436\u0438\u043d"
    ],
    "name:rus_x_variant":[
        "\u041f\u0435\u0447\u0435\u043d\u0435\u0436\u0438\u043d"
    ],
    "name:swe_x_preferred":[
        "Petjenizjyn"
    ],
    "name:ukr_x_preferred":[
        "\u041f\u0435\u0447\u0435\u043d\u0456\u0436\u0438\u043d"
    ],
    "name:und_x_variant":[
        "Pechenezhin"
    ],
    "name:uzb_x_preferred":[
        "Pechenizhyn"
    ],
    "name:yid_x_preferred":[
        "\u05e4\u05e2\u05d8\u05e9\u05d9\u05e0\u05d9\u05d6\u05e9\u05d9\u05df"
    ],
    "name:zho_x_preferred":[
        "\u4f69\u5207\u5c3c\u4efb"
    ],
    "qs_pg:aaroncc":"UA",
    "qs_pg:gn_country":"UA",
    "qs_pg:gn_fcode":"PPL",
    "qs_pg:gn_pop":5126,
    "qs_pg:name":"Pechenizhyn",
    "qs_pg:photos_9r":0,
    "qs_pg:photos_sr":0,
    "qs_pg:pop_sr":5,
    "qs_pg:qs_pg_placetype":"locality",
    "wof:name":"Pechenizhyn",
    "wof:placetype":"locality",
    "wof:population":5126
},
  "geometry": {"coordinates":[24.89423,48.51551],"type":"Point"}
}