{
  "type": "Feature",
  "properties": {
    "gn:admin1_code":"16.0",
    "gn:asciiname":"Pavlivka",
    "gn:country_code":"UA",
    "gn:dem":86,
    "gn:feature_class":"P",
    "gn:feature_code":"PPL",
    "gn:name":"Pavlivka",
    "gn:population":0,
    "gn:timezone":"Europe/Kiev",
    "iso:country":"UA",
    "name:bel_x_preferred":[
        "\u041f\u0430\u045e\u043b\u0430\u045e\u043a\u0430"
    ],
    "name:ceb_x_preferred":[
        "Pavlivka"
    ],
    "name:crh_x_preferred":[
        "Pavlivka"
    ],
    "name:fra_x_preferred":[
        "Paw\u0142\u00f3wka"
    ],
    "name:hye_x_preferred":[
        "\u054a\u0561\u057e\u056c\u0578\u057e\u056f\u0561"
    ],
    "name:pol_x_preferred":[
        "Paw\u0142\u00f3wka"
    ],
    "name:rus_x_preferred":[
        "\u041f\u0430\u0432\u043b\u043e\u0432\u043a\u0430"
    ],
    "name:ukr_x_preferred":[
        "Pavlivka"
    ],
    "name:ukr_x_variant":[
        "\u041f\u0430\u0432\u043b\u0456\u0432\u043a\u0430",
        "\u041f\u0430\u0432\u043b\u0443\u0432\u043a\u0430"
    ],
    "name:und_x_variant":[
        "Pavlovka"
    ],
    "wof:name":"Pavlivka",
    "wof:placetype":"locality"
},
  "geometry": {"coordinates":[32.94661,47.71815],"type":"Point"}
}