{
  "type": "Feature",
  "properties": {
    "gn:admin1_code":"26.0",
    "gn:asciiname":"Dobrovol'ches'ke",
    "gn:country_code":"UA",
    "gn:dem":78,
    "gn:feature_class":"P",
    "gn:feature_code":"PPL",
    "gn:name":"Dobrovol\u2019ches\u2019ke",
    "gn:population":0,
    "gn:timezone":"Europe/Zaporozhye",
    "iso:country":"UA",
    "name:ukr_x_preferred":[
        "Dobrovol\u2019ches\u2019ke"
    ],
    "name:ukr_x_variant":[
        "\u0414\u043e\u0431\u0440\u043e\u0432\u043e\u043b\u044c\u0447\u0435\u0441\u044c\u043a\u0435"
    ],
    "name:und_x_variant":[
        "Dobrovol\u2019cheskiy"
    ],
    "wof:name":"Dobrovol'ches'ke",
    "wof:placetype":"locality"
},
  "geometry": {"coordinates":[34.5719,47.13664],"type":"Point"}
}