{
  "type": "Feature",
  "properties": {
    "gn:admin1_code":"8.0",
    "gn:asciiname":"Skhidne",
    "gn:country_code":"UA",
    "gn:dem":28,
    "gn:feature_class":"P",
    "gn:feature_code":"PPL",
    "gn:name":"Skhidne",
    "gn:population":0,
    "gn:timezone":"Europe/Kiev",
    "iso:country":"UA",
    "name:ukr_x_preferred":[
        "Skhidne"
    ],
    "name:ukr_x_variant":[
        "\u0421\u0445\u0456\u0434\u043d\u0435"
    ],
    "name:und_x_variant":[
        "Skhidnoye"
    ],
    "wof:name":"Skhidne",
    "wof:placetype":"locality"
},
  "geometry": {"coordinates":[32.59844,46.81446],"type":"Point"}
}