{
  "type": "Feature",
  "properties": {
    "gn:admin1_code":"19.0",
    "gn:asciiname":"Mychiv",
    "gn:country_code":"UA",
    "gn:dem":207,
    "gn:feature_class":"P",
    "gn:feature_code":"PPL",
    "gn:name":"Mychiv",
    "gn:population":0,
    "gn:timezone":"Europe/Kiev",
    "iso:country":"UA",
    "name:ukr_x_preferred":[
        "Mychiv"
    ],
    "name:ukr_x_variant":[
        "\u041c\u0438\u0447\u0456\u0432"
    ],
    "name:und_x_variant":[
        "Mychev"
    ],
    "wof:name":"Mychiv",
    "wof:placetype":"locality"
},
  "geometry": {"coordinates":[26.78429,50.73783],"type":"Point"}
}