{
  "type": "Feature",
  "properties": {
    "gn:admin1_code":"26.0",
    "gn:asciiname":"Lisne",
    "gn:country_code":"UA",
    "gn:dem":127,
    "gn:feature_class":"P",
    "gn:feature_code":"PPL",
    "gn:name":"Lisne",
    "gn:population":0,
    "gn:timezone":"Europe/Zaporozhye",
    "iso:country":"UA",
    "name:ukr_x_preferred":[
        "Lisne"
    ],
    "name:ukr_x_variant":[
        "\u041b\u0456\u0441\u043d\u0435"
    ],
    "wof:name":"Lisne",
    "wof:placetype":"locality"
},
  "geometry": {"coordinates":[35.98625999999999,47.74638],"type":"Point"}
}