{
  "type": "Feature",
  "properties": {
    "gn:admin1_code":"17.0",
    "gn:asciiname":"Parapory",
    "gn:country_code":"UA",
    "gn:dem":6,
    "gn:feature_class":"P",
    "gn:feature_code":"PPL",
    "gn:name":"Parapory",
    "gn:population":0,
    "gn:timezone":"Europe/Kiev",
    "iso:country":"UA",
    "name:und_x_variant":[
        "Paravora",
        "Parapory"
    ],
    "wof:name":"Parapory",
    "wof:placetype":"locality"
},
  "geometry": {"coordinates":[29.38333,45.51667],"type":"Point"}
}