{
  "type": "Feature",
  "properties": {
    "gn:admin1_code":"24.0",
    "gn:asciiname":"Lypa",
    "gn:country_code":"UA",
    "gn:dem":198,
    "gn:feature_class":"P",
    "gn:feature_code":"PPL",
    "gn:name":"Lypa",
    "gn:population":0,
    "gn:timezone":"Europe/Kiev",
    "iso:country":"UA",
    "name:deu_x_preferred":[
        "Lypa"
    ],
    "name:ukr_x_preferred":[
        "Lypa"
    ],
    "name:ukr_x_variant":[
        "\u041b\u0438\u043f\u0430"
    ],
    "wof:name":"Lypa",
    "wof:placetype":"locality"
},
  "geometry": {"coordinates":[24.74525,50.92677],"type":"Point"}
}