{
  "type": "Feature",
  "properties": {
    "gn:admin1_code":"16.0",
    "gn:asciiname":"Tsaredarovka",
    "gn:country_code":"UA",
    "gn:dem":137,
    "gn:feature_class":"P",
    "gn:feature_code":"PPL",
    "gn:name":"Tsaredarovka",
    "gn:population":0,
    "gn:timezone":"Europe/Kiev",
    "iso:country":"UA",
    "wof:name":"Tsaredarovka",
    "wof:placetype":"locality"
},
  "geometry": {"coordinates":[30.8429,47.71942],"type":"Point"}
}