{
  "type": "Feature",
  "properties": {
    "gn:admin1_code":"13.0",
    "gn:asciiname":"Ozhegovka",
    "gn:country_code":"UA",
    "gn:dem":182,
    "gn:feature_class":"P",
    "gn:feature_code":"PPL",
    "gn:name":"Ozhegovka",
    "gn:population":0,
    "gn:timezone":"Europe/Kiev",
    "iso:country":"UA",
    "name:und_x_variant":[
        "Ozhigovka",
        "Ozhegovka"
    ],
    "wof:name":"Ozhegovka",
    "wof:placetype":"locality"
},
  "geometry": {"coordinates":[30.04917,49.52688],"type":"Point"}
}