{
  "type": "Feature",
  "properties": {
    "gn:admin1_code":"27.0",
    "gn:asciiname":"Begunskiye",
    "gn:country_code":"UA",
    "gn:dem":140,
    "gn:feature_class":"P",
    "gn:feature_code":"PPL",
    "gn:name":"Begunskiye",
    "gn:population":0,
    "gn:timezone":"Europe/Kiev",
    "iso:country":"UA",
    "name:und_x_variant":[
        "Begunskiy",
        "Begunskiye"
    ],
    "wof:name":"Begunskiye",
    "wof:placetype":"locality"
},
  "geometry": {"coordinates":[28.26667,51.66667],"type":"Point"}
}