{
  "type": "Feature",
  "properties": {
    "iso:country":"UA",
    "name:bul_x_preferred":[
        "\u0421\u043f\u0430\u0441 \u0414\u0436\u0435\u0432\u0438\u0437\u043e\u0432"
    ],
    "name:ell_x_preferred":[
        "\u03a3\u03c0\u03b1\u03c2 \u03a4\u03b6\u03b5\u03b2\u03af\u03b6\u03bf\u03c6"
    ],
    "name:eng_x_preferred":[
        "Spas Dzhevizov"
    ],
    "name:fra_x_preferred":[
        "Spas Dzhevizov"
    ],
    "name:ita_x_preferred":[
        "Spas D\u017eevizov"
    ],
    "name:nld_x_preferred":[
        "Spas Dzhevizov"
    ],
    "name:nno_x_preferred":[
        "Spas Dzjevizov"
    ],
    "name:nob_x_preferred":[
        "Spas Dzjevizov"
    ],
    "name:pol_x_preferred":[
        "Spas D\u017cewizow"
    ],
    "name:spa_x_preferred":[
        "Spas Dzhevizov"
    ],
    "name:unk_x_variant":[
        "Hirs\u2019ke"
    ],
    "qs:a0":"\u0423\u043a\u0440\u0430\u0457\u043d\u0430",
    "qs:a1":"*\u0406\u0432\u0430\u043d\u043e-\u0424\u0440\u0430\u043d\u043a\u0456\u0432\u0441\u044c\u043a\u0430",
    "qs:a1_alt":"Ivano-Frankivs'ka",
    "qs:a1r":"0",
    "qs:a2":"\u041a\u043e\u0441\u0456\u0432\u0441\u044c\u043a\u0438\u0439",
    "qs:a2_alt":"Kosivs'kyi",
    "qs:adm0":"\u0423\u043a\u0440\u0430\u0457\u043d\u0430",
    "qs:la_lc":"*",
    "qs:level":"locality",
    "qs:loc":"\u0421\u043f\u0430\u0441",
    "qs:loc_alt":"Spas",
    "qs:pop":0,
    "qs:type":"buffered point",
    "wd:wordcount":191,
    "wof:name":"\u0421\u043f\u0430\u0441",
    "wof:placetype":"locality"
},
  "geometry": {"coordinates":[25.067441,48.423952],"type":"Point"}
}