{
  "type": "Feature",
  "properties": {
    "gn:admin1_code":"15.0",
    "gn:asciiname":"Boloziv",
    "gn:country_code":"UA",
    "gn:dem":297,
    "gn:feature_class":"P",
    "gn:feature_code":"PPL",
    "gn:name":"Boloziv",
    "gn:population":0,
    "gn:timezone":"Europe/Kiev",
    "iso:country":"UA",
    "name:rus_x_preferred":[
        "\u0411\u043e\u043b\u043e\u0437\u0435\u0432"
    ],
    "name:ukr_x_preferred":[
        "\u0411\u043e\u043b\u043e\u0437\u0456\u0432"
    ],
    "name:und_x_variant":[
        "Blazhev",
        "Bolozev"
    ],
    "wof:name":"Boloziv",
    "wof:placetype":"locality"
},
  "geometry": {"coordinates":[22.91848,49.59174],"type":"Point"}
}