{
  "type": "Feature",
  "properties": {
    "gn:admin1_code":"14.0",
    "gn:asciiname":"Kul'va",
    "gn:country_code":"UA",
    "gn:dem":298,
    "gn:feature_class":"P",
    "gn:feature_code":"PPL",
    "gn:name":"Kul\u2019va",
    "gn:population":0,
    "gn:timezone":"Europe/Zaporozhye",
    "iso:country":"UA",
    "wof:name":"Kul'va",
    "wof:placetype":"locality"
},
  "geometry": {"coordinates":[38.93417,48.15694000000001],"type":"Point"}
}