{
  "type": "Feature",
  "properties": {
    "iso:country":"UA",
    "name:eng_x_preferred":[
        "Fornosh"
    ],
    "name:epo_x_preferred":[
        "Forno\u015d"
    ],
    "name:hun_x_preferred":[
        "Fornos"
    ],
    "name:hye_x_preferred":[
        "\u0556\u0578\u0580\u0576\u0578\u0577"
    ],
    "name:nld_x_preferred":[
        "Fornos"
    ],
    "name:ron_x_preferred":[
        "Forno\u0219"
    ],
    "name:rus_x_preferred":[
        "\u0424\u043e\u0440\u043d\u043e\u0448"
    ],
    "name:ukr_x_preferred":[
        "\u0424\u043e\u0440\u043d\u043e\u0448"
    ],
    "name:und_x_variant":[
        "Liskove"
    ],
    "name:zho_x_preferred":[
        "\u798f\u723e\u8afe\u4ec0"
    ],
    "qs:a0":"\u0423\u043a\u0440\u0430\u0457\u043d\u0430",
    "qs:a1":"*\u0417\u0430\u043a\u0430\u0440\u043f\u0430\u0442\u0441\u044c\u043a\u0430",
    "qs:a1_alt":"Zakarpats'ka",
    "qs:a1r":"0",
    "qs:a2":"\u041c\u0443\u043a\u0430\u0447\u0456\u0432\u0441\u044c\u043a\u0438\u0439",
    "qs:a2_alt":"Mukachivs'kyi",
    "qs:adm0":"\u0423\u043a\u0440\u0430\u0457\u043d\u0430",
    "qs:la_lc":"*",
    "qs:level":"locality",
    "qs:loc":"\u0424\u043e\u0440\u043d\u043e\u0448",
    "qs:loc_alt":"Fornosh",
    "qs:pop":0,
    "qs:type":"buffered point",
    "wd:wordcount":84,
    "wof:name":"\u0424\u043e\u0440\u043d\u043e\u0448",
    "wof:placetype":"locality"
},
  "geometry": {"coordinates":[22.742806,48.365063],"type":"Point"}
}