{
  "type": "Feature",
  "properties": {
    "gn:admin1_code":"22.0",
    "gn:asciiname":"Vanzhuliv",
    "gn:country_code":"UA",
    "gn:dem":280,
    "gn:feature_class":"P",
    "gn:feature_code":"PPL",
    "gn:name":"Vanzhuliv",
    "gn:population":0,
    "gn:timezone":"Europe/Kiev",
    "iso:country":"UA",
    "name:und_x_variant":[
        "Vanzhulov",
        "Vanzhuliv"
    ],
    "wof:name":"Vanzhuliv",
    "wof:placetype":"locality"
},
  "geometry": {"coordinates":[26.07657,49.78947],"type":"Point"}
}