{
  "type": "Feature",
  "properties": {
    "gn:admin1_code":"26.0",
    "gn:asciiname":"Vernyy",
    "gn:cc2":"UA",
    "gn:country_code":"UA",
    "gn:dem":214,
    "gn:feature_class":"P",
    "gn:feature_code":"PPL",
    "gn:name":"Vernyy",
    "gn:population":0,
    "gn:timezone":"Europe/Zaporozhye",
    "iso:country":"UA",
    "name:und_x_variant":[
        "Verny",
        "Vernyy"
    ],
    "wof:name":"Vernyy",
    "wof:placetype":"locality"
},
  "geometry": {"coordinates":[36.86667,47.33333],"type":"Point"}
}