{
  "type": "Feature",
  "properties": {
    "gn:admin1_code":"11.0",
    "gn:admin2_code":"693803",
    "gn:admin3_code":"11152620.0",
    "gn:asciiname":"Peredovoye",
    "gn:country_code":"UA",
    "gn:dem":104,
    "gn:elevation":"122.0",
    "gn:feature_class":"P",
    "gn:feature_code":"PPL",
    "gn:name":"Peredovoye",
    "gn:population":218,
    "gn:timezone":"Europe/Simferopol",
    "iso:country":"UA",
    "name:che_x_preferred":[
        "\u041f\u0435\u0440\u0435\u0434\u043e\u0432\u0438"
    ],
    "name:eng_x_preferred":[
        "Peredovoye"
    ],
    "name:rus_x_preferred":[
        "\u041f\u0435\u0440\u0435\u0434\u043e\u0432\u043e\u0435"
    ],
    "name:tgk_x_preferred":[
        "\u041f\u0435\u0440\u0435\u0434\u043e\u0432\u043e\u0435"
    ],
    "name:ukr_x_preferred":[
        "\u041f\u0435\u0440\u0435\u0434\u043e\u0432\u0435"
    ],
    "wof:name":"Peredovoye",
    "wof:placetype":"locality",
    "wof:population":218
},
  "geometry": {"coordinates":[33.8254,45.05169],"type":"Point"}
}