{
  "type": "Feature",
  "properties": {
    "gn:admin1_code":"18.0",
    "gn:asciiname":"Khudoliyivka",
    "gn:country_code":"UA",
    "gn:dem":86,
    "gn:feature_class":"P",
    "gn:feature_code":"PPL",
    "gn:name":"Khudoliyivka",
    "gn:population":0,
    "gn:timezone":"Europe/Kiev",
    "iso:country":"UA",
    "name:eng_x_preferred":[
        "Khudoleyevka"
    ],
    "name:rus_x_preferred":[
        "\u0425\u0443\u0434\u043e\u043b\u0438\u0435\u0432\u043a\u0430"
    ],
    "name:ukr_x_preferred":[
        "Khudoliyivka"
    ],
    "name:ukr_x_variant":[
        "\u0425\u0443\u0434\u043e\u043b\u0456\u0457\u0432\u043a\u0430"
    ],
    "name:und_x_variant":[
        "Khudoleyevka"
    ],
    "wof:name":"Khudoliyivka",
    "wof:placetype":"locality"
},
  "geometry": {"coordinates":[32.91542,49.75684],"type":"Point"}
}