{
  "type": "Feature",
  "properties": {
    "gn:admin1_code":"24.0",
    "gn:asciiname":"Korsyni",
    "gn:country_code":"UA",
    "gn:dem":174,
    "gn:feature_class":"P",
    "gn:feature_code":"PPL",
    "gn:name":"Korsyni",
    "gn:population":0,
    "gn:timezone":"Europe/Kiev",
    "iso:country":"UA",
    "name:ukr_x_preferred":[
        "Korsyni"
    ],
    "name:ukr_x_variant":[
        "\u041a\u043e\u0440\u0441\u0438\u043d\u0456"
    ],
    "name:und_x_variant":[
        "Korsyne"
    ],
    "wof:name":"Korsyni",
    "wof:placetype":"locality"
},
  "geometry": {"coordinates":[25.30458,51.11187],"type":"Point"}
}