{
  "type": "Feature",
  "properties": {
    "gn:admin1_code":"24.0",
    "gn:asciiname":"Zemlitsa",
    "gn:country_code":"UA",
    "gn:dem":183,
    "gn:feature_class":"P",
    "gn:feature_code":"PPL",
    "gn:name":"Zemlitsa",
    "gn:population":0,
    "gn:timezone":"Europe/Kiev",
    "iso:country":"UA",
    "wof:name":"Zemlitsa",
    "wof:placetype":"locality"
},
  "geometry": {"coordinates":[24.05,51.08333],"type":"Point"}
}