{
  "type": "Feature",
  "properties": {
    "gn:admin1_code":"25.0",
    "gn:asciiname":"Kholmets'",
    "gn:country_code":"UA",
    "gn:dem":113,
    "gn:feature_class":"P",
    "gn:feature_code":"PPL",
    "gn:name":"Kholmets\u2019",
    "gn:population":0,
    "gn:timezone":"Europe/Uzhgorod",
    "iso:country":"UA",
    "name:hun_x_preferred":[
        "Korl\u00e1thelmec"
    ],
    "name:hun_x_variant":[
        "Helmec"
    ],
    "name:ukr_x_preferred":[
        "Kholmets\u2019"
    ],
    "name:ukr_x_variant":[
        "\u0425\u043e\u043b\u043c\u0435\u0446\u044c"
    ],
    "name:und_x_variant":[
        "Chlumec",
        "Chomec",
        "Gubka Khlmets",
        "Kholmets",
        "Helmec"
    ],
    "wof:name":"Kholmets'",
    "wof:placetype":"locality"
},
  "geometry": {"coordinates":[22.38641,48.52404],"type":"Point"}
}