{
  "type": "Feature",
  "properties": {
    "gn:admin1_code":"21.0",
    "gn:asciiname":"Mykytivka",
    "gn:country_code":"UA",
    "gn:dem":162,
    "gn:feature_class":"P",
    "gn:feature_code":"PPL",
    "gn:name":"Mykytivka",
    "gn:population":0,
    "gn:timezone":"Europe/Kiev",
    "iso:country":"UA",
    "name:ukr_x_preferred":[
        "Mykytivka"
    ],
    "name:ukr_x_variant":[
        "\u041c\u0438\u043a\u0438\u0442\u0456\u0432\u043a\u0430"
    ],
    "name:und_x_variant":[
        "Nikitovka"
    ],
    "wof:name":"Mykytivka",
    "wof:placetype":"locality"
},
  "geometry": {"coordinates":[33.97578,51.90891],"type":"Point"}
}