{
  "type": "Feature",
  "properties": {
    "gn:admin1_code":"19.0",
    "gn:asciiname":"Malyy Stydyn",
    "gn:country_code":"UA",
    "gn:dem":187,
    "gn:feature_class":"P",
    "gn:feature_code":"PPL",
    "gn:name":"Malyy Stydyn",
    "gn:population":0,
    "gn:timezone":"Europe/Kiev",
    "iso:country":"UA",
    "name:ukr_x_preferred":[
        "Malyy Stydyn"
    ],
    "name:ukr_x_variant":[
        "\u041c\u0430\u043b\u0438\u0439 \u0421\u0442\u0438\u0434\u0438\u043d"
    ],
    "name:und_x_variant":[
        "Stydyn\u2019 Maly",
        "Malyy Stydin"
    ],
    "wof:name":"Malyy Stydyn",
    "wof:placetype":"locality"
},
  "geometry": {"coordinates":[26.16493,51.01689],"type":"Point"}
}