{
  "type": "Feature",
  "properties": {
    "gn:admin1_code":"10.0",
    "gn:asciiname":"Vasil'yevka",
    "gn:country_code":"UA",
    "gn:dem":118,
    "gn:feature_class":"P",
    "gn:feature_code":"PPL",
    "gn:name":"Vasil\u2019yevka",
    "gn:population":0,
    "gn:timezone":"Europe/Kiev",
    "iso:country":"UA",
    "wof:name":"Vasil'yevka",
    "wof:placetype":"locality"
},
  "geometry": {"coordinates":[32.26855,47.95113],"type":"Point"}
}