{
  "type": "Feature",
  "properties": {
    "iso:country":"UA",
    "name:ces_x_preferred":[
        "Karlo-Marxove"
    ],
    "name:deu_x_preferred":[
        "Karlo-Marxowe"
    ],
    "name:eng_x_preferred":[
        "Karlo-Marksovo"
    ],
    "name:hye_x_preferred":[
        "\u053f\u0561\u0580\u056c\u0578-\u0544\u0561\u0580\u056f\u057d\u0578\u057e\u0578"
    ],
    "name:lav_x_preferred":[
        "Karlomarksove"
    ],
    "name:rus_x_preferred":[
        "\u041a\u0430\u0440\u043b\u043e-\u041c\u0430\u0440\u043a\u0441\u043e\u0432\u043e"
    ],
    "name:ukr_x_preferred":[
        "Karlo-Marksove"
    ],
    "name:ukr_x_variant":[
        "\u041a\u0430\u0440\u043b\u043e-\u041c\u0430\u0440\u043a\u0441\u043e\u0432\u0435"
    ],
    "name:unk_x_variant":[
        "Imeni Karla Marksa"
    ],
    "name:zho_x_preferred":[
        "\u5361\u723e\u6d1b-\u99ac\u723e\u514b\u7d22\u97cb"
    ],
    "qs:a0":"\u0423\u043a\u0440\u0430\u0457\u043d\u0430",
    "qs:a1":"*\u0414\u043e\u043d\u0435\u0446\u044c\u043a\u0430",
    "qs:a1_alt":"Donets'ka",
    "qs:a1r":"0",
    "qs:a2":"\u042f\u0441\u0438\u043d\u0443\u0432\u0430\u0442\u0441\u044c\u043a\u0438\u0439",
    "qs:a2_alt":"Yasynuvats'kyi",
    "qs:adm0":"\u0423\u043a\u0440\u0430\u0457\u043d\u0430",
    "qs:la_lc":"*",
    "qs:level":"locality",
    "qs:loc":"\u041a\u0430\u0440\u043b\u043e-\u041c\u0430\u0440\u043a\u0441\u043e\u0432\u0435",
    "qs:loc_alt":"Karlo-Marksove",
    "qs:pop":0,
    "qs:type":"buffered point",
    "wof:name":"\u041a\u0430\u0440\u043b\u043e-\u041c\u0430\u0440\u043a\u0441\u043e\u0432\u0435",
    "wof:placetype":"locality"
},
  "geometry": {"coordinates":[38.156994,48.266863],"type":"Point"}
}