{
  "type": "Feature",
  "properties": {
    "gn:admin1_code":"11.0",
    "gn:admin2_code":"703233",
    "gn:admin3_code":"11133124.0",
    "gn:asciiname":"Ogon'ki",
    "gn:country_code":"UA",
    "gn:dem":11,
    "gn:feature_class":"P",
    "gn:feature_code":"PPL",
    "gn:name":"Ogon\u2019ki",
    "gn:population":96,
    "gn:timezone":"Europe/Simferopol",
    "iso:country":"UA",
    "name:eng_x_preferred":[
        "Ogon\u2019ki"
    ],
    "name:rus_x_historical":[
        "\u041e\u0440\u0442\u0430\u0301-\u042d\u043b\u0438\u0301"
    ],
    "name:rus_x_preferred":[
        "\u041e\u0433\u043e\u043d\u044c\u043a\u0438"
    ],
    "name:rus_x_variant":[
        "\u041e\u0440\u0442\u0430\u0301-\u042d\u043b\u0438\u0301"
    ],
    "name:ukr_x_preferred":[
        "\u041e\u0433\u043e\u043d\u044c\u043a\u0438"
    ],
    "wof:name":"Ogon'ki",
    "wof:placetype":"locality",
    "wof:population":96
},
  "geometry": {"coordinates":[36.32708,45.19316],"type":"Point"}
}