{
  "type": "Feature",
  "properties": {
    "gn:admin1_code":"11.0",
    "gn:admin2_code":"710690",
    "gn:admin3_code":"11153137.0",
    "gn:asciiname":"Ozerovka",
    "gn:country_code":"UA",
    "gn:dem":6,
    "gn:elevation":"6.0",
    "gn:feature_class":"P",
    "gn:feature_code":"PPL",
    "gn:name":"Ozerovka",
    "gn:population":8,
    "gn:timezone":"Europe/Simferopol",
    "iso:country":"UA",
    "name:crh_x_historical":[
        "Tabuldy As"
    ],
    "name:crh_x_preferred":[
        "Tabuldy As"
    ],
    "name:eng_x_preferred":[
        "Ozerovka"
    ],
    "name:rus_x_historical":[
        "\u0422\u0435\u0440\u0435\u043a\u043b\u044b\u0301-\u0410\u0441\u0441"
    ],
    "name:rus_x_preferred":[
        "\u041e\u0437\u0451\u0440\u043e\u0432\u043a\u0430"
    ],
    "name:rus_x_variant":[
        "\u0422\u0435\u0440\u0435\u043a\u043b\u044b\u0301-\u0410\u0441\u0441"
    ],
    "name:ukr_x_preferred":[
        "\u041e\u0437\u0435\u0440\u0456\u0432\u043a\u0430"
    ],
    "wof:name":"Ozerovka",
    "wof:placetype":"locality",
    "wof:population":8
},
  "geometry": {"coordinates":[32.97945,45.36318],"type":"Point"}
}