{
  "type": "Feature",
  "properties": {
    "iso:country":"UA",
    "name:deu_x_preferred":[
        "Krasne"
    ],
    "name:eng_x_preferred":[
        "Krasne"
    ],
    "name:lav_x_preferred":[
        "Krasne"
    ],
    "name:ron_x_preferred":[
        "Crasna"
    ],
    "name:rus_x_preferred":[
        "\u041a\u0440\u0430\u0441\u043d\u0435"
    ],
    "name:rus_x_variant":[
        "\u041a\u0440\u0430\u0441\u043d\u043e\u0435"
    ],
    "name:spa_x_preferred":[
        "Krasne"
    ],
    "name:ukr_x_preferred":[
        "\u041a\u0440\u0430\u0441\u043d\u0435"
    ],
    "name:zho_x_preferred":[
        "\u514b\u62c9\u65af\u6d85"
    ],
    "qs:a0":"\u0423\u043a\u0440\u0430\u0457\u043d\u0430",
    "qs:a1":"*\u041e\u0434\u0435\u0441\u044c\u043a\u0430",
    "qs:a1_alt":"Odes'ka",
    "qs:a1r":"0",
    "qs:a2":"\u0422\u0430\u0440\u0443\u0442\u0438\u043d\u0441\u044c\u043a\u0438\u0439",
    "qs:a2_alt":"Tarutyns'kyi",
    "qs:adm0":"\u0423\u043a\u0440\u0430\u0457\u043d\u0430",
    "qs:la_lc":"*",
    "qs:level":"locality",
    "qs:loc":"\u041a\u0440\u0430\u0441\u043d\u0435",
    "qs:loc_alt":"Krasne",
    "qs:pop":0,
    "qs:type":"buffered point",
    "wd:wordcount":97,
    "wof:name":"\u041a\u0440\u0430\u0441\u043d\u0435",
    "wof:placetype":"locality"
},
  "geometry": {"coordinates":[29.246205,46.120479],"type":"Point"}
}