{
  "type": "Feature",
  "properties": {
    "gn:admin1_code":"27.0",
    "gn:asciiname":"Sytne",
    "gn:country_code":"UA",
    "gn:dem":207,
    "gn:feature_class":"P",
    "gn:feature_code":"PPL",
    "gn:name":"Sytne",
    "gn:population":0,
    "gn:timezone":"Europe/Kiev",
    "iso:country":"UA",
    "name:ukr_x_preferred":[
        "Sytne"
    ],
    "name:ukr_x_variant":[
        "\u0421\u0438\u0442\u043d\u0435"
    ],
    "name:und_x_variant":[
        "Sitnoye",
        "Sytnoye"
    ],
    "wof:name":"Sytne",
    "wof:placetype":"locality"
},
  "geometry": {"coordinates":[27.44778,50.84002],"type":"Point"}
}