{
  "type": "Feature",
  "properties": {
    "gn:admin1_code":"9.0",
    "gn:asciiname":"Udriyevtsy",
    "gn:country_code":"UA",
    "gn:dem":328,
    "gn:feature_class":"P",
    "gn:feature_code":"PPL",
    "gn:name":"Udriyevtsy",
    "gn:population":0,
    "gn:timezone":"Europe/Kiev",
    "iso:country":"UA",
    "wof:name":"Udriyevtsy",
    "wof:placetype":"locality"
},
  "geometry": {"coordinates":[26.81332,49.05673],"type":"Point"}
}