{
  "type": "Feature",
  "properties": {
    "gn:admin1_code":"18.0",
    "gn:asciiname":"Shevchenky",
    "gn:country_code":"UA",
    "gn:dem":153,
    "gn:feature_class":"P",
    "gn:feature_code":"PPL",
    "gn:name":"Shevchenky",
    "gn:population":0,
    "gn:timezone":"Europe/Kiev",
    "iso:country":"UA",
    "name:ukr_x_preferred":[
        "Shevchenky"
    ],
    "name:ukr_x_variant":[
        "\u0428\u0435\u0432\u0447\u0435\u043d\u043a\u0438"
    ],
    "name:und_x_variant":[
        "Shevchenki"
    ],
    "wof:name":"Shevchenky",
    "wof:placetype":"locality"
},
  "geometry": {"coordinates":[33.54715,50.37602],"type":"Point"}
}