{
  "type": "Feature",
  "properties": {
    "iso:country":"UA",
    "name:ukr_x_preferred":[
        "Barashivka"
    ],
    "name:ukr_x_variant":[
        "\u0411\u0430\u0440\u0430\u0448\u0456\u0432\u043a\u0430"
    ],
    "name:und_x_variant":[
        "Baryshevka"
    ],
    "qs:a0":"\u0423\u043a\u0440\u0430\u0457\u043d\u0430",
    "qs:a1":"*\u0416\u0438\u0442\u043e\u043c\u0438\u0440\u0441\u044c\u043a\u0430",
    "qs:a1_alt":"Zhytomyrs'ka",
    "qs:a1r":"0",
    "qs:a2":"\u0416\u0438\u0442\u043e\u043c\u0438\u0440\u0441\u044c\u043a\u0438\u0439",
    "qs:a2_alt":"Zhytomyrs'kyi",
    "qs:adm0":"\u0423\u043a\u0440\u0430\u0457\u043d\u0430",
    "qs:la_lc":"*",
    "qs:level":"locality",
    "qs:loc":"\u0411\u0430\u0440\u0430\u0448\u0456\u0432\u043a\u0430",
    "qs:loc_alt":"Barashivka",
    "qs:pop":0,
    "qs:type":"buffered point",
    "wof:name":"\u0411\u0430\u0440\u0430\u0448\u0456\u0432\u043a\u0430",
    "wof:placetype":"locality"
},
  "geometry": {"coordinates":[28.547641,50.274729],"type":"Point"}
}