{
  "type": "Feature",
  "properties": {
    "gn:admin1_code":"2.0",
    "gn:asciiname":"Dukhanky",
    "gn:country_code":"UA",
    "gn:dem":158,
    "gn:feature_class":"P",
    "gn:feature_code":"PPL",
    "gn:name":"Dukhanky",
    "gn:population":0,
    "gn:timezone":"Europe/Kiev",
    "iso:country":"UA",
    "name:ukr_x_preferred":[
        "Dukhanky"
    ],
    "name:ukr_x_variant":[
        "\u0414\u0443\u0445\u0430\u043d\u043a\u0438"
    ],
    "name:und_x_variant":[
        "Dukhanki"
    ],
    "wof:name":"Dukhanky",
    "wof:placetype":"locality"
},
  "geometry": {"coordinates":[30.86318,51.62347000000001],"type":"Point"}
}