{
  "type": "Feature",
  "properties": {
    "gn:admin1_code":"14.0",
    "gn:asciiname":"Sukhoy Baglay",
    "gn:country_code":"UA",
    "gn:dem":124,
    "gn:feature_class":"P",
    "gn:feature_code":"PPL",
    "gn:name":"Sukhoy Baglay",
    "gn:population":0,
    "gn:timezone":"Europe/Zaporozhye",
    "iso:country":"UA",
    "wof:name":"Sukhoy Baglay",
    "wof:placetype":"locality"
},
  "geometry": {"coordinates":[38.53389,49.40638],"type":"Point"}
}