{
  "type": "Feature",
  "properties": {
    "gn:admin1_code":"27.0",
    "gn:asciiname":"Hunychi",
    "gn:country_code":"UA",
    "gn:dem":143,
    "gn:feature_class":"P",
    "gn:feature_code":"PPL",
    "gn:name":"Hunychi",
    "gn:population":0,
    "gn:timezone":"Europe/Kiev",
    "iso:country":"UA",
    "name:bel_x_preferred":[
        "\u0413\u0443\u043d\u044b\u0447\u044b"
    ],
    "name:hye_x_preferred":[
        "\u0533\u0578\u0582\u0576\u056b\u0579\u056b"
    ],
    "name:ron_x_preferred":[
        "Hun\u00eeci"
    ],
    "name:rus_x_preferred":[
        "\u0413\u0443\u043d\u0438\u0447\u0438"
    ],
    "name:ukr_x_preferred":[
        "Hunychi"
    ],
    "name:ukr_x_variant":[
        "\u0413\u0443\u043d\u0438\u0447\u0456"
    ],
    "name:und_x_variant":[
        "Gunichi"
    ],
    "name:zho_x_preferred":[
        "\u53e4\u5c3c\u5947"
    ],
    "wof:name":"Hunychi",
    "wof:placetype":"locality"
},
  "geometry": {"coordinates":[28.91535,51.26508],"type":"Point"}
}