{
  "type": "Feature",
  "properties": {
    "iso:country":"UA",
    "qs:a0":"\u0423\u043a\u0440\u0430\u0457\u043d\u0430",
    "qs:a1":"*\u0425\u043c\u0435\u043b\u044c\u043d\u0438\u0446\u044c\u043a\u0430",
    "qs:a1_alt":"Khmel'nyts'ka",
    "qs:a1r":"0",
    "qs:a2":"\u041b\u0435\u0442\u0438\u0447\u0456\u0432\u0441\u044c\u043a\u0438\u0439",
    "qs:a2_alt":"Letychivs'kyi",
    "qs:adm0":"\u0423\u043a\u0440\u0430\u0457\u043d\u0430",
    "qs:la_lc":"*",
    "qs:level":"locality",
    "qs:loc":"\u0413\u043e\u043b\u043e\u0441\u043a\u0456\u0432",
    "qs:loc_alt":"Holoskiv",
    "qs:pop":0,
    "qs:type":"buffered point",
    "wd:wordcount":266,
    "wof:name":"\u0413\u043e\u043b\u043e\u0441\u043a\u0456\u0432",
    "wof:placetype":"locality"
},
  "geometry": {"coordinates":[27.34395,49.385677],"type":"Point"}
}