{
  "type": "Feature",
  "properties": {
    "gn:admin1_code":"23.0",
    "gn:asciiname":"Staryi Pykiv",
    "gn:country_code":"UA",
    "gn:dem":247,
    "gn:feature_class":"P",
    "gn:feature_code":"PPL",
    "gn:name":"Staryi Pykiv",
    "gn:population":0,
    "gn:timezone":"Europe/Kiev",
    "iso:country":"UA",
    "name:rus_x_historical":[
        "\u0421\u0442\u0430\u0440\u044b\u0439 \u041f\u0438\u043a\u043e\u0432"
    ],
    "name:rus_x_preferred":[
        "\u0421\u0442\u0430\u0440\u044b\u0439 \u041f\u0438\u043a\u043e\u0432"
    ],
    "name:ukr_x_historical":[
        "\u0421\u0442\u0430\u0440\u0438\u0439 \u041f\u0438\u043a\u0456\u0432"
    ],
    "name:ukr_x_preferred":[
        "\u0421\u0442\u0430\u0440\u0438\u0439 \u041f\u0438\u043a\u0456\u0432"
    ],
    "name:und_x_variant":[
        "Staryy Pykiv",
        "Stary Pykiv",
        "Staryy Pikov"
    ],
    "wof:name":"Staryi Pykiv",
    "wof:placetype":"locality"
},
  "geometry": {"coordinates":[28.27891,49.56102],"type":"Point"}
}