{
  "type": "Feature",
  "properties": {
    "iso:country":"UA",
    "name:che_x_preferred":[
        "\u0412\u043e\u0437\u0434\u0432\u0438\u0436\u0435\u0432\u043a\u0430"
    ],
    "name:deu_x_preferred":[
        "Wosdwyschiwka"
    ],
    "name:eng_x_preferred":[
        "Vozdvyzhivka"
    ],
    "name:fin_x_preferred":[
        "V\u043ezdvy\u017e\u0456vk\u0430"
    ],
    "name:jpn_x_preferred":[
        "\u30f4\u30a9\u30ba\u30c9\u30f4\u30a3\u30b8\u30a6\u30ab"
    ],
    "name:lav_x_preferred":[
        "Vozdvi\u017eivka"
    ],
    "name:nan_x_preferred":[
        "Vozdvyzhivka"
    ],
    "name:nno_x_preferred":[
        "Vozdvyzjivka"
    ],
    "name:nob_x_preferred":[
        "Vozdvyzjivka"
    ],
    "name:ron_x_preferred":[
        "Vozdv\u00eejivka"
    ],
    "name:rus_x_preferred":[
        "\u0412\u043e\u0437\u0434\u0432\u0438\u0436\u0435\u0432\u043a\u0430"
    ],
    "name:ukr_x_preferred":[
        "\u0412\u043e\u0437\u0434\u0432\u0438\u0436\u0456\u0432\u043a\u0430"
    ],
    "name:und_x_variant":[
        "Vozdvizhenka"
    ],
    "name:zho_x_preferred":[
        "\u6c83\u8332\u5fb7\u7dad\u65e5\u592b\u5361"
    ],
    "qs:a0":"\u0423\u043a\u0440\u0430\u0457\u043d\u0430",
    "qs:a1":"*\u0417\u0430\u043f\u043e\u0440\u0456\u0437\u044c\u043a\u0430",
    "qs:a1_alt":"Zaporiz'ka",
    "qs:a1r":"0",
    "qs:a2":"\u0413\u0443\u043b\u044f\u0439\u043f\u0456\u043b\u044c\u0441\u044c\u043a\u0438\u0439",
    "qs:a2_alt":"Huliaipil's'kyi",
    "qs:adm0":"\u0423\u043a\u0440\u0430\u0457\u043d\u0430",
    "qs:la_lc":"*",
    "qs:level":"locality",
    "qs:loc":"\u0412\u043e\u0437\u0434\u0432\u0438\u0436\u0456\u0432\u043a\u0430",
    "qs:loc_alt":"Vozdvyzhivka",
    "qs:pop":0,
    "qs:type":"buffered point",
    "wof:name":"\u0412\u043e\u0437\u0434\u0432\u0438\u0436\u0456\u0432\u043a\u0430",
    "wof:placetype":"locality"
},
  "geometry": {"coordinates":[36.07642,47.744695],"type":"Point"}
}