{
  "type": "Feature",
  "properties": {
    "gn:admin1_code":"11.0",
    "gn:admin2_code":"693803",
    "gn:admin3_code":"11152612.0",
    "gn:asciiname":"Sukhorechye",
    "gn:country_code":"UA",
    "gn:dem":111,
    "gn:elevation":"112.0",
    "gn:feature_class":"P",
    "gn:feature_code":"PPL",
    "gn:name":"Sukhorechye",
    "gn:population":58,
    "gn:timezone":"Europe/Simferopol",
    "iso:country":"UA",
    "name:eng_x_preferred":[
        "Sukhorechye"
    ],
    "name:rus_x_historical":[
        "\u0414\u0436\u0430\u0433\u0430\u0301-\u041c\u0430\u043c\u044b\u0301\u0448"
    ],
    "name:rus_x_preferred":[
        "\u0421\u0443\u0445\u043e\u0440\u0435\u0447\u044c\u0435"
    ],
    "name:rus_x_variant":[
        "\u0414\u0436\u0430\u0433\u0430\u0301-\u041c\u0430\u043c\u044b\u0301\u0448"
    ],
    "name:ukr_x_preferred":[
        "\u0421\u0443\u0445\u043e\u0440\u0456\u0447\u0447\u044f"
    ],
    "wof:name":"Sukhorechye",
    "wof:placetype":"locality",
    "wof:population":58
},
  "geometry": {"coordinates":[34.08497,45.17822],"type":"Point"}
}