{
  "type": "Feature",
  "properties": {
    "gn:admin1_code":"17.0",
    "gn:asciiname":"Ignatovo",
    "gn:cc2":"UA",
    "gn:country_code":"UA",
    "gn:dem":0,
    "gn:feature_class":"P",
    "gn:feature_code":"PPL",
    "gn:name":"Ignatovo",
    "gn:population":0,
    "gn:timezone":"Europe/Kiev",
    "iso:country":"UA",
    "name:und_x_variant":[
        "Gnatovo",
        "Ignatovka",
        "Ignatovo"
    ],
    "wof:name":"Ignatovo",
    "wof:placetype":"locality"
},
  "geometry": {"coordinates":[30.48333,46.83333],"type":"Point"}
}