{
  "type": "Feature",
  "properties": {
    "iso:country":"UA",
    "name:ukr_x_preferred":[
        "Yablunivka"
    ],
    "name:ukr_x_variant":[
        "\u042f\u0431\u043b\u0443\u043d\u0456\u0432\u043a\u0430"
    ],
    "name:und_x_variant":[
        "Yablonovka"
    ],
    "qs:a0":"\u0423\u043a\u0440\u0430\u0457\u043d\u0430",
    "qs:a1":"*\u0417\u0430\u043a\u0430\u0440\u043f\u0430\u0442\u0441\u044c\u043a\u0430",
    "qs:a1_alt":"Zakarpats'ka",
    "qs:a1r":"0",
    "qs:a2":"\u0425\u0443\u0441\u0442\u0441\u044c\u043a\u0438\u0439",
    "qs:a2_alt":"Khusts'kyi",
    "qs:adm0":"\u0423\u043a\u0440\u0430\u0457\u043d\u0430",
    "qs:la_lc":"*",
    "qs:level":"locality",
    "qs:loc":"\u042f\u0431\u043b\u0443\u043d\u0456\u0432\u043a\u0430",
    "qs:loc_alt":"Yablunivka",
    "qs:pop":0,
    "qs:type":"buffered point",
    "wd:wordcount":49,
    "wof:name":"\u042f\u0431\u043b\u0443\u043d\u0456\u0432\u043a\u0430",
    "wof:placetype":"locality"
},
  "geometry": {"coordinates":[23.510175,48.012035],"type":"Point"}
}