{
  "type": "Feature",
  "properties": {
    "gn:admin1_code":"06",
    "gn:asciiname":"Zarichchya",
    "gn:country_code":"UA",
    "gn:dem":334,
    "gn:feature_class":"P",
    "gn:feature_code":"PPL",
    "gn:name":"Zarichchya",
    "gn:population":0,
    "gn:timezone":"Europe/Kiev",
    "iso:country":"UA",
    "name:rus_x_preferred":[
        "Zarech\u2019ye"
    ],
    "name:rus_x_variant":[
        "\u0417\u0430\u0440\u0435\u0447\u044c\u0435"
    ],
    "name:ukr_x_preferred":[
        "Zarichchya"
    ],
    "name:ukr_x_variant":[
        "\u0417\u0430\u0440\u0456\u0447\u0447\u044f"
    ],
    "wof:name":"Zarichchya",
    "wof:placetype":"locality"
},
  "geometry": {"coordinates":[23.95727,49.09726],"type":"Point"}
}