{
  "type": "Feature",
  "properties": {
    "gn:admin1_code":"13.0",
    "gn:asciiname":"Nizhylovychi",
    "gn:country_code":"UA",
    "gn:dem":179,
    "gn:feature_class":"P",
    "gn:feature_code":"PPL",
    "gn:name":"Nizhylovychi",
    "gn:population":0,
    "gn:timezone":"Europe/Kiev",
    "iso:country":"UA",
    "name:ukr_x_preferred":[
        "Nizhylovychi"
    ],
    "name:ukr_x_variant":[
        "\u041d\u0456\u0436\u0438\u043b\u043e\u0432\u0438\u0447\u0456"
    ],
    "name:und_x_variant":[
        "Nizhilovichi",
        "Nezhilovichi"
    ],
    "wof:name":"Nizhylovychi",
    "wof:placetype":"locality"
},
  "geometry": {"coordinates":[29.63396,50.48807],"type":"Point"}
}