{
  "type": "Feature",
  "properties": {
    "gn:population":10683,
    "iso:country":"UA",
    "name:rus_x_preferred":[
        "\u0412\u0435\u0441\u0435\u043b\u0435"
    ],
    "name:ukr_x_preferred":[
        "\u0412\u0435\u0441\u0435\u043b\u0435"
    ],
    "name:und_x_variant":[
        "Ves\u00ebloye"
    ],
    "qs:a0":"\u0423\u043a\u0440\u0430\u0457\u043d\u0430",
    "qs:a1":"*\u0417\u0430\u043f\u043e\u0440\u0456\u0437\u044c\u043a\u0430",
    "qs:a1_alt":"Zaporiz'ka",
    "qs:a1r":"0",
    "qs:a2":"\u0412\u0435\u0441\u0435\u043b\u0456\u0432\u0441\u044c\u043a\u0438\u0439",
    "qs:a2_alt":"Veselivs'kyi",
    "qs:adm0":"\u0423\u043a\u0440\u0430\u0457\u043d\u0430",
    "qs:la_lc":"*",
    "qs:level":"locality",
    "qs:loc":"\u0412\u0435\u0441\u0435\u043b\u0435",
    "qs:loc_alt":"Vesele",
    "qs:pop":0,
    "qs:type":"buffered point",
    "wof:name":"\u0412\u0435\u0441\u0435\u043b\u0435",
    "wof:placetype":"locality",
    "wof:population":10683
},
  "geometry": {"coordinates":[34.889157,47.01293],"type":"Point"}
}