{
  "type": "Feature",
  "properties": {
    "gn:admin1_code":"15.0",
    "gn:asciiname":"Sykhiv",
    "gn:country_code":"UA",
    "gn:dem":351,
    "gn:feature_class":"P",
    "gn:feature_code":"PPL",
    "gn:name":"Sykhiv",
    "gn:population":0,
    "gn:timezone":"Europe/Kiev",
    "iso:country":"UA",
    "name:rus_x_preferred":[
        "\u0421\u0438\u0445\u043e\u0432"
    ],
    "name:ukr_x_preferred":[
        "\u0421\u0438\u0445\u0456\u0432"
    ],
    "name:ukr_x_variant":[
        "Sykhiv"
    ],
    "name:und_x_variant":[
        "Sikhuv",
        "Sich\u00f3w",
        "Sikhov"
    ],
    "wof:name":"Sykhiv",
    "wof:placetype":"locality"
},
  "geometry": {"coordinates":[24.06284,49.79427],"type":"Point"}
}