{
  "type": "Feature",
  "properties": {
    "gn:admin1_code":"5.0",
    "gn:asciiname":"Pryshyb",
    "gn:country_code":"UA",
    "gn:dem":86,
    "gn:feature_class":"P",
    "gn:feature_code":"PPL",
    "gn:name":"Pryshyb",
    "gn:population":0,
    "gn:timezone":"Europe/Kiev",
    "iso:country":"UA",
    "name:ron_x_preferred":[
        "Pr\u00ee\u0219\u00eeb"
    ],
    "name:rus_x_preferred":[
        "\u041f\u0440\u0438\u0448\u0438\u0431"
    ],
    "name:ukr_x_preferred":[
        "Pryshyb"
    ],
    "name:ukr_x_variant":[
        "\u041f\u0440\u0438\u0448\u0438\u0431"
    ],
    "name:und_x_variant":[
        "Prishib"
    ],
    "name:zho_x_preferred":[
        "\u666e\u91cc\u5e0c\u5e03"
    ],
    "wof:name":"Pryshyb",
    "wof:placetype":"locality"
},
  "geometry": {"coordinates":[37.64809,49.02301],"type":"Point"}
}