{
  "type": "Feature",
  "properties": {
    "gn:admin1_code":"20.0",
    "gn:admin2_code":"712927",
    "gn:admin3_code":"11153385.0",
    "gn:asciiname":"Oboronnoye",
    "gn:country_code":"UA",
    "gn:dem":204,
    "gn:feature_class":"P",
    "gn:feature_code":"PPL",
    "gn:name":"Oboronnoye",
    "gn:population":107,
    "gn:timezone":"Europe/Simferopol",
    "iso:country":"UA",
    "name:eng_x_historical":[
        "Kamara"
    ],
    "name:eng_x_preferred":[
        "Oboronnoye"
    ],
    "name:eng_x_variant":[
        "Kamara"
    ],
    "name:rus_x_historical":[
        "\u041a\u0430\u043c\u0430\u0440\u0430"
    ],
    "name:rus_x_preferred":[
        "\u041e\u0431\u043e\u0440\u043e\u043d\u043d\u043e\u0435"
    ],
    "name:rus_x_variant":[
        "\u041a\u0430\u043c\u0430\u0440\u0430"
    ],
    "name:ukr_x_preferred":[
        "\u041e\u0431\u043e\u0440\u043e\u043d\u043d\u0435"
    ],
    "wof:name":"Oboronnoye",
    "wof:placetype":"locality",
    "wof:population":107
},
  "geometry": {"coordinates":[33.6539,44.5173],"type":"Point"}
}