{
  "type": "Feature",
  "properties": {
    "gn:admin1_code":"7.0",
    "gn:asciiname":"Borove",
    "gn:country_code":"UA",
    "gn:dem":131,
    "gn:feature_class":"P",
    "gn:feature_code":"PPL",
    "gn:name":"Borove",
    "gn:population":0,
    "gn:timezone":"Europe/Kiev",
    "iso:country":"UA",
    "name:ukr_x_preferred":[
        "Borove"
    ],
    "name:ukr_x_variant":[
        "\u0411\u043e\u0440\u043e\u0432\u0435"
    ],
    "wof:name":"Borove",
    "wof:placetype":"locality"
},
  "geometry": {"coordinates":[36.35358,49.90225],"type":"Point"}
}