{
  "type": "Feature",
  "properties": {
    "gn:admin1_code":"7.0",
    "gn:asciiname":"Rostyka",
    "gn:country_code":"UA",
    "gn:dem":159,
    "gn:feature_class":"P",
    "gn:feature_code":"PPL",
    "gn:name":"Rostyka",
    "gn:population":0,
    "gn:timezone":"Europe/Kiev",
    "iso:country":"UA",
    "name:rus_x_preferred":[
        "\u0420\u043e\u0441\u0442\u044b\u043a\u0430"
    ],
    "name:ukr_x_preferred":[
        "Rostanya"
    ],
    "wof:name":"Rostyka",
    "wof:placetype":"locality"
},
  "geometry": {"coordinates":[36.08333,49.51667],"type":"Point"}
}