{
  "type": "Feature",
  "properties": {
    "gn:admin1_code":"11.0",
    "gn:admin2_code":"704383",
    "gn:admin3_code":"11152909.0",
    "gn:asciiname":"Nakhimovo",
    "gn:country_code":"UA",
    "gn:dem":26,
    "gn:elevation":"25.0",
    "gn:feature_class":"P",
    "gn:feature_code":"PPL",
    "gn:name":"Nakhimovo",
    "gn:population":90,
    "gn:timezone":"Europe/Simferopol",
    "iso:country":"UA",
    "name:eng_x_preferred":[
        "Nakhimovo"
    ],
    "name:rus_x_historical":[
        "\u041c\u0435\u0448\u0435\u0301\u043d\u044c"
    ],
    "name:rus_x_preferred":[
        "\u041d\u0430\u0445\u0438\u043c\u043e\u0432\u043e"
    ],
    "name:rus_x_variant":[
        "\u041c\u0435\u0448\u0435\u0301\u043d\u044c"
    ],
    "name:ukr_x_preferred":[
        "\u041d\u0430\u0445\u0456\u043c\u043e\u0432\u0435"
    ],
    "wof:name":"Nakhimovo",
    "wof:placetype":"locality",
    "wof:population":90
},
  "geometry": {"coordinates":[34.50163,45.52695],"type":"Point"}
}