{
  "type": "Feature",
  "properties": {
    "iso:country":"UA",
    "name:eng_x_preferred":[
        "Tur'ya"
    ],
    "name:rus_x_preferred":[
        "\u0422\u0443\u0440\u044c\u044f"
    ],
    "name:ukr_x_preferred":[
        "Tur\u201dya"
    ],
    "name:ukr_x_variant":[
        "\u0422\u0443\u0440\u2019\u044f"
    ],
    "name:unk_x_variant":[
        "Tur\u2019ya"
    ],
    "qs:a0":"\u0423\u043a\u0440\u0430\u0457\u043d\u0430",
    "qs:a1":"*\u0427\u0435\u0440\u043d\u0456\u0433\u0456\u0432\u0441\u044c\u043a\u0430",
    "qs:a1_alt":"Chernihivs'ka",
    "qs:a1r":"0",
    "qs:a2":"\u0429\u043e\u0440\u0441\u044c\u043a\u0438\u0439",
    "qs:a2_alt":"Schors'kyi",
    "qs:adm0":"\u0423\u043a\u0440\u0430\u0457\u043d\u0430",
    "qs:la_lc":"*",
    "qs:level":"locality",
    "qs:loc":"\u0422\u0443\u0440'\u044f",
    "qs:loc_alt":"Turia",
    "qs:pop":0,
    "qs:type":"buffered point",
    "wd:wordcount":1042,
    "wof:name":"\u0422\u0443\u0440'\u044f",
    "wof:placetype":"locality"
},
  "geometry": {"coordinates":[32.005629,51.905391],"type":"Point"}
}