{
  "type": "Feature",
  "properties": {
    "gn:admin1_code":"21.0",
    "gn:asciiname":"Panasivka",
    "gn:country_code":"UA",
    "gn:dem":127,
    "gn:feature_class":"P",
    "gn:feature_code":"PPL",
    "gn:name":"Panasivka",
    "gn:population":0,
    "gn:timezone":"Europe/Kiev",
    "iso:country":"UA",
    "name:eng_x_preferred":[
        "Afanas'yevka"
    ],
    "name:rus_x_preferred":[
        "\u041f\u0430\u043d\u0430\u0441\u043e\u0432\u043a\u0430"
    ],
    "name:ukr_x_preferred":[
        "Panasivka"
    ],
    "name:ukr_x_variant":[
        "\u041f\u0430\u043d\u0430\u0441\u0456\u0432\u043a\u0430"
    ],
    "name:und_x_variant":[
        "Apanasovka",
        "Aponasovka",
        "Afanas\u2019yevka",
        "Panasovka"
    ],
    "wof:name":"Panasivka",
    "wof:placetype":"locality"
},
  "geometry": {"coordinates":[33.80529,50.61819000000001],"type":"Point"}
}