{
  "type": "Feature",
  "properties": {
    "gn:admin1_code":"2.0",
    "gn:asciiname":"Bil'shovyk",
    "gn:country_code":"UA",
    "gn:dem":126,
    "gn:feature_class":"P",
    "gn:feature_code":"PPL",
    "gn:name":"Bil\u2019shovyk",
    "gn:population":0,
    "gn:timezone":"Europe/Kiev",
    "iso:country":"UA",
    "name:rus_x_preferred":[
        "Bol\u2019shovik"
    ],
    "name:ukr_x_preferred":[
        "Bil\u2019shovyk"
    ],
    "name:ukr_x_variant":[
        "\u0411\u0456\u043b\u044c\u0448\u043e\u0432\u0438\u043a"
    ],
    "wof:name":"Bil'shovyk",
    "wof:placetype":"locality"
},
  "geometry": {"coordinates":[32.50247,51.28058],"type":"Point"}
}