{
  "type": "Feature",
  "properties": {
    "gn:country":"UA",
    "gn:fcode":"PPL",
    "gn:population":1205,
    "iso:country":"UA",
    "name:rus_x_preferred":[
        "\u0412\u0435\u0440\u0445\u043d\u0438\u0439 \u042f\u0441\u0435\u043d\u043e\u0432"
    ],
    "name:und_x_variant":[
        "Jasienow"
    ],
    "qs_pg:aaroncc":"UA",
    "qs_pg:gn_country":"UA",
    "qs_pg:gn_fcode":"PPL",
    "qs_pg:gn_pop":1205,
    "qs_pg:name":"Verkhniy Yasenov",
    "qs_pg:photos_9r":0,
    "qs_pg:photos_sr":0,
    "qs_pg:pop_sr":3,
    "qs_pg:qs_pg_placetype":"locality",
    "wof:name":"Verkhniy Yasenov",
    "wof:placetype":"locality",
    "wof:population":1205
},
  "geometry": {"coordinates":[24.94532,48.16156],"type":"Point"}
}