{
  "type": "Feature",
  "properties": {
    "gn:admin1_code":"9.0",
    "gn:asciiname":"Vorobeyevka",
    "gn:country_code":"UA",
    "gn:dem":288,
    "gn:feature_class":"P",
    "gn:feature_code":"PPL",
    "gn:name":"Vorobeyevka",
    "gn:population":0,
    "gn:timezone":"Europe/Kiev",
    "iso:country":"UA",
    "wof:name":"Vorobeyevka",
    "wof:placetype":"locality"
},
  "geometry": {"coordinates":[26.82542,48.84091],"type":"Point"}
}