{
  "type": "Feature",
  "properties": {
    "gn:admin1_code":"18.0",
    "gn:asciiname":"Strutynivka",
    "gn:country_code":"UA",
    "gn:dem":81,
    "gn:feature_class":"P",
    "gn:feature_code":"PPL",
    "gn:name":"Strutynivka",
    "gn:population":0,
    "gn:timezone":"Europe/Kiev",
    "iso:country":"UA",
    "name:ukr_x_preferred":[
        "Strutynivka"
    ],
    "name:ukr_x_variant":[
        "\u0421\u0442\u0440\u0443\u0442\u0438\u043d\u0456\u0432\u043a\u0430"
    ],
    "wof:name":"Strutynivka",
    "wof:placetype":"locality"
},
  "geometry": {"coordinates":[32.86702,49.50666],"type":"Point"}
}