{
  "type": "Feature",
  "properties": {
    "gn:admin1_code":"19.0",
    "gn:asciiname":"Mochulyanka",
    "gn:country_code":"UA",
    "gn:dem":200,
    "gn:feature_class":"P",
    "gn:feature_code":"PPL",
    "gn:name":"Mochulyanka",
    "gn:population":0,
    "gn:timezone":"Europe/Kiev",
    "iso:country":"UA",
    "name:ukr_x_preferred":[
        "Mochulyanka"
    ],
    "name:ukr_x_variant":[
        "\u041c\u043e\u0447\u0443\u043b\u044f\u043d\u043a\u0430"
    ],
    "wof:name":"Mochulyanka",
    "wof:placetype":"locality"
},
  "geometry": {"coordinates":[27.11138,50.88947],"type":"Point"}
}