{
  "type": "Feature",
  "properties": {
    "gn:admin1_code":"23.0",
    "gn:asciiname":"Ratush",
    "gn:country_code":"UA",
    "gn:dem":193,
    "gn:feature_class":"P",
    "gn:feature_code":"PPL",
    "gn:name":"Ratush",
    "gn:population":0,
    "gn:timezone":"Europe/Kiev",
    "iso:country":"UA",
    "name:und_x_variant":[
        "Ratusha",
        "Ratush",
        "\u0420\u0430\u0442\u0443\u0448"
    ],
    "wof:name":"Ratush",
    "wof:placetype":"locality"
},
  "geometry": {"coordinates":[28.45653,48.34818],"type":"Point"}
}