{
  "type": "Feature",
  "properties": {
    "gn:admin1_code":"17.0",
    "gn:asciiname":"Onylove",
    "gn:country_code":"UA",
    "gn:dem":118,
    "gn:feature_class":"P",
    "gn:feature_code":"PPL",
    "gn:name":"Onylove",
    "gn:population":0,
    "gn:timezone":"Europe/Kiev",
    "iso:country":"UA",
    "name:ukr_x_preferred":[
        "Onilove"
    ],
    "name:ukr_x_variant":[
        "Onylove",
        "\u041e\u043d\u0438\u043b\u043e\u0432\u0435"
    ],
    "name:und_x_variant":[
        "Onilovo"
    ],
    "wof:name":"Onylove",
    "wof:placetype":"locality"
},
  "geometry": {"coordinates":[29.90197,47.44727],"type":"Point"}
}