{
  "type": "Feature",
  "properties": {
    "gn:admin1_code":"25.0",
    "gn:asciiname":"Mali Heyivtsi",
    "gn:country_code":"UA",
    "gn:dem":103,
    "gn:feature_class":"P",
    "gn:feature_code":"PPL",
    "gn:name":"Mali Heyivtsi",
    "gn:population":0,
    "gn:timezone":"Europe/Uzhgorod",
    "iso:country":"UA",
    "name:ukr_x_preferred":[
        "Mali Heyivtsi"
    ],
    "name:ukr_x_variant":[
        "\u041c\u0430\u043b\u0456 \u0413\u0435\u0457\u0432\u0446\u0456"
    ],
    "name:und_x_variant":[
        "Maloye Geyovtse",
        "Malyye Geyevtsy"
    ],
    "wof:name":"Mali Heyivtsi",
    "wof:placetype":"locality"
},
  "geometry": {"coordinates":[22.30097,48.49702],"type":"Point"}
}