{
  "type": "Feature",
  "properties": {
    "gn:admin1_code":"26.0",
    "gn:asciiname":"Vodne",
    "gn:country_code":"UA",
    "gn:dem":80,
    "gn:feature_class":"P",
    "gn:feature_code":"PPL",
    "gn:name":"Vodne",
    "gn:population":0,
    "gn:timezone":"Europe/Zaporozhye",
    "iso:country":"UA",
    "name:ukr_x_preferred":[
        "Vodne"
    ],
    "name:ukr_x_variant":[
        "\u0412\u043e\u0434\u043d\u0435"
    ],
    "name:und_x_variant":[
        "Vasserau",
        "Vodnoye"
    ],
    "wof:name":"Vodne",
    "wof:placetype":"locality"
},
  "geometry": {"coordinates":[35.43012,47.2028],"type":"Point"}
}