{
  "type": "Feature",
  "properties": {
    "gn:admin1_code":"3.0",
    "gn:asciiname":"Nizhniye Stanovtsy",
    "gn:country_code":"UA",
    "gn:dem":237,
    "gn:feature_class":"P",
    "gn:feature_code":"PPL",
    "gn:name":"Nizhniye Stanovtsy",
    "gn:population":0,
    "gn:timezone":"Europe/Kiev",
    "iso:country":"UA",
    "name:und_x_variant":[
        "Untershtaneshti",
        "Nizhniye Stanovtsy"
    ],
    "wof:name":"Nizhniye Stanovtsy",
    "wof:placetype":"locality"
},
  "geometry": {"coordinates":[25.56948,48.32055],"type":"Point"}
}