{
  "type": "Feature",
  "properties": {
    "gn:admin1_code":"24.0",
    "gn:asciiname":"Okhlopiv",
    "gn:country_code":"UA",
    "gn:dem":217,
    "gn:feature_class":"P",
    "gn:feature_code":"PPL",
    "gn:name":"Okhlopiv",
    "gn:population":0,
    "gn:timezone":"Europe/Kiev",
    "iso:country":"UA",
    "name:ukr_x_preferred":[
        "Okhlopiv"
    ],
    "name:ukr_x_variant":[
        "\u041e\u0445\u043b\u043e\u043f\u0456\u0432"
    ],
    "name:und_x_variant":[
        "Och\u0141op\u00f3w",
        "Okhlopuv",
        "Okhlopov"
    ],
    "wof:name":"Okhlopiv",
    "wof:placetype":"locality"
},
  "geometry": {"coordinates":[24.64391,50.45913],"type":"Point"}
}