{
  "type": "Feature",
  "properties": {
    "iso:country":"UA",
    "name:bul_x_preferred":[
        "\u041f\u0440\u044f\u043c\u043e\u0431\u0430\u043b\u043a\u0430"
    ],
    "name:deu_x_preferred":[
        "Prjamobalka"
    ],
    "name:eng_x_preferred":[
        "Priamobalka"
    ],
    "name:lav_x_preferred":[
        "Prjamobalka"
    ],
    "name:ron_x_preferred":[
        "Preamobalka"
    ],
    "name:rus_x_preferred":[
        "\u041f\u0440\u044f\u043c\u043e\u0431\u0430\u043b\u043a\u0430"
    ],
    "name:spa_x_preferred":[
        "Pryamobalka"
    ],
    "name:ukr_x_preferred":[
        "\u041f\u0440\u044f\u043c\u043e\u0431\u0430\u043b\u043a\u0430"
    ],
    "name:und_x_variant":[
        "Denevits"
    ],
    "name:zho_x_preferred":[
        "\u666e\u91cc\u4e9e\u83ab\u5df4\u723e\u5361"
    ],
    "qs:a0":"\u0423\u043a\u0440\u0430\u0457\u043d\u0430",
    "qs:a1":"*\u041e\u0434\u0435\u0441\u044c\u043a\u0430",
    "qs:a1_alt":"Odes'ka",
    "qs:a1r":"0",
    "qs:a2":"\u0410\u0440\u0446\u0438\u0437\u044c\u043a\u0438\u0439",
    "qs:a2_alt":"Artsyz'kyi",
    "qs:adm0":"\u0423\u043a\u0440\u0430\u0457\u043d\u0430",
    "qs:la_lc":"*",
    "qs:level":"locality",
    "qs:loc":"\u041f\u0440\u044f\u043c\u043e\u0431\u0430\u043b\u043a\u0430",
    "qs:loc_alt":"Priamobalka",
    "qs:pop":0,
    "qs:type":"buffered point",
    "wof:name":"\u041f\u0440\u044f\u043c\u043e\u0431\u0430\u043b\u043a\u0430",
    "wof:placetype":"locality"
},
  "geometry": {"coordinates":[29.299668,45.889488],"type":"Point"}
}