{
  "type": "Feature",
  "properties": {
    "iso:country":"UA",
    "name:ukr_x_preferred":[
        "\u041d\u043e\u0432\u0430 \u0414\u043c\u0438\u0442\u0440\u0456\u0432\u043a\u0430"
    ],
    "name:und_x_variant":[
        "Nova Dmytrivka"
    ],
    "qs:a0":"\u0423\u043a\u0440\u0430\u0457\u043d\u0430",
    "qs:a1":"*\u0427\u0435\u0440\u043a\u0430\u0441\u044c\u043a\u0430",
    "qs:a1_alt":"Cherkas'ka",
    "qs:a1r":"0",
    "qs:a2":"\u0417\u043e\u043b\u043e\u0442\u043e\u043d\u0456\u0441\u044c\u043a\u0438\u0439",
    "qs:a2_alt":"Zolotonis'kyi",
    "qs:adm0":"\u0423\u043a\u0440\u0430\u0457\u043d\u0430",
    "qs:la_lc":"*",
    "qs:level":"locality",
    "qs:loc":"\u041d\u043e\u0432\u0430 \u0414\u043c\u0438\u0442\u0440\u0456\u0432\u043a\u0430",
    "qs:loc_alt":"Nova Dmytrivka",
    "qs:pop":0,
    "qs:type":"buffered point",
    "wof:name":"\u041d\u043e\u0432\u0430 \u0414\u043c\u0438\u0442\u0440\u0456\u0432\u043a\u0430",
    "wof:placetype":"locality"
},
  "geometry": {"coordinates":[32.005521,49.686404],"type":"Point"}
}