{
  "type": "Feature",
  "properties": {
    "gn:admin1_code":"27.0",
    "gn:asciiname":"Maydanivka",
    "gn:country_code":"UA",
    "gn:dem":180,
    "gn:feature_class":"P",
    "gn:feature_code":"PPL",
    "gn:name":"Maydanivka",
    "gn:population":0,
    "gn:timezone":"Europe/Kiev",
    "iso:country":"UA",
    "name:ukr_x_preferred":[
        "Maydanivka"
    ],
    "name:ukr_x_variant":[
        "\u041c\u0430\u0439\u0434\u0430\u043d\u0456\u0432\u043a\u0430"
    ],
    "name:und_x_variant":[
        "Maydanovka"
    ],
    "wof:name":"Maydanivka",
    "wof:placetype":"locality"
},
  "geometry": {"coordinates":[28.8768,50.90407],"type":"Point"}
}