{
  "type": "Feature",
  "properties": {
    "iso:country":"UA",
    "qs:a0":"\u0423\u043a\u0440\u0430\u0457\u043d\u0430",
    "qs:a1":"*\u0425\u0435\u0440\u0441\u043e\u043d\u0441\u044c\u043a\u0430",
    "qs:a1_alt":"Khersons'ka",
    "qs:a1r":"0",
    "qs:a2":"\u0413\u043e\u0440\u043d\u043e\u0441\u0442\u0430\u0457\u0432\u0441\u044c\u043a\u0438\u0439",
    "qs:a2_alt":"Hornostaivs'kyi",
    "qs:adm0":"\u0423\u043a\u0440\u0430\u0457\u043d\u0430",
    "qs:la_lc":"*",
    "qs:level":"locality",
    "qs:loc":"\u041a\u043e\u0441\u0442\u044f\u043d\u0442\u0438\u043d\u0456\u0432\u043a\u0430",
    "qs:loc_alt":"Kostiantynivka",
    "qs:pop":0,
    "qs:type":"buffered point",
    "wd:wordcount":364,
    "wof:name":"\u041a\u043e\u0441\u0442\u044f\u043d\u0442\u0438\u043d\u0456\u0432\u043a\u0430",
    "wof:placetype":"locality"
},
  "geometry": {"coordinates":[33.862809,46.82576],"type":"Point"}
}