{
  "type": "Feature",
  "properties": {
    "iso:country":"UA",
    "name:ukr_x_preferred":[
        "Rudnya-Ivanivs\u2019ka"
    ],
    "name:ukr_x_variant":[
        "\u0420\u0443\u0434\u043d\u044f-\u0406\u0432\u0430\u043d\u0456\u0432\u0441\u044c\u043a\u0430"
    ],
    "name:und_x_variant":[
        "Yancha Rudnya"
    ],
    "qs:a0":"\u0423\u043a\u0440\u0430\u0457\u043d\u0430",
    "qs:a1":"*\u0416\u0438\u0442\u043e\u043c\u0438\u0440\u0441\u044c\u043a\u0430",
    "qs:a1_alt":"Zhytomyrs'ka",
    "qs:a1r":"0",
    "qs:a2":"\u0404\u043c\u0456\u043b\u044c\u0447\u0438\u043d\u0441\u044c\u043a\u0438\u0439",
    "qs:a2_alt":"Yemil'chyns'kyi",
    "qs:adm0":"\u0423\u043a\u0440\u0430\u0457\u043d\u0430",
    "qs:la_lc":"*",
    "qs:level":"locality",
    "qs:loc":"\u0420\u0443\u0434\u043d\u044f-\u0406\u0432\u0430\u043d\u0456\u0432\u0441\u044c\u043a\u0430",
    "qs:loc_alt":"Rudnia-Ivanivs'ka",
    "qs:pop":0,
    "qs:type":"buffered point",
    "wof:name":"\u0420\u0443\u0434\u043d\u044f-\u0406\u0432\u0430\u043d\u0456\u0432\u0441\u044c\u043a\u0430",
    "wof:placetype":"locality"
},
  "geometry": {"coordinates":[27.702773,50.981816],"type":"Point"}
}