{
  "type": "Feature",
  "properties": {
    "gn:admin1_code":"17.0",
    "gn:asciiname":"Orlivka",
    "gn:country_code":"UA",
    "gn:dem":53,
    "gn:feature_class":"P",
    "gn:feature_code":"PPL",
    "gn:name":"Orlivka",
    "gn:population":0,
    "gn:timezone":"Europe/Kiev",
    "iso:country":"UA",
    "name:bul_x_preferred":[
        "\u041a\u0430\u0440\u0442\u0430\u043b"
    ],
    "name:deu_x_preferred":[
        "Orliwka"
    ],
    "name:ron_x_preferred":[
        "Cartal"
    ],
    "name:rus_x_preferred":[
        "\u041e\u0440\u043b\u043e\u0432\u043a\u0430"
    ],
    "name:spa_x_preferred":[
        "Orlivka"
    ],
    "name:ukr_x_preferred":[
        "Selyshche Orlivka"
    ],
    "name:ukr_x_variant":[
        "Orlivka",
        "\u041e\u0440\u043b\u0456\u0432\u043a\u0430"
    ],
    "name:und_x_variant":[
        "Orlovka"
    ],
    "name:zho_x_preferred":[
        "\u5967\u723e\u5229\u592b\u5361"
    ],
    "wof:name":"Orlivka",
    "wof:placetype":"locality"
},
  "geometry": {"coordinates":[29.32708,47.45823],"type":"Point"}
}