{
  "type": "Feature",
  "properties": {
    "gn:country":"UA",
    "gn:fcode":"PPL",
    "gn:population":0,
    "iso:country":"UA",
    "name:crh_x_preferred":[
        "Hrustalne"
    ],
    "name:deu_x_preferred":[
        "Chrystalne"
    ],
    "name:eng_x_preferred":[
        "Khrustalne"
    ],
    "name:est_x_preferred":[
        "Hrustalne"
    ],
    "name:lav_x_preferred":[
        "Hrusta\u013cne"
    ],
    "name:ron_x_preferred":[
        "Hrustalne"
    ],
    "name:rus_x_preferred":[
        "\u0425\u0440\u0443\u0441\u0442\u0430\u043b\u044c\u043d\u043e\u0435"
    ],
    "name:ukr_x_preferred":[
        "Khrustal\u2019ne"
    ],
    "name:ukr_x_variant":[
        "\u0425\u0440\u0443\u0441\u0442\u0430\u043b\u044c\u043d\u0435"
    ],
    "name:und_x_variant":[
        "Khrustal\u2019nyy"
    ],
    "name:zho_x_preferred":[
        "\u8d6b\u9b6f\u65af\u5854\u5229\u6d85"
    ],
    "qs_pg:aaroncc":"UA",
    "qs_pg:gn_country":"UA",
    "qs_pg:gn_fcode":"PPL",
    "qs_pg:gn_pop":0,
    "qs_pg:name":"Khrustal'noye",
    "qs_pg:name_adm0":"Ukraine",
    "qs_pg:name_adm1":"Luhans\u00b4ka Oblast\u00b4",
    "qs_pg:photos":92,
    "qs_pg:photos_1k":19,
    "qs_pg:photos_9k":1,
    "qs_pg:photos_9r":3,
    "qs_pg:photos_all":92,
    "qs_pg:photos_sr":3,
    "qs_pg:pop_sr":0,
    "qs_pg:qs_pg_placetype":"locality",
    "qs_pg:qs_pg_placetype_gp":"Town",
    "qs_pg:woe_adm0":23424976,
    "woe:adm0_id":23424976,
    "woe:name_adm0":"Ukraine",
    "woe:name_adm1":"Luhans\u00b4ka Oblast\u00b4",
    "woe:placetype":"Town",
    "wof:name":"Khrustal'noye",
    "wof:placetype":"locality"
},
  "geometry": {"coordinates":[38.85151,48.14782],"type":"Point"}
}