{
  "type": "Feature",
  "properties": {
    "gn:admin1_code":"2.0",
    "gn:asciiname":"Osnova",
    "gn:country_code":"UA",
    "gn:dem":158,
    "gn:feature_class":"P",
    "gn:feature_code":"PPL",
    "gn:name":"Osnova",
    "gn:population":0,
    "gn:timezone":"Europe/Kiev",
    "iso:country":"UA",
    "name:ukr_x_preferred":[
        "Osnova"
    ],
    "name:ukr_x_variant":[
        "\u041e\u0441\u043d\u043e\u0432\u0430"
    ],
    "wof:name":"Osnova",
    "wof:placetype":"locality"
},
  "geometry": {"coordinates":[33.1584,50.75629],"type":"Point"}
}