{
  "type": "Feature",
  "properties": {
    "gn:admin1_code":"2.0",
    "gn:asciiname":"Chervonyy Kolodyaz'",
    "gn:country_code":"UA",
    "gn:dem":126,
    "gn:feature_class":"P",
    "gn:feature_code":"PPL",
    "gn:name":"Chervonyy Kolodyaz\u2019",
    "gn:population":0,
    "gn:timezone":"Europe/Kiev",
    "iso:country":"UA",
    "name:ukr_x_preferred":[
        "Chervonyy Kolodyaz\u2019"
    ],
    "name:ukr_x_variant":[
        "\u0427\u0435\u0440\u0432\u043e\u043d\u0438\u0439 \u041a\u043e\u043b\u043e\u0434\u044f\u0437\u044c"
    ],
    "wof:name":"Chervonyy Kolodyaz'",
    "wof:placetype":"locality"
},
  "geometry": {"coordinates":[32.0449,50.82911],"type":"Point"}
}