{
  "type": "Feature",
  "properties": {
    "gn:admin1_code":"9.0",
    "gn:asciiname":"Ovsyaniki",
    "gn:country_code":"UA",
    "gn:dem":348,
    "gn:feature_class":"P",
    "gn:feature_code":"PPL",
    "gn:name":"Ovsyaniki",
    "gn:population":0,
    "gn:timezone":"Europe/Kiev",
    "iso:country":"UA",
    "wof:name":"Ovsyaniki",
    "wof:placetype":"locality"
},
  "geometry": {"coordinates":[27.88037000000001,49.20242],"type":"Point"}
}