{
  "type": "Feature",
  "properties": {
    "gn:admin1_code":"26.0",
    "gn:asciiname":"Rivne",
    "gn:country_code":"UA",
    "gn:dem":83,
    "gn:feature_class":"P",
    "gn:feature_code":"PPL",
    "gn:name":"Rivne",
    "gn:population":0,
    "gn:timezone":"Europe/Zaporozhye",
    "iso:country":"UA",
    "name:ukr_x_preferred":[
        "Rivne"
    ],
    "name:ukr_x_variant":[
        "\u0420\u0456\u0432\u043d\u0435"
    ],
    "name:und_x_variant":[
        "Rovnoye"
    ],
    "wof:name":"Rivne",
    "wof:placetype":"locality"
},
  "geometry": {"coordinates":[35.47859000000001,47.2098],"type":"Point"}
}