{
  "type": "Feature",
  "properties": {
    "gn:admin1_code":"10.0",
    "gn:asciiname":"Ketrisanovka",
    "gn:country_code":"UA",
    "gn:dem":122,
    "gn:feature_class":"P",
    "gn:feature_code":"PPL",
    "gn:name":"Ketrisanovka",
    "gn:population":0,
    "gn:timezone":"Europe/Kiev",
    "iso:country":"UA",
    "name:und_x_variant":[
        "Kitrisanovka",
        "Ketrisanovka"
    ],
    "wof:name":"Ketrisanovka",
    "wof:placetype":"locality"
},
  "geometry": {"coordinates":[32.1706,47.91263],"type":"Point"}
}