{
  "type": "Feature",
  "properties": {
    "gn:admin1_code":"17.0",
    "gn:asciiname":"Blahodatne",
    "gn:country_code":"UA",
    "gn:dem":28,
    "gn:feature_class":"P",
    "gn:feature_code":"PPL",
    "gn:name":"Blahodatne",
    "gn:population":0,
    "gn:timezone":"Europe/Kiev",
    "iso:country":"UA",
    "name:ara_x_preferred":[
        "\u0632\u0647\u0648\u0641\u062a\u0646\u064a\u0641\u064a"
    ],
    "name:bel_x_preferred":[
        "\u0411\u043b\u0430\u0433\u0430\u0434\u0430\u0442\u043d\u044d"
    ],
    "name:ceb_x_preferred":[
        "Zhovtneve"
    ],
    "name:crh_x_preferred":[
        "Blagodatne"
    ],
    "name:deu_x_preferred":[
        "Blahodatne"
    ],
    "name:hye_x_preferred":[
        "\u053a\u0578\u057e\u057f\u0576\u0587\u0578\u0565"
    ],
    "name:pol_x_preferred":[
        "B\u0142ahodatne"
    ],
    "name:rus_x_preferred":[
        "\u0411\u043b\u0430\u0433\u043e\u0434\u0430\u0442\u043d\u043e\u0435"
    ],
    "name:ukr_x_preferred":[
        "Blahodatne"
    ],
    "name:ukr_x_variant":[
        "\u0411\u043b\u0430\u0433\u043e\u0434\u0430\u0442\u043d\u0435"
    ],
    "name:und_x_variant":[
        "Staro-Blagodatnyy",
        "Caiabeii Micii",
        "Kaibey-Mich\u2019",
        "Blagodatnoye"
    ],
    "name:zho_x_preferred":[
        "\u82e5\u592b\u7279\u6d85\u97cb"
    ],
    "wof:name":"Blahodatne",
    "wof:placetype":"locality"
},
  "geometry": {"coordinates":[30.1752,45.98585],"type":"Point"}
}