{
  "type": "Feature",
  "properties": {
    "gn:admin1_code":"5.0",
    "gn:asciiname":"Komyshuvate",
    "gn:country_code":"UA",
    "gn:dem":91,
    "gn:feature_class":"P",
    "gn:feature_code":"PPL",
    "gn:name":"Komyshuvate",
    "gn:population":0,
    "gn:timezone":"Europe/Kiev",
    "iso:country":"UA",
    "name:eng_x_preferred":[
        "Kamyshevatoye"
    ],
    "name:rus_x_preferred":[
        "\u041a\u0430\u043c\u044b\u0448\u0435\u0432\u0430\u0442\u043e\u0435"
    ],
    "name:ukr_x_preferred":[
        "Komyshuvate"
    ],
    "name:ukr_x_variant":[
        "\u041a\u043e\u043c\u0438\u0448\u0443\u0432\u0430\u0442\u0435"
    ],
    "name:und_x_variant":[
        "Voroshilovo"
    ],
    "wof:name":"Komyshuvate",
    "wof:placetype":"locality"
},
  "geometry": {"coordinates":[37.16703,47.08561],"type":"Point"}
}