{
  "type": "Feature",
  "properties": {
    "gn:admin1_code":"15",
    "gn:asciiname":"Pobuk",
    "gn:country_code":"UA",
    "gn:dem":412,
    "gn:feature_class":"P",
    "gn:feature_code":"PPL",
    "gn:name":"Pobuk",
    "gn:population":0,
    "gn:timezone":"Europe/Kiev",
    "iso:country":"UA",
    "name:ukr_x_preferred":[
        "Pobuk"
    ],
    "name:ukr_x_variant":[
        "\u041f\u043e\u0431\u0443\u043a"
    ],
    "wof:name":"Pobuk",
    "wof:placetype":"locality"
},
  "geometry": {"coordinates":[23.61247,49.07945],"type":"Point"}
}