{
  "type": "Feature",
  "properties": {
    "iso:country":"UA",
    "name:bul_x_preferred":[
        "\u0428\u0438\u043a\u0438\u0440\u043b\u0438 \u041a\u0438\u0442\u0430\u0439"
    ],
    "name:crh_x_preferred":[
        "Suvorove"
    ],
    "name:deu_x_preferred":[
        "Suworowe"
    ],
    "name:eng_x_preferred":[
        "Suvorove"
    ],
    "name:lav_x_preferred":[
        "Suvorove"
    ],
    "name:pol_x_preferred":[
        "Suworowe"
    ],
    "name:ron_x_preferred":[
        "\u0218ichirlichitai"
    ],
    "name:rus_x_preferred":[
        "\u0421\u0443\u0432\u043e\u0440\u043e\u0432\u043e"
    ],
    "name:sah_x_preferred":[
        "\u0421\u0443\u0432\u043e\u0440\u043e\u0432\u043e"
    ],
    "name:ukr_x_preferred":[
        "Suvorove"
    ],
    "name:ukr_x_variant":[
        "\u0421\u0443\u0432\u043e\u0440\u043e\u0432\u0435"
    ],
    "name:und_x_variant":[
        "Regele Carol II"
    ],
    "name:zho_x_preferred":[
        "\u8607\u6c83\u7f85\u97cb"
    ],
    "qs:a0":"\u0423\u043a\u0440\u0430\u0457\u043d\u0430",
    "qs:a1":"*\u041e\u0434\u0435\u0441\u044c\u043a\u0430",
    "qs:a1_alt":"Odes'ka",
    "qs:a1r":"0",
    "qs:a2":"\u0406\u0437\u043c\u0430\u0457\u043b\u044c\u0441\u044c\u043a\u0438\u0439",
    "qs:a2_alt":"Izmail's'kyi",
    "qs:adm0":"\u0423\u043a\u0440\u0430\u0457\u043d\u0430",
    "qs:la_lc":"*",
    "qs:level":"locality",
    "qs:loc":"\u0421\u0443\u0432\u043e\u0440\u043e\u0432\u0435",
    "qs:loc_alt":"Suvorove",
    "qs:pop":0,
    "qs:type":"buffered point",
    "wof:name":"\u0421\u0443\u0432\u043e\u0440\u043e\u0432\u0435",
    "wof:placetype":"locality"
},
  "geometry": {"coordinates":[28.982777,45.58089],"type":"Point"}
}