{
  "type": "Feature",
  "properties": {
    "gn:admin1_code":"14.0",
    "gn:asciiname":"Karpaty",
    "gn:country_code":"UA",
    "gn:dem":166,
    "gn:feature_class":"P",
    "gn:feature_code":"PPL",
    "gn:name":"Karpaty",
    "gn:population":0,
    "gn:timezone":"Europe/Zaporozhye",
    "iso:country":"UA",
    "name:bar_x_preferred":[
        "Karpaty"
    ],
    "name:ceb_x_preferred":[
        "Karpaty"
    ],
    "name:deu_x_preferred":[
        "Karpaty"
    ],
    "name:ita_x_preferred":[
        "Karpaty"
    ],
    "name:pol_x_preferred":[
        "Karpaty"
    ],
    "name:rus_x_preferred":[
        "\u041a\u0430\u0440\u043f\u0430\u0442\u044b"
    ],
    "name:slk_x_preferred":[
        "Karpaty"
    ],
    "name:ukr_x_preferred":[
        "Karpaty"
    ],
    "name:ukr_x_variant":[
        "\u041a\u0430\u0440\u043f\u0430\u0442\u0438"
    ],
    "wof:name":"Karpaty",
    "wof:placetype":"locality"
},
  "geometry": {"coordinates":[38.85807,48.50729000000001],"type":"Point"}
}