{
  "type": "Feature",
  "properties": {
    "gn:admin1_code":"19.0",
    "gn:asciiname":"Pidbrusyn'",
    "gn:country_code":"UA",
    "gn:dem":278,
    "gn:feature_class":"P",
    "gn:feature_code":"PPL",
    "gn:name":"Pidbrusyn\u2019",
    "gn:population":0,
    "gn:timezone":"Europe/Kiev",
    "iso:country":"UA",
    "name:rus_x_preferred":[
        "Podbrusin\u2019"
    ],
    "name:ukr_x_preferred":[
        "Pidbrusyn\u2019"
    ],
    "name:ukr_x_variant":[
        "\u041f\u0456\u0434\u0431\u0440\u0443\u0441\u0438\u043d\u044c"
    ],
    "wof:name":"Pidbrusyn'",
    "wof:placetype":"locality"
},
  "geometry": {"coordinates":[25.47724,50.37972],"type":"Point"}
}