{
  "type": "Feature",
  "properties": {
    "gn:admin1_code":"18.0",
    "gn:asciiname":"Kosyaky",
    "gn:country_code":"UA",
    "gn:dem":161,
    "gn:feature_class":"P",
    "gn:feature_code":"PPL",
    "gn:name":"Kosyaky",
    "gn:population":0,
    "gn:timezone":"Europe/Kiev",
    "iso:country":"UA",
    "name:ukr_x_preferred":[
        "Kosyaky"
    ],
    "name:ukr_x_variant":[
        "\u041a\u043e\u0441\u044f\u043a\u0438"
    ],
    "name:und_x_variant":[
        "Goropashmi"
    ],
    "wof:name":"Kosyaky",
    "wof:placetype":"locality"
},
  "geometry": {"coordinates":[34.33532,50.33044],"type":"Point"}
}