{
  "type": "Feature",
  "properties": {
    "gn:admin1_code":"15.0",
    "gn:asciiname":"Tsetulya",
    "gn:country_code":"UA",
    "gn:dem":244,
    "gn:elevation":"243.0",
    "gn:feature_class":"P",
    "gn:feature_code":"PPL",
    "gn:name":"Tsetulya",
    "gn:population":309,
    "gn:timezone":"Europe/Kiev",
    "iso:country":"UA",
    "name:rus_x_preferred":[
        "\u0426\u0435\u0442\u0443\u043b\u044f"
    ],
    "name:ukr_x_preferred":[
        "\u0426\u0435\u0442\u0443\u043b\u044f"
    ],
    "name:und_x_variant":[
        "Zheltula",
        "Tsetulya",
        "Tsetula"
    ],
    "wof:name":"Tsetulya",
    "wof:placetype":"locality",
    "wof:population":309
},
  "geometry": {"coordinates":[23.46308,49.96834000000001],"type":"Point"}
}