{
  "type": "Feature",
  "properties": {
    "gn:admin1_code":"19.0",
    "gn:asciiname":"Hnativka",
    "gn:country_code":"UA",
    "gn:dem":252,
    "gn:feature_class":"P",
    "gn:feature_code":"PPL",
    "gn:name":"Hnativka",
    "gn:population":0,
    "gn:timezone":"Europe/Kiev",
    "iso:country":"UA",
    "name:ukr_x_preferred":[
        "Hnativka"
    ],
    "name:ukr_x_variant":[
        "\u0413\u043d\u0430\u0442\u0456\u0432\u043a\u0430"
    ],
    "wof:name":"Hnativka",
    "wof:placetype":"locality"
},
  "geometry": {"coordinates":[25.58947,50.41269000000001],"type":"Point"}
}