{
  "type": "Feature",
  "properties": {
    "gn:admin1_code":"5.0",
    "gn:asciiname":"Kabachki",
    "gn:country_code":"UA",
    "gn:dem":230,
    "gn:feature_class":"P",
    "gn:feature_code":"PPL",
    "gn:name":"Kabachki",
    "gn:population":0,
    "gn:timezone":"Europe/Kiev",
    "iso:country":"UA",
    "wof:name":"Kabachki",
    "wof:placetype":"locality"
},
  "geometry": {"coordinates":[38.45833,48.03111],"type":"Point"}
}