{
  "type": "Feature",
  "properties": {
    "gn:admin1_code":"2.0",
    "gn:asciiname":"Samsony",
    "gn:country_code":"UA",
    "gn:dem":116,
    "gn:feature_class":"P",
    "gn:feature_code":"PPL",
    "gn:name":"Samsony",
    "gn:population":0,
    "gn:timezone":"Europe/Kiev",
    "iso:country":"UA",
    "name:ukr_x_preferred":[
        "Samsony"
    ],
    "name:ukr_x_variant":[
        "\u0421\u0430\u043c\u0441\u043e\u043d\u0438"
    ],
    "wof:name":"Samsony",
    "wof:placetype":"locality"
},
  "geometry": {"coordinates":[31.03125,50.94686],"type":"Point"}
}