{
  "type": "Feature",
  "properties": {
    "gn:admin1_code":"24.0",
    "gn:asciiname":"Slavne",
    "gn:country_code":"UA",
    "gn:dem":179,
    "gn:feature_class":"P",
    "gn:feature_code":"PPL",
    "gn:name":"Slavne",
    "gn:population":0,
    "gn:timezone":"Europe/Kiev",
    "iso:country":"UA",
    "name:hye_x_preferred":[
        "\u054d\u056c\u0561\u057e\u0576\u0578\u0565"
    ],
    "name:rus_x_preferred":[
        "\u0421\u043b\u0430\u0432\u043d\u043e\u0435"
    ],
    "name:ukr_x_preferred":[
        "Slavne"
    ],
    "name:ukr_x_variant":[
        "\u0421\u043b\u0430\u0432\u043d\u0435"
    ],
    "name:und_x_variant":[
        "Stanislavka",
        "Slavnoye"
    ],
    "wof:name":"Slavne",
    "wof:placetype":"locality"
},
  "geometry": {"coordinates":[25.36849,50.95588],"type":"Point"}
}