{
  "type": "Feature",
  "properties": {
    "gn:admin1_code":"24.0",
    "gn:asciiname":"Maly Stavygorozh",
    "gn:country_code":"UA",
    "gn:dem":181,
    "gn:feature_class":"P",
    "gn:feature_code":"PPL",
    "gn:name":"Maly Stavygorozh",
    "gn:population":0,
    "gn:timezone":"Europe/Kiev",
    "iso:country":"UA",
    "wof:name":"Maly Stavygorozh",
    "wof:placetype":"locality"
},
  "geometry": {"coordinates":[25.78333,51.06667],"type":"Point"}
}