{
  "type": "Feature",
  "properties": {
    "gn:admin1_code":"24.0",
    "gn:asciiname":"Khorokhoryn",
    "gn:country_code":"UA",
    "gn:dem":210,
    "gn:feature_class":"P",
    "gn:feature_code":"PPL",
    "gn:name":"Khorokhoryn",
    "gn:population":0,
    "gn:timezone":"Europe/Kiev",
    "iso:country":"UA",
    "name:ukr_x_preferred":[
        "\u0425\u043e\u0440\u043e\u0445\u043e\u0440\u0438\u043d"
    ],
    "name:und_x_variant":[
        "Chorochoryn",
        "Khorokhoryn",
        "Khorokhorin"
    ],
    "wof:name":"Khorokhoryn",
    "wof:placetype":"locality"
},
  "geometry": {"coordinates":[24.95185,50.82746],"type":"Point"}
}