{
  "type": "Feature",
  "properties": {
    "gn:admin1_code":"21.0",
    "gn:asciiname":"Hrusheve",
    "gn:country_code":"UA",
    "gn:dem":148,
    "gn:feature_class":"P",
    "gn:feature_code":"PPL",
    "gn:name":"Hrusheve",
    "gn:population":0,
    "gn:timezone":"Europe/Kiev",
    "iso:country":"UA",
    "name:ukr_x_preferred":[
        "Hrusheve"
    ],
    "name:ukr_x_variant":[
        "\u0413\u0440\u0443\u0448\u0435\u0432\u0435"
    ],
    "name:und_x_variant":[
        "Grushev"
    ],
    "wof:name":"Hrusheve",
    "wof:placetype":"locality"
},
  "geometry": {"coordinates":[34.27014,50.58235],"type":"Point"}
}