{
  "type": "Feature",
  "properties": {
    "gn:admin1_code":"27.0",
    "gn:asciiname":"Smykivka",
    "gn:country_code":"UA",
    "gn:dem":196,
    "gn:feature_class":"P",
    "gn:feature_code":"PPL",
    "gn:name":"Smykivka",
    "gn:population":0,
    "gn:timezone":"Europe/Kiev",
    "iso:country":"UA",
    "name:ukr_x_preferred":[
        "Smykivka"
    ],
    "name:ukr_x_variant":[
        "\u0421\u043c\u0438\u043a\u0456\u0432\u043a\u0430"
    ],
    "name:und_x_variant":[
        "Smykovka"
    ],
    "wof:name":"Smykivka",
    "wof:placetype":"locality"
},
  "geometry": {"coordinates":[28.95543,50.45648],"type":"Point"}
}