{
  "type": "Feature",
  "properties": {
    "gn:admin1_code":"27.0",
    "gn:admin2_code":"9642483",
    "gn:asciiname":"Dubrivka",
    "gn:country_code":"UA",
    "gn:dem":170,
    "gn:feature_class":"P",
    "gn:feature_code":"PPL",
    "gn:name":"Dubrivka",
    "gn:population":0,
    "gn:timezone":"Europe/Kiev",
    "iso:country":"UA",
    "name:deu_x_historical":[
        "Dibrowka"
    ],
    "name:deu_x_preferred":[
        "Dubriwka"
    ],
    "name:deu_x_variant":[
        "Dibrowka"
    ],
    "name:fra_x_preferred":[
        "Doubrivka"
    ],
    "name:hye_x_historical":[
        "\u0534\u056b\u0562\u0580\u0578\u057e\u056f\u0561"
    ],
    "name:hye_x_preferred":[
        "\u0534\u056b\u0562\u0580\u0578\u057e\u056f\u0561"
    ],
    "name:rus_x_historical":[
        "Dibrovka",
        "\u0414\u0438\u0431\u0440\u043e\u0432\u043a\u0430"
    ],
    "name:rus_x_preferred":[
        "Dubrovka"
    ],
    "name:rus_x_variant":[
        "Dibrovka",
        "\u0414\u0438\u0431\u0440\u043e\u0432\u043a\u0430",
        "Dubrowka"
    ],
    "name:ukr_x_historical":[
        "Dibrivka",
        "\u0414\u0456\u0431\u0440\u0456\u0432\u043a\u0430"
    ],
    "name:ukr_x_preferred":[
        "\u0414\u0443\u0431\u0440\u0456\u0432\u043a\u0430"
    ],
    "name:ukr_x_variant":[
        "Dibrivka",
        "\u0414\u0456\u0431\u0440\u0456\u0432\u043a\u0430"
    ],
    "name:zho_x_historical":[
        "\u5b63\u5e03\u91cc\u592b\u5361"
    ],
    "name:zho_x_preferred":[
        "\u5b63\u5e03\u91cc\u592b\u5361"
    ],
    "wof:name":"Dubrivka",
    "wof:placetype":"locality"
},
  "geometry": {"coordinates":[29.5917,50.287],"type":"Point"}
}