{
  "type": "Feature",
  "properties": {
    "gn:admin1_code":"14.0",
    "gn:asciiname":"Sofiyivka",
    "gn:country_code":"UA",
    "gn:dem":226,
    "gn:feature_class":"P",
    "gn:feature_code":"PPL",
    "gn:name":"Sofiyivka",
    "gn:population":0,
    "gn:timezone":"Europe/Zaporozhye",
    "iso:country":"UA",
    "name:ukr_x_preferred":[
        "Sofiyivka"
    ],
    "name:ukr_x_variant":[
        "\u0421\u043e\u0444\u0456\u0457\u0432\u043a\u0430"
    ],
    "name:und_x_variant":[
        "Sofiyevka"
    ],
    "wof:name":"Sofiyivka",
    "wof:placetype":"locality"
},
  "geometry": {"coordinates":[38.56972,48.37444],"type":"Point"}
}