{
  "type": "Feature",
  "properties": {
    "gn:admin1_code":"21.0",
    "gn:asciiname":"Chervonohvardiys'ke",
    "gn:country_code":"UA",
    "gn:dem":159,
    "gn:feature_class":"P",
    "gn:feature_code":"PPL",
    "gn:name":"Chervonohvardiys\u2019ke",
    "gn:population":0,
    "gn:timezone":"Europe/Kiev",
    "iso:country":"UA",
    "name:ukr_x_preferred":[
        "Chervonohvardiys\u2019ke"
    ],
    "name:ukr_x_variant":[
        "\u0427\u0435\u0440\u0432\u043e\u043d\u043e\u0433\u0432\u0430\u0440\u0434\u0456\u0439\u0441\u044c\u043a\u0435"
    ],
    "name:und_x_variant":[
        "Chervonogvardeyskoye"
    ],
    "wof:name":"Chervonohvardiys'ke",
    "wof:placetype":"locality"
},
  "geometry": {"coordinates":[33.69068,50.72679],"type":"Point"}
}