{
  "type": "Feature",
  "properties": {
    "gn:admin1_code":"18.0",
    "gn:asciiname":"Klyushnyky",
    "gn:country_code":"UA",
    "gn:dem":89,
    "gn:feature_class":"P",
    "gn:feature_code":"PPL",
    "gn:name":"Klyushnyky",
    "gn:population":0,
    "gn:timezone":"Europe/Kiev",
    "iso:country":"UA",
    "name:ukr_x_preferred":[
        "Klyushnyky"
    ],
    "name:ukr_x_variant":[
        "\u041a\u043b\u044e\u0448\u043d\u0438\u043a\u0438"
    ],
    "wof:name":"Klyushnyky",
    "wof:placetype":"locality"
},
  "geometry": {"coordinates":[34.64057,49.52748],"type":"Point"}
}