{
  "type": "Feature",
  "properties": {
    "gn:admin1_code":"26.0",
    "gn:asciiname":"Lystvyanka",
    "gn:country_code":"UA",
    "gn:dem":164,
    "gn:feature_class":"P",
    "gn:feature_code":"PPL",
    "gn:name":"Lystvyanka",
    "gn:population":0,
    "gn:timezone":"Europe/Zaporozhye",
    "iso:country":"UA",
    "name:ukr_x_preferred":[
        "Lystvyanka"
    ],
    "name:ukr_x_variant":[
        "\u041b\u0438\u0441\u0442\u0432\u044f\u043d\u043a\u0430"
    ],
    "name:und_x_variant":[
        "Shenbaum"
    ],
    "wof:name":"Lystvyanka",
    "wof:placetype":"locality"
},
  "geometry": {"coordinates":[37.16818,47.39595],"type":"Point"}
}