{
  "type": "Feature",
  "properties": {
    "gn:admin1_code":"8.0",
    "gn:asciiname":"Blakytne",
    "gn:country_code":"UA",
    "gn:dem":67,
    "gn:feature_class":"P",
    "gn:feature_code":"PPL",
    "gn:name":"Blakytne",
    "gn:population":0,
    "gn:timezone":"Europe/Kiev",
    "iso:country":"UA",
    "name:ukr_x_preferred":[
        "Blakytne"
    ],
    "name:ukr_x_variant":[
        "\u0411\u043b\u0430\u043a\u0438\u0442\u043d\u0435"
    ],
    "name:und_x_variant":[
        "Blakitnaya",
        "Blakitnoye"
    ],
    "wof:name":"Blakytne",
    "wof:placetype":"locality"
},
  "geometry": {"coordinates":[33.4381,47.41005],"type":"Point"}
}