{
  "type": "Feature",
  "properties": {
    "gn:admin1_code":"19.0",
    "gn:asciiname":"Richyshche",
    "gn:country_code":"UA",
    "gn:dem":223,
    "gn:feature_class":"P",
    "gn:feature_code":"PPL",
    "gn:name":"Richyshche",
    "gn:population":0,
    "gn:timezone":"Europe/Kiev",
    "iso:country":"UA",
    "name:ukr_x_preferred":[
        "Richyshche"
    ],
    "name:ukr_x_variant":[
        "\u0420\u0456\u0447\u0438\u0449\u0435"
    ],
    "name:und_x_variant":[
        "Rechishche"
    ],
    "wof:name":"Richyshche",
    "wof:placetype":"locality"
},
  "geometry": {"coordinates":[25.8006,50.62815],"type":"Point"}
}