{
  "type": "Feature",
  "properties": {
    "gn:admin1_code":"8.0",
    "gn:asciiname":"Kosakivka",
    "gn:country_code":"UA",
    "gn:dem":67,
    "gn:feature_class":"P",
    "gn:feature_code":"PPL",
    "gn:name":"Kosakivka",
    "gn:population":0,
    "gn:timezone":"Europe/Kiev",
    "iso:country":"UA",
    "name:ukr_x_preferred":[
        "Kosakivka"
    ],
    "name:ukr_x_variant":[
        "\u041a\u043e\u0441\u0430\u043a\u0456\u0432\u043a\u0430"
    ],
    "name:und_x_variant":[
        "Kosakovka"
    ],
    "wof:name":"Kosakivka",
    "wof:placetype":"locality"
},
  "geometry": {"coordinates":[34.35556,47.02963],"type":"Point"}
}