{
  "type": "Feature",
  "properties": {
    "gn:admin1_code":"17.0",
    "gn:asciiname":"Vovkove",
    "gn:country_code":"UA",
    "gn:dem":38,
    "gn:feature_class":"P",
    "gn:feature_code":"PPL",
    "gn:name":"Vovkove",
    "gn:population":0,
    "gn:timezone":"Europe/Kiev",
    "iso:country":"UA",
    "name:ukr_x_preferred":[
        "Vovkove"
    ],
    "name:ukr_x_variant":[
        "\u0412\u043e\u0432\u043a\u043e\u0432\u0435"
    ],
    "name:und_x_variant":[
        "Ney-Libental\u2019",
        "Volkovo"
    ],
    "wof:name":"Vovkove",
    "wof:placetype":"locality"
},
  "geometry": {"coordinates":[30.66459,47.01506],"type":"Point"}
}