{
  "type": "Feature",
  "properties": {
    "gn:admin1_code":"5.0",
    "gn:asciiname":"Lozove",
    "gn:country_code":"UA",
    "gn:dem":179,
    "gn:feature_class":"P",
    "gn:feature_code":"PPL",
    "gn:name":"Lozove",
    "gn:population":0,
    "gn:timezone":"Europe/Kiev",
    "iso:country":"UA",
    "name:bel_x_preferred":[
        "\u041b\u0430\u0437\u0430\u0432\u044d"
    ],
    "name:crh_x_preferred":[
        "Lozove"
    ],
    "name:deu_x_preferred":[
        "Losowe"
    ],
    "name:hye_x_preferred":[
        "\u053c\u0578\u0566\u0578\u057e\u0578\u0565"
    ],
    "name:pol_x_preferred":[
        "\u0141ozowe"
    ],
    "name:ron_x_preferred":[
        "Lozove"
    ],
    "name:rus_x_preferred":[
        "\u041b\u043e\u0437\u043e\u0432\u043e\u0435"
    ],
    "name:ukr_x_preferred":[
        "Lozove"
    ],
    "name:ukr_x_variant":[
        "\u041b\u043e\u0437\u043e\u0432\u0435"
    ],
    "name:und_x_variant":[
        "Lozovaya"
    ],
    "name:zho_x_preferred":[
        "\u6d1b\u4f50\u97cb"
    ],
    "wof:name":"Lozove",
    "wof:placetype":"locality"
},
  "geometry": {"coordinates":[37.63831,48.00383],"type":"Point"}
}