{
  "type": "Feature",
  "properties": {
    "gn:admin1_code":"5.0",
    "gn:asciiname":"Lozove",
    "gn:country_code":"UA",
    "gn:dem":179,
    "gn:feature_class":"P",
    "gn:feature_code":"PPL",
    "gn:name":"Lozove",
    "gn:population":0,
    "gn:timezone":"Europe/Kiev",
    "iso:country":"UA",
    "name:ukr_x_preferred":[
        "Lozove"
    ],
    "name:ukr_x_variant":[
        "\u041b\u043e\u0437\u043e\u0432\u0435"
    ],
    "name:und_x_variant":[
        "Lozovaya"
    ],
    "wof:name":"Lozove",
    "wof:placetype":"locality"
},
  "geometry": {"coordinates":[37.63831,48.00383],"type":"Point"}
}