{
  "type": "Feature",
  "properties": {
    "gn:admin1_code":"5.0",
    "gn:asciiname":"Yasnobrodivka",
    "gn:country_code":"UA",
    "gn:dem":156,
    "gn:feature_class":"P",
    "gn:feature_code":"PPL",
    "gn:name":"Yasnobrodivka",
    "gn:population":0,
    "gn:timezone":"Europe/Kiev",
    "iso:country":"UA",
    "name:ukr_x_preferred":[
        "Yasnobrodivka"
    ],
    "name:ukr_x_variant":[
        "\u042f\u0441\u043d\u043e\u0431\u0440\u043e\u0434\u0456\u0432\u043a\u0430"
    ],
    "wof:name":"Yasnobrodivka",
    "wof:placetype":"locality"
},
  "geometry": {"coordinates":[37.5392,48.13683],"type":"Point"}
}