{
  "type": "Feature",
  "properties": {
    "gn:admin1_code":"2.0",
    "gn:asciiname":"Liskivka",
    "gn:country_code":"UA",
    "gn:dem":128,
    "gn:feature_class":"P",
    "gn:feature_code":"PPL",
    "gn:name":"Liskivka",
    "gn:population":0,
    "gn:timezone":"Europe/Kiev",
    "iso:country":"UA",
    "name:ukr_x_preferred":[
        "Liskivka"
    ],
    "name:ukr_x_variant":[
        "\u041b\u0456\u0441\u043a\u0456\u0432\u043a\u0430"
    ],
    "name:und_x_variant":[
        "Leskovka"
    ],
    "wof:name":"Liskivka",
    "wof:placetype":"locality"
},
  "geometry": {"coordinates":[30.66336,51.61125],"type":"Point"}
}