{
  "type": "Feature",
  "properties": {
    "gn:admin1_code":"23.0",
    "gn:asciiname":"Lysogorka",
    "gn:country_code":"UA",
    "gn:dem":321,
    "gn:feature_class":"P",
    "gn:feature_code":"PPL",
    "gn:name":"Lysogorka",
    "gn:population":0,
    "gn:timezone":"Europe/Kiev",
    "iso:country":"UA",
    "name:und_x_variant":[
        "Lysa Gorka",
        "Lysogorka"
    ],
    "wof:name":"Lysogorka",
    "wof:placetype":"locality"
},
  "geometry": {"coordinates":[27.98339,49.23554],"type":"Point"}
}