{
  "type": "Feature",
  "properties": {
    "gn:admin1_code":"23.0",
    "gn:asciiname":"Lysogorka",
    "gn:country_code":"UA",
    "gn:dem":321,
    "gn:feature_class":"P",
    "gn:feature_code":"PPL",
    "gn:name":"Lysogorka",
    "gn:population":0,
    "gn:timezone":"Europe/Kiev",
    "iso:country":"UA",
    "name:bak_x_preferred":[
        "\u041b\u044b\u0441\u043e\u0433\u043e\u0440\u043a\u0430"
    ],
    "name:che_x_preferred":[
        "\u041b\u044b\u0441\u043e\u0433\u043e\u0440\u043a\u0430"
    ],
    "name:hye_x_preferred":[
        "\u053c\u056b\u057d\u0578\u0563\u0578\u0580\u056f\u0561"
    ],
    "name:kaz_x_preferred":[
        "\u041b\u044b\u0441\u043e\u0433\u043e\u0440\u043a\u0430"
    ],
    "name:myv_x_preferred":[
        "\u041b\u044b\u0441\u043e\u0433\u043e\u0440\u043a\u0430"
    ],
    "name:rus_x_preferred":[
        "\u041b\u044b\u0441\u043e\u0433\u043e\u0440\u043a\u0430"
    ],
    "name:tat_x_preferred":[
        "\u041b\u044b\u0441\u043e\u0433\u043e\u0440\u043a\u0430"
    ],
    "name:ukr_x_preferred":[
        "\u041b\u0438\u0441\u043e\u0433\u043e\u0440\u043a\u0430"
    ],
    "name:und_x_variant":[
        "Lysa Gorka",
        "Lysogorka"
    ],
    "wof:name":"Lysogorka",
    "wof:placetype":"locality"
},
  "geometry": {"coordinates":[27.98339,49.23554],"type":"Point"}
}