{
  "type": "Feature",
  "properties": {
    "iso:country":"UA",
    "name:eng_x_preferred":[
        "Rafailivka"
    ],
    "name:ger_x_preferred":[
        "Rafajliwka"
    ],
    "name:lav_x_preferred":[
        "Rafajlivka"
    ],
    "name:rum_x_preferred":[
        "Rafailivka"
    ],
    "name:rus_x_preferred":[
        "\u0420\u0430\u0444\u0430\u0439\u043b\u043e\u0432\u043a\u0430"
    ],
    "name:ukr_x_preferred":[
        "Rafaylivka"
    ],
    "name:ukr_x_variant":[
        "\u0420\u0430\u0444\u0430\u0439\u043b\u0456\u0432\u043a\u0430"
    ],
    "name:unk_x_variant":[
        "Rafailovskoy"
    ],
    "qs:a0":"\u0423\u043a\u0440\u0430\u0457\u043d\u0430",
    "qs:a1":"*\u041b\u0443\u0433\u0430\u043d\u0441\u044c\u043a\u0430",
    "qs:a1_alt":"Luhans'ka",
    "qs:a1r":"0",
    "qs:a2":"\u0410\u043d\u0442\u0440\u0430\u0446\u0438\u0442\u0456\u0432\u0441\u044c\u043a\u0438\u0439",
    "qs:a2_alt":"Antratsytivs'kyi",
    "qs:adm0":"\u0423\u043a\u0440\u0430\u0457\u043d\u0430",
    "qs:la_lc":"*",
    "qs:level":"locality",
    "qs:loc":"\u0420\u0430\u0444\u0430\u0439\u043b\u0456\u0432\u043a\u0430",
    "qs:loc_alt":"Rafailivka",
    "qs:pop":0,
    "qs:type":"buffered point",
    "wof:name":"\u0420\u0430\u0444\u0430\u0439\u043b\u0456\u0432\u043a\u0430",
    "wof:placetype":"locality"
},
  "geometry": {"coordinates":[39.202767,48.122296],"type":"Point"}
}