{
  "type": "Feature",
  "properties": {
    "gn:admin1_code":"2.0",
    "gn:asciiname":"Lisky",
    "gn:country_code":"UA",
    "gn:dem":117,
    "gn:feature_class":"P",
    "gn:feature_code":"PPL",
    "gn:name":"Lisky",
    "gn:population":0,
    "gn:timezone":"Europe/Kiev",
    "iso:country":"UA",
    "name:ukr_x_preferred":[
        "Lisky"
    ],
    "name:ukr_x_variant":[
        "\u041b\u0456\u0441\u043a\u0438"
    ],
    "name:und_x_variant":[
        "Leski"
    ],
    "wof:name":"Lisky",
    "wof:placetype":"locality"
},
  "geometry": {"coordinates":[32.14798,51.46356],"type":"Point"}
}