{
  "type": "Feature",
  "properties": {
    "gn:admin1_code":"7.0",
    "gn:asciiname":"Martynivka",
    "gn:country_code":"UA",
    "gn:dem":167,
    "gn:feature_class":"P",
    "gn:feature_code":"PPL",
    "gn:name":"Martynivka",
    "gn:population":0,
    "gn:timezone":"Europe/Kiev",
    "iso:country":"UA",
    "name:ukr_x_preferred":[
        "Martynivka"
    ],
    "name:ukr_x_variant":[
        "\u041c\u0430\u0440\u0442\u0438\u043d\u0456\u0432\u043a\u0430"
    ],
    "wof:name":"Martynivka",
    "wof:placetype":"locality"
},
  "geometry": {"coordinates":[35.93379,50.33754],"type":"Point"}
}