{
  "type": "Feature",
  "properties": {
    "gn:admin1_code":"16.0",
    "gn:asciiname":"Lisove",
    "gn:country_code":"UA",
    "gn:dem":85,
    "gn:feature_class":"P",
    "gn:feature_code":"PPL",
    "gn:name":"Lisove",
    "gn:population":0,
    "gn:timezone":"Europe/Kiev",
    "iso:country":"UA",
    "name:rus_x_preferred":[
        "\u041b\u0435\u0441\u043d\u043e\u0435"
    ],
    "name:ukr_x_preferred":[
        "Lisove"
    ],
    "name:ukr_x_variant":[
        "\u041b\u0456\u0441\u043e\u0432\u0435"
    ],
    "name:und_x_variant":[
        "Lesnoye"
    ],
    "wof:name":"Lisove",
    "wof:placetype":"locality"
},
  "geometry": {"coordinates":[33.11512,47.51207],"type":"Point"}
}