{
  "type": "Feature",
  "properties": {
    "gn:admin1_code":"7.0",
    "gn:asciiname":"Romanki",
    "gn:country_code":"UA",
    "gn:dem":131,
    "gn:feature_class":"P",
    "gn:feature_code":"PPL",
    "gn:name":"Romanki",
    "gn:population":0,
    "gn:timezone":"Europe/Kiev",
    "iso:country":"UA",
    "wof:name":"Romanki",
    "wof:placetype":"locality"
},
  "geometry": {"coordinates":[36.04694,49.3475],"type":"Point"}
}