{
  "type": "Feature",
  "properties": {
    "gn:admin1_code":"4.0",
    "gn:asciiname":"Ozhenkivka",
    "gn:country_code":"UA",
    "gn:dem":116,
    "gn:feature_class":"P",
    "gn:feature_code":"PPL",
    "gn:name":"Ozhenkivka",
    "gn:population":0,
    "gn:timezone":"Europe/Kiev",
    "iso:country":"UA",
    "name:ukr_x_preferred":[
        "Ozhenkivka"
    ],
    "name:ukr_x_variant":[
        "\u041e\u0436\u0435\u043d\u043a\u0456\u0432\u043a\u0430"
    ],
    "name:und_x_variant":[
        "Ozhenkovka"
    ],
    "wof:name":"Ozhenkivka",
    "wof:placetype":"locality"
},
  "geometry": {"coordinates":[35.7066,48.49504],"type":"Point"}
}