{
  "type": "Feature",
  "properties": {
    "gn:admin1_code":"18.0",
    "gn:asciiname":"Kolodna",
    "gn:country_code":"UA",
    "gn:dem":89,
    "gn:feature_class":"P",
    "gn:feature_code":"PPL",
    "gn:name":"Kolodna",
    "gn:population":0,
    "gn:timezone":"Europe/Kiev",
    "iso:country":"UA",
    "name:ukr_x_preferred":[
        "Kolodna"
    ],
    "name:ukr_x_variant":[
        "\u041a\u043e\u043b\u043e\u0434\u043d\u0430"
    ],
    "wof:name":"Kolodna",
    "wof:placetype":"locality"
},
  "geometry": {"coordinates":[32.91261,49.84965],"type":"Point"}
}