{
  "type": "Feature",
  "properties": {
    "gn:admin1_code":"17.0",
    "gn:asciiname":"Uspenka",
    "gn:country_code":"UA",
    "gn:dem":77,
    "gn:feature_class":"P",
    "gn:feature_code":"PPL",
    "gn:name":"Uspenka",
    "gn:population":0,
    "gn:timezone":"Europe/Kiev",
    "iso:country":"UA",
    "name:ukr_x_preferred":[
        "Uspenka"
    ],
    "name:ukr_x_variant":[
        "\u0423\u0441\u043f\u0435\u043d\u043a\u0430"
    ],
    "wof:name":"Uspenka",
    "wof:placetype":"locality"
},
  "geometry": {"coordinates":[30.50042,47.35743],"type":"Point"}
}