{
  "type": "Feature",
  "properties": {
    "gn:admin1_code":"15.0",
    "gn:asciiname":"Ruda Seletska",
    "gn:country_code":"UA",
    "gn:dem":204,
    "gn:feature_class":"P",
    "gn:feature_code":"PPL",
    "gn:name":"Ruda Seletska",
    "gn:population":0,
    "gn:timezone":"Europe/Kiev",
    "iso:country":"UA",
    "wof:name":"Ruda Seletska",
    "wof:placetype":"locality"
},
  "geometry": {"coordinates":[24.41137,50.15595],"type":"Point"}
}