{
  "type": "Feature",
  "properties": {
    "gn:admin1_code":"22.0",
    "gn:asciiname":"Chistopady",
    "gn:country_code":"UA",
    "gn:dem":343,
    "gn:feature_class":"P",
    "gn:feature_code":"PPL",
    "gn:name":"Chistopady",
    "gn:population":0,
    "gn:timezone":"Europe/Kiev",
    "iso:country":"UA",
    "wof:name":"Chistopady",
    "wof:placetype":"locality"
},
  "geometry": {"coordinates":[25.33945,49.8135],"type":"Point"}
}