{
  "type": "Feature",
  "properties": {
    "gn:admin1_code":"19.0",
    "gn:asciiname":"Birok",
    "gn:country_code":"UA",
    "gn:dem":200,
    "gn:feature_class":"P",
    "gn:feature_code":"PPL",
    "gn:name":"Birok",
    "gn:population":0,
    "gn:timezone":"Europe/Kiev",
    "iso:country":"UA",
    "name:ukr_x_preferred":[
        "Birok"
    ],
    "name:ukr_x_variant":[
        "\u0411\u0456\u0440\u043e\u043a"
    ],
    "wof:name":"Birok",
    "wof:placetype":"locality"
},
  "geometry": {"coordinates":[25.73665,50.30496],"type":"Point"}
}