{
  "type": "Feature",
  "properties": {
    "gn:admin1_code":"16.0",
    "gn:asciiname":"Kotlyareve",
    "gn:country_code":"UA",
    "gn:dem":48,
    "gn:feature_class":"P",
    "gn:feature_code":"PPL",
    "gn:name":"Kotlyareve",
    "gn:population":0,
    "gn:timezone":"Europe/Kiev",
    "iso:country":"UA",
    "name:eng_x_preferred":[
        "Kotlyareve"
    ],
    "name:eng_x_variant":[
        "Kotlyarevo"
    ],
    "name:rus_x_preferred":[
        "\u041a\u043e\u0442\u043b\u044f\u0440e\u0432\u043e"
    ],
    "name:ukr_x_preferred":[
        "\u041a\u043e\u0442\u043b\u044f\u0440e\u0432\u0435"
    ],
    "wof:name":"Kotlyareve",
    "wof:placetype":"locality"
},
  "geometry": {"coordinates":[32.21949,46.88586],"type":"Point"}
}