{
  "type": "Feature",
  "properties": {
    "gn:admin1_code":"4.0",
    "gn:asciiname":"Novoivanivanka",
    "gn:country_code":"UA",
    "gn:dem":73,
    "gn:feature_class":"P",
    "gn:feature_code":"PPL",
    "gn:name":"Novoivanivanka",
    "gn:population":0,
    "gn:timezone":"Europe/Kiev",
    "iso:country":"UA",
    "name:rus_x_preferred":[
        "\u041d\u043e\u0432\u043e\u0438\u0432\u0430\u043d\u043e\u0432\u043a\u0430"
    ],
    "name:ukr_x_preferred":[
        "Novoivanivanka"
    ],
    "name:ukr_x_variant":[
        "\u041d\u043e\u0432\u043e\u0456\u0432\u0430\u043d\u0456\u0432\u043a\u0430"
    ],
    "name:und_x_variant":[
        "Novoivanovka"
    ],
    "wof:name":"Novoivanivanka",
    "wof:placetype":"locality"
},
  "geometry": {"coordinates":[33.52532,48.04548],"type":"Point"}
}