{
  "type": "Feature",
  "properties": {
    "gn:admin1_code":"4.0",
    "gn:asciiname":"Derezuvate",
    "gn:country_code":"UA",
    "gn:dem":122,
    "gn:feature_class":"P",
    "gn:feature_code":"PPL",
    "gn:name":"Derezuvate",
    "gn:population":0,
    "gn:timezone":"Europe/Kiev",
    "iso:country":"UA",
    "name:eng_x_preferred":[
        "Derezovatoye"
    ],
    "name:rus_x_preferred":[
        "\u0414\u0435\u0440\u0435\u0437\u043e\u0432\u0430\u0442\u043e\u0435"
    ],
    "name:ukr_x_preferred":[
        "Derezuvate"
    ],
    "name:ukr_x_variant":[
        "\u0414\u0435\u0440\u0435\u0437\u0443\u0432\u0430\u0442\u0435"
    ],
    "name:und_x_variant":[
        "Derezovatka"
    ],
    "wof:name":"Derezuvate",
    "wof:placetype":"locality"
},
  "geometry": {"coordinates":[35.43823,48.48651],"type":"Point"}
}