{
  "type": "Feature",
  "properties": {
    "iso:country":"UA",
    "qs:a0":"\u0423\u043a\u0440\u0430\u0457\u043d\u0430",
    "qs:a1":"*\u041a\u0438\u0457\u0432\u0441\u044c\u043a\u0430",
    "qs:a1_alt":"Kyivs'ka",
    "qs:a1r":"0",
    "qs:a2":"\u0420\u043e\u043a\u0438\u0442\u043d\u044f\u043d\u0441\u044c\u043a\u0438\u0439",
    "qs:a2_alt":"Rokytnians'kyi",
    "qs:adm0":"\u0423\u043a\u0440\u0430\u0457\u043d\u0430",
    "qs:la_lc":"*",
    "qs:level":"locality",
    "qs:loc":"\u0416\u0438\u0442\u043d\u0456 \u0413\u043e\u0440\u0438",
    "qs:loc_alt":"Zhytni Hory",
    "qs:pop":0,
    "qs:type":"buffered point",
    "wof:name":"\u0416\u0438\u0442\u043d\u0456 \u0413\u043e\u0440\u0438",
    "wof:placetype":"locality"
},
  "geometry": {"coordinates":[30.463234,49.727876],"type":"Point"}
}