{
  "type": "Feature",
  "properties": {
    "gn:gn_country":"UA",
    "gn:gn_fcode":"PPL",
    "gn:gn_pop":5010,
    "gn:population":5010,
    "iso:country":"UA",
    "name:eng_x_preferred":[
        "Zavallya"
    ],
    "name:rus_x_preferred":[
        "\u0417\u0430\u0432\u0430\u043b\u044c\u0435"
    ],
    "name:rus_x_variant":[
        "\u0417\u0430\u0432\u0430\u043b\u043b\u044f"
    ],
    "name:ukr_x_preferred":[
        "\u0417\u0430\u0432\u0430\u043b\u043b\u044f"
    ],
    "name:unk_x_variant":[
        "Zaval\u2019ye"
    ],
    "qs_pg:aaroncc":"UA",
    "qs_pg:gn_country":"UA",
    "qs_pg:gn_fcode":"PPL",
    "qs_pg:gn_pop":5010,
    "qs_pg:name":"Zavallya",
    "qs_pg:photos_9r":0,
    "qs_pg:photos_sr":0,
    "qs_pg:pop_sr":5,
    "qs_pg:qs_pg_placetype":"locality",
    "wof:name":"Zavallya",
    "wof:placetype":"locality",
    "wof:population":5010
},
  "geometry": {"coordinates":[30.01558,48.21354],"type":"Point"}
}