{
  "type": "Feature",
  "properties": {
    "iso:country":"UA",
    "name:eng_x_preferred":[
        "Chernetchina"
    ],
    "name:rus_x_preferred":[
        "\u0427\u0435\u0440\u043d\u0435\u0442\u0447\u0438\u043d\u0430"
    ],
    "name:ukr_x_preferred":[
        "Chernechchyna"
    ],
    "name:ukr_x_variant":[
        "\u0427\u0435\u0440\u043d\u0435\u0447\u0447\u0438\u043d\u0430"
    ],
    "qs:a0":"\u0423\u043a\u0440\u0430\u0457\u043d\u0430",
    "qs:a1":"*\u0421\u0443\u043c\u0441\u044c\u043a\u0430",
    "qs:a1_alt":"Sums'ka",
    "qs:a1r":"0",
    "qs:a2":"\u041a\u0440\u0430\u0441\u043d\u043e\u043f\u0456\u043b\u044c\u0441\u044c\u043a\u0438\u0439",
    "qs:a2_alt":"Krasnopil's'kyi",
    "qs:adm0":"\u0423\u043a\u0440\u0430\u0457\u043d\u0430",
    "qs:la_lc":"*",
    "qs:level":"locality",
    "qs:loc":"\u0427\u0435\u0440\u043d\u0435\u0447\u0447\u0438\u043d\u0430",
    "qs:loc_alt":"Chernechchyna",
    "qs:pop":0,
    "qs:type":"buffered point",
    "wof:name":"\u0427\u0435\u0440\u043d\u0435\u0447\u0447\u0438\u043d\u0430",
    "wof:placetype":"locality"
},
  "geometry": {"coordinates":[35.164784,50.752777],"type":"Point"}
}