{
  "type": "Feature",
  "properties": {
    "gn:admin1_code":"16.0",
    "gn:asciiname":"Yekaterinovka",
    "gn:country_code":"UA",
    "gn:dem":16,
    "gn:feature_class":"P",
    "gn:feature_code":"PPL",
    "gn:name":"Yekaterinovka",
    "gn:population":0,
    "gn:timezone":"Europe/Kiev",
    "iso:country":"UA",
    "name:und_x_variant":[
        "Gorbova",
        "Yekaterinovka"
    ],
    "wof:name":"Yekaterinovka",
    "wof:placetype":"locality"
},
  "geometry": {"coordinates":[32.18417,47.4096],"type":"Point"}
}