{
  "type": "Feature",
  "properties": {
    "gn:admin1_code":"18.0",
    "gn:asciiname":"Kyrpotivka",
    "gn:country_code":"UA",
    "gn:dem":134,
    "gn:feature_class":"P",
    "gn:feature_code":"PPL",
    "gn:name":"Kyrpotivka",
    "gn:population":0,
    "gn:timezone":"Europe/Kiev",
    "iso:country":"UA",
    "name:ukr_x_preferred":[
        "Kyrpotivka"
    ],
    "name:ukr_x_variant":[
        "\u041a\u0438\u0440\u043f\u043e\u0442\u0456\u0432\u043a\u0430"
    ],
    "name:und_x_variant":[
        "Kernot",
        "Kirpotovka"
    ],
    "wof:name":"Kyrpotivka",
    "wof:placetype":"locality"
},
  "geometry": {"coordinates":[34.0311,49.73676],"type":"Point"}
}