{
  "type": "Feature",
  "properties": {
    "gn:admin1_code":"7.0",
    "gn:asciiname":"Kuryache",
    "gn:country_code":"UA",
    "gn:dem":141,
    "gn:feature_class":"P",
    "gn:feature_code":"PPL",
    "gn:name":"Kuryache",
    "gn:population":0,
    "gn:timezone":"Europe/Kiev",
    "iso:country":"UA",
    "wof:name":"Kuryache",
    "wof:placetype":"locality"
},
  "geometry": {"coordinates":[36.13972,49.68917],"type":"Point"}
}