{
  "type": "Feature",
  "properties": {
    "gn:admin1_code":"2.0",
    "gn:asciiname":"Omelyaniv",
    "gn:country_code":"UA",
    "gn:dem":111,
    "gn:feature_class":"P",
    "gn:feature_code":"PPL",
    "gn:name":"Omelyaniv",
    "gn:population":0,
    "gn:timezone":"Europe/Kiev",
    "iso:country":"UA",
    "name:rus_x_preferred":[
        "Omel\u2019yanov"
    ],
    "name:ukr_x_preferred":[
        "Omelyaniv"
    ],
    "name:ukr_x_variant":[
        "\u041e\u043c\u0435\u043b\u044f\u043d\u0456\u0432"
    ],
    "name:und_x_variant":[
        "Yemel Yanovo",
        "Yemel\u2019yanov"
    ],
    "wof:name":"Omelyaniv",
    "wof:placetype":"locality"
},
  "geometry": {"coordinates":[31.03333,50.76667],"type":"Point"}
}