{
  "type": "Feature",
  "properties": {
    "gn:admin1_code":"15.0",
    "gn:asciiname":"Makhlynets'",
    "gn:country_code":"UA",
    "gn:dem":285,
    "gn:feature_class":"P",
    "gn:feature_code":"PPL",
    "gn:name":"Makhlynets\u2019",
    "gn:population":0,
    "gn:timezone":"Europe/Kiev",
    "iso:country":"UA",
    "name:rus_x_preferred":[
        "\u041c\u0430\u0445\u043b\u0438\u043d\u0435\u0446"
    ],
    "name:ukr_x_preferred":[
        "Makhlynets\u2019"
    ],
    "name:ukr_x_variant":[
        "\u041c\u0430\u0445\u043b\u0438\u043d\u0435\u0446\u044c"
    ],
    "name:und_x_variant":[
        "Machliniec",
        "Machlinice",
        "Makhlinets"
    ],
    "wof:name":"Makhlynets'",
    "wof:placetype":"locality"
},
  "geometry": {"coordinates":[24.08673,49.23971],"type":"Point"}
}