{
  "type": "Feature",
  "properties": {
    "gn:admin1_code":"8.0",
    "gn:asciiname":"Kleyn-Libental'",
    "gn:country_code":"UA",
    "gn:dem":69,
    "gn:feature_class":"P",
    "gn:feature_code":"PPL",
    "gn:name":"Kleyn-Libental\u2019",
    "gn:population":0,
    "gn:timezone":"Europe/Kiev",
    "iso:country":"UA",
    "wof:name":"Kleyn-Libental'",
    "wof:placetype":"locality"
},
  "geometry": {"coordinates":[33.96667,46.96667],"type":"Point"}
}