{
  "type": "Feature",
  "properties": {
    "gn:admin1_code":"9.0",
    "gn:asciiname":"Karasikha",
    "gn:country_code":"UA",
    "gn:dem":267,
    "gn:feature_class":"P",
    "gn:feature_code":"PPL",
    "gn:name":"Karasikha",
    "gn:population":0,
    "gn:timezone":"Europe/Kiev",
    "iso:country":"UA",
    "wof:name":"Karasikha",
    "wof:placetype":"locality"
},
  "geometry": {"coordinates":[26.35307,50.04375],"type":"Point"}
}