{
  "type": "Feature",
  "properties": {
    "gn:admin1_code":"15.0",
    "gn:asciiname":"Beregovoye",
    "gn:country_code":"UA",
    "gn:dem":225,
    "gn:feature_class":"P",
    "gn:feature_code":"PPL",
    "gn:name":"Beregovoye",
    "gn:population":0,
    "gn:timezone":"Europe/Kiev",
    "iso:country":"UA",
    "name:und_x_variant":[
        "Tulyholovy",
        "Beregove",
        "Tuligolovy",
        "Berehove",
        "Beregovoye"
    ],
    "wof:name":"Beregovoye",
    "wof:placetype":"locality"
},
  "geometry": {"coordinates":[23.30409,49.79871],"type":"Point"}
}