{
  "type": "Feature",
  "properties": {
    "gn:admin1_code":"14.0",
    "gn:asciiname":"Artema",
    "gn:country_code":"UA",
    "gn:dem":315,
    "gn:feature_class":"P",
    "gn:feature_code":"PPL",
    "gn:name":"Artema",
    "gn:population":0,
    "gn:timezone":"Europe/Zaporozhye",
    "iso:country":"UA",
    "name:ceb_x_preferred":[
        "Artema"
    ],
    "name:fra_x_preferred":[
        "Artema"
    ],
    "name:nld_x_preferred":[
        "Artema"
    ],
    "name:swe_x_preferred":[
        "Artema"
    ],
    "name:ukr_x_preferred":[
        "\u0410\u0440\u0442\u0435\u043c\u0430"
    ],
    "name:und_x_variant":[
        "Imeni Art\u00ebma"
    ],
    "name:vie_x_preferred":[
        "Artema"
    ],
    "name:war_x_preferred":[
        "Artema"
    ],
    "wof:name":"Artema",
    "wof:placetype":"locality"
},
  "geometry": {"coordinates":[38.78263,48.28012],"type":"Point"}
}