{
  "type": "Feature",
  "properties": {
    "gn:admin1_code":"4.0",
    "gn:asciiname":"Chervona Balka",
    "gn:country_code":"UA",
    "gn:dem":112,
    "gn:feature_class":"P",
    "gn:feature_code":"PPL",
    "gn:name":"Chervona Balka",
    "gn:population":0,
    "gn:timezone":"Europe/Kiev",
    "iso:country":"UA",
    "name:ukr_x_preferred":[
        "Chervona Balka"
    ],
    "name:ukr_x_variant":[
        "\u0427\u0435\u0440\u0432\u043e\u043d\u0430 \u0411\u0430\u043b\u043a\u0430"
    ],
    "wof:name":"Chervona Balka",
    "wof:placetype":"locality"
},
  "geometry": {"coordinates":[34.28878,48.26526],"type":"Point"}
}