{
  "type": "Feature",
  "properties": {
    "gn:admin1_code":"15.0",
    "gn:asciiname":"Hrymalivka",
    "gn:country_code":"UA",
    "gn:dem":192,
    "gn:feature_class":"P",
    "gn:feature_code":"PPL",
    "gn:name":"Hrymalivka",
    "gn:population":0,
    "gn:timezone":"Europe/Kiev",
    "iso:country":"UA",
    "name:ceb_x_preferred":[
        "Hrymalivka"
    ],
    "name:pol_x_preferred":[
        "Grzyma\u0142\u00f3wka"
    ],
    "name:ron_x_preferred":[
        "Hr\u00eemalivka"
    ],
    "name:rus_x_preferred":[
        "\u0413\u0440\u0438\u043c\u0430\u043b\u043e\u0432\u043a\u0430"
    ],
    "name:ukr_x_preferred":[
        "Hrymalivka"
    ],
    "name:ukr_x_variant":[
        "\u0413\u0440\u0438\u043c\u0430\u043b\u0456\u0432\u043a\u0430"
    ],
    "name:und_x_variant":[
        "Grimalovka"
    ],
    "name:zho_x_preferred":[
        "\u683c\u91cc\u99ac\u5229\u592b\u5361"
    ],
    "wof:name":"Hrymalivka",
    "wof:placetype":"locality"
},
  "geometry": {"coordinates":[25.04876,50.27974],"type":"Point"}
}