{
  "type": "Feature",
  "properties": {
    "iso:country":"UA",
    "qs:a0":"\u0423\u043a\u0440\u0430\u0457\u043d\u0430",
    "qs:a1":"*\u041c\u0438\u043a\u043e\u043b\u0430\u0457\u0432\u0441\u044c\u043a\u0430",
    "qs:a1_alt":"Mykolaivs'ka",
    "qs:a1r":"0",
    "qs:a2":"\u041e\u0447\u0430\u043a\u0456\u0432\u0441\u044c\u043a\u0438\u0439",
    "qs:a2_alt":"Ochakivs'kyi",
    "qs:adm0":"\u0423\u043a\u0440\u0430\u0457\u043d\u0430",
    "qs:la_lc":"*",
    "qs:level":"locality",
    "qs:loc":"\u041a\u0430\u043c'\u044f\u043d\u043a\u0430",
    "qs:loc_alt":"Kamianka",
    "qs:pop":0,
    "qs:type":"buffered point",
    "wd:wordcount":55,
    "wof:name":"\u041a\u0430\u043c'\u044f\u043d\u043a\u0430",
    "wof:placetype":"locality"
},
  "geometry": {"coordinates":[31.664549,46.818458],"type":"Point"}
}