{
  "type": "Feature",
  "properties": {
    "gn:admin1_code":"26.0",
    "gn:asciiname":"Kalinovka",
    "gn:country_code":"UA",
    "gn:dem":67,
    "gn:feature_class":"P",
    "gn:feature_code":"PPL",
    "gn:name":"Kalinovka",
    "gn:population":0,
    "gn:timezone":"Europe/Zaporozhye",
    "iso:country":"UA",
    "wof:name":"Kalinovka",
    "wof:placetype":"locality"
},
  "geometry": {"coordinates":[34.81667,46.91667],"type":"Point"}
}