{
  "type": "Feature",
  "properties": {
    "gn:admin1_code":"26.0",
    "gn:asciiname":"Petrivs'ke",
    "gn:country_code":"UA",
    "gn:dem":112,
    "gn:feature_class":"P",
    "gn:feature_code":"PPL",
    "gn:name":"Petrivs\u2019ke",
    "gn:population":0,
    "gn:timezone":"Europe/Zaporozhye",
    "iso:country":"UA",
    "name:rus_x_preferred":[
        "\u041f\u0435\u0442\u0440\u043e\u0432\u0441\u043a\u043e\u0435"
    ],
    "name:ukr_x_preferred":[
        "Petrivs\u2019ke"
    ],
    "name:ukr_x_variant":[
        "\u041f\u0435\u0442\u0440\u0456\u0432\u0441\u044c\u043a\u0435"
    ],
    "name:und_x_variant":[
        "Novo-Petrovskiy",
        "Petrovskoye"
    ],
    "wof:name":"Petrivs'ke",
    "wof:placetype":"locality"
},
  "geometry": {"coordinates":[34.92336,47.85133],"type":"Point"}
}