{
  "type": "Feature",
  "properties": {
    "gn:admin1_code":"18.0",
    "gn:asciiname":"Savulivka",
    "gn:country_code":"UA",
    "gn:dem":106,
    "gn:feature_class":"P",
    "gn:feature_code":"PPL",
    "gn:name":"Savulivka",
    "gn:population":0,
    "gn:timezone":"Europe/Kiev",
    "iso:country":"UA",
    "name:ukr_x_preferred":[
        "Savulivka"
    ],
    "name:ukr_x_variant":[
        "\u0421\u0430\u0432\u0443\u043b\u0456\u0432\u043a\u0430"
    ],
    "wof:name":"Savulivka",
    "wof:placetype":"locality"
},
  "geometry": {"coordinates":[32.73185,49.92907],"type":"Point"}
}