{
  "type": "Feature",
  "properties": {
    "gn:admin1_code":"11.0",
    "gn:admin2_code":"704383",
    "gn:admin3_code":"11152922.0",
    "gn:asciiname":"Krasnaya Dolina",
    "gn:country_code":"UA",
    "gn:dem":33,
    "gn:elevation":"22.0",
    "gn:feature_class":"P",
    "gn:feature_code":"PPL",
    "gn:name":"Krasnaya Dolina",
    "gn:population":59,
    "gn:timezone":"Europe/Simferopol",
    "iso:country":"UA",
    "name:eng_x_preferred":[
        "Krasnaya Dolina"
    ],
    "name:rus_x_preferred":[
        "\u041a\u0440\u0430\u0441\u043d\u0430\u044f \u0414\u043e\u043b\u0438\u043d\u0430"
    ],
    "name:ukr_x_preferred":[
        "\u041a\u0440\u0430\u0441\u043d\u0430 \u0414\u043e\u043b\u0438\u043d\u0430"
    ],
    "wof:name":"Krasnaya Dolina",
    "wof:placetype":"locality",
    "wof:population":59
},
  "geometry": {"coordinates":[34.51397,45.43674],"type":"Point"}
}