{
  "type": "Feature",
  "properties": {
    "gn:admin1_code":"19.0",
    "gn:asciiname":"Mali Zahirtsi",
    "gn:country_code":"UA",
    "gn:dem":206,
    "gn:feature_class":"P",
    "gn:feature_code":"PPL",
    "gn:name":"Mali Zahirtsi",
    "gn:population":0,
    "gn:timezone":"Europe/Kiev",
    "iso:country":"UA",
    "name:ukr_x_preferred":[
        "Mali Zahirtsi"
    ],
    "name:ukr_x_variant":[
        "\u041c\u0430\u043b\u0456 \u0417\u0430\u0433\u0456\u0440\u0446\u0456"
    ],
    "name:und_x_variant":[
        "Malyye Zagortsy"
    ],
    "wof:name":"Mali Zahirtsi",
    "wof:placetype":"locality"
},
  "geometry": {"coordinates":[25.67216,50.36297],"type":"Point"}
}