{
  "type": "Feature",
  "properties": {
    "iso:country":"UA",
    "name:eng_x_preferred":[
        "Krasnoflotskoye"
    ],
    "name:rus_x_historical":[
        "\u041a\u0430\u0439\u043d\u0430\u0301\u0448"
    ],
    "name:rus_x_preferred":[
        "\u041a\u0430\u0439\u043d\u0430\u0301\u0448"
    ],
    "name:rus_x_variant":[
        "\u041a\u0440\u0430\u0441\u043d\u043e\u0444\u043b\u043e\u0442\u0441\u043a\u043e\u0435"
    ],
    "name:ukr_x_preferred":[
        "\u041a\u0440\u0430\u0441\u043d\u043e\u0444\u043b\u043e\u0442\u0441\u044c\u043a\u0435"
    ],
    "qs:a0":"\u0423\u043a\u0440\u0430\u0457\u043d\u0430",
    "qs:a1":"*\u041a\u0440\u0438\u043c",
    "qs:a1_alt":"Krym",
    "qs:a1r":"0",
    "qs:a2":"\u0421\u043e\u0432\u0454\u0442\u0441\u044c\u043a\u0438\u0439",
    "qs:a2_alt":"Soviets'kyi",
    "qs:adm0":"\u0423\u043a\u0440\u0430\u0457\u043d\u0430",
    "qs:la_lc":"*",
    "qs:level":"locality",
    "qs:loc":"\u041a\u0440\u0430\u0441\u043d\u043e\u0444\u043b\u043e\u0442\u0441\u044c\u043a\u0435",
    "qs:loc_alt":"Krasnoflots'ke",
    "qs:pop":0,
    "qs:type":"buffered point",
    "wof:name":"\u041a\u0440\u0430\u0441\u043d\u043e\u0444\u043b\u043e\u0442\u0441\u044c\u043a\u0435",
    "wof:placetype":"locality"
},
  "geometry": {"coordinates":[34.952894,45.307916],"type":"Point"}
}