{
  "type": "Feature",
  "properties": {
    "gn:admin1_code":"24.0",
    "gn:asciiname":"Rivne",
    "gn:country_code":"UA",
    "gn:dem":171,
    "gn:feature_class":"P",
    "gn:feature_code":"PPL",
    "gn:name":"Rivne",
    "gn:population":0,
    "gn:timezone":"Europe/Kiev",
    "iso:country":"UA",
    "name:ukr_x_preferred":[
        "\u0420\u0456\u0432\u043d\u0435"
    ],
    "name:und_x_variant":[
        "Rovno",
        "Ruvno",
        "R\u00f3wno",
        "Rivne"
    ],
    "wof:name":"Rivne",
    "wof:placetype":"locality"
},
  "geometry": {"coordinates":[23.81653,51.23566],"type":"Point"}
}