{
  "type": "Feature",
  "properties": {
    "gn:admin1_code":"17.0",
    "gn:asciiname":"Betsilovo",
    "gn:country_code":"UA",
    "gn:dem":44,
    "gn:feature_class":"P",
    "gn:feature_code":"PPL",
    "gn:name":"Betsilovo",
    "gn:population":0,
    "gn:timezone":"Europe/Kiev",
    "iso:country":"UA",
    "name:und_x_variant":[
        "Betsilivka",
        "Betsilovo"
    ],
    "wof:name":"Betsilovo",
    "wof:placetype":"locality"
},
  "geometry": {"coordinates":[30.25058,46.86785],"type":"Point"}
}