{
  "type": "Feature",
  "properties": {
    "gn:admin1_code":"6.0",
    "gn:asciiname":"Luhy",
    "gn:country_code":"UA",
    "gn:dem":475,
    "gn:feature_class":"P",
    "gn:feature_code":"PPL",
    "gn:name":"Luhy",
    "gn:population":0,
    "gn:timezone":"Europe/Kiev",
    "iso:country":"UA",
    "name:ukr_x_preferred":[
        "Luhy"
    ],
    "name:ukr_x_variant":[
        "\u041b\u0443\u0433\u0438"
    ],
    "name:und_x_variant":[
        "Luki",
        "Lukhy",
        "Lugi"
    ],
    "wof:name":"Luhy",
    "wof:placetype":"locality"
},
  "geometry": {"coordinates":[24.03059,48.84578],"type":"Point"}
}