{
  "type": "Feature",
  "properties": {
    "gn:admin1_code":"9.0",
    "gn:asciiname":"Leskovtsy",
    "gn:country_code":"UA",
    "gn:dem":195,
    "gn:feature_class":"P",
    "gn:feature_code":"PPL",
    "gn:name":"Leskovtsy",
    "gn:population":0,
    "gn:timezone":"Europe/Kiev",
    "iso:country":"UA",
    "name:und_x_variant":[
        "Lyaskovtsy",
        "Leskovtsy"
    ],
    "wof:name":"Leskovtsy",
    "wof:placetype":"locality"
},
  "geometry": {"coordinates":[26.40518,48.67461],"type":"Point"}
}