{
  "type": "Feature",
  "properties": {
    "iso:country":"UA",
    "name:ukr_x_preferred":[
        "Velyki Bubny"
    ],
    "name:ukr_x_variant":[
        "\u0412\u0435\u043b\u0438\u043a\u0456 \u0411\u0443\u0431\u043d\u0438"
    ],
    "name:unk_x_variant":[
        "Bol\u2019shiye Bubny"
    ],
    "qs:a0":"\u0423\u043a\u0440\u0430\u0457\u043d\u0430",
    "qs:a1":"*\u0421\u0443\u043c\u0441\u044c\u043a\u0430",
    "qs:a1_alt":"Sums'ka",
    "qs:a1r":"0",
    "qs:a2":"\u0420\u043e\u043c\u0435\u043d\u0441\u044c\u043a\u0438\u0439",
    "qs:a2_alt":"Romens'kyi",
    "qs:adm0":"\u0423\u043a\u0440\u0430\u0457\u043d\u0430",
    "qs:la_lc":"*",
    "qs:level":"locality",
    "qs:loc":"\u0412\u0435\u043b\u0438\u043a\u0456 \u0411\u0443\u0431\u043d\u0438",
    "qs:loc_alt":"Velyki Bubny",
    "qs:pop":0,
    "qs:type":"buffered point",
    "wof:name":"\u0412\u0435\u043b\u0438\u043a\u0456 \u0411\u0443\u0431\u043d\u0438",
    "wof:placetype":"locality"
},
  "geometry": {"coordinates":[33.279474,50.843209],"type":"Point"}
}