{
  "type": "Feature",
  "properties": {
    "gn:admin1_code":"18.0",
    "gn:asciiname":"Skybyntsi",
    "gn:country_code":"UA",
    "gn:dem":98,
    "gn:feature_class":"P",
    "gn:feature_code":"PPL",
    "gn:name":"Skybyntsi",
    "gn:population":0,
    "gn:timezone":"Europe/Kiev",
    "iso:country":"UA",
    "name:ukr_x_preferred":[
        "Skybyntsi"
    ],
    "name:ukr_x_variant":[
        "\u0421\u043a\u0438\u0431\u0438\u043d\u0446\u0456"
    ],
    "wof:name":"Skybyntsi",
    "wof:placetype":"locality"
},
  "geometry": {"coordinates":[32.69623,50.19158],"type":"Point"}
}