{
  "type": "Feature",
  "properties": {
    "gn:admin1_code":"5.0",
    "gn:asciiname":"Novoselydivka",
    "gn:country_code":"UA",
    "gn:dem":160,
    "gn:feature_class":"P",
    "gn:feature_code":"PPL",
    "gn:name":"Novoselydivka",
    "gn:population":0,
    "gn:timezone":"Europe/Kiev",
    "iso:country":"UA",
    "name:ukr_x_preferred":[
        "Novoselydivka"
    ],
    "name:ukr_x_variant":[
        "\u041d\u043e\u0432\u043e\u0441\u0435\u043b\u0438\u0434\u0456\u0432\u043a\u0430"
    ],
    "name:und_x_variant":[
        "Novo-Selidovskiy",
        "Novoselidovka"
    ],
    "wof:name":"Novoselydivka",
    "wof:placetype":"locality"
},
  "geometry": {"coordinates":[37.29288,48.05745],"type":"Point"}
}