{
  "type": "Feature",
  "properties": {
    "gn:admin1_code":"22.0",
    "gn:asciiname":"Zagortsy",
    "gn:country_code":"UA",
    "gn:dem":273,
    "gn:feature_class":"P",
    "gn:feature_code":"PPL",
    "gn:name":"Zagortsy",
    "gn:population":0,
    "gn:timezone":"Europe/Kiev",
    "iso:country":"UA",
    "name:und_x_variant":[
        "Zagortse",
        "Zagortsy"
    ],
    "wof:name":"Zagortsy",
    "wof:placetype":"locality"
},
  "geometry": {"coordinates":[26.11952,49.93824],"type":"Point"}
}