{
  "type": "Feature",
  "properties": {
    "gn:admin1_code":"7.0",
    "gn:asciiname":"Mayak",
    "gn:country_code":"UA",
    "gn:dem":87,
    "gn:feature_class":"P",
    "gn:feature_code":"PPL",
    "gn:name":"Mayak",
    "gn:population":0,
    "gn:timezone":"Europe/Kiev",
    "iso:country":"UA",
    "name:ukr_x_preferred":[
        "Mayak"
    ],
    "name:ukr_x_variant":[
        "\u041c\u0430\u044f\u043a"
    ],
    "name:und_x_variant":[
        "Gusarovka"
    ],
    "wof:name":"Mayak",
    "wof:placetype":"locality"
},
  "geometry": {"coordinates":[37.13808,48.9007],"type":"Point"}
}