{
  "type": "Feature",
  "properties": {
    "gn:admin1_code":"7.0",
    "gn:asciiname":"Mayak",
    "gn:country_code":"UA",
    "gn:dem":87,
    "gn:feature_class":"P",
    "gn:feature_code":"PPL",
    "gn:name":"Mayak",
    "gn:population":0,
    "gn:timezone":"Europe/Kiev",
    "iso:country":"UA",
    "name:bul_x_preferred":[
        "\u041c\u0430\u044f\u043a"
    ],
    "name:cat_x_preferred":[
        "Maiak"
    ],
    "name:ces_x_preferred":[
        "Majak"
    ],
    "name:dan_x_preferred":[
        "Majak"
    ],
    "name:eus_x_preferred":[
        "Maiak"
    ],
    "name:fin_x_preferred":[
        "Majak"
    ],
    "name:heb_x_preferred":[
        "\u05de\u05d0\u05d9\u05d0\u05e7"
    ],
    "name:hun_x_preferred":[
        "Majak"
    ],
    "name:ita_x_preferred":[
        "Majak"
    ],
    "name:jpn_x_preferred":[
        "\u30de\u30e4\u30fc\u30af\u6838\u6280\u8853\u65bd\u8a2d"
    ],
    "name:nld_x_preferred":[
        "Majak"
    ],
    "name:nno_x_preferred":[
        "Majak"
    ],
    "name:nor_x_preferred":[
        "Majak"
    ],
    "name:pol_x_preferred":[
        "Majak"
    ],
    "name:por_x_preferred":[
        "Mayak"
    ],
    "name:rus_x_preferred":[
        "\u041c\u0430\u044f\u043a"
    ],
    "name:slk_x_preferred":[
        "Majak"
    ],
    "name:spa_x_preferred":[
        "Mayak"
    ],
    "name:swe_x_preferred":[
        "Majak"
    ],
    "name:tur_x_preferred":[
        "Mayak"
    ],
    "name:ukr_x_preferred":[
        "Mayak"
    ],
    "name:ukr_x_variant":[
        "\u041c\u0430\u044f\u043a"
    ],
    "name:und_x_variant":[
        "Gusarovka"
    ],
    "wof:name":"Mayak",
    "wof:placetype":"locality"
},
  "geometry": {"coordinates":[37.13808,48.9007],"type":"Point"}
}