{
  "type": "Feature",
  "properties": {
    "gn:admin1_code":"16.0",
    "gn:asciiname":"Krasnopol'",
    "gn:country_code":"UA",
    "gn:dem":81,
    "gn:feature_class":"P",
    "gn:feature_code":"PPL",
    "gn:name":"Krasnopol\u2019",
    "gn:population":0,
    "gn:timezone":"Europe/Kiev",
    "iso:country":"UA",
    "name:und_x_variant":[
        "Bol\u2019shoye Kolendovo",
        "Krasnopol\u2019"
    ],
    "wof:name":"Krasnopol'",
    "wof:placetype":"locality"
},
  "geometry": {"coordinates":[30.4375,47.74679],"type":"Point"}
}