{
  "type": "Feature",
  "properties": {
    "gn:admin1_code":"21.0",
    "gn:asciiname":"Brusky",
    "gn:country_code":"UA",
    "gn:dem":195,
    "gn:feature_class":"P",
    "gn:feature_code":"PPL",
    "gn:name":"Brusky",
    "gn:population":0,
    "gn:timezone":"Europe/Kiev",
    "iso:country":"UA",
    "name:eng_x_preferred":[
        "Bruski"
    ],
    "name:rus_x_preferred":[
        "\u0411\u0440\u0443\u0441\u043a\u0438"
    ],
    "name:ukr_x_preferred":[
        "Brusky"
    ],
    "name:ukr_x_variant":[
        "\u0411\u0440\u0443\u0441\u043a\u0438"
    ],
    "name:und_x_variant":[
        "Bruski"
    ],
    "wof:name":"Brusky",
    "wof:placetype":"locality"
},
  "geometry": {"coordinates":[34.19927,51.40563],"type":"Point"}
}