{
  "type": "Feature",
  "properties": {
    "iso:country":"UA",
    "name:ces_x_preferred":[
        "Izvaryne"
    ],
    "name:crh_x_preferred":[
        "\u0130zvar\u0131ne"
    ],
    "name:deu_x_preferred":[
        "Iswaryne"
    ],
    "name:ell_x_preferred":[
        "\u0399\u03b6\u03b2\u03b1\u03c1\u03cd\u03bd\u03b5"
    ],
    "name:eng_x_preferred":[
        "Izvaryne"
    ],
    "name:est_x_preferred":[
        "Izvar\u00f5ne"
    ],
    "name:hye_x_preferred":[
        "\u053b\u0566\u057e\u0561\u0580\u056b\u0576\u0578"
    ],
    "name:lav_x_preferred":[
        "Izvarine"
    ],
    "name:ron_x_preferred":[
        "Izvar\u00eene"
    ],
    "name:rus_x_preferred":[
        "\u0418\u0437\u0432\u0430\u0440\u0438\u043d\u043e"
    ],
    "name:spa_x_preferred":[
        "Izvarine"
    ],
    "name:ukr_x_preferred":[
        "\u0406\u0437\u0432\u0430\u0440\u0438\u043d\u0435"
    ],
    "name:zho_x_preferred":[
        "\u4f0a\u8332\u74e6\u91cc\u6d85"
    ],
    "qs:a0":"\u0423\u043a\u0440\u0430\u0457\u043d\u0430",
    "qs:a1":"*\u041b\u0443\u0433\u0430\u043d\u0441\u044c\u043a\u0430",
    "qs:a1_alt":"Luhans'ka",
    "qs:a1r":"0",
    "qs:a2":"\u041a\u0440\u0430\u0441\u043d\u043e\u0434\u043e\u043d\u0441\u044c\u043a\u0438\u0439",
    "qs:a2_alt":"Krasnodons'kyi",
    "qs:adm0":"\u0423\u043a\u0440\u0430\u0457\u043d\u0430",
    "qs:la_lc":"*",
    "qs:level":"locality",
    "qs:loc":"\u0406\u0437\u0432\u0430\u0440\u0438\u043d\u0435",
    "qs:loc_alt":"Izvaryne",
    "qs:pop":0,
    "qs:type":"buffered point",
    "wd:wordcount":476,
    "wof:name":"\u0406\u0437\u0432\u0430\u0440\u0438\u043d\u0435",
    "wof:placetype":"locality"
},
  "geometry": {"coordinates":[39.897471,48.287789],"type":"Point"}
}