{
  "type": "Feature",
  "properties": {
    "gn:admin1_code":"4.0",
    "gn:asciiname":"Kudashivka",
    "gn:country_code":"UA",
    "gn:dem":150,
    "gn:feature_class":"P",
    "gn:feature_code":"PPL",
    "gn:name":"Kudashivka",
    "gn:population":0,
    "gn:timezone":"Europe/Kiev",
    "iso:country":"UA",
    "name:rus_x_preferred":[
        "\u041a\u0443\u0434\u0430\u0448\u0435\u0432\u043a\u0430"
    ],
    "name:ukr_x_preferred":[
        "Kudashivka"
    ],
    "name:ukr_x_variant":[
        "\u041a\u0443\u0434\u0430\u0448\u0456\u0432\u043a\u0430"
    ],
    "name:und_x_variant":[
        "Kudashyevka"
    ],
    "wof:name":"Kudashivka",
    "wof:placetype":"locality"
},
  "geometry": {"coordinates":[34.02326,48.2774],"type":"Point"}
}