{
  "type": "Feature",
  "properties": {
    "gn:admin1_code":"4.0",
    "gn:asciiname":"Rakove",
    "gn:country_code":"UA",
    "gn:dem":71,
    "gn:feature_class":"P",
    "gn:feature_code":"PPL",
    "gn:name":"Rakove",
    "gn:population":0,
    "gn:timezone":"Europe/Kiev",
    "iso:country":"UA",
    "name:ukr_x_preferred":[
        "Rakove"
    ],
    "name:ukr_x_variant":[
        "\u0420\u0430\u043a\u043e\u0432\u0435"
    ],
    "name:und_x_variant":[
        "Rakovo"
    ],
    "wof:name":"Rakove",
    "wof:placetype":"locality"
},
  "geometry": {"coordinates":[35.27583,48.30286],"type":"Point"}
}