{
  "type": "Feature",
  "properties": {
    "gn:admin1_code":"10.0",
    "gn:asciiname":"Budenovka",
    "gn:country_code":"UA",
    "gn:dem":148,
    "gn:feature_class":"P",
    "gn:feature_code":"PPL",
    "gn:name":"Budenovka",
    "gn:population":0,
    "gn:timezone":"Europe/Kiev",
    "iso:country":"UA",
    "name:und_x_variant":[
        "Pep\u2019yampol\u2019",
        "Budenovka",
        "Bud\u00ebnnovka"
    ],
    "wof:name":"Budenovka",
    "wof:placetype":"locality"
},
  "geometry": {"coordinates":[29.91667,48.38333],"type":"Point"}
}