{
  "type": "Feature",
  "properties": {
    "gn:admin1_code":"10.0",
    "gn:asciiname":"Budenovka",
    "gn:country_code":"UA",
    "gn:dem":148,
    "gn:feature_class":"P",
    "gn:feature_code":"PPL",
    "gn:name":"Budenovka",
    "gn:population":0,
    "gn:timezone":"Europe/Kiev",
    "iso:country":"UA",
    "name:cat_x_preferred":[
        "Budi\u00f3novka"
    ],
    "name:ces_x_preferred":[
        "Bu\u010fonovka"
    ],
    "name:deu_x_preferred":[
        "Budjonowka"
    ],
    "name:est_x_preferred":[
        "Budjonn\u00f5i m\u00fcts"
    ],
    "name:fin_x_preferred":[
        "Budjonnovka"
    ],
    "name:fra_x_preferred":[
        "Boudionovka"
    ],
    "name:heb_x_preferred":[
        "\u05d1\u05d5\u05d3\u05d9\u05d5\u05e0\u05d5\u05d1\u05e7\u05d4"
    ],
    "name:ita_x_preferred":[
        "Bud\u00ebnovka"
    ],
    "name:lit_x_preferred":[
        "Budionovka"
    ],
    "name:nor_x_preferred":[
        "Budjonovka"
    ],
    "name:pol_x_preferred":[
        "Budionowka"
    ],
    "name:por_x_preferred":[
        "Budi\u00f3novka"
    ],
    "name:rus_x_preferred":[
        "\u0411\u0443\u0434\u0451\u043d\u043e\u0432\u043a\u0430"
    ],
    "name:spa_x_preferred":[
        "Budi\u00f3novka"
    ],
    "name:swe_x_preferred":[
        "Budenovka"
    ],
    "name:tur_x_preferred":[
        "Budenovka"
    ],
    "name:ukr_x_preferred":[
        "\u0411\u0443\u0434\u044c\u043e\u043d\u0456\u0432\u043a\u0430"
    ],
    "name:und_x_variant":[
        "Pep\u2019yampol\u2019",
        "Budenovka",
        "Bud\u00ebnnovka"
    ],
    "name:zho_x_preferred":[
        "\u5e03\u743c\u5c3c\u5e3d"
    ],
    "wof:name":"Budenovka",
    "wof:placetype":"locality"
},
  "geometry": {"coordinates":[29.91667,48.38333],"type":"Point"}
}