{
  "type": "Feature",
  "properties": {
    "gn:admin1_code":"20.0",
    "gn:admin2_code":"712927",
    "gn:admin3_code":"11153385.0",
    "gn:asciiname":"Sakharnaya Golovka",
    "gn:country_code":"UA",
    "gn:dem":44,
    "gn:feature_class":"P",
    "gn:feature_code":"PPL",
    "gn:name":"Sakharnaya Golovka",
    "gn:population":4146,
    "gn:timezone":"Europe/Simferopol",
    "iso:country":"UA",
    "name:eng_x_preferred":[
        "Sakharnaya Golovka"
    ],
    "name:rus_x_preferred":[
        "\u0421\u0430\u0445\u0430\u0440\u043d\u0430\u044f \u0413\u043e\u043b\u043e\u0432\u043a\u0430"
    ],
    "name:ukr_x_preferred":[
        "\u0421\u0430\u0445\u0430\u0440\u043d\u0430 \u0413\u043e\u043b\u043e\u0432\u043a\u0430"
    ],
    "wof:name":"Sakharnaya Golovka",
    "wof:placetype":"locality",
    "wof:population":4146
},
  "geometry": {"coordinates":[33.64383,44.58362],"type":"Point"}
}