{
  "type": "Feature",
  "properties": {
    "gn:admin1_code":"21.0",
    "gn:asciiname":"Zemlyanka",
    "gn:country_code":"UA",
    "gn:dem":157,
    "gn:feature_class":"P",
    "gn:feature_code":"PPL",
    "gn:name":"Zemlyanka",
    "gn:population":0,
    "gn:timezone":"Europe/Kiev",
    "iso:country":"UA",
    "name:ukr_x_preferred":[
        "Zemlyanka"
    ],
    "name:ukr_x_variant":[
        "\u0417\u0435\u043c\u043b\u044f\u043d\u043a\u0430"
    ],
    "wof:name":"Zemlyanka",
    "wof:placetype":"locality"
},
  "geometry": {"coordinates":[33.54551,51.18133],"type":"Point"}
}