{
  "type": "Feature",
  "properties": {
    "gn:admin1_code":"21.0",
    "gn:asciiname":"Polohy",
    "gn:country_code":"UA",
    "gn:dem":115,
    "gn:feature_class":"P",
    "gn:feature_code":"PPL",
    "gn:name":"Polohy",
    "gn:population":0,
    "gn:timezone":"Europe/Kiev",
    "iso:country":"UA",
    "name:ara_x_preferred":[
        "\u0628\u0648\u0644\u0648\u0647\u064a"
    ],
    "name:azb_x_preferred":[
        "\u067e\u0648\u0644\u0648\u0647\u06cc"
    ],
    "name:bel_x_preferred":[
        "\u041f\u0430\u043b\u043e\u0433\u044b"
    ],
    "name:bul_x_preferred":[
        "\u041f\u043e\u043b\u043e\u0433\u0438"
    ],
    "name:ceb_x_preferred":[
        "Polohy"
    ],
    "name:ces_x_preferred":[
        "Polohy"
    ],
    "name:crh_x_preferred":[
        "Polog\u0131"
    ],
    "name:deu_x_preferred":[
        "Polohy"
    ],
    "name:eng_x_preferred":[
        "Pologiye"
    ],
    "name:fas_x_preferred":[
        "\u067e\u0648\u0644\u0648\u0647\u06cc"
    ],
    "name:fra_x_preferred":[
        "Polohy"
    ],
    "name:heb_x_preferred":[
        "\u05e4\u05d5\u05dc\u05d5\u05d4\u05d9"
    ],
    "name:hsb_x_preferred":[
        "Polohy"
    ],
    "name:hye_x_preferred":[
        "\u054a\u0578\u056c\u0578\u0563\u056b"
    ],
    "name:ita_x_preferred":[
        "Polohy"
    ],
    "name:kat_x_preferred":[
        "\u10de\u10dd\u10da\u10dd\u10d2\u10d8"
    ],
    "name:nno_x_preferred":[
        "Polohy"
    ],
    "name:pol_x_preferred":[
        "Po\u0142ohy"
    ],
    "name:ron_x_preferred":[
        "Poloh\u00ee"
    ],
    "name:rus_x_preferred":[
        "\u041f\u043e\u043b\u043e\u0433\u0438"
    ],
    "name:srp_x_preferred":[
        "\u041f\u043e\u043b\u043e\u0433\u0438"
    ],
    "name:ukr_x_preferred":[
        "Polohy"
    ],
    "name:ukr_x_variant":[
        "\u041f\u043e\u043b\u043e\u0433\u0438"
    ],
    "name:und_x_variant":[
        "Pologi"
    ],
    "name:vie_x_preferred":[
        "Polohy"
    ],
    "name:zho_x_preferred":[
        "\u6ce2\u6d1b\u5409"
    ],
    "wof:name":"Polohy",
    "wof:placetype":"locality"
},
  "geometry": {"coordinates":[34.99579,50.33436],"type":"Point"}
}