{
  "type": "Feature",
  "properties": {
    "gn:admin1_code":"21.0",
    "gn:asciiname":"Polohy",
    "gn:country_code":"UA",
    "gn:dem":115,
    "gn:feature_class":"P",
    "gn:feature_code":"PPL",
    "gn:name":"Polohy",
    "gn:population":0,
    "gn:timezone":"Europe/Kiev",
    "iso:country":"UA",
    "name:eng_x_preferred":[
        "Pologiye"
    ],
    "name:rus_x_preferred":[
        "\u041f\u043e\u043b\u043e\u0433\u0438"
    ],
    "name:ukr_x_preferred":[
        "Polohy"
    ],
    "name:ukr_x_variant":[
        "\u041f\u043e\u043b\u043e\u0433\u0438"
    ],
    "name:und_x_variant":[
        "Pologiye",
        "Pologi"
    ],
    "wof:name":"Polohy",
    "wof:placetype":"locality"
},
  "geometry": {"coordinates":[34.99579,50.33436],"type":"Point"}
}