{
  "type": "Feature",
  "properties": {
    "gn:admin1_code":"16.0",
    "gn:asciiname":"Ul'yanovka",
    "gn:country_code":"UA",
    "gn:dem":85,
    "gn:feature_class":"P",
    "gn:feature_code":"PPL",
    "gn:name":"Ul\u2019yanovka",
    "gn:population":0,
    "gn:timezone":"Europe/Kiev",
    "iso:country":"UA",
    "wof:name":"Ul'yanovka",
    "wof:placetype":"locality"
},
  "geometry": {"coordinates":[32.03211,47.28592],"type":"Point"}
}