{
  "type": "Feature",
  "properties": {
    "gn:admin1_code":"27.0",
    "gn:asciiname":"Maydan-Kopyshchens'kyy",
    "gn:country_code":"UA",
    "gn:dem":155,
    "gn:feature_class":"P",
    "gn:feature_code":"PPL",
    "gn:name":"Maydan-Kopyshchens\u2019kyy",
    "gn:population":0,
    "gn:timezone":"Europe/Kiev",
    "iso:country":"UA",
    "name:ukr_x_preferred":[
        "Maydan-Kopyshchens\u2019kyy"
    ],
    "name:ukr_x_variant":[
        "\u041c\u0430\u0439\u0434\u0430\u043d-\u041a\u043e\u043f\u0438\u0449\u0435\u043d\u0441\u044c\u043a\u0438\u0439"
    ],
    "name:und_x_variant":[
        "Khutora Maydanskiye",
        "Maydan Kopishchenskiy"
    ],
    "wof:name":"Maydan-Kopyshchens'kyy",
    "wof:placetype":"locality"
},
  "geometry": {"coordinates":[27.85803,51.53069],"type":"Point"}
}