{
  "type": "Feature",
  "properties": {
    "gn:gn_country":"UA",
    "gn:gn_fcode":"PPL",
    "gn:gn_pop":12069,
    "gn:population":12069,
    "iso:country":"UA",
    "name:ara_x_preferred":[
        "\u0628\u0648\u0631\u0648\u062f\u064a\u0627\u0646\u0643\u0627\u060c \u062c\u0648\u0632\u0646\u0648-\u0628\u0627\u0646\u0627\u062a"
    ],
    "name:ara_x_variant":[
        "\u0628\u0648\u0631\u0648\u062f\u064a\u0627\u0646\u0643\u0627"
    ],
    "name:bel_x_preferred":[
        "\u0411\u0430\u0440\u0430\u0434\u0437\u044f\u043d\u043a\u0430"
    ],
    "name:ceb_x_preferred":[
        "Borodyanka"
    ],
    "name:crh_x_preferred":[
        "Borod\u00e2nka"
    ],
    "name:deu_x_preferred":[
        "Borodjanka"
    ],
    "name:eng_x_preferred":[
        "Borodianka"
    ],
    "name:fin_x_preferred":[
        "Borodjanka"
    ],
    "name:ita_x_preferred":[
        "Borodjanka"
    ],
    "name:pol_x_preferred":[
        "Borodzianka"
    ],
    "name:ron_x_preferred":[
        "Borodeanka"
    ],
    "name:rus_x_preferred":[
        "\u0411\u043e\u0440\u043e\u0434\u044f\u043d\u043a\u0430"
    ],
    "name:sah_x_preferred":[
        "\u0411\u043e\u0440\u043e\u0434\u044f\u043d\u043a\u0430"
    ],
    "name:sco_x_preferred":[
        "Borodianka"
    ],
    "name:ukr_x_preferred":[
        "\u0411\u043e\u0440\u043e\u0434\u044f\u043d\u043a\u0430"
    ],
    "name:unk_x_variant":[
        "Borodjanka"
    ],
    "name:zho_x_preferred":[
        "\u535a\u7f85\u6c5f\u5361"
    ],
    "qs_pg:aaroncc":"UA",
    "qs_pg:gn_country":"UA",
    "qs_pg:gn_fcode":"PPL",
    "qs_pg:gn_pop":12069,
    "qs_pg:name":"Borodyanka",
    "qs_pg:photos_9r":0,
    "qs_pg:photos_sr":0,
    "qs_pg:pop_sr":6,
    "qs_pg:qs_pg_placetype":"locality",
    "wof:name":"Borodyanka",
    "wof:placetype":"locality",
    "wof:population":12069
},
  "geometry": {"coordinates":[29.9201,50.64484],"type":"Point"}
}