{
  "type": "Feature",
  "properties": {
    "gn:admin1_code":"13.0",
    "gn:asciiname":"Buda-Vovchkivs'ka",
    "gn:country_code":"UA",
    "gn:dem":138,
    "gn:feature_class":"P",
    "gn:feature_code":"PPL",
    "gn:name":"Buda-Vovchkivs\u2019ka",
    "gn:population":0,
    "gn:timezone":"Europe/Kiev",
    "iso:country":"UA",
    "name:ukr_x_preferred":[
        "Buda-Vovchkivs\u2019ka"
    ],
    "name:ukr_x_variant":[
        "\u0411\u0443\u0434\u0430-\u0412\u043e\u0432\u0447\u043a\u0456\u0432\u0441\u044c\u043a\u0430"
    ],
    "name:und_x_variant":[
        "Buda-Volchkovskaya"
    ],
    "wof:name":"Buda-Vovchkivs'ka",
    "wof:placetype":"locality"
},
  "geometry": {"coordinates":[29.6052,51.13591],"type":"Point"}
}