{
  "type": "Feature",
  "properties": {
    "gn:admin1_code":"5.0",
    "gn:asciiname":"Sosnove",
    "gn:country_code":"UA",
    "gn:dem":107,
    "gn:feature_class":"P",
    "gn:feature_code":"PPL",
    "gn:name":"Sosnove",
    "gn:population":0,
    "gn:timezone":"Europe/Kiev",
    "iso:country":"UA",
    "name:ukr_x_preferred":[
        "Sosnove"
    ],
    "name:und_x_variant":[
        "Svyatogorskaya"
    ],
    "wof:name":"Sosnove",
    "wof:placetype":"locality"
},
  "geometry": {"coordinates":[37.55333,49.07417],"type":"Point"}
}