{
  "type": "Feature",
  "properties": {
    "gn:admin1_code":"5.0",
    "gn:asciiname":"Sosnove",
    "gn:country_code":"UA",
    "gn:dem":107,
    "gn:feature_class":"P",
    "gn:feature_code":"PPL",
    "gn:name":"Sosnove",
    "gn:population":0,
    "gn:timezone":"Europe/Kiev",
    "iso:country":"UA",
    "name:bel_x_preferred":[
        "\u0421\u0430\u0441\u043d\u043e\u0432\u044d"
    ],
    "name:crh_x_preferred":[
        "Sosnove"
    ],
    "name:deu_x_preferred":[
        "Sosnowe"
    ],
    "name:fra_x_preferred":[
        "Sosnove"
    ],
    "name:heb_x_preferred":[
        "\u05e1\u05d5\u05e1\u05e0\u05d5\u05d1\u05d4"
    ],
    "name:pol_x_preferred":[
        "Sosnowe"
    ],
    "name:ron_x_preferred":[
        "Sosnove"
    ],
    "name:rus_x_preferred":[
        "\u0421\u043e\u0441\u043d\u043e\u0432\u043e\u0435"
    ],
    "name:ukr_x_preferred":[
        "Sosnove"
    ],
    "name:ukr_x_variant":[
        "\u0421\u043e\u0441\u043d\u043e\u0432\u0435"
    ],
    "name:und_x_variant":[
        "Svyatogorskaya"
    ],
    "name:zho_x_preferred":[
        "\u7d22\u65af\u8afe\u97cb"
    ],
    "wof:name":"Sosnove",
    "wof:placetype":"locality"
},
  "geometry": {"coordinates":[37.55333,49.07417],"type":"Point"}
}