{
  "type": "Feature",
  "properties": {
    "gn:admin1_code":"10.0",
    "gn:asciiname":"Lyubivka",
    "gn:country_code":"UA",
    "gn:dem":92,
    "gn:feature_class":"P",
    "gn:feature_code":"PPL",
    "gn:name":"Lyubivka",
    "gn:population":0,
    "gn:timezone":"Europe/Kiev",
    "iso:country":"UA",
    "name:ukr_x_preferred":[
        "Lyubivka"
    ],
    "name:ukr_x_variant":[
        "\u041b\u044e\u0431\u0456\u0432\u043a\u0430"
    ],
    "wof:name":"Lyubivka",
    "wof:placetype":"locality"
},
  "geometry": {"coordinates":[33.48178,48.90978],"type":"Point"}
}