{
  "type": "Feature",
  "properties": {
    "gn:admin1_code":"7.0",
    "gn:asciiname":"Pil'na",
    "gn:country_code":"UA",
    "gn:dem":120,
    "gn:feature_class":"P",
    "gn:feature_code":"PPL",
    "gn:name":"Pil\u2019na",
    "gn:population":0,
    "gn:timezone":"Europe/Kiev",
    "iso:country":"UA",
    "name:rus_x_preferred":[
        "\u041f\u043e\u043b\u044c\u043d\u0430\u044f"
    ],
    "name:ukr_x_preferred":[
        "\u041f\u0456\u043b\u044c\u043d\u0430"
    ],
    "name:und_x_variant":[
        "Pol\u2019naya",
        "Pil\u2019na"
    ],
    "wof:name":"Pil'na",
    "wof:placetype":"locality"
},
  "geometry": {"coordinates":[36.98454,50.16213],"type":"Point"}
}