{
  "type": "Feature",
  "properties": {
    "gn:admin1_code":"22.0",
    "gn:asciiname":"Nushche",
    "gn:country_code":"UA",
    "gn:dem":377,
    "gn:feature_class":"P",
    "gn:feature_code":"PPL",
    "gn:name":"Nushche",
    "gn:population":0,
    "gn:timezone":"Europe/Kiev",
    "iso:country":"UA",
    "wof:name":"Nushche",
    "wof:placetype":"locality"
},
  "geometry": {"coordinates":[25.11336,49.80601],"type":"Point"}
}