{
  "type": "Feature",
  "properties": {
    "gn:admin1_code":"27.0",
    "gn:asciiname":"Borok",
    "gn:country_code":"UA",
    "gn:dem":179,
    "gn:feature_class":"P",
    "gn:feature_code":"PPL",
    "gn:name":"Borok",
    "gn:population":0,
    "gn:timezone":"Europe/Kiev",
    "iso:country":"UA",
    "name:ukr_x_preferred":[
        "Borok"
    ],
    "name:ukr_x_variant":[
        "\u0411\u043e\u0440\u043e\u043a"
    ],
    "wof:name":"Borok",
    "wof:placetype":"locality"
},
  "geometry": {"coordinates":[29.21263,50.3078],"type":"Point"}
}