{
  "type": "Feature",
  "properties": {
    "gn:admin1_code":"4.0",
    "gn:asciiname":"Troyits'ke",
    "gn:country_code":"UA",
    "gn:dem":81,
    "gn:feature_class":"P",
    "gn:feature_code":"PPL",
    "gn:name":"Troyits\u2019ke",
    "gn:population":0,
    "gn:timezone":"Europe/Kiev",
    "iso:country":"UA",
    "name:eng_x_preferred":[
        "Troitskoye"
    ],
    "name:rus_x_preferred":[
        "\u0422\u0440\u043e\u0438\u0446\u043a\u043e\u0435"
    ],
    "name:ukr_x_preferred":[
        "Troyits\u2019ke"
    ],
    "name:ukr_x_variant":[
        "\u0422\u0440\u043e\u0457\u0446\u044c\u043a\u0435"
    ],
    "name:und_x_variant":[
        "Troitskoye"
    ],
    "wof:name":"Troyits'ke",
    "wof:placetype":"locality"
},
  "geometry": {"coordinates":[36.53594,48.45257],"type":"Point"}
}