{
  "type": "Feature",
  "properties": {
    "gn:admin1_code":"13.0",
    "gn:asciiname":"Stovpne",
    "gn:country_code":"UA",
    "gn:dem":177,
    "gn:feature_class":"P",
    "gn:feature_code":"PPL",
    "gn:name":"Stovpne",
    "gn:population":0,
    "gn:timezone":"Europe/Kiev",
    "iso:country":"UA",
    "name:ukr_x_preferred":[
        "Stovpne"
    ],
    "name:ukr_x_variant":[
        "\u0421\u0442\u043e\u0432\u043f\u043d\u0435"
    ],
    "wof:name":"Stovpne",
    "wof:placetype":"locality"
},
  "geometry": {"coordinates":[29.51712,51.07479],"type":"Point"}
}