{
  "type": "Feature",
  "properties": {
    "gn:gn_country":"UA",
    "gn:gn_fcode":"PPL",
    "gn:gn_pop":15252,
    "gn:population":15252,
    "iso:country":"UA",
    "name:bel_x_preferred":[
        "\u0420\u0430\u0434\u0430\u043c\u044b\u0448\u043b\u044c"
    ],
    "name:ces_x_preferred":[
        "Radomy\u0161l"
    ],
    "name:deu_x_preferred":[
        "Radomyschl"
    ],
    "name:eng_x_preferred":[
        "Radomyshl"
    ],
    "name:fas_x_preferred":[
        "\u0631\u0627\u062f\u0648\u0645\u06cc\u0634\u0644"
    ],
    "name:fra_x_preferred":[
        "Radomychl"
    ],
    "name:heb_x_preferred":[
        "\u05e8\u05d3\u05d5\u05de\u05d9\u05e9\u05dc"
    ],
    "name:hsb_x_preferred":[
        "Radomy\u0161l"
    ],
    "name:hye_x_preferred":[
        "\u054c\u0561\u0564\u0578\u0574\u056b\u0577\u056c"
    ],
    "name:ita_x_preferred":[
        "Radomy\u0161l'"
    ],
    "name:kat_x_preferred":[
        "\u10e0\u10d0\u10d3\u10dd\u10db\u10d8\u10e8\u10da\u10d8"
    ],
    "name:nno_x_preferred":[
        "Radomysjl"
    ],
    "name:pol_x_preferred":[
        "Radomy\u015bl"
    ],
    "name:ron_x_preferred":[
        "Radom\u00ee\u0219l"
    ],
    "name:rus_x_preferred":[
        "\u0420\u0430\u0434\u043e\u043c\u044b\u0448\u043b\u044c"
    ],
    "name:sah_x_preferred":[
        "\u0420\u0430\u0434\u043e\u043c\u044b\u0448\u043b\u044c"
    ],
    "name:sco_x_preferred":[
        "Radomyshl"
    ],
    "name:tat_x_preferred":[
        "\u0420\u0430\u0434\u043e\u043c\u044b\u0448\u043b\u044c"
    ],
    "name:ukr_x_preferred":[
        "\u0420\u0430\u0434\u043e\u043c\u0438\u0448\u043b\u044c"
    ],
    "name:unk_x_variant":[
        "Radomyshl\u2019"
    ],
    "name:vie_x_preferred":[
        "Radomyshl"
    ],
    "name:zho_x_preferred":[
        "\u62c9\u591a\u6885\u4ec0\u5229"
    ],
    "qs_pg:aaroncc":"UA",
    "qs_pg:gn_country":"UA",
    "qs_pg:gn_fcode":"PPL",
    "qs_pg:gn_pop":15252,
    "qs_pg:name":"Radomishl",
    "qs_pg:name_adm0":"Ukraine",
    "qs_pg:name_adm1":"Zhytomyrs\u00b4ka Oblast\u00b4",
    "qs_pg:photos_9k":1,
    "qs_pg:photos_9r":2,
    "qs_pg:photos_all":74,
    "qs_pg:photos_sr":0,
    "qs_pg:pop_sr":6,
    "qs_pg:qs_pg_placetype":"locality",
    "qs_pg:qs_pg_placetype_gp":"Town",
    "qs_pg:woe_adm0":23424976,
    "woe:adm0_id":23424976,
    "woe:name_adm0":"Ukraine",
    "woe:name_adm1":"Zhytomyrs\u00b4ka Oblast\u00b4",
    "woe:placetype":"Town",
    "wof:name":"Radomishl",
    "wof:placetype":"locality",
    "wof:population":15252
},
  "geometry": {"coordinates":[29.22911,50.49613],"type":"Point"}
}