{
  "type": "Feature",
  "properties": {
    "gn:admin1_code":"7.0",
    "gn:asciiname":"Lozova Druha",
    "gn:country_code":"UA",
    "gn:dem":122,
    "gn:feature_class":"P",
    "gn:feature_code":"PPL",
    "gn:name":"Lozova Druha",
    "gn:population":0,
    "gn:timezone":"Europe/Kiev",
    "iso:country":"UA",
    "name:ukr_x_preferred":[
        "Lozova Druha"
    ],
    "name:ukr_x_variant":[
        "\u041b\u043e\u0437\u043e\u0432\u0430 \u0414\u0440\u0443\u0433\u0430"
    ],
    "name:und_x_variant":[
        "Lozovaya Vtoraya"
    ],
    "wof:name":"Lozova Druha",
    "wof:placetype":"locality"
},
  "geometry": {"coordinates":[37.54942,49.86232],"type":"Point"}
}