{
  "type": "Feature",
  "properties": {
    "gn:admin1_code":"9.0",
    "gn:asciiname":"Krachki",
    "gn:country_code":"UA",
    "gn:dem":300,
    "gn:feature_class":"P",
    "gn:feature_code":"PPL",
    "gn:name":"Krachki",
    "gn:population":0,
    "gn:timezone":"Europe/Kiev",
    "iso:country":"UA",
    "wof:name":"Krachki",
    "wof:placetype":"locality"
},
  "geometry": {"coordinates":[26.68378,49.5442],"type":"Point"}
}