{
  "type": "Feature",
  "properties": {
    "gn:admin1_code":"5.0",
    "gn:admin2_code":"689154",
    "gn:asciiname":"Kelerivka",
    "gn:country_code":"UA",
    "gn:dem":119,
    "gn:feature_class":"P",
    "gn:feature_code":"PPL",
    "gn:name":"Kelerivka",
    "gn:population":0,
    "gn:timezone":"Europe/Kiev",
    "iso:country":"UA",
    "name:hye_x_historical":[
        "\u053f\u056b\u0580\u0578\u057e\u0578"
    ],
    "name:hye_x_preferred":[
        "\u053f\u056b\u0580\u0578\u057e\u0578"
    ],
    "name:rus_x_historical":[
        "Kirovo"
    ],
    "name:rus_x_preferred":[
        "Kellerovka"
    ],
    "name:rus_x_variant":[
        "Kirovo",
        "\u041a\u0435\u043b\u043b\u0435\u0440\u043e\u0432\u043a\u0430"
    ],
    "name:ukr_x_historical":[
        "Kirove",
        "\u041a\u0456\u0440\u043e\u0432\u0435"
    ],
    "name:ukr_x_preferred":[
        "\u041a\u0435\u043b\u0435\u0440\u0456\u0432\u043a\u0430"
    ],
    "name:ukr_x_variant":[
        "Kirove",
        "\u041a\u0456\u0440\u043e\u0432\u0435",
        "Kelerivka"
    ],
    "wof:name":"Kelerivka",
    "wof:placetype":"locality"
},
  "geometry": {"coordinates":[37.61195,47.35197],"type":"Point"}
}