{
  "type": "Feature",
  "properties": {
    "iso:country":"UA",
    "name:ukr_x_preferred":[
        "Veresy"
    ],
    "name:ukr_x_variant":[
        "\u0412\u0435\u0440\u0435\u0441\u0438"
    ],
    "qs:a0":"\u0423\u043a\u0440\u0430\u0457\u043d\u0430",
    "qs:a1":"*\u0416\u0438\u0442\u043e\u043c\u0438\u0440\u0441\u044c\u043a\u0430",
    "qs:a1_alt":"Zhytomyrs'ka",
    "qs:a1r":"0",
    "qs:a2":"\u0416\u0438\u0442\u043e\u043c\u0438\u0440\u0441\u044c\u043a\u0438\u0439",
    "qs:a2_alt":"Zhytomyrs'kyi",
    "qs:adm0":"\u0423\u043a\u0440\u0430\u0457\u043d\u0430",
    "qs:la_lc":"*",
    "qs:level":"locality",
    "qs:loc":"\u0412\u0435\u0440\u0435\u0441\u0438",
    "qs:loc_alt":"Veresy",
    "qs:pop":0,
    "qs:type":"buffered point",
    "wof:name":"\u0412\u0435\u0440\u0435\u0441\u0438",
    "wof:placetype":"locality"
},
  "geometry": {"coordinates":[28.761298,50.337694],"type":"Point"}
}