{
  "type": "Feature",
  "properties": {
    "gn:admin1_code":"26.0",
    "gn:asciiname":"Yevreyskaya Koloniya",
    "gn:country_code":"UA",
    "gn:dem":155,
    "gn:feature_class":"P",
    "gn:feature_code":"PPL",
    "gn:name":"Yevreyskaya Koloniya",
    "gn:population":0,
    "gn:timezone":"Europe/Zaporozhye",
    "iso:country":"UA",
    "name:und_x_variant":[
        "Vol\u2019nyy"
    ],
    "wof:name":"Yevreyskaya Koloniya",
    "wof:placetype":"locality"
},
  "geometry": {"coordinates":[36.61667,47.63333],"type":"Point"}
}