{
  "type": "Feature",
  "properties": {
    "gn:population":3983,
    "iso:country":"UA",
    "name:bel_x_variant":[
        "\u0420\u0430\u0436\u043d\u044f\u0442\u0430\u045e"
    ],
    "name:crh_x_preferred":[
        "Rojn\u00e2tiv"
    ],
    "name:deu_x_preferred":[
        "Roschnjatiw"
    ],
    "name:eng_x_preferred":[
        "Rozhniativ"
    ],
    "name:heb_x_preferred":[
        "\u05e8\u05d5\u05d6'\u05e0\u05d9\u05d0\u05d8\u05d9\u05d1"
    ],
    "name:pol_x_preferred":[
        "Ro\u017cniat\u00f3w"
    ],
    "name:ron_x_preferred":[
        "Rojneativ"
    ],
    "name:rus_x_preferred":[
        "\u0420\u043e\u0436\u043d\u044f\u0442\u043e\u0432"
    ],
    "name:rus_x_variant":[
        "\u0420\u043e\u0436\u043d\u044f\u0442\u0456\u0432"
    ],
    "name:ukr_x_preferred":[
        "\u0420\u043e\u0436\u043d\u044f\u0442\u0456\u0432"
    ],
    "name:unk_x_variant":[
        "Roznatov"
    ],
    "name:zho_x_preferred":[
        "\u7f85\u65e5\u5c3c\u4e9e\u5b63\u592b"
    ],
    "qs:a0":"\u0423\u043a\u0440\u0430\u0457\u043d\u0430",
    "qs:a1":"*\u0406\u0432\u0430\u043d\u043e-\u0424\u0440\u0430\u043d\u043a\u0456\u0432\u0441\u044c\u043a\u0430",
    "qs:a1_alt":"Ivano-Frankivs'ka",
    "qs:a1r":"0",
    "qs:a2":"\u0420\u043e\u0436\u043d\u044f\u0442\u0456\u0432\u0441\u044c\u043a\u0438\u0439",
    "qs:a2_alt":"Rozhniativs'kyi",
    "qs:adm0":"\u0423\u043a\u0440\u0430\u0457\u043d\u0430",
    "qs:la_lc":"*",
    "qs:level":"locality",
    "qs:loc":"\u0420\u043e\u0436\u043d\u044f\u0442\u0456\u0432",
    "qs:loc_alt":"Rozhniativ",
    "qs:pop":0,
    "qs:type":"buffered point",
    "wd:wordcount":71,
    "wof:name":"\u0420\u043e\u0436\u043d\u044f\u0442\u0456\u0432",
    "wof:placetype":"locality",
    "wof:population":3983
},
  "geometry": {"coordinates":[24.15263,48.929209],"type":"Point"}
}