{
  "type": "Feature",
  "properties": {
    "iso:country":"UA",
    "name:deu_x_preferred":[
        "Krasna Poljana"
    ],
    "name:eng_x_preferred":[
        "Krasnaya Polyana"
    ],
    "name:eng_x_variant":[
        "Krasna Poliana"
    ],
    "name:hye_x_preferred":[
        "\u053f\u0580\u0561\u057d\u0576\u0561\u0575\u0561 \u054a\u0578\u056c\u0575\u0561\u0576\u0561"
    ],
    "name:lav_x_preferred":[
        "Krasna Po\u013cana"
    ],
    "name:rus_x_preferred":[
        "\u041a\u0440\u0430\u0441\u043d\u0430\u044f \u041f\u043e\u043b\u044f\u043d\u0430"
    ],
    "name:ukr_x_preferred":[
        "Krasna Polyana"
    ],
    "name:ukr_x_variant":[
        "\u041a\u0440\u0430\u0441\u043d\u0430 \u041f\u043e\u043b\u044f\u043d\u0430"
    ],
    "name:und_x_variant":[
        "Goncharikha"
    ],
    "qs:a0":"\u0423\u043a\u0440\u0430\u0457\u043d\u0430",
    "qs:a1":"*\u0414\u043e\u043d\u0435\u0446\u044c\u043a\u0430",
    "qs:a1_alt":"Donets'ka",
    "qs:a1r":"0",
    "qs:a2":"\u0412\u0435\u043b\u0438\u043a\u043e\u043d\u043e\u0432\u043e\u0441\u0456\u043b\u043a\u0456\u0432\u0441\u044c\u043a\u0438\u0439",
    "qs:a2_alt":"Velykonovosilkivs'kyi",
    "qs:adm0":"\u0423\u043a\u0440\u0430\u0457\u043d\u0430",
    "qs:la_lc":"*",
    "qs:level":"locality",
    "qs:loc":"\u041a\u0440\u0430\u0441\u043d\u0430 \u041f\u043e\u043b\u044f\u043d\u0430",
    "qs:loc_alt":"Krasna Poliana",
    "qs:pop":0,
    "qs:type":"buffered point",
    "wd:wordcount":93,
    "wof:name":"\u041a\u0440\u0430\u0441\u043d\u0430 \u041f\u043e\u043b\u044f\u043d\u0430",
    "wof:placetype":"locality"
},
  "geometry": {"coordinates":[37.089802,47.543228],"type":"Point"}
}