{
  "type": "Feature",
  "properties": {
    "gn:admin1_code":"14.0",
    "gn:asciiname":"Tsvitni Piski",
    "gn:country_code":"UA",
    "gn:dem":145,
    "gn:feature_class":"P",
    "gn:feature_code":"PPL",
    "gn:name":"Tsvitni Piski",
    "gn:population":0,
    "gn:timezone":"Europe/Zaporozhye",
    "iso:country":"UA",
    "name:ukr_x_preferred":[
        "Tsvitni Piski"
    ],
    "name:ukr_x_variant":[
        "\u0426\u0432\u0456\u0442\u043d\u0456 \u041f\u0456\u0441\u043a\u0456"
    ],
    "name:und_x_variant":[
        "Tsvetnyye Peski"
    ],
    "wof:name":"Tsvitni Piski",
    "wof:placetype":"locality"
},
  "geometry": {"coordinates":[39.27322,48.66444],"type":"Point"}
}