{
  "type": "Feature",
  "properties": {
    "iso:country":"UA",
    "qs:a0":"\u0423\u043a\u0440\u0430\u0457\u043d\u0430",
    "qs:a1":"*\u041a\u0440\u0438\u043c",
    "qs:a1_alt":"Krym",
    "qs:a1r":"0",
    "qs:a2":"\u0427\u043e\u0440\u043d\u043e\u043c\u043e\u0440\u0441\u044c\u043a\u0438\u0439",
    "qs:a2_alt":"Chornomors'kyi",
    "qs:adm0":"\u0423\u043a\u0440\u0430\u0457\u043d\u0430",
    "qs:la_lc":"*",
    "qs:level":"locality",
    "qs:loc":"\u041e\u043b\u0435\u043d\u0456\u0432\u043a\u0430",
    "qs:loc_alt":"Olenivka",
    "qs:pop":0,
    "qs:type":"buffered point",
    "wof:name":"\u041e\u043b\u0435\u043d\u0456\u0432\u043a\u0430",
    "wof:placetype":"locality"
},
  "geometry": {"coordinates":[32.533767,45.381523],"type":"Point"}
}