{
  "type": "Feature",
  "properties": {
    "gn:admin1_code":"4.0",
    "gn:asciiname":"Kostyantynivka",
    "gn:country_code":"UA",
    "gn:dem":117,
    "gn:feature_class":"P",
    "gn:feature_code":"PPL",
    "gn:name":"Kostyantynivka",
    "gn:population":0,
    "gn:timezone":"Europe/Kiev",
    "iso:country":"UA",
    "name:ukr_x_preferred":[
        "Kostyantynivka"
    ],
    "name:ukr_x_variant":[
        "\u041a\u043e\u0441\u0442\u044f\u043d\u0442\u0438\u043d\u0456\u0432\u043a\u0430"
    ],
    "wof:name":"Kostyantynivka",
    "wof:placetype":"locality"
},
  "geometry": {"coordinates":[34.48056,48.20542],"type":"Point"}
}