{
  "type": "Feature",
  "properties": {
    "gn:admin1_code":"11.0",
    "gn:admin2_code":"712585",
    "gn:admin3_code":"11152841.0",
    "gn:asciiname":"Rusakovka",
    "gn:country_code":"UA",
    "gn:dem":240,
    "gn:elevation":"242.0",
    "gn:feature_class":"P",
    "gn:feature_code":"PPLA3",
    "gn:name":"Rusakovka",
    "gn:population":918,
    "gn:timezone":"Europe/Simferopol",
    "iso:country":"UA",
    "name:eng_x_preferred":[
        "Rusakovka"
    ],
    "name:rus_x_historical":[
        "\u041a\u043e\u043a\u0435\u0301\u0439 \u0420\u0443\u0301\u0441\u0441\u043a\u0438\u0439"
    ],
    "name:rus_x_preferred":[
        "\u0420\u0443\u0441\u0430\u043a\u043e\u0432\u043a\u0430"
    ],
    "name:rus_x_variant":[
        "\u041a\u043e\u043a\u0435\u0301\u0439 \u0420\u0443\u0301\u0441\u0441\u043a\u0438\u0439"
    ],
    "name:ukr_x_preferred":[
        "\u0420\u0443\u0441\u0430\u043a\u0456\u0432\u043a\u0430"
    ],
    "wof:name":"Rusakovka",
    "wof:placetype":"locality",
    "wof:population":918
},
  "geometry": {"coordinates":[34.47458,45.12369],"type":"Point"}
}