{
  "type": "Feature",
  "properties": {
    "gn:admin1_code":"22.0",
    "gn:asciiname":"Khorobruv",
    "gn:country_code":"UA",
    "gn:dem":360,
    "gn:feature_class":"P",
    "gn:feature_code":"PPL",
    "gn:name":"Khorobruv",
    "gn:population":0,
    "gn:timezone":"Europe/Kiev",
    "iso:country":"UA",
    "wof:name":"Khorobruv",
    "wof:placetype":"locality"
},
  "geometry": {"coordinates":[25.12186,49.59855],"type":"Point"}
}