{
  "type": "Feature",
  "properties": {
    "gn:admin1_code":"11.0",
    "gn:admin2_code":"694905",
    "gn:admin3_code":"11153090.0",
    "gn:asciiname":"Soldatskoye",
    "gn:country_code":"UA",
    "gn:dem":47,
    "gn:elevation":"44.0",
    "gn:feature_class":"P",
    "gn:feature_code":"PPL",
    "gn:name":"Soldatskoye",
    "gn:population":73,
    "gn:timezone":"Europe/Simferopol",
    "iso:country":"UA",
    "name:eng_x_preferred":[
        "Soldatskoye"
    ],
    "name:rus_x_historical":[
        "\u0421\u0435\u0438\u0442-\u0414\u0436\u0435\u0443\u0301\u0442",
        "\u0421\u0435\u0434\u0436\u0435\u0432\u0443\u0301\u0442"
    ],
    "name:rus_x_preferred":[
        "\u0421\u043e\u043b\u0434\u0430\u0442\u0441\u043a\u043e\u0435"
    ],
    "name:rus_x_variant":[
        "\u0421\u0435\u0438\u0442-\u0414\u0436\u0435\u0443\u0301\u0442",
        "\u0421\u0435\u0434\u0436\u0435\u0432\u0443\u0301\u0442"
    ],
    "name:ukr_x_preferred":[
        "\u0421\u043e\u043b\u0434\u0430\u0442\u0441\u044c\u043a\u0435"
    ],
    "wof:name":"Soldatskoye",
    "wof:placetype":"locality",
    "wof:population":73
},
  "geometry": {"coordinates":[33.39711,45.48789],"type":"Point"}
}