{
  "type": "Feature",
  "properties": {
    "gn:admin1_code":"23.0",
    "gn:asciiname":"Borshchahivka",
    "gn:country_code":"UA",
    "gn:dem":192,
    "gn:feature_class":"P",
    "gn:feature_code":"PPL",
    "gn:name":"Borshchahivka",
    "gn:population":0,
    "gn:timezone":"Europe/Kiev",
    "iso:country":"UA",
    "name:bel_x_preferred":[
        "\u0411\u0430\u0440\u0448\u0447\u0430\u0433\u043e\u045e\u043a\u0430"
    ],
    "name:rus_x_preferred":[
        "\u0411\u043e\u0440\u0449\u0430\u0433\u043e\u0432\u043a\u0430"
    ],
    "name:sco_x_preferred":[
        "Borschahivka"
    ],
    "name:ukr_x_preferred":[
        "\u0411\u043e\u0440\u0449\u0430\u0433\u0456\u0432\u043a\u0430"
    ],
    "name:und_x_variant":[
        "Borshchagovka"
    ],
    "wof:name":"Borshchahivka",
    "wof:placetype":"locality"
},
  "geometry": {"coordinates":[29.53397,49.48665],"type":"Point"}
}