{
  "type": "Feature",
  "properties": {
    "gn:admin1_code":"16.0",
    "gn:asciiname":"Katerynivka",
    "gn:country_code":"UA",
    "gn:dem":82,
    "gn:feature_class":"P",
    "gn:feature_code":"PPL",
    "gn:name":"Katerynivka",
    "gn:population":0,
    "gn:timezone":"Europe/Kiev",
    "iso:country":"UA",
    "name:und_x_variant":[
        "Katerinental\u2019",
        "Yekaterinovka",
        "Yekaterinenstal\u2019",
        "Katerinka",
        "Katerynivka"
    ],
    "wof:name":"Katerynivka",
    "wof:placetype":"locality"
},
  "geometry": {"coordinates":[31.50275,47.22848],"type":"Point"}
}