{
  "type": "Feature",
  "properties": {
    "gn:admin1_code":"11.0",
    "gn:admin2_code":"704361",
    "gn:admin3_code":"11152946.0",
    "gn:asciiname":"Svatovo",
    "gn:country_code":"UA",
    "gn:dem":9,
    "gn:elevation":"10.0",
    "gn:feature_class":"P",
    "gn:feature_code":"PPL",
    "gn:name":"Svatovo",
    "gn:population":142,
    "gn:timezone":"Europe/Simferopol",
    "iso:country":"UA",
    "name:eng_x_preferred":[
        "Svatovo"
    ],
    "name:rus_x_historical":[
        "\u0421\u0443\u043b\u0442\u0430\u043d\u0430\u0301\u0448"
    ],
    "name:rus_x_preferred":[
        "\u0421\u0432\u0430\u0442\u043e\u0432\u043e"
    ],
    "name:rus_x_variant":[
        "\u0421\u0443\u043b\u0442\u0430\u043d\u0430\u0301\u0448"
    ],
    "name:ukr_x_preferred":[
        "\u0421\u0432\u0430\u0442\u043e\u0432\u0435"
    ],
    "wof:name":"Svatovo",
    "wof:placetype":"locality",
    "wof:population":142
},
  "geometry": {"coordinates":[33.86702,45.81293],"type":"Point"}
}