{
  "type": "Feature",
  "properties": {
    "gn:admin1_code":"2.0",
    "gn:asciiname":"Mykolayiv",
    "gn:country_code":"UA",
    "gn:dem":134,
    "gn:feature_class":"P",
    "gn:feature_code":"PPL",
    "gn:name":"Mykolayiv",
    "gn:population":0,
    "gn:timezone":"Europe/Kiev",
    "iso:country":"UA",
    "name:ukr_x_preferred":[
        "Mykolayiv"
    ],
    "name:ukr_x_variant":[
        "\u041c\u0438\u043a\u043e\u043b\u0430\u0457\u0432"
    ],
    "name:und_x_variant":[
        "Nikolayev"
    ],
    "wof:name":"Mykolayiv",
    "wof:placetype":"locality"
},
  "geometry": {"coordinates":[31.72112000000001,50.67167],"type":"Point"}
}