{
  "type": "Feature",
  "properties": {
    "gn:population":1005,
    "iso:country":"UA",
    "name:rus_x_preferred":[
        "\u0427\u0435\u0440\u043d\u043e\u0440\u0443\u0434\u043a\u0430"
    ],
    "name:ukr_x_preferred":[
        "Chornorudka"
    ],
    "name:ukr_x_variant":[
        "\u0427\u043e\u0440\u043d\u043e\u0440\u0443\u0434\u043a\u0430"
    ],
    "name:unk_x_variant":[
        "Chernorudka"
    ],
    "qs:a0":"\u0423\u043a\u0440\u0430\u0457\u043d\u0430",
    "qs:a1":"*\u0416\u0438\u0442\u043e\u043c\u0438\u0440\u0441\u044c\u043a\u0430",
    "qs:a1_alt":"Zhytomyrs'ka",
    "qs:a1r":"0",
    "qs:a2":"\u0420\u0443\u0436\u0438\u043d\u0441\u044c\u043a\u0438\u0439",
    "qs:a2_alt":"Ruzhyns'kyi",
    "qs:adm0":"\u0423\u043a\u0440\u0430\u0457\u043d\u0430",
    "qs:la_lc":"*",
    "qs:level":"locality",
    "qs:loc":"\u0427\u043e\u0440\u043d\u043e\u0440\u0443\u0434\u043a\u0430",
    "qs:loc_alt":"Chornorudka",
    "qs:pop":0,
    "qs:type":"buffered point",
    "wof:name":"\u0427\u043e\u0440\u043d\u043e\u0440\u0443\u0434\u043a\u0430",
    "wof:placetype":"locality",
    "wof:population":1005
},
  "geometry": {"coordinates":[29.059852,49.838569],"type":"Point"}
}