{
  "type": "Feature",
  "properties": {
    "gn:admin1_code":"2.0",
    "gn:asciiname":"Kurylivka",
    "gn:country_code":"UA",
    "gn:dem":130,
    "gn:feature_class":"P",
    "gn:feature_code":"PPL",
    "gn:name":"Kurylivka",
    "gn:population":0,
    "gn:timezone":"Europe/Kiev",
    "iso:country":"UA",
    "name:ukr_x_preferred":[
        "Kurylivka"
    ],
    "name:ukr_x_variant":[
        "\u041a\u0443\u0440\u0438\u043b\u0456\u0432\u043a\u0430"
    ],
    "name:und_x_variant":[
        "Kurilovka"
    ],
    "wof:name":"Kurylivka",
    "wof:placetype":"locality"
},
  "geometry": {"coordinates":[33.07497,51.84889],"type":"Point"}
}