{
  "type": "Feature",
  "properties": {
    "gn:admin1_code":"15.0",
    "gn:asciiname":"Porech'ye",
    "gn:country_code":"UA",
    "gn:dem":295,
    "gn:feature_class":"P",
    "gn:feature_code":"PPL",
    "gn:name":"Porech\u2019ye",
    "gn:population":0,
    "gn:timezone":"Europe/Kiev",
    "iso:country":"UA",
    "wof:name":"Porech'ye",
    "wof:placetype":"locality"
},
  "geometry": {"coordinates":[23.76839,49.87833],"type":"Point"}
}