{
  "type": "Feature",
  "properties": {
    "gn:admin1_code":"21.0",
    "gn:asciiname":"Uspenka",
    "gn:cc2":"UA",
    "gn:country_code":"UA",
    "gn:dem":176,
    "gn:feature_class":"P",
    "gn:feature_code":"PPL",
    "gn:name":"Uspenka",
    "gn:population":0,
    "gn:timezone":"Europe/Kiev",
    "iso:country":"UA",
    "name:und_x_variant":[
        "Uspenskoye",
        "Uslepskoye",
        "Uspenka"
    ],
    "wof:name":"Uspenka",
    "wof:placetype":"locality"
},
  "geometry": {"coordinates":[35.26444,50.79583],"type":"Point"}
}