{
  "type": "Feature",
  "properties": {
    "gn:admin1_code":"5.0",
    "gn:admin2_code":"709904",
    "gn:asciiname":"Zolotyy Kolodyaz'",
    "gn:country_code":"UA",
    "gn:dem":143,
    "gn:feature_class":"P",
    "gn:feature_code":"PPL",
    "gn:name":"Zolotyy Kolodyaz\u2019",
    "gn:population":0,
    "gn:timezone":"Europe/Kiev",
    "iso:country":"UA",
    "name:hye_x_preferred":[
        "\u0536\u0578\u056c\u0578\u057f\u0578\u0575 \u053f\u0578\u056c\u0578\u0564\u0565\u0566"
    ],
    "name:rus_x_preferred":[
        "Zolotoy Kolodets"
    ],
    "name:rus_x_variant":[
        "Zolotoy Kolodez\u2019",
        "\u0417\u043e\u043b\u043e\u0442\u043e\u0439 \u041a\u043e\u043b\u043e\u0434\u0435\u0437\u044c"
    ],
    "name:ukr_x_preferred":[
        "\u0417\u043e\u043b\u043e\u0442\u0438\u0439 \u041a\u043e\u043b\u043e\u0434\u044f\u0437\u044c"
    ],
    "name:ukr_x_variant":[
        "Zolotyy Kolodyaz\u2019"
    ],
    "wof:name":"Zolotyy Kolodyaz'",
    "wof:placetype":"locality"
},
  "geometry": {"coordinates":[37.23558,48.53013],"type":"Point"}
}