{
  "type": "Feature",
  "properties": {
    "gn:admin1_code":"18.0",
    "gn:asciiname":"Chaykivshchyna",
    "gn:country_code":"UA",
    "gn:dem":111,
    "gn:feature_class":"P",
    "gn:feature_code":"PPL",
    "gn:name":"Chaykivshchyna",
    "gn:population":0,
    "gn:timezone":"Europe/Kiev",
    "iso:country":"UA",
    "name:eng_x_preferred":[
        "Chaykovshchina"
    ],
    "name:rus_x_preferred":[
        "\u0427\u0430\u0439\u043a\u043e\u0432\u0449\u0438\u043d\u0430"
    ],
    "name:ukr_x_preferred":[
        "Chaykivshchyna"
    ],
    "name:ukr_x_variant":[
        "\u0427\u0430\u0439\u043a\u0456\u0432\u0449\u0438\u043d\u0430"
    ],
    "wof:name":"Chaykivshchyna",
    "wof:placetype":"locality"
},
  "geometry": {"coordinates":[32.57535,49.78063],"type":"Point"}
}