{
  "type": "Feature",
  "properties": {
    "gn:admin1_code":"18.0",
    "gn:asciiname":"Veselka",
    "gn:country_code":"UA",
    "gn:dem":109,
    "gn:feature_class":"P",
    "gn:feature_code":"PPL",
    "gn:name":"Veselka",
    "gn:population":0,
    "gn:timezone":"Europe/Kiev",
    "iso:country":"UA",
    "name:fra_x_preferred":[
        "Veselka"
    ],
    "name:ukr_x_preferred":[
        "Veselka"
    ],
    "name:ukr_x_variant":[
        "\u0412\u0435\u0441\u0435\u043b\u043a\u0430"
    ],
    "wof:name":"Veselka",
    "wof:placetype":"locality"
},
  "geometry": {"coordinates":[34.59422,49.30091],"type":"Point"}
}