{
  "type": "Feature",
  "properties": {
    "gn:admin1_code":"13.0",
    "gn:asciiname":"Lubyanka",
    "gn:country_code":"UA",
    "gn:dem":152,
    "gn:feature_class":"P",
    "gn:feature_code":"PPL",
    "gn:name":"Lubyanka",
    "gn:population":0,
    "gn:timezone":"Europe/Kiev",
    "iso:country":"UA",
    "name:bel_x_preferred":[
        "\u041b\u0443\u0431\u044f\u043d\u043a\u0430"
    ],
    "name:ceb_x_preferred":[
        "Lubyanka"
    ],
    "name:ces_x_preferred":[
        "Lubjanka"
    ],
    "name:deu_x_preferred":[
        "Lubjanka"
    ],
    "name:fra_x_preferred":[
        "Loubianka"
    ],
    "name:hye_x_preferred":[
        "\u053c\u0578\u0582\u0562\u0575\u0561\u0576\u056f\u0561"
    ],
    "name:lit_x_preferred":[
        "Lubianka"
    ],
    "name:ron_x_preferred":[
        "Lubianka"
    ],
    "name:rus_x_preferred":[
        "\u041b\u0443\u0431\u044f\u043d\u043a\u0430"
    ],
    "name:spa_x_preferred":[
        "Lubianka"
    ],
    "name:srp_x_preferred":[
        "\u041b\u0443\u0431\u0458\u0430\u043d\u043a\u0430"
    ],
    "name:swe_x_preferred":[
        "Lubyanka"
    ],
    "name:ukr_x_preferred":[
        "\u041b\u0443\u0431'\u044f\u043d\u043a\u0430"
    ],
    "wof:name":"Lubyanka",
    "wof:placetype":"locality"
},
  "geometry": {"coordinates":[30.72488,49.69975],"type":"Point"}
}