{
  "type": "Feature",
  "properties": {
    "gn:admin1_code":"21.0",
    "gn:asciiname":"Berizky",
    "gn:country_code":"UA",
    "gn:dem":180,
    "gn:feature_class":"P",
    "gn:feature_code":"PPL",
    "gn:name":"Berizky",
    "gn:population":0,
    "gn:timezone":"Europe/Kiev",
    "iso:country":"UA",
    "name:ukr_x_preferred":[
        "Berizky"
    ],
    "name:ukr_x_variant":[
        "\u0411\u0435\u0440\u0456\u0437\u043a\u0438"
    ],
    "name:und_x_variant":[
        "Berezki"
    ],
    "wof:name":"Berizky",
    "wof:placetype":"locality"
},
  "geometry": {"coordinates":[33.92944,50.88113],"type":"Point"}
}