{
  "type": "Feature",
  "properties": {
    "gn:admin1_code":"2.0",
    "gn:asciiname":"Chervonyy Ranok",
    "gn:country_code":"UA",
    "gn:dem":132,
    "gn:feature_class":"P",
    "gn:feature_code":"PPL",
    "gn:name":"Chervonyy Ranok",
    "gn:population":0,
    "gn:timezone":"Europe/Kiev",
    "iso:country":"UA",
    "name:ukr_x_preferred":[
        "Chervonyy Ranok"
    ],
    "name:ukr_x_variant":[
        "\u0427\u0435\u0440\u0432\u043e\u043d\u0438\u0439 \u0420\u0430\u043d\u043e\u043a"
    ],
    "name:und_x_variant":[
        "Nezamozhnik"
    ],
    "wof:name":"Chervonyy Ranok",
    "wof:placetype":"locality"
},
  "geometry": {"coordinates":[33.15903,51.5514],"type":"Point"}
}