{
  "type": "Feature",
  "properties": {
    "iso:country":"UA",
    "qs:a0":"\u0423\u043a\u0440\u0430\u0457\u043d\u0430",
    "qs:a1":"*\u0425\u043c\u0435\u043b\u044c\u043d\u0438\u0446\u044c\u043a\u0430",
    "qs:a1_alt":"Khmel'nyts'ka",
    "qs:a1r":"0",
    "qs:a2":"\u0414\u0443\u043d\u0430\u0454\u0432\u0435\u0446\u044c\u043a\u0438\u0439",
    "qs:a2_alt":"Dunaievets'kyi",
    "qs:adm0":"\u0423\u043a\u0440\u0430\u0457\u043d\u0430",
    "qs:la_lc":"*",
    "qs:level":"locality",
    "qs:loc":"\u041c\u0456\u0446\u0456\u0432\u0446\u0456",
    "qs:loc_alt":"Mitsivtsi",
    "qs:pop":0,
    "qs:type":"buffered point",
    "wof:name":"\u041c\u0456\u0446\u0456\u0432\u0446\u0456",
    "wof:placetype":"locality"
},
  "geometry": {"coordinates":[26.894901,49.00656],"type":"Point"}
}