{
  "type": "Feature",
  "properties": {
    "gn:admin1_code":"9.0",
    "gn:asciiname":"Andreyevka",
    "gn:country_code":"UA",
    "gn:dem":256,
    "gn:feature_class":"P",
    "gn:feature_code":"PPL",
    "gn:name":"Andreyevka",
    "gn:population":0,
    "gn:timezone":"Europe/Kiev",
    "iso:country":"UA",
    "wof:name":"Andreyevka",
    "wof:placetype":"locality"
},
  "geometry": {"coordinates":[26.30225,48.9603],"type":"Point"}
}