{
  "type": "Feature",
  "properties": {
    "gn:admin1_code":"16.0",
    "gn:asciiname":"Tat'yanovka",
    "gn:country_code":"UA",
    "gn:dem":43,
    "gn:feature_class":"P",
    "gn:feature_code":"PPL",
    "gn:name":"Tat\u2019yanovka",
    "gn:population":0,
    "gn:timezone":"Europe/Kiev",
    "iso:country":"UA",
    "wof:name":"Tat'yanovka",
    "wof:placetype":"locality"
},
  "geometry": {"coordinates":[32.77918,47.38148],"type":"Point"}
}