{
  "type": "Feature",
  "properties": {
    "gn:admin1_code":"7.0",
    "gn:asciiname":"Marsovka Vtoraya",
    "gn:country_code":"UA",
    "gn:dem":159,
    "gn:feature_class":"P",
    "gn:feature_code":"PPL",
    "gn:name":"Marsovka Vtoraya",
    "gn:population":0,
    "gn:timezone":"Europe/Kiev",
    "iso:country":"UA",
    "wof:name":"Marsovka Vtoraya",
    "wof:placetype":"locality"
},
  "geometry": {"coordinates":[37.51556,49.47639],"type":"Point"}
}