{
  "type": "Feature",
  "properties": {
    "gn:admin1_code":"5.0",
    "gn:asciiname":"Izmaylovka",
    "gn:country_code":"UA",
    "gn:dem":194,
    "gn:feature_class":"P",
    "gn:feature_code":"PPL",
    "gn:name":"Izmaylovka",
    "gn:population":0,
    "gn:timezone":"Europe/Kiev",
    "iso:country":"UA",
    "wof:name":"Izmaylovka",
    "wof:placetype":"locality"
},
  "geometry": {"coordinates":[37.63333,48.06667],"type":"Point"}
}