{
  "type": "Feature",
  "properties": {
    "gn:admin1_code":"18.0",
    "gn:asciiname":"Pishchane",
    "gn:country_code":"UA",
    "gn:dem":81,
    "gn:feature_class":"P",
    "gn:feature_code":"PPL",
    "gn:name":"Pishchane",
    "gn:population":0,
    "gn:timezone":"Europe/Kiev",
    "iso:country":"UA",
    "name:eng_x_preferred":[
        "Peschanoye"
    ],
    "name:rus_x_preferred":[
        "\u041f\u0435\u0441\u0447\u0430\u043d\u043e\u0435"
    ],
    "name:ukr_x_preferred":[
        "Pishchane"
    ],
    "name:ukr_x_variant":[
        "\u041f\u0456\u0449\u0430\u043d\u0435"
    ],
    "name:und_x_variant":[
        "Peschanskoye",
        "Peschanoye"
    ],
    "wof:name":"Pishchane",
    "wof:placetype":"locality"
},
  "geometry": {"coordinates":[33.39414,49.12899],"type":"Point"}
}