{
  "type": "Feature",
  "properties": {
    "gn:admin1_code":"5.0",
    "gn:asciiname":"Novooleksiyivka",
    "gn:country_code":"UA",
    "gn:dem":190,
    "gn:feature_class":"P",
    "gn:feature_code":"PPL",
    "gn:name":"Novooleksiyivka",
    "gn:population":0,
    "gn:timezone":"Europe/Kiev",
    "iso:country":"UA",
    "name:bel_x_preferred":[
        "\u041d\u043e\u0432\u0430\u0430\u043b\u044d\u043a\u0441\u0456\u0456\u045e\u043a\u0430"
    ],
    "name:bul_x_preferred":[
        "\u041d\u043e\u0432\u043e\u043e\u043b\u0435\u043a\u0441\u0438\u0438\u0432\u043a\u0430"
    ],
    "name:ceb_x_preferred":[
        "Novooleksiyivka"
    ],
    "name:crh_x_preferred":[
        "Novooleksiyivka"
    ],
    "name:deu_x_preferred":[
        "Nowoolexijiwka"
    ],
    "name:pol_x_preferred":[
        "Nowoo\u0142eksijiwka"
    ],
    "name:ron_x_preferred":[
        "Novooleksiivka"
    ],
    "name:rus_x_preferred":[
        "\u041d\u043e\u0432\u043e\u0430\u043b\u0435\u043a\u0441\u0435\u0435\u0432\u043a\u0430"
    ],
    "name:ukr_x_preferred":[
        "Novooleksiyivka"
    ],
    "name:ukr_x_variant":[
        "\u041d\u043e\u0432\u043e\u043e\u043b\u0435\u043a\u0441\u0456\u0457\u0432\u043a\u0430"
    ],
    "name:zho_x_preferred":[
        "\u65b0\u5967\u5217\u514b\u897f\u4f0a\u592b\u5361"
    ],
    "wof:name":"Novooleksiyivka",
    "wof:placetype":"locality"
},
  "geometry": {"coordinates":[37.20677,48.13178],"type":"Point"}
}