{
  "type": "Feature",
  "properties": {
    "gn:admin1_code":"5.0",
    "gn:asciiname":"Novooleksiyivka",
    "gn:country_code":"UA",
    "gn:dem":190,
    "gn:feature_class":"P",
    "gn:feature_code":"PPL",
    "gn:name":"Novooleksiyivka",
    "gn:population":0,
    "gn:timezone":"Europe/Kiev",
    "iso:country":"UA",
    "name:ukr_x_preferred":[
        "Novooleksiyivka"
    ],
    "name:ukr_x_variant":[
        "\u041d\u043e\u0432\u043e\u043e\u043b\u0435\u043a\u0441\u0456\u0457\u0432\u043a\u0430"
    ],
    "wof:name":"Novooleksiyivka",
    "wof:placetype":"locality"
},
  "geometry": {"coordinates":[37.20677,48.13178],"type":"Point"}
}