{
  "type": "Feature",
  "properties": {
    "gn:admin1_code":"24.0",
    "gn:asciiname":"Humnyshche",
    "gn:country_code":"UA",
    "gn:dem":200,
    "gn:feature_class":"P",
    "gn:feature_code":"PPL",
    "gn:name":"Humnyshche",
    "gn:population":0,
    "gn:timezone":"Europe/Kiev",
    "iso:country":"UA",
    "name:ukr_x_preferred":[
        "Humnyshche"
    ],
    "name:ukr_x_variant":[
        "\u0413\u0443\u043c\u043d\u0438\u0449\u0435"
    ],
    "name:und_x_variant":[
        "Gumnishche"
    ],
    "wof:name":"Humnyshche",
    "wof:placetype":"locality"
},
  "geometry": {"coordinates":[25.16132,50.41474],"type":"Point"}
}