{
  "type": "Feature",
  "properties": {
    "gn:admin1_code":"6.0",
    "gn:asciiname":"Sorochanka",
    "gn:country_code":"UA",
    "gn:dem":203,
    "gn:feature_class":"P",
    "gn:feature_code":"PPL",
    "gn:name":"Sorochanka",
    "gn:population":0,
    "gn:timezone":"Europe/Kiev",
    "iso:country":"UA",
    "wof:name":"Sorochanka",
    "wof:placetype":"locality"
},
  "geometry": {"coordinates":[25.55,48.43333],"type":"Point"}
}