{
  "type": "Feature",
  "properties": {
    "gn:admin1_code":"19.0",
    "gn:asciiname":"Koloniya Pzherva",
    "gn:country_code":"UA",
    "gn:dem":168,
    "gn:feature_class":"P",
    "gn:feature_code":"PPL",
    "gn:name":"Koloniya Pzherva",
    "gn:population":0,
    "gn:timezone":"Europe/Kiev",
    "iso:country":"UA",
    "wof:name":"Koloniya Pzherva",
    "wof:placetype":"locality"
},
  "geometry": {"coordinates":[26.21667,51.38333],"type":"Point"}
}