{
  "type": "Feature",
  "properties": {
    "gn:admin1_code":"16.0",
    "gn:asciiname":"Kavkaz",
    "gn:country_code":"UA",
    "gn:dem":64,
    "gn:feature_class":"P",
    "gn:feature_code":"PPL",
    "gn:name":"Kavkaz",
    "gn:population":0,
    "gn:timezone":"Europe/Kiev",
    "iso:country":"UA",
    "name:bos_x_preferred":[
        "Kavkaz"
    ],
    "name:ces_x_preferred":[
        "Kavkaz"
    ],
    "name:hrv_x_preferred":[
        "Kavkaz"
    ],
    "name:ukr_x_preferred":[
        "Kavkaz"
    ],
    "name:ukr_x_variant":[
        "\u041a\u0430\u0432\u043a\u0430\u0437"
    ],
    "wof:name":"Kavkaz",
    "wof:placetype":"locality"
},
  "geometry": {"coordinates":[33.06483,47.28758],"type":"Point"}
}