{
  "type": "Feature",
  "properties": {
    "gn:admin1_code":"13.0",
    "gn:asciiname":"Huta-Mezhyhirs'ka",
    "gn:country_code":"UA",
    "gn:dem":126,
    "gn:feature_class":"P",
    "gn:feature_code":"PPL",
    "gn:name":"Huta-Mezhyhirs\u2019ka",
    "gn:population":0,
    "gn:timezone":"Europe/Kiev",
    "iso:country":"UA",
    "name:ukr_x_preferred":[
        "Huta-Mezhyhirs\u2019ka"
    ],
    "name:ukr_x_variant":[
        "\u0413\u0443\u0442\u0430-\u041c\u0435\u0436\u0438\u0433\u0456\u0440\u0441\u044c\u043a\u0430"
    ],
    "name:und_x_variant":[
        "Guta",
        "Guta Mezhigovskaya",
        "Guta-Mezhigorskaya"
    ],
    "wof:name":"Huta-Mezhyhirs'ka",
    "wof:placetype":"locality"
},
  "geometry": {"coordinates":[30.31001,50.6738],"type":"Point"}
}