{
  "type": "Feature",
  "properties": {
    "gn:admin1_code":"5.0",
    "gn:asciiname":"Molodets'ke",
    "gn:country_code":"UA",
    "gn:dem":218,
    "gn:feature_class":"P",
    "gn:feature_code":"PPL",
    "gn:name":"Molodets\u2019ke",
    "gn:population":0,
    "gn:timezone":"Europe/Kiev",
    "iso:country":"UA",
    "name:ukr_x_preferred":[
        "Molodets\u2019ke"
    ],
    "name:ukr_x_variant":[
        "\u041c\u043e\u043b\u043e\u0434\u0435\u0446\u044c\u043a\u0435"
    ],
    "wof:name":"Molodets'ke",
    "wof:placetype":"locality"
},
  "geometry": {"coordinates":[38.45251,48.02677],"type":"Point"}
}