{
  "type": "Feature",
  "properties": {
    "gn:admin1_code":"24.0",
    "gn:asciiname":"Mykove",
    "gn:country_code":"UA",
    "gn:dem":191,
    "gn:feature_class":"P",
    "gn:feature_code":"PPL",
    "gn:name":"Mykove",
    "gn:population":0,
    "gn:timezone":"Europe/Kiev",
    "iso:country":"UA",
    "name:ukr_x_preferred":[
        "Mykove"
    ],
    "name:ukr_x_variant":[
        "\u041c\u0438\u043a\u043e\u0432\u0435"
    ],
    "name:und_x_variant":[
        "Mykovo"
    ],
    "wof:name":"Mykove",
    "wof:placetype":"locality"
},
  "geometry": {"coordinates":[25.70773,50.96279000000001],"type":"Point"}
}