{
  "type": "Feature",
  "properties": {
    "gn:admin1_code":"19.0",
    "gn:asciiname":"Kozyrshchyna",
    "gn:country_code":"UA",
    "gn:dem":218,
    "gn:feature_class":"P",
    "gn:feature_code":"PPL",
    "gn:name":"Kozyrshchyna",
    "gn:population":0,
    "gn:timezone":"Europe/Kiev",
    "iso:country":"UA",
    "name:ukr_x_preferred":[
        "Kozyrshchyna"
    ],
    "name:ukr_x_variant":[
        "\u041a\u043e\u0437\u0438\u0440\u0449\u0438\u043d\u0430"
    ],
    "name:und_x_variant":[
        "Kozyrshchina"
    ],
    "wof:name":"Kozyrshchyna",
    "wof:placetype":"locality"
},
  "geometry": {"coordinates":[25.44409,50.4489],"type":"Point"}
}