{
  "type": "Feature",
  "properties": {
    "gn:admin1_code":"8.0",
    "gn:asciiname":"Novopoltavka",
    "gn:country_code":"UA",
    "gn:dem":21,
    "gn:feature_class":"P",
    "gn:feature_code":"PPL",
    "gn:name":"Novopoltavka",
    "gn:population":0,
    "gn:timezone":"Europe/Kiev",
    "iso:country":"UA",
    "name:ceb_x_preferred":[
        "Novopoltavka"
    ],
    "name:ron_x_preferred":[
        "Novopoltavka"
    ],
    "name:rus_x_preferred":[
        "\u041d\u043e\u0432\u043e\u043f\u043e\u043b\u0442\u0430\u0432\u043a\u0430"
    ],
    "name:ukr_x_preferred":[
        "Novopoltavka"
    ],
    "name:ukr_x_variant":[
        "\u041d\u043e\u0432\u043e\u043f\u043e\u043b\u0442\u0430\u0432\u043a\u0430"
    ],
    "name:zho_x_preferred":[
        "\u65b0\u6ce2\u723e\u5854\u592b\u5361"
    ],
    "wof:name":"Novopoltavka",
    "wof:placetype":"locality"
},
  "geometry": {"coordinates":[32.98417,47.14464],"type":"Point"}
}