{
  "type": "Feature",
  "properties": {
    "gn:admin1_code":"5.0",
    "gn:asciiname":"Rayskoye",
    "gn:cc2":"UA",
    "gn:country_code":"UA",
    "gn:dem":85,
    "gn:feature_class":"P",
    "gn:feature_code":"PPL",
    "gn:name":"Rayskoye",
    "gn:population":0,
    "gn:timezone":"Europe/Kiev",
    "iso:country":"UA",
    "name:und_x_variant":[
        "Rayskiy",
        "Rayskoye"
    ],
    "wof:name":"Rayskoye",
    "wof:placetype":"locality"
},
  "geometry": {"coordinates":[37.46046,48.57354],"type":"Point"}
}