{
  "type": "Feature",
  "properties": {
    "gn:admin1_code":"18.0",
    "gn:asciiname":"Demydivka",
    "gn:country_code":"UA",
    "gn:dem":76,
    "gn:feature_class":"P",
    "gn:feature_code":"PPL",
    "gn:name":"Demydivka",
    "gn:population":0,
    "gn:timezone":"Europe/Kiev",
    "iso:country":"UA",
    "name:ukr_x_preferred":[
        "Demydivka"
    ],
    "name:ukr_x_variant":[
        "\u0414\u0435\u043c\u0438\u0434\u0456\u0432\u043a\u0430"
    ],
    "name:und_x_variant":[
        "Demurovka",
        "Demidovka"
    ],
    "wof:name":"Demydivka",
    "wof:placetype":"locality"
},
  "geometry": {"coordinates":[33.52691,49.25186],"type":"Point"}
}