{
  "type": "Feature",
  "properties": {
    "gn:admin1_code":"4.0",
    "gn:asciiname":"Bahate",
    "gn:country_code":"UA",
    "gn:dem":91,
    "gn:feature_class":"P",
    "gn:feature_code":"PPL",
    "gn:name":"Bahate",
    "gn:population":0,
    "gn:timezone":"Europe/Kiev",
    "iso:country":"UA",
    "name:eng_x_preferred":[
        "Bogatoye"
    ],
    "name:rus_x_preferred":[
        "\u041f\u0430\u043d\u0430\u0441\u043e\u0432\u043a\u0430"
    ],
    "name:rus_x_variant":[
        "\u0411\u043e\u0433\u0430\u0442\u043e\u0435"
    ],
    "name:ukr_x_preferred":[
        "Bahate"
    ],
    "name:ukr_x_variant":[
        "\u0411\u0430\u0433\u0430\u0442\u0435"
    ],
    "name:und_x_variant":[
        "Pavlovka"
    ],
    "wof:name":"Bahate",
    "wof:placetype":"locality"
},
  "geometry": {"coordinates":[35.51867,48.97095],"type":"Point"}
}