{
  "type": "Feature",
  "properties": {
    "gn:admin1_code":"5.0",
    "gn:asciiname":"Kurakhove",
    "gn:country_code":"UA",
    "gn:dem":132,
    "gn:feature_class":"P",
    "gn:feature_code":"PPL",
    "gn:name":"Kurakhove",
    "gn:population":0,
    "gn:timezone":"Europe/Kiev",
    "iso:country":"UA",
    "name:ces_x_preferred":[
        "Kurachove"
    ],
    "name:crh_x_preferred":[
        "Kurahove"
    ],
    "name:deu_x_preferred":[
        "Kurachowe"
    ],
    "name:fas_x_preferred":[
        "\u06a9\u0648\u0631\u0627\u062e\u0648\u0641\u0647"
    ],
    "name:fra_x_preferred":[
        "Kourakhove"
    ],
    "name:hye_x_preferred":[
        "\u053f\u0578\u0582\u0580\u0561\u056d\u0578\u057e\u0578"
    ],
    "name:kat_x_preferred":[
        "\u10d9\u10e3\u10e0\u10d0\u10ee\u10dd\u10d5\u10dd"
    ],
    "name:lav_x_preferred":[
        "Kurahove"
    ],
    "name:pol_x_preferred":[
        "Kurachowe"
    ],
    "name:ron_x_preferred":[
        "Kurahove"
    ],
    "name:rus_x_preferred":[
        "\u041a\u0443\u0440\u0430\u0445\u043e\u0432\u043e"
    ],
    "name:srp_x_preferred":[
        "\u041a\u0443\u0440\u0430\u0445\u043e\u0432\u0435"
    ],
    "name:ukr_x_preferred":[
        "Kurakhove"
    ],
    "name:ukr_x_variant":[
        "\u041a\u0443\u0440\u0430\u0445\u043e\u0432\u0435"
    ],
    "name:und_x_variant":[
        "Roy",
        "Roya",
        "Petrovka",
        "Novo-Ulakly",
        "Kurakhovstroy",
        "Kurakhovo"
    ],
    "name:zho_x_preferred":[
        "\u5eab\u62c9\u970d\u97cb"
    ],
    "wof:name":"Kurakhove",
    "wof:placetype":"locality"
},
  "geometry": {"coordinates":[37.27909,47.98437],"type":"Point"}
}