{
  "type": "Feature",
  "properties": {
    "gn:admin1_code":"4.0",
    "gn:asciiname":"Barkove",
    "gn:country_code":"UA",
    "gn:dem":94,
    "gn:feature_class":"P",
    "gn:feature_code":"PPL",
    "gn:name":"Barkove",
    "gn:population":0,
    "gn:timezone":"Europe/Kiev",
    "iso:country":"UA",
    "name:rus_x_preferred":[
        "\u0411\u0430\u0440\u043a\u043e\u0432\u043e\u0435"
    ],
    "name:ukr_x_preferred":[
        "Barkove"
    ],
    "name:ukr_x_variant":[
        "\u0411\u0430\u0440\u043a\u043e\u0432\u0435"
    ],
    "name:und_x_variant":[
        "Barkovskiy",
        "Barkovoye"
    ],
    "wof:name":"Barkove",
    "wof:placetype":"locality"
},
  "geometry": {"coordinates":[34.73018,47.93846],"type":"Point"}
}