{
  "type": "Feature",
  "properties": {
    "gn:admin1_code":"14.0",
    "gn:asciiname":"Kurhan",
    "gn:country_code":"UA",
    "gn:dem":237,
    "gn:feature_class":"P",
    "gn:feature_code":"PPL",
    "gn:name":"Kurhan",
    "gn:population":0,
    "gn:timezone":"Europe/Zaporozhye",
    "iso:country":"UA",
    "name:ukr_x_preferred":[
        "Kurhan"
    ],
    "name:ukr_x_variant":[
        "\u041a\u0443\u0440\u0433\u0430\u043d"
    ],
    "wof:name":"Kurhan",
    "wof:placetype":"locality"
},
  "geometry": {"coordinates":[38.97839000000001,48.17881],"type":"Point"}
}