{
  "type": "Feature",
  "properties": {
    "iso:country":"UA",
    "name:cat_x_preferred":[
        "Badia d'Arabat"
    ],
    "name:ces_x_preferred":[
        "Arabatsk\u00fd z\u00e1liv"
    ],
    "name:chv_x_preferred":[
        "\u0410\u0440\u0430\u0431\u0430\u0442 \u043a\u04f3\u043b\u043c\u0435\u043a\u0115"
    ],
    "name:deu_x_preferred":[
        "Arabat-Bucht"
    ],
    "name:fra_x_preferred":[
        "Baie d'Arabat"
    ],
    "name:nno_x_preferred":[
        "Arabatbukta"
    ],
    "name:nor_x_preferred":[
        "Arabatbukten"
    ],
    "name:pol_x_preferred":[
        "Zatoka Arabacka"
    ],
    "name:rus_x_preferred":[
        "\u0410\u0440\u0430\u0431\u0430\u0442\u0441\u043a\u0438\u0439 \u0437\u0430\u043b\u0438\u0432"
    ],
    "name:spa_x_preferred":[
        "Bah\u00eda de Arabat"
    ],
    "name:ukr_x_preferred":[
        "\u0410\u0440\u0430\u0431\u0430\u0442\u0441\u044c\u043a\u0430 \u0437\u0430\u0442\u043e\u043a\u0430"
    ],
    "qs:a0":"\u0423\u043a\u0440\u0430\u0457\u043d\u0430",
    "qs:a1":"*\u041e\u0434\u0435\u0441\u044c\u043a\u0430",
    "qs:a1_alt":"Odes'ka",
    "qs:a1r":"0",
    "qs:a2":"\u0411\u0456\u043b\u0433\u043e\u0440\u043e\u0434-\u0414\u043d\u0456\u0441\u0442\u0440\u043e\u0432\u0441\u044c\u043a\u0438\u0439",
    "qs:a2_alt":"Bilhorod-Dnistrovs'kyi",
    "qs:adm0":"\u0423\u043a\u0440\u0430\u0457\u043d\u0430",
    "qs:la_lc":"*",
    "qs:level":"locality",
    "qs:loc":"\u0417\u0430\u0442\u043e\u043a\u0430",
    "qs:loc_alt":"Zatoka",
    "qs:pop":0,
    "qs:type":"buffered point",
    "wd:wordcount":47,
    "wof:name":"\u0417\u0430\u0442\u043e\u043a\u0430",
    "wof:placetype":"locality"
},
  "geometry": {"coordinates":[30.445863,46.063674],"type":"Point"}
}