{
  "type": "Feature",
  "properties": {
    "gn:admin1_code":"6.0",
    "gn:asciiname":"Chesniki",
    "gn:country_code":"UA",
    "gn:dem":279,
    "gn:feature_class":"P",
    "gn:feature_code":"PPL",
    "gn:name":"Chesniki",
    "gn:population":852,
    "gn:timezone":"Europe/Kiev",
    "iso:country":"UA",
    "name:rus_x_preferred":[
        "\u0427\u0435\u0441\u043d\u0438\u043a\u0438"
    ],
    "name:ukr_x_preferred":[
        "\u0427\u0435\u0441\u043d\u0438\u043a\u0438"
    ],
    "wof:name":"Chesniki",
    "wof:placetype":"locality",
    "wof:population":852
},
  "geometry": {"coordinates":[24.72647000000001,49.38806],"type":"Point"}
}