{
  "type": "Feature",
  "properties": {
    "gn:admin1_code":"21.0",
    "gn:asciiname":"Shapovalivka",
    "gn:country_code":"UA",
    "gn:dem":152,
    "gn:feature_class":"P",
    "gn:feature_code":"PPL",
    "gn:name":"Shapovalivka",
    "gn:population":0,
    "gn:timezone":"Europe/Kiev",
    "iso:country":"UA",
    "name:ukr_x_preferred":[
        "Shapovalivka"
    ],
    "name:ukr_x_variant":[
        "\u0428\u0430\u043f\u043e\u0432\u0430\u043b\u0456\u0432\u043a\u0430"
    ],
    "name:und_x_variant":[
        "Shapovalovka"
    ],
    "wof:name":"Shapovalivka",
    "wof:placetype":"locality"
},
  "geometry": {"coordinates":[33.12452,51.17344],"type":"Point"}
}