{
  "type": "Feature",
  "properties": {
    "gn:admin1_code":"17.0",
    "gn:asciiname":"Sadove",
    "gn:country_code":"UA",
    "gn:dem":21,
    "gn:feature_class":"P",
    "gn:feature_code":"PPL",
    "gn:name":"Sadove",
    "gn:population":0,
    "gn:timezone":"Europe/Kiev",
    "iso:country":"UA",
    "name:ukr_x_preferred":[
        "Sadove"
    ],
    "name:ukr_x_variant":[
        "\u0421\u0430\u0434\u043e\u0432\u0435"
    ],
    "name:und_x_variant":[
        "Sadovyy",
        "Sadovoye"
    ],
    "wof:name":"Sadove",
    "wof:placetype":"locality"
},
  "geometry": {"coordinates":[30.08423,45.91025],"type":"Point"}
}