{
  "type": "Feature",
  "properties": {
    "iso:country":"UA",
    "qs:a0":"\u0423\u043a\u0440\u0430\u0457\u043d\u0430",
    "qs:a1":"*\u041f\u043e\u043b\u0442\u0430\u0432\u0441\u044c\u043a\u0430",
    "qs:a1_alt":"Poltavs'ka",
    "qs:a1r":"0",
    "qs:a2":"\u0413\u0430\u0434\u044f\u0446\u044c\u043a\u0438\u0439",
    "qs:a2_alt":"Hadiats'kyi",
    "qs:adm0":"\u0423\u043a\u0440\u0430\u0457\u043d\u0430",
    "qs:la_lc":"*",
    "qs:level":"locality",
    "qs:loc":"\u041f\u0435\u0442\u0440\u0456\u0432\u043a\u0430-\u0420\u043e\u043c\u0435\u043d\u0441\u044c\u043a\u0430",
    "qs:loc_alt":"Petrivka-Romens'ka",
    "qs:pop":0,
    "qs:type":"buffered point",
    "wof:name":"\u041f\u0435\u0442\u0440\u0456\u0432\u043a\u0430-\u0420\u043e\u043c\u0435\u043d\u0441\u044c\u043a\u0430",
    "wof:placetype":"locality"
},
  "geometry": {"coordinates":[33.740791,50.371264],"type":"Point"}
}