{
  "type": "Feature",
  "properties": {
    "gn:admin1_code":"2.0",
    "gn:asciiname":"Kabluky",
    "gn:country_code":"UA",
    "gn:dem":118,
    "gn:feature_class":"P",
    "gn:feature_code":"PPL",
    "gn:name":"Kabluky",
    "gn:population":0,
    "gn:timezone":"Europe/Kiev",
    "iso:country":"UA",
    "name:ukr_x_preferred":[
        "Kabluky"
    ],
    "name:ukr_x_variant":[
        "\u041a\u0430\u0431\u043b\u0443\u043a\u0438"
    ],
    "name:und_x_variant":[
        "Kabluki"
    ],
    "wof:name":"Kabluky",
    "wof:placetype":"locality"
},
  "geometry": {"coordinates":[31.8263,51.11502],"type":"Point"}
}