{
  "type": "Feature",
  "properties": {
    "gn:admin1_code":"9.0",
    "gn:asciiname":"Ostoya",
    "gn:country_code":"UA",
    "gn:dem":285,
    "gn:feature_class":"P",
    "gn:feature_code":"PPL",
    "gn:name":"Ostoya",
    "gn:population":0,
    "gn:timezone":"Europe/Kiev",
    "iso:country":"UA",
    "name:und_x_variant":[
        "Dzerzhanovka",
        "Ostoya"
    ],
    "wof:name":"Ostoya",
    "wof:placetype":"locality"
},
  "geometry": {"coordinates":[26.93685,48.84398],"type":"Point"}
}