{
  "type": "Feature",
  "properties": {
    "gn:admin1_code":"22.0",
    "gn:asciiname":"Podvysoke",
    "gn:country_code":"UA",
    "gn:dem":285,
    "gn:feature_class":"P",
    "gn:feature_code":"PPL",
    "gn:name":"Podvysoke",
    "gn:population":0,
    "gn:timezone":"Europe/Kiev",
    "iso:country":"UA",
    "wof:name":"Podvysoke",
    "wof:placetype":"locality"
},
  "geometry": {"coordinates":[24.78716,49.39046],"type":"Point"}
}