{
  "type": "Feature",
  "properties": {
    "gn:admin1_code":"9.0",
    "gn:asciiname":"Shumovtsy",
    "gn:country_code":"UA",
    "gn:dem":293,
    "gn:feature_class":"P",
    "gn:feature_code":"PPL",
    "gn:name":"Shumovtsy",
    "gn:population":0,
    "gn:timezone":"Europe/Kiev",
    "iso:country":"UA",
    "wof:name":"Shumovtsy",
    "wof:placetype":"locality"
},
  "geometry": {"coordinates":[27.04752,49.35149000000001],"type":"Point"}
}