{
  "type": "Feature",
  "properties": {
    "iso:country":"UA",
    "name:bel_x_preferred":[
        "\u0421\u0430\u043a\u0430\u043b\u043e\u0432\u044d"
    ],
    "name:ces_x_preferred":[
        "Sokolovo"
    ],
    "name:che_x_preferred":[
        "\u0421\u043e\u043a\u043e\u043b\u043e\u0432\u043e"
    ],
    "name:deu_x_preferred":[
        "Sokolowe"
    ],
    "name:eng_x_preferred":[
        "Sokolov"
    ],
    "name:eng_x_variant":[
        "Sokolove"
    ],
    "name:epo_x_preferred":[
        "Sokolove"
    ],
    "name:fin_x_preferred":[
        "S\u043ek\u043el\u043ev\u0435"
    ],
    "name:hye_x_preferred":[
        "\u054d\u0578\u056f\u0578\u056c\u0578\u057e\u0578"
    ],
    "name:nan_x_preferred":[
        "Sokolove"
    ],
    "name:nld_x_preferred":[
        "Sokolove"
    ],
    "name:nno_x_preferred":[
        "Sokolove"
    ],
    "name:nob_x_preferred":[
        "Sokolove"
    ],
    "name:pol_x_preferred":[
        "Soko\u0142owo"
    ],
    "name:rus_x_preferred":[
        "\u0421\u043e\u043a\u043e\u043b\u043e\u0432"
    ],
    "name:rus_x_variant":[
        "\u0421\u043e\u043a\u043e\u043b\u043e\u0432\u043e"
    ],
    "name:ukr_x_preferred":[
        "Sokolove"
    ],
    "name:ukr_x_variant":[
        "\u0421\u043e\u043a\u043e\u043b\u043e\u0432\u0435"
    ],
    "name:und_x_variant":[
        "Sokoliv"
    ],
    "name:zho_x_preferred":[
        "\u7d22\u79d1\u6d1b\u97cb"
    ],
    "qs:a0":"\u0423\u043a\u0440\u0430\u0457\u043d\u0430",
    "qs:a1":"*\u0425\u0430\u0440\u043a\u0456\u0432\u0441\u044c\u043a\u0430",
    "qs:a1_alt":"Kharkivs'ka",
    "qs:a1r":"0",
    "qs:a2":"\u0417\u043c\u0456\u0457\u0432\u0441\u044c\u043a\u0438\u0439",
    "qs:a2_alt":"Zmiivs'kyi",
    "qs:adm0":"\u0423\u043a\u0440\u0430\u0457\u043d\u0430",
    "qs:la_lc":"*",
    "qs:level":"locality",
    "qs:loc":"\u0421\u043e\u043a\u043e\u043b\u043e\u0432\u0435",
    "qs:loc_alt":"Sokolove",
    "qs:pop":0,
    "qs:type":"buffered point",
    "wof:name":"\u0421\u043e\u043a\u043e\u043b\u043e\u0432\u0435",
    "wof:placetype":"locality"
},
  "geometry": {"coordinates":[36.202936,49.708936],"type":"Point"}
}