{
  "type": "Feature",
  "properties": {
    "gn:admin1_code":"15.0",
    "gn:asciiname":"Khlebovitse S'vizhske",
    "gn:country_code":"UA",
    "gn:dem":328,
    "gn:feature_class":"P",
    "gn:feature_code":"PPL",
    "gn:name":"Khlebovitse S\u2019vizhske",
    "gn:population":0,
    "gn:timezone":"Europe/Kiev",
    "iso:country":"UA",
    "wof:name":"Khlebovitse S'vizhske",
    "wof:placetype":"locality"
},
  "geometry": {"coordinates":[24.43333,49.61667],"type":"Point"}
}