{
  "type": "Feature",
  "properties": {
    "gn:admin1_code":"17.0",
    "gn:asciiname":"Karabanove",
    "gn:country_code":"UA",
    "gn:dem":119,
    "gn:feature_class":"P",
    "gn:feature_code":"PPL",
    "gn:name":"Karabanove",
    "gn:population":0,
    "gn:timezone":"Europe/Kiev",
    "iso:country":"UA",
    "name:ukr_x_preferred":[
        "Karabanove"
    ],
    "name:ukr_x_variant":[
        "\u041a\u0430\u0440\u0430\u0431\u0430\u043d\u043e\u0432\u0435"
    ],
    "name:und_x_variant":[
        "Korobanovo",
        "Karabanovo",
        "Korobinovo"
    ],
    "wof:name":"Karabanove",
    "wof:placetype":"locality"
},
  "geometry": {"coordinates":[29.64638,47.42888],"type":"Point"}
}