{
  "type": "Feature",
  "properties": {
    "gn:admin1_code":"1.0",
    "gn:asciiname":"Pal'mira",
    "gn:country_code":"UA",
    "gn:dem":119,
    "gn:feature_class":"P",
    "gn:feature_code":"PPL",
    "gn:name":"Pal\u2019mira",
    "gn:population":0,
    "gn:timezone":"Europe/Kiev",
    "iso:country":"UA",
    "name:ukr_x_preferred":[
        "Pal\u2019mira"
    ],
    "name:ukr_x_variant":[
        "\u041f\u0430\u043b\u044c\u043c\u0456\u0440\u0430"
    ],
    "wof:name":"Pal'mira",
    "wof:placetype":"locality"
},
  "geometry": {"coordinates":[32.17412,49.76944],"type":"Point"}
}