{
  "type": "Feature",
  "properties": {
    "gn:admin1_code":"7.0",
    "gn:asciiname":"Hryhorivka",
    "gn:country_code":"UA",
    "gn:dem":161,
    "gn:feature_class":"P",
    "gn:feature_code":"PPL",
    "gn:name":"Hryhorivka",
    "gn:population":0,
    "gn:timezone":"Europe/Kiev",
    "iso:country":"UA",
    "name:ukr_x_preferred":[
        "Hryhorivka"
    ],
    "name:ukr_x_variant":[
        "\u0413\u0440\u0438\u0433\u043e\u0440\u0456\u0432\u043a\u0430"
    ],
    "wof:name":"Hryhorivka",
    "wof:placetype":"locality"
},
  "geometry": {"coordinates":[35.15516,49.86409],"type":"Point"}
}