{
  "type": "Feature",
  "properties": {
    "gn:admin1_code":"1.0",
    "gn:asciiname":"Khutor Tarasivka",
    "gn:country_code":"UA",
    "gn:dem":233,
    "gn:feature_class":"P",
    "gn:feature_code":"PPL",
    "gn:name":"Khutor Tarasivka",
    "gn:population":0,
    "gn:timezone":"Europe/Kiev",
    "iso:country":"UA",
    "name:und_x_variant":[
        "Tarasivka",
        "Khutor Tarasivka"
    ],
    "wof:name":"Khutor Tarasivka",
    "wof:placetype":"locality"
},
  "geometry": {"coordinates":[29.73798,49.22218],"type":"Point"}
}