{
  "type": "Feature",
  "properties": {
    "gn:admin1_code":"13.0",
    "gn:asciiname":"Pyrohovychi",
    "gn:country_code":"UA",
    "gn:dem":117,
    "gn:feature_class":"P",
    "gn:feature_code":"PPL",
    "gn:name":"Pyrohovychi",
    "gn:population":0,
    "gn:timezone":"Europe/Kiev",
    "iso:country":"UA",
    "name:ukr_x_preferred":[
        "Pyrohovychi"
    ],
    "name:ukr_x_variant":[
        "\u041f\u0438\u0440\u043e\u0433\u043e\u0432\u0438\u0447\u0456"
    ],
    "name:und_x_variant":[
        "Pirogovichi"
    ],
    "wof:name":"Pyrohovychi",
    "wof:placetype":"locality"
},
  "geometry": {"coordinates":[29.97946,50.98678],"type":"Point"}
}