{
  "type": "Feature",
  "properties": {
    "gn:admin1_code":"26.0",
    "gn:asciiname":"Novopavlivka",
    "gn:country_code":"UA",
    "gn:dem":48,
    "gn:feature_class":"P",
    "gn:feature_code":"PPL",
    "gn:name":"Novopavlivka",
    "gn:population":0,
    "gn:timezone":"Europe/Zaporozhye",
    "iso:country":"UA",
    "name:ukr_x_preferred":[
        "Novopavlivka"
    ],
    "name:ukr_x_variant":[
        "\u041d\u043e\u0432\u043e\u043f\u0430\u0432\u043b\u0456\u0432\u043a\u0430"
    ],
    "name:und_x_variant":[
        "Novopavlovka"
    ],
    "wof:name":"Novopavlivka",
    "wof:placetype":"locality"
},
  "geometry": {"coordinates":[35.70789,47.59383],"type":"Point"}
}