{
  "type": "Feature",
  "properties": {
    "gn:admin1_code":"11.0",
    "gn:admin2_code":"700018",
    "gn:admin3_code":"11152973.0",
    "gn:asciiname":"Plodovoye",
    "gn:country_code":"UA",
    "gn:dem":23,
    "gn:elevation":"22.0",
    "gn:feature_class":"P",
    "gn:feature_code":"PPL",
    "gn:name":"Plodovoye",
    "gn:population":551,
    "gn:timezone":"Europe/Simferopol",
    "iso:country":"UA",
    "name:eng_x_preferred":[
        "Plodovoye"
    ],
    "name:rus_x_historical":[
        "\u0427\u0435\u043b\u0435\u0431\u0438\u043b\u0435\u0301\u0440"
    ],
    "name:rus_x_preferred":[
        "\u041f\u043b\u043e\u0434\u043e\u0432\u043e\u0435"
    ],
    "name:rus_x_variant":[
        "\u0427\u0435\u043b\u0435\u0431\u0438\u043b\u0435\u0301\u0440"
    ],
    "name:ukr_x_preferred":[
        "\u041f\u043b\u043e\u0434\u043e\u0432\u0435"
    ],
    "wof:name":"Plodovoye",
    "wof:placetype":"locality",
    "wof:population":551
},
  "geometry": {"coordinates":[34.71995,45.45],"type":"Point"}
}