{
  "type": "Feature",
  "properties": {
    "gn:admin1_code":"25.0",
    "gn:asciiname":"Syuryuk",
    "gn:country_code":"UA",
    "gn:dem":300,
    "gn:feature_class":"P",
    "gn:feature_code":"PPL",
    "gn:name":"Syuryuk",
    "gn:population":0,
    "gn:timezone":"Europe/Uzhgorod",
    "iso:country":"UA",
    "name:ukr_x_preferred":[
        "Syuryuk"
    ],
    "name:ukr_x_variant":[
        "\u0421\u044e\u0440\u044e\u043a"
    ],
    "wof:name":"Syuryuk",
    "wof:placetype":"locality"
},
  "geometry": {"coordinates":[23.47804,48.26694000000001],"type":"Point"}
}