{
  "type": "Feature",
  "properties": {
    "gn:admin1_code":"27.0",
    "gn:asciiname":"Ivanivka",
    "gn:country_code":"UA",
    "gn:dem":160,
    "gn:feature_class":"P",
    "gn:feature_code":"PPL",
    "gn:name":"Ivanivka",
    "gn:population":0,
    "gn:timezone":"Europe/Kiev",
    "iso:country":"UA",
    "name:ukr_x_preferred":[
        "Ivanivka"
    ],
    "name:ukr_x_variant":[
        "\u0406\u0432\u0430\u043d\u0456\u0432\u043a\u0430"
    ],
    "name:und_x_variant":[
        "Yanovka",
        "Yanivka",
        "Ivanovka"
    ],
    "wof:name":"Ivanivka",
    "wof:placetype":"locality"
},
  "geometry": {"coordinates":[29.06061,50.69529],"type":"Point"}
}