{
  "type": "Feature",
  "properties": {
    "gn:admin1_code":"14.0",
    "gn:asciiname":"Utkyne",
    "gn:country_code":"UA",
    "gn:dem":296,
    "gn:feature_class":"P",
    "gn:feature_code":"PPL",
    "gn:name":"Utkyne",
    "gn:population":0,
    "gn:timezone":"Europe/Zaporozhye",
    "iso:country":"UA",
    "name:ukr_x_preferred":[
        "Utkyne"
    ],
    "name:ukr_x_variant":[
        "\u0423\u0442\u043a\u0438\u043d\u0435"
    ],
    "name:und_x_variant":[
        "Utkino"
    ],
    "wof:name":"Utkyne",
    "wof:placetype":"locality"
},
  "geometry": {"coordinates":[38.79196,48.32265],"type":"Point"}
}