{
  "type": "Feature",
  "properties": {
    "iso:country":"UA",
    "name:und_x_variant":[
        "Vorotov"
    ],
    "qs:a0":"\u0423\u043a\u0440\u0430\u0457\u043d\u0430",
    "qs:a1":"*\u041b\u044c\u0432\u0456\u0432\u0441\u044c\u043a\u0430",
    "qs:a1_alt":"L'vivs'ka",
    "qs:a1r":"0",
    "qs:a2":"\u042f\u0432\u043e\u0440\u0456\u0432\u0441\u044c\u043a\u0438\u0439",
    "qs:a2_alt":"Yavorivs'kyi",
    "qs:adm0":"\u0423\u043a\u0440\u0430\u0457\u043d\u0430",
    "qs:la_lc":"*",
    "qs:level":"locality",
    "qs:loc":"\u0412\u043e\u0440\u043e\u0446\u0456\u0432",
    "qs:loc_alt":"Vorotsiv",
    "qs:pop":0,
    "qs:type":"buffered point",
    "wof:name":"\u0412\u043e\u0440\u043e\u0446\u0456\u0432",
    "wof:placetype":"locality"
},
  "geometry": {"coordinates":[23.822042,49.861612],"type":"Point"}
}