{
  "type": "Feature",
  "properties": {
    "gn:admin1_code":"18.0",
    "gn:asciiname":"Ll'yashenkov",
    "gn:country_code":"UA",
    "gn:dem":152,
    "gn:feature_class":"P",
    "gn:feature_code":"PPL",
    "gn:name":"Ll\u2019yashenkov",
    "gn:population":0,
    "gn:timezone":"Europe/Kiev",
    "iso:country":"UA",
    "wof:name":"Ll'yashenkov",
    "wof:placetype":"locality"
},
  "geometry": {"coordinates":[34.19889000000001,50.50861],"type":"Point"}
}