{
  "type": "Feature",
  "properties": {
    "gn:admin1_code":"27.0",
    "gn:asciiname":"Taboryshche",
    "gn:country_code":"UA",
    "gn:dem":161,
    "gn:feature_class":"P",
    "gn:feature_code":"PPL",
    "gn:name":"Taboryshche",
    "gn:population":0,
    "gn:timezone":"Europe/Kiev",
    "iso:country":"UA",
    "name:ukr_x_preferred":[
        "Taboryshche"
    ],
    "name:ukr_x_variant":[
        "\u0422\u0430\u0431\u043e\u0440\u0438\u0449\u0435"
    ],
    "name:und_x_variant":[
        "Taburishche",
        "Taborishche"
    ],
    "wof:name":"Taboryshche",
    "wof:placetype":"locality"
},
  "geometry": {"coordinates":[29.4576,50.50285],"type":"Point"}
}