{
  "type": "Feature",
  "properties": {
    "gn:admin1_code":"11.0",
    "gn:admin2_code":"709333",
    "gn:admin3_code":"11152861.0",
    "gn:asciiname":"Nizhniye Otrozhki",
    "gn:country_code":"UA",
    "gn:dem":9,
    "gn:elevation":"9.0",
    "gn:feature_class":"P",
    "gn:feature_code":"PPL",
    "gn:name":"Nizhniye Otrozhki",
    "gn:population":118,
    "gn:timezone":"Europe/Simferopol",
    "iso:country":"UA",
    "name:eng_x_preferred":[
        "Nizhniye Otrozhki"
    ],
    "name:rus_x_historical":[
        "\u041d\u0438\u0301\u0436\u043d\u0438\u0439 \u0410\u043b\u0430\u0301\u0447",
        "\u041d\u0438\u0301\u0436\u043d\u0438\u0435 \u041e\u0441\u0442\u0440\u043e\u0301\u0436\u043a\u0438"
    ],
    "name:rus_x_preferred":[
        "\u041d\u0438\u0436\u043d\u0438\u0435 \u041e\u0442\u0440\u043e\u0436\u043a\u0438"
    ],
    "name:rus_x_variant":[
        "\u041d\u0438\u0301\u0436\u043d\u0438\u0439 \u0410\u043b\u0430\u0301\u0447",
        "\u041d\u0438\u0301\u0436\u043d\u0438\u0435 \u041e\u0441\u0442\u0440\u043e\u0301\u0436\u043a\u0438"
    ],
    "name:ukr_x_preferred":[
        "\u041d\u0438\u0436\u043d\u0456 \u041e\u0442\u0440\u043e\u0436\u043a\u0438"
    ],
    "wof:name":"Nizhniye Otrozhki",
    "wof:placetype":"locality",
    "wof:population":118
},
  "geometry": {"coordinates":[34.65778,45.66426],"type":"Point"}
}