{
  "type": "Feature",
  "properties": {
    "gn:admin1_code":"7.0",
    "gn:asciiname":"Zemlyanky",
    "gn:country_code":"UA",
    "gn:dem":144,
    "gn:feature_class":"P",
    "gn:feature_code":"PPL",
    "gn:name":"Zemlyanky",
    "gn:population":0,
    "gn:timezone":"Europe/Kiev",
    "iso:country":"UA",
    "name:ukr_x_preferred":[
        "Zemlyanky"
    ],
    "name:ukr_x_variant":[
        "\u0417\u0435\u043c\u043b\u044f\u043d\u043a\u0438"
    ],
    "name:und_x_variant":[
        "Zemlyanki"
    ],
    "wof:name":"Zemlyanky",
    "wof:placetype":"locality"
},
  "geometry": {"coordinates":[35.64095,49.20093],"type":"Point"}
}