{
  "type": "Feature",
  "properties": {
    "gn:admin1_code":"2.0",
    "gn:asciiname":"Petrove",
    "gn:country_code":"UA",
    "gn:dem":118,
    "gn:feature_class":"P",
    "gn:feature_code":"PPL",
    "gn:name":"Petrove",
    "gn:population":0,
    "gn:timezone":"Europe/Kiev",
    "iso:country":"UA",
    "name:bel_x_preferred":[
        "\u041f\u044d\u0442\u0440\u043e\u0432\u044d"
    ],
    "name:ceb_x_preferred":[
        "Petrove"
    ],
    "name:crh_x_preferred":[
        "Petrove"
    ],
    "name:deu_x_preferred":[
        "Petrowe"
    ],
    "name:lit_x_preferred":[
        "Petrov\u0117"
    ],
    "name:pol_x_preferred":[
        "Petrowe"
    ],
    "name:ron_x_preferred":[
        "Petrove"
    ],
    "name:rus_x_preferred":[
        "\u041f\u0435\u0442\u0440\u043e\u0432\u043e"
    ],
    "name:spa_x_preferred":[
        "Petrove"
    ],
    "name:ukr_x_preferred":[
        "Petrove"
    ],
    "name:ukr_x_variant":[
        "\u041f\u0435\u0442\u0440\u043e\u0432\u0435"
    ],
    "name:und_x_variant":[
        "Petrovo"
    ],
    "name:zho_x_preferred":[
        "\u4f69\u7279\u7f85\u97cb"
    ],
    "wof:name":"Petrove",
    "wof:placetype":"locality"
},
  "geometry": {"coordinates":[31.64823,51.55852],"type":"Point"}
}