{
  "type": "Feature",
  "properties": {
    "gn:admin1_code":"5.0",
    "gn:asciiname":"Komyshuvakha",
    "gn:country_code":"UA",
    "gn:dem":112,
    "gn:feature_class":"P",
    "gn:feature_code":"PPL",
    "gn:name":"Komyshuvakha",
    "gn:population":0,
    "gn:timezone":"Europe/Kiev",
    "iso:country":"UA",
    "name:ceb_x_preferred":[
        "Komyshuvakha"
    ],
    "name:deu_x_preferred":[
        "Komyschuwacha"
    ],
    "name:est_x_preferred":[
        "Kom\u00f5\u0161uvahha"
    ],
    "name:hye_x_preferred":[
        "\u053f\u0561\u0574\u056b\u0577\u0587\u0561\u056d\u0561"
    ],
    "name:rus_x_preferred":[
        "\u041a\u0430\u043c\u044b\u0448\u0435\u0432\u0430\u0445\u0430"
    ],
    "name:ukr_x_preferred":[
        "Komyshuvakha"
    ],
    "name:ukr_x_variant":[
        "\u041a\u043e\u043c\u0438\u0448\u0443\u0432\u0430\u0445\u0430"
    ],
    "name:und_x_variant":[
        "Kamshevakha",
        "Kamyshevakha"
    ],
    "wof:name":"Komyshuvakha",
    "wof:placetype":"locality"
},
  "geometry": {"coordinates":[36.59065,47.88882],"type":"Point"}
}