{
  "type": "Feature",
  "properties": {
    "gn:admin1_code":"27.0",
    "gn:asciiname":"Skolobiv",
    "gn:country_code":"UA",
    "gn:dem":222,
    "gn:feature_class":"P",
    "gn:feature_code":"PPL",
    "gn:name":"Skolobiv",
    "gn:population":0,
    "gn:timezone":"Europe/Kiev",
    "iso:country":"UA",
    "name:ukr_x_preferred":[
        "Skolobiv"
    ],
    "name:ukr_x_variant":[
        "\u0421\u043a\u043e\u043b\u043e\u0431\u0456\u0432"
    ],
    "name:und_x_variant":[
        "Skolobov"
    ],
    "wof:name":"Skolobiv",
    "wof:placetype":"locality"
},
  "geometry": {"coordinates":[28.35882,50.51203],"type":"Point"}
}