{
  "type": "Feature",
  "properties": {
    "gn:admin1_code":"5.0",
    "gn:asciiname":"Rybats'ke",
    "gn:country_code":"UA",
    "gn:dem":14,
    "gn:feature_class":"P",
    "gn:feature_code":"PPL",
    "gn:name":"Rybats\u2019ke",
    "gn:population":0,
    "gn:timezone":"Europe/Kiev",
    "iso:country":"UA",
    "name:ukr_x_preferred":[
        "Rybats\u2019ke"
    ],
    "name:ukr_x_variant":[
        "\u0420\u0438\u0431\u0430\u0446\u044c\u043a\u0435"
    ],
    "name:und_x_variant":[
        "Rybatskoye"
    ],
    "wof:name":"Rybats'ke",
    "wof:placetype":"locality"
},
  "geometry": {"coordinates":[37.45298,47.00704],"type":"Point"}
}