{
  "type": "Feature",
  "properties": {
    "gn:admin1_code":"19.0",
    "gn:asciiname":"Yel'ne",
    "gn:country_code":"UA",
    "gn:dem":160,
    "gn:feature_class":"P",
    "gn:feature_code":"PPL",
    "gn:name":"Yel\u2019ne",
    "gn:population":0,
    "gn:timezone":"Europe/Kiev",
    "iso:country":"UA",
    "name:rus_x_preferred":[
        "Yel\u2019no"
    ],
    "name:ukr_x_preferred":[
        "Yel\u2019ne"
    ],
    "name:ukr_x_variant":[
        "\u0404\u043b\u044c\u043d\u0435"
    ],
    "wof:name":"Yel'ne",
    "wof:placetype":"locality"
},
  "geometry": {"coordinates":[27.134,51.45322],"type":"Point"}
}