{
  "type": "Feature",
  "properties": {
    "gn:admin1_code":"16.0",
    "gn:asciiname":"Bezvodnyy",
    "gn:country_code":"UA",
    "gn:dem":51,
    "gn:feature_class":"P",
    "gn:feature_code":"PPL",
    "gn:name":"Bezvodnyy",
    "gn:population":0,
    "gn:timezone":"Europe/Kiev",
    "iso:country":"UA",
    "name:mkd_x_preferred":[
        "\u0411\u0435\u0437\u0432\u043e\u0434\u043d\u0438"
    ],
    "name:msa_x_preferred":[
        "Bezvodnyy"
    ],
    "name:und_x_variant":[
        "Bezvodny"
    ],
    "wof:name":"Bezvodnyy",
    "wof:placetype":"locality"
},
  "geometry": {"coordinates":[31.74286,46.88487],"type":"Point"}
}