{
  "type": "Feature",
  "properties": {
    "gn:admin1_code":"21.0",
    "gn:asciiname":"Kam'yane",
    "gn:country_code":"UA",
    "gn:dem":168,
    "gn:feature_class":"P",
    "gn:feature_code":"PPL",
    "gn:name":"Kam\u2019yane",
    "gn:population":0,
    "gn:timezone":"Europe/Kiev",
    "iso:country":"UA",
    "name:ukr_x_preferred":[
        "Kam\u2019yane"
    ],
    "name:ukr_x_variant":[
        "\u041a\u0430\u043c\u2019\u044f\u043d\u0435"
    ],
    "wof:name":"Kam'yane",
    "wof:placetype":"locality"
},
  "geometry": {"coordinates":[34.9954,50.76284],"type":"Point"}
}