{
  "type": "Feature",
  "properties": {
    "gn:admin1_code":"5.0",
    "gn:asciiname":"Novyy Kavkaz",
    "gn:country_code":"UA",
    "gn:dem":179,
    "gn:feature_class":"P",
    "gn:feature_code":"PPL",
    "gn:name":"Novyy Kavkaz",
    "gn:population":0,
    "gn:timezone":"Europe/Kiev",
    "iso:country":"UA",
    "name:ukr_x_preferred":[
        "Novyy Kavkaz"
    ],
    "name:ukr_x_variant":[
        "\u041d\u043e\u0432\u0438\u0439 \u041a\u0430\u0432\u043a\u0430\u0437"
    ],
    "name:und_x_variant":[
        "Novo-Kavkaz"
    ],
    "wof:name":"Novyy Kavkaz",
    "wof:placetype":"locality"
},
  "geometry": {"coordinates":[36.86083,48.75434],"type":"Point"}
}