{
  "type": "Feature",
  "properties": {
    "iso:country":"UA",
    "name:rus_x_preferred":[
        "\u041f\u043e\u0433\u043e\u0440\u0446\u044b"
    ],
    "name:ukr_x_preferred":[
        "Pohirtsi"
    ],
    "name:ukr_x_variant":[
        "\u041f\u043e\u0433\u0456\u0440\u0446\u0456"
    ],
    "name:und_x_variant":[
        "Pokhortsy"
    ],
    "qs:a0":"\u0423\u043a\u0440\u0430\u0457\u043d\u0430",
    "qs:a1":"*\u041b\u044c\u0432\u0456\u0432\u0441\u044c\u043a\u0430",
    "qs:a1_alt":"L'vivs'ka",
    "qs:a1r":"0",
    "qs:a2":"\u0421\u0430\u043c\u0431\u0456\u0440\u0441\u044c\u043a\u0438\u0439",
    "qs:a2_alt":"Sambirs'kyi",
    "qs:adm0":"\u0423\u043a\u0440\u0430\u0457\u043d\u0430",
    "qs:la_lc":"*",
    "qs:level":"locality",
    "qs:loc":"\u041f\u043e\u0433\u0456\u0440\u0446\u0456",
    "qs:loc_alt":"Pohirtsi",
    "qs:pop":0,
    "qs:type":"buffered point",
    "wof:name":"\u041f\u043e\u0433\u0456\u0440\u0446\u0456",
    "wof:placetype":"locality"
},
  "geometry": {"coordinates":[23.560075,49.593408],"type":"Point"}
}