{
  "type": "Feature",
  "properties": {
    "gn:admin1_code":"9.0",
    "gn:asciiname":"Berezne",
    "gn:country_code":"UA",
    "gn:dem":304,
    "gn:feature_class":"P",
    "gn:feature_code":"PPL",
    "gn:name":"Berezne",
    "gn:population":0,
    "gn:timezone":"Europe/Kiev",
    "iso:country":"UA",
    "name:ara_x_preferred":[
        "\u0628\u064a\u0631\u064a\u0632\u0646\u064a"
    ],
    "name:bel_x_preferred":[
        "\u0411\u044d\u0440\u044d\u0437\u043d\u044d"
    ],
    "name:ces_x_preferred":[
        "Berezne"
    ],
    "name:crh_x_preferred":[
        "Berezne"
    ],
    "name:deu_x_preferred":[
        "Beresne"
    ],
    "name:fas_x_preferred":[
        "\u0628\u0631\u0632\u0646\u0647"
    ],
    "name:fra_x_preferred":[
        "Berezne"
    ],
    "name:heb_x_preferred":[
        "\u05d1\u05e8\u05d6\u05e0\u05d4"
    ],
    "name:hsb_x_preferred":[
        "Berezne"
    ],
    "name:hye_x_preferred":[
        "\u0532\u0565\u0580\u0565\u0566\u0576\u0578"
    ],
    "name:ita_x_preferred":[
        "Berezne"
    ],
    "name:kat_x_preferred":[
        "\u10d1\u10d4\u10e0\u10d4\u10d6\u10dc\u10dd"
    ],
    "name:lav_x_preferred":[
        "Berezne"
    ],
    "name:nno_x_preferred":[
        "Berezne"
    ],
    "name:pol_x_preferred":[
        "Bere\u017ane"
    ],
    "name:ron_x_preferred":[
        "Berezne"
    ],
    "name:rus_x_preferred":[
        "\u0411\u0435\u0440\u0435\u0437\u043d\u043e"
    ],
    "name:spa_x_preferred":[
        "Berezne"
    ],
    "name:ukr_x_preferred":[
        "Berezne"
    ],
    "name:ukr_x_variant":[
        "\u0411\u0435\u0440\u0435\u0437\u043d\u0435"
    ],
    "name:und_x_variant":[
        "Berezovka",
        "Ber\u00ebznoye"
    ],
    "name:vie_x_preferred":[
        "Berezne"
    ],
    "name:zho_x_preferred":[
        "\u5225\u5ed6\u8332\u8afe"
    ],
    "wof:name":"Berezne",
    "wof:placetype":"locality"
},
  "geometry": {"coordinates":[27.04556,49.86886],"type":"Point"}
}