{
  "type": "Feature",
  "properties": {
    "gn:admin1_code":"9.0",
    "gn:asciiname":"Berezne",
    "gn:country_code":"UA",
    "gn:dem":304,
    "gn:feature_class":"P",
    "gn:feature_code":"PPL",
    "gn:name":"Berezne",
    "gn:population":0,
    "gn:timezone":"Europe/Kiev",
    "iso:country":"UA",
    "name:ukr_x_preferred":[
        "Berezne"
    ],
    "name:ukr_x_variant":[
        "\u0411\u0435\u0440\u0435\u0437\u043d\u0435"
    ],
    "name:und_x_variant":[
        "Berezovka",
        "Ber\u00ebznoye"
    ],
    "wof:name":"Berezne",
    "wof:placetype":"locality"
},
  "geometry": {"coordinates":[27.04556,49.86886],"type":"Point"}
}