{
  "type": "Feature",
  "properties": {
    "gn:admin1_code":"26.0",
    "gn:asciiname":"Vostochnyy",
    "gn:cc2":"UA",
    "gn:country_code":"UA",
    "gn:dem":207,
    "gn:feature_class":"P",
    "gn:feature_code":"PPL",
    "gn:name":"Vostochnyy",
    "gn:population":0,
    "gn:timezone":"Europe/Zaporozhye",
    "iso:country":"UA",
    "name:und_x_variant":[
        "Vostochny",
        "Vostochnyy"
    ],
    "wof:name":"Vostochnyy",
    "wof:placetype":"locality"
},
  "geometry": {"coordinates":[36.81667,47.43333],"type":"Point"}
}