{
  "type": "Feature",
  "properties": {
    "gn:admin1_code":"26.0",
    "gn:asciiname":"Shevchenkove",
    "gn:country_code":"UA",
    "gn:dem":155,
    "gn:feature_class":"P",
    "gn:feature_code":"PPL",
    "gn:name":"Shevchenkove",
    "gn:population":0,
    "gn:timezone":"Europe/Zaporozhye",
    "iso:country":"UA",
    "name:ceb_x_preferred":[
        "Shevchenkove"
    ],
    "name:deu_x_preferred":[
        "Schewtschenkowe"
    ],
    "name:hye_x_preferred":[
        "\u0547\u0587\u0579\u0565\u0576\u056f\u0578\u057e\u0578"
    ],
    "name:rus_x_preferred":[
        "\u0428\u0435\u0432\u0447\u0435\u043d\u043a\u043e\u0432\u043e"
    ],
    "name:spa_x_preferred":[
        "Shevchenkove"
    ],
    "name:ukr_x_preferred":[
        "Shevchenkove"
    ],
    "name:ukr_x_variant":[
        "\u0428\u0435\u0431\u0447\u0435\u043d\u043a\u043e\u0432\u0435",
        "\u0428\u0435\u0432\u0447\u0435\u043d\u043a\u043e\u0432\u0435"
    ],
    "name:und_x_variant":[
        "Shevchenkovo"
    ],
    "wof:name":"Shevchenkove",
    "wof:placetype":"locality"
},
  "geometry": {"coordinates":[35.5055,48.03699],"type":"Point"}
}