{
  "type": "Feature",
  "properties": {
    "gn:admin1_code":"17.0",
    "gn:asciiname":"Danylivka",
    "gn:country_code":"UA",
    "gn:dem":101,
    "gn:feature_class":"P",
    "gn:feature_code":"PPL",
    "gn:name":"Danylivka",
    "gn:population":0,
    "gn:timezone":"Europe/Kiev",
    "iso:country":"UA",
    "name:crh_x_preferred":[
        "Ay Danil"
    ],
    "name:rus_x_preferred":[
        "\u0414\u0430\u043d\u0438\u043b\u043e\u0432\u043a\u0430"
    ],
    "name:ukr_x_preferred":[
        "Danylivka"
    ],
    "name:ukr_x_variant":[
        "\u0414\u0430\u043d\u0438\u043b\u0456\u0432\u043a\u0430"
    ],
    "name:und_x_variant":[
        "Danilovka"
    ],
    "wof:name":"Danylivka",
    "wof:placetype":"locality"
},
  "geometry": {"coordinates":[30.61711,47.16764000000001],"type":"Point"}
}