{
  "type": "Feature",
  "properties": {
    "gn:admin1_code":"17.0",
    "gn:asciiname":"Kalahliya",
    "gn:country_code":"UA",
    "gn:dem":33,
    "gn:feature_class":"P",
    "gn:feature_code":"PPL",
    "gn:name":"Kalahliya",
    "gn:population":0,
    "gn:timezone":"Europe/Kiev",
    "iso:country":"UA",
    "name:ukr_x_preferred":[
        "Kalahliya"
    ],
    "name:ukr_x_variant":[
        "\u041a\u0430\u043b\u0430\u0433\u043b\u0456\u044f"
    ],
    "wof:name":"Kalahliya",
    "wof:placetype":"locality"
},
  "geometry": {"coordinates":[30.35837,46.28288],"type":"Point"}
}