{
  "type": "Feature",
  "properties": {
    "gn:admin1_code":"18.0",
    "gn:asciiname":"Vechirky",
    "gn:country_code":"UA",
    "gn:dem":124,
    "gn:feature_class":"P",
    "gn:feature_code":"PPL",
    "gn:name":"Vechirky",
    "gn:population":0,
    "gn:timezone":"Europe/Kiev",
    "iso:country":"UA",
    "name:ukr_x_preferred":[
        "Vechirky"
    ],
    "name:ukr_x_variant":[
        "\u0412\u0435\u0447\u0456\u0440\u043a\u0438"
    ],
    "name:und_x_variant":[
        "Vecherki"
    ],
    "wof:name":"Vechirky",
    "wof:placetype":"locality"
},
  "geometry": {"coordinates":[32.27152,50.34004],"type":"Point"}
}