{
  "type": "Feature",
  "properties": {
    "gn:admin1_code":"16.0",
    "gn:asciiname":"Nay-Karasrue",
    "gn:cc2":"UA",
    "gn:country_code":"UA",
    "gn:dem":36,
    "gn:feature_class":"P",
    "gn:feature_code":"PPL",
    "gn:name":"Nay-Karasrue",
    "gn:population":0,
    "gn:timezone":"Europe/Kiev",
    "iso:country":"UA",
    "name:und_x_variant":[
        "Kalistrovo",
        "Nay-Karasrue"
    ],
    "wof:name":"Nay-Karasrue",
    "wof:placetype":"locality"
},
  "geometry": {"coordinates":[32.31667,47.38333],"type":"Point"}
}