{
  "type": "Feature",
  "properties": {
    "gn:admin1_code":"8.0",
    "gn:asciiname":"Babenkivka Persha",
    "gn:country_code":"UA",
    "gn:dem":11,
    "gn:feature_class":"P",
    "gn:feature_code":"PPL",
    "gn:name":"Babenkivka Persha",
    "gn:population":0,
    "gn:timezone":"Europe/Kiev",
    "iso:country":"UA",
    "name:ukr_x_preferred":[
        "\u0411\u0430\u0431\u0435\u043d\u043a\u0456\u0432\u043a\u0430 \u041f\u0435\u0440\u0448\u0430"
    ],
    "name:und_x_variant":[
        "Babenkovka Pervaya",
        "Babenkivka Persha"
    ],
    "wof:name":"Babenkivka Persha",
    "wof:placetype":"locality"
},
  "geometry": {"coordinates":[33.49512,46.18186],"type":"Point"}
}