{
  "type": "Feature",
  "properties": {
    "gn:admin1_code":"3.0",
    "gn:asciiname":"Shyshkovtse",
    "gn:country_code":"UA",
    "gn:dem":241,
    "gn:feature_class":"P",
    "gn:feature_code":"PPL",
    "gn:name":"Shyshkovtse",
    "gn:population":0,
    "gn:timezone":"Europe/Kiev",
    "iso:country":"UA",
    "name:und_x_variant":[
        "Shishkovtsy",
        "Shyshkovtse"
    ],
    "wof:name":"Shyshkovtse",
    "wof:placetype":"locality"
},
  "geometry": {"coordinates":[25.63356,48.55163],"type":"Point"}
}