{
  "type": "Feature",
  "properties": {
    "gn:admin1_code":"9.0",
    "gn:asciiname":"Novoselka",
    "gn:country_code":"UA",
    "gn:dem":294,
    "gn:feature_class":"P",
    "gn:feature_code":"PPL",
    "gn:name":"Novos\u00eblka",
    "gn:population":0,
    "gn:timezone":"Europe/Kiev",
    "iso:country":"UA",
    "name:und_x_variant":[
        "Novoselki",
        "Novos\u00eblka"
    ],
    "wof:name":"Novoselka",
    "wof:placetype":"locality"
},
  "geometry": {"coordinates":[27.31855,49.24855],"type":"Point"}
}