{
  "type": "Feature",
  "properties": {
    "gn:admin1_code":"27.0",
    "gn:asciiname":"Horopayi",
    "gn:country_code":"UA",
    "gn:dem":278,
    "gn:feature_class":"P",
    "gn:feature_code":"PPL",
    "gn:name":"Horopayi",
    "gn:population":0,
    "gn:timezone":"Europe/Kiev",
    "iso:country":"UA",
    "name:ukr_x_preferred":[
        "Horopayi"
    ],
    "name:ukr_x_variant":[
        "\u0413\u043e\u0440\u043e\u043f\u0430\u0457"
    ],
    "name:und_x_variant":[
        "Goropai"
    ],
    "wof:name":"Horopayi",
    "wof:placetype":"locality"
},
  "geometry": {"coordinates":[27.83407,50.01563],"type":"Point"}
}