{
  "type": "Feature",
  "properties": {
    "gn:admin1_code":"7.0",
    "gn:asciiname":"Yasynuvate",
    "gn:country_code":"UA",
    "gn:dem":189,
    "gn:feature_class":"P",
    "gn:feature_code":"PPL",
    "gn:name":"Yasynuvate",
    "gn:population":0,
    "gn:timezone":"Europe/Kiev",
    "iso:country":"UA",
    "name:ukr_x_preferred":[
        "Yasynuvate"
    ],
    "name:und_x_variant":[
        "Yasenovatyy"
    ],
    "wof:name":"Yasynuvate",
    "wof:placetype":"locality"
},
  "geometry": {"coordinates":[37.44806,49.42694],"type":"Point"}
}