{
  "type": "Feature",
  "properties": {
    "gn:admin1_code":"26.0",
    "gn:asciiname":"Malyy Utlyuh",
    "gn:country_code":"UA",
    "gn:dem":38,
    "gn:feature_class":"P",
    "gn:feature_code":"PPL",
    "gn:name":"Malyy Utlyuh",
    "gn:population":0,
    "gn:timezone":"Europe/Zaporozhye",
    "iso:country":"UA",
    "name:ukr_x_preferred":[
        "Malyy Utlyuh"
    ],
    "name:ukr_x_variant":[
        "\u041c\u0430\u043b\u0438\u0439 \u0423\u0442\u043b\u044e\u0433"
    ],
    "wof:name":"Malyy Utlyuh",
    "wof:placetype":"locality"
},
  "geometry": {"coordinates":[35.0412,46.85446],"type":"Point"}
}