{
  "type": "Feature",
  "properties": {
    "gn:admin1_code":"6.0",
    "gn:asciiname":"Kulynka",
    "gn:country_code":"UA",
    "gn:dem":336,
    "gn:feature_class":"P",
    "gn:feature_code":"PPL",
    "gn:name":"Kulynka",
    "gn:population":0,
    "gn:timezone":"Europe/Kiev",
    "iso:country":"UA",
    "name:ukr_x_preferred":[
        "Kulynka"
    ],
    "name:ukr_x_variant":[
        "\u041a\u0443\u043b\u0438\u043d\u043a\u0430"
    ],
    "name:und_x_variant":[
        "Kulinka"
    ],
    "wof:name":"Kulynka",
    "wof:placetype":"locality"
},
  "geometry": {"coordinates":[24.24758,49.14488],"type":"Point"}
}