{
  "type": "Feature",
  "properties": {
    "gn:admin1_code":"2.0",
    "gn:asciiname":"Petrivka",
    "gn:country_code":"UA",
    "gn:dem":127,
    "gn:feature_class":"P",
    "gn:feature_code":"PPL",
    "gn:name":"Petrivka",
    "gn:population":0,
    "gn:timezone":"Europe/Kiev",
    "iso:country":"UA",
    "name:bel_x_preferred":[
        "\u041f\u044d\u0442\u0440\u044b\u045e\u043a\u0430"
    ],
    "name:deu_x_preferred":[
        "Petriwka"
    ],
    "name:eng_x_preferred":[
        "Petrovka"
    ],
    "name:nld_x_preferred":[
        "Petrivka"
    ],
    "name:pol_x_preferred":[
        "Petriwka"
    ],
    "name:rus_x_preferred":[
        "\u041f\u0435\u0442\u0440\u043e\u0432\u043a\u0430"
    ],
    "name:spa_x_preferred":[
        "Petrivka"
    ],
    "name:ukr_x_preferred":[
        "Petrivka"
    ],
    "name:ukr_x_variant":[
        "\u041f\u0435\u0442\u0440\u0456\u0432\u043a\u0430"
    ],
    "wof:name":"Petrivka",
    "wof:placetype":"locality"
},
  "geometry": {"coordinates":[31.69972000000001,50.5787],"type":"Point"}
}