{
  "type": "Feature",
  "properties": {
    "gn:admin1_code":"23.0",
    "gn:asciiname":"Yarove",
    "gn:country_code":"UA",
    "gn:dem":258,
    "gn:feature_class":"P",
    "gn:feature_code":"PPL",
    "gn:name":"Yarove",
    "gn:population":0,
    "gn:timezone":"Europe/Kiev",
    "iso:country":"UA",
    "name:ukr_x_preferred":[
        "\u042f\u0440\u043e\u0432\u0435"
    ],
    "name:und_x_variant":[
        "Chernchk",
        "Yarove",
        "Kichman\u2019",
        "Yarovoye"
    ],
    "wof:name":"Yarove",
    "wof:placetype":"locality"
},
  "geometry": {"coordinates":[28.50656,48.68807],"type":"Point"}
}