{
  "type": "Feature",
  "properties": {
    "gn:admin1_code":"26.0",
    "gn:asciiname":"Topolyne",
    "gn:country_code":"UA",
    "gn:dem":80,
    "gn:feature_class":"P",
    "gn:feature_code":"PPL",
    "gn:name":"Topolyne",
    "gn:population":0,
    "gn:timezone":"Europe/Zaporozhye",
    "iso:country":"UA",
    "name:ukr_x_preferred":[
        "Topolyne"
    ],
    "name:ukr_x_variant":[
        "\u0422\u043e\u043f\u043e\u043b\u0438\u043d\u0435"
    ],
    "name:und_x_variant":[
        "Shmal\u2019kova",
        "Shmal\u2019ki"
    ],
    "wof:name":"Topolyne",
    "wof:placetype":"locality"
},
  "geometry": {"coordinates":[35.01667,47.28333],"type":"Point"}
}