{
  "type": "Feature",
  "properties": {
    "gn:admin1_code":"27.0",
    "gn:asciiname":"Lypky",
    "gn:country_code":"UA",
    "gn:dem":201,
    "gn:feature_class":"P",
    "gn:feature_code":"PPL",
    "gn:name":"Lypky",
    "gn:population":0,
    "gn:timezone":"Europe/Kiev",
    "iso:country":"UA",
    "name:ukr_x_preferred":[
        "Lypky"
    ],
    "name:ukr_x_variant":[
        "\u041b\u0438\u043f\u043a\u0438"
    ],
    "name:und_x_variant":[
        "Lipki"
    ],
    "wof:name":"Lypky",
    "wof:placetype":"locality"
},
  "geometry": {"coordinates":[29.41622000000001,50.0688],"type":"Point"}
}