{
  "type": "Feature",
  "properties": {
    "gn:admin1_code":"21.0",
    "gn:asciiname":"Shutovka",
    "gn:country_code":"UA",
    "gn:dem":150,
    "gn:feature_class":"P",
    "gn:feature_code":"PPL",
    "gn:name":"Shutovka",
    "gn:population":0,
    "gn:timezone":"Europe/Kiev",
    "iso:country":"UA",
    "wof:name":"Shutovka",
    "wof:placetype":"locality"
},
  "geometry": {"coordinates":[34.05,51.63333],"type":"Point"}
}