{
  "type": "Feature",
  "properties": {
    "iso:country":"UA",
    "name:und_x_variant":[
        "Yampol\u2019"
    ],
    "qs:a0":"\u0423\u043a\u0440\u0430\u0457\u043d\u0430",
    "qs:a1":"*\u0425\u043c\u0435\u043b\u044c\u043d\u0438\u0446\u044c\u043a\u0430",
    "qs:a1_alt":"Khmel'nyts'ka",
    "qs:a1r":"0",
    "qs:a2":"\u0411\u0456\u043b\u043e\u0433\u0456\u0440\u0441\u044c\u043a\u0438\u0439",
    "qs:a2_alt":"Bilohirs'kyi",
    "qs:adm0":"\u0423\u043a\u0440\u0430\u0457\u043d\u0430",
    "qs:la_lc":"*",
    "qs:level":"locality",
    "qs:loc":"\u042f\u043c\u043f\u0456\u043b\u044c",
    "qs:loc_alt":"Yampil",
    "qs:pop":0,
    "qs:type":"buffered point",
    "wd:wordcount":109,
    "wof:name":"\u042f\u043c\u043f\u0456\u043b\u044c",
    "wof:placetype":"locality"
},
  "geometry": {"coordinates":[26.229771,49.958046],"type":"Point"}
}