{
  "type": "Feature",
  "properties": {
    "gn:admin1_code":"3.0",
    "gn:asciiname":"Velykyy Lypovets'",
    "gn:country_code":"UA",
    "gn:dem":851,
    "gn:feature_class":"P",
    "gn:feature_code":"PPL",
    "gn:name":"Velykyy Lypovets\u2019",
    "gn:population":0,
    "gn:timezone":"Europe/Kiev",
    "iso:country":"UA",
    "name:ukr_x_preferred":[
        "Velykyy Lypovets\u2019"
    ],
    "name:ukr_x_variant":[
        "\u0412\u0435\u043b\u0438\u043a\u0438\u0439 \u041b\u0438\u043f\u043e\u0432\u0435\u0446\u044c"
    ],
    "name:und_x_variant":[
        "Velikiy Lipovets"
    ],
    "wof:name":"Velykyy Lypovets'",
    "wof:placetype":"locality"
},
  "geometry": {"coordinates":[24.97521,48.04376],"type":"Point"}
}