{
  "type": "Feature",
  "properties": {
    "gn:admin1_code":"18.0",
    "gn:asciiname":"Chervoni Luky",
    "gn:country_code":"UA",
    "gn:dem":109,
    "gn:feature_class":"P",
    "gn:feature_code":"PPL",
    "gn:name":"Chervoni Luky",
    "gn:population":0,
    "gn:timezone":"Europe/Kiev",
    "iso:country":"UA",
    "name:ukr_x_preferred":[
        "Chervoni Luky"
    ],
    "name:ukr_x_variant":[
        "\u0427\u0435\u0440\u0432\u043e\u043d\u0456 \u041b\u0443\u043a\u0438"
    ],
    "name:und_x_variant":[
        "Chervonyye Luki"
    ],
    "wof:name":"Chervoni Luky",
    "wof:placetype":"locality"
},
  "geometry": {"coordinates":[33.55087,50.30798],"type":"Point"}
}