{
  "type": "Feature",
  "properties": {
    "iso:country":"UA",
    "name:deu_x_preferred":[
        "Tarassiwka"
    ],
    "name:eng_x_preferred":[
        "Tarasovka"
    ],
    "name:eng_x_variant":[
        "Tarasivka"
    ],
    "name:hye_x_preferred":[
        "\u054f\u0561\u0580\u0561\u057d\u0578\u057e\u056f\u0561"
    ],
    "name:ron_x_preferred":[
        "Tarasivka"
    ],
    "name:rus_x_preferred":[
        "\u0422\u0430\u0440\u0430\u0441\u043e\u0432\u043a\u0430"
    ],
    "name:ukr_x_preferred":[
        "Tarasivka"
    ],
    "name:ukr_x_variant":[
        "\u0422\u0430\u0440\u0430\u0441\u0456\u0432\u043a\u0430"
    ],
    "name:unk_x_variant":[
        "Tarasovka"
    ],
    "name:zho_x_preferred":[
        "\u5854\u62c9\u897f\u592b\u5361"
    ],
    "qs:a0":"\u0423\u043a\u0440\u0430\u0457\u043d\u0430",
    "qs:a1":"*\u041f\u043e\u043b\u0442\u0430\u0432\u0441\u044c\u043a\u0430",
    "qs:a1_alt":"Poltavs'ka",
    "qs:a1r":"0",
    "qs:a2":"\u0417\u0456\u043d\u044c\u043a\u0456\u0432\u0441\u044c\u043a\u0438\u0439",
    "qs:a2_alt":"Zin'kivs'kyi",
    "qs:adm0":"\u0423\u043a\u0440\u0430\u0457\u043d\u0430",
    "qs:la_lc":"*",
    "qs:level":"locality",
    "qs:loc":"\u0422\u0430\u0440\u0430\u0441\u0456\u0432\u043a\u0430",
    "qs:loc_alt":"Tarasivka",
    "qs:pop":0,
    "qs:type":"buffered point",
    "wof:name":"\u0422\u0430\u0440\u0430\u0441\u0456\u0432\u043a\u0430",
    "wof:placetype":"locality"
},
  "geometry": {"coordinates":[34.347951,50.243657],"type":"Point"}
}