{
  "type": "Feature",
  "properties": {
    "iso:country":"UA",
    "name:rus_x_preferred":[
        "\u0427\u0435\u0440\u0435\u043f\u0430\u043d\u043e\u0432\u0430 \u0433\u043e\u0440\u0430"
    ],
    "name:ukr_x_preferred":[
        "\u0427\u0435\u0440\u0435\u043f\u0430\u043d\u043e\u0432\u0430 \u0433\u043e\u0440\u0430"
    ],
    "wof:name":"Cherepanova Hora",
    "wof:placetype":"neighbourhood"
},
  "geometry": {"coordinates":[30.52683047939719,50.42887733651951],"type":"Point"}
}