{
  "type": "Feature",
  "properties": {
    "gn:admin1_code":"13.0",
    "gn:asciiname":"Otday-Pole",
    "gn:country_code":"UA",
    "gn:dem":222,
    "gn:feature_class":"P",
    "gn:feature_code":"PPL",
    "gn:name":"Otday-Pole",
    "gn:population":0,
    "gn:timezone":"Europe/Kiev",
    "iso:country":"UA",
    "name:und_x_variant":[
        "Oddaypil\u2019",
        "Otday-Pole"
    ],
    "wof:name":"Otday-Pole",
    "wof:placetype":"locality"
},
  "geometry": {"coordinates":[29.9749,49.33709],"type":"Point"}
}