{
  "type": "Feature",
  "properties": {
    "gn:admin1_code":"18.0",
    "gn:asciiname":"Shyshats'ke",
    "gn:country_code":"UA",
    "gn:dem":132,
    "gn:feature_class":"P",
    "gn:feature_code":"PPL",
    "gn:name":"Shyshats\u2019ke",
    "gn:population":0,
    "gn:timezone":"Europe/Kiev",
    "iso:country":"UA",
    "name:ukr_x_preferred":[
        "Shyshats\u2019ke"
    ],
    "name:ukr_x_variant":[
        "\u0428\u0438\u0448\u0430\u0446\u044c\u043a\u0435"
    ],
    "wof:name":"Shyshats'ke",
    "wof:placetype":"locality"
},
  "geometry": {"coordinates":[34.07339,49.67908],"type":"Point"}
}