{
  "type": "Feature",
  "properties": {
    "iso:country":"UA",
    "qs_pg:aaroncc":"UA",
    "qs_pg:name":"Vinogradov",
    "qs_pg:name_adm0":"Ukraine",
    "qs_pg:name_adm1":"Zakarpats\u00b4ka Oblast\u00b4",
    "qs_pg:photos":86,
    "qs_pg:photos_1k":17,
    "qs_pg:photos_9k":1,
    "qs_pg:photos_9r":3,
    "qs_pg:photos_all":86,
    "qs_pg:photos_sr":3,
    "qs_pg:pop_sr":0,
    "qs_pg:qs_pg_placetype":"locality",
    "qs_pg:qs_pg_placetype_gp":"Town",
    "qs_pg:woe_adm0":23424976,
    "woe:adm0_id":23424976,
    "woe:name_adm0":"Ukraine",
    "woe:name_adm1":"Zakarpats\u00b4ka Oblast\u00b4",
    "woe:placetype":"Town",
    "wof:name":"Vinogradov",
    "wof:placetype":"locality"
},
  "geometry": {"coordinates":[23.046569,48.138599],"type":"Point"}
}