{
  "type": "Feature",
  "properties": {
    "gn:admin1_code":"2.0",
    "gn:asciiname":"Korniyiv",
    "gn:country_code":"UA",
    "gn:dem":114,
    "gn:feature_class":"P",
    "gn:feature_code":"PPL",
    "gn:name":"Korniyiv",
    "gn:population":0,
    "gn:timezone":"Europe/Kiev",
    "iso:country":"UA",
    "name:ukr_x_preferred":[
        "Korniyiv"
    ],
    "name:ukr_x_variant":[
        "\u041a\u043e\u0440\u043d\u0456\u0457\u0432"
    ],
    "name:und_x_variant":[
        "Korneyev"
    ],
    "wof:name":"Korniyiv",
    "wof:placetype":"locality"
},
  "geometry": {"coordinates":[31.11415,50.83293],"type":"Point"}
}