{
  "type": "Feature",
  "properties": {
    "gn:admin1_code":"2.0",
    "gn:asciiname":"Maybutnye",
    "gn:country_code":"UA",
    "gn:dem":147,
    "gn:feature_class":"P",
    "gn:feature_code":"PPL",
    "gn:name":"Maybutnye",
    "gn:population":0,
    "gn:timezone":"Europe/Kiev",
    "iso:country":"UA",
    "name:ukr_x_preferred":[
        "Maybutnye"
    ],
    "name:ukr_x_variant":[
        "\u041c\u0430\u0439\u0431\u0443\u0442\u043d\u0454"
    ],
    "name:und_x_variant":[
        "Maybutne"
    ],
    "wof:name":"Maybutnye",
    "wof:placetype":"locality"
},
  "geometry": {"coordinates":[32.46517,51.96252],"type":"Point"}
}