{
  "type": "Feature",
  "properties": {
    "iso:country":"UA",
    "name:ara_x_preferred":[
        "\u062c\u0648\u0631\u0627\u0641\u0646\u0648"
    ],
    "name:arm_x_preferred":[
        "\u053a\u0578\u0582\u0580\u0561\u057e\u0576\u0578"
    ],
    "name:bel_x_preferred":[
        "\u0416\u0443\u0440\u0430\u045e\u043d\u0430"
    ],
    "name:chi_x_preferred":[
        "\u8339\u62c9\u592b\u8afe"
    ],
    "name:crh_x_preferred":[
        "Juravno"
    ],
    "name:cze_x_preferred":[
        "\u017burawno"
    ],
    "name:deu_x_preferred":[
        "Schurawno"
    ],
    "name:eng_x_preferred":[
        "Zhuravno"
    ],
    "name:fra_x_preferred":[
        "Jouravno"
    ],
    "name:fre_x_preferred":[
        "Jouravno"
    ],
    "name:ger_x_preferred":[
        "Schurawno"
    ],
    "name:heb_x_preferred":[
        "\u05d6'\u05d5\u05e8\u05d0\u05d1\u05e0\u05d5"
    ],
    "name:hye_x_preferred":[
        "\u053a\u0578\u0582\u0580\u0561\u057e\u0576\u0578"
    ],
    "name:pol_x_preferred":[
        "\u017burawno"
    ],
    "name:rum_x_preferred":[
        "Juravne"
    ],
    "name:rus_x_preferred":[
        "\u0416\u0443\u0440\u0430\u0432\u043d\u043e"
    ],
    "name:slv_x_preferred":[
        "Zhuravno"
    ],
    "name:ukr_x_preferred":[
        "\u0416\u0443\u0440\u0430\u0432\u043d\u043e"
    ],
    "name:unk_x_variant":[
        "\u017burawno"
    ],
    "name:zho_x_preferred":[
        "\u8339\u62c9\u592b\u8afe"
    ],
    "qs:a0":"\u0423\u043a\u0440\u0430\u0457\u043d\u0430",
    "qs:a1":"*\u041b\u044c\u0432\u0456\u0432\u0441\u044c\u043a\u0430",
    "qs:a1_alt":"L'vivs'ka",
    "qs:a1r":"0",
    "qs:a2":"\u0416\u0438\u0434\u0430\u0447\u0456\u0432\u0441\u044c\u043a\u0438\u0439",
    "qs:a2_alt":"Zhydachivs'kyi",
    "qs:adm0":"\u0423\u043a\u0440\u0430\u0457\u043d\u0430",
    "qs:la_lc":"*",
    "qs:level":"locality",
    "qs:loc":"\u0416\u0443\u0440\u0430\u0432\u043d\u043e",
    "qs:loc_alt":"Zhuravno",
    "qs:pop":0,
    "qs:type":"buffered point",
    "wd:wordcount":138,
    "wof:name":"\u0416\u0443\u0440\u0430\u0432\u043d\u043e",
    "wof:placetype":"locality"
},
  "geometry": {"coordinates":[24.27694,49.261052],"type":"Point"}
}