{
  "type": "Feature",
  "properties": {
    "gn:admin1_code":"4.0",
    "gn:asciiname":"Komunarivka",
    "gn:country_code":"UA",
    "gn:dem":171,
    "gn:feature_class":"P",
    "gn:feature_code":"PPL",
    "gn:name":"Komunarivka",
    "gn:population":0,
    "gn:timezone":"Europe/Kiev",
    "iso:country":"UA",
    "name:rus_x_preferred":[
        "\u041a\u043e\u043c\u043c\u0443\u043d\u0432\u0430\u0440\u043e\u0432\u043a\u0430"
    ],
    "name:ukr_x_preferred":[
        "Komunarivka"
    ],
    "name:ukr_x_variant":[
        "\u041a\u043e\u043c\u0443\u043d\u0430\u0440\u0456\u0432\u043a\u0430"
    ],
    "name:und_x_variant":[
        "Kommunarovka"
    ],
    "wof:name":"Komunarivka",
    "wof:placetype":"locality"
},
  "geometry": {"coordinates":[33.90948,48.59824],"type":"Point"}
}