{
  "type": "Feature",
  "properties": {
    "iso:country":"UA",
    "name:eng_x_preferred":[
        "Medvedivtsi"
    ],
    "name:pol_x_preferred":[
        "Medwedowce"
    ],
    "name:ron_x_preferred":[
        "Medvediv\u021bi"
    ],
    "name:rus_x_preferred":[
        "\u041c\u0435\u0434\u0432\u0435\u0434\u0435\u0432\u0446\u044b"
    ],
    "name:ukr_x_preferred":[
        "\u041c\u0435\u0434\u0432\u0435\u0434\u0456\u0432\u0446\u0456"
    ],
    "name:unk_x_variant":[
        "Medvedivtsi"
    ],
    "qs:a0":"\u0423\u043a\u0440\u0430\u0457\u043d\u0430",
    "qs:a1":"*\u0422\u0435\u0440\u043d\u043e\u043f\u0456\u043b\u044c\u0441\u044c\u043a\u0430",
    "qs:a1_alt":"Ternopil's'ka",
    "qs:a1r":"0",
    "qs:a2":"\u0411\u0443\u0447\u0430\u0446\u044c\u043a\u0438\u0439",
    "qs:a2_alt":"Buchats'kyi",
    "qs:adm0":"\u0423\u043a\u0440\u0430\u0457\u043d\u0430",
    "qs:la_lc":"*",
    "qs:level":"locality",
    "qs:loc":"\u041c\u0435\u0434\u0432\u0435\u0434\u0456\u0432\u0446\u0456",
    "qs:loc_alt":"Medvedivtsi",
    "qs:pop":0,
    "qs:type":"buffered point",
    "wd:wordcount":84,
    "wof:name":"\u041c\u0435\u0434\u0432\u0435\u0434\u0456\u0432\u0446\u0456",
    "wof:placetype":"locality"
},
  "geometry": {"coordinates":[25.443434,49.092768],"type":"Point"}
}