{
  "type": "Feature",
  "properties": {
    "iso:country":"UA",
    "name:eng_x_preferred":[
        "Aleksandrovka"
    ],
    "name:rus_x_historical":[
        "\u0411\u0438\u0439-\u0410\u043a\u0430\u0301\u0439-\u041a\u0435\u043c\u0435\u043b\u044c\u0447\u0438\u0301"
    ],
    "name:rus_x_preferred":[
        "\u0410\u043b\u0435\u043a\u0441\u0430\u043d\u0434\u0440\u043e\u0432\u043a\u0430"
    ],
    "name:rus_x_variant":[
        "\u0411\u0438\u0439-\u0410\u043a\u0430\u0301\u0439-\u041a\u0435\u043c\u0435\u043b\u044c\u0447\u0438\u0301"
    ],
    "name:ukr_x_preferred":[
        "\u041e\u043b\u0435\u043a\u0441\u0430\u043d\u0434\u0440\u0456\u0432\u043a\u0430"
    ],
    "qs:a0":"\u0423\u043a\u0440\u0430\u0457\u043d\u0430",
    "qs:a1":"*\u041a\u0440\u0438\u043c",
    "qs:a1_alt":"Krym",
    "qs:a1r":"0",
    "qs:a2":"\u041a\u0440\u0430\u0441\u043d\u043e\u0433\u0432\u0430\u0440\u0434\u0456\u0439\u0441\u044c\u043a\u0438\u0439",
    "qs:a2_alt":"Krasnohvardiis'kyi",
    "qs:adm0":"\u0423\u043a\u0440\u0430\u0457\u043d\u0430",
    "qs:la_lc":"*",
    "qs:level":"locality",
    "qs:loc":"\u041e\u043b\u0435\u043a\u0441\u0430\u043d\u0434\u0440\u0456\u0432\u043a\u0430",
    "qs:loc_alt":"Oleksandrivka",
    "qs:pop":0,
    "qs:type":"buffered point",
    "wd:wordcount":153,
    "wof:name":"\u041e\u043b\u0435\u043a\u0441\u0430\u043d\u0434\u0440\u0456\u0432\u043a\u0430",
    "wof:placetype":"locality"
},
  "geometry": {"coordinates":[34.105153,45.571109],"type":"Point"}
}