{
  "type": "Feature",
  "properties": {
    "gn:admin1_code":"4.0",
    "gn:asciiname":"Serhiyivka",
    "gn:country_code":"UA",
    "gn:dem":104,
    "gn:feature_class":"P",
    "gn:feature_code":"PPL",
    "gn:name":"Serhiyivka",
    "gn:population":0,
    "gn:timezone":"Europe/Kiev",
    "iso:country":"UA",
    "name:eng_x_preferred":[
        "Sergeyevka"
    ],
    "name:rus_x_preferred":[
        "\u0421\u0435\u0440\u0433\u0435\u0435\u0432\u043a\u0430"
    ],
    "name:ukr_x_preferred":[
        "Serhiyivka"
    ],
    "name:ukr_x_variant":[
        "\u0421\u0435\u0440\u0433\u0456\u0457\u0432\u043a\u0430"
    ],
    "wof:name":"Serhiyivka",
    "wof:placetype":"locality"
},
  "geometry": {"coordinates":[35.76063,48.79475],"type":"Point"}
}