{
  "type": "Feature",
  "properties": {
    "gn:admin1_code":"5.0",
    "gn:asciiname":"Brazhyne",
    "gn:country_code":"UA",
    "gn:dem":213,
    "gn:feature_class":"P",
    "gn:feature_code":"PPL",
    "gn:name":"Brazhyne",
    "gn:population":0,
    "gn:timezone":"Europe/Kiev",
    "iso:country":"UA",
    "name:eng_x_preferred":[
        "Brazhyne"
    ],
    "name:rus_x_preferred":[
        "\u0411\u0440\u0430\u0436\u0438\u043d\u0435"
    ],
    "name:rus_x_variant":[
        "\u0411\u0440\u0430\u0436\u0438\u043d\u043e"
    ],
    "name:ukr_x_preferred":[
        "\u0411\u0440\u0430\u0436\u0438\u043d\u0435"
    ],
    "name:und_x_variant":[
        "Brazhino"
    ],
    "wof:name":"Brazhyne",
    "wof:placetype":"locality"
},
  "geometry": {"coordinates":[38.83563,47.99838],"type":"Point"}
}