{
  "type": "Feature",
  "properties": {
    "gn:admin1_code":"0.0",
    "gn:asciiname":"Zhelon'-Sitovka",
    "gn:country_code":"UA",
    "gn:dem":148,
    "gn:feature_class":"P",
    "gn:feature_code":"PPL",
    "gn:name":"Zhelon\u2019-Sitovka",
    "gn:population":0,
    "gn:timezone":"Europe/Kiev",
    "iso:country":"UA",
    "name:und_x_variant":[
        "Zhelon\u2019",
        "Zhelon\u2019-Sitovka"
    ],
    "wof:name":"Zhelon'-Sitovka",
    "wof:placetype":"locality"
},
  "geometry": {"coordinates":[29.23333,51.46667],"type":"Point"}
}