{
  "type": "Feature",
  "properties": {
    "gn:admin1_code":"2.0",
    "gn:asciiname":"Slava",
    "gn:country_code":"UA",
    "gn:dem":141,
    "gn:feature_class":"P",
    "gn:feature_code":"PPL",
    "gn:name":"Slava",
    "gn:population":0,
    "gn:timezone":"Europe/Kiev",
    "iso:country":"UA",
    "name:ukr_x_preferred":[
        "Slava"
    ],
    "name:ukr_x_variant":[
        "\u0421\u043b\u0430\u0432\u0430"
    ],
    "wof:name":"Slava",
    "wof:placetype":"locality"
},
  "geometry": {"coordinates":[32.18965,51.96477],"type":"Point"}
}