{
  "type": "Feature",
  "properties": {
    "gn:admin1_code":"21.0",
    "gn:asciiname":"Katerynivka",
    "gn:country_code":"UA",
    "gn:dem":168,
    "gn:feature_class":"P",
    "gn:feature_code":"PPL",
    "gn:name":"Katerynivka",
    "gn:population":0,
    "gn:timezone":"Europe/Kiev",
    "iso:country":"UA",
    "name:ukr_x_preferred":[
        "Katerynivka"
    ],
    "name:ukr_x_variant":[
        "\u041a\u0430\u0442\u0435\u0440\u0438\u043d\u0456\u0432\u043a\u0430"
    ],
    "name:und_x_variant":[
        "Yekaterinovka",
        "Katerinovka"
    ],
    "wof:name":"Katerynivka",
    "wof:placetype":"locality"
},
  "geometry": {"coordinates":[34.5637,51.21209],"type":"Point"}
}