{
  "type": "Feature",
  "properties": {
    "gn:admin1_code":"27.0",
    "gn:asciiname":"Velykyy Molod'kiv",
    "gn:country_code":"UA",
    "gn:dem":222,
    "gn:feature_class":"P",
    "gn:feature_code":"PPL",
    "gn:name":"Velykyy Molod\u2019kiv",
    "gn:population":0,
    "gn:timezone":"Europe/Kiev",
    "iso:country":"UA",
    "name:ukr_x_preferred":[
        "Velykyy Molod\u2019kiv"
    ],
    "name:ukr_x_variant":[
        "\u0412\u0435\u043b\u0438\u043a\u0438\u0439 \u041c\u043e\u043b\u043e\u0434\u044c\u043a\u0456\u0432"
    ],
    "name:und_x_variant":[
        "Bol\u2019shoy Molod\u2019kov",
        "Velikiy Molod\u2019kov"
    ],
    "wof:name":"Velykyy Molod'kiv",
    "wof:placetype":"locality"
},
  "geometry": {"coordinates":[27.42024,50.58351],"type":"Point"}
}