{
  "type": "Feature",
  "properties": {
    "gn:population":6054,
    "iso:country":"UA",
    "name:ceb_x_preferred":[
        "Kosmach"
    ],
    "name:deu_x_preferred":[
        "Kosmatsch"
    ],
    "name:eng_x_preferred":[
        "Kosmach"
    ],
    "name:pol_x_preferred":[
        "Kosmacz"
    ],
    "name:ron_x_preferred":[
        "Kosmaci"
    ],
    "name:rus_x_preferred":[
        "\u041a\u043e\u0441\u043c\u0430\u0447"
    ],
    "name:ukr_x_preferred":[
        "\u041a\u043e\u0441\u043c\u0430\u0447"
    ],
    "name:zho_x_preferred":[
        "\u79d1\u65af\u99ac\u5947"
    ],
    "qs:a0":"\u0423\u043a\u0440\u0430\u0457\u043d\u0430",
    "qs:a1":"*\u0406\u0432\u0430\u043d\u043e-\u0424\u0440\u0430\u043d\u043a\u0456\u0432\u0441\u044c\u043a\u0430",
    "qs:a1_alt":"Ivano-Frankivs'ka",
    "qs:a1r":"0",
    "qs:a2":"\u041a\u043e\u0441\u0456\u0432\u0441\u044c\u043a\u0438\u0439",
    "qs:a2_alt":"Kosivs'kyi",
    "qs:adm0":"\u0423\u043a\u0440\u0430\u0457\u043d\u0430",
    "qs:la_lc":"*",
    "qs:level":"locality",
    "qs:loc":"\u041a\u043e\u0441\u043c\u0430\u0447",
    "qs:loc_alt":"Kosmach",
    "qs:pop":0,
    "qs:type":"buffered point",
    "wd:wordcount":49,
    "wof:name":"\u041a\u043e\u0441\u043c\u0430\u0447",
    "wof:placetype":"locality",
    "wof:population":6054
},
  "geometry": {"coordinates":[24.84474,48.327098],"type":"Point"}
}