{
  "type": "Feature",
  "properties": {
    "gn:admin1_code":"4.0",
    "gn:asciiname":"Spasovskiy",
    "gn:cc2":"UA",
    "gn:country_code":"UA",
    "gn:dem":66,
    "gn:feature_class":"P",
    "gn:feature_code":"PPL",
    "gn:name":"Spasovskiy",
    "gn:population":0,
    "gn:timezone":"Europe/Kiev",
    "iso:country":"UA",
    "name:und_x_variant":[
        "Pos\u00eblok Spasovskiy",
        "Spasovskiy"
    ],
    "wof:name":"Spasovskiy",
    "wof:placetype":"locality"
},
  "geometry": {"coordinates":[33.85,47.83333],"type":"Point"}
}