{
  "type": "Feature",
  "properties": {
    "gn:admin1_code":"27.0",
    "gn:asciiname":"Kustyn",
    "gn:country_code":"UA",
    "gn:dem":244,
    "gn:feature_class":"P",
    "gn:feature_code":"PPL",
    "gn:name":"Kustyn",
    "gn:population":0,
    "gn:timezone":"Europe/Kiev",
    "iso:country":"UA",
    "name:ukr_x_preferred":[
        "Kustyn"
    ],
    "name:ukr_x_variant":[
        "\u041a\u0443\u0441\u0442\u0438\u043d"
    ],
    "name:und_x_variant":[
        "Kustin"
    ],
    "wof:name":"Kustyn",
    "wof:placetype":"locality"
},
  "geometry": {"coordinates":[28.47475,49.9374],"type":"Point"}
}