{
  "type": "Feature",
  "properties": {
    "gn:admin1_code":"4.0",
    "gn:asciiname":"Zorya",
    "gn:country_code":"UA",
    "gn:dem":25,
    "gn:feature_class":"P",
    "gn:feature_code":"PPL",
    "gn:name":"Zorya",
    "gn:population":0,
    "gn:timezone":"Europe/Kiev",
    "iso:country":"UA",
    "name:rus_x_preferred":[
        "\u0417\u0430\u0440\u044f"
    ],
    "name:ukr_x_preferred":[
        "Zorya"
    ],
    "name:ukr_x_variant":[
        "\u0417\u043e\u0440\u044f"
    ],
    "name:und_x_variant":[
        "Zarya"
    ],
    "wof:name":"Zorya",
    "wof:placetype":"locality"
},
  "geometry": {"coordinates":[34.68096,47.69552],"type":"Point"}
}