{
  "type": "Feature",
  "properties": {
    "gn:admin1_code":"26.0",
    "gn:asciiname":"Blyumenort",
    "gn:country_code":"UA",
    "gn:dem":27,
    "gn:feature_class":"P",
    "gn:feature_code":"PPL",
    "gn:name":"Blyumenort",
    "gn:population":0,
    "gn:timezone":"Europe/Zaporozhye",
    "iso:country":"UA",
    "wof:name":"Blyumenort",
    "wof:placetype":"locality"
},
  "geometry": {"coordinates":[35.59531,47.07257],"type":"Point"}
}