{
  "type": "Feature",
  "properties": {
    "gn:population":6412,
    "iso:country":"UA",
    "name:eng_x_preferred":[
        "Lozuvatka"
    ],
    "name:eng_x_variant":[
        "Lozovatka"
    ],
    "name:rus_x_preferred":[
        "\u041b\u043e\u0437\u043e\u0432\u0430\u0442\u043a\u0430"
    ],
    "name:rus_x_variant":[
        "\u041b\u043e\u0437\u0443\u0432\u0430\u0442\u043a\u0430"
    ],
    "name:ukr_x_preferred":[
        "\u041b\u043e\u0437\u0443\u0432\u0430\u0442\u043a\u0430"
    ],
    "qs:a0":"\u0423\u043a\u0440\u0430\u0457\u043d\u0430",
    "qs:a1":"*\u0414\u043d\u0456\u043f\u0440\u043e\u043f\u0435\u0442\u0440\u043e\u0432\u0441\u044c\u043a\u0430",
    "qs:a1_alt":"Dnipropetrovs'ka",
    "qs:a1r":"0",
    "qs:a2":"\u041a\u0440\u0438\u0432\u043e\u0440\u0456\u0437\u044c\u043a\u0438\u0439",
    "qs:a2_alt":"Kryvoriz'kyi",
    "qs:adm0":"\u0423\u043a\u0440\u0430\u0457\u043d\u0430",
    "qs:la_lc":"*",
    "qs:level":"locality",
    "qs:loc":"\u041b\u043e\u0437\u0443\u0432\u0430\u0442\u043a\u0430",
    "qs:loc_alt":"Lozuvatka",
    "qs:pop":0,
    "qs:type":"buffered point",
    "wof:name":"\u041b\u043e\u0437\u0443\u0432\u0430\u0442\u043a\u0430",
    "wof:placetype":"locality",
    "wof:population":6412
},
  "geometry": {"coordinates":[33.287496,48.052198],"type":"Point"}
}