{
  "type": "Feature",
  "properties": {
    "gn:admin1_code":"14.0",
    "gn:asciiname":"Shlyakhtino",
    "gn:country_code":"UA",
    "gn:dem":197,
    "gn:feature_class":"P",
    "gn:feature_code":"PPL",
    "gn:name":"Shlyakhtino",
    "gn:population":0,
    "gn:timezone":"Europe/Zaporozhye",
    "iso:country":"UA",
    "wof:name":"Shlyakhtino",
    "wof:placetype":"locality"
},
  "geometry": {"coordinates":[39.44778,48.18861],"type":"Point"}
}