{
  "type": "Feature",
  "properties": {
    "gn:admin1_code":"14.0",
    "gn:asciiname":"Voroshilovskiy",
    "gn:country_code":"UA",
    "gn:dem":159,
    "gn:feature_class":"P",
    "gn:feature_code":"PPL",
    "gn:name":"Voroshilovskiy",
    "gn:population":0,
    "gn:timezone":"Europe/Zaporozhye",
    "iso:country":"UA",
    "wof:name":"Voroshilovskiy",
    "wof:placetype":"locality"
},
  "geometry": {"coordinates":[39.11139,48.42694],"type":"Point"}
}