{
  "type": "Feature",
  "properties": {
    "iso:country":"UA",
    "name:rus_x_preferred":[
        "Zagal\u2019tsy"
    ],
    "name:ukr_x_preferred":[
        "Zahal\u2019tsi"
    ],
    "name:ukr_x_variant":[
        "\u0417\u0430\u0433\u0430\u043b\u044c\u0446\u0456"
    ],
    "qs:a0":"\u0423\u043a\u0440\u0430\u0457\u043d\u0430",
    "qs:a1":"*\u041a\u0438\u0457\u0432\u0441\u044c\u043a\u0430",
    "qs:a1_alt":"Kyivs'ka",
    "qs:a1r":"0",
    "qs:a2":"\u0411\u043e\u0440\u043e\u0434\u044f\u043d\u0441\u044c\u043a\u0438\u0439",
    "qs:a2_alt":"Borodians'kyi",
    "qs:adm0":"\u0423\u043a\u0440\u0430\u0457\u043d\u0430",
    "qs:la_lc":"*",
    "qs:level":"locality",
    "qs:loc":"\u0417\u0430\u0433\u0430\u043b\u044c\u0446\u0456",
    "qs:loc_alt":"Zahal'tsi",
    "qs:pop":0,
    "qs:type":"buffered point",
    "wof:name":"\u0417\u0430\u0433\u0430\u043b\u044c\u0446\u0456",
    "wof:placetype":"locality"
},
  "geometry": {"coordinates":[29.809121,50.664985],"type":"Point"}
}