{
  "type": "Feature",
  "properties": {
    "gn:admin1_code":"18.0",
    "gn:asciiname":"Zamoriyivka",
    "gn:country_code":"UA",
    "gn:dem":122,
    "gn:feature_class":"P",
    "gn:feature_code":"PPL",
    "gn:name":"Zamoriyivka",
    "gn:population":0,
    "gn:timezone":"Europe/Kiev",
    "iso:country":"UA",
    "name:ukr_x_preferred":[
        "Zamoriyivka"
    ],
    "name:ukr_x_variant":[
        "\u0417\u0430\u043c\u043e\u0440\u0456\u0457\u0432\u043a\u0430"
    ],
    "name:und_x_variant":[
        "Zamoriyevka"
    ],
    "wof:name":"Zamoriyivka",
    "wof:placetype":"locality"
},
  "geometry": {"coordinates":[33.56783,50.31936],"type":"Point"}
}