{
  "type": "Feature",
  "properties": {
    "gn:admin1_code":"7.0",
    "gn:asciiname":"Prohres",
    "gn:country_code":"UA",
    "gn:dem":166,
    "gn:feature_class":"P",
    "gn:feature_code":"PPL",
    "gn:name":"Prohres",
    "gn:population":0,
    "gn:timezone":"Europe/Kiev",
    "iso:country":"UA",
    "name:ukr_x_preferred":[
        "Prohres"
    ],
    "name:ukr_x_variant":[
        "\u041f\u0440\u043e\u0433\u0440\u0435\u0441"
    ],
    "wof:name":"Prohres",
    "wof:placetype":"locality"
},
  "geometry": {"coordinates":[35.2306,49.92816],"type":"Point"}
}