{
  "type": "Feature",
  "properties": {
    "gn:admin1_code":"8.0",
    "gn:asciiname":"Chereshen'ky",
    "gn:country_code":"UA",
    "gn:dem":26,
    "gn:feature_class":"P",
    "gn:feature_code":"PPL",
    "gn:name":"Chereshen\u2019ky",
    "gn:population":0,
    "gn:timezone":"Europe/Kiev",
    "iso:country":"UA",
    "name:ukr_x_preferred":[
        "Chereshen\u2019ky"
    ],
    "name:ukr_x_variant":[
        "\u0427\u0435\u0440\u0435\u0448\u0435\u043d\u044c\u043a\u0438"
    ],
    "name:und_x_variant":[
        "Chereshenki"
    ],
    "wof:name":"Chereshen'ky",
    "wof:placetype":"locality"
},
  "geometry": {"coordinates":[32.39965,46.6787],"type":"Point"}
}