{
  "type": "Feature",
  "properties": {
    "gn:admin1_code":"17.0",
    "gn:asciiname":"Shlyakhovoye",
    "gn:country_code":"UA",
    "gn:dem":120,
    "gn:feature_class":"P",
    "gn:feature_code":"PPL",
    "gn:name":"Shlyakhovoye",
    "gn:population":0,
    "gn:timezone":"Europe/Kiev",
    "iso:country":"UA",
    "name:und_x_variant":[
        "Shlyakhovo",
        "Shlyakhova",
        "Shlyakhovoye"
    ],
    "wof:name":"Shlyakhovoye",
    "wof:placetype":"locality"
},
  "geometry": {"coordinates":[29.75391,48.07377],"type":"Point"}
}