{
  "type": "Feature",
  "properties": {
    "gn:admin1_code":"24.0",
    "gn:asciiname":"Kolodnytsya",
    "gn:country_code":"UA",
    "gn:dem":166,
    "gn:feature_class":"P",
    "gn:feature_code":"PPL",
    "gn:name":"Kolodnytsya",
    "gn:population":0,
    "gn:timezone":"Europe/Kiev",
    "iso:country":"UA",
    "name:ukr_x_preferred":[
        "Kolodnytsya"
    ],
    "name:ukr_x_variant":[
        "\u041a\u043e\u043b\u043e\u0434\u043d\u0438\u0446\u044f"
    ],
    "name:und_x_variant":[
        "Kolodnitsa"
    ],
    "wof:name":"Kolodnytsya",
    "wof:placetype":"locality"
},
  "geometry": {"coordinates":[24.75843,51.2397],"type":"Point"}
}