{
  "type": "Feature",
  "properties": {
    "gn:admin1_code":"18.0",
    "gn:asciiname":"Buluky",
    "gn:country_code":"UA",
    "gn:dem":158,
    "gn:feature_class":"P",
    "gn:feature_code":"PPL",
    "gn:name":"Buluky",
    "gn:population":0,
    "gn:timezone":"Europe/Kiev",
    "iso:country":"UA",
    "name:ukr_x_preferred":[
        "Buluky"
    ],
    "name:ukr_x_variant":[
        "\u0411\u0443\u043b\u0443\u043a\u0438"
    ],
    "wof:name":"Buluky",
    "wof:placetype":"locality"
},
  "geometry": {"coordinates":[33.56783,50.15453],"type":"Point"}
}