{
  "type": "Feature",
  "properties": {
    "gn:admin1_code":"5.0",
    "gn:asciiname":"Vodyanskoye",
    "gn:country_code":"UA",
    "gn:dem":163,
    "gn:feature_class":"P",
    "gn:feature_code":"PPL",
    "gn:name":"Vodyanskoye",
    "gn:population":0,
    "gn:timezone":"Europe/Kiev",
    "iso:country":"UA",
    "name:eng_x_preferred":[
        "Vodyanskoye"
    ],
    "name:rus_x_preferred":[
        "\u0412\u043e\u0434\u044f\u043d\u0441\u043a\u043e\u0435"
    ],
    "name:und_x_variant":[
        "Vodyanoye"
    ],
    "wof:name":"Vodyanskoye",
    "wof:placetype":"locality"
},
  "geometry": {"coordinates":[37.10241,48.40961],"type":"Point"}
}