{
  "type": "Feature",
  "properties": {
    "gn:admin1_code":"23.0",
    "gn:asciiname":"Frantovka",
    "gn:country_code":"UA",
    "gn:dem":267,
    "gn:feature_class":"P",
    "gn:feature_code":"PPL",
    "gn:name":"Frantovka",
    "gn:population":0,
    "gn:timezone":"Europe/Kiev",
    "iso:country":"UA",
    "name:und_x_variant":[
        "Frantivka",
        "Frantovka"
    ],
    "wof:name":"Frantovka",
    "wof:placetype":"locality"
},
  "geometry": {"coordinates":[29.55586,49.09989],"type":"Point"}
}