{
  "type": "Feature",
  "properties": {
    "gn:admin1_code":"22.0",
    "gn:asciiname":"Radoshevka",
    "gn:country_code":"UA",
    "gn:dem":278,
    "gn:feature_class":"P",
    "gn:feature_code":"PPL",
    "gn:name":"Radosh\u00ebvka",
    "gn:population":0,
    "gn:timezone":"Europe/Kiev",
    "iso:country":"UA",
    "name:und_x_variant":[
        "Radoshuvka",
        "Radosh\u00ebvka"
    ],
    "wof:name":"Radoshevka",
    "wof:placetype":"locality"
},
  "geometry": {"coordinates":[26.12972,49.98522],"type":"Point"}
}