{
  "type": "Feature",
  "properties": {
    "gn:admin1_code":"5.0",
    "gn:asciiname":"Annovka",
    "gn:cc2":"UA",
    "gn:country_code":"UA",
    "gn:dem":113,
    "gn:feature_class":"P",
    "gn:feature_code":"PPL",
    "gn:name":"Annovka",
    "gn:population":0,
    "gn:timezone":"Europe/Kiev",
    "iso:country":"UA",
    "name:und_x_variant":[
        "Yelinovka",
        "Annovka"
    ],
    "wof:name":"Annovka",
    "wof:placetype":"locality"
},
  "geometry": {"coordinates":[38.05,48.71667],"type":"Point"}
}