{
  "type": "Feature",
  "properties": {
    "gn:admin1_code":"27.0",
    "gn:asciiname":"Hranitne",
    "gn:country_code":"UA",
    "gn:dem":142,
    "gn:feature_class":"P",
    "gn:feature_code":"PPL",
    "gn:name":"Hranitne",
    "gn:population":0,
    "gn:timezone":"Europe/Kiev",
    "iso:country":"UA",
    "name:bel_x_preferred":[
        "\u0413\u0440\u0430\u043d\u0456\u0442\u043d\u044d"
    ],
    "name:crh_x_preferred":[
        "Granitne"
    ],
    "name:deu_x_preferred":[
        "Hranitne"
    ],
    "name:fra_x_preferred":[
        "Hranitne"
    ],
    "name:hye_x_preferred":[
        "\u0533\u0580\u0561\u0576\u056b\u057f\u0576\u0578\u0565"
    ],
    "name:pol_x_preferred":[
        "Hranitne"
    ],
    "name:ron_x_preferred":[
        "Hranitne"
    ],
    "name:rus_x_preferred":[
        "\u0413\u0440\u0430\u043d\u0438\u0442\u043d\u043e\u0435"
    ],
    "name:sah_x_preferred":[
        "\u0413\u0440\u0430\u043d\u0438\u0442\u043d\u043e\u0435"
    ],
    "name:ukr_x_preferred":[
        "Hranitne"
    ],
    "name:ukr_x_variant":[
        "\u0413\u0440\u0430\u043d\u0456\u0442\u043d\u0435"
    ],
    "name:und_x_variant":[
        "Granitnoye"
    ],
    "name:zho_x_preferred":[
        "\u683c\u62c9\u5c3c\u7279\u6d85"
    ],
    "wof:name":"Hranitne",
    "wof:placetype":"locality"
},
  "geometry": {"coordinates":[29.3516,50.74327],"type":"Point"}
}