{
  "type": "Feature",
  "properties": {
    "gn:population":2981,
    "iso:country":"UA",
    "name:arm_x_preferred":[
        "\u0534\u0561\u057e\u056b\u0564\u0578\u057e\u056f\u0561"
    ],
    "name:chi_x_preferred":[
        "\u9054\u7dad\u5b63\u592b\u5361"
    ],
    "name:dut_x_preferred":[
        "Davydivka"
    ],
    "name:eng_x_preferred":[
        "Davydivka"
    ],
    "name:heb_x_preferred":[
        "\u05d3\u05d5\u05d9\u05d3\u05e0\u05d9"
    ],
    "name:hye_x_preferred":[
        "\u0534\u0561\u057e\u056b\u0564\u0578\u057e\u056f\u0561"
    ],
    "name:nld_x_preferred":[
        "Davydivka"
    ],
    "name:pol_x_preferred":[
        "Dawideny"
    ],
    "name:ron_x_preferred":[
        "Davideni"
    ],
    "name:rum_x_preferred":[
        "Davideni"
    ],
    "name:rus_x_preferred":[
        "\u0414\u0430\u0432\u044b\u0434\u043e\u0432\u043a\u0430"
    ],
    "name:rus_x_variant":[
        "\u0414\u0430\u0432\u0438\u0434\u0456\u0432\u043a\u0430"
    ],
    "name:ukr_x_preferred":[
        "\u0414\u0430\u0432\u0438\u0434\u0456\u0432\u043a\u0430"
    ],
    "name:unk_x_variant":[
        "Davideni"
    ],
    "name:zho_x_preferred":[
        "\u9054\u7dad\u5b63\u592b\u5361"
    ],
    "qs:a0":"\u0423\u043a\u0440\u0430\u0457\u043d\u0430",
    "qs:a1":"*\u0427\u0435\u0440\u043d\u0456\u0432\u0435\u0446\u044c\u043a\u0430",
    "qs:a1_alt":"Chernivets'ka",
    "qs:a1r":"0",
    "qs:a2":"\u0421\u0442\u043e\u0440\u043e\u0436\u0438\u043d\u0435\u0446\u044c\u043a\u0438\u0439",
    "qs:a2_alt":"Storozhynets'kyi",
    "qs:adm0":"\u0423\u043a\u0440\u0430\u0457\u043d\u0430",
    "qs:la_lc":"*",
    "qs:level":"locality",
    "qs:loc":"\u0414\u0430\u0432\u0438\u0434\u0456\u0432\u043a\u0430",
    "qs:loc_alt":"Davydivka",
    "qs:pop":0,
    "qs:type":"buffered point",
    "wd:wordcount":41,
    "wof:name":"\u0414\u0430\u0432\u0438\u0434\u0456\u0432\u043a\u0430",
    "wof:placetype":"locality",
    "wof:population":2981
},
  "geometry": {"coordinates":[25.550415,48.129408],"type":"Point"}
}