{
  "type": "Feature",
  "properties": {
    "gn:admin1_code":"1.0",
    "gn:asciiname":"L'vivka",
    "gn:country_code":"UA",
    "gn:dem":120,
    "gn:feature_class":"P",
    "gn:feature_code":"PPL",
    "gn:name":"L\u2019vivka",
    "gn:population":0,
    "gn:timezone":"Europe/Kiev",
    "iso:country":"UA",
    "name:ukr_x_preferred":[
        "L\u2019vivka"
    ],
    "name:ukr_x_variant":[
        "\u041b\u044c\u0432\u0456\u0432\u043a\u0430"
    ],
    "wof:name":"L'vivka",
    "wof:placetype":"locality"
},
  "geometry": {"coordinates":[32.10011,49.83454],"type":"Point"}
}