{
  "type": "Feature",
  "properties": {
    "gn:admin1_code":"24.0",
    "gn:asciiname":"Nevir",
    "gn:country_code":"UA",
    "gn:dem":148,
    "gn:feature_class":"P",
    "gn:feature_code":"PPL",
    "gn:name":"Nevir",
    "gn:population":0,
    "gn:timezone":"Europe/Kiev",
    "iso:country":"UA",
    "name:ukr_x_preferred":[
        "Nevir"
    ],
    "name:ukr_x_variant":[
        "\u041d\u0435\u0432\u0456\u0440"
    ],
    "name:und_x_variant":[
        "Nevezh",
        "Nevir"
    ],
    "wof:name":"Nevir",
    "wof:placetype":"locality"
},
  "geometry": {"coordinates":[24.98791,51.87416],"type":"Point"}
}