{
  "type": "Feature",
  "properties": {
    "gn:country":"UA",
    "gn:fcode":"PPL",
    "gn:population":5038,
    "iso:country":"UA",
    "name:ceb_x_preferred":[
        "Plakhtiyivka"
    ],
    "name:deu_x_preferred":[
        "Plachtijiwka"
    ],
    "name:eng_x_preferred":[
        "Plakhtiivka"
    ],
    "name:lav_x_preferred":[
        "Plahtijivka"
    ],
    "name:ron_x_preferred":[
        "Plahteevca"
    ],
    "name:rus_x_preferred":[
        "\u041f\u043b\u0430\u0445\u0442\u0456\u0457\u0432\u043a\u0430"
    ],
    "name:rus_x_variant":[
        "\u041f\u043b\u0430\u0445\u0442\u0438\u0435\u0432\u043a\u0430"
    ],
    "name:spa_x_preferred":[
        "Plajtiyivka"
    ],
    "name:ukr_x_preferred":[
        "\u041f\u043b\u0430\u0445\u0442\u0456\u0457\u0432\u043a\u0430"
    ],
    "name:und_x_variant":[
        "Kletereshti"
    ],
    "name:zho_x_preferred":[
        "\u4f69\u62c9\u8d6b\u5b63\u4f0a\u592b\u5361"
    ],
    "qs_pg:aaroncc":"UA",
    "qs_pg:gn_country":"UA",
    "qs_pg:gn_fcode":"PPL",
    "qs_pg:gn_pop":5038,
    "qs_pg:name":"Plakhtiyivka",
    "qs_pg:photos_9r":0,
    "qs_pg:photos_sr":0,
    "qs_pg:pop_sr":5,
    "qs_pg:qs_pg_placetype":"locality",
    "wof:name":"Plakhtiyivka",
    "wof:placetype":"locality",
    "wof:population":5038
},
  "geometry": {"coordinates":[29.72169,46.1006],"type":"Point"}
}