{
  "type": "Feature",
  "properties": {
    "iso:country":"UA",
    "name:arm_x_preferred":[
        "\u054f\u0565\u056f\u0578\u057e\u0578"
    ],
    "name:chi_x_preferred":[
        "\u6377\u79d1\u6c83"
    ],
    "name:dut_x_preferred":[
        "Tekovo"
    ],
    "name:eng_x_preferred":[
        "Tekovo"
    ],
    "name:epo_x_preferred":[
        "Tekovo"
    ],
    "name:ger_x_preferred":[
        "Tekowo"
    ],
    "name:hun_x_preferred":[
        "Tekeh\u00e1za"
    ],
    "name:rum_x_preferred":[
        "Tekovo"
    ],
    "name:rus_x_preferred":[
        "\u0422\u0435\u043a\u043e\u0432\u043e"
    ],
    "name:ukr_x_preferred":[
        "\u0422\u0435\u043a\u043e\u0432\u043e"
    ],
    "name:unk_x_variant":[
        "Tekove"
    ],
    "qs:a0":"\u0423\u043a\u0440\u0430\u0457\u043d\u0430",
    "qs:a1":"*\u0417\u0430\u043a\u0430\u0440\u043f\u0430\u0442\u0441\u044c\u043a\u0430",
    "qs:a1_alt":"Zakarpats'ka",
    "qs:a1r":"0",
    "qs:a2":"\u0412\u0438\u043d\u043e\u0433\u0440\u0430\u0434\u0456\u0432\u0441\u044c\u043a\u0438\u0439",
    "qs:a2_alt":"Vynohradivs'kyi",
    "qs:adm0":"\u0423\u043a\u0440\u0430\u0457\u043d\u0430",
    "qs:la_lc":"*",
    "qs:level":"locality",
    "qs:loc":"\u0422\u0435\u043a\u043e\u0432\u043e",
    "qs:loc_alt":"Tekovo",
    "qs:pop":0,
    "qs:type":"buffered point",
    "wof:name":"\u0422\u0435\u043a\u043e\u0432\u043e",
    "wof:placetype":"locality"
},
  "geometry": {"coordinates":[23.098505,48.121462],"type":"Point"}
}