{
  "type": "Feature",
  "properties": {
    "gn:admin1_code":"7.0",
    "gn:asciiname":"Chervonyy Prapor",
    "gn:country_code":"UA",
    "gn:dem":151,
    "gn:feature_class":"P",
    "gn:feature_code":"PPL",
    "gn:name":"Chervonyy Prapor",
    "gn:population":0,
    "gn:timezone":"Europe/Kiev",
    "iso:country":"UA",
    "name:ukr_x_preferred":[
        "\u0427\u0435\u0440\u0432\u043e\u043d\u0438\u0439 \u041f\u0440\u0430\u043f\u043e\u0440"
    ],
    "name:und_x_variant":[
        "Knyazha Dolyna",
        "Chervonyy Prapor"
    ],
    "wof:name":"Chervonyy Prapor",
    "wof:placetype":"locality"
},
  "geometry": {"coordinates":[35.36623,49.96763],"type":"Point"}
}