{
  "type": "Feature",
  "properties": {
    "gn:admin1_code":"23.0",
    "gn:asciiname":"Svitintsy",
    "gn:country_code":"UA",
    "gn:dem":250,
    "gn:feature_class":"P",
    "gn:feature_code":"PPL",
    "gn:name":"Svitintsy",
    "gn:population":0,
    "gn:timezone":"Europe/Kiev",
    "iso:country":"UA",
    "wof:name":"Svitintsy",
    "wof:placetype":"locality"
},
  "geometry": {"coordinates":[29.03252,49.57028],"type":"Point"}
}