{
  "type": "Feature",
  "properties": {
    "gn:admin1_code":"18.0",
    "gn:asciiname":"Holoborod'kivs'ke",
    "gn:country_code":"UA",
    "gn:dem":135,
    "gn:feature_class":"P",
    "gn:feature_code":"PPL",
    "gn:name":"Holoborod\u2019kivs\u2019ke",
    "gn:population":0,
    "gn:timezone":"Europe/Kiev",
    "iso:country":"UA",
    "name:rus_x_preferred":[
        "Galoborod\u2019novskoye"
    ],
    "name:ukr_x_preferred":[
        "Holoborod\u2019kivs\u2019ke"
    ],
    "name:ukr_x_variant":[
        "\u0413\u043e\u043b\u043e\u0431\u043e\u0440\u043e\u0434\u044c\u043a\u0456\u0432\u0441\u044c\u043a\u0435"
    ],
    "wof:name":"Holoborod'kivs'ke",
    "wof:placetype":"locality"
},
  "geometry": {"coordinates":[35.09353,49.48904],"type":"Point"}
}