{
  "type": "Feature",
  "properties": {
    "iso:country":"UA",
    "name:und_x_variant":[
        "Stanislavovka"
    ],
    "qs:a0":"\u0423\u043a\u0440\u0430\u0457\u043d\u0430",
    "qs:a1":"*\u041e\u0434\u0435\u0441\u044c\u043a\u0430",
    "qs:a1_alt":"Odes'ka",
    "qs:a1r":"0",
    "qs:a2":"\u041a\u043e\u0442\u043e\u0432\u0441\u044c\u043a\u0438\u0439",
    "qs:a2_alt":"Kotovs'kyi",
    "qs:adm0":"\u0423\u043a\u0440\u0430\u0457\u043d\u0430",
    "qs:la_lc":"*",
    "qs:level":"locality",
    "qs:loc":"\u0421\u0442\u0430\u043d\u0456\u0441\u043b\u0430\u0432\u043a\u0430",
    "qs:loc_alt":"Stanislavka",
    "qs:pop":0,
    "qs:type":"buffered point",
    "wof:name":"\u0421\u0442\u0430\u043d\u0456\u0441\u043b\u0430\u0432\u043a\u0430",
    "wof:placetype":"locality"
},
  "geometry": {"coordinates":[29.259861,47.727581],"type":"Point"}
}