{
  "type": "Feature",
  "properties": {
    "iso:country":"UA",
    "name:deu_x_preferred":[
        "Snowytschi"
    ],
    "name:eng_x_preferred":[
        "Snovychi"
    ],
    "name:pol_x_preferred":[
        "Snowicz"
    ],
    "name:ron_x_preferred":[
        "Snov\u00eeci"
    ],
    "name:rus_x_preferred":[
        "\u0421\u043d\u043e\u0432\u0438\u0447\u0438"
    ],
    "name:ukr_x_preferred":[
        "\u0421\u043d\u043e\u0432\u0438\u0447\u0456"
    ],
    "name:zho_x_preferred":[
        "\u65af\u8afe\u7dad\u5947"
    ],
    "qs:a0":"\u0423\u043a\u0440\u0430\u0457\u043d\u0430",
    "qs:a1":"*\u041b\u044c\u0432\u0456\u0432\u0441\u044c\u043a\u0430",
    "qs:a1_alt":"L'vivs'ka",
    "qs:a1r":"0",
    "qs:a2":"\u0417\u043e\u043b\u043e\u0447\u0456\u0432\u0441\u044c\u043a\u0438\u0439",
    "qs:a2_alt":"Zolochivs'kyi",
    "qs:adm0":"\u0423\u043a\u0440\u0430\u0457\u043d\u0430",
    "qs:la_lc":"*",
    "qs:level":"locality",
    "qs:loc":"\u0421\u043d\u043e\u0432\u0438\u0447\u0456",
    "qs:loc_alt":"Snovychi",
    "qs:pop":0,
    "qs:type":"buffered point",
    "wof:name":"\u0421\u043d\u043e\u0432\u0438\u0447\u0456",
    "wof:placetype":"locality"
},
  "geometry": {"coordinates":[24.93789,49.735567],"type":"Point"}
}