{
  "type": "Feature",
  "properties": {
    "gn:admin1_code":"27.0",
    "gn:asciiname":"Nozdryshche",
    "gn:country_code":"UA",
    "gn:dem":127,
    "gn:feature_class":"P",
    "gn:feature_code":"PPL",
    "gn:name":"Nozdryshche",
    "gn:population":0,
    "gn:timezone":"Europe/Kiev",
    "iso:country":"UA",
    "name:ukr_x_preferred":[
        "Nozdryshche"
    ],
    "name:ukr_x_variant":[
        "\u041d\u043e\u0437\u0434\u0440\u0438\u0449\u0435"
    ],
    "name:und_x_variant":[
        "Nozdrishche"
    ],
    "wof:name":"Nozdryshche",
    "wof:placetype":"locality"
},
  "geometry": {"coordinates":[29.18006,51.24182],"type":"Point"}
}