{
  "type": "Feature",
  "properties": {
    "gn:admin1_code":"13.0",
    "gn:asciiname":"Zabuyannya",
    "gn:country_code":"UA",
    "gn:dem":174,
    "gn:feature_class":"P",
    "gn:feature_code":"PPL",
    "gn:name":"Zabuyannya",
    "gn:population":0,
    "gn:timezone":"Europe/Kiev",
    "iso:country":"UA",
    "name:ukr_x_preferred":[
        "Zabuyannya"
    ],
    "name:ukr_x_variant":[
        "\u0417\u0430\u0431\u0443\u044f\u043d\u043d\u044f"
    ],
    "name:und_x_variant":[
        "Buyan",
        "Zabuyan\u2019ye"
    ],
    "wof:name":"Zabuyannya",
    "wof:placetype":"locality"
},
  "geometry": {"coordinates":[29.64715,50.56362],"type":"Point"}
}