{
  "type": "Feature",
  "properties": {
    "gn:admin1_code":"13.0",
    "gn:asciiname":"Stanyshivka",
    "gn:country_code":"UA",
    "gn:dem":150,
    "gn:feature_class":"P",
    "gn:feature_code":"PPL",
    "gn:name":"Stanyshivka",
    "gn:population":0,
    "gn:timezone":"Europe/Kiev",
    "iso:country":"UA",
    "name:rus_x_preferred":[
        "Stanish\u00ebvka"
    ],
    "name:ukr_x_preferred":[
        "Stanyshivka"
    ],
    "name:ukr_x_variant":[
        "\u0421\u0442\u0430\u043d\u0438\u0448\u0456\u0432\u043a\u0430"
    ],
    "wof:name":"Stanyshivka",
    "wof:placetype":"locality"
},
  "geometry": {"coordinates":[29.74986,50.95814],"type":"Point"}
}