{
  "type": "Feature",
  "properties": {
    "gn:admin1_code":"27.0",
    "gn:asciiname":"Poyasky",
    "gn:country_code":"UA",
    "gn:dem":192,
    "gn:feature_class":"P",
    "gn:feature_code":"PPL",
    "gn:name":"Poyasky",
    "gn:population":0,
    "gn:timezone":"Europe/Kiev",
    "iso:country":"UA",
    "name:ukr_x_preferred":[
        "Poyasky"
    ],
    "name:ukr_x_variant":[
        "\u041f\u043e\u044f\u0441\u043a\u0438"
    ],
    "name:und_x_variant":[
        "Poyaski"
    ],
    "wof:name":"Poyasky",
    "wof:placetype":"locality"
},
  "geometry": {"coordinates":[27.79908,51.20142],"type":"Point"}
}