{
  "type": "Feature",
  "properties": {
    "iso:country":"UA",
    "name:eng_x_preferred":[
        "Brovarki"
    ],
    "name:rus_x_preferred":[
        "\u0411\u0440\u043e\u0432\u0430\u0440\u043a\u0438"
    ],
    "name:ukr_x_preferred":[
        "Brovarky"
    ],
    "name:ukr_x_variant":[
        "\u0411\u0440\u043e\u0432\u0430\u0440\u043a\u0438"
    ],
    "name:und_x_variant":[
        "Brosarki"
    ],
    "qs:a0":"\u0423\u043a\u0440\u0430\u0457\u043d\u0430",
    "qs:a1":"*\u041f\u043e\u043b\u0442\u0430\u0432\u0441\u044c\u043a\u0430",
    "qs:a1_alt":"Poltavs'ka",
    "qs:a1r":"0",
    "qs:a2":"\u0413\u043b\u043e\u0431\u0438\u043d\u0441\u044c\u043a\u0438\u0439",
    "qs:a2_alt":"Hlobyns'kyi",
    "qs:adm0":"\u0423\u043a\u0440\u0430\u0457\u043d\u0430",
    "qs:la_lc":"*",
    "qs:level":"locality",
    "qs:loc":"\u0411\u0440\u043e\u0432\u0430\u0440\u043a\u0438",
    "qs:loc_alt":"Brovarky",
    "qs:pop":0,
    "qs:type":"buffered point",
    "wof:name":"\u0411\u0440\u043e\u0432\u0430\u0440\u043a\u0438",
    "wof:placetype":"locality"
},
  "geometry": {"coordinates":[32.968422,49.368255],"type":"Point"}
}