{
  "type": "Feature",
  "properties": {
    "gn:admin1_code":"8.0",
    "gn:asciiname":"Rybal'che",
    "gn:country_code":"UA",
    "gn:dem":2,
    "gn:feature_class":"P",
    "gn:feature_code":"PPL",
    "gn:name":"Rybal\u2019che",
    "gn:population":0,
    "gn:timezone":"Europe/Kiev",
    "iso:country":"UA",
    "name:ukr_x_preferred":[
        "Rybal\u2019che"
    ],
    "name:ukr_x_variant":[
        "\u0420\u0438\u0431\u0430\u043b\u044c\u0447\u0435"
    ],
    "wof:name":"Rybal'che",
    "wof:placetype":"locality"
},
  "geometry": {"coordinates":[32.23584,46.47506],"type":"Point"}
}