{
  "type": "Feature",
  "properties": {
    "gn:admin1_code":"13.0",
    "gn:asciiname":"Pidvarki",
    "gn:cc2":"UA",
    "gn:country_code":"UA",
    "gn:dem":96,
    "gn:feature_class":"P",
    "gn:feature_code":"PPL",
    "gn:name":"Pidvarki",
    "gn:population":0,
    "gn:timezone":"Europe/Kiev",
    "iso:country":"UA",
    "name:und_x_variant":[
        "Prigorod Pidvarki",
        "Pidvarki"
    ],
    "wof:name":"Pidvarki",
    "wof:placetype":"locality"
},
  "geometry": {"coordinates":[31.48333,50.08333],"type":"Point"}
}