{
  "type": "Feature",
  "properties": {
    "gn:admin1_code":"15.0",
    "gn:asciiname":"Borove",
    "gn:country_code":"UA",
    "gn:dem":198,
    "gn:feature_class":"P",
    "gn:feature_code":"PPL",
    "gn:name":"Borove",
    "gn:population":0,
    "gn:timezone":"Europe/Kiev",
    "iso:country":"UA",
    "name:ukr_x_preferred":[
        "\u0411\u043e\u0440\u043e\u0432\u0435"
    ],
    "name:und_x_variant":[
        "Borowe",
        "Borove",
        "Borovoye"
    ],
    "wof:name":"Borove",
    "wof:placetype":"locality"
},
  "geometry": {"coordinates":[24.20102,50.26165],"type":"Point"}
}