{
  "type": "Feature",
  "properties": {
    "gn:admin1_code":"23.0",
    "gn:asciiname":"Sloboda Mizyakivskaya",
    "gn:country_code":"UA",
    "gn:dem":238,
    "gn:feature_class":"P",
    "gn:feature_code":"PPL",
    "gn:name":"Sloboda Mizyakivskaya",
    "gn:population":0,
    "gn:timezone":"Europe/Kiev",
    "iso:country":"UA",
    "wof:name":"Sloboda Mizyakivskaya",
    "wof:placetype":"locality"
},
  "geometry": {"coordinates":[28.40809,49.40204],"type":"Point"}
}