{
  "type": "Feature",
  "properties": {
    "gn:admin1_code":"11.0",
    "gn:admin2_code":"703233",
    "gn:admin3_code":"11128515",
    "gn:asciiname":"Vulkanovka",
    "gn:country_code":"UA",
    "gn:dem":70,
    "gn:feature_class":"P",
    "gn:feature_code":"PPL",
    "gn:name":"Vulkanovka",
    "gn:population":129,
    "gn:timezone":"Europe/Simferopol",
    "iso:country":"UA",
    "name:eng_x_preferred":[
        "Vulkanovka"
    ],
    "name:rus_x_historical":[
        "\u0414\u0436\u0430\u0432-\u0422\u043e\u0431\u0435\u0301"
    ],
    "name:rus_x_preferred":[
        "\u0412\u0443\u043b\u043a\u0430\u043d\u043e\u0432\u043a\u0430"
    ],
    "name:rus_x_variant":[
        "\u0414\u0436\u0430\u0432-\u0422\u043e\u0431\u0435\u0301"
    ],
    "name:ukr_x_preferred":[
        "\u0412\u0443\u043b\u043a\u0430\u043d\u0456\u0432\u043a\u0430"
    ],
    "wof:name":"Vulkanovka",
    "wof:placetype":"locality",
    "wof:population":129
},
  "geometry": {"coordinates":[35.9462,45.13963],"type":"Point"}
}