{
  "type": "Feature",
  "properties": {
    "iso:country":"UA",
    "qs:a0":"\u0423\u043a\u0440\u0430\u0457\u043d\u0430",
    "qs:a1":"*\u0417\u0430\u043f\u043e\u0440\u0456\u0437\u044c\u043a\u0430",
    "qs:a1_alt":"Zaporiz'ka",
    "qs:a1r":"0",
    "qs:a2":"\u041c\u0438\u0445\u0430\u0439\u043b\u0456\u0432\u0441\u044c\u043a\u0438\u0439",
    "qs:a2_alt":"Mykhailivs'kyi",
    "qs:adm0":"\u0423\u043a\u0440\u0430\u0457\u043d\u0430",
    "qs:la_lc":"*",
    "qs:level":"locality",
    "qs:loc":"\u0421\u0442\u0430\u0440\u043e\u0431\u043e\u0433\u0434\u0430\u043d\u0456\u0432\u043a\u0430",
    "qs:loc_alt":"Starobohdanivka",
    "qs:pop":0,
    "qs:type":"buffered point",
    "wof:name":"\u0421\u0442\u0430\u0440\u043e\u0431\u043e\u0433\u0434\u0430\u043d\u0456\u0432\u043a\u0430",
    "wof:placetype":"locality"
},
  "geometry": {"coordinates":[35.484865,47.102263],"type":"Point"}
}