{
  "type": "Feature",
  "properties": {
    "iso:country":"UA",
    "name:ara_x_preferred":[
        "\u0647\u0627\u0646\u064a\u062a\u0634\u064a\u060c \u0632\u0627\u0643\u0627\u0631\u0628\u0627\u062a\u0633\u0643\u0627"
    ],
    "name:ara_x_variant":[
        "\u0647\u0627\u0646\u064a\u062a\u0634\u064a"
    ],
    "name:eng_x_preferred":[
        "Ganichi"
    ],
    "name:epo_x_preferred":[
        "Hani\u0109i"
    ],
    "name:hun_x_preferred":[
        "G\u00e1nya"
    ],
    "name:hye_x_preferred":[
        "\u0533\u0561\u0576\u056b\u0579\u056b"
    ],
    "name:nld_x_preferred":[
        "G\u00e1nya"
    ],
    "name:ron_x_preferred":[
        "Han\u00eeci"
    ],
    "name:rus_x_preferred":[
        "\u0413\u0430\u043d\u0438\u0447\u0438"
    ],
    "name:ukr_x_preferred":[
        "Hanychi"
    ],
    "name:ukr_x_variant":[
        "\u0413\u0430\u043d\u0438\u0447\u0456"
    ],
    "name:und_x_variant":[
        "Gani\u010de"
    ],
    "name:zho_x_preferred":[
        "\u52a0\u5c3c\u5947"
    ],
    "qs:a0":"\u0423\u043a\u0440\u0430\u0457\u043d\u0430",
    "qs:a1":"*\u0417\u0430\u043a\u0430\u0440\u043f\u0430\u0442\u0441\u044c\u043a\u0430",
    "qs:a1_alt":"Zakarpats'ka",
    "qs:a1r":"0",
    "qs:a2":"\u0422\u044f\u0447\u0456\u0432\u0441\u044c\u043a\u0438\u0439",
    "qs:a2_alt":"Tiachivs'kyi",
    "qs:adm0":"\u0423\u043a\u0440\u0430\u0457\u043d\u0430",
    "qs:la_lc":"*",
    "qs:level":"locality",
    "qs:loc":"\u0413\u0430\u043d\u0438\u0447\u0456",
    "qs:loc_alt":"Hanychi",
    "qs:pop":0,
    "qs:type":"buffered point",
    "wd:wordcount":20505,
    "wof:name":"\u0413\u0430\u043d\u0438\u0447\u0456",
    "wof:placetype":"locality"
},
  "geometry": {"coordinates":[23.839735,48.126123],"type":"Point"}
}