{
  "type": "Feature",
  "properties": {
    "gn:admin1_code":"10.0",
    "gn:asciiname":"Trudivka",
    "gn:country_code":"UA",
    "gn:dem":137,
    "gn:feature_class":"P",
    "gn:feature_code":"PPL",
    "gn:name":"Trudivka",
    "gn:population":0,
    "gn:timezone":"Europe/Kiev",
    "iso:country":"UA",
    "name:ukr_x_preferred":[
        "Trudivka"
    ],
    "name:ukr_x_variant":[
        "\u0422\u0440\u0443\u0434\u0456\u0432\u043a\u0430"
    ],
    "name:und_x_variant":[
        "Trudovka"
    ],
    "wof:name":"Trudivka",
    "wof:placetype":"locality"
},
  "geometry": {"coordinates":[33.34812,48.7136],"type":"Point"}
}