{
  "type": "Feature",
  "properties": {
    "gn:admin1_code":"16.0",
    "gn:asciiname":"Kudryavtsevka",
    "gn:country_code":"UA",
    "gn:dem":112,
    "gn:feature_class":"P",
    "gn:feature_code":"PPL",
    "gn:name":"Kudryavtsevka",
    "gn:population":0,
    "gn:timezone":"Europe/Kiev",
    "iso:country":"UA",
    "name:und_x_variant":[
        "Kudryaztsevka",
        "Kudryavtsevo",
        "Kudryavtsevka"
    ],
    "wof:name":"Kudryavtsevka",
    "wof:placetype":"locality"
},
  "geometry": {"coordinates":[31.0233,47.30483],"type":"Point"}
}