{
  "type": "Feature",
  "properties": {
    "gn:admin1_code":"18.0",
    "gn:asciiname":"Iskivtsi",
    "gn:country_code":"UA",
    "gn:dem":95,
    "gn:feature_class":"P",
    "gn:feature_code":"PPL",
    "gn:name":"Iskivtsi",
    "gn:population":0,
    "gn:timezone":"Europe/Kiev",
    "iso:country":"UA",
    "name:eng_x_preferred":[
        "Iskovtsy"
    ],
    "name:rus_x_preferred":[
        "\u0418\u0441\u043a\u043e\u0432\u0446\u044b"
    ],
    "name:ukr_x_preferred":[
        "Iskivtsi"
    ],
    "name:ukr_x_variant":[
        "\u0406\u0441\u043a\u0456\u0432\u0446\u0456"
    ],
    "name:und_x_variant":[
        "Iskovtsy"
    ],
    "wof:name":"Iskivtsi",
    "wof:placetype":"locality"
},
  "geometry": {"coordinates":[32.80815,49.94600000000001],"type":"Point"}
}