{
  "type": "Feature",
  "properties": {
    "gn:admin1_code":"16.0",
    "gn:asciiname":"Suvorovka",
    "gn:country_code":"UA",
    "gn:dem":91,
    "gn:feature_class":"P",
    "gn:feature_code":"PPL",
    "gn:name":"Suvorovka",
    "gn:population":0,
    "gn:timezone":"Europe/Kiev",
    "iso:country":"UA",
    "name:und_x_variant":[
        "Suvarovka",
        "Suvorovka"
    ],
    "wof:name":"Suvorovka",
    "wof:placetype":"locality"
},
  "geometry": {"coordinates":[32.08524,47.38828],"type":"Point"}
}