{
  "type": "Feature",
  "properties": {
    "iso:country":"UA",
    "name:bel_x_variant":[
        "\u0428\u0447\u043e\u043b\u043a\u0456\u043d\u0430"
    ],
    "name:ces_x_preferred":[
        "\u0160\u010dolkine"
    ],
    "name:crh_x_preferred":[
        "\u015e\u00e7olkino"
    ],
    "name:deu_x_preferred":[
        "Schtscholkine"
    ],
    "name:eng_x_preferred":[
        "Shcholkine"
    ],
    "name:epo_x_preferred":[
        "\u015c\u0109olkino"
    ],
    "name:fas_x_preferred":[
        "\u0634\u0686\u0648\u0644\u06a9\u06cc\u0646\u0647"
    ],
    "name:fra_x_preferred":[
        "Chtchiolkino"
    ],
    "name:fra_x_variant":[
        "Chtcholkine"
    ],
    "name:hsb_x_preferred":[
        "\u0160\u0107olkine"
    ],
    "name:hye_x_preferred":[
        "\u0547\u0579\u0575\u0578\u056c\u056f\u056b\u0576\u0578"
    ],
    "name:ita_x_preferred":[
        "\u0160\u010dolkine"
    ],
    "name:kat_x_preferred":[
        "\u10e8\u10e9\u10d8\u10dd\u10da\u10d9\u10d8\u10dc\u10dd"
    ],
    "name:kor_x_preferred":[
        "\uc204\ud0a4\ub124"
    ],
    "name:lit_x_preferred":[
        "\u0160\u010diolkinas"
    ],
    "name:nld_x_preferred":[
        "Sjtsjjolkino"
    ],
    "name:nno_x_preferred":[
        "Sjtsjolkine"
    ],
    "name:nob_x_preferred":[
        "Sjtsjolkine"
    ],
    "name:nor_x_preferred":[
        "Sjtsjolkine"
    ],
    "name:pol_x_preferred":[
        "Szczo\u0142kine"
    ],
    "name:ron_x_preferred":[
        "\u0218ciolkine"
    ],
    "name:rus_x_preferred":[
        "\u0429\u0451\u043b\u043a\u0438\u043d\u043e"
    ],
    "name:spa_x_preferred":[
        "Shcholkine"
    ],
    "name:tat_x_preferred":[
        "\u0429\u0451\u043b\u043a\u0438\u043d\u043e"
    ],
    "name:ukr_x_preferred":[
        "\u0429\u043e\u043b\u043a\u0456\u043d\u0435"
    ],
    "name:vep_x_preferred":[
        "\u0160\u010delkino"
    ],
    "name:vie_x_preferred":[
        "Shcholkine"
    ],
    "name:zho_x_preferred":[
        "\u66c9\u723e\u57fa\u8afe"
    ],
    "qs:a0":"\u0423\u043a\u0440\u0430\u0457\u043d\u0430",
    "qs:a1":"*\u041a\u0440\u0438\u043c",
    "qs:a1_alt":"Krym",
    "qs:a1r":"0",
    "qs:a2":"\u041b\u0435\u043d\u0456\u043d\u0441\u044c\u043a\u0438\u0439",
    "qs:a2_alt":"Lenins'kyi",
    "qs:adm0":"\u0423\u043a\u0440\u0430\u0457\u043d\u0430",
    "qs:la_lc":"*",
    "qs:level":"locality",
    "qs:loc":"\u0429\u043e\u043b\u043a\u0456\u043d\u0435",
    "qs:loc_alt":"Scholkine",
    "qs:pop":0,
    "qs:type":"buffered point",
    "wd:elevation":20.0,
    "wd:wordcount":405,
    "wof:name":"\u0429\u043e\u043b\u043a\u0456\u043d\u0435",
    "wof:placetype":"locality"
},
  "geometry": {"coordinates":[35.819633,45.430041],"type":"Point"}
}