{
  "type": "Feature",
  "properties": {
    "gn:admin1_code":"26.0",
    "gn:asciiname":"Boykove",
    "gn:country_code":"UA",
    "gn:dem":139,
    "gn:feature_class":"P",
    "gn:feature_code":"PPL",
    "gn:name":"Boykove",
    "gn:population":0,
    "gn:timezone":"Europe/Zaporozhye",
    "iso:country":"UA",
    "name:ukr_x_preferred":[
        "Boykove"
    ],
    "name:ukr_x_variant":[
        "\u0411\u043e\u0439\u043a\u043e\u0432\u0435"
    ],
    "wof:name":"Boykove",
    "wof:placetype":"locality"
},
  "geometry": {"coordinates":[36.07189,47.83600000000001],"type":"Point"}
}