{
  "type": "Feature",
  "properties": {
    "gn:admin1_code":"15.0",
    "gn:asciiname":"Pshedmes'tse Male",
    "gn:country_code":"UA",
    "gn:dem":271,
    "gn:feature_class":"P",
    "gn:feature_code":"PPL",
    "gn:name":"Pshedmes\u2019tse Male",
    "gn:population":0,
    "gn:timezone":"Europe/Kiev",
    "iso:country":"UA",
    "name:und_x_variant":[
        "Przedmie\u015bcie Ma\u0142e",
        "Pshedmes\u2019tse Male"
    ],
    "wof:name":"Pshedmes'tse Male",
    "wof:placetype":"locality"
},
  "geometry": {"coordinates":[23.56667,50.21667],"type":"Point"}
}