{
  "type": "Feature",
  "properties": {
    "iso:country":"UA",
    "name:unk_x_variant":[
        "Zapyt\u00f3w"
    ],
    "qs:a0":"\u0423\u043a\u0440\u0430\u0457\u043d\u0430",
    "qs:a1":"*\u041b\u044c\u0432\u0456\u0432\u0441\u044c\u043a\u0430",
    "qs:a1_alt":"L'vivs'ka",
    "qs:a1r":"0",
    "qs:a2":"\u041a\u0430\u043c'\u044f\u043d\u043a\u0430-\u0411\u0443\u0437\u044c\u043a\u0438\u0439",
    "qs:a2_alt":"Kamyanka-Buz'kyi",
    "qs:adm0":"\u0423\u043a\u0440\u0430\u0457\u043d\u0430",
    "qs:la_lc":"*",
    "qs:level":"locality",
    "qs:loc":"\u0417\u0430\u043f\u0438\u0442\u0456\u0432",
    "qs:loc_alt":"Zapytiv",
    "qs:pop":0,
    "qs:type":"buffered point",
    "wof:name":"\u0417\u0430\u043f\u0438\u0442\u0456\u0432",
    "wof:placetype":"locality"
},
  "geometry": {"coordinates":[24.222154,49.926804],"type":"Point"}
}