{
  "type": "Feature",
  "properties": {
    "iso:country":"UA",
    "name:hun_x_preferred":[
        "Bere\u017anica Wy\u017cna"
    ],
    "name:nld_x_preferred":[
        "Bere\u017anica Wy\u017cna"
    ],
    "name:pol_x_preferred":[
        "Bere\u017cnica Wy\u017cna"
    ],
    "name:rus_x_preferred":[
        "\u0411\u0435\u0440\u0435\u0436\u043d\u0438\u0446\u0430"
    ],
    "name:ukr_x_preferred":[
        "\u0411\u0435\u0440\u0435\u0436\u043d\u0438\u0446\u044f"
    ],
    "name:und_x_variant":[
        "Berezhnytsya"
    ],
    "qs:a0":"\u0423\u043a\u0440\u0430\u0457\u043d\u0430",
    "qs:a1":"*\u041b\u044c\u0432\u0456\u0432\u0441\u044c\u043a\u0430",
    "qs:a1_alt":"L'vivs'ka",
    "qs:a1r":"0",
    "qs:a2":"\u0416\u0438\u0434\u0430\u0447\u0456\u0432\u0441\u044c\u043a\u0438\u0439",
    "qs:a2_alt":"Zhydachivs'kyi",
    "qs:adm0":"\u0423\u043a\u0440\u0430\u0457\u043d\u0430",
    "qs:la_lc":"*",
    "qs:level":"locality",
    "qs:loc":"\u0411\u0435\u0440\u0435\u0436\u043d\u0438\u0446\u044f",
    "qs:loc_alt":"Berezhnytsia",
    "qs:pop":0,
    "qs:type":"buffered point",
    "wd:wordcount":100,
    "wof:name":"\u0411\u0435\u0440\u0435\u0436\u043d\u0438\u0446\u044f",
    "wof:placetype":"locality"
},
  "geometry": {"coordinates":[24.18985,49.335595],"type":"Point"}
}