{
  "type": "Feature",
  "properties": {
    "gn:admin1_code":"15.0",
    "gn:asciiname":"Chepele",
    "gn:country_code":"UA",
    "gn:dem":336,
    "gn:feature_class":"P",
    "gn:feature_code":"PPL",
    "gn:name":"Chepele",
    "gn:population":0,
    "gn:timezone":"Europe/Kiev",
    "iso:country":"UA",
    "wof:name":"Chepele",
    "wof:placetype":"locality"
},
  "geometry": {"coordinates":[25.19876,49.88317],"type":"Point"}
}