{
  "type": "Feature",
  "properties": {
    "gn:admin1_code":"7.0",
    "gn:asciiname":"Mylivka",
    "gn:country_code":"UA",
    "gn:dem":98,
    "gn:feature_class":"P",
    "gn:feature_code":"PPL",
    "gn:name":"Mylivka",
    "gn:population":0,
    "gn:timezone":"Europe/Kiev",
    "iso:country":"UA",
    "name:ukr_x_preferred":[
        "Mylivka"
    ],
    "name:ukr_x_variant":[
        "\u041c\u0438\u043b\u0456\u0432\u043a\u0430"
    ],
    "name:und_x_variant":[
        "Mylovka"
    ],
    "wof:name":"Mylivka",
    "wof:placetype":"locality"
},
  "geometry": {"coordinates":[36.33873,48.79018],"type":"Point"}
}