{
  "type": "Feature",
  "properties": {
    "iso:country":"UA",
    "name:deu_x_preferred":[
        "Mykolajiwka-Noworossijska"
    ],
    "name:eng_x_preferred":[
        "Mykolaivka-Novorosiiska"
    ],
    "name:lav_x_preferred":[
        "Mikolajivka-Novorosijska"
    ],
    "name:ron_x_preferred":[
        "Bairamcea"
    ],
    "name:rus_x_preferred":[
        "\u041d\u0438\u043a\u043e\u043b\u0430\u0435\u0432\u043a\u0430-\u041d\u043e\u0432\u043e\u0440\u043e\u0441\u0441\u0438\u0439\u0441\u043a\u0430\u044f"
    ],
    "name:spa_x_preferred":[
        "Nikolaevka-Novorossiysk"
    ],
    "name:ukr_x_preferred":[
        "\u041c\u0438\u043a\u043e\u043b\u0430\u0457\u0432\u043a\u0430-\u041d\u043e\u0432\u043e\u0440\u043e\u0441\u0456\u0439\u0441\u044c\u043a\u0430"
    ],
    "name:und_x_variant":[
        "Bayramcha"
    ],
    "name:zho_x_preferred":[
        "\u7c73\u79d1\u62c9\u4f0a\u592b\u5361-\u8afe\u6c83\u7f85\u897f\u897f\u5361"
    ],
    "qs:a0":"\u0423\u043a\u0440\u0430\u0457\u043d\u0430",
    "qs:a1":"*\u041e\u0434\u0435\u0441\u044c\u043a\u0430",
    "qs:a1_alt":"Odes'ka",
    "qs:a1r":"0",
    "qs:a2":"\u0421\u0430\u0440\u0430\u0442\u0441\u044c\u043a\u0438\u0439",
    "qs:a2_alt":"Sarats'kyi",
    "qs:adm0":"\u0423\u043a\u0440\u0430\u0457\u043d\u0430",
    "qs:la_lc":"*",
    "qs:level":"locality",
    "qs:loc":"\u041c\u0438\u043a\u043e\u043b\u0430\u0457\u0432\u043a\u0430-\u041d\u043e\u0432\u043e\u0440\u043e\u0441\u0456\u0439\u0441\u044c\u043a\u0430",
    "qs:loc_alt":"Mykolaivka-Novorosiis'ka",
    "qs:pop":0,
    "qs:type":"buffered point",
    "wof:name":"\u041c\u0438\u043a\u043e\u043b\u0430\u0457\u0432\u043a\u0430-\u041d\u043e\u0432\u043e\u0440\u043e\u0441\u0456\u0439\u0441\u044c\u043a\u0430",
    "wof:placetype":"locality"
},
  "geometry": {"coordinates":[29.902394,46.134884],"type":"Point"}
}