{
  "type": "Feature",
  "properties": {
    "iso:country":"UA",
    "name:eng_x_preferred":[
        "Kolodistoye"
    ],
    "name:rus_x_preferred":[
        "\u041a\u043e\u043b\u043e\u0434\u0438\u0441\u0442\u043e\u0435"
    ],
    "name:unk_x_variant":[
        "Kolodistoye"
    ],
    "qs:a0":"\u0423\u043a\u0440\u0430\u0457\u043d\u0430",
    "qs:a1":"*\u0427\u0435\u0440\u043a\u0430\u0441\u044c\u043a\u0430",
    "qs:a1_alt":"Cherkas'ka",
    "qs:a1r":"0",
    "qs:a2":"\u0423\u043c\u0430\u043d\u0441\u044c\u043a\u0438\u0439",
    "qs:a2_alt":"Umans'kyi",
    "qs:adm0":"\u0423\u043a\u0440\u0430\u0457\u043d\u0430",
    "qs:la_lc":"*",
    "qs:level":"locality",
    "qs:loc":"\u041a\u043e\u043b\u043e\u0434\u0438\u0441\u0442\u0435",
    "qs:loc_alt":"Kolodyste",
    "qs:pop":0,
    "qs:type":"buffered point",
    "wof:name":"\u041a\u043e\u043b\u043e\u0434\u0438\u0441\u0442\u0435",
    "wof:placetype":"locality"
},
  "geometry": {"coordinates":[30.120658,48.484574],"type":"Point"}
}