{
  "type": "Feature",
  "properties": {
    "gn:admin1_code":"23.0",
    "gn:asciiname":"Voyevodchintsy",
    "gn:country_code":"UA",
    "gn:dem":145,
    "gn:feature_class":"P",
    "gn:feature_code":"PPL",
    "gn:name":"Voyevodchintsy",
    "gn:population":0,
    "gn:timezone":"Europe/Kiev",
    "iso:country":"UA",
    "name:und_x_variant":[
        "Sokol",
        "Voyevodchintsy"
    ],
    "wof:name":"Voyevodchintsy",
    "wof:placetype":"locality"
},
  "geometry": {"coordinates":[27.87657,48.49983],"type":"Point"}
}