{
  "type": "Feature",
  "properties": {
    "iso:country":"UA",
    "name:eng_x_preferred":[
        "Tynovka"
    ],
    "name:rus_x_preferred":[
        "\u0422\u044b\u043d\u043e\u0432\u043a\u0430"
    ],
    "name:unk_x_variant":[
        "Tinovka"
    ],
    "qs:a0":"\u0423\u043a\u0440\u0430\u0457\u043d\u0430",
    "qs:a1":"*\u0427\u0435\u0440\u043a\u0430\u0441\u044c\u043a\u0430",
    "qs:a1_alt":"Cherkas'ka",
    "qs:a1r":"0",
    "qs:a2":"\u0416\u0430\u0448\u043a\u0456\u0432\u0441\u044c\u043a\u0438\u0439",
    "qs:a2_alt":"Zhashkivs'kyi",
    "qs:adm0":"\u0423\u043a\u0440\u0430\u0457\u043d\u0430",
    "qs:la_lc":"*",
    "qs:level":"locality",
    "qs:loc":"\u0422\u0438\u043d\u0456\u0432\u043a\u0430",
    "qs:loc_alt":"Tynivka",
    "qs:pop":0,
    "qs:type":"buffered point",
    "wof:name":"\u0422\u0438\u043d\u0456\u0432\u043a\u0430",
    "wof:placetype":"locality"
},
  "geometry": {"coordinates":[30.431068,49.269773],"type":"Point"}
}