{
  "type": "Feature",
  "properties": {
    "gn:admin1_code":"16.0",
    "gn:asciiname":"Tamaryne",
    "gn:country_code":"UA",
    "gn:dem":59,
    "gn:feature_class":"P",
    "gn:feature_code":"PPL",
    "gn:name":"Tamaryne",
    "gn:population":0,
    "gn:timezone":"Europe/Kiev",
    "iso:country":"UA",
    "name:ukr_x_preferred":[
        "Tamaryne"
    ],
    "name:ukr_x_variant":[
        "\u0422\u0430\u043c\u0430\u0440\u0438\u043d\u0435"
    ],
    "name:und_x_variant":[
        "Tamarino"
    ],
    "wof:name":"Tamaryne",
    "wof:placetype":"locality"
},
  "geometry": {"coordinates":[32.9996,47.01709],"type":"Point"}
}