{
  "type": "Feature",
  "properties": {
    "iso:country":"UA",
    "name:che_x_preferred":[
        "\u0421\u0442\u0435\u043f\u0430\u043d\u043e\u0432\u043a\u0430"
    ],
    "name:deu_x_preferred":[
        "Stepaniwka"
    ],
    "name:eng_x_preferred":[
        "Stepanovka"
    ],
    "name:eng_x_variant":[
        "Stepanivka"
    ],
    "name:fin_x_preferred":[
        "St\u0435p\u0430n\u0456vk\u0430"
    ],
    "name:lav_x_preferred":[
        "Stepa\u0146ivka"
    ],
    "name:nan_x_preferred":[
        "Stepanivka"
    ],
    "name:nno_x_preferred":[
        "Stepanivka"
    ],
    "name:nob_x_preferred":[
        "Stepanivka"
    ],
    "name:ron_x_preferred":[
        "Stepanivka"
    ],
    "name:rus_x_preferred":[
        "\u0421\u0442\u0435\u043f\u0430\u043d\u043e\u0432\u043a\u0430"
    ],
    "name:ukr_x_preferred":[
        "Stepanivka"
    ],
    "name:ukr_x_variant":[
        "\u0421\u0442\u0435\u043f\u0430\u043d\u0456\u0432\u043a\u0430"
    ],
    "name:zho_x_preferred":[
        "\u65af\u6377\u5e15\u5c3c\u592b\u5361"
    ],
    "qs:a0":"\u0423\u043a\u0440\u0430\u0457\u043d\u0430",
    "qs:a1":"*\u0414\u043e\u043d\u0435\u0446\u044c\u043a\u0430",
    "qs:a1_alt":"Donets'ka",
    "qs:a1r":"0",
    "qs:a2":"\u041e\u043b\u0435\u043a\u0441\u0430\u043d\u0434\u0440\u0456\u0432\u0441\u044c\u043a\u0438\u0439",
    "qs:a2_alt":"Oleksandrivs'kyi",
    "qs:adm0":"\u0423\u043a\u0440\u0430\u0457\u043d\u0430",
    "qs:la_lc":"*",
    "qs:level":"locality",
    "qs:loc":"\u0421\u0442\u0435\u043f\u0430\u043d\u0456\u0432\u043a\u0430",
    "qs:loc_alt":"Stepanivka",
    "qs:pop":0,
    "qs:type":"buffered point",
    "wd:wordcount":230,
    "wof:name":"\u0421\u0442\u0435\u043f\u0430\u043d\u0456\u0432\u043a\u0430",
    "wof:placetype":"locality"
},
  "geometry": {"coordinates":[37.028725,48.60851],"type":"Point"}
}