{
  "type": "Feature",
  "properties": {
    "gn:admin1_code":"9.0",
    "gn:asciiname":"Annovka",
    "gn:country_code":"UA",
    "gn:dem":285,
    "gn:feature_class":"P",
    "gn:feature_code":"PPL",
    "gn:name":"Annovka",
    "gn:population":0,
    "gn:timezone":"Europe/Kiev",
    "iso:country":"UA",
    "name:und_x_variant":[
        "Ganovka",
        "Annovka"
    ],
    "wof:name":"Annovka",
    "wof:placetype":"locality"
},
  "geometry": {"coordinates":[26.8295,48.93598],"type":"Point"}
}