{
  "type": "Feature",
  "properties": {
    "gn:admin1_code":"22.0",
    "gn:asciiname":"Tarnavka",
    "gn:country_code":"UA",
    "gn:dem":306,
    "gn:feature_class":"P",
    "gn:feature_code":"PPL",
    "gn:name":"Tarnavka",
    "gn:population":0,
    "gn:timezone":"Europe/Kiev",
    "iso:country":"UA",
    "name:und_x_variant":[
        "Tarnawka",
        "Tarnavka"
    ],
    "wof:name":"Tarnavka",
    "wof:placetype":"locality"
},
  "geometry": {"coordinates":[26.02264,48.90544000000001],"type":"Point"}
}