{
  "type": "Feature",
  "properties": {
    "gn:admin1_code":"27.0",
    "gn:asciiname":"Sarnivka",
    "gn:country_code":"UA",
    "gn:dem":185,
    "gn:feature_class":"P",
    "gn:feature_code":"PPL",
    "gn:name":"Sarnivka",
    "gn:population":0,
    "gn:timezone":"Europe/Kiev",
    "iso:country":"UA",
    "name:ukr_x_preferred":[
        "Sarnivka"
    ],
    "name:ukr_x_variant":[
        "\u0421\u0430\u0440\u043d\u0456\u0432\u043a\u0430"
    ],
    "name:und_x_variant":[
        "Sarnovka"
    ],
    "wof:name":"Sarnivka",
    "wof:placetype":"locality"
},
  "geometry": {"coordinates":[27.46334,51.11037],"type":"Point"}
}