{
  "type": "Feature",
  "properties": {
    "gn:admin1_code":"4.0",
    "gn:asciiname":"Shevchenkivka",
    "gn:country_code":"UA",
    "gn:dem":90,
    "gn:feature_class":"P",
    "gn:feature_code":"PPL",
    "gn:name":"Shevchenkivka",
    "gn:population":0,
    "gn:timezone":"Europe/Kiev",
    "iso:country":"UA",
    "name:ukr_x_preferred":[
        "Shevchenkivka"
    ],
    "name:ukr_x_variant":[
        "\u0428\u0435\u0432\u0447\u0435\u043d\u043a\u0456\u0432\u043a\u0430"
    ],
    "name:und_x_variant":[
        "Taraso-Shevchenkovka",
        "Shevchenkovo",
        "Shevchenkovka"
    ],
    "wof:name":"Shevchenkivka",
    "wof:placetype":"locality"
},
  "geometry": {"coordinates":[34.84336,48.80782],"type":"Point"}
}