{
  "type": "Feature",
  "properties": {
    "gn:admin1_code":"21.0",
    "gn:asciiname":"Stanova",
    "gn:country_code":"UA",
    "gn:dem":157,
    "gn:feature_class":"P",
    "gn:feature_code":"PPL",
    "gn:name":"Stanova",
    "gn:population":0,
    "gn:timezone":"Europe/Kiev",
    "iso:country":"UA",
    "name:eng_x_preferred":[
        "Stanovaya"
    ],
    "name:rus_x_preferred":[
        "\u0421\u0442\u0430\u043d\u043e\u0432\u0430\u044f"
    ],
    "name:ukr_x_preferred":[
        "\u0421\u0442\u0430\u043d\u043e\u0432\u0430"
    ],
    "name:und_x_variant":[
        "Stanovaya"
    ],
    "wof:name":"Stanova",
    "wof:placetype":"locality"
},
  "geometry": {"coordinates":[34.88817,50.49024],"type":"Point"}
}