{
  "type": "Feature",
  "properties": {
    "gn:admin1_code":"13.0",
    "gn:asciiname":"Rozhivka",
    "gn:country_code":"UA",
    "gn:dem":131,
    "gn:feature_class":"P",
    "gn:feature_code":"PPL",
    "gn:name":"Rozhivka",
    "gn:population":0,
    "gn:timezone":"Europe/Kiev",
    "iso:country":"UA",
    "name:ukr_x_preferred":[
        "Rozhivka"
    ],
    "name:ukr_x_variant":[
        "\u0420\u043e\u0436\u0456\u0432\u043a\u0430"
    ],
    "name:und_x_variant":[
        "Rozhevka"
    ],
    "wof:name":"Rozhivka",
    "wof:placetype":"locality"
},
  "geometry": {"coordinates":[30.75746,50.60176],"type":"Point"}
}