{
  "type": "Feature",
  "properties": {
    "gn:admin1_code":"11.0",
    "gn:admin2_code":"694905",
    "gn:admin3_code":"11153101.0",
    "gn:asciiname":"Chebotarka",
    "gn:country_code":"UA",
    "gn:dem":18,
    "gn:elevation":"26.0",
    "gn:feature_class":"P",
    "gn:feature_code":"PPL",
    "gn:name":"Chebotarka",
    "gn:population":202,
    "gn:timezone":"Europe/Simferopol",
    "iso:country":"UA",
    "name:eng_x_preferred":[
        "Chebotarka"
    ],
    "name:eng_x_variant":[
        "Chobotarka"
    ],
    "name:rus_x_historical":[
        "\u0427\u043e\u0431\u0430\u0442\u0430\u0301\u0440"
    ],
    "name:rus_x_preferred":[
        "\u0427\u0435\u0431\u043e\u0442\u0430\u0440\u043a\u0430"
    ],
    "name:rus_x_variant":[
        "\u0427\u043e\u0431\u0430\u0442\u0430\u0301\u0440"
    ],
    "name:ukr_x_preferred":[
        "\u0427\u043e\u0431\u043e\u0442\u0430\u0440\u043a\u0430"
    ],
    "wof:name":"Chebotarka",
    "wof:placetype":"locality",
    "wof:population":202
},
  "geometry": {"coordinates":[33.65722,45.11448],"type":"Point"}
}