{
  "type": "Feature",
  "properties": {
    "gn:admin1_code":"17.0",
    "gn:admin2_code":"690076",
    "gn:asciiname":"Yurashevo",
    "gn:country_code":"UA",
    "gn:dem":32,
    "gn:feature_class":"P",
    "gn:feature_code":"PPL",
    "gn:name":"Yurashevo",
    "gn:population":0,
    "gn:timezone":"Europe/Kiev",
    "iso:country":"UA",
    "name:deu_x_preferred":[
        "Juraschewo"
    ],
    "name:ron_x_preferred":[
        "Iura\u0219eve"
    ],
    "name:rus_x_preferred":[
        "\u042e\u0440\u0430\u0448\u0435\u0432\u043e"
    ],
    "name:ukr_x_preferred":[
        "\u042e\u0440\u0430\u0448\u0435\u0432\u0435"
    ],
    "wof:name":"Yurashevo",
    "wof:placetype":"locality"
},
  "geometry": {"coordinates":[30.25191,47.13196],"type":"Point"}
}