{
  "type": "Feature",
  "properties": {
    "gn:admin1_code":"3.0",
    "gn:asciiname":"Buzovitsa",
    "gn:country_code":"UA",
    "gn:dem":250,
    "gn:feature_class":"P",
    "gn:feature_code":"PPL",
    "gn:name":"Buzovitsa",
    "gn:population":0,
    "gn:timezone":"Europe/Kiev",
    "iso:country":"UA",
    "name:und_x_variant":[
        "Buzovitsy",
        "Buzovitsa"
    ],
    "wof:name":"Buzovitsa",
    "wof:placetype":"locality"
},
  "geometry": {"coordinates":[26.93221,48.49859],"type":"Point"}
}