{
  "type": "Feature",
  "properties": {
    "gn:admin1_code":"8.0",
    "gn:asciiname":"Novorepivka",
    "gn:country_code":"UA",
    "gn:dem":37,
    "gn:feature_class":"P",
    "gn:feature_code":"PPL",
    "gn:name":"Novorepivka",
    "gn:population":0,
    "gn:timezone":"Europe/Kiev",
    "iso:country":"UA",
    "name:rus_x_preferred":[
        "\u041d\u043e\u0432\u043e\u0440\u0435\u043f\u043e\u0432\u043a\u0430"
    ],
    "name:ukr_x_preferred":[
        "Novorepivka"
    ],
    "name:ukr_x_variant":[
        "\u041d\u043e\u0432\u043e\u0440\u0435\u043f\u0456\u0432\u043a\u0430"
    ],
    "name:und_x_variant":[
        "Novaya Rep\u2019yevka",
        "Novo-Rep\u2019yevka",
        "Novorepovka"
    ],
    "wof:name":"Novorepivka",
    "wof:placetype":"locality"
},
  "geometry": {"coordinates":[34.12638,46.70198],"type":"Point"}
}