{
  "type": "Feature",
  "properties": {
    "gn:admin1_code":"6.0",
    "gn:asciiname":"Daleshova",
    "gn:country_code":"UA",
    "gn:dem":352,
    "gn:feature_class":"P",
    "gn:feature_code":"PPL",
    "gn:name":"Daleshova",
    "gn:population":0,
    "gn:timezone":"Europe/Kiev",
    "iso:country":"UA",
    "name:und_x_variant":[
        "Daleshevo",
        "Daleshova"
    ],
    "wof:name":"Daleshova",
    "wof:placetype":"locality"
},
  "geometry": {"coordinates":[25.48233,48.78726],"type":"Point"}
}