{
  "type": "Feature",
  "properties": {
    "gn:admin1_code":"21.0",
    "gn:asciiname":"Polyane",
    "gn:country_code":"UA",
    "gn:dem":137,
    "gn:feature_class":"P",
    "gn:feature_code":"PPL",
    "gn:name":"Polyane",
    "gn:population":0,
    "gn:timezone":"Europe/Kiev",
    "iso:country":"UA",
    "name:eng_x_preferred":[
        "Polyany"
    ],
    "name:fra_x_preferred":[
        "Polyane"
    ],
    "name:rus_x_preferred":[
        "\u041f\u043e\u043b\u044f\u043d\u043e\u0435"
    ],
    "name:spa_x_preferred":[
        "Polyane"
    ],
    "name:ukr_x_preferred":[
        "Polyane"
    ],
    "name:ukr_x_variant":[
        "\u041f\u043e\u043b\u044f\u043d\u0435"
    ],
    "name:und_x_variant":[
        "Polyanoye"
    ],
    "wof:name":"Polyane",
    "wof:placetype":"locality"
},
  "geometry": {"coordinates":[35.22428,50.53824],"type":"Point"}
}