{
  "type": "Feature",
  "properties": {
    "gn:admin1_code":"7.0",
    "gn:asciiname":"Kupyansk-Uzlovoy",
    "gn:country_code":"UA",
    "gn:dem":78,
    "gn:feature_class":"P",
    "gn:feature_code":"PPL",
    "gn:name":"Kupyansk-Uzlovoy",
    "gn:population":0,
    "gn:timezone":"Europe/Kiev",
    "iso:country":"UA",
    "name:eng_x_preferred":[
        "Kup\"yans'k Vuzlovyy"
    ],
    "name:rus_x_preferred":[
        "\u041a\u0443\u043f\u044f\u043d\u0441\u043a-\u0423\u0437\u043b\u043e\u0432\u043e\u0439"
    ],
    "name:ukr_x_preferred":[
        "Kup\u201dyans\u2019k-Vuzlovyy"
    ],
    "name:ukr_x_variant":[
        "\u041a\u0443\u043f\u2019\u044f\u043d\u0441\u044c\u043a-\u0412\u0443\u0437\u043b\u043e\u0432\u0438\u0439"
    ],
    "name:und_x_variant":[
        "Kupyansk Uzlovoi",
        "Kupyansk-Uzlovoy",
        "Kupyansk Uslovoi"
    ],
    "wof:name":"Kupyansk-Uzlovoy",
    "wof:placetype":"locality"
},
  "geometry": {"coordinates":[37.64633,49.65865],"type":"Point"}
}