{
  "type": "Feature",
  "properties": {
    "gn:admin1_code":"11.0",
    "gn:admin2_code":"704383",
    "gn:admin3_code":"11152908",
    "gn:asciiname":"Novozuyevka",
    "gn:country_code":"UA",
    "gn:dem":101,
    "gn:elevation":"102.0",
    "gn:feature_class":"P",
    "gn:feature_code":"PPL",
    "gn:name":"Novozuyevka",
    "gn:population":501,
    "gn:timezone":"Europe/Simferopol",
    "iso:country":"UA",
    "name:eng_x_preferred":[
        "Novozuyevka"
    ],
    "name:rus_x_preferred":[
        "\u041d\u043e\u0432\u043e\u0437\u0443\u0435\u0432\u043a\u0430"
    ],
    "name:ukr_x_preferred":[
        "\u041d\u043e\u0432\u043e\u0437\u0443\u0457\u0432\u043a\u0430"
    ],
    "wof:name":"Novozuyevka",
    "wof:placetype":"locality",
    "wof:population":501
},
  "geometry": {"coordinates":[34.15456,45.2387],"type":"Point"}
}