{
  "type": "Feature",
  "properties": {
    "gn:admin1_code":"17.0",
    "gn:asciiname":"Karpeshty",
    "gn:country_code":"UA",
    "gn:dem":215,
    "gn:feature_class":"P",
    "gn:feature_code":"PPL",
    "gn:name":"Karpeshty",
    "gn:population":0,
    "gn:timezone":"Europe/Kiev",
    "iso:country":"UA",
    "wof:name":"Karpeshty",
    "wof:placetype":"locality"
},
  "geometry": {"coordinates":[29.36222,47.78167],"type":"Point"}
}