{
  "type": "Feature",
  "properties": {
    "gn:admin1_code":"21.0",
    "gn:asciiname":"Tereshchenky",
    "gn:country_code":"UA",
    "gn:dem":165,
    "gn:feature_class":"P",
    "gn:feature_code":"PPL",
    "gn:name":"Tereshchenky",
    "gn:population":0,
    "gn:timezone":"Europe/Kiev",
    "iso:country":"UA",
    "name:ukr_x_preferred":[
        "\u0422\u0435\u0440\u0435\u0449\u0435\u043d\u043a\u0438"
    ],
    "name:und_x_variant":[
        "Tereshchenki",
        "Tereshchenkov",
        "Tereshchenky"
    ],
    "wof:name":"Tereshchenky",
    "wof:placetype":"locality"
},
  "geometry": {"coordinates":[34.19439000000001,51.01975],"type":"Point"}
}