{
  "type": "Feature",
  "properties": {
    "gn:admin1_code":"27.0",
    "gn:asciiname":"Malakhivka",
    "gn:country_code":"UA",
    "gn:dem":195,
    "gn:feature_class":"P",
    "gn:feature_code":"PPL",
    "gn:name":"Malakhivka",
    "gn:population":0,
    "gn:timezone":"Europe/Kiev",
    "iso:country":"UA",
    "name:ukr_x_preferred":[
        "Malakhivka"
    ],
    "name:ukr_x_variant":[
        "\u041c\u0430\u043b\u0430\u0445\u0456\u0432\u043a\u0430"
    ],
    "name:und_x_variant":[
        "Malakhovka"
    ],
    "wof:name":"Malakhivka",
    "wof:placetype":"locality"
},
  "geometry": {"coordinates":[28.36515,51.20292],"type":"Point"}
}