{
  "type": "Feature",
  "properties": {
    "iso:country":"UA",
    "name:rus_x_preferred":[
        "Tatarka"
    ],
    "name:sqi_x_preferred":[
        "Tatarka"
    ],
    "name:tat_x_preferred":[
        "\u0418\u0440\u0438\u043d\u0430 \u0421\u043c\u0435\u043b\u0430\u044f"
    ],
    "name:ukr_x_preferred":[
        "\u0422\u0430\u0442\u0430\u0440\u043a\u0430"
    ],
    "name:ukr_x_variant":[
        "Tatarka"
    ],
    "wof:name":"Tatarka",
    "wof:placetype":"neighbourhood"
},
  "geometry": {"coordinates":[30.4837720623466,50.46906625723078],"type":"Point"}
}