{
  "type": "Feature",
  "properties": {
    "gn:admin1_code":"5.0",
    "gn:asciiname":"Dymytrova",
    "gn:country_code":"UA",
    "gn:dem":309,
    "gn:feature_class":"P",
    "gn:feature_code":"PPL",
    "gn:name":"Dymytrova",
    "gn:population":0,
    "gn:timezone":"Europe/Kiev",
    "iso:country":"UA",
    "name:ukr_x_preferred":[
        "Dymytrova"
    ],
    "name:ukr_x_variant":[
        "\u0414\u0438\u043c\u0438\u0442\u0440\u043e\u0432\u0430"
    ],
    "wof:name":"Dymytrova",
    "wof:placetype":"locality"
},
  "geometry": {"coordinates":[38.50986,48.20065],"type":"Point"}
}