{
  "type": "Feature",
  "properties": {
    "gn:admin1_code":"19.0",
    "gn:asciiname":"Adamivka",
    "gn:country_code":"UA",
    "gn:dem":174,
    "gn:feature_class":"P",
    "gn:feature_code":"PPL",
    "gn:name":"Adamivka",
    "gn:population":0,
    "gn:timezone":"Europe/Kiev",
    "iso:country":"UA",
    "name:ukr_x_preferred":[
        "Adamivka"
    ],
    "name:ukr_x_variant":[
        "\u0410\u0434\u0430\u043c\u0456\u0432\u043a\u0430"
    ],
    "name:und_x_variant":[
        "Adamuvka",
        "Adamovka"
    ],
    "wof:name":"Adamivka",
    "wof:placetype":"locality"
},
  "geometry": {"coordinates":[26.94343,50.84031],"type":"Point"}
}