{
  "type": "Feature",
  "properties": {
    "gn:admin1_code":"18.0",
    "gn:asciiname":"Horyanshchyna",
    "gn:country_code":"UA",
    "gn:dem":183,
    "gn:feature_class":"P",
    "gn:feature_code":"PPL",
    "gn:name":"Horyanshchyna",
    "gn:population":0,
    "gn:timezone":"Europe/Kiev",
    "iso:country":"UA",
    "name:ukr_x_preferred":[
        "Horyanshchyna"
    ],
    "name:ukr_x_variant":[
        "\u0413\u043e\u0440\u044f\u043d\u0449\u0438\u043d\u0430"
    ],
    "wof:name":"Horyanshchyna",
    "wof:placetype":"locality"
},
  "geometry": {"coordinates":[34.45502,49.91177],"type":"Point"}
}