{
  "type": "Feature",
  "properties": {
    "gn:admin1_code":"7.0",
    "gn:asciiname":"Koloniya",
    "gn:country_code":"UA",
    "gn:dem":158,
    "gn:feature_class":"P",
    "gn:feature_code":"PPL",
    "gn:name":"Koloniya",
    "gn:population":0,
    "gn:timezone":"Europe/Kiev",
    "iso:country":"UA",
    "wof:name":"Koloniya",
    "wof:placetype":"locality"
},
  "geometry": {"coordinates":[37.42167,49.28778],"type":"Point"}
}