{
  "type": "Feature",
  "properties": {
    "iso:country":"UA",
    "name:ukr_x_preferred":[
        "Tur\u201dya-Bystra"
    ],
    "name:ukr_x_variant":[
        "\u0422\u0443\u0440\u2019\u044f-\u0411\u0438\u0441\u0442\u0440\u0430"
    ],
    "name:und_x_variant":[
        "Turyanske-Bystre"
    ],
    "qs:a0":"\u0423\u043a\u0440\u0430\u0457\u043d\u0430",
    "qs:a1":"*\u0417\u0430\u043a\u0430\u0440\u043f\u0430\u0442\u0441\u044c\u043a\u0430",
    "qs:a1_alt":"Zakarpats'ka",
    "qs:a1r":"0",
    "qs:a2":"\u041f\u0435\u0440\u0435\u0447\u0438\u043d\u0441\u044c\u043a\u0438\u0439",
    "qs:a2_alt":"Perechyns'kyi",
    "qs:adm0":"\u0423\u043a\u0440\u0430\u0457\u043d\u0430",
    "qs:la_lc":"*",
    "qs:level":"locality",
    "qs:loc":"\u0422\u0443\u0440'\u044f-\u0411\u0438\u0441\u0442\u0440\u0430",
    "qs:loc_alt":"Turia-Bystra",
    "qs:pop":0,
    "qs:type":"buffered point",
    "wof:name":"\u0422\u0443\u0440'\u044f-\u0411\u0438\u0441\u0442\u0440\u0430",
    "wof:placetype":"locality"
},
  "geometry": {"coordinates":[22.809352,48.658556],"type":"Point"}
}