{
  "type": "Feature",
  "properties": {
    "gn:admin1_code":"13.0",
    "gn:admin2_code":"Vyshhorod Raion (undefined)",
    "gn:asciiname":"Bodenky",
    "gn:country_code":"UA",
    "gn:dem":99,
    "gn:feature_class":"P",
    "gn:feature_code":"PPL",
    "gn:name":"Bodenky",
    "gn:population":0,
    "gn:timezone":"Europe/Kiev",
    "iso:country":"UA",
    "name:eng_x_preferred":[
        "Bodenky"
    ],
    "name:rus_x_preferred":[
        "\u0411\u043e\u0434\u0435\u043d\u044c\u043a\u0438"
    ],
    "name:ukr_x_preferred":[
        "\u0411\u043e\u0434\u0435\u043d\u044c\u043a\u0438"
    ],
    "wof:name":"Bodenky",
    "wof:placetype":"locality"
},
  "geometry": {"coordinates":[30.73277,50.83758],"type":"Point"}
}