{
  "type": "Feature",
  "properties": {
    "iso:country":"UA",
    "name:eng_x_preferred":[
        "Karpylivka"
    ],
    "name:ron_x_preferred":[
        "Karp\u00eelivka"
    ],
    "name:rus_x_preferred":[
        "\u041a\u0430\u0440\u043f\u0438\u043b\u043e\u0432\u043a\u0430"
    ],
    "name:ukr_x_preferred":[
        "Karpylivka"
    ],
    "name:ukr_x_variant":[
        "\u041a\u0430\u0440\u043f\u0438\u043b\u0456\u0432\u043a\u0430"
    ],
    "name:unk_x_variant":[
        "Karpiluvka"
    ],
    "qs:a0":"\u0423\u043a\u0440\u0430\u0457\u043d\u0430",
    "qs:a1":"*\u0420\u0456\u0432\u043d\u0435\u043d\u0441\u044c\u043a\u0430",
    "qs:a1_alt":"Rivnens'ka",
    "qs:a1r":"0",
    "qs:a2":"\u0421\u0430\u0440\u043d\u0435\u043d\u0441\u044c\u043a\u0438\u0439",
    "qs:a2_alt":"Sarnens'kyi",
    "qs:adm0":"\u0423\u043a\u0440\u0430\u0457\u043d\u0430",
    "qs:la_lc":"*",
    "qs:level":"locality",
    "qs:loc":"\u041a\u0430\u0440\u043f\u0438\u043b\u0456\u0432\u043a\u0430",
    "qs:loc_alt":"Karpylivka",
    "qs:pop":0,
    "qs:type":"buffered point",
    "wd:wordcount":68,
    "wof:name":"\u041a\u0430\u0440\u043f\u0438\u043b\u0456\u0432\u043a\u0430",
    "wof:placetype":"locality"
},
  "geometry": {"coordinates":[26.696754,51.411908],"type":"Point"}
}