{
  "type": "Feature",
  "properties": {
    "gn:gn_country":"UA",
    "gn:gn_fcode":"PPL",
    "gn:gn_pop":9749,
    "gn:population":9749,
    "iso:country":"UA",
    "name:pol_x_preferred":[
        "Zaleszczyki"
    ],
    "name:rus_x_preferred":[
        "\u0417\u0430\u043b\u0456\u0449\u0438\u043a\u0438"
    ],
    "name:ukr_x_preferred":[
        "\u0417\u0430\u043b\u0456\u0449\u0438\u043a\u0438"
    ],
    "name:unk_x_variant":[
        "Zalishchiki"
    ],
    "qs_pg:aaroncc":"UA",
    "qs_pg:gn_country":"UA",
    "qs_pg:gn_fcode":"PPL",
    "qs_pg:gn_pop":9749,
    "qs_pg:name":"Zalishchyky",
    "qs_pg:photos_9r":0,
    "qs_pg:photos_sr":0,
    "qs_pg:pop_sr":5,
    "qs_pg:qs_pg_placetype":"locality",
    "wof:name":"Zalishchyky",
    "wof:placetype":"locality",
    "wof:population":9749
},
  "geometry": {"coordinates":[25.73794,48.64331],"type":"Point"}
}