{
  "type": "Feature",
  "properties": {
    "gn:gn_country":"UA",
    "gn:gn_fcode":"PPL",
    "gn:gn_pop":9749,
    "gn:population":9749,
    "iso:country":"UA",
    "name:ara_x_preferred":[
        "\u0632\u0627\u0644\u064a\u0634\u062a\u0634\u064a\u0643\u064a"
    ],
    "name:bel_x_preferred":[
        "\u0417\u0430\u043b\u0456\u0448\u0447\u044b\u043a\u044b"
    ],
    "name:ceb_x_preferred":[
        "Zalishchyky"
    ],
    "name:crh_x_preferred":[
        "Zali\u015f\u00e7\u0131k\u0131"
    ],
    "name:deu_x_preferred":[
        "Salischtschyky"
    ],
    "name:fra_x_preferred":[
        "Zalichtchyky"
    ],
    "name:heb_x_preferred":[
        "\u05d6\u05d0\u05dc\u05e9\u05e6'\u05d9\u05e7\u05d9"
    ],
    "name:hsb_x_preferred":[
        "Zali\u0161\u0107yky"
    ],
    "name:hye_x_preferred":[
        "\u0536\u0561\u056c\u0565\u0577\u0579\u056b\u056f\u056b"
    ],
    "name:ita_x_preferred":[
        "Zali\u0161\u010dyky"
    ],
    "name:kat_x_preferred":[
        "\u10d6\u10d0\u10da\u10d4\u10e8\u10e9\u10d8\u10d9\u10d8"
    ],
    "name:lav_x_preferred":[
        "Za\u013ci\u0161\u010diki"
    ],
    "name:nno_x_preferred":[
        "Zalisjtsjyky"
    ],
    "name:pol_x_preferred":[
        "Zaleszczyki"
    ],
    "name:ron_x_preferred":[
        "Zali\u0219ci\u00eek\u00ee"
    ],
    "name:rus_x_preferred":[
        "\u0417\u0430\u043b\u0456\u0449\u0438\u043a\u0438"
    ],
    "name:rus_x_variant":[
        "\u0417\u0430\u043b\u0435\u0449\u0438\u043a\u0438"
    ],
    "name:szl_x_preferred":[
        "Zaliszczyki"
    ],
    "name:ukr_x_preferred":[
        "\u0417\u0430\u043b\u0456\u0449\u0438\u043a\u0438"
    ],
    "name:unk_x_variant":[
        "Zalishchiki"
    ],
    "name:vie_x_preferred":[
        "Zalischyky"
    ],
    "name:yid_x_preferred":[
        "\u05d6\u05d0\u05dc\u05d9\u05e9\u05d8\u05e9\u05d9\u05e7"
    ],
    "name:zho_x_preferred":[
        "\u624e\u5217\u5e0c\u57fa"
    ],
    "qs_pg:aaroncc":"UA",
    "qs_pg:gn_country":"UA",
    "qs_pg:gn_fcode":"PPL",
    "qs_pg:gn_pop":9749,
    "qs_pg:name":"Zalishchyky",
    "qs_pg:photos_9r":0,
    "qs_pg:photos_sr":0,
    "qs_pg:pop_sr":5,
    "qs_pg:qs_pg_placetype":"locality",
    "wof:name":"Zalishchyky",
    "wof:placetype":"locality",
    "wof:population":9749
},
  "geometry": {"coordinates":[25.73794,48.64331],"type":"Point"}
}