{
  "type": "Feature",
  "properties": {
    "gn:population":19404,
    "iso:country":"UA",
    "name:azb_x_preferred":[
        "\u0627\u0633\u06a9\u0627\u062f\u0648\u0641\u0633\u06a9"
    ],
    "name:bel_x_preferred":[
        "\u0421\u043a\u0430\u0434\u043e\u045e\u0441\u043a"
    ],
    "name:bul_x_preferred":[
        "\u0421\u043a\u0430\u0434\u043e\u0432\u0441\u043a"
    ],
    "name:ceb_x_preferred":[
        "Skadovs'k"
    ],
    "name:ces_x_preferred":[
        "Skadovsk"
    ],
    "name:crh_x_preferred":[
        "Skadovsk"
    ],
    "name:deu_x_preferred":[
        "Skadowsk"
    ],
    "name:eng_x_preferred":[
        "Skadowsk"
    ],
    "name:eng_x_variant":[
        "Skadovsk"
    ],
    "name:epo_x_preferred":[
        "Skadovsk"
    ],
    "name:fas_x_preferred":[
        "\u0627\u0633\u06a9\u0627\u062f\u0648\u0641\u0633\u06a9"
    ],
    "name:fra_x_preferred":[
        "Skadovsk"
    ],
    "name:heb_x_preferred":[
        "\u05e1\u05e7\u05d3\u05d5\u05d1\u05e1\u05e7"
    ],
    "name:hsb_x_preferred":[
        "Skadowsk"
    ],
    "name:hye_x_preferred":[
        "\u054d\u056f\u0561\u0564\u0578\u057e\u057d\u056f"
    ],
    "name:ita_x_preferred":[
        "Skadovs'k"
    ],
    "name:kat_x_preferred":[
        "\u10e1\u10d9\u10d0\u10d3\u10dd\u10d5\u10e1\u10d9\u10d8"
    ],
    "name:lav_x_preferred":[
        "Skadovska"
    ],
    "name:nld_x_preferred":[
        "Skadovsk"
    ],
    "name:nno_x_preferred":[
        "Skadovsk"
    ],
    "name:pol_x_preferred":[
        "Skadow\u015bk"
    ],
    "name:pol_x_variant":[
        "Skadowsk"
    ],
    "name:ron_x_preferred":[
        "Skadovsk"
    ],
    "name:rus_x_preferred":[
        "\u0421\u043a\u0430\u0434\u043e\u0432\u0441\u043a"
    ],
    "name:sco_x_preferred":[
        "Skadovsk"
    ],
    "name:spa_x_preferred":[
        "Skadovsk"
    ],
    "name:tat_x_preferred":[
        "\u0421\u043a\u0430\u0434\u043e\u0432\u0441\u043a"
    ],
    "name:ukr_x_preferred":[
        "\u0421\u043a\u0430\u0434\u043e\u0432\u0441\u044c\u043a"
    ],
    "name:ukr_x_variant":[
        "Skadovs\u2019k"
    ],
    "name:vie_x_preferred":[
        "Skadovsk"
    ],
    "name:zho_x_preferred":[
        "\u65af\u5361\u591a\u592b\u65af\u514b"
    ],
    "qs:a0":"\u0423\u043a\u0440\u0430\u0457\u043d\u0430",
    "qs:a1":"*\u0425\u0435\u0440\u0441\u043e\u043d\u0441\u044c\u043a\u0430",
    "qs:a1_alt":"Khersons'ka",
    "qs:a1r":"0",
    "qs:a2":"\u0421\u043a\u0430\u0434\u043e\u0432\u0441\u044c\u043a\u0438\u0439",
    "qs:a2_alt":"Skadovs'kyi",
    "qs:adm0":"\u0423\u043a\u0440\u0430\u0457\u043d\u0430",
    "qs:la_lc":"*",
    "qs:level":"locality",
    "qs:loc":"\u0421\u043a\u0430\u0434\u043e\u0432\u0441\u044c\u043a",
    "qs:loc_alt":"Skadovs'k",
    "qs:pop":0,
    "qs:type":"buffered point",
    "wd:wordcount":300,
    "wof:name":"\u0421\u043a\u0430\u0434\u043e\u0432\u0441\u044c\u043a",
    "wof:placetype":"locality",
    "wof:population":19404
},
  "geometry": {"coordinates":[32.90965,46.119733],"type":"Point"}
}