{
  "type": "Feature",
  "properties": {
    "gn:admin1_code":"15.0",
    "gn:asciiname":"Lesnevichi",
    "gn:country_code":"UA",
    "gn:dem":255,
    "gn:feature_class":"P",
    "gn:feature_code":"PPL",
    "gn:name":"Lesnevichi",
    "gn:population":0,
    "gn:timezone":"Europe/Kiev",
    "iso:country":"UA",
    "name:und_x_variant":[
        "Lesniovitse",
        "Lesnevichi"
    ],
    "wof:name":"Lesnevichi",
    "wof:placetype":"locality"
},
  "geometry": {"coordinates":[23.56728,49.86667],"type":"Point"}
}