{
  "type": "Feature",
  "properties": {
    "gn:admin1_code":"27.0",
    "gn:asciiname":"Kolodyaz'ky",
    "gn:country_code":"UA",
    "gn:dem":213,
    "gn:feature_class":"P",
    "gn:feature_code":"PPL",
    "gn:name":"Kolodyaz\u2019ky",
    "gn:population":0,
    "gn:timezone":"Europe/Kiev",
    "iso:country":"UA",
    "name:rus_x_preferred":[
        "Kolodez\u2019ki"
    ],
    "name:ukr_x_preferred":[
        "Kolodyaz\u2019ky"
    ],
    "name:ukr_x_variant":[
        "\u041a\u043e\u043b\u043e\u0434\u044f\u0437\u044c\u043a\u0438"
    ],
    "wof:name":"Kolodyaz'ky",
    "wof:placetype":"locality"
},
  "geometry": {"coordinates":[28.90732,50.30073],"type":"Point"}
}