{
  "type": "Feature",
  "properties": {
    "gn:admin1_code":"4.0",
    "gn:asciiname":"Byshneve",
    "gn:country_code":"UA",
    "gn:dem":91,
    "gn:feature_class":"P",
    "gn:feature_code":"PPL",
    "gn:name":"Byshneve",
    "gn:population":0,
    "gn:timezone":"Europe/Kiev",
    "iso:country":"UA",
    "name:ukr_x_preferred":[
        "Byshneve"
    ],
    "name:ukr_x_variant":[
        "\u0412\u0438\u0448\u043d\u0435\u0432\u0435"
    ],
    "wof:name":"Byshneve",
    "wof:placetype":"locality"
},
  "geometry": {"coordinates":[34.41282,48.49822],"type":"Point"}
}