{
  "type": "Feature",
  "properties": {
    "gn:admin1_code":"23.0",
    "gn:asciiname":"Pochapintsy",
    "gn:country_code":"UA",
    "gn:dem":316,
    "gn:feature_class":"P",
    "gn:feature_code":"PPL",
    "gn:name":"Pochapintsy",
    "gn:population":0,
    "gn:timezone":"Europe/Kiev",
    "iso:country":"UA",
    "name:und_x_variant":[
        "Pochapinets",
        "Pochapintsy"
    ],
    "wof:name":"Pochapintsy",
    "wof:placetype":"locality"
},
  "geometry": {"coordinates":[28.04639,49.21564],"type":"Point"}
}