{
  "type": "Feature",
  "properties": {
    "gn:admin1_code":"18.0",
    "gn:asciiname":"Hyryavi Iskivtsi",
    "gn:country_code":"UA",
    "gn:dem":108,
    "gn:feature_class":"P",
    "gn:feature_code":"PPL",
    "gn:name":"Hyryavi Iskivtsi",
    "gn:population":0,
    "gn:timezone":"Europe/Kiev",
    "iso:country":"UA",
    "name:ukr_x_preferred":[
        "Hyryavi Iskivtsi"
    ],
    "name:ukr_x_variant":[
        "\u0413\u0438\u0440\u044f\u0432\u0456 \u0406\u0441\u043a\u0456\u0432\u0446\u0456"
    ],
    "name:und_x_variant":[
        "Giryavyye Iskovtsy",
        "Girevy Yuskovtsy",
        "Girevy Iskovtsy"
    ],
    "wof:name":"Hyryavi Iskivtsi",
    "wof:placetype":"locality"
},
  "geometry": {"coordinates":[33.3105,50.42631],"type":"Point"}
}