{
  "type": "Feature",
  "properties": {
    "gn:admin1_code":"14.0",
    "gn:asciiname":"Kuban'",
    "gn:country_code":"UA",
    "gn:dem":69,
    "gn:feature_class":"P",
    "gn:feature_code":"PPL",
    "gn:name":"Kuban\u2019",
    "gn:population":0,
    "gn:timezone":"Europe/Zaporozhye",
    "iso:country":"UA",
    "name:ukr_x_preferred":[
        "Kuban\u2019"
    ],
    "name:ukr_x_variant":[
        "\u041a\u0443\u0431\u0430\u043d\u044c"
    ],
    "name:und_x_variant":[
        "Kuban"
    ],
    "wof:name":"Kuban'",
    "wof:placetype":"locality"
},
  "geometry": {"coordinates":[39.02931,49.6513],"type":"Point"}
}