{
  "type": "Feature",
  "properties": {
    "gn:admin1_code":"1.0",
    "gn:asciiname":"Serbynivka",
    "gn:country_code":"UA",
    "gn:dem":116,
    "gn:feature_class":"P",
    "gn:feature_code":"PPL",
    "gn:name":"Serbynivka",
    "gn:population":0,
    "gn:timezone":"Europe/Kiev",
    "iso:country":"UA",
    "name:eng_x_preferred":[
        "Pershe Travnya"
    ],
    "name:rus_x_preferred":[
        "\u041f\u0435\u0440\u0448\u0435-\u0422\u0440\u0430\u0432\u043d\u044f"
    ],
    "name:ukr_x_preferred":[
        "Serbynivka"
    ],
    "name:ukr_x_variant":[
        "\u0421\u0435\u0440\u0431\u0438\u043d\u0456\u0432\u043a\u0430"
    ],
    "name:und_x_variant":[
        "Serbinovka",
        "Pervoye Maya",
        "Pershe Travnya"
    ],
    "wof:name":"Serbynivka",
    "wof:placetype":"locality"
},
  "geometry": {"coordinates":[32.28061,50.09952],"type":"Point"}
}