{
  "type": "Feature",
  "properties": {
    "iso:country":"UA",
    "qs:a0":"\u0423\u043a\u0440\u0430\u0457\u043d\u0430",
    "qs:a1":"*\u0427\u0435\u0440\u043d\u0456\u0432\u0435\u0446\u044c\u043a\u0430",
    "qs:a1_alt":"Chernivets'ka",
    "qs:a1r":"0",
    "qs:a2":"\u041f\u0443\u0442\u0438\u043b\u044c\u0441\u044c\u043a\u0438\u0439",
    "qs:a2_alt":"Putyl's'kyi",
    "qs:adm0":"\u0423\u043a\u0440\u0430\u0457\u043d\u0430",
    "qs:la_lc":"*",
    "qs:level":"locality",
    "qs:loc":"\u0420\u043e\u0437\u0442\u043e\u043a\u0438",
    "qs:loc_alt":"Roztoky",
    "qs:pop":0,
    "qs:type":"buffered point",
    "wd:wordcount":105,
    "wof:name":"\u0420\u043e\u0437\u0442\u043e\u043a\u0438",
    "wof:placetype":"locality"
},
  "geometry": {"coordinates":[25.163397,48.151986],"type":"Point"}
}