{
  "type": "Feature",
  "properties": {
    "gn:admin1_code":"4.0",
    "gn:asciiname":"Mali Buchky",
    "gn:country_code":"UA",
    "gn:dem":93,
    "gn:feature_class":"P",
    "gn:feature_code":"PPL",
    "gn:name":"Mali Buchky",
    "gn:population":0,
    "gn:timezone":"Europe/Kiev",
    "iso:country":"UA",
    "name:rus_x_preferred":[
        "\u041c\u0430\u043b\u044b\u0435 \u0411\u0443\u0447\u043a\u0438"
    ],
    "name:ukr_x_preferred":[
        "Mali Buchky"
    ],
    "name:ukr_x_variant":[
        "\u041c\u0430\u043b\u0456 \u0411\u0443\u0447\u043a\u0438"
    ],
    "name:und_x_variant":[
        "Malyy Buchki",
        "Malyye Buchki"
    ],
    "wof:name":"Mali Buchky",
    "wof:placetype":"locality"
},
  "geometry": {"coordinates":[35.53088,49.00202],"type":"Point"}
}