{
  "type": "Feature",
  "properties": {
    "gn:admin1_code":"2.0",
    "gn:asciiname":"Kloniv",
    "gn:country_code":"UA",
    "gn:dem":144,
    "gn:feature_class":"P",
    "gn:feature_code":"PPL",
    "gn:name":"Kloniv",
    "gn:population":0,
    "gn:timezone":"Europe/Kiev",
    "iso:country":"UA",
    "name:ukr_x_preferred":[
        "Kloniv"
    ],
    "name:ukr_x_variant":[
        "\u041a\u043b\u043e\u043d\u0456\u0432"
    ],
    "name:und_x_variant":[
        "Klonov"
    ],
    "wof:name":"Kloniv",
    "wof:placetype":"locality"
},
  "geometry": {"coordinates":[30.76026,51.64656],"type":"Point"}
}