{
  "type": "Feature",
  "properties": {
    "gn:admin1_code":"5.0",
    "gn:asciiname":"Pishchane",
    "gn:country_code":"UA",
    "gn:dem":153,
    "gn:feature_class":"P",
    "gn:feature_code":"PPL",
    "gn:name":"Pishchane",
    "gn:population":0,
    "gn:timezone":"Europe/Kiev",
    "iso:country":"UA",
    "name:ukr_x_preferred":[
        "Pishchane"
    ],
    "name:ukr_x_variant":[
        "\u041f\u0456\u0449\u0430\u043d\u0435"
    ],
    "name:und_x_variant":[
        "Mar\u2019inskaya-Pustosh\u2019",
        "Peschanoye"
    ],
    "wof:name":"Pishchane",
    "wof:placetype":"locality"
},
  "geometry": {"coordinates":[37.11148,48.23399000000001],"type":"Point"}
}