{
  "type": "Feature",
  "properties": {
    "gn:admin1_code":"2.0",
    "gn:asciiname":"Bubnivshchyna",
    "gn:country_code":"UA",
    "gn:dem":128,
    "gn:feature_class":"P",
    "gn:feature_code":"PPL",
    "gn:name":"Bubnivshchyna",
    "gn:population":0,
    "gn:timezone":"Europe/Kiev",
    "iso:country":"UA",
    "name:ukr_x_preferred":[
        "Bubnivshchyna"
    ],
    "name:ukr_x_variant":[
        "\u0411\u0443\u0431\u043d\u0456\u0432\u0449\u0438\u043d\u0430"
    ],
    "name:und_x_variant":[
        "Bubnovshchina"
    ],
    "wof:name":"Bubnivshchyna",
    "wof:placetype":"locality"
},
  "geometry": {"coordinates":[32.28117,50.4043],"type":"Point"}
}