{
  "type": "Feature",
  "properties": {
    "gn:admin1_code":"2.0",
    "gn:asciiname":"Lopatyn",
    "gn:country_code":"UA",
    "gn:dem":121,
    "gn:feature_class":"P",
    "gn:feature_code":"PPL",
    "gn:name":"Lopatyn",
    "gn:population":0,
    "gn:timezone":"Europe/Kiev",
    "iso:country":"UA",
    "name:ukr_x_preferred":[
        "Lopatyn"
    ],
    "name:ukr_x_variant":[
        "\u041b\u043e\u043f\u0430\u0442\u0438\u043d"
    ],
    "name:und_x_variant":[
        "Lopatin"
    ],
    "wof:name":"Lopatyn",
    "wof:placetype":"locality"
},
  "geometry": {"coordinates":[32.93713,51.38696],"type":"Point"}
}