{
  "type": "Feature",
  "properties": {
    "gn:admin1_code":"14.0",
    "gn:asciiname":"Vysochynivka",
    "gn:country_code":"UA",
    "gn:dem":182,
    "gn:feature_class":"P",
    "gn:feature_code":"PPL",
    "gn:name":"Vysochynivka",
    "gn:population":0,
    "gn:timezone":"Europe/Zaporozhye",
    "iso:country":"UA",
    "name:ukr_x_preferred":[
        "Vysochynivka"
    ],
    "name:ukr_x_variant":[
        "\u0412\u0438\u0441\u043e\u0447\u0438\u043d\u0456\u0432\u043a\u0430"
    ],
    "name:und_x_variant":[
        "Vysochinov",
        "Vysochinovka",
        "Vysochanovka"
    ],
    "wof:name":"Vysochynivka",
    "wof:placetype":"locality"
},
  "geometry": {"coordinates":[39.55013,49.70653],"type":"Point"}
}