{
  "type": "Feature",
  "properties": {
    "gn:admin1_code":"17.0",
    "gn:asciiname":"Sukhomlinovo",
    "gn:country_code":"UA",
    "gn:dem":15,
    "gn:feature_class":"P",
    "gn:feature_code":"PPL",
    "gn:name":"Sukhomlinovo",
    "gn:population":0,
    "gn:timezone":"Europe/Kiev",
    "iso:country":"UA",
    "name:und_x_variant":[
        "Novo-Sukhomlinovo",
        "Sukhomlinovo"
    ],
    "wof:name":"Sukhomlinovo",
    "wof:placetype":"locality"
},
  "geometry": {"coordinates":[30.3628,46.97638],"type":"Point"}
}