{
  "type": "Feature",
  "properties": {
    "gn:admin1_code":"4.0",
    "gn:asciiname":"Morozivs'ke",
    "gn:country_code":"UA",
    "gn:dem":133,
    "gn:feature_class":"P",
    "gn:feature_code":"PPL",
    "gn:name":"Morozivs\u2019ke",
    "gn:population":0,
    "gn:timezone":"Europe/Kiev",
    "iso:country":"UA",
    "name:ukr_x_preferred":[
        "Morozivs\u2019ke"
    ],
    "name:ukr_x_variant":[
        "\u041c\u043e\u0440\u043e\u0437\u0456\u0432\u0441\u044c\u043a\u0435"
    ],
    "name:und_x_variant":[
        "Morozovskiy",
        "Morozovskoye"
    ],
    "wof:name":"Morozivs'ke",
    "wof:placetype":"locality"
},
  "geometry": {"coordinates":[35.42401,48.37271],"type":"Point"}
}