{
  "type": "Feature",
  "properties": {
    "gn:admin1_code":"6.0",
    "gn:asciiname":"Bohrivka",
    "gn:country_code":"UA",
    "gn:dem":616,
    "gn:feature_class":"P",
    "gn:feature_code":"PPL",
    "gn:name":"Bohrivka",
    "gn:population":0,
    "gn:timezone":"Europe/Kiev",
    "iso:country":"UA",
    "name:ukr_x_preferred":[
        "Bohrivka"
    ],
    "name:ukr_x_variant":[
        "\u0411\u043e\u0433\u0440\u0456\u0432\u043a\u0430"
    ],
    "name:und_x_variant":[
        "Bogrovka",
        "Bogruvka"
    ],
    "wof:name":"Bohrivka",
    "wof:placetype":"locality"
},
  "geometry": {"coordinates":[24.26449,48.71922],"type":"Point"}
}