{
  "type": "Feature",
  "properties": {
    "gn:admin1_code":"1.0",
    "gn:asciiname":"Nesterovka",
    "gn:country_code":"UA",
    "gn:dem":232,
    "gn:feature_class":"P",
    "gn:feature_code":"PPL",
    "gn:name":"Nesterovka",
    "gn:population":0,
    "gn:timezone":"Europe/Kiev",
    "iso:country":"UA",
    "name:eng_x_preferred":[
        "Nesterovka"
    ],
    "name:rus_x_preferred":[
        "\u041d\u0435\u0441\u0442\u0435\u0440\u043e\u0432\u043a\u0430"
    ],
    "wof:name":"Nesterovka",
    "wof:placetype":"locality"
},
  "geometry": {"coordinates":[30.17998,48.98398],"type":"Point"}
}