{
  "type": "Feature",
  "properties": {
    "gn:admin1_code":"2.0",
    "gn:asciiname":"Uborky",
    "gn:country_code":"UA",
    "gn:dem":113,
    "gn:feature_class":"P",
    "gn:feature_code":"PPL",
    "gn:name":"Uborky",
    "gn:population":0,
    "gn:timezone":"Europe/Kiev",
    "iso:country":"UA",
    "name:ukr_x_preferred":[
        "Uborky"
    ],
    "name:ukr_x_variant":[
        "\u0423\u0431\u043e\u0440\u043a\u0438"
    ],
    "name:und_x_variant":[
        "Uborki"
    ],
    "wof:name":"Uborky",
    "wof:placetype":"locality"
},
  "geometry": {"coordinates":[31.53529,51.48381],"type":"Point"}
}