{
  "type": "Feature",
  "properties": {
    "gn:admin1_code":"14.0",
    "gn:asciiname":"Petroven'ky",
    "gn:country_code":"UA",
    "gn:dem":69,
    "gn:feature_class":"P",
    "gn:feature_code":"PPL",
    "gn:name":"Petroven\u2019ky",
    "gn:population":0,
    "gn:timezone":"Europe/Zaporozhye",
    "iso:country":"UA",
    "name:rus_x_preferred":[
        "Petroven\u2019ki"
    ],
    "name:ukr_x_preferred":[
        "Petroven\u2019ky"
    ],
    "name:ukr_x_variant":[
        "\u041f\u0435\u0442\u0440\u043e\u0432\u0435\u043d\u044c\u043a\u0438"
    ],
    "wof:name":"Petroven'ky",
    "wof:placetype":"locality"
},
  "geometry": {"coordinates":[38.78911,48.6455],"type":"Point"}
}