{
  "type": "Feature",
  "properties": {
    "gn:admin1_code":"2.0",
    "gn:asciiname":"Petrushivka",
    "gn:country_code":"UA",
    "gn:dem":157,
    "gn:feature_class":"P",
    "gn:feature_code":"PPL",
    "gn:name":"Petrushivka",
    "gn:population":0,
    "gn:timezone":"Europe/Kiev",
    "iso:country":"UA",
    "name:ukr_x_preferred":[
        "Petrushivka"
    ],
    "name:ukr_x_variant":[
        "\u041f\u0435\u0442\u0440\u0443\u0448\u0456\u0432\u043a\u0430"
    ],
    "name:und_x_variant":[
        "Petrushovka"
    ],
    "wof:name":"Petrushivka",
    "wof:placetype":"locality"
},
  "geometry": {"coordinates":[32.66537,50.85302],"type":"Point"}
}