{
  "type": "Feature",
  "properties": {
    "gn:gn_country":"UA",
    "gn:gn_fcode":"PPL",
    "gn:gn_pop":8443,
    "gn:population":8443,
    "iso:country":"UA",
    "name:ara_x_preferred":[
        "\u0641\u0627\u0628\u0646\u064a\u0627\u0631\u0643\u0627"
    ],
    "name:chi_x_preferred":[
        "\u74e6\u666e\u5c3c\u4e9e\u723e\u5361"
    ],
    "name:eng_x_preferred":[
        "Vapniarka"
    ],
    "name:fre_x_preferred":[
        "Vapniarka"
    ],
    "name:ger_x_preferred":[
        "Wapnjarka"
    ],
    "name:ita_x_preferred":[
        "Vapniarca"
    ],
    "name:pol_x_preferred":[
        "Wapniarka"
    ],
    "name:rum_x_preferred":[
        "Vapniarka"
    ],
    "name:rus_x_preferred":[
        "\u0412\u0430\u043f\u043d\u044f\u0440\u043a\u0430"
    ],
    "name:sah_x_preferred":[
        "\u0412\u0430\u043f\u043d\u044f\u0440\u043a\u0430"
    ],
    "name:ukr_x_preferred":[
        "\u0412\u0430\u043f\u043d\u044f\u0440\u043a\u0430"
    ],
    "name:unk_x_variant":[
        "Wapnjarka"
    ],
    "qs_pg:aaroncc":"UA",
    "qs_pg:gn_country":"UA",
    "qs_pg:gn_fcode":"PPL",
    "qs_pg:gn_pop":8443,
    "qs_pg:name":"Vapnyarka",
    "qs_pg:photos_9r":0,
    "qs_pg:photos_sr":0,
    "qs_pg:pop_sr":5,
    "qs_pg:qs_pg_placetype":"locality",
    "wof:name":"Vapnyarka",
    "wof:placetype":"locality",
    "wof:population":8443
},
  "geometry": {"coordinates":[28.74358,48.53479],"type":"Point"}
}