{
  "type": "Feature",
  "properties": {
    "gn:admin1_code":"21.0",
    "gn:asciiname":"Paliyivka",
    "gn:country_code":"UA",
    "gn:dem":161,
    "gn:feature_class":"P",
    "gn:feature_code":"PPL",
    "gn:name":"Paliyivka",
    "gn:population":0,
    "gn:timezone":"Europe/Kiev",
    "iso:country":"UA",
    "name:ukr_x_preferred":[
        "Paliyivka"
    ],
    "name:ukr_x_variant":[
        "\u041f\u0430\u043b\u0456\u0457\u0432\u043a\u0430"
    ],
    "name:und_x_variant":[
        "Poleyevka",
        "Paleyevka"
    ],
    "wof:name":"Paliyivka",
    "wof:placetype":"locality"
},
  "geometry": {"coordinates":[33.64377,51.91978],"type":"Point"}
}