{
  "type": "Feature",
  "properties": {
    "iso:country":"UA",
    "name:eng_x_preferred":[
        "Heronymivka"
    ],
    "name:ron_x_preferred":[
        "Heron\u00eemivka"
    ],
    "name:rus_x_preferred":[
        "\u0413\u0435\u0440\u043e\u043d\u0438\u043c\u043e\u0432\u043a\u0430"
    ],
    "name:ukr_x_preferred":[
        "\u0413\u0435\u0440\u043e\u043d\u0438\u043c\u0456\u0432\u043a\u0430"
    ],
    "qs:a0":"\u0423\u043a\u0440\u0430\u0457\u043d\u0430",
    "qs:a1":"*\u0427\u0435\u0440\u043a\u0430\u0441\u044c\u043a\u0430",
    "qs:a1_alt":"Cherkas'ka",
    "qs:a1r":"0",
    "qs:a2":"\u0427\u0435\u0440\u043a\u0430\u0441\u044c\u043a\u0438\u0439",
    "qs:a2_alt":"Cherkas'kyi",
    "qs:adm0":"\u0423\u043a\u0440\u0430\u0457\u043d\u0430",
    "qs:la_lc":"*",
    "qs:level":"locality",
    "qs:loc":"\u0413\u0435\u0440\u043e\u043d\u0438\u043c\u0456\u0432\u043a\u0430",
    "qs:loc_alt":"Heronymivka",
    "qs:pop":0,
    "qs:type":"buffered point",
    "wd:wordcount":132,
    "wof:name":"\u0413\u0435\u0440\u043e\u043d\u0438\u043c\u0456\u0432\u043a\u0430",
    "wof:placetype":"locality"
},
  "geometry": {"coordinates":[31.946809,49.449023],"type":"Point"}
}