{
  "type": "Feature",
  "properties": {
    "gn:admin1_code":"18.0",
    "gn:asciiname":"Osokory",
    "gn:country_code":"UA",
    "gn:dem":102,
    "gn:feature_class":"P",
    "gn:feature_code":"PPL",
    "gn:name":"Osokory",
    "gn:population":0,
    "gn:timezone":"Europe/Kiev",
    "iso:country":"UA",
    "name:ukr_x_preferred":[
        "Osokory"
    ],
    "name:ukr_x_variant":[
        "\u041e\u0441\u043e\u043a\u043e\u0440\u0438"
    ],
    "wof:name":"Osokory",
    "wof:placetype":"locality"
},
  "geometry": {"coordinates":[33.01102,49.69706],"type":"Point"}
}