{
  "type": "Feature",
  "properties": {
    "iso:country":"UA",
    "name:eng_x_preferred":[
        "Zhovtnevoye"
    ],
    "name:rus_x_preferred":[
        "\u0416\u043e\u0432\u0442\u043d\u0435\u0432\u043e\u0435"
    ],
    "name:ukr_x_preferred":[
        "Zhovtneve"
    ],
    "name:ukr_x_variant":[
        "\u0416\u043e\u0432\u0442\u043d\u0435\u0432\u0435"
    ],
    "qs:a0":"\u0423\u043a\u0440\u0430\u0457\u043d\u0430",
    "qs:a1":"*\u041f\u043e\u043b\u0442\u0430\u0432\u0441\u044c\u043a\u0430",
    "qs:a1_alt":"Poltavs'ka",
    "qs:a1r":"0",
    "qs:a2":"\u0420\u0435\u0448\u0435\u0442\u0438\u043b\u0456\u0432\u0441\u044c\u043a\u0438\u0439",
    "qs:a2_alt":"Reshetylivs'kyi",
    "qs:adm0":"\u0423\u043a\u0440\u0430\u0457\u043d\u0430",
    "qs:la_lc":"*",
    "qs:level":"locality",
    "qs:loc":"\u0416\u043e\u0432\u0442\u043d\u0435\u0432\u0435",
    "qs:loc_alt":"Zhovtneve",
    "qs:pop":0,
    "qs:type":"buffered point",
    "wd:wordcount":105,
    "wof:name":"\u0416\u043e\u0432\u0442\u043d\u0435\u0432\u0435",
    "wof:placetype":"locality"
},
  "geometry": {"coordinates":[34.136187,49.643779],"type":"Point"}
}