{
  "type": "Feature",
  "properties": {
    "gn:admin1_code":"27.0",
    "gn:asciiname":"Klynets'",
    "gn:country_code":"UA",
    "gn:dem":190,
    "gn:feature_class":"P",
    "gn:feature_code":"PPL",
    "gn:name":"Klynets\u2019",
    "gn:population":0,
    "gn:timezone":"Europe/Kiev",
    "iso:country":"UA",
    "name:ukr_x_preferred":[
        "Klynets\u2019"
    ],
    "name:ukr_x_variant":[
        "\u041a\u043b\u0438\u043d\u0435\u0446\u044c"
    ],
    "name:und_x_variant":[
        "Klinets"
    ],
    "wof:name":"Klynets'",
    "wof:placetype":"locality"
},
  "geometry": {"coordinates":[28.68237,51.33027],"type":"Point"}
}