{
  "type": "Feature",
  "properties": {
    "gn:admin1_code":"24.0",
    "gn:asciiname":"Berezniki",
    "gn:country_code":"UA",
    "gn:dem":150,
    "gn:feature_class":"P",
    "gn:feature_code":"PPL",
    "gn:name":"Berezniki",
    "gn:population":0,
    "gn:timezone":"Europe/Kiev",
    "iso:country":"UA",
    "name:rus_x_preferred":[
        "\u0411\u0435\u0440\u0435\u0437\u043d\u0438\u043a\u0438"
    ],
    "wof:name":"Berezniki",
    "wof:placetype":"locality"
},
  "geometry": {"coordinates":[24.68455,51.87268],"type":"Point"}
}