{
  "type": "Feature",
  "properties": {
    "iso:country":"UA",
    "name:deu_x_preferred":[
        "Tokari"
    ],
    "name:eng_x_preferred":[
        "Tokari"
    ],
    "name:hye_x_preferred":[
        "\u054f\u0578\u056f\u0561\u0580\u056b"
    ],
    "name:ron_x_preferred":[
        "Tokari"
    ],
    "name:rus_x_preferred":[
        "\u0422\u043e\u043a\u0430\u0440\u0438"
    ],
    "name:ukr_x_preferred":[
        "\u0422\u043e\u043a\u0430\u0440\u0456"
    ],
    "name:und_x_variant":[
        "Tokapi"
    ],
    "qs:a0":"\u0423\u043a\u0440\u0430\u0457\u043d\u0430",
    "qs:a1":"*\u041f\u043e\u043b\u0442\u0430\u0432\u0441\u044c\u043a\u0430",
    "qs:a1_alt":"Poltavs'ka",
    "qs:a1r":"0",
    "qs:a2":"\u041b\u043e\u0445\u0432\u0438\u0446\u044c\u043a\u0438\u0439",
    "qs:a2_alt":"Lokhvyts'kyi",
    "qs:adm0":"\u0423\u043a\u0440\u0430\u0457\u043d\u0430",
    "qs:la_lc":"*",
    "qs:level":"locality",
    "qs:loc":"\u0422\u043e\u043a\u0430\u0440\u0456",
    "qs:loc_alt":"Tokari",
    "qs:pop":0,
    "qs:type":"buffered point",
    "wof:name":"\u0422\u043e\u043a\u0430\u0440\u0456",
    "wof:placetype":"locality"
},
  "geometry": {"coordinates":[33.426227,50.409094],"type":"Point"}
}