{
  "type": "Feature",
  "properties": {
    "gn:population":13008,
    "iso:country":"UA",
    "name:bel_x_preferred":[
        "\u042f\u0432\u0430\u0440\u044b\u045e"
    ],
    "name:bel_x_variant":[
        "\u042f\u0432\u0430\u0440\u0430\u045e"
    ],
    "name:bul_x_preferred":[
        "\u042f\u0432\u043e\u0440\u043e\u0432"
    ],
    "name:ceb_x_preferred":[
        "Yavoriv"
    ],
    "name:ces_x_preferred":[
        "Javoriv"
    ],
    "name:crh_x_preferred":[
        "Yavoriv"
    ],
    "name:deu_x_preferred":[
        "Jaworiw"
    ],
    "name:eng_x_preferred":[
        "Yavoriv"
    ],
    "name:fas_x_preferred":[
        "\u06cc\u0627\u0641\u0648\u0631\u0648\u0641"
    ],
    "name:fra_x_preferred":[
        "Yavoriv"
    ],
    "name:heb_x_preferred":[
        "\u05d9\u05d1\u05d5\u05e8\u05d9\u05d1"
    ],
    "name:hsb_x_preferred":[
        "Jaworiw"
    ],
    "name:hun_x_preferred":[
        "Javoriv"
    ],
    "name:hye_x_preferred":[
        "\u0545\u0561\u057e\u0578\u0580\u0578\u057e"
    ],
    "name:ita_x_preferred":[
        "Javorov"
    ],
    "name:jpn_x_preferred":[
        "\u30e4\u30fc\u30f4\u30a9\u30ea\u30a6"
    ],
    "name:kat_x_preferred":[
        "\u10d8\u10d0\u10d5\u10dd\u10e0\u10dd\u10d5\u10d8"
    ],
    "name:kir_x_preferred":[
        "\u042f\u0432\u043e\u0440\u043e\u0432"
    ],
    "name:kor_x_preferred":[
        "\uc57c\ubcf4\ub9ac\uc6b0"
    ],
    "name:lav_x_preferred":[
        "Javoriva"
    ],
    "name:nld_x_preferred":[
        "Yavoriv"
    ],
    "name:nno_x_preferred":[
        "Javoriv"
    ],
    "name:pol_x_preferred":[
        "Jawor\u00f3w"
    ],
    "name:ron_x_preferred":[
        "Iavoriv"
    ],
    "name:rus_x_preferred":[
        "\u042f\u0432\u043e\u0440\u043e\u0432"
    ],
    "name:sco_x_preferred":[
        "Yavoriv"
    ],
    "name:slv_x_preferred":[
        "Javoriv"
    ],
    "name:spa_x_preferred":[
        "Yavoriv"
    ],
    "name:srp_x_preferred":[
        "\u0408\u0430\u0432\u043e\u0440\u043e\u0432"
    ],
    "name:swe_x_preferred":[
        "Javoriv"
    ],
    "name:tat_x_preferred":[
        "\u042f\u0432\u043e\u0440\u0438\u0432"
    ],
    "name:ukr_x_preferred":[
        "\u042f\u0432\u043e\u0440\u0456\u0432"
    ],
    "name:und_x_variant":[
        "Yavorov"
    ],
    "name:vie_x_preferred":[
        "Yavoriv"
    ],
    "name:zho_x_preferred":[
        "\u4e9e\u6c83\u91cc\u592b"
    ],
    "qs:a0":"\u0423\u043a\u0440\u0430\u0457\u043d\u0430",
    "qs:a1":"*\u041b\u044c\u0432\u0456\u0432\u0441\u044c\u043a\u0430",
    "qs:a1_alt":"L'vivs'ka",
    "qs:a1r":"0",
    "qs:a2":"\u042f\u0432\u043e\u0440\u0456\u0432\u0441\u044c\u043a\u0438\u0439",
    "qs:a2_alt":"Yavorivs'kyi",
    "qs:adm0":"\u0423\u043a\u0440\u0430\u0457\u043d\u0430",
    "qs:la_lc":"*",
    "qs:level":"locality",
    "qs:loc":"\u042f\u0432\u043e\u0440\u0456\u0432",
    "qs:loc_alt":"Yavoriv",
    "qs:pop":0,
    "qs:type":"buffered point",
    "wd:wordcount":448,
    "wof:name":"\u042f\u0432\u043e\u0440\u0456\u0432",
    "wof:placetype":"locality",
    "wof:population":13008
},
  "geometry": {"coordinates":[23.396149,49.938143],"type":"Point"}
}