{
  "type": "Feature",
  "properties": {
    "gn:admin1_code":"1.0",
    "gn:asciiname":"Prokhorovka",
    "gn:country_code":"UA",
    "gn:dem":82,
    "gn:feature_class":"P",
    "gn:feature_code":"PPL",
    "gn:name":"Prokhorovka",
    "gn:population":0,
    "gn:timezone":"Europe/Kiev",
    "iso:country":"UA",
    "name:eng_x_preferred":[
        "Prokhorovka"
    ],
    "name:rus_x_preferred":[
        "\u041f\u0440\u043e\u0445\u043e\u0440\u043e\u0432\u043a\u0430"
    ],
    "wof:name":"Prokhorovka",
    "wof:placetype":"locality"
},
  "geometry": {"coordinates":[31.60856,49.71244],"type":"Point"}
}