{
  "type": "Feature",
  "properties": {
    "gn:admin1_code":"6.0",
    "gn:asciiname":"Molodyluv",
    "gn:country_code":"UA",
    "gn:dem":343,
    "gn:feature_class":"P",
    "gn:feature_code":"PPL",
    "gn:name":"Molodyluv",
    "gn:population":0,
    "gn:timezone":"Europe/Kiev",
    "iso:country":"UA",
    "name:und_x_variant":[
        "Molodilov",
        "Molodyluv"
    ],
    "wof:name":"Molodyluv",
    "wof:placetype":"locality"
},
  "geometry": {"coordinates":[24.85697,48.67941],"type":"Point"}
}