{
  "type": "Feature",
  "properties": {
    "iso:country":"UA",
    "name:ukr_x_preferred":[
        "\u0412\u0456\u0439\u0441\u044c\u043a\u043e\u0432\u0438\u0439 \u0456\u043d\u0441\u0442\u0438\u0442\u0443\u0442 \u0442\u0435\u043b\u0435\u043a\u043e\u043c\u0443\u043d\u0456\u043a\u0430\u0446\u0456\u0439 \u0442\u0430 \u0456\u043d\u0444\u043e\u0440\u043c\u0430\u0442\u0438\u0437\u0430\u0446\u0456\u0457"
    ],
    "qs:a0":"\u0423\u043a\u0440\u0430\u0457\u043d\u0430",
    "qs:a1":"*\u0417\u0430\u043f\u043e\u0440\u0456\u0437\u044c\u043a\u0430",
    "qs:a1_alt":"Zaporiz'ka",
    "qs:a1r":"0",
    "qs:a2":"\u041f\u043e\u043b\u043e\u0433\u0456\u0432\u0441\u044c\u043a\u0438\u0439",
    "qs:a2_alt":"Polohivs'kyi",
    "qs:adm0":"\u0423\u043a\u0440\u0430\u0457\u043d\u0430",
    "qs:la_lc":"*",
    "qs:level":"locality",
    "qs:loc":"\u0406\u043d\u0436\u0435\u043d\u0435\u0440\u043d\u0435",
    "qs:loc_alt":"Inzhenerne",
    "qs:pop":0,
    "qs:type":"buffered point",
    "wd:wordcount":719,
    "wof:name":"\u0406\u043d\u0436\u0435\u043d\u0435\u0440\u043d\u0435",
    "wof:placetype":"locality"
},
  "geometry": {"coordinates":[36.1446,47.493517],"type":"Point"}
}