{
  "type": "Feature",
  "properties": {
    "gn:admin1_code":"23.0",
    "gn:asciiname":"Berezna",
    "gn:country_code":"UA",
    "gn:dem":259,
    "gn:feature_class":"P",
    "gn:feature_code":"PPL",
    "gn:name":"Berezna",
    "gn:population":0,
    "gn:timezone":"Europe/Kiev",
    "iso:country":"UA",
    "wof:name":"Berezna",
    "wof:placetype":"locality"
},
  "geometry": {"coordinates":[27.84919,49.56209000000001],"type":"Point"}
}