{
  "type": "Feature",
  "properties": {
    "gn:admin1_code":"5.0",
    "gn:asciiname":"Novotroyits'ke",
    "gn:country_code":"UA",
    "gn:dem":171,
    "gn:feature_class":"P",
    "gn:feature_code":"PPL",
    "gn:name":"Novotroyits\u2019ke",
    "gn:population":0,
    "gn:timezone":"Europe/Kiev",
    "iso:country":"UA",
    "name:eng_x_preferred":[
        "Novotroitskoye"
    ],
    "name:rus_x_preferred":[
        "\u041d\u043e\u0432\u043e\u0442\u0440\u043e\u0438\u0446\u043a\u043e\u0435"
    ],
    "name:ukr_x_preferred":[
        "Novotroyits\u2019ke"
    ],
    "name:ukr_x_variant":[
        "\u041d\u043e\u0432\u043e\u0442\u0440\u043e\u0457\u0446\u044c\u043a\u0435"
    ],
    "name:und_x_variant":[
        "Seredneye",
        "Novotroitskoye"
    ],
    "wof:name":"Novotroyits'ke",
    "wof:placetype":"locality"
},
  "geometry": {"coordinates":[37.59189,47.7158],"type":"Point"}
}