{
  "type": "Feature",
  "properties": {
    "gn:admin1_code":"3.0",
    "gn:asciiname":"Klokuchka",
    "gn:country_code":"UA",
    "gn:dem":203,
    "gn:feature_class":"P",
    "gn:feature_code":"PPL",
    "gn:name":"Klokuchka",
    "gn:population":0,
    "gn:timezone":"Europe/Kiev",
    "iso:country":"UA",
    "name:und_x_variant":[
        "Kolokuchka",
        "Klokuchka"
    ],
    "wof:name":"Klokuchka",
    "wof:placetype":"locality"
},
  "geometry": {"coordinates":[25.91431,48.30546],"type":"Point"}
}