{
  "type": "Feature",
  "properties": {
    "gn:admin1_code":"19.0",
    "gn:asciiname":"Yapolot'",
    "gn:country_code":"UA",
    "gn:dem":178,
    "gn:feature_class":"P",
    "gn:feature_code":"PPL",
    "gn:name":"Yapolot\u2019",
    "gn:population":0,
    "gn:timezone":"Europe/Kiev",
    "iso:country":"UA",
    "name:bel_x_preferred":[
        "\u042f\u043f\u0430\u043b\u0430\u0446\u044c"
    ],
    "name:ceb_x_preferred":[
        "Yapolot'"
    ],
    "name:ron_x_preferred":[
        "Iapolot"
    ],
    "name:rus_x_preferred":[
        "\u042f\u043f\u043e\u043b\u043e\u0442\u044c"
    ],
    "name:ukr_x_preferred":[
        "Yapolot\u2019"
    ],
    "name:ukr_x_variant":[
        "\u042f\u043f\u043e\u043b\u043e\u0442\u044c"
    ],
    "name:und_x_variant":[
        "Japo\u0142o\u0107",
        "Yapolots\u2019"
    ],
    "name:zho_x_preferred":[
        "\u4e9e\u6ce2\u6d1b\u5b63"
    ],
    "wof:name":"Yapolot'",
    "wof:placetype":"locality"
},
  "geometry": {"coordinates":[26.26744,50.98743],"type":"Point"}
}