{
  "type": "Feature",
  "properties": {
    "gn:admin1_code":"7.0",
    "gn:asciiname":"Kadnytsya",
    "gn:country_code":"UA",
    "gn:dem":168,
    "gn:feature_class":"P",
    "gn:feature_code":"PPL",
    "gn:name":"Kadnytsya",
    "gn:population":0,
    "gn:timezone":"Europe/Kiev",
    "iso:country":"UA",
    "name:ukr_x_preferred":[
        "Kadnytsya"
    ],
    "name:ukr_x_variant":[
        "\u041a\u0430\u0434\u043d\u0438\u0446\u044f"
    ],
    "name:und_x_variant":[
        "Kadnitsa"
    ],
    "wof:name":"Kadnytsya",
    "wof:placetype":"locality"
},
  "geometry": {"coordinates":[35.76148,50.1134],"type":"Point"}
}