{
  "type": "Feature",
  "properties": {
    "gn:admin1_code":"2.0",
    "gn:asciiname":"Opolons'ke",
    "gn:country_code":"UA",
    "gn:dem":149,
    "gn:feature_class":"P",
    "gn:feature_code":"PPL",
    "gn:name":"Opolons\u2019ke",
    "gn:population":0,
    "gn:timezone":"Europe/Kiev",
    "iso:country":"UA",
    "name:ukr_x_preferred":[
        "Opolons\u2019ke"
    ],
    "name:ukr_x_variant":[
        "\u041e\u043f\u043e\u043b\u043e\u043d\u0441\u044c\u043a\u0435"
    ],
    "name:und_x_variant":[
        "Apolonskiy",
        "Opolonskoye"
    ],
    "wof:name":"Opolons'ke",
    "wof:placetype":"locality"
},
  "geometry": {"coordinates":[32.70913,51.10594],"type":"Point"}
}