{
  "type": "Feature",
  "properties": {
    "gn:admin1_code":"23.0",
    "gn:asciiname":"Seredinka",
    "gn:country_code":"UA",
    "gn:dem":178,
    "gn:feature_class":"P",
    "gn:feature_code":"PPL",
    "gn:name":"Seredinka",
    "gn:population":0,
    "gn:timezone":"Europe/Kiev",
    "iso:country":"UA",
    "wof:name":"Seredinka",
    "wof:placetype":"locality"
},
  "geometry": {"coordinates":[29.8946,48.55276],"type":"Point"}
}