{
  "type": "Feature",
  "properties": {
    "gn:admin1_code":"21.0",
    "gn:asciiname":"Reshayushchiy",
    "gn:country_code":"UA",
    "gn:dem":192,
    "gn:feature_class":"P",
    "gn:feature_code":"PPL",
    "gn:name":"Reshayushchiy",
    "gn:population":0,
    "gn:timezone":"Europe/Kiev",
    "iso:country":"UA",
    "name:ukr_x_preferred":[
        "Reshayushchiy"
    ],
    "wof:name":"Reshayushchiy",
    "wof:placetype":"locality"
},
  "geometry": {"coordinates":[34.01056,52.05944],"type":"Point"}
}