{
  "type": "Feature",
  "properties": {
    "gn:admin1_code":"15.0",
    "gn:asciiname":"Syn'kiv",
    "gn:country_code":"UA",
    "gn:dem":224,
    "gn:feature_class":"P",
    "gn:feature_code":"PPL",
    "gn:name":"Syn\u2019kiv",
    "gn:population":0,
    "gn:timezone":"Europe/Kiev",
    "iso:country":"UA",
    "name:ukr_x_preferred":[
        "Syn\u2019kiv"
    ],
    "name:ukr_x_variant":[
        "\u0421\u0438\u043d\u044c\u043a\u0456\u0432"
    ],
    "name:und_x_variant":[
        "Sen\u2019kuv",
        "Sen\u2019kiv",
        "Sie\u0144k\u00f3w",
        "Sen\u2019kov"
    ],
    "wof:name":"Syn'kiv",
    "wof:placetype":"locality"
},
  "geometry": {"coordinates":[24.77895,50.30727],"type":"Point"}
}