{
  "type": "Feature",
  "properties": {
    "gn:admin1_code":"27.0",
    "gn:asciiname":"Novi Zhad'ky",
    "gn:country_code":"UA",
    "gn:dem":200,
    "gn:feature_class":"P",
    "gn:feature_code":"PPL",
    "gn:name":"Novi Zhad\u2019ky",
    "gn:population":0,
    "gn:timezone":"Europe/Kiev",
    "iso:country":"UA",
    "name:ukr_x_preferred":[
        "Karla Marksa"
    ],
    "name:ukr_x_variant":[
        "\u041a\u0430\u0440\u043b\u0430 \u041c\u0430\u0440\u043a\u0441\u0430",
        "Novi Zhad\u2019ky",
        "\u041d\u043e\u0432\u0456 \u0416\u0430\u0434\u044c\u043a\u0438"
    ],
    "wof:name":"Novi Zhad'ky",
    "wof:placetype":"locality"
},
  "geometry": {"coordinates":[28.84215,50.59654000000001],"type":"Point"}
}