{
  "type": "Feature",
  "properties": {
    "gn:admin1_code":"18.0",
    "gn:asciiname":"Pidlepychi",
    "gn:country_code":"UA",
    "gn:dem":145,
    "gn:feature_class":"P",
    "gn:feature_code":"PPL",
    "gn:name":"Pidlepychi",
    "gn:population":0,
    "gn:timezone":"Europe/Kiev",
    "iso:country":"UA",
    "name:ukr_x_preferred":[
        "Pidlepychi"
    ],
    "name:ukr_x_variant":[
        "\u041f\u0456\u0434\u043b\u0435\u043f\u0438\u0447\u0456"
    ],
    "wof:name":"Pidlepychi",
    "wof:placetype":"locality"
},
  "geometry": {"coordinates":[34.3383,49.53056],"type":"Point"}
}