{
  "type": "Feature",
  "properties": {
    "gn:admin1_code":"21.0",
    "gn:asciiname":"Mukiyivka",
    "gn:country_code":"UA",
    "gn:dem":176,
    "gn:feature_class":"P",
    "gn:feature_code":"PPL",
    "gn:name":"Mukiyivka",
    "gn:population":0,
    "gn:timezone":"Europe/Kiev",
    "iso:country":"UA",
    "name:ukr_x_preferred":[
        "Mukiyivka"
    ],
    "name:ukr_x_variant":[
        "\u041c\u0443\u043a\u0456\u0457\u0432\u043a\u0430"
    ],
    "name:und_x_variant":[
        "Makoveyevka",
        "Mukiyevka"
    ],
    "wof:name":"Mukiyivka",
    "wof:placetype":"locality"
},
  "geometry": {"coordinates":[34.27872,50.82429000000001],"type":"Point"}
}