{
  "type": "Feature",
  "properties": {
    "gn:admin1_code":"17.0",
    "gn:asciiname":"Bahate",
    "gn:country_code":"UA",
    "gn:dem":13,
    "gn:feature_class":"P",
    "gn:feature_code":"PPL",
    "gn:name":"Bahate",
    "gn:population":0,
    "gn:timezone":"Europe/Kiev",
    "iso:country":"UA",
    "name:ukr_x_preferred":[
        "Bahate"
    ],
    "name:ukr_x_variant":[
        "\u0411\u0430\u0433\u0430\u0442\u0435"
    ],
    "name:und_x_variant":[
        "Dolucnioi",
        "Dolukioy",
        "Doluknoy",
        "Doluk\u2019yuy",
        "Bogatoye"
    ],
    "wof:name":"Bahate",
    "wof:placetype":"locality"
},
  "geometry": {"coordinates":[28.94032,45.40775],"type":"Point"}
}