{
  "type": "Feature",
  "properties": {
    "iso:country":"UA",
    "name:eng_x_preferred":[
        "Velikaya Andrusovka"
    ],
    "name:rus_x_preferred":[
        "\u0412\u0435\u043b.\u0430\u043d\u0434\u0440\u0443\u0441\u043e\u0432\u043a\u0430"
    ],
    "name:ukr_x_preferred":[
        "\u0412\u0435\u043b\u0438\u043a\u0430 \u0410\u043d\u0434\u0440\u0443\u0441\u0456\u0432\u043a\u0430"
    ],
    "name:und_x_variant":[
        "Andrusovka"
    ],
    "qs:a0":"\u0423\u043a\u0440\u0430\u0457\u043d\u0430",
    "qs:a1":"*\u041a\u0456\u0440\u043e\u0432\u043e\u0433\u0440\u0430\u0434\u0441\u044c\u043a\u0430",
    "qs:a1_alt":"Kirovohrads'ka",
    "qs:a1r":"0",
    "qs:a2":"\u0421\u0432\u0456\u0442\u043b\u043e\u0432\u043e\u0434\u0441\u044c\u043a\u0438\u0439",
    "qs:a2_alt":"Svitlovods'kyi",
    "qs:adm0":"\u0423\u043a\u0440\u0430\u0457\u043d\u0430",
    "qs:la_lc":"*",
    "qs:level":"locality",
    "qs:loc":"\u0412\u0435\u043b\u0438\u043a\u0430 \u0410\u043d\u0434\u0440\u0443\u0441\u0456\u0432\u043a\u0430",
    "qs:loc_alt":"Velyka Andrusivka",
    "qs:pop":0,
    "qs:type":"buffered point",
    "wof:name":"\u0412\u0435\u043b\u0438\u043a\u0430 \u0410\u043d\u0434\u0440\u0443\u0441\u0456\u0432\u043a\u0430",
    "wof:placetype":"locality"
},
  "geometry": {"coordinates":[32.953817,49.042368],"type":"Point"}
}