{
  "type": "Feature",
  "properties": {
    "gn:admin1_code":"27.0",
    "gn:asciiname":"Velykyy Luh",
    "gn:country_code":"UA",
    "gn:dem":232,
    "gn:feature_class":"P",
    "gn:feature_code":"PPL",
    "gn:name":"Velykyy Luh",
    "gn:population":0,
    "gn:timezone":"Europe/Kiev",
    "iso:country":"UA",
    "name:ukr_x_preferred":[
        "Velykyy Luh"
    ],
    "name:ukr_x_variant":[
        "\u0412\u0435\u043b\u0438\u043a\u0438\u0439 \u041b\u0443\u0433"
    ],
    "name:und_x_variant":[
        "Velikiy Lug"
    ],
    "wof:name":"Velykyy Luh",
    "wof:placetype":"locality"
},
  "geometry": {"coordinates":[28.0324,50.43342],"type":"Point"}
}