{
  "type": "Feature",
  "properties": {
    "gn:admin1_code":"27.0",
    "gn:asciiname":"Kornyns'ke",
    "gn:country_code":"UA",
    "gn:dem":198,
    "gn:feature_class":"P",
    "gn:feature_code":"PPL",
    "gn:name":"Kornyns\u2019ke",
    "gn:population":0,
    "gn:timezone":"Europe/Kiev",
    "iso:country":"UA",
    "name:ukr_x_preferred":[
        "Radhospne"
    ],
    "name:ukr_x_variant":[
        "\u0420\u0430\u0434\u0433\u043e\u0441\u043f\u043d\u0435",
        "Kornyns\u2019ke",
        "\u041a\u043e\u0440\u043d\u0438\u043d\u0441\u044c\u043a\u0435"
    ],
    "wof:name":"Kornyns'ke",
    "wof:placetype":"locality"
},
  "geometry": {"coordinates":[29.51405,50.0469],"type":"Point"}
}