{
  "type": "Feature",
  "properties": {
    "gn:admin1_code":"15.0",
    "gn:asciiname":"Domashiv",
    "gn:country_code":"UA",
    "gn:dem":214,
    "gn:feature_class":"P",
    "gn:feature_code":"PPL",
    "gn:name":"Domashiv",
    "gn:population":0,
    "gn:timezone":"Europe/Kiev",
    "iso:country":"UA",
    "name:ukr_x_preferred":[
        "\u0414\u043e\u043c\u0430\u0448\u0456\u0432"
    ],
    "name:und_x_variant":[
        "Domashov",
        "Domashiv",
        "Domashuv",
        "Domashev"
    ],
    "wof:name":"Domashiv",
    "wof:placetype":"locality"
},
  "geometry": {"coordinates":[23.858,50.341],"type":"Point"}
}