{
  "type": "Feature",
  "properties": {
    "gn:admin1_code":"21.0",
    "gn:asciiname":"Kulychka",
    "gn:country_code":"UA",
    "gn:dem":126,
    "gn:feature_class":"P",
    "gn:feature_code":"PPL",
    "gn:name":"Kulychka",
    "gn:population":0,
    "gn:timezone":"Europe/Kiev",
    "iso:country":"UA",
    "name:ukr_x_preferred":[
        "Kulychka"
    ],
    "name:ukr_x_variant":[
        "\u041a\u0443\u043b\u0438\u0447\u043a\u0430"
    ],
    "name:und_x_variant":[
        "Kulichka",
        "Kulichki"
    ],
    "wof:name":"Kulychka",
    "wof:placetype":"locality"
},
  "geometry": {"coordinates":[34.48012,50.49488],"type":"Point"}
}