{
  "type": "Feature",
  "properties": {
    "gn:admin1_code":"19.0",
    "gn:asciiname":"Zamostyshche",
    "gn:country_code":"UA",
    "gn:dem":189,
    "gn:feature_class":"P",
    "gn:feature_code":"PPL",
    "gn:name":"Zamostyshche",
    "gn:population":0,
    "gn:timezone":"Europe/Kiev",
    "iso:country":"UA",
    "name:ukr_x_preferred":[
        "Zamostyshche"
    ],
    "name:ukr_x_variant":[
        "\u0417\u0430\u043c\u043e\u0441\u0442\u0438\u0449\u0435"
    ],
    "name:und_x_variant":[
        "Zamostishche"
    ],
    "wof:name":"Zamostyshche",
    "wof:placetype":"locality"
},
  "geometry": {"coordinates":[26.61709,50.92683],"type":"Point"}
}