{
  "type": "Feature",
  "properties": {
    "gn:admin1_code":"21.0",
    "gn:asciiname":"Svydnya",
    "gn:country_code":"UA",
    "gn:dem":166,
    "gn:feature_class":"P",
    "gn:feature_code":"PPL",
    "gn:name":"Svydnya",
    "gn:population":0,
    "gn:timezone":"Europe/Kiev",
    "iso:country":"UA",
    "name:ukr_x_preferred":[
        "Svydnya"
    ],
    "name:ukr_x_variant":[
        "\u0421\u0432\u0438\u0434\u043d\u044f"
    ],
    "name:und_x_variant":[
        "Svidnya"
    ],
    "wof:name":"Svydnya",
    "wof:placetype":"locality"
},
  "geometry": {"coordinates":[33.44207,51.50374],"type":"Point"}
}