{
  "type": "Feature",
  "properties": {
    "gn:admin1_code":"13.0",
    "gn:asciiname":"Ol'shanskaya Novoselitsa",
    "gn:country_code":"UA",
    "gn:dem":193,
    "gn:feature_class":"P",
    "gn:feature_code":"PPL",
    "gn:name":"Ol\u2019shanskaya Novoselitsa",
    "gn:population":0,
    "gn:timezone":"Europe/Kiev",
    "iso:country":"UA",
    "name:und_x_variant":[
        "Ol\u2019shanskoye",
        "Ol\u2019shanskaya Novoselitsa"
    ],
    "wof:name":"Ol'shanskaya Novoselitsa",
    "wof:placetype":"locality"
},
  "geometry": {"coordinates":[30.32371,49.98878],"type":"Point"}
}