{
  "type": "Feature",
  "properties": {
    "gn:admin1_code":"14.0",
    "gn:asciiname":"Novovodyane",
    "gn:country_code":"UA",
    "gn:dem":95,
    "gn:feature_class":"P",
    "gn:feature_code":"PPL",
    "gn:name":"Novovodyane",
    "gn:population":0,
    "gn:timezone":"Europe/Zaporozhye",
    "iso:country":"UA",
    "name:ukr_x_preferred":[
        "Novovodyane"
    ],
    "name:und_x_variant":[
        "Novovodyanoye"
    ],
    "wof:name":"Novovodyane",
    "wof:placetype":"locality"
},
  "geometry": {"coordinates":[38.02218,49.27382],"type":"Point"}
}