{
  "type": "Feature",
  "properties": {
    "gn:admin1_code":"21.0",
    "gn:asciiname":"Cherepivka",
    "gn:country_code":"UA",
    "gn:dem":154,
    "gn:feature_class":"P",
    "gn:feature_code":"PPL",
    "gn:name":"Cherepivka",
    "gn:population":0,
    "gn:timezone":"Europe/Kiev",
    "iso:country":"UA",
    "name:eng_x_preferred":[
        "Cherepovka"
    ],
    "name:rus_x_preferred":[
        "\u0427\u0435\u0440\u0435\u043f\u043e\u0432\u043a\u0430"
    ],
    "name:ukr_x_preferred":[
        "Cherepivka"
    ],
    "name:ukr_x_variant":[
        "\u0427\u0435\u0440\u0435\u043f\u0456\u0432\u043a\u0430"
    ],
    "name:und_x_variant":[
        "Cherepovka"
    ],
    "wof:name":"Cherepivka",
    "wof:placetype":"locality"
},
  "geometry": {"coordinates":[33.90292,51.04752],"type":"Point"}
}