{
  "type": "Feature",
  "properties": {
    "gn:admin1_code":"14.0",
    "gn:asciiname":"Kopani",
    "gn:country_code":"UA",
    "gn:dem":92,
    "gn:feature_class":"P",
    "gn:feature_code":"PPL",
    "gn:name":"Kopani",
    "gn:population":0,
    "gn:timezone":"Europe/Zaporozhye",
    "iso:country":"UA",
    "wof:name":"Kopani",
    "wof:placetype":"locality"
},
  "geometry": {"coordinates":[39.68944000000001,48.48278],"type":"Point"}
}