{
  "type": "Feature",
  "properties": {
    "gn:admin1_code":"14.0",
    "gn:asciiname":"Isakovo",
    "gn:country_code":"UA",
    "gn:dem":99,
    "gn:feature_class":"P",
    "gn:feature_code":"PPL",
    "gn:name":"Isakovo",
    "gn:population":0,
    "gn:timezone":"Europe/Zaporozhye",
    "iso:country":"UA",
    "wof:name":"Isakovo",
    "wof:placetype":"locality"
},
  "geometry": {"coordinates":[38.90333,48.46972],"type":"Point"}
}