{
  "type": "Feature",
  "properties": {
    "gn:admin1_code":"19.0",
    "gn:asciiname":"Zhyl'zha",
    "gn:country_code":"UA",
    "gn:dem":180,
    "gn:feature_class":"P",
    "gn:feature_code":"PPL",
    "gn:name":"Zhyl\u2019zha",
    "gn:population":0,
    "gn:timezone":"Europe/Kiev",
    "iso:country":"UA",
    "name:rus_x_preferred":[
        "Zhil\u2019zha"
    ],
    "name:ukr_x_preferred":[
        "Zhyl\u2019zha"
    ],
    "name:ukr_x_variant":[
        "\u0416\u0438\u043b\u044c\u0436\u0430"
    ],
    "wof:name":"Zhyl'zha",
    "wof:placetype":"locality"
},
  "geometry": {"coordinates":[26.20883,50.83565],"type":"Point"}
}