{
  "type": "Feature",
  "properties": {
    "gn:admin1_code":"25.0",
    "gn:asciiname":"Dubrinich na Beregu",
    "gn:country_code":"UA",
    "gn:dem":177,
    "gn:feature_class":"P",
    "gn:feature_code":"PPL",
    "gn:name":"Dubrinich na Beregu",
    "gn:population":0,
    "gn:timezone":"Europe/Uzhgorod",
    "iso:country":"UA",
    "wof:name":"Dubrinich na Beregu",
    "wof:placetype":"locality"
},
  "geometry": {"coordinates":[22.50115,48.81076],"type":"Point"}
}