{
  "type": "Feature",
  "properties": {
    "gn:admin1_code":"21.0",
    "gn:asciiname":"Melyachykha",
    "gn:country_code":"UA",
    "gn:dem":142,
    "gn:feature_class":"P",
    "gn:feature_code":"PPL",
    "gn:name":"Melyachykha",
    "gn:population":0,
    "gn:timezone":"Europe/Kiev",
    "iso:country":"UA",
    "name:ukr_x_preferred":[
        "Petrivs\u2019ke"
    ],
    "name:ukr_x_variant":[
        "\u041f\u0435\u0442\u0440\u0456\u0432\u0441\u044c\u043a\u0435",
        "Melyachykha",
        "\u041c\u0435\u043b\u044f\u0447\u0438\u0445\u0430"
    ],
    "name:und_x_variant":[
        "Petrovskiy",
        "Petrovskoye"
    ],
    "wof:name":"Melyachykha",
    "wof:placetype":"locality"
},
  "geometry": {"coordinates":[34.5194,51.17578],"type":"Point"}
}