{
  "type": "Feature",
  "properties": {
    "gn:admin1_code":"7.0",
    "gn:asciiname":"Moskalenky",
    "gn:country_code":"UA",
    "gn:dem":136,
    "gn:feature_class":"P",
    "gn:feature_code":"PPL",
    "gn:name":"Moskalenky",
    "gn:population":0,
    "gn:timezone":"Europe/Kiev",
    "iso:country":"UA",
    "name:ukr_x_preferred":[
        "Moskalenky"
    ],
    "name:ukr_x_variant":[
        "\u041c\u043e\u0441\u043a\u0430\u043b\u0435\u043d\u043a\u0438"
    ],
    "name:und_x_variant":[
        "Khutor Moskalenki",
        "Moskal\u00ebnki"
    ],
    "wof:name":"Moskalenky",
    "wof:placetype":"locality"
},
  "geometry": {"coordinates":[35.59155,50.17168],"type":"Point"}
}