{
  "type": "Feature",
  "properties": {
    "gn:admin1_code":"14.0",
    "gn:asciiname":"Podgornyy",
    "gn:cc2":"UA",
    "gn:country_code":"UA",
    "gn:dem":45,
    "gn:feature_class":"P",
    "gn:feature_code":"PPL",
    "gn:name":"Podgornyy",
    "gn:population":0,
    "gn:timezone":"Europe/Zaporozhye",
    "iso:country":"UA",
    "name:und_x_variant":[
        "Podgornoye",
        "Podgornyy"
    ],
    "wof:name":"Podgornyy",
    "wof:placetype":"locality"
},
  "geometry": {"coordinates":[39.61528,48.57278],"type":"Point"}
}