{
  "type": "Feature",
  "properties": {
    "gn:admin1_code":"2.0",
    "gn:asciiname":"Shevchenko",
    "gn:country_code":"UA",
    "gn:dem":131,
    "gn:feature_class":"P",
    "gn:feature_code":"PPL",
    "gn:name":"Shevchenko",
    "gn:population":0,
    "gn:timezone":"Europe/Kiev",
    "iso:country":"UA",
    "name:rus_x_preferred":[
        "\u0428\u0435\u0432\u0447\u0435\u043d\u043a\u043e"
    ],
    "name:slk_x_preferred":[
        "\u0160ev\u010denko"
    ],
    "name:slv_x_preferred":[
        "\u0160ev\u010denko"
    ],
    "name:ukr_x_preferred":[
        "Shevchenko"
    ],
    "name:ukr_x_variant":[
        "\u0428\u0435\u0432\u0447\u0435\u043d\u043a\u043e"
    ],
    "wof:name":"Shevchenko",
    "wof:placetype":"locality"
},
  "geometry": {"coordinates":[31.37043,50.75954],"type":"Point"}
}