{
  "type": "Feature",
  "properties": {
    "gn:country":"UA",
    "gn:fcode":"PPL",
    "gn:population":0,
    "iso:country":"UA",
    "name:crh_x_preferred":[
        "Yuryivka"
    ],
    "name:deu_x_preferred":[
        "Jurjiwka"
    ],
    "name:eng_x_preferred":[
        "Yur'yevka"
    ],
    "name:eng_x_variant":[
        "Yurivka"
    ],
    "name:lav_x_preferred":[
        "Jurjivka"
    ],
    "name:ron_x_preferred":[
        "Iuriivka"
    ],
    "name:rus_x_preferred":[
        "\u042e\u0440\u044c\u0435\u0432\u043a\u0430"
    ],
    "name:ukr_x_preferred":[
        "Yur\u201dyivka"
    ],
    "name:ukr_x_variant":[
        "\u042e\u0440\u2019\u0457\u0432\u043a\u0430",
        "\u042e\u0440'\u0457\u0432\u043a\u0430"
    ],
    "name:und_x_variant":[
        "Shcheglovka"
    ],
    "name:zho_x_preferred":[
        "\u5c24\u723e\u4f0a\u592b\u5361"
    ],
    "qs_pg:aaroncc":"UA",
    "qs_pg:gn_country":"UA",
    "qs_pg:gn_fcode":"PPL",
    "qs_pg:gn_pop":0,
    "qs_pg:name":"Yur'yevka",
    "qs_pg:name_adm0":"Ukraine",
    "qs_pg:name_adm1":"Luhans\u00b4ka Oblast\u00b4",
    "qs_pg:photos":56,
    "qs_pg:photos_1k":11,
    "qs_pg:photos_9k":1,
    "qs_pg:photos_9r":2,
    "qs_pg:photos_all":56,
    "qs_pg:photos_sr":2,
    "qs_pg:pop_sr":0,
    "qs_pg:qs_pg_placetype":"locality",
    "qs_pg:qs_pg_placetype_gp":"Town",
    "qs_pg:woe_adm0":23424976,
    "woe:adm0_id":23424976,
    "woe:name_adm0":"Ukraine",
    "woe:name_adm1":"Luhans\u00b4ka Oblast\u00b4",
    "woe:placetype":"Town",
    "wof:name":"Yur'yevka",
    "wof:placetype":"locality"
},
  "geometry": {"coordinates":[38.9784,48.50452],"type":"Point"}
}