{
  "type": "Feature",
  "properties": {
    "gn:admin1_code":"18.0",
    "gn:asciiname":"Shovkoplyasy",
    "gn:country_code":"UA",
    "gn:dem":111,
    "gn:feature_class":"P",
    "gn:feature_code":"PPL",
    "gn:name":"Shovkoplyasy",
    "gn:population":0,
    "gn:timezone":"Europe/Kiev",
    "iso:country":"UA",
    "name:ukr_x_preferred":[
        "Shovkoplyasy"
    ],
    "name:ukr_x_variant":[
        "\u0428\u043e\u0432\u043a\u043e\u043f\u043b\u044f\u0441\u0438"
    ],
    "wof:name":"Shovkoplyasy",
    "wof:placetype":"locality"
},
  "geometry": {"coordinates":[34.13803,49.3447],"type":"Point"}
}