{
  "type": "Feature",
  "properties": {
    "gn:admin1_code":"15.0",
    "gn:asciiname":"Sudkivska Volya",
    "gn:cc2":"UA",
    "gn:country_code":"UA",
    "gn:dem":256,
    "gn:feature_class":"P",
    "gn:feature_code":"PPL",
    "gn:name":"Sudkivska Volya",
    "gn:population":0,
    "gn:timezone":"Europe/Kiev",
    "iso:country":"UA",
    "name:und_x_variant":[
        "Sudkovska Volya",
        "Sudkovskaya Volya",
        "Sudkivska Volya"
    ],
    "wof:name":"Sudkivska Volya",
    "wof:placetype":"locality"
},
  "geometry": {"coordinates":[23.16667,49.66667],"type":"Point"}
}