{
  "type": "Feature",
  "properties": {
    "gn:admin1_code":"13.0",
    "gn:asciiname":"Yakhnivka",
    "gn:country_code":"UA",
    "gn:dem":124,
    "gn:feature_class":"P",
    "gn:feature_code":"PPL",
    "gn:name":"Yakhnivka",
    "gn:population":0,
    "gn:timezone":"Europe/Kiev",
    "iso:country":"UA",
    "name:ukr_x_preferred":[
        "Yakhnivka"
    ],
    "name:ukr_x_variant":[
        "\u042f\u0445\u043d\u0456\u0432\u043a\u0430"
    ],
    "name:und_x_variant":[
        "Yakhnovka"
    ],
    "wof:name":"Yakhnivka",
    "wof:placetype":"locality"
},
  "geometry": {"coordinates":[29.63554,50.81326],"type":"Point"}
}