{
  "type": "Feature",
  "properties": {
    "gn:admin1_code":"15.0",
    "gn:asciiname":"Orkhovichi",
    "gn:country_code":"UA",
    "gn:dem":283,
    "gn:feature_class":"P",
    "gn:feature_code":"PPL",
    "gn:name":"Orkhovichi",
    "gn:population":0,
    "gn:timezone":"Europe/Kiev",
    "iso:country":"UA",
    "name:und_x_variant":[
        "Orkhovitse",
        "Orkhovichi"
    ],
    "wof:name":"Orkhovichi",
    "wof:placetype":"locality"
},
  "geometry": {"coordinates":[23.4098,49.71001],"type":"Point"}
}