{
  "type": "Feature",
  "properties": {
    "gn:admin1_code":"24.0",
    "gn:asciiname":"Ozyutychi",
    "gn:country_code":"UA",
    "gn:dem":215,
    "gn:feature_class":"P",
    "gn:feature_code":"PPL",
    "gn:name":"Ozyutychi",
    "gn:population":0,
    "gn:timezone":"Europe/Kiev",
    "iso:country":"UA",
    "name:ukr_x_preferred":[
        "Ozyutychi"
    ],
    "name:ukr_x_variant":[
        "\u041e\u0437\u044e\u0442\u0438\u0447\u0456"
    ],
    "name:und_x_variant":[
        "Ozdyutyche",
        "Ozdyutichi",
        "Oz\u2019dzyutyche",
        "Ozdziutycze",
        "Ozyutichi"
    ],
    "wof:name":"Ozyutychi",
    "wof:placetype":"locality"
},
  "geometry": {"coordinates":[24.70963,50.84838],"type":"Point"}
}