{
  "type": "Feature",
  "properties": {
    "gn:admin1_code":"22.0",
    "gn:asciiname":"Payuvka",
    "gn:country_code":"UA",
    "gn:dem":321,
    "gn:feature_class":"P",
    "gn:feature_code":"PPL",
    "gn:name":"Payuvka",
    "gn:population":0,
    "gn:timezone":"Europe/Kiev",
    "iso:country":"UA",
    "name:und_x_variant":[
        "Pay\u00ebvka"
    ],
    "wof:name":"Payuvka",
    "wof:placetype":"locality"
},
  "geometry": {"coordinates":[26.1152,49.32225],"type":"Point"}
}