{
  "type": "Feature",
  "properties": {
    "gn:admin1_code":"7.0",
    "gn:asciiname":"Odynets'ke",
    "gn:country_code":"UA",
    "gn:dem":97,
    "gn:feature_class":"P",
    "gn:feature_code":"PPL",
    "gn:name":"Odynets\u2019ke",
    "gn:population":0,
    "gn:timezone":"Europe/Kiev",
    "iso:country":"UA",
    "name:ukr_x_preferred":[
        "Odynets\u2019ke"
    ],
    "name:ukr_x_variant":[
        "\u041e\u0434\u0438\u043d\u0435\u0446\u044c\u043a\u0435"
    ],
    "name:und_x_variant":[
        "Odinetskoye"
    ],
    "wof:name":"Odynets'ke",
    "wof:placetype":"locality"
},
  "geometry": {"coordinates":[36.59274,48.7246],"type":"Point"}
}