{
  "type": "Feature",
  "properties": {
    "gn:admin1_code":"21.0",
    "gn:asciiname":"Bayrak",
    "gn:country_code":"UA",
    "gn:dem":167,
    "gn:feature_class":"P",
    "gn:feature_code":"PPL",
    "gn:name":"Bayrak",
    "gn:population":0,
    "gn:timezone":"Europe/Kiev",
    "iso:country":"UA",
    "name:ukr_x_preferred":[
        "Bayrak"
    ],
    "name:ukr_x_variant":[
        "\u0411\u0430\u0439\u0440\u0430\u043a"
    ],
    "wof:name":"Bayrak",
    "wof:placetype":"locality"
},
  "geometry": {"coordinates":[33.68137,50.60373],"type":"Point"}
}