{
  "type": "Feature",
  "properties": {
    "iso:country":"UA",
    "name:ceb_x_preferred":[
        "Chornukhyne"
    ],
    "name:crh_x_preferred":[
        "\u00c7ornuh\u0131ne"
    ],
    "name:deu_x_preferred":[
        "Tschornuchyne"
    ],
    "name:eng_x_preferred":[
        "Chornukhyne"
    ],
    "name:est_x_preferred":[
        "T\u0161ornuhh\u00f5ne"
    ],
    "name:lav_x_preferred":[
        "\u010cornuhine"
    ],
    "name:nob_x_preferred":[
        "Tsjornukhine"
    ],
    "name:nor_x_preferred":[
        "Tsjornukhine"
    ],
    "name:ron_x_preferred":[
        "Ciornuh\u00eene"
    ],
    "name:ron_x_variant":[
        "Cernuh\u00eene"
    ],
    "name:rus_x_preferred":[
        "\u0427\u0435\u0440\u043d\u0443\u0445\u0438\u043d\u043e"
    ],
    "name:spa_x_preferred":[
        "Chornukhyne"
    ],
    "name:ukr_x_preferred":[
        "\u0427\u043e\u0440\u043d\u0443\u0445\u0438\u043d\u0435"
    ],
    "name:zho_x_preferred":[
        "\u55ac\u723e\u52aa\u5e0c\u6d85"
    ],
    "qs:a0":"\u0423\u043a\u0440\u0430\u0457\u043d\u0430",
    "qs:a1":"*\u041b\u0443\u0433\u0430\u043d\u0441\u044c\u043a\u0430",
    "qs:a1_alt":"Luhans'ka",
    "qs:a1r":"0",
    "qs:a2":"\u041f\u0435\u0440\u0435\u0432\u0430\u043b\u044c\u0441\u044c\u043a\u0438\u0439",
    "qs:a2_alt":"Pereval's'kyi",
    "qs:adm0":"\u0423\u043a\u0440\u0430\u0457\u043d\u0430",
    "qs:la_lc":"*",
    "qs:level":"locality",
    "qs:loc":"\u0427\u043e\u0440\u043d\u0443\u0445\u0438\u043d\u0435",
    "qs:loc_alt":"Chornukhyne",
    "qs:pop":0,
    "qs:type":"buffered point",
    "wd:wordcount":230,
    "wof:name":"\u0427\u043e\u0440\u043d\u0443\u0445\u0438\u043d\u0435",
    "wof:placetype":"locality"
},
  "geometry": {"coordinates":[38.515956,48.317527],"type":"Point"}
}