{
  "type": "Feature",
  "properties": {
    "iso:country":"UA",
    "name:eng_x_preferred":[
        "Kysorychi"
    ],
    "name:pol_x_preferred":[
        "Kisorycze"
    ],
    "name:ron_x_preferred":[
        "K\u00eesor\u00eeci"
    ],
    "name:rum_x_preferred":[
        "K\u00eesor\u00eeci"
    ],
    "name:rus_x_preferred":[
        "\u041a\u0438\u0441\u043e\u0440\u0438\u0447\u0438"
    ],
    "name:ukr_x_preferred":[
        "\u041a\u0438\u0441\u043e\u0440\u0438\u0447\u0456"
    ],
    "name:ukr_x_variant":[
        "Kysorychi"
    ],
    "name:unk_x_variant":[
        "Kisorycze"
    ],
    "qs:a0":"\u0423\u043a\u0440\u0430\u0457\u043d\u0430",
    "qs:a1":"*\u0420\u0456\u0432\u043d\u0435\u043d\u0441\u044c\u043a\u0430",
    "qs:a1_alt":"Rivnens'ka",
    "qs:a1r":"0",
    "qs:a2":"\u0420\u043e\u043a\u0438\u0442\u043d\u0456\u0432\u0441\u044c\u043a\u0438\u0439",
    "qs:a2_alt":"Rokytnivs'kyi",
    "qs:adm0":"\u0423\u043a\u0440\u0430\u0457\u043d\u0430",
    "qs:la_lc":"*",
    "qs:level":"locality",
    "qs:loc":"\u041a\u0438\u0441\u043e\u0440\u0438\u0447\u0456",
    "qs:loc_alt":"Kysorychi",
    "qs:pop":0,
    "qs:type":"buffered point",
    "wd:wordcount":299,
    "wof:name":"\u041a\u0438\u0441\u043e\u0440\u0438\u0447\u0456",
    "wof:placetype":"locality"
},
  "geometry": {"coordinates":[27.250568,51.189538],"type":"Point"}
}