{
  "type": "Feature",
  "properties": {
    "gn:admin1_code":"17.0",
    "gn:asciiname":"Volodymyrivka",
    "gn:country_code":"UA",
    "gn:dem":174,
    "gn:feature_class":"P",
    "gn:feature_code":"PPL",
    "gn:name":"Volodymyrivka",
    "gn:population":0,
    "gn:timezone":"Europe/Kiev",
    "iso:country":"UA",
    "name:spa_x_preferred":[
        "Volodymyrivka"
    ],
    "name:ukr_x_preferred":[
        "Volodymyrivka"
    ],
    "name:und_x_variant":[
        "Vladimirovka"
    ],
    "wof:name":"Volodymyrivka",
    "wof:placetype":"locality"
},
  "geometry": {"coordinates":[29.97771,47.19091],"type":"Point"}
}