{
  "type": "Feature",
  "properties": {
    "gn:admin1_code":"27.0",
    "gn:asciiname":"Mistechko",
    "gn:country_code":"UA",
    "gn:dem":163,
    "gn:feature_class":"P",
    "gn:feature_code":"PPL",
    "gn:name":"Mistechko",
    "gn:population":0,
    "gn:timezone":"Europe/Kiev",
    "iso:country":"UA",
    "name:ukr_x_preferred":[
        "\u041c\u0456\u0441\u0442\u0435\u0447\u043a\u043e"
    ],
    "name:und_x_variant":[
        "Mestechko"
    ],
    "wof:name":"Mistechko",
    "wof:placetype":"locality"
},
  "geometry": {"coordinates":[29.60017,50.34112],"type":"Point"}
}