{
  "type": "Feature",
  "properties": {
    "iso:country":"UA",
    "name:ast_x_preferred":[
        "Micha\u0142\u00f3wka"
    ],
    "name:eng_x_preferred":[
        "Micha\u0142\u00f3wka"
    ],
    "name:fra_x_preferred":[
        "Micha\u0142\u00f3wka"
    ],
    "name:lit_x_preferred":[
        "Michaluvka"
    ],
    "name:pol_x_preferred":[
        "Micha\u0142\u00f3wka"
    ],
    "name:ukr_x_preferred":[
        "\u041c\u0438\u0445\u0430\u0439\u043b\u0456\u0432\u043a\u0430"
    ],
    "name:ukr_x_variant":[
        "\u041c\u0456\u0445\u0430\u043b\u0443\u0432\u043a\u0430"
    ],
    "name:unk_x_variant":[
        "Mykhaylivka"
    ],
    "qs:a0":"\u0423\u043a\u0440\u0430\u0457\u043d\u0430",
    "qs:a1":"*\u0412\u0456\u043d\u043d\u0438\u0446\u044c\u043a\u0430",
    "qs:a1_alt":"Vinnyts'ka",
    "qs:a1r":"0",
    "qs:a2":"\u0428\u0430\u0440\u0433\u043e\u0440\u043e\u0434\u0441\u044c\u043a\u0438\u0439",
    "qs:a2_alt":"Sharhorods'kyi",
    "qs:adm0":"\u0423\u043a\u0440\u0430\u0457\u043d\u0430",
    "qs:la_lc":"*",
    "qs:level":"locality",
    "qs:loc":"\u041c\u0438\u0445\u0430\u0439\u043b\u0456\u0432\u043a\u0430",
    "qs:loc_alt":"Mykhailivka",
    "qs:pop":0,
    "qs:type":"buffered point",
    "wd:wordcount":93,
    "wof:name":"\u041c\u0438\u0445\u0430\u0439\u043b\u0456\u0432\u043a\u0430",
    "wof:placetype":"locality"
},
  "geometry": {"coordinates":[28.290541,48.810061],"type":"Point"}
}