{
  "type": "Feature",
  "properties": {
    "gn:admin1_code":"26.0",
    "gn:asciiname":"Nazarovicheva",
    "gn:cc2":"UA",
    "gn:country_code":"UA",
    "gn:dem":113,
    "gn:feature_class":"P",
    "gn:feature_code":"PPL",
    "gn:name":"Nazarovicheva",
    "gn:population":0,
    "gn:timezone":"Europe/Zaporozhye",
    "iso:country":"UA",
    "name:und_x_variant":[
        "Nazarovineva",
        "Nazarovicheva"
    ],
    "wof:name":"Nazarovicheva",
    "wof:placetype":"locality"
},
  "geometry": {"coordinates":[36.56667,47.73333],"type":"Point"}
}