{
  "type": "Feature",
  "properties": {
    "gn:admin1_code":"27.0",
    "gn:asciiname":"Voronenka",
    "gn:country_code":"UA",
    "gn:dem":225,
    "gn:feature_class":"P",
    "gn:feature_code":"PPL",
    "gn:name":"Voronenka",
    "gn:population":0,
    "gn:timezone":"Europe/Kiev",
    "iso:country":"UA",
    "wof:name":"Voronenka",
    "wof:placetype":"locality"
},
  "geometry": {"coordinates":[28.45,50.06667],"type":"Point"}
}