{
  "type": "Feature",
  "properties": {
    "gn:admin1_code":"18.0",
    "gn:asciiname":"Chizhovka",
    "gn:cc2":"UA",
    "gn:country_code":"UA",
    "gn:dem":172,
    "gn:feature_class":"P",
    "gn:feature_code":"PPL",
    "gn:name":"Chizhovka",
    "gn:population":0,
    "gn:timezone":"Europe/Kiev",
    "iso:country":"UA",
    "name:und_x_variant":[
        "Posady",
        "Chizhovka"
    ],
    "wof:name":"Chizhovka",
    "wof:placetype":"locality"
},
  "geometry": {"coordinates":[34.48333,50.21667],"type":"Point"}
}