{
  "type": "Feature",
  "properties": {
    "gn:admin1_code":"27.0",
    "gn:asciiname":"Chervonyy Hay",
    "gn:country_code":"UA",
    "gn:dem":203,
    "gn:feature_class":"P",
    "gn:feature_code":"PPL",
    "gn:name":"Chervonyy Hay",
    "gn:population":0,
    "gn:timezone":"Europe/Kiev",
    "iso:country":"UA",
    "name:ukr_x_preferred":[
        "Chervonyy Hay"
    ],
    "name:ukr_x_variant":[
        "\u0427\u0435\u0440\u0432\u043e\u043d\u0438\u0439 \u0413\u0430\u0439"
    ],
    "name:und_x_variant":[
        "Chervonyy Gay"
    ],
    "wof:name":"Chervonyy Hay",
    "wof:placetype":"locality"
},
  "geometry": {"coordinates":[28.85579,50.44476],"type":"Point"}
}