{
  "type": "Feature",
  "properties": {
    "iso:country":"UA",
    "name:unk_x_variant":[
        "Kremennaya"
    ],
    "qs:a0":"\u0423\u043a\u0440\u0430\u0457\u043d\u0430",
    "qs:a1":"*\u0425\u043c\u0435\u043b\u044c\u043d\u0438\u0446\u044c\u043a\u0430",
    "qs:a1_alt":"Khmel'nyts'ka",
    "qs:a1r":"0",
    "qs:a2":"\u0413\u043e\u0440\u043e\u0434\u043e\u0446\u044c\u043a\u0438\u0439",
    "qs:a2_alt":"Horodots'kyi",
    "qs:adm0":"\u0423\u043a\u0440\u0430\u0457\u043d\u0430",
    "qs:la_lc":"*",
    "qs:level":"locality",
    "qs:loc":"\u041a\u0440\u0435\u043c\u0456\u043d\u043d\u0430",
    "qs:loc_alt":"Kreminna",
    "qs:pop":0,
    "qs:type":"buffered point",
    "wd:wordcount":106,
    "wof:name":"\u041a\u0440\u0435\u043c\u0456\u043d\u043d\u0430",
    "wof:placetype":"locality"
},
  "geometry": {"coordinates":[26.482833,49.19828],"type":"Point"}
}