{
  "type": "Feature",
  "properties": {
    "gn:admin1_code":"27.0",
    "gn:asciiname":"Klichin",
    "gn:country_code":"UA",
    "gn:dem":226,
    "gn:feature_class":"P",
    "gn:feature_code":"PPL",
    "gn:name":"Klichin",
    "gn:population":0,
    "gn:timezone":"Europe/Kiev",
    "iso:country":"UA",
    "wof:name":"Klichin",
    "wof:placetype":"locality"
},
  "geometry": {"coordinates":[28.76369,50.24367],"type":"Point"}
}