{
  "type": "Feature",
  "properties": {
    "gn:admin1_code":"14.0",
    "gn:asciiname":"Yasne",
    "gn:country_code":"UA",
    "gn:dem":109,
    "gn:feature_class":"P",
    "gn:feature_code":"PPL",
    "gn:name":"Yasne",
    "gn:population":0,
    "gn:timezone":"Europe/Zaporozhye",
    "iso:country":"UA",
    "name:ukr_x_preferred":[
        "Yasne"
    ],
    "name:ukr_x_variant":[
        "\u042f\u0441\u043d\u0435"
    ],
    "wof:name":"Yasne",
    "wof:placetype":"locality"
},
  "geometry": {"coordinates":[39.09238,48.39948],"type":"Point"}
}