{
  "type": "Feature",
  "properties": {
    "gn:admin1_code":"21.0",
    "gn:asciiname":"Myrne",
    "gn:country_code":"UA",
    "gn:dem":177,
    "gn:feature_class":"P",
    "gn:feature_code":"PPL",
    "gn:name":"Myrne",
    "gn:population":0,
    "gn:timezone":"Europe/Kiev",
    "iso:country":"UA",
    "name:ukr_x_preferred":[
        "Lenins\u2019ke"
    ],
    "name:ukr_x_variant":[
        "\u041b\u0435\u043d\u0456\u043d\u0441\u044c\u043a\u0435",
        "Myrne",
        "\u041c\u0438\u0440\u043d\u0435"
    ],
    "name:und_x_variant":[
        "Lenin",
        "Leninskoye"
    ],
    "wof:name":"Myrne",
    "wof:placetype":"locality"
},
  "geometry": {"coordinates":[34.20785,50.76791],"type":"Point"}
}