{
  "type": "Feature",
  "properties": {
    "gn:admin1_code":"20.0",
    "gn:admin2_code":"712927",
    "gn:admin3_code":"11153385.0",
    "gn:asciiname":"Zolotaya Balka (1 otd.)",
    "gn:country_code":"UA",
    "gn:dem":94,
    "gn:feature_class":"P",
    "gn:feature_code":"PPL",
    "gn:name":"Zolotaya Balka (1 otd.)",
    "gn:population":551,
    "gn:timezone":"Europe/Simferopol",
    "iso:country":"UA",
    "name:eng_x_preferred":[
        "Zolotaya Balka (1 otd.)"
    ],
    "name:rus_x_preferred":[
        "\u0417\u043e\u043b\u043e\u0442\u0430\u044f \u0411\u0430\u043b\u043a\u0430 (1-\u0435 \u043e\u0442\u0434.)"
    ],
    "wof:name":"Zolotaya Balka (1 otd.)",
    "wof:placetype":"locality",
    "wof:population":551
},
  "geometry": {"coordinates":[33.59405,44.53249],"type":"Point"}
}