{
  "type": "Feature",
  "properties": {
    "gn:admin1_code":"15.0",
    "gn:asciiname":"Pechenya",
    "gn:country_code":"UA",
    "gn:dem":246,
    "gn:feature_class":"P",
    "gn:feature_code":"PPL",
    "gn:name":"Pechenya",
    "gn:population":0,
    "gn:timezone":"Europe/Kiev",
    "iso:country":"UA",
    "wof:name":"Pechenya",
    "wof:placetype":"locality"
},
  "geometry": {"coordinates":[24.36985,49.77746],"type":"Point"}
}