{
  "type": "Feature",
  "properties": {
    "gn:gn_country":"UA",
    "gn:gn_fcode":"PPL",
    "gn:gn_pop":11160,
    "gn:population":11160,
    "iso:country":"UA",
    "name:ara_x_preferred":[
        "\u0632\u0648\u0644\u0648\u062a\u0634\u064a\u0641\u060c \u0643\u0627\u0631\u0643\u064a\u0641\u0633\u0643\u0627"
    ],
    "name:arm_x_preferred":[
        "\u0536\u0578\u056c\u0578\u0579\u0587"
    ],
    "name:chi_x_preferred":[
        "\u4f50\u6d1b\u55ac\u592b"
    ],
    "name:eng_x_preferred":[
        "Zolochiv"
    ],
    "name:ger_x_preferred":[
        "Solotschiw"
    ],
    "name:pol_x_preferred":[
        "Zo\u0142oczow"
    ],
    "name:rus_x_preferred":[
        "\u0417\u043e\u043b\u043e\u0447\u0435\u0432"
    ],
    "name:ukr_x_preferred":[
        "\u0417\u043e\u043b\u043e\u0447\u0456\u0432"
    ],
    "name:unk_x_variant":[
        "Zolochiv"
    ],
    "qs_pg:aaroncc":"UA",
    "qs_pg:gn_country":"UA",
    "qs_pg:gn_fcode":"PPL",
    "qs_pg:gn_pop":11160,
    "qs_pg:name":"Zolochev",
    "qs_pg:name_adm0":"Ukraine",
    "qs_pg:name_adm1":"Kharkivs\u00b4ka Oblast\u00b4",
    "qs_pg:photos_9r":0,
    "qs_pg:photos_sr":0,
    "qs_pg:pop_sr":6,
    "qs_pg:qs_pg_placetype":"locality",
    "qs_pg:qs_pg_placetype_gp":"Town",
    "qs_pg:woe_adm0":23424976,
    "woe:adm0_id":23424976,
    "woe:name_adm0":"Ukraine",
    "woe:name_adm1":"Kharkivs\u00b4ka Oblast\u00b4",
    "woe:placetype":"Town",
    "wof:name":"Zolochev",
    "wof:placetype":"locality",
    "wof:population":11160
},
  "geometry": {"coordinates":[35.98178,50.27985],"type":"Point"}
}