{
  "type": "Feature",
  "properties": {
    "gn:admin1_code":"4.0",
    "gn:asciiname":"Taranove",
    "gn:country_code":"UA",
    "gn:dem":145,
    "gn:feature_class":"P",
    "gn:feature_code":"PPL",
    "gn:name":"Taranove",
    "gn:population":0,
    "gn:timezone":"Europe/Kiev",
    "iso:country":"UA",
    "name:ukr_x_preferred":[
        "Taranove"
    ],
    "name:ukr_x_variant":[
        "\u0422\u0430\u0440\u0430\u043d\u043e\u0432\u0435"
    ],
    "name:und_x_variant":[
        "Taranovaya",
        "Taranovskaya",
        "Taranovo"
    ],
    "wof:name":"Taranove",
    "wof:placetype":"locality"
},
  "geometry": {"coordinates":[36.31179,48.15229],"type":"Point"}
}