{
  "type": "Feature",
  "properties": {
    "iso:country":"UA",
    "name:deu_x_preferred":[
        "Ruska Losowa"
    ],
    "name:eng_x_preferred":[
        "Rus'ka Lozova"
    ],
    "name:hye_x_preferred":[
        "\u054c\u0578\u0582\u057d\u056f\u0561\u0575\u0561 \u053c\u0578\u0566\u0578\u057e\u0561\u0575\u0561"
    ],
    "name:pol_x_preferred":[
        "Ruska \u0141ozowa"
    ],
    "name:rus_x_preferred":[
        "\u0420\u0443\u0441\u0441\u043a\u0430\u044f \u041b\u043e\u0437\u043e\u0432\u0430\u044f"
    ],
    "name:ukr_x_preferred":[
        "\u0420\u0443\u0441\u044c\u043a\u0430 \u041b\u043e\u0437\u043e\u0432\u0430"
    ],
    "name:und_x_variant":[
        "Lozovoye Russkoye"
    ],
    "name:zho_x_preferred":[
        "\u9b6f\u897f\u5361\u6d1b\u4f50\u74e6"
    ],
    "qs:a0":"\u0423\u043a\u0440\u0430\u0457\u043d\u0430",
    "qs:a1":"*\u0425\u0430\u0440\u043a\u0456\u0432\u0441\u044c\u043a\u0430",
    "qs:a1_alt":"Kharkivs'ka",
    "qs:a1r":"0",
    "qs:a2":"\u0414\u0435\u0440\u0433\u0430\u0447\u0456\u0432\u0441\u044c\u043a\u0438\u0439",
    "qs:a2_alt":"Derhachivs'kyi",
    "qs:adm0":"\u0423\u043a\u0440\u0430\u0457\u043d\u0430",
    "qs:la_lc":"*",
    "qs:level":"locality",
    "qs:loc":"\u0420\u0443\u0441\u044c\u043a\u0430 \u041b\u043e\u0437\u043e\u0432\u0430",
    "qs:loc_alt":"Rus'ka Lozova",
    "qs:pop":0,
    "qs:type":"buffered point",
    "wof:name":"\u0420\u0443\u0441\u044c\u043a\u0430 \u041b\u043e\u0437\u043e\u0432\u0430",
    "wof:placetype":"locality"
},
  "geometry": {"coordinates":[36.257752,50.143144],"type":"Point"}
}