{
  "type": "Feature",
  "properties": {
    "iso:country":"UA",
    "name:bel_x_preferred":[
        "\u0412\u0456\u043a\u043d\u043e"
    ],
    "name:che_x_preferred":[
        "\u041e\u043a\u043d\u043e"
    ],
    "name:deu_x_preferred":[
        "Wikno"
    ],
    "name:eng_x_preferred":[
        "Vikno"
    ],
    "name:fin_x_preferred":[
        "V\u0456kn\u043e"
    ],
    "name:nan_x_preferred":[
        "Vikno"
    ],
    "name:nno_x_preferred":[
        "Vikno"
    ],
    "name:nob_x_preferred":[
        "Vikno"
    ],
    "name:pol_x_preferred":[
        "Okno"
    ],
    "name:ron_x_preferred":[
        "Vikno"
    ],
    "name:rus_x_preferred":[
        "\u041e\u043a\u043d\u043e"
    ],
    "name:ukr_x_preferred":[
        "\u0412\u0456\u043a\u043d\u043e"
    ],
    "name:zho_x_preferred":[
        "\u7dad\u514b\u8afe"
    ],
    "qs:a0":"\u0423\u043a\u0440\u0430\u0457\u043d\u0430",
    "qs:a1":"*\u0422\u0435\u0440\u043d\u043e\u043f\u0456\u043b\u044c\u0441\u044c\u043a\u0430",
    "qs:a1_alt":"Ternopil's'ka",
    "qs:a1r":"0",
    "qs:a2":"\u0413\u0443\u0441\u044f\u0442\u0438\u043d\u0441\u044c\u043a\u0438\u0439",
    "qs:a2_alt":"Husiatyns'kyi",
    "qs:adm0":"\u0423\u043a\u0440\u0430\u0457\u043d\u0430",
    "qs:la_lc":"*",
    "qs:level":"locality",
    "qs:loc":"\u0412\u0456\u043a\u043d\u043e",
    "qs:loc_alt":"Vikno",
    "qs:pop":0,
    "qs:type":"buffered point",
    "wd:wordcount":82,
    "wof:name":"\u0412\u0456\u043a\u043d\u043e",
    "wof:placetype":"locality"
},
  "geometry": {"coordinates":[26.068181,49.344517],"type":"Point"}
}