{
  "type": "Feature",
  "properties": {
    "gn:admin1_code":"22.0",
    "gn:asciiname":"Shul'ganuvka",
    "gn:country_code":"UA",
    "gn:dem":283,
    "gn:feature_class":"P",
    "gn:feature_code":"PPL",
    "gn:name":"Shul\u2019ganuvka",
    "gn:population":0,
    "gn:timezone":"Europe/Kiev",
    "iso:country":"UA",
    "name:und_x_variant":[
        "Shul\u2019ganovka",
        "Shul\u2019ganuvka"
    ],
    "wof:name":"Shul'ganuvka",
    "wof:placetype":"locality"
},
  "geometry": {"coordinates":[25.71942,48.9561],"type":"Point"}
}