{
  "type": "Feature",
  "properties": {
    "iso:country":"UA",
    "name:deu_x_preferred":[
        "Dmuchajliwka"
    ],
    "name:eng_x_preferred":[
        "Dmukhaylovka"
    ],
    "name:eng_x_variant":[
        "Dmukhailivka"
    ],
    "name:lav_x_preferred":[
        "Dmuhaj\u013civka"
    ],
    "name:ron_x_preferred":[
        "Dmuhailivka"
    ],
    "name:rus_x_preferred":[
        "\u0414\u043c\u0443\u0445\u0430\u0439\u043b\u043e\u0432\u043a\u0430"
    ],
    "name:ukr_x_preferred":[
        "Dmukhaylivka"
    ],
    "name:ukr_x_variant":[
        "\u0414\u043c\u0443\u0445\u0430\u0439\u043b\u0456\u0432\u043a\u0430"
    ],
    "qs:a0":"\u0423\u043a\u0440\u0430\u0457\u043d\u0430",
    "qs:a1":"*\u0414\u043d\u0456\u043f\u0440\u043e\u043f\u0435\u0442\u0440\u043e\u0432\u0441\u044c\u043a\u0430",
    "qs:a1_alt":"Dnipropetrovs'ka",
    "qs:a1r":"0",
    "qs:a2":"\u041c\u0430\u0433\u0434\u0430\u043b\u0438\u043d\u0456\u0432\u0441\u044c\u043a\u0438\u0439",
    "qs:a2_alt":"Mahdalynivs'kyi",
    "qs:adm0":"\u0423\u043a\u0440\u0430\u0457\u043d\u0430",
    "qs:la_lc":"*",
    "qs:level":"locality",
    "qs:loc":"\u0414\u043c\u0443\u0445\u0430\u0439\u043b\u0456\u0432\u043a\u0430",
    "qs:loc_alt":"Dmukhailivka",
    "qs:pop":0,
    "qs:type":"buffered point",
    "wof:name":"\u0414\u043c\u0443\u0445\u0430\u0439\u043b\u0456\u0432\u043a\u0430",
    "wof:placetype":"locality"
},
  "geometry": {"coordinates":[34.725039,49.056416],"type":"Point"}
}