{
  "type": "Feature",
  "properties": {
    "gn:admin1_code":"2.0",
    "gn:asciiname":"Patyuty",
    "gn:country_code":"UA",
    "gn:dem":115,
    "gn:feature_class":"P",
    "gn:feature_code":"PPL",
    "gn:name":"Patyuty",
    "gn:population":0,
    "gn:timezone":"Europe/Kiev",
    "iso:country":"UA",
    "name:eng_x_preferred":[
        "Patyuty"
    ],
    "name:rus_x_preferred":[
        "\u041f\u0430\u0442\u044e\u0442\u044b"
    ],
    "name:ukr_x_preferred":[
        "\u041f\u0430\u0442\u044e\u0442\u0438"
    ],
    "name:und_x_variant":[
        "Patyuta",
        "Patyuty"
    ],
    "wof:name":"Patyuty",
    "wof:placetype":"locality"
},
  "geometry": {"coordinates":[31.23694,51.0103],"type":"Point"}
}