{
  "type": "Feature",
  "properties": {
    "gn:admin1_code":"5.0",
    "gn:asciiname":"Lymanchuk",
    "gn:country_code":"UA",
    "gn:dem":243,
    "gn:feature_class":"P",
    "gn:feature_code":"PPL",
    "gn:name":"Lymanchuk",
    "gn:population":0,
    "gn:timezone":"Europe/Kiev",
    "iso:country":"UA",
    "name:ukr_x_preferred":[
        "Lymanchuk"
    ],
    "name:ukr_x_variant":[
        "\u041b\u0438\u043c\u0430\u043d\u0447\u0443\u043a"
    ],
    "name:und_x_variant":[
        "Lomanchuk",
        "Limanchuk"
    ],
    "wof:name":"Lymanchuk",
    "wof:placetype":"locality"
},
  "geometry": {"coordinates":[38.82399,48.01604],"type":"Point"}
}