{
  "type": "Feature",
  "properties": {
    "gn:admin1_code":"18.0",
    "gn:asciiname":"Mala Pereshchepyna",
    "gn:country_code":"UA",
    "gn:dem":85,
    "gn:feature_class":"P",
    "gn:feature_code":"PPL",
    "gn:name":"Mala Pereshchepyna",
    "gn:population":0,
    "gn:timezone":"Europe/Kiev",
    "iso:country":"UA",
    "name:ukr_x_preferred":[
        "Mala Pereshchepyna"
    ],
    "name:ukr_x_variant":[
        "\u041c\u0430\u043b\u0430 \u041f\u0435\u0440\u0435\u0449\u0435\u043f\u0438\u043d\u0430"
    ],
    "name:und_x_variant":[
        "Maloye Pereshchepino",
        "Malaya Pereshchepina"
    ],
    "wof:name":"Mala Pereshchepyna",
    "wof:placetype":"locality"
},
  "geometry": {"coordinates":[34.57445,49.39037],"type":"Point"}
}