{
  "type": "Feature",
  "properties": {
    "iso:country":"UA",
    "name:eng_x_preferred":[
        "Senokosnoye"
    ],
    "name:rus_x_historical":[
        "\u0411\u0443\u0437\u0443\u043a\u043a\u043e\u0301\u0439",
        "\u0411\u043e\u0437\u0443\u0301\u043a-\u041a\u0443\u044e\u0301"
    ],
    "name:rus_x_preferred":[
        "\u0411\u0443\u0437\u0443\u043a\u043a\u043e\u0301\u0439"
    ],
    "name:rus_x_variant":[
        "\u0421\u0435\u043d\u043e\u043a\u043e\u0441\u043d\u043e\u0435",
        "\u0411\u043e\u0437\u0443\u0301\u043a-\u041a\u0443\u044e\u0301"
    ],
    "name:ukr_x_preferred":[
        "\u0421\u0456\u043d\u043e\u043a\u0456\u0441\u043d\u0435"
    ],
    "qs:a0":"\u0423\u043a\u0440\u0430\u0457\u043d\u0430",
    "qs:a1":"*\u041a\u0440\u0438\u043c",
    "qs:a1_alt":"Krym",
    "qs:a1r":"0",
    "qs:a2":"\u0420\u043e\u0437\u0434\u043e\u043b\u044c\u043d\u0435\u043d\u0441\u044c\u043a\u0438\u0439",
    "qs:a2_alt":"Rozdol'nens'kyi",
    "qs:adm0":"\u0423\u043a\u0440\u0430\u0457\u043d\u0430",
    "qs:la_lc":"*",
    "qs:level":"locality",
    "qs:loc":"\u0421\u0456\u043d\u043e\u043a\u0456\u0441\u043d\u0435",
    "qs:loc_alt":"Sinokisne",
    "qs:pop":0,
    "qs:type":"buffered point",
    "wof:name":"\u0421\u0456\u043d\u043e\u043a\u0456\u0441\u043d\u0435",
    "wof:placetype":"locality"
},
  "geometry": {"coordinates":[33.515411,45.731856],"type":"Point"}
}