{
  "type": "Feature",
  "properties": {
    "gn:admin1_code":"16.0",
    "gn:asciiname":"Khutor Mayskiy",
    "gn:country_code":"UA",
    "gn:dem":84,
    "gn:feature_class":"P",
    "gn:feature_code":"PPL",
    "gn:name":"Khutor Mayskiy",
    "gn:population":0,
    "gn:timezone":"Europe/Kiev",
    "iso:country":"UA",
    "name:und_x_variant":[
        "Mayskiy",
        "Khutor Mayskiy"
    ],
    "wof:name":"Khutor Mayskiy",
    "wof:placetype":"locality"
},
  "geometry": {"coordinates":[32.20156,47.70595],"type":"Point"}
}