{
  "type": "Feature",
  "properties": {
    "gn:country":"UA",
    "gn:fcode":"PPL",
    "gn:population":617,
    "iso:country":"UA",
    "name:ceb_x_preferred":[
        "Yablonovka"
    ],
    "name:deu_x_preferred":[
        "Jaslowez"
    ],
    "name:eng_x_preferred":[
        "Yazlovets"
    ],
    "name:eng_x_variant":[
        "Yablunivka"
    ],
    "name:heb_x_preferred":[
        "\u05d9\u05d0\u05d6\u05dc\u05d5\u05d1\u05d9\u05d9\u05e5"
    ],
    "name:pol_x_preferred":[
        "Jaz\u0142owiec"
    ],
    "name:ron_x_preferred":[
        "Iazlove\u021b"
    ],
    "name:rus_x_preferred":[
        "\u042f\u0437\u043b\u043e\u0432\u0435\u0446"
    ],
    "name:rus_x_variant":[
        "\u042f\u0431\u043b\u043e\u043d\u043e\u0432\u043a\u0430"
    ],
    "name:swe_x_preferred":[
        "Jazlovets"
    ],
    "name:ukr_x_preferred":[
        "\u042f\u0437\u043b\u043e\u0432\u0435\u0446\u044c"
    ],
    "name:und_x_variant":[
        "Novosyulka Yazlovetska"
    ],
    "name:zho_x_preferred":[
        "\u4e9e\u8332\u6d1b\u97cb\u9f4a"
    ],
    "qs_pg:aaroncc":"UA",
    "qs_pg:gn_country":"UA",
    "qs_pg:gn_fcode":"PPL",
    "qs_pg:gn_pop":617,
    "qs_pg:name":"Yablonovka",
    "qs_pg:photos_9r":0,
    "qs_pg:photos_sr":0,
    "qs_pg:pop_sr":2,
    "qs_pg:qs_pg_placetype":"locality",
    "wof:name":"Yablonovka",
    "wof:placetype":"locality",
    "wof:population":617
},
  "geometry": {"coordinates":[25.44159,48.96512],"type":"Point"}
}