{
  "type": "Feature",
  "properties": {
    "gn:admin1_code":"15",
    "gn:asciiname":"Hlyboch",
    "gn:country_code":"UA",
    "gn:dem":320,
    "gn:feature_class":"P",
    "gn:feature_code":"PPL",
    "gn:name":"Hlyboch",
    "gn:population":0,
    "gn:timezone":"Europe/Kiev",
    "iso:country":"UA",
    "name:ukr_x_preferred":[
        "Hlyboch"
    ],
    "name:ukr_x_variant":[
        "\u0413\u043b\u0438\u0431\u043e\u0447"
    ],
    "wof:name":"Hlyboch",
    "wof:placetype":"locality"
},
  "geometry": {"coordinates":[23.26777,49.45457],"type":"Point"}
}