{
  "type": "Feature",
  "properties": {
    "gn:admin1_code":"4.0",
    "gn:asciiname":"Moprivs'ke",
    "gn:country_code":"UA",
    "gn:dem":116,
    "gn:feature_class":"P",
    "gn:feature_code":"PPL",
    "gn:name":"Moprivs\u2019ke",
    "gn:population":0,
    "gn:timezone":"Europe/Kiev",
    "iso:country":"UA",
    "name:ukr_x_preferred":[
        "Moprivs\u2019ke"
    ],
    "name:ukr_x_variant":[
        "\u041c\u043e\u043f\u0440\u0456\u0432\u0441\u044c\u043a\u0435"
    ],
    "wof:name":"Moprivs'ke",
    "wof:placetype":"locality"
},
  "geometry": {"coordinates":[34.72695,48.0637],"type":"Point"}
}