{
  "type": "Feature",
  "properties": {
    "gn:population":22545,
    "iso:country":"UA",
    "name:azb_x_preferred":[
        "\u0644\u06cc\u0648\u0628\u0648\u062a\u06cc\u0646"
    ],
    "name:bel_x_preferred":[
        "\u041b\u044e\u0431\u043e\u0442\u044b\u043d"
    ],
    "name:ceb_x_preferred":[
        "Lyubotyn"
    ],
    "name:ces_x_preferred":[
        "Ljubotyn"
    ],
    "name:crh_x_preferred":[
        "L\u00fcbot\u0131n"
    ],
    "name:deu_x_preferred":[
        "Ljubotyn"
    ],
    "name:eng_x_preferred":[
        "Lyubotyn"
    ],
    "name:eng_x_variant":[
        "Liubotyn"
    ],
    "name:fas_x_preferred":[
        "\u0644\u06cc\u0648\u0628\u0648\u062a\u06cc\u0646"
    ],
    "name:fra_x_preferred":[
        "Lioubotyn"
    ],
    "name:hsb_x_preferred":[
        "Ljubotyn"
    ],
    "name:hye_x_preferred":[
        "\u053c\u0575\u0578\u0582\u0562\u0578\u057f\u056b\u0576"
    ],
    "name:ita_x_preferred":[
        "Ljubotyn"
    ],
    "name:kat_x_preferred":[
        "\u10da\u10d8\u10e3\u10d1\u10dd\u10e2\u10d8\u10dc\u10d8"
    ],
    "name:lav_x_preferred":[
        "\u013bubotina"
    ],
    "name:lit_x_preferred":[
        "Liubotynas"
    ],
    "name:nld_x_preferred":[
        "Liubotyn"
    ],
    "name:nno_x_preferred":[
        "Ljubotyn"
    ],
    "name:pol_x_preferred":[
        "Lubotyn"
    ],
    "name:ron_x_preferred":[
        "Liubot\u00een"
    ],
    "name:rus_x_preferred":[
        "\u041b\u044e\u0431\u043e\u0442\u0438\u043d"
    ],
    "name:sco_x_preferred":[
        "Liubotyn"
    ],
    "name:srp_x_preferred":[
        "\u0409\u0443\u0431\u043e\u0442\u0438\u043d"
    ],
    "name:tat_x_preferred":[
        "\u041b\u044e\u0431\u043e\u0442\u0438\u043d"
    ],
    "name:tat_x_variant":[
        "\u041b\u04af\u0431\u043e\u0442\u044b\u043d"
    ],
    "name:ukr_x_preferred":[
        "\u041b\u044e\u0431\u043e\u0442\u0438\u043d"
    ],
    "name:und_x_variant":[
        "Lyobotin"
    ],
    "name:vie_x_preferred":[
        "Liubotyn"
    ],
    "name:zho_x_preferred":[
        "\u67f3\u535a\u4eac"
    ],
    "qs:a0":"\u0423\u043a\u0440\u0430\u0457\u043d\u0430",
    "qs:a1":"*\u0425\u0430\u0440\u043a\u0456\u0432\u0441\u044c\u043a\u0430",
    "qs:a1_alt":"Kharkivs'ka",
    "qs:a1r":"0",
    "qs:a2":"\u0425\u0430\u0440\u043a\u0456\u0432\u0441\u044c\u043a\u0438\u0439",
    "qs:a2_alt":"Kharkivs'kyi",
    "qs:adm0":"\u0423\u043a\u0440\u0430\u0457\u043d\u0430",
    "qs:la_lc":"*",
    "qs:level":"locality",
    "qs:loc":"\u041b\u044e\u0431\u043e\u0442\u0438\u043d",
    "qs:loc_alt":"Liubotyn",
    "qs:pop":0,
    "qs:type":"buffered point",
    "wd:wordcount":117,
    "wof:name":"\u041b\u044e\u0431\u043e\u0442\u0438\u043d",
    "wof:placetype":"locality",
    "wof:population":22545
},
  "geometry": {"coordinates":[35.921374,49.940696],"type":"Point"}
}