{
  "type": "Feature",
  "properties": {
    "iso:country":"UA",
    "name:pol_x_preferred":[
        "D\u0105browa"
    ],
    "name:ukr_x_preferred":[
        "Dibrova"
    ],
    "name:ukr_x_variant":[
        "\u0414\u0456\u0431\u0440\u043e\u0432\u0430"
    ],
    "name:und_x_variant":[
        "Kabany"
    ],
    "qs:a0":"\u0423\u043a\u0440\u0430\u0457\u043d\u0430",
    "qs:a1":"*\u041a\u0438\u0457\u0432\u0441\u044c\u043a\u0430",
    "qs:a1_alt":"Kyivs'ka",
    "qs:a1r":"0",
    "qs:a2":"\u041f\u043e\u043b\u0456\u0441\u044c\u043a\u0438\u0439",
    "qs:a2_alt":"Polis'kyi",
    "qs:adm0":"\u0423\u043a\u0440\u0430\u0457\u043d\u0430",
    "qs:la_lc":"*",
    "qs:level":"locality",
    "qs:loc":"\u0414\u0456\u0431\u0440\u043e\u0432\u0430",
    "qs:loc_alt":"Dibrova",
    "qs:pop":0,
    "qs:type":"buffered point",
    "wd:wordcount":104,
    "wof:name":"\u0414\u0456\u0431\u0440\u043e\u0432\u0430",
    "wof:placetype":"locality"
},
  "geometry": {"coordinates":[29.672691,51.28987],"type":"Point"}
}