{
  "type": "Feature",
  "properties": {
    "iso:country":"UA",
    "name:ukr_x_preferred":[
        "Noryns\u2019k"
    ],
    "name:ukr_x_variant":[
        "\u041d\u043e\u0440\u0438\u043d\u0441\u044c\u043a"
    ],
    "name:unk_x_variant":[
        "Norinsk"
    ],
    "qs:a0":"\u0423\u043a\u0440\u0430\u0457\u043d\u0430",
    "qs:a1":"*\u0416\u0438\u0442\u043e\u043c\u0438\u0440\u0441\u044c\u043a\u0430",
    "qs:a1_alt":"Zhytomyrs'ka",
    "qs:a1r":"0",
    "qs:a2":"\u041e\u0432\u0440\u0443\u0446\u044c\u043a\u0438\u0439",
    "qs:a2_alt":"Ovruts'kyi",
    "qs:adm0":"\u0423\u043a\u0440\u0430\u0457\u043d\u0430",
    "qs:la_lc":"*",
    "qs:level":"locality",
    "qs:loc":"\u041d\u043e\u0440\u0438\u043d\u0441\u044c\u043a",
    "qs:loc_alt":"Noryns'k",
    "qs:pop":0,
    "qs:type":"buffered point",
    "wof:name":"\u041d\u043e\u0440\u0438\u043d\u0441\u044c\u043a",
    "wof:placetype":"locality"
},
  "geometry": {"coordinates":[28.575688,51.268572],"type":"Point"}
}