{
  "type": "Feature",
  "properties": {
    "iso:country":"UA",
    "name:eng_x_preferred":[
        "Tarasovka"
    ],
    "name:rus_x_preferred":[
        "\u0422\u0430\u0440\u0430\u0441\u043e\u0432\u043a\u0430"
    ],
    "name:ukr_x_preferred":[
        "\u0422\u0430\u0440\u0430\u0441\u0456\u0432\u043a\u0430"
    ],
    "name:ukr_x_variant":[
        "Tarasivka"
    ],
    "qs:a0":"\u0423\u043a\u0440\u0430\u0457\u043d\u0430",
    "qs:a1":"*\u041f\u043e\u043b\u0442\u0430\u0432\u0441\u044c\u043a\u0430",
    "qs:a1_alt":"Poltavs'ka",
    "qs:a1r":"0",
    "qs:a2":"\u0413\u0440\u0435\u0431\u0456\u043d\u043a\u0456\u0432\u0441\u044c\u043a\u0438\u0439",
    "qs:a2_alt":"Hrebinkivs'kyi",
    "qs:adm0":"\u0423\u043a\u0440\u0430\u0457\u043d\u0430",
    "qs:la_lc":"*",
    "qs:level":"locality",
    "qs:loc":"\u0422\u0430\u0440\u0430\u0441\u0456\u0432\u043a\u0430",
    "qs:loc_alt":"Tarasivka",
    "qs:pop":0,
    "qs:type":"buffered point",
    "wof:name":"\u0422\u0430\u0440\u0430\u0441\u0456\u0432\u043a\u0430",
    "wof:placetype":"locality"
},
  "geometry": {"coordinates":[32.483946,50.194914],"type":"Point"}
}