{
  "type": "Feature",
  "properties": {
    "gn:admin1_code":"14.0",
    "gn:asciiname":"Karayichne",
    "gn:country_code":"UA",
    "gn:dem":187,
    "gn:feature_class":"P",
    "gn:feature_code":"PPL",
    "gn:name":"Karayichne",
    "gn:population":0,
    "gn:timezone":"Europe/Zaporozhye",
    "iso:country":"UA",
    "name:ukr_x_preferred":[
        "Karayichne"
    ],
    "name:ukr_x_variant":[
        "\u041a\u0430\u0440\u0430\u0457\u0447\u043d\u0435"
    ],
    "name:und_x_variant":[
        "Karaichnoye"
    ],
    "wof:name":"Karayichne",
    "wof:placetype":"locality"
},
  "geometry": {"coordinates":[38.29735,49.80184000000001],"type":"Point"}
}