{
  "type": "Feature",
  "properties": {
    "gn:admin1_code":"7.0",
    "gn:asciiname":"Shuby",
    "gn:country_code":"UA",
    "gn:dem":164,
    "gn:feature_class":"P",
    "gn:feature_code":"PPL",
    "gn:name":"Shuby",
    "gn:population":0,
    "gn:timezone":"Europe/Kiev",
    "iso:country":"UA",
    "name:ukr_x_preferred":[
        "Shuby"
    ],
    "name:ukr_x_variant":[
        "\u0428\u0443\u0431\u0438"
    ],
    "wof:name":"Shuby",
    "wof:placetype":"locality"
},
  "geometry": {"coordinates":[35.67225,50.25773],"type":"Point"}
}