{
  "type": "Feature",
  "properties": {
    "gn:admin1_code":"18.0",
    "gn:asciiname":"Kovalenkivka",
    "gn:country_code":"UA",
    "gn:dem":115,
    "gn:feature_class":"P",
    "gn:feature_code":"PPL",
    "gn:name":"Kovalenkivka",
    "gn:population":0,
    "gn:timezone":"Europe/Kiev",
    "iso:country":"UA",
    "name:ukr_x_preferred":[
        "Kovalenkivka"
    ],
    "name:ukr_x_variant":[
        "\u041a\u043e\u0432\u0430\u043b\u0435\u043d\u043a\u0456\u0432\u043a\u0430"
    ],
    "name:und_x_variant":[
        "Kovali",
        "Koval\u00ebnki"
    ],
    "wof:name":"Kovalenkivka",
    "wof:placetype":"locality"
},
  "geometry": {"coordinates":[34.01875,49.04734000000001],"type":"Point"}
}