{
  "type": "Feature",
  "properties": {
    "gn:admin1_code":"19.0",
    "gn:asciiname":"Zhdan'",
    "gn:country_code":"UA",
    "gn:dem":152,
    "gn:feature_class":"P",
    "gn:feature_code":"PPL",
    "gn:name":"Zhdan\u2019",
    "gn:population":0,
    "gn:timezone":"Europe/Kiev",
    "iso:country":"UA",
    "name:ukr_x_preferred":[
        "Zhdan\u2019"
    ],
    "name:ukr_x_variant":[
        "\u0416\u0434\u0430\u043d\u044c"
    ],
    "wof:name":"Zhdan'",
    "wof:placetype":"locality"
},
  "geometry": {"coordinates":[25.73824,51.64437],"type":"Point"}
}