{
  "type": "Feature",
  "properties": {
    "gn:admin1_code":"14.0",
    "gn:asciiname":"Zayikivka",
    "gn:country_code":"UA",
    "gn:dem":72,
    "gn:feature_class":"P",
    "gn:feature_code":"PPL",
    "gn:name":"Zayikivka",
    "gn:population":0,
    "gn:timezone":"Europe/Zaporozhye",
    "iso:country":"UA",
    "name:ukr_x_preferred":[
        "Zayikivka"
    ],
    "name:und_x_variant":[
        "Zaikovka",
        "Zaykovka"
    ],
    "wof:name":"Zayikivka",
    "wof:placetype":"locality"
},
  "geometry": {"coordinates":[38.76275,49.45417],"type":"Point"}
}