{
  "type": "Feature",
  "properties": {
    "gn:admin1_code":"7.0",
    "gn:asciiname":"Pohorile",
    "gn:country_code":"UA",
    "gn:dem":173,
    "gn:feature_class":"P",
    "gn:feature_code":"PPL",
    "gn:name":"Pohorile",
    "gn:population":0,
    "gn:timezone":"Europe/Kiev",
    "iso:country":"UA",
    "name:rus_x_preferred":[
        "\u041f\u043e\u0433\u043e\u0440\u0435\u043b\u043e\u0435"
    ],
    "name:ukr_x_preferred":[
        "Pohorile"
    ],
    "name:ukr_x_variant":[
        "\u041f\u043e\u0433\u043e\u0440\u0456\u043b\u0435"
    ],
    "name:und_x_variant":[
        "Pohoreloye",
        "Pogorely"
    ],
    "wof:name":"Pohorile",
    "wof:placetype":"locality"
},
  "geometry": {"coordinates":[37.12441,50.10793],"type":"Point"}
}