{
  "type": "Feature",
  "properties": {
    "gn:population":1816,
    "iso:country":"UA",
    "name:eng_x_preferred":[
        "Mezhvodnoye"
    ],
    "name:eng_x_variant":[
        "Yarylgach"
    ],
    "name:rus_x_historical":[
        "\u042f\u0440\u044b\u043b\u0433\u0430\u0301\u0447"
    ],
    "name:rus_x_preferred":[
        "\u042f\u0440\u044b\u043b\u0433\u0430\u0301\u0447"
    ],
    "name:rus_x_variant":[
        "\u041c\u0435\u0436\u0432\u043e\u0434\u043d\u043e\u0435"
    ],
    "name:ukr_x_preferred":[
        "\u041c\u0456\u0436\u0432\u043e\u0434\u043d\u0435"
    ],
    "qs:a0":"\u0423\u043a\u0440\u0430\u0457\u043d\u0430",
    "qs:a1":"*\u041a\u0440\u0438\u043c",
    "qs:a1_alt":"Krym",
    "qs:a1r":"0",
    "qs:a2":"\u0427\u043e\u0440\u043d\u043e\u043c\u043e\u0440\u0441\u044c\u043a\u0438\u0439",
    "qs:a2_alt":"Chornomors'kyi",
    "qs:adm0":"\u0423\u043a\u0440\u0430\u0457\u043d\u0430",
    "qs:la_lc":"*",
    "qs:level":"locality",
    "qs:loc":"\u041c\u0456\u0436\u0432\u043e\u0434\u043d\u0435",
    "qs:loc_alt":"Mizhvodne",
    "qs:pop":0,
    "qs:type":"buffered point",
    "wof:lang":[
        "eng"
    ],
    "wof:name":"\u041c\u0456\u0436\u0432\u043e\u0434\u043d\u0435",
    "wof:placetype":"locality",
    "wof:population":1816
},
  "geometry": {"coordinates":[32.844603,45.586341],"type":"Point"}
}