{
  "type": "Feature",
  "properties": {
    "gn:admin1_code":"27.0",
    "gn:asciiname":"Osnyky",
    "gn:country_code":"UA",
    "gn:dem":208,
    "gn:feature_class":"P",
    "gn:feature_code":"PPL",
    "gn:name":"Osnyky",
    "gn:population":0,
    "gn:timezone":"Europe/Kiev",
    "iso:country":"UA",
    "name:ukr_x_preferred":[
        "Osnyky"
    ],
    "name:ukr_x_variant":[
        "\u041e\u0441\u043d\u0438\u043a\u0438"
    ],
    "name:und_x_variant":[
        "Osniki",
        "Osnyki"
    ],
    "wof:name":"Osnyky",
    "wof:placetype":"locality"
},
  "geometry": {"coordinates":[28.81902,50.44461],"type":"Point"}
}