{
  "type": "Feature",
  "properties": {
    "gn:admin1_code":"17.0",
    "gn:asciiname":"Tomay Nou",
    "gn:cc2":"UA",
    "gn:country_code":"UA",
    "gn:dem":134,
    "gn:feature_class":"P",
    "gn:feature_code":"PPL",
    "gn:name":"Tomay Nou",
    "gn:population":0,
    "gn:timezone":"Europe/Kiev",
    "iso:country":"UA",
    "name:und_x_variant":[
        "Tomai-Nou"
    ],
    "wof:name":"Tomay Nou",
    "wof:placetype":"locality"
},
  "geometry": {"coordinates":[29.18583,46.41472],"type":"Point"}
}