{
  "type": "Feature",
  "properties": {
    "gn:admin1_code":"2.0",
    "gn:asciiname":"Vykhvostiv",
    "gn:country_code":"UA",
    "gn:dem":127,
    "gn:feature_class":"P",
    "gn:feature_code":"PPL",
    "gn:name":"Vykhvostiv",
    "gn:population":0,
    "gn:timezone":"Europe/Kiev",
    "iso:country":"UA",
    "name:eng_x_preferred":[
        "Vykhvostov"
    ],
    "name:rus_x_preferred":[
        "\u0412\u044b\u0445\u0432\u043e\u0441\u0442\u043e\u0432"
    ],
    "name:ukr_x_preferred":[
        "Vykhvostiv"
    ],
    "name:ukr_x_variant":[
        "\u0412\u0438\u0445\u0432\u043e\u0441\u0442\u0456\u0432"
    ],
    "name:und_x_variant":[
        "Vykhvostovo"
    ],
    "wof:name":"Vykhvostiv",
    "wof:placetype":"locality"
},
  "geometry": {"coordinates":[31.4003,51.73412],"type":"Point"}
}