{
  "type": "Feature",
  "properties": {
    "gn:admin1_code":"22.0",
    "gn:asciiname":"Tolsten'koye",
    "gn:country_code":"UA",
    "gn:dem":290,
    "gn:feature_class":"P",
    "gn:feature_code":"PPL",
    "gn:name":"Tolsten\u2019koye",
    "gn:population":0,
    "gn:timezone":"Europe/Kiev",
    "iso:country":"UA",
    "name:und_x_variant":[
        "Tlusten\u2019ke",
        "Tolsten\u2019koye"
    ],
    "wof:name":"Tolsten'koye",
    "wof:placetype":"locality"
},
  "geometry": {"coordinates":[26.06132,49.02348],"type":"Point"}
}