{
  "type": "Feature",
  "properties": {
    "iso:country":"UA",
    "name:bel_x_preferred":[
        "\u0421\u044d\u0434\u043b\u044b\u0448\u0447\u044d"
    ],
    "name:deu_x_preferred":[
        "Sedlyschtsche"
    ],
    "name:eng_x_preferred":[
        "Sedlysche"
    ],
    "name:hye_x_preferred":[
        "\u054d\u0565\u0564\u056c\u056b\u0577\u0579\u0565"
    ],
    "name:lav_x_preferred":[
        "Sedli\u0161\u010de"
    ],
    "name:nld_x_preferred":[
        "Sedlysche"
    ],
    "name:pol_x_preferred":[
        "Siedliszcze"
    ],
    "name:ron_x_preferred":[
        "Sedl\u00ee\u0219ce"
    ],
    "name:rus_x_preferred":[
        "\u0421\u0435\u0434\u043b\u0438\u0449\u0435"
    ],
    "name:ukr_x_preferred":[
        "Sedlyshche"
    ],
    "name:ukr_x_variant":[
        "\u0421\u0435\u0434\u043b\u0438\u0449\u0435"
    ],
    "name:und_x_variant":[
        "Sedlishche"
    ],
    "name:zho_x_preferred":[
        "\u8b1d\u5fb7\u5229\u8b1d"
    ],
    "qs:a0":"\u0423\u043a\u0440\u0430\u0457\u043d\u0430",
    "qs:a1":"*\u0412\u043e\u043b\u0438\u043d\u0441\u044c\u043a\u0430",
    "qs:a1_alt":"Volyns'ka",
    "qs:a1r":"0",
    "qs:a2":"\u041b\u044e\u0431\u0435\u0448\u0456\u0432\u0441\u044c\u043a\u0438\u0439",
    "qs:a2_alt":"Liubeshivs'kyi",
    "qs:adm0":"\u0423\u043a\u0440\u0430\u0457\u043d\u0430",
    "qs:la_lc":"*",
    "qs:level":"locality",
    "qs:loc":"\u0421\u0435\u0434\u043b\u0438\u0449\u0435",
    "qs:loc_alt":"Sedlysche",
    "qs:pop":0,
    "qs:type":"buffered point",
    "wof:name":"\u0421\u0435\u0434\u043b\u0438\u0449\u0435",
    "wof:placetype":"locality"
},
  "geometry": {"coordinates":[25.382487,51.67502],"type":"Point"}
}