{
  "type": "Feature",
  "properties": {
    "gn:admin1_code":"23.0",
    "gn:asciiname":"Vapnyarky",
    "gn:country_code":"UA",
    "gn:dem":234,
    "gn:feature_class":"P",
    "gn:feature_code":"PPL",
    "gn:name":"Vapnyarky",
    "gn:population":0,
    "gn:timezone":"Europe/Kiev",
    "iso:country":"UA",
    "name:ukr_x_preferred":[
        "\u0412\u0430\u043f\u043d\u044f\u0440\u043a\u0438"
    ],
    "name:und_x_variant":[
        "Vapnyarki"
    ],
    "wof:name":"Vapnyarky",
    "wof:placetype":"locality"
},
  "geometry": {"coordinates":[28.67295,48.58637],"type":"Point"}
}