{
  "type": "Feature",
  "properties": {
    "gn:admin1_code":"21.0",
    "gn:asciiname":"Shpotivka",
    "gn:country_code":"UA",
    "gn:dem":158,
    "gn:feature_class":"P",
    "gn:feature_code":"PPL",
    "gn:name":"Shpotivka",
    "gn:population":0,
    "gn:timezone":"Europe/Kiev",
    "iso:country":"UA",
    "name:ukr_x_preferred":[
        "Shpotivka"
    ],
    "name:ukr_x_variant":[
        "\u0428\u043f\u043e\u0442\u0456\u0432\u043a\u0430"
    ],
    "name:und_x_variant":[
        "Shpotovka"
    ],
    "wof:name":"Shpotivka",
    "wof:placetype":"locality"
},
  "geometry": {"coordinates":[33.43524,51.04366],"type":"Point"}
}