{
  "type": "Feature",
  "properties": {
    "gn:admin1_code":"14.0",
    "gn:asciiname":"Hrybuvakha",
    "gn:country_code":"UA",
    "gn:dem":119,
    "gn:feature_class":"P",
    "gn:feature_code":"PPL",
    "gn:name":"Hrybuvakha",
    "gn:population":0,
    "gn:timezone":"Europe/Zaporozhye",
    "iso:country":"UA",
    "name:eng_x_preferred":[
        "Hribuvakha"
    ],
    "name:rus_x_preferred":[
        "\u0413\u0440\u0438\u0431\u043e\u0432\u0430\u0445\u0430"
    ],
    "name:ukr_x_preferred":[
        "Hrybuvakha"
    ],
    "name:ukr_x_variant":[
        "\u0413\u0440\u0438\u0431\u0443\u0432\u0430\u0445\u0430"
    ],
    "name:und_x_variant":[
        "Gribovakha"
    ],
    "wof:name":"Hrybuvakha",
    "wof:placetype":"locality"
},
  "geometry": {"coordinates":[39.32687,47.98221],"type":"Point"}
}