{
  "type": "Feature",
  "properties": {
    "gn:admin1_code":"17.0",
    "gn:asciiname":"Sila",
    "gn:country_code":"UA",
    "gn:dem":78,
    "gn:feature_class":"P",
    "gn:feature_code":"PPL",
    "gn:name":"Sila",
    "gn:population":0,
    "gn:timezone":"Europe/Kiev",
    "iso:country":"UA",
    "wof:name":"Sila",
    "wof:placetype":"locality"
},
  "geometry": {"coordinates":[30.61667000000001,46.78333],"type":"Point"}
}