{
  "type": "Feature",
  "properties": {
    "gn:admin1_code":"27.0",
    "gn:asciiname":"Mala Chernihivka",
    "gn:country_code":"UA",
    "gn:dem":136,
    "gn:feature_class":"P",
    "gn:feature_code":"PPL",
    "gn:name":"Mala Chernihivka",
    "gn:population":0,
    "gn:timezone":"Europe/Kiev",
    "iso:country":"UA",
    "name:ukr_x_preferred":[
        "Mala Chernihivka"
    ],
    "name:ukr_x_variant":[
        "\u041c\u0430\u043b\u0430 \u0427\u0435\u0440\u043d\u0456\u0433\u0456\u0432\u043a\u0430"
    ],
    "name:und_x_variant":[
        "Malaya Chernigovka"
    ],
    "wof:name":"Mala Chernihivka",
    "wof:placetype":"locality"
},
  "geometry": {"coordinates":[28.94331,51.28366],"type":"Point"}
}