{
  "type": "Feature",
  "properties": {
    "gn:admin1_code":"15.0",
    "gn:asciiname":"Meleshki",
    "gn:country_code":"UA",
    "gn:dem":194,
    "gn:feature_class":"P",
    "gn:feature_code":"PPL",
    "gn:name":"Meleshki",
    "gn:population":0,
    "gn:timezone":"Europe/Kiev",
    "iso:country":"UA",
    "wof:name":"Meleshki",
    "wof:placetype":"locality"
},
  "geometry": {"coordinates":[23.07964,49.87649],"type":"Point"}
}