{
  "type": "Feature",
  "properties": {
    "gn:admin1_code":"24.0",
    "gn:asciiname":"Kuty",
    "gn:country_code":"UA",
    "gn:dem":230,
    "gn:feature_class":"P",
    "gn:feature_code":"PPL",
    "gn:name":"Kuty",
    "gn:population":0,
    "gn:timezone":"Europe/Kiev",
    "iso:country":"UA",
    "name:ukr_x_preferred":[
        "Kuty"
    ],
    "name:ukr_x_variant":[
        "\u041a\u0443\u0442\u0438"
    ],
    "wof:name":"Kuty",
    "wof:placetype":"locality"
},
  "geometry": {"coordinates":[24.69617,50.60084000000001],"type":"Point"}
}