{
  "type": "Feature",
  "properties": {
    "gn:admin1_code":"13.0",
    "gn:asciiname":"Mala Berezanka",
    "gn:country_code":"UA",
    "gn:dem":132,
    "gn:feature_class":"P",
    "gn:feature_code":"PPL",
    "gn:name":"Mala Berezanka",
    "gn:population":0,
    "gn:timezone":"Europe/Kiev",
    "iso:country":"UA",
    "name:ukr_x_preferred":[
        "Mala Berezanka"
    ],
    "name:ukr_x_variant":[
        "\u041c\u0430\u043b\u0430 \u0411\u0435\u0440\u0435\u0437\u0430\u043d\u043a\u0430"
    ],
    "name:und_x_variant":[
        "Berezanka",
        "Malaya Berezanka"
    ],
    "wof:name":"Mala Berezanka",
    "wof:placetype":"locality"
},
  "geometry": {"coordinates":[31.70982,50.389],"type":"Point"}
}