{
  "type": "Feature",
  "properties": {
    "gn:admin1_code":"15.0",
    "gn:asciiname":"Kropyvna",
    "gn:country_code":"UA",
    "gn:dem":354,
    "gn:feature_class":"P",
    "gn:feature_code":"PPL",
    "gn:name":"Kropyvna",
    "gn:population":0,
    "gn:timezone":"Europe/Kiev",
    "iso:country":"UA",
    "wof:name":"Kropyvna",
    "wof:placetype":"locality"
},
  "geometry": {"coordinates":[24.80669,49.69283],"type":"Point"}
}