{
  "type": "Feature",
  "properties": {
    "gn:admin1_code":"3.0",
    "gn:asciiname":"Samakova",
    "gn:country_code":"UA",
    "gn:dem":833,
    "gn:feature_class":"P",
    "gn:feature_code":"PPL",
    "gn:name":"Samakova",
    "gn:population":0,
    "gn:timezone":"Europe/Kiev",
    "iso:country":"UA",
    "name:ukr_x_preferred":[
        "Samakova"
    ],
    "name:ukr_x_variant":[
        "\u0421\u0430\u043c\u0430\u043a\u043e\u0432\u0430"
    ],
    "name:und_x_variant":[
        "Lipovets",
        "Semakova"
    ],
    "wof:name":"Samakova",
    "wof:placetype":"locality"
},
  "geometry": {"coordinates":[24.96952000000001,48.0073],"type":"Point"}
}