{
  "type": "Feature",
  "properties": {
    "iso:country":"UA",
    "qs:a0":"\u0423\u043a\u0440\u0430\u0457\u043d\u0430",
    "qs:a1":"*\u0412\u0456\u043d\u043d\u0438\u0446\u044c\u043a\u0430",
    "qs:a1_alt":"Vinnyts'ka",
    "qs:a1r":"0",
    "qs:a2":"\u0411\u0435\u0440\u0448\u0430\u0434\u0441\u044c\u043a\u0438\u0439",
    "qs:a2_alt":"Bershads'kyi",
    "qs:adm0":"\u0423\u043a\u0440\u0430\u0457\u043d\u0430",
    "qs:la_lc":"*",
    "qs:level":"locality",
    "qs:loc":"\u042f\u043b\u0430\u043d\u0435\u0446\u044c",
    "qs:loc_alt":"Yalanets",
    "qs:pop":0,
    "qs:type":"buffered point",
    "wof:name":"\u042f\u043b\u0430\u043d\u0435\u0446\u044c",
    "wof:placetype":"locality"
},
  "geometry": {"coordinates":[29.458036,48.301736],"type":"Point"}
}