{
  "type": "Feature",
  "properties": {
    "gn:admin1_code":"27.0",
    "gn:asciiname":"Zaboroche",
    "gn:country_code":"UA",
    "gn:dem":187,
    "gn:feature_class":"P",
    "gn:feature_code":"PPL",
    "gn:name":"Zaboroche",
    "gn:population":0,
    "gn:timezone":"Europe/Kiev",
    "iso:country":"UA",
    "name:rus_x_preferred":[
        "Zaboroch\u2019ye"
    ],
    "name:ukr_x_preferred":[
        "Zaboroche"
    ],
    "name:ukr_x_variant":[
        "\u0417\u0430\u0431\u043e\u0440\u043e\u0447\u0435"
    ],
    "wof:name":"Zaboroche",
    "wof:placetype":"locality"
},
  "geometry": {"coordinates":[27.64908,51.15916],"type":"Point"}
}