{
  "type": "Feature",
  "properties": {
    "gn:admin1_code":"18.0",
    "gn:asciiname":"Suprotyvna Balka",
    "gn:country_code":"UA",
    "gn:dem":116,
    "gn:feature_class":"P",
    "gn:feature_code":"PPL",
    "gn:name":"Suprotyvna Balka",
    "gn:population":0,
    "gn:timezone":"Europe/Kiev",
    "iso:country":"UA",
    "name:ukr_x_preferred":[
        "Suprotyvna Balka"
    ],
    "name:ukr_x_variant":[
        "\u0421\u0443\u043f\u0440\u043e\u0442\u0438\u0432\u043d\u0430 \u0411\u0430\u043b\u043a\u0430"
    ],
    "name:und_x_variant":[
        "Suprotivna Balka",
        "Suprotivnaya Balka"
    ],
    "wof:name":"Suprotyvna Balka",
    "wof:placetype":"locality"
},
  "geometry": {"coordinates":[34.09181,49.39581],"type":"Point"}
}