{
  "type": "Feature",
  "properties": {
    "gn:admin1_code":"2.0",
    "gn:asciiname":"Koval'ove",
    "gn:country_code":"UA",
    "gn:dem":140,
    "gn:feature_class":"P",
    "gn:feature_code":"PPL",
    "gn:name":"Koval\u2019ove",
    "gn:population":0,
    "gn:timezone":"Europe/Kiev",
    "iso:country":"UA",
    "name:ukr_x_preferred":[
        "Koval\u2019ove"
    ],
    "name:ukr_x_variant":[
        "\u041a\u043e\u0432\u0430\u043b\u044c\u043e\u0432\u0435"
    ],
    "name:und_x_variant":[
        "Kovalevo"
    ],
    "wof:name":"Koval'ove",
    "wof:placetype":"locality"
},
  "geometry": {"coordinates":[32.72095,50.95588],"type":"Point"}
}