{
  "type": "Feature",
  "properties": {
    "gn:admin1_code":"14.0",
    "gn:asciiname":"Kopani",
    "gn:country_code":"UA",
    "gn:dem":183,
    "gn:feature_class":"P",
    "gn:feature_code":"PPL",
    "gn:name":"Kopani",
    "gn:population":0,
    "gn:timezone":"Europe/Zaporozhye",
    "iso:country":"UA",
    "name:ukr_x_preferred":[
        "Kopani"
    ],
    "name:ukr_x_variant":[
        "\u041a\u043e\u043f\u0430\u043d\u0456"
    ],
    "wof:name":"Kopani",
    "wof:placetype":"locality"
},
  "geometry": {"coordinates":[39.39386,49.24174],"type":"Point"}
}