{
  "type": "Feature",
  "properties": {
    "gn:admin1_code":"24.0",
    "gn:asciiname":"Khorlupy",
    "gn:country_code":"UA",
    "gn:dem":231,
    "gn:feature_class":"P",
    "gn:feature_code":"PPL",
    "gn:name":"Khorlupy",
    "gn:population":0,
    "gn:timezone":"Europe/Kiev",
    "iso:country":"UA",
    "name:ukr_x_preferred":[
        "Khorlupy"
    ],
    "name:ukr_x_variant":[
        "\u0425\u043e\u0440\u043b\u0443\u043f\u0438"
    ],
    "wof:name":"Khorlupy",
    "wof:placetype":"locality"
},
  "geometry": {"coordinates":[25.66112,50.73608],"type":"Point"}
}