{
  "type": "Feature",
  "properties": {
    "iso:country":"UA",
    "name:eng_x_preferred":[
        "Pletenyy Tashlyk"
    ],
    "name:rus_x_preferred":[
        "\u041f\u043b\u0435\u0442\u0435\u043d\u044b\u0439 \u0422\u0430\u0448\u043b\u044b\u043a"
    ],
    "name:unk_x_variant":[
        "Pleteniy Tashlyk"
    ],
    "qs:a0":"\u0423\u043a\u0440\u0430\u0457\u043d\u0430",
    "qs:a1":"*\u041a\u0456\u0440\u043e\u0432\u043e\u0433\u0440\u0430\u0434\u0441\u044c\u043a\u0430",
    "qs:a1_alt":"Kirovohrads'ka",
    "qs:a1r":"0",
    "qs:a2":"\u041c\u0430\u043b\u043e\u0432\u0438\u0441\u043a\u0456\u0432\u0441\u044c\u043a\u0438\u0439",
    "qs:a2_alt":"Malovyskivs'kyi",
    "qs:adm0":"\u0423\u043a\u0440\u0430\u0457\u043d\u0430",
    "qs:la_lc":"*",
    "qs:level":"locality",
    "qs:loc":"\u041f\u043b\u0435\u0442\u0435\u043d\u0438\u0439 \u0422\u0430\u0448\u043b\u0438\u043a",
    "qs:loc_alt":"Pletenyi Tashlyk",
    "qs:pop":0,
    "qs:type":"buffered point",
    "wof:name":"\u041f\u043b\u0435\u0442\u0435\u043d\u0438\u0439 \u0422\u0430\u0448\u043b\u0438\u043a",
    "wof:placetype":"locality"
},
  "geometry": {"coordinates":[31.667026,48.477414],"type":"Point"}
}