{
  "type": "Feature",
  "properties": {
    "gn:population":4901,
    "iso:country":"UA",
    "name:bul_x_preferred":[
        "\u0427\u0438\u0439\u0448\u0438\u044f"
    ],
    "name:ceb_x_preferred":[
        "Horodnye"
    ],
    "name:deu_x_preferred":[
        "Horodnje"
    ],
    "name:eng_x_preferred":[
        "Horodnie"
    ],
    "name:hye_x_preferred":[
        "\u0555\u0563\u0578\u0580\u0578\u0564\u0576\u0578\u0565"
    ],
    "name:lav_x_preferred":[
        "Horodne"
    ],
    "name:ron_x_preferred":[
        "Cii\u0219ia"
    ],
    "name:rus_x_preferred":[
        "\u0413\u043e\u0440\u043e\u0434\u043d\u044d"
    ],
    "name:rus_x_variant":[
        "\u041e\u0433\u043e\u0440\u043e\u0434\u043d\u043e\u0435"
    ],
    "name:spa_x_preferred":[
        "Horodnie"
    ],
    "name:ukr_x_preferred":[
        "\u0413\u043e\u0440\u043e\u0434\u043d\u044d"
    ],
    "name:ukr_x_variant":[
        "Horodne",
        "\u0413\u043e\u0440\u043e\u0434\u043d\u0454"
    ],
    "name:und_x_variant":[
        "Cii\u015fia"
    ],
    "name:zho_x_preferred":[
        "\u6208\u7f85\u5fb7\u5167"
    ],
    "qs:a0":"\u0423\u043a\u0440\u0430\u0457\u043d\u0430",
    "qs:a1":"*\u041e\u0434\u0435\u0441\u044c\u043a\u0430",
    "qs:a1_alt":"Odes'ka",
    "qs:a1r":"0",
    "qs:a2":"\u0411\u043e\u043b\u0433\u0440\u0430\u0434\u0441\u044c\u043a\u0438\u0439",
    "qs:a2_alt":"Bolhrads'kyi",
    "qs:adm0":"\u0423\u043a\u0440\u0430\u0457\u043d\u0430",
    "qs:la_lc":"*",
    "qs:level":"locality",
    "qs:loc":"\u0413\u043e\u0440\u043e\u0434\u043d\u0454",
    "qs:loc_alt":"Horodnie",
    "qs:pop":0,
    "qs:type":"buffered point",
    "wof:name":"\u0413\u043e\u0440\u043e\u0434\u043d\u0454",
    "wof:placetype":"locality",
    "wof:population":4901
},
  "geometry": {"coordinates":[28.850685,45.893533],"type":"Point"}
}