{
  "type": "Feature",
  "properties": {
    "gn:admin1_code":"7.0",
    "gn:asciiname":"Sen'ok",
    "gn:country_code":"UA",
    "gn:dem":122,
    "gn:feature_class":"P",
    "gn:feature_code":"PPL",
    "gn:name":"Sen\u2019ok",
    "gn:population":0,
    "gn:timezone":"Europe/Kiev",
    "iso:country":"UA",
    "name:ukr_x_preferred":[
        "Sen\u2019ok"
    ],
    "name:ukr_x_variant":[
        "\u0421\u0435\u043d\u044c\u043e\u043a"
    ],
    "name:und_x_variant":[
        "Zhikharevka"
    ],
    "wof:name":"Sen'ok",
    "wof:placetype":"locality"
},
  "geometry": {"coordinates":[37.52188,49.58676],"type":"Point"}
}