{
  "type": "Feature",
  "properties": {
    "gn:admin1_code":"5.0",
    "gn:asciiname":"Verkhne-Lozovyy",
    "gn:country_code":"UA",
    "gn:dem":300,
    "gn:feature_class":"P",
    "gn:feature_code":"PPL",
    "gn:name":"Verkhne-Lozovyy",
    "gn:population":0,
    "gn:timezone":"Europe/Kiev",
    "iso:country":"UA",
    "wof:name":"Verkhne-Lozovyy",
    "wof:placetype":"locality"
},
  "geometry": {"coordinates":[38.42222,48.39194000000001],"type":"Point"}
}