{
  "type": "Feature",
  "properties": {
    "gn:admin1_code":"13.0",
    "gn:asciiname":"Vytachiv",
    "gn:country_code":"UA",
    "gn:dem":141,
    "gn:feature_class":"P",
    "gn:feature_code":"PPL",
    "gn:name":"Vytachiv",
    "gn:population":816,
    "gn:timezone":"Europe/Kiev",
    "iso:country":"UA",
    "name:eng_x_preferred":[
        "Vitachov"
    ],
    "name:rus_x_preferred":[
        "\u0412\u0438\u0442\u0430\u0447\u043e\u0432"
    ],
    "name:und_x_variant":[
        "Vitach\u00ebv",
        "Vytachiv"
    ],
    "wof:name":"Vytachiv",
    "wof:placetype":"locality",
    "wof:population":816
},
  "geometry": {"coordinates":[30.8698,50.11436],"type":"Point"}
}