{
  "type": "Feature",
  "properties": {
    "iso:country":"UA",
    "name:bel_x_preferred":[
        "\u0421\u0442\u0430\u0440\u044b \u0411\u0456\u043b\u0430\u0432\u0443\u0441"
    ],
    "name:deu_x_preferred":[
        "Staryj Bilous"
    ],
    "name:eng_x_preferred":[
        "Staryi Bilous"
    ],
    "name:ron_x_preferred":[
        "Star\u00eei Bilous"
    ],
    "name:rus_x_preferred":[
        "\u0421\u0442\u0430\u0440\u044b\u0439 \u0411\u0435\u043b\u043e\u0443\u0441"
    ],
    "name:ukr_x_preferred":[
        "Staryy Bilous"
    ],
    "name:ukr_x_variant":[
        "\u0421\u0442\u0430\u0440\u0438\u0439 \u0411\u0456\u043b\u043e\u0443\u0441"
    ],
    "name:und_x_variant":[
        "Stary-Belous"
    ],
    "name:zho_x_preferred":[
        "\u820a\u6bd4\u6d1b\u70cf\u65af"
    ],
    "qs:a0":"\u0423\u043a\u0440\u0430\u0457\u043d\u0430",
    "qs:a1":"*\u0427\u0435\u0440\u043d\u0456\u0433\u0456\u0432\u0441\u044c\u043a\u0430",
    "qs:a1_alt":"Chernihivs'ka",
    "qs:a1r":"0",
    "qs:a2":"\u0427\u0435\u0440\u043d\u0456\u0433\u0456\u0432\u0441\u044c\u043a\u0438\u0439",
    "qs:a2_alt":"Chernihivs'kyi",
    "qs:adm0":"\u0423\u043a\u0440\u0430\u0457\u043d\u0430",
    "qs:la_lc":"*",
    "qs:level":"locality",
    "qs:loc":"\u0421\u0442\u0430\u0440\u0438\u0439 \u0411\u0456\u043b\u043e\u0443\u0441",
    "qs:loc_alt":"Staryi Bilous",
    "qs:pop":0,
    "qs:type":"buffered point",
    "wof:name":"\u0421\u0442\u0430\u0440\u0438\u0439 \u0411\u0456\u043b\u043e\u0443\u0441",
    "wof:placetype":"locality"
},
  "geometry": {"coordinates":[31.213879,51.488647],"type":"Point"}
}