{
  "type": "Feature",
  "properties": {
    "gn:admin1_code":"19.0",
    "gn:asciiname":"Tryputnya",
    "gn:country_code":"UA",
    "gn:dem":167,
    "gn:feature_class":"P",
    "gn:feature_code":"PPL",
    "gn:name":"Tryputnya",
    "gn:population":0,
    "gn:timezone":"Europe/Kiev",
    "iso:country":"UA",
    "name:ukr_x_preferred":[
        "Tryputnya"
    ],
    "name:ukr_x_variant":[
        "\u0422\u0440\u0438\u043f\u0443\u0442\u043d\u044f"
    ],
    "name:und_x_variant":[
        "Tryputna",
        "Triputnya"
    ],
    "wof:name":"Tryputnya",
    "wof:placetype":"locality"
},
  "geometry": {"coordinates":[26.3183,51.54691],"type":"Point"}
}