{
  "type": "Feature",
  "properties": {
    "gn:admin1_code":"23.0",
    "gn:asciiname":"Bugaivka",
    "gn:country_code":"UA",
    "gn:dem":200,
    "gn:feature_class":"P",
    "gn:feature_code":"PPL",
    "gn:name":"Bugaivka",
    "gn:population":0,
    "gn:timezone":"Europe/Kiev",
    "iso:country":"UA",
    "wof:name":"Bugaivka",
    "wof:placetype":"locality"
},
  "geometry": {"coordinates":[29.57186,49.31241],"type":"Point"}
}