{
  "type": "Feature",
  "properties": {
    "gn:admin1_code":"4.0",
    "gn:asciiname":"Zelene Pole",
    "gn:country_code":"UA",
    "gn:dem":109,
    "gn:feature_class":"P",
    "gn:feature_code":"PPL",
    "gn:name":"Zelene Pole",
    "gn:population":0,
    "gn:timezone":"Europe/Kiev",
    "iso:country":"UA",
    "name:rus_x_preferred":[
        "\u0417\u0435\u043b\u0435\u043d\u043e\u0435 \u041f\u043e\u043b\u0435"
    ],
    "name:ukr_x_preferred":[
        "Zelene Pole"
    ],
    "name:ukr_x_variant":[
        "\u0417\u0435\u043b\u0435\u043d\u0435 \u041f\u043e\u043b\u0435"
    ],
    "name:und_x_variant":[
        "Zyelyenoye Polye"
    ],
    "wof:name":"Zelene Pole",
    "wof:placetype":"locality"
},
  "geometry": {"coordinates":[33.63244,48.05816],"type":"Point"}
}