{
  "type": "Feature",
  "properties": {
    "gn:admin1_code":"16.0",
    "gn:asciiname":"Novopavlivs'ke",
    "gn:country_code":"UA",
    "gn:dem":30,
    "gn:feature_class":"P",
    "gn:feature_code":"PPL",
    "gn:name":"Novopavlivs\u2019ke",
    "gn:population":0,
    "gn:timezone":"Europe/Kiev",
    "iso:country":"UA",
    "name:ukr_x_preferred":[
        "Novopavlivs\u2019ke"
    ],
    "name:ukr_x_variant":[
        "\u041d\u043e\u0432\u043e\u043f\u0430\u0432\u043b\u0456\u0432\u0441\u044c\u043a\u0435"
    ],
    "wof:name":"Novopavlivs'ke",
    "wof:placetype":"locality"
},
  "geometry": {"coordinates":[32.90077,47.13397],"type":"Point"}
}