{
  "type": "Feature",
  "properties": {
    "gn:admin1_code":"15.0",
    "gn:asciiname":"Volitsa",
    "gn:cc2":"UA",
    "gn:country_code":"UA",
    "gn:dem":268,
    "gn:feature_class":"P",
    "gn:feature_code":"PPL",
    "gn:name":"Volitsa",
    "gn:population":0,
    "gn:timezone":"Europe/Kiev",
    "iso:country":"UA",
    "name:und_x_variant":[
        "Valitsa",
        "Volitsa"
    ],
    "wof:name":"Volitsa",
    "wof:placetype":"locality"
},
  "geometry": {"coordinates":[23.91667,49.36667],"type":"Point"}
}