{
  "type": "Feature",
  "properties": {
    "gn:admin1_code":"19.0",
    "gn:asciiname":"Tochevyky",
    "gn:country_code":"UA",
    "gn:dem":222,
    "gn:feature_class":"P",
    "gn:feature_code":"PPL",
    "gn:name":"Tochevyky",
    "gn:population":0,
    "gn:timezone":"Europe/Kiev",
    "iso:country":"UA",
    "name:ukr_x_preferred":[
        "Tochevyky"
    ],
    "name:ukr_x_variant":[
        "\u0422\u043e\u0447\u0435\u0432\u0438\u043a\u0438"
    ],
    "name:und_x_variant":[
        "Tocheviki"
    ],
    "wof:name":"Tochevyky",
    "wof:placetype":"locality"
},
  "geometry": {"coordinates":[26.3539,50.35038],"type":"Point"}
}