{
  "type": "Feature",
  "properties": {
    "gn:admin1_code":"14.0",
    "gn:asciiname":"Illinka",
    "gn:country_code":"UA",
    "gn:dem":200,
    "gn:feature_class":"P",
    "gn:feature_code":"PPL",
    "gn:name":"Illinka",
    "gn:population":0,
    "gn:timezone":"Europe/Zaporozhye",
    "iso:country":"UA",
    "name:rus_x_preferred":[
        "Il\u2019inka"
    ],
    "name:ukr_x_preferred":[
        "Illinka"
    ],
    "name:ukr_x_variant":[
        "\u0406\u043b\u043b\u0456\u043d\u043a\u0430"
    ],
    "wof:name":"Illinka",
    "wof:placetype":"locality"
},
  "geometry": {"coordinates":[39.22248,48.09143],"type":"Point"}
}