{
  "type": "Feature",
  "properties": {
    "gn:admin1_code":"26.0",
    "gn:asciiname":"Kulykivs'ke",
    "gn:country_code":"UA",
    "gn:dem":27,
    "gn:feature_class":"P",
    "gn:feature_code":"PPL",
    "gn:name":"Kulykivs\u2019ke",
    "gn:population":0,
    "gn:timezone":"Europe/Kiev",
    "iso:country":"UA",
    "name:ukr_x_preferred":[
        "Kulykivs\u2019ke"
    ],
    "name:ukr_x_variant":[
        "\u041a\u0443\u043b\u0438\u043a\u0456\u0432\u0441\u044c\u043a\u0435"
    ],
    "name:und_x_variant":[
        "Kulikovy",
        "Kulikovskoye"
    ],
    "wof:name":"Kulykivs'ke",
    "wof:placetype":"locality"
},
  "geometry": {"coordinates":[37.04511,46.88256],"type":"Point"}
}