{
  "type": "Feature",
  "properties": {
    "iso:country":"UA",
    "name:che_x_preferred":[
        "\u041f\u043e\u043a\u0440\u043e\u0432\u043a\u0430"
    ],
    "name:deu_x_preferred":[
        "Pokrowka"
    ],
    "name:eng_x_preferred":[
        "Pokrovka"
    ],
    "name:hye_x_preferred":[
        "\u054a\u0578\u056f\u0580\u0578\u057e\u056f\u0561"
    ],
    "name:lav_x_preferred":[
        "Pokrovka"
    ],
    "name:ron_x_preferred":[
        "Pokrovka"
    ],
    "name:rus_x_preferred":[
        "\u041f\u043e\u043a\u0440\u043e\u0432\u043a\u0430"
    ],
    "name:ukr_x_preferred":[
        "\u041f\u043e\u043a\u0440\u043e\u0432\u043a\u0430"
    ],
    "name:zho_x_preferred":[
        "\u6ce2\u514b\u7f85\u592b\u5361"
    ],
    "qs:a0":"\u0423\u043a\u0440\u0430\u0457\u043d\u0430",
    "qs:a1":"*\u041c\u0438\u043a\u043e\u043b\u0430\u0457\u0432\u0441\u044c\u043a\u0430",
    "qs:a1_alt":"Mykolaivs'ka",
    "qs:a1r":"0",
    "qs:a2":"\u041e\u0447\u0430\u043a\u0456\u0432\u0441\u044c\u043a\u0438\u0439",
    "qs:a2_alt":"Ochakivs'kyi",
    "qs:adm0":"\u0423\u043a\u0440\u0430\u0457\u043d\u0430",
    "qs:la_lc":"*",
    "qs:level":"locality",
    "qs:loc":"\u0406\u0432\u0430\u043d\u0456\u0432\u043a\u0430",
    "qs:loc_alt":"Ivanivka",
    "qs:pop":0,
    "qs:type":"buffered point",
    "wof:name":"\u0406\u0432\u0430\u043d\u0456\u0432\u043a\u0430",
    "wof:placetype":"locality"
},
  "geometry": {"coordinates":[31.671407,46.657605],"type":"Point"}
}