{
  "type": "Feature",
  "properties": {
    "gn:admin1_code":"11.0",
    "gn:asciiname":"Barsove",
    "gn:country_code":"UA",
    "gn:dem":8,
    "gn:feature_class":"P",
    "gn:feature_code":"PPL",
    "gn:name":"Barsove",
    "gn:population":0,
    "gn:timezone":"Europe/Simferopol",
    "iso:country":"UA",
    "name:ukr_x_preferred":[
        "Barsove"
    ],
    "name:ukr_x_variant":[
        "\u0411\u0430\u0440\u0441\u043e\u0432\u0435"
    ],
    "name:und_x_variant":[
        "Barasanovka",
        "Barsovo",
        "Barasonovka"
    ],
    "wof:name":"Barsove",
    "wof:placetype":"locality"
},
  "geometry": {"coordinates":[34.93543,45.48281],"type":"Point"}
}