{
  "type": "Feature",
  "properties": {
    "gn:admin1_code":"4.0",
    "gn:asciiname":"Dobrohirs'ke",
    "gn:country_code":"UA",
    "gn:dem":162,
    "gn:feature_class":"P",
    "gn:feature_code":"PPL",
    "gn:name":"Dobrohirs\u2019ke",
    "gn:population":0,
    "gn:timezone":"Europe/Kiev",
    "iso:country":"UA",
    "name:ukr_x_preferred":[
        "Dobrohirs\u2019ke"
    ],
    "name:ukr_x_variant":[
        "\u0414\u043e\u0431\u0440\u043e\u0433\u0456\u0440\u0441\u044c\u043a\u0435"
    ],
    "name:und_x_variant":[
        "Dobrogorskaya"
    ],
    "wof:name":"Dobrohirs'ke",
    "wof:placetype":"locality"
},
  "geometry": {"coordinates":[33.97883,48.50625],"type":"Point"}
}