{
  "type": "Feature",
  "properties": {
    "gn:admin1_code":"4.0",
    "gn:asciiname":"Blahodatne",
    "gn:country_code":"UA",
    "gn:dem":67,
    "gn:feature_class":"P",
    "gn:feature_code":"PPL",
    "gn:name":"Blahodatne",
    "gn:population":0,
    "gn:timezone":"Europe/Kiev",
    "iso:country":"UA",
    "name:ukr_x_preferred":[
        "Blahodatne"
    ],
    "name:ukr_x_variant":[
        "\u0411\u043b\u0430\u0433\u043e\u0434\u0430\u0442\u043d\u0435"
    ],
    "name:und_x_variant":[
        "Blagodatnaya"
    ],
    "wof:name":"Blahodatne",
    "wof:placetype":"locality"
},
  "geometry": {"coordinates":[34.20924,48.13238],"type":"Point"}
}