{
  "type": "Feature",
  "properties": {
    "gn:admin1_code":"15.0",
    "gn:asciiname":"Voloshchyna",
    "gn:country_code":"UA",
    "gn:dem":299,
    "gn:feature_class":"P",
    "gn:feature_code":"PPL",
    "gn:name":"Voloshchyna",
    "gn:population":0,
    "gn:timezone":"Europe/Kiev",
    "iso:country":"UA",
    "name:ukr_x_preferred":[
        "Voloshchyna"
    ],
    "name:ukr_x_variant":[
        "\u0412\u043e\u043b\u043e\u0449\u0438\u043d\u0430"
    ],
    "name:und_x_variant":[
        "Voloshchizna"
    ],
    "wof:name":"Voloshchyna",
    "wof:placetype":"locality"
},
  "geometry": {"coordinates":[24.22137,49.62312],"type":"Point"}
}