{
  "type": "Feature",
  "properties": {
    "gn:admin1_code":"5.0",
    "gn:admin2_code":"704417",
    "gn:asciiname":"Hryhorivka",
    "gn:country_code":"UA",
    "gn:dem":144,
    "gn:feature_class":"P",
    "gn:feature_code":"PPL",
    "gn:name":"Hryhorivka",
    "gn:population":0,
    "gn:timezone":"Europe/Kiev",
    "iso:country":"UA",
    "name:hye_x_preferred":[
        "\u0533\u0580\u0575\u0563\u0578\u0580\u056b\u057e\u056f\u0561"
    ],
    "name:jpn_x_preferred":[
        "\u30b0\u30ea\u30b4\u30ea\u30d5\u30ab"
    ],
    "name:kat_x_preferred":[
        "\u10d2\u10e0\u10d8\u10d2\u10dd\u10e0\u10d8\u10d5\u10d9\u10d0"
    ],
    "name:rus_x_historical":[
        "\u041b\u0435\u043d\u0438\u043d\u0441\u043a\u043e\u0435"
    ],
    "name:rus_x_preferred":[
        "\u0413\u0440\u0438\u0433\u043e\u0440\u044c\u0435\u0432\u043a\u0430"
    ],
    "name:rus_x_variant":[
        "\u041b\u0435\u043d\u0438\u043d\u0441\u043a\u043e\u0435"
    ],
    "name:ukr_x_historical":[
        "Lenins\u2019ke",
        "\u041b\u0435\u043d\u0456\u043d\u0441\u044c\u043a\u0435"
    ],
    "name:ukr_x_preferred":[
        "\u0413\u0440\u0438\u0433\u043e\u0440\u0456\u0432\u043a\u0430"
    ],
    "name:ukr_x_variant":[
        "Lenins\u2019ke",
        "\u041b\u0435\u043d\u0456\u043d\u0441\u044c\u043a\u0435"
    ],
    "name:und_x_variant":[
        "Hryhoriwka"
    ],
    "wof:name":"Hryhorivka",
    "wof:placetype":"locality"
},
  "geometry": {"coordinates":[37.23127,48.1634],"type":"Point"}
}