{
  "type": "Feature",
  "properties": {
    "gn:admin1_code":"7.0",
    "gn:asciiname":"Chervona Polyana",
    "gn:country_code":"UA",
    "gn:dem":129,
    "gn:feature_class":"P",
    "gn:feature_code":"PPL",
    "gn:name":"Chervona Polyana",
    "gn:population":0,
    "gn:timezone":"Europe/Kiev",
    "iso:country":"UA",
    "name:ukr_x_preferred":[
        "Chervona Polyana"
    ],
    "name:und_x_variant":[
        "Krasnaya Polyana"
    ],
    "wof:name":"Chervona Polyana",
    "wof:placetype":"locality"
},
  "geometry": {"coordinates":[37.18917,49.35722],"type":"Point"}
}