{
  "type": "Feature",
  "properties": {
    "gn:admin1_code":"24.0",
    "gn:asciiname":"Boholyuby",
    "gn:country_code":"UA",
    "gn:dem":200,
    "gn:feature_class":"P",
    "gn:feature_code":"PPL",
    "gn:name":"Boholyuby",
    "gn:population":0,
    "gn:timezone":"Europe/Kiev",
    "iso:country":"UA",
    "name:ukr_x_preferred":[
        "Boholyuby"
    ],
    "name:ukr_x_variant":[
        "\u0411\u043e\u0433\u043e\u043b\u044e\u0431\u0438"
    ],
    "name:und_x_variant":[
        "Pershotravnevoye"
    ],
    "wof:name":"Boholyuby",
    "wof:placetype":"locality"
},
  "geometry": {"coordinates":[25.24022,50.76645],"type":"Point"}
}