{
  "type": "Feature",
  "properties": {
    "gn:admin1_code":"19.0",
    "gn:asciiname":"Dert'",
    "gn:country_code":"UA",
    "gn:dem":191,
    "gn:feature_class":"P",
    "gn:feature_code":"PPL",
    "gn:name":"Dert\u2019",
    "gn:population":0,
    "gn:timezone":"Europe/Kiev",
    "iso:country":"UA",
    "name:ukr_x_preferred":[
        "Dert\u2019"
    ],
    "name:ukr_x_variant":[
        "\u0414\u0435\u0440\u0442\u044c"
    ],
    "wof:name":"Dert'",
    "wof:placetype":"locality"
},
  "geometry": {"coordinates":[27.33376,51.20872],"type":"Point"}
}