{
  "type": "Feature",
  "properties": {
    "gn:admin1_code":"7.0",
    "gn:asciiname":"Tymofiyivka",
    "gn:country_code":"UA",
    "gn:dem":200,
    "gn:feature_class":"P",
    "gn:feature_code":"PPL",
    "gn:name":"Tymofiyivka",
    "gn:population":0,
    "gn:timezone":"Europe/Kiev",
    "iso:country":"UA",
    "name:ukr_x_preferred":[
        "Tymofiyivka"
    ],
    "name:ukr_x_variant":[
        "\u0422\u0438\u043c\u043e\u0444\u0456\u0457\u0432\u043a\u0430"
    ],
    "wof:name":"Tymofiyivka",
    "wof:placetype":"locality"
},
  "geometry": {"coordinates":[35.78972,50.35744],"type":"Point"}
}