{
  "type": "Feature",
  "properties": {
    "gn:admin1_code":"26.0",
    "gn:asciiname":"Dzhekel'nya",
    "gn:country_code":"UA",
    "gn:dem":16,
    "gn:feature_class":"P",
    "gn:feature_code":"PPL",
    "gn:name":"Dzhekel\u2019nya",
    "gn:population":0,
    "gn:timezone":"Europe/Zaporozhye",
    "iso:country":"UA",
    "name:und_x_variant":[
        "Pos\u00eblok Nomer Pervyy",
        "Dzhegel\u2019na",
        "Dzhekel\u2019nya"
    ],
    "wof:name":"Dzhekel'nya",
    "wof:placetype":"locality"
},
  "geometry": {"coordinates":[35.46667,46.73333],"type":"Point"}
}