{
  "type": "Feature",
  "properties": {
    "gn:admin1_code":"23.0",
    "gn:asciiname":"Zakhar'yashevka",
    "gn:country_code":"UA",
    "gn:dem":253,
    "gn:feature_class":"P",
    "gn:feature_code":"PPL",
    "gn:name":"Zakhar\u2019yashevka",
    "gn:population":0,
    "gn:timezone":"Europe/Kiev",
    "iso:country":"UA",
    "wof:name":"Zakhar'yashevka",
    "wof:placetype":"locality"
},
  "geometry": {"coordinates":[28.95,48.73333],"type":"Point"}
}