{
  "type": "Feature",
  "properties": {
    "gn:admin1_code":"15.0",
    "gn:asciiname":"Boyovichi",
    "gn:country_code":"UA",
    "gn:dem":231,
    "gn:feature_class":"P",
    "gn:feature_code":"PPL",
    "gn:name":"Boyovichi",
    "gn:population":0,
    "gn:timezone":"Europe/Kiev",
    "iso:country":"UA",
    "name:und_x_variant":[
        "Boyevichi",
        "Boyevitse",
        "Boyovichi"
    ],
    "wof:name":"Boyovichi",
    "wof:placetype":"locality"
},
  "geometry": {"coordinates":[22.98652,49.72359],"type":"Point"}
}