{
  "type": "Feature",
  "properties": {
    "gn:admin1_code":"5.0",
    "gn:asciiname":"Mazanivka",
    "gn:country_code":"UA",
    "gn:dem":158,
    "gn:feature_class":"P",
    "gn:feature_code":"PPL",
    "gn:name":"Mazanivka",
    "gn:population":0,
    "gn:timezone":"Europe/Kiev",
    "iso:country":"UA",
    "name:ukr_x_preferred":[
        "Mazanivka"
    ],
    "name:ukr_x_variant":[
        "\u041c\u0430\u0437\u0430\u043d\u0456\u0432\u043a\u0430"
    ],
    "wof:name":"Mazanivka",
    "wof:placetype":"locality"
},
  "geometry": {"coordinates":[37.35443,48.99279],"type":"Point"}
}