{
  "type": "Feature",
  "properties": {
    "gn:admin1_code":"11.0",
    "gn:admin2_code":"694905",
    "gn:admin3_code":"11153107",
    "gn:asciiname":"Zheltokamenka",
    "gn:country_code":"UA",
    "gn:dem":24,
    "gn:elevation":"20.0",
    "gn:feature_class":"P",
    "gn:feature_code":"PPL",
    "gn:name":"Zheltokamenka",
    "gn:population":428,
    "gn:timezone":"Europe/Simferopol",
    "iso:country":"UA",
    "name:eng_x_preferred":[
        "Zheltokamenka"
    ],
    "name:rus_x_historical":[
        "\u041e\u0440\u0442\u0430\u0301-\u041c\u0430\u043c\u0430\u0301\u0439 \u2116 4"
    ],
    "name:rus_x_preferred":[
        "\u0416\u0435\u043b\u0442\u043e\u043a\u0430\u043c\u0435\u043d\u043a\u0430"
    ],
    "name:rus_x_variant":[
        "\u041e\u0440\u0442\u0430\u0301-\u041c\u0430\u043c\u0430\u0301\u0439 \u2116 4"
    ],
    "name:ukr_x_preferred":[
        "\u0416\u043e\u0432\u0442\u043e\u043a\u0430\u043c\u2019\u044f\u043d\u043a\u0430"
    ],
    "wof:name":"Zheltokamenka",
    "wof:placetype":"locality",
    "wof:population":428
},
  "geometry": {"coordinates":[33.45146,45.27335],"type":"Point"}
}