{
  "type": "Feature",
  "properties": {
    "gn:admin1_code":"21.0",
    "gn:asciiname":"Muraveynya",
    "gn:country_code":"UA",
    "gn:dem":192,
    "gn:feature_class":"P",
    "gn:feature_code":"PPL",
    "gn:name":"Muraveynya",
    "gn:population":0,
    "gn:timezone":"Europe/Kiev",
    "iso:country":"UA",
    "name:ukr_x_preferred":[
        "\u041c\u0443\u0440\u0430\u0432\u0435\u0439\u043d\u044f"
    ],
    "name:und_x_variant":[
        "Muraveyka",
        "Muraveyna",
        "Muraveynya"
    ],
    "wof:name":"Muraveynya",
    "wof:placetype":"locality"
},
  "geometry": {"coordinates":[34.19751,51.90608],"type":"Point"}
}