{
  "type": "Feature",
  "properties": {
    "iso:country":"UA",
    "qs:a0":"\u0423\u043a\u0440\u0430\u0457\u043d\u0430",
    "qs:a1":"*\u041a\u0438\u0457\u0432\u0441\u044c\u043a\u0430",
    "qs:a1_alt":"Kyivs'ka",
    "qs:a1r":"0",
    "qs:a2":"\u0411\u0456\u043b\u043e\u0446\u0435\u0440\u043a\u0456\u0432\u0441\u044c\u043a\u0438\u0439",
    "qs:a2_alt":"Bilotserkivs'kyi",
    "qs:adm0":"\u0423\u043a\u0440\u0430\u0457\u043d\u0430",
    "qs:la_lc":"*",
    "qs:level":"locality",
    "qs:loc":"\u0422\u0440\u0443\u0448\u043a\u0438",
    "qs:loc_alt":"Trushky",
    "qs:pop":0,
    "qs:type":"buffered point",
    "wof:name":"\u0422\u0440\u0443\u0448\u043a\u0438",
    "wof:placetype":"locality"
},
  "geometry": {"coordinates":[29.954225,49.756364],"type":"Point"}
}