{
  "type": "Feature",
  "properties": {
    "gn:admin1_code":"5.0",
    "gn:asciiname":"Timofeyevka",
    "gn:country_code":"UA",
    "gn:dem":222,
    "gn:feature_class":"P",
    "gn:feature_code":"PPL",
    "gn:name":"Timofeyevka",
    "gn:population":0,
    "gn:timezone":"Europe/Kiev",
    "iso:country":"UA",
    "name:und_x_variant":[
        "Greko-Timofeyevskiy",
        "Grekov-Timofeyevka",
        "Timofeyevka"
    ],
    "wof:name":"Timofeyevka",
    "wof:placetype":"locality"
},
  "geometry": {"coordinates":[38.55386,48.1975],"type":"Point"}
}