{
  "type": "Feature",
  "properties": {
    "gn:admin1_code":"14.0",
    "gn:asciiname":"Tsarivka",
    "gn:country_code":"UA",
    "gn:dem":48,
    "gn:feature_class":"P",
    "gn:feature_code":"PPL",
    "gn:name":"Tsarivka",
    "gn:population":0,
    "gn:timezone":"Europe/Zaporozhye",
    "iso:country":"UA",
    "name:rus_x_preferred":[
        "Tsar\u00ebvka"
    ],
    "name:ukr_x_preferred":[
        "Tsarivka"
    ],
    "name:ukr_x_variant":[
        "\u0426\u0430\u0440\u0456\u0432\u043a\u0430"
    ],
    "wof:name":"Tsarivka",
    "wof:placetype":"locality"
},
  "geometry": {"coordinates":[39.05808,48.88571],"type":"Point"}
}