{
  "type": "Feature",
  "properties": {
    "gn:admin1_code":"4.0",
    "gn:asciiname":"Tarasivka",
    "gn:country_code":"UA",
    "gn:dem":157,
    "gn:feature_class":"P",
    "gn:feature_code":"PPL",
    "gn:name":"Tarasivka",
    "gn:population":0,
    "gn:timezone":"Europe/Kiev",
    "iso:country":"UA",
    "name:ukr_x_preferred":[
        "Tarasivka"
    ],
    "name:ukr_x_variant":[
        "\u0422\u0430\u0440\u0430\u0441\u0456\u0432\u043a\u0430"
    ],
    "name:und_x_variant":[
        "Tarasovka"
    ],
    "wof:name":"Tarasivka",
    "wof:placetype":"locality"
},
  "geometry": {"coordinates":[36.58887,48.18381],"type":"Point"}
}