{
  "type": "Feature",
  "properties": {
    "gn:admin1_code":"7.0",
    "gn:asciiname":"Mykhaylivka",
    "gn:country_code":"UA",
    "gn:dem":160,
    "gn:feature_class":"P",
    "gn:feature_code":"PPL",
    "gn:name":"Mykhaylivka",
    "gn:population":0,
    "gn:timezone":"Europe/Kiev",
    "iso:country":"UA",
    "name:ukr_x_preferred":[
        "Mykhaylivka"
    ],
    "name:ukr_x_variant":[
        "\u041c\u0438\u0445\u0430\u0439\u043b\u0456\u0432\u043a\u0430"
    ],
    "name:und_x_variant":[
        "Mikhaylovka"
    ],
    "wof:name":"Mykhaylivka",
    "wof:placetype":"locality"
},
  "geometry": {"coordinates":[36.5281,50.07772],"type":"Point"}
}