{
  "type": "Feature",
  "properties": {
    "iso:country":"UA",
    "name:eng_x_preferred":[
        "Klimovka"
    ],
    "name:rus_x_preferred":[
        "\u041a\u043b\u0438\u043c\u043e\u0432\u043a\u0430"
    ],
    "name:ukr_x_preferred":[
        "Klymivka"
    ],
    "name:ukr_x_variant":[
        "\u041a\u043b\u0438\u043c\u0456\u0432\u043a\u0430"
    ],
    "qs:a0":"\u0423\u043a\u0440\u0430\u0457\u043d\u0430",
    "qs:a1":"*\u041f\u043e\u043b\u0442\u0430\u0432\u0441\u044c\u043a\u0430",
    "qs:a1_alt":"Poltavs'ka",
    "qs:a1r":"0",
    "qs:a2":"\u041a\u0430\u0440\u043b\u0456\u0432\u0441\u044c\u043a\u0438\u0439",
    "qs:a2_alt":"Karlivs'kyi",
    "qs:adm0":"\u0423\u043a\u0440\u0430\u0457\u043d\u0430",
    "qs:la_lc":"*",
    "qs:level":"locality",
    "qs:loc":"\u041a\u043b\u0438\u043c\u0456\u0432\u043a\u0430",
    "qs:loc_alt":"Klymivka",
    "qs:pop":0,
    "qs:type":"buffered point",
    "wof:name":"\u041a\u043b\u0438\u043c\u0456\u0432\u043a\u0430",
    "wof:placetype":"locality"
},
  "geometry": {"coordinates":[35.123008,49.333329],"type":"Point"}
}