{
  "type": "Feature",
  "properties": {
    "gn:admin1_code":"9.0",
    "gn:asciiname":"Chernelivtsy",
    "gn:country_code":"UA",
    "gn:dem":327,
    "gn:feature_class":"P",
    "gn:feature_code":"PPL",
    "gn:name":"Chernelivtsy",
    "gn:population":0,
    "gn:timezone":"Europe/Kiev",
    "iso:country":"UA",
    "name:und_x_variant":[
        "Chernilivtsy",
        "Chernelivtsy"
    ],
    "wof:name":"Chernelivtsy",
    "wof:placetype":"locality"
},
  "geometry": {"coordinates":[27.80727000000001,49.20458],"type":"Point"}
}