{
  "type": "Feature",
  "properties": {
    "gn:admin1_code":"17.0",
    "gn:asciiname":"Nove",
    "gn:country_code":"UA",
    "gn:dem":57,
    "gn:feature_class":"P",
    "gn:feature_code":"PPL",
    "gn:name":"Nove",
    "gn:population":0,
    "gn:timezone":"Europe/Kiev",
    "iso:country":"UA",
    "name:rus_x_preferred":[
        "\u041d\u043e\u0432\u0435"
    ],
    "name:ukr_x_preferred":[
        "\u041d\u043e\u0432\u0435"
    ],
    "name:ukr_x_variant":[
        "Nove"
    ],
    "name:und_x_variant":[
        "Novoye",
        "Novo Naksiya"
    ],
    "wof:name":"Nove",
    "wof:placetype":"locality"
},
  "geometry": {"coordinates":[29.86934,46.8876],"type":"Point"}
}