{
  "type": "Feature",
  "properties": {
    "gn:admin1_code":"26.0",
    "gn:asciiname":"Fedorivka",
    "gn:country_code":"UA",
    "gn:dem":22,
    "gn:feature_class":"P",
    "gn:feature_code":"PPL",
    "gn:name":"Fedorivka",
    "gn:population":0,
    "gn:timezone":"Europe/Zaporozhye",
    "iso:country":"UA",
    "name:rus_x_preferred":[
        "\u0424\u0435\u0434\u043e\u0440\u0456\u0432\u043a\u0430"
    ],
    "name:ukr_x_preferred":[
        "\u0424\u0435\u0434\u043e\u0440\u0456\u0432\u043a\u0430"
    ],
    "name:und_x_variant":[
        "Planchik",
        "F\u00ebdorovka",
        "Fedorivka"
    ],
    "wof:name":"Fedorivka",
    "wof:placetype":"locality"
},
  "geometry": {"coordinates":[35.7917,46.78712],"type":"Point"}
}