{
  "type": "Feature",
  "properties": {
    "gn:admin1_code":"7.0",
    "gn:asciiname":"Stepova Novoselivka",
    "gn:country_code":"UA",
    "gn:dem":141,
    "gn:feature_class":"P",
    "gn:feature_code":"PPL",
    "gn:name":"Stepova Novoselivka",
    "gn:population":0,
    "gn:timezone":"Europe/Kiev",
    "iso:country":"UA",
    "name:ukr_x_preferred":[
        "Stepova Novoselivka"
    ],
    "name:ukr_x_variant":[
        "\u0421\u0442\u0435\u043f\u043e\u0432\u0430 \u041d\u043e\u0432\u043e\u0441\u0435\u043b\u0456\u0432\u043a\u0430"
    ],
    "name:und_x_variant":[
        "Gorodskoy"
    ],
    "wof:name":"Stepova Novoselivka",
    "wof:placetype":"locality"
},
  "geometry": {"coordinates":[37.86216,49.65976],"type":"Point"}
}