{
  "type": "Feature",
  "properties": {
    "gn:admin1_code":"7.0",
    "gn:asciiname":"Khyzhnyakove",
    "gn:country_code":"UA",
    "gn:dem":181,
    "gn:feature_class":"P",
    "gn:feature_code":"PPL",
    "gn:name":"Khyzhnyakove",
    "gn:population":0,
    "gn:timezone":"Europe/Kiev",
    "iso:country":"UA",
    "name:rus_x_preferred":[
        "\u0425\u0438\u0436\u043d\u044f\u043a\u043e\u0432\u043e"
    ],
    "name:ukr_x_preferred":[
        "Khyzhnyakove"
    ],
    "name:ukr_x_variant":[
        "\u0425\u0438\u0436\u043d\u044f\u043a\u043e\u0432\u0435"
    ],
    "name:und_x_variant":[
        "Khizhnyakovo",
        "Khizhnyakov"
    ],
    "wof:name":"Khyzhnyakove",
    "wof:placetype":"locality"
},
  "geometry": {"coordinates":[37.46027,50.31197],"type":"Point"}
}