{
  "type": "Feature",
  "properties": {
    "gn:admin1_code":"21.0",
    "gn:asciiname":"Guschtschi",
    "gn:country_code":"UA",
    "gn:dem":135,
    "gn:feature_class":"P",
    "gn:feature_code":"PPL",
    "gn:name":"Guschtschi",
    "gn:population":0,
    "gn:timezone":"Europe/Kiev",
    "iso:country":"UA",
    "name:rus_x_preferred":[
        "\u0413\u0440\u0443\u0437\u043a\u0438\u0439"
    ],
    "wof:name":"Guschtschi",
    "wof:placetype":"locality"
},
  "geometry": {"coordinates":[34.15375,50.52227],"type":"Point"}
}