{
  "type": "Feature",
  "properties": {
    "gn:admin1_code":"11.0",
    "gn:admin2_code":"8449688",
    "gn:asciiname":"Rozovy",
    "gn:country_code":"UA",
    "gn:dem":304,
    "gn:elevation":"299.0",
    "gn:feature_class":"P",
    "gn:feature_code":"PPL",
    "gn:name":"Rozovy",
    "gn:population":227,
    "gn:timezone":"Europe/Simferopol",
    "iso:country":"UA",
    "name:eng_x_preferred":[
        "Rozovy"
    ],
    "name:rus_x_preferred":[
        "\u0420\u043e\u0437\u043e\u0432\u044b\u0439"
    ],
    "name:ukr_x_preferred":[
        "\u0420\u043e\u0437\u043e\u0432\u0438\u0439"
    ],
    "wof:name":"Rozovy",
    "wof:placetype":"locality",
    "wof:population":227
},
  "geometry": {"coordinates":[34.32167,44.69624],"type":"Point"}
}