{
  "type": "Feature",
  "properties": {
    "gn:admin1_code":"19.0",
    "gn:asciiname":"Zagrebl'ye",
    "gn:country_code":"UA",
    "gn:dem":221,
    "gn:feature_class":"P",
    "gn:feature_code":"PPL",
    "gn:name":"Zagrebl\u2019ye",
    "gn:population":0,
    "gn:timezone":"Europe/Kiev",
    "iso:country":"UA",
    "name:und_x_variant":[
        "Zagreblya",
        "Zagrebl\u2019ye"
    ],
    "wof:name":"Zagrebl'ye",
    "wof:placetype":"locality"
},
  "geometry": {"coordinates":[26.29123,50.1809],"type":"Point"}
}