{
  "type": "Feature",
  "properties": {
    "gn:admin1_code":"26.0",
    "gn:asciiname":"Myrne",
    "gn:country_code":"UA",
    "gn:dem":68,
    "gn:feature_class":"P",
    "gn:feature_code":"PPL",
    "gn:name":"Myrne",
    "gn:population":0,
    "gn:timezone":"Europe/Zaporozhye",
    "iso:country":"UA",
    "name:ukr_x_preferred":[
        "Myrne"
    ],
    "name:ukr_x_variant":[
        "\u041c\u0438\u0440\u043d\u0435"
    ],
    "name:und_x_variant":[
        "Mirnoye"
    ],
    "wof:name":"Myrne",
    "wof:placetype":"locality"
},
  "geometry": {"coordinates":[35.44348,46.94796],"type":"Point"}
}