{
  "type": "Feature",
  "properties": {
    "gn:admin1_code":"10.0",
    "gn:asciiname":"Shevchenka",
    "gn:country_code":"UA",
    "gn:dem":128,
    "gn:feature_class":"P",
    "gn:feature_code":"PPL",
    "gn:name":"Shevchenka",
    "gn:population":0,
    "gn:timezone":"Europe/Kiev",
    "iso:country":"UA",
    "name:ukr_x_preferred":[
        "Shevchenka"
    ],
    "name:ukr_x_variant":[
        "\u0428\u0435\u0432\u0447\u0435\u043d\u043a\u0430"
    ],
    "wof:name":"Shevchenka",
    "wof:placetype":"locality"
},
  "geometry": {"coordinates":[33.26781,48.88016],"type":"Point"}
}