{
  "type": "Feature",
  "properties": {
    "gn:admin1_code":"21.0",
    "gn:asciiname":"Pyrotchyne",
    "gn:country_code":"UA",
    "gn:dem":152,
    "gn:feature_class":"P",
    "gn:feature_code":"PPL",
    "gn:name":"Pyrotchyne",
    "gn:population":0,
    "gn:timezone":"Europe/Kiev",
    "iso:country":"UA",
    "name:ukr_x_preferred":[
        "Pyrotchyne"
    ],
    "name:ukr_x_variant":[
        "\u041f\u0438\u0440\u043e\u0442\u0447\u0438\u043d\u0435"
    ],
    "name:und_x_variant":[
        "Pirotchino"
    ],
    "wof:name":"Pyrotchyne",
    "wof:placetype":"locality"
},
  "geometry": {"coordinates":[33.43767,51.71611],"type":"Point"}
}