{
  "type": "Feature",
  "properties": {
    "gn:admin1_code":"2.0",
    "gn:asciiname":"Shumany",
    "gn:country_code":"UA",
    "gn:dem":153,
    "gn:feature_class":"P",
    "gn:feature_code":"PPL",
    "gn:name":"Shumany",
    "gn:population":0,
    "gn:timezone":"Europe/Kiev",
    "iso:country":"UA",
    "name:ukr_x_preferred":[
        "Shumany"
    ],
    "name:ukr_x_variant":[
        "\u0428\u0443\u043c\u0430\u043d\u0438"
    ],
    "wof:name":"Shumany",
    "wof:placetype":"locality"
},
  "geometry": {"coordinates":[30.8582,51.65924],"type":"Point"}
}