{
  "type": "Feature",
  "properties": {
    "gn:admin1_code":"21.0",
    "gn:asciiname":"Kalynivka",
    "gn:country_code":"UA",
    "gn:dem":154,
    "gn:feature_class":"P",
    "gn:feature_code":"PPL",
    "gn:name":"Kalynivka",
    "gn:population":0,
    "gn:timezone":"Europe/Kiev",
    "iso:country":"UA",
    "name:rus_x_preferred":[
        "Komsomol\u2019skaya Kommuna"
    ],
    "name:ukr_x_preferred":[
        "Komsomol\u2019s\u2019ka Komuna"
    ],
    "name:ukr_x_variant":[
        "\u041a\u043e\u043c\u0441\u043e\u043c\u043e\u043b\u044c\u0441\u044c\u043a\u0430 \u041a\u043e\u043c\u0443\u043d\u0430",
        "Kalynivka",
        "\u041a\u0430\u043b\u0438\u043d\u0456\u0432\u043a\u0430"
    ],
    "wof:name":"Kalynivka",
    "wof:placetype":"locality"
},
  "geometry": {"coordinates":[33.25403,51.20172],"type":"Point"}
}