{
  "type": "Feature",
  "properties": {
    "gn:admin1_code":"2.0",
    "gn:asciiname":"Berezanka",
    "gn:country_code":"UA",
    "gn:dem":127,
    "gn:feature_class":"P",
    "gn:feature_code":"PPL",
    "gn:name":"Berezanka",
    "gn:population":0,
    "gn:timezone":"Europe/Kiev",
    "iso:country":"UA",
    "name:ara_x_preferred":[
        "\u0628\u064a\u0631\u064a\u0632\u0627\u0646\u0643\u0627"
    ],
    "name:bel_x_preferred":[
        "\u0411\u044d\u0440\u044d\u0437\u0430\u043d\u043a\u0430"
    ],
    "name:bul_x_preferred":[
        "\u0411\u0435\u0440\u0435\u0437\u0430\u043d\u043a\u0430"
    ],
    "name:ceb_x_preferred":[
        "Berezanka"
    ],
    "name:crh_x_preferred":[
        "Berezanka"
    ],
    "name:deu_x_preferred":[
        "Beresanka"
    ],
    "name:hye_x_preferred":[
        "\u0532\u0565\u0580\u0565\u0566\u0561\u0576\u056f\u0561"
    ],
    "name:pol_x_preferred":[
        "Berezanka"
    ],
    "name:ron_x_preferred":[
        "Berezanka"
    ],
    "name:rus_x_preferred":[
        "\u0411\u0435\u0440\u0435\u0437\u0430\u043d\u043a\u0430"
    ],
    "name:ukr_x_preferred":[
        "Berezanka"
    ],
    "name:ukr_x_variant":[
        "\u0411\u0435\u0440\u0435\u0437\u0430\u043d\u043a\u0430"
    ],
    "name:zho_x_preferred":[
        "\u5225\u5217\u8d0a\u5361"
    ],
    "wof:name":"Berezanka",
    "wof:placetype":"locality"
},
  "geometry": {"coordinates":[31.97646,51.09915],"type":"Point"}
}