{
  "type": "Feature",
  "properties": {
    "gn:admin1_code":"2.0",
    "gn:asciiname":"Berezanka",
    "gn:country_code":"UA",
    "gn:dem":127,
    "gn:feature_class":"P",
    "gn:feature_code":"PPL",
    "gn:name":"Berezanka",
    "gn:population":0,
    "gn:timezone":"Europe/Kiev",
    "iso:country":"UA",
    "name:ukr_x_preferred":[
        "Berezanka"
    ],
    "name:ukr_x_variant":[
        "\u0411\u0435\u0440\u0435\u0437\u0430\u043d\u043a\u0430"
    ],
    "wof:name":"Berezanka",
    "wof:placetype":"locality"
},
  "geometry": {"coordinates":[31.97646,51.09915],"type":"Point"}
}