{
  "type": "Feature",
  "properties": {
    "gn:admin1_code":"2.0",
    "gn:asciiname":"Hladke",
    "gn:country_code":"UA",
    "gn:dem":116,
    "gn:feature_class":"P",
    "gn:feature_code":"PPL",
    "gn:name":"Hladke",
    "gn:population":0,
    "gn:timezone":"Europe/Kiev",
    "iso:country":"UA",
    "name:ukr_x_preferred":[
        "\u0413\u043b\u0430\u0434\u043a\u0435"
    ],
    "name:und_x_variant":[
        "Smorshki",
        "Gladki",
        "Hladke",
        "Gladkoye"
    ],
    "wof:name":"Hladke",
    "wof:placetype":"locality"
},
  "geometry": {"coordinates":[31.19578,51.0107],"type":"Point"}
}