{
  "type": "Feature",
  "properties": {
    "gn:admin1_code":"4.0",
    "gn:asciiname":"Skotuvate",
    "gn:country_code":"UA",
    "gn:dem":111,
    "gn:feature_class":"P",
    "gn:feature_code":"PPL",
    "gn:name":"Skotuvate",
    "gn:population":0,
    "gn:timezone":"Europe/Kiev",
    "iso:country":"UA",
    "name:ukr_x_preferred":[
        "Skotuvate"
    ],
    "name:ukr_x_variant":[
        "\u0421\u043a\u043e\u0442\u0443\u0432\u0430\u0442\u0435"
    ],
    "name:und_x_variant":[
        "Skotovatoye"
    ],
    "wof:name":"Skotuvate",
    "wof:placetype":"locality"
},
  "geometry": {"coordinates":[35.18647,48.72133],"type":"Point"}
}