{
  "type": "Feature",
  "properties": {
    "gn:admin1_code":"16.0",
    "gn:asciiname":"Vinogradnyy Sad",
    "gn:country_code":"UA",
    "gn:dem":46,
    "gn:feature_class":"P",
    "gn:feature_code":"PPL",
    "gn:name":"Vinogradnyy Sad",
    "gn:population":0,
    "gn:timezone":"Europe/Kiev",
    "iso:country":"UA",
    "name:und_x_variant":[
        "Khutor Vinogradnyy Sad",
        "Vinogradnyy Sad"
    ],
    "wof:name":"Vinogradnyy Sad",
    "wof:placetype":"locality"
},
  "geometry": {"coordinates":[31.17466,47.76123],"type":"Point"}
}