{
  "type": "Feature",
  "properties": {
    "gn:admin1_code":"26.0",
    "gn:asciiname":"Marynopil'",
    "gn:country_code":"UA",
    "gn:dem":184,
    "gn:feature_class":"P",
    "gn:feature_code":"PPL",
    "gn:name":"Marynopil\u2019",
    "gn:population":0,
    "gn:timezone":"Europe/Zaporozhye",
    "iso:country":"UA",
    "name:ukr_x_preferred":[
        "Marynopil\u2019"
    ],
    "name:ukr_x_variant":[
        "\u041c\u0430\u0440\u0438\u043d\u043e\u043f\u0456\u043b\u044c"
    ],
    "name:und_x_variant":[
        "Marinopol\u2019 Nomer Dvadtsat\u2019 Shestoy"
    ],
    "wof:name":"Marynopil'",
    "wof:placetype":"locality"
},
  "geometry": {"coordinates":[36.84464000000001,47.49706],"type":"Point"}
}