{
  "type": "Feature",
  "properties": {
    "gn:admin1_code":"16.0",
    "gn:asciiname":"Starosoldatskiy",
    "gn:country_code":"UA",
    "gn:dem":81,
    "gn:feature_class":"P",
    "gn:feature_code":"PPL",
    "gn:name":"Starosoldatskiy",
    "gn:population":0,
    "gn:timezone":"Europe/Kiev",
    "iso:country":"UA",
    "name:und_x_variant":[
        "Staro-Soldatskoye",
        "Starosoldatskiy"
    ],
    "wof:name":"Starosoldatskiy",
    "wof:placetype":"locality"
},
  "geometry": {"coordinates":[32.5519,47.38975],"type":"Point"}
}