{
  "type": "Feature",
  "properties": {
    "gn:gn_country":"UA",
    "gn:gn_fcode":"PPL",
    "gn:gn_pop":5162,
    "gn:population":5162,
    "iso:country":"UA",
    "name:bul_x_preferred":[
        "\u041e\u0437\u0435\u0440\u043d\u043e\u0435"
    ],
    "name:ceb_x_preferred":[
        "Ozerne"
    ],
    "name:deu_x_preferred":[
        "Oserne"
    ],
    "name:ell_x_preferred":[
        "\u039f\u03b6\u03ad\u03c1\u03bd\u03b5"
    ],
    "name:eng_x_preferred":[
        "Ozerne"
    ],
    "name:heb_x_preferred":[
        "\u05d0\u05d5\u05d6\u05e8\u05e0\u05d4"
    ],
    "name:lav_x_preferred":[
        "Ozerne"
    ],
    "name:ron_x_preferred":[
        "Babele"
    ],
    "name:rus_x_preferred":[
        "\u041e\u0437\u0435\u0440\u043d\u0435"
    ],
    "name:rus_x_variant":[
        "\u041e\u0437\u0451\u0440\u043d\u043e\u0435"
    ],
    "name:spa_x_preferred":[
        "Ozerne"
    ],
    "name:ukr_x_preferred":[
        "\u041e\u0437\u0435\u0440\u043d\u0435"
    ],
    "name:unk_x_variant":[
        "General-Averesku"
    ],
    "qs_pg:aaroncc":"UA",
    "qs_pg:gn_country":"UA",
    "qs_pg:gn_fcode":"PPL",
    "qs_pg:gn_pop":5162,
    "qs_pg:name":"Ozerne",
    "qs_pg:photos_9r":0,
    "qs_pg:photos_sr":0,
    "qs_pg:pop_sr":5,
    "qs_pg:qs_pg_placetype":"locality",
    "wof:name":"Ozerne",
    "wof:placetype":"locality",
    "wof:population":5162
},
  "geometry": {"coordinates":[28.67546,45.403],"type":"Point"}
}