{
  "type": "Feature",
  "properties": {
    "iso:country":"UA",
    "name:ukr_x_preferred":[
        "\u0422\u0440\u0430\u043d\u0441\u043b\u0456\u0442\u0435\u0440\u0430\u0446\u0456\u044f"
    ],
    "name:ukr_x_variant":[
        "Zhezheliv",
        "\u0416\u0435\u0436\u0435\u043b\u0456\u0432"
    ],
    "name:unk_x_variant":[
        "Zhezhelevo"
    ],
    "qs:a0":"\u0423\u043a\u0440\u0430\u0457\u043d\u0430",
    "qs:a1":"*\u0412\u0456\u043d\u043d\u0438\u0446\u044c\u043a\u0430",
    "qs:a1_alt":"Vinnyts'ka",
    "qs:a1r":"0",
    "qs:a2":"\u041a\u043e\u0437\u044f\u0442\u0438\u043d\u0441\u044c\u043a\u0438\u0439",
    "qs:a2_alt":"Koziatyns'kyi",
    "qs:adm0":"\u0423\u043a\u0440\u0430\u0457\u043d\u0430",
    "qs:la_lc":"*",
    "qs:level":"locality",
    "qs:loc":"\u0416\u0435\u0436\u0435\u043b\u0456\u0432",
    "qs:loc_alt":"Zhezheliv",
    "qs:pop":0,
    "qs:type":"buffered point",
    "wd:wordcount":359,
    "wof:name":"\u0416\u0435\u0436\u0435\u043b\u0456\u0432",
    "wof:placetype":"locality"
},
  "geometry": {"coordinates":[28.648771,49.792065],"type":"Point"}
}