{
  "type": "Feature",
  "properties": {
    "gn:admin1_code":"11.0",
    "gn:admin2_code":"693058",
    "gn:admin3_code":"11153128.0",
    "gn:asciiname":"Makovka",
    "gn:country_code":"UA",
    "gn:dem":46,
    "gn:elevation":"48.0",
    "gn:feature_class":"P",
    "gn:feature_code":"PPL",
    "gn:name":"Makovka",
    "gn:population":237,
    "gn:timezone":"Europe/Simferopol",
    "iso:country":"UA",
    "name:eng_x_preferred":[
        "Makovka"
    ],
    "name:rus_x_historical":[
        "\u041a\u043e\u043d\u0433\u0440\u0430\u0301\u0442"
    ],
    "name:rus_x_preferred":[
        "\u041c\u0430\u043a\u043e\u0432\u043a\u0430"
    ],
    "name:rus_x_variant":[
        "\u041a\u043e\u043d\u0433\u0440\u0430\u0301\u0442"
    ],
    "name:ukr_x_preferred":[
        "\u041c\u0430\u043a\u0456\u0432\u043a\u0430"
    ],
    "wof:name":"Makovka",
    "wof:placetype":"locality",
    "wof:population":237
},
  "geometry": {"coordinates":[34.97487,45.24444],"type":"Point"}
}