{
  "type": "Feature",
  "properties": {
    "gn:admin1_code":"18.0",
    "gn:asciiname":"Nova Petrivka",
    "gn:country_code":"UA",
    "gn:dem":110,
    "gn:feature_class":"P",
    "gn:feature_code":"PPL",
    "gn:name":"Nova Petrivka",
    "gn:population":0,
    "gn:timezone":"Europe/Kiev",
    "iso:country":"UA",
    "name:ukr_x_preferred":[
        "Nova Petrivka"
    ],
    "name:ukr_x_variant":[
        "\u041d\u043e\u0432\u0430 \u041f\u0435\u0442\u0440\u0456\u0432\u043a\u0430"
    ],
    "wof:name":"Nova Petrivka",
    "wof:placetype":"locality"
},
  "geometry": {"coordinates":[33.0491,49.69777],"type":"Point"}
}