{
  "type": "Feature",
  "properties": {
    "gn:admin1_code":"4.0",
    "gn:asciiname":"Zelenyy Luh",
    "gn:country_code":"UA",
    "gn:dem":111,
    "gn:feature_class":"P",
    "gn:feature_code":"PPL",
    "gn:name":"Zelenyy Luh",
    "gn:population":0,
    "gn:timezone":"Europe/Kiev",
    "iso:country":"UA",
    "name:ukr_x_preferred":[
        "Zelenyy Luh"
    ],
    "name:ukr_x_variant":[
        "\u0417\u0435\u043b\u0435\u043d\u0438\u0439 \u041b\u0443\u0433"
    ],
    "wof:name":"Zelenyy Luh",
    "wof:placetype":"locality"
},
  "geometry": {"coordinates":[33.74590999999999,48.44671],"type":"Point"}
}