{
  "type": "Feature",
  "properties": {
    "iso:country":"UA",
    "name:eng_x_preferred":[
        "Zelen'kiv"
    ],
    "name:rus_x_preferred":[
        "\u0417\u0435\u043b\u0435\u043d\u044c\u043a\u043e\u0432"
    ],
    "name:und_x_variant":[
        "Zelen\u2019kov"
    ],
    "qs:a0":"\u0423\u043a\u0440\u0430\u0457\u043d\u0430",
    "qs:a1":"*\u0427\u0435\u0440\u043a\u0430\u0441\u044c\u043a\u0430",
    "qs:a1_alt":"Cherkas'ka",
    "qs:a1r":"0",
    "qs:a2":"\u0422\u0430\u043b\u044c\u043d\u0456\u0432\u0441\u044c\u043a\u0438\u0439",
    "qs:a2_alt":"Tal'nivs'kyi",
    "qs:adm0":"\u0423\u043a\u0440\u0430\u0457\u043d\u0430",
    "qs:la_lc":"*",
    "qs:level":"locality",
    "qs:loc":"\u0417\u0435\u043b\u0435\u043d\u044c\u043a\u0456\u0432",
    "qs:loc_alt":"Zelen'kiv",
    "qs:pop":0,
    "qs:type":"buffered point",
    "wof:name":"\u0417\u0435\u043b\u0435\u043d\u044c\u043a\u0456\u0432",
    "wof:placetype":"locality"
},
  "geometry": {"coordinates":[30.642973,48.782723],"type":"Point"}
}