{
  "type": "Feature",
  "properties": {
    "gn:admin1_code":"25.0",
    "gn:asciiname":"Kalena",
    "gn:country_code":"UA",
    "gn:dem":652,
    "gn:feature_class":"P",
    "gn:feature_code":"PPL",
    "gn:name":"Kalena",
    "gn:population":0,
    "gn:timezone":"Europe/Uzhgorod",
    "iso:country":"UA",
    "name:ceb_x_preferred":[
        "Kalena"
    ],
    "name:fra_x_preferred":[
        "Kalena"
    ],
    "name:mai_x_preferred":[
        "\u0915\u0932\u0947\u0928\u093e"
    ],
    "name:msa_x_preferred":[
        "Kalena"
    ],
    "name:nep_x_preferred":[
        "\u0915\u0932\u0947\u0928\u093e"
    ],
    "name:new_x_preferred":[
        "\u0915\u0932\u0947\u0928\u093e"
    ],
    "name:pol_x_preferred":[
        "Kalena"
    ],
    "wof:name":"Kalena",
    "wof:placetype":"locality"
},
  "geometry": {"coordinates":[24.33333,48.05],"type":"Point"}
}