{
  "type": "Feature",
  "properties": {
    "gn:admin1_code":"18.0",
    "gn:asciiname":"Kyselivka",
    "gn:country_code":"UA",
    "gn:dem":84,
    "gn:feature_class":"P",
    "gn:feature_code":"PPL",
    "gn:name":"Kyselivka",
    "gn:population":0,
    "gn:timezone":"Europe/Kiev",
    "iso:country":"UA",
    "name:eng_x_preferred":[
        "Prilipka"
    ],
    "name:rus_x_preferred":[
        "\u041f\u0440\u0438\u043b\u0438\u043f\u043a\u0430"
    ],
    "name:ukr_x_preferred":[
        "Kyselivka"
    ],
    "name:ukr_x_variant":[
        "\u041a\u0438\u0441\u0435\u043b\u0456\u0432\u043a\u0430"
    ],
    "name:und_x_variant":[
        "Prilipki"
    ],
    "wof:name":"Kyselivka",
    "wof:placetype":"locality"
},
  "geometry": {"coordinates":[33.84022,49.39944000000001],"type":"Point"}
}