{
  "type": "Feature",
  "properties": {
    "gn:admin1_code":"15.0",
    "gn:asciiname":"Romanuvka",
    "gn:cc2":"UA",
    "gn:country_code":"UA",
    "gn:dem":216,
    "gn:feature_class":"P",
    "gn:feature_code":"PPL",
    "gn:name":"Romanuvka",
    "gn:population":0,
    "gn:timezone":"Europe/Kiev",
    "iso:country":"UA",
    "name:und_x_variant":[
        "Fol\u2019vark Romanuvka",
        "Romanovka",
        "Romanuvka"
    ],
    "wof:name":"Romanuvka",
    "wof:placetype":"locality"
},
  "geometry": {"coordinates":[23.96667,50.31667],"type":"Point"}
}