{
  "type": "Feature",
  "properties": {
    "iso:country":"UA",
    "name:heb_x_preferred":[
        "\u05e0\u05d9\u05d6\u05f3\u05e0\u05d9 \u05e1\u05d8\u05d5\u05d3\u05e0\u05d9"
    ],
    "name:hun_x_historical":[
        "Als\u00f3hidegpatak",
        "Hidegpatak"
    ],
    "name:hun_x_preferred":[
        "Als\u00f3hidegpatak"
    ],
    "name:hun_x_variant":[
        "Hidegpatak"
    ],
    "name:ukr_x_preferred":[
        "\u041d\u0438\u0436\u043d\u0456\u0439 \u0421\u0442\u0443\u0434\u0435\u043d\u0438\u0439"
    ],
    "name:und_x_variant":[
        "Nyzhniy Studenyy"
    ],
    "qs:a0":"\u0423\u043a\u0440\u0430\u0457\u043d\u0430",
    "qs:a1":"*\u0417\u0430\u043a\u0430\u0440\u043f\u0430\u0442\u0441\u044c\u043a\u0430",
    "qs:a1_alt":"Zakarpats'ka",
    "qs:a1r":"0",
    "qs:a2":"\u041c\u0456\u0436\u0433\u0456\u0440\u0441\u044c\u043a\u0438\u0439",
    "qs:a2_alt":"Mizhhirs'kyi",
    "qs:adm0":"\u0423\u043a\u0440\u0430\u0457\u043d\u0430",
    "qs:la_lc":"*",
    "qs:level":"locality",
    "qs:loc":"\u041d\u0438\u0436\u043d\u0456\u0439 \u0421\u0442\u0443\u0434\u0435\u043d\u0438\u0439",
    "qs:loc_alt":"Nyzhnii Studenyi",
    "qs:pop":0,
    "qs:type":"buffered point",
    "wof:name":"\u041d\u0438\u0436\u043d\u0456\u0439 \u0421\u0442\u0443\u0434\u0435\u043d\u0438\u0439",
    "wof:placetype":"locality"
},
  "geometry": {"coordinates":[23.36476,48.703082],"type":"Point"}
}