{
  "type": "Feature",
  "properties": {
    "gn:admin1_code":"19.0",
    "gn:asciiname":"Plyashivka",
    "gn:country_code":"UA",
    "gn:dem":195,
    "gn:feature_class":"P",
    "gn:feature_code":"PPL",
    "gn:name":"Plyashivka",
    "gn:population":0,
    "gn:timezone":"Europe/Kiev",
    "iso:country":"UA",
    "name:ukr_x_preferred":[
        "Plyashivka"
    ],
    "name:ukr_x_variant":[
        "\u041f\u043b\u044f\u0448\u0456\u0432\u043a\u0430"
    ],
    "name:und_x_variant":[
        "Plyashevka"
    ],
    "wof:name":"Plyashivka",
    "wof:placetype":"locality"
},
  "geometry": {"coordinates":[25.24898,50.3269],"type":"Point"}
}