{
  "type": "Feature",
  "properties": {
    "gn:admin1_code":"6.0",
    "gn:asciiname":"Nevochin",
    "gn:country_code":"UA",
    "gn:dem":363,
    "gn:feature_class":"P",
    "gn:feature_code":"PPL",
    "gn:name":"Nevochin",
    "gn:population":0,
    "gn:timezone":"Europe/Kiev",
    "iso:country":"UA",
    "wof:name":"Nevochin",
    "wof:placetype":"locality"
},
  "geometry": {"coordinates":[24.50404,48.86963],"type":"Point"}
}