{
  "type": "Feature",
  "properties": {
    "gn:admin1_code":"18.0",
    "gn:asciiname":"Chaplyntsi",
    "gn:country_code":"UA",
    "gn:dem":83,
    "gn:feature_class":"P",
    "gn:feature_code":"PPL",
    "gn:name":"Chaplyntsi",
    "gn:population":0,
    "gn:timezone":"Europe/Kiev",
    "iso:country":"UA",
    "name:ukr_x_preferred":[
        "Chaplyntsi"
    ],
    "name:ukr_x_variant":[
        "\u0427\u0430\u043f\u043b\u0438\u043d\u0446\u0456"
    ],
    "wof:name":"Chaplyntsi",
    "wof:placetype":"locality"
},
  "geometry": {"coordinates":[33.33217,49.59646],"type":"Point"}
}