{
  "type": "Feature",
  "properties": {
    "gn:admin1_code":"15.0",
    "gn:asciiname":"Pomlynuv",
    "gn:country_code":"UA",
    "gn:dem":226,
    "gn:feature_class":"P",
    "gn:feature_code":"PPL",
    "gn:name":"Pomlynuv",
    "gn:population":0,
    "gn:timezone":"Europe/Kiev",
    "iso:country":"UA",
    "name:und_x_variant":[
        "Pomlynov",
        "Pomlynuv"
    ],
    "wof:name":"Pomlynuv",
    "wof:placetype":"locality"
},
  "geometry": {"coordinates":[23.72037000000001,50.18477],"type":"Point"}
}