{
  "type": "Feature",
  "properties": {
    "gn:admin1_code":"9.0",
    "gn:asciiname":"Volytsya",
    "gn:country_code":"UA",
    "gn:dem":299,
    "gn:feature_class":"P",
    "gn:feature_code":"PPL",
    "gn:name":"Volytsya",
    "gn:population":0,
    "gn:timezone":"Europe/Kiev",
    "iso:country":"UA",
    "name:ukr_x_preferred":[
        "Volytsya"
    ],
    "name:ukr_x_variant":[
        "\u0412\u043e\u043b\u0438\u0446\u044f"
    ],
    "name:und_x_variant":[
        "Volitsa Dubishchskaya"
    ],
    "wof:name":"Volytsya",
    "wof:placetype":"locality"
},
  "geometry": {"coordinates":[26.91667,49.68333],"type":"Point"}
}