{
  "type": "Feature",
  "properties": {
    "gn:admin1_code":"11.0",
    "gn:admin2_code":"709333",
    "gn:admin3_code":"11152855.0",
    "gn:asciiname":"Komsomol'skoye",
    "gn:country_code":"UA",
    "gn:dem":16,
    "gn:elevation":"13.0",
    "gn:feature_class":"P",
    "gn:feature_code":"PPL",
    "gn:name":"Komsomol\u2019skoye",
    "gn:population":644,
    "gn:timezone":"Europe/Simferopol",
    "iso:country":"UA",
    "name:eng_x_preferred":[
        "Komsomol\u2019skoye"
    ],
    "name:rus_x_preferred":[
        "\u041a\u043e\u043c\u0441\u043e\u043c\u043e\u043b\u044c\u0441\u043a\u043e\u0435"
    ],
    "name:ukr_x_preferred":[
        "\u041a\u043e\u043c\u0441\u043e\u043c\u043e\u043b\u044c\u0441\u044c\u043a\u0435"
    ],
    "wof:name":"Komsomol'skoye",
    "wof:placetype":"locality",
    "wof:population":644
},
  "geometry": {"coordinates":[34.39453,45.77595],"type":"Point"}
}