{
  "type": "Feature",
  "properties": {
    "gn:admin1_code":"2.0",
    "gn:asciiname":"Kukari",
    "gn:country_code":"UA",
    "gn:dem":110,
    "gn:feature_class":"P",
    "gn:feature_code":"PPL",
    "gn:name":"Kukari",
    "gn:population":0,
    "gn:timezone":"Europe/Kiev",
    "iso:country":"UA",
    "name:ukr_x_preferred":[
        "Kukari"
    ],
    "name:ukr_x_variant":[
        "\u041a\u0443\u043a\u0430\u0440\u0456"
    ],
    "name:und_x_variant":[
        "Kukary"
    ],
    "wof:name":"Kukari",
    "wof:placetype":"locality"
},
  "geometry": {"coordinates":[30.60112,51.68842],"type":"Point"}
}