{
  "type": "Feature",
  "properties": {
    "gn:admin1_code":"19.0",
    "gn:asciiname":"Buderazh",
    "gn:country_code":"UA",
    "gn:dem":274,
    "gn:feature_class":"P",
    "gn:feature_code":"PPL",
    "gn:name":"Buderazh",
    "gn:population":0,
    "gn:timezone":"Europe/Kiev",
    "iso:country":"UA",
    "name:ukr_x_preferred":[
        "\u0411\u0443\u0434\u0435\u0440\u0430\u0436"
    ],
    "name:und_x_variant":[
        "Listvin",
        "Budera\u017c",
        "Buderazh"
    ],
    "wof:name":"Buderazh",
    "wof:placetype":"locality"
},
  "geometry": {"coordinates":[26.15386,50.32401],"type":"Point"}
}