{
  "type": "Feature",
  "properties": {
    "gn:admin1_code":"9.0",
    "gn:asciiname":"Lesovyye Grinevtsy",
    "gn:country_code":"UA",
    "gn:dem":357,
    "gn:feature_class":"P",
    "gn:feature_code":"PPL",
    "gn:name":"Lesovyye Grinevtsy",
    "gn:population":0,
    "gn:timezone":"Europe/Kiev",
    "iso:country":"UA",
    "name:und_x_variant":[
        "Grinevtsy",
        "Lesovyye Grinevtsy",
        "Lesnyye Grin\u00ebvtsy"
    ],
    "wof:name":"Lesovyye Grinevtsy",
    "wof:placetype":"locality"
},
  "geometry": {"coordinates":[27.02038,49.47843],"type":"Point"}
}