{
  "type": "Feature",
  "properties": {
    "gn:admin1_code":"11.0",
    "gn:admin2_code":"712968",
    "gn:admin3_code":"11152820.0",
    "gn:asciiname":"Sevastyanovka",
    "gn:country_code":"UA",
    "gn:dem":177,
    "gn:elevation":"172.0",
    "gn:feature_class":"P",
    "gn:feature_code":"PPL",
    "gn:name":"Sevastyanovka",
    "gn:population":508,
    "gn:timezone":"Europe/Simferopol",
    "iso:country":"UA",
    "name:eng_x_preferred":[
        "Sevastyanovka"
    ],
    "name:rus_x_preferred":[
        "\u0421\u0435\u0432\u0430\u0441\u0442\u044c\u044f\u043d\u043e\u0432\u043a\u0430"
    ],
    "name:ukr_x_preferred":[
        "\u0421\u0435\u0432\u0430\u0441\u0442\u044f\u043d\u0456\u0432\u043a\u0430"
    ],
    "wof:name":"Sevastyanovka",
    "wof:placetype":"locality",
    "wof:population":508
},
  "geometry": {"coordinates":[33.933,44.81974],"type":"Point"}
}