{
  "type": "Feature",
  "properties": {
    "gn:admin1_code":"5.0",
    "gn:asciiname":"Kruta Balka",
    "gn:country_code":"UA",
    "gn:dem":192,
    "gn:feature_class":"P",
    "gn:feature_code":"PPL",
    "gn:name":"Kruta Balka",
    "gn:population":0,
    "gn:timezone":"Europe/Kiev",
    "iso:country":"UA",
    "name:ukr_x_preferred":[
        "Kruta Balka"
    ],
    "name:ukr_x_variant":[
        "\u041a\u0440\u0443\u0442\u0430 \u0411\u0430\u043b\u043a\u0430"
    ],
    "wof:name":"Kruta Balka",
    "wof:placetype":"locality"
},
  "geometry": {"coordinates":[37.81938,48.14717],"type":"Point"}
}