{
  "type": "Feature",
  "properties": {
    "iso:country":"UA",
    "name:eng_x_preferred":[
        "Krasnyi Mak"
    ],
    "name:hye_x_preferred":[
        "\u053f\u0580\u0561\u057d\u0576\u056b\u0575 \u0544\u0561\u056f"
    ],
    "name:nld_x_preferred":[
        "Krasnyi Mak"
    ],
    "name:ron_x_preferred":[
        "Krasn\u00eei Mak"
    ],
    "name:rus_x_historical":[
        "\u0411\u0438\u044e\u0301\u043a-\u041a\u0430\u0440\u0430\u043b\u0435\u0301\u0437"
    ],
    "name:rus_x_preferred":[
        "\u0411\u0438\u044e\u0301\u043a-\u041a\u0430\u0440\u0430\u043b\u0435\u0301\u0437"
    ],
    "name:rus_x_variant":[
        "\u041a\u0440\u0430\u0441\u043d\u044b\u0439 \u041c\u0430\u043a"
    ],
    "name:ukr_x_preferred":[
        "\u041a\u0440\u0430\u0441\u043d\u0438\u0439 \u041c\u0430\u043a"
    ],
    "qs:a0":"\u0423\u043a\u0440\u0430\u0457\u043d\u0430",
    "qs:a1":"*\u041a\u0440\u0438\u043c",
    "qs:a1_alt":"Krym",
    "qs:a1r":"0",
    "qs:a2":"\u0411\u0430\u0445\u0447\u0438\u0441\u0430\u0440\u0430\u0439\u0441\u044c\u043a\u0438\u0439",
    "qs:a2_alt":"Bakhchysarais'kyi",
    "qs:adm0":"\u0423\u043a\u0440\u0430\u0457\u043d\u0430",
    "qs:la_lc":"*",
    "qs:level":"locality",
    "qs:loc":"\u041a\u0440\u0430\u0441\u043d\u0438\u0439 \u041c\u0430\u043a",
    "qs:loc_alt":"Krasnyi Mak",
    "qs:pop":0,
    "qs:type":"buffered point",
    "wof:name":"\u041a\u0440\u0430\u0441\u043d\u0438\u0439 \u041c\u0430\u043a",
    "wof:placetype":"locality"
},
  "geometry": {"coordinates":[33.785047,44.641235],"type":"Point"}
}