{
  "type": "Feature",
  "properties": {
    "gn:admin1_code":"8.0",
    "gn:asciiname":"Stepne",
    "gn:country_code":"UA",
    "gn:dem":46,
    "gn:feature_class":"P",
    "gn:feature_code":"PPL",
    "gn:name":"Stepne",
    "gn:population":0,
    "gn:timezone":"Europe/Kiev",
    "iso:country":"UA",
    "name:rus_x_preferred":[
        "\u0421\u0442\u0435\u043f\u043d\u043e\u0435"
    ],
    "name:ukr_x_preferred":[
        "\u0421\u0442\u0435\u043f\u043d\u0435"
    ],
    "name:und_x_variant":[
        "Novaya Zavadovka",
        "Stepnoy",
        "Novo-Zavadovka",
        "Stepne",
        "Stepnoye"
    ],
    "wof:name":"Stepne",
    "wof:placetype":"locality"
},
  "geometry": {"coordinates":[34.08166,46.76277],"type":"Point"}
}