{
  "type": "Feature",
  "properties": {
    "gn:admin1_code":"5.0",
    "gn:admin2_code":"697607",
    "gn:asciiname":"Prymis'ke",
    "gn:country_code":"UA",
    "gn:dem":72,
    "gn:feature_class":"P",
    "gn:feature_code":"PPL",
    "gn:name":"Prymis'ke",
    "gn:population":0,
    "gn:timezone":"Europe/Kiev",
    "iso:country":"UA",
    "name:hye_x_colloquial":[
        "\u054a\u0580\u0575\ufb15\u057d\u057d\u056f\u0578\u0575\u0567",
        "\u054a\u0580\u056b\u0563\u0578\u0580\u0578\u0564\u0576\u0578\u0575\u0567",
        "\u054a\u0580\u056b\u0563\u0578\u0580\u0578\u0564\u0576\u0578\u0567"
    ],
    "name:hye_x_historical":[
        "\u054c\u0561\u0564\u0575\u0561\u0576\u057d\u056f\u0561\u0575\u0561 \u0548\u0582\u056f\u0580\u0561\u056b\u0576\u0561"
    ],
    "name:hye_x_preferred":[
        "\u054c\u0561\u0564\u0575\u0561\u0576\u057d\u056f\u0561\u0575\u0561 \u0548\u0582\u056f\u0580\u0561\u056b\u0576\u0561"
    ],
    "name:hye_x_variant":[
        "\u054a\u0580\u0575\ufb15\u057d\u056f\u0565",
        "\u054a\u0580\u0575\ufb15\u057d\u057d\u056f\u0578\u0575\u0567",
        "\u054a\u0580\u056b\u0563\u0578\u0580\u0578\u0564\u0576\u0578\u0575\u0567",
        "\u054a\u0580\u056b\u0563\u0578\u0580\u0578\u0564\u0576\u0578\u0567"
    ],
    "name:rus_x_colloquial":[
        "\u041f\u0440\u0438\u0433\u043e\u0440\u043e\u0434\u043d\u043e\u0435"
    ],
    "name:rus_x_historical":[
        "Radyanskaya Ukraina",
        "\u0421\u043e\u0432\u0435\u0442\u0441\u043a\u0430\u044f \u0423\u043a\u0440\u0430\u0438\u043d\u0430",
        "\u0420\u0430\u0434\u044f\u043d\u0441\u043a\u0430\u044f \u0423\u043a\u0440\u0430\u0438\u043d\u0430",
        "\u041f\u0440\u0438\u043c\u0438\u0441\u0441\u043a\u043e\u0435"
    ],
    "name:rus_x_preferred":[
        "\u041f\u0440\u0438\u043c\u0438\u0441\u0441\u043a\u043e\u0435"
    ],
    "name:rus_x_variant":[
        "Radyanskaya Ukraina",
        "\u041f\u0440\u0438\u0433\u043e\u0440\u043e\u0434\u043d\u043e\u0435",
        "\u0421\u043e\u0432\u0435\u0442\u0441\u043a\u0430\u044f \u0423\u043a\u0440\u0430\u0438\u043d\u0430",
        "\u0420\u0430\u0434\u044f\u043d\u0441\u043a\u0430\u044f \u0423\u043a\u0440\u0430\u0438\u043d\u0430"
    ],
    "name:ukr_x_historical":[
        "Radyans\u2019ka Ukrayina",
        "\u0420\u0430\u0434\u044f\u043d\u0441\u044c\u043a\u0430 \u0423\u043a\u0440\u0430\u0457\u043d\u0430"
    ],
    "name:ukr_x_preferred":[
        "\u041f\u0440\u0438\u043c\u0456\u0441\u044c\u043a\u0435"
    ],
    "name:ukr_x_variant":[
        "Radyans\u2019ka Ukrayina",
        "\u0420\u0430\u0434\u044f\u043d\u0441\u044c\u043a\u0430 \u0423\u043a\u0440\u0430\u0457\u043d\u0430"
    ],
    "name:und_x_variant":[
        "Radianska Ukraina",
        "Prymis'ke",
        "Prymisske"
    ],
    "wof:name":"Prymis'ke",
    "wof:placetype":"locality"
},
  "geometry": {"coordinates":[37.45144000000001,47.12024],"type":"Point"}
}