{
  "type": "Feature",
  "properties": {
    "gn:admin1_code":"19.0",
    "gn:asciiname":"Spasiv",
    "gn:country_code":"UA",
    "gn:dem":243,
    "gn:feature_class":"P",
    "gn:feature_code":"PPL",
    "gn:name":"Spasiv",
    "gn:population":0,
    "gn:timezone":"Europe/Kiev",
    "iso:country":"UA",
    "name:ukr_x_preferred":[
        "Spasiv"
    ],
    "name:ukr_x_variant":[
        "\u0421\u043f\u0430\u0441\u0456\u0432"
    ],
    "name:und_x_variant":[
        "Spasuv",
        "Spasov"
    ],
    "wof:name":"Spasiv",
    "wof:placetype":"locality"
},
  "geometry": {"coordinates":[26.09865,50.45016],"type":"Point"}
}