{
  "type": "Feature",
  "properties": {
    "gn:admin1_code":"24.0",
    "gn:asciiname":"Polozheve",
    "gn:country_code":"UA",
    "gn:dem":168,
    "gn:feature_class":"P",
    "gn:feature_code":"PPL",
    "gn:name":"Polozheve",
    "gn:population":0,
    "gn:timezone":"Europe/Kiev",
    "iso:country":"UA",
    "name:ukr_x_preferred":[
        "Polozheve"
    ],
    "name:ukr_x_variant":[
        "\u041f\u043e\u043b\u043e\u0436\u0435\u0432\u0435"
    ],
    "name:und_x_variant":[
        "Polozhevo"
    ],
    "wof:name":"Polozheve",
    "wof:placetype":"locality"
},
  "geometry": {"coordinates":[23.94176,51.43089000000001],"type":"Point"}
}