{
  "type": "Feature",
  "properties": {
    "gn:admin1_code":"7.0",
    "gn:asciiname":"Dvurechnyy Kut",
    "gn:country_code":"UA",
    "gn:dem":115,
    "gn:feature_class":"P",
    "gn:feature_code":"PPL",
    "gn:name":"Dvurechnyy Kut",
    "gn:population":0,
    "gn:timezone":"Europe/Kiev",
    "iso:country":"UA",
    "name:rus_x_preferred":[
        "\u0414\u0432\u0443\u0440\u0435\u0447\u043d\u044b\u0439 \u041a\u0443\u0442"
    ],
    "wof:name":"Dvurechnyy Kut",
    "wof:placetype":"locality"
},
  "geometry": {"coordinates":[35.93652,50.04345],"type":"Point"}
}