{
  "type": "Feature",
  "properties": {
    "gn:admin1_code":"7.0",
    "gn:asciiname":"Myrhorody",
    "gn:country_code":"UA",
    "gn:dem":89,
    "gn:feature_class":"P",
    "gn:feature_code":"PPL",
    "gn:name":"Myrhorody",
    "gn:population":0,
    "gn:timezone":"Europe/Kiev",
    "iso:country":"UA",
    "name:ukr_x_preferred":[
        "Myrhorody"
    ],
    "name:ukr_x_variant":[
        "\u041c\u0438\u0440\u0433\u043e\u0440\u043e\u0434\u0438"
    ],
    "name:und_x_variant":[
        "Mirgorod",
        "Mirgorody"
    ],
    "wof:name":"Myrhorody",
    "wof:placetype":"locality"
},
  "geometry": {"coordinates":[36.18408,49.7414],"type":"Point"}
}