{
  "type": "Feature",
  "properties": {
    "gn:admin1_code":"15.0",
    "gn:asciiname":"Krynytsya",
    "gn:country_code":"UA",
    "gn:dem":268,
    "gn:feature_class":"P",
    "gn:feature_code":"PPL",
    "gn:name":"Krynytsya",
    "gn:population":0,
    "gn:timezone":"Europe/Kiev",
    "iso:country":"UA",
    "name:rus_x_preferred":[
        "\u041a\u0440\u0438\u043d\u0438\u0446\u0430"
    ],
    "name:ukr_x_preferred":[
        "Krynytsya"
    ],
    "name:ukr_x_variant":[
        "\u041a\u0440\u0438\u043d\u0438\u0446\u044f"
    ],
    "name:und_x_variant":[
        "Krynitsa",
        "Krinitsa"
    ],
    "wof:name":"Krynytsya",
    "wof:placetype":"locality"
},
  "geometry": {"coordinates":[23.83414,49.42746],"type":"Point"}
}