{
  "type": "Feature",
  "properties": {
    "gn:admin1_code":"2.0",
    "gn:asciiname":"Step",
    "gn:country_code":"UA",
    "gn:dem":155,
    "gn:feature_class":"P",
    "gn:feature_code":"PPL",
    "gn:name":"Step",
    "gn:population":0,
    "gn:timezone":"Europe/Kiev",
    "iso:country":"UA",
    "name:dan_x_preferred":[
        "Step"
    ],
    "name:epo_x_preferred":[
        "\u015ctupo"
    ],
    "name:fas_x_preferred":[
        "\u067e\u0644\u0647"
    ],
    "name:hun_x_preferred":[
        "Step"
    ],
    "name:ita_x_preferred":[
        "Step"
    ],
    "name:jpn_x_preferred":[
        "\u30b9\u30c6\u30c3\u30d7"
    ],
    "name:pol_x_preferred":[
        "Step"
    ],
    "name:rus_x_preferred":[
        "Step\u2019"
    ],
    "name:rus_x_variant":[
        "Step"
    ],
    "name:slk_x_preferred":[
        "Step"
    ],
    "name:tur_x_preferred":[
        "Step"
    ],
    "name:ukr_x_preferred":[
        "Step"
    ],
    "name:ukr_x_variant":[
        "\u0421\u0442\u0435\u043f",
        "\u0421\u0442\u0443\u043f\u0456\u043d\u044c"
    ],
    "wof:name":"Step",
    "wof:placetype":"locality"
},
  "geometry": {"coordinates":[32.67333,50.72962],"type":"Point"}
}