{
  "type": "Feature",
  "properties": {
    "gn:admin1_code":"2.0",
    "gn:asciiname":"Step",
    "gn:country_code":"UA",
    "gn:dem":155,
    "gn:feature_class":"P",
    "gn:feature_code":"PPL",
    "gn:name":"Step",
    "gn:population":0,
    "gn:timezone":"Europe/Kiev",
    "iso:country":"UA",
    "name:rus_x_preferred":[
        "Step\u2019"
    ],
    "name:ukr_x_preferred":[
        "Step"
    ],
    "name:ukr_x_variant":[
        "\u0421\u0442\u0435\u043f"
    ],
    "wof:name":"Step",
    "wof:placetype":"locality"
},
  "geometry": {"coordinates":[32.67333,50.72962],"type":"Point"}
}