{
  "type": "Feature",
  "properties": {
    "gn:admin1_code":"19.0",
    "gn:asciiname":"Budky-Snovydovyts'ki",
    "gn:country_code":"UA",
    "gn:dem":189,
    "gn:feature_class":"P",
    "gn:feature_code":"PPL",
    "gn:name":"Budky-Snovydovyts\u2019ki",
    "gn:population":0,
    "gn:timezone":"Europe/Kiev",
    "iso:country":"UA",
    "name:ukr_x_preferred":[
        "Budky-Snovydovyts\u2019ki"
    ],
    "name:ukr_x_variant":[
        "\u0411\u0443\u0434\u043a\u0438-\u0421\u043d\u043e\u0432\u0438\u0434\u043e\u0432\u0438\u0446\u044c\u043a\u0456"
    ],
    "name:und_x_variant":[
        "Budki Snovidovitske",
        "Budki-Snovidovichskiye"
    ],
    "wof:name":"Budky-Snovydovyts'ki",
    "wof:placetype":"locality"
},
  "geometry": {"coordinates":[27.45531,51.24642],"type":"Point"}
}