{
  "type": "Feature",
  "properties": {
    "gn:admin1_code":"9.0",
    "gn:asciiname":"Guta Staraya",
    "gn:country_code":"UA",
    "gn:dem":286,
    "gn:feature_class":"P",
    "gn:feature_code":"PPL",
    "gn:name":"Guta Staraya",
    "gn:population":0,
    "gn:timezone":"Europe/Kiev",
    "iso:country":"UA",
    "wof:name":"Guta Staraya",
    "wof:placetype":"locality"
},
  "geometry": {"coordinates":[27.15,48.96667],"type":"Point"}
}