{
  "type": "Feature",
  "properties": {
    "gn:admin1_code":"17.0",
    "gn:asciiname":"Donskaya Balka",
    "gn:country_code":"UA",
    "gn:dem":18,
    "gn:feature_class":"P",
    "gn:feature_code":"PPL",
    "gn:name":"Donskaya Balka",
    "gn:population":0,
    "gn:timezone":"Europe/Kiev",
    "iso:country":"UA",
    "name:und_x_variant":[
        "Panchuly",
        "Donskaya Balka"
    ],
    "wof:name":"Donskaya Balka",
    "wof:placetype":"locality"
},
  "geometry": {"coordinates":[30.94035,47.09402],"type":"Point"}
}