{
  "type": "Feature",
  "properties": {
    "gn:admin1_code":"19.0",
    "gn:asciiname":"Hirnyky",
    "gn:country_code":"UA",
    "gn:dem":243,
    "gn:feature_class":"P",
    "gn:feature_code":"PPL",
    "gn:name":"Hirnyky",
    "gn:population":0,
    "gn:timezone":"Europe/Kiev",
    "iso:country":"UA",
    "name:ukr_x_preferred":[
        "Hirnyky"
    ],
    "name:ukr_x_variant":[
        "\u0413\u0456\u0440\u043d\u0438\u043a\u0438"
    ],
    "name:und_x_variant":[
        "Gorniki"
    ],
    "wof:name":"Hirnyky",
    "wof:placetype":"locality"
},
  "geometry": {"coordinates":[25.82258,50.38206],"type":"Point"}
}