{
  "type": "Feature",
  "properties": {
    "gn:admin1_code":"26.0",
    "gn:asciiname":"Vishneve",
    "gn:country_code":"UA",
    "gn:dem":138,
    "gn:feature_class":"P",
    "gn:feature_code":"PPL",
    "gn:name":"Vishneve",
    "gn:population":0,
    "gn:timezone":"Europe/Zaporozhye",
    "iso:country":"UA",
    "name:ukr_x_preferred":[
        "Vishneve"
    ],
    "name:ukr_x_variant":[
        "\u0412\u0438\u0448\u043d\u0435\u0432\u0435"
    ],
    "name:und_x_variant":[
        "Vishnevy",
        "Vishn\u00ebvyy",
        "Vishnevoye"
    ],
    "wof:name":"Vishneve",
    "wof:placetype":"locality"
},
  "geometry": {"coordinates":[35.43786,47.92135],"type":"Point"}
}