{
  "type": "Feature",
  "properties": {
    "gn:admin1_code":"18.0",
    "gn:asciiname":"Maslivtsi",
    "gn:country_code":"UA",
    "gn:dem":162,
    "gn:feature_class":"P",
    "gn:feature_code":"PPL",
    "gn:name":"Maslivtsi",
    "gn:population":0,
    "gn:timezone":"Europe/Kiev",
    "iso:country":"UA",
    "name:ukr_x_preferred":[
        "Maslivtsi"
    ],
    "name:ukr_x_variant":[
        "\u041c\u0430\u0441\u043b\u0456\u0432\u0446\u0456"
    ],
    "wof:name":"Maslivtsi",
    "wof:placetype":"locality"
},
  "geometry": {"coordinates":[34.12579,49.95621],"type":"Point"}
}