{
  "type": "Feature",
  "properties": {
    "gn:admin1_code":"15.0",
    "gn:asciiname":"Trudovach",
    "gn:country_code":"UA",
    "gn:dem":397,
    "gn:feature_class":"P",
    "gn:feature_code":"PPL",
    "gn:name":"Trudovach",
    "gn:population":0,
    "gn:timezone":"Europe/Kiev",
    "iso:country":"UA",
    "wof:name":"Trudovach",
    "wof:placetype":"locality"
},
  "geometry": {"coordinates":[24.68333,49.76667],"type":"Point"}
}