{
  "type": "Feature",
  "properties": {
    "gn:admin1_code":"11.0",
    "gn:admin2_code":"712968",
    "gn:admin3_code":"11152823.0",
    "gn:asciiname":"Nekrasovka",
    "gn:country_code":"UA",
    "gn:dem":42,
    "gn:elevation":"50.0",
    "gn:feature_class":"P",
    "gn:feature_code":"PPL",
    "gn:name":"Nekrasovka",
    "gn:population":331,
    "gn:timezone":"Europe/Simferopol",
    "iso:country":"UA",
    "name:eng_x_preferred":[
        "Nekrasovka"
    ],
    "name:rus_x_preferred":[
        "\u041d\u0435\u043a\u0440\u0430\u0441\u043e\u0432\u043a\u0430"
    ],
    "name:ukr_x_preferred":[
        "\u041d\u0435\u043a\u0440\u0430\u0441\u043e\u0432\u043a\u0430"
    ],
    "name:und_x_variant":[
        "Golumbey"
    ],
    "wof:name":"Nekrasovka",
    "wof:placetype":"locality",
    "wof:population":331
},
  "geometry": {"coordinates":[33.69273,44.74653],"type":"Point"}
}