{
  "type": "Feature",
  "properties": {
    "gn:admin1_code":"5.0",
    "gn:asciiname":"Novohryshyne",
    "gn:country_code":"UA",
    "gn:dem":128,
    "gn:feature_class":"P",
    "gn:feature_code":"PPL",
    "gn:name":"Novohryshyne",
    "gn:population":0,
    "gn:timezone":"Europe/Kiev",
    "iso:country":"UA",
    "name:ukr_x_preferred":[
        "Novohryshyne"
    ],
    "name:ukr_x_variant":[
        "\u041d\u043e\u0432\u043e\u0433\u0440\u0438\u0448\u0438\u043d\u0435"
    ],
    "name:und_x_variant":[
        "Khutor Novogrishinskiy",
        "Novogrishino"
    ],
    "wof:name":"Novohryshyne",
    "wof:placetype":"locality"
},
  "geometry": {"coordinates":[37.02648,48.4168],"type":"Point"}
}