{
  "type": "Feature",
  "properties": {
    "gn:admin1_code":"7.0",
    "gn:asciiname":"Kluhyno-Bashkyrivka",
    "gn:country_code":"UA",
    "gn:dem":101,
    "gn:feature_class":"P",
    "gn:feature_code":"PPL",
    "gn:name":"Kluhyno-Bashkyrivka",
    "gn:population":0,
    "gn:timezone":"Europe/Kiev",
    "iso:country":"UA",
    "name:ukr_x_preferred":[
        "Kluhyno-Bashkyrivka"
    ],
    "name:ukr_x_variant":[
        "\u041a\u043b\u0443\u0433\u0438\u043d\u043e-\u0411\u0430\u0448\u043a\u0438\u0440\u0456\u0432\u043a\u0430"
    ],
    "name:und_x_variant":[
        "Bashkirovka",
        "Kluginovka",
        "Klugino-Bashkirovka"
    ],
    "wof:name":"Kluhyno-Bashkyrivka",
    "wof:placetype":"locality"
},
  "geometry": {"coordinates":[36.72783,49.84101],"type":"Point"}
}