{
  "type": "Feature",
  "properties": {
    "gn:admin1_code":"8.0",
    "gn:asciiname":"Tokareve",
    "gn:country_code":"UA",
    "gn:dem":61,
    "gn:feature_class":"P",
    "gn:feature_code":"PPL",
    "gn:name":"Tokareve",
    "gn:population":0,
    "gn:timezone":"Europe/Kiev",
    "iso:country":"UA",
    "name:ukr_x_preferred":[
        "Tokareve"
    ],
    "name:ukr_x_variant":[
        "\u0422\u043e\u043a\u0430\u0440\u0435\u0432\u0435"
    ],
    "name:und_x_variant":[
        "Tokar\u00ebv",
        "Tokar\u00ebvo"
    ],
    "wof:name":"Tokareve",
    "wof:placetype":"locality"
},
  "geometry": {"coordinates":[33.16752,47.29982],"type":"Point"}
}