{
  "type": "Feature",
  "properties": {
    "iso:country":"UA",
    "name:deu_x_preferred":[
        "Schwarzmeerdeutsche"
    ],
    "name:fin_x_preferred":[
        "Mustanmeren saksalaiset"
    ],
    "name:jpn_x_preferred":[
        "\u9ed2\u6d77\u30c9\u30a4\u30c4\u4eba"
    ],
    "name:kor_x_preferred":[
        "\ud751\ud574 \ub3c5\uc77c\uc778"
    ],
    "name:ron_x_preferred":[
        "Germani transnistreni"
    ],
    "name:ukr_x_preferred":[
        "\u0427\u043e\u0440\u043d\u043e\u043c\u043e\u0440\u0441\u044c\u043a\u0456 \u043d\u0456\u043c\u0446\u0456"
    ],
    "name:zho_x_preferred":[
        "\u9ed1\u6d77\u5fb7\u610f\u5fd7\u4eba"
    ],
    "qs:a0":"\u0423\u043a\u0440\u0430\u0457\u043d\u0430",
    "qs:a1":"*\u041b\u044c\u0432\u0456\u0432\u0441\u044c\u043a\u0430",
    "qs:a1_alt":"L'vivs'ka",
    "qs:a1r":"0",
    "qs:a2":"\u0413\u043e\u0440\u043e\u0434\u043e\u0446\u044c\u043a\u0438\u0439",
    "qs:a2_alt":"Horodots'kyi",
    "qs:adm0":"\u0423\u043a\u0440\u0430\u0457\u043d\u0430",
    "qs:la_lc":"*",
    "qs:level":"locality",
    "qs:loc":"\u041f\u0435\u0440\u0435\u043c\u043e\u0436\u043d\u0435",
    "qs:loc_alt":"Peremozhne",
    "qs:pop":0,
    "qs:type":"buffered point",
    "wd:wordcount":2089,
    "wof:name":"\u041f\u0435\u0440\u0435\u043c\u043e\u0436\u043d\u0435",
    "wof:placetype":"locality"
},
  "geometry": {"coordinates":[23.668142,49.621549],"type":"Point"}
}