{
  "type": "Feature",
  "properties": {
    "gn:admin1_code":"5.0",
    "gn:asciiname":"Dubovo-Vasylivka",
    "gn:country_code":"UA",
    "gn:dem":136,
    "gn:feature_class":"P",
    "gn:feature_code":"PPL",
    "gn:name":"Dubovo-Vasylivka",
    "gn:population":0,
    "gn:timezone":"Europe/Kiev",
    "iso:country":"UA",
    "name:ukr_x_preferred":[
        "Dubovo-Vasylivka"
    ],
    "name:ukr_x_variant":[
        "\u0414\u0443\u0431\u043e\u0432\u043e-\u0412\u0430\u0441\u0438\u043b\u0456\u0432\u043a\u0430"
    ],
    "wof:name":"Dubovo-Vasylivka",
    "wof:placetype":"locality"
},
  "geometry": {"coordinates":[37.92428,48.64813],"type":"Point"}
}