{
  "type": "Feature",
  "properties": {
    "iso:country":"UA",
    "name:rus_x_preferred":[
        "\u0411\u043e\u0433\u0434\u0430\u043d\u0456\u0432\u043a\u0430"
    ],
    "name:ukr_x_preferred":[
        "\u0411\u043e\u0433\u0434\u0430\u043d\u0456\u0432\u043a\u0430"
    ],
    "name:unk_x_variant":[
        "Kalinovka"
    ],
    "qs:a0":"\u0423\u043a\u0440\u0430\u0457\u043d\u0430",
    "qs:a1":"*\u0412\u0456\u043d\u043d\u0438\u0446\u044c\u043a\u0430",
    "qs:a1_alt":"Vinnyts'ka",
    "qs:a1r":"0",
    "qs:a2":"\u0422\u0443\u043b\u044c\u0447\u0438\u043d\u0441\u044c\u043a\u0438\u0439",
    "qs:a2_alt":"Tul'chyns'kyi",
    "qs:adm0":"\u0423\u043a\u0440\u0430\u0457\u043d\u0430",
    "qs:la_lc":"*",
    "qs:level":"locality",
    "qs:loc":"\u0411\u043e\u0433\u0434\u0430\u043d\u0456\u0432\u043a\u0430",
    "qs:loc_alt":"Bohdanivka",
    "qs:pop":0,
    "qs:type":"buffered point",
    "wd:wordcount":679,
    "wof:name":"\u0411\u043e\u0433\u0434\u0430\u043d\u0456\u0432\u043a\u0430",
    "wof:placetype":"locality"
},
  "geometry": {"coordinates":[29.116058,48.641805],"type":"Point"}
}