{
  "type": "Feature",
  "properties": {
    "gn:admin1_code":"2.0",
    "gn:asciiname":"Semaky",
    "gn:country_code":"UA",
    "gn:dem":157,
    "gn:feature_class":"P",
    "gn:feature_code":"PPL",
    "gn:name":"Semaky",
    "gn:population":0,
    "gn:timezone":"Europe/Kiev",
    "iso:country":"UA",
    "name:ukr_x_preferred":[
        "Semaky"
    ],
    "name:ukr_x_variant":[
        "\u0421\u0435\u043c\u0430\u043a\u0438"
    ],
    "name:und_x_variant":[
        "Semaki"
    ],
    "wof:name":"Semaky",
    "wof:placetype":"locality"
},
  "geometry": {"coordinates":[30.79249,51.73763],"type":"Point"}
}