{
  "type": "Feature",
  "properties": {
    "gn:admin1_code":"2.0",
    "gn:asciiname":"Vidradne",
    "gn:country_code":"UA",
    "gn:dem":131,
    "gn:feature_class":"P",
    "gn:feature_code":"PPL",
    "gn:name":"Vidradne",
    "gn:population":0,
    "gn:timezone":"Europe/Kiev",
    "iso:country":"UA",
    "name:ukr_x_preferred":[
        "Vidradne"
    ],
    "name:ukr_x_variant":[
        "\u0412\u0456\u0434\u0440\u0430\u0434\u043d\u0435"
    ],
    "name:und_x_variant":[
        "Otradnoye"
    ],
    "wof:name":"Vidradne",
    "wof:placetype":"locality"
},
  "geometry": {"coordinates":[31.74551,50.83472],"type":"Point"}
}