{
  "type": "Feature",
  "properties": {
    "iso:country":"UA",
    "name:eng_x_preferred":[
        "Prybuzhzhya"
    ],
    "name:ukr_x_preferred":[
        "\u041f\u0440\u0438\u0431\u0443\u0436\u0436\u044f"
    ],
    "name:und_x_variant":[
        "Ak-Mechet\u2019"
    ],
    "qs:a0":"\u0423\u043a\u0440\u0430\u0457\u043d\u0430",
    "qs:a1":"*\u041c\u0438\u043a\u043e\u043b\u0430\u0457\u0432\u0441\u044c\u043a\u0430",
    "qs:a1_alt":"Mykolaivs'ka",
    "qs:a1r":"0",
    "qs:a2":"\u0414\u043e\u043c\u0430\u043d\u0456\u0432\u0441\u044c\u043a\u0438\u0439",
    "qs:a2_alt":"Domanivs'kyi",
    "qs:adm0":"\u0423\u043a\u0440\u0430\u0457\u043d\u0430",
    "qs:la_lc":"*",
    "qs:level":"locality",
    "qs:loc":"\u041f\u0440\u0438\u0431\u0443\u0436\u0436\u044f",
    "qs:loc_alt":"Prybuzhzhia",
    "qs:pop":0,
    "qs:type":"buffered point",
    "wof:name":"\u041f\u0440\u0438\u0431\u0443\u0436\u0436\u044f",
    "wof:placetype":"locality"
},
  "geometry": {"coordinates":[31.241428,47.67562],"type":"Point"}
}