{
  "type": "Feature",
  "properties": {
    "gn:admin1_code":"22.0",
    "gn:asciiname":"Berimovtsy",
    "gn:country_code":"UA",
    "gn:dem":364,
    "gn:feature_class":"P",
    "gn:feature_code":"PPL",
    "gn:name":"Berimovtsy",
    "gn:population":0,
    "gn:timezone":"Europe/Kiev",
    "iso:country":"UA",
    "name:und_x_variant":[
        "Beremovtse",
        "Berymivtsi",
        "Berimovtsy"
    ],
    "wof:name":"Berimovtsy",
    "wof:placetype":"locality"
},
  "geometry": {"coordinates":[25.20129,49.71822],"type":"Point"}
}