{
  "type": "Feature",
  "properties": {
    "gn:admin1_code":"9.0",
    "gn:asciiname":"Novoye Selo",
    "gn:country_code":"UA",
    "gn:dem":312,
    "gn:feature_class":"P",
    "gn:feature_code":"PPL",
    "gn:name":"Novoye S\u00eblo",
    "gn:population":815,
    "gn:timezone":"Europe/Kiev",
    "iso:country":"UA",
    "name:eng_x_preferred":[
        "Nove Selo"
    ],
    "name:rus_x_preferred":[
        "\u041d\u043e\u0432\u043e\u0435 \u0441\u0435\u043b\u043e"
    ],
    "name:ukr_x_preferred":[
        "\u041d\u043e\u0432\u0435 \u0441\u0435\u043b\u043e"
    ],
    "name:und_x_variant":[
        "Novoye S\u00eblo"
    ],
    "wof:name":"Novoye Selo",
    "wof:placetype":"locality",
    "wof:population":815
},
  "geometry": {"coordinates":[26.79932,49.17444],"type":"Point"}
}