{
  "type": "Feature",
  "properties": {
    "gn:admin1_code":"2.0",
    "gn:asciiname":"Tereshykha",
    "gn:country_code":"UA",
    "gn:dem":142,
    "gn:feature_class":"P",
    "gn:feature_code":"PPL",
    "gn:name":"Tereshykha",
    "gn:population":0,
    "gn:timezone":"Europe/Kiev",
    "iso:country":"UA",
    "name:ukr_x_preferred":[
        "Tereshykha"
    ],
    "name:ukr_x_variant":[
        "\u0422\u0435\u0440\u0435\u0448\u0438\u0445\u0430"
    ],
    "name:und_x_variant":[
        "Tereshikha"
    ],
    "wof:name":"Tereshykha",
    "wof:placetype":"locality"
},
  "geometry": {"coordinates":[32.75145,50.94415],"type":"Point"}
}