{
  "type": "Feature",
  "properties": {
    "gn:admin1_code":"17.0",
    "gn:asciiname":"Dumianovca",
    "gn:country_code":"UA",
    "gn:dem":2,
    "gn:feature_class":"P",
    "gn:feature_code":"PPL",
    "gn:name":"Dumianovca",
    "gn:population":0,
    "gn:timezone":"Europe/Kiev",
    "iso:country":"UA",
    "name:und_x_variant":[
        "Dem\u2019yanovka"
    ],
    "wof:name":"Dumianovca",
    "wof:placetype":"locality"
},
  "geometry": {"coordinates":[29.31667,45.48333],"type":"Point"}
}