{
  "type": "Feature",
  "properties": {
    "gn:admin1_code":"16.0",
    "gn:asciiname":"Novo-Grigor'yevka",
    "gn:country_code":"UA",
    "gn:dem":135,
    "gn:feature_class":"P",
    "gn:feature_code":"PPL",
    "gn:name":"Novo-Grigor\u2019yevka",
    "gn:population":0,
    "gn:timezone":"Europe/Kiev",
    "iso:country":"UA",
    "wof:name":"Novo-Grigor'yevka",
    "wof:placetype":"locality"
},
  "geometry": {"coordinates":[30.6937,47.84904],"type":"Point"}
}