{
  "type": "Feature",
  "properties": {
    "gn:admin1_code":"4.0",
    "gn:asciiname":"Lukacharskoye",
    "gn:country_code":"UA",
    "gn:dem":144,
    "gn:feature_class":"P",
    "gn:feature_code":"PPL",
    "gn:name":"Lukacharskoye",
    "gn:population":0,
    "gn:timezone":"Europe/Kiev",
    "iso:country":"UA",
    "name:ukr_x_preferred":[
        "Lunachars\u2019ke"
    ],
    "name:und_x_variant":[
        "Zlodeyka",
        "Lunacharskiy",
        "Lukacharskoye"
    ],
    "wof:name":"Lukacharskoye",
    "wof:placetype":"locality"
},
  "geometry": {"coordinates":[36.39662,47.99711],"type":"Point"}
}