{
  "type": "Feature",
  "properties": {
    "iso:country":"UA",
    "qs:a0":"\u0423\u043a\u0440\u0430\u0457\u043d\u0430",
    "qs:a1":"*\u0427\u0435\u0440\u043a\u0430\u0441\u044c\u043a\u0430",
    "qs:a1_alt":"Cherkas'ka",
    "qs:a1r":"0",
    "qs:a2":"\u0417\u043e\u043b\u043e\u0442\u043e\u043d\u0456\u0441\u044c\u043a\u0438\u0439",
    "qs:a2_alt":"Zolotonis'kyi",
    "qs:adm0":"\u0423\u043a\u0440\u0430\u0457\u043d\u0430",
    "qs:la_lc":"*",
    "qs:level":"locality",
    "qs:loc":"\u0412\u043e\u0437\u043d\u0435\u0441\u0435\u043d\u0441\u044c\u043a\u0435",
    "qs:loc_alt":"Voznesens'ke",
    "qs:pop":0,
    "qs:type":"buffered point",
    "wof:name":"\u0412\u043e\u0437\u043d\u0435\u0441\u0435\u043d\u0441\u044c\u043a\u0435",
    "wof:placetype":"locality"
},
  "geometry": {"coordinates":[32.158634,49.75741],"type":"Point"}
}