{
  "type": "Feature",
  "properties": {
    "gn:admin1_code":"26.0",
    "gn:asciiname":"Dolinsk",
    "gn:cc2":"UA",
    "gn:country_code":"UA",
    "gn:dem":100,
    "gn:feature_class":"P",
    "gn:feature_code":"PPL",
    "gn:name":"Dolinsk",
    "gn:population":0,
    "gn:timezone":"Europe/Zaporozhye",
    "iso:country":"UA",
    "name:ben_x_preferred":[
        "\u09a6\u09cb\u09b2\u09bf\u09a8\u09b8\u09cd\u0995"
    ],
    "name:ell_x_preferred":[
        "\u039d\u03c4\u03cc\u03bb\u03b9\u03bd\u03c3\u03ba"
    ],
    "name:heb_x_preferred":[
        "\u05d3\u05d5\u05dc\u05d9\u05e0\u05e1\u05e7"
    ],
    "name:hin_x_preferred":[
        "\u0921\u094b\u0932\u093f\u0902\u0938\u094d\u0915"
    ],
    "name:hun_x_preferred":[
        "Dolinsk"
    ],
    "name:spa_x_preferred":[
        "Dolinsk"
    ],
    "name:und_x_variant":[
        "Kronstal\u2019",
        "Dolinsk"
    ],
    "wof:name":"Dolinsk",
    "wof:placetype":"locality"
},
  "geometry": {"coordinates":[34.96667,47.78333],"type":"Point"}
}