{
  "type": "Feature",
  "properties": {
    "gn:admin1_code":"26.0",
    "gn:asciiname":"Dolinsk",
    "gn:cc2":"UA",
    "gn:country_code":"UA",
    "gn:dem":100,
    "gn:feature_class":"P",
    "gn:feature_code":"PPL",
    "gn:name":"Dolinsk",
    "gn:population":0,
    "gn:timezone":"Europe/Zaporozhye",
    "iso:country":"UA",
    "name:und_x_variant":[
        "Kronstal\u2019",
        "Dolinsk"
    ],
    "wof:name":"Dolinsk",
    "wof:placetype":"locality"
},
  "geometry": {"coordinates":[34.96667,47.78333],"type":"Point"}
}