{
  "type": "Feature",
  "properties": {
    "gn:admin1_code":"16.0",
    "gn:asciiname":"Pyataya Nikolayevka",
    "gn:country_code":"UA",
    "gn:dem":96,
    "gn:feature_class":"P",
    "gn:feature_code":"PPL",
    "gn:name":"Pyataya Nikolayevka",
    "gn:population":0,
    "gn:timezone":"Europe/Kiev",
    "iso:country":"UA",
    "wof:name":"Pyataya Nikolayevka",
    "wof:placetype":"locality"
},
  "geometry": {"coordinates":[32.26667,47.71667],"type":"Point"}
}