{
  "type": "Feature",
  "properties": {
    "gn:admin1_code":"19.0",
    "gn:asciiname":"Glushkovo",
    "gn:country_code":"UA",
    "gn:dem":199,
    "gn:feature_class":"P",
    "gn:feature_code":"PPL",
    "gn:name":"Glushkovo",
    "gn:population":0,
    "gn:timezone":"Europe/Kiev",
    "iso:country":"UA",
    "wof:name":"Glushkovo",
    "wof:placetype":"locality"
},
  "geometry": {"coordinates":[27.15,50.86667],"type":"Point"}
}