{
  "type": "Feature",
  "properties": {
    "iso:country":"UA",
    "name:eng_x_preferred":[
        "Tomyna Balka"
    ],
    "name:ger_x_preferred":[
        "Tomyna Balka"
    ],
    "name:lav_x_preferred":[
        "Tomina Balka"
    ],
    "name:pol_x_preferred":[
        "Tomyna Ba\u0142ka"
    ],
    "name:rum_x_preferred":[
        "Tom\u00eena Balka"
    ],
    "name:rus_x_preferred":[
        "\u0422\u043e\u043c\u0438\u043d\u0430 \u0411\u0430\u043b\u043a\u0430"
    ],
    "name:ukr_x_preferred":[
        "Tomyna Balka"
    ],
    "name:ukr_x_variant":[
        "\u0422\u043e\u043c\u0438\u043d\u0430 \u0411\u0430\u043b\u043a\u0430"
    ],
    "name:unk_x_variant":[
        "Khutora Tomina Balka"
    ],
    "qs:a0":"\u0423\u043a\u0440\u0430\u0457\u043d\u0430",
    "qs:a1":"*\u0425\u0435\u0440\u0441\u043e\u043d\u0441\u044c\u043a\u0430",
    "qs:a1_alt":"Khersons'ka",
    "qs:a1r":"0",
    "qs:a2":"\u0411\u0456\u043b\u043e\u0437\u0435\u0440\u0441\u044c\u043a\u0438\u0439",
    "qs:a2_alt":"Bilozers'kyi",
    "qs:adm0":"\u0423\u043a\u0440\u0430\u0457\u043d\u0430",
    "qs:la_lc":"*",
    "qs:level":"locality",
    "qs:loc":"\u0422\u043e\u043c\u0438\u043d\u0430 \u0411\u0430\u043b\u043a\u0430",
    "qs:loc_alt":"Tomyna Balka",
    "qs:pop":0,
    "qs:type":"buffered point",
    "wof:name":"\u0422\u043e\u043c\u0438\u043d\u0430 \u0411\u0430\u043b\u043a\u0430",
    "wof:placetype":"locality"
},
  "geometry": {"coordinates":[32.312935,46.619797],"type":"Point"}
}