{
  "type": "Feature",
  "properties": {
    "gn:admin1_code":"11.0",
    "gn:admin2_code":"8449687",
    "gn:asciiname":"Okhotnich'e",
    "gn:country_code":"UA",
    "gn:dem":1167,
    "gn:elevation":"1160.0",
    "gn:feature_class":"P",
    "gn:feature_code":"PPL",
    "gn:name":"Okhotnich'e",
    "gn:population":17,
    "gn:timezone":"Europe/Simferopol",
    "iso:country":"UA",
    "name:crh_x_preferred":[
        "Ohotni\u00e7ye"
    ],
    "name:eng_x_preferred":[
        "Okhotnich\u2019e"
    ],
    "name:rus_x_preferred":[
        "\u041e\u0445\u043e\u0442\u043d\u0438\u0447\u044c\u0435"
    ],
    "name:ukr_x_preferred":[
        "\u041e\u0445\u043e\u0442\u043d\u0438\u0447\u0435"
    ],
    "wof:name":"Okhotnich'e",
    "wof:placetype":"locality",
    "wof:population":17
},
  "geometry": {"coordinates":[34.06873,44.47049000000001],"type":"Point"}
}