{
  "type": "Feature",
  "properties": {
    "gn:admin1_code":"2.0",
    "gn:asciiname":"Lustivka",
    "gn:country_code":"UA",
    "gn:dem":128,
    "gn:feature_class":"P",
    "gn:feature_code":"PPL",
    "gn:name":"Lustivka",
    "gn:population":0,
    "gn:timezone":"Europe/Kiev",
    "iso:country":"UA",
    "name:ukr_x_preferred":[
        "Lustivka"
    ],
    "name:ukr_x_variant":[
        "\u041b\u0443\u0441\u0442\u0456\u0432\u043a\u0430"
    ],
    "name:und_x_variant":[
        "Lustovka"
    ],
    "wof:name":"Lustivka",
    "wof:placetype":"locality"
},
  "geometry": {"coordinates":[31.90321,50.88957],"type":"Point"}
}