{
  "type": "Feature",
  "properties": {
    "gn:admin1_code":"11.0",
    "gn:admin2_code":"694905",
    "gn:admin3_code":"11153095.0",
    "gn:asciiname":"Harshyne",
    "gn:country_code":"UA",
    "gn:dem":11,
    "gn:feature_class":"P",
    "gn:feature_code":"PPL",
    "gn:name":"Harshyne",
    "gn:population":0,
    "gn:timezone":"Europe/Simferopol",
    "iso:country":"UA",
    "name:eng_x_preferred":[
        "Garshino"
    ],
    "name:ukr_x_preferred":[
        "Harshyne"
    ],
    "name:ukr_x_variant":[
        "\u0413\u0430\u0440\u0448\u0438\u043d\u0435"
    ],
    "name:und_x_variant":[
        "Biyuk-Aktachi",
        "Aktachi"
    ],
    "wof:name":"Harshyne",
    "wof:placetype":"locality"
},
  "geometry": {"coordinates":[33.59115,45.21602],"type":"Point"}
}