{
  "type": "Feature",
  "properties": {
    "gn:admin1_code":"2.0",
    "gn:asciiname":"Mokri Velychky",
    "gn:country_code":"UA",
    "gn:dem":147,
    "gn:feature_class":"P",
    "gn:feature_code":"PPL",
    "gn:name":"Mokri Velychky",
    "gn:population":0,
    "gn:timezone":"Europe/Kiev",
    "iso:country":"UA",
    "name:ukr_x_preferred":[
        "Mokri Velychky"
    ],
    "name:ukr_x_variant":[
        "\u041c\u043e\u043a\u0440\u0456 \u0412\u0435\u043b\u0438\u0447\u043a\u0438"
    ],
    "name:und_x_variant":[
        "Mokryye Velichki"
    ],
    "wof:name":"Mokri Velychky",
    "wof:placetype":"locality"
},
  "geometry": {"coordinates":[30.78389,51.61424],"type":"Point"}
}