{
  "type": "Feature",
  "properties": {
    "gn:admin1_code":"5.0",
    "gn:asciiname":"Vysokopillya",
    "gn:country_code":"UA",
    "gn:dem":173,
    "gn:feature_class":"P",
    "gn:feature_code":"PPL",
    "gn:name":"Vysokopillya",
    "gn:population":0,
    "gn:timezone":"Europe/Kiev",
    "iso:country":"UA",
    "name:rus_x_preferred":[
        "Vysokopol\u2019ye"
    ],
    "name:ukr_x_preferred":[
        "Vysokopillya"
    ],
    "name:ukr_x_variant":[
        "\u0412\u0438\u0441\u043e\u043a\u043e\u043f\u0456\u043b\u043b\u044f"
    ],
    "wof:name":"Vysokopillya",
    "wof:placetype":"locality"
},
  "geometry": {"coordinates":[37.07411,48.77083],"type":"Point"}
}