{
  "type": "Feature",
  "properties": {
    "iso:country":"UA",
    "name:eng_x_preferred":[
        "Dmitrovka"
    ],
    "name:hye_x_preferred":[
        "\u0534\u0574\u056b\u057f\u0580\u0578\u057e\u056f\u0561"
    ],
    "name:rus_x_historical":[
        "\u0427\u0451\u0440\u043d\u043e-\u041a\u043e\u0448"
    ],
    "name:rus_x_preferred":[
        "\u0414\u043c\u0438\u0442\u0440\u043e\u0432\u043a\u0430"
    ],
    "name:rus_x_variant":[
        "\u0427\u0451\u0440\u043d\u043e-\u041a\u043e\u0448"
    ],
    "name:ukr_x_preferred":[
        "\u0414\u043c\u0438\u0442\u0440\u0456\u0432\u043a\u0430"
    ],
    "qs:a0":"\u0423\u043a\u0440\u0430\u0457\u043d\u0430",
    "qs:a1":"*\u041a\u0440\u0438\u043c",
    "qs:a1_alt":"Krym",
    "qs:a1r":"0",
    "qs:a2":"\u0421\u043e\u0432\u0454\u0442\u0441\u044c\u043a\u0438\u0439",
    "qs:a2_alt":"Soviets'kyi",
    "qs:adm0":"\u0423\u043a\u0440\u0430\u0457\u043d\u0430",
    "qs:la_lc":"*",
    "qs:level":"locality",
    "qs:loc":"\u0414\u043c\u0438\u0442\u0440\u0456\u0432\u043a\u0430",
    "qs:loc_alt":"Dmytrivka",
    "qs:pop":0,
    "qs:type":"buffered point",
    "wd:wordcount":72,
    "wof:name":"\u0414\u043c\u0438\u0442\u0440\u0456\u0432\u043a\u0430",
    "wof:placetype":"locality"
},
  "geometry": {"coordinates":[35.053655,45.481889],"type":"Point"}
}