{
  "type": "Feature",
  "properties": {
    "gn:admin1_code":"19.0",
    "gn:asciiname":"Kotyra",
    "gn:country_code":"UA",
    "gn:dem":143,
    "gn:feature_class":"P",
    "gn:feature_code":"PPL",
    "gn:name":"Kotyra",
    "gn:population":0,
    "gn:timezone":"Europe/Kiev",
    "iso:country":"UA",
    "name:ukr_x_preferred":[
        "Kotyra"
    ],
    "name:ukr_x_variant":[
        "\u041a\u043e\u0442\u0438\u0440\u0430"
    ],
    "wof:name":"Kotyra",
    "wof:placetype":"locality"
},
  "geometry": {"coordinates":[25.78534,51.84859],"type":"Point"}
}