{
  "type": "Feature",
  "properties": {
    "gn:admin1_code":"27.0",
    "gn:asciiname":"Lyudvynivka",
    "gn:country_code":"UA",
    "gn:dem":144,
    "gn:feature_class":"P",
    "gn:feature_code":"PPL",
    "gn:name":"Lyudvynivka",
    "gn:population":0,
    "gn:timezone":"Europe/Kiev",
    "iso:country":"UA",
    "name:ukr_x_preferred":[
        "Lyudvynivka"
    ],
    "name:ukr_x_variant":[
        "\u041b\u044e\u0434\u0432\u0438\u043d\u0456\u0432\u043a\u0430"
    ],
    "name:und_x_variant":[
        "Lyudvinovka"
    ],
    "wof:name":"Lyudvynivka",
    "wof:placetype":"locality"
},
  "geometry": {"coordinates":[29.05428,51.51046],"type":"Point"}
}