{
  "type": "Feature",
  "properties": {
    "gn:admin1_code":"26.0",
    "gn:asciiname":"Vil'noulanivs'ke",
    "gn:country_code":"UA",
    "gn:dem":67,
    "gn:feature_class":"P",
    "gn:feature_code":"PPL",
    "gn:name":"Vil\u2019noulanivs\u2019ke",
    "gn:population":0,
    "gn:timezone":"Europe/Zaporozhye",
    "iso:country":"UA",
    "name:rus_x_preferred":[
        "Vol\u2019noulanovskoye"
    ],
    "name:rus_x_variant":[
        "Vil\u2019no-Ulyanovskiye",
        "\u0412\u043e\u043b\u044c\u043d\u043e\u0443\u043b\u0430\u043d\u043e\u0432\u0441\u043a\u043e\u0435"
    ],
    "name:ukr_x_preferred":[
        "Vil\u2019noulanivs\u2019ke"
    ],
    "name:ukr_x_variant":[
        "\u0412\u0456\u043b\u044c\u043d\u043e\u0443\u043b\u0430\u043d\u0456\u0432\u0441\u044c\u043a\u0435"
    ],
    "wof:name":"Vil'noulanivs'ke",
    "wof:placetype":"locality"
},
  "geometry": {"coordinates":[35.19584000000001,47.95698],"type":"Point"}
}