{
  "type": "Feature",
  "properties": {
    "gn:admin1_code":"1.0",
    "gn:asciiname":"Shabastivka",
    "gn:country_code":"UA",
    "gn:dem":229,
    "gn:feature_class":"P",
    "gn:feature_code":"PPL",
    "gn:name":"Shabastivka",
    "gn:population":0,
    "gn:timezone":"Europe/Kiev",
    "iso:country":"UA",
    "wof:name":"Shabastivka",
    "wof:placetype":"locality"
},
  "geometry": {"coordinates":[29.73199,49.05355],"type":"Point"}
}