{
  "type": "Feature",
  "properties": {
    "gn:admin1_code":"9.0",
    "gn:asciiname":"Ostashki",
    "gn:country_code":"UA",
    "gn:dem":301,
    "gn:feature_class":"P",
    "gn:feature_code":"PPL",
    "gn:name":"Ostashki",
    "gn:population":0,
    "gn:timezone":"Europe/Kiev",
    "iso:country":"UA",
    "wof:name":"Ostashki",
    "wof:placetype":"locality"
},
  "geometry": {"coordinates":[26.84595,49.50534],"type":"Point"}
}