{
  "type": "Feature",
  "properties": {
    "gn:admin1_code":"26.0",
    "gn:asciiname":"Sovyets'ke",
    "gn:country_code":"UA",
    "gn:dem":39,
    "gn:feature_class":"P",
    "gn:feature_code":"PPL",
    "gn:name":"Sovyets\u2019ke",
    "gn:population":0,
    "gn:timezone":"Europe/Zaporozhye",
    "iso:country":"UA",
    "name:ukr_x_preferred":[
        "Sovyets\u2019ke"
    ],
    "name:ukr_x_variant":[
        "\u0421\u043e\u0432\u0454\u0442\u0441\u044c\u043a\u0435"
    ],
    "name:und_x_variant":[
        "Sovetskoye"
    ],
    "wof:name":"Sovyets'ke",
    "wof:placetype":"locality"
},
  "geometry": {"coordinates":[35.66316,47.04404],"type":"Point"}
}