{
  "type": "Feature",
  "properties": {
    "gn:admin1_code":"18.0",
    "gn:asciiname":"Pelekhi",
    "gn:country_code":"UA",
    "gn:dem":68,
    "gn:feature_class":"P",
    "gn:feature_code":"PPL",
    "gn:name":"Pelekhi",
    "gn:population":0,
    "gn:timezone":"Europe/Kiev",
    "iso:country":"UA",
    "wof:name":"Pelekhi",
    "wof:placetype":"locality"
},
  "geometry": {"coordinates":[34.26667,48.98333],"type":"Point"}
}