{
  "type": "Feature",
  "properties": {
    "gn:admin1_code":"27.0",
    "gn:asciiname":"Medvedeve",
    "gn:country_code":"UA",
    "gn:dem":201,
    "gn:feature_class":"P",
    "gn:feature_code":"PPL",
    "gn:name":"Medvedeve",
    "gn:population":0,
    "gn:timezone":"Europe/Kiev",
    "iso:country":"UA",
    "name:ukr_x_preferred":[
        "Medvedeve"
    ],
    "name:ukr_x_variant":[
        "\u041c\u0435\u0434\u0432\u0435\u0434\u0435\u0432\u0435"
    ],
    "name:und_x_variant":[
        "Sloboda Medvedovo",
        "Medvedovo",
        "Medvedevo"
    ],
    "wof:name":"Medvedeve",
    "wof:placetype":"locality"
},
  "geometry": {"coordinates":[27.67776,50.88937],"type":"Point"}
}