{
  "type": "Feature",
  "properties": {
    "gn:admin1_code":"23.0",
    "gn:asciiname":"Deresheva",
    "gn:country_code":"UA",
    "gn:dem":248,
    "gn:feature_class":"P",
    "gn:feature_code":"PPL",
    "gn:name":"Deresh\u00ebva",
    "gn:population":0,
    "gn:timezone":"Europe/Kiev",
    "iso:country":"UA",
    "wof:name":"Deresheva",
    "wof:placetype":"locality"
},
  "geometry": {"coordinates":[27.51689,48.77381],"type":"Point"}
}