{
  "type": "Feature",
  "properties": {
    "gn:admin1_code":"8.0",
    "gn:asciiname":"Tverdomedove",
    "gn:country_code":"UA",
    "gn:dem":17,
    "gn:feature_class":"P",
    "gn:feature_code":"PPL",
    "gn:name":"Tverdomedove",
    "gn:population":0,
    "gn:timezone":"Europe/Kiev",
    "iso:country":"UA",
    "name:ukr_x_preferred":[
        "Tverdomedove"
    ],
    "name:ukr_x_variant":[
        "\u0422\u0432\u0435\u0440\u0434\u043e\u043c\u0435\u0434\u043e\u0432\u0435"
    ],
    "name:und_x_variant":[
        "Tverdomedovka"
    ],
    "wof:name":"Tverdomedove",
    "wof:placetype":"locality"
},
  "geometry": {"coordinates":[33.28461,47.35217],"type":"Point"}
}