{
  "type": "Feature",
  "properties": {
    "gn:admin1_code":"15.0",
    "gn:asciiname":"Naditychi",
    "gn:country_code":"UA",
    "gn:dem":252,
    "gn:feature_class":"P",
    "gn:feature_code":"PPL",
    "gn:name":"Naditychi",
    "gn:population":0,
    "gn:timezone":"Europe/Kiev",
    "iso:country":"UA",
    "name:rus_x_preferred":[
        "\u041d\u0430\u0434\u0435\u0442\u044b\u0447\u0438"
    ],
    "name:ukr_x_preferred":[
        "Naditychi"
    ],
    "name:ukr_x_variant":[
        "\u041d\u0430\u0434\u0456\u0442\u0438\u0447\u0456"
    ],
    "name:und_x_variant":[
        "Nadyatychi",
        "Nadyatche",
        "Nadetychi"
    ],
    "wof:name":"Naditychi",
    "wof:placetype":"locality"
},
  "geometry": {"coordinates":[23.97146,49.47243],"type":"Point"}
}