{
  "type": "Feature",
  "properties": {
    "iso:country":"UA",
    "name:ara_x_preferred":[
        "\u0634\u064a\u0628\u064a\u062a\u064a\u0641\u0643\u0627"
    ],
    "name:bel_x_preferred":[
        "\u0428\u044d\u043f\u044d\u0446\u0456\u045e\u043a\u0430"
    ],
    "name:bul_x_preferred":[
        "\u0428\u0435\u043f\u0435\u0442\u043e\u0432\u043a\u0430"
    ],
    "name:ces_x_preferred":[
        "\u0160epetivka"
    ],
    "name:deu_x_preferred":[
        "Schepetiwka"
    ],
    "name:eng_x_preferred":[
        "Shepetivka"
    ],
    "name:fas_x_preferred":[
        "\u0634\u067e\u062a\u06cc\u0641\u06a9\u0627"
    ],
    "name:fin_x_preferred":[
        "\u0160epetivka"
    ],
    "name:fra_x_preferred":[
        "Chepetivka"
    ],
    "name:heb_x_preferred":[
        "\u05e9\u05e4\u05d8\u05d9\u05d1\u05e7\u05d4"
    ],
    "name:hsb_x_preferred":[
        "\u0160epetiwka"
    ],
    "name:hun_x_preferred":[
        "Sepetyivka"
    ],
    "name:hye_x_preferred":[
        "\u0547\u0565\u057a\u0565\u057f\u0578\u057e\u056f\u0561"
    ],
    "name:ita_x_preferred":[
        "\u0160epet\u00efvka"
    ],
    "name:jpn_x_preferred":[
        "\u30b7\u30a7\u30da\u30c6\u30a3\u30a6\u30ab"
    ],
    "name:kat_x_preferred":[
        "\u10e8\u10d4\u10de\u10d4\u10e2\u10dd\u10d5\u10d9\u10d0"
    ],
    "name:lav_x_preferred":[
        "\u0160epetivka"
    ],
    "name:lit_x_preferred":[
        "\u0160epetivka"
    ],
    "name:nld_x_preferred":[
        "Shepetivka"
    ],
    "name:nno_x_preferred":[
        "Sjepetivka"
    ],
    "name:pol_x_preferred":[
        "Szepet\u00f3wka"
    ],
    "name:ron_x_preferred":[
        "\u0218epetivka"
    ],
    "name:rus_x_preferred":[
        "\u0428\u0435\u043f\u0435\u0442\u043e\u0432\u043a\u0430"
    ],
    "name:slk_x_preferred":[
        "\u0160epetivka"
    ],
    "name:srp_x_preferred":[
        "\u0428\u0435\u043f\u0435\u0442\u0456\u0432\u043a\u0430"
    ],
    "name:swe_x_preferred":[
        "Sjepetivka"
    ],
    "name:tat_x_preferred":[
        "\u0428\u0435\u043f\u0435\u0442\u0438\u0432\u043a\u0430"
    ],
    "name:ukr_x_preferred":[
        "\u0428\u0435\u043f\u0435\u0442\u0456\u0432\u043a\u0430"
    ],
    "name:unk_x_variant":[
        "Shepetovka"
    ],
    "name:vie_x_preferred":[
        "Shepetivka"
    ],
    "name:yid_x_preferred":[
        "\u05e9\u05e2\u05e4\u05e2\u05d8\u05d9\u05d5\u05d5\u05e7\u05e2"
    ],
    "name:zho_x_preferred":[
        "\u820d\u4f69\u8482\u592b\u5361"
    ],
    "qs:a0":"\u0423\u043a\u0440\u0430\u0457\u043d\u0430",
    "qs:a1":"*\u0425\u043c\u0435\u043b\u044c\u043d\u0438\u0446\u044c\u043a\u0430",
    "qs:a1_alt":"Khmel'nyts'ka",
    "qs:a1r":"0",
    "qs:a2":"\u0428\u0435\u043f\u0435\u0442\u0456\u0432\u0441\u044c\u043a\u0438\u0439",
    "qs:a2_alt":"Shepetivs'kyi",
    "qs:adm0":"\u0423\u043a\u0440\u0430\u0457\u043d\u0430",
    "qs:la_lc":"*",
    "qs:level":"locality",
    "qs:loc":"\u0428\u0435\u043f\u0435\u0442\u0456\u0432\u043a\u0430",
    "qs:loc_alt":"Shepetivka",
    "qs:pop":0,
    "qs:type":"buffered point",
    "wd:wordcount":320,
    "wof:name":"\u0428\u0435\u043f\u0435\u0442\u0456\u0432\u043a\u0430",
    "wof:placetype":"locality"
},
  "geometry": {"coordinates":[27.072329,50.170592],"type":"Point"}
}