{
  "type": "Feature",
  "properties": {
    "iso:country":"UA",
    "name:eng_x_preferred":[
        "Kamburleyevka"
    ],
    "name:rus_x_preferred":[
        "\u041a\u0430\u043c\u0431\u0443\u0440\u043b\u0438\u0435\u0432\u043a\u0430"
    ],
    "name:ukr_x_preferred":[
        "Kamburliyivka"
    ],
    "name:ukr_x_variant":[
        "\u041a\u0430\u043c\u0431\u0443\u0440\u043b\u0456\u0457\u0432\u043a\u0430"
    ],
    "qs:a0":"\u0423\u043a\u0440\u0430\u0457\u043d\u0430",
    "qs:a1":"*\u041a\u0456\u0440\u043e\u0432\u043e\u0433\u0440\u0430\u0434\u0441\u044c\u043a\u0430",
    "qs:a1_alt":"Kirovohrads'ka",
    "qs:a1r":"0",
    "qs:a2":"\u041e\u043d\u0443\u0444\u0440\u0456\u0457\u0432\u0441\u044c\u043a\u0438\u0439",
    "qs:a2_alt":"Onufriivs'kyi",
    "qs:adm0":"\u0423\u043a\u0440\u0430\u0457\u043d\u0430",
    "qs:la_lc":"*",
    "qs:level":"locality",
    "qs:loc":"\u041a\u0430\u043c\u0431\u0443\u0440\u043b\u0456\u0457\u0432\u043a\u0430",
    "qs:loc_alt":"Kamburliivka",
    "qs:pop":0,
    "qs:type":"buffered point",
    "wof:name":"\u041a\u0430\u043c\u0431\u0443\u0440\u043b\u0456\u0457\u0432\u043a\u0430",
    "wof:placetype":"locality"
},
  "geometry": {"coordinates":[33.399864,48.865197],"type":"Point"}
}