{
  "type": "Feature",
  "properties": {
    "gn:gn_country":"UA",
    "gn:gn_fcode":"PPL",
    "gn:gn_pop":10673,
    "gn:population":10673,
    "iso:country":"UA",
    "name:bul_x_preferred":[
        "\u041a\u0430\u043b\u0430\u043d\u0447\u0430\u043a"
    ],
    "name:ceb_x_preferred":[
        "Kalanchak"
    ],
    "name:crh_x_preferred":[
        "Qalan\u00e7aq"
    ],
    "name:deu_x_preferred":[
        "Kalantschak"
    ],
    "name:eng_x_preferred":[
        "Kalanchak"
    ],
    "name:lav_x_preferred":[
        "Kalan\u010daka"
    ],
    "name:pol_x_preferred":[
        "Ka\u0142anczak"
    ],
    "name:rus_x_preferred":[
        "\u041a\u0430\u043b\u0430\u043d\u0447\u0430\u043a"
    ],
    "name:ukr_x_preferred":[
        "\u041a\u0430\u043b\u0430\u043d\u0447\u0430\u043a"
    ],
    "name:zho_x_preferred":[
        "\u5361\u862d\u6070\u514b"
    ],
    "qs_pg:aaroncc":"UA",
    "qs_pg:gn_country":"UA",
    "qs_pg:gn_fcode":"PPL",
    "qs_pg:gn_pop":10673,
    "qs_pg:name":"Kalanchak",
    "qs_pg:photos_9r":0,
    "qs_pg:photos_sr":0,
    "qs_pg:pop_sr":6,
    "qs_pg:qs_pg_placetype":"locality",
    "wof:name":"Kalanchak",
    "wof:placetype":"locality",
    "wof:population":10673
},
  "geometry": {"coordinates":[33.2907,46.25623],"type":"Point"}
}