{
  "type": "Feature",
  "properties": {
    "iso:country":"UA",
    "name:bel_x_preferred":[
        "\u0421\u0442\u044d\u0446\u044c\u043a\u0456\u045e\u043a\u0430"
    ],
    "name:cat_x_preferred":[
        "Stetskivka"
    ],
    "name:che_x_preferred":[
        "\u0421\u0442\u0435\u0446\u043a\u043e\u0432\u043a\u0430"
    ],
    "name:deu_x_preferred":[
        "Stezkiwka"
    ],
    "name:eng_x_preferred":[
        "Stets'kivka"
    ],
    "name:eng_x_variant":[
        "Stetskivka"
    ],
    "name:fin_x_preferred":[
        "St\u0435tsk\u0456vk\u0430"
    ],
    "name:hye_x_preferred":[
        "\u054d\u057f\u0565\u0581\u056f\u0578\u057e\u056f\u0561"
    ],
    "name:nno_x_preferred":[
        "Stetskivka"
    ],
    "name:nob_x_preferred":[
        "Stetskivka"
    ],
    "name:pol_x_preferred":[
        "Ste\u0107kiwka"
    ],
    "name:ron_x_preferred":[
        "Ste\u021bkivka"
    ],
    "name:rus_x_preferred":[
        "\u0421\u0442\u0435\u0446\u043a\u043e\u0432\u043a\u0430"
    ],
    "name:ukr_x_preferred":[
        "\u0421\u0442\u0435\u0446\u044c\u043a\u0456\u0432\u043a\u0430"
    ],
    "name:und_x_variant":[
        "Stetskowka"
    ],
    "name:zho_x_preferred":[
        "\u65af\u6377\u9f4a\u57fa\u592b\u5361"
    ],
    "qs:a0":"\u0423\u043a\u0440\u0430\u0457\u043d\u0430",
    "qs:a1":"*\u0421\u0443\u043c\u0441\u044c\u043a\u0430",
    "qs:a1_alt":"Sums'ka",
    "qs:a1r":"0",
    "qs:a2":"\u0421\u0443\u043c\u0441\u044c\u043a\u0438\u0439",
    "qs:a2_alt":"Sums'kyi",
    "qs:adm0":"\u0423\u043a\u0440\u0430\u0457\u043d\u0430",
    "qs:la_lc":"*",
    "qs:level":"locality",
    "qs:loc":"\u0421\u0442\u0435\u0446\u044c\u043a\u0456\u0432\u043a\u0430",
    "qs:loc_alt":"Stets'kivka",
    "qs:pop":0,
    "qs:type":"buffered point",
    "wof:name":"\u0421\u0442\u0435\u0446\u044c\u043a\u0456\u0432\u043a\u0430",
    "wof:placetype":"locality"
},
  "geometry": {"coordinates":[34.78417,51.012047],"type":"Point"}
}