{
  "type": "Feature",
  "properties": {
    "iso:country":"UA",
    "name:deu_x_preferred":[
        "Schyrokolaniwka"
    ],
    "name:eng_x_preferred":[
        "Shyrokolanivka"
    ],
    "name:hye_x_preferred":[
        "\u0547\u056b\u0580\u0578\u056f\u0578\u056c\u0561\u0576\u0578\u057e\u056f\u0561"
    ],
    "name:ita_x_preferred":[
        "\u0160yrokolanivka"
    ],
    "name:jpn_x_preferred":[
        "\u30b7\u30ed\u30b3\u30e9\u30cb\u30a6\u30ab"
    ],
    "name:lav_x_preferred":[
        "\u0160irokola\u0146ivka"
    ],
    "name:ron_x_preferred":[
        "\u0218\u00eerokolanivka"
    ],
    "name:ron_x_variant":[
        "\u0414\u043d\u0456\u043f\u0440\u043e\u0432\u043a\u0430"
    ],
    "name:rus_x_preferred":[
        "\u0428\u0438\u0440\u043e\u043a\u043e\u043b\u0430\u043d\u043e\u0432\u043a\u0430"
    ],
    "name:ukr_x_preferred":[
        "\u0428\u0438\u0440\u043e\u043a\u043e\u043b\u0430\u043d\u0456\u0432\u043a\u0430"
    ],
    "name:zho_x_preferred":[
        "\u4ec0\u7f85\u79d1\u62c9\u5c3c\u592b\u5361"
    ],
    "qs:a0":"\u0423\u043a\u0440\u0430\u0457\u043d\u0430",
    "qs:a1":"*\u041c\u0438\u043a\u043e\u043b\u0430\u0457\u0432\u0441\u044c\u043a\u0430",
    "qs:a1_alt":"Mykolaivs'ka",
    "qs:a1r":"0",
    "qs:a2":"\u0412\u0435\u0441\u0435\u043b\u0438\u043d\u0456\u0432\u0441\u044c\u043a\u0438\u0439",
    "qs:a2_alt":"Veselynivs'kyi",
    "qs:adm0":"\u0423\u043a\u0440\u0430\u0457\u043d\u0430",
    "qs:la_lc":"*",
    "qs:level":"locality",
    "qs:loc":"\u0428\u0438\u0440\u043e\u043a\u043e\u043b\u0430\u043d\u0456\u0432\u043a\u0430",
    "qs:loc_alt":"Shyrokolanivka",
    "qs:pop":0,
    "qs:type":"buffered point",
    "wd:wordcount":337,
    "wof:name":"\u0428\u0438\u0440\u043e\u043a\u043e\u043b\u0430\u043d\u0456\u0432\u043a\u0430",
    "wof:placetype":"locality"
},
  "geometry": {"coordinates":[31.429388,47.164289],"type":"Point"}
}