{
  "type": "Feature",
  "properties": {
    "gn:admin1_code":"23.0",
    "gn:asciiname":"Napadovka",
    "gn:country_code":"UA",
    "gn:dem":285,
    "gn:feature_class":"P",
    "gn:feature_code":"PPL",
    "gn:name":"Napadovka",
    "gn:population":0,
    "gn:timezone":"Europe/Kiev",
    "iso:country":"UA",
    "wof:name":"Napadovka",
    "wof:placetype":"locality"
},
  "geometry": {"coordinates":[28.55506,49.6138],"type":"Point"}
}