{
  "type": "Feature",
  "properties": {
    "gn:admin1_code":"21.0",
    "gn:asciiname":"Topoli",
    "gn:country_code":"UA",
    "gn:dem":184,
    "gn:feature_class":"P",
    "gn:feature_code":"PPL",
    "gn:name":"Topoli",
    "gn:population":0,
    "gn:timezone":"Europe/Kiev",
    "iso:country":"UA",
    "wof:name":"Topoli",
    "wof:placetype":"locality"
},
  "geometry": {"coordinates":[34.19931,51.75293],"type":"Point"}
}