{
  "type": "Feature",
  "properties": {
    "gn:admin1_code":"21.0",
    "gn:asciiname":"Topoli",
    "gn:country_code":"UA",
    "gn:dem":184,
    "gn:feature_class":"P",
    "gn:feature_code":"PPL",
    "gn:name":"Topoli",
    "gn:population":0,
    "gn:timezone":"Europe/Kiev",
    "iso:country":"UA",
    "name:bul_x_preferred":[
        "\u0422\u043e\u043f\u043e\u043b\u0438"
    ],
    "name:ceb_x_preferred":[
        "Topoli"
    ],
    "name:fas_x_preferred":[
        "\u062a\u0648\u067e\u0648\u0644\u06cc"
    ],
    "name:kaz_x_preferred":[
        "\u0422\u043e\u043f\u043e\u043b\u0438"
    ],
    "name:ron_x_preferred":[
        "Topoli"
    ],
    "name:rus_x_preferred":[
        "\u0422\u043e\u043f\u043e\u043b\u0438"
    ],
    "name:swe_x_preferred":[
        "Topoli"
    ],
    "name:ukr_x_preferred":[
        "\u0422\u043e\u043f\u043e\u043b\u0456"
    ],
    "wof:name":"Topoli",
    "wof:placetype":"locality"
},
  "geometry": {"coordinates":[34.19931,51.75293],"type":"Point"}
}