{
  "type": "Feature",
  "properties": {
    "gn:admin1_code":"27.0",
    "gn:asciiname":"Ploska",
    "gn:country_code":"UA",
    "gn:dem":207,
    "gn:feature_class":"P",
    "gn:feature_code":"PPL",
    "gn:name":"Ploska",
    "gn:population":0,
    "gn:timezone":"Europe/Kiev",
    "iso:country":"UA",
    "name:ukr_x_preferred":[
        "Ploska"
    ],
    "name:ukr_x_variant":[
        "\u041f\u043b\u043e\u0441\u043a\u0430"
    ],
    "name:und_x_variant":[
        "Ploskoye"
    ],
    "wof:name":"Ploska",
    "wof:placetype":"locality"
},
  "geometry": {"coordinates":[29.29181,49.7372],"type":"Point"}
}