{
  "type": "Feature",
  "properties": {
    "gn:admin1_code":"7.0",
    "gn:asciiname":"Krutoyarivka",
    "gn:country_code":"UA",
    "gn:dem":147,
    "gn:feature_class":"P",
    "gn:feature_code":"PPL",
    "gn:name":"Krutoyarivka",
    "gn:population":0,
    "gn:timezone":"Europe/Kiev",
    "iso:country":"UA",
    "name:rus_x_preferred":[
        "\u041a\u0440\u0443\u0442\u043e\u044f\u0440\u043e\u0432\u043a\u0430"
    ],
    "name:ukr_x_preferred":[
        "Krutoyarivka"
    ],
    "name:ukr_x_variant":[
        "\u041a\u0440\u0443\u0442\u043e\u044f\u0440\u0456\u0432\u043a\u0430"
    ],
    "name:und_x_variant":[
        "Krutoyarovka"
    ],
    "wof:name":"Krutoyarivka",
    "wof:placetype":"locality"
},
  "geometry": {"coordinates":[35.69527,49.31282],"type":"Point"}
}