{
  "type": "Feature",
  "properties": {
    "gn:admin1_code":"23.0",
    "gn:asciiname":"Vanzhuly",
    "gn:country_code":"UA",
    "gn:dem":261,
    "gn:feature_class":"P",
    "gn:feature_code":"PPL",
    "gn:name":"Vanzhuly",
    "gn:population":0,
    "gn:timezone":"Europe/Kiev",
    "iso:country":"UA",
    "wof:name":"Vanzhuly",
    "wof:placetype":"locality"
},
  "geometry": {"coordinates":[28.41667,49.33333],"type":"Point"}
}