{
  "type": "Feature",
  "properties": {
    "gn:admin1_code":"2.0",
    "gn:asciiname":"Dibrivka",
    "gn:country_code":"UA",
    "gn:dem":114,
    "gn:feature_class":"P",
    "gn:feature_code":"PPL",
    "gn:name":"Dibrivka",
    "gn:population":0,
    "gn:timezone":"Europe/Kiev",
    "iso:country":"UA",
    "name:ukr_x_preferred":[
        "Dibrivka"
    ],
    "name:ukr_x_variant":[
        "\u0414\u0456\u0431\u0440\u0456\u0432\u043a\u0430"
    ],
    "name:und_x_variant":[
        "Dubrovka"
    ],
    "wof:name":"Dibrivka",
    "wof:placetype":"locality"
},
  "geometry": {"coordinates":[32.11931,51.42552],"type":"Point"}
}