{
  "type": "Feature",
  "properties": {
    "gn:admin1_code":"13.0",
    "gn:asciiname":"Ustynkova Hreblya",
    "gn:country_code":"UA",
    "gn:dem":99,
    "gn:feature_class":"P",
    "gn:feature_code":"PPL",
    "gn:name":"Ustynkova Hreblya",
    "gn:population":0,
    "gn:timezone":"Europe/Kiev",
    "iso:country":"UA",
    "name:ukr_x_preferred":[
        "Ustynkova Hreblya"
    ],
    "name:ukr_x_variant":[
        "\u0423\u0441\u0442\u0438\u043d\u043a\u043e\u0432\u0430 \u0413\u0440\u0435\u0431\u043b\u044f"
    ],
    "name:und_x_variant":[
        "Ustinkova Greblya"
    ],
    "wof:name":"Ustynkova Hreblya",
    "wof:placetype":"locality"
},
  "geometry": {"coordinates":[31.29726,50.28855],"type":"Point"}
}