{
  "type": "Feature",
  "properties": {
    "gn:admin1_code":"27.0",
    "gn:asciiname":"Vynarivka",
    "gn:country_code":"UA",
    "gn:dem":183,
    "gn:feature_class":"P",
    "gn:feature_code":"PPL",
    "gn:name":"Vynarivka",
    "gn:population":0,
    "gn:timezone":"Europe/Kiev",
    "iso:country":"UA",
    "name:ukr_x_preferred":[
        "Vynarivka"
    ],
    "name:ukr_x_variant":[
        "\u0412\u0438\u043d\u0430\u0440\u0456\u0432\u043a\u0430"
    ],
    "name:und_x_variant":[
        "Vinarovka"
    ],
    "wof:name":"Vynarivka",
    "wof:placetype":"locality"
},
  "geometry": {"coordinates":[28.867,50.8607],"type":"Point"}
}