{
  "type": "Feature",
  "properties": {
    "gn:admin1_code":"15.0",
    "gn:asciiname":"Kolonitsa",
    "gn:country_code":"UA",
    "gn:dem":243,
    "gn:feature_class":"P",
    "gn:feature_code":"PPL",
    "gn:name":"Kolonitsa",
    "gn:population":0,
    "gn:timezone":"Europe/Kiev",
    "iso:country":"UA",
    "name:und_x_variant":[
        "Klonitsy",
        "Klonitse",
        "Kolonitsa"
    ],
    "wof:name":"Kolonitsa",
    "wof:placetype":"locality"
},
  "geometry": {"coordinates":[23.3168,50.07333],"type":"Point"}
}