{
  "type": "Feature",
  "properties": {
    "gn:admin1_code":"15.0",
    "gn:asciiname":"Trushevichi",
    "gn:country_code":"UA",
    "gn:dem":243,
    "gn:feature_class":"P",
    "gn:feature_code":"PPL",
    "gn:name":"Trushevichi",
    "gn:population":0,
    "gn:timezone":"Europe/Kiev",
    "iso:country":"UA",
    "name:und_x_variant":[
        "Trushovitse",
        "Trushevichi"
    ],
    "wof:name":"Trushevichi",
    "wof:placetype":"locality"
},
  "geometry": {"coordinates":[22.78135,49.64206],"type":"Point"}
}