{
  "type": "Feature",
  "properties": {
    "gn:admin1_code":"14.0",
    "gn:asciiname":"Holubivs'ke",
    "gn:country_code":"UA",
    "gn:dem":81,
    "gn:feature_class":"P",
    "gn:feature_code":"PPL",
    "gn:name":"Holubivs\u2019ke",
    "gn:population":0,
    "gn:timezone":"Europe/Zaporozhye",
    "iso:country":"UA",
    "name:ukr_x_preferred":[
        "Holubivs\u2019ke"
    ],
    "name:ukr_x_variant":[
        "\u0413\u043e\u043b\u0443\u0431\u0456\u0432\u0441\u044c\u043a\u0435"
    ],
    "name:und_x_variant":[
        "Golubovka"
    ],
    "wof:name":"Holubivs'ke",
    "wof:placetype":"locality"
},
  "geometry": {"coordinates":[38.64608,48.6919],"type":"Point"}
}