{
  "type": "Feature",
  "properties": {
    "gn:admin1_code":"1.0",
    "gn:asciiname":"Kononcha",
    "gn:country_code":"UA",
    "gn:dem":99,
    "gn:feature_class":"P",
    "gn:feature_code":"PPL",
    "gn:name":"Kononcha",
    "gn:population":0,
    "gn:timezone":"Europe/Kiev",
    "iso:country":"UA",
    "wof:name":"Kononcha",
    "wof:placetype":"locality"
},
  "geometry": {"coordinates":[31.46657,49.64889],"type":"Point"}
}