{
  "type": "Feature",
  "properties": {
    "gn:admin1_code":"2.0",
    "gn:asciiname":"Vyshnivka",
    "gn:country_code":"UA",
    "gn:dem":133,
    "gn:feature_class":"P",
    "gn:feature_code":"PPL",
    "gn:name":"Vyshnivka",
    "gn:population":0,
    "gn:timezone":"Europe/Kiev",
    "iso:country":"UA",
    "name:rus_x_preferred":[
        "Vishn\u00ebvka"
    ],
    "name:ukr_x_preferred":[
        "Vyshnivka"
    ],
    "name:ukr_x_variant":[
        "\u0412\u0438\u0448\u043d\u0456\u0432\u043a\u0430"
    ],
    "wof:name":"Vyshnivka",
    "wof:placetype":"locality"
},
  "geometry": {"coordinates":[32.28042,50.96404],"type":"Point"}
}