{
  "type": "Feature",
  "properties": {
    "gn:admin1_code":"7.0",
    "gn:asciiname":"Mykolayivka",
    "gn:country_code":"UA",
    "gn:dem":190,
    "gn:feature_class":"P",
    "gn:feature_code":"PPL",
    "gn:name":"Mykolayivka",
    "gn:population":0,
    "gn:timezone":"Europe/Kiev",
    "iso:country":"UA",
    "name:ukr_x_preferred":[
        "Mykolayivka"
    ],
    "name:ukr_x_variant":[
        "\u041c\u0438\u043a\u043e\u043b\u0430\u0457\u0432\u043a\u0430"
    ],
    "wof:name":"Mykolayivka",
    "wof:placetype":"locality"
},
  "geometry": {"coordinates":[37.39088,50.12186],"type":"Point"}
}