{
  "type": "Feature",
  "properties": {
    "gn:admin1_code":"27.0",
    "gn:asciiname":"Pavelky",
    "gn:country_code":"UA",
    "gn:dem":227,
    "gn:feature_class":"P",
    "gn:feature_code":"PPL",
    "gn:name":"Pavelky",
    "gn:population":0,
    "gn:timezone":"Europe/Kiev",
    "iso:country":"UA",
    "name:ukr_x_preferred":[
        "Pavelky"
    ],
    "name:ukr_x_variant":[
        "\u041f\u0430\u0432\u0435\u043b\u043a\u0438"
    ],
    "name:und_x_variant":[
        "Pavelki"
    ],
    "wof:name":"Pavelky",
    "wof:placetype":"locality"
},
  "geometry": {"coordinates":[29.087,49.95052],"type":"Point"}
}