{
  "type": "Feature",
  "properties": {
    "gn:admin1_code":"7.0",
    "gn:asciiname":"Zolotukhivka",
    "gn:country_code":"UA",
    "gn:dem":106,
    "gn:feature_class":"P",
    "gn:feature_code":"PPL",
    "gn:name":"Zolotukhivka",
    "gn:population":0,
    "gn:timezone":"Europe/Kiev",
    "iso:country":"UA",
    "name:rus_x_preferred":[
        "\u0417\u043e\u043b\u043e\u0442\u0443\u0445\u043e\u0432\u043a\u0430"
    ],
    "name:ukr_x_preferred":[
        "Zolotukhivka"
    ],
    "name:ukr_x_variant":[
        "\u0417\u043e\u043b\u043e\u0442\u0443\u0445\u0456\u0432\u043a\u0430"
    ],
    "name:und_x_variant":[
        "Zolotukhovka"
    ],
    "wof:name":"Zolotukhivka",
    "wof:placetype":"locality"
},
  "geometry": {"coordinates":[35.81814,49.46378],"type":"Point"}
}