{
  "type": "Feature",
  "properties": {
    "gn:admin1_code":"21.0",
    "gn:asciiname":"Zabuhy",
    "gn:country_code":"UA",
    "gn:dem":177,
    "gn:feature_class":"P",
    "gn:feature_code":"PPL",
    "gn:name":"Zabuhy",
    "gn:population":0,
    "gn:timezone":"Europe/Kiev",
    "iso:country":"UA",
    "name:ukr_x_preferred":[
        "Zabuhy"
    ],
    "name:ukr_x_variant":[
        "\u0417\u0430\u0431\u0443\u0433\u0438"
    ],
    "name:und_x_variant":[
        "Zabugi"
    ],
    "wof:name":"Zabuhy",
    "wof:placetype":"locality"
},
  "geometry": {"coordinates":[34.55560999999999,50.48675],"type":"Point"}
}