{
  "type": "Feature",
  "properties": {
    "gn:admin1_code":"4.0",
    "gn:asciiname":"Vydvyzhenets'",
    "gn:country_code":"UA",
    "gn:dem":136,
    "gn:feature_class":"P",
    "gn:feature_code":"PPL",
    "gn:name":"Vydvyzhenets\u2019",
    "gn:population":0,
    "gn:timezone":"Europe/Kiev",
    "iso:country":"UA",
    "name:ukr_x_preferred":[
        "Vydvyzhenets\u2019"
    ],
    "name:ukr_x_variant":[
        "\u0412\u0438\u0434\u0432\u0438\u0436\u0435\u043d\u0435\u0446\u044c"
    ],
    "name:und_x_variant":[
        "Vydvizhenets"
    ],
    "wof:name":"Vydvyzhenets'",
    "wof:placetype":"locality"
},
  "geometry": {"coordinates":[35.27735999999999,48.9444],"type":"Point"}
}