{
  "type": "Feature",
  "properties": {
    "gn:admin1_code":"21.0",
    "gn:asciiname":"Seleznivka",
    "gn:country_code":"UA",
    "gn:dem":128,
    "gn:feature_class":"P",
    "gn:feature_code":"PPL",
    "gn:name":"Seleznivka",
    "gn:population":0,
    "gn:timezone":"Europe/Kiev",
    "iso:country":"UA",
    "name:ukr_x_preferred":[
        "Seleznivka"
    ],
    "name:ukr_x_variant":[
        "\u0421\u0435\u043b\u0435\u0437\u043d\u0456\u0432\u043a\u0430"
    ],
    "name:und_x_variant":[
        "Seleznevka"
    ],
    "wof:name":"Seleznivka",
    "wof:placetype":"locality"
},
  "geometry": {"coordinates":[33.8141,51.3362],"type":"Point"}
}