{
  "type": "Feature",
  "properties": {
    "gn:admin1_code":"23.0",
    "gn:asciiname":"Voskodavintsy",
    "gn:country_code":"UA",
    "gn:dem":297,
    "gn:feature_class":"P",
    "gn:feature_code":"PPL",
    "gn:name":"Voskodavintsy",
    "gn:population":0,
    "gn:timezone":"Europe/Kiev",
    "iso:country":"UA",
    "wof:name":"Voskodavintsy",
    "wof:placetype":"locality"
},
  "geometry": {"coordinates":[28.96993,49.53318],"type":"Point"}
}