{
  "type": "Feature",
  "properties": {
    "gn:admin1_code":"21.0",
    "gn:asciiname":"Kozinka",
    "gn:country_code":"UA",
    "gn:dem":149,
    "gn:feature_class":"P",
    "gn:feature_code":"PPL",
    "gn:name":"Kozinka",
    "gn:population":0,
    "gn:timezone":"Europe/Kiev",
    "iso:country":"UA",
    "name:che_x_preferred":[
        "\u041a\u043e\u0437\u0438\u043d\u043a\u0430"
    ],
    "name:rus_x_preferred":[
        "\u041a\u043e\u0437\u0438\u043d\u043a\u0430"
    ],
    "name:tgk_x_preferred":[
        "\u041a\u043e\u0437\u0438\u043d\u043a\u0430"
    ],
    "wof:name":"Kozinka",
    "wof:placetype":"locality"
},
  "geometry": {"coordinates":[34.05860999999999,51.43194],"type":"Point"}
}