{
  "type": "Feature",
  "properties": {
    "gn:admin1_code":"16.0",
    "gn:asciiname":"Vladimiro-Matveyevka",
    "gn:cc2":"UA",
    "gn:country_code":"UA",
    "gn:dem":103,
    "gn:feature_class":"P",
    "gn:feature_code":"PPL",
    "gn:name":"Vladimiro-Matveyevka",
    "gn:population":0,
    "gn:timezone":"Europe/Kiev",
    "iso:country":"UA",
    "name:und_x_variant":[
        "Vladimiro-Matayeyevka",
        "Vladimiro-Matveyevka"
    ],
    "wof:name":"Vladimiro-Matveyevka",
    "wof:placetype":"locality"
},
  "geometry": {"coordinates":[32.06667,47.73333],"type":"Point"}
}