{
  "type": "Feature",
  "properties": {
    "gn:admin1_code":"18.0",
    "gn:asciiname":"Makhnivka",
    "gn:country_code":"UA",
    "gn:dem":67,
    "gn:feature_class":"P",
    "gn:feature_code":"PPL",
    "gn:name":"Makhnivka",
    "gn:population":0,
    "gn:timezone":"Europe/Kiev",
    "iso:country":"UA",
    "name:ukr_x_preferred":[
        "Makhnivka"
    ],
    "name:ukr_x_variant":[
        "\u041c\u0430\u0445\u043d\u0456\u0432\u043a\u0430"
    ],
    "wof:name":"Makhnivka",
    "wof:placetype":"locality"
},
  "geometry": {"coordinates":[33.73259,49.01542],"type":"Point"}
}