{
  "type": "Feature",
  "properties": {
    "gn:admin1_code":"16.0",
    "gn:asciiname":"Kamennaya Balka",
    "gn:country_code":"UA",
    "gn:dem":72,
    "gn:feature_class":"P",
    "gn:feature_code":"PPL",
    "gn:name":"Kamennaya Balka",
    "gn:population":0,
    "gn:timezone":"Europe/Kiev",
    "iso:country":"UA",
    "wof:name":"Kamennaya Balka",
    "wof:placetype":"locality"
},
  "geometry": {"coordinates":[31.31314,47.41325],"type":"Point"}
}