{
  "type": "Feature",
  "properties": {
    "gn:admin1_code":"16.0",
    "gn:asciiname":"Kamennaya Balka",
    "gn:country_code":"UA",
    "gn:dem":72,
    "gn:feature_class":"P",
    "gn:feature_code":"PPL",
    "gn:name":"Kamennaya Balka",
    "gn:population":0,
    "gn:timezone":"Europe/Kiev",
    "iso:country":"UA",
    "name:pol_x_preferred":[
        "Kamennaja Ba\u0142ka"
    ],
    "name:rus_x_preferred":[
        "\u041a\u0430\u043c\u0435\u043d\u043d\u0430\u044f \u0431\u0430\u043b\u043a\u0430"
    ],
    "wof:name":"Kamennaya Balka",
    "wof:placetype":"locality"
},
  "geometry": {"coordinates":[31.31314,47.41325],"type":"Point"}
}