{
  "type": "Feature",
  "properties": {
    "gn:admin1_code":"27.0",
    "gn:asciiname":"Koloniya Emilin",
    "gn:country_code":"UA",
    "gn:dem":184,
    "gn:feature_class":"P",
    "gn:feature_code":"PPL",
    "gn:name":"Koloniya Emilin",
    "gn:population":0,
    "gn:timezone":"Europe/Kiev",
    "iso:country":"UA",
    "wof:name":"Koloniya Emilin",
    "wof:placetype":"locality"
},
  "geometry": {"coordinates":[28.75,50.68333],"type":"Point"}
}