{
  "type": "Feature",
  "properties": {
    "gn:admin1_code":"13.0",
    "gn:asciiname":"Chepizhentsy",
    "gn:country_code":"UA",
    "gn:dem":204,
    "gn:feature_class":"P",
    "gn:feature_code":"PPL",
    "gn:name":"Chepizhentsy",
    "gn:population":0,
    "gn:timezone":"Europe/Kiev",
    "iso:country":"UA",
    "name:und_x_variant":[
        "Chepizhintsy",
        "Chepizhentsy"
    ],
    "wof:name":"Chepizhentsy",
    "wof:placetype":"locality"
},
  "geometry": {"coordinates":[29.59846,49.54711],"type":"Point"}
}