{
  "type": "Feature",
  "properties": {
    "gn:admin1_code":"9.0",
    "gn:asciiname":"Selychiv",
    "gn:country_code":"UA",
    "gn:dem":219,
    "gn:feature_class":"P",
    "gn:feature_code":"PPL",
    "gn:name":"Selychiv",
    "gn:population":0,
    "gn:timezone":"Europe/Kiev",
    "iso:country":"UA",
    "name:ukr_x_preferred":[
        "Selychiv"
    ],
    "name:ukr_x_variant":[
        "\u0421\u0435\u043b\u0438\u0447\u0456\u0432"
    ],
    "name:und_x_variant":[
        "Selichev"
    ],
    "wof:name":"Selychiv",
    "wof:placetype":"locality"
},
  "geometry": {"coordinates":[27.12109,50.47474],"type":"Point"}
}