{
  "type": "Feature",
  "properties": {
    "gn:admin1_code":"14.0",
    "gn:asciiname":"Zakhidne",
    "gn:country_code":"UA",
    "gn:dem":219,
    "gn:feature_class":"P",
    "gn:feature_code":"PPL",
    "gn:name":"Zakhidne",
    "gn:population":0,
    "gn:timezone":"Europe/Zaporozhye",
    "iso:country":"UA",
    "name:ukr_x_preferred":[
        "Zakhidne"
    ],
    "name:ukr_x_variant":[
        "\u0417\u0430\u0445\u0456\u0434\u043d\u0435"
    ],
    "wof:name":"Zakhidne",
    "wof:placetype":"locality"
},
  "geometry": {"coordinates":[39.01968,48.28457],"type":"Point"}
}