{
  "type": "Feature",
  "properties": {
    "gn:admin1_code":"17.0",
    "gn:asciiname":"Novozarits'ke",
    "gn:country_code":"UA",
    "gn:dem":205,
    "gn:feature_class":"P",
    "gn:feature_code":"PPL",
    "gn:name":"Novozarits\u2019ke",
    "gn:population":0,
    "gn:timezone":"Europe/Kiev",
    "iso:country":"UA",
    "name:ukr_x_preferred":[
        "Novozarits\u2019ke"
    ],
    "name:ukr_x_variant":[
        "\u041d\u043e\u0432\u043e\u0437\u0430\u0440\u0456\u0446\u044c\u043a\u0435"
    ],
    "name:und_x_variant":[
        "Novozaritskoye",
        "Novoye Zaritskoye",
        "Novozaretskoye"
    ],
    "wof:name":"Novozarits'ke",
    "wof:placetype":"locality"
},
  "geometry": {"coordinates":[29.80215,47.50701],"type":"Point"}
}