{
  "type": "Feature",
  "properties": {
    "gn:admin1_code":"21.0",
    "gn:asciiname":"Novi Honchari",
    "gn:country_code":"UA",
    "gn:dem":190,
    "gn:feature_class":"P",
    "gn:feature_code":"PPL",
    "gn:name":"Novi Honchari",
    "gn:population":0,
    "gn:timezone":"Europe/Kiev",
    "iso:country":"UA",
    "name:ukr_x_preferred":[
        "Novi Honchari"
    ],
    "name:ukr_x_variant":[
        "\u041d\u043e\u0432\u0456 \u0413\u043e\u043d\u0447\u0430\u0440\u0456"
    ],
    "name:und_x_variant":[
        "Novyye Gonchary"
    ],
    "wof:name":"Novi Honchari",
    "wof:placetype":"locality"
},
  "geometry": {"coordinates":[33.9671,51.30135],"type":"Point"}
}