{
  "type": "Feature",
  "properties": {
    "iso:country":"UA",
    "name:unk_x_variant":[
        "Yaltshkov"
    ],
    "qs:a0":"\u0423\u043a\u0440\u0430\u0457\u043d\u0430",
    "qs:a1":"*\u0412\u0456\u043d\u043d\u0438\u0446\u044c\u043a\u0430",
    "qs:a1_alt":"Vinnyts'ka",
    "qs:a1r":"0",
    "qs:a2":"\u0411\u0430\u0440\u0441\u044c\u043a\u0438\u0439",
    "qs:a2_alt":"Bars'kyi",
    "qs:adm0":"\u0423\u043a\u0440\u0430\u0457\u043d\u0430",
    "qs:la_lc":"*",
    "qs:level":"locality",
    "qs:loc":"\u042f\u043b\u0442\u0443\u0448\u043a\u0456\u0432",
    "qs:loc_alt":"Yaltushkiv",
    "qs:pop":0,
    "qs:type":"buffered point",
    "wof:name":"\u042f\u043b\u0442\u0443\u0448\u043a\u0456\u0432",
    "wof:placetype":"locality"
},
  "geometry": {"coordinates":[27.518922,48.983803],"type":"Point"}
}