{
  "type": "Feature",
  "properties": {
    "gn:admin1_code":"18.0",
    "gn:asciiname":"Shkurpely",
    "gn:country_code":"UA",
    "gn:dem":123,
    "gn:feature_class":"P",
    "gn:feature_code":"PPL",
    "gn:name":"Shkurpely",
    "gn:population":0,
    "gn:timezone":"Europe/Kiev",
    "iso:country":"UA",
    "name:ukr_x_preferred":[
        "Shkurpely"
    ],
    "name:ukr_x_variant":[
        "\u0428\u043a\u0443\u0440\u043f\u0435\u043b\u0438"
    ],
    "name:und_x_variant":[
        "Shkurpeli"
    ],
    "wof:name":"Shkurpely",
    "wof:placetype":"locality"
},
  "geometry": {"coordinates":[34.42534000000001,50.0469],"type":"Point"}
}