{
  "type": "Feature",
  "properties": {
    "gn:admin1_code":"26.0",
    "gn:asciiname":"Vasyl'kove",
    "gn:country_code":"UA",
    "gn:dem":131,
    "gn:feature_class":"P",
    "gn:feature_code":"PPL",
    "gn:name":"Vasyl\u2019kove",
    "gn:population":0,
    "gn:timezone":"Europe/Zaporozhye",
    "iso:country":"UA",
    "name:ukr_x_preferred":[
        "Vasyl\u2019kove"
    ],
    "name:ukr_x_variant":[
        "\u0412\u0430\u0441\u0438\u043b\u044c\u043a\u043e\u0432\u0435"
    ],
    "name:und_x_variant":[
        "Vasilovskoye"
    ],
    "wof:name":"Vasyl'kove",
    "wof:placetype":"locality"
},
  "geometry": {"coordinates":[35.85615,47.80719000000001],"type":"Point"}
}