{
  "type": "Feature",
  "properties": {
    "iso:country":"UA",
    "name:eng_x_preferred":[
        "Kosari"
    ],
    "name:rus_x_preferred":[
        "\u0411\u0430\u0440\u0432\u0438\u043d\u0441\u043a\u0438\u0439"
    ],
    "name:rus_x_variant":[
        "\u041a\u043e\u0441\u0430\u0440\u0438"
    ],
    "name:ukr_x_preferred":[
        "\u0411\u0430\u0440\u0432\u0456\u043d\u0441\u044c\u043a\u0438\u0439 \u0412\u0430\u0441\u0438\u043b\u044c \u041e\u043b\u0435\u043a\u0441\u0430\u043d\u0434\u0440\u043e\u0432\u0438\u0447"
    ],
    "name:unk_x_variant":[
        "Kosara"
    ],
    "qs:a0":"\u0423\u043a\u0440\u0430\u0457\u043d\u0430",
    "qs:a1":"*\u0427\u0435\u0440\u043a\u0430\u0441\u044c\u043a\u0430",
    "qs:a1_alt":"Cherkas'ka",
    "qs:a1r":"0",
    "qs:a2":"\u041a\u0430\u043c'\u044f\u043d\u0441\u044c\u043a\u0438\u0439",
    "qs:a2_alt":"Kamyans'kyi",
    "qs:adm0":"\u0423\u043a\u0440\u0430\u0457\u043d\u0430",
    "qs:la_lc":"*",
    "qs:level":"locality",
    "qs:loc":"\u041a\u043e\u0441\u0430\u0440\u0456",
    "qs:loc_alt":"Kosari",
    "qs:pop":0,
    "qs:type":"buffered point",
    "wd:wordcount":692,
    "wof:name":"\u041a\u043e\u0441\u0430\u0440\u0456",
    "wof:placetype":"locality"
},
  "geometry": {"coordinates":[32.186921,49.057002],"type":"Point"}
}