{
  "type": "Feature",
  "properties": {
    "gn:population":3651,
    "iso:country":"UA",
    "name:ara_x_preferred":[
        "\u0641\u064a\u0634\u062a\u0634\u064a\u062a\u0627\u0631\u0627\u0633\u064a\u0641\u0643\u0627\u060c \u062f\u0646\u064a\u0628\u0631\u0648\u0628\u064a\u062a\u0631\u0648\u0641\u0633\u0643\u0627"
    ],
    "name:ara_x_variant":[
        "\u0641\u064a\u0634\u062a\u0634\u064a\u062a\u0627\u0631\u0627\u0633\u064a\u0641\u0643\u0627"
    ],
    "name:ceb_x_preferred":[
        "Vyshchetarasivka"
    ],
    "name:che_x_preferred":[
        "\u0412\u044b\u0441\u0448\u0435\u0442\u0430\u0440\u0430\u0441\u043e\u0432\u043a\u0430"
    ],
    "name:deu_x_preferred":[
        "Wyschtschetarassiwka"
    ],
    "name:eng_x_preferred":[
        "Vyschetarasivka"
    ],
    "name:lav_x_preferred":[
        "Vi\u0161\u010detarasivka"
    ],
    "name:ron_x_preferred":[
        "V\u00ee\u0219cetarasivka"
    ],
    "name:rus_x_preferred":[
        "\u0412\u0438\u0449\u0435\u0442\u0430\u0440\u0430\u0441\u0456\u0432\u043a\u0430"
    ],
    "name:rus_x_variant":[
        "Novoanastas\u2019yevka",
        "\u0412\u044b\u0441\u0448\u0435\u0442\u0430\u0440\u0430\u0441\u043e\u0432\u043a\u0430",
        "\u041d\u043e\u0432\u043e\u0430\u043d\u0430\u0441\u0442\u0430\u0441\u044c\u0435\u0432\u043a\u0430"
    ],
    "name:ukr_x_preferred":[
        "\u0412\u0438\u0449\u0435\u0442\u0430\u0440\u0430\u0441\u0456\u0432\u043a\u0430"
    ],
    "name:unk_x_variant":[
        "Vysshetarasovka"
    ],
    "qs:a0":"\u0423\u043a\u0440\u0430\u0457\u043d\u0430",
    "qs:a1":"*\u0414\u043d\u0456\u043f\u0440\u043e\u043f\u0435\u0442\u0440\u043e\u0432\u0441\u044c\u043a\u0430",
    "qs:a1_alt":"Dnipropetrovs'ka",
    "qs:a1r":"0",
    "qs:a2":"\u0422\u043e\u043c\u0430\u043a\u0456\u0432\u0441\u044c\u043a\u0438\u0439",
    "qs:a2_alt":"Tomakivs'kyi",
    "qs:adm0":"\u0423\u043a\u0440\u0430\u0457\u043d\u0430",
    "qs:la_lc":"*",
    "qs:level":"locality",
    "qs:loc":"\u0412\u0438\u0449\u0435\u0442\u0430\u0440\u0430\u0441\u0456\u0432\u043a\u0430",
    "qs:loc_alt":"Vyschetarasivka",
    "qs:pop":0,
    "qs:type":"buffered point",
    "wof:name":"\u0412\u0438\u0449\u0435\u0442\u0430\u0440\u0430\u0441\u0456\u0432\u043a\u0430",
    "wof:placetype":"locality",
    "wof:population":3651
},
  "geometry": {"coordinates":[34.883301,47.572489],"type":"Point"}
}