{
  "type": "Feature",
  "properties": {
    "gn:admin1_code":"22.0",
    "gn:asciiname":"Malaya Luka",
    "gn:country_code":"UA",
    "gn:dem":279,
    "gn:feature_class":"P",
    "gn:feature_code":"PPL",
    "gn:name":"Malaya Luka",
    "gn:population":0,
    "gn:timezone":"Europe/Kiev",
    "iso:country":"UA",
    "name:und_x_variant":[
        "Luka-Mala",
        "Malaya Luka"
    ],
    "wof:name":"Malaya Luka",
    "wof:placetype":"locality"
},
  "geometry": {"coordinates":[26.2353,49.36855],"type":"Point"}
}