{
  "type": "Feature",
  "properties": {
    "gn:admin1_code":"7.0",
    "gn:asciiname":"Semeniv Yar",
    "gn:country_code":"UA",
    "gn:dem":140,
    "gn:feature_class":"P",
    "gn:feature_code":"PPL",
    "gn:name":"Semeniv Yar",
    "gn:population":0,
    "gn:timezone":"Europe/Kiev",
    "iso:country":"UA",
    "name:ukr_x_preferred":[
        "Semeniv Yar"
    ],
    "name:ukr_x_variant":[
        "\u0421\u0435\u043c\u0435\u043d\u0456\u0432 \u042f\u0440"
    ],
    "name:und_x_variant":[
        "Khutor Semenov Yar",
        "Semenov Yar"
    ],
    "wof:name":"Semeniv Yar",
    "wof:placetype":"locality"
},
  "geometry": {"coordinates":[35.51262,50.13381],"type":"Point"}
}