{
  "type": "Feature",
  "properties": {
    "gn:admin1_code":"21.0",
    "gn:asciiname":"Moskalenky",
    "gn:country_code":"UA",
    "gn:dem":185,
    "gn:feature_class":"P",
    "gn:feature_code":"PPL",
    "gn:name":"Moskalenky",
    "gn:population":0,
    "gn:timezone":"Europe/Kiev",
    "iso:country":"UA",
    "name:ukr_x_preferred":[
        "Moskalenky"
    ],
    "name:ukr_x_variant":[
        "\u041c\u043e\u0441\u043a\u0430\u043b\u0435\u043d\u043a\u0438"
    ],
    "name:und_x_variant":[
        "Moskalenkov",
        "Moskalenki"
    ],
    "wof:name":"Moskalenky",
    "wof:placetype":"locality"
},
  "geometry": {"coordinates":[34.01,51.72053],"type":"Point"}
}