{
  "type": "Feature",
  "properties": {
    "gn:admin1_code":"26.0",
    "gn:asciiname":"Tersyanka",
    "gn:country_code":"UA",
    "gn:dem":97,
    "gn:feature_class":"P",
    "gn:feature_code":"PPL",
    "gn:name":"Tersyanka",
    "gn:population":0,
    "gn:timezone":"Europe/Zaporozhye",
    "iso:country":"UA",
    "name:ukr_x_preferred":[
        "Tersyanka"
    ],
    "name:ukr_x_variant":[
        "\u0422\u0435\u0440\u0441\u044f\u043d\u043a\u0430"
    ],
    "name:und_x_variant":[
        "Terstyanka"
    ],
    "wof:name":"Tersyanka",
    "wof:placetype":"locality"
},
  "geometry": {"coordinates":[35.89343,47.88323],"type":"Point"}
}