{
  "type": "Feature",
  "properties": {
    "gn:gn_country":"UA",
    "gn:gn_fcode":"PPL",
    "gn:gn_pop":2628,
    "gn:population":2628,
    "iso:country":"UA",
    "name:eng_x_preferred":[
        "Vvedenka"
    ],
    "name:rus_x_preferred":[
        "\u0412\u0432\u0435\u0434\u0435\u043d\u043a\u0430"
    ],
    "name:ukr_x_preferred":[
        "\u0412\u0432\u0435\u0434\u0435\u043d\u043a\u0430"
    ],
    "name:unk_x_variant":[
        "Vvedenskoye"
    ],
    "qs_pg:aaroncc":"UA",
    "qs_pg:gn_country":"UA",
    "qs_pg:gn_fcode":"PPL",
    "qs_pg:gn_pop":2628,
    "qs_pg:name":"Vvedenka",
    "qs_pg:photos_9r":0,
    "qs_pg:photos_sr":0,
    "qs_pg:pop_sr":4,
    "qs_pg:qs_pg_placetype":"locality",
    "wof:name":"Vvedenka",
    "wof:placetype":"locality",
    "wof:population":2628
},
  "geometry": {"coordinates":[36.50747,49.82441],"type":"Point"}
}