{
  "type": "Feature",
  "properties": {
    "gn:admin1_code":"4.0",
    "gn:asciiname":"Petrykivka",
    "gn:country_code":"UA",
    "gn:dem":78,
    "gn:feature_class":"P",
    "gn:feature_code":"PPL",
    "gn:name":"Petrykivka",
    "gn:population":0,
    "gn:timezone":"Europe/Kiev",
    "iso:country":"UA",
    "name:ceb_x_preferred":[
        "Petrykivka"
    ],
    "name:crh_x_preferred":[
        "Petr\u0131kivka"
    ],
    "name:deu_x_preferred":[
        "Petrykiwka"
    ],
    "name:fra_x_preferred":[
        "Petrykivka"
    ],
    "name:hye_x_preferred":[
        "\u054a\u0565\u057f\u0580\u056b\u056f\u0578\u057e\u056f\u0561"
    ],
    "name:ita_x_preferred":[
        "Petrykivka"
    ],
    "name:pol_x_preferred":[
        "Petrykiwka"
    ],
    "name:ron_x_preferred":[
        "Petr\u00eekivka"
    ],
    "name:rus_x_preferred":[
        "\u041f\u0435\u0442\u0440\u0438\u043a\u043e\u0432\u043a\u0430"
    ],
    "name:ukr_x_preferred":[
        "Petrykivka"
    ],
    "name:ukr_x_variant":[
        "\u041f\u0435\u0442\u0440\u0438\u043a\u0456\u0432\u043a\u0430"
    ],
    "name:zho_x_preferred":[
        "\u4f69\u7279\u91cc\u57fa\u592b\u5361"
    ],
    "wof:name":"Petrykivka",
    "wof:placetype":"locality"
},
  "geometry": {"coordinates":[35.99587000000001,48.24524],"type":"Point"}
}