{
  "type": "Feature",
  "properties": {
    "gn:admin1_code":"4.0",
    "gn:asciiname":"Petrykivka",
    "gn:country_code":"UA",
    "gn:dem":78,
    "gn:feature_class":"P",
    "gn:feature_code":"PPL",
    "gn:name":"Petrykivka",
    "gn:population":0,
    "gn:timezone":"Europe/Kiev",
    "iso:country":"UA",
    "name:ukr_x_preferred":[
        "Petrykivka"
    ],
    "name:ukr_x_variant":[
        "\u041f\u0435\u0442\u0440\u0438\u043a\u0456\u0432\u043a\u0430"
    ],
    "wof:name":"Petrykivka",
    "wof:placetype":"locality"
},
  "geometry": {"coordinates":[35.99587000000001,48.24524],"type":"Point"}
}