{
  "type": "Feature",
  "properties": {
    "gn:admin1_code":"18.0",
    "gn:asciiname":"Zhyrky",
    "gn:country_code":"UA",
    "gn:dem":77,
    "gn:feature_class":"P",
    "gn:feature_code":"PPL",
    "gn:name":"Zhyrky",
    "gn:population":0,
    "gn:timezone":"Europe/Kiev",
    "iso:country":"UA",
    "name:ukr_x_preferred":[
        "Zhyrky"
    ],
    "name:ukr_x_variant":[
        "\u0416\u0438\u0440\u043a\u0438"
    ],
    "wof:name":"Zhyrky",
    "wof:placetype":"locality"
},
  "geometry": {"coordinates":[34.31308,49.28452],"type":"Point"}
}