{
  "type": "Feature",
  "properties": {
    "gn:admin1_code":"21.0",
    "gn:asciiname":"Pas'ovyny",
    "gn:country_code":"UA",
    "gn:dem":172,
    "gn:feature_class":"P",
    "gn:feature_code":"PPL",
    "gn:name":"Pas\u2019ovyny",
    "gn:population":0,
    "gn:timezone":"Europe/Kiev",
    "iso:country":"UA",
    "name:rus_x_preferred":[
        "Pas\u00ebviny"
    ],
    "name:ukr_x_preferred":[
        "Pas\u2019ovyny"
    ],
    "name:ukr_x_variant":[
        "\u041f\u0430\u0441\u044c\u043e\u0432\u0438\u043d\u0438"
    ],
    "wof:name":"Pas'ovyny",
    "wof:placetype":"locality"
},
  "geometry": {"coordinates":[33.70372,50.98095],"type":"Point"}
}