{
  "type": "Feature",
  "properties": {
    "gn:admin1_code":"27.0",
    "gn:asciiname":"Yaroslavka",
    "gn:country_code":"UA",
    "gn:dem":242,
    "gn:feature_class":"P",
    "gn:feature_code":"PPL",
    "gn:name":"Yaroslavka",
    "gn:population":0,
    "gn:timezone":"Europe/Kiev",
    "iso:country":"UA",
    "name:che_x_preferred":[
        "\u042f\u0440\u043e\u0441\u043b\u0430\u0432\u043a\u0430"
    ],
    "name:rus_x_preferred":[
        "\u042f\u0440\u043e\u0441\u043b\u0430\u0432\u043a\u0430"
    ],
    "name:ukr_x_preferred":[
        "Yaroslavka"
    ],
    "name:ukr_x_variant":[
        "\u042f\u0440\u043e\u0441\u043b\u0430\u0432\u043a\u0430"
    ],
    "wof:name":"Yaroslavka",
    "wof:placetype":"locality"
},
  "geometry": {"coordinates":[29.16236,49.79783],"type":"Point"}
}