{
  "type": "Feature",
  "properties": {
    "gn:admin1_code":"19.0",
    "gn:asciiname":"Villya",
    "gn:country_code":"UA",
    "gn:dem":171,
    "gn:feature_class":"P",
    "gn:feature_code":"PPL",
    "gn:name":"Villya",
    "gn:population":0,
    "gn:timezone":"Europe/Kiev",
    "iso:country":"UA",
    "name:rus_x_preferred":[
        "Vil\u2019ya"
    ],
    "name:ukr_x_preferred":[
        "Villya"
    ],
    "name:ukr_x_variant":[
        "\u0412\u0456\u043b\u043b\u044f"
    ],
    "wof:name":"Villya",
    "wof:placetype":"locality"
},
  "geometry": {"coordinates":[26.96236,50.86436],"type":"Point"}
}