{
  "type": "Feature",
  "properties": {
    "iso:country":"UA",
    "qs:a0":"\u0423\u043a\u0440\u0430\u0457\u043d\u0430",
    "qs:a1":"*\u0427\u0435\u0440\u043a\u0430\u0441\u044c\u043a\u0430",
    "qs:a1_alt":"Cherkas'ka",
    "qs:a1r":"0",
    "qs:a2":"\u0417\u0432\u0435\u043d\u0438\u0433\u043e\u0440\u043e\u0434\u0441\u044c\u043a\u0438\u0439",
    "qs:a2_alt":"Zvenyhorods'kyi",
    "qs:adm0":"\u0423\u043a\u0440\u0430\u0457\u043d\u0430",
    "qs:la_lc":"*",
    "qs:level":"locality",
    "qs:loc":"\u041a\u043e\u0437\u0430\u0446\u044c\u043a\u0435",
    "qs:loc_alt":"Kozats'ke",
    "qs:pop":0,
    "qs:type":"buffered point",
    "wd:wordcount":1753,
    "wof:name":"\u041a\u043e\u0437\u0430\u0446\u044c\u043a\u0435",
    "wof:placetype":"locality"
},
  "geometry": {"coordinates":[31.143932,49.097386],"type":"Point"}
}