{
  "type": "Feature",
  "properties": {
    "gn:admin1_code":"15.0",
    "gn:asciiname":"Vyshnivchyk",
    "gn:country_code":"UA",
    "gn:dem":318,
    "gn:elevation":"327.0",
    "gn:feature_class":"P",
    "gn:feature_code":"PPL",
    "gn:name":"Vyshnivchyk",
    "gn:population":567,
    "gn:timezone":"Europe/Kiev",
    "iso:country":"UA",
    "name:deu_x_preferred":[
        "Wyschniwtschyk"
    ],
    "name:pol_x_preferred":[
        "Wi\u015bniowczyk"
    ],
    "name:ron_x_preferred":[
        "V\u00ee\u0219nivci\u00eek"
    ],
    "name:rus_x_preferred":[
        "\u0412\u0438\u0448\u043d\u0435\u0432\u0447\u0438\u043a"
    ],
    "name:ukr_x_preferred":[
        "\u0412\u0438\u0448\u043d\u0456\u0432\u0447\u0438\u043a"
    ],
    "name:und_x_variant":[
        "Vis\u2019nevchik",
        "Vishnevchik"
    ],
    "name:zho_x_preferred":[
        "\u7dad\u4ec0\u5c3c\u592b\u5947\u514b"
    ],
    "wof:name":"Vyshnivchyk",
    "wof:placetype":"locality",
    "wof:population":567
},
  "geometry": {"coordinates":[24.74599,49.70069],"type":"Point"}
}