{
  "type": "Feature",
  "properties": {
    "gn:admin1_code":"15.0",
    "gn:asciiname":"Novosyulki",
    "gn:country_code":"UA",
    "gn:dem":240,
    "gn:feature_class":"P",
    "gn:feature_code":"PPL",
    "gn:name":"Novosyulki",
    "gn:population":0,
    "gn:timezone":"Europe/Kiev",
    "iso:country":"UA",
    "name:und_x_variant":[
        "Novoselki",
        "Novosyulki"
    ],
    "wof:name":"Novosyulki",
    "wof:placetype":"locality"
},
  "geometry": {"coordinates":[23.44221,49.83728],"type":"Point"}
}