{
  "type": "Feature",
  "properties": {
    "gn:admin1_code":"13.0",
    "gn:asciiname":"Tashan'",
    "gn:country_code":"UA",
    "gn:dem":128,
    "gn:feature_class":"P",
    "gn:feature_code":"PPL",
    "gn:name":"Tashan\u2019",
    "gn:population":0,
    "gn:timezone":"Europe/Kiev",
    "iso:country":"UA",
    "name:eng_x_preferred":[
        "Tashan'"
    ],
    "name:rus_x_preferred":[
        "\u0422\u0430\u0448\u0430\u043d\u044c"
    ],
    "name:und_x_variant":[
        "Tashan\u2019"
    ],
    "wof:name":"Tashan'",
    "wof:placetype":"locality"
},
  "geometry": {"coordinates":[31.84225,50.04522],"type":"Point"}
}