{
  "type": "Feature",
  "properties": {
    "gn:admin1_code":"8.0",
    "gn:asciiname":"Ukrayins'ke",
    "gn:country_code":"UA",
    "gn:dem":34,
    "gn:feature_class":"P",
    "gn:feature_code":"PPL",
    "gn:name":"Ukrayins\u2019ke",
    "gn:population":0,
    "gn:timezone":"Europe/Kiev",
    "iso:country":"UA",
    "name:rus_x_preferred":[
        "\u0423\u043a\u0440\u0430\u0438\u043d\u0441\u043a\u0438\u0439 \u0420\u0430\u0431\u043e\u0447\u0438\u0439"
    ],
    "name:rus_x_variant":[
        "\u0423\u043a\u0440\u0430\u0438\u043d\u0441\u043a\u043e\u0435"
    ],
    "name:ukr_x_preferred":[
        "Ukrayins\u2019ke"
    ],
    "name:ukr_x_variant":[
        "\u0423\u043a\u0440\u0430\u0457\u043d\u0441\u044c\u043a\u0435"
    ],
    "name:und_x_variant":[
        "Ukrainskiy Rabochiy",
        "Ukrainskoye"
    ],
    "wof:name":"Ukrayins'ke",
    "wof:placetype":"locality"
},
  "geometry": {"coordinates":[34.65432,46.66877],"type":"Point"}
}