{
  "type": "Feature",
  "properties": {
    "gn:admin1_code":"26.0",
    "gn:asciiname":"Dobrivka",
    "gn:country_code":"UA",
    "gn:dem":22,
    "gn:feature_class":"P",
    "gn:feature_code":"PPL",
    "gn:name":"Dobrivka",
    "gn:population":0,
    "gn:timezone":"Europe/Zaporozhye",
    "iso:country":"UA",
    "name:ukr_x_preferred":[
        "Dobrivka"
    ],
    "name:ukr_x_variant":[
        "\u0414\u043e\u0431\u0440\u0456\u0432\u043a\u0430"
    ],
    "name:und_x_variant":[
        "Dachnyy",
        "Dachny",
        "Dobrovka"
    ],
    "wof:name":"Dobrivka",
    "wof:placetype":"locality"
},
  "geometry": {"coordinates":[35.54566,46.70875],"type":"Point"}
}