{
  "type": "Feature",
  "properties": {
    "gn:admin1_code":"27",
    "gn:asciiname":"Suslivka",
    "gn:country_code":"UA",
    "gn:dem":293,
    "gn:feature_class":"P",
    "gn:feature_code":"PPL",
    "gn:name":"Suslivka",
    "gn:population":0,
    "gn:timezone":"Europe/Kiev",
    "iso:country":"UA",
    "name:ukr_x_preferred":[
        "Suslivka"
    ],
    "name:ukr_x_variant":[
        "\u0421\u0443\u0441\u043b\u0456\u0432\u043a\u0430"
    ],
    "wof:name":"Suslivka",
    "wof:placetype":"locality"
},
  "geometry": {"coordinates":[27.92372,49.79467],"type":"Point"}
}