{
  "type": "Feature",
  "properties": {
    "gn:admin1_code":"15.0",
    "gn:asciiname":"Lan-Soltyski",
    "gn:country_code":"UA",
    "gn:dem":339,
    "gn:feature_class":"P",
    "gn:feature_code":"PPL",
    "gn:name":"Lan-Soltyski",
    "gn:population":0,
    "gn:timezone":"Europe/Kiev",
    "iso:country":"UA",
    "wof:name":"Lan-Soltyski",
    "wof:placetype":"locality"
},
  "geometry": {"coordinates":[23.35407,49.39662],"type":"Point"}
}