{
  "type": "Feature",
  "properties": {
    "gn:admin1_code":"18.0",
    "gn:asciiname":"Grishovka",
    "gn:cc2":"UA",
    "gn:country_code":"UA",
    "gn:dem":128,
    "gn:feature_class":"P",
    "gn:feature_code":"PPL",
    "gn:name":"Grishovka",
    "gn:population":0,
    "gn:timezone":"Europe/Kiev",
    "iso:country":"UA",
    "name:und_x_variant":[
        "Grishkevka",
        "Grishovka"
    ],
    "wof:name":"Grishovka",
    "wof:placetype":"locality"
},
  "geometry": {"coordinates":[34.33333,49.73333],"type":"Point"}
}