{
  "type": "Feature",
  "properties": {
    "iso:country":"UA",
    "name:ukr_x_preferred":[
        "Velymche"
    ],
    "name:ukr_x_variant":[
        "\u0412\u0435\u043b\u0438\u043c\u0447\u0435"
    ],
    "name:und_x_variant":[
        "Wielimcze"
    ],
    "qs:a0":"\u0423\u043a\u0440\u0430\u0457\u043d\u0430",
    "qs:a1":"*\u0412\u043e\u043b\u0438\u043d\u0441\u044c\u043a\u0430",
    "qs:a1_alt":"Volyns'ka",
    "qs:a1r":"0",
    "qs:a2":"\u0420\u0430\u0442\u043d\u0456\u0432\u0441\u044c\u043a\u0438\u0439",
    "qs:a2_alt":"Ratnivs'kyi",
    "qs:adm0":"\u0423\u043a\u0440\u0430\u0457\u043d\u0430",
    "qs:la_lc":"*",
    "qs:level":"locality",
    "qs:loc":"\u0412\u0435\u043b\u0438\u043c\u0447\u0435",
    "qs:loc_alt":"Velymche",
    "qs:pop":0,
    "qs:type":"buffered point",
    "wof:name":"\u0412\u0435\u043b\u0438\u043c\u0447\u0435",
    "wof:placetype":"locality"
},
  "geometry": {"coordinates":[24.739629,51.582639],"type":"Point"}
}