{
  "type": "Feature",
  "properties": {
    "gn:admin1_code":"10.0",
    "gn:asciiname":"Poselyanivka",
    "gn:country_code":"UA",
    "gn:dem":139,
    "gn:feature_class":"P",
    "gn:feature_code":"PPL",
    "gn:name":"Poselyanivka",
    "gn:population":0,
    "gn:timezone":"Europe/Kiev",
    "iso:country":"UA",
    "name:ukr_x_preferred":[
        "Poselyanivka"
    ],
    "name:ukr_x_variant":[
        "\u041f\u043e\u0441\u0435\u043b\u044f\u043d\u0456\u0432\u043a\u0430"
    ],
    "wof:name":"Poselyanivka",
    "wof:placetype":"locality"
},
  "geometry": {"coordinates":[32.30966,49.05664],"type":"Point"}
}