{
  "type": "Feature",
  "properties": {
    "gn:admin1_code":"18.0",
    "gn:asciiname":"Staryy Khutir",
    "gn:country_code":"UA",
    "gn:dem":109,
    "gn:feature_class":"P",
    "gn:feature_code":"PPL",
    "gn:name":"Staryy Khutir",
    "gn:population":0,
    "gn:timezone":"Europe/Kiev",
    "iso:country":"UA",
    "name:ukr_x_preferred":[
        "Staryy Khutir"
    ],
    "name:ukr_x_variant":[
        "\u0421\u0442\u0430\u0440\u0438\u0439 \u0425\u0443\u0442\u0456\u0440"
    ],
    "name:und_x_variant":[
        "Staryy",
        "Staryy Khutor"
    ],
    "wof:name":"Staryy Khutir",
    "wof:placetype":"locality"
},
  "geometry": {"coordinates":[33.48829,50.45606],"type":"Point"}
}