{
  "type": "Feature",
  "properties": {
    "gn:admin1_code":"24.0",
    "gn:asciiname":"Nemyr",
    "gn:country_code":"UA",
    "gn:dem":189,
    "gn:feature_class":"P",
    "gn:feature_code":"PPL",
    "gn:name":"Nemyr",
    "gn:population":0,
    "gn:timezone":"Europe/Kiev",
    "iso:country":"UA",
    "name:ukr_x_preferred":[
        "Nemyr"
    ],
    "name:ukr_x_variant":[
        "\u041d\u0435\u043c\u0438\u0440"
    ],
    "name:und_x_variant":[
        "Niemir",
        "Nemer",
        "Nemir"
    ],
    "wof:name":"Nemyr",
    "wof:placetype":"locality"
},
  "geometry": {"coordinates":[25.00046,50.9834],"type":"Point"}
}