{
  "type": "Feature",
  "properties": {
    "gn:admin1_code":"7.0",
    "gn:asciiname":"Leninka",
    "gn:country_code":"UA",
    "gn:dem":146,
    "gn:feature_class":"P",
    "gn:feature_code":"PPL",
    "gn:name":"Leninka",
    "gn:population":0,
    "gn:timezone":"Europe/Kiev",
    "iso:country":"UA",
    "name:rus_x_preferred":[
        "\u041b\u0435\u043d\u0438\u043d\u043a\u0430"
    ],
    "name:ukr_x_preferred":[
        "Leninka"
    ],
    "name:ukr_x_variant":[
        "\u041b\u0435\u043d\u0456\u043d\u043a\u0430"
    ],
    "wof:name":"Leninka",
    "wof:placetype":"locality"
},
  "geometry": {"coordinates":[35.42856,49.44563],"type":"Point"}
}