{
  "type": "Feature",
  "properties": {
    "gn:admin1_code":"5.0",
    "gn:asciiname":"Moskvets",
    "gn:country_code":"UA",
    "gn:dem":146,
    "gn:feature_class":"P",
    "gn:feature_code":"PPL",
    "gn:name":"Moskvets",
    "gn:population":0,
    "gn:timezone":"Europe/Kiev",
    "iso:country":"UA",
    "name:und_x_variant":[
        "Khutor Moskovets",
        "Moskovets",
        "Moskvets"
    ],
    "wof:name":"Moskvets",
    "wof:placetype":"locality"
},
  "geometry": {"coordinates":[38.41611,47.96556],"type":"Point"}
}