{
  "type": "Feature",
  "properties": {
    "gn:admin1_code":"22.0",
    "gn:asciiname":"Polskie Folwarki",
    "gn:country_code":"UA",
    "gn:dem":308,
    "gn:feature_class":"P",
    "gn:feature_code":"PPL",
    "gn:name":"Polskie Folwarki",
    "gn:population":0,
    "gn:timezone":"Europe/Kiev",
    "iso:country":"UA",
    "name:und_x_variant":[
        "Folwarki",
        "Fol\u2019varki"
    ],
    "wof:name":"Polskie Folwarki",
    "wof:placetype":"locality"
},
  "geometry": {"coordinates":[25.16667,49.08333],"type":"Point"}
}