{
  "type": "Feature",
  "properties": {
    "iso:country":"UA",
    "name:eng_x_preferred":[
        "Vyry"
    ],
    "name:rus_x_preferred":[
        "\u0412\u0438\u0440\u044b"
    ],
    "name:ukr_x_preferred":[
        "\u0412\u0438\u0440\u0438"
    ],
    "name:und_x_variant":[
        "Wiry"
    ],
    "qs:a0":"\u0423\u043a\u0440\u0430\u0457\u043d\u0430",
    "qs:a1":"*\u0421\u0443\u043c\u0441\u044c\u043a\u0430",
    "qs:a1_alt":"Sums'ka",
    "qs:a1r":"0",
    "qs:a2":"\u0411\u0456\u043b\u043e\u043f\u0456\u043b\u044c\u0441\u044c\u043a\u0438\u0439",
    "qs:a2_alt":"Bilopil's'kyi",
    "qs:adm0":"\u0423\u043a\u0440\u0430\u0457\u043d\u0430",
    "qs:la_lc":"*",
    "qs:level":"locality",
    "qs:loc":"\u0412\u0438\u0440\u0438",
    "qs:loc_alt":"Vyry",
    "qs:pop":0,
    "qs:type":"buffered point",
    "wof:name":"\u0412\u0438\u0440\u0438",
    "wof:placetype":"locality"
},
  "geometry": {"coordinates":[34.412554,51.042461],"type":"Point"}
}