{
  "type": "Feature",
  "properties": {
    "gn:admin1_code":"11.0",
    "gn:admin2_code":"709333",
    "gn:admin3_code":"11152846",
    "gn:asciiname":"Solyonoye Ozero",
    "gn:country_code":"UA",
    "gn:dem":11,
    "gn:elevation":"14.0",
    "gn:feature_class":"P",
    "gn:feature_code":"PPL",
    "gn:name":"Solyonoye Ozero",
    "gn:population":838,
    "gn:timezone":"Europe/Zaporozhye",
    "iso:country":"UA",
    "name:eng_x_preferred":[
        "Solyonoye Ozero"
    ],
    "name:rus_x_historical":[
        "\u0422\u043e\u0433\u0430\u043d\u0430\u0301\u0448"
    ],
    "name:rus_x_preferred":[
        "\u0421\u043e\u043b\u0451\u043d\u043e\u0435 \u041e\u0437\u0435\u0440\u043e"
    ],
    "name:rus_x_variant":[
        "\u0422\u043e\u0433\u0430\u043d\u0430\u0301\u0448"
    ],
    "name:ukr_x_preferred":[
        "\u0421\u043e\u043b\u043e\u043d\u0435 \u041e\u0437\u0435\u0440\u043e"
    ],
    "wof:name":"Solyonoye Ozero",
    "wof:placetype":"locality",
    "wof:population":838
},
  "geometry": {"coordinates":[34.44811,45.88208],"type":"Point"}
}