{
  "type": "Feature",
  "properties": {
    "gn:admin1_code":"16.0",
    "gn:asciiname":"Zelenyy",
    "gn:country_code":"UA",
    "gn:dem":57,
    "gn:feature_class":"P",
    "gn:feature_code":"PPL",
    "gn:name":"Zel\u00ebnyy",
    "gn:population":0,
    "gn:timezone":"Europe/Kiev",
    "iso:country":"UA",
    "name:und_x_variant":[
        "Khutor Zelenyy",
        "Zel\u00ebnyy"
    ],
    "wof:name":"Zelenyy",
    "wof:placetype":"locality"
},
  "geometry": {"coordinates":[31.73994,46.95171],"type":"Point"}
}