{
  "type": "Feature",
  "properties": {
    "gn:admin1_code":"26.0",
    "gn:asciiname":"Chervonokozats'ke",
    "gn:country_code":"UA",
    "gn:dem":127,
    "gn:feature_class":"P",
    "gn:feature_code":"PPL",
    "gn:name":"Chervonokozats\u2019ke",
    "gn:population":0,
    "gn:timezone":"Europe/Zaporozhye",
    "iso:country":"UA",
    "name:ukr_x_preferred":[
        "Chervonokozats\u2019ke"
    ],
    "name:ukr_x_variant":[
        "\u0427\u0435\u0440\u0432\u043e\u043d\u043e\u043a\u043e\u0437\u0430\u0442\u0441\u044c\u043a\u0435"
    ],
    "name:und_x_variant":[
        "Chervonokazatskoye"
    ],
    "wof:name":"Chervonokozats'ke",
    "wof:placetype":"locality"
},
  "geometry": {"coordinates":[35.72573,48.00075],"type":"Point"}
}