{
  "type": "Feature",
  "properties": {
    "gn:admin1_code":"8.0",
    "gn:asciiname":"Shostakove",
    "gn:country_code":"UA",
    "gn:dem":18,
    "gn:feature_class":"P",
    "gn:feature_code":"PPL",
    "gn:name":"Shostakove",
    "gn:population":0,
    "gn:timezone":"Europe/Kiev",
    "iso:country":"UA",
    "name:ukr_x_preferred":[
        "Shostakove"
    ],
    "name:ukr_x_variant":[
        "\u0428\u043e\u0441\u0442\u0430\u043a\u043e\u0432\u0435"
    ],
    "name:und_x_variant":[
        "Shostakova"
    ],
    "wof:name":"Shostakove",
    "wof:placetype":"locality"
},
  "geometry": {"coordinates":[33.3649,47.39673],"type":"Point"}
}