{
  "type": "Feature",
  "properties": {
    "gn:admin1_code":"15.0",
    "gn:asciiname":"Miloshovitse",
    "gn:country_code":"UA",
    "gn:dem":273,
    "gn:feature_class":"P",
    "gn:feature_code":"PPL",
    "gn:name":"Miloshovitse",
    "gn:population":0,
    "gn:timezone":"Europe/Kiev",
    "iso:country":"UA",
    "name:und_x_variant":[
        "Miloshevich",
        "Miloshovitse"
    ],
    "wof:name":"Miloshovitse",
    "wof:placetype":"locality"
},
  "geometry": {"coordinates":[23.93608,49.67886],"type":"Point"}
}