{
  "type": "Feature",
  "properties": {
    "gn:admin1_code":"4.0",
    "gn:asciiname":"Ivanovka",
    "gn:country_code":"UA",
    "gn:dem":74,
    "gn:feature_class":"P",
    "gn:feature_code":"PPL",
    "gn:name":"Ivanovka",
    "gn:population":0,
    "gn:timezone":"Europe/Kiev",
    "iso:country":"UA",
    "wof:name":"Ivanovka",
    "wof:placetype":"locality"
},
  "geometry": {"coordinates":[34.36667,48.98333],"type":"Point"}
}