{
  "type": "Feature",
  "properties": {
    "gn:admin1_code":"26.0",
    "gn:asciiname":"Pryyutne",
    "gn:country_code":"UA",
    "gn:dem":156,
    "gn:feature_class":"P",
    "gn:feature_code":"PPL",
    "gn:name":"Pryyutne",
    "gn:population":0,
    "gn:timezone":"Europe/Zaporozhye",
    "iso:country":"UA",
    "name:eng_x_preferred":[
        "Priyutnoye"
    ],
    "name:rus_x_preferred":[
        "\u041f\u0440\u0438\u044e\u0442\u043d\u043e\u0435"
    ],
    "name:ukr_x_preferred":[
        "Pryyutne"
    ],
    "name:ukr_x_variant":[
        "\u041f\u0440\u0438\u044e\u0442\u043d\u0435"
    ],
    "name:und_x_variant":[
        "Yevreyskaya Koloniya Priyutnaya Nomer Vos\u2019moy",
        "Priyutnaya",
        "Priyutnoye"
    ],
    "wof:name":"Pryyutne",
    "wof:placetype":"locality"
},
  "geometry": {"coordinates":[36.67396,47.72658],"type":"Point"}
}