{
  "type": "Feature",
  "properties": {
    "iso:country":"UA",
    "qs:a0":"\u0423\u043a\u0440\u0430\u0457\u043d\u0430",
    "qs:a1":"*\u041e\u0434\u0435\u0441\u044c\u043a\u0430",
    "qs:a1_alt":"Odes'ka",
    "qs:a1r":"0",
    "qs:a2":"\u0421\u0430\u0432\u0440\u0430\u043d\u0441\u044c\u043a\u0438\u0439",
    "qs:a2_alt":"Savrans'kyi",
    "qs:adm0":"\u0423\u043a\u0440\u0430\u0457\u043d\u0430",
    "qs:la_lc":"*",
    "qs:level":"locality",
    "qs:loc":"\u041a\u043e\u043d\u0446\u0435\u0431\u0430",
    "qs:loc_alt":"Kontseba",
    "qs:pop":0,
    "qs:type":"buffered point",
    "wof:name":"\u041a\u043e\u043d\u0446\u0435\u0431\u0430",
    "wof:placetype":"locality"
},
  "geometry": {"coordinates":[29.971738,48.123223],"type":"Point"}
}