{
  "type": "Feature",
  "properties": {
    "gn:admin1_code":"27.0",
    "gn:asciiname":"Yarochyshche",
    "gn:country_code":"UA",
    "gn:dem":168,
    "gn:feature_class":"P",
    "gn:feature_code":"PPL",
    "gn:name":"Yarochyshche",
    "gn:population":0,
    "gn:timezone":"Europe/Kiev",
    "iso:country":"UA",
    "name:ukr_x_preferred":[
        "Yarochyshche"
    ],
    "name:ukr_x_variant":[
        "\u042f\u0440\u043e\u0447\u0438\u0449\u0435"
    ],
    "name:und_x_variant":[
        "Yarochishche"
    ],
    "wof:name":"Yarochyshche",
    "wof:placetype":"locality"
},
  "geometry": {"coordinates":[29.19204,50.93928],"type":"Point"}
}