{
  "type": "Feature",
  "properties": {
    "gn:admin1_code":"18.0",
    "gn:asciiname":"Naderzhynshchyna",
    "gn:country_code":"UA",
    "gn:dem":95,
    "gn:feature_class":"P",
    "gn:feature_code":"PPL",
    "gn:name":"Naderzhynshchyna",
    "gn:population":0,
    "gn:timezone":"Europe/Kiev",
    "iso:country":"UA",
    "name:ukr_x_preferred":[
        "Naderzhynshchyna"
    ],
    "name:ukr_x_variant":[
        "\u041d\u0430\u0434\u0435\u0440\u0436\u0438\u043d\u0449\u0438\u043d\u0430"
    ],
    "wof:name":"Naderzhynshchyna",
    "wof:placetype":"locality"
},
  "geometry": {"coordinates":[34.69378,49.66238],"type":"Point"}
}