{
  "type": "Feature",
  "properties": {
    "gn:admin1_code":"17.0",
    "gn:asciiname":"Velikaya Balabanka",
    "gn:country_code":"UA",
    "gn:dem":8,
    "gn:feature_class":"P",
    "gn:feature_code":"PPL",
    "gn:name":"Velikaya Balabanka",
    "gn:population":0,
    "gn:timezone":"Europe/Kiev",
    "iso:country":"UA",
    "name:und_x_variant":[
        "Balabanka Mare",
        "Bol\u2019shaya Balabanka"
    ],
    "wof:name":"Velikaya Balabanka",
    "wof:placetype":"locality"
},
  "geometry": {"coordinates":[30.23333,45.88333],"type":"Point"}
}