{
  "type": "Feature",
  "properties": {
    "gn:admin1_code":"14.0",
    "gn:asciiname":"Hayove",
    "gn:country_code":"UA",
    "gn:dem":53,
    "gn:feature_class":"P",
    "gn:feature_code":"PPL",
    "gn:name":"Hayove",
    "gn:population":0,
    "gn:timezone":"Europe/Zaporozhye",
    "iso:country":"UA",
    "name:ukr_x_preferred":[
        "Hayove"
    ],
    "name:ukr_x_variant":[
        "\u0413\u0430\u0439\u043e\u0432\u0435"
    ],
    "wof:name":"Hayove",
    "wof:placetype":"locality"
},
  "geometry": {"coordinates":[39.1184,48.53225],"type":"Point"}
}