{
  "type": "Feature",
  "properties": {
    "gn:admin1_code":"18.0",
    "gn:asciiname":"Hanzhi",
    "gn:country_code":"UA",
    "gn:dem":107,
    "gn:feature_class":"P",
    "gn:feature_code":"PPL",
    "gn:name":"Hanzhi",
    "gn:population":0,
    "gn:timezone":"Europe/Kiev",
    "iso:country":"UA",
    "name:ukr_x_preferred":[
        "Hanzhi"
    ],
    "name:ukr_x_variant":[
        "\u0413\u0430\u043d\u0436\u0456"
    ],
    "name:und_x_variant":[
        "Isachki",
        "Ganzhi"
    ],
    "wof:name":"Hanzhi",
    "wof:placetype":"locality"
},
  "geometry": {"coordinates":[34.10384000000001,49.50523],"type":"Point"}
}