{
  "type": "Feature",
  "properties": {
    "gn:admin1_code":"5.0",
    "gn:asciiname":"Nekremenne",
    "gn:country_code":"UA",
    "gn:dem":103,
    "gn:feature_class":"P",
    "gn:feature_code":"PPL",
    "gn:name":"Nekremenne",
    "gn:population":0,
    "gn:timezone":"Europe/Kiev",
    "iso:country":"UA",
    "name:eng_x_preferred":[
        "Nekremennoye"
    ],
    "name:rus_x_preferred":[
        "\u041d\u0435\u043a\u0440\u0435\u043c\u0435\u043d\u043d\u043e\u0435"
    ],
    "name:ukr_x_preferred":[
        "Nekremenne"
    ],
    "name:ukr_x_variant":[
        "\u041d\u0435\u043a\u0440\u0435\u043c\u0435\u043d\u043d\u0435"
    ],
    "wof:name":"Nekremenne",
    "wof:placetype":"locality"
},
  "geometry": {"coordinates":[37.13498,48.8204],"type":"Point"}
}