{
  "type": "Feature",
  "properties": {
    "gn:admin1_code":"2.0",
    "gn:asciiname":"Zaderiyivka",
    "gn:country_code":"UA",
    "gn:dem":113,
    "gn:feature_class":"P",
    "gn:feature_code":"PPL",
    "gn:name":"Zaderiyivka",
    "gn:population":0,
    "gn:timezone":"Europe/Kiev",
    "iso:country":"UA",
    "name:eng_x_preferred":[
        "Zadereyevka"
    ],
    "name:rus_x_preferred":[
        "\u0417\u0430\u0434\u0435\u0440\u0438\u0435\u0432\u043a\u0430"
    ],
    "name:ukr_x_preferred":[
        "Zaderiyivka"
    ],
    "name:ukr_x_variant":[
        "\u0417\u0430\u0434\u0435\u0440\u0456\u0457\u0432\u043a\u0430"
    ],
    "name:und_x_variant":[
        "Zadereyevskoye",
        "Zadereyevka",
        "Zaderiyevka"
    ],
    "wof:name":"Zaderiyivka",
    "wof:placetype":"locality"
},
  "geometry": {"coordinates":[30.85497,51.90892],"type":"Point"}
}