{
  "type": "Feature",
  "properties": {
    "gn:admin1_code":"4.0",
    "gn:asciiname":"Blahovishchenka",
    "gn:country_code":"UA",
    "gn:dem":88,
    "gn:feature_class":"P",
    "gn:feature_code":"PPL",
    "gn:name":"Blahovishchenka",
    "gn:population":0,
    "gn:timezone":"Europe/Kiev",
    "iso:country":"UA",
    "name:ukr_x_preferred":[
        "Blahovishchenka"
    ],
    "name:ukr_x_variant":[
        "\u0411\u043b\u0430\u0433\u043e\u0432\u0456\u0449\u0435\u043d\u043a\u0430"
    ],
    "wof:name":"Blahovishchenka",
    "wof:placetype":"locality"
},
  "geometry": {"coordinates":[34.59085,48.42142],"type":"Point"}
}