{
  "type": "Feature",
  "properties": {
    "gn:admin1_code":"14.0",
    "gn:asciiname":"Tymoshyne",
    "gn:country_code":"UA",
    "gn:dem":159,
    "gn:feature_class":"P",
    "gn:feature_code":"PPL",
    "gn:name":"Tymoshyne",
    "gn:population":0,
    "gn:timezone":"Europe/Zaporozhye",
    "iso:country":"UA",
    "name:ukr_x_preferred":[
        "Tymoshyne"
    ],
    "name:ukr_x_variant":[
        "\u0422\u0438\u043c\u043e\u0448\u0438\u043d\u0435"
    ],
    "wof:name":"Tymoshyne",
    "wof:placetype":"locality"
},
  "geometry": {"coordinates":[38.80419000000001,49.67546],"type":"Point"}
}