{
  "type": "Feature",
  "properties": {
    "gn:admin1_code":"22.0",
    "gn:asciiname":"Tsetsory",
    "gn:country_code":"UA",
    "gn:dem":370,
    "gn:feature_class":"P",
    "gn:feature_code":"PPL",
    "gn:name":"Tsetsory",
    "gn:population":0,
    "gn:timezone":"Europe/Kiev",
    "iso:country":"UA",
    "wof:name":"Tsetsory",
    "wof:placetype":"locality"
},
  "geometry": {"coordinates":[25.27602000000001,49.60068],"type":"Point"}
}