{
  "type": "Feature",
  "properties": {
    "gn:admin1_code":"23.0",
    "gn:asciiname":"Bayrakovka",
    "gn:country_code":"UA",
    "gn:dem":311,
    "gn:feature_class":"P",
    "gn:feature_code":"PPL",
    "gn:name":"Bayrakovka",
    "gn:population":0,
    "gn:timezone":"Europe/Kiev",
    "iso:country":"UA",
    "wof:name":"Bayrakovka",
    "wof:placetype":"locality"
},
  "geometry": {"coordinates":[28.78333,49.05],"type":"Point"}
}