{
  "type": "Feature",
  "properties": {
    "iso:country":"UA",
    "name:deu_x_preferred":[
        "Nowopoltawka"
    ],
    "name:eng_x_preferred":[
        "Novopoltavka"
    ],
    "name:lav_x_preferred":[
        "Novopoltavka"
    ],
    "name:ron_x_preferred":[
        "Novopoltavka"
    ],
    "name:rus_x_preferred":[
        "\u041d\u043e\u0432\u043e\u043f\u043e\u043b\u0442\u0430\u0432\u043a\u0430"
    ],
    "name:ukr_x_preferred":[
        "\u041d\u043e\u0432\u043e\u043f\u043e\u043b\u0442\u0430\u0432\u043a\u0430"
    ],
    "name:unk_x_variant":[
        "Novaya Poltavka"
    ],
    "name:zho_x_preferred":[
        "\u65b0\u6ce2\u723e\u5854\u592b\u5361"
    ],
    "qs:a0":"\u0423\u043a\u0440\u0430\u0457\u043d\u0430",
    "qs:a1":"*\u0417\u0430\u043f\u043e\u0440\u0456\u0437\u044c\u043a\u0430",
    "qs:a1_alt":"Zaporiz'ka",
    "qs:a1r":"0",
    "qs:a2":"\u0427\u0435\u0440\u043d\u0456\u0433\u0456\u0432\u0441\u044c\u043a\u0438\u0439",
    "qs:a2_alt":"Chernihivs'kyi",
    "qs:adm0":"\u0423\u043a\u0440\u0430\u0457\u043d\u0430",
    "qs:la_lc":"*",
    "qs:level":"locality",
    "qs:loc":"\u041d\u043e\u0432\u043e\u043f\u043e\u043b\u0442\u0430\u0432\u043a\u0430",
    "qs:loc_alt":"Novopoltavka",
    "qs:pop":0,
    "qs:type":"buffered point",
    "wd:wordcount":149,
    "wof:name":"\u041d\u043e\u0432\u043e\u043f\u043e\u043b\u0442\u0430\u0432\u043a\u0430",
    "wof:placetype":"locality"
},
  "geometry": {"coordinates":[36.274102,47.263065],"type":"Point"}
}