{
  "type": "Feature",
  "properties": {
    "gn:admin1_code":"4.0",
    "gn:asciiname":"Yednost'",
    "gn:country_code":"UA",
    "gn:dem":34,
    "gn:feature_class":"P",
    "gn:feature_code":"PPL",
    "gn:name":"Yednost\u2019",
    "gn:population":0,
    "gn:timezone":"Europe/Kiev",
    "iso:country":"UA",
    "name:rus_x_preferred":[
        "Yednost\u2019"
    ],
    "name:rus_x_variant":[
        "\u0415\u0434\u043d\u043e\u0441\u0442\u044c"
    ],
    "wof:name":"Yednost'",
    "wof:placetype":"locality"
},
  "geometry": {"coordinates":[34.08098,47.84267],"type":"Point"}
}