{
  "type": "Feature",
  "properties": {
    "iso:country":"UA",
    "name:crh_x_preferred":[
        "Uspenka"
    ],
    "name:eng_x_preferred":[
        "Uspenka"
    ],
    "name:hye_x_preferred":[
        "\u0548\u0582\u057d\u057a\u0565\u0576\u056f\u0561"
    ],
    "name:ron_x_preferred":[
        "Uspenka"
    ],
    "name:rus_x_preferred":[
        "\u0423\u0441\u043f\u0435\u043d\u043a\u0430"
    ],
    "name:ukr_x_preferred":[
        "\u0423\u0441\u043f\u0435\u043d\u043a\u0430"
    ],
    "name:und_x_variant":[
        "Bol\u2019shaya Neplyuyevo"
    ],
    "name:zho_x_preferred":[
        "\u70cf\u65af\u7247\u5361"
    ],
    "qs:a0":"\u0423\u043a\u0440\u0430\u0457\u043d\u0430",
    "qs:a1":"*\u0421\u0443\u043c\u0441\u044c\u043a\u0430",
    "qs:a1_alt":"Sums'ka",
    "qs:a1r":"0",
    "qs:a2":"\u0411\u0443\u0440\u0438\u043d\u0441\u044c\u043a\u0438\u0439",
    "qs:a2_alt":"Buryns'kyi",
    "qs:adm0":"\u0423\u043a\u0440\u0430\u0457\u043d\u0430",
    "qs:la_lc":"*",
    "qs:level":"locality",
    "qs:loc":"\u0423\u0441\u043f\u0435\u043d\u043a\u0430",
    "qs:loc_alt":"Uspenka",
    "qs:pop":0,
    "qs:type":"buffered point",
    "wd:wordcount":258,
    "wof:name":"\u0423\u0441\u043f\u0435\u043d\u043a\u0430",
    "wof:placetype":"locality"
},
  "geometry": {"coordinates":[33.758268,51.113746],"type":"Point"}
}