{
  "type": "Feature",
  "properties": {
    "gn:admin1_code":"18.0",
    "gn:asciiname":"Padusi",
    "gn:country_code":"UA",
    "gn:dem":138,
    "gn:feature_class":"P",
    "gn:feature_code":"PPL",
    "gn:name":"Padusi",
    "gn:population":0,
    "gn:timezone":"Europe/Kiev",
    "iso:country":"UA",
    "name:ukr_x_preferred":[
        "Padusi"
    ],
    "name:ukr_x_variant":[
        "\u041f\u0430\u0434\u0443\u0441\u0456"
    ],
    "wof:name":"Padusi",
    "wof:placetype":"locality"
},
  "geometry": {"coordinates":[33.23278,49.84938],"type":"Point"}
}