{
  "type": "Feature",
  "properties": {
    "iso:country":"UA",
    "name:ukr_x_preferred":[
        "\u0411\u0430\u0433\u0440\u0438\u043d\u043e\u0432\u0430 \u0433\u043e\u0440\u0430"
    ],
    "wof:name":"Bagrinova Gora",
    "wof:placetype":"neighbourhood"
},
  "geometry": {"coordinates":[30.53807430524498,50.38606395229262],"type":"Point"}
}