{
  "type": "Feature",
  "properties": {
    "gn:admin1_code":"5.0",
    "gn:asciiname":"Manych",
    "gn:country_code":"UA",
    "gn:dem":95,
    "gn:feature_class":"P",
    "gn:feature_code":"PPL",
    "gn:name":"Manych",
    "gn:population":0,
    "gn:timezone":"Europe/Kiev",
    "iso:country":"UA",
    "name:ukr_x_preferred":[
        "\u041c\u0430\u043d\u0438\u0447"
    ],
    "name:und_x_variant":[
        "Many"
    ],
    "wof:name":"Manych",
    "wof:placetype":"locality"
},
  "geometry": {"coordinates":[38.74429,47.75556],"type":"Point"}
}