{
  "type": "Feature",
  "properties": {
    "gn:admin1_code":"1.0",
    "gn:asciiname":"Kolomytsi",
    "gn:country_code":"UA",
    "gn:dem":112,
    "gn:feature_class":"P",
    "gn:feature_code":"PPL",
    "gn:name":"Kolomytsi",
    "gn:population":0,
    "gn:timezone":"Europe/Kiev",
    "iso:country":"UA",
    "name:ukr_x_preferred":[
        "Kolomytsi"
    ],
    "name:ukr_x_variant":[
        "\u041a\u043e\u043b\u043e\u043c\u0438\u0446\u0456"
    ],
    "name:und_x_variant":[
        "Kolomiytsy"
    ],
    "wof:name":"Kolomytsi",
    "wof:placetype":"locality"
},
  "geometry": {"coordinates":[32.17553,50.07075],"type":"Point"}
}