{
  "type": "Feature",
  "properties": {
    "iso:country":"UA",
    "name:rus_x_preferred":[
        "Letnich\u2019ye"
    ],
    "name:ukr_x_preferred":[
        "L\u2019othyche"
    ],
    "name:ukr_x_variant":[
        "\u041b\u044c\u043e\u0442\u043d\u0438\u0447\u0435"
    ],
    "qs:a0":"\u0423\u043a\u0440\u0430\u0457\u043d\u0430",
    "qs:a1":"*\u0412\u043e\u043b\u0438\u043d\u0441\u044c\u043a\u0430",
    "qs:a1_alt":"Volyns'ka",
    "qs:a1r":"0",
    "qs:a2":"\u0412\u043e\u043b\u043e\u0434\u0438\u043c\u0438\u0440-\u0412\u043e\u043b\u0438\u043d\u0441\u044c\u043a\u0438\u0439",
    "qs:a2_alt":"Volodymyr-Volyns'kyi",
    "qs:adm0":"\u0423\u043a\u0440\u0430\u0457\u043d\u0430",
    "qs:la_lc":"*",
    "qs:level":"locality",
    "qs:loc":"\u041b\u044c\u043e\u0442\u043d\u0438\u0447\u0435",
    "qs:loc_alt":"L'otnyche",
    "qs:pop":0,
    "qs:type":"buffered point",
    "wof:name":"\u041b\u044c\u043e\u0442\u043d\u0438\u0447\u0435",
    "wof:placetype":"locality"
},
  "geometry": {"coordinates":[24.347089,50.86131],"type":"Point"}
}