{
  "type": "Feature",
  "properties": {
    "gn:admin1_code":"24.0",
    "gn:asciiname":"Velykyy Kurin'",
    "gn:country_code":"UA",
    "gn:dem":146,
    "gn:feature_class":"P",
    "gn:feature_code":"PPL",
    "gn:name":"Velykyy Kurin\u2019",
    "gn:population":0,
    "gn:timezone":"Europe/Kiev",
    "iso:country":"UA",
    "name:rus_x_preferred":[
        "Velikiy Kuren\u2019"
    ],
    "name:ukr_x_preferred":[
        "Velykyy Kurin\u2019"
    ],
    "name:ukr_x_variant":[
        "\u0412\u0435\u043b\u0438\u043a\u0438\u0439 \u041a\u0443\u0440\u0456\u043d\u044c"
    ],
    "name:und_x_variant":[
        "Kuryn\u2019"
    ],
    "wof:name":"Velykyy Kurin'",
    "wof:placetype":"locality"
},
  "geometry": {"coordinates":[25.42129,51.79144],"type":"Point"}
}