{
  "type": "Feature",
  "properties": {
    "gn:admin1_code":"21.0",
    "gn:asciiname":"Novoselivka",
    "gn:country_code":"UA",
    "gn:dem":132,
    "gn:feature_class":"P",
    "gn:feature_code":"PPL",
    "gn:name":"Novoselivka",
    "gn:population":0,
    "gn:timezone":"Europe/Kiev",
    "iso:country":"UA",
    "name:deu_x_preferred":[
        "Nowoseliwka"
    ],
    "name:hye_x_preferred":[
        "\u0546\u0578\u057e\u0578\u057d\u0575\u0578\u056c\u0578\u057e\u056f\u0561"
    ],
    "name:kaz_x_preferred":[
        "\u041d\u043e\u0432\u043e\u0441\u0435\u043b\u043e\u0432\u043a\u0430"
    ],
    "name:rus_x_preferred":[
        "\u041d\u043e\u0432\u043e\u0441\u0451\u043b\u043e\u0432\u043a\u0430"
    ],
    "name:spa_x_preferred":[
        "Novoselivka"
    ],
    "name:ukr_x_preferred":[
        "Novoselivka"
    ],
    "name:ukr_x_variant":[
        "\u041d\u043e\u0432\u043e\u0441\u0435\u043b\u0456\u0432\u043a\u0430"
    ],
    "name:und_x_variant":[
        "Novoselovka"
    ],
    "wof:name":"Novoselivka",
    "wof:placetype":"locality"
},
  "geometry": {"coordinates":[33.3024,51.26799000000001],"type":"Point"}
}