{
  "type": "Feature",
  "properties": {
    "gn:admin1_code":"21.0",
    "gn:asciiname":"Rostov",
    "gn:country_code":"UA",
    "gn:dem":160,
    "gn:feature_class":"P",
    "gn:feature_code":"PPL",
    "gn:name":"Rostov",
    "gn:population":0,
    "gn:timezone":"Europe/Kiev",
    "iso:country":"UA",
    "name:ukr_x_preferred":[
        "Rostov"
    ],
    "name:ukr_x_variant":[
        "\u0420\u043e\u0441\u0442\u043e\u0432"
    ],
    "wof:name":"Rostov",
    "wof:placetype":"locality"
},
  "geometry": {"coordinates":[33.74392,51.95915],"type":"Point"}
}