{
  "type": "Feature",
  "properties": {
    "gn:admin1_code":"23.0",
    "gn:asciiname":"Myagkokhod",
    "gn:country_code":"UA",
    "gn:dem":169,
    "gn:feature_class":"P",
    "gn:feature_code":"PPL",
    "gn:name":"Myagkokhod",
    "gn:population":0,
    "gn:timezone":"Europe/Kiev",
    "iso:country":"UA",
    "wof:name":"Myagkokhod",
    "wof:placetype":"locality"
},
  "geometry": {"coordinates":[29.67682000000001,48.54062],"type":"Point"}
}