{
  "type": "Feature",
  "properties": {
    "iso:country":"UA",
    "qs:a0":"\u0423\u043a\u0440\u0430\u0457\u043d\u0430",
    "qs:a1":"*\u0412\u0456\u043d\u043d\u0438\u0446\u044c\u043a\u0430",
    "qs:a1_alt":"Vinnyts'ka",
    "qs:a1r":"0",
    "qs:a2":"\u0413\u0430\u0439\u0441\u0438\u043d\u0441\u044c\u043a\u0438\u0439",
    "qs:a2_alt":"Haisyns'kyi",
    "qs:adm0":"\u0423\u043a\u0440\u0430\u0457\u043d\u0430",
    "qs:la_lc":"*",
    "qs:level":"locality",
    "qs:loc":"\u0413\u0443\u0431\u043d\u0438\u043a",
    "qs:loc_alt":"Hubnyk",
    "qs:pop":0,
    "qs:type":"buffered point",
    "wof:name":"\u0413\u0443\u0431\u043d\u0438\u043a",
    "wof:placetype":"locality"
},
  "geometry": {"coordinates":[29.328787,48.615764],"type":"Point"}
}