{
  "type": "Feature",
  "properties": {
    "gn:admin1_code":"14.0",
    "gn:asciiname":"Harmashivka",
    "gn:country_code":"UA",
    "gn:dem":81,
    "gn:feature_class":"P",
    "gn:feature_code":"PPL",
    "gn:name":"Harmashivka",
    "gn:population":0,
    "gn:timezone":"Europe/Zaporozhye",
    "iso:country":"UA",
    "name:ukr_x_preferred":[
        "Harmashivka"
    ],
    "name:ukr_x_variant":[
        "\u0413\u0430\u0440\u043c\u0430\u0448\u0456\u0432\u043a\u0430"
    ],
    "name:und_x_variant":[
        "Khutor Garmashev",
        "Garmashev",
        "Garmashovka"
    ],
    "wof:name":"Harmashivka",
    "wof:placetype":"locality"
},
  "geometry": {"coordinates":[39.62944,49.36389000000001],"type":"Point"}
}