{
  "type": "Feature",
  "properties": {
    "gn:admin1_code":"27.0",
    "gn:asciiname":"Myroslavl'",
    "gn:country_code":"UA",
    "gn:dem":224,
    "gn:feature_class":"P",
    "gn:feature_code":"PPL",
    "gn:name":"Myroslavl\u2019",
    "gn:population":0,
    "gn:timezone":"Europe/Kiev",
    "iso:country":"UA",
    "name:rus_x_preferred":[
        "Miroslavl\u2019"
    ],
    "name:ukr_x_preferred":[
        "Myroslavl\u2019"
    ],
    "name:ukr_x_variant":[
        "\u041c\u0438\u0440\u043e\u0441\u043b\u0430\u0432\u043b\u044c"
    ],
    "name:und_x_variant":[
        "Miroslav\u2019ye",
        "Malinovka"
    ],
    "wof:name":"Myroslavl'",
    "wof:placetype":"locality"
},
  "geometry": {"coordinates":[27.47706,50.37942],"type":"Point"}
}