{
  "type": "Feature",
  "properties": {
    "gn:admin1_code":"17.0",
    "gn:asciiname":"Kommuna Krestintern",
    "gn:country_code":"UA",
    "gn:dem":153,
    "gn:feature_class":"P",
    "gn:feature_code":"PPL",
    "gn:name":"Kommuna Krestintern",
    "gn:population":0,
    "gn:timezone":"Europe/Kiev",
    "iso:country":"UA",
    "wof:name":"Kommuna Krestintern",
    "wof:placetype":"locality"
},
  "geometry": {"coordinates":[29.42278,47.95778],"type":"Point"}
}