{
  "type": "Feature",
  "properties": {
    "iso:country":"UA",
    "name:und_x_variant":[
        "Praskoveyevka"
    ],
    "qs:a0":"\u0423\u043a\u0440\u0430\u0457\u043d\u0430",
    "qs:a1":"*\u0414\u043e\u043d\u0435\u0446\u044c\u043a\u0430",
    "qs:a1_alt":"Donets'ka",
    "qs:a1r":"0",
    "qs:a2":"\u0410\u0440\u0442\u0435\u043c\u0456\u0432\u0441\u044c\u043a\u0438\u0439",
    "qs:a2_alt":"Artemivs'kyi",
    "qs:adm0":"\u0423\u043a\u0440\u0430\u0457\u043d\u0430",
    "qs:la_lc":"*",
    "qs:level":"locality",
    "qs:loc":"\u041f\u0430\u0440\u0430\u0441\u043a\u043e\u0432\u0456\u0457\u0432\u043a\u0430",
    "qs:loc_alt":"Paraskoviivka",
    "qs:pop":0,
    "qs:type":"buffered point",
    "wof:name":"\u041f\u0430\u0440\u0430\u0441\u043a\u043e\u0432\u0456\u0457\u0432\u043a\u0430",
    "wof:placetype":"locality"
},
  "geometry": {"coordinates":[38.00041,48.675009],"type":"Point"}
}