{
  "type": "Feature",
  "properties": {
    "gn:admin1_code":"14.0",
    "gn:asciiname":"Kovyl'ne",
    "gn:country_code":"UA",
    "gn:dem":303,
    "gn:feature_class":"P",
    "gn:feature_code":"PPL",
    "gn:name":"Kovyl\u2019ne",
    "gn:population":0,
    "gn:timezone":"Europe/Zaporozhye",
    "iso:country":"UA",
    "name:ukr_x_preferred":[
        "Kovyl\u2019ne"
    ],
    "name:ukr_x_variant":[
        "\u041a\u043e\u0432\u0438\u043b\u044c\u043d\u0435"
    ],
    "wof:name":"Kovyl'ne",
    "wof:placetype":"locality"
},
  "geometry": {"coordinates":[38.92168,48.27666],"type":"Point"}
}