{
  "type": "Feature",
  "properties": {
    "gn:admin1_code":"25.0",
    "gn:asciiname":"Khmil'nyk",
    "gn:country_code":"UA",
    "gn:dem":133,
    "gn:feature_class":"P",
    "gn:feature_code":"PPL",
    "gn:name":"Khmil\u2019nyk",
    "gn:population":0,
    "gn:timezone":"Europe/Uzhgorod",
    "iso:country":"UA",
    "name:rus_x_preferred":[
        "Khmel\u2019nik"
    ],
    "name:ukr_x_preferred":[
        "Khmil\u2019nyk"
    ],
    "name:ukr_x_variant":[
        "\u0425\u043c\u0456\u043b\u044c\u043d\u0438\u043a"
    ],
    "wof:name":"Khmil'nyk",
    "wof:placetype":"locality"
},
  "geometry": {"coordinates":[22.88539,48.27681],"type":"Point"}
}