{
  "type": "Feature",
  "properties": {
    "gn:gn_country":"UA",
    "gn:gn_fcode":"PPL",
    "gn:gn_pop":6436,
    "gn:population":6436,
    "iso:country":"UA",
    "name:chi_x_preferred":[
        "\u820a\u591a\u5e03\u7f85\u7279\u7dad\u723e"
    ],
    "name:eng_x_preferred":[
        "Staryi Dobrotvir"
    ],
    "name:ger_x_preferred":[
        "Staryj Dobrotwir"
    ],
    "name:pol_x_preferred":[
        "Stary Dobrotw\u00f3r"
    ],
    "name:rum_x_preferred":[
        "Star\u00eei Dobrotvir"
    ],
    "name:rus_x_preferred":[
        "\u0421\u0442\u0430\u0440\u044b\u0439 \u0414\u043e\u0431\u0440\u043e\u0442\u0432\u043e\u0440"
    ],
    "name:ukr_x_preferred":[
        "\u0421\u0442\u0430\u0440\u0438\u0439 \u0414\u043e\u0431\u0440\u043e\u0442\u0432\u0456\u0440"
    ],
    "name:unk_x_variant":[
        "Staryy Dobrotvor"
    ],
    "qs_pg:aaroncc":"UA",
    "qs_pg:gn_country":"UA",
    "qs_pg:gn_fcode":"PPL",
    "qs_pg:gn_pop":6436,
    "qs_pg:name":"Staryy Dobrotvir",
    "qs_pg:photos_9r":0,
    "qs_pg:photos_sr":0,
    "qs_pg:pop_sr":5,
    "qs_pg:qs_pg_placetype":"locality",
    "wof:name":"Staryy Dobrotvir",
    "wof:placetype":"locality",
    "wof:population":6436
},
  "geometry": {"coordinates":[24.377,50.23154],"type":"Point"}
}