{
  "type": "Feature",
  "properties": {
    "iso:country":"UA",
    "qs:a0":"\u0423\u043a\u0440\u0430\u0457\u043d\u0430",
    "qs:a1":"*\u0422\u0435\u0440\u043d\u043e\u043f\u0456\u043b\u044c\u0441\u044c\u043a\u0430",
    "qs:a1_alt":"Ternopil's'ka",
    "qs:a1r":"0",
    "qs:a2":"\u041a\u0440\u0435\u043c\u0435\u043d\u0435\u0446\u044c\u043a\u0438\u0439",
    "qs:a2_alt":"Kremenets'kyi",
    "qs:adm0":"\u0423\u043a\u0440\u0430\u0457\u043d\u0430",
    "qs:la_lc":"*",
    "qs:level":"locality",
    "qs:loc":"\u0421\u0442\u0430\u0440\u0438\u0439 \u041f\u043e\u0447\u0430\u0457\u0432",
    "qs:loc_alt":"Staryi Pochaiv",
    "qs:pop":0,
    "qs:type":"buffered point",
    "wof:name":"\u0421\u0442\u0430\u0440\u0438\u0439 \u041f\u043e\u0447\u0430\u0457\u0432",
    "wof:placetype":"locality"
},
  "geometry": {"coordinates":[25.470836,50.011114],"type":"Point"}
}