{
  "type": "Feature",
  "properties": {
    "gn:admin1_code":"7.0",
    "gn:asciiname":"Oleksandrivka",
    "gn:country_code":"UA",
    "gn:dem":108,
    "gn:feature_class":"P",
    "gn:feature_code":"PPL",
    "gn:name":"Oleksandrivka",
    "gn:population":0,
    "gn:timezone":"Europe/Kiev",
    "iso:country":"UA",
    "name:ceb_x_preferred":[
        "Oleksandrivka"
    ],
    "name:deu_x_preferred":[
        "Olexandriwka"
    ],
    "name:est_x_preferred":[
        "Oleksandrivka"
    ],
    "name:ita_x_preferred":[
        "Oleksandrivka"
    ],
    "name:pol_x_preferred":[
        "O\u0142eksandriwka"
    ],
    "name:sco_x_preferred":[
        "Oleksandrivka"
    ],
    "name:spa_x_preferred":[
        "Oleksandrivka"
    ],
    "name:ukr_x_preferred":[
        "Oleksandrivka"
    ],
    "name:ukr_x_variant":[
        "\u041e\u043b\u0435\u043a\u0441\u0430\u043d\u0434\u0440\u0456\u0432\u043a\u0430"
    ],
    "name:und_x_variant":[
        "Aleksandrovka"
    ],
    "wof:name":"Oleksandrivka",
    "wof:placetype":"locality"
},
  "geometry": {"coordinates":[36.64938,48.7627],"type":"Point"}
}