{
  "type": "Feature",
  "properties": {
    "gn:admin1_code":"24.0",
    "gn:asciiname":"Pshovaly",
    "gn:cc2":"UA",
    "gn:country_code":"UA",
    "gn:dem":192,
    "gn:feature_class":"P",
    "gn:feature_code":"PPL",
    "gn:name":"Pshovaly",
    "gn:population":0,
    "gn:timezone":"Europe/Kiev",
    "iso:country":"UA",
    "name:und_x_variant":[
        "Pshevaly",
        "Pshovaly"
    ],
    "wof:name":"Pshovaly",
    "wof:placetype":"locality"
},
  "geometry": {"coordinates":[24.33333,51.13333],"type":"Point"}
}