{
  "type": "Feature",
  "properties": {
    "gn:admin1_code":"23.0",
    "gn:asciiname":"Posukhov",
    "gn:country_code":"UA",
    "gn:dem":278,
    "gn:feature_class":"P",
    "gn:feature_code":"PPL",
    "gn:name":"Posukhov",
    "gn:population":0,
    "gn:timezone":"Europe/Kiev",
    "iso:country":"UA",
    "wof:name":"Posukhov",
    "wof:placetype":"locality"
},
  "geometry": {"coordinates":[27.56599000000001,48.75816],"type":"Point"}
}