{
  "type": "Feature",
  "properties": {
    "gn:admin1_code":"5.0",
    "gn:asciiname":"Malovodne",
    "gn:country_code":"UA",
    "gn:dem":167,
    "gn:feature_class":"P",
    "gn:feature_code":"PPL",
    "gn:name":"Malovodne",
    "gn:population":0,
    "gn:timezone":"Europe/Kiev",
    "iso:country":"UA",
    "name:ukr_x_preferred":[
        "Malovodne"
    ],
    "name:ukr_x_variant":[
        "\u041c\u0430\u043b\u043e\u0432\u043e\u0434\u043d\u0435"
    ],
    "wof:name":"Malovodne",
    "wof:placetype":"locality"
},
  "geometry": {"coordinates":[37.67762000000001,47.36983],"type":"Point"}
}