{
  "type": "Feature",
  "properties": {
    "gn:admin1_code":"8.0",
    "gn:asciiname":"Ptakhivka",
    "gn:country_code":"UA",
    "gn:dem":16,
    "gn:feature_class":"P",
    "gn:feature_code":"PPL",
    "gn:name":"Ptakhivka",
    "gn:population":0,
    "gn:timezone":"Europe/Kiev",
    "iso:country":"UA",
    "name:rus_x_preferred":[
        "\u041f\u0442\u0430\u0445\u043e\u0432\u043a\u0430"
    ],
    "name:ukr_x_preferred":[
        "\u041f\u0442\u0430\u0445\u0456\u0432\u043a\u0430"
    ],
    "name:und_x_variant":[
        "Aleksandrovka",
        "Ptakhovka",
        "Ptakhivka"
    ],
    "wof:name":"Ptakhivka",
    "wof:placetype":"locality"
},
  "geometry": {"coordinates":[33.08991,46.29425],"type":"Point"}
}