{
  "type": "Feature",
  "properties": {
    "gn:country":"UA",
    "gn:fcode":"PPL",
    "gn:population":3264,
    "iso:country":"UA",
    "name:bel_x_preferred":[
        "\u0410\u0431\u044d\u0440\u0442\u044b\u043d"
    ],
    "name:cat_x_preferred":[
        "Obertin"
    ],
    "name:ceb_x_preferred":[
        "Obertyn"
    ],
    "name:ces_x_preferred":[
        "Obertyn"
    ],
    "name:che_x_preferred":[
        "\u041e\u0431\u0435\u0440\u0442\u0438\u043d"
    ],
    "name:crh_x_preferred":[
        "Obert\u0131n"
    ],
    "name:deu_x_preferred":[
        "Obertyn"
    ],
    "name:ell_x_preferred":[
        "\u039f\u03bc\u03c0\u03b5\u03c1\u03c4\u03af\u03bd"
    ],
    "name:eng_x_preferred":[
        "Obertyn"
    ],
    "name:fra_x_preferred":[
        "Obertyn"
    ],
    "name:heb_x_preferred":[
        "\u05d0\u05d5\u05d1\u05e8\u05d8\u05d9\u05df"
    ],
    "name:jpn_x_preferred":[
        "\u30aa\u30d0\u30fc\u30c6\u30a3\uff9d"
    ],
    "name:nld_x_preferred":[
        "Obertyn"
    ],
    "name:pol_x_preferred":[
        "Obertyn"
    ],
    "name:ron_x_preferred":[
        "Obertyn"
    ],
    "name:rus_x_preferred":[
        "\u041e\u0431\u0435\u0440\u0442\u0438\u043d"
    ],
    "name:ukr_x_preferred":[
        "\u041e\u0431\u0435\u0440\u0442\u0438\u043d"
    ],
    "name:uzb_x_preferred":[
        "Obertyn"
    ],
    "name:zho_x_preferred":[
        "\u5967\u5225\u723e\u4eac"
    ],
    "qs_pg:aaroncc":"UA",
    "qs_pg:gn_country":"UA",
    "qs_pg:gn_fcode":"PPL",
    "qs_pg:gn_pop":3264,
    "qs_pg:name":"Obertin",
    "qs_pg:name_adm0":"Ukraine",
    "qs_pg:name_adm1":"Ivano-Frankivs\u00b4ka Oblast\u00b4",
    "qs_pg:photos_9k":1,
    "qs_pg:photos_9r":1,
    "qs_pg:photos_all":7,
    "qs_pg:photos_sr":0,
    "qs_pg:pop_sr":4,
    "qs_pg:qs_pg_placetype":"locality",
    "qs_pg:qs_pg_placetype_gp":"Town",
    "qs_pg:woe_adm0":23424976,
    "woe:adm0_id":23424976,
    "woe:name_adm0":"Ukraine",
    "woe:name_adm1":"Ivano-Frankivs\u00b4ka Oblast\u00b4",
    "woe:placetype":"Town",
    "wof:name":"Obertin",
    "wof:placetype":"locality",
    "wof:population":3264
},
  "geometry": {"coordinates":[25.17012,48.70032],"type":"Point"}
}