{
  "type": "Feature",
  "properties": {
    "gn:admin1_code":"17.0",
    "gn:asciiname":"Salhany",
    "gn:country_code":"UA",
    "gn:dem":35,
    "gn:feature_class":"P",
    "gn:feature_code":"PPL",
    "gn:name":"Salhany",
    "gn:population":1186,
    "gn:timezone":"Europe/Kiev",
    "iso:country":"UA",
    "name:ukr_x_preferred":[
        "Salhany"
    ],
    "name:ukr_x_variant":[
        "\u0421\u0430\u043b\u0433\u0430\u043d\u0438"
    ],
    "name:und_x_variant":[
        "Salgany"
    ],
    "wof:name":"Salhany",
    "wof:placetype":"locality",
    "wof:population":1186
},
  "geometry": {"coordinates":[30.34601,46.14881],"type":"Point"}
}