{
  "type": "Feature",
  "properties": {
    "gn:admin1_code":"18.0",
    "gn:asciiname":"Novofedorivka",
    "gn:country_code":"UA",
    "gn:dem":98,
    "gn:feature_class":"P",
    "gn:feature_code":"PPL",
    "gn:name":"Novofedorivka",
    "gn:population":0,
    "gn:timezone":"Europe/Kiev",
    "iso:country":"UA",
    "name:rus_x_preferred":[
        "F\u00ebdorovka"
    ],
    "name:ukr_x_preferred":[
        "Novofedorivka"
    ],
    "name:ukr_x_variant":[
        "\u041d\u043e\u0432\u043e\u0444\u0435\u0434\u043e\u0440\u0456\u0432\u043a\u0430"
    ],
    "wof:name":"Novofedorivka",
    "wof:placetype":"locality"
},
  "geometry": {"coordinates":[35.09004,49.6839],"type":"Point"}
}