{
  "type": "Feature",
  "properties": {
    "gn:admin1_code":"27.0",
    "gn:asciiname":"Zabolot'",
    "gn:country_code":"UA",
    "gn:dem":178,
    "gn:feature_class":"P",
    "gn:feature_code":"PPL",
    "gn:name":"Zabolot\u2019",
    "gn:population":0,
    "gn:timezone":"Europe/Kiev",
    "iso:country":"UA",
    "name:ukr_x_preferred":[
        "\u0417\u0430\u0431\u043e\u043b\u043e\u0442\u044c"
    ],
    "name:und_x_variant":[
        "Zabolot\u2019",
        "Zabolot\u2019ye",
        "Zablot\u2019"
    ],
    "wof:name":"Zabolot'",
    "wof:placetype":"locality"
},
  "geometry": {"coordinates":[29.22537,50.57573],"type":"Point"}
}