{
  "type": "Feature",
  "properties": {
    "gn:admin1_code":"10.0",
    "gn:asciiname":"Bratolyubovka",
    "gn:country_code":"UA",
    "gn:dem":136,
    "gn:feature_class":"P",
    "gn:feature_code":"PPL",
    "gn:name":"Bratolyubovka",
    "gn:population":0,
    "gn:timezone":"Europe/Kiev",
    "iso:country":"UA",
    "name:che_x_preferred":[
        "\u0411\u0440\u0430\u0442\u043e\u043b\u044e\u0431\u043e\u0432\u043a\u0430"
    ],
    "name:eng_x_preferred":[
        "Bratolyubovka"
    ],
    "name:rus_x_preferred":[
        "\u0411\u0440\u0430\u0442\u043e\u043b\u044e\u0431\u043e\u0432\u043a\u0430"
    ],
    "wof:name":"Bratolyubovka",
    "wof:placetype":"locality"
},
  "geometry": {"coordinates":[32.95152,48.21113],"type":"Point"}
}