{
  "type": "Feature",
  "properties": {
    "iso:country":"UA",
    "name:crh_x_preferred":[
        "Novgorodske"
    ],
    "name:deu_x_preferred":[
        "Nowhorodske"
    ],
    "name:eng_x_preferred":[
        "Novgorodskoye"
    ],
    "name:eng_x_variant":[
        "Novhorodske"
    ],
    "name:hye_x_preferred":[
        "\u0546\u0578\u057e\u0563\u0578\u0580\u0578\u0564\u057d\u056f\u0578\u0565"
    ],
    "name:lav_x_preferred":[
        "Novhorodske"
    ],
    "name:rus_x_preferred":[
        "\u041d\u043e\u0432\u0433\u043e\u0440\u043e\u0434\u0441\u043a\u043e\u0435"
    ],
    "name:ukr_x_preferred":[
        "\u041d\u043e\u0432\u0433\u043e\u0440\u043e\u0434\u0441\u044c\u043a\u0435"
    ],
    "name:und_x_variant":[
        "Novgorods\u2019ke"
    ],
    "name:zho_x_preferred":[
        "\u8afe\u592b\u6208\u7f85\u5fb7\u897f\u514b"
    ],
    "qs:a0":"\u0423\u043a\u0440\u0430\u0457\u043d\u0430",
    "qs:a1":"*\u0414\u043e\u043d\u0435\u0446\u044c\u043a\u0430",
    "qs:a1_alt":"Donets'ka",
    "qs:a1r":"0",
    "qs:a2":"\u041a\u043e\u0441\u0442\u044f\u043d\u0442\u0438\u043d\u0456\u0432\u0441\u044c\u043a\u0438\u0439",
    "qs:a2_alt":"Kostiantynivs'kyi",
    "qs:adm0":"\u0423\u043a\u0440\u0430\u0457\u043d\u0430",
    "qs:la_lc":"*",
    "qs:level":"locality",
    "qs:loc":"\u041d\u043e\u0432\u0433\u043e\u0440\u043e\u0434\u0441\u044c\u043a\u0435",
    "qs:loc_alt":"Novhorods'ke",
    "qs:pop":0,
    "qs:type":"buffered point",
    "wof:name":"\u041d\u043e\u0432\u0433\u043e\u0440\u043e\u0434\u0441\u044c\u043a\u0435",
    "wof:placetype":"locality"
},
  "geometry": {"coordinates":[37.851305,48.3151],"type":"Point"}
}