{
  "type": "Feature",
  "properties": {
    "gn:admin1_code":"23.0",
    "gn:asciiname":"Kusikovtsy",
    "gn:country_code":"UA",
    "gn:dem":286,
    "gn:feature_class":"P",
    "gn:feature_code":"PPL",
    "gn:name":"Kusikovtsy",
    "gn:population":0,
    "gn:timezone":"Europe/Kiev",
    "iso:country":"UA",
    "name:und_x_variant":[
        "Kusikivtsy",
        "Kusikovtsy"
    ],
    "wof:name":"Kusikovtsy",
    "wof:placetype":"locality"
},
  "geometry": {"coordinates":[27.93005,49.4164],"type":"Point"}
}