{
  "type": "Feature",
  "properties": {
    "gn:admin1_code":"17.0",
    "gn:asciiname":"Anastas'yevka Vtoraya",
    "gn:country_code":"UA",
    "gn:dem":53,
    "gn:feature_class":"P",
    "gn:feature_code":"PPL",
    "gn:name":"Anastas\u2019yevka Vtoraya",
    "gn:population":0,
    "gn:timezone":"Europe/Kiev",
    "iso:country":"UA",
    "wof:name":"Anastas'yevka Vtoraya",
    "wof:placetype":"locality"
},
  "geometry": {"coordinates":[30.36667000000001,47.56667],"type":"Point"}
}