{
  "type": "Feature",
  "properties": {
    "gn:admin1_code":"22.0",
    "gn:asciiname":"Soroka",
    "gn:country_code":"UA",
    "gn:dem":298,
    "gn:feature_class":"P",
    "gn:feature_code":"PPL",
    "gn:name":"Soroka",
    "gn:population":0,
    "gn:timezone":"Europe/Kiev",
    "iso:country":"UA",
    "wof:name":"Soroka",
    "wof:placetype":"locality"
},
  "geometry": {"coordinates":[26.0123,49.22043],"type":"Point"}
}