{
  "type": "Feature",
  "properties": {
    "gn:admin1_code":"26.0",
    "gn:asciiname":"Shevchenka",
    "gn:country_code":"UA",
    "gn:dem":100,
    "gn:feature_class":"P",
    "gn:feature_code":"PPL",
    "gn:name":"Shevchenka",
    "gn:population":0,
    "gn:timezone":"Europe/Zaporozhye",
    "iso:country":"UA",
    "name:ukr_x_preferred":[
        "Shevchenka"
    ],
    "name:ukr_x_variant":[
        "\u0428\u0435\u0432\u0447\u0435\u043d\u043a\u0430"
    ],
    "name:und_x_variant":[
        "Shevchenko"
    ],
    "wof:name":"Shevchenka",
    "wof:placetype":"locality"
},
  "geometry": {"coordinates":[35.25917000000001,48.12109],"type":"Point"}
}