{
  "type": "Feature",
  "properties": {
    "gn:admin1_code":"2.0",
    "gn:asciiname":"Malyye Osnyaki",
    "gn:cc2":"UA",
    "gn:country_code":"UA",
    "gn:dem":145,
    "gn:feature_class":"P",
    "gn:feature_code":"PPL",
    "gn:name":"Malyye Osnyaki",
    "gn:population":0,
    "gn:timezone":"Europe/Kiev",
    "iso:country":"UA",
    "name:und_x_variant":[
        "Malyye-osnjaki",
        "Malyye Osnyaki"
    ],
    "wof:name":"Malyye Osnyaki",
    "wof:placetype":"locality"
},
  "geometry": {"coordinates":[30.93333,51.46667],"type":"Point"}
}