{
  "type": "Feature",
  "properties": {
    "gn:admin1_code":"10.0",
    "gn:asciiname":"Lelekovka",
    "gn:country_code":"UA",
    "gn:dem":118,
    "gn:feature_class":"P",
    "gn:feature_code":"PPL",
    "gn:name":"Lelekovka",
    "gn:population":0,
    "gn:timezone":"Europe/Kiev",
    "iso:country":"UA",
    "wof:name":"Lelekovka",
    "wof:placetype":"locality"
},
  "geometry": {"coordinates":[32.21844,48.56062],"type":"Point"}
}