{
  "type": "Feature",
  "properties": {
    "gn:admin1_code":"21.0",
    "gn:asciiname":"Yasnopillya",
    "gn:country_code":"UA",
    "gn:dem":188,
    "gn:feature_class":"P",
    "gn:feature_code":"PPL",
    "gn:name":"Yasnopillya",
    "gn:population":0,
    "gn:timezone":"Europe/Kiev",
    "iso:country":"UA",
    "name:ukr_x_preferred":[
        "Komisarivka"
    ],
    "name:ukr_x_variant":[
        "\u041a\u043e\u043c\u0456\u0441\u0430\u0440\u0456\u0432\u043a\u0430",
        "Yasnopillya",
        "\u042f\u0441\u043d\u043e\u043f\u0456\u043b\u043b\u044f"
    ],
    "name:und_x_variant":[
        "Komissarovka"
    ],
    "wof:name":"Yasnopillya",
    "wof:placetype":"locality"
},
  "geometry": {"coordinates":[34.29393,50.80222],"type":"Point"}
}