{
  "type": "Feature",
  "properties": {
    "gn:admin1_code":"4.0",
    "gn:asciiname":"Lyubomirovka",
    "gn:country_code":"UA",
    "gn:dem":141,
    "gn:feature_class":"P",
    "gn:feature_code":"PPL",
    "gn:name":"Lyubomirovka",
    "gn:population":0,
    "gn:timezone":"Europe/Kiev",
    "iso:country":"UA",
    "name:ukr_x_preferred":[
        "\u041b\u044e\u0431\u043e\u043c\u0438\u0440\u0456\u0432\u043a\u0430"
    ],
    "name:und_x_variant":[
        "Kazyduby",
        "Kozodub",
        "Ljubomirowka",
        "Lyudmylivka",
        "Lyubomirovka"
    ],
    "wof:name":"Lyubomirovka",
    "wof:placetype":"locality"
},
  "geometry": {"coordinates":[34.32060999999999,48.4379],"type":"Point"}
}