{
  "type": "Feature",
  "properties": {
    "iso:country":"UA",
    "name:eng_x_preferred":[
        "Pervomayskoye"
    ],
    "name:rus_x_historical":[
        "\u041a\u0430\u0440\u0430\u0433\u043e\u0301\u0437"
    ],
    "name:rus_x_preferred":[
        "\u041f\u0435\u0440\u0432\u043e\u043c\u0430\u0439\u0441\u043a\u043e\u0435"
    ],
    "name:rus_x_variant":[
        "\u041a\u0430\u0440\u0430\u0433\u043e\u0301\u0437"
    ],
    "name:ukr_x_preferred":[
        "\u041f\u0435\u0440\u0432\u043e\u043c\u0430\u0439\u0441\u044c\u043a\u0435"
    ],
    "qs:a0":"\u0423\u043a\u0440\u0430\u0457\u043d\u0430",
    "qs:a1":"*\u041a\u0440\u0438\u043c",
    "qs:a1_alt":"Krym",
    "qs:a1r":"0",
    "qs:a2":"\u041a\u0456\u0440\u043e\u0432\u0441\u044c\u043a\u0438\u0439",
    "qs:a2_alt":"Kirovs'kyi",
    "qs:adm0":"\u0423\u043a\u0440\u0430\u0457\u043d\u0430",
    "qs:la_lc":"*",
    "qs:level":"locality",
    "qs:loc":"\u041f\u0435\u0440\u0432\u043e\u043c\u0430\u0439\u0441\u044c\u043a\u0435",
    "qs:loc_alt":"Pervomais'ke",
    "qs:pop":0,
    "qs:type":"buffered point",
    "wof:name":"\u041f\u0435\u0440\u0432\u043e\u043c\u0430\u0439\u0441\u044c\u043a\u0435",
    "wof:placetype":"locality"
},
  "geometry": {"coordinates":[35.168374,45.05889],"type":"Point"}
}