{
  "type": "Feature",
  "properties": {
    "iso:country":"UA",
    "name:eng_x_preferred":[
        "Verbove"
    ],
    "name:rus_x_preferred":[
        "\u0412\u0435\u0440\u0431\u043e\u0432\u043e\u0435"
    ],
    "name:ukr_x_preferred":[
        "\u0412\u0435\u0440\u0431\u043e\u0432\u0435"
    ],
    "name:und_x_variant":[
        "Verbovoye"
    ],
    "qs:a0":"\u0423\u043a\u0440\u0430\u0457\u043d\u0430",
    "qs:a1":"*\u0417\u0430\u043f\u043e\u0440\u0456\u0437\u044c\u043a\u0430",
    "qs:a1_alt":"Zaporiz'ka",
    "qs:a1r":"0",
    "qs:a2":"\u041f\u043e\u043b\u043e\u0433\u0456\u0432\u0441\u044c\u043a\u0438\u0439",
    "qs:a2_alt":"Polohivs'kyi",
    "qs:adm0":"\u0423\u043a\u0440\u0430\u0457\u043d\u0430",
    "qs:la_lc":"*",
    "qs:level":"locality",
    "qs:loc":"\u0412\u0435\u0440\u0431\u043e\u0432\u0435",
    "qs:loc_alt":"Verbove",
    "qs:pop":0,
    "qs:type":"buffered point",
    "wof:name":"\u0412\u0435\u0440\u0431\u043e\u0432\u0435",
    "wof:placetype":"locality"
},
  "geometry": {"coordinates":[36.011472,47.417193],"type":"Point"}
}