{
  "type": "Feature",
  "properties": {
    "gn:admin1_code":"27",
    "gn:asciiname":"Rozdol'ne",
    "gn:country_code":"UA",
    "gn:dem":229,
    "gn:feature_class":"P",
    "gn:feature_code":"PPL",
    "gn:name":"Rozdol\u2019ne",
    "gn:population":0,
    "gn:timezone":"Europe/Kiev",
    "iso:country":"UA",
    "name:ukr_x_preferred":[
        "Rozdol\u2019ne"
    ],
    "name:ukr_x_variant":[
        "\u0420\u043e\u0437\u0434\u043e\u043b\u044c\u043d\u0435"
    ],
    "wof:name":"Rozdol'ne",
    "wof:placetype":"locality"
},
  "geometry": {"coordinates":[28.46347,50.02873],"type":"Point"}
}