{
  "type": "Feature",
  "properties": {
    "gn:admin1_code":"22.0",
    "gn:asciiname":"Molotkov",
    "gn:country_code":"UA",
    "gn:dem":303,
    "gn:feature_class":"P",
    "gn:feature_code":"PPL",
    "gn:name":"Molotkov",
    "gn:population":0,
    "gn:timezone":"Europe/Kiev",
    "iso:country":"UA",
    "name:und_x_variant":[
        "Molotkuv",
        "Molotkov"
    ],
    "wof:name":"Molotkov",
    "wof:placetype":"locality"
},
  "geometry": {"coordinates":[26.19618,49.81719],"type":"Point"}
}