{
  "type": "Feature",
  "properties": {
    "gn:admin1_code":"14.0",
    "gn:asciiname":"Kalinine",
    "gn:country_code":"UA",
    "gn:dem":166,
    "gn:feature_class":"P",
    "gn:feature_code":"PPL",
    "gn:name":"Kalinine",
    "gn:population":0,
    "gn:timezone":"Europe/Zaporozhye",
    "iso:country":"UA",
    "name:ukr_x_preferred":[
        "Kalinine"
    ],
    "name:ukr_x_variant":[
        "\u041a\u0430\u043b\u0456\u043d\u0456\u043d\u0435"
    ],
    "name:und_x_variant":[
        "Kalinino",
        "Kalinovka"
    ],
    "wof:name":"Kalinine",
    "wof:placetype":"locality"
},
  "geometry": {"coordinates":[38.4029,49.94891],"type":"Point"}
}