{
  "type": "Feature",
  "properties": {
    "gn:admin1_code":"2.0",
    "gn:asciiname":"Chervonyy Lan",
    "gn:country_code":"UA",
    "gn:dem":132,
    "gn:feature_class":"P",
    "gn:feature_code":"PPL",
    "gn:name":"Chervonyy Lan",
    "gn:population":0,
    "gn:timezone":"Europe/Kiev",
    "iso:country":"UA",
    "name:ukr_x_preferred":[
        "Chervonyy Lan"
    ],
    "name:ukr_x_variant":[
        "\u0427\u0435\u0440\u0432\u043e\u043d\u0438\u0439 \u041b\u0430\u043d"
    ],
    "name:und_x_variant":[
        "Chervonny Lan",
        "Chervonnyy Lan"
    ],
    "wof:name":"Chervonyy Lan",
    "wof:placetype":"locality"
},
  "geometry": {"coordinates":[33.19398,51.57755],"type":"Point"}
}