{
  "type": "Feature",
  "properties": {
    "gn:admin1_code":"4.0",
    "gn:asciiname":"Hrushky",
    "gn:country_code":"UA",
    "gn:dem":128,
    "gn:feature_class":"P",
    "gn:feature_code":"PPL",
    "gn:name":"Hrushky",
    "gn:population":0,
    "gn:timezone":"Europe/Kiev",
    "iso:country":"UA",
    "name:ukr_x_preferred":[
        "Hrushky"
    ],
    "name:ukr_x_variant":[
        "\u0413\u0440\u0443\u0448\u043a\u0438"
    ],
    "name:und_x_variant":[
        "Grushki"
    ],
    "wof:name":"Hrushky",
    "wof:placetype":"locality"
},
  "geometry": {"coordinates":[33.803,48.09426],"type":"Point"}
}