{
  "type": "Feature",
  "properties": {
    "gn:admin1_code":"16.0",
    "gn:asciiname":"Novosvetlovka",
    "gn:country_code":"UA",
    "gn:dem":76,
    "gn:feature_class":"P",
    "gn:feature_code":"PPL",
    "gn:name":"Novosvetlovka",
    "gn:population":0,
    "gn:timezone":"Europe/Kiev",
    "iso:country":"UA",
    "name:und_x_variant":[
        "Rorbakh",
        "Koloniya Rorbakh",
        "Novosvetlovka"
    ],
    "wof:name":"Novosvetlovka",
    "wof:placetype":"locality"
},
  "geometry": {"coordinates":[31.18389,47.19885],"type":"Point"}
}