{
  "type": "Feature",
  "properties": {
    "gn:admin1_code":"3.0",
    "gn:asciiname":"Novosel'tsy",
    "gn:country_code":"UA",
    "gn:dem":238,
    "gn:feature_class":"P",
    "gn:feature_code":"PPL",
    "gn:name":"Novosel\u2019tsy",
    "gn:population":0,
    "gn:timezone":"Europe/Kiev",
    "iso:country":"UA",
    "name:und_x_variant":[
        "Sulita",
        "Noua Sulitsa",
        "Nuvaselitz",
        "Novoselitskiy",
        "Novoselitsy",
        "Novoselitsa",
        "Noua Suli\u0163\u0103",
        "Novosel\u2019tsy"
    ],
    "wof:name":"Novosel'tsy",
    "wof:placetype":"locality"
},
  "geometry": {"coordinates":[26.98904000000001,48.43355],"type":"Point"}
}