{
  "type": "Feature",
  "properties": {
    "gn:admin1_code":"7.0",
    "gn:asciiname":"Nova Hnylytsya",
    "gn:country_code":"UA",
    "gn:dem":130,
    "gn:feature_class":"P",
    "gn:feature_code":"PPL",
    "gn:name":"Nova Hnylytsya",
    "gn:population":0,
    "gn:timezone":"Europe/Kiev",
    "iso:country":"UA",
    "name:ukr_x_preferred":[
        "Nova Hnylytsya"
    ],
    "name:ukr_x_variant":[
        "\u041d\u043e\u0432\u0430 \u0413\u043d\u0438\u043b\u0438\u0446\u044f"
    ],
    "name:und_x_variant":[
        "Novo-Gnilitsa"
    ],
    "wof:name":"Nova Hnylytsya",
    "wof:placetype":"locality"
},
  "geometry": {"coordinates":[36.86722,49.70992],"type":"Point"}
}