{
  "type": "Feature",
  "properties": {
    "gn:admin1_code":"18.0",
    "gn:asciiname":"Mogil'nyy",
    "gn:country_code":"UA",
    "gn:dem":142,
    "gn:feature_class":"P",
    "gn:feature_code":"PPL",
    "gn:name":"Mogil\u2019nyy",
    "gn:population":0,
    "gn:timezone":"Europe/Kiev",
    "iso:country":"UA",
    "wof:name":"Mogil'nyy",
    "wof:placetype":"locality"
},
  "geometry": {"coordinates":[34.43833,50.07111],"type":"Point"}
}