{
  "type": "Feature",
  "properties": {
    "gn:admin1_code":"6.0",
    "gn:asciiname":"Gorod",
    "gn:country_code":"UA",
    "gn:dem":409,
    "gn:feature_class":"P",
    "gn:feature_code":"PPL",
    "gn:name":"Gorod",
    "gn:population":0,
    "gn:timezone":"Europe/Kiev",
    "iso:country":"UA",
    "wof:name":"Gorod",
    "wof:placetype":"locality"
},
  "geometry": {"coordinates":[25.03982,48.30179],"type":"Point"}
}