{
  "type": "Feature",
  "properties": {
    "gn:admin1_code":"7.0",
    "gn:asciiname":"Shcherbaky",
    "gn:country_code":"UA",
    "gn:dem":162,
    "gn:feature_class":"P",
    "gn:feature_code":"PPL",
    "gn:name":"Shcherbaky",
    "gn:population":0,
    "gn:timezone":"Europe/Kiev",
    "iso:country":"UA",
    "name:ukr_x_preferred":[
        "Shcherbaky"
    ],
    "name:ukr_x_variant":[
        "\u0429\u0435\u0440\u0431\u0430\u043a\u0438"
    ],
    "name:und_x_variant":[
        "Sncherbaki",
        "Shcherbaki"
    ],
    "wof:name":"Shcherbaky",
    "wof:placetype":"locality"
},
  "geometry": {"coordinates":[35.44613,50.19059],"type":"Point"}
}