{
  "type": "Feature",
  "properties": {
    "gn:gn_country":"UA",
    "gn:gn_fcode":"PPL",
    "gn:gn_pop":15761,
    "gn:population":15761,
    "iso:country":"UA",
    "name:ara_x_preferred":[
        "\u0623\u0631\u062a\u0633\u064a\u0632"
    ],
    "name:bul_x_preferred":[
        "\u0410\u0440\u0446\u0438\u0437"
    ],
    "name:ces_x_preferred":[
        "Arcyz"
    ],
    "name:crh_x_preferred":[
        "Arts\u0131z"
    ],
    "name:deu_x_preferred":[
        "Arzys"
    ],
    "name:eng_x_preferred":[
        "Artsyz"
    ],
    "name:fas_x_preferred":[
        "\u0622\u0631\u062a\u0633\u06cc\u0632"
    ],
    "name:fra_x_preferred":[
        "Artsyz"
    ],
    "name:hsb_x_preferred":[
        "Arcyz"
    ],
    "name:hye_x_preferred":[
        "\u0531\u0580\u0581\u056b\u0566"
    ],
    "name:ita_x_preferred":[
        "Arcyz"
    ],
    "name:kat_x_preferred":[
        "\u10d0\u10e0\u10ea\u10d8\u10d6\u10d8"
    ],
    "name:kaz_x_preferred":[
        "\u0410\u0440\u0446\u0438\u0437"
    ],
    "name:lav_x_preferred":[
        "Arciza"
    ],
    "name:lit_x_preferred":[
        "Arcyzas"
    ],
    "name:nld_x_preferred":[
        "Artsyz"
    ],
    "name:nno_x_preferred":[
        "Artsyz"
    ],
    "name:nob_x_preferred":[
        "Artsyz"
    ],
    "name:pol_x_preferred":[
        "Arcyz"
    ],
    "name:ron_x_preferred":[
        "Arciz"
    ],
    "name:rus_x_preferred":[
        "\u0410\u0440\u0446\u0438\u0437"
    ],
    "name:sah_x_preferred":[
        "\u0410\u0440\u0446\u0438\u0437"
    ],
    "name:spa_x_preferred":[
        "Artsyz"
    ],
    "name:tat_x_preferred":[
        "\u0410\u0440\u0441\u044b\u0437"
    ],
    "name:ukr_x_preferred":[
        "\u0410\u0440\u0446\u0438\u0437"
    ],
    "name:unk_x_variant":[
        "Arsiz"
    ],
    "name:vie_x_preferred":[
        "Artsyz"
    ],
    "name:zho_x_preferred":[
        "\u963f\u723e\u9f4a\u8332"
    ],
    "qs_pg:aaroncc":"UA",
    "qs_pg:gn_country":"UA",
    "qs_pg:gn_fcode":"PPL",
    "qs_pg:gn_pop":15761,
    "qs_pg:name":"Artsyz",
    "qs_pg:photos_9r":0,
    "qs_pg:photos_sr":0,
    "qs_pg:pop_sr":6,
    "qs_pg:qs_pg_placetype":"locality",
    "wof:name":"Artsyz",
    "wof:placetype":"locality",
    "wof:population":15761
},
  "geometry": {"coordinates":[29.41824,45.99194],"type":"Point"}
}