{
  "type": "Feature",
  "properties": {
    "gn:admin1_code":"21.0",
    "gn:asciiname":"Burchak",
    "gn:country_code":"UA",
    "gn:dem":181,
    "gn:feature_class":"P",
    "gn:feature_code":"PPL",
    "gn:name":"Burchak",
    "gn:population":0,
    "gn:timezone":"Europe/Kiev",
    "iso:country":"UA",
    "name:ukr_x_preferred":[
        "Burchak"
    ],
    "name:ukr_x_variant":[
        "\u0411\u0443\u0440\u0447\u0430\u043a"
    ],
    "name:und_x_variant":[
        "Burchan"
    ],
    "wof:name":"Burchak",
    "wof:placetype":"locality"
},
  "geometry": {"coordinates":[34.57404,51.03772],"type":"Point"}
}