{
  "type": "Feature",
  "properties": {
    "gn:admin1_code":"18.0",
    "gn:asciiname":"Vyshen'ky",
    "gn:country_code":"UA",
    "gn:dem":96,
    "gn:feature_class":"P",
    "gn:feature_code":"PPL",
    "gn:name":"Vyshen\u2019ky",
    "gn:population":0,
    "gn:timezone":"Europe/Kiev",
    "iso:country":"UA",
    "name:ukr_x_preferred":[
        "Vyshen\u2019ky"
    ],
    "name:ukr_x_variant":[
        "\u0412\u0438\u0448\u0435\u043d\u044c\u043a\u0438"
    ],
    "wof:name":"Vyshen'ky",
    "wof:placetype":"locality"
},
  "geometry": {"coordinates":[33.02503,49.37492],"type":"Point"}
}