{
  "type": "Feature",
  "properties": {
    "gn:admin1_code":"8.0",
    "gn:asciiname":"Popelak",
    "gn:country_code":"UA",
    "gn:dem":29,
    "gn:feature_class":"P",
    "gn:feature_code":"PPL",
    "gn:name":"Popelak",
    "gn:population":0,
    "gn:timezone":"Europe/Kiev",
    "iso:country":"UA",
    "name:ukr_x_preferred":[
        "\u041f\u043e\u043f\u0435\u043b\u0430\u043a"
    ],
    "name:und_x_variant":[
        "Popilnak",
        "Popelak"
    ],
    "wof:name":"Popelak",
    "wof:placetype":"locality"
},
  "geometry": {"coordinates":[34.43158,46.52629],"type":"Point"}
}