{
  "type": "Feature",
  "properties": {
    "gn:admin1_code":"21.0",
    "gn:asciiname":"Khyl'kove",
    "gn:country_code":"UA",
    "gn:dem":170,
    "gn:feature_class":"P",
    "gn:feature_code":"PPL",
    "gn:name":"Khyl\u2019kove",
    "gn:population":0,
    "gn:timezone":"Europe/Kiev",
    "iso:country":"UA",
    "name:ukr_x_preferred":[
        "Khyl\u2019kove"
    ],
    "name:ukr_x_variant":[
        "\u0425\u0438\u043b\u044c\u043a\u043e\u0432\u0435"
    ],
    "name:und_x_variant":[
        "Khil\u2019koy"
    ],
    "wof:name":"Khyl'kove",
    "wof:placetype":"locality"
},
  "geometry": {"coordinates":[34.57398,50.7712],"type":"Point"}
}