{
  "type": "Feature",
  "properties": {
    "iso:country":"UA",
    "name:eng_x_preferred":[
        "Hnizdychne"
    ],
    "name:pol_x_preferred":[
        "Hniezdyczna"
    ],
    "name:ron_x_preferred":[
        "Hnizd\u00eecine"
    ],
    "name:rus_x_preferred":[
        "\u0413\u043d\u0435\u0437\u0434\u044b\u0447\u043d\u043e"
    ],
    "name:ukr_x_preferred":[
        "\u0413\u043d\u0456\u0437\u0434\u0438\u0447\u043d\u0435"
    ],
    "name:unk_x_variant":[
        "Gnezdechna"
    ],
    "name:zho_x_preferred":[
        "\u683c\u5c3c\u8332\u5b63\u5947\u6d85"
    ],
    "qs:a0":"\u0423\u043a\u0440\u0430\u0457\u043d\u0430",
    "qs:a1":"*\u0422\u0435\u0440\u043d\u043e\u043f\u0456\u043b\u044c\u0441\u044c\u043a\u0430",
    "qs:a1_alt":"Ternopil's'ka",
    "qs:a1r":"0",
    "qs:a2":"\u041a\u0440\u0435\u043c\u0435\u043d\u0435\u0446\u044c\u043a\u0438\u0439",
    "qs:a2_alt":"Kremenets'kyi",
    "qs:adm0":"\u0423\u043a\u0440\u0430\u0457\u043d\u0430",
    "qs:la_lc":"*",
    "qs:level":"locality",
    "qs:loc":"\u0413\u043d\u0456\u0437\u0434\u0438\u0447\u043d\u0435",
    "qs:loc_alt":"Hnizdychne",
    "qs:pop":0,
    "qs:type":"buffered point",
    "wd:wordcount":541,
    "wof:name":"\u0413\u043d\u0456\u0437\u0434\u0438\u0447\u043d\u0435",
    "wof:placetype":"locality"
},
  "geometry": {"coordinates":[25.640593,49.806573],"type":"Point"}
}