{
  "type": "Feature",
  "properties": {
    "gn:admin1_code":"9.0",
    "gn:asciiname":"Privorot'ye",
    "gn:country_code":"UA",
    "gn:dem":318,
    "gn:feature_class":"P",
    "gn:feature_code":"PPL",
    "gn:name":"Privorot\u2019ye",
    "gn:population":0,
    "gn:timezone":"Europe/Kiev",
    "iso:country":"UA",
    "wof:name":"Privorot'ye",
    "wof:placetype":"locality"
},
  "geometry": {"coordinates":[26.96948,48.70197],"type":"Point"}
}