{
  "type": "Feature",
  "properties": {
    "gn:admin1_code":"27.0",
    "gn:asciiname":"Novozelene",
    "gn:country_code":"UA",
    "gn:dem":222,
    "gn:feature_class":"P",
    "gn:feature_code":"PPL",
    "gn:name":"Novozelene",
    "gn:population":0,
    "gn:timezone":"Europe/Kiev",
    "iso:country":"UA",
    "name:ukr_x_preferred":[
        "Novozelene"
    ],
    "name:ukr_x_variant":[
        "\u041d\u043e\u0432\u043e\u0437\u0435\u043b\u0435\u043d\u0435"
    ],
    "name:und_x_variant":[
        "Novozelenoye"
    ],
    "wof:name":"Novozelene",
    "wof:placetype":"locality"
},
  "geometry": {"coordinates":[27.88514,50.61263],"type":"Point"}
}