{
  "type": "Feature",
  "properties": {
    "gn:admin1_code":"11.0",
    "gn:admin2_code":"694905",
    "gn:admin3_code":"11153096.0",
    "gn:asciiname":"Listovoye",
    "gn:country_code":"UA",
    "gn:dem":19,
    "gn:elevation":"17.0",
    "gn:feature_class":"P",
    "gn:feature_code":"PPL",
    "gn:name":"Listovoye",
    "gn:population":301,
    "gn:timezone":"Europe/Simferopol",
    "iso:country":"UA",
    "name:eng_x_preferred":[
        "Listovoye"
    ],
    "name:rus_x_historical":[
        "\u0412\u043e\u0301\u0439\u043e-\u041d\u043e\u0301\u0432\u0430"
    ],
    "name:rus_x_preferred":[
        "\u041b\u0438\u0441\u0442\u043e\u0432\u043e\u0435"
    ],
    "name:rus_x_variant":[
        "\u0412\u043e\u0301\u0439\u043e-\u041d\u043e\u0301\u0432\u0430"
    ],
    "name:ukr_x_preferred":[
        "\u041b\u0438\u0441\u0442\u043e\u0432\u0435"
    ],
    "wof:name":"Listovoye",
    "wof:placetype":"locality",
    "wof:population":301
},
  "geometry": {"coordinates":[33.66595,45.2603],"type":"Point"}
}