{
  "type": "Feature",
  "properties": {
    "gn:population":4569,
    "iso:country":"UA",
    "name:bel_x_preferred":[
        "\u0425\u043e\u0446\u0456\u045e"
    ],
    "name:ceb_x_preferred":[
        "Khotiv"
    ],
    "name:che_x_preferred":[
        "\u0425\u043e\u0442\u043e\u0432"
    ],
    "name:deu_x_preferred":[
        "Chotiw"
    ],
    "name:eng_x_preferred":[
        "Khotiv"
    ],
    "name:fin_x_preferred":[
        "Khotin"
    ],
    "name:hye_x_preferred":[
        "\u053d\u0578\u057f\u0578\u057e"
    ],
    "name:nno_x_preferred":[
        "Khotiv"
    ],
    "name:nob_x_preferred":[
        "Khotiv"
    ],
    "name:pol_x_preferred":[
        "Chotiw"
    ],
    "name:ron_x_preferred":[
        "Hotiv"
    ],
    "name:rus_x_preferred":[
        "\u0425\u043e\u0442\u043e\u0432"
    ],
    "name:tat_x_preferred":[
        "\u0425\u043e\u0442\u0438\u0432"
    ],
    "name:ukr_x_preferred":[
        "\u0425\u043e\u0442\u0456\u0432"
    ],
    "name:und_x_variant":[
        "Khotov"
    ],
    "name:zho_x_preferred":[
        "\u970d\u5b63\u592b"
    ],
    "qs:a0":"\u0423\u043a\u0440\u0430\u0457\u043d\u0430",
    "qs:a1":"*\u041a\u0438\u0457\u0432\u0441\u044c\u043a\u0430",
    "qs:a1_alt":"Kyivs'ka",
    "qs:a1r":"0",
    "qs:a2":"\u041a\u0438\u0454\u0432\u043e-\u0421\u0432\u044f\u0442\u043e\u0448\u0438\u043d\u0441\u044c\u043a\u0438\u0439",
    "qs:a2_alt":"Kyievo-Sviatoshyns'kyi",
    "qs:adm0":"\u0423\u043a\u0440\u0430\u0457\u043d\u0430",
    "qs:la_lc":"*",
    "qs:level":"locality",
    "qs:loc":"\u0425\u043e\u0442\u0456\u0432",
    "qs:loc_alt":"Khotiv",
    "qs:pop":0,
    "qs:type":"buffered point",
    "wd:wordcount":142,
    "wof:name":"\u0425\u043e\u0442\u0456\u0432",
    "wof:placetype":"locality",
    "wof:population":4569
},
  "geometry": {"coordinates":[30.467833,50.331042],"type":"Point"}
}