{
  "type": "Feature",
  "properties": {
    "gn:admin1_code":"18.0",
    "gn:asciiname":"Berezivka",
    "gn:country_code":"UA",
    "gn:dem":141,
    "gn:feature_class":"P",
    "gn:feature_code":"PPL",
    "gn:name":"Berezivka",
    "gn:population":0,
    "gn:timezone":"Europe/Kiev",
    "iso:country":"UA",
    "name:ukr_x_preferred":[
        "\u0411\u0435\u0440\u0435\u0437\u0456\u0432\u043a\u0430"
    ],
    "name:und_x_variant":[
        "Ber\u00ebzovka"
    ],
    "wof:name":"Berezivka",
    "wof:placetype":"locality"
},
  "geometry": {"coordinates":[33.1789,49.91793],"type":"Point"}
}