{
  "type": "Feature",
  "properties": {
    "gn:admin1_code":"4.0",
    "gn:asciiname":"Otrishky",
    "gn:country_code":"UA",
    "gn:dem":170,
    "gn:feature_class":"P",
    "gn:feature_code":"PPL",
    "gn:name":"Otrishky",
    "gn:population":0,
    "gn:timezone":"Europe/Kiev",
    "iso:country":"UA",
    "name:ukr_x_preferred":[
        "Otrishky"
    ],
    "name:ukr_x_variant":[
        "\u041e\u0442\u0440\u0456\u0448\u043a\u0438"
    ],
    "name:und_x_variant":[
        "Otrishki"
    ],
    "wof:name":"Otrishky",
    "wof:placetype":"locality"
},
  "geometry": {"coordinates":[36.28645,48.08402],"type":"Point"}
}