{
  "type": "Feature",
  "properties": {
    "gn:admin1_code":"16.0",
    "gn:asciiname":"Novoskelyuvatka",
    "gn:country_code":"UA",
    "gn:dem":87,
    "gn:feature_class":"P",
    "gn:feature_code":"PPL",
    "gn:name":"Novoskelyuvatka",
    "gn:population":0,
    "gn:timezone":"Europe/Kiev",
    "iso:country":"UA",
    "name:eng_x_preferred":[
        "Novoskelevatka"
    ],
    "name:rus_x_preferred":[
        "\u041d\u043e\u0432\u043e\u0441\u043a\u0435\u043b\u0435\u0432\u0430\u0442\u043a\u0430"
    ],
    "name:ukr_x_preferred":[
        "Novoskelyuvatka"
    ],
    "name:ukr_x_variant":[
        "\u041d\u043e\u0432\u043e\u0441\u043a\u0435\u043b\u044e\u0432\u0430\u0442\u043a\u0430"
    ],
    "wof:name":"Novoskelyuvatka",
    "wof:placetype":"locality"
},
  "geometry": {"coordinates":[32.95652,48.02602],"type":"Point"}
}