{
  "type": "Feature",
  "properties": {
    "gn:admin1_code":"5.0",
    "gn:asciiname":"Viktoriya",
    "gn:country_code":"UA",
    "gn:dem":180,
    "gn:feature_class":"P",
    "gn:feature_code":"PPL",
    "gn:name":"Viktoriya",
    "gn:population":0,
    "gn:timezone":"Europe/Kiev",
    "iso:country":"UA",
    "name:ukr_x_preferred":[
        "Viktoriya"
    ],
    "name:ukr_x_variant":[
        "\u0412\u0456\u043a\u0442\u043e\u0440\u0456\u044f"
    ],
    "wof:name":"Viktoriya",
    "wof:placetype":"locality"
},
  "geometry": {"coordinates":[38.47457,48.06682],"type":"Point"}
}