{
  "type": "Feature",
  "properties": {
    "gn:admin1_code":"13.0",
    "gn:asciiname":"Dubove",
    "gn:country_code":"UA",
    "gn:dem":123,
    "gn:feature_class":"P",
    "gn:feature_code":"PPL",
    "gn:name":"Dubove",
    "gn:population":0,
    "gn:timezone":"Europe/Kiev",
    "iso:country":"UA",
    "name:bel_x_preferred":[
        "\u0414\u0443\u0431\u0430\u0432\u044d"
    ],
    "name:deu_x_preferred":[
        "Dubov\u00e9"
    ],
    "name:epo_x_preferred":[
        "Dubov\u00e9"
    ],
    "name:fra_x_preferred":[
        "Dubov\u00e9"
    ],
    "name:hun_x_preferred":[
        "Dubov\u00e9"
    ],
    "name:ita_x_preferred":[
        "Dubov\u00e9"
    ],
    "name:nld_x_preferred":[
        "Dubov\u00e9"
    ],
    "name:pol_x_preferred":[
        "Dubov\u00e9"
    ],
    "name:ron_x_preferred":[
        "Dubove"
    ],
    "name:rus_x_preferred":[
        "Bol\u2019shevik"
    ],
    "name:slk_x_preferred":[
        "Dubov\u00e9"
    ],
    "name:srp_x_preferred":[
        "\u0414\u0443\u0431\u043e\u0432\u0435"
    ],
    "name:ukr_x_preferred":[
        "Bil\u2019shovyk"
    ],
    "name:ukr_x_variant":[
        "\u0411\u0456\u043b\u044c\u0448\u043e\u0432\u0438\u043a",
        "Dubove",
        "\u0414\u0443\u0431\u043e\u0432\u0435"
    ],
    "wof:name":"Dubove",
    "wof:placetype":"locality"
},
  "geometry": {"coordinates":[31.59527000000001,50.29419],"type":"Point"}
}