{
  "type": "Feature",
  "properties": {
    "gn:admin1_code":"8.0",
    "gn:asciiname":"Sukhyy Stavok",
    "gn:country_code":"UA",
    "gn:dem":64,
    "gn:feature_class":"P",
    "gn:feature_code":"PPL",
    "gn:name":"Sukhyy Stavok",
    "gn:population":0,
    "gn:timezone":"Europe/Kiev",
    "iso:country":"UA",
    "name:ukr_x_preferred":[
        "Sukhyy Stavok"
    ],
    "name:ukr_x_variant":[
        "\u0421\u0443\u0445\u0438\u0439 \u0421\u0442\u0430\u0432\u043e\u043a"
    ],
    "name:und_x_variant":[
        "Sukhoy Stavok"
    ],
    "wof:name":"Sukhyy Stavok",
    "wof:placetype":"locality"
},
  "geometry": {"coordinates":[33.10468,47.15823],"type":"Point"}
}