{
  "type": "Feature",
  "properties": {
    "iso:country":"UA",
    "name:und_x_variant":[
        "Galaurovka"
    ],
    "qs:a0":"\u0423\u043a\u0440\u0430\u0457\u043d\u0430",
    "qs:a1":"*\u041a\u0438\u0457\u0432\u0441\u044c\u043a\u0430",
    "qs:a1_alt":"Kyivs'ka",
    "qs:a1r":"0",
    "qs:a2":"\u0411\u043e\u0440\u0438\u0441\u043f\u0456\u043b\u044c\u0441\u044c\u043a\u0438\u0439",
    "qs:a2_alt":"Boryspil's'kyi",
    "qs:adm0":"\u0423\u043a\u0440\u0430\u0457\u043d\u0430",
    "qs:la_lc":"*",
    "qs:level":"locality",
    "qs:loc":"\u0413\u043e\u043b\u043e\u0432\u0443\u0440\u0456\u0432",
    "qs:loc_alt":"Holovuriv",
    "qs:pop":0,
    "qs:type":"buffered point",
    "wof:name":"\u0413\u043e\u043b\u043e\u0432\u0443\u0440\u0456\u0432",
    "wof:placetype":"locality"
},
  "geometry": {"coordinates":[30.983746,50.182858],"type":"Point"}
}