{
  "type": "Feature",
  "properties": {
    "iso:country":"UA",
    "name:eng_x_preferred":[
        "Zimovishche"
    ],
    "name:rus_x_preferred":[
        "\u0417\u0438\u043c\u043e\u0432\u0438\u0449\u0435"
    ],
    "name:ukr_x_preferred":[
        "Zymovyshche"
    ],
    "name:ukr_x_variant":[
        "\u0417\u0438\u043c\u043e\u0432\u0438\u0449\u0435"
    ],
    "qs:a0":"\u0423\u043a\u0440\u0430\u0457\u043d\u0430",
    "qs:a1":"*\u041a\u0438\u0457\u0432\u0441\u044c\u043a\u0430",
    "qs:a1_alt":"Kyivs'ka",
    "qs:a1r":"0",
    "qs:a2":"\u0406\u0432\u0430\u043d\u043a\u0456\u0432\u0441\u044c\u043a\u0438\u0439",
    "qs:a2_alt":"Ivankivs'kyi",
    "qs:adm0":"\u0423\u043a\u0440\u0430\u0457\u043d\u0430",
    "qs:la_lc":"*",
    "qs:level":"locality",
    "qs:loc":"\u0417\u0438\u043c\u043e\u0432\u0438\u0449\u0435",
    "qs:loc_alt":"Zymovysche",
    "qs:pop":0,
    "qs:type":"buffered point",
    "wof:name":"\u0417\u0438\u043c\u043e\u0432\u0438\u0449\u0435",
    "wof:placetype":"locality"
},
  "geometry": {"coordinates":[30.191007,51.421349],"type":"Point"}
}