{
  "type": "Feature",
  "properties": {
    "gn:admin1_code":"7.0",
    "gn:asciiname":"Manuyilivka",
    "gn:country_code":"UA",
    "gn:dem":117,
    "gn:feature_class":"P",
    "gn:feature_code":"PPL",
    "gn:name":"Manuyilivka",
    "gn:population":0,
    "gn:timezone":"Europe/Kiev",
    "iso:country":"UA",
    "name:ukr_x_preferred":[
        "Manuyilivka"
    ],
    "name:ukr_x_variant":[
        "\u041c\u0430\u043d\u0443\u0457\u043b\u0456\u0432\u043a\u0430"
    ],
    "wof:name":"Manuyilivka",
    "wof:placetype":"locality"
},
  "geometry": {"coordinates":[35.93259000000001,50.07121],"type":"Point"}
}