{
  "type": "Feature",
  "properties": {
    "gn:admin1_code":"5.0",
    "gn:asciiname":"Ternove",
    "gn:country_code":"UA",
    "gn:dem":246,
    "gn:feature_class":"P",
    "gn:feature_code":"PPL",
    "gn:name":"Ternove",
    "gn:population":0,
    "gn:timezone":"Europe/Kiev",
    "iso:country":"UA",
    "name:ukr_x_preferred":[
        "Ternove"
    ],
    "name:ukr_x_variant":[
        "\u0422\u0435\u0440\u043d\u043e\u0432\u0435"
    ],
    "name:und_x_variant":[
        "Ternovyy"
    ],
    "wof:name":"Ternove",
    "wof:placetype":"locality"
},
  "geometry": {"coordinates":[38.56217,48.00572],"type":"Point"}
}