{
  "type": "Feature",
  "properties": {
    "gn:admin1_code":"14.0",
    "gn:asciiname":"Rassypnoy",
    "gn:cc2":"UA",
    "gn:country_code":"UA",
    "gn:dem":146,
    "gn:feature_class":"P",
    "gn:feature_code":"PPL",
    "gn:name":"Rassypnoy",
    "gn:population":0,
    "gn:timezone":"Europe/Zaporozhye",
    "iso:country":"UA",
    "name:und_x_variant":[
        "Verkhniy Rassypnoy",
        "Rassypnoy"
    ],
    "wof:name":"Rassypnoy",
    "wof:placetype":"locality"
},
  "geometry": {"coordinates":[39.18083,48.63972],"type":"Point"}
}