{
  "type": "Feature",
  "properties": {
    "gn:admin1_code":"8.0",
    "gn:asciiname":"Krasno-Radenskoye",
    "gn:cc2":"UA",
    "gn:country_code":"UA",
    "gn:dem":27,
    "gn:feature_class":"P",
    "gn:feature_code":"PPL",
    "gn:name":"Krasno-Radenskoye",
    "gn:population":0,
    "gn:timezone":"Europe/Kiev",
    "iso:country":"UA",
    "name:und_x_variant":[
        "Khutora Radinskiye Orlovy",
        "Krasno-Radenskoye"
    ],
    "wof:name":"Krasno-Radenskoye",
    "wof:placetype":"locality"
},
  "geometry": {"coordinates":[32.76667,46.25],"type":"Point"}
}