{
  "type": "Feature",
  "properties": {
    "gn:admin1_code":"6.0",
    "gn:asciiname":"Chekhova",
    "gn:country_code":"UA",
    "gn:dem":299,
    "gn:feature_class":"P",
    "gn:feature_code":"PPL",
    "gn:name":"Chekhova",
    "gn:population":0,
    "gn:timezone":"Europe/Kiev",
    "iso:country":"UA",
    "wof:name":"Chekhova",
    "wof:placetype":"locality"
},
  "geometry": {"coordinates":[25.27207000000001,48.59807],"type":"Point"}
}