{
  "type": "Feature",
  "properties": {
    "gn:admin1_code":"5.0",
    "gn:asciiname":"Klinovoe",
    "gn:country_code":"UA",
    "gn:dem":155,
    "gn:feature_class":"P",
    "gn:feature_code":"PPL",
    "gn:name":"Klinovoe",
    "gn:population":0,
    "gn:timezone":"Europe/Kiev",
    "iso:country":"UA",
    "name:rus_x_preferred":[
        "\u041a\u043b\u0438\u043d\u043e\u0432\u043e\u0435"
    ],
    "wof:name":"Klinovoe",
    "wof:placetype":"locality"
},
  "geometry": {"coordinates":[37.67343,48.61351],"type":"Point"}
}