{
  "type": "Feature",
  "properties": {
    "gn:admin1_code":"21.0",
    "gn:asciiname":"Mykolayivka",
    "gn:country_code":"UA",
    "gn:dem":153,
    "gn:feature_class":"P",
    "gn:feature_code":"PPL",
    "gn:name":"Mykolayivka",
    "gn:population":0,
    "gn:timezone":"Europe/Kiev",
    "iso:country":"UA",
    "name:ukr_x_preferred":[
        "Mykolayivka"
    ],
    "name:ukr_x_variant":[
        "\u041c\u0438\u043a\u043e\u043b\u0430\u0457\u0432\u043a\u0430"
    ],
    "name:und_x_variant":[
        "Nikolayevka"
    ],
    "wof:name":"Mykolayivka",
    "wof:placetype":"locality"
},
  "geometry": {"coordinates":[33.9021,51.09208],"type":"Point"}
}