{
  "type": "Feature",
  "properties": {
    "gn:admin1_code":"2.0",
    "gn:asciiname":"Lykholitky",
    "gn:country_code":"UA",
    "gn:dem":111,
    "gn:feature_class":"P",
    "gn:feature_code":"PPL",
    "gn:name":"Lykholitky",
    "gn:population":0,
    "gn:timezone":"Europe/Kiev",
    "iso:country":"UA",
    "name:ukr_x_preferred":[
        "Lykholitky"
    ],
    "name:ukr_x_variant":[
        "\u041b\u0438\u0445\u043e\u043b\u0456\u0442\u043a\u0438"
    ],
    "name:und_x_variant":[
        "Likholetki"
    ],
    "wof:name":"Lykholitky",
    "wof:placetype":"locality"
},
  "geometry": {"coordinates":[31.14106,50.94898],"type":"Point"}
}