{
  "type": "Feature",
  "properties": {
    "gn:admin1_code":"18.0",
    "gn:asciiname":"Ustymenky",
    "gn:country_code":"UA",
    "gn:dem":184,
    "gn:feature_class":"P",
    "gn:feature_code":"PPL",
    "gn:name":"Ustymenky",
    "gn:population":0,
    "gn:timezone":"Europe/Kiev",
    "iso:country":"UA",
    "name:ukr_x_preferred":[
        "Ustymenky"
    ],
    "name:ukr_x_variant":[
        "\u0423\u0441\u0442\u0438\u043c\u0435\u043d\u043a\u0438"
    ],
    "wof:name":"Ustymenky",
    "wof:placetype":"locality"
},
  "geometry": {"coordinates":[34.52558,49.97579],"type":"Point"}
}