{
  "type": "Feature",
  "properties": {
    "gn:admin1_code":"23.0",
    "gn:asciiname":"Kislyak",
    "gn:country_code":"UA",
    "gn:dem":183,
    "gn:feature_class":"P",
    "gn:feature_code":"PPL",
    "gn:name":"Kislyak",
    "gn:population":0,
    "gn:timezone":"Europe/Kiev",
    "iso:country":"UA",
    "wof:name":"Kislyak",
    "wof:placetype":"locality"
},
  "geometry": {"coordinates":[29.4162,48.84073],"type":"Point"}
}