{
  "type": "Feature",
  "properties": {
    "gn:admin1_code":"9.0",
    "gn:asciiname":"Pereroslov",
    "gn:country_code":"UA",
    "gn:dem":288,
    "gn:feature_class":"P",
    "gn:feature_code":"PPL",
    "gn:name":"Pereroslov",
    "gn:population":0,
    "gn:timezone":"Europe/Kiev",
    "iso:country":"UA",
    "name:und_x_variant":[
        "Pererosloye",
        "Pereroslov"
    ],
    "wof:name":"Pereroslov",
    "wof:placetype":"locality"
},
  "geometry": {"coordinates":[26.38663,50.13042],"type":"Point"}
}