{
  "type": "Feature",
  "properties": {
    "gn:admin1_code":"10.0",
    "gn:asciiname":"Stavidla",
    "gn:country_code":"UA",
    "gn:dem":172,
    "gn:feature_class":"P",
    "gn:feature_code":"PPL",
    "gn:name":"Stavidla",
    "gn:population":0,
    "gn:timezone":"Europe/Kiev",
    "iso:country":"UA",
    "name:eng_x_preferred":[
        "Stavidla"
    ],
    "name:rus_x_preferred":[
        "\u0421\u0442\u0430\u0432\u0438\u0434\u043b\u0430"
    ],
    "name:und_x_variant":[
        "Stavishcha",
        "Stavidlo",
        "Stavydla"
    ],
    "wof:name":"Stavidla",
    "wof:placetype":"locality"
},
  "geometry": {"coordinates":[31.98623,48.83933],"type":"Point"}
}