{
  "type": "Feature",
  "properties": {
    "gn:admin1_code":"2.0",
    "gn:asciiname":"Krasylivka",
    "gn:country_code":"UA",
    "gn:dem":141,
    "gn:feature_class":"P",
    "gn:feature_code":"PPL",
    "gn:name":"Krasylivka",
    "gn:population":0,
    "gn:timezone":"Europe/Kiev",
    "iso:country":"UA",
    "name:ukr_x_preferred":[
        "Krasylivka"
    ],
    "name:ukr_x_variant":[
        "\u041a\u0440\u0430\u0441\u0438\u043b\u0456\u0432\u043a\u0430"
    ],
    "name:und_x_variant":[
        "Krasilovka"
    ],
    "wof:name":"Krasylivka",
    "wof:placetype":"locality"
},
  "geometry": {"coordinates":[32.56885,51.14616],"type":"Point"}
}