{
  "type": "Feature",
  "properties": {
    "gn:admin1_code":"19.0",
    "gn:asciiname":"Novosilky",
    "gn:country_code":"UA",
    "gn:dem":245,
    "gn:feature_class":"P",
    "gn:feature_code":"PPL",
    "gn:name":"Novosilky",
    "gn:population":0,
    "gn:timezone":"Europe/Kiev",
    "iso:country":"UA",
    "name:ukr_x_preferred":[
        "Novosilky"
    ],
    "name:ukr_x_variant":[
        "\u041d\u043e\u0432\u043e\u0441\u0456\u043b\u043a\u0438"
    ],
    "name:und_x_variant":[
        "Novoselki"
    ],
    "wof:name":"Novosilky",
    "wof:placetype":"locality"
},
  "geometry": {"coordinates":[25.62636,50.69849],"type":"Point"}
}