{
  "type": "Feature",
  "properties": {
    "gn:admin1_code":"14.0",
    "gn:asciiname":"Krasne Pole",
    "gn:country_code":"UA",
    "gn:dem":152,
    "gn:feature_class":"P",
    "gn:feature_code":"PPL",
    "gn:name":"Krasne Pole",
    "gn:population":0,
    "gn:timezone":"Europe/Zaporozhye",
    "iso:country":"UA",
    "name:ces_x_preferred":[
        "Kr\u00e1sn\u00e9 Pole"
    ],
    "name:slk_x_preferred":[
        "Kr\u00e1sn\u00e9 Pole"
    ],
    "name:ukr_x_preferred":[
        "Krasne Pole"
    ],
    "name:ukr_x_variant":[
        "\u041a\u0440\u0430\u0441\u043d\u0435 \u041f\u043e\u043b\u0435"
    ],
    "name:und_x_variant":[
        "Krasnoye Pole"
    ],
    "wof:name":"Krasne Pole",
    "wof:placetype":"locality"
},
  "geometry": {"coordinates":[39.51694000000001,49.66944],"type":"Point"}
}