{
  "type": "Feature",
  "properties": {
    "gn:admin1_code":"2.0",
    "gn:asciiname":"Novi Yarylovychi",
    "gn:country_code":"UA",
    "gn:dem":122,
    "gn:feature_class":"P",
    "gn:feature_code":"PPL",
    "gn:name":"Novi Yarylovychi",
    "gn:population":667,
    "gn:timezone":"Europe/Kiev",
    "iso:country":"UA",
    "name:eng_x_preferred":[
        "Novyye Yarylovichi"
    ],
    "name:ron_x_preferred":[
        "Novi Iar\u00eelov\u00eeci"
    ],
    "name:rus_x_preferred":[
        "\u041d\u043e\u0432\u044b\u0435 \u042f\u0440\u044b\u043b\u043e\u0432\u0438\u0447\u0438"
    ],
    "name:ukr_x_preferred":[
        "Novi Yarylovychi"
    ],
    "name:ukr_x_variant":[
        "\u041d\u043e\u0432\u0456 \u042f\u0440\u0438\u043b\u043e\u0432\u0438\u0447\u0456"
    ],
    "name:und_x_variant":[
        "Novyye Yarylovichi"
    ],
    "name:zho_x_preferred":[
        "\u65b0\u4e9e\u91cc\u6d1b\u7dad\u5947"
    ],
    "wof:name":"Novi Yarylovychi",
    "wof:placetype":"locality",
    "wof:population":667
},
  "geometry": {"coordinates":[31.00605,52.0302],"type":"Point"}
}