{
  "type": "Feature",
  "properties": {
    "gn:admin1_code":"4.0",
    "gn:asciiname":"Klevtsova",
    "gn:country_code":"UA",
    "gn:dem":132,
    "gn:feature_class":"P",
    "gn:feature_code":"PPL",
    "gn:name":"Klevtsova",
    "gn:population":0,
    "gn:timezone":"Europe/Kiev",
    "iso:country":"UA",
    "name:und_x_variant":[
        "Klebtsova",
        "Klevtsova"
    ],
    "wof:name":"Klevtsova",
    "wof:placetype":"locality"
},
  "geometry": {"coordinates":[35.61667,48.85],"type":"Point"}
}