{
  "type": "Feature",
  "properties": {
    "gn:admin1_code":"11.0",
    "gn:admin2_code":"703233",
    "gn:admin3_code":"11128516.0",
    "gn:asciiname":"Krasnogorka",
    "gn:country_code":"UA",
    "gn:dem":52,
    "gn:feature_class":"P",
    "gn:feature_code":"PPLA3",
    "gn:name":"Krasnogorka",
    "gn:population":827,
    "gn:timezone":"Europe/Simferopol",
    "iso:country":"UA",
    "name:eng_x_preferred":[
        "Krasnogorka"
    ],
    "name:rus_x_historical":[
        "\u041a\u0435\u043d\u0435\u0433\u0435\u0301\u0437",
        "\u041a\u043e\u043f-\u041a\u0435\u043d\u0435\u0433\u0435\u0301\u0437"
    ],
    "name:rus_x_preferred":[
        "\u041a\u0440\u0430\u0441\u043d\u043e\u0433\u043e\u0440\u043a\u0430"
    ],
    "name:rus_x_variant":[
        "\u041a\u0435\u043d\u0435\u0433\u0435\u0301\u0437",
        "\u041a\u043e\u043f-\u041a\u0435\u043d\u0435\u0433\u0435\u0301\u0437"
    ],
    "name:ukr_x_preferred":[
        "\u041a\u0440\u0430\u0441\u043d\u043e\u0433\u0456\u0440\u043a\u0430"
    ],
    "wof:name":"Krasnogorka",
    "wof:placetype":"locality",
    "wof:population":827
},
  "geometry": {"coordinates":[35.80739000000001,45.24513],"type":"Point"}
}