{
  "type": "Feature",
  "properties": {
    "iso:country":"UA",
    "name:crh_x_preferred":[
        "Kalinino"
    ],
    "name:eng_x_preferred":[
        "Kalinino"
    ],
    "name:eng_x_variant":[
        "\u041d\u043e\u0432\u043e\u043f\u043e\u043a\u0440\u043e\u0432\u043a\u0430",
        "Kalinine"
    ],
    "name:hye_x_preferred":[
        "\u053f\u0561\u056c\u056b\u0576\u056b\u0576\u0578"
    ],
    "name:nld_x_preferred":[
        "Kalinino"
    ],
    "name:pol_x_preferred":[
        "Kalinine"
    ],
    "name:ron_x_preferred":[
        "Kalinine"
    ],
    "name:rus_x_historical":[
        "\u041a\u0430\u043b\u0438\u043d\u0438\u043d\u0434\u043e\u0301\u0440\u0444"
    ],
    "name:rus_x_preferred":[
        "\u041a\u0430\u043b\u0438\u043d\u0438\u043d\u0434\u043e\u0301\u0440\u0444"
    ],
    "name:rus_x_variant":[
        "\u041a\u0430\u043b\u0438\u043d\u0438\u043d\u043e"
    ],
    "name:ukr_x_preferred":[
        "\u041a\u0430\u043b\u0456\u043d\u0456\u043d\u0435"
    ],
    "qs:a0":"\u0423\u043a\u0440\u0430\u0457\u043d\u0430",
    "qs:a1":"*\u041a\u0440\u0438\u043c",
    "qs:a1_alt":"Krym",
    "qs:a1r":"0",
    "qs:a2":"\u041a\u0440\u0430\u0441\u043d\u043e\u0433\u0432\u0430\u0440\u0434\u0456\u0439\u0441\u044c\u043a\u0438\u0439",
    "qs:a2_alt":"Krasnohvardiis'kyi",
    "qs:adm0":"\u0423\u043a\u0440\u0430\u0457\u043d\u0430",
    "qs:la_lc":"*",
    "qs:level":"locality",
    "qs:loc":"\u041a\u0430\u043b\u0456\u043d\u0456\u043d\u0435",
    "qs:loc_alt":"Kalinine",
    "qs:pop":0,
    "qs:type":"buffered point",
    "wof:name":"\u041a\u0430\u043b\u0456\u043d\u0456\u043d\u0435",
    "wof:placetype":"locality"
},
  "geometry": {"coordinates":[34.225481,45.589989],"type":"Point"}
}