{
  "type": "Feature",
  "properties": {
    "gn:admin1_code":"8.0",
    "gn:asciiname":"Pryozerne",
    "gn:country_code":"UA",
    "gn:dem":7,
    "gn:feature_class":"P",
    "gn:feature_code":"PPL",
    "gn:name":"Pryozerne",
    "gn:population":0,
    "gn:timezone":"Europe/Kiev",
    "iso:country":"UA",
    "name:ukr_x_preferred":[
        "Pryozerne"
    ],
    "name:ukr_x_variant":[
        "\u041f\u0440\u0438\u043e\u0437\u0435\u0440\u043d\u0435"
    ],
    "name:und_x_variant":[
        "Priozernoye"
    ],
    "wof:name":"Pryozerne",
    "wof:placetype":"locality"
},
  "geometry": {"coordinates":[34.78274,46.06966],"type":"Point"}
}