{
  "type": "Feature",
  "properties": {
    "iso:country":"UA",
    "name:bel_x_preferred":[
        "\u0413\u0430\u0440\u043d\u0430\u0441\u0442\u0430\u0439\u043f\u0456\u043b\u044c"
    ],
    "name:deu_x_preferred":[
        "Hornostajpil"
    ],
    "name:eng_x_preferred":[
        "Gornostaypol'"
    ],
    "name:eng_x_variant":[
        "Hornostaipil"
    ],
    "name:fra_x_preferred":[
        "Hornostaypil"
    ],
    "name:heb_x_preferred":[
        "\u05d4\u05d5\u05e8\u05e0\u05d5\u05e1\u05d8\u05d9\u05d9\u05e4\u05dc"
    ],
    "name:pol_x_preferred":[
        "Hornostajpol"
    ],
    "name:ron_x_preferred":[
        "Hornostaipil"
    ],
    "name:rus_x_preferred":[
        "\u0413\u043e\u0440\u043d\u043e\u0441\u0442\u0430\u0439\u043f\u043e\u043b\u044c"
    ],
    "name:ukr_x_preferred":[
        "\u0413\u043e\u0440\u043d\u043e\u0441\u0442\u0430\u0439\u043f\u0456\u043b\u044c"
    ],
    "name:ukr_x_variant":[
        "Hornostaypil\u2019"
    ],
    "name:unk_x_variant":[
        "Gornastaypol\u2019"
    ],
    "name:yid_x_preferred":[
        "\u05d4\u05d0\u05e8\u05e0\u05e1\u05d8\u05d9\u05d9\u05e4\u05dc"
    ],
    "name:zho_x_preferred":[
        "\u6208\u723e\u8afe\u65af\u6cf0\u76ae\u5229"
    ],
    "qs:a0":"\u0423\u043a\u0440\u0430\u0457\u043d\u0430",
    "qs:a1":"*\u041a\u0438\u0457\u0432\u0441\u044c\u043a\u0430",
    "qs:a1_alt":"Kyivs'ka",
    "qs:a1r":"0",
    "qs:a2":"\u0406\u0432\u0430\u043d\u043a\u0456\u0432\u0441\u044c\u043a\u0438\u0439",
    "qs:a2_alt":"Ivankivs'kyi",
    "qs:adm0":"\u0423\u043a\u0440\u0430\u0457\u043d\u0430",
    "qs:la_lc":"*",
    "qs:level":"locality",
    "qs:loc":"\u0413\u043e\u0440\u043d\u043e\u0441\u0442\u0430\u0439\u043f\u0456\u043b\u044c",
    "qs:loc_alt":"Hornostaipil",
    "qs:pop":0,
    "qs:type":"buffered point",
    "wd:wordcount":127,
    "wof:name":"\u0413\u043e\u0440\u043d\u043e\u0441\u0442\u0430\u0439\u043f\u0456\u043b\u044c",
    "wof:placetype":"locality"
},
  "geometry": {"coordinates":[30.246743,51.071358],"type":"Point"}
}