{
  "type": "Feature",
  "properties": {
    "gn:admin1_code":"7.0",
    "gn:asciiname":"Kam'yanka",
    "gn:country_code":"UA",
    "gn:dem":86,
    "gn:feature_class":"P",
    "gn:feature_code":"PPL",
    "gn:name":"Kam\u2019yanka",
    "gn:population":0,
    "gn:timezone":"Europe/Kiev",
    "iso:country":"UA",
    "name:ukr_x_preferred":[
        "Kam\u2019yanka"
    ],
    "name:ukr_x_variant":[
        "\u041a\u0430\u043c\u2019\u044f\u043d\u043a\u0430"
    ],
    "name:und_x_variant":[
        "Kamenka"
    ],
    "wof:name":"Kam'yanka",
    "wof:placetype":"locality"
},
  "geometry": {"coordinates":[37.83107,49.97964],"type":"Point"}
}