{
  "type": "Feature",
  "properties": {
    "gn:admin1_code":"5.0",
    "gn:asciiname":"Spasovka",
    "gn:country_code":"UA",
    "gn:dem":125,
    "gn:feature_class":"P",
    "gn:feature_code":"PPL",
    "gn:name":"Spasovka",
    "gn:population":0,
    "gn:timezone":"Europe/Zaporozhye",
    "iso:country":"UA",
    "wof:name":"Spasovka",
    "wof:placetype":"locality"
},
  "geometry": {"coordinates":[38.25528,48.67278],"type":"Point"}
}