{
  "type": "Feature",
  "properties": {
    "gn:admin1_code":"27.0",
    "gn:asciiname":"Fylyntsi",
    "gn:country_code":"UA",
    "gn:dem":246,
    "gn:feature_class":"P",
    "gn:feature_code":"PPL",
    "gn:name":"Fylyntsi",
    "gn:population":0,
    "gn:timezone":"Europe/Kiev",
    "iso:country":"UA",
    "name:ukr_x_preferred":[
        "Fylyntsi"
    ],
    "name:ukr_x_variant":[
        "\u0424\u0438\u043b\u0438\u043d\u0446\u0456"
    ],
    "name:und_x_variant":[
        "Filintsy"
    ],
    "wof:name":"Fylyntsi",
    "wof:placetype":"locality"
},
  "geometry": {"coordinates":[27.89481,49.92903],"type":"Point"}
}