{
  "type": "Feature",
  "properties": {
    "iso:country":"UA",
    "name:deu_x_preferred":[
        "Hussarka"
    ],
    "name:eng_x_preferred":[
        "Husarka"
    ],
    "name:lav_x_preferred":[
        "Husarka"
    ],
    "name:ron_x_preferred":[
        "Husarka"
    ],
    "name:rus_x_preferred":[
        "\u0413\u0443\u0441\u0430\u0440\u043a\u0430"
    ],
    "name:ukr_x_preferred":[
        "\u0413\u0443\u0441\u0430\u0440\u043a\u0430"
    ],
    "name:unk_x_variant":[
        "Gusarka"
    ],
    "name:zho_x_preferred":[
        "\u53e4\u85a9\u723e\u5361"
    ],
    "qs:a0":"\u0423\u043a\u0440\u0430\u0457\u043d\u0430",
    "qs:a1":"*\u0417\u0430\u043f\u043e\u0440\u0456\u0437\u044c\u043a\u0430",
    "qs:a1_alt":"Zaporiz'ka",
    "qs:a1r":"0",
    "qs:a2":"\u041a\u0443\u0439\u0431\u0438\u0448\u0435\u0432\u0441\u044c\u043a\u0438\u0439",
    "qs:a2_alt":"Kuibyshevs'kyi",
    "qs:adm0":"\u0423\u043a\u0440\u0430\u0457\u043d\u0430",
    "qs:la_lc":"*",
    "qs:level":"locality",
    "qs:loc":"\u0413\u0443\u0441\u0430\u0440\u043a\u0430",
    "qs:loc_alt":"Husarka",
    "qs:pop":0,
    "qs:type":"buffered point",
    "wof:name":"\u0413\u0443\u0441\u0430\u0440\u043a\u0430",
    "wof:placetype":"locality"
},
  "geometry": {"coordinates":[36.521085,47.374253],"type":"Point"}
}