{
  "type": "Feature",
  "properties": {
    "gn:admin1_code":"7.0",
    "gn:asciiname":"Husynka",
    "gn:country_code":"UA",
    "gn:dem":170,
    "gn:feature_class":"P",
    "gn:feature_code":"PPL",
    "gn:name":"Husynka",
    "gn:population":0,
    "gn:timezone":"Europe/Kiev",
    "iso:country":"UA",
    "name:eng_x_preferred":[
        "Gusinka"
    ],
    "name:rus_x_preferred":[
        "\u0413\u0443\u0441\u0438\u043d\u043a\u0430"
    ],
    "name:ukr_x_preferred":[
        "Husynka"
    ],
    "name:ukr_x_variant":[
        "\u0413\u0443\u0441\u0438\u043d\u043a\u0430"
    ],
    "name:und_x_variant":[
        "Gusinka"
    ],
    "wof:name":"Husynka",
    "wof:placetype":"locality"
},
  "geometry": {"coordinates":[37.42897,49.82378],"type":"Point"}
}