{
  "type": "Feature",
  "properties": {
    "gn:population":3669,
    "iso:country":"UA",
    "name:eng_x_preferred":[
        "Verkhnyaya Syrovatka"
    ],
    "name:rus_x_preferred":[
        "\u0412\u0435\u0440\u0445.\u0421\u044b\u0440\u043e\u0432\u0430\u0442\u043a\u0430"
    ],
    "name:rus_x_variant":[
        "\u0412\u0435\u0440\u0445\u043d\u044f \u0421\u0438\u0440\u043e\u0432\u0430\u0442\u043a\u0430"
    ],
    "name:ukr_x_preferred":[
        "\u0412\u0435\u0440\u0445\u043d\u044f \u0421\u0438\u0440\u043e\u0432\u0430\u0442\u043a\u0430"
    ],
    "name:und_x_variant":[
        "Verkhnya Syrovatka"
    ],
    "qs:a0":"\u0423\u043a\u0440\u0430\u0457\u043d\u0430",
    "qs:a1":"*\u0421\u0443\u043c\u0441\u044c\u043a\u0430",
    "qs:a1_alt":"Sums'ka",
    "qs:a1r":"0",
    "qs:a2":"\u0421\u0443\u043c\u0441\u044c\u043a\u0438\u0439",
    "qs:a2_alt":"Sums'kyi",
    "qs:adm0":"\u0423\u043a\u0440\u0430\u0457\u043d\u0430",
    "qs:la_lc":"*",
    "qs:level":"locality",
    "qs:loc":"\u0412\u0435\u0440\u0445\u043d\u044f \u0421\u0438\u0440\u043e\u0432\u0430\u0442\u043a\u0430",
    "qs:loc_alt":"Verkhnia Syrovatka",
    "qs:pop":0,
    "qs:type":"buffered point",
    "wof:name":"\u0412\u0435\u0440\u0445\u043d\u044f \u0421\u0438\u0440\u043e\u0432\u0430\u0442\u043a\u0430",
    "wof:placetype":"locality",
    "wof:population":3669
},
  "geometry": {"coordinates":[34.944498,50.829655],"type":"Point"}
}