{
  "type": "Feature",
  "properties": {
    "gn:admin1_code":"19.0",
    "gn:asciiname":"Rudnya Bobrovska",
    "gn:cc2":"UA",
    "gn:country_code":"UA",
    "gn:dem":189,
    "gn:feature_class":"P",
    "gn:feature_code":"PPL",
    "gn:name":"Rudnya Bobrovska",
    "gn:population":0,
    "gn:timezone":"Europe/Kiev",
    "iso:country":"UA",
    "name:und_x_variant":[
        "Rudnia Bobrowska",
        "Rudnya-Borovskaya",
        "Rudnya Bobrovska"
    ],
    "wof:name":"Rudnya Bobrovska",
    "wof:placetype":"locality"
},
  "geometry": {"coordinates":[27.06667,51.05],"type":"Point"}
}