{
  "type": "Feature",
  "properties": {
    "gn:admin1_code":"24.0",
    "gn:asciiname":"Bilyn",
    "gn:country_code":"UA",
    "gn:dem":201,
    "gn:feature_class":"P",
    "gn:feature_code":"PPL",
    "gn:name":"Bilyn",
    "gn:population":0,
    "gn:timezone":"Europe/Kiev",
    "iso:country":"UA",
    "name:ukr_x_preferred":[
        "Bilyn"
    ],
    "name:ukr_x_variant":[
        "\u0411\u0456\u043b\u0438\u043d"
    ],
    "name:und_x_variant":[
        "Bielin",
        "Belin"
    ],
    "wof:name":"Bilyn",
    "wof:placetype":"locality"
},
  "geometry": {"coordinates":[24.26569,50.94214],"type":"Point"}
}