{
  "type": "Feature",
  "properties": {
    "gn:admin1_code":"7.0",
    "gn:asciiname":"Ustynivka",
    "gn:country_code":"UA",
    "gn:dem":175,
    "gn:feature_class":"P",
    "gn:feature_code":"PPL",
    "gn:name":"Ustynivka",
    "gn:population":0,
    "gn:timezone":"Europe/Kiev",
    "iso:country":"UA",
    "name:rus_x_preferred":[
        "\u0423\u0441\u0442\u0438\u043d\u043e\u0432\u043a\u0430"
    ],
    "name:ukr_x_preferred":[
        "Ustynivka"
    ],
    "name:ukr_x_variant":[
        "\u0423\u0441\u0442\u0438\u043d\u0456\u0432\u043a\u0430"
    ],
    "name:und_x_variant":[
        "Ustinovka"
    ],
    "wof:name":"Ustynivka",
    "wof:placetype":"locality"
},
  "geometry": {"coordinates":[37.52678,50.24872],"type":"Point"}
}