{
  "type": "Feature",
  "properties": {
    "gn:admin1_code":"17.0",
    "gn:asciiname":"Hrabove",
    "gn:country_code":"UA",
    "gn:dem":146,
    "gn:feature_class":"P",
    "gn:feature_code":"PPL",
    "gn:name":"Hrabove",
    "gn:population":0,
    "gn:timezone":"Europe/Kiev",
    "iso:country":"UA",
    "name:ukr_x_preferred":[
        "Hrabove"
    ],
    "name:ukr_x_variant":[
        "\u0413\u0440\u0430\u0431\u043e\u0432\u0435"
    ],
    "name:und_x_variant":[
        "Grabova",
        "Grabovo"
    ],
    "wof:name":"Hrabove",
    "wof:placetype":"locality"
},
  "geometry": {"coordinates":[29.03893,48.03025],"type":"Point"}
}