{
  "type": "Feature",
  "properties": {
    "gn:admin1_code":"7.0",
    "gn:asciiname":"Burbulatove",
    "gn:country_code":"UA",
    "gn:dem":180,
    "gn:feature_class":"P",
    "gn:feature_code":"PPL",
    "gn:name":"Burbulatove",
    "gn:population":0,
    "gn:timezone":"Europe/Kiev",
    "iso:country":"UA",
    "name:eng_x_preferred":[
        "Burbulatovo"
    ],
    "name:rus_x_preferred":[
        "\u0411\u0443\u0440\u0431\u0443\u043b\u0430\u0442\u043e\u0432\u043e"
    ],
    "name:ukr_x_preferred":[
        "Burbulatove"
    ],
    "name:ukr_x_variant":[
        "\u0411\u0443\u0440\u0431\u0443\u043b\u0430\u0442\u043e\u0432\u0435"
    ],
    "name:und_x_variant":[
        "Barbalatovo",
        "Burbulatovo"
    ],
    "wof:name":"Burbulatove",
    "wof:placetype":"locality"
},
  "geometry": {"coordinates":[36.64155,48.82069],"type":"Point"}
}