{
  "type": "Feature",
  "properties": {
    "gn:admin1_code":"7.0",
    "gn:asciiname":"Sukha Balka",
    "gn:country_code":"UA",
    "gn:dem":133,
    "gn:feature_class":"P",
    "gn:feature_code":"PPL",
    "gn:name":"Sukha Balka",
    "gn:population":0,
    "gn:timezone":"Europe/Kiev",
    "iso:country":"UA",
    "name:ukr_x_preferred":[
        "Sukha Balka"
    ],
    "name:ukr_x_variant":[
        "\u0421\u0443\u0445\u0430 \u0411\u0430\u043b\u043a\u0430"
    ],
    "name:und_x_variant":[
        "Novaya Aleksandrovka",
        "Sukhaya Balka"
    ],
    "wof:name":"Sukha Balka",
    "wof:placetype":"locality"
},
  "geometry": {"coordinates":[35.55498,49.65762],"type":"Point"}
}