{
  "type": "Feature",
  "properties": {
    "gn:admin1_code":"9.0",
    "gn:asciiname":"Ripna",
    "gn:country_code":"UA",
    "gn:dem":324,
    "gn:feature_class":"P",
    "gn:feature_code":"PPL",
    "gn:name":"Ripna",
    "gn:population":0,
    "gn:timezone":"Europe/Kiev",
    "iso:country":"UA",
    "name:und_x_variant":[
        "Rypna",
        "Ripna"
    ],
    "wof:name":"Ripna",
    "wof:placetype":"locality"
},
  "geometry": {"coordinates":[26.30933,49.41065],"type":"Point"}
}