{
  "type": "Feature",
  "properties": {
    "gn:admin1_code":"5.0",
    "gn:asciiname":"Chumak",
    "gn:country_code":"UA",
    "gn:dem":72,
    "gn:feature_class":"P",
    "gn:feature_code":"PPL",
    "gn:name":"Chumak",
    "gn:population":0,
    "gn:timezone":"Europe/Kiev",
    "iso:country":"UA",
    "name:ukr_x_preferred":[
        "Chumak"
    ],
    "name:ukr_x_variant":[
        "\u0427\u0443\u043c\u0430\u043a"
    ],
    "wof:name":"Chumak",
    "wof:placetype":"locality"
},
  "geometry": {"coordinates":[38.0081,47.29478],"type":"Point"}
}