{
  "type": "Feature",
  "properties": {
    "iso:country":"UA",
    "qs:a0":"\u0423\u043a\u0440\u0430\u0457\u043d\u0430",
    "qs:a1":"*\u0406\u0432\u0430\u043d\u043e-\u0424\u0440\u0430\u043d\u043a\u0456\u0432\u0441\u044c\u043a\u0430",
    "qs:a1_alt":"Ivano-Frankivs'ka",
    "qs:a1r":"0",
    "qs:a2":"\u0412\u0435\u0440\u0445\u043e\u0432\u0438\u043d\u0441\u044c\u043a\u0438\u0439",
    "qs:a2_alt":"Verkhovyns'kyi",
    "qs:adm0":"\u0423\u043a\u0440\u0430\u0457\u043d\u0430",
    "qs:la_lc":"*",
    "qs:level":"locality",
    "qs:loc":"\u0411\u0456\u043b\u043e\u0431\u0435\u0440\u0456\u0437\u043a\u0430",
    "qs:loc_alt":"Biloberizka",
    "qs:pop":0,
    "qs:type":"buffered point",
    "wof:name":"\u0411\u0456\u043b\u043e\u0431\u0435\u0440\u0456\u0437\u043a\u0430",
    "wof:placetype":"locality"
},
  "geometry": {"coordinates":[25.060439,48.155662],"type":"Point"}
}