{
  "type": "Feature",
  "properties": {
    "gn:admin1_code":"15.0",
    "gn:asciiname":"Polove",
    "gn:country_code":"UA",
    "gn:dem":218,
    "gn:feature_class":"P",
    "gn:feature_code":"PPL",
    "gn:name":"Polove",
    "gn:population":0,
    "gn:timezone":"Europe/Kiev",
    "iso:country":"UA",
    "name:ukr_x_preferred":[
        "Polove"
    ],
    "name:ukr_x_variant":[
        "\u041f\u043e\u043b\u043e\u0432\u0435"
    ],
    "name:und_x_variant":[
        "Plove",
        "Polovoye"
    ],
    "wof:name":"Polove",
    "wof:placetype":"locality"
},
  "geometry": {"coordinates":[24.57032,50.31021],"type":"Point"}
}