{
  "type": "Feature",
  "properties": {
    "gn:admin1_code":"24.0",
    "gn:asciiname":"Sil'tse",
    "gn:country_code":"UA",
    "gn:dem":232,
    "gn:feature_class":"P",
    "gn:feature_code":"PPL",
    "gn:name":"Sil\u2019tse",
    "gn:population":0,
    "gn:timezone":"Europe/Kiev",
    "iso:country":"UA",
    "name:ukr_x_preferred":[
        "Sil\u2019tse"
    ],
    "name:ukr_x_variant":[
        "\u0421\u0456\u043b\u044c\u0446\u0435"
    ],
    "name:und_x_variant":[
        "Selets",
        "Sel\u2019tse"
    ],
    "wof:name":"Sil'tse",
    "wof:placetype":"locality"
},
  "geometry": {"coordinates":[24.70541,50.46414],"type":"Point"}
}