{
  "type": "Feature",
  "properties": {
    "iso:country":"UA",
    "qs:a0":"\u0423\u043a\u0440\u0430\u0457\u043d\u0430",
    "qs:a1":"*\u0414\u043e\u043d\u0435\u0446\u044c\u043a\u0430",
    "qs:a1_alt":"Donets'ka",
    "qs:a1r":"0",
    "qs:a2":"\u0428\u0430\u0445\u0442\u0430\u0440\u0441\u044c\u043a\u0438\u0439",
    "qs:a2_alt":"Shakhtars'kyi",
    "qs:adm0":"\u0423\u043a\u0440\u0430\u0457\u043d\u0430",
    "qs:la_lc":"*",
    "qs:level":"locality",
    "qs:loc":"\u0413\u0456\u0440\u043d\u0435",
    "qs:loc_alt":"Hirne",
    "qs:pop":0,
    "qs:type":"buffered point",
    "wd:wordcount":386,
    "wof:name":"\u0413\u0456\u0440\u043d\u0435",
    "wof:placetype":"locality"
},
  "geometry": {"coordinates":[38.542469,48.033267],"type":"Point"}
}