{
  "type": "Feature",
  "properties": {
    "gn:admin1_code":"14.0",
    "gn:asciiname":"Hannivka",
    "gn:country_code":"UA",
    "gn:dem":238,
    "gn:feature_class":"P",
    "gn:feature_code":"PPL",
    "gn:name":"Hannivka",
    "gn:population":0,
    "gn:timezone":"Europe/Zaporozhye",
    "iso:country":"UA",
    "name:ukr_x_preferred":[
        "Hannivka"
    ],
    "name:ukr_x_variant":[
        "\u0413\u0430\u043d\u043d\u0456\u0432\u043a\u0430"
    ],
    "wof:name":"Hannivka",
    "wof:placetype":"locality"
},
  "geometry": {"coordinates":[38.87945,48.37627],"type":"Point"}
}