{
  "type": "Feature",
  "properties": {
    "gn:admin1_code":"8.0",
    "gn:asciiname":"Pchilka",
    "gn:country_code":"UA",
    "gn:dem":9,
    "gn:feature_class":"P",
    "gn:feature_code":"PPL",
    "gn:name":"Pchilka",
    "gn:population":0,
    "gn:timezone":"Europe/Kiev",
    "iso:country":"UA",
    "name:rus_x_preferred":[
        "Pch\u00eblka"
    ],
    "name:rus_x_variant":[
        "\u041f\u0447\u0451\u043b\u043a\u0430"
    ],
    "name:ukr_x_preferred":[
        "Pchilka"
    ],
    "name:ukr_x_variant":[
        "\u041f\u0447\u0456\u043b\u043a\u0430"
    ],
    "wof:name":"Pchilka",
    "wof:placetype":"locality"
},
  "geometry": {"coordinates":[35.0534,46.3208],"type":"Point"}
}