{
  "type": "Feature",
  "properties": {
    "iso:country":"UA",
    "name:bel_x_preferred":[
        "\u041a\u0430\u043c\u0430\u0440"
    ],
    "name:deu_x_preferred":[
        "Komar"
    ],
    "name:eng_x_preferred":[
        "Komar"
    ],
    "name:hye_x_preferred":[
        "\u053f\u0578\u0574\u0561\u0580"
    ],
    "name:lav_x_preferred":[
        "Komara"
    ],
    "name:rus_x_preferred":[
        "\u041a\u043e\u043c\u0430\u0440"
    ],
    "name:ukr_x_preferred":[
        "\u041a\u043e\u043c\u0430\u0440"
    ],
    "qs:a0":"\u0423\u043a\u0440\u0430\u0457\u043d\u0430",
    "qs:a1":"*\u0414\u043e\u043d\u0435\u0446\u044c\u043a\u0430",
    "qs:a1_alt":"Donets'ka",
    "qs:a1r":"0",
    "qs:a2":"\u0412\u0435\u043b\u0438\u043a\u043e\u043d\u043e\u0432\u043e\u0441\u0456\u043b\u043a\u0456\u0432\u0441\u044c\u043a\u0438\u0439",
    "qs:a2_alt":"Velykonovosilkivs'kyi",
    "qs:adm0":"\u0423\u043a\u0440\u0430\u0457\u043d\u0430",
    "qs:la_lc":"*",
    "qs:level":"locality",
    "qs:loc":"\u041a\u043e\u043c\u0430\u0440",
    "qs:loc_alt":"Komar",
    "qs:pop":0,
    "qs:type":"buffered point",
    "wd:wordcount":93,
    "wof:name":"\u041a\u043e\u043c\u0430\u0440",
    "wof:placetype":"locality"
},
  "geometry": {"coordinates":[36.745907,47.980147],"type":"Point"}
}