{
  "type": "Feature",
  "properties": {
    "gn:admin1_code":"22.0",
    "gn:asciiname":"Dolge",
    "gn:cc2":"UA",
    "gn:country_code":"UA",
    "gn:dem":250,
    "gn:feature_class":"P",
    "gn:feature_code":"PPL",
    "gn:name":"Dolge",
    "gn:population":0,
    "gn:timezone":"Europe/Kiev",
    "iso:country":"UA",
    "name:und_x_variant":[
        "Dolhe",
        "Dolge"
    ],
    "wof:name":"Dolge",
    "wof:placetype":"locality"
},
  "geometry": {"coordinates":[25.71667,49.21667],"type":"Point"}
}