{
  "type": "Feature",
  "properties": {
    "gn:admin1_code":"21.0",
    "gn:asciiname":"Romashkove",
    "gn:country_code":"UA",
    "gn:dem":173,
    "gn:feature_class":"P",
    "gn:feature_code":"PPL",
    "gn:name":"Romashkove",
    "gn:population":0,
    "gn:timezone":"Europe/Kiev",
    "iso:country":"UA",
    "name:ukr_x_preferred":[
        "Romashkovo"
    ],
    "name:und_x_variant":[
        "Romashkove"
    ],
    "wof:name":"Romashkove",
    "wof:placetype":"locality"
},
  "geometry": {"coordinates":[33.96147,52.15546],"type":"Point"}
}