{
  "type": "Feature",
  "properties": {
    "gn:admin1_code":"24.0",
    "gn:asciiname":"Vul'ka Shel'vuvska",
    "gn:country_code":"UA",
    "gn:dem":214,
    "gn:feature_class":"P",
    "gn:feature_code":"PPL",
    "gn:name":"Vul\u2019ka Shel\u2019vuvska",
    "gn:population":0,
    "gn:timezone":"Europe/Kiev",
    "iso:country":"UA",
    "name:und_x_variant":[
        "W\u00f3lka Szelwowska",
        "Vul\u2019ka Shel\u2019vuvska"
    ],
    "wof:name":"Vul'ka Shel'vuvska",
    "wof:placetype":"locality"
},
  "geometry": {"coordinates":[24.75,50.73333],"type":"Point"}
}