{
  "type": "Feature",
  "properties": {
    "gn:admin1_code":"3.0",
    "gn:asciiname":"Osel'yevka",
    "gn:country_code":"UA",
    "gn:dem":185,
    "gn:feature_class":"P",
    "gn:feature_code":"PPL",
    "gn:name":"Osel\u2019yevka",
    "gn:population":0,
    "gn:timezone":"Europe/Kiev",
    "iso:country":"UA",
    "name:und_x_variant":[
        "Kishla-Nedzhimen\u2019",
        "Oselovka",
        "Osel\u2019yevka"
    ],
    "wof:name":"Osel'yevka",
    "wof:placetype":"locality"
},
  "geometry": {"coordinates":[26.61836,48.43992],"type":"Point"}
}