{
  "type": "Feature",
  "properties": {
    "gn:admin1_code":"10.0",
    "gn:asciiname":"Nedoharky",
    "gn:country_code":"UA",
    "gn:dem":184,
    "gn:feature_class":"P",
    "gn:feature_code":"PPL",
    "gn:name":"Nedoharky",
    "gn:population":0,
    "gn:timezone":"Europe/Kiev",
    "iso:country":"UA",
    "name:eng_x_preferred":[
        "Nedogarki"
    ],
    "name:rus_x_preferred":[
        "\u041d\u0435\u0434\u043e\u0433\u0430\u0440\u043a\u0438"
    ],
    "name:ukr_x_preferred":[
        "Nedoharky"
    ],
    "name:ukr_x_variant":[
        "\u041d\u0435\u0434\u043e\u0433\u0430\u0440\u043a\u0438"
    ],
    "name:und_x_variant":[
        "Nedogorki",
        "Nedogarki"
    ],
    "wof:name":"Nedoharky",
    "wof:placetype":"locality"
},
  "geometry": {"coordinates":[33.26464,48.78531],"type":"Point"}
}