{
  "type": "Feature",
  "properties": {
    "gn:admin1_code":"26.0",
    "gn:asciiname":"Kutsiy",
    "gn:cc2":"UA",
    "gn:country_code":"UA",
    "gn:dem":150,
    "gn:feature_class":"P",
    "gn:feature_code":"PPL",
    "gn:name":"Kutsiy",
    "gn:population":0,
    "gn:timezone":"Europe/Zaporozhye",
    "iso:country":"UA",
    "name:und_x_variant":[
        "Imeni Shevchenko",
        "Kutsyy",
        "Kutsiy"
    ],
    "wof:name":"Kutsiy",
    "wof:placetype":"locality"
},
  "geometry": {"coordinates":[36.66667,47.75],"type":"Point"}
}