{
  "type": "Feature",
  "properties": {
    "gn:admin1_code":"18.0",
    "gn:asciiname":"Zayichyntsi",
    "gn:country_code":"UA",
    "gn:dem":86,
    "gn:feature_class":"P",
    "gn:feature_code":"PPL",
    "gn:name":"Zayichyntsi",
    "gn:population":0,
    "gn:timezone":"Europe/Kiev",
    "iso:country":"UA",
    "name:ukr_x_preferred":[
        "Zayichyntsi"
    ],
    "name:ukr_x_variant":[
        "\u0417\u0430\u0457\u0447\u0438\u043d\u0446\u0456"
    ],
    "name:und_x_variant":[
        "Zaychentsy",
        "Zaichentsy"
    ],
    "wof:name":"Zayichyntsi",
    "wof:placetype":"locality"
},
  "geometry": {"coordinates":[33.3654,49.58844000000001],"type":"Point"}
}