{
  "type": "Feature",
  "properties": {
    "gn:admin1_code":"24.0",
    "gn:asciiname":"Pisky-Rishyts'ki",
    "gn:country_code":"UA",
    "gn:dem":155,
    "gn:feature_class":"P",
    "gn:feature_code":"PPL",
    "gn:name":"Pisky-Rishyts\u2019ki",
    "gn:population":0,
    "gn:timezone":"Europe/Kiev",
    "iso:country":"UA",
    "name:ukr_x_preferred":[
        "Pisky-Rishyts\u2019ki"
    ],
    "name:ukr_x_variant":[
        "\u041f\u0456\u0441\u043a\u0438-\u0420\u0456\u0447\u0438\u0446\u044c\u043a\u0456"
    ],
    "name:und_x_variant":[
        "Pyaski Zhechitske",
        "Peski-Rechitskiye"
    ],
    "wof:name":"Pisky-Rishyts'ki",
    "wof:placetype":"locality"
},
  "geometry": {"coordinates":[24.65714,51.77728],"type":"Point"}
}