{
  "type": "Feature",
  "properties": {
    "gn:admin1_code":"18.0",
    "gn:asciiname":"Kharchenky",
    "gn:country_code":"UA",
    "gn:dem":77,
    "gn:feature_class":"P",
    "gn:feature_code":"PPL",
    "gn:name":"Kharchenky",
    "gn:population":0,
    "gn:timezone":"Europe/Kiev",
    "iso:country":"UA",
    "name:ukr_x_preferred":[
        "Kharchenky"
    ],
    "name:ukr_x_variant":[
        "\u0425\u0430\u0440\u0447\u0435\u043d\u043a\u0438"
    ],
    "wof:name":"Kharchenky",
    "wof:placetype":"locality"
},
  "geometry": {"coordinates":[33.7481,49.29337],"type":"Point"}
}