{
  "type": "Feature",
  "properties": {
    "gn:admin1_code":"10.0",
    "gn:asciiname":"Antonopol'",
    "gn:country_code":"UA",
    "gn:dem":124,
    "gn:feature_class":"P",
    "gn:feature_code":"PPL",
    "gn:name":"Antonopol\u2019",
    "gn:population":0,
    "gn:timezone":"Europe/Kiev",
    "iso:country":"UA",
    "name:und_x_variant":[
        "Mollerovo",
        "Antonopol\u2019"
    ],
    "wof:name":"Antonopol'",
    "wof:placetype":"locality"
},
  "geometry": {"coordinates":[31.7637,47.94284],"type":"Point"}
}