{
  "type": "Feature",
  "properties": {
    "gn:admin1_code":"15.0",
    "gn:asciiname":"Ternuv",
    "gn:country_code":"UA",
    "gn:dem":266,
    "gn:feature_class":"P",
    "gn:feature_code":"PPL",
    "gn:name":"Ternuv",
    "gn:population":0,
    "gn:timezone":"Europe/Kiev",
    "iso:country":"UA",
    "name:und_x_variant":[
        "Ternov",
        "Ternuv"
    ],
    "wof:name":"Ternuv",
    "wof:placetype":"locality"
},
  "geometry": {"coordinates":[23.92627,50.02274],"type":"Point"}
}