{
  "type": "Feature",
  "properties": {
    "gn:admin1_code":"8.0",
    "gn:asciiname":"Maslivka",
    "gn:country_code":"UA",
    "gn:dem":15,
    "gn:feature_class":"P",
    "gn:feature_code":"PPL",
    "gn:name":"Maslivka",
    "gn:population":0,
    "gn:timezone":"Europe/Kiev",
    "iso:country":"UA",
    "name:rus_x_preferred":[
        "\u041c\u0430\u0441\u043b\u043e\u0432\u043a\u0430"
    ],
    "name:ukr_x_preferred":[
        "Maslivka"
    ],
    "name:ukr_x_variant":[
        "\u041c\u0430\u0441\u043b\u0456\u0432\u043a\u0430"
    ],
    "name:und_x_variant":[
        "Maslouskiy",
        "Maslovskiy",
        "Maslovka"
    ],
    "wof:name":"Maslivka",
    "wof:placetype":"locality"
},
  "geometry": {"coordinates":[33.23331,46.69635],"type":"Point"}
}