{
  "type": "Feature",
  "properties": {
    "gn:admin1_code":"21.0",
    "gn:asciiname":"Veseleya Malaya",
    "gn:country_code":"UA",
    "gn:dem":173,
    "gn:feature_class":"P",
    "gn:feature_code":"PPL",
    "gn:name":"Veseleya Malaya",
    "gn:population":0,
    "gn:timezone":"Europe/Kiev",
    "iso:country":"UA",
    "wof:name":"Veseleya Malaya",
    "wof:placetype":"locality"
},
  "geometry": {"coordinates":[35.18194,50.68389000000001],"type":"Point"}
}