{
  "type": "Feature",
  "properties": {
    "iso:country":"UA",
    "name:ukr_x_preferred":[
        "\u041f\u0440\u0438\u043c\u043e\u0440\u0441\u044c\u043a\u0435"
    ],
    "name:unk_x_variant":[
        "Karga"
    ],
    "qs:a0":"\u0423\u043a\u0440\u0430\u0457\u043d\u0430",
    "qs:a1":"*\u0425\u0435\u0440\u0441\u043e\u043d\u0441\u044c\u043a\u0430",
    "qs:a1_alt":"Khersons'ka",
    "qs:a1r":"0",
    "qs:a2":"\u0421\u043a\u0430\u0434\u043e\u0432\u0441\u044c\u043a\u0438\u0439",
    "qs:a2_alt":"Skadovs'kyi",
    "qs:adm0":"\u0423\u043a\u0440\u0430\u0457\u043d\u0430",
    "qs:la_lc":"*",
    "qs:level":"locality",
    "qs:loc":"\u041f\u0440\u0438\u043c\u043e\u0440\u0441\u044c\u043a\u0435",
    "qs:loc_alt":"Prymors'ke",
    "qs:pop":0,
    "qs:type":"buffered point",
    "wd:wordcount":688,
    "wof:name":"\u041f\u0440\u0438\u043c\u043e\u0440\u0441\u044c\u043a\u0435",
    "wof:placetype":"locality"
},
  "geometry": {"coordinates":[33.022244,46.180686],"type":"Point"}
}