{
  "type": "Feature",
  "properties": {
    "gn:admin1_code":"27.0",
    "gn:asciiname":"Yelisavet",
    "gn:cc2":"UA",
    "gn:country_code":"UA",
    "gn:dem":203,
    "gn:feature_class":"P",
    "gn:feature_code":"PPL",
    "gn:name":"Yelisavet",
    "gn:population":0,
    "gn:timezone":"Europe/Kiev",
    "iso:country":"UA",
    "name:und_x_variant":[
        "Yelizavet",
        "Yelisavet"
    ],
    "wof:name":"Yelisavet",
    "wof:placetype":"locality"
},
  "geometry": {"coordinates":[27.56667,50.63333],"type":"Point"}
}