{
  "type": "Feature",
  "properties": {
    "gn:admin1_code":"10.0",
    "gn:asciiname":"Oleksandro-Pashchenkove",
    "gn:country_code":"UA",
    "gn:dem":128,
    "gn:feature_class":"P",
    "gn:feature_code":"PPL",
    "gn:name":"Oleksandro-Pashchenkove",
    "gn:population":0,
    "gn:timezone":"Europe/Kiev",
    "iso:country":"UA",
    "name:ukr_x_preferred":[
        "Oleksandro-Pashchenkove"
    ],
    "name:ukr_x_variant":[
        "\u041e\u043b\u0435\u043a\u0441\u0430\u043d\u0434\u0440\u043e-\u041f\u0430\u0449\u0435\u043d\u043a\u043e\u0432\u0435"
    ],
    "wof:name":"Oleksandro-Pashchenkove",
    "wof:placetype":"locality"
},
  "geometry": {"coordinates":[32.81935,48.51300000000001],"type":"Point"}
}