{
  "type": "Feature",
  "properties": {
    "gn:country":"UA",
    "gn:fcode":"PPL",
    "gn:population":10959,
    "iso:country":"UA",
    "name:ara_x_preferred":[
        "\u0628\u0648\u0631\u0634\u062a\u0634\u064a\u0641"
    ],
    "name:bel_x_preferred":[
        "\u0411\u0430\u0440\u0448\u0447\u044b\u045e"
    ],
    "name:ceb_x_preferred":[
        "Borshchiv"
    ],
    "name:ces_x_preferred":[
        "Bor\u0161\u010div"
    ],
    "name:crh_x_preferred":[
        "Bor\u015f\u00e7iv"
    ],
    "name:deu_x_preferred":[
        "Borschtschiw"
    ],
    "name:eng_x_preferred":[
        "Borschiv"
    ],
    "name:eng_x_variant":[
        "Borshchiv"
    ],
    "name:fas_x_preferred":[
        "\u0628\u0648\u0631\u0634\u0686\u06cc\u0641"
    ],
    "name:fra_x_preferred":[
        "Borchtchiv"
    ],
    "name:heb_x_preferred":[
        "\u05d1\u05d5\u05e8\u05e9\u05e6'\u05d9\u05d1"
    ],
    "name:hsb_x_preferred":[
        "Bor\u0161\u0107iw"
    ],
    "name:hye_x_preferred":[
        "\u0532\u0578\u0580\u0577\u0579\u0575\u0578\u057e"
    ],
    "name:ita_x_preferred":[
        "Bor\u0161\u010div"
    ],
    "name:kat_x_preferred":[
        "\u10d1\u10dd\u10e0\u10e8\u10e9\u10dd\u10d5\u10d8"
    ],
    "name:lav_x_preferred":[
        "Bor\u0161\u010diva"
    ],
    "name:lit_x_preferred":[
        "Bor\u0161\u010divas"
    ],
    "name:nno_x_preferred":[
        "Borsjtsjiv"
    ],
    "name:pol_x_preferred":[
        "Borszcz\u00f3w"
    ],
    "name:ron_x_preferred":[
        "Bor\u0219civ"
    ],
    "name:rus_x_preferred":[
        "\u0411\u043e\u0440\u0449\u0456\u0432"
    ],
    "name:rus_x_variant":[
        "\u0411\u043e\u0440\u0449\u0451\u0432"
    ],
    "name:slv_x_preferred":[
        "Borschiv"
    ],
    "name:tat_x_preferred":[
        "\u0411\u043e\u0440\u0447\u0438\u0432"
    ],
    "name:ukr_x_preferred":[
        "\u0411\u043e\u0440\u0449\u0456\u0432"
    ],
    "name:und_x_variant":[
        "Berchev"
    ],
    "name:vie_x_preferred":[
        "Borschiv"
    ],
    "name:zho_x_preferred":[
        "\u535a\u723e\u66c9\u592b"
    ],
    "qs_pg:aaroncc":"UA",
    "qs_pg:gn_country":"UA",
    "qs_pg:gn_fcode":"PPL",
    "qs_pg:gn_pop":10959,
    "qs_pg:name":"Borshchiv",
    "qs_pg:photos_9r":0,
    "qs_pg:photos_sr":0,
    "qs_pg:pop_sr":6,
    "qs_pg:qs_pg_placetype":"locality",
    "wof:name":"Borshchiv",
    "wof:placetype":"locality",
    "wof:population":10959
},
  "geometry": {"coordinates":[26.04347,48.80332],"type":"Point"}
}