{
  "type": "Feature",
  "properties": {
    "gn:admin1_code":"13.0",
    "gn:asciiname":"Selezenivka",
    "gn:country_code":"UA",
    "gn:dem":216,
    "gn:feature_class":"P",
    "gn:feature_code":"PPL",
    "gn:name":"Selezenivka",
    "gn:population":0,
    "gn:timezone":"Europe/Kiev",
    "iso:country":"UA",
    "name:rus_x_preferred":[
        "\u0421\u0435\u043b\u0435\u0437\u043d\u0456\u0432\u043a\u0430"
    ],
    "name:ukr_x_preferred":[
        "\u0421\u0435\u043b\u0435\u0437\u043d\u0456\u0432\u043a\u0430"
    ],
    "name:ukr_x_variant":[
        "Selezenivka",
        "\u0421\u0435\u043b\u0435\u0437\u0435\u043d\u0456\u0432\u043a\u0430"
    ],
    "name:und_x_variant":[
        "Seleznivka",
        "Selezenovka",
        "Selezenevka"
    ],
    "wof:name":"Selezenivka",
    "wof:placetype":"locality"
},
  "geometry": {"coordinates":[29.57163,49.75905],"type":"Point"}
}