{
  "type": "Feature",
  "properties": {
    "gn:admin1_code":"21.0",
    "gn:asciiname":"Nova Oleksandrivka",
    "gn:country_code":"UA",
    "gn:dem":155,
    "gn:feature_class":"P",
    "gn:feature_code":"PPL",
    "gn:name":"Nova Oleksandrivka",
    "gn:population":0,
    "gn:timezone":"Europe/Kiev",
    "iso:country":"UA",
    "name:ukr_x_preferred":[
        "Nova Oleksandrivka"
    ],
    "name:ukr_x_variant":[
        "\u041d\u043e\u0432\u0430 \u041e\u043b\u0435\u043a\u0441\u0430\u043d\u0434\u0440\u0456\u0432\u043a\u0430"
    ],
    "name:und_x_variant":[
        "Novo-Aleksandrovka",
        "Novoselka",
        "Novaya Aleksandrovka"
    ],
    "wof:name":"Nova Oleksandrivka",
    "wof:placetype":"locality"
},
  "geometry": {"coordinates":[33.96986,51.12467],"type":"Point"}
}