{
  "type": "Feature",
  "properties": {
    "gn:admin1_code":"23.0",
    "gn:asciiname":"Shyroka Hreblia",
    "gn:country_code":"UA",
    "gn:dem":280,
    "gn:feature_class":"P",
    "gn:feature_code":"PPL",
    "gn:name":"Shyroka Hreblia",
    "gn:population":0,
    "gn:timezone":"Europe/Kiev",
    "iso:country":"UA",
    "name:rus_x_preferred":[
        "\u0428\u0438\u0440\u043e\u043a\u0430\u044f \u0413\u0440\u0435\u0431\u043b\u044f"
    ],
    "name:ukr_x_preferred":[
        "\u0428\u0438\u0440\u043e\u043a\u0430 \u0413\u0440\u0435\u0431\u043b\u044f"
    ],
    "name:und_x_variant":[
        "Shiroka Greblya"
    ],
    "wof:name":"Shyroka Hreblia",
    "wof:placetype":"locality"
},
  "geometry": {"coordinates":[28.8301,49.57422],"type":"Point"}
}