{
  "type": "Feature",
  "properties": {
    "gn:admin1_code":"7.0",
    "gn:asciiname":"Viytenky",
    "gn:country_code":"UA",
    "gn:dem":184,
    "gn:feature_class":"P",
    "gn:feature_code":"PPL",
    "gn:name":"Viytenky",
    "gn:population":0,
    "gn:timezone":"Europe/Kiev",
    "iso:country":"UA",
    "name:ukr_x_preferred":[
        "Viytenky"
    ],
    "name:ukr_x_variant":[
        "\u0412\u0456\u0439\u0442\u0435\u043d\u043a\u0438"
    ],
    "name:und_x_variant":[
        "Khutor Voytenkov",
        "Voytenkov"
    ],
    "wof:name":"Viytenky",
    "wof:placetype":"locality"
},
  "geometry": {"coordinates":[35.61676,49.94347],"type":"Point"}
}