{
  "type": "Feature",
  "properties": {
    "gn:admin1_code":"5.0",
    "gn:asciiname":"Novo-Rayskoye",
    "gn:country_code":"UA",
    "gn:dem":83,
    "gn:feature_class":"P",
    "gn:feature_code":"PPL",
    "gn:name":"Novo-Rayskoye",
    "gn:population":0,
    "gn:timezone":"Europe/Kiev",
    "iso:country":"UA",
    "wof:name":"Novo-Rayskoye",
    "wof:placetype":"locality"
},
  "geometry": {"coordinates":[37.48333,48.58333],"type":"Point"}
}