{
  "type": "Feature",
  "properties": {
    "gn:admin1_code":"25.0",
    "gn:asciiname":"Pallo",
    "gn:country_code":"UA",
    "gn:dem":106,
    "gn:feature_class":"P",
    "gn:feature_code":"PPL",
    "gn:name":"Pallo",
    "gn:population":0,
    "gn:timezone":"Europe/Uzhgorod",
    "iso:country":"UA",
    "name:deu_x_preferred":[
        "Pallo"
    ],
    "name:fin_x_preferred":[
        "Pallo"
    ],
    "name:slk_x_preferred":[
        "Pallo"
    ],
    "name:ukr_x_preferred":[
        "Pallo"
    ],
    "name:ukr_x_variant":[
        "\u041f\u0430\u043b\u043b\u043e"
    ],
    "name:und_x_variant":[
        "Pavdovo"
    ],
    "wof:name":"Pallo",
    "wof:placetype":"locality"
},
  "geometry": {"coordinates":[22.17344,48.56465],"type":"Point"}
}