{
  "type": "Feature",
  "properties": {
    "gn:admin1_code":"2.0",
    "gn:asciiname":"Okhramiyevychi",
    "gn:country_code":"UA",
    "gn:dem":156,
    "gn:feature_class":"P",
    "gn:feature_code":"PPL",
    "gn:name":"Okhramiyevychi",
    "gn:population":0,
    "gn:timezone":"Europe/Kiev",
    "iso:country":"UA",
    "name:eng_x_preferred":[
        "Okhrameyevichi"
    ],
    "name:rus_x_preferred":[
        "\u041e\u0445\u0440\u0430\u043c\u0438\u0435\u0432\u0438\u0447\u0438"
    ],
    "name:ukr_x_preferred":[
        "Okhramiyevychi"
    ],
    "name:ukr_x_variant":[
        "\u041e\u0445\u0440\u0430\u043c\u0456\u0454\u0432\u0438\u0447\u0456"
    ],
    "name:und_x_variant":[
        "Okhrameyevichi",
        "Okhramiyevichi"
    ],
    "wof:name":"Okhramiyevychi",
    "wof:placetype":"locality"
},
  "geometry": {"coordinates":[32.28353,51.90914],"type":"Point"}
}