{
  "type": "Feature",
  "properties": {
    "gn:admin1_code":"21.0",
    "gn:asciiname":"Avramkivshchyna",
    "gn:country_code":"UA",
    "gn:dem":184,
    "gn:feature_class":"P",
    "gn:feature_code":"PPL",
    "gn:name":"Avramkivshchyna",
    "gn:population":0,
    "gn:timezone":"Europe/Kiev",
    "iso:country":"UA",
    "name:ukr_x_preferred":[
        "Avramkivshchyna"
    ],
    "name:ukr_x_variant":[
        "\u0410\u0432\u0440\u0430\u043c\u043a\u0456\u0432\u0449\u0438\u043d\u0430"
    ],
    "wof:name":"Avramkivshchyna",
    "wof:placetype":"locality"
},
  "geometry": {"coordinates":[34.55356,50.25078],"type":"Point"}
}