{
  "type": "Feature",
  "properties": {
    "gn:admin1_code":"23.0",
    "gn:asciiname":"Khomutintsy",
    "gn:country_code":"UA",
    "gn:dem":255,
    "gn:feature_class":"P",
    "gn:feature_code":"PPL",
    "gn:name":"Khomutintsy",
    "gn:population":0,
    "gn:timezone":"Europe/Kiev",
    "iso:country":"UA",
    "name:und_x_variant":[
        "Khomutyntsi",
        "Khomutintsy"
    ],
    "wof:name":"Khomutintsy",
    "wof:placetype":"locality"
},
  "geometry": {"coordinates":[28.42843,49.54278],"type":"Point"}
}