{
  "type": "Feature",
  "properties": {
    "gn:admin1_code":"8.0",
    "gn:asciiname":"Novodmytrivka",
    "gn:country_code":"UA",
    "gn:dem":27,
    "gn:feature_class":"P",
    "gn:feature_code":"PPL",
    "gn:name":"Novodmytrivka",
    "gn:population":0,
    "gn:timezone":"Europe/Kiev",
    "iso:country":"UA",
    "name:ukr_x_preferred":[
        "Novodmytrivka"
    ],
    "name:ukr_x_variant":[
        "\u041d\u043e\u0432\u043e\u0434\u043c\u0438\u0442\u0440\u0456\u0432\u043a\u0430"
    ],
    "name:und_x_variant":[
        "Novodmitriyevka",
        "Novodmitrovka"
    ],
    "wof:name":"Novodmytrivka",
    "wof:placetype":"locality"
},
  "geometry": {"coordinates":[33.35491,47.36178],"type":"Point"}
}