{
  "type": "Feature",
  "properties": {
    "gn:admin1_code":"11.0",
    "gn:admin2_code":"709333",
    "gn:admin3_code":"11152866.0",
    "gn:asciiname":"Novosel'tsevo",
    "gn:country_code":"UA",
    "gn:dem":15,
    "gn:elevation":"15.0",
    "gn:feature_class":"P",
    "gn:feature_code":"PPL",
    "gn:name":"Novosel\u2019tsevo",
    "gn:population":433,
    "gn:timezone":"Europe/Simferopol",
    "iso:country":"UA",
    "name:eng_x_preferred":[
        "Novosel\u2019tsevo"
    ],
    "name:rus_x_historical":[
        "\u0410\u043a-\u0428\u0435\u0438\u0445"
    ],
    "name:rus_x_preferred":[
        "\u041d\u043e\u0432\u043e\u0441\u0435\u043b\u044c\u0446\u0435\u0432\u043e"
    ],
    "name:rus_x_variant":[
        "\u0410\u043a-\u0428\u0435\u0438\u0445"
    ],
    "name:ukr_x_preferred":[
        "\u041d\u043e\u0432\u043e\u0441\u0456\u043b\u044c\u0446\u0435\u0432\u0435"
    ],
    "wof:name":"Novosel'tsevo",
    "wof:placetype":"locality",
    "wof:population":433
},
  "geometry": {"coordinates":[34.67057,45.58508],"type":"Point"}
}