{
  "type": "Feature",
  "properties": {
    "gn:population":5164,
    "iso:country":"UA",
    "name:bel_x_preferred":[
        "\u0428\u043a\u043b\u043e"
    ],
    "name:ceb_x_preferred":[
        "Shklo"
    ],
    "name:crh_x_preferred":[
        "\u015eklo"
    ],
    "name:deu_x_preferred":[
        "Schklo"
    ],
    "name:eng_x_preferred":[
        "Shklo"
    ],
    "name:pol_x_preferred":[
        "Szk\u0142o"
    ],
    "name:ron_x_preferred":[
        "\u0218klo"
    ],
    "name:rus_x_preferred":[
        "\u0428\u043a\u043b\u043e"
    ],
    "name:ukr_x_preferred":[
        "\u0428\u043a\u043b\u043e"
    ],
    "name:zho_x_preferred":[
        "\u4ec0\u514b\u6d1b"
    ],
    "qs:a0":"\u0423\u043a\u0440\u0430\u0457\u043d\u0430",
    "qs:a1":"*\u041b\u044c\u0432\u0456\u0432\u0441\u044c\u043a\u0430",
    "qs:a1_alt":"L'vivs'ka",
    "qs:a1r":"0",
    "qs:a2":"\u042f\u0432\u043e\u0440\u0456\u0432\u0441\u044c\u043a\u0438\u0439",
    "qs:a2_alt":"Yavorivs'kyi",
    "qs:adm0":"\u0423\u043a\u0440\u0430\u0457\u043d\u0430",
    "qs:la_lc":"*",
    "qs:level":"locality",
    "qs:loc":"\u0428\u043a\u043b\u043e",
    "qs:loc_alt":"Shklo",
    "qs:pop":0,
    "qs:type":"buffered point",
    "wd:wordcount":209,
    "wof:name":"\u0428\u043a\u043b\u043e",
    "wof:placetype":"locality",
    "wof:population":5164
},
  "geometry": {"coordinates":[23.541936,49.951377],"type":"Point"}
}