{
  "type": "Feature",
  "properties": {
    "gn:admin1_code":"3.0",
    "gn:asciiname":"Fundoaya",
    "gn:cc2":"UA",
    "gn:country_code":"UA",
    "gn:dem":207,
    "gn:feature_class":"P",
    "gn:feature_code":"PPL",
    "gn:name":"Fundoaya",
    "gn:population":0,
    "gn:timezone":"Europe/Kiev",
    "iso:country":"UA",
    "name:und_x_variant":[
        "Fundovaya",
        "Fundoaya"
    ],
    "wof:name":"Fundoaya",
    "wof:placetype":"locality"
},
  "geometry": {"coordinates":[25.71667,48.31667],"type":"Point"}
}