{
  "type": "Feature",
  "properties": {
    "gn:admin1_code":"15.0",
    "gn:asciiname":"Polyany",
    "gn:country_code":"UA",
    "gn:dem":316,
    "gn:feature_class":"P",
    "gn:feature_code":"PPL",
    "gn:name":"Polyany",
    "gn:population":0,
    "gn:timezone":"Europe/Kiev",
    "iso:country":"UA",
    "wof:name":"Polyany",
    "wof:placetype":"locality"
},
  "geometry": {"coordinates":[23.88333,49.98333],"type":"Point"}
}