{
  "type": "Feature",
  "properties": {
    "iso:country":"UA",
    "name:ukr_x_preferred":[
        "Khazhyn"
    ],
    "name:ukr_x_variant":[
        "\u0425\u0430\u0436\u0438\u043d"
    ],
    "name:unk_x_variant":[
        "Chasin"
    ],
    "qs:a0":"\u0423\u043a\u0440\u0430\u0457\u043d\u0430",
    "qs:a1":"*\u0416\u0438\u0442\u043e\u043c\u0438\u0440\u0441\u044c\u043a\u0430",
    "qs:a1_alt":"Zhytomyrs'ka",
    "qs:a1r":"0",
    "qs:a2":"\u0411\u0435\u0440\u0434\u0438\u0447\u0456\u0432\u0441\u044c\u043a\u0438\u0439",
    "qs:a2_alt":"Berdychivs'kyi",
    "qs:adm0":"\u0423\u043a\u0440\u0430\u0457\u043d\u0430",
    "qs:la_lc":"*",
    "qs:level":"locality",
    "qs:loc":"\u0425\u0430\u0436\u0438\u043d",
    "qs:loc_alt":"Khazhyn",
    "qs:pop":0,
    "qs:type":"buffered point",
    "wof:name":"\u0425\u0430\u0436\u0438\u043d",
    "wof:placetype":"locality"
},
  "geometry": {"coordinates":[28.622641,49.829869],"type":"Point"}
}