{
  "type": "Feature",
  "properties": {
    "gn:gn_country":"UA",
    "gn:gn_fcode":"PPL",
    "gn:gn_pop":3250,
    "gn:population":3250,
    "iso:country":"UA",
    "name:eng_x_preferred":[
        "Dobryanka"
    ],
    "name:rus_x_preferred":[
        "\u0414\u043e\u0431\u0440\u043e\u0432\u0435\u043b\u0438\u0447\u043a\u0456\u0432\u043a\u0430"
    ],
    "name:rus_x_variant":[
        "\u0414\u043e\u0431\u0440\u044f\u043d\u043a\u0430"
    ],
    "name:ukr_x_preferred":[
        "\u0414\u043e\u0431\u0440\u043e\u0432\u0435\u043b\u0438\u0447\u043a\u0456\u0432\u043a\u0430"
    ],
    "name:ukr_x_variant":[
        "\u0414\u043e\u0431\u0440\u044f\u043d\u043a\u0430"
    ],
    "qs_pg:aaroncc":"UA",
    "qs_pg:gn_country":"UA",
    "qs_pg:gn_fcode":"PPL",
    "qs_pg:gn_pop":3250,
    "qs_pg:name":"Dobryanka",
    "qs_pg:photos_9r":0,
    "qs_pg:photos_sr":0,
    "qs_pg:pop_sr":4,
    "qs_pg:qs_pg_placetype":"locality",
    "wof:name":"Dobryanka",
    "wof:placetype":"locality",
    "wof:population":3250
},
  "geometry": {"coordinates":[31.18567,52.06314],"type":"Point"}
}