{
  "type": "Feature",
  "properties": {
    "gn:admin1_code":"1.0",
    "gn:asciiname":"Poboynaya",
    "gn:country_code":"UA",
    "gn:dem":193,
    "gn:feature_class":"P",
    "gn:feature_code":"PPL",
    "gn:name":"Poboynaya",
    "gn:population":0,
    "gn:timezone":"Europe/Kiev",
    "iso:country":"UA",
    "name:und_x_variant":[
        "Poboyna",
        "Podobna",
        "Poboynaya"
    ],
    "wof:name":"Poboynaya",
    "wof:placetype":"locality"
},
  "geometry": {"coordinates":[30.29468,49.206],"type":"Point"}
}