{
  "type": "Feature",
  "properties": {
    "gn:admin1_code":"17.0",
    "gn:asciiname":"Maloroshove",
    "gn:country_code":"UA",
    "gn:dem":100,
    "gn:feature_class":"P",
    "gn:feature_code":"PPL",
    "gn:name":"Maloroshove",
    "gn:population":0,
    "gn:timezone":"Europe/Kiev",
    "iso:country":"UA",
    "name:ukr_x_preferred":[
        "Maloroshove"
    ],
    "name:und_x_variant":[
        "Kolkhoz Novaya Zhizn\u2019 Malorosha",
        "Maloroshevo",
        "Malorosha",
        "Malarosha"
    ],
    "wof:name":"Maloroshove",
    "wof:placetype":"locality"
},
  "geometry": {"coordinates":[29.92394,47.23536],"type":"Point"}
}