{
  "type": "Feature",
  "properties": {
    "iso:country":"UA",
    "name:deu_x_preferred":[
        "Slowetschne"
    ],
    "name:eng_x_preferred":[
        "Slovechne"
    ],
    "name:est_x_preferred":[
        "Slovet\u0161ne"
    ],
    "name:hye_x_preferred":[
        "\u054d\u056c\u0578\u057e\u0565\u0579\u0576\u0578"
    ],
    "name:ron_x_preferred":[
        "Slovecine"
    ],
    "name:rus_x_preferred":[
        "\u0421\u043b\u043e\u0432\u0435\u0447\u043d\u043e"
    ],
    "name:ukr_x_preferred":[
        "Slovechne"
    ],
    "name:ukr_x_variant":[
        "\u0421\u043b\u043e\u0432\u0435\u0447\u043d\u0435"
    ],
    "name:unk_x_variant":[
        "Slavechno"
    ],
    "name:zho_x_preferred":[
        "\u65af\u6d1b\u97cb\u5947\u6d85"
    ],
    "qs:a0":"\u0423\u043a\u0440\u0430\u0457\u043d\u0430",
    "qs:a1":"*\u0416\u0438\u0442\u043e\u043c\u0438\u0440\u0441\u044c\u043a\u0430",
    "qs:a1_alt":"Zhytomyrs'ka",
    "qs:a1r":"0",
    "qs:a2":"\u041e\u0432\u0440\u0443\u0446\u044c\u043a\u0438\u0439",
    "qs:a2_alt":"Ovruts'kyi",
    "qs:adm0":"\u0423\u043a\u0440\u0430\u0457\u043d\u0430",
    "qs:la_lc":"*",
    "qs:level":"locality",
    "qs:loc":"\u0421\u043b\u043e\u0432\u0435\u0447\u043d\u0435",
    "qs:loc_alt":"Slovechne",
    "qs:pop":0,
    "qs:type":"buffered point",
    "wof:name":"\u0421\u043b\u043e\u0432\u0435\u0447\u043d\u0435",
    "wof:placetype":"locality"
},
  "geometry": {"coordinates":[28.35127,51.379571],"type":"Point"}
}