{
  "type": "Feature",
  "properties": {
    "gn:admin1_code":"27.0",
    "gn:asciiname":"Khutor Vas'kov",
    "gn:country_code":"UA",
    "gn:dem":161,
    "gn:feature_class":"P",
    "gn:feature_code":"PPL",
    "gn:name":"Khutor Vas\u2019kov",
    "gn:population":0,
    "gn:timezone":"Europe/Kiev",
    "iso:country":"UA",
    "name:und_x_variant":[
        "Vas\u2019kov",
        "Khutor Vas\u2019kov"
    ],
    "wof:name":"Khutor Vas'kov",
    "wof:placetype":"locality"
},
  "geometry": {"coordinates":[28.91667,51.41667],"type":"Point"}
}