{
  "type": "Feature",
  "properties": {
    "gn:admin1_code":"24.0",
    "gn:asciiname":"Smolova",
    "gn:country_code":"UA",
    "gn:dem":205,
    "gn:feature_class":"P",
    "gn:feature_code":"PPL",
    "gn:name":"Smolova",
    "gn:population":0,
    "gn:timezone":"Europe/Kiev",
    "iso:country":"UA",
    "wof:name":"Smolova",
    "wof:placetype":"locality"
},
  "geometry": {"coordinates":[24.23333,50.78333],"type":"Point"}
}