{
  "type": "Feature",
  "properties": {
    "gn:admin1_code":"23.0",
    "gn:asciiname":"Vasil'kovtsy",
    "gn:country_code":"UA",
    "gn:dem":233,
    "gn:feature_class":"P",
    "gn:feature_code":"PPL",
    "gn:name":"Vasil\u2019kovtsy",
    "gn:population":0,
    "gn:timezone":"Europe/Kiev",
    "iso:country":"UA",
    "wof:name":"Vasil'kovtsy",
    "wof:placetype":"locality"
},
  "geometry": {"coordinates":[29.22347,49.41514],"type":"Point"}
}