{
  "type": "Feature",
  "properties": {
    "gn:admin1_code":"15.0",
    "gn:asciiname":"Losynets'",
    "gn:country_code":"UA",
    "gn:dem":614,
    "gn:feature_class":"P",
    "gn:feature_code":"PPL",
    "gn:name":"Losynets\u2019",
    "gn:population":0,
    "gn:timezone":"Europe/Kiev",
    "iso:country":"UA",
    "name:run_x_preferred":[
        "\u041b\u043e\u0441\u0438\u043d\u0435\u0446"
    ],
    "name:ukr_x_preferred":[
        "Losynets\u2019"
    ],
    "name:ukr_x_variant":[
        "\u041b\u043e\u0441\u0438\u043d\u0435\u0446\u044c"
    ],
    "name:und_x_variant":[
        "Losinets"
    ],
    "wof:name":"Losynets'",
    "wof:placetype":"locality"
},
  "geometry": {"coordinates":[23.10735,49.1364],"type":"Point"}
}