{
  "type": "Feature",
  "properties": {
    "gn:admin1_code":"22.0",
    "gn:asciiname":"Ivanovka",
    "gn:country_code":"UA",
    "gn:dem":320,
    "gn:feature_class":"P",
    "gn:feature_code":"PPL",
    "gn:name":"Ivanovka",
    "gn:population":0,
    "gn:timezone":"Europe/Kiev",
    "iso:country":"UA",
    "name:aze_x_preferred":[
        "\u0130vanovka"
    ],
    "name:bak_x_preferred":[
        "\u0418\u0432\u0430\u043d\u043e\u0432\u043a\u0430"
    ],
    "name:bel_x_preferred":[
        "\u0406\u0432\u0430\u043d\u0430\u045e\u043a\u0430"
    ],
    "name:ceb_x_preferred":[
        "Ivanovka"
    ],
    "name:deu_x_preferred":[
        "Iwanowka"
    ],
    "name:hun_x_preferred":[
        "Ivanovka"
    ],
    "name:hye_x_preferred":[
        "\u053b\u057e\u0561\u0576\u0578\u057e\u056f\u0561"
    ],
    "name:kat_x_preferred":[
        "\u10d8\u10d5\u10d0\u10dc\u10dd\u10d5\u10d9\u10d0"
    ],
    "name:kaz_x_preferred":[
        "\u0418\u0432\u0430\u043d\u043e\u0432\u043a\u0430"
    ],
    "name:lav_x_preferred":[
        "Ivanovka"
    ],
    "name:mhr_x_preferred":[
        "\u0418\u0432\u0430\u043d\u043e\u0432\u043a\u0430"
    ],
    "name:myv_x_preferred":[
        "\u0418\u0432\u0430\u043d\u043e\u0432\u043a\u0430"
    ],
    "name:nld_x_preferred":[
        "Ivanovka"
    ],
    "name:rus_x_preferred":[
        "\u0418\u0432\u0430\u043d\u043e\u0432\u043a\u0430"
    ],
    "name:slv_x_preferred":[
        "Ivanovka"
    ],
    "name:swe_x_preferred":[
        "Ivanovka"
    ],
    "name:tat_x_preferred":[
        "\u0418\u0432\u0430\u043d\u043e\u0432\u043a\u0430"
    ],
    "name:tgk_x_preferred":[
        "\u0418\u0432\u0430\u043d\u043e\u0432\u043a\u0430"
    ],
    "name:ukr_x_preferred":[
        "\u0406\u0432\u0430\u043d\u043e\u0432\u043a\u0430"
    ],
    "name:und_x_variant":[
        "Ivanuvka",
        "Iwanowka",
        "Ivanovka"
    ],
    "wof:name":"Ivanovka",
    "wof:placetype":"locality"
},
  "geometry": {"coordinates":[25.82471,49.2799],"type":"Point"}
}