{
  "type": "Feature",
  "properties": {
    "gn:admin1_code":"22.0",
    "gn:asciiname":"Ivanovka",
    "gn:country_code":"UA",
    "gn:dem":320,
    "gn:feature_class":"P",
    "gn:feature_code":"PPL",
    "gn:name":"Ivanovka",
    "gn:population":0,
    "gn:timezone":"Europe/Kiev",
    "iso:country":"UA",
    "name:und_x_variant":[
        "Ivanuvka",
        "Iwanowka",
        "Ivanovka"
    ],
    "wof:name":"Ivanovka",
    "wof:placetype":"locality"
},
  "geometry": {"coordinates":[25.82471,49.2799],"type":"Point"}
}