{
  "type": "Feature",
  "properties": {
    "gn:admin1_code":"7.0",
    "gn:asciiname":"Harashkivka",
    "gn:country_code":"UA",
    "gn:dem":116,
    "gn:feature_class":"P",
    "gn:feature_code":"PPL",
    "gn:name":"Harashkivka",
    "gn:population":0,
    "gn:timezone":"Europe/Kiev",
    "iso:country":"UA",
    "name:rus_x_preferred":[
        "\u0413\u0430\u0440\u0430\u0448\u043a\u043e\u0432\u043a\u0430"
    ],
    "name:ukr_x_preferred":[
        "Harashkivka"
    ],
    "name:ukr_x_variant":[
        "\u0413\u0430\u0440\u0430\u0448\u043a\u0456\u0432\u043a\u0430"
    ],
    "name:und_x_variant":[
        "Garashkovka"
    ],
    "wof:name":"Harashkivka",
    "wof:placetype":"locality"
},
  "geometry": {"coordinates":[37.03588,50.00976],"type":"Point"}
}