{
  "type": "Feature",
  "properties": {
    "gn:admin1_code":"19.0",
    "gn:asciiname":"Barmaky",
    "gn:country_code":"UA",
    "gn:dem":211,
    "gn:feature_class":"P",
    "gn:feature_code":"PPL",
    "gn:name":"Barmaky",
    "gn:population":0,
    "gn:timezone":"Europe/Kiev",
    "iso:country":"UA",
    "name:ukr_x_preferred":[
        "Barmaky"
    ],
    "name:ukr_x_variant":[
        "\u0411\u0430\u0440\u043c\u0430\u043a\u0438"
    ],
    "name:und_x_variant":[
        "Barmaki"
    ],
    "wof:name":"Barmaky",
    "wof:placetype":"locality"
},
  "geometry": {"coordinates":[26.30412,50.63567000000001],"type":"Point"}
}