{
  "type": "Feature",
  "properties": {
    "gn:admin1_code":"15.0",
    "gn:asciiname":"Zazhitse",
    "gn:cc2":"UA",
    "gn:country_code":"UA",
    "gn:dem":530,
    "gn:feature_class":"P",
    "gn:feature_code":"PPL",
    "gn:name":"Zazhitse",
    "gn:population":0,
    "gn:timezone":"Europe/Kiev",
    "iso:country":"UA",
    "name:und_x_variant":[
        "Zarech\u2019ye",
        "Zazhitse"
    ],
    "wof:name":"Zazhitse",
    "wof:placetype":"locality"
},
  "geometry": {"coordinates":[23.28333,49.21667],"type":"Point"}
}