{
  "type": "Feature",
  "properties": {
    "gn:admin1_code":"2.0",
    "gn:asciiname":"Mala Koshelivka",
    "gn:country_code":"UA",
    "gn:dem":127,
    "gn:feature_class":"P",
    "gn:feature_code":"PPL",
    "gn:name":"Mala Koshelivka",
    "gn:population":0,
    "gn:timezone":"Europe/Kiev",
    "iso:country":"UA",
    "name:rus_x_preferred":[
        "Malaya Koshel\u00ebvka"
    ],
    "name:ukr_x_preferred":[
        "Mala Koshelivka"
    ],
    "name:ukr_x_variant":[
        "\u041c\u0430\u043b\u0430 \u041a\u043e\u0448\u0435\u043b\u0456\u0432\u043a\u0430"
    ],
    "wof:name":"Mala Koshelivka",
    "wof:placetype":"locality"
},
  "geometry": {"coordinates":[31.97299000000001,51.14091],"type":"Point"}
}