{
  "type": "Feature",
  "properties": {
    "gn:admin1_code":"24.0",
    "gn:asciiname":"Vyzhhiv",
    "gn:country_code":"UA",
    "gn:dem":183,
    "gn:feature_class":"P",
    "gn:feature_code":"PPL",
    "gn:name":"Vyzhhiv",
    "gn:population":0,
    "gn:timezone":"Europe/Kiev",
    "iso:country":"UA",
    "name:ukr_x_preferred":[
        "Vyzhhiv"
    ],
    "name:ukr_x_variant":[
        "\u0412\u0438\u0436\u0433\u0456\u0432"
    ],
    "name:und_x_variant":[
        "Vydz\u2019guv",
        "Vyzhguv",
        "Vyzhgov"
    ],
    "wof:name":"Vyzhhiv",
    "wof:placetype":"locality"
},
  "geometry": {"coordinates":[24.0858,51.11671],"type":"Point"}
}