{
  "type": "Feature",
  "properties": {
    "gn:admin1_code":"15.0",
    "gn:asciiname":"Volya Zhultanetska",
    "gn:country_code":"UA",
    "gn:dem":220,
    "gn:feature_class":"P",
    "gn:feature_code":"PPL",
    "gn:name":"Volya Zhultanetska",
    "gn:population":0,
    "gn:timezone":"Europe/Kiev",
    "iso:country":"UA",
    "wof:name":"Volya Zhultanetska",
    "wof:placetype":"locality"
},
  "geometry": {"coordinates":[24.18092,50.0777],"type":"Point"}
}