{
  "type": "Feature",
  "properties": {
    "gn:admin1_code":"7.0",
    "gn:asciiname":"Zholtyye Zori",
    "gn:country_code":"UA",
    "gn:dem":147,
    "gn:feature_class":"P",
    "gn:feature_code":"PPL",
    "gn:name":"Zholtyye Zori",
    "gn:population":0,
    "gn:timezone":"Europe/Kiev",
    "iso:country":"UA",
    "wof:name":"Zholtyye Zori",
    "wof:placetype":"locality"
},
  "geometry": {"coordinates":[36.09074,49.09758],"type":"Point"}
}