{
  "type": "Feature",
  "properties": {
    "gn:admin1_code":"17.0",
    "gn:asciiname":"Soshe-Ostrivs'ke",
    "gn:country_code":"UA",
    "gn:dem":67,
    "gn:feature_class":"P",
    "gn:feature_code":"PPL",
    "gn:name":"Soshe-Ostrivs\u2019ke",
    "gn:population":0,
    "gn:timezone":"Europe/Kiev",
    "iso:country":"UA",
    "name:ukr_x_preferred":[
        "Soshe-Ostrivs\u2019ke"
    ],
    "name:und_x_variant":[
        "Soshe-Ostrovskoye"
    ],
    "wof:name":"Soshe-Ostrivs'ke",
    "wof:placetype":"locality"
},
  "geometry": {"coordinates":[29.75248,47.19045],"type":"Point"}
}