{
  "type": "Feature",
  "properties": {
    "gn:admin1_code":"27.0",
    "gn:asciiname":"Sadybne",
    "gn:country_code":"UA",
    "gn:dem":202,
    "gn:feature_class":"P",
    "gn:feature_code":"PPL",
    "gn:name":"Sadybne",
    "gn:population":0,
    "gn:timezone":"Europe/Kiev",
    "iso:country":"UA",
    "name:ukr_x_preferred":[
        "Sadybne"
    ],
    "name:ukr_x_variant":[
        "\u0421\u0430\u0434\u0438\u0431\u043d\u0435"
    ],
    "name:und_x_variant":[
        "Sadybnoye"
    ],
    "wof:name":"Sadybne",
    "wof:placetype":"locality"
},
  "geometry": {"coordinates":[28.40079,50.88265],"type":"Point"}
}