{
  "type": "Feature",
  "properties": {
    "gn:admin1_code":"7.0",
    "gn:asciiname":"Petrovskiy",
    "gn:country_code":"UA",
    "gn:dem":213,
    "gn:feature_class":"P",
    "gn:feature_code":"PPL",
    "gn:name":"Petrovskiy",
    "gn:population":0,
    "gn:timezone":"Europe/Kiev",
    "iso:country":"UA",
    "wof:name":"Petrovskiy",
    "wof:placetype":"locality"
},
  "geometry": {"coordinates":[35.73444,50.00806],"type":"Point"}
}