{
  "type": "Feature",
  "properties": {
    "gn:admin1_code":"17.0",
    "gn:asciiname":"Novokalanchak",
    "gn:country_code":"UA",
    "gn:dem":75,
    "gn:feature_class":"P",
    "gn:feature_code":"PPL",
    "gn:name":"Novokalanchak",
    "gn:population":0,
    "gn:timezone":"Europe/Kiev",
    "iso:country":"UA",
    "name:ukr_x_preferred":[
        "Novokalanchak"
    ],
    "name:ukr_x_variant":[
        "\u041d\u043e\u0432\u043e\u043a\u0430\u043b\u0430\u043d\u0447\u0430\u043a"
    ],
    "name:und_x_variant":[
        "Novaya-Aleksandriya",
        "Alexandria Nova",
        "Mar\u2019yanovka"
    ],
    "wof:name":"Novokalanchak",
    "wof:placetype":"locality"
},
  "geometry": {"coordinates":[28.77599,45.58574],"type":"Point"}
}