{
  "type": "Feature",
  "properties": {
    "gn:admin1_code":"2.0",
    "gn:asciiname":"Yashchenkiv",
    "gn:country_code":"UA",
    "gn:dem":166,
    "gn:feature_class":"P",
    "gn:feature_code":"PPL",
    "gn:name":"Yashchenkiv",
    "gn:population":0,
    "gn:timezone":"Europe/Kiev",
    "iso:country":"UA",
    "name:ukr_x_preferred":[
        "Yashchenkiv"
    ],
    "name:ukr_x_variant":[
        "\u042f\u0449\u0435\u043d\u043a\u0456\u0432"
    ],
    "name:und_x_variant":[
        "Yashchenkov"
    ],
    "wof:name":"Yashchenkiv",
    "wof:placetype":"locality"
},
  "geometry": {"coordinates":[32.76130999999999,50.40799000000001],"type":"Point"}
}