{
  "type": "Feature",
  "properties": {
    "gn:admin1_code":"17.0",
    "gn:asciiname":"Myhayeve",
    "gn:country_code":"UA",
    "gn:dem":156,
    "gn:feature_class":"P",
    "gn:feature_code":"PPL",
    "gn:name":"Myhayeve",
    "gn:population":0,
    "gn:timezone":"Europe/Kiev",
    "iso:country":"UA",
    "name:ukr_x_preferred":[
        "Myhayeve"
    ],
    "name:ukr_x_variant":[
        "\u041c\u0438\u0433\u0430\u0454\u0432\u0435"
    ],
    "name:und_x_variant":[
        "Migayevo"
    ],
    "wof:name":"Myhayeve",
    "wof:placetype":"locality"
},
  "geometry": {"coordinates":[30.04227,46.98828],"type":"Point"}
}