{
  "type": "Feature",
  "properties": {
    "gn:admin1_code":"4.0",
    "gn:asciiname":"Novospas'ke",
    "gn:country_code":"UA",
    "gn:dem":104,
    "gn:feature_class":"P",
    "gn:feature_code":"PPL",
    "gn:name":"Novospas\u2019ke",
    "gn:population":0,
    "gn:timezone":"Europe/Kiev",
    "iso:country":"UA",
    "name:ukr_x_preferred":[
        "Novospas\u2019ke"
    ],
    "name:ukr_x_variant":[
        "\u041d\u043e\u0432\u043e\u0441\u043f\u0430\u0441\u044c\u043a\u0435"
    ],
    "name:und_x_variant":[
        "Novospasskoye"
    ],
    "wof:name":"Novospas'ke",
    "wof:placetype":"locality"
},
  "geometry": {"coordinates":[34.92235,48.76322],"type":"Point"}
}