{
  "type": "Feature",
  "properties": {
    "gn:admin1_code":"5.0",
    "gn:asciiname":"Novokhats'ke",
    "gn:country_code":"UA",
    "gn:dem":94,
    "gn:feature_class":"P",
    "gn:feature_code":"PPL",
    "gn:name":"Novokhats\u2019ke",
    "gn:population":0,
    "gn:timezone":"Europe/Kiev",
    "iso:country":"UA",
    "name:ukr_x_preferred":[
        "Novokhats\u2019ke"
    ],
    "name:ukr_x_variant":[
        "\u041d\u043e\u0432\u043e\u0445\u0430\u0442\u0441\u044c\u043a\u0435"
    ],
    "name:und_x_variant":[
        "Novokhatskiy",
        "Novokhatskoye"
    ],
    "wof:name":"Novokhats'ke",
    "wof:placetype":"locality"
},
  "geometry": {"coordinates":[36.68728,48.06341],"type":"Point"}
}