{
  "type": "Feature",
  "properties": {
    "gn:admin1_code":"9.0",
    "gn:asciiname":"Varvarivka",
    "gn:country_code":"UA",
    "gn:dem":260,
    "gn:feature_class":"P",
    "gn:feature_code":"PPL",
    "gn:name":"Varvarivka",
    "gn:population":0,
    "gn:timezone":"Europe/Kiev",
    "iso:country":"UA",
    "name:ukr_x_preferred":[
        "Varvarivka"
    ],
    "name:ukr_x_variant":[
        "\u0412\u0430\u0440\u0432\u0430\u0440\u0456\u0432\u043a\u0430"
    ],
    "name:und_x_variant":[
        "Barbarowka",
        "Varvarovka"
    ],
    "wof:name":"Varvarivka",
    "wof:placetype":"locality"
},
  "geometry": {"coordinates":[27.49502,50.01925],"type":"Point"}
}