{
  "type": "Feature",
  "properties": {
    "iso:country":"UA",
    "name:eng_x_preferred":[
        "Rogintsy"
    ],
    "name:rus_x_preferred":[
        "\u0420\u043e\u0433\u0438\u043d\u0446\u044b"
    ],
    "name:ukr_x_preferred":[
        "Rohyntsi"
    ],
    "name:ukr_x_variant":[
        "\u0420\u043e\u0433\u0438\u043d\u0446\u0456"
    ],
    "qs:a0":"\u0423\u043a\u0440\u0430\u0457\u043d\u0430",
    "qs:a1":"*\u0421\u0443\u043c\u0441\u044c\u043a\u0430",
    "qs:a1_alt":"Sums'ka",
    "qs:a1r":"0",
    "qs:a2":"\u0420\u043e\u043c\u0435\u043d\u0441\u044c\u043a\u0438\u0439",
    "qs:a2_alt":"Romens'kyi",
    "qs:adm0":"\u0423\u043a\u0440\u0430\u0457\u043d\u0430",
    "qs:la_lc":"*",
    "qs:level":"locality",
    "qs:loc":"\u0420\u043e\u0433\u0438\u043d\u0446\u0456",
    "qs:loc_alt":"Rohyntsi",
    "qs:pop":0,
    "qs:type":"buffered point",
    "wof:name":"\u0420\u043e\u0433\u0438\u043d\u0446\u0456",
    "wof:placetype":"locality"
},
  "geometry": {"coordinates":[33.346416,50.850877],"type":"Point"}
}