{
  "type": "Feature",
  "properties": {
    "gn:admin1_code":"11.0",
    "gn:admin2_code":"694905",
    "gn:admin3_code":"11153097.0",
    "gn:asciiname":"Vitino",
    "gn:country_code":"UA",
    "gn:dem":8,
    "gn:elevation":"2.0",
    "gn:feature_class":"P",
    "gn:feature_code":"PPL",
    "gn:name":"Vitino",
    "gn:population":627,
    "gn:timezone":"Europe/Simferopol",
    "iso:country":"UA",
    "name:eng_x_preferred":[
        "Vitino"
    ],
    "name:est_x_preferred":[
        "Vitino"
    ],
    "name:fin_x_preferred":[
        "Vitinon satama"
    ],
    "name:pol_x_preferred":[
        "Witino"
    ],
    "name:rus_x_historical":[
        "\u0410\u0438\u0440\u0447\u0430\u0301"
    ],
    "name:rus_x_preferred":[
        "\u0410\u0438\u0440\u0447\u0430\u0301"
    ],
    "name:rus_x_variant":[
        "\u0412\u0438\u0442\u0438\u043d\u043e"
    ],
    "name:ukr_x_preferred":[
        "\u0412\u0456\u0442\u0438\u043d\u0435"
    ],
    "wof:name":"Vitino",
    "wof:placetype":"locality",
    "wof:population":627
},
  "geometry": {"coordinates":[33.15951,45.21654],"type":"Point"}
}