{
  "type": "Feature",
  "properties": {
    "gn:admin1_code":"9.0",
    "gn:asciiname":"Mal'ky",
    "gn:country_code":"UA",
    "gn:dem":309,
    "gn:feature_class":"P",
    "gn:feature_code":"PPL",
    "gn:name":"Mal\u2019ky",
    "gn:population":0,
    "gn:timezone":"Europe/Kiev",
    "iso:country":"UA",
    "name:ukr_x_preferred":[
        "Mal\u2019ky"
    ],
    "name:ukr_x_variant":[
        "\u041c\u0430\u043b\u2019\u043a\u0438"
    ],
    "name:und_x_variant":[
        "Mal\u2019ki"
    ],
    "wof:name":"Mal'ky",
    "wof:placetype":"locality"
},
  "geometry": {"coordinates":[27.11692,49.867],"type":"Point"}
}