{
  "type": "Feature",
  "properties": {
    "gn:population":4432,
    "iso:country":"UA",
    "name:eng_x_preferred":[
        "Khorosheve"
    ],
    "name:rus_x_preferred":[
        "\u0425\u043e\u0440\u043e\u0448\u0435\u0432\u043e"
    ],
    "name:rus_x_variant":[
        "\u0425\u043e\u0440\u043e\u0448\u0435\u0432\u0435"
    ],
    "name:ukr_x_preferred":[
        "\u0425\u043e\u0440\u043e\u0448\u0435\u0432\u0435"
    ],
    "name:und_x_variant":[
        "Khoroshevo"
    ],
    "qs:a0":"\u0423\u043a\u0440\u0430\u0457\u043d\u0430",
    "qs:a1":"*\u0425\u0430\u0440\u043a\u0456\u0432\u0441\u044c\u043a\u0430",
    "qs:a1_alt":"Kharkivs'ka",
    "qs:a1r":"0",
    "qs:a2":"\u0425\u0430\u0440\u043a\u0456\u0432\u0441\u044c\u043a\u0438\u0439",
    "qs:a2_alt":"Kharkivs'kyi",
    "qs:adm0":"\u0423\u043a\u0440\u0430\u0457\u043d\u0430",
    "qs:la_lc":"*",
    "qs:level":"locality",
    "qs:loc":"\u0425\u043e\u0440\u043e\u0448\u0435\u0432\u0435",
    "qs:loc_alt":"Khorosheve",
    "qs:pop":0,
    "qs:type":"buffered point",
    "wof:name":"\u0425\u043e\u0440\u043e\u0448\u0435\u0432\u0435",
    "wof:placetype":"locality",
    "wof:population":4432
},
  "geometry": {"coordinates":[36.22542,49.854957],"type":"Point"}
}