{
  "type": "Feature",
  "properties": {
    "gn:admin1_code":"23.0",
    "gn:asciiname":"Vynokurnya",
    "gn:country_code":"UA",
    "gn:dem":282,
    "gn:feature_class":"P",
    "gn:feature_code":"PPL",
    "gn:name":"Vynokurnya",
    "gn:population":0,
    "gn:timezone":"Europe/Kiev",
    "iso:country":"UA",
    "name:ukr_x_preferred":[
        "Vynokurnya"
    ],
    "name:und_x_variant":[
        "\u0412\u0438\u043d\u043e\u043a\u0443\u0440\u043d\u044f",
        "Vinokurnya"
    ],
    "wof:name":"Vynokurnya",
    "wof:placetype":"locality"
},
  "geometry": {"coordinates":[28.54895,48.77027],"type":"Point"}
}