{
  "type": "Feature",
  "properties": {
    "iso:country":"UA",
    "name:eng_x_preferred":[
        "Novoavramovka"
    ],
    "name:rus_x_preferred":[
        "\u041d\u043e\u0432\u043e\u0430\u0432\u0440\u0430\u043c\u043e\u0432\u043a\u0430"
    ],
    "name:ukr_x_preferred":[
        "Novoavramivka"
    ],
    "name:ukr_x_variant":[
        "\u041d\u043e\u0432\u043e\u0430\u0432\u0440\u0430\u043c\u0456\u0432\u043a\u0430"
    ],
    "name:und_x_variant":[
        "Novaya Avramovka"
    ],
    "qs:a0":"\u0423\u043a\u0440\u0430\u0457\u043d\u0430",
    "qs:a1":"*\u041f\u043e\u043b\u0442\u0430\u0432\u0441\u044c\u043a\u0430",
    "qs:a1_alt":"Poltavs'ka",
    "qs:a1r":"0",
    "qs:a2":"\u0425\u043e\u0440\u043e\u043b\u044c\u0441\u044c\u043a\u0438\u0439",
    "qs:a2_alt":"Khorol's'kyi",
    "qs:adm0":"\u0423\u043a\u0440\u0430\u0457\u043d\u0430",
    "qs:la_lc":"*",
    "qs:level":"locality",
    "qs:loc":"\u041d\u043e\u0432\u043e\u0430\u0432\u0440\u0430\u043c\u0456\u0432\u043a\u0430",
    "qs:loc_alt":"Novoavramivka",
    "qs:pop":0,
    "qs:type":"buffered point",
    "wof:name":"\u041d\u043e\u0432\u043e\u0430\u0432\u0440\u0430\u043c\u0456\u0432\u043a\u0430",
    "wof:placetype":"locality"
},
  "geometry": {"coordinates":[33.416466,49.797066],"type":"Point"}
}