{
  "type": "Feature",
  "properties": {
    "gn:admin1_code":"5.0",
    "gn:asciiname":"Monakhove",
    "gn:country_code":"UA",
    "gn:dem":199,
    "gn:feature_class":"P",
    "gn:feature_code":"PPL",
    "gn:name":"Monakhove",
    "gn:population":0,
    "gn:timezone":"Europe/Kiev",
    "iso:country":"UA",
    "name:ukr_x_preferred":[
        "\u041c\u043e\u043d\u0430\u0445\u043e\u0432\u0435"
    ],
    "name:und_x_variant":[
        "Monakhovo"
    ],
    "wof:name":"Monakhove",
    "wof:placetype":"locality"
},
  "geometry": {"coordinates":[38.11586,48.15034],"type":"Point"}
}