{
  "type": "Feature",
  "properties": {
    "gn:admin1_code":"6.0",
    "gn:asciiname":"Oleyeva-Korolevka",
    "gn:country_code":"UA",
    "gn:dem":300,
    "gn:feature_class":"P",
    "gn:feature_code":"PPL",
    "gn:name":"Oley\u00ebva-Korol\u00ebvka",
    "gn:population":0,
    "gn:timezone":"Europe/Kiev",
    "iso:country":"UA",
    "name:und_x_variant":[
        "Oley\u00ebva Korolyuvka",
        "Oley\u00ebva-Korol\u00ebvka"
    ],
    "wof:name":"Oleyeva-Korolevka",
    "wof:placetype":"locality"
},
  "geometry": {"coordinates":[25.37298,48.75067],"type":"Point"}
}