{
  "type": "Feature",
  "properties": {
    "iso:country":"UA",
    "name:ukr_x_preferred":[
        "\u0417\u0430\u0440\u0456\u0447\u043d\u0435"
    ],
    "name:unk_x_variant":[
        "Zarichne"
    ],
    "qs:a0":"\u0423\u043a\u0440\u0430\u0457\u043d\u0430",
    "qs:a1":"*\u0412\u0456\u043d\u043d\u0438\u0446\u044c\u043a\u0430",
    "qs:a1_alt":"Vinnyts'ka",
    "qs:a1r":"0",
    "qs:a2":"\u0422\u0443\u043b\u044c\u0447\u0438\u043d\u0441\u044c\u043a\u0438\u0439",
    "qs:a2_alt":"Tul'chyns'kyi",
    "qs:adm0":"\u0423\u043a\u0440\u0430\u0457\u043d\u0430",
    "qs:la_lc":"*",
    "qs:level":"locality",
    "qs:loc":"\u0417\u0430\u0440\u0456\u0447\u043d\u0435",
    "qs:loc_alt":"Zarichne",
    "qs:pop":0,
    "qs:type":"buffered point",
    "wof:name":"\u0417\u0430\u0440\u0456\u0447\u043d\u0435",
    "wof:placetype":"locality"
},
  "geometry": {"coordinates":[28.792757,48.695856],"type":"Point"}
}