{
  "type": "Feature",
  "properties": {
    "gn:admin1_code":"9.0",
    "gn:asciiname":"Kunev",
    "gn:country_code":"UA",
    "gn:dem":209,
    "gn:feature_class":"P",
    "gn:feature_code":"PPL",
    "gn:name":"Kun\u00ebv",
    "gn:population":0,
    "gn:timezone":"Europe/Kiev",
    "iso:country":"UA",
    "wof:name":"Kunev",
    "wof:placetype":"locality"
},
  "geometry": {"coordinates":[26.36322,50.24349],"type":"Point"}
}