{
  "type": "Feature",
  "properties": {
    "gn:admin1_code":"19.0",
    "gn:asciiname":"Levachi",
    "gn:country_code":"UA",
    "gn:dem":199,
    "gn:feature_class":"P",
    "gn:feature_code":"PPL",
    "gn:name":"Levachi",
    "gn:population":0,
    "gn:timezone":"Europe/Kiev",
    "iso:country":"UA",
    "name:und_x_variant":[
        "Levache",
        "Levachi"
    ],
    "wof:name":"Levachi",
    "wof:placetype":"locality"
},
  "geometry": {"coordinates":[27.16743,50.94133],"type":"Point"}
}