{
  "type": "Feature",
  "properties": {
    "gn:admin1_code":"8.0",
    "gn:asciiname":"Bruskyns'ke",
    "gn:country_code":"UA",
    "gn:dem":68,
    "gn:feature_class":"P",
    "gn:feature_code":"PPL",
    "gn:name":"Bruskyns\u2019ke",
    "gn:population":0,
    "gn:timezone":"Europe/Kiev",
    "iso:country":"UA",
    "name:ukr_x_preferred":[
        "Bruskyns\u2019ke"
    ],
    "name:ukr_x_variant":[
        "\u0411\u0440\u0443\u0441\u043a\u0438\u043d\u0441\u044c\u043a\u0435"
    ],
    "name:und_x_variant":[
        "Bruskinskiy"
    ],
    "wof:name":"Bruskyns'ke",
    "wof:placetype":"locality"
},
  "geometry": {"coordinates":[33.20941,47.15792],"type":"Point"}
}