{
  "type": "Feature",
  "properties": {
    "gn:admin1_code":"24.0",
    "gn:asciiname":"Viynytsya",
    "gn:country_code":"UA",
    "gn:dem":217,
    "gn:feature_class":"P",
    "gn:feature_code":"PPL",
    "gn:name":"Viynytsya",
    "gn:population":0,
    "gn:timezone":"Europe/Kiev",
    "iso:country":"UA",
    "name:ukr_x_preferred":[
        "Viynytsya"
    ],
    "name:ukr_x_variant":[
        "\u0412\u0456\u0439\u043d\u0438\u0446\u044f"
    ],
    "name:und_x_variant":[
        "Voinitsa",
        "Wojnica",
        "Voynitsa"
    ],
    "wof:name":"Viynytsya",
    "wof:placetype":"locality"
},
  "geometry": {"coordinates":[24.67598,50.79116],"type":"Point"}
}