{
  "type": "Feature",
  "properties": {
    "gn:admin1_code":"13.0",
    "gn:asciiname":"Parkhomovka",
    "gn:country_code":"UA",
    "gn:dem":184,
    "gn:feature_class":"P",
    "gn:feature_code":"PPL",
    "gn:name":"Parkhomovka",
    "gn:population":0,
    "gn:timezone":"Europe/Kiev",
    "iso:country":"UA",
    "wof:name":"Parkhomovka",
    "wof:placetype":"locality"
},
  "geometry": {"coordinates":[30.04364,49.55423],"type":"Point"}
}