{
  "type": "Feature",
  "properties": {
    "gn:admin1_code":"23.0",
    "gn:asciiname":"Stepne",
    "gn:country_code":"UA",
    "gn:dem":166,
    "gn:feature_class":"P",
    "gn:feature_code":"PPL",
    "gn:name":"Stepne",
    "gn:population":0,
    "gn:timezone":"Europe/Kiev",
    "iso:country":"UA",
    "name:ukr_x_preferred":[
        "\u0421\u0442\u0435\u043f\u043d\u0435"
    ],
    "name:und_x_variant":[
        "Stepnoye"
    ],
    "wof:name":"Stepne",
    "wof:placetype":"locality"
},
  "geometry": {"coordinates":[28.26864,48.40124],"type":"Point"}
}