{
  "type": "Feature",
  "properties": {
    "gn:admin1_code":"15.0",
    "gn:asciiname":"Nagachev",
    "gn:country_code":"UA",
    "gn:dem":219,
    "gn:feature_class":"P",
    "gn:feature_code":"PPL",
    "gn:name":"Nagach\u00ebv",
    "gn:population":0,
    "gn:timezone":"Europe/Kiev",
    "iso:country":"UA",
    "name:deu_x_preferred":[
        "Nahatschiw"
    ],
    "name:pol_x_preferred":[
        "Nahacz\u00f3w"
    ],
    "name:ron_x_preferred":[
        "Nahaciv"
    ],
    "name:rus_x_preferred":[
        "\u041d\u0430\u0433\u0430\u0447\u0435\u0432"
    ],
    "name:ukr_x_preferred":[
        "\u041d\u0430\u0433\u0430\u0447\u0456\u0432"
    ],
    "name:und_x_variant":[
        "Nagachuv",
        "Nahacz\u00f3w",
        "Nagach\u00ebv"
    ],
    "name:zho_x_preferred":[
        "\u7d0d\u52a0\u5947\u592b"
    ],
    "wof:name":"Nagachev",
    "wof:placetype":"locality"
},
  "geometry": {"coordinates":[23.28047,50.00698],"type":"Point"}
}