{
  "type": "Feature",
  "properties": {
    "gn:admin1_code":"18.0",
    "gn:asciiname":"Morozivshchyna",
    "gn:country_code":"UA",
    "gn:dem":122,
    "gn:feature_class":"P",
    "gn:feature_code":"PPL",
    "gn:name":"Morozivshchyna",
    "gn:population":0,
    "gn:timezone":"Europe/Kiev",
    "iso:country":"UA",
    "name:ukr_x_preferred":[
        "Morozivshchyna"
    ],
    "name:ukr_x_variant":[
        "\u041c\u043e\u0440\u043e\u0437\u0456\u0432\u0449\u0438\u043d\u0430"
    ],
    "wof:name":"Morozivshchyna",
    "wof:placetype":"locality"
},
  "geometry": {"coordinates":[33.7262,49.66884],"type":"Point"}
}