{
  "type": "Feature",
  "properties": {
    "gn:admin1_code":"6.0",
    "gn:asciiname":"Podkamen'",
    "gn:country_code":"UA",
    "gn:dem":281,
    "gn:feature_class":"P",
    "gn:feature_code":"PPL",
    "gn:name":"Podkamen\u2019",
    "gn:population":0,
    "gn:timezone":"Europe/Kiev",
    "iso:country":"UA",
    "name:und_x_variant":[
        "Podkamie\u0144",
        "Podkamen\u2019",
        "Pidkamien",
        "Pidkamin'"
    ],
    "wof:name":"Podkamen'",
    "wof:placetype":"locality"
},
  "geometry": {"coordinates":[24.48026,49.45027],"type":"Point"}
}