{
  "type": "Feature",
  "properties": {
    "gn:admin1_code":"27.0",
    "gn:asciiname":"Kozhukhivka",
    "gn:country_code":"UA",
    "gn:dem":179,
    "gn:feature_class":"P",
    "gn:feature_code":"PPL",
    "gn:name":"Kozhukhivka",
    "gn:population":0,
    "gn:timezone":"Europe/Kiev",
    "iso:country":"UA",
    "name:ukr_x_preferred":[
        "Kozhukhivka"
    ],
    "name:ukr_x_variant":[
        "\u041a\u043e\u0436\u0443\u0445\u0456\u0432\u043a\u0430"
    ],
    "name:und_x_variant":[
        "Kozhukhovka"
    ],
    "wof:name":"Kozhukhivka",
    "wof:placetype":"locality"
},
  "geometry": {"coordinates":[28.56705,50.99148],"type":"Point"}
}