{
  "type": "Feature",
  "properties": {
    "gn:admin1_code":"10.0",
    "gn:asciiname":"Sablyne",
    "gn:country_code":"UA",
    "gn:dem":146,
    "gn:feature_class":"P",
    "gn:feature_code":"PPL",
    "gn:name":"Sablyne",
    "gn:population":0,
    "gn:timezone":"Europe/Kiev",
    "iso:country":"UA",
    "name:ukr_x_preferred":[
        "Sablyne"
    ],
    "name:ukr_x_variant":[
        "\u0421\u0430\u0431\u043b\u0438\u043d\u0435"
    ],
    "wof:name":"Sablyne",
    "wof:placetype":"locality"
},
  "geometry": {"coordinates":[32.65335,48.64762],"type":"Point"}
}