{
  "type": "Feature",
  "properties": {
    "gn:admin1_code":"6.0",
    "gn:asciiname":"Sukhodul",
    "gn:country_code":"UA",
    "gn:dem":209,
    "gn:feature_class":"P",
    "gn:feature_code":"PPL",
    "gn:name":"Sukhodul",
    "gn:population":0,
    "gn:timezone":"Europe/Kiev",
    "iso:country":"UA",
    "name:und_x_variant":[
        "Sukhodol",
        "Sukhodul"
    ],
    "wof:name":"Sukhodul",
    "wof:placetype":"locality"
},
  "geometry": {"coordinates":[25.19379,48.88491],"type":"Point"}
}