{
  "type": "Feature",
  "properties": {
    "gn:population":3033,
    "iso:country":"UA",
    "name:ceb_x_preferred":[
        "Uralo-Kavkaz"
    ],
    "name:crh_x_preferred":[
        "Uralo-Kavkaz"
    ],
    "name:deu_x_preferred":[
        "Uralo-Kawkas"
    ],
    "name:eng_x_preferred":[
        "Uralo-Kavkaz"
    ],
    "name:lav_x_preferred":[
        "Uralo-Kavkaza"
    ],
    "name:ron_x_preferred":[
        "Uralo-Kavkaz"
    ],
    "name:rus_x_preferred":[
        "\u0423\u0440\u0430\u043b\u043e-\u041a\u0430\u0432\u043a\u0430\u0437"
    ],
    "name:ukr_x_preferred":[
        "\u0423\u0440\u0430\u043b\u043e-\u041a\u0430\u0432\u043a\u0430\u0437"
    ],
    "name:und_x_variant":[
        "Uralo-Kavkazskiy"
    ],
    "name:zho_x_preferred":[
        "\u70cf\u62c9\u6d1b-\u5361\u592b\u5361\u8332"
    ],
    "qs:a0":"\u0423\u043a\u0440\u0430\u0457\u043d\u0430",
    "qs:a1":"*\u041b\u0443\u0433\u0430\u043d\u0441\u044c\u043a\u0430",
    "qs:a1_alt":"Luhans'ka",
    "qs:a1r":"0",
    "qs:a2":"\u041a\u0440\u0430\u0441\u043d\u043e\u0434\u043e\u043d\u0441\u044c\u043a\u0438\u0439",
    "qs:a2_alt":"Krasnodons'kyi",
    "qs:adm0":"\u0423\u043a\u0440\u0430\u0457\u043d\u0430",
    "qs:la_lc":"*",
    "qs:level":"locality",
    "qs:loc":"\u0423\u0440\u0430\u043b\u043e-\u041a\u0430\u0432\u043a\u0430\u0437",
    "qs:loc_alt":"Uralo-Kavkaz",
    "qs:pop":0,
    "qs:type":"buffered point",
    "wd:wordcount":435,
    "wof:name":"\u0423\u0440\u0430\u043b\u043e-\u041a\u0430\u0432\u043a\u0430\u0437",
    "wof:placetype":"locality",
    "wof:population":3033
},
  "geometry": {"coordinates":[39.798,48.326775],"type":"Point"}
}