{
  "type": "Feature",
  "properties": {
    "iso:country":"UA",
    "name:ara_x_preferred":[
        "\u0641\u064a\u0644\u064a\u0643\u064a\u064a \u0631\u0627\u0643\u0648\u0641\u064a\u062a\u0633"
    ],
    "name:deu_x_preferred":[
        "Welykyj Rakowez"
    ],
    "name:eng_x_preferred":[
        "Velykyi Rakovets"
    ],
    "name:epo_x_preferred":[
        "Velikij Rakovec"
    ],
    "name:heb_x_preferred":[
        "\u05e8\u05e7\u05d5\u05d1\u05d9\u05e5"
    ],
    "name:hun_x_preferred":[
        "Nagyr\u00e1k\u00f3c"
    ],
    "name:hye_x_preferred":[
        "\u054e\u0565\u056c\u056b\u056f\u056b \u054c\u0561\u056f\u0578\u057e\u0565\u0581"
    ],
    "name:hye_x_variant":[
        "\u054e\u0565\u056c\u056b\u056f\u056b\u0575 \u054c\u0561\u056f\u0578\u057e\u0565\u0581"
    ],
    "name:nld_x_preferred":[
        "Velykyi Rakovets"
    ],
    "name:ron_x_preferred":[
        "Vel\u00eek\u00eei Rakove\u021b"
    ],
    "name:rus_x_preferred":[
        "\u0412\u0435\u043b\u0438\u043a\u0438\u0439 \u0420\u0430\u043a\u043e\u0432\u0435\u0446"
    ],
    "name:ukr_x_preferred":[
        "\u0412\u0435\u043b\u0438\u043a\u0438\u0439 \u0420\u0430\u043a\u043e\u0432\u0435\u0446\u044c"
    ],
    "name:zho_x_preferred":[
        "\u5927\u62c9\u79d1\u97cb\u9f4a"
    ],
    "qs:a0":"\u0423\u043a\u0440\u0430\u0457\u043d\u0430",
    "qs:a1":"*\u0406\u0432\u0430\u043d\u043e-\u0424\u0440\u0430\u043d\u043a\u0456\u0432\u0441\u044c\u043a\u0430",
    "qs:a1_alt":"Ivano-Frankivs'ka",
    "qs:a1r":"0",
    "qs:a2":"\u0411\u043e\u0433\u043e\u0440\u043e\u0434\u0447\u0430\u043d\u0441\u044c\u043a\u0438\u0439",
    "qs:a2_alt":"Bohorodchans'kyi",
    "qs:adm0":"\u0423\u043a\u0440\u0430\u0457\u043d\u0430",
    "qs:la_lc":"*",
    "qs:level":"locality",
    "qs:loc":"\u0420\u0430\u043a\u043e\u0432\u0435\u0446\u044c",
    "qs:loc_alt":"Rakovets",
    "qs:pop":0,
    "qs:type":"buffered point",
    "wd:wordcount":90,
    "wof:name":"\u0420\u0430\u043a\u043e\u0432\u0435\u0446\u044c",
    "wof:placetype":"locality"
},
  "geometry": {"coordinates":[24.395896,48.71084],"type":"Point"}
}