{
  "type": "Feature",
  "properties": {
    "gn:admin1_code":"11.0",
    "gn:admin2_code":"710690",
    "gn:admin3_code":"11153140.0",
    "gn:asciiname":"Artemovka",
    "gn:country_code":"UA",
    "gn:dem":93,
    "gn:elevation":"93.0",
    "gn:feature_class":"P",
    "gn:feature_code":"PPL",
    "gn:name":"Artemovka",
    "gn:population":216,
    "gn:timezone":"Europe/Simferopol",
    "iso:country":"UA",
    "name:eng_x_preferred":[
        "Artemovka"
    ],
    "name:rus_x_historical":[
        "\u0422\u043e\u043a\u0430\u0301"
    ],
    "name:rus_x_preferred":[
        "\u0410\u0440\u0442\u0451\u043c\u043e\u0432\u043a\u0430"
    ],
    "name:rus_x_variant":[
        "\u0422\u043e\u043a\u0430\u0301"
    ],
    "name:ukr_x_preferred":[
        "\u0410\u0440\u0442\u0435\u043c\u0456\u0432\u043a\u0430"
    ],
    "wof:name":"Artemovka",
    "wof:placetype":"locality",
    "wof:population":216
},
  "geometry": {"coordinates":[32.82392,45.46861],"type":"Point"}
}