{
  "type": "Feature",
  "properties": {
    "gn:admin1_code":"18.0",
    "gn:asciiname":"Pysarshchyna",
    "gn:country_code":"UA",
    "gn:dem":87,
    "gn:feature_class":"P",
    "gn:feature_code":"PPL",
    "gn:name":"Pysarshchyna",
    "gn:population":0,
    "gn:timezone":"Europe/Kiev",
    "iso:country":"UA",
    "name:ukr_x_preferred":[
        "Pysarshchyna"
    ],
    "name:ukr_x_variant":[
        "\u041f\u0438\u0441\u0430\u0440\u0449\u0438\u043d\u0430"
    ],
    "wof:name":"Pysarshchyna",
    "wof:placetype":"locality"
},
  "geometry": {"coordinates":[33.44463,49.24402],"type":"Point"}
}