{
  "type": "Feature",
  "properties": {
    "gn:admin1_code":"27.0",
    "gn:asciiname":"Bilylivka",
    "gn:country_code":"UA",
    "gn:dem":232,
    "gn:feature_class":"P",
    "gn:feature_code":"PPL",
    "gn:name":"Bilylivka",
    "gn:population":0,
    "gn:timezone":"Europe/Kiev",
    "iso:country":"UA",
    "name:rus_x_preferred":[
        "\u0411\u0435\u043b\u0438\u043b\u043e\u0432\u043a\u0430"
    ],
    "name:ukr_x_preferred":[
        "Bilylivka"
    ],
    "name:ukr_x_variant":[
        "\u0411\u0456\u043b\u0438\u043b\u0456\u0432\u043a\u0430"
    ],
    "name:und_x_variant":[
        "Belilovka"
    ],
    "wof:name":"Bilylivka",
    "wof:placetype":"locality"
},
  "geometry": {"coordinates":[29.03062000000001,49.68634],"type":"Point"}
}