{
  "type": "Feature",
  "properties": {
    "gn:admin1_code":"21.0",
    "gn:asciiname":"Topolyne",
    "gn:country_code":"UA",
    "gn:dem":162,
    "gn:feature_class":"P",
    "gn:feature_code":"PPL",
    "gn:name":"Topolyne",
    "gn:population":0,
    "gn:timezone":"Europe/Kiev",
    "iso:country":"UA",
    "name:ukr_x_preferred":[
        "Topolyne"
    ],
    "name:ukr_x_variant":[
        "\u0422\u043e\u043f\u043e\u043b\u0438\u043d\u0435"
    ],
    "name:und_x_variant":[
        "Topolinoye"
    ],
    "wof:name":"Topolyne",
    "wof:placetype":"locality"
},
  "geometry": {"coordinates":[33.40924,51.11898],"type":"Point"}
}