{
  "type": "Feature",
  "properties": {
    "gn:admin1_code":"9.0",
    "gn:asciiname":"Derevyannoye",
    "gn:country_code":"UA",
    "gn:dem":295,
    "gn:feature_class":"P",
    "gn:feature_code":"PPL",
    "gn:name":"Derevyannoye",
    "gn:population":0,
    "gn:timezone":"Europe/Kiev",
    "iso:country":"UA",
    "name:und_x_variant":[
        "Derevyane",
        "Derevyannoye"
    ],
    "wof:name":"Derevyannoye",
    "wof:placetype":"locality"
},
  "geometry": {"coordinates":[26.83761,48.70918],"type":"Point"}
}