{
  "type": "Feature",
  "properties": {
    "gn:admin1_code":"19.0",
    "gn:asciiname":"Shostakiv",
    "gn:country_code":"UA",
    "gn:dem":198,
    "gn:feature_class":"P",
    "gn:feature_code":"PPL",
    "gn:name":"Shostakiv",
    "gn:population":0,
    "gn:timezone":"Europe/Kiev",
    "iso:country":"UA",
    "name:ukr_x_preferred":[
        "Shostakiv"
    ],
    "name:ukr_x_variant":[
        "\u0428\u043e\u0441\u0442\u0430\u043a\u0456\u0432"
    ],
    "wof:name":"Shostakiv",
    "wof:placetype":"locality"
},
  "geometry": {"coordinates":[25.9912,50.64634],"type":"Point"}
}