{
  "type": "Feature",
  "properties": {
    "gn:admin1_code":"4.0",
    "gn:asciiname":"Pravoberezhne",
    "gn:country_code":"UA",
    "gn:dem":109,
    "gn:feature_class":"P",
    "gn:feature_code":"PPL",
    "gn:name":"Pravoberezhne",
    "gn:population":0,
    "gn:timezone":"Europe/Kiev",
    "iso:country":"UA",
    "name:ukr_x_preferred":[
        "Pravoberezhne"
    ],
    "name:ukr_x_variant":[
        "\u041f\u0440\u0430\u0432\u043e\u0431\u0435\u0440\u0435\u0436\u043d\u0435"
    ],
    "wof:name":"Pravoberezhne",
    "wof:placetype":"locality"
},
  "geometry": {"coordinates":[34.19621,48.73725],"type":"Point"}
}