{
  "type": "Feature",
  "properties": {
    "gn:admin1_code":"22.0",
    "gn:asciiname":"Draganovka",
    "gn:country_code":"UA",
    "gn:dem":321,
    "gn:feature_class":"P",
    "gn:feature_code":"PPL",
    "gn:name":"Draganovka",
    "gn:population":0,
    "gn:timezone":"Europe/Kiev",
    "iso:country":"UA",
    "name:und_x_variant":[
        "Drahanivka",
        "Draganovka"
    ],
    "wof:name":"Draganovka",
    "wof:placetype":"locality"
},
  "geometry": {"coordinates":[25.5145,49.50833],"type":"Point"}
}