{
  "type": "Feature",
  "properties": {
    "gn:admin1_code":"7.0",
    "gn:asciiname":"Duvanka",
    "gn:country_code":"UA",
    "gn:dem":170,
    "gn:feature_class":"P",
    "gn:feature_code":"PPL",
    "gn:name":"Duvanka",
    "gn:population":0,
    "gn:timezone":"Europe/Kiev",
    "iso:country":"UA",
    "name:ukr_x_preferred":[
        "Duvanka"
    ],
    "name:ukr_x_variant":[
        "\u0414\u0443\u0432\u0430\u043d\u043a\u0430"
    ],
    "wof:name":"Duvanka",
    "wof:placetype":"locality"
},
  "geometry": {"coordinates":[36.05376,50.3044],"type":"Point"}
}