{
  "type": "Feature",
  "properties": {
    "gn:admin1_code":"25.0",
    "gn:asciiname":"Chernyk",
    "gn:country_code":"UA",
    "gn:dem":273,
    "gn:feature_class":"P",
    "gn:feature_code":"PPL",
    "gn:name":"Chernyk",
    "gn:population":0,
    "gn:timezone":"Europe/Uzhgorod",
    "iso:country":"UA",
    "name:ukr_x_preferred":[
        "Chernyk"
    ],
    "name:ukr_x_variant":[
        "\u0427\u0435\u0440\u043d\u0438\u043a"
    ],
    "name:und_x_variant":[
        "Chernik"
    ],
    "wof:name":"Chernyk",
    "wof:placetype":"locality"
},
  "geometry": {"coordinates":[23.01096,48.52726],"type":"Point"}
}