{
  "type": "Feature",
  "properties": {
    "gn:admin1_code":"15.0",
    "gn:asciiname":"Jalynkuvate",
    "gn:country_code":"UA",
    "gn:dem":785,
    "gn:feature_class":"P",
    "gn:feature_code":"PPL",
    "gn:name":"Jalynkuvate",
    "gn:population":0,
    "gn:timezone":"Europe/Kiev",
    "iso:country":"UA",
    "name:ukr_x_preferred":[
        "Yalynkuvate"
    ],
    "name:ukr_x_variant":[
        "\u042f\u043b\u0438\u043d\u043a\u0443\u0432\u0430\u0442\u0435"
    ],
    "name:und_x_variant":[
        "Yelenkovate",
        "Yalinkovataya",
        "Yalinkovatoye"
    ],
    "wof:name":"Jalynkuvate",
    "wof:placetype":"locality"
},
  "geometry": {"coordinates":[23.46954,48.73887],"type":"Point"}
}