{
  "type": "Feature",
  "properties": {
    "gn:admin1_code":"21.0",
    "gn:asciiname":"Malushyne",
    "gn:country_code":"UA",
    "gn:dem":183,
    "gn:feature_class":"P",
    "gn:feature_code":"PPL",
    "gn:name":"Malushyne",
    "gn:population":0,
    "gn:timezone":"Europe/Kiev",
    "iso:country":"UA",
    "name:ukr_x_preferred":[
        "Malushyne"
    ],
    "name:ukr_x_variant":[
        "\u041c\u0430\u043b\u0443\u0448\u0438\u043d\u0435"
    ],
    "name:und_x_variant":[
        "Malushino",
        "Milushino"
    ],
    "wof:name":"Malushyne",
    "wof:placetype":"locality"
},
  "geometry": {"coordinates":[34.22287,51.48493],"type":"Point"}
}