{
  "type": "Feature",
  "properties": {
    "gn:admin1_code":"4.0",
    "gn:asciiname":"Homel's'ke",
    "gn:country_code":"UA",
    "gn:dem":143,
    "gn:feature_class":"P",
    "gn:feature_code":"PPL",
    "gn:name":"Homel\u2019s\u2019ke",
    "gn:population":0,
    "gn:timezone":"Europe/Kiev",
    "iso:country":"UA",
    "name:rus_x_preferred":[
        "Gomel\u2019skoye"
    ],
    "name:rus_x_variant":[
        "\u0413\u043e\u043c\u0435\u043b\u044c\u0441\u043a\u043e\u0435"
    ],
    "name:ukr_x_preferred":[
        "Homel\u2019s\u2019ke"
    ],
    "name:ukr_x_variant":[
        "\u0413\u043e\u043c\u0435\u043b\u044c\u0441\u044c\u043a\u0435"
    ],
    "wof:name":"Homel's'ke",
    "wof:placetype":"locality"
},
  "geometry": {"coordinates":[33.57236,48.2396],"type":"Point"}
}