{
  "type": "Feature",
  "properties": {
    "iso:country":"UA",
    "name:deu_x_preferred":[
        "Poltawka"
    ],
    "name:eng_x_preferred":[
        "Poltavka"
    ],
    "name:lav_x_preferred":[
        "Poltavka"
    ],
    "name:pol_x_preferred":[
        "Nata\u0142ka Po\u0142tawka"
    ],
    "name:ron_x_preferred":[
        "Poltavka"
    ],
    "name:rus_x_preferred":[
        "\u041d\u0430\u0442\u0430\u043b\u043a\u0430 \u041f\u043e\u043b\u0442\u0430\u0432\u043a\u0430"
    ],
    "name:rus_x_variant":[
        "\u041f\u043e\u043b\u0442\u0430\u0432\u043a\u0430"
    ],
    "name:ukr_x_preferred":[
        "\u041d\u0430\u0442\u0430\u043b\u043a\u0430 \u041f\u043e\u043b\u0442\u0430\u0432\u043a\u0430"
    ],
    "name:ukr_x_variant":[
        "\u041f\u043e\u043b\u0442\u0430\u0432\u043a\u0430"
    ],
    "name:und_x_variant":[
        "Sanzharovka"
    ],
    "name:zho_x_preferred":[
        "\u6ce2\u723e\u5854\u592b\u5361"
    ],
    "qs:a0":"\u0423\u043a\u0440\u0430\u0457\u043d\u0430",
    "qs:a1":"*\u0417\u0430\u043f\u043e\u0440\u0456\u0437\u044c\u043a\u0430",
    "qs:a1_alt":"Zaporiz'ka",
    "qs:a1r":"0",
    "qs:a2":"\u0413\u0443\u043b\u044f\u0439\u043f\u0456\u043b\u044c\u0441\u044c\u043a\u0438\u0439",
    "qs:a2_alt":"Huliaipil's'kyi",
    "qs:adm0":"\u0423\u043a\u0440\u0430\u0457\u043d\u0430",
    "qs:la_lc":"*",
    "qs:level":"locality",
    "qs:loc":"\u041f\u043e\u043b\u0442\u0430\u0432\u043a\u0430",
    "qs:loc_alt":"Poltavka",
    "qs:pop":0,
    "qs:type":"buffered point",
    "wd:wordcount":751,
    "wof:name":"\u041f\u043e\u043b\u0442\u0430\u0432\u043a\u0430",
    "wof:placetype":"locality"
},
  "geometry": {"coordinates":[36.48846,47.713072],"type":"Point"}
}