{
  "type": "Feature",
  "properties": {
    "iso:country":"UA",
    "name:deu_x_preferred":[
        "Ridkiwzi"
    ],
    "name:eng_x_preferred":[
        "Ridkivtsi"
    ],
    "name:hye_x_preferred":[
        "\u054c\u0565\u0564\u056f\u0578\u057e\u0581\u056b"
    ],
    "name:pol_x_preferred":[
        "Ridkiwci"
    ],
    "name:ron_x_preferred":[
        "Rarancea"
    ],
    "name:rus_x_preferred":[
        "\u0420\u0435\u0434\u043a\u043e\u0432\u0446\u044b"
    ],
    "name:sco_x_preferred":[
        "Ridkivtsi"
    ],
    "name:ukr_x_preferred":[
        "\u0420\u0456\u0434\u043a\u0456\u0432\u0446\u0456"
    ],
    "name:zho_x_preferred":[
        "\u91cc\u5fb7\u57fa\u592b\u9f4a"
    ],
    "qs:a0":"\u0423\u043a\u0440\u0430\u0457\u043d\u0430",
    "qs:a1":"*\u0427\u0435\u0440\u043d\u0456\u0432\u0435\u0446\u044c\u043a\u0430",
    "qs:a1_alt":"Chernivets'ka",
    "qs:a1r":"0",
    "qs:a2":"\u041d\u043e\u0432\u043e\u0441\u0435\u043b\u0438\u0446\u044c\u043a\u0438\u0439",
    "qs:a2_alt":"Novoselyts'kyi",
    "qs:adm0":"\u0423\u043a\u0440\u0430\u0457\u043d\u0430",
    "qs:la_lc":"*",
    "qs:level":"locality",
    "qs:loc":"\u0420\u0456\u0434\u043a\u0456\u0432\u0446\u0456",
    "qs:loc_alt":"Ridkivtsi",
    "qs:pop":0,
    "qs:type":"buffered point",
    "wd:wordcount":34,
    "wof:name":"\u0420\u0456\u0434\u043a\u0456\u0432\u0446\u0456",
    "wof:placetype":"locality"
},
  "geometry": {"coordinates":[26.060012,48.336571],"type":"Point"}
}