{
  "type": "Feature",
  "properties": {
    "gn:gn_country":"UA",
    "gn:gn_fcode":"PPL",
    "gn:gn_pop":4559,
    "gn:population":4559,
    "iso:country":"UA",
    "name:ara_x_preferred":[
        "\u062f\u0648\u0641\u0628\u064a\u0634"
    ],
    "name:deu_x_preferred":[
        "Dowbysch"
    ],
    "name:eng_x_preferred":[
        "Dovbysh"
    ],
    "name:fra_x_preferred":[
        "Dovbych"
    ],
    "name:pol_x_preferred":[
        "Do\u0142bysz"
    ],
    "name:ron_x_preferred":[
        "Dovb\u00ee\u0219"
    ],
    "name:rus_x_preferred":[
        "\u0414\u043e\u0432\u0431\u0438\u0448"
    ],
    "name:sah_x_preferred":[
        "\u0414\u043e\u0432\u0431\u044b\u0448"
    ],
    "name:ukr_x_preferred":[
        "\u0414\u043e\u0432\u0431\u0438\u0448"
    ],
    "name:unk_x_variant":[
        "Markhlevsk"
    ],
    "name:zho_x_preferred":[
        "\u591a\u592b\u6bd4\u4ec0"
    ],
    "qs_pg:aaroncc":"UA",
    "qs_pg:gn_country":"UA",
    "qs_pg:gn_fcode":"PPL",
    "qs_pg:gn_pop":4559,
    "qs_pg:name":"Dovbysh",
    "qs_pg:name_adm0":"Ukraine",
    "qs_pg:name_adm1":"Zhytomyrs\u00b4ka Oblast\u00b4",
    "qs_pg:photos_9r":0,
    "qs_pg:photos_sr":0,
    "qs_pg:pop_sr":4,
    "qs_pg:qs_pg_placetype":"locality",
    "qs_pg:qs_pg_placetype_gp":"Town",
    "qs_pg:woe_adm0":23424976,
    "woe:adm0_id":23424976,
    "woe:name_adm0":"Ukraine",
    "woe:name_adm1":"Zhytomyrs\u00b4ka Oblast\u00b4",
    "woe:placetype":"Town",
    "wof:name":"Dovbysh",
    "wof:placetype":"locality",
    "wof:population":4559
},
  "geometry": {"coordinates":[27.98742,50.37332],"type":"Point"}
}