{
  "type": "Feature",
  "properties": {
    "gn:admin1_code":"26.0",
    "gn:asciiname":"Novo Grigorevka",
    "gn:country_code":"UA",
    "gn:dem":187,
    "gn:feature_class":"P",
    "gn:feature_code":"PPL",
    "gn:name":"Novo Grigorevka",
    "gn:population":0,
    "gn:timezone":"Europe/Zaporozhye",
    "iso:country":"UA",
    "name:und_x_variant":[
        "Novaya Grigor\u2019yevka",
        "Novo-Grigor\u2019yevka"
    ],
    "wof:name":"Novo Grigorevka",
    "wof:placetype":"locality"
},
  "geometry": {"coordinates":[36.28333,47.33333],"type":"Point"}
}