{
  "type": "Feature",
  "properties": {
    "gn:admin1_code":"19.0",
    "gn:asciiname":"Bronnyky",
    "gn:country_code":"UA",
    "gn:dem":188,
    "gn:feature_class":"P",
    "gn:feature_code":"PPL",
    "gn:name":"Bronnyky",
    "gn:population":0,
    "gn:timezone":"Europe/Kiev",
    "iso:country":"UA",
    "name:ukr_x_preferred":[
        "Bronnyky"
    ],
    "name:ukr_x_variant":[
        "\u0411\u0440\u043e\u043d\u043d\u0438\u043a\u0438"
    ],
    "name:und_x_variant":[
        "Broniki",
        "Bronniki"
    ],
    "wof:name":"Bronnyky",
    "wof:placetype":"locality"
},
  "geometry": {"coordinates":[26.08987,50.70585],"type":"Point"}
}