{
  "type": "Feature",
  "properties": {
    "gn:admin1_code":"15.0",
    "gn:asciiname":"Monastyr-Lishnyans'kyy",
    "gn:country_code":"UA",
    "gn:dem":317,
    "gn:feature_class":"P",
    "gn:feature_code":"PPL",
    "gn:name":"Monastyr-Lishnyans\u2019kyy",
    "gn:population":0,
    "gn:timezone":"Europe/Kiev",
    "iso:country":"UA",
    "name:rus_x_preferred":[
        "Monastyr\u2019-Lishnyanskiy"
    ],
    "name:rus_x_variant":[
        "\u041c\u043e\u043d\u0430\u0441\u0442\u044b\u0440\u044c-\u041b\u0438\u0448\u043d\u044f\u043d\u0441\u043a\u0438\u0439"
    ],
    "name:ukr_x_preferred":[
        "Monastyr-Lishnyans\u2019kyy"
    ],
    "name:ukr_x_variant":[
        "\u041c\u043e\u043d\u0430\u0441\u0442\u0438\u0440-\u041b\u0456\u0448\u043d\u044f\u043d\u0441\u044c\u043a\u0438\u0439"
    ],
    "name:und_x_variant":[
        "Manaster Lishnyan\u2019ski",
        "Monaster Lishnyanskiy"
    ],
    "wof:name":"Monastyr-Lishnyans'kyy",
    "wof:placetype":"locality"
},
  "geometry": {"coordinates":[23.43119,49.38348],"type":"Point"}
}