{
  "type": "Feature",
  "properties": {
    "gn:admin1_code":"23.0",
    "gn:asciiname":"Kitay Gorod",
    "gn:country_code":"UA",
    "gn:dem":202,
    "gn:feature_class":"P",
    "gn:feature_code":"PPL",
    "gn:name":"Kitay Gorod",
    "gn:population":0,
    "gn:timezone":"Europe/Kiev",
    "iso:country":"UA",
    "wof:name":"Kitay Gorod",
    "wof:placetype":"locality"
},
  "geometry": {"coordinates":[29.00932,48.48598],"type":"Point"}
}