{
  "type": "Feature",
  "properties": {
    "gn:admin1_code":"18.0",
    "gn:asciiname":"Zmazhyne",
    "gn:country_code":"UA",
    "gn:dem":156,
    "gn:feature_class":"P",
    "gn:feature_code":"PPL",
    "gn:name":"Zmazhyne",
    "gn:population":0,
    "gn:timezone":"Europe/Kiev",
    "iso:country":"UA",
    "name:ukr_x_preferred":[
        "Zmazhyne"
    ],
    "name:ukr_x_variant":[
        "\u0417\u043c\u0430\u0436\u0438\u043d\u0435"
    ],
    "wof:name":"Zmazhyne",
    "wof:placetype":"locality"
},
  "geometry": {"coordinates":[33.91402,50.46942],"type":"Point"}
}