{
  "type": "Feature",
  "properties": {
    "gn:admin1_code":"22.0",
    "gn:asciiname":"Butsyki",
    "gn:country_code":"UA",
    "gn:dem":296,
    "gn:feature_class":"P",
    "gn:feature_code":"PPL",
    "gn:name":"Butsyki",
    "gn:population":0,
    "gn:timezone":"Europe/Kiev",
    "iso:country":"UA",
    "wof:name":"Butsyki",
    "wof:placetype":"locality"
},
  "geometry": {"coordinates":[26.02541,49.32176],"type":"Point"}
}