{
  "type": "Feature",
  "properties": {
    "gn:admin1_code":"7.0",
    "gn:asciiname":"Nasten'kivka",
    "gn:country_code":"UA",
    "gn:dem":178,
    "gn:feature_class":"P",
    "gn:feature_code":"PPL",
    "gn:name":"Nasten\u2019kivka",
    "gn:population":0,
    "gn:timezone":"Europe/Kiev",
    "iso:country":"UA",
    "name:ukr_x_preferred":[
        "Nasten\u2019kivka"
    ],
    "name:ukr_x_variant":[
        "\u041d\u0430\u0441\u0442\u0435\u043d\u044c\u043a\u0456\u0432\u043a\u0430"
    ],
    "wof:name":"Nasten'kivka",
    "wof:placetype":"locality"
},
  "geometry": {"coordinates":[35.2344,49.95077],"type":"Point"}
}