{
  "type": "Feature",
  "properties": {
    "gn:admin1_code":"10.0",
    "gn:asciiname":"Annovka",
    "gn:country_code":"UA",
    "gn:dem":92,
    "gn:feature_class":"P",
    "gn:feature_code":"PPL",
    "gn:name":"Annovka",
    "gn:population":0,
    "gn:timezone":"Europe/Kiev",
    "iso:country":"UA",
    "name:und_x_variant":[
        "Gannovka",
        "Annovka"
    ],
    "wof:name":"Annovka",
    "wof:placetype":"locality"
},
  "geometry": {"coordinates":[33.10492,48.15923],"type":"Point"}
}