{
  "type": "Feature",
  "properties": {
    "gn:admin1_code":"14.0",
    "gn:asciiname":"Arapivka",
    "gn:country_code":"UA",
    "gn:dem":108,
    "gn:feature_class":"P",
    "gn:feature_code":"PPL",
    "gn:name":"Arapivka",
    "gn:population":0,
    "gn:timezone":"Europe/Zaporozhye",
    "iso:country":"UA",
    "name:ukr_x_preferred":[
        "Arapivka"
    ],
    "name:ukr_x_variant":[
        "\u0410\u0440\u0430\u043f\u0456\u0432\u043a\u0430"
    ],
    "name:und_x_variant":[
        "Arabovka",
        "Arapovka"
    ],
    "wof:name":"Arapivka",
    "wof:placetype":"locality"
},
  "geometry": {"coordinates":[38.03645,49.73944],"type":"Point"}
}