{
  "type": "Feature",
  "properties": {
    "gn:admin1_code":"18.0",
    "gn:asciiname":"Sokolovshchina",
    "gn:country_code":"UA",
    "gn:dem":141,
    "gn:feature_class":"P",
    "gn:feature_code":"PPL",
    "gn:name":"Sokolovshchina",
    "gn:population":0,
    "gn:timezone":"Europe/Kiev",
    "iso:country":"UA",
    "name:rus_x_preferred":[
        "\u0421\u043e\u043a\u043e\u043b\u043e\u0432\u0449\u0438\u043d\u0430"
    ],
    "wof:name":"Sokolovshchina",
    "wof:placetype":"locality"
},
  "geometry": {"coordinates":[34.37736,49.74995],"type":"Point"}
}