{
  "type": "Feature",
  "properties": {
    "gn:admin1_code":"19.0",
    "gn:asciiname":"Semyduby",
    "gn:country_code":"UA",
    "gn:dem":209,
    "gn:feature_class":"P",
    "gn:feature_code":"PPL",
    "gn:name":"Semyduby",
    "gn:population":0,
    "gn:timezone":"Europe/Kiev",
    "iso:country":"UA",
    "name:ukr_x_preferred":[
        "Semyduby"
    ],
    "name:ukr_x_variant":[
        "\u0421\u0435\u043c\u0438\u0434\u0443\u0431\u0438"
    ],
    "name:und_x_variant":[
        "Semiduby"
    ],
    "wof:name":"Semyduby",
    "wof:placetype":"locality"
},
  "geometry": {"coordinates":[25.80778,50.3451],"type":"Point"}
}