{
  "type": "Feature",
  "properties": {
    "gn:admin1_code":"3.0",
    "gn:asciiname":"Kazintsy",
    "gn:country_code":"UA",
    "gn:dem":249,
    "gn:feature_class":"P",
    "gn:feature_code":"PPL",
    "gn:name":"Kazintsy",
    "gn:population":0,
    "gn:timezone":"Europe/Kiev",
    "iso:country":"UA",
    "name:und_x_variant":[
        "Kazyn\u2019tse"
    ],
    "wof:name":"Kazintsy",
    "wof:placetype":"locality"
},
  "geometry": {"coordinates":[25.61667000000001,48.58333],"type":"Point"}
}