{
  "type": "Feature",
  "properties": {
    "gn:admin1_code":"21.0",
    "gn:asciiname":"Bilohalytsya",
    "gn:country_code":"UA",
    "gn:dem":134,
    "gn:feature_class":"P",
    "gn:feature_code":"PPL",
    "gn:name":"Bilohalytsya",
    "gn:population":0,
    "gn:timezone":"Europe/Kiev",
    "iso:country":"UA",
    "name:ukr_x_preferred":[
        "Bilohalytsya"
    ],
    "name:ukr_x_variant":[
        "\u0411\u0456\u043b\u043e\u0433\u0430\u043b\u0438\u0446\u044f"
    ],
    "name:und_x_variant":[
        "Belogalitsa"
    ],
    "wof:name":"Bilohalytsya",
    "wof:placetype":"locality"
},
  "geometry": {"coordinates":[33.94514,51.27588],"type":"Point"}
}