{
  "type": "Feature",
  "properties": {
    "gn:admin1_code":"13.0",
    "gn:asciiname":"Rokopicy",
    "gn:country_code":"UA",
    "gn:dem":166,
    "gn:feature_class":"P",
    "gn:feature_code":"PPL",
    "gn:name":"Rokopicy",
    "gn:population":0,
    "gn:timezone":"Europe/Kiev",
    "iso:country":"UA",
    "name:rus_x_preferred":[
        "\u0420\u0430\u0441\u043a\u043e\u043f\u0430\u043d\u0446\u044b"
    ],
    "wof:name":"Rokopicy",
    "wof:placetype":"locality"
},
  "geometry": {"coordinates":[30.83382000000001,49.53836],"type":"Point"}
}