{
  "type": "Feature",
  "properties": {
    "gn:admin1_code":"26.0",
    "gn:asciiname":"Rivnopillya",
    "gn:country_code":"UA",
    "gn:dem":142,
    "gn:feature_class":"P",
    "gn:feature_code":"PPL",
    "gn:name":"Rivnopillya",
    "gn:population":0,
    "gn:timezone":"Europe/Zaporozhye",
    "iso:country":"UA",
    "name:ukr_x_preferred":[
        "Rivnopillya"
    ],
    "name:ukr_x_variant":[
        "\u0420\u0456\u0432\u043d\u043e\u043f\u0456\u043b\u043b\u044f"
    ],
    "name:und_x_variant":[
        "Ravnopol\u2019ye"
    ],
    "wof:name":"Rivnopillya",
    "wof:placetype":"locality"
},
  "geometry": {"coordinates":[36.3184,47.74531],"type":"Point"}
}