{
  "type": "Feature",
  "properties": {
    "gn:admin1_code":"26.0",
    "gn:asciiname":"Yuvileyne",
    "gn:country_code":"UA",
    "gn:dem":58,
    "gn:feature_class":"P",
    "gn:feature_code":"PPL",
    "gn:name":"Yuvileyne",
    "gn:population":0,
    "gn:timezone":"Europe/Zaporozhye",
    "iso:country":"UA",
    "name:ukr_x_preferred":[
        "Yuvileyne"
    ],
    "name:ukr_x_variant":[
        "\u042e\u0432\u0456\u043b\u0435\u0439\u043d\u0435"
    ],
    "name:und_x_variant":[
        "Yubileynoye"
    ],
    "wof:name":"Yuvileyne",
    "wof:placetype":"locality"
},
  "geometry": {"coordinates":[35.69836,47.0264],"type":"Point"}
}