{
  "type": "Feature",
  "properties": {
    "iso:country":"UA",
    "name:eng_x_preferred":[
        "Bogatoye"
    ],
    "name:rus_x_historical":[
        "\u0411\u0430\u0445\u0447\u0438\u0301-\u042d\u043b\u0438\u0301"
    ],
    "name:rus_x_preferred":[
        "\u0411\u0430\u0445\u0447\u0438\u0301-\u042d\u043b\u0438\u0301"
    ],
    "name:rus_x_variant":[
        "\u0411\u043e\u0433\u0430\u0442\u043e\u0435"
    ],
    "name:ukr_x_preferred":[
        "\u0411\u0430\u0433\u0430\u0442\u0435"
    ],
    "qs:a0":"\u0423\u043a\u0440\u0430\u0457\u043d\u0430",
    "qs:a1":"*\u041a\u0440\u0438\u043c",
    "qs:a1_alt":"Krym",
    "qs:a1r":"0",
    "qs:a2":"\u0411\u0456\u043b\u043e\u0433\u0456\u0440\u0441\u044c\u043a\u0438\u0439",
    "qs:a2_alt":"Bilohirs'kyi",
    "qs:adm0":"\u0423\u043a\u0440\u0430\u0457\u043d\u0430",
    "qs:la_lc":"*",
    "qs:level":"locality",
    "qs:loc":"\u0411\u0430\u0433\u0430\u0442\u0435",
    "qs:loc_alt":"Bahate",
    "qs:pop":0,
    "qs:type":"buffered point",
    "wof:name":"\u0411\u0430\u0433\u0430\u0442\u0435",
    "wof:placetype":"locality"
},
  "geometry": {"coordinates":[34.767822,45.029802],"type":"Point"}
}