{
  "type": "Feature",
  "properties": {
    "gn:population":12766,
    "iso:country":"UA",
    "name:arm_x_preferred":[
        "\u0544\u0565\u0576\u0561"
    ],
    "name:bel_x_variant":[
        "\u041c\u0435\u043d\u0430"
    ],
    "name:chi_x_preferred":[
        "\u6885\u7d0d"
    ],
    "name:crh_x_preferred":[
        "Mena"
    ],
    "name:deu_x_preferred":[
        "Mena"
    ],
    "name:dut_x_preferred":[
        "Mena"
    ],
    "name:eng_x_preferred":[
        "Mena"
    ],
    "name:fas_x_preferred":[
        "\u0645\u0646\u0627\u060c \u0627\u0648\u06a9\u0631\u0627\u06cc\u0646"
    ],
    "name:fin_x_preferred":[
        "Mena"
    ],
    "name:fra_x_preferred":[
        "Mena"
    ],
    "name:fre_x_preferred":[
        "Mena"
    ],
    "name:geo_x_preferred":[
        "\u10db\u10d4\u10dc\u10d0"
    ],
    "name:ger_x_preferred":[
        "Mena"
    ],
    "name:heb_x_preferred":[
        "\u05de\u05e0\u05d4"
    ],
    "name:hsb_x_preferred":[
        "Mena"
    ],
    "name:hye_x_preferred":[
        "\u0544\u0565\u0576\u0561"
    ],
    "name:ita_x_preferred":[
        "Mena"
    ],
    "name:kat_x_preferred":[
        "\u10db\u10d4\u10dc\u10d0"
    ],
    "name:kaz_x_preferred":[
        "\u041c\u0435\u043d\u0430"
    ],
    "name:lav_x_preferred":[
        "Mena"
    ],
    "name:nno_x_preferred":[
        "Mena i Ukraina"
    ],
    "name:per_x_preferred":[
        "\u0645\u0646\u0627\u060c \u0627\u0648\u06a9\u0631\u0627\u06cc\u0646"
    ],
    "name:pol_x_preferred":[
        "Mena"
    ],
    "name:ron_x_preferred":[
        "Mena"
    ],
    "name:rum_x_preferred":[
        "Mena"
    ],
    "name:rus_x_preferred":[
        "\u041c\u0435\u043d\u0430"
    ],
    "name:sah_x_preferred":[
        "\u041c\u0435\u043d\u0430"
    ],
    "name:spa_x_preferred":[
        "Mena"
    ],
    "name:tat_x_preferred":[
        "\u041c\u0435\u043d\u0430"
    ],
    "name:ukr_x_preferred":[
        "\u041c\u0435\u043d\u0430"
    ],
    "name:unk_x_variant":[
        "Mena"
    ],
    "name:zho_x_preferred":[
        "\u6885\u7eb3"
    ],
    "qs:a0":"\u0423\u043a\u0440\u0430\u0457\u043d\u0430",
    "qs:a1":"*\u0427\u0435\u0440\u043d\u0456\u0433\u0456\u0432\u0441\u044c\u043a\u0430",
    "qs:a1_alt":"Chernihivs'ka",
    "qs:a1r":"0",
    "qs:a2":"\u041c\u0435\u043d\u0441\u044c\u043a\u0438\u0439",
    "qs:a2_alt":"Mens'kyi",
    "qs:adm0":"\u0423\u043a\u0440\u0430\u0457\u043d\u0430",
    "qs:la_lc":"*",
    "qs:level":"locality",
    "qs:loc":"\u041c\u0435\u043d\u0430",
    "qs:loc_alt":"Mena",
    "qs:pop":0,
    "qs:type":"buffered point",
    "wd:wordcount":37,
    "wof:name":"\u041c\u0435\u043d\u0430",
    "wof:placetype":"locality",
    "wof:population":12766
},
  "geometry": {"coordinates":[32.209857,51.519959],"type":"Point"}
}