{
  "type": "Feature",
  "properties": {
    "gn:admin1_code":"5.0",
    "gn:asciiname":"Hirne",
    "gn:country_code":"UA",
    "gn:dem":273,
    "gn:feature_class":"P",
    "gn:feature_code":"PPL",
    "gn:name":"Hirne",
    "gn:population":0,
    "gn:timezone":"Europe/Kiev",
    "iso:country":"UA",
    "name:bel_x_preferred":[
        "\u0413\u043e\u0440\u043d\u0430\u0435"
    ],
    "name:deu_x_preferred":[
        "Hirne"
    ],
    "name:hye_x_preferred":[
        "\u0533\u0578\u0580\u0576\u0578\u0565"
    ],
    "name:kaz_x_preferred":[
        "\u0413\u043e\u0440\u043d\u043e\u0435"
    ],
    "name:rus_x_preferred":[
        "\u0413\u043e\u0440\u043d\u043e\u0435"
    ],
    "name:ukr_x_preferred":[
        "Hirne"
    ],
    "name:ukr_x_variant":[
        "\u0413\u0456\u0440\u043d\u0435"
    ],
    "wof:name":"Hirne",
    "wof:placetype":"locality"
},
  "geometry": {"coordinates":[38.54403,48.0345],"type":"Point"}
}