{
  "type": "Feature",
  "properties": {
    "gn:admin1_code":"11.0",
    "gn:admin2_code":"705800",
    "gn:admin3_code":"11152903.0",
    "gn:asciiname":"Sofiyevka",
    "gn:country_code":"UA",
    "gn:dem":18,
    "gn:elevation":"15.0",
    "gn:feature_class":"P",
    "gn:feature_code":"PPL",
    "gn:name":"Sofiyevka",
    "gn:population":10,
    "gn:timezone":"Europe/Simferopol",
    "iso:country":"UA",
    "name:eng_x_preferred":[
        "Sofiyevka"
    ],
    "name:rus_x_preferred":[
        "\u0421\u043e\u0444\u0438\u0435\u0432\u043a\u0430"
    ],
    "name:ukr_x_preferred":[
        "\u0421\u043e\u0444\u0456\u0457\u0432\u043a\u0430"
    ],
    "wof:name":"Sofiyevka",
    "wof:placetype":"locality",
    "wof:population":10
},
  "geometry": {"coordinates":[35.12475,45.27364],"type":"Point"}
}