{
  "type": "Feature",
  "properties": {
    "gn:admin1_code":"6.0",
    "gn:asciiname":"Zelenitsa",
    "gn:country_code":"UA",
    "gn:dem":650,
    "gn:feature_class":"P",
    "gn:feature_code":"PPL",
    "gn:name":"Zelenitsa",
    "gn:population":0,
    "gn:timezone":"Europe/Kiev",
    "iso:country":"UA",
    "wof:name":"Zelenitsa",
    "wof:placetype":"locality"
},
  "geometry": {"coordinates":[24.38613,48.51421],"type":"Point"}
}