{
  "type": "Feature",
  "properties": {
    "gn:country":"UA",
    "gn:fcode":"PPL",
    "gn:population":4070,
    "iso:country":"UA",
    "name:ceb_x_preferred":[
        "Dmytrivka"
    ],
    "name:deu_x_preferred":[
        "Dmytriwka"
    ],
    "name:eng_x_preferred":[
        "Dmytrivka"
    ],
    "name:est_x_preferred":[
        "Dm\u00f5trivka"
    ],
    "name:hye_x_preferred":[
        "\u0534\u0574\u056b\u057f\u0580\u0578\u057e\u056f\u0561"
    ],
    "name:rus_x_preferred":[
        "\u0414\u043c\u0438\u0442\u0440\u043e\u0432\u043a\u0430"
    ],
    "name:spa_x_preferred":[
        "Dmytrivka"
    ],
    "name:ukr_x_preferred":[
        "\u0414\u043c\u0438\u0442\u0440\u0456\u0432\u043a\u0430"
    ],
    "name:und_x_variant":[
        "Dmitrovka"
    ],
    "qs_pg:aaroncc":"UA",
    "qs_pg:gn_country":"UA",
    "qs_pg:gn_fcode":"PPL",
    "qs_pg:gn_pop":4070,
    "qs_pg:name":"Dmytrivka",
    "qs_pg:photos_9r":0,
    "qs_pg:photos_sr":0,
    "qs_pg:pop_sr":4,
    "qs_pg:qs_pg_placetype":"locality",
    "wof:name":"Dmytrivka",
    "wof:placetype":"locality",
    "wof:population":4070
},
  "geometry": {"coordinates":[32.71645,48.7969],"type":"Point"}
}