{
  "type": "Feature",
  "properties": {
    "gn:admin1_code":"9.0",
    "gn:asciiname":"Holyky",
    "gn:country_code":"UA",
    "gn:dem":218,
    "gn:feature_class":"P",
    "gn:feature_code":"PPL",
    "gn:name":"Holyky",
    "gn:population":0,
    "gn:timezone":"Europe/Kiev",
    "iso:country":"UA",
    "name:ukr_x_preferred":[
        "Holyky"
    ],
    "name:ukr_x_variant":[
        "\u0413\u043e\u043b\u0438\u043a\u0438"
    ],
    "name:und_x_variant":[
        "Goliki"
    ],
    "wof:name":"Holyky",
    "wof:placetype":"locality"
},
  "geometry": {"coordinates":[26.89267000000001,50.21856],"type":"Point"}
}