{
  "type": "Feature",
  "properties": {
    "gn:admin1_code":"7.0",
    "gn:asciiname":"Izyums'ke",
    "gn:country_code":"UA",
    "gn:dem":175,
    "gn:feature_class":"P",
    "gn:feature_code":"PPL",
    "gn:name":"Izyums\u2019ke",
    "gn:population":0,
    "gn:timezone":"Europe/Kiev",
    "iso:country":"UA",
    "name:rus_x_preferred":[
        "Dvadtsatoye Oktyabrya\u2019"
    ],
    "name:ukr_x_preferred":[
        "Izyums\u2019ke"
    ],
    "wof:name":"Izyums'ke",
    "wof:placetype":"locality"
},
  "geometry": {"coordinates":[37.81222,49.2725],"type":"Point"}
}