{
  "type": "Feature",
  "properties": {
    "gn:admin1_code":"7.0",
    "gn:asciiname":"Korsunove",
    "gn:country_code":"UA",
    "gn:dem":173,
    "gn:feature_class":"P",
    "gn:feature_code":"PPL",
    "gn:name":"Korsunove",
    "gn:population":0,
    "gn:timezone":"Europe/Kiev",
    "iso:country":"UA",
    "name:ukr_x_preferred":[
        "Korsunove"
    ],
    "name:ukr_x_variant":[
        "\u041a\u043e\u0440\u0441\u0443\u043d\u043e\u0432\u0435"
    ],
    "wof:name":"Korsunove",
    "wof:placetype":"locality"
},
  "geometry": {"coordinates":[35.49835,49.72433],"type":"Point"}
}