{
  "type": "Feature",
  "properties": {
    "gn:admin1_code":"22.0",
    "gn:asciiname":"Gukalovtsy",
    "gn:country_code":"UA",
    "gn:dem":370,
    "gn:feature_class":"P",
    "gn:feature_code":"PPL",
    "gn:name":"Gukalovtsy",
    "gn:population":0,
    "gn:timezone":"Europe/Kiev",
    "iso:country":"UA",
    "name:und_x_variant":[
        "Gukalovtse",
        "Hukalivtsi",
        "Gukalovtsy"
    ],
    "wof:name":"Gukalovtsy",
    "wof:placetype":"locality"
},
  "geometry": {"coordinates":[25.1706,49.77736],"type":"Point"}
}