{
  "type": "Feature",
  "properties": {
    "gn:admin1_code":"27.0",
    "gn:asciiname":"Tartachok",
    "gn:country_code":"UA",
    "gn:dem":236,
    "gn:feature_class":"P",
    "gn:feature_code":"PPL",
    "gn:name":"Tartachok",
    "gn:population":0,
    "gn:timezone":"Europe/Kiev",
    "iso:country":"UA",
    "name:ukr_x_preferred":[
        "Tartachok"
    ],
    "name:ukr_x_variant":[
        "\u0422\u0430\u0440\u0442\u0430\u0447\u043e\u043a"
    ],
    "wof:name":"Tartachok",
    "wof:placetype":"locality"
},
  "geometry": {"coordinates":[28.2858,50.28707],"type":"Point"}
}