{
  "type": "Feature",
  "properties": {
    "gn:admin1_code":"24.0",
    "gn:asciiname":"Lyudmyl'pil'",
    "gn:country_code":"UA",
    "gn:dem":220,
    "gn:feature_class":"P",
    "gn:feature_code":"PPL",
    "gn:name":"Lyudmyl\u2019pil\u2019",
    "gn:population":0,
    "gn:timezone":"Europe/Kiev",
    "iso:country":"UA",
    "name:rus_x_preferred":[
        "Lyumilpol\u2019"
    ],
    "name:ukr_x_preferred":[
        "Lyudmyl\u2019pil\u2019"
    ],
    "name:ukr_x_variant":[
        "\u041b\u044e\u0434\u043c\u0438\u043b\u044c\u043f\u0456\u043b\u044c"
    ],
    "name:und_x_variant":[
        "Kamel\u00f3wka",
        "Kamelyuvka"
    ],
    "wof:name":"Lyudmyl'pil'",
    "wof:placetype":"locality"
},
  "geometry": {"coordinates":[24.45073,50.87765],"type":"Point"}
}