{
  "type": "Feature",
  "properties": {
    "iso:country":"UA",
    "name:chi_x_preferred":[
        "\u514b\u74e6\u897f\u5229\u592b"
    ],
    "name:crh_x_preferred":[
        "Kvas\u0131liv"
    ],
    "name:deu_x_preferred":[
        "Kwassyliw"
    ],
    "name:dut_x_preferred":[
        "Kvasyliv"
    ],
    "name:eng_x_preferred":[
        "Kvasyliv"
    ],
    "name:fra_x_preferred":[
        "Kvassyliv"
    ],
    "name:fre_x_preferred":[
        "Kvassyliv"
    ],
    "name:ger_x_preferred":[
        "Kwassyliw"
    ],
    "name:hun_x_preferred":[
        "Kvasziliv"
    ],
    "name:pol_x_preferred":[
        "Kwasi\u0142\u00f3w"
    ],
    "name:ron_x_preferred":[
        "Kvas\u00eeliv"
    ],
    "name:rum_x_preferred":[
        "Kvas\u00eeliv"
    ],
    "name:rus_x_preferred":[
        "\u041a\u0432\u0430\u0441\u0438\u043b\u043e\u0432"
    ],
    "name:ukr_x_preferred":[
        "\u041a\u0432\u0430\u0441\u0438\u043b\u0456\u0432"
    ],
    "name:ukr_x_variant":[
        "Kvasyliv"
    ],
    "name:unk_x_variant":[
        "Kvasilov"
    ],
    "name:zho_x_preferred":[
        "\u514b\u74e6\u897f\u5229\u592b"
    ],
    "qs:a0":"\u0423\u043a\u0440\u0430\u0457\u043d\u0430",
    "qs:a1":"*\u0420\u0456\u0432\u043d\u0435\u043d\u0441\u044c\u043a\u0430",
    "qs:a1_alt":"Rivnens'ka",
    "qs:a1r":"0",
    "qs:a2":"\u0420\u0456\u0432\u043d\u0435\u043d\u0441\u044c\u043a\u0438\u0439",
    "qs:a2_alt":"Rivnens'kyi",
    "qs:adm0":"\u0423\u043a\u0440\u0430\u0457\u043d\u0430",
    "qs:la_lc":"*",
    "qs:level":"locality",
    "qs:loc":"\u041a\u0432\u0430\u0441\u0438\u043b\u0456\u0432",
    "qs:loc_alt":"Kvasyliv",
    "qs:pop":0,
    "qs:type":"buffered point",
    "wd:area":4.46,
    "wd:elevation":190.0,
    "wd:population":8117,
    "wd:wordcount":97,
    "wof:name":"\u041a\u0432\u0430\u0441\u0438\u043b\u0456\u0432",
    "wof:placetype":"locality",
    "wof:population":8117
},
  "geometry": {"coordinates":[26.261111,50.557721],"type":"Point"}
}