{
  "type": "Feature",
  "properties": {
    "gn:admin1_code":"16.0",
    "gn:asciiname":"Novobogdanovka",
    "gn:country_code":"UA",
    "gn:dem":38,
    "gn:feature_class":"P",
    "gn:feature_code":"PPL",
    "gn:name":"Novobogdanovka",
    "gn:population":0,
    "gn:timezone":"Europe/Kiev",
    "iso:country":"UA",
    "name:und_x_variant":[
        "Novaya Bogdanovka",
        "Novobogdanovka"
    ],
    "wof:name":"Novobogdanovka",
    "wof:placetype":"locality"
},
  "geometry": {"coordinates":[31.96285,46.87192],"type":"Point"}
}