{
  "type": "Feature",
  "properties": {
    "gn:admin1_code":"18.0",
    "gn:asciiname":"Zapsil's'ke",
    "gn:country_code":"UA",
    "gn:dem":111,
    "gn:feature_class":"P",
    "gn:feature_code":"PPL",
    "gn:name":"Zapsil\u2019s\u2019ke",
    "gn:population":0,
    "gn:timezone":"Europe/Kiev",
    "iso:country":"UA",
    "name:ukr_x_preferred":[
        "Zapsil\u2019s\u2019ke"
    ],
    "name:ukr_x_variant":[
        "\u0417\u0430\u043f\u0441\u0456\u043b\u044c\u0441\u044c\u043a\u0435"
    ],
    "wof:name":"Zapsil's'ke",
    "wof:placetype":"locality"
},
  "geometry": {"coordinates":[34.07483,50.30629],"type":"Point"}
}