{
  "type": "Feature",
  "properties": {
    "gn:population":11017,
    "iso:country":"UA",
    "name:ara_x_preferred":[
        "\u0647\u0631\u064a\u0628\u064a\u0646\u0643\u0627"
    ],
    "name:bel_x_preferred":[
        "\u0413\u0440\u044d\u0431\u0456\u043d\u043a\u0430"
    ],
    "name:bel_x_variant":[
        "\u0413\u0440\u0430\u0431\u0451\u043d\u043a\u0430"
    ],
    "name:ceb_x_preferred":[
        "Hrebinka"
    ],
    "name:crh_x_preferred":[
        "Grebinka"
    ],
    "name:deu_x_preferred":[
        "Hrebinka"
    ],
    "name:eng_x_preferred":[
        "Hrebinka"
    ],
    "name:fas_x_preferred":[
        "\u0647\u0631\u0628\u06cc\u0646\u06a9\u0627"
    ],
    "name:fra_x_preferred":[
        "Hrebinka"
    ],
    "name:hsb_x_preferred":[
        "Hrebinka"
    ],
    "name:hye_x_preferred":[
        "\u0533\u0580\u0565\u0562\u0575\u0578\u0576\u056f\u0561"
    ],
    "name:ita_x_preferred":[
        "Grebinka"
    ],
    "name:jpn_x_preferred":[
        "\u30d5\u30ec\u30d3\u30f3\u30ab"
    ],
    "name:kat_x_preferred":[
        "\u10d2\u10e0\u10d4\u10d1\u10d8\u10dd\u10dc\u10d9\u10d0"
    ],
    "name:lav_x_preferred":[
        "Hrebinka"
    ],
    "name:lit_x_preferred":[
        "Hrebinka"
    ],
    "name:nld_x_preferred":[
        "Hrebinka"
    ],
    "name:nno_x_preferred":[
        "Hrebinka"
    ],
    "name:pol_x_preferred":[
        "Hrebinka"
    ],
    "name:por_x_preferred":[
        "Hrebinka"
    ],
    "name:ron_x_preferred":[
        "Hrebinka"
    ],
    "name:rus_x_preferred":[
        "\u0413\u0440\u0435\u0431\u0451\u043d\u043a\u0430"
    ],
    "name:rus_x_variant":[
        "Greb\u00ebnka",
        "\u0413\u0440\u0435\u0431\u0435\u043d\u043a\u0430",
        "\u0413\u0440\u0435\u0431\u0456\u043d\u043a\u0430"
    ],
    "name:sah_x_preferred":[
        "\u0413\u0440\u0435\u0431\u0438\u043d\u043a\u0430"
    ],
    "name:tat_x_preferred":[
        "\u04ba\u0440\u0435\u0431\u0438\u043d\u043a\u0430"
    ],
    "name:ukr_x_preferred":[
        "\u0413\u0440\u0435\u0431\u0456\u043d\u043a\u0430"
    ],
    "name:und_x_variant":[
        "Grebenkovskiy"
    ],
    "name:vie_x_preferred":[
        "Hrebinka"
    ],
    "name:zho_x_preferred":[
        "\u683c\u5217\u6bd4\u7fc1\u5361"
    ],
    "qs:a0":"\u0423\u043a\u0440\u0430\u0457\u043d\u0430",
    "qs:a1":"*\u041f\u043e\u043b\u0442\u0430\u0432\u0441\u044c\u043a\u0430",
    "qs:a1_alt":"Poltavs'ka",
    "qs:a1r":"0",
    "qs:a2":"\u0413\u0440\u0435\u0431\u0456\u043d\u043a\u0456\u0432\u0441\u044c\u043a\u0438\u0439",
    "qs:a2_alt":"Hrebinkivs'kyi",
    "qs:adm0":"\u0423\u043a\u0440\u0430\u0457\u043d\u0430",
    "qs:la_lc":"*",
    "qs:level":"locality",
    "qs:loc":"\u0413\u0440\u0435\u0431\u0456\u043d\u043a\u0430",
    "qs:loc_alt":"Hrebinka",
    "qs:pop":0,
    "qs:type":"buffered point",
    "wd:wordcount":62,
    "wof:name":"\u0413\u0440\u0435\u0431\u0456\u043d\u043a\u0430",
    "wof:placetype":"locality",
    "wof:population":11017
},
  "geometry": {"coordinates":[32.438386,50.112861],"type":"Point"}
}