{
  "type": "Feature",
  "properties": {
    "gn:gn_country":"UA",
    "gn:gn_fcode":"PPL",
    "gn:gn_pop":2937,
    "gn:population":2937,
    "iso:country":"UA",
    "name:ceb_x_preferred":[
        "Shypyntsi"
    ],
    "name:deu_x_preferred":[
        "Schypynzi"
    ],
    "name:eng_x_preferred":[
        "Shypyntsi"
    ],
    "name:hye_x_preferred":[
        "\u0547\u056b\u057a\u056b\u0576\u0581\u056b"
    ],
    "name:ron_x_preferred":[
        "\u0218ipeni\u021b"
    ],
    "name:rus_x_preferred":[
        "\u0428\u0438\u043f\u0438\u043d\u0446\u0456"
    ],
    "name:rus_x_variant":[
        "\u0428\u0438\u043f\u0438\u043d\u0446\u044b"
    ],
    "name:ukr_x_preferred":[
        "\u0428\u0438\u043f\u0438\u043d\u0446\u0456"
    ],
    "name:unk_x_variant":[
        "Shipentsi"
    ],
    "qs_pg:aaroncc":"UA",
    "qs_pg:gn_country":"UA",
    "qs_pg:gn_fcode":"PPL",
    "qs_pg:gn_pop":2937,
    "qs_pg:name":"Shypyntsi",
    "qs_pg:photos_9r":0,
    "qs_pg:photos_sr":0,
    "qs_pg:pop_sr":4,
    "qs_pg:qs_pg_placetype":"locality",
    "wof:name":"Shypyntsi",
    "wof:placetype":"locality",
    "wof:population":2937
},
  "geometry": {"coordinates":[25.74664,48.37677],"type":"Point"}
}