{
  "type": "Feature",
  "properties": {
    "gn:admin1_code":"22.0",
    "gn:asciiname":"Andrushovka",
    "gn:country_code":"UA",
    "gn:dem":238,
    "gn:feature_class":"P",
    "gn:feature_code":"PPL",
    "gn:name":"Andrushovka",
    "gn:population":0,
    "gn:timezone":"Europe/Kiev",
    "iso:country":"UA",
    "name:rus_x_preferred":[
        "\u0410\u043d\u0434\u0440\u0443\u0448\u043e\u0432\u043a\u0430"
    ],
    "name:und_x_variant":[
        "Andrusz\u00f3wka",
        "Andrushuvka",
        "Andrushovka"
    ],
    "wof:name":"Andrushovka",
    "wof:placetype":"locality"
},
  "geometry": {"coordinates":[26.17071,50.22552],"type":"Point"}
}