{
  "type": "Feature",
  "properties": {
    "gn:admin1_code":"2.0",
    "gn:asciiname":"Losevka",
    "gn:country_code":"UA",
    "gn:dem":163,
    "gn:feature_class":"P",
    "gn:feature_code":"PPL",
    "gn:name":"Losevka",
    "gn:population":0,
    "gn:timezone":"Europe/Kiev",
    "iso:country":"UA",
    "name:ukr_x_preferred":[
        "Losivka"
    ],
    "name:ukr_x_variant":[
        "\u041b\u043e\u0441\u0456\u0432\u043a\u0430"
    ],
    "wof:name":"Losevka",
    "wof:placetype":"locality"
},
  "geometry": {"coordinates":[32.56474,52.05468],"type":"Point"}
}