{
  "type": "Feature",
  "properties": {
    "gn:admin1_code":"27.0",
    "gn:asciiname":"Veselivka",
    "gn:country_code":"UA",
    "gn:dem":153,
    "gn:feature_class":"P",
    "gn:feature_code":"PPL",
    "gn:name":"Veselivka",
    "gn:population":0,
    "gn:timezone":"Europe/Kiev",
    "iso:country":"UA",
    "name:ukr_x_preferred":[
        "Veselivka"
    ],
    "name:ukr_x_variant":[
        "\u0412\u0435\u0441\u0435\u043b\u0456\u0432\u043a\u0430"
    ],
    "name:und_x_variant":[
        "Veselovka"
    ],
    "wof:name":"Veselivka",
    "wof:placetype":"locality"
},
  "geometry": {"coordinates":[28.84004,51.23538],"type":"Point"}
}