{
  "type": "Feature",
  "properties": {
    "gn:admin1_code":"24.0",
    "gn:asciiname":"Syl'ne",
    "gn:country_code":"UA",
    "gn:dem":174,
    "gn:feature_class":"P",
    "gn:feature_code":"PPL",
    "gn:name":"Syl\u2019ne",
    "gn:population":0,
    "gn:timezone":"Europe/Kiev",
    "iso:country":"UA",
    "name:ukr_x_preferred":[
        "Syl\u2019ne"
    ],
    "name:ukr_x_variant":[
        "\u0421\u0438\u043b\u044c\u043d\u0435"
    ],
    "name:und_x_variant":[
        "Silino",
        "Sil\u2019noye",
        "Sil\u2019ne"
    ],
    "wof:name":"Syl'ne",
    "wof:placetype":"locality"
},
  "geometry": {"coordinates":[24.01442,51.38093],"type":"Point"}
}