{
  "type": "Feature",
  "properties": {
    "iso:country":"UA",
    "name:ukr_x_preferred":[
        "Shcherbani"
    ],
    "name:ukr_x_variant":[
        "\u0429\u0435\u0440\u0431\u0430\u043d\u0456"
    ],
    "name:unk_x_variant":[
        "Shcherbany"
    ],
    "qs:a0":"\u0423\u043a\u0440\u0430\u0457\u043d\u0430",
    "qs:a1":"*\u041f\u043e\u043b\u0442\u0430\u0432\u0441\u044c\u043a\u0430",
    "qs:a1_alt":"Poltavs'ka",
    "qs:a1r":"0",
    "qs:a2":"\u041f\u043e\u043b\u0442\u0430\u0432\u0441\u044c\u043a\u0438\u0439",
    "qs:a2_alt":"Poltavs'kyi",
    "qs:adm0":"\u0423\u043a\u0440\u0430\u0457\u043d\u0430",
    "qs:la_lc":"*",
    "qs:level":"locality",
    "qs:loc":"\u0429\u0435\u0440\u0431\u0430\u043d\u0456",
    "qs:loc_alt":"Scherbani",
    "qs:pop":0,
    "qs:type":"buffered point",
    "wof:name":"\u0429\u0435\u0440\u0431\u0430\u043d\u0456",
    "wof:placetype":"locality"
},
  "geometry": {"coordinates":[34.541965,49.531962],"type":"Point"}
}