{
  "type": "Feature",
  "properties": {
    "gn:admin1_code":"18.0",
    "gn:asciiname":"Kozache",
    "gn:country_code":"UA",
    "gn:dem":111,
    "gn:feature_class":"P",
    "gn:feature_code":"PPL",
    "gn:name":"Kozache",
    "gn:population":0,
    "gn:timezone":"Europe/Kiev",
    "iso:country":"UA",
    "name:ukr_x_preferred":[
        "Kozache"
    ],
    "name:ukr_x_variant":[
        "\u041a\u043e\u0437\u0430\u0447\u0435"
    ],
    "wof:name":"Kozache",
    "wof:placetype":"locality"
},
  "geometry": {"coordinates":[32.68406,50.01933],"type":"Point"}
}