{
  "type": "Feature",
  "properties": {
    "iso:country":"UA",
    "name:deu_x_preferred":[
        "Bakscha"
    ],
    "name:eng_x_preferred":[
        "Baksha"
    ],
    "name:kat_x_preferred":[
        "\u10d1\u10d0\u10d9\u10e8\u10d0"
    ],
    "name:lav_x_preferred":[
        "Bak\u0161a"
    ],
    "name:pol_x_preferred":[
        "Baksza"
    ],
    "name:ron_x_preferred":[
        "Bak\u0219a"
    ],
    "name:rus_x_preferred":[
        "\u0411\u0430\u043a\u0448\u0430"
    ],
    "name:spa_x_preferred":[
        "Baksha"
    ],
    "name:ukr_x_preferred":[
        "Baksha"
    ],
    "name:ukr_x_variant":[
        "\u0411\u0430\u043a\u0448\u0430"
    ],
    "name:zho_x_preferred":[
        "\u5df4\u514b\u6c99"
    ],
    "qs:a0":"\u0423\u043a\u0440\u0430\u0457\u043d\u0430",
    "qs:a1":"*\u041e\u0434\u0435\u0441\u044c\u043a\u0430",
    "qs:a1_alt":"Odes'ka",
    "qs:a1r":"0",
    "qs:a2":"\u0421\u0430\u0432\u0440\u0430\u043d\u0441\u044c\u043a\u0438\u0439",
    "qs:a2_alt":"Savrans'kyi",
    "qs:adm0":"\u0423\u043a\u0440\u0430\u0457\u043d\u0430",
    "qs:la_lc":"*",
    "qs:level":"locality",
    "qs:loc":"\u0411\u0430\u043a\u0448\u0430",
    "qs:loc_alt":"Baksha",
    "qs:pop":0,
    "qs:type":"buffered point",
    "wof:name":"\u0411\u0430\u043a\u0448\u0430",
    "wof:placetype":"locality"
},
  "geometry": {"coordinates":[29.972621,48.00904],"type":"Point"}
}