{
  "type": "Feature",
  "properties": {
    "gn:admin1_code":"21.0",
    "gn:asciiname":"Pavlenki",
    "gn:country_code":"UA",
    "gn:dem":154,
    "gn:feature_class":"P",
    "gn:feature_code":"PPL",
    "gn:name":"Pavlenki",
    "gn:population":0,
    "gn:timezone":"Europe/Kiev",
    "iso:country":"UA",
    "wof:name":"Pavlenki",
    "wof:placetype":"locality"
},
  "geometry": {"coordinates":[34.68444,50.20111],"type":"Point"}
}