{
  "type": "Feature",
  "properties": {
    "gn:admin1_code":"21.0",
    "gn:asciiname":"Beyeve",
    "gn:country_code":"UA",
    "gn:dem":154,
    "gn:feature_class":"P",
    "gn:feature_code":"PPL",
    "gn:name":"Beyeve",
    "gn:population":0,
    "gn:timezone":"Europe/Kiev",
    "iso:country":"UA",
    "name:ukr_x_preferred":[
        "Beyeve"
    ],
    "name:ukr_x_variant":[
        "\u0411\u0435\u0454\u0432\u0435"
    ],
    "name:und_x_variant":[
        "Chernishevka",
        "Beyeva",
        "Chernyshevo",
        "Beyevo"
    ],
    "wof:name":"Beyeve",
    "wof:placetype":"locality"
},
  "geometry": {"coordinates":[33.99223,50.65073],"type":"Point"}
}