{
  "type": "Feature",
  "properties": {
    "gn:admin1_code":"08",
    "gn:asciiname":"Lymantsi",
    "gn:country_code":"UA",
    "gn:dem":10,
    "gn:feature_class":"P",
    "gn:feature_code":"PPL",
    "gn:name":"Lymantsi",
    "gn:population":0,
    "gn:timezone":"Europe/Kiev",
    "iso:country":"UA",
    "name:ukr_x_preferred":[
        "Lymantsi"
    ],
    "name:ukr_x_variant":[
        "\u041b\u0438\u043c\u0430\u043d\u0446\u0456"
    ],
    "wof:name":"Lymantsi",
    "wof:placetype":"locality"
},
  "geometry": {"coordinates":[32.82567,46.86836],"type":"Point"}
}