{
  "type": "Feature",
  "properties": {
    "gn:admin1_code":"1.0",
    "gn:asciiname":"Yavorivka",
    "gn:country_code":"UA",
    "gn:dem":121,
    "gn:feature_class":"P",
    "gn:feature_code":"PPL",
    "gn:name":"Yavorivka",
    "gn:population":0,
    "gn:timezone":"Europe/Kiev",
    "iso:country":"UA",
    "name:ukr_x_preferred":[
        "Yavorivka"
    ],
    "name:ukr_x_variant":[
        "\u042f\u0432\u043e\u0440\u0456\u0432\u043a\u0430"
    ],
    "name:und_x_variant":[
        "Stalinovka",
        "Bogodarovka",
        "Yavorovka"
    ],
    "wof:name":"Yavorivka",
    "wof:placetype":"locality"
},
  "geometry": {"coordinates":[32.05921,50.12971],"type":"Point"}
}