{
  "type": "Feature",
  "properties": {
    "gn:admin1_code":"27.0",
    "gn:asciiname":"Kamin'",
    "gn:country_code":"UA",
    "gn:dem":138,
    "gn:feature_class":"P",
    "gn:feature_code":"PPL",
    "gn:name":"Kamin\u2019",
    "gn:population":0,
    "gn:timezone":"Europe/Kiev",
    "iso:country":"UA",
    "name:rus_x_preferred":[
        "Kamen\u2019"
    ],
    "name:ukr_x_preferred":[
        "Kamin\u2019"
    ],
    "name:ukr_x_variant":[
        "\u041a\u0430\u043c\u0456\u043d\u044c"
    ],
    "wof:name":"Kamin'",
    "wof:placetype":"locality"
},
  "geometry": {"coordinates":[28.88941,51.27658],"type":"Point"}
}