{
  "type": "Feature",
  "properties": {
    "gn:admin1_code":"7.0",
    "gn:asciiname":"Stare Mazharove",
    "gn:country_code":"UA",
    "gn:dem":87,
    "gn:feature_class":"P",
    "gn:feature_code":"PPL",
    "gn:name":"Stare Mazharove",
    "gn:population":0,
    "gn:timezone":"Europe/Kiev",
    "iso:country":"UA",
    "name:ukr_x_preferred":[
        "Stare Mazharove"
    ],
    "name:ukr_x_variant":[
        "\u0421\u0442\u0430\u0440\u0435 \u041c\u0430\u0436\u0430\u0440\u043e\u0432\u0435"
    ],
    "name:und_x_variant":[
        "Mozharovo",
        "Staroye Mazharovo"
    ],
    "wof:name":"Stare Mazharove",
    "wof:placetype":"locality"
},
  "geometry": {"coordinates":[35.44499000000001,49.02876],"type":"Point"}
}