{
  "type": "Feature",
  "properties": {
    "gn:admin1_code":"8.0",
    "gn:asciiname":"Katerynivka",
    "gn:country_code":"UA",
    "gn:dem":67,
    "gn:feature_class":"P",
    "gn:feature_code":"PPL",
    "gn:name":"Katerynivka",
    "gn:population":0,
    "gn:timezone":"Europe/Kiev",
    "iso:country":"UA",
    "name:deu_x_preferred":[
        "Kateryniwka"
    ],
    "name:est_x_preferred":[
        "Kater\u00f5nivka"
    ],
    "name:rus_x_preferred":[
        "\u041a\u0430\u0442\u0435\u0440\u0438\u043d\u043e\u0432\u043a\u0430"
    ],
    "name:ukr_x_preferred":[
        "Katerynivka"
    ],
    "name:ukr_x_variant":[
        "\u041a\u0430\u0442\u0435\u0440\u0438\u043d\u0456\u0432\u043a\u0430"
    ],
    "name:und_x_variant":[
        "Barnyshevka",
        "Yekaterinovka",
        "Katerinovka"
    ],
    "wof:name":"Katerynivka",
    "wof:placetype":"locality"
},
  "geometry": {"coordinates":[34.16114,47.10938],"type":"Point"}
}