{
  "type": "Feature",
  "properties": {
    "gn:admin1_code":"24.0",
    "gn:asciiname":"Terekhy",
    "gn:country_code":"UA",
    "gn:dem":175,
    "gn:feature_class":"P",
    "gn:feature_code":"PPL",
    "gn:name":"Terekhy",
    "gn:population":0,
    "gn:timezone":"Europe/Kiev",
    "iso:country":"UA",
    "name:rus_x_preferred":[
        "Ter\u00ebkhi"
    ],
    "name:ukr_x_preferred":[
        "Terekhy"
    ],
    "name:ukr_x_variant":[
        "\u0422\u0435\u0440\u0435\u0445\u0438"
    ],
    "wof:name":"Terekhy",
    "wof:placetype":"locality"
},
  "geometry": {"coordinates":[23.88714,51.11778],"type":"Point"}
}