{
  "type": "Feature",
  "properties": {
    "gn:population":4052,
    "iso:country":"UA",
    "name:ceb_x_preferred":[
        "Myrnyy"
    ],
    "name:crh_x_preferred":[
        "Mirn\u0131y"
    ],
    "name:deu_x_preferred":[
        "Myrnyj"
    ],
    "name:eng_x_preferred":[
        "Mirnyy"
    ],
    "name:eng_x_variant":[
        "Mirnyi",
        "Mirny",
        "Myrnyi"
    ],
    "name:epo_x_preferred":[
        "Mirno"
    ],
    "name:hun_x_preferred":[
        "Mirnij"
    ],
    "name:hye_x_preferred":[
        "\u0544\u056b\u0580\u0576\u056b"
    ],
    "name:hye_x_variant":[
        "\u0544\u056b\u0580\u0576\u056b\u0575"
    ],
    "name:nld_x_preferred":[
        "Mirniy"
    ],
    "name:ron_x_preferred":[
        "M\u00eerne"
    ],
    "name:rus_x_preferred":[
        "\u041c\u0438\u0440\u043d\u044b\u0439"
    ],
    "name:ukr_x_preferred":[
        "\u041c\u0438\u0440\u043d\u0438\u0439"
    ],
    "name:urd_x_preferred":[
        "\u0645\u0626\u0631\u0646\u06cc"
    ],
    "name:zho_x_preferred":[
        "\u7c73\u723e\u5c3c"
    ],
    "qs:a0":"\u0423\u043a\u0440\u0430\u0457\u043d\u0430",
    "qs:a1":"*\u041a\u0440\u0438\u043c",
    "qs:a1_alt":"Krym",
    "qs:a1r":"0",
    "qs:a2":"\u0421\u0430\u043a\u0441\u044c\u043a\u0438\u0439",
    "qs:a2_alt":"Saks'kyi",
    "qs:adm0":"\u0423\u043a\u0440\u0430\u0457\u043d\u0430",
    "qs:la_lc":"*",
    "qs:level":"locality",
    "qs:loc":"\u041c\u0438\u0440\u043d\u0438\u0439",
    "qs:loc_alt":"Myrnyi",
    "qs:pop":0,
    "qs:type":"buffered point",
    "wd:wordcount":186,
    "wof:name":"\u041c\u0438\u0440\u043d\u0438\u0439",
    "wof:placetype":"locality",
    "wof:population":4052
},
  "geometry": {"coordinates":[33.034462,45.306312],"type":"Point"}
}