{
  "type": "Feature",
  "properties": {
    "gn:admin1_code":"11.0",
    "gn:admin2_code":"709333",
    "gn:admin3_code":"11152863.0",
    "gn:asciiname":"Ozyornoye",
    "gn:country_code":"UA",
    "gn:dem":16,
    "gn:elevation":"12.0",
    "gn:feature_class":"P",
    "gn:feature_code":"PPL",
    "gn:name":"Ozyornoye",
    "gn:population":44,
    "gn:timezone":"Europe/Simferopol",
    "iso:country":"UA",
    "name:crh_x_historical":[
        "Uzun Saqal"
    ],
    "name:crh_x_preferred":[
        "Uzun Saqal"
    ],
    "name:eng_x_preferred":[
        "Ozyornoye"
    ],
    "name:rus_x_historical":[
        "\u041d\u043e\u0301\u0432\u044b\u0439 \u0414\u0436\u0430\u043d\u043a\u043e\u0301\u0439",
        "\u0423\u0437\u0443\u0301\u043d-\u0421\u0430\u043a\u0430\u0301\u043b \u0422\u0430\u0442\u0430\u0301\u0440\u0441\u043a\u0438\u0439"
    ],
    "name:rus_x_preferred":[
        "\u041e\u0437\u0451\u0440\u043d\u043e\u0435"
    ],
    "name:rus_x_variant":[
        "\u041d\u043e\u0301\u0432\u044b\u0439 \u0414\u0436\u0430\u043d\u043a\u043e\u0301\u0439",
        "\u0423\u0437\u0443\u0301\u043d-\u0421\u0430\u043a\u0430\u0301\u043b \u0422\u0430\u0442\u0430\u0301\u0440\u0441\u043a\u0438\u0439"
    ],
    "name:ukr_x_preferred":[
        "\u041e\u0437\u0435\u0440\u043d\u0435"
    ],
    "wof:name":"Ozyornoye",
    "wof:placetype":"locality",
    "wof:population":44
},
  "geometry": {"coordinates":[34.38327,45.65067],"type":"Point"}
}