{
  "type": "Feature",
  "properties": {
    "gn:admin1_code":"16.0",
    "gn:asciiname":"Semenivka",
    "gn:country_code":"UA",
    "gn:dem":16,
    "gn:feature_class":"P",
    "gn:feature_code":"PPL",
    "gn:name":"Semenivka",
    "gn:population":0,
    "gn:timezone":"Europe/Kiev",
    "iso:country":"UA",
    "name:ukr_x_preferred":[
        "Semenivka"
    ],
    "name:ukr_x_variant":[
        "\u0421\u0435\u043c\u0435\u043d\u0456\u0432\u043a\u0430"
    ],
    "wof:name":"Semenivka",
    "wof:placetype":"locality"
},
  "geometry": {"coordinates":[32.83298,47.27488],"type":"Point"}
}