{
  "type": "Feature",
  "properties": {
    "gn:admin1_code":"4.0",
    "gn:asciiname":"Chornohlazivka",
    "gn:country_code":"UA",
    "gn:dem":94,
    "gn:feature_class":"P",
    "gn:feature_code":"PPL",
    "gn:name":"Chornohlazivka",
    "gn:population":0,
    "gn:timezone":"Europe/Kiev",
    "iso:country":"UA",
    "name:rus_x_preferred":[
        "\u0427\u0435\u0440\u043d\u043e\u0433\u043b\u0430\u0437\u043e\u0432\u043a\u0430"
    ],
    "name:ukr_x_preferred":[
        "Chornohlazivka"
    ],
    "name:ukr_x_variant":[
        "\u0427\u043e\u0440\u043d\u043e\u0433\u043b\u0430\u0437\u0456\u0432\u043a\u0430"
    ],
    "name:und_x_variant":[
        "Chernoglazovka"
    ],
    "wof:name":"Chornohlazivka",
    "wof:placetype":"locality"
},
  "geometry": {"coordinates":[35.8975,48.95137],"type":"Point"}
}