{
  "type": "Feature",
  "properties": {
    "gn:admin1_code":"5.0",
    "gn:asciiname":"Solodke",
    "gn:country_code":"UA",
    "gn:dem":197,
    "gn:feature_class":"P",
    "gn:feature_code":"PPL",
    "gn:name":"Solodke",
    "gn:population":0,
    "gn:timezone":"Europe/Kiev",
    "iso:country":"UA",
    "name:ukr_x_preferred":[
        "Solodke"
    ],
    "name:ukr_x_variant":[
        "\u0421\u043e\u043b\u043e\u0434\u043a\u0435"
    ],
    "name:und_x_variant":[
        "Sladkoye"
    ],
    "wof:name":"Solodke",
    "wof:placetype":"locality"
},
  "geometry": {"coordinates":[37.49491,47.79013],"type":"Point"}
}