{
  "type": "Feature",
  "properties": {
    "gn:admin1_code":"9.0",
    "gn:asciiname":"Markovtsy",
    "gn:country_code":"UA",
    "gn:dem":276,
    "gn:feature_class":"P",
    "gn:feature_code":"PPL",
    "gn:name":"Markovtsy",
    "gn:population":0,
    "gn:timezone":"Europe/Kiev",
    "iso:country":"UA",
    "wof:name":"Markovtsy",
    "wof:placetype":"locality"
},
  "geometry": {"coordinates":[27.5168,49.41995],"type":"Point"}
}