{
  "type": "Feature",
  "properties": {
    "gn:admin1_code":"22.0",
    "gn:asciiname":"Trostyantsy",
    "gn:country_code":"UA",
    "gn:dem":276,
    "gn:feature_class":"P",
    "gn:feature_code":"PPL",
    "gn:name":"Trostyantsy",
    "gn:population":0,
    "gn:timezone":"Europe/Kiev",
    "iso:country":"UA",
    "name:und_x_variant":[
        "Trostyantsi",
        "Trostyantsy"
    ],
    "wof:name":"Trostyantsy",
    "wof:placetype":"locality"
},
  "geometry": {"coordinates":[24.93568,49.06719],"type":"Point"}
}