{
  "type": "Feature",
  "properties": {
    "gn:admin1_code":"15.0",
    "gn:asciiname":"Stadniki",
    "gn:country_code":"UA",
    "gn:dem":275,
    "gn:feature_class":"P",
    "gn:feature_code":"PPL",
    "gn:name":"Stadniki",
    "gn:population":0,
    "gn:timezone":"Europe/Kiev",
    "iso:country":"UA",
    "name:und_x_variant":[
        "Stadnik",
        "Stadniki"
    ],
    "wof:name":"Stadniki",
    "wof:placetype":"locality"
},
  "geometry": {"coordinates":[23.54502,49.92973],"type":"Point"}
}