{
  "type": "Feature",
  "properties": {
    "gn:admin1_code":"27.0",
    "gn:asciiname":"Polovets'ke",
    "gn:country_code":"UA",
    "gn:dem":244,
    "gn:feature_class":"P",
    "gn:feature_code":"PPL",
    "gn:name":"Polovets\u2019ke",
    "gn:population":0,
    "gn:timezone":"Europe/Kiev",
    "iso:country":"UA",
    "name:ukr_x_preferred":[
        "Polovets\u2019ke"
    ],
    "name:ukr_x_variant":[
        "\u041f\u043e\u043b\u043e\u0432\u0435\u0446\u044c\u043a\u0435"
    ],
    "name:und_x_variant":[
        "Polovetskoye"
    ],
    "wof:name":"Polovets'ke",
    "wof:placetype":"locality"
},
  "geometry": {"coordinates":[28.67145,49.96397],"type":"Point"}
}