{
  "type": "Feature",
  "properties": {
    "gn:admin1_code":"8.0",
    "gn:asciiname":"Bilohirka",
    "gn:country_code":"UA",
    "gn:dem":49,
    "gn:feature_class":"P",
    "gn:feature_code":"PPL",
    "gn:name":"Bilohirka",
    "gn:population":0,
    "gn:timezone":"Europe/Kiev",
    "iso:country":"UA",
    "name:ukr_x_preferred":[
        "Bilohirka"
    ],
    "name:ukr_x_variant":[
        "\u0411\u0456\u043b\u043e\u0433\u0456\u0440\u043a\u0430"
    ],
    "name:und_x_variant":[
        "Belogorskiy"
    ],
    "wof:name":"Bilohirka",
    "wof:placetype":"locality"
},
  "geometry": {"coordinates":[33.13703,47.19931],"type":"Point"}
}