{
  "type": "Feature",
  "properties": {
    "gn:admin1_code":"18.0",
    "gn:asciiname":"Kumy",
    "gn:country_code":"UA",
    "gn:dem":136,
    "gn:feature_class":"P",
    "gn:feature_code":"PPL",
    "gn:name":"Kumy",
    "gn:population":0,
    "gn:timezone":"Europe/Kiev",
    "iso:country":"UA",
    "name:ukr_x_preferred":[
        "Kumy"
    ],
    "name:ukr_x_variant":[
        "\u041a\u0443\u043c\u0438"
    ],
    "wof:name":"Kumy",
    "wof:placetype":"locality"
},
  "geometry": {"coordinates":[35.25437,49.34421],"type":"Point"}
}