{
  "type": "Feature",
  "properties": {
    "gn:admin1_code":"6.0",
    "gn:asciiname":"Yamna",
    "gn:country_code":"UA",
    "gn:dem":600,
    "gn:feature_class":"P",
    "gn:feature_code":"PPL",
    "gn:name":"Yamna",
    "gn:population":0,
    "gn:timezone":"Europe/Kiev",
    "iso:country":"UA",
    "name:ara_x_preferred":[
        "\u064a\u0627\u0645\u0646\u0629"
    ],
    "name:ceb_x_preferred":[
        "Yamna"
    ],
    "name:ukr_x_preferred":[
        "Yamna"
    ],
    "name:ukr_x_variant":[
        "\u042f\u043c\u043d\u0430"
    ],
    "wof:name":"Yamna",
    "wof:placetype":"locality"
},
  "geometry": {"coordinates":[24.56938,48.43716],"type":"Point"}
}