{
  "type": "Feature",
  "properties": {
    "gn:admin1_code":"21.0",
    "gn:asciiname":"Chalyshchivka",
    "gn:country_code":"UA",
    "gn:dem":155,
    "gn:feature_class":"P",
    "gn:feature_code":"PPL",
    "gn:name":"Chalyshchivka",
    "gn:population":0,
    "gn:timezone":"Europe/Kiev",
    "iso:country":"UA",
    "name:ukr_x_preferred":[
        "Chalyshchivka"
    ],
    "name:ukr_x_variant":[
        "\u0427\u0430\u043b\u0438\u0449\u0456\u0432\u043a\u0430"
    ],
    "name:und_x_variant":[
        "Chelishchevka",
        "Chalishch\u00ebvka"
    ],
    "wof:name":"Chalyshchivka",
    "wof:placetype":"locality"
},
  "geometry": {"coordinates":[33.73722,51.1688],"type":"Point"}
}