{
  "type": "Feature",
  "properties": {
    "iso:country":"UA",
    "name:ara_x_preferred":[
        "\u0628\u0644\u0627\u0647\u0648\u0641\u064a\u0634\u064a\u0646\u0633\u0643\u064a"
    ],
    "name:bel_x_variant":[
        "\u0411\u043b\u0430\u0433\u0430\u0432\u0435\u0448\u0447\u0430\u043d\u0441\u043a\u0430\u0435"
    ],
    "name:crh_x_preferred":[
        "Blahovi\u015f\u00e7enske"
    ],
    "name:deu_x_preferred":[
        "Blahowischtschenske"
    ],
    "name:eng_x_preferred":[
        "Ul'yanovka"
    ],
    "name:fas_x_preferred":[
        "\u0627\u0648\u0644\u06cc\u0627\u0646\u0648\u0641\u06a9\u0627"
    ],
    "name:fra_x_preferred":[
        "Blahovichtchenske"
    ],
    "name:hye_x_preferred":[
        "\u0548\u0582\u056c\u0575\u0561\u0576\u0578\u057e\u056f\u0561"
    ],
    "name:ita_x_preferred":[
        "Blahovichtchenske"
    ],
    "name:kat_x_preferred":[
        "\u10d1\u10da\u10d0\u10d2\u10dd\u10d5\u10d4\u10e8\u10e9\u10d4\u10dc\u10e1\u10d9\u10dd\u10d4"
    ],
    "name:kat_x_variant":[
        "\u10e3\u10da\u10d8\u10d0\u10dc\u10dd\u10d5\u10d9\u10d0"
    ],
    "name:nno_x_preferred":[
        "Uljanovka"
    ],
    "name:pol_x_preferred":[
        "B\u0142ahowiszczen\u015bke"
    ],
    "name:ron_x_preferred":[
        "Uleanovka"
    ],
    "name:ron_x_variant":[
        "Ulianovka"
    ],
    "name:rus_x_preferred":[
        "\u0411\u043b\u0430\u0433\u043e\u0432\u0435\u0449\u0435\u043d\u0441\u043a\u043e\u0435"
    ],
    "name:rus_x_variant":[
        "\u0423\u043b\u044c\u044f\u043d\u043e\u0432\u043a\u0430"
    ],
    "name:sco_x_preferred":[
        "Blahovishchenske"
    ],
    "name:tat_x_preferred":[
        "\u0411\u043b\u0430\u04bb\u043e\u0432\u0438\u0447\u0447\u0435\u043d\u0441\u043a\u0435"
    ],
    "name:ukr_x_preferred":[
        "\u0411\u043b\u0430\u0433\u043e\u0432\u0456\u0449\u0435\u043d\u0441\u044c\u043a\u0435"
    ],
    "name:ukr_x_variant":[
        "\u0423\u043b\u044c\u044f\u043d\u043e\u0432\u043a\u0430"
    ],
    "name:unk_x_variant":[
        "Ul\u2019yanovka"
    ],
    "name:vie_x_preferred":[
        "Ulianovka"
    ],
    "name:zho_x_preferred":[
        "\u70cf\u91cc\u63da\u8afe\u592b\u5361"
    ],
    "qs:a0":"\u0423\u043a\u0440\u0430\u0457\u043d\u0430",
    "qs:a1":"*\u041a\u0456\u0440\u043e\u0432\u043e\u0433\u0440\u0430\u0434\u0441\u044c\u043a\u0430",
    "qs:a1_alt":"Kirovohrads'ka",
    "qs:a1r":"0",
    "qs:a2":"\u0423\u043b\u044c\u044f\u043d\u043e\u0432\u0441\u044c\u043a\u0438\u0439",
    "qs:a2_alt":"Ul'ianovs'kyi",
    "qs:adm0":"\u0423\u043a\u0440\u0430\u0457\u043d\u0430",
    "qs:la_lc":"*",
    "qs:level":"locality",
    "qs:loc":"\u0423\u043b\u044c\u044f\u043d\u043e\u0432\u043a\u0430",
    "qs:loc_alt":"Ul'ianovka",
    "qs:pop":0,
    "qs:type":"buffered point",
    "wd:wordcount":126,
    "wof:name":"\u0423\u043b\u044c\u044f\u043d\u043e\u0432\u043a\u0430",
    "wof:placetype":"locality"
},
  "geometry": {"coordinates":[30.230658,48.321236],"type":"Point"}
}