{
  "type": "Feature",
  "properties": {
    "gn:admin1_code":"9.0",
    "gn:asciiname":"Manyatyn",
    "gn:country_code":"UA",
    "gn:dem":223,
    "gn:feature_class":"P",
    "gn:feature_code":"PPL",
    "gn:name":"Manyatyn",
    "gn:population":0,
    "gn:timezone":"Europe/Kiev",
    "iso:country":"UA",
    "name:ukr_x_preferred":[
        "Manyatyn"
    ],
    "name:ukr_x_variant":[
        "\u041c\u0430\u043d\u044f\u0442\u0438\u043d"
    ],
    "name:und_x_variant":[
        "Manyatin"
    ],
    "wof:name":"Manyatyn",
    "wof:placetype":"locality"
},
  "geometry": {"coordinates":[27.22492,50.42607],"type":"Point"}
}