{
  "type": "Feature",
  "properties": {
    "gn:admin1_code":"13.0",
    "gn:asciiname":"Bucha",
    "gn:country_code":"UA",
    "gn:dem":161,
    "gn:feature_class":"P",
    "gn:feature_code":"PPL",
    "gn:name":"Bucha",
    "gn:population":0,
    "gn:timezone":"Europe/Kiev",
    "iso:country":"UA",
    "name:ceb_x_preferred":[
        "Bucha"
    ],
    "name:deu_x_preferred":[
        "Bucha"
    ],
    "name:epo_x_preferred":[
        "Bucha"
    ],
    "name:eus_x_preferred":[
        "Bucha"
    ],
    "name:ita_x_preferred":[
        "Bucha"
    ],
    "name:nld_x_preferred":[
        "Bucha"
    ],
    "name:pol_x_preferred":[
        "Bucha"
    ],
    "name:por_x_preferred":[
        "Bucha"
    ],
    "name:rus_x_preferred":[
        "\u0411\u0443\u0447\u0430"
    ],
    "name:swe_x_preferred":[
        "Bucha"
    ],
    "name:ukr_x_preferred":[
        "\u0411\u0443\u0447\u0430"
    ],
    "name:vol_x_preferred":[
        "Bucha"
    ],
    "wof:name":"Bucha",
    "wof:placetype":"locality"
},
  "geometry": {"coordinates":[30.36667000000001,50.58333],"type":"Point"}
}