{
  "type": "Feature",
  "properties": {
    "gn:admin1_code":"2.0",
    "gn:asciiname":"Velykyy Zliyiv",
    "gn:country_code":"UA",
    "gn:dem":152,
    "gn:feature_class":"P",
    "gn:feature_code":"PPL",
    "gn:name":"Velykyy Zliyiv",
    "gn:population":0,
    "gn:timezone":"Europe/Kiev",
    "iso:country":"UA",
    "name:ukr_x_preferred":[
        "Velykyy Zliyiv"
    ],
    "name:ukr_x_variant":[
        "\u0412\u0435\u043b\u0438\u043a\u0438\u0439 \u0417\u043b\u0456\u0457\u0432"
    ],
    "name:und_x_variant":[
        "Bol\u2019shoye Sleyevo",
        "Bol\u2019shoye Zleyevo",
        "Bol\u2019shoy Zleyev",
        "Zaleyevo",
        "Velikiy Zliyev"
    ],
    "wof:name":"Velykyy Zliyiv",
    "wof:placetype":"locality"
},
  "geometry": {"coordinates":[30.86263,51.71459],"type":"Point"}
}