{
  "type": "Feature",
  "properties": {
    "gn:admin1_code":"19.0",
    "gn:asciiname":"Kutyanka",
    "gn:country_code":"UA",
    "gn:dem":209,
    "gn:feature_class":"P",
    "gn:feature_code":"PPL",
    "gn:name":"Kutyanka",
    "gn:population":0,
    "gn:timezone":"Europe/Kiev",
    "iso:country":"UA",
    "name:und_x_variant":[
        "Lyakhuv",
        "Kutyanka"
    ],
    "wof:name":"Kutyanka",
    "wof:placetype":"locality"
},
  "geometry": {"coordinates":[26.31979,50.239],"type":"Point"}
}