{
  "type": "Feature",
  "properties": {
    "gn:admin1_code":"24.0",
    "gn:asciiname":"Berezhnytsya",
    "gn:country_code":"UA",
    "gn:dem":156,
    "gn:feature_class":"P",
    "gn:feature_code":"PPL",
    "gn:name":"Berezhnytsya",
    "gn:population":0,
    "gn:timezone":"Europe/Kiev",
    "iso:country":"UA",
    "name:ukr_x_preferred":[
        "Berezhnytsya"
    ],
    "name:ukr_x_variant":[
        "\u0411\u0435\u0440\u0435\u0436\u043d\u0438\u0446\u044f"
    ],
    "name:und_x_variant":[
        "Bereznitsa",
        "Berezhnitsa"
    ],
    "wof:name":"Berezhnytsya",
    "wof:placetype":"locality"
},
  "geometry": {"coordinates":[25.21886,51.37445],"type":"Point"}
}