{
  "type": "Feature",
  "properties": {
    "gn:admin1_code":"14.0",
    "gn:asciiname":"Mykhaylyuky",
    "gn:country_code":"UA",
    "gn:dem":96,
    "gn:feature_class":"P",
    "gn:feature_code":"PPL",
    "gn:name":"Mykhaylyuky",
    "gn:population":0,
    "gn:timezone":"Europe/Zaporozhye",
    "iso:country":"UA",
    "name:ukr_x_preferred":[
        "Mykhaylyuky"
    ],
    "name:ukr_x_variant":[
        "\u041c\u0438\u0445\u0430\u0439\u043b\u044e\u043a\u0438"
    ],
    "name:und_x_variant":[
        "Mikhaylyukov"
    ],
    "wof:name":"Mykhaylyuky",
    "wof:placetype":"locality"
},
  "geometry": {"coordinates":[39.29891,48.98575],"type":"Point"}
}