{
  "type": "Feature",
  "properties": {
    "gn:admin1_code":"4.0",
    "gn:asciiname":"Zaporizhzhya",
    "gn:country_code":"UA",
    "gn:dem":125,
    "gn:feature_class":"P",
    "gn:feature_code":"PPL",
    "gn:name":"Zaporizhzhya",
    "gn:population":0,
    "gn:timezone":"Europe/Kiev",
    "iso:country":"UA",
    "name:rus_x_preferred":[
        "Krasnoye Zaporozh\u2019ye"
    ],
    "name:rus_x_variant":[
        "Zaporozh\u2019ye"
    ],
    "name:ukr_x_preferred":[
        "Zaporizhzhya"
    ],
    "name:ukr_x_variant":[
        "\u0417\u0430\u043f\u043e\u0440\u0456\u0436\u0436\u044f"
    ],
    "wof:name":"Zaporizhzhya",
    "wof:placetype":"locality"
},
  "geometry": {"coordinates":[36.43514,48.29727000000001],"type":"Point"}
}