{
  "type": "Feature",
  "properties": {
    "gn:admin1_code":"1.0",
    "gn:asciiname":"Knyazh'ye",
    "gn:country_code":"UA",
    "gn:dem":191,
    "gn:feature_class":"P",
    "gn:feature_code":"PPL",
    "gn:name":"Knyazh\u2019ye",
    "gn:population":0,
    "gn:timezone":"Europe/Kiev",
    "iso:country":"UA",
    "name:eng_x_preferred":[
        "Knyazh'ye"
    ],
    "name:rus_x_preferred":[
        "\u041a\u043d\u044f\u0436\u044c\u044f"
    ],
    "name:und_x_variant":[
        "Knyazh\u2019ye"
    ],
    "wof:name":"Knyazh'ye",
    "wof:placetype":"locality"
},
  "geometry": {"coordinates":[31.21099,49.06444000000001],"type":"Point"}
}