{
  "type": "Feature",
  "properties": {
    "gn:admin1_code":"7.0",
    "gn:asciiname":"Krasnyans'ke",
    "gn:country_code":"UA",
    "gn:dem":137,
    "gn:feature_class":"P",
    "gn:feature_code":"PPL",
    "gn:name":"Krasnyans\u2019ke",
    "gn:population":0,
    "gn:timezone":"Europe/Kiev",
    "iso:country":"UA",
    "name:rus_x_preferred":[
        "\u041a\u0440\u0430\u0441\u043d\u044f\u043d\u0441\u043a\u043e\u0435"
    ],
    "name:ukr_x_preferred":[
        "Krasnyans\u2019ke"
    ],
    "name:ukr_x_variant":[
        "\u041a\u0440\u0430\u0441\u043d\u044f\u043d\u0441\u044c\u043a\u0435"
    ],
    "name:und_x_variant":[
        "Uchastok Krasnoye",
        "Krasnoye",
        "Krasnyanskoye"
    ],
    "wof:name":"Krasnyans'ke",
    "wof:placetype":"locality"
},
  "geometry": {"coordinates":[35.68783,49.17171],"type":"Point"}
}