{
  "type": "Feature",
  "properties": {
    "gn:admin1_code":"3.0",
    "gn:asciiname":"Rivnya",
    "gn:cc2":"UA",
    "gn:country_code":"UA",
    "gn:dem":557,
    "gn:feature_class":"P",
    "gn:feature_code":"PPL",
    "gn:name":"Rivnya",
    "gn:population":0,
    "gn:timezone":"Europe/Kiev",
    "iso:country":"UA",
    "name:und_x_variant":[
        "Rovnya",
        "Rivna",
        "Rivnya"
    ],
    "wof:name":"Rivnya",
    "wof:placetype":"locality"
},
  "geometry": {"coordinates":[25.28333,48.08333],"type":"Point"}
}