{
  "type": "Feature",
  "properties": {
    "gn:admin1_code":"9.0",
    "gn:asciiname":"Klimashevka",
    "gn:country_code":"UA",
    "gn:dem":322,
    "gn:feature_class":"P",
    "gn:feature_code":"PPL",
    "gn:name":"Klimash\u00ebvka",
    "gn:population":0,
    "gn:timezone":"Europe/Kiev",
    "iso:country":"UA",
    "wof:name":"Klimashevka",
    "wof:placetype":"locality"
},
  "geometry": {"coordinates":[26.99347,49.51999],"type":"Point"}
}