{
  "type": "Feature",
  "properties": {
    "gn:admin1_code":"9.0",
    "gn:asciiname":"Kamenka",
    "gn:country_code":"UA",
    "gn:dem":201,
    "gn:feature_class":"P",
    "gn:feature_code":"PPL",
    "gn:name":"Kamenka",
    "gn:population":0,
    "gn:timezone":"Europe/Kiev",
    "iso:country":"UA",
    "wof:name":"Kamenka",
    "wof:placetype":"locality"
},
  "geometry": {"coordinates":[26.43762000000001,50.25797],"type":"Point"}
}