{
  "type": "Feature",
  "properties": {
    "iso:country":"UA",
    "name:deu_x_preferred":[
        "Nowotrojizke"
    ],
    "name:eng_x_preferred":[
        "Novotroyits'ke"
    ],
    "name:eng_x_variant":[
        "Novotroitske"
    ],
    "name:lav_x_preferred":[
        "Novotrojicke"
    ],
    "name:ron_x_preferred":[
        "Novotroii\u021bke"
    ],
    "name:rus_x_preferred":[
        "\u041d\u043e\u0432\u043e\u0442\u0440\u043e\u0438\u0446\u043a\u043e\u0435"
    ],
    "name:ukr_x_preferred":[
        "\u041d\u043e\u0432\u043e\u0442\u0440\u043e\u0457\u0446\u044c\u043a\u0435"
    ],
    "name:und_x_variant":[
        "Novotroitskoye"
    ],
    "name:zho_x_preferred":[
        "\u65b0\u7279\u7f85\u4f0a\u9f4a\u514b"
    ],
    "qs:a0":"\u0423\u043a\u0440\u0430\u0457\u043d\u0430",
    "qs:a1":"*\u0417\u0430\u043f\u043e\u0440\u0456\u0437\u044c\u043a\u0430",
    "qs:a1_alt":"Zaporiz'ka",
    "qs:a1r":"0",
    "qs:a2":"\u0411\u0435\u0440\u0434\u044f\u043d\u0441\u044c\u043a\u0438\u0439",
    "qs:a2_alt":"Berdians'kyi",
    "qs:adm0":"\u0423\u043a\u0440\u0430\u0457\u043d\u0430",
    "qs:la_lc":"*",
    "qs:level":"locality",
    "qs:loc":"\u041d\u043e\u0432\u043e\u0442\u0440\u043e\u0457\u0446\u044c\u043a\u0435",
    "qs:loc_alt":"Novotroits'ke",
    "qs:pop":0,
    "qs:type":"buffered point",
    "wd:wordcount":79,
    "wof:name":"\u041d\u043e\u0432\u043e\u0442\u0440\u043e\u0457\u0446\u044c\u043a\u0435",
    "wof:placetype":"locality"
},
  "geometry": {"coordinates":[36.653731,46.956864],"type":"Point"}
}