{
  "type": "Feature",
  "properties": {
    "gn:admin1_code":"9.0",
    "gn:asciiname":"Potereba",
    "gn:country_code":"UA",
    "gn:dem":250,
    "gn:feature_class":"P",
    "gn:feature_code":"PPL",
    "gn:name":"Potereba",
    "gn:population":0,
    "gn:timezone":"Europe/Kiev",
    "iso:country":"UA",
    "name:ukr_x_preferred":[
        "Potereba"
    ],
    "name:ukr_x_variant":[
        "\u041f\u043e\u0442\u0435\u0440\u0435\u0431\u0430"
    ],
    "wof:name":"Potereba",
    "wof:placetype":"locality"
},
  "geometry": {"coordinates":[26.73521,50.42388],"type":"Point"}
}