{
  "type": "Feature",
  "properties": {
    "gn:admin1_code":"14.0",
    "gn:asciiname":"Kruhlyk",
    "gn:country_code":"UA",
    "gn:dem":240,
    "gn:feature_class":"P",
    "gn:feature_code":"PPL",
    "gn:name":"Kruhlyk",
    "gn:population":0,
    "gn:timezone":"Europe/Zaporozhye",
    "iso:country":"UA",
    "name:ukr_x_preferred":[
        "Kruhlyk"
    ],
    "name:ukr_x_variant":[
        "\u041a\u0440\u0443\u0433\u043b\u0438\u043a"
    ],
    "name:und_x_variant":[
        "Kruglik"
    ],
    "wof:name":"Kruhlyk",
    "wof:placetype":"locality"
},
  "geometry": {"coordinates":[39.14119,48.30547],"type":"Point"}
}