{
  "type": "Feature",
  "properties": {
    "gn:admin1_code":"21.0",
    "gn:asciiname":"Kocherhy",
    "gn:country_code":"UA",
    "gn:dem":150,
    "gn:feature_class":"P",
    "gn:feature_code":"PPL",
    "gn:name":"Kocherhy",
    "gn:population":0,
    "gn:timezone":"Europe/Kiev",
    "iso:country":"UA",
    "name:ukr_x_preferred":[
        "Kocherhy"
    ],
    "name:ukr_x_variant":[
        "\u041a\u043e\u0447\u0435\u0440\u0433\u0438"
    ],
    "name:und_x_variant":[
        "Kochergi"
    ],
    "wof:name":"Kocherhy",
    "wof:placetype":"locality"
},
  "geometry": {"coordinates":[33.86719,51.46659],"type":"Point"}
}