{
  "type": "Feature",
  "properties": {
    "gn:admin1_code":"16.0",
    "gn:asciiname":"Krysov",
    "gn:cc2":"UA",
    "gn:country_code":"UA",
    "gn:dem":83,
    "gn:feature_class":"P",
    "gn:feature_code":"PPL",
    "gn:name":"Krysov",
    "gn:population":0,
    "gn:timezone":"Europe/Kiev",
    "iso:country":"UA",
    "name:und_x_variant":[
        "Krysovo",
        "Krysov"
    ],
    "wof:name":"Krysov",
    "wof:placetype":"locality"
},
  "geometry": {"coordinates":[30.91667,47.35],"type":"Point"}
}