{
  "type": "Feature",
  "properties": {
    "gn:admin1_code":"7.0",
    "gn:asciiname":"Petrenkove",
    "gn:country_code":"UA",
    "gn:dem":143,
    "gn:feature_class":"P",
    "gn:feature_code":"PPL",
    "gn:name":"Petrenkove",
    "gn:population":0,
    "gn:timezone":"Europe/Kiev",
    "iso:country":"UA",
    "name:rus_x_preferred":[
        "\u041f\u0435\u0442\u0440\u0435\u043d\u043a\u043e\u0432\u043e"
    ],
    "wof:name":"Petrenkove",
    "wof:placetype":"locality"
},
  "geometry": {"coordinates":[35.68686,49.90121],"type":"Point"}
}