{
  "type": "Feature",
  "properties": {
    "gn:admin1_code":"7.0",
    "gn:asciiname":"Novoyehorivka",
    "gn:country_code":"UA",
    "gn:dem":159,
    "gn:feature_class":"P",
    "gn:feature_code":"PPL",
    "gn:name":"Novoyehorivka",
    "gn:population":0,
    "gn:timezone":"Europe/Kiev",
    "iso:country":"UA",
    "name:ukr_x_preferred":[
        "Novoyehorivka"
    ],
    "name:ukr_x_variant":[
        "\u041d\u043e\u0432\u043e\u0454\u0433\u043e\u0440\u0456\u0432\u043a\u0430"
    ],
    "name:und_x_variant":[
        "Kuberla",
        "Nizhnyaya Yegor\u2019yevka"
    ],
    "wof:name":"Novoyehorivka",
    "wof:placetype":"locality"
},
  "geometry": {"coordinates":[36.17972,49.20583],"type":"Point"}
}