{
  "type": "Feature",
  "properties": {
    "gn:admin1_code":"19.0",
    "gn:asciiname":"Malyy Myds'k",
    "gn:country_code":"UA",
    "gn:dem":175,
    "gn:feature_class":"P",
    "gn:feature_code":"PPL",
    "gn:name":"Malyy Myds\u2019k",
    "gn:population":0,
    "gn:timezone":"Europe/Kiev",
    "iso:country":"UA",
    "name:ukr_x_preferred":[
        "Malyy Myds\u2019k"
    ],
    "name:ukr_x_variant":[
        "\u041c\u0430\u043b\u0438\u0439 \u041c\u0438\u0434\u0441\u044c\u043a"
    ],
    "name:und_x_variant":[
        "Mydzk Maly",
        "Malyy Midsk"
    ],
    "wof:name":"Malyy Myds'k",
    "wof:placetype":"locality"
},
  "geometry": {"coordinates":[26.18388,51.09348],"type":"Point"}
}