{
  "type": "Feature",
  "properties": {
    "gn:admin1_code":"13.0",
    "gn:asciiname":"Rozaleyevka",
    "gn:country_code":"UA",
    "gn:dem":174,
    "gn:feature_class":"P",
    "gn:feature_code":"PPL",
    "gn:name":"Rozaleyevka",
    "gn:population":0,
    "gn:timezone":"Europe/Kiev",
    "iso:country":"UA",
    "name:eng_x_preferred":[
        "Rozaleyevka"
    ],
    "name:rus_x_preferred":[
        "\u0420\u043e\u0437\u0430\u043b\u0438\u0435\u0432\u043a\u0430"
    ],
    "wof:name":"Rozaleyevka",
    "wof:placetype":"locality"
},
  "geometry": {"coordinates":[30.54066,49.8978],"type":"Point"}
}