{
  "type": "Feature",
  "properties": {
    "gn:admin1_code":"1.0",
    "gn:asciiname":"Semenovka",
    "gn:country_code":"UA",
    "gn:dem":164,
    "gn:feature_class":"P",
    "gn:feature_code":"PPL",
    "gn:name":"Sem\u00ebnovka",
    "gn:population":0,
    "gn:timezone":"Europe/Kiev",
    "iso:country":"UA",
    "wof:name":"Semenovka",
    "wof:placetype":"locality"
},
  "geometry": {"coordinates":[30.6858,49.29289],"type":"Point"}
}