{
  "type": "Feature",
  "properties": {
    "gn:admin1_code":"1.0",
    "gn:asciiname":"Yampol'",
    "gn:country_code":"UA",
    "gn:dem":126,
    "gn:feature_class":"P",
    "gn:feature_code":"PPL",
    "gn:name":"Yampol\u2019",
    "gn:population":0,
    "gn:timezone":"Europe/Kiev",
    "iso:country":"UA",
    "name:und_x_variant":[
        "Starostinskaya",
        "Yampol\u2019"
    ],
    "wof:name":"Yampol'",
    "wof:placetype":"locality"
},
  "geometry": {"coordinates":[30.97396,48.76442],"type":"Point"}
}