{
  "type": "Feature",
  "properties": {
    "iso:country":"UA",
    "name:eng_x_preferred":[
        "Cheresh"
    ],
    "name:hye_x_preferred":[
        "\u0549\u0565\u0580\u0565\u0577"
    ],
    "name:pol_x_preferred":[
        "Czeresz"
    ],
    "name:ron_x_preferred":[
        "Cire\u0219"
    ],
    "name:rus_x_preferred":[
        "\u0427\u0435\u0440\u0435\u0448"
    ],
    "name:ukr_x_preferred":[
        "\u0427\u0435\u0440\u0435\u0448"
    ],
    "qs:a0":"\u0423\u043a\u0440\u0430\u0457\u043d\u0430",
    "qs:a1":"*\u0427\u0435\u0440\u043d\u0456\u0432\u0435\u0446\u044c\u043a\u0430",
    "qs:a1_alt":"Chernivets'ka",
    "qs:a1r":"0",
    "qs:a2":"\u0421\u0442\u043e\u0440\u043e\u0436\u0438\u043d\u0435\u0446\u044c\u043a\u0438\u0439",
    "qs:a2_alt":"Storozhynets'kyi",
    "qs:adm0":"\u0423\u043a\u0440\u0430\u0457\u043d\u0430",
    "qs:la_lc":"*",
    "qs:level":"locality",
    "qs:loc":"\u0427\u0435\u0440\u0435\u0448",
    "qs:loc_alt":"Cheresh",
    "qs:pop":0,
    "qs:type":"buffered point",
    "wd:wordcount":42,
    "wof:name":"\u0427\u0435\u0440\u0435\u0448",
    "wof:placetype":"locality"
},
  "geometry": {"coordinates":[25.608282,48.098746],"type":"Point"}
}