{
  "type": "Feature",
  "properties": {
    "gn:admin1_code":"27.0",
    "gn:asciiname":"Yazhberen'",
    "gn:country_code":"UA",
    "gn:dem":138,
    "gn:feature_class":"P",
    "gn:feature_code":"PPL",
    "gn:name":"Yazhberen\u2019",
    "gn:population":0,
    "gn:timezone":"Europe/Kiev",
    "iso:country":"UA",
    "name:ukr_x_preferred":[
        "Yazhberen\u2019"
    ],
    "name:ukr_x_variant":[
        "\u042f\u0436\u0431\u0435\u0440\u0435\u043d\u044c"
    ],
    "name:und_x_variant":[
        "Pos\u00eblok Pervomayskiy",
        "Pervomayskiy"
    ],
    "wof:name":"Yazhberen'",
    "wof:placetype":"locality"
},
  "geometry": {"coordinates":[29.13415,51.25235],"type":"Point"}
}