{
  "type": "Feature",
  "properties": {
    "gn:admin1_code":"9.0",
    "gn:asciiname":"Rudnya Noven'ka",
    "gn:country_code":"UA",
    "gn:dem":242,
    "gn:feature_class":"P",
    "gn:feature_code":"PPL",
    "gn:name":"Rudnya Noven\u2019ka",
    "gn:population":0,
    "gn:timezone":"Europe/Kiev",
    "iso:country":"UA",
    "name:ukr_x_preferred":[
        "\u0420\u0443\u0434\u043d\u044f \u041d\u043e\u0432\u0435\u043d\u044c\u043a\u0430"
    ],
    "name:und_x_variant":[
        "Rudnya Noven\u2019ka",
        "Rudnya Noven\u2019kaya"
    ],
    "wof:name":"Rudnya Noven'ka",
    "wof:placetype":"locality"
},
  "geometry": {"coordinates":[27.18567,50.22054],"type":"Point"}
}