{
  "type": "Feature",
  "properties": {
    "gn:admin1_code":"5.0",
    "gn:asciiname":"Stepne",
    "gn:country_code":"UA",
    "gn:dem":144,
    "gn:feature_class":"P",
    "gn:feature_code":"PPL",
    "gn:name":"Stepne",
    "gn:population":0,
    "gn:timezone":"Europe/Kiev",
    "iso:country":"UA",
    "name:ukr_x_preferred":[
        "Stepne"
    ],
    "name:ukr_x_variant":[
        "\u0421\u0442\u0435\u043f\u043d\u0435"
    ],
    "name:und_x_variant":[
        "Malaya",
        "Stepnoye"
    ],
    "wof:name":"Stepne",
    "wof:placetype":"locality"
},
  "geometry": {"coordinates":[38.63361,47.68083],"type":"Point"}
}