{
  "type": "Feature",
  "properties": {
    "gn:admin1_code":"26.0",
    "gn:asciiname":"Nove Zaporizhzhya",
    "gn:country_code":"UA",
    "gn:dem":110,
    "gn:feature_class":"P",
    "gn:feature_code":"PPL",
    "gn:name":"Nove Zaporizhzhya",
    "gn:population":0,
    "gn:timezone":"Europe/Zaporozhye",
    "iso:country":"UA",
    "name:rus_x_preferred":[
        "Novoye Zaporozh\u2019ye"
    ],
    "name:rus_x_variant":[
        "\u041d\u043e\u0432\u043e\u0435 \u0417\u0430\u043f\u043e\u0440\u043e\u0436\u044c\u0435"
    ],
    "name:ukr_x_preferred":[
        "Nove Zaporizhzhya"
    ],
    "name:ukr_x_variant":[
        "\u041d\u043e\u0432\u0435 \u0417\u0430\u043f\u043e\u0440\u0456\u0436\u0436\u044f"
    ],
    "name:und_x_variant":[
        "Novo-Zaporozh\u2019ye",
        "Khortitsa"
    ],
    "wof:name":"Nove Zaporizhzhya",
    "wof:placetype":"locality"
},
  "geometry": {"coordinates":[34.93457,47.82809],"type":"Point"}
}