{
  "type": "Feature",
  "properties": {
    "gn:admin1_code":"22.0",
    "gn:asciiname":"Novyye Petlikovtsy",
    "gn:country_code":"UA",
    "gn:dem":355,
    "gn:feature_class":"P",
    "gn:feature_code":"PPL",
    "gn:name":"Novyye Petlikovtsy",
    "gn:population":0,
    "gn:timezone":"Europe/Kiev",
    "iso:country":"UA",
    "name:und_x_variant":[
        "Novi Petlykivtsi",
        "Novyye Petlikovtsy"
    ],
    "wof:name":"Novyye Petlikovtsy",
    "wof:placetype":"locality"
},
  "geometry": {"coordinates":[25.45781,49.16497],"type":"Point"}
}