{
  "type": "Feature",
  "properties": {
    "gn:admin1_code":"10.0",
    "gn:asciiname":"Myronivka",
    "gn:country_code":"UA",
    "gn:dem":122,
    "gn:feature_class":"P",
    "gn:feature_code":"PPL",
    "gn:name":"Myronivka",
    "gn:population":0,
    "gn:timezone":"Europe/Kiev",
    "iso:country":"UA",
    "name:eng_x_preferred":[
        "Mironovka"
    ],
    "name:rus_x_preferred":[
        "\u041c\u0438\u0440\u043e\u043d\u043e\u0432\u043a\u0430"
    ],
    "name:ukr_x_preferred":[
        "Myronivka"
    ],
    "name:ukr_x_variant":[
        "\u041c\u0438\u0440\u043e\u043d\u0456\u0432\u043a\u0430"
    ],
    "name:und_x_variant":[
        "Mironovka"
    ],
    "wof:name":"Myronivka",
    "wof:placetype":"locality"
},
  "geometry": {"coordinates":[33.11762,48.90453],"type":"Point"}
}