{
  "type": "Feature",
  "properties": {
    "gn:admin1_code":"21.0",
    "gn:asciiname":"Danilovka",
    "gn:country_code":"UA",
    "gn:dem":131,
    "gn:feature_class":"P",
    "gn:feature_code":"PPL",
    "gn:name":"Danilovka",
    "gn:population":0,
    "gn:timezone":"Europe/Kiev",
    "iso:country":"UA",
    "wof:name":"Danilovka",
    "wof:placetype":"locality"
},
  "geometry": {"coordinates":[35.15,51.01667],"type":"Point"}
}