{
  "type": "Feature",
  "properties": {
    "gn:admin1_code":"9.0",
    "gn:asciiname":"Maydan-Verbetskiy",
    "gn:country_code":"UA",
    "gn:dem":327,
    "gn:feature_class":"P",
    "gn:feature_code":"PPL",
    "gn:name":"Maydan-Verbetskiy",
    "gn:population":0,
    "gn:timezone":"Europe/Kiev",
    "iso:country":"UA",
    "wof:name":"Maydan-Verbetskiy",
    "wof:placetype":"locality"
},
  "geometry": {"coordinates":[27.78597,49.36618],"type":"Point"}
}