{
  "type": "Feature",
  "properties": {
    "gn:admin1_code":"21.0",
    "gn:asciiname":"Volyntsivs'ke",
    "gn:country_code":"UA",
    "gn:dem":133,
    "gn:feature_class":"P",
    "gn:feature_code":"PPL",
    "gn:name":"Volyntsivs\u2019ke",
    "gn:population":0,
    "gn:timezone":"Europe/Kiev",
    "iso:country":"UA",
    "name:ukr_x_preferred":[
        "Volyntsivs\u2019ke"
    ],
    "name:ukr_x_variant":[
        "\u0412\u043e\u043b\u0438\u043d\u0446\u0456\u0432\u0441\u044c\u043a\u0435"
    ],
    "name:und_x_variant":[
        "Volyntsevskoye"
    ],
    "wof:name":"Volyntsivs'ke",
    "wof:placetype":"locality"
},
  "geometry": {"coordinates":[34.01021,51.27402],"type":"Point"}
}