{
  "type": "Feature",
  "properties": {
    "gn:admin1_code":"4.0",
    "gn:asciiname":"Koshove",
    "gn:country_code":"UA",
    "gn:dem":81,
    "gn:feature_class":"P",
    "gn:feature_code":"PPL",
    "gn:name":"Koshove",
    "gn:population":0,
    "gn:timezone":"Europe/Kiev",
    "iso:country":"UA",
    "name:ukr_x_preferred":[
        "Koshove"
    ],
    "name:ukr_x_variant":[
        "\u041a\u043e\u0448\u043e\u0432\u0435"
    ],
    "name:und_x_variant":[
        "Koshovoy"
    ],
    "wof:name":"Koshove",
    "wof:placetype":"locality"
},
  "geometry": {"coordinates":[33.42890999999999,47.55567],"type":"Point"}
}