{
  "type": "Feature",
  "properties": {
    "gn:admin1_code":"14.0",
    "gn:asciiname":"Malomykolayivka",
    "gn:country_code":"UA",
    "gn:dem":191,
    "gn:feature_class":"P",
    "gn:feature_code":"PPL",
    "gn:name":"Malomykolayivka",
    "gn:population":0,
    "gn:timezone":"Europe/Zaporozhye",
    "iso:country":"UA",
    "name:eng_x_preferred":[
        "Malonikolayevka"
    ],
    "name:rus_x_preferred":[
        "\u041c\u0430\u043b\u043e\u043d\u0438\u043a\u043e\u043b\u0430\u0435\u0432\u043a\u0430"
    ],
    "name:ukr_x_preferred":[
        "Malomykolayivka"
    ],
    "name:ukr_x_variant":[
        "\u041c\u0430\u043b\u043e\u043c\u0438\u043a\u043e\u043b\u0430\u0457\u0432\u043a\u0430"
    ],
    "name:und_x_variant":[
        "Malaya Nikolayevka",
        "Malonokolayevka",
        "Malonikolayevka"
    ],
    "wof:name":"Malomykolayivka",
    "wof:placetype":"locality"
},
  "geometry": {"coordinates":[39.02709,48.3098],"type":"Point"}
}