{
  "type": "Feature",
  "properties": {
    "iso:country":"UA",
    "name:bel_x_preferred":[
        "\u0422\u044d\u0430\u0444\u0456\u043f\u0430\u043b\u044c"
    ],
    "name:ces_x_preferred":[
        "Teofipol"
    ],
    "name:che_x_preferred":[
        "\u0422\u0435\u043e\u0444\u0438\u043f\u043e\u043b\u044c"
    ],
    "name:crh_x_preferred":[
        "Teofipol"
    ],
    "name:deu_x_preferred":[
        "Teofipol"
    ],
    "name:eng_x_preferred":[
        "Teofipol"
    ],
    "name:fra_x_preferred":[
        "T\u00e9ofipol"
    ],
    "name:heb_x_preferred":[
        "\u05d8\u05d0\u05d5\u05e4\u05d9\u05e4\u05d5\u05dc"
    ],
    "name:hye_x_preferred":[
        "\u054f\u0565\u0578\u0586\u056b\u057a\u0578\u056c"
    ],
    "name:lat_x_preferred":[
        "Teofipolis"
    ],
    "name:lit_x_preferred":[
        "Teofipolis"
    ],
    "name:mhr_x_preferred":[
        "\u0422\u0435\u043e\u0444\u0438\u043f\u043e\u043b\u044c"
    ],
    "name:nld_x_preferred":[
        "Teofipol"
    ],
    "name:pol_x_preferred":[
        "Teofipol"
    ],
    "name:ron_x_preferred":[
        "Teofipol"
    ],
    "name:rus_x_preferred":[
        "\u0422\u0435\u043e\u0444\u0438\u043f\u043e\u043b\u044c"
    ],
    "name:ukr_x_preferred":[
        "\u0422\u0435\u043e\u0444\u0456\u043f\u043e\u043b\u044c"
    ],
    "name:und_x_variant":[
        "Teotipol\u2019"
    ],
    "name:uzb_x_preferred":[
        "Teofipol"
    ],
    "name:yid_x_preferred":[
        "\u05d8\u05e9\u05d0\u05df"
    ],
    "name:zho_x_preferred":[
        "\u6377\u5967\u83f2\u6ce2\u5229"
    ],
    "qs:a0":"\u0423\u043a\u0440\u0430\u0457\u043d\u0430",
    "qs:a1":"*\u0425\u043c\u0435\u043b\u044c\u043d\u0438\u0446\u044c\u043a\u0430",
    "qs:a1_alt":"Khmel'nyts'ka",
    "qs:a1r":"0",
    "qs:a2":"\u0422\u0435\u043e\u0444\u0456\u043f\u043e\u043b\u044c\u0441\u044c\u043a\u0438\u0439",
    "qs:a2_alt":"Teofipol's'kyi",
    "qs:adm0":"\u0423\u043a\u0440\u0430\u0457\u043d\u0430",
    "qs:la_lc":"*",
    "qs:level":"locality",
    "qs:loc":"\u0422\u0435\u043e\u0444\u0456\u043f\u043e\u043b\u044c",
    "qs:loc_alt":"Teofipol",
    "qs:pop":0,
    "qs:type":"buffered point",
    "wd:wordcount":143,
    "wof:name":"\u0422\u0435\u043e\u0444\u0456\u043f\u043e\u043b\u044c",
    "wof:placetype":"locality"
},
  "geometry": {"coordinates":[26.413401,49.844369],"type":"Point"}
}