{
  "type": "Feature",
  "properties": {
    "iso:country":"UA",
    "name:eng_x_preferred":[
        "Budishche"
    ],
    "name:rus_x_preferred":[
        "\u0411\u0443\u0434\u0438\u0449\u0435"
    ],
    "qs:a0":"\u0423\u043a\u0440\u0430\u0457\u043d\u0430",
    "qs:a1":"*\u0427\u0435\u0440\u043a\u0430\u0441\u044c\u043a\u0430",
    "qs:a1_alt":"Cherkas'ka",
    "qs:a1r":"0",
    "qs:a2":"\u0427\u0435\u0440\u043a\u0430\u0441\u044c\u043a\u0438\u0439",
    "qs:a2_alt":"Cherkas'kyi",
    "qs:adm0":"\u0423\u043a\u0440\u0430\u0457\u043d\u0430",
    "qs:la_lc":"*",
    "qs:level":"locality",
    "qs:loc":"\u0411\u0443\u0434\u0438\u0449\u0435",
    "qs:loc_alt":"Budysche",
    "qs:pop":0,
    "qs:type":"buffered point",
    "wof:name":"\u0411\u0443\u0434\u0438\u0449\u0435",
    "wof:placetype":"locality"
},
  "geometry": {"coordinates":[31.830887,49.521188],"type":"Point"}
}