{
  "type": "Feature",
  "properties": {
    "gn:admin1_code":"2.0",
    "gn:asciiname":"IIvashkivka",
    "gn:country_code":"UA",
    "gn:dem":128,
    "gn:feature_class":"P",
    "gn:feature_code":"PPL",
    "gn:name":"IIvashkivka",
    "gn:population":0,
    "gn:timezone":"Europe/Kiev",
    "iso:country":"UA",
    "name:eng_x_preferred":[
        "Ivashkovka"
    ],
    "name:rus_x_preferred":[
        "\u0418\u0432\u0430\u0448\u043a\u043e\u0432\u043a\u0430"
    ],
    "name:ukr_x_preferred":[
        "IIvashkivka"
    ],
    "name:ukr_x_variant":[
        "\u0406\u0432\u0430\u0448\u043a\u0456\u0432\u043a\u0430"
    ],
    "name:und_x_variant":[
        "Ivashkovka"
    ],
    "wof:name":"IIvashkivka",
    "wof:placetype":"locality"
},
  "geometry": {"coordinates":[31.43252,51.70235],"type":"Point"}
}