{
  "type": "Feature",
  "properties": {
    "gn:admin1_code":"21.0",
    "gn:asciiname":"Velyki Luky",
    "gn:country_code":"UA",
    "gn:dem":142,
    "gn:feature_class":"P",
    "gn:feature_code":"PPL",
    "gn:name":"Velyki Luky",
    "gn:population":0,
    "gn:timezone":"Europe/Kiev",
    "iso:country":"UA",
    "name:ukr_x_preferred":[
        "Velyki Luky"
    ],
    "name:ukr_x_variant":[
        "\u0412\u0435\u043b\u0438\u043a\u0456 \u041b\u0443\u043a\u0438"
    ],
    "name:und_x_variant":[
        "Imeni Shevchenko",
        "Velikiye Luki"
    ],
    "wof:name":"Velyki Luky",
    "wof:placetype":"locality"
},
  "geometry": {"coordinates":[34.16004,50.7464],"type":"Point"}
}