{
  "type": "Feature",
  "properties": {
    "gn:admin1_code":"3.0",
    "gn:asciiname":"Byalobereska",
    "gn:country_code":"UA",
    "gn:dem":482,
    "gn:feature_class":"P",
    "gn:feature_code":"PPL",
    "gn:name":"Byalobereska",
    "gn:population":0,
    "gn:timezone":"Europe/Kiev",
    "iso:country":"UA",
    "name:und_x_variant":[
        "Belober\u00ebzka"
    ],
    "wof:name":"Byalobereska",
    "wof:placetype":"locality"
},
  "geometry": {"coordinates":[25.05516,48.15164],"type":"Point"}
}