{
  "type": "Feature",
  "properties": {
    "gn:admin1_code":"7.0",
    "gn:asciiname":"Komunar",
    "gn:country_code":"UA",
    "gn:dem":152,
    "gn:feature_class":"P",
    "gn:feature_code":"PPL",
    "gn:name":"Komunar",
    "gn:population":0,
    "gn:timezone":"Europe/Kiev",
    "iso:country":"UA",
    "name:ukr_x_preferred":[
        "Komunar"
    ],
    "name:ukr_x_variant":[
        "\u041a\u043e\u043c\u0443\u043d\u0430\u0440"
    ],
    "wof:name":"Komunar",
    "wof:placetype":"locality"
},
  "geometry": {"coordinates":[36.00917000000001,49.9592],"type":"Point"}
}