{
  "type": "Feature",
  "properties": {
    "gn:admin1_code":"7.0",
    "gn:asciiname":"Zabaryne",
    "gn:country_code":"UA",
    "gn:dem":91,
    "gn:feature_class":"P",
    "gn:feature_code":"PPL",
    "gn:name":"Zabaryne",
    "gn:population":0,
    "gn:timezone":"Europe/Kiev",
    "iso:country":"UA",
    "name:rus_x_preferred":[
        "\u0417\u0430\u0431\u0430\u0440\u0438\u043d\u043e"
    ],
    "name:ukr_x_preferred":[
        "Zabaryne"
    ],
    "name:ukr_x_variant":[
        "\u0417\u0430\u0431\u0430\u0440\u0438\u043d\u0435"
    ],
    "name:und_x_variant":[
        "Brodshchyna",
        "Zabarinskaya",
        "Zabarino"
    ],
    "wof:name":"Zabaryne",
    "wof:placetype":"locality"
},
  "geometry": {"coordinates":[35.41656,49.17219],"type":"Point"}
}