{
  "type": "Feature",
  "properties": {
    "gn:admin1_code":"17.0",
    "gn:asciiname":"Minyaylivka",
    "gn:country_code":"UA",
    "gn:dem":46,
    "gn:feature_class":"P",
    "gn:feature_code":"PPL",
    "gn:name":"Minyaylivka",
    "gn:population":0,
    "gn:timezone":"Europe/Kiev",
    "iso:country":"UA",
    "name:ukr_x_preferred":[
        "Minyaylivka"
    ],
    "name:und_x_variant":[
        "Manza",
        "Menyaylovka",
        "Manzha",
        "Mania"
    ],
    "wof:name":"Minyaylivka",
    "wof:placetype":"locality"
},
  "geometry": {"coordinates":[29.52051,46.37336],"type":"Point"}
}