{
  "type": "Feature",
  "properties": {
    "gn:admin1_code":"23.0",
    "gn:asciiname":"Paliivka",
    "gn:country_code":"UA",
    "gn:dem":352,
    "gn:feature_class":"P",
    "gn:feature_code":"PPL",
    "gn:name":"Paliivka",
    "gn:population":0,
    "gn:timezone":"Europe/Kiev",
    "iso:country":"UA",
    "name:und_x_variant":[
        "Pavlivka",
        "Paliivka"
    ],
    "wof:name":"Paliivka",
    "wof:placetype":"locality"
},
  "geometry": {"coordinates":[27.69082,49.02459],"type":"Point"}
}