{
  "type": "Feature",
  "properties": {
    "gn:admin1_code":"24.0",
    "gn:asciiname":"Prokhody",
    "gn:country_code":"UA",
    "gn:dem":145,
    "gn:feature_class":"P",
    "gn:feature_code":"PPL",
    "gn:name":"Prokhody",
    "gn:population":0,
    "gn:timezone":"Europe/Kiev",
    "iso:country":"UA",
    "name:ukr_x_preferred":[
        "Prokhody"
    ],
    "name:ukr_x_variant":[
        "\u041f\u0440\u043e\u0445\u043e\u0434\u0438"
    ],
    "wof:name":"Prokhody",
    "wof:placetype":"locality"
},
  "geometry": {"coordinates":[25.4674,51.78926],"type":"Point"}
}