{
  "type": "Feature",
  "properties": {
    "gn:admin1_code":"27.0",
    "gn:asciiname":"Kovanka",
    "gn:country_code":"UA",
    "gn:dem":185,
    "gn:feature_class":"P",
    "gn:feature_code":"PPL",
    "gn:name":"Kovanka",
    "gn:population":0,
    "gn:timezone":"Europe/Kiev",
    "iso:country":"UA",
    "name:ukr_x_preferred":[
        "\u041a\u043e\u0432\u0430\u043d\u043a\u0430"
    ],
    "name:und_x_variant":[
        "Rudnya Kovanka",
        "Kovanka"
    ],
    "wof:name":"Kovanka",
    "wof:placetype":"locality"
},
  "geometry": {"coordinates":[28.09406,51.38853],"type":"Point"}
}