{
  "type": "Feature",
  "properties": {
    "gn:admin1_code":"18.0",
    "gn:asciiname":"Rymyhy",
    "gn:country_code":"UA",
    "gn:dem":137,
    "gn:feature_class":"P",
    "gn:feature_code":"PPL",
    "gn:name":"Rymyhy",
    "gn:population":0,
    "gn:timezone":"Europe/Kiev",
    "iso:country":"UA",
    "name:ukr_x_preferred":[
        "Rymyhy"
    ],
    "name:ukr_x_variant":[
        "\u0420\u0438\u043c\u0438\u0433\u0438"
    ],
    "wof:name":"Rymyhy",
    "wof:placetype":"locality"
},
  "geometry": {"coordinates":[33.89102,49.73947],"type":"Point"}
}