{
  "type": "Feature",
  "properties": {
    "gn:admin1_code":"27.0",
    "gn:asciiname":"Kurchytsya",
    "gn:country_code":"UA",
    "gn:dem":191,
    "gn:feature_class":"P",
    "gn:feature_code":"PPL",
    "gn:name":"Kurchytsya",
    "gn:population":0,
    "gn:timezone":"Europe/Kiev",
    "iso:country":"UA",
    "name:ukr_x_preferred":[
        "Kurchytsya"
    ],
    "name:ukr_x_variant":[
        "\u041a\u0443\u0440\u0447\u0438\u0446\u044f"
    ],
    "name:und_x_variant":[
        "Kurchitsy",
        "Kurchitsa"
    ],
    "wof:name":"Kurchytsya",
    "wof:placetype":"locality"
},
  "geometry": {"coordinates":[27.43799000000001,50.75951],"type":"Point"}
}