{
  "type": "Feature",
  "properties": {
    "iso:country":"UA",
    "name:che_x_preferred":[
        "\u0413\u0435\u0447\u0430"
    ],
    "name:deu_x_preferred":[
        "Job von Telmessos"
    ],
    "name:eng_x_preferred":[
        "Gecha"
    ],
    "name:epo_x_preferred":[
        "He\u0109a"
    ],
    "name:fin_x_preferred":[
        "H\u0435t\u0161\u0430"
    ],
    "name:fra_x_preferred":[
        "Job Getcha"
    ],
    "name:hun_x_preferred":[
        "Mez\u0151gecse"
    ],
    "name:hye_x_preferred":[
        "\u0533\u0565\u0579\u0561"
    ],
    "name:nan_x_preferred":[
        "Hecha"
    ],
    "name:nld_x_preferred":[
        "Mez\u0151gecse"
    ],
    "name:nno_x_preferred":[
        "Hetsja"
    ],
    "name:nob_x_preferred":[
        "Hetsja"
    ],
    "name:pol_x_preferred":[
        "Hiob"
    ],
    "name:ron_x_preferred":[
        "Hecea"
    ],
    "name:rus_x_preferred":[
        "\u0418\u043e\u0432"
    ],
    "name:rus_x_variant":[
        "\u0413\u0435\u0447\u0430"
    ],
    "name:swe_x_preferred":[
        "Job Getcha"
    ],
    "name:ukr_x_preferred":[
        "Hecha"
    ],
    "name:ukr_x_variant":[
        "\u0413\u0435\u0447\u0430"
    ],
    "name:zho_x_preferred":[
        "\u5091\u6070"
    ],
    "qs:a0":"\u0423\u043a\u0440\u0430\u0457\u043d\u0430",
    "qs:a1":"*\u0417\u0430\u043a\u0430\u0440\u043f\u0430\u0442\u0441\u044c\u043a\u0430",
    "qs:a1_alt":"Zakarpats'ka",
    "qs:a1r":"0",
    "qs:a2":"\u0411\u0435\u0440\u0435\u0433\u0456\u0432\u0441\u044c\u043a\u0438\u0439",
    "qs:a2_alt":"Berehivs'kyi",
    "qs:adm0":"\u0423\u043a\u0440\u0430\u0457\u043d\u0430",
    "qs:la_lc":"*",
    "qs:level":"locality",
    "qs:loc":"\u0413\u0435\u0447\u0430",
    "qs:loc_alt":"Hecha",
    "qs:pop":0,
    "qs:type":"buffered point",
    "wd:wordcount":381,
    "wof:name":"\u0413\u0435\u0447\u0430",
    "wof:placetype":"locality"
},
  "geometry": {"coordinates":[22.654486,48.139359],"type":"Point"}
}