{
  "type": "Feature",
  "properties": {
    "gn:admin1_code":"10.0",
    "gn:asciiname":"Perekhrestivka",
    "gn:country_code":"UA",
    "gn:dem":99,
    "gn:feature_class":"P",
    "gn:feature_code":"PPL",
    "gn:name":"Perekhrestivka",
    "gn:population":0,
    "gn:timezone":"Europe/Kiev",
    "iso:country":"UA",
    "name:ukr_x_preferred":[
        "Perekhrestivka"
    ],
    "name:ukr_x_variant":[
        "\u041f\u0435\u0440\u0435\u0445\u0440\u0435\u0441\u0442\u0456\u0432\u043a\u0430"
    ],
    "wof:name":"Perekhrestivka",
    "wof:placetype":"locality"
},
  "geometry": {"coordinates":[33.05303,48.98982],"type":"Point"}
}