{
  "type": "Feature",
  "properties": {
    "iso:country":"UA",
    "name:und_x_variant":[
        "Monasterchany"
    ],
    "qs:a0":"\u0423\u043a\u0440\u0430\u0457\u043d\u0430",
    "qs:a1":"*\u0406\u0432\u0430\u043d\u043e-\u0424\u0440\u0430\u043d\u043a\u0456\u0432\u0441\u044c\u043a\u0430",
    "qs:a1_alt":"Ivano-Frankivs'ka",
    "qs:a1r":"0",
    "qs:a2":"\u0411\u043e\u0433\u043e\u0440\u043e\u0434\u0447\u0430\u043d\u0441\u044c\u043a\u0438\u0439",
    "qs:a2_alt":"Bohorodchans'kyi",
    "qs:adm0":"\u0423\u043a\u0440\u0430\u0457\u043d\u0430",
    "qs:la_lc":"*",
    "qs:level":"locality",
    "qs:loc":"\u041c\u043e\u043d\u0430\u0441\u0442\u0438\u0440\u0447\u0430\u043d\u0438",
    "qs:loc_alt":"Monastyrchany",
    "qs:pop":0,
    "qs:type":"buffered point",
    "wof:name":"\u041c\u043e\u043d\u0430\u0441\u0442\u0438\u0440\u0447\u0430\u043d\u0438",
    "wof:placetype":"locality"
},
  "geometry": {"coordinates":[24.460862,48.71762],"type":"Point"}
}