{
  "type": "Feature",
  "properties": {
    "iso:country":"UA",
    "name:deu_x_preferred":[
        "Perechrestowe Persche"
    ],
    "name:eng_x_preferred":[
        "Perekhrestove Pershe"
    ],
    "name:lav_x_preferred":[
        "Perehrestove Per\u0161e"
    ],
    "name:ron_x_preferred":[
        "Perehrestove Per\u0219e"
    ],
    "name:rus_x_preferred":[
        "\u041f\u0435\u0440\u0435\u043a\u0440\u0435\u0441\u0442\u043e\u0432\u043e \u041f\u0435\u0440\u0432\u043e\u0435"
    ],
    "name:ukr_x_preferred":[
        "Perekhrestove Pershe"
    ],
    "name:ukr_x_variant":[
        "\u041f\u0435\u0440\u0435\u0445\u0440\u0435\u0441\u0442\u043e\u0432\u0435 \u041f\u0435\u0440\u0448\u0435"
    ],
    "name:und_x_variant":[
        "Perekrestovo"
    ],
    "name:zho_x_preferred":[
        "\u4f69\u5217\u8d6b\u5217\u65af\u6258\u97cb\u4f69\u723e\u820d"
    ],
    "qs:a0":"\u0423\u043a\u0440\u0430\u0457\u043d\u0430",
    "qs:a1":"*\u041e\u0434\u0435\u0441\u044c\u043a\u0430",
    "qs:a1_alt":"Odes'ka",
    "qs:a1r":"0",
    "qs:a2":"\u0424\u0440\u0443\u043d\u0437\u0456\u0432\u0441\u044c\u043a\u0438\u0439",
    "qs:a2_alt":"Frunzivs'kyi",
    "qs:adm0":"\u0423\u043a\u0440\u0430\u0457\u043d\u0430",
    "qs:la_lc":"*",
    "qs:level":"locality",
    "qs:loc":"\u041f\u0435\u0440\u0435\u0445\u0440\u0435\u0441\u0442\u043e\u0432\u0435 \u041f\u0435\u0440\u0448\u0435",
    "qs:loc_alt":"Perekhrestove Pershe",
    "qs:pop":0,
    "qs:type":"buffered point",
    "wd:wordcount":264,
    "wof:name":"\u041f\u0435\u0440\u0435\u0445\u0440\u0435\u0441\u0442\u043e\u0432\u0435 \u041f\u0435\u0440\u0448\u0435",
    "wof:placetype":"locality"
},
  "geometry": {"coordinates":[29.769038,47.442352],"type":"Point"}
}