{
  "type": "Feature",
  "properties": {
    "gn:admin1_code":"5.0",
    "gn:admin2_code":"689196",
    "gn:asciiname":"Novomykolayivka",
    "gn:country_code":"UA",
    "gn:dem":201,
    "gn:elevation":"194.0",
    "gn:feature_class":"P",
    "gn:feature_code":"PPL",
    "gn:name":"Novomykolayivka",
    "gn:population":162,
    "gn:timezone":"Europe/Kiev",
    "iso:country":"UA",
    "name:deu_x_preferred":[
        "Nowomykolajiwka"
    ],
    "name:fra_x_preferred":[
        "Novomykola\u00efvka"
    ],
    "name:rus_x_historical":[
        "Kamenevo"
    ],
    "name:rus_x_preferred":[
        "Kamenevo"
    ],
    "name:rus_x_variant":[
        "\u041d\u043e\u0432\u043e\u043d\u0438\u043a\u043e\u043b\u0430\u0435\u0432\u043a\u0430",
        "Nowonikolajewka",
        "Nowonikolaewka"
    ],
    "name:ukr_x_preferred":[
        "\u041d\u043e\u0432\u043e\u043c\u0438\u043a\u043e\u043b\u0430\u0457\u0432\u043a\u0430"
    ],
    "name:ukr_x_variant":[
        "Novomykolajivka",
        "Novomykolaivka"
    ],
    "wof:name":"Novomykolayivka",
    "wof:placetype":"locality",
    "wof:population":162
},
  "geometry": {"coordinates":[37.38889,47.43944000000001],"type":"Point"}
}