{
  "type": "Feature",
  "properties": {
    "gn:admin1_code":"21.0",
    "gn:asciiname":"Stara Sharpivka",
    "gn:country_code":"UA",
    "gn:dem":131,
    "gn:feature_class":"P",
    "gn:feature_code":"PPL",
    "gn:name":"Stara Sharpivka",
    "gn:population":0,
    "gn:timezone":"Europe/Kiev",
    "iso:country":"UA",
    "name:ukr_x_preferred":[
        "Stara Sharpivka"
    ],
    "name:ukr_x_variant":[
        "\u0421\u0442\u0430\u0440\u0430 \u0428\u0430\u0440\u043f\u0456\u0432\u043a\u0430"
    ],
    "name:und_x_variant":[
        "Staraya",
        "Staraya Sharapovka",
        "Staraya Sharpovka"
    ],
    "wof:name":"Stara Sharpivka",
    "wof:placetype":"locality"
},
  "geometry": {"coordinates":[33.71955999999999,51.41025],"type":"Point"}
}