{
  "type": "Feature",
  "properties": {
    "gn:admin1_code":"7.0",
    "gn:asciiname":"Lozovaya Pervaya",
    "gn:country_code":"UA",
    "gn:dem":130,
    "gn:feature_class":"P",
    "gn:feature_code":"PPL",
    "gn:name":"Lozovaya Pervaya",
    "gn:population":0,
    "gn:timezone":"Europe/Kiev",
    "iso:country":"UA",
    "wof:name":"Lozovaya Pervaya",
    "wof:placetype":"locality"
},
  "geometry": {"coordinates":[37.49694,49.88917],"type":"Point"}
}