{
  "type": "Feature",
  "properties": {
    "gn:gn_country":"UA",
    "gn:gn_fcode":"PPL",
    "gn:gn_pop":6481,
    "gn:population":6481,
    "iso:country":"UA",
    "name:pol_x_preferred":[
        "Husiatyn"
    ],
    "name:rus_x_preferred":[
        "\u0413\u0443\u0441\u044f\u0442\u0438\u043d"
    ],
    "name:ukr_x_preferred":[
        "\u0413\u0443\u0441\u044f\u0442\u0438\u043d"
    ],
    "name:unk_x_variant":[
        "Gusyatin"
    ],
    "qs_pg:aaroncc":"UA",
    "qs_pg:gn_country":"UA",
    "qs_pg:gn_fcode":"PPL",
    "qs_pg:gn_pop":6481,
    "qs_pg:name":"Husyatyn",
    "qs_pg:photos_9r":0,
    "qs_pg:photos_sr":0,
    "qs_pg:pop_sr":5,
    "qs_pg:qs_pg_placetype":"locality",
    "wof:name":"Husyatyn",
    "wof:placetype":"locality",
    "wof:population":6481
},
  "geometry": {"coordinates":[26.2141,49.07263],"type":"Point"}
}