{
  "type": "Feature",
  "properties": {
    "gn:admin1_code":"15.0",
    "gn:asciiname":"Novo-Aleksandrovka",
    "gn:country_code":"UA",
    "gn:dem":182,
    "gn:feature_class":"P",
    "gn:feature_code":"PPL",
    "gn:name":"Novo-Aleksandrovka",
    "gn:population":0,
    "gn:timezone":"Europe/Zaporozhye",
    "iso:country":"UA",
    "wof:name":"Novo-Aleksandrovka",
    "wof:placetype":"locality"
},
  "geometry": {"coordinates":[39.48944,47.86861],"type":"Point"}
}