{
  "type": "Feature",
  "properties": {
    "gn:country":"UA",
    "gn:fcode":"PPL",
    "gn:population":6917,
    "iso:country":"UA",
    "name:cat_x_preferred":[
        "Starob\u00e9ixeve"
    ],
    "name:ceb_x_preferred":[
        "Starobesheve"
    ],
    "name:ces_x_preferred":[
        "Starobe\u0161eve"
    ],
    "name:crh_x_preferred":[
        "Starobe\u015feve"
    ],
    "name:deu_x_preferred":[
        "Starobeschewe"
    ],
    "name:eng_x_preferred":[
        "Starobesheve"
    ],
    "name:est_x_preferred":[
        "Starobe\u0161eve"
    ],
    "name:fra_x_preferred":[
        "Starobecheve"
    ],
    "name:ita_x_preferred":[
        "Starobe\u0161eve"
    ],
    "name:jpn_x_preferred":[
        "\u30b9\u30bf\u30ed\u30d9\u30b7\u30a7\u30f4\u30a7"
    ],
    "name:lav_x_preferred":[
        "Starobe\u0161eve"
    ],
    "name:pol_x_preferred":[
        "Starobeszewe"
    ],
    "name:rus_x_preferred":[
        "\u0421\u0442\u0430\u0440\u043e\u0431\u0435\u0448\u0435\u0432\u043e"
    ],
    "name:rus_x_variant":[
        "\u0421\u0442\u0430\u0440\u043e\u0431\u0435\u0448\u0435\u0432\u0435"
    ],
    "name:spa_x_preferred":[
        "Starob\u00e9sheve"
    ],
    "name:tat_x_preferred":[
        "\u0421\u0442\u0430\u0440\u043e\u0431\u0435\u0448\u0435\u0432\u0435"
    ],
    "name:ukr_x_preferred":[
        "\u0421\u0442\u0430\u0440\u043e\u0431\u0435\u0448\u0435\u0432\u0435"
    ],
    "name:und_x_variant":[
        "Staroye Beshevo"
    ],
    "name:zho_x_preferred":[
        "\u65af\u5854\u62c9\u5225\u820d\u97cb"
    ],
    "qs_pg:aaroncc":"UA",
    "qs_pg:gn_country":"UA",
    "qs_pg:gn_fcode":"PPL",
    "qs_pg:gn_pop":6917,
    "qs_pg:name":"Starobeshevo",
    "qs_pg:name_adm0":"Ukraine",
    "qs_pg:name_adm1":"Donets\u00b4ka Oblast\u00b4",
    "qs_pg:photos_9k":1,
    "qs_pg:photos_9r":1,
    "qs_pg:photos_all":1,
    "qs_pg:photos_sr":0,
    "qs_pg:pop_sr":5,
    "qs_pg:qs_pg_placetype":"locality",
    "qs_pg:qs_pg_placetype_gp":"Town",
    "qs_pg:woe_adm0":23424976,
    "woe:adm0_id":23424976,
    "woe:name_adm0":"Ukraine",
    "woe:name_adm1":"Donets\u00b4ka Oblast\u00b4",
    "woe:placetype":"Town",
    "wof:name":"Starobeshevo",
    "wof:placetype":"locality",
    "wof:population":6917
},
  "geometry": {"coordinates":[38.03051,47.75038],"type":"Point"}
}