{
  "type": "Feature",
  "properties": {
    "gn:admin1_code":"13.0",
    "gn:asciiname":"Rozhiv",
    "gn:country_code":"UA",
    "gn:dem":158,
    "gn:feature_class":"P",
    "gn:feature_code":"PPL",
    "gn:name":"Rozhiv",
    "gn:population":0,
    "gn:timezone":"Europe/Kiev",
    "iso:country":"UA",
    "name:ukr_x_preferred":[
        "Rozhiv"
    ],
    "name:ukr_x_variant":[
        "\u0420\u043e\u0436\u0456\u0432"
    ],
    "name:und_x_variant":[
        "Rozhev"
    ],
    "wof:name":"Rozhiv",
    "wof:placetype":"locality"
},
  "geometry": {"coordinates":[29.65056,50.38444000000001],"type":"Point"}
}