{
  "type": "Feature",
  "properties": {
    "gn:admin1_code":"14.0",
    "gn:asciiname":"Luhove",
    "gn:country_code":"UA",
    "gn:dem":113,
    "gn:feature_class":"P",
    "gn:feature_code":"PPL",
    "gn:name":"Luhove",
    "gn:population":0,
    "gn:timezone":"Europe/Zaporozhye",
    "iso:country":"UA",
    "name:ukr_x_preferred":[
        "Luhove"
    ],
    "name:ukr_x_variant":[
        "\u041b\u0443\u0433\u043e\u0432\u0435"
    ],
    "name:und_x_variant":[
        "Lugovoye"
    ],
    "wof:name":"Luhove",
    "wof:placetype":"locality"
},
  "geometry": {"coordinates":[38.56204,49.87712],"type":"Point"}
}