{
  "type": "Feature",
  "properties": {
    "gn:admin1_code":"2.0",
    "gn:asciiname":"Revuniv Kruh",
    "gn:country_code":"UA",
    "gn:dem":138,
    "gn:feature_class":"P",
    "gn:feature_code":"PPL",
    "gn:name":"Revuniv Kruh",
    "gn:population":0,
    "gn:timezone":"Europe/Kiev",
    "iso:country":"UA",
    "name:ukr_x_preferred":[
        "Revuniv Kruh"
    ],
    "name:ukr_x_variant":[
        "\u0420\u0435\u0432\u0443\u043d\u0456\u0432 \u041a\u0440\u0443\u0433"
    ],
    "name:und_x_variant":[
        "Revunov Krug"
    ],
    "wof:name":"Revuniv Kruh",
    "wof:placetype":"locality"
},
  "geometry": {"coordinates":[30.85231,51.338],"type":"Point"}
}