{
  "type": "Feature",
  "properties": {
    "gn:admin1_code":"17.0",
    "gn:asciiname":"Peremozhne",
    "gn:country_code":"UA",
    "gn:dem":70,
    "gn:feature_class":"P",
    "gn:feature_code":"PPL",
    "gn:name":"Peremozhne",
    "gn:population":0,
    "gn:timezone":"Europe/Kiev",
    "iso:country":"UA",
    "name:ukr_x_preferred":[
        "Peremozhne"
    ],
    "name:ukr_x_variant":[
        "\u041f\u0435\u0440\u0435\u043c\u043e\u0436\u043d\u0435"
    ],
    "name:und_x_variant":[
        "Peremozhnoye"
    ],
    "wof:name":"Peremozhne",
    "wof:placetype":"locality"
},
  "geometry": {"coordinates":[30.7997,46.7038],"type":"Point"}
}