{
  "type": "Feature",
  "properties": {
    "iso:country":"UA",
    "name:ces_x_preferred":[
        "Projekt 885"
    ],
    "name:deu_x_preferred":[
        "Projekt 885"
    ],
    "name:fas_x_preferred":[
        "\u0632\u06cc\u0631\u062f\u0631\u06cc\u0627\u06cc\u06cc \u06a9\u0644\u0627\u0633 \u06cc\u0627\u0632\u0646"
    ],
    "name:fin_x_preferred":[
        "Projekti 885"
    ],
    "name:fra_x_preferred":[
        "Classe Iassen"
    ],
    "name:ita_x_preferred":[
        "Classe Graney"
    ],
    "name:jpn_x_preferred":[
        "\u30e4\u30fc\u30bb\u30f3\u578b\u539f\u5b50\u529b\u6f5c\u6c34\u8266"
    ],
    "name:kor_x_preferred":[
        "\ud504\ub85c\uc81d\ud2b8 885 \uc57c\uc13c\uae09 \uc7a0\uc218\ud568"
    ],
    "name:msa_x_preferred":[
        "Kapal selam Kelas Graney"
    ],
    "name:pol_x_preferred":[
        "Okr\u0119ty podwodne projektu 885"
    ],
    "name:por_x_preferred":[
        "Classe Yassen"
    ],
    "name:rus_x_preferred":[
        "\u041f\u043e\u0434\u0432\u043e\u0434\u043d\u044b\u0435 \u043b\u043e\u0434\u043a\u0438 \u043f\u0440\u043e\u0435\u043a\u0442\u0430 885 \u00ab\u042f\u0441\u0435\u043d\u044c\u00bb"
    ],
    "name:slv_x_preferred":[
        "Podmornice razreda Jasen"
    ],
    "name:spa_x_preferred":[
        "Clase Graney"
    ],
    "name:swe_x_preferred":[
        "Projekt 885 Jasen"
    ],
    "name:ukr_x_preferred":[
        "\u042f\u0441\u0435\u043d\u044c"
    ],
    "name:unk_x_variant":[
        "Jasien"
    ],
    "name:zho_x_preferred":[
        "855\u578b\u6838\u6f5b\u8247"
    ],
    "qs:a0":"\u0423\u043a\u0440\u0430\u0457\u043d\u0430",
    "qs:a1":"*\u0406\u0432\u0430\u043d\u043e-\u0424\u0440\u0430\u043d\u043a\u0456\u0432\u0441\u044c\u043a\u0430",
    "qs:a1_alt":"Ivano-Frankivs'ka",
    "qs:a1r":"0",
    "qs:a2":"\u0420\u043e\u0436\u043d\u044f\u0442\u0456\u0432\u0441\u044c\u043a\u0438\u0439",
    "qs:a2_alt":"Rozhniativs'kyi",
    "qs:adm0":"\u0423\u043a\u0440\u0430\u0457\u043d\u0430",
    "qs:la_lc":"*",
    "qs:level":"locality",
    "qs:loc":"\u042f\u0441\u0435\u043d\u044c",
    "qs:loc_alt":"Yasen",
    "qs:pop":0,
    "qs:type":"buffered point",
    "wd:wordcount":2329,
    "wof:name":"\u042f\u0441\u0435\u043d\u044c",
    "wof:placetype":"locality"
},
  "geometry": {"coordinates":[24.170559,48.74533],"type":"Point"}
}