{
  "type": "Feature",
  "properties": {
    "gn:admin1_code":"17.0",
    "gn:asciiname":"Krasnoarmeyskoye",
    "gn:cc2":"UA",
    "gn:country_code":"UA",
    "gn:dem":79,
    "gn:feature_class":"P",
    "gn:feature_code":"PPL",
    "gn:name":"Krasnoarmeyskoye",
    "gn:population":0,
    "gn:timezone":"Europe/Kiev",
    "iso:country":"UA",
    "name:und_x_variant":[
        "Krasnoarmeysk",
        "Krasnoarmeyskoye"
    ],
    "wof:name":"Krasnoarmeyskoye",
    "wof:placetype":"locality"
},
  "geometry": {"coordinates":[31.03333,47.15],"type":"Point"}
}