{
  "type": "Feature",
  "properties": {
    "gn:admin1_code":"15.0",
    "gn:asciiname":"Shcherets",
    "gn:cc2":"UA",
    "gn:country_code":"UA",
    "gn:dem":352,
    "gn:feature_class":"P",
    "gn:feature_code":"PPL",
    "gn:name":"Shcherets",
    "gn:population":0,
    "gn:timezone":"Europe/Kiev",
    "iso:country":"UA",
    "name:und_x_variant":[
        "Szczerzec",
        "Shchezhets",
        "Shcherets"
    ],
    "wof:name":"Shcherets",
    "wof:placetype":"locality"
},
  "geometry": {"coordinates":[23.56667,50.11667],"type":"Point"}
}