{
  "type": "Feature",
  "properties": {
    "gn:admin1_code":"19.0",
    "gn:asciiname":"Yasynets'",
    "gn:country_code":"UA",
    "gn:dem":143,
    "gn:feature_class":"P",
    "gn:feature_code":"PPL",
    "gn:name":"Yasynets\u2019",
    "gn:population":0,
    "gn:timezone":"Europe/Kiev",
    "iso:country":"UA",
    "name:ukr_x_preferred":[
        "Yasynets\u2019"
    ],
    "name:ukr_x_variant":[
        "\u042f\u0441\u0438\u043d\u0435\u0446\u044c"
    ],
    "name:und_x_variant":[
        "Yasinets"
    ],
    "wof:name":"Yasynets'",
    "wof:placetype":"locality"
},
  "geometry": {"coordinates":[26.58298,51.64002],"type":"Point"}
}