{
  "type": "Feature",
  "properties": {
    "gn:admin1_code":"15.0",
    "gn:asciiname":"Novyy Stav",
    "gn:country_code":"UA",
    "gn:dem":222,
    "gn:feature_class":"P",
    "gn:feature_code":"PPL",
    "gn:name":"Novyy Stav",
    "gn:population":0,
    "gn:timezone":"Europe/Kiev",
    "iso:country":"UA",
    "name:und_x_variant":[
        "Nowy Staw",
        "Novy Stav",
        "Novyy Stav"
    ],
    "wof:name":"Novyy Stav",
    "wof:placetype":"locality"
},
  "geometry": {"coordinates":[24.33903,50.03995],"type":"Point"}
}