{
  "type": "Feature",
  "properties": {
    "gn:admin1_code":"5.0",
    "gn:asciiname":"Krasna Hora",
    "gn:country_code":"UA",
    "gn:dem":93,
    "gn:feature_class":"P",
    "gn:feature_code":"PPL",
    "gn:name":"Krasna Hora",
    "gn:population":0,
    "gn:timezone":"Europe/Kiev",
    "iso:country":"UA",
    "name:ces_x_preferred":[
        "Kr\u00e1sn\u00e1 Hora"
    ],
    "name:deu_x_preferred":[
        "Kr\u00e1sn\u00e1 Hora"
    ],
    "name:ukr_x_preferred":[
        "Krasna Hora"
    ],
    "name:ukr_x_variant":[
        "\u041a\u0440\u0430\u0441\u043d\u0430 \u0413\u043e\u0440\u0430"
    ],
    "name:und_x_variant":[
        "Krasnaya Gora"
    ],
    "wof:name":"Krasna Hora",
    "wof:placetype":"locality"
},
  "geometry": {"coordinates":[38.01623,48.65933],"type":"Point"}
}