{
  "type": "Feature",
  "properties": {
    "gn:admin1_code":"7.0",
    "gn:asciiname":"Serebryakov",
    "gn:country_code":"UA",
    "gn:dem":133,
    "gn:feature_class":"P",
    "gn:feature_code":"PPL",
    "gn:name":"Serebryakov",
    "gn:population":0,
    "gn:timezone":"Europe/Kiev",
    "iso:country":"UA",
    "name:slv_x_preferred":[
        "Serebrjakov"
    ],
    "wof:name":"Serebryakov",
    "wof:placetype":"locality"
},
  "geometry": {"coordinates":[36.57583,50.21611],"type":"Point"}
}