{
  "type": "Feature",
  "properties": {
    "gn:admin1_code":"10.0",
    "gn:asciiname":"Nagornyy",
    "gn:cc2":"UA",
    "gn:country_code":"UA",
    "gn:dem":116,
    "gn:feature_class":"P",
    "gn:feature_code":"PPL",
    "gn:name":"Nagornyy",
    "gn:population":0,
    "gn:timezone":"Europe/Kiev",
    "iso:country":"UA",
    "name:und_x_variant":[
        "Khutor Nagornyy",
        "Nagorny",
        "Nagornyy"
    ],
    "wof:name":"Nagornyy",
    "wof:placetype":"locality"
},
  "geometry": {"coordinates":[32.05,47.83333],"type":"Point"}
}