{
  "type": "Feature",
  "properties": {
    "iso:country":"UA",
    "name:eng_x_preferred":[
        "Tabachnoye"
    ],
    "name:rus_x_historical":[
        "\u0410\u0434\u0436\u0438\u0301-\u0410\u0445\u043c\u0430\u0301\u0442"
    ],
    "name:rus_x_preferred":[
        "\u0410\u0434\u0436\u0438\u0301-\u0410\u0445\u043c\u0430\u0301\u0442"
    ],
    "name:rus_x_variant":[
        "\u0422\u0430\u0431\u0430\u0447\u043d\u043e\u0435"
    ],
    "name:ukr_x_preferred":[
        "\u0422\u0430\u0431\u0430\u0447\u043d\u0435"
    ],
    "qs:a0":"\u0423\u043a\u0440\u0430\u0457\u043d\u0430",
    "qs:a1":"*\u041a\u0440\u0438\u043c",
    "qs:a1_alt":"Krym",
    "qs:a1r":"0",
    "qs:a2":"\u0414\u0436\u0430\u043d\u043a\u043e\u0439\u0441\u044c\u043a\u0438\u0439",
    "qs:a2_alt":"Dzhankois'kyi",
    "qs:adm0":"\u0423\u043a\u0440\u0430\u0457\u043d\u0430",
    "qs:la_lc":"*",
    "qs:level":"locality",
    "qs:loc":"\u0422\u0430\u0431\u0430\u0447\u043d\u0435",
    "qs:loc_alt":"Tabachne",
    "qs:pop":0,
    "qs:type":"buffered point",
    "wof:name":"\u0422\u0430\u0431\u0430\u0447\u043d\u0435",
    "wof:placetype":"locality"
},
  "geometry": {"coordinates":[34.605869,45.611708],"type":"Point"}
}