{
  "type": "Feature",
  "properties": {
    "gn:admin1_code":"21.0",
    "gn:asciiname":"Velyka Berizka",
    "gn:country_code":"UA",
    "gn:dem":162,
    "gn:feature_class":"P",
    "gn:feature_code":"PPL",
    "gn:name":"Velyka Berizka",
    "gn:population":0,
    "gn:timezone":"Europe/Kiev",
    "iso:country":"UA",
    "name:ukr_x_preferred":[
        "\u0412\u0435\u043b\u0438\u043a\u0430 \u0411\u0435\u0440\u0456\u0437\u043a\u0430"
    ],
    "name:ukr_x_variant":[
        "Velikaya Berezka",
        "Bol\u2019shaya Ber\u00ebzka"
    ],
    "name:und_x_variant":[
        "Velyka Berizka"
    ],
    "wof:name":"Velyka Berizka",
    "wof:placetype":"locality"
},
  "geometry": {"coordinates":[33.84901,52.21603],"type":"Point"}
}