{
  "type": "Feature",
  "properties": {
    "gn:admin1_code":"7.0",
    "gn:asciiname":"Shkavrove",
    "gn:country_code":"UA",
    "gn:dem":146,
    "gn:feature_class":"P",
    "gn:feature_code":"PPL",
    "gn:name":"Shkavrove",
    "gn:population":0,
    "gn:timezone":"Europe/Kiev",
    "iso:country":"UA",
    "name:rus_x_preferred":[
        "\u0428\u043a\u0430\u0432\u0440\u043e\u0432\u043e"
    ],
    "name:ukr_x_preferred":[
        "Shkavrove"
    ],
    "name:ukr_x_variant":[
        "\u0428\u043a\u0430\u0432\u0440\u043e\u0432\u0435"
    ],
    "name:und_x_variant":[
        "Shkavrovo"
    ],
    "wof:name":"Shkavrove",
    "wof:placetype":"locality"
},
  "geometry": {"coordinates":[35.54907,49.26877],"type":"Point"}
}