{
  "type": "Feature",
  "properties": {
    "gn:admin1_code":"19.0",
    "gn:asciiname":"Ivachkove",
    "gn:country_code":"UA",
    "gn:dem":203,
    "gn:feature_class":"P",
    "gn:feature_code":"PPL",
    "gn:name":"Ivachkove",
    "gn:population":0,
    "gn:timezone":"Europe/Kiev",
    "iso:country":"UA",
    "name:ukr_x_preferred":[
        "Ivachkove"
    ],
    "name:ukr_x_variant":[
        "\u0406\u0432\u0430\u0447\u043a\u043e\u0432\u0435"
    ],
    "name:und_x_variant":[
        "Ivachkuv",
        "Ivachkovo"
    ],
    "wof:name":"Ivachkove",
    "wof:placetype":"locality"
},
  "geometry": {"coordinates":[26.32905,50.47444],"type":"Point"}
}