{
  "type": "Feature",
  "properties": {
    "gn:admin1_code":"15.0",
    "gn:asciiname":"Stankivtsi",
    "gn:country_code":"UA",
    "gn:dem":260,
    "gn:feature_class":"P",
    "gn:feature_code":"PPL",
    "gn:name":"Stankivtsi",
    "gn:population":0,
    "gn:timezone":"Europe/Kiev",
    "iso:country":"UA",
    "name:rus_x_preferred":[
        "\u0421\u0442\u0430\u043d\u043a\u043e\u0432\u0446\u044b"
    ],
    "name:ukr_x_preferred":[
        "Stankivtsi"
    ],
    "name:ukr_x_variant":[
        "\u0421\u0442\u0430\u043d\u043a\u0456\u0432\u0446\u0456"
    ],
    "name:und_x_variant":[
        "Tuzhanovtse",
        "Stankovtsy"
    ],
    "wof:name":"Stankivtsi",
    "wof:placetype":"locality"
},
  "geometry": {"coordinates":[24.18319,49.43913],"type":"Point"}
}