{
  "type": "Feature",
  "properties": {
    "gn:admin1_code":"18.0",
    "gn:asciiname":"Zirka",
    "gn:country_code":"UA",
    "gn:dem":123,
    "gn:feature_class":"P",
    "gn:feature_code":"PPL",
    "gn:name":"Zirka",
    "gn:population":0,
    "gn:timezone":"Europe/Kiev",
    "iso:country":"UA",
    "name:rus_x_preferred":[
        "\u0417\u0438\u0440\u043a\u0430"
    ],
    "wof:name":"Zirka",
    "wof:placetype":"locality"
},
  "geometry": {"coordinates":[33.8703,50.1188],"type":"Point"}
}