{
  "type": "Feature",
  "properties": {
    "gn:admin1_code":"18.0",
    "gn:asciiname":"Bubereve",
    "gn:country_code":"UA",
    "gn:dem":115,
    "gn:feature_class":"P",
    "gn:feature_code":"PPL",
    "gn:name":"Bubereve",
    "gn:population":0,
    "gn:timezone":"Europe/Kiev",
    "iso:country":"UA",
    "name:ukr_x_preferred":[
        "Bubereve"
    ],
    "name:ukr_x_variant":[
        "\u0411\u0443\u0431\u0435\u0440\u0435\u0432\u0435"
    ],
    "wof:name":"Bubereve",
    "wof:placetype":"locality"
},
  "geometry": {"coordinates":[33.52032,49.81842],"type":"Point"}
}