{
  "type": "Feature",
  "properties": {
    "gn:admin1_code":"13.0",
    "gn:asciiname":"Rudnya-Sydorivs'ka",
    "gn:country_code":"UA",
    "gn:dem":142,
    "gn:feature_class":"P",
    "gn:feature_code":"PPL",
    "gn:name":"Rudnya-Sydorivs\u2019ka",
    "gn:population":0,
    "gn:timezone":"Europe/Kiev",
    "iso:country":"UA",
    "name:ukr_x_preferred":[
        "Rudnya-Sydorivs\u2019ka"
    ],
    "name:ukr_x_variant":[
        "\u0420\u0443\u0434\u043d\u044f-\u0421\u0438\u0434\u043e\u0440\u0456\u0432\u0441\u044c\u043a\u0430"
    ],
    "name:und_x_variant":[
        "Rudnya-Sidorovskaya"
    ],
    "wof:name":"Rudnya-Sydorivs'ka",
    "wof:placetype":"locality"
},
  "geometry": {"coordinates":[29.56901,50.95047],"type":"Point"}
}