{
  "type": "Feature",
  "properties": {
    "gn:admin1_code":"18.0",
    "gn:asciiname":"Pauchki",
    "gn:country_code":"UA",
    "gn:dem":140,
    "gn:feature_class":"P",
    "gn:feature_code":"PPL",
    "gn:name":"Pauchki",
    "gn:population":0,
    "gn:timezone":"Europe/Kiev",
    "iso:country":"UA",
    "wof:name":"Pauchki",
    "wof:placetype":"locality"
},
  "geometry": {"coordinates":[35.05,49.56667],"type":"Point"}
}