{
  "type": "Feature",
  "properties": {
    "gn:admin1_code":"14.0",
    "gn:asciiname":"Davydivka",
    "gn:country_code":"UA",
    "gn:dem":283,
    "gn:feature_class":"P",
    "gn:feature_code":"PPL",
    "gn:name":"Davydivka",
    "gn:population":0,
    "gn:timezone":"Europe/Zaporozhye",
    "iso:country":"UA",
    "name:ceb_x_preferred":[
        "Davydivka"
    ],
    "name:deu_x_preferred":[
        "Dawydiwka"
    ],
    "name:heb_x_preferred":[
        "\u05d3\u05d5\u05d9\u05d3\u05e0\u05d9"
    ],
    "name:hye_x_preferred":[
        "\u0534\u0561\u057e\u056b\u0564\u0578\u057e\u056f\u0561"
    ],
    "name:nld_x_preferred":[
        "Davydivka"
    ],
    "name:pol_x_preferred":[
        "Dawydiwka"
    ],
    "name:ron_x_preferred":[
        "Davideni"
    ],
    "name:rus_x_preferred":[
        "\u0414\u0430\u0432\u044b\u0434\u043e\u0432\u043a\u0430"
    ],
    "name:ukr_x_preferred":[
        "Davydivka"
    ],
    "name:ukr_x_variant":[
        "\u0414\u0430\u0432\u0438\u0434\u0456\u0432\u043a\u0430"
    ],
    "name:und_x_variant":[
        "Davidovka"
    ],
    "name:zho_x_preferred":[
        "\u9054\u7dad\u5b63\u592b\u5361"
    ],
    "wof:name":"Davydivka",
    "wof:placetype":"locality"
},
  "geometry": {"coordinates":[38.82201,48.25533],"type":"Point"}
}