{
  "type": "Feature",
  "properties": {
    "gn:admin1_code":"25.0",
    "gn:asciiname":"Tur'ya Paseka",
    "gn:cc2":"UA",
    "gn:country_code":"UA",
    "gn:dem":209,
    "gn:feature_class":"P",
    "gn:feature_code":"PPL",
    "gn:name":"Tur'ya Paseka",
    "gn:population":0,
    "gn:timezone":"Europe/Uzhgorod",
    "iso:country":"UA",
    "name:und_x_variant":[
        "Tur'ya Pasika"
    ],
    "wof:name":"Tur'ya Paseka",
    "wof:placetype":"locality"
},
  "geometry": {"coordinates":[22.68368,48.68507],"type":"Point"}
}