{
  "type": "Feature",
  "properties": {
    "gn:admin1_code":"16.0",
    "gn:asciiname":"Romanivka",
    "gn:country_code":"UA",
    "gn:dem":41,
    "gn:feature_class":"P",
    "gn:feature_code":"PPL",
    "gn:name":"Romanivka",
    "gn:population":0,
    "gn:timezone":"Europe/Kiev",
    "iso:country":"UA",
    "name:rus_x_preferred":[
        "\u0420\u043e\u043c\u0430\u043d\u043e\u0432\u043a\u0430"
    ],
    "name:ukr_x_preferred":[
        "Romanivka"
    ],
    "name:ukr_x_variant":[
        "\u0420\u043e\u043c\u0430\u043d\u0456\u0432\u043a\u0430"
    ],
    "name:und_x_variant":[
        "Bol\u2019shaya Romanovka",
        "Velikaya Romanovka",
        "Romanovka"
    ],
    "wof:name":"Romanivka",
    "wof:placetype":"locality"
},
  "geometry": {"coordinates":[32.9483,47.43557],"type":"Point"}
}