{
  "type": "Feature",
  "properties": {
    "gn:admin1_code":"1.0",
    "gn:asciiname":"Bakayeve",
    "gn:country_code":"UA",
    "gn:dem":112,
    "gn:feature_class":"P",
    "gn:feature_code":"PPL",
    "gn:name":"Bakayeve",
    "gn:population":0,
    "gn:timezone":"Europe/Kiev",
    "iso:country":"UA",
    "name:ukr_x_preferred":[
        "Bakayeve"
    ],
    "name:ukr_x_variant":[
        "\u0411\u0430\u043a\u0430\u0454\u0432\u0435"
    ],
    "wof:name":"Bakayeve",
    "wof:placetype":"locality"
},
  "geometry": {"coordinates":[32.47604,49.68821],"type":"Point"}
}