{
  "type": "Feature",
  "properties": {
    "gn:population":8188,
    "iso:country":"UA",
    "name:arm_x_preferred":[
        "\u054d\u0561\u056d\u0576\u0578\u057e\u0577\u0579\u056b\u0576\u0561"
    ],
    "name:chi_x_preferred":[
        "\u85a9\u8d6b\u8afe\u592b\u5e0c\u7d0d"
    ],
    "name:eng_x_preferred":[
        "Sakhnovshchyna"
    ],
    "name:ger_x_preferred":[
        "Sachnowschtschyna"
    ],
    "name:pol_x_preferred":[
        "Sachnowszczyna"
    ],
    "name:rus_x_preferred":[
        "\u0421\u0430\u0445\u043d\u043e\u0432\u0449\u0438\u043d\u0430"
    ],
    "name:ukr_x_preferred":[
        "\u0421\u0430\u0445\u043d\u043e\u0432\u0449\u0438\u043d\u0430"
    ],
    "name:unk_x_variant":[
        "Sakhnovshchina"
    ],
    "qs:a0":"\u0423\u043a\u0440\u0430\u0457\u043d\u0430",
    "qs:a1":"*\u0425\u0430\u0440\u043a\u0456\u0432\u0441\u044c\u043a\u0430",
    "qs:a1_alt":"Kharkivs'ka",
    "qs:a1r":"0",
    "qs:a2":"\u0421\u0430\u0445\u043d\u043e\u0432\u0449\u0438\u043d\u0441\u044c\u043a\u0438\u0439",
    "qs:a2_alt":"Sakhnovschyns'kyi",
    "qs:adm0":"\u0423\u043a\u0440\u0430\u0457\u043d\u0430",
    "qs:la_lc":"*",
    "qs:level":"locality",
    "qs:loc":"\u0421\u0430\u0445\u043d\u043e\u0432\u0449\u0438\u043d\u0430",
    "qs:loc_alt":"Sakhnovschyna",
    "qs:pop":0,
    "qs:type":"buffered point",
    "wof:name":"\u0421\u0430\u0445\u043d\u043e\u0432\u0449\u0438\u043d\u0430",
    "wof:placetype":"locality",
    "wof:population":8188
},
  "geometry": {"coordinates":[35.87865,49.1403],"type":"Point"}
}