{
  "type": "Feature",
  "properties": {
    "iso:country":"UA",
    "name:che_x_preferred":[
        "\u041d\u043e\u0432\u043e\u043f\u0435\u0442\u0440\u0438\u043a\u043e\u0432\u043a\u0430"
    ],
    "name:deu_x_preferred":[
        "Nowopetrykiwka"
    ],
    "name:eng_x_preferred":[
        "Novopetrikovka"
    ],
    "name:eng_x_variant":[
        "Novopetrykivka"
    ],
    "name:fin_x_preferred":[
        "N\u043ev\u043ep\u0435tryk\u0456vk\u0430"
    ],
    "name:hye_x_preferred":[
        "\u0546\u0578\u057e\u0578\u057a\u0565\u057f\u0580\u056b\u056f\u0578\u057e\u056f\u0561"
    ],
    "name:lav_x_preferred":[
        "Novopetrikivka"
    ],
    "name:nan_x_preferred":[
        "Novopetrykivka"
    ],
    "name:nno_x_preferred":[
        "Novopetrykivka"
    ],
    "name:nob_x_preferred":[
        "Novopetrykivka"
    ],
    "name:rus_x_preferred":[
        "\u041d\u043e\u0432\u043e\u043f\u0435\u0442\u0440\u0438\u043a\u043e\u0432\u043a\u0430"
    ],
    "name:swe_x_preferred":[
        "Novopetrykivka"
    ],
    "name:ukr_x_preferred":[
        "Novopetrykivka"
    ],
    "name:ukr_x_variant":[
        "\u041d\u043e\u0432\u043e\u043f\u0435\u0442\u0440\u0438\u043a\u0456\u0432\u043a\u0430"
    ],
    "name:und_x_variant":[
        "Novaya Petrikovka"
    ],
    "qs:a0":"\u0423\u043a\u0440\u0430\u0457\u043d\u0430",
    "qs:a1":"*\u0414\u043e\u043d\u0435\u0446\u044c\u043a\u0430",
    "qs:a1_alt":"Donets'ka",
    "qs:a1r":"0",
    "qs:a2":"\u0412\u0435\u043b\u0438\u043a\u043e\u043d\u043e\u0432\u043e\u0441\u0456\u043b\u043a\u0456\u0432\u0441\u044c\u043a\u0438\u0439",
    "qs:a2_alt":"Velykonovosilkivs'kyi",
    "qs:adm0":"\u0423\u043a\u0440\u0430\u0457\u043d\u0430",
    "qs:la_lc":"*",
    "qs:level":"locality",
    "qs:loc":"\u041d\u043e\u0432\u043e\u043f\u0435\u0442\u0440\u0438\u043a\u0456\u0432\u043a\u0430",
    "qs:loc_alt":"Novopetrykivka",
    "qs:pop":0,
    "qs:type":"buffered point",
    "wof:name":"\u041d\u043e\u0432\u043e\u043f\u0435\u0442\u0440\u0438\u043a\u0456\u0432\u043a\u0430",
    "wof:placetype":"locality"
},
  "geometry": {"coordinates":[36.93607,47.627715],"type":"Point"}
}