{
  "type": "Feature",
  "properties": {
    "gn:admin1_code":"22.0",
    "gn:asciiname":"Gnidava",
    "gn:country_code":"UA",
    "gn:dem":289,
    "gn:feature_class":"P",
    "gn:feature_code":"PPL",
    "gn:name":"Gnidava",
    "gn:population":0,
    "gn:timezone":"Europe/Kiev",
    "iso:country":"UA",
    "name:und_x_variant":[
        "Hnydava",
        "Gnidava"
    ],
    "wof:name":"Gnidava",
    "wof:placetype":"locality"
},
  "geometry": {"coordinates":[25.83306,49.84704],"type":"Point"}
}