{
  "type": "Feature",
  "properties": {
    "gn:admin1_code":"14.0",
    "gn:asciiname":"Kalynove-Borshchuvate",
    "gn:country_code":"UA",
    "gn:dem":181,
    "gn:feature_class":"P",
    "gn:feature_code":"PPL",
    "gn:name":"Kalynove-Borshchuvate",
    "gn:population":0,
    "gn:timezone":"Europe/Zaporozhye",
    "iso:country":"UA",
    "name:ukr_x_preferred":[
        "Kalynove-Borshchuvate"
    ],
    "name:ukr_x_variant":[
        "\u041a\u0430\u043b\u0438\u043d\u043e\u0432\u0435-\u0411\u043e\u0440\u0449\u0443\u0432\u0430\u0442\u0435"
    ],
    "name:und_x_variant":[
        "Borshchevatoye"
    ],
    "wof:name":"Kalynove-Borshchuvate",
    "wof:placetype":"locality"
},
  "geometry": {"coordinates":[38.49194,48.61972],"type":"Point"}
}