{
  "type": "Feature",
  "properties": {
    "gn:admin1_code":"27.0",
    "gn:asciiname":"Yahodynka",
    "gn:country_code":"UA",
    "gn:dem":179,
    "gn:feature_class":"P",
    "gn:feature_code":"PPL",
    "gn:name":"Yahodynka",
    "gn:population":0,
    "gn:timezone":"Europe/Kiev",
    "iso:country":"UA",
    "name:ukr_x_preferred":[
        "Yahodynka"
    ],
    "name:ukr_x_variant":[
        "\u042f\u0433\u043e\u0434\u0438\u043d\u043a\u0430"
    ],
    "name:und_x_variant":[
        "Yagodinka"
    ],
    "wof:name":"Yahodynka",
    "wof:placetype":"locality"
},
  "geometry": {"coordinates":[28.59165,50.70435],"type":"Point"}
}