{
  "type": "Feature",
  "properties": {
    "gn:admin1_code":"13.0",
    "gn:asciiname":"Kolentsivs'ke",
    "gn:country_code":"UA",
    "gn:dem":113,
    "gn:feature_class":"P",
    "gn:feature_code":"PPL",
    "gn:name":"Kolentsivs\u2019ke",
    "gn:population":0,
    "gn:timezone":"Europe/Kiev",
    "iso:country":"UA",
    "name:ukr_x_preferred":[
        "Kolentsivs\u2019ke"
    ],
    "name:ukr_x_variant":[
        "\u041a\u043e\u043b\u0435\u043d\u0446\u0456\u0432\u0441\u044c\u043a\u0435"
    ],
    "name:und_x_variant":[
        "Kolentsovskoye"
    ],
    "wof:name":"Kolentsivs'ke",
    "wof:placetype":"locality"
},
  "geometry": {"coordinates":[29.8449,50.87389],"type":"Point"}
}