{
  "type": "Feature",
  "properties": {
    "gn:admin1_code":"5.0",
    "gn:asciiname":"Tykhonivka",
    "gn:country_code":"UA",
    "gn:dem":188,
    "gn:feature_class":"P",
    "gn:feature_code":"PPL",
    "gn:name":"Tykhonivka",
    "gn:population":0,
    "gn:timezone":"Europe/Kiev",
    "iso:country":"UA",
    "name:ukr_x_preferred":[
        "Tykhonivka"
    ],
    "name:ukr_x_variant":[
        "\u0422\u0438\u0445\u043e\u043d\u0456\u0432\u043a\u0430"
    ],
    "wof:name":"Tykhonivka",
    "wof:placetype":"locality"
},
  "geometry": {"coordinates":[37.77993,48.71728],"type":"Point"}
}