{
  "type": "Feature",
  "properties": {
    "gn:admin1_code":"2.0",
    "gn:asciiname":"Bezpechne",
    "gn:country_code":"UA",
    "gn:dem":143,
    "gn:feature_class":"P",
    "gn:feature_code":"PPL",
    "gn:name":"Bezpechne",
    "gn:population":0,
    "gn:timezone":"Europe/Kiev",
    "iso:country":"UA",
    "name:ukr_x_preferred":[
        "Bezpechne"
    ],
    "name:ukr_x_variant":[
        "\u0411\u0435\u0437\u043f\u0435\u0447\u043d\u0435"
    ],
    "name:und_x_variant":[
        "Bespechnoye"
    ],
    "wof:name":"Bezpechne",
    "wof:placetype":"locality"
},
  "geometry": {"coordinates":[32.60673,51.08778],"type":"Point"}
}