{
  "type": "Feature",
  "properties": {
    "gn:country":"UA",
    "gn:fcode":"PPL",
    "gn:population":156,
    "iso:country":"UA",
    "name:eng_x_preferred":[
        "Unizh"
    ],
    "name:rus_x_preferred":[
        "\u0423\u043d\u0438\u0436"
    ],
    "qs_pg:aaroncc":"UA",
    "qs_pg:gn_country":"UA",
    "qs_pg:gn_fcode":"PPL",
    "qs_pg:gn_pop":156,
    "qs_pg:name":"Unizh",
    "qs_pg:photos_9r":0,
    "qs_pg:photos_sr":0,
    "qs_pg:pop_sr":1,
    "qs_pg:qs_pg_placetype":"locality",
    "wof:name":"Unizh",
    "wof:placetype":"locality",
    "wof:population":156
},
  "geometry": {"coordinates":[25.35144,48.8093],"type":"Point"}
}