{
  "type": "Feature",
  "properties": {
    "gn:admin1_code":"1.0",
    "gn:asciiname":"Khizhnya",
    "gn:country_code":"UA",
    "gn:dem":221,
    "gn:feature_class":"P",
    "gn:feature_code":"PPL",
    "gn:name":"Khizhnya",
    "gn:population":0,
    "gn:timezone":"Europe/Kiev",
    "iso:country":"UA",
    "name:eng_x_preferred":[
        "Khizhnya"
    ],
    "name:rus_x_preferred":[
        "\u0425\u0438\u0436\u043d\u044f"
    ],
    "name:und_x_variant":[
        "Khizhna",
        "Khizhnya"
    ],
    "wof:name":"Khizhnya",
    "wof:placetype":"locality"
},
  "geometry": {"coordinates":[30.27057000000001,49.10696],"type":"Point"}
}