{
  "type": "Feature",
  "properties": {
    "gn:admin1_code":"15.0",
    "gn:asciiname":"Berbeki",
    "gn:country_code":"UA",
    "gn:dem":210,
    "gn:feature_class":"P",
    "gn:feature_code":"PPL",
    "gn:name":"Berbeki",
    "gn:population":0,
    "gn:timezone":"Europe/Kiev",
    "iso:country":"UA",
    "wof:name":"Berbeki",
    "wof:placetype":"locality"
},
  "geometry": {"coordinates":[24.46667,50.13333],"type":"Point"}
}