{
  "type": "Feature",
  "properties": {
    "gn:admin1_code":"27.0",
    "gn:asciiname":"Zhovte",
    "gn:country_code":"UA",
    "gn:dem":227,
    "gn:feature_class":"P",
    "gn:feature_code":"PPL",
    "gn:name":"Zhovte",
    "gn:population":0,
    "gn:timezone":"Europe/Kiev",
    "iso:country":"UA",
    "name:ukr_x_preferred":[
        "Zhovte"
    ],
    "name:ukr_x_variant":[
        "\u0416\u043e\u0432\u0442\u0435"
    ],
    "name:und_x_variant":[
        "Zholtoye"
    ],
    "wof:name":"Zhovte",
    "wof:placetype":"locality"
},
  "geometry": {"coordinates":[27.82267,50.40502],"type":"Point"}
}