{
  "type": "Feature",
  "properties": {
    "gn:admin1_code":"4.0",
    "gn:asciiname":"Smolenka",
    "gn:country_code":"UA",
    "gn:dem":117,
    "gn:feature_class":"P",
    "gn:feature_code":"PPL",
    "gn:name":"Smolenka",
    "gn:population":0,
    "gn:timezone":"Europe/Kiev",
    "iso:country":"UA",
    "name:fra_x_preferred":[
        "Smolenka"
    ],
    "name:lit_x_preferred":[
        "Smolenka"
    ],
    "name:pol_x_preferred":[
        "Smolenka"
    ],
    "name:ukr_x_preferred":[
        "Smolenka"
    ],
    "name:ukr_x_variant":[
        "\u0421\u043c\u043e\u043b\u0435\u043d\u043a\u0430"
    ],
    "wof:name":"Smolenka",
    "wof:placetype":"locality"
},
  "geometry": {"coordinates":[34.22438,48.16638],"type":"Point"}
}