{
  "type": "Feature",
  "properties": {
    "gn:admin1_code":"19.0",
    "gn:asciiname":"Hrabun'",
    "gn:country_code":"UA",
    "gn:dem":151,
    "gn:feature_class":"P",
    "gn:feature_code":"PPL",
    "gn:name":"Hrabun\u2019",
    "gn:population":0,
    "gn:timezone":"Europe/Kiev",
    "iso:country":"UA",
    "name:rus_x_preferred":[
        "Grabun\u2019"
    ],
    "name:ukr_x_preferred":[
        "Hrabun\u2019"
    ],
    "name:ukr_x_variant":[
        "\u0413\u0440\u0430\u0431\u0443\u043d\u044c"
    ],
    "wof:name":"Hrabun'",
    "wof:placetype":"locality"
},
  "geometry": {"coordinates":[27.23648,51.55382],"type":"Point"}
}