{
  "type": "Feature",
  "properties": {
    "gn:admin1_code":"13.0",
    "gn:asciiname":"Velykyy Lis",
    "gn:country_code":"UA",
    "gn:dem":150,
    "gn:feature_class":"P",
    "gn:feature_code":"PPL",
    "gn:name":"Velykyy Lis",
    "gn:population":0,
    "gn:timezone":"Europe/Kiev",
    "iso:country":"UA",
    "name:ukr_x_preferred":[
        "Velykyy Lis"
    ],
    "name:ukr_x_variant":[
        "\u0412\u0435\u043b\u0438\u043a\u0438\u0439 \u041b\u0456\u0441"
    ],
    "name:und_x_variant":[
        "Velikiy Les"
    ],
    "wof:name":"Velykyy Lis",
    "wof:placetype":"locality"
},
  "geometry": {"coordinates":[29.91525,50.74327],"type":"Point"}
}