{
  "type": "Feature",
  "properties": {
    "gn:admin1_code":"18.0",
    "gn:asciiname":"Smotryky",
    "gn:country_code":"UA",
    "gn:dem":117,
    "gn:feature_class":"P",
    "gn:feature_code":"PPL",
    "gn:name":"Smotryky",
    "gn:population":0,
    "gn:timezone":"Europe/Kiev",
    "iso:country":"UA",
    "name:eng_x_preferred":[
        "Smotriki"
    ],
    "name:rus_x_preferred":[
        "\u0421\u043c\u043e\u0442\u0440\u0438\u043a\u0438"
    ],
    "name:ukr_x_preferred":[
        "Smotryky"
    ],
    "name:ukr_x_variant":[
        "\u0421\u043c\u043e\u0442\u0440\u0438\u043a\u0438"
    ],
    "name:und_x_variant":[
        "Smotriki"
    ],
    "wof:name":"Smotryky",
    "wof:placetype":"locality"
},
  "geometry": {"coordinates":[32.13812,50.27913],"type":"Point"}
}