{
  "type": "Feature",
  "properties": {
    "gn:admin1_code":"13.0",
    "gn:asciiname":"Litochky",
    "gn:country_code":"UA",
    "gn:dem":98,
    "gn:feature_class":"P",
    "gn:feature_code":"PPL",
    "gn:name":"Litochky",
    "gn:population":0,
    "gn:timezone":"Europe/Kiev",
    "iso:country":"UA",
    "name:ukr_x_preferred":[
        "Litochky"
    ],
    "name:ukr_x_variant":[
        "\u041b\u0456\u0442\u043e\u0447\u043a\u0438"
    ],
    "name:und_x_variant":[
        "Letochki"
    ],
    "wof:name":"Litochky",
    "wof:placetype":"locality"
},
  "geometry": {"coordinates":[30.77229,50.7552],"type":"Point"}
}