{
  "type": "Feature",
  "properties": {
    "gn:admin1_code":"27.0",
    "gn:asciiname":"Dibrivs'ke",
    "gn:country_code":"UA",
    "gn:dem":201,
    "gn:feature_class":"P",
    "gn:feature_code":"PPL",
    "gn:name":"Dibrivs\u2019ke",
    "gn:population":0,
    "gn:timezone":"Europe/Kiev",
    "iso:country":"UA",
    "name:ukr_x_preferred":[
        "Dibrivs\u2019ke"
    ],
    "name:ukr_x_variant":[
        "\u0414\u0456\u0431\u0440\u0456\u0432\u0441\u044c\u043a\u0435"
    ],
    "name:und_x_variant":[
        "Dubrovka",
        "Dibrovskoye"
    ],
    "wof:name":"Dibrivs'ke",
    "wof:placetype":"locality"
},
  "geometry": {"coordinates":[27.46313,50.69916],"type":"Point"}
}