{
  "type": "Feature",
  "properties": {
    "iso:country":"UA",
    "name:bos_x_preferred":[
        "Suha"
    ],
    "name:bul_x_preferred":[
        "\u0421\u0443\u0445\u0430"
    ],
    "name:deu_x_preferred":[
        "Sucha"
    ],
    "name:eng_x_preferred":[
        "Sukha"
    ],
    "name:epo_x_preferred":[
        "Su\u0125a"
    ],
    "name:fra_x_preferred":[
        "Suha"
    ],
    "name:hbs_x_preferred":[
        "Suha"
    ],
    "name:hrv_x_preferred":[
        "Suha"
    ],
    "name:hun_x_preferred":[
        "Szuha"
    ],
    "name:hye_x_preferred":[
        "\u054d\u0578\u0582\u056d\u0561"
    ],
    "name:lav_x_preferred":[
        "Suha"
    ],
    "name:nld_x_preferred":[
        "Sukha"
    ],
    "name:ron_x_preferred":[
        "Suha"
    ],
    "name:rus_x_preferred":[
        "\u0421\u0443\u0445\u0430"
    ],
    "name:srp_x_preferred":[
        "\u0421\u0443\u0445\u0430"
    ],
    "name:ukr_x_preferred":[
        "Sukha"
    ],
    "name:ukr_x_variant":[
        "\u0421\u0443\u0445\u0430"
    ],
    "name:zho_x_preferred":[
        "\u8607\u54c8"
    ],
    "qs:a0":"\u0423\u043a\u0440\u0430\u0457\u043d\u0430",
    "qs:a1":"*\u0417\u0430\u043a\u0430\u0440\u043f\u0430\u0442\u0441\u044c\u043a\u0430",
    "qs:a1_alt":"Zakarpats'ka",
    "qs:a1r":"0",
    "qs:a2":"\u0406\u0440\u0448\u0430\u0432\u0441\u044c\u043a\u0438\u0439",
    "qs:a2_alt":"Irshavs'kyi",
    "qs:adm0":"\u0423\u043a\u0440\u0430\u0457\u043d\u0430",
    "qs:la_lc":"*",
    "qs:level":"locality",
    "qs:loc":"\u0421\u0443\u0445\u0430",
    "qs:loc_alt":"Sukha",
    "qs:pop":0,
    "qs:type":"buffered point",
    "wd:wordcount":59,
    "wof:name":"\u0421\u0443\u0445\u0430",
    "wof:placetype":"locality"
},
  "geometry": {"coordinates":[23.296832,48.426866],"type":"Point"}
}