{
  "type": "Feature",
  "properties": {
    "gn:admin1_code":"21.0",
    "gn:asciiname":"Hannivka-Vyrivs'ka",
    "gn:country_code":"UA",
    "gn:dem":154,
    "gn:feature_class":"P",
    "gn:feature_code":"PPL",
    "gn:name":"Hannivka-Vyrivs\u2019ka",
    "gn:population":0,
    "gn:timezone":"Europe/Kiev",
    "iso:country":"UA",
    "name:ukr_x_preferred":[
        "Hannivka-Vyrivs\u2019ka"
    ],
    "name:ukr_x_variant":[
        "\u0413\u0430\u043d\u043d\u0456\u0432\u043a\u0430-\u0412\u0438\u0440\u0456\u0432\u0441\u044c\u043a\u0430"
    ],
    "name:und_x_variant":[
        "Annovka",
        "Annovka-Virovskaya"
    ],
    "wof:name":"Hannivka-Vyrivs'ka",
    "wof:placetype":"locality"
},
  "geometry": {"coordinates":[34.29437,51.02825],"type":"Point"}
}