{
  "type": "Feature",
  "properties": {
    "gn:admin1_code":"17.0",
    "gn:asciiname":"Oleksandrivka",
    "gn:country_code":"UA",
    "gn:dem":16,
    "gn:feature_class":"P",
    "gn:feature_code":"PPL",
    "gn:name":"Oleksandrivka",
    "gn:population":0,
    "gn:timezone":"Europe/Kiev",
    "iso:country":"UA",
    "name:ukr_x_preferred":[
        "Oleksandrivka"
    ],
    "name:ukr_x_variant":[
        "\u041e\u043b\u0435\u043a\u0441\u0430\u043d\u0434\u0440\u0456\u0432\u043a\u0430"
    ],
    "name:und_x_variant":[
        "Aleksandrovka"
    ],
    "wof:name":"Oleksandrivka",
    "wof:placetype":"locality"
},
  "geometry": {"coordinates":[30.37341,46.75148],"type":"Point"}
}