{
  "type": "Feature",
  "properties": {
    "gn:admin1_code":"9.0",
    "gn:asciiname":"Verbka",
    "gn:country_code":"UA",
    "gn:dem":282,
    "gn:feature_class":"P",
    "gn:feature_code":"PPL",
    "gn:name":"Verbka",
    "gn:population":0,
    "gn:timezone":"Europe/Kiev",
    "iso:country":"UA",
    "wof:name":"Verbka",
    "wof:placetype":"locality"
},
  "geometry": {"coordinates":[27.74714,49.38759],"type":"Point"}
}