{
  "type": "Feature",
  "properties": {
    "gn:admin1_code":"22.0",
    "gn:asciiname":"Dobrovody",
    "gn:country_code":"UA",
    "gn:dem":335,
    "gn:feature_class":"P",
    "gn:feature_code":"PPL",
    "gn:name":"Dobrovody",
    "gn:population":0,
    "gn:timezone":"Europe/Kiev",
    "iso:country":"UA",
    "name:und_x_variant":[
        "Dobrowody",
        "Dobrovody"
    ],
    "wof:name":"Dobrovody",
    "wof:placetype":"locality"
},
  "geometry": {"coordinates":[25.20932,49.15613],"type":"Point"}
}