{
  "type": "Feature",
  "properties": {
    "gn:admin1_code":"22.0",
    "gn:asciiname":"Dobrovody",
    "gn:country_code":"UA",
    "gn:dem":335,
    "gn:feature_class":"P",
    "gn:feature_code":"PPL",
    "gn:name":"Dobrovody",
    "gn:population":0,
    "gn:timezone":"Europe/Kiev",
    "iso:country":"UA",
    "name:fra_x_preferred":[
        "Dobrovody"
    ],
    "name:rus_x_preferred":[
        "\u0414\u043e\u0431\u0440\u043e\u0432\u043e\u0434\u044b"
    ],
    "name:ukr_x_preferred":[
        "\u0414\u043e\u0431\u0440\u043e\u0432\u043e\u0434\u0438"
    ],
    "name:und_x_variant":[
        "Dobrowody"
    ],
    "wof:name":"Dobrovody",
    "wof:placetype":"locality"
},
  "geometry": {"coordinates":[25.20932,49.15613],"type":"Point"}
}