{
  "type": "Feature",
  "properties": {
    "gn:admin1_code":"18.0",
    "gn:asciiname":"Voloshkove",
    "gn:country_code":"UA",
    "gn:dem":181,
    "gn:feature_class":"P",
    "gn:feature_code":"PPL",
    "gn:name":"Voloshkove",
    "gn:population":0,
    "gn:timezone":"Europe/Kiev",
    "iso:country":"UA",
    "name:ukr_x_preferred":[
        "Voloshkove"
    ],
    "name:ukr_x_variant":[
        "\u0412\u043e\u043b\u043e\u0448\u043a\u043e\u0432\u0435"
    ],
    "wof:name":"Voloshkove",
    "wof:placetype":"locality"
},
  "geometry": {"coordinates":[34.45025,49.96093],"type":"Point"}
}