{
  "type": "Feature",
  "properties": {
    "gn:admin1_code":"15.0",
    "gn:asciiname":"Yasenitsa",
    "gn:country_code":"UA",
    "gn:dem":211,
    "gn:feature_class":"P",
    "gn:feature_code":"PPL",
    "gn:name":"Yasenitsa",
    "gn:population":0,
    "gn:timezone":"Europe/Kiev",
    "iso:country":"UA",
    "name:und_x_variant":[
        "Jasienica",
        "Yasenitsa Russka",
        "Jasienica Ruska",
        "Yasenitsa Pol\u2019ska",
        "Yasenitsa"
    ],
    "wof:name":"Yasenitsa",
    "wof:placetype":"locality"
},
  "geometry": {"coordinates":[24.43828,50.11654],"type":"Point"}
}