{
  "type": "Feature",
  "properties": {
    "iso:country":"UA",
    "name:eng_x_preferred":[
        "Nove Selo"
    ],
    "name:epo_x_preferred":[
        "Nove Selo"
    ],
    "name:hun_x_preferred":[
        "Nowa Wie\u015b"
    ],
    "name:hun_x_variant":[
        "Tisza\u00fajhely"
    ],
    "name:hye_x_preferred":[
        "\u0546\u0578\u057e\u0578\u0565 \u054d\u0565\u056c\u0578"
    ],
    "name:nld_x_preferred":[
        "Tisza\u00fajhely"
    ],
    "name:pol_x_preferred":[
        "Nowa Wie\u015b"
    ],
    "name:ron_x_preferred":[
        "Nove Selo"
    ],
    "name:rus_x_preferred":[
        "\u041d\u043e\u0432\u043e\u0435 \u0421\u0435\u043b\u043e"
    ],
    "name:ukr_x_preferred":[
        "\u041d\u043e\u0432\u0435 \u0421\u0435\u043b\u043e"
    ],
    "name:und_x_variant":[
        "Vukheli"
    ],
    "name:zho_x_preferred":[
        "\u65b0\u8b1d\u6d1b"
    ],
    "qs:a0":"\u0423\u043a\u0440\u0430\u0457\u043d\u0430",
    "qs:a1":"*\u0417\u0430\u043a\u0430\u0440\u043f\u0430\u0442\u0441\u044c\u043a\u0430",
    "qs:a1_alt":"Zakarpats'ka",
    "qs:a1r":"0",
    "qs:a2":"\u0412\u0438\u043d\u043e\u0433\u0440\u0430\u0434\u0456\u0432\u0441\u044c\u043a\u0438\u0439",
    "qs:a2_alt":"Vynohradivs'kyi",
    "qs:adm0":"\u0423\u043a\u0440\u0430\u0457\u043d\u0430",
    "qs:la_lc":"*",
    "qs:level":"locality",
    "qs:loc":"\u041d\u043e\u0432\u0435 \u0421\u0435\u043b\u043e",
    "qs:loc_alt":"Nove Selo",
    "qs:pop":0,
    "qs:type":"buffered point",
    "wd:wordcount":91,
    "wof:name":"\u041d\u043e\u0432\u0435 \u0421\u0435\u043b\u043e",
    "wof:placetype":"locality"
},
  "geometry": {"coordinates":[22.887972,48.115184],"type":"Point"}
}