{
  "type": "Feature",
  "properties": {
    "gn:admin1_code":"27.0",
    "gn:asciiname":"Deleta",
    "gn:country_code":"UA",
    "gn:dem":142,
    "gn:feature_class":"P",
    "gn:feature_code":"PPL",
    "gn:name":"Deleta",
    "gn:population":0,
    "gn:timezone":"Europe/Kiev",
    "iso:country":"UA",
    "name:rus_x_preferred":[
        "\u0414\u0435\u043b\u0435\u0442\u0430"
    ],
    "wof:name":"Deleta",
    "wof:placetype":"locality"
},
  "geometry": {"coordinates":[28.2447,51.63056],"type":"Point"}
}