{
  "type": "Feature",
  "properties": {
    "gn:admin1_code":"4.0",
    "gn:asciiname":"Verbivs'ke",
    "gn:country_code":"UA",
    "gn:dem":142,
    "gn:feature_class":"P",
    "gn:feature_code":"PPL",
    "gn:name":"Verbivs\u2019ke",
    "gn:population":0,
    "gn:timezone":"Europe/Kiev",
    "iso:country":"UA",
    "name:ukr_x_preferred":[
        "Verbivs\u2019ke"
    ],
    "name:ukr_x_variant":[
        "\u0412\u0435\u0440\u0431\u0456\u0432\u0441\u044c\u043a\u0435"
    ],
    "name:und_x_variant":[
        "Verbovskoye"
    ],
    "wof:name":"Verbivs'ke",
    "wof:placetype":"locality"
},
  "geometry": {"coordinates":[35.74994,48.13423],"type":"Point"}
}