{
  "type": "Feature",
  "properties": {
    "gn:admin1_code":"16.0",
    "gn:asciiname":"Matrono-Vasylivka",
    "gn:country_code":"UA",
    "gn:dem":54,
    "gn:feature_class":"P",
    "gn:feature_code":"PPL",
    "gn:name":"Matrono-Vasylivka",
    "gn:population":0,
    "gn:timezone":"Europe/Kiev",
    "iso:country":"UA",
    "name:rus_x_preferred":[
        "Matr\u00ebno-Vasil\u2019yevka"
    ],
    "name:rus_x_variant":[
        "\u041c\u0430\u0442\u0440\u0451\u043d\u043e-\u0412\u0430\u0441\u0438\u043b\u044c\u0435\u0432\u043a\u0430"
    ],
    "name:ukr_x_preferred":[
        "Matrono-Vasylivka"
    ],
    "name:ukr_x_variant":[
        "\u041c\u0430\u0442\u0440\u043e\u043d\u043e-\u0412\u0430\u0441\u0438\u043b\u0456\u0432\u043a\u0430"
    ],
    "wof:name":"Matrono-Vasylivka",
    "wof:placetype":"locality"
},
  "geometry": {"coordinates":[32.97248,47.53339],"type":"Point"}
}