{
  "type": "Feature",
  "properties": {
    "gn:admin1_code":"15.0",
    "gn:asciiname":"Zagortse",
    "gn:country_code":"UA",
    "gn:dem":268,
    "gn:feature_class":"P",
    "gn:feature_code":"PPL",
    "gn:name":"Zagortse",
    "gn:population":0,
    "gn:timezone":"Europe/Kiev",
    "iso:country":"UA",
    "wof:name":"Zagortse",
    "wof:placetype":"locality"
},
  "geometry": {"coordinates":[24.97621,49.95881],"type":"Point"}
}