{
  "type": "Feature",
  "properties": {
    "gn:admin1_code":"7.0",
    "gn:asciiname":"Hadyach",
    "gn:country_code":"UA",
    "gn:dem":96,
    "gn:feature_class":"P",
    "gn:feature_code":"PPL",
    "gn:name":"Hadyach",
    "gn:population":0,
    "gn:timezone":"Europe/Kiev",
    "iso:country":"UA",
    "name:ukr_x_preferred":[
        "Hadyach"
    ],
    "name:ukr_x_variant":[
        "\u0413\u0430\u0434\u044f\u0447"
    ],
    "name:und_x_variant":[
        "Gadyach"
    ],
    "wof:name":"Hadyach",
    "wof:placetype":"locality"
},
  "geometry": {"coordinates":[35.40175,49.28901],"type":"Point"}
}