{
  "type": "Feature",
  "properties": {
    "gn:admin1_code":"11.0",
    "gn:admin2_code":"709333",
    "gn:admin3_code":"11152860",
    "gn:asciiname":"Novaya Zhizn'",
    "gn:country_code":"UA",
    "gn:dem":17,
    "gn:elevation":"16.0",
    "gn:feature_class":"P",
    "gn:feature_code":"PPL",
    "gn:name":"Novaya Zhizn\u2019",
    "gn:population":722,
    "gn:timezone":"Europe/Simferopol",
    "iso:country":"UA",
    "name:eng_x_preferred":[
        "Novaya Zhizn\u2019"
    ],
    "name:rus_x_preferred":[
        "\u041d\u043e\u0432\u0430\u044f \u0416\u0438\u0437\u043d\u044c"
    ],
    "name:ukr_x_preferred":[
        "\u041d\u043e\u0432\u0435 \u0416\u0438\u0442\u0442\u044f"
    ],
    "wof:name":"Novaya Zhizn'",
    "wof:placetype":"locality",
    "wof:population":722
},
  "geometry": {"coordinates":[34.4982,45.66462],"type":"Point"}
}