{
  "type": "Feature",
  "properties": {
    "gn:admin1_code":"26.0",
    "gn:asciiname":"Ocheretuvate",
    "gn:country_code":"UA",
    "gn:dem":198,
    "gn:feature_class":"P",
    "gn:feature_code":"PPL",
    "gn:name":"Ocheretuvate",
    "gn:population":0,
    "gn:timezone":"Europe/Zaporozhye",
    "iso:country":"UA",
    "name:ukr_x_preferred":[
        "Ocheretuvate"
    ],
    "name:ukr_x_variant":[
        "\u041e\u0447\u0435\u0440\u0435\u0442\u0443\u0432\u0430\u0442\u0435"
    ],
    "name:und_x_variant":[
        "Ocheretovaty",
        "Ocheretovatyy"
    ],
    "wof:name":"Ocheretuvate",
    "wof:placetype":"locality"
},
  "geometry": {"coordinates":[36.78943,47.36955],"type":"Point"}
}