{
  "type": "Feature",
  "properties": {
    "iso:country":"UA",
    "name:eng_x_preferred":[
        "Rovnoye"
    ],
    "name:eng_x_variant":[
        "Adzhi Atman",
        "Adzhsi-Atman"
    ],
    "name:rus_x_historical":[
        "\u041a\u0430\u0440\u0430\u0441\u0430\u0301\u043d"
    ],
    "name:rus_x_preferred":[
        "\u041a\u0430\u0440\u0430\u0441\u0430\u0301\u043d"
    ],
    "name:rus_x_variant":[
        "\u0420\u043e\u0432\u043d\u043e\u0435"
    ],
    "name:ukr_x_preferred":[
        "\u0420\u0456\u0432\u043d\u0435"
    ],
    "qs:a0":"\u0423\u043a\u0440\u0430\u0457\u043d\u0430",
    "qs:a1":"*\u041a\u0440\u0438\u043c",
    "qs:a1_alt":"Krym",
    "qs:a1r":"0",
    "qs:a2":"\u041a\u0440\u0430\u0441\u043d\u043e\u0433\u0432\u0430\u0440\u0434\u0456\u0439\u0441\u044c\u043a\u0438\u0439",
    "qs:a2_alt":"Krasnohvardiis'kyi",
    "qs:adm0":"\u0423\u043a\u0440\u0430\u0457\u043d\u0430",
    "qs:la_lc":"*",
    "qs:level":"locality",
    "qs:loc":"\u0420\u0456\u0432\u043d\u0435",
    "qs:loc_alt":"Rivne",
    "qs:pop":0,
    "qs:type":"buffered point",
    "wd:wordcount":1511,
    "wof:lang":[
        "eng"
    ],
    "wof:name":"\u0420\u0456\u0432\u043d\u0435",
    "wof:placetype":"locality"
},
  "geometry": {"coordinates":[34.354437,45.350175],"type":"Point"}
}