{
  "type": "Feature",
  "properties": {
    "gn:admin1_code":"18.0",
    "gn:asciiname":"Burty",
    "gn:country_code":"UA",
    "gn:dem":102,
    "gn:feature_class":"P",
    "gn:feature_code":"PPL",
    "gn:name":"Burty",
    "gn:population":0,
    "gn:timezone":"Europe/Kiev",
    "iso:country":"UA",
    "name:ukr_x_preferred":[
        "Burty"
    ],
    "name:ukr_x_variant":[
        "\u0411\u0443\u0440\u0442\u0438"
    ],
    "wof:name":"Burty",
    "wof:placetype":"locality"
},
  "geometry": {"coordinates":[34.64482,49.14528],"type":"Point"}
}