{
  "type": "Feature",
  "properties": {
    "gn:admin1_code":"9.0",
    "gn:asciiname":"Chernyy Ostrov",
    "gn:country_code":"UA",
    "gn:dem":293,
    "gn:feature_class":"P",
    "gn:feature_code":"PPL",
    "gn:name":"Ch\u00ebrnyy Ostrov",
    "gn:population":0,
    "gn:timezone":"Europe/Kiev",
    "iso:country":"UA",
    "name:und_x_variant":[
        "Cherny Ostrov",
        "Ch\u00ebrnyy Ostrov"
    ],
    "wof:name":"Chernyy Ostrov",
    "wof:placetype":"locality"
},
  "geometry": {"coordinates":[26.75766,49.50569],"type":"Point"}
}