{
  "type": "Feature",
  "properties": {
    "gn:admin1_code":"4.0",
    "gn:asciiname":"Brats'ke",
    "gn:country_code":"UA",
    "gn:dem":125,
    "gn:feature_class":"P",
    "gn:feature_code":"PPL",
    "gn:name":"Brats\u2019ke",
    "gn:population":0,
    "gn:timezone":"Europe/Kiev",
    "iso:country":"UA",
    "name:ukr_x_preferred":[
        "Brats\u2019ke"
    ],
    "name:ukr_x_variant":[
        "\u0411\u0440\u0430\u0442\u0441\u044c\u043a\u0435"
    ],
    "wof:name":"Brats'ke",
    "wof:placetype":"locality"
},
  "geometry": {"coordinates":[34.35468,48.53888],"type":"Point"}
}