{
  "type": "Feature",
  "properties": {
    "iso:country":"UA",
    "name:eng_x_preferred":[
        "Nyzhnie Synovydne"
    ],
    "name:pol_x_preferred":[
        "Synow\u00f3dzko Ni\u017cne"
    ],
    "name:ron_x_preferred":[
        "N\u00eejnie S\u00eenov\u00eedne"
    ],
    "name:rus_x_preferred":[
        "\u041d\u0438\u0436\u043d\u0435\u0435 \u0421\u0438\u043d\u0435\u0432\u0438\u0434\u043d\u043e\u0435"
    ],
    "name:ukr_x_preferred":[
        "\u041d\u0438\u0436\u043d\u0454 \u0421\u0438\u043d\u044c\u043e\u0432\u0438\u0434\u043d\u0435"
    ],
    "name:und_x_variant":[
        "Nyzhnye Syn\u2019ovydne"
    ],
    "name:zho_x_preferred":[
        "\u4e0b\u8f9b\u5967\u7dad\u5fb7\u6d85"
    ],
    "qs:a0":"\u0423\u043a\u0440\u0430\u0457\u043d\u0430",
    "qs:a1":"*\u041b\u044c\u0432\u0456\u0432\u0441\u044c\u043a\u0430",
    "qs:a1_alt":"L'vivs'ka",
    "qs:a1r":"0",
    "qs:a2":"\u0421\u043a\u043e\u043b\u0456\u0432\u0441\u044c\u043a\u0438\u0439",
    "qs:a2_alt":"Skolivs'kyi",
    "qs:adm0":"\u0423\u043a\u0440\u0430\u0457\u043d\u0430",
    "qs:la_lc":"*",
    "qs:level":"locality",
    "qs:loc":"\u041d\u0438\u0436\u043d\u0454 \u0421\u0438\u043d\u044c\u043e\u0432\u0438\u0434\u043d\u0435",
    "qs:loc_alt":"Nyzhnie Syn'ovydne",
    "qs:pop":0,
    "qs:type":"buffered point",
    "wd:wordcount":221,
    "wof:name":"\u041d\u0438\u0436\u043d\u0454 \u0421\u0438\u043d\u044c\u043e\u0432\u0438\u0434\u043d\u0435",
    "wof:placetype":"locality"
},
  "geometry": {"coordinates":[23.635137,49.105542],"type":"Point"}
}