{
  "type": "Feature",
  "properties": {
    "gn:admin1_code":"21.0",
    "gn:asciiname":"Anastasivka",
    "gn:country_code":"UA",
    "gn:dem":168,
    "gn:feature_class":"P",
    "gn:feature_code":"PPL",
    "gn:name":"Anastasivka",
    "gn:population":0,
    "gn:timezone":"Europe/Kiev",
    "iso:country":"UA",
    "name:rus_x_preferred":[
        "Anastas\u2019yevka"
    ],
    "name:ukr_x_preferred":[
        "Anastasivka"
    ],
    "name:ukr_x_variant":[
        "\u0410\u043d\u0430\u0441\u0442\u0430\u0441\u0456\u0432\u043a\u0430"
    ],
    "wof:name":"Anastasivka",
    "wof:placetype":"locality"
},
  "geometry": {"coordinates":[33.55935,50.58202],"type":"Point"}
}