{
  "type": "Feature",
  "properties": {
    "gn:admin1_code":"11.0",
    "gn:admin2_code":"693803",
    "gn:admin3_code":"11152617.0",
    "gn:asciiname":"Topol'noye",
    "gn:country_code":"UA",
    "gn:dem":365,
    "gn:elevation":"365.0",
    "gn:feature_class":"P",
    "gn:feature_code":"PPL",
    "gn:name":"Topol\u2019noye",
    "gn:population":181,
    "gn:timezone":"Europe/Simferopol",
    "iso:country":"UA",
    "name:eng_x_preferred":[
        "Topol\u2019noye"
    ],
    "name:rus_x_preferred":[
        "\u0422\u043e\u043f\u043e\u043b\u044c\u043d\u043e\u0435"
    ],
    "name:ukr_x_preferred":[
        "\u0422\u043e\u043f\u043e\u043b\u044c\u043d\u0435"
    ],
    "wof:name":"Topol'noye",
    "wof:placetype":"locality",
    "wof:population":181
},
  "geometry": {"coordinates":[34.09315,44.84404],"type":"Point"}
}