{
  "type": "Feature",
  "properties": {
    "iso:country":"UA",
    "name:deu_x_preferred":[
        "Kossiwska Poljana"
    ],
    "name:eng_x_preferred":[
        "Kosivska Poliana"
    ],
    "name:epo_x_preferred":[
        "Kosivska Poljana"
    ],
    "name:hun_x_preferred":[
        "Kasz\u00f3mez\u0151"
    ],
    "name:hye_x_preferred":[
        "\u053f\u0578\u057d\u0578\u057e\u057d\u056f\u0561\u0575\u0561 \u054a\u0578\u056c\u0575\u0561\u0576\u0561"
    ],
    "name:nld_x_preferred":[
        "Kosivska Poliana"
    ],
    "name:ron_x_preferred":[
        "Cos\u0103u\u021bi"
    ],
    "name:rus_x_preferred":[
        "\u041a\u043e\u0441\u043e\u0432\u0441\u043a\u0430\u044f \u041f\u043e\u043b\u044f\u043d\u0430"
    ],
    "name:ukr_x_preferred":[
        "\u041a\u043e\u0441\u0456\u0432\u0441\u044c\u043a\u0430 \u041f\u043e\u043b\u044f\u043d\u0430"
    ],
    "name:und_x_variant":[
        "Kosovska Polyana"
    ],
    "name:zho_x_preferred":[
        "\u79d1\u897f\u592b\u897f\u5361\u6ce2\u5229\u4e9e\u7d0d"
    ],
    "qs:a0":"\u0423\u043a\u0440\u0430\u0457\u043d\u0430",
    "qs:a1":"*\u0417\u0430\u043a\u0430\u0440\u043f\u0430\u0442\u0441\u044c\u043a\u0430",
    "qs:a1_alt":"Zakarpats'ka",
    "qs:a1r":"0",
    "qs:a2":"\u0420\u0430\u0445\u0456\u0432\u0441\u044c\u043a\u0438\u0439",
    "qs:a2_alt":"Rakhivs'kyi",
    "qs:adm0":"\u0423\u043a\u0440\u0430\u0457\u043d\u0430",
    "qs:la_lc":"*",
    "qs:level":"locality",
    "qs:loc":"\u041a\u043e\u0441\u0456\u0432\u0441\u044c\u043a\u0430 \u041f\u043e\u043b\u044f\u043d\u0430",
    "qs:loc_alt":"Kosivs'ka Poliana",
    "qs:pop":0,
    "qs:type":"buffered point",
    "wd:wordcount":40,
    "wof:name":"\u041a\u043e\u0441\u0456\u0432\u0441\u044c\u043a\u0430 \u041f\u043e\u043b\u044f\u043d\u0430",
    "wof:placetype":"locality"
},
  "geometry": {"coordinates":[24.096233,47.985061],"type":"Point"}
}