{
  "type": "Feature",
  "properties": {
    "gn:admin1_code":"18.0",
    "gn:asciiname":"Vyshchi Vil'shany",
    "gn:country_code":"UA",
    "gn:dem":89,
    "gn:feature_class":"P",
    "gn:feature_code":"PPL",
    "gn:name":"Vyshchi Vil\u2019shany",
    "gn:population":0,
    "gn:timezone":"Europe/Kiev",
    "iso:country":"UA",
    "name:ukr_x_preferred":[
        "Vyshchi Vil\u2019shany"
    ],
    "name:ukr_x_variant":[
        "\u0412\u0438\u0449\u0456 \u0412\u0456\u043b\u044c\u0448\u0430\u043d\u0438"
    ],
    "name:und_x_variant":[
        "Verkhnaya Ol\u2019shanka",
        "Verkhnyaya Ol\u2019shanka",
        "Ol\u2019shany"
    ],
    "wof:name":"Vyshchi Vil'shany",
    "wof:placetype":"locality"
},
  "geometry": {"coordinates":[34.47767,49.50363],"type":"Point"}
}