{
  "type": "Feature",
  "properties": {
    "gn:admin1_code":"18.0",
    "gn:asciiname":"Solontsi",
    "gn:country_code":"UA",
    "gn:dem":96,
    "gn:feature_class":"P",
    "gn:feature_code":"PPL",
    "gn:name":"Solontsi",
    "gn:population":0,
    "gn:timezone":"Europe/Kiev",
    "iso:country":"UA",
    "name:eng_x_preferred":[
        "Solontsy"
    ],
    "name:rus_x_preferred":[
        "\u0421\u043e\u043b\u043e\u043d\u0446\u044b"
    ],
    "name:ukr_x_preferred":[
        "Solontsi"
    ],
    "name:ukr_x_variant":[
        "\u0421\u043e\u043b\u043e\u043d\u0446\u0456"
    ],
    "wof:name":"Solontsi",
    "wof:placetype":"locality"
},
  "geometry": {"coordinates":[33.87297,49.98361],"type":"Point"}
}