{
  "type": "Feature",
  "properties": {
    "gn:admin1_code":"5.0",
    "gn:asciiname":"Vitava",
    "gn:cc2":"UA",
    "gn:country_code":"UA",
    "gn:dem":34,
    "gn:feature_class":"P",
    "gn:feature_code":"PPL",
    "gn:name":"Vitava",
    "gn:population":0,
    "gn:timezone":"Europe/Kiev",
    "iso:country":"UA",
    "name:ukr_x_preferred":[
        "\u0412\u0456\u0442\u0430\u0432\u0430"
    ],
    "name:und_x_variant":[
        "Vitaya",
        "Vitava"
    ],
    "wof:name":"Vitava",
    "wof:placetype":"locality"
},
  "geometry": {"coordinates":[38.14694,47.26833],"type":"Point"}
}