{
  "type": "Feature",
  "properties": {
    "gn:admin1_code":"7.0",
    "gn:asciiname":"Fedorivka",
    "gn:country_code":"UA",
    "gn:dem":138,
    "gn:feature_class":"P",
    "gn:feature_code":"PPL",
    "gn:name":"Fedorivka",
    "gn:population":0,
    "gn:timezone":"Europe/Kiev",
    "iso:country":"UA",
    "name:ukr_x_preferred":[
        "Fedorivka"
    ],
    "name:ukr_x_variant":[
        "\u0424\u0435\u0434\u043e\u0440\u0456\u0432\u043a\u0430"
    ],
    "name:und_x_variant":[
        "Fedorovshchino"
    ],
    "wof:name":"Fedorivka",
    "wof:placetype":"locality"
},
  "geometry": {"coordinates":[36.06117,49.72466],"type":"Point"}
}