{
  "type": "Feature",
  "properties": {
    "gn:admin1_code":"24.0",
    "gn:asciiname":"Novosilky",
    "gn:country_code":"UA",
    "gn:dem":193,
    "gn:feature_class":"P",
    "gn:feature_code":"PPL",
    "gn:name":"Novosilky",
    "gn:population":0,
    "gn:timezone":"Europe/Kiev",
    "iso:country":"UA",
    "name:rus_x_preferred":[
        "Novos\u00eblki"
    ],
    "name:ukr_x_preferred":[
        "Novosilky"
    ],
    "name:ukr_x_variant":[
        "\u041d\u043e\u0432\u043e\u0441\u0456\u043b\u043a\u0438"
    ],
    "wof:name":"Novosilky",
    "wof:placetype":"locality"
},
  "geometry": {"coordinates":[24.29282000000001,51.18697],"type":"Point"}
}