{
  "type": "Feature",
  "properties": {
    "gn:admin1_code":"27.0",
    "gn:asciiname":"Horodyshche",
    "gn:country_code":"UA",
    "gn:dem":213,
    "gn:feature_class":"P",
    "gn:feature_code":"PPL",
    "gn:name":"Horodyshche",
    "gn:population":0,
    "gn:timezone":"Europe/Kiev",
    "iso:country":"UA",
    "name:ara_x_preferred":[
        "\u0647\u0648\u0631\u0648\u062f\u064a\u0634\u062a\u0634\u064a"
    ],
    "name:bel_x_preferred":[
        "\u0413\u0430\u0440\u0430\u0434\u044b\u0448\u0447\u044d"
    ],
    "name:ceb_x_preferred":[
        "Horodyshche"
    ],
    "name:ces_x_preferred":[
        "Horody\u0161\u010de"
    ],
    "name:crh_x_preferred":[
        "Gorod\u0131\u015f\u00e7e"
    ],
    "name:deu_x_preferred":[
        "Horodyschtsche"
    ],
    "name:fas_x_preferred":[
        "\u0647\u0648\u0631\u0648\u062f\u06cc\u0634\u0686\u0647"
    ],
    "name:fra_x_preferred":[
        "Horodychtche"
    ],
    "name:hsb_x_preferred":[
        "Horody\u0161\u0107e"
    ],
    "name:hye_x_preferred":[
        "\u0533\u0578\u0580\u0578\u0564\u056b\u0577\u0579\u0565"
    ],
    "name:ita_x_preferred":[
        "Horody\u0161\u010de"
    ],
    "name:kat_x_preferred":[
        "\u10d2\u10dd\u10e0\u10dd\u10d3\u10d8\u10e8\u10e9\u10d4"
    ],
    "name:lav_x_preferred":[
        "Horodi\u0161\u010de"
    ],
    "name:lit_x_preferred":[
        "Horody\u0161\u010d\u0117"
    ],
    "name:nno_x_preferred":[
        "Horodysjtsje"
    ],
    "name:pol_x_preferred":[
        "Horodyszcze"
    ],
    "name:ron_x_preferred":[
        "Horod\u00ee\u0219ce"
    ],
    "name:rus_x_preferred":[
        "\u0413\u043e\u0440\u043e\u0434\u0438\u0449\u0435"
    ],
    "name:ukr_x_preferred":[
        "Horodyshche"
    ],
    "name:ukr_x_variant":[
        "\u0413\u043e\u0440\u043e\u0434\u0438\u0449\u0435"
    ],
    "name:und_x_variant":[
        "Gorodishche"
    ],
    "name:vie_x_preferred":[
        "Horodysche"
    ],
    "name:zho_x_preferred":[
        "\u6208\u7f85\u5b63\u8b1d"
    ],
    "wof:name":"Horodyshche",
    "wof:placetype":"locality"
},
  "geometry": {"coordinates":[27.49616,50.61967],"type":"Point"}
}