{
  "type": "Feature",
  "properties": {
    "iso:country":"UA",
    "name:eng_x_preferred":[
        "Vedil'tsy"
    ],
    "name:rus_x_preferred":[
        "\u0412\u0435\u0434\u0438\u043b\u044c\u0446\u044b"
    ],
    "name:rus_x_variant":[
        "Vedil\u2019tsy"
    ],
    "name:ukr_x_preferred":[
        "Vedyl\u2019tsi"
    ],
    "name:ukr_x_variant":[
        "\u0412\u0435\u0434\u0438\u043b\u044c\u0446\u0456"
    ],
    "name:unk_x_variant":[
        "Videl\u2019tsy"
    ],
    "qs:a0":"\u0423\u043a\u0440\u0430\u0457\u043d\u0430",
    "qs:a1":"*\u0427\u0435\u0440\u043d\u0456\u0433\u0456\u0432\u0441\u044c\u043a\u0430",
    "qs:a1_alt":"Chernihivs'ka",
    "qs:a1r":"0",
    "qs:a2":"\u0427\u0435\u0440\u043d\u0456\u0433\u0456\u0432\u0441\u044c\u043a\u0438\u0439",
    "qs:a2_alt":"Chernihivs'kyi",
    "qs:adm0":"\u0423\u043a\u0440\u0430\u0457\u043d\u0430",
    "qs:la_lc":"*",
    "qs:level":"locality",
    "qs:loc":"\u0412\u0435\u0434\u0438\u043b\u044c\u0446\u0456",
    "qs:loc_alt":"Vedyl'tsi",
    "qs:pop":0,
    "qs:type":"buffered point",
    "wof:name":"\u0412\u0435\u0434\u0438\u043b\u044c\u0446\u0456",
    "wof:placetype":"locality"
},
  "geometry": {"coordinates":[30.838265,51.459819],"type":"Point"}
}