{
  "type": "Feature",
  "properties": {
    "gn:admin1_code":"3.0",
    "gn:asciiname":"Lomachintsy",
    "gn:country_code":"UA",
    "gn:dem":252,
    "gn:feature_class":"P",
    "gn:feature_code":"PPL",
    "gn:name":"Lomachintsy",
    "gn:population":0,
    "gn:timezone":"Europe/Kiev",
    "iso:country":"UA",
    "name:und_x_variant":[
        "Lomacine\u0163i",
        "Lomachinets\u2019",
        "Lomachintsy"
    ],
    "wof:name":"Lomachintsy",
    "wof:placetype":"locality"
},
  "geometry": {"coordinates":[27.37027,48.59577],"type":"Point"}
}