{
  "type": "Feature",
  "properties": {
    "gn:admin1_code":"21.0",
    "gn:asciiname":"Dovhopolivka",
    "gn:country_code":"UA",
    "gn:dem":148,
    "gn:feature_class":"P",
    "gn:feature_code":"PPL",
    "gn:name":"Dovhopolivka",
    "gn:population":0,
    "gn:timezone":"Europe/Kiev",
    "iso:country":"UA",
    "name:ukr_x_preferred":[
        "Dovhopolivka"
    ],
    "name:ukr_x_variant":[
        "\u0414\u043e\u0432\u0433\u043e\u043f\u043e\u043b\u0456\u0432\u043a\u0430"
    ],
    "name:und_x_variant":[
        "Dolgopolovka"
    ],
    "wof:name":"Dovhopolivka",
    "wof:placetype":"locality"
},
  "geometry": {"coordinates":[33.3577,50.76091],"type":"Point"}
}