{
  "type": "Feature",
  "properties": {
    "gn:admin1_code":"7.0",
    "gn:asciiname":"Dehtyarka",
    "gn:country_code":"UA",
    "gn:dem":181,
    "gn:feature_class":"P",
    "gn:feature_code":"PPL",
    "gn:name":"Dehtyarka",
    "gn:population":0,
    "gn:timezone":"Europe/Kiev",
    "iso:country":"UA",
    "name:ukr_x_preferred":[
        "Dehtyarka"
    ],
    "name:ukr_x_variant":[
        "\u0414\u0435\u0433\u0442\u044f\u0440\u043a\u0430"
    ],
    "name:und_x_variant":[
        "Degtyarka"
    ],
    "wof:name":"Dehtyarka",
    "wof:placetype":"locality"
},
  "geometry": {"coordinates":[35.71124000000001,49.61259],"type":"Point"}
}