{
  "type": "Feature",
  "properties": {
    "gn:admin1_code":"13.0",
    "gn:asciiname":"Ivankovychi",
    "gn:country_code":"UA",
    "gn:dem":157,
    "gn:feature_class":"P",
    "gn:feature_code":"PPL",
    "gn:name":"Ivankovychi",
    "gn:population":0,
    "gn:timezone":"Europe/Kiev",
    "iso:country":"UA",
    "name:ukr_x_preferred":[
        "Ivankovychi"
    ],
    "name:ukr_x_variant":[
        "\u0406\u0432\u0430\u043d\u043a\u043e\u0432\u0438\u0447\u0456"
    ],
    "name:und_x_variant":[
        "Ivankovichi"
    ],
    "wof:name":"Ivankovychi",
    "wof:placetype":"locality"
},
  "geometry": {"coordinates":[30.41513,50.27542],"type":"Point"}
}