{
  "type": "Feature",
  "properties": {
    "gn:admin1_code":"21.0",
    "gn:asciiname":"Zhuravne",
    "gn:country_code":"UA",
    "gn:dem":108,
    "gn:feature_class":"P",
    "gn:feature_code":"PPL",
    "gn:name":"Zhuravne",
    "gn:population":0,
    "gn:timezone":"Europe/Kiev",
    "iso:country":"UA",
    "name:eng_x_preferred":[
        "Zhuravnoye"
    ],
    "name:rus_x_preferred":[
        "\u0416\u0443\u0440\u0430\u0432\u043d\u043e\u0435"
    ],
    "name:ukr_x_preferred":[
        "Zhuravne"
    ],
    "name:ukr_x_variant":[
        "\u0416\u0443\u0440\u0430\u0432\u043d\u0435"
    ],
    "name:und_x_variant":[
        "Zhuravnoye"
    ],
    "wof:name":"Zhuravne",
    "wof:placetype":"locality"
},
  "geometry": {"coordinates":[34.76379,50.24424000000001],"type":"Point"}
}