{
  "type": "Feature",
  "properties": {
    "gn:admin1_code":"21.0",
    "gn:asciiname":"Zhuravne",
    "gn:country_code":"UA",
    "gn:dem":108,
    "gn:feature_class":"P",
    "gn:feature_code":"PPL",
    "gn:name":"Zhuravne",
    "gn:population":0,
    "gn:timezone":"Europe/Kiev",
    "iso:country":"UA",
    "name:ara_x_preferred":[
        "\u062c\u0648\u0631\u0627\u0641\u0646\u0648"
    ],
    "name:bel_x_preferred":[
        "\u0416\u0443\u0440\u0430\u045e\u043d\u044d"
    ],
    "name:crh_x_preferred":[
        "Juravno"
    ],
    "name:deu_x_preferred":[
        "Schurawno"
    ],
    "name:eng_x_preferred":[
        "Zhuravnoye"
    ],
    "name:fra_x_preferred":[
        "Jouravno"
    ],
    "name:heb_x_preferred":[
        "\u05d6'\u05d5\u05e8\u05d0\u05d1\u05e0\u05d5"
    ],
    "name:hye_x_preferred":[
        "\u053a\u0578\u0582\u0580\u0561\u057e\u0576\u0578"
    ],
    "name:pol_x_preferred":[
        "\u017burawno"
    ],
    "name:ron_x_preferred":[
        "Juravne"
    ],
    "name:rus_x_preferred":[
        "\u0416\u0443\u0440\u0430\u0432\u043d\u043e\u0435"
    ],
    "name:rus_x_variant":[
        "\u0416\u0443\u0440\u0430\u0432\u043d\u043e"
    ],
    "name:ukr_x_preferred":[
        "Zhuravne"
    ],
    "name:ukr_x_variant":[
        "\u0416\u0443\u0440\u0430\u0432\u043d\u0435",
        "\u0416\u0443\u0440\u0430\u0432\u043d\u043e"
    ],
    "name:zho_x_preferred":[
        "\u8339\u62c9\u592b\u8afe"
    ],
    "wof:name":"Zhuravne",
    "wof:placetype":"locality"
},
  "geometry": {"coordinates":[34.76379,50.24424000000001],"type":"Point"}
}