{
  "type": "Feature",
  "properties": {
    "gn:admin1_code":"09",
    "gn:asciiname":"Verbivochka",
    "gn:country_code":"UA",
    "gn:dem":327,
    "gn:feature_class":"P",
    "gn:feature_code":"PPL",
    "gn:name":"Verbivochka",
    "gn:population":0,
    "gn:timezone":"Europe/Kiev",
    "iso:country":"UA",
    "name:ukr_x_preferred":[
        "Verbivochka"
    ],
    "name:ukr_x_variant":[
        "\u0412\u0435\u0440\u0431\u0456\u0432\u043e\u0447\u043a\u0430"
    ],
    "wof:name":"Verbivochka",
    "wof:placetype":"locality"
},
  "geometry": {"coordinates":[27.03413,49.83944],"type":"Point"}
}