{
  "type": "Feature",
  "properties": {
    "gn:admin1_code":"3.0",
    "gn:asciiname":"Toporovtsy",
    "gn:country_code":"UA",
    "gn:dem":235,
    "gn:feature_class":"P",
    "gn:feature_code":"PPL",
    "gn:name":"Toporovtsy",
    "gn:population":0,
    "gn:timezone":"Europe/Kiev",
    "iso:country":"UA",
    "name:und_x_variant":[
        "Topor\u0103u\u0163i",
        "Toporouts\u2019",
        "Toporautsy",
        "Toporovtsy"
    ],
    "wof:name":"Toporovtsy",
    "wof:placetype":"locality"
},
  "geometry": {"coordinates":[26.09087,48.38575],"type":"Point"}
}