{
  "type": "Feature",
  "properties": {
    "gn:admin1_code":"7.0",
    "gn:asciiname":"Bugay",
    "gn:cc2":"UA",
    "gn:country_code":"UA",
    "gn:dem":138,
    "gn:feature_class":"P",
    "gn:feature_code":"PPL",
    "gn:name":"Bugay",
    "gn:population":0,
    "gn:timezone":"Europe/Kiev",
    "iso:country":"UA",
    "name:und_x_variant":[
        "Khutor Bugai Pervyye",
        "Bugay"
    ],
    "wof:name":"Bugay",
    "wof:placetype":"locality"
},
  "geometry": {"coordinates":[35.98333,50.31667],"type":"Point"}
}