{
  "type": "Feature",
  "properties": {
    "gn:admin1_code":"27.0",
    "gn:asciiname":"Dvirets'",
    "gn:country_code":"UA",
    "gn:dem":225,
    "gn:feature_class":"P",
    "gn:feature_code":"PPL",
    "gn:name":"Dvirets\u2019",
    "gn:population":0,
    "gn:timezone":"Europe/Kiev",
    "iso:country":"UA",
    "name:ukr_x_preferred":[
        "Dvirets\u2019"
    ],
    "name:ukr_x_variant":[
        "\u0414\u0432\u0456\u0440\u0435\u0446\u044c"
    ],
    "name:und_x_variant":[
        "Dvorets"
    ],
    "wof:name":"Dvirets'",
    "wof:placetype":"locality"
},
  "geometry": {"coordinates":[28.63543,50.1316],"type":"Point"}
}