{
  "type": "Feature",
  "properties": {
    "iso:country":"UA",
    "qs:a0":"\u0423\u043a\u0440\u0430\u0457\u043d\u0430",
    "qs:a1":"*\u0417\u0430\u043f\u043e\u0440\u0456\u0437\u044c\u043a\u0430",
    "qs:a1_alt":"Zaporiz'ka",
    "qs:a1r":"0",
    "qs:a2":"\u041a\u0430\u043c'\u044f\u043d\u0441\u044c\u043a\u043e-\u0414\u043d\u0456\u043f\u0440\u043e\u0432\u0441\u044c\u043a\u0438\u0439",
    "qs:a2_alt":"Kamyans'ko-Dniprovs'kyi",
    "qs:adm0":"\u0423\u043a\u0440\u0430\u0457\u043d\u0430",
    "qs:la_lc":"*",
    "qs:level":"locality",
    "qs:loc":"\u0411\u043b\u0430\u0433\u043e\u0432\u0456\u0449\u0435\u043d\u043a\u0430",
    "qs:loc_alt":"Blahovischenka",
    "qs:pop":0,
    "qs:type":"buffered point",
    "wof:name":"\u0411\u043b\u0430\u0433\u043e\u0432\u0456\u0449\u0435\u043d\u043a\u0430",
    "wof:placetype":"locality"
},
  "geometry": {"coordinates":[34.811084,47.4519],"type":"Point"}
}