{
  "type": "Feature",
  "properties": {
    "gn:admin1_code":"18.0",
    "gn:asciiname":"Melekhy",
    "gn:country_code":"UA",
    "gn:dem":103,
    "gn:feature_class":"P",
    "gn:feature_code":"PPL",
    "gn:name":"Melekhy",
    "gn:population":0,
    "gn:timezone":"Europe/Kiev",
    "iso:country":"UA",
    "name:ukr_x_preferred":[
        "Melekhy"
    ],
    "name:ukr_x_variant":[
        "\u041c\u0435\u043b\u0435\u0445\u0438"
    ],
    "name:und_x_variant":[
        "Melekhi"
    ],
    "wof:name":"Melekhy",
    "wof:placetype":"locality"
},
  "geometry": {"coordinates":[33.05669,50.20878],"type":"Point"}
}