{
  "type": "Feature",
  "properties": {
    "gn:admin1_code":"18.0",
    "gn:asciiname":"Podil",
    "gn:country_code":"UA",
    "gn:dem":104,
    "gn:feature_class":"P",
    "gn:feature_code":"PPL",
    "gn:name":"Podil",
    "gn:population":0,
    "gn:timezone":"Europe/Kiev",
    "iso:country":"UA",
    "name:bel_x_preferred":[
        "\u041f\u0430\u0434\u043e\u043b"
    ],
    "name:chv_x_preferred":[
        "\u041f\u043e\u0434\u043e\u043b"
    ],
    "name:deu_x_preferred":[
        "Podil"
    ],
    "name:fra_x_preferred":[
        "Podil"
    ],
    "name:heb_x_preferred":[
        "\u05e4\u05d5\u05d3\u05d9\u05dc"
    ],
    "name:pol_x_preferred":[
        "Pad\u00f3\u0142"
    ],
    "name:rus_x_preferred":[
        "\u041f\u043e\u0434\u043e\u043b"
    ],
    "name:tur_x_preferred":[
        "Podil"
    ],
    "name:ukr_x_preferred":[
        "Podil"
    ],
    "name:ukr_x_variant":[
        "\u041f\u043e\u0434\u0456\u043b"
    ],
    "name:zho_x_preferred":[
        "\u6ce2\u8fea\u723e\u5340"
    ],
    "wof:name":"Podil",
    "wof:placetype":"locality"
},
  "geometry": {"coordinates":[33.41939,49.56312],"type":"Point"}
}