{
  "type": "Feature",
  "properties": {
    "gn:admin1_code":"18.0",
    "gn:asciiname":"Podil",
    "gn:country_code":"UA",
    "gn:dem":104,
    "gn:feature_class":"P",
    "gn:feature_code":"PPL",
    "gn:name":"Podil",
    "gn:population":0,
    "gn:timezone":"Europe/Kiev",
    "iso:country":"UA",
    "name:ukr_x_preferred":[
        "Podil"
    ],
    "name:ukr_x_variant":[
        "\u041f\u043e\u0434\u0456\u043b"
    ],
    "wof:name":"Podil",
    "wof:placetype":"locality"
},
  "geometry": {"coordinates":[33.41939,49.56312],"type":"Point"}
}