{
  "type": "Feature",
  "properties": {
    "gn:admin1_code":"4.0",
    "gn:asciiname":"Chervonoarmiys'ke",
    "gn:country_code":"UA",
    "gn:dem":73,
    "gn:feature_class":"P",
    "gn:feature_code":"PPL",
    "gn:name":"Chervonoarmiys\u2019ke",
    "gn:population":0,
    "gn:timezone":"Europe/Kiev",
    "iso:country":"UA",
    "name:rus_x_preferred":[
        "\u0427\u0435\u0440\u0432\u043e\u043d\u043e\u0430\u0440\u043c\u0435\u0439\u0441\u043a\u043e\u0435"
    ],
    "name:ukr_x_preferred":[
        "Chervonoarmiys\u2019ke"
    ],
    "name:ukr_x_variant":[
        "\u0427\u0435\u0440\u0432\u043e\u043d\u043e\u0430\u0440\u043c\u0456\u0439\u0441\u044c\u043a\u0435"
    ],
    "name:und_x_variant":[
        "Chervonoarmeyskoye"
    ],
    "wof:name":"Chervonoarmiys'ke",
    "wof:placetype":"locality"
},
  "geometry": {"coordinates":[34.21793,47.98217],"type":"Point"}
}