{
  "type": "Feature",
  "properties": {
    "gn:admin1_code":"22.0",
    "gn:asciiname":"Gribova",
    "gn:country_code":"UA",
    "gn:dem":254,
    "gn:feature_class":"P",
    "gn:feature_code":"PPL",
    "gn:name":"Gribova",
    "gn:population":0,
    "gn:timezone":"Europe/Kiev",
    "iso:country":"UA",
    "name:ita_x_preferred":[
        "Gribova"
    ],
    "name:kat_x_preferred":[
        "\u10d2\u10e0\u10d8\u10d1\u10dd\u10d5\u10d0"
    ],
    "name:ron_x_preferred":[
        "Gribova"
    ],
    "name:rus_x_preferred":[
        "\u0413\u0440\u0438\u0431\u043e\u0432\u0430"
    ],
    "name:ukr_x_preferred":[
        "\u0413\u0440\u0456\u0431\u043e\u0432\u0430"
    ],
    "name:und_x_variant":[
        "Gzhybova"
    ],
    "wof:name":"Gribova",
    "wof:placetype":"locality"
},
  "geometry": {"coordinates":[26.11866,49.89071],"type":"Point"}
}