{
  "type": "Feature",
  "properties": {
    "gn:admin1_code":"22.0",
    "gn:asciiname":"Gribova",
    "gn:country_code":"UA",
    "gn:dem":254,
    "gn:feature_class":"P",
    "gn:feature_code":"PPL",
    "gn:name":"Gribova",
    "gn:population":0,
    "gn:timezone":"Europe/Kiev",
    "iso:country":"UA",
    "name:und_x_variant":[
        "Gzhybova",
        "Gribova"
    ],
    "wof:name":"Gribova",
    "wof:placetype":"locality"
},
  "geometry": {"coordinates":[26.11866,49.89071],"type":"Point"}
}