{
  "type": "Feature",
  "properties": {
    "gn:admin1_code":"15.0",
    "gn:asciiname":"Peremozhnoye",
    "gn:country_code":"UA",
    "gn:dem":277,
    "gn:feature_class":"P",
    "gn:feature_code":"PPL",
    "gn:name":"Peremozhnoye",
    "gn:population":0,
    "gn:timezone":"Europe/Kiev",
    "iso:country":"UA",
    "name:und_x_variant":[
        "Khlopy",
        "Peremozhnoye"
    ],
    "wof:name":"Peremozhnoye",
    "wof:placetype":"locality"
},
  "geometry": {"coordinates":[23.66242,49.63246],"type":"Point"}
}