{
  "type": "Feature",
  "properties": {
    "gn:admin1_code":"5.0",
    "gn:asciiname":"Vovche",
    "gn:country_code":"UA",
    "gn:dem":190,
    "gn:feature_class":"P",
    "gn:feature_code":"PPL",
    "gn:name":"Vovche",
    "gn:population":0,
    "gn:timezone":"Europe/Kiev",
    "iso:country":"UA",
    "name:ukr_x_preferred":[
        "Vovche"
    ],
    "name:ukr_x_variant":[
        "\u0412\u043e\u0432\u0447\u0435"
    ],
    "wof:name":"Vovche",
    "wof:placetype":"locality"
},
  "geometry": {"coordinates":[37.48858,48.23409],"type":"Point"}
}