{
  "type": "Feature",
  "properties": {
    "gn:admin1_code":"23",
    "gn:asciiname":"Yasenetske",
    "gn:country_code":"UA",
    "gn:dem":283,
    "gn:feature_class":"P",
    "gn:feature_code":"PPL",
    "gn:name":"Yasenetske",
    "gn:population":0,
    "gn:timezone":"Europe/Kiev",
    "iso:country":"UA",
    "name:und_x_variant":[
        "\u042f\u0441\u0435\u043d\u0435\u0446\u044c\u043a\u0435"
    ],
    "wof:name":"Yasenetske",
    "wof:placetype":"locality"
},
  "geometry": {"coordinates":[28.88374,49.28348],"type":"Point"}
}