{
  "type": "Feature",
  "properties": {
    "gn:admin1_code":"2.0",
    "gn:asciiname":"Pererost",
    "gn:country_code":"UA",
    "gn:dem":150,
    "gn:feature_class":"P",
    "gn:feature_code":"PPL",
    "gn:name":"Pererost",
    "gn:population":0,
    "gn:timezone":"Europe/Kiev",
    "iso:country":"UA",
    "name:ukr_x_preferred":[
        "Pererost"
    ],
    "name:ukr_x_variant":[
        "\u041f\u0435\u0440\u0435\u0440\u043e\u0441\u0442"
    ],
    "wof:name":"Pererost",
    "wof:placetype":"locality"
},
  "geometry": {"coordinates":[31.31195,51.88216],"type":"Point"}
}