{
  "type": "Feature",
  "properties": {
    "iso:country":"UA",
    "qs:a0":"\u0423\u043a\u0440\u0430\u0457\u043d\u0430",
    "qs:a1":"*\u0412\u0456\u043d\u043d\u0438\u0446\u044c\u043a\u0430",
    "qs:a1_alt":"Vinnyts'ka",
    "qs:a1r":"0",
    "qs:a2":"\u041b\u0456\u0442\u0438\u043d\u0441\u044c\u043a\u0438\u0439",
    "qs:a2_alt":"Lityns'kyi",
    "qs:adm0":"\u0423\u043a\u0440\u0430\u0457\u043d\u0430",
    "qs:la_lc":"*",
    "qs:level":"locality",
    "qs:loc":"\u0406\u0432\u0447\u0430",
    "qs:loc_alt":"Ivcha",
    "qs:pop":0,
    "qs:type":"buffered point",
    "wof:name":"\u0406\u0432\u0447\u0430",
    "wof:placetype":"locality"
},
  "geometry": {"coordinates":[28.046265,49.417322],"type":"Point"}
}