{
  "type": "Feature",
  "properties": {
    "gn:admin1_code":"7.0",
    "gn:asciiname":"Dunyne",
    "gn:country_code":"UA",
    "gn:dem":176,
    "gn:feature_class":"P",
    "gn:feature_code":"PPL",
    "gn:name":"Dunyne",
    "gn:population":0,
    "gn:timezone":"Europe/Kiev",
    "iso:country":"UA",
    "name:ukr_x_preferred":[
        "Dunyne"
    ],
    "name:ukr_x_variant":[
        "\u0414\u0443\u043d\u0438\u043d\u0435"
    ],
    "name:und_x_variant":[
        "Dunina",
        "Dunino"
    ],
    "wof:name":"Dunyne",
    "wof:placetype":"locality"
},
  "geometry": {"coordinates":[36.6568,48.8616],"type":"Point"}
}