{
  "type": "Feature",
  "properties": {
    "gn:admin1_code":"13.0",
    "gn:asciiname":"Stepove",
    "gn:country_code":"UA",
    "gn:dem":221,
    "gn:feature_class":"P",
    "gn:feature_code":"PPL",
    "gn:name":"Stepove",
    "gn:population":0,
    "gn:timezone":"Europe/Kiev",
    "iso:country":"UA",
    "name:deu_x_preferred":[
        "Stepowe"
    ],
    "name:hye_x_preferred":[
        "\u054d\u057f\u0565\u057a\u0578\u057e\u0578\u0565"
    ],
    "name:rus_x_preferred":[
        "\u0421\u0442\u0435\u043f\u043e\u0432\u043e\u0435"
    ],
    "name:ukr_x_preferred":[
        "Stepove"
    ],
    "name:ukr_x_variant":[
        "\u0421\u0442\u0435\u043f\u043e\u0432\u0435"
    ],
    "wof:name":"Stepove",
    "wof:placetype":"locality"
},
  "geometry": {"coordinates":[29.66483,49.89773],"type":"Point"}
}