{
  "type": "Feature",
  "properties": {
    "gn:admin1_code":"24.0",
    "gn:asciiname":"Dykovyny",
    "gn:country_code":"UA",
    "gn:dem":213,
    "gn:feature_class":"P",
    "gn:feature_code":"PPL",
    "gn:name":"Dykovyny",
    "gn:population":0,
    "gn:timezone":"Europe/Kiev",
    "iso:country":"UA",
    "name:ukr_x_preferred":[
        "Dykovyny"
    ],
    "name:ukr_x_variant":[
        "\u0414\u0438\u043a\u043e\u0432\u0438\u043d\u0438"
    ],
    "name:und_x_variant":[
        "Dzikowiny",
        "Dzikoviny",
        "Dikoviny"
    ],
    "wof:name":"Dykovyny",
    "wof:placetype":"locality"
},
  "geometry": {"coordinates":[24.9821,50.38374],"type":"Point"}
}