{
  "type": "Feature",
  "properties": {
    "gn:admin1_code":"11.0",
    "gn:admin2_code":"709333",
    "gn:admin3_code":"11152848.0",
    "gn:asciiname":"Perepyolkino",
    "gn:country_code":"UA",
    "gn:dem":12,
    "gn:elevation":"11.0",
    "gn:feature_class":"P",
    "gn:feature_code":"PPL",
    "gn:name":"Perepyolkino",
    "gn:population":461,
    "gn:timezone":"Europe/Simferopol",
    "iso:country":"UA",
    "name:eng_x_preferred":[
        "Perepyolkino"
    ],
    "name:rus_x_historical":[
        "\u041a\u0430\u043c\u0431\u0430\u0301\u0440-\u0412\u0430\u043a\u0443\u0301\u0444"
    ],
    "name:rus_x_preferred":[
        "\u041f\u0435\u0440\u0435\u043f\u0451\u043b\u043a\u0438\u043d\u043e"
    ],
    "name:rus_x_variant":[
        "\u041a\u0430\u043c\u0431\u0430\u0301\u0440-\u0412\u0430\u043a\u0443\u0301\u0444"
    ],
    "name:ukr_x_preferred":[
        "\u041f\u0435\u0440\u0435\u043f\u0456\u043b\u043a\u0438\u043d\u0435"
    ],
    "wof:name":"Perepyolkino",
    "wof:placetype":"locality",
    "wof:population":461
},
  "geometry": {"coordinates":[34.56375999999999,45.74237],"type":"Point"}
}