{
  "type": "Feature",
  "properties": {
    "gn:admin1_code":"17.0",
    "gn:asciiname":"Dzhuhastrove",
    "gn:country_code":"UA",
    "gn:dem":83,
    "gn:feature_class":"P",
    "gn:feature_code":"PPL",
    "gn:name":"Dzhuhastrove",
    "gn:population":0,
    "gn:timezone":"Europe/Kiev",
    "iso:country":"UA",
    "name:ukr_x_preferred":[
        "Dzhuhastrove"
    ],
    "name:ukr_x_variant":[
        "\u0414\u0436\u0443\u0433\u0430\u0441\u0442\u0440\u043e\u0432\u0435"
    ],
    "name:und_x_variant":[
        "Dzhugastrova",
        "Dzhugastrovo"
    ],
    "wof:name":"Dzhuhastrove",
    "wof:placetype":"locality"
},
  "geometry": {"coordinates":[30.59474,47.08704],"type":"Point"}
}