{
  "type": "Feature",
  "properties": {
    "gn:admin1_code":"27.0",
    "gn:asciiname":"Lisna Rudnya",
    "gn:country_code":"UA",
    "gn:dem":221,
    "gn:feature_class":"P",
    "gn:feature_code":"PPL",
    "gn:name":"Lisna Rudnya",
    "gn:population":0,
    "gn:timezone":"Europe/Kiev",
    "iso:country":"UA",
    "name:ukr_x_preferred":[
        "Lisna Rudnya"
    ],
    "name:ukr_x_variant":[
        "\u041b\u0456\u0441\u043d\u0430 \u0420\u0443\u0434\u043d\u044f"
    ],
    "name:und_x_variant":[
        "Lesnaya Rudnya",
        "Khutor Lesnaya Rudnya"
    ],
    "wof:name":"Lisna Rudnya",
    "wof:placetype":"locality"
},
  "geometry": {"coordinates":[28.12564,50.16149],"type":"Point"}
}