{
  "type": "Feature",
  "properties": {
    "gn:admin1_code":"21.0",
    "gn:asciiname":"Olenyns'ke",
    "gn:country_code":"UA",
    "gn:dem":121,
    "gn:feature_class":"P",
    "gn:feature_code":"PPL",
    "gn:name":"Olenyns\u2019ke",
    "gn:population":0,
    "gn:timezone":"Europe/Kiev",
    "iso:country":"UA",
    "name:ukr_x_preferred":[
        "Olenyns\u2019ke"
    ],
    "name:ukr_x_variant":[
        "\u041e\u043b\u0435\u043d\u0438\u043d\u0441\u044c\u043a\u0435"
    ],
    "name:und_x_variant":[
        "Alenina",
        "Alenino"
    ],
    "wof:name":"Olenyns'ke",
    "wof:placetype":"locality"
},
  "geometry": {"coordinates":[34.52887,50.37149],"type":"Point"}
}