{
  "type": "Feature",
  "properties": {
    "gn:admin1_code":"19.0",
    "gn:asciiname":"Novomyl's'k",
    "gn:country_code":"UA",
    "gn:dem":202,
    "gn:feature_class":"P",
    "gn:feature_code":"PPL",
    "gn:name":"Novomyl\u2019s\u2019k",
    "gn:population":0,
    "gn:timezone":"Europe/Kiev",
    "iso:country":"UA",
    "name:ukr_x_preferred":[
        "Novomyl\u2019s\u2019k"
    ],
    "name:ukr_x_variant":[
        "\u041d\u043e\u0432\u043e\u043c\u0438\u043b\u044c\u0441\u044c\u043a"
    ],
    "name:und_x_variant":[
        "Myysk Novy",
        "Novy Myish",
        "Novomil\u2019sk",
        "Novomyl\u2019sk"
    ],
    "wof:name":"Novomyl's'k",
    "wof:placetype":"locality"
},
  "geometry": {"coordinates":[26.29721,50.50666],"type":"Point"}
}