{
  "type": "Feature",
  "properties": {
    "gn:admin1_code":"26.0",
    "gn:asciiname":"Mar'yivka",
    "gn:country_code":"UA",
    "gn:dem":98,
    "gn:feature_class":"P",
    "gn:feature_code":"PPL",
    "gn:name":"Mar\u2019yivka",
    "gn:population":0,
    "gn:timezone":"Europe/Zaporozhye",
    "iso:country":"UA",
    "name:und_x_variant":[
        "Mar\u2019yevka",
        "Mar\u2019yivka"
    ],
    "wof:name":"Mar'yivka",
    "wof:placetype":"locality"
},
  "geometry": {"coordinates":[34.99516,47.69305],"type":"Point"}
}