{
  "type": "Feature",
  "properties": {
    "gn:admin1_code":"27.0",
    "gn:asciiname":"Tarasivka",
    "gn:country_code":"UA",
    "gn:dem":223,
    "gn:feature_class":"P",
    "gn:feature_code":"PPL",
    "gn:name":"Tarasivka",
    "gn:population":0,
    "gn:timezone":"Europe/Kiev",
    "iso:country":"UA",
    "name:bel_x_preferred":[
        "\u0422\u0430\u0440\u0430\u0441\u0430\u045e\u043a\u0430"
    ],
    "name:deu_x_preferred":[
        "Tarassiwka"
    ],
    "name:rus_x_preferred":[
        "\u0422\u0430\u0440\u0430\u0441\u043e\u0432\u043a\u0430"
    ],
    "name:ukr_x_preferred":[
        "Tarasivka"
    ],
    "name:ukr_x_variant":[
        "\u0422\u0430\u0440\u0430\u0441\u0456\u0432\u043a\u0430"
    ],
    "name:und_x_variant":[
        "Tarasovka"
    ],
    "wof:name":"Tarasivka",
    "wof:placetype":"locality"
},
  "geometry": {"coordinates":[28.85804000000001,50.17711],"type":"Point"}
}