{
  "type": "Feature",
  "properties": {
    "gn:admin1_code":"5.0",
    "gn:asciiname":"Kleban-Byk",
    "gn:country_code":"UA",
    "gn:dem":132,
    "gn:feature_class":"P",
    "gn:feature_code":"PPL",
    "gn:name":"Kleban-Byk",
    "gn:population":0,
    "gn:timezone":"Europe/Kiev",
    "iso:country":"UA",
    "name:ukr_x_preferred":[
        "\u041a\u043b\u0435\u0431\u0430\u043d-\u0411\u0438\u043a"
    ],
    "name:und_x_variant":[
        "Bykstroy",
        "Kleban-Byk"
    ],
    "wof:name":"Kleban-Byk",
    "wof:placetype":"locality"
},
  "geometry": {"coordinates":[37.76521,48.42608],"type":"Point"}
}