{
  "type": "Feature",
  "properties": {
    "gn:admin1_code":"16.0",
    "gn:asciiname":"Kozubovka",
    "gn:country_code":"UA",
    "gn:dem":34,
    "gn:feature_class":"P",
    "gn:feature_code":"PPL",
    "gn:name":"Kozubovka",
    "gn:population":0,
    "gn:timezone":"Europe/Kiev",
    "iso:country":"UA",
    "name:und_x_variant":[
        "Moldavka",
        "Kozubovka"
    ],
    "wof:name":"Kozubovka",
    "wof:placetype":"locality"
},
  "geometry": {"coordinates":[31.14531,47.54244],"type":"Point"}
}