{
  "type": "Feature",
  "properties": {
    "gn:admin1_code":"7.0",
    "gn:asciiname":"Ryabukhyne",
    "gn:country_code":"UA",
    "gn:dem":179,
    "gn:feature_class":"P",
    "gn:feature_code":"PPL",
    "gn:name":"Ryabukhyne",
    "gn:population":0,
    "gn:timezone":"Europe/Kiev",
    "iso:country":"UA",
    "name:ukr_x_preferred":[
        "Ryabukhyne"
    ],
    "name:ukr_x_variant":[
        "\u0420\u044f\u0431\u0443\u0445\u0438\u043d\u0435"
    ],
    "name:und_x_variant":[
        "Ryabukhino"
    ],
    "wof:name":"Ryabukhyne",
    "wof:placetype":"locality"
},
  "geometry": {"coordinates":[36.03061,49.6296],"type":"Point"}
}