{
  "type": "Feature",
  "properties": {
    "gn:admin1_code":"11.0",
    "gn:admin2_code":"712585",
    "gn:admin3_code":"11152839.0",
    "gn:asciiname":"Muromskoye",
    "gn:country_code":"UA",
    "gn:dem":213,
    "gn:elevation":"209.0",
    "gn:feature_class":"P",
    "gn:feature_code":"PPLA3",
    "gn:name":"Muromskoye",
    "gn:population":755,
    "gn:timezone":"Europe/Simferopol",
    "iso:country":"UA",
    "name:eng_x_preferred":[
        "Muromskoye"
    ],
    "name:rus_x_historical":[
        "\u041c\u0430\u0301\u043b\u044b\u0439 \u0411\u0443\u0440\u0443\u043d\u0434\u0443\u0301\u043a"
    ],
    "name:rus_x_preferred":[
        "\u041c\u0443\u0440\u043e\u043c\u0441\u043a\u043e\u0435"
    ],
    "name:rus_x_variant":[
        "\u041c\u0430\u0301\u043b\u044b\u0439 \u0411\u0443\u0440\u0443\u043d\u0434\u0443\u0301\u043a"
    ],
    "name:ukr_x_preferred":[
        "\u041c\u0443\u0440\u043e\u043c\u0441\u044c\u043a\u0435"
    ],
    "wof:name":"Muromskoye",
    "wof:placetype":"locality",
    "wof:population":755
},
  "geometry": {"coordinates":[34.849,45.09051],"type":"Point"}
}