{
  "type": "Feature",
  "properties": {
    "gn:admin1_code":"7.0",
    "gn:asciiname":"Artil'ne",
    "gn:country_code":"UA",
    "gn:dem":113,
    "gn:feature_class":"P",
    "gn:feature_code":"PPL",
    "gn:name":"Artil\u2019ne",
    "gn:population":0,
    "gn:timezone":"Europe/Kiev",
    "iso:country":"UA",
    "name:rus_x_preferred":[
        "Artel\u2019noye"
    ],
    "name:ukr_x_preferred":[
        "Artil\u2019ne"
    ],
    "name:ukr_x_variant":[
        "\u0410\u0440\u0442\u0456\u043b\u044c\u043d\u0435"
    ],
    "wof:name":"Artil'ne",
    "wof:placetype":"locality"
},
  "geometry": {"coordinates":[36.15886,49.05905],"type":"Point"}
}