{
  "type": "Feature",
  "properties": {
    "gn:admin1_code":"10.0",
    "gn:asciiname":"Bobrinka",
    "gn:country_code":"UA",
    "gn:dem":186,
    "gn:feature_class":"P",
    "gn:feature_code":"PPL",
    "gn:name":"Bobrinka",
    "gn:population":0,
    "gn:timezone":"Europe/Kiev",
    "iso:country":"UA",
    "wof:name":"Bobrinka",
    "wof:placetype":"locality"
},
  "geometry": {"coordinates":[31.98781,48.00178],"type":"Point"}
}