{
  "type": "Feature",
  "properties": {
    "iso:country":"UA",
    "name:crh_x_historical":[
        "K\u00f6p Taqyl"
    ],
    "name:crh_x_preferred":[
        "K\u00f6p Taqyl"
    ],
    "name:eng_x_preferred":[
        "Zavetnoye"
    ],
    "name:rus_x_historical":[
        "\u042f\u043d\u044b\u0301\u0448-\u0422\u0430\u043a\u0438\u0301\u043b"
    ],
    "name:rus_x_preferred":[
        "\u0417\u0430\u0432\u0435\u0442\u043d\u043e\u0435"
    ],
    "name:rus_x_variant":[
        "\u042f\u043d\u044b\u0301\u0448-\u0422\u0430\u043a\u0438\u0301\u043b"
    ],
    "name:ukr_x_preferred":[
        "\u0417\u0430\u0432\u0456\u0442\u043d\u0435"
    ],
    "qs:a0":"\u0423\u043a\u0440\u0430\u0457\u043d\u0430",
    "qs:a1":"*\u041a\u0440\u0438\u043c",
    "qs:a1_alt":"Krym",
    "qs:a1r":"0",
    "qs:a2":"\u041b\u0435\u043d\u0456\u043d\u0441\u044c\u043a\u0438\u0439",
    "qs:a2_alt":"Lenins'kyi",
    "qs:adm0":"\u0423\u043a\u0440\u0430\u0457\u043d\u0430",
    "qs:la_lc":"*",
    "qs:level":"locality",
    "qs:loc":"\u0417\u0430\u0432\u0456\u0442\u043d\u0435",
    "qs:loc_alt":"Zavitne",
    "qs:pop":0,
    "qs:type":"buffered point",
    "wof:name":"\u0417\u0430\u0432\u0456\u0442\u043d\u0435",
    "wof:placetype":"locality"
},
  "geometry": {"coordinates":[36.398525,45.121091],"type":"Point"}
}