{
  "type": "Feature",
  "properties": {
    "gn:admin1_code":"22.0",
    "gn:asciiname":"Krasnov",
    "gn:country_code":"UA",
    "gn:dem":366,
    "gn:feature_class":"P",
    "gn:feature_code":"PPL",
    "gn:name":"Krasnov",
    "gn:population":0,
    "gn:timezone":"Europe/Kiev",
    "iso:country":"UA",
    "name:chv_x_preferred":[
        "\u041a\u0440\u0430\u0441\u043d\u043e\u0432"
    ],
    "name:deu_x_preferred":[
        "Krasnow"
    ],
    "name:fra_x_preferred":[
        "Krasnov"
    ],
    "name:rus_x_preferred":[
        "\u041a\u0440\u0430\u0441\u043d\u043e\u0432"
    ],
    "name:slv_x_preferred":[
        "Krasnov"
    ],
    "name:ukr_x_preferred":[
        "\u041a\u0440\u0430\u0441\u043d\u043e\u0432"
    ],
    "name:und_x_variant":[
        "Krasne",
        "Krasnoye",
        "Krasnov"
    ],
    "wof:name":"Krasnov",
    "wof:placetype":"locality"
},
  "geometry": {"coordinates":[26.16473,49.3025],"type":"Point"}
}