{
  "type": "Feature",
  "properties": {
    "gn:admin1_code":"21.0",
    "gn:asciiname":"Lyse",
    "gn:country_code":"UA",
    "gn:dem":124,
    "gn:feature_class":"P",
    "gn:feature_code":"PPL",
    "gn:name":"Lyse",
    "gn:population":0,
    "gn:timezone":"Europe/Kiev",
    "iso:country":"UA",
    "name:ceb_x_preferred":[
        "Lyse"
    ],
    "name:deu_x_preferred":[
        "Lyse"
    ],
    "name:fra_x_preferred":[
        "Lyse"
    ],
    "name:nno_x_preferred":[
        "Lyse"
    ],
    "name:nor_x_preferred":[
        "Lyse"
    ],
    "name:ukr_x_preferred":[
        "Lyse"
    ],
    "name:ukr_x_variant":[
        "\u041b\u0438\u0441\u0435"
    ],
    "wof:name":"Lyse",
    "wof:placetype":"locality"
},
  "geometry": {"coordinates":[34.79093,50.40358],"type":"Point"}
}