{
  "type": "Feature",
  "properties": {
    "gn:admin1_code":"7.0",
    "gn:asciiname":"Dmytrivka",
    "gn:country_code":"UA",
    "gn:dem":177,
    "gn:feature_class":"P",
    "gn:feature_code":"PPL",
    "gn:name":"Dmytrivka",
    "gn:population":0,
    "gn:timezone":"Europe/Kiev",
    "iso:country":"UA",
    "name:ukr_x_preferred":[
        "Dmytrivka"
    ],
    "name:ukr_x_variant":[
        "\u0414\u043c\u0438\u0442\u0440\u0456\u0432\u043a\u0430"
    ],
    "wof:name":"Dmytrivka",
    "wof:placetype":"locality"
},
  "geometry": {"coordinates":[35.38589,49.79882],"type":"Point"}
}