{
  "type": "Feature",
  "properties": {
    "gn:admin1_code":"2.0",
    "gn:asciiname":"Radomka",
    "gn:country_code":"UA",
    "gn:dem":174,
    "gn:feature_class":"P",
    "gn:feature_code":"PPL",
    "gn:name":"Radomka",
    "gn:population":0,
    "gn:timezone":"Europe/Kiev",
    "iso:country":"UA",
    "name:eng_x_preferred":[
        "Radomka"
    ],
    "name:rus_x_preferred":[
        "\u0420\u0430\u0434\u043e\u043c\u043a\u0430"
    ],
    "name:ukr_x_preferred":[
        "\u0420\u0430\u0434\u043e\u043c\u043a\u0430"
    ],
    "wof:name":"Radomka",
    "wof:placetype":"locality"
},
  "geometry": {"coordinates":[32.56225999999999,51.93645],"type":"Point"}
}