{
  "type": "Feature",
  "properties": {
    "gn:admin1_code":"4.0",
    "gn:asciiname":"Andriyivka",
    "gn:country_code":"UA",
    "gn:dem":110,
    "gn:feature_class":"P",
    "gn:feature_code":"PPL",
    "gn:name":"Andriyivka",
    "gn:population":0,
    "gn:timezone":"Europe/Kiev",
    "iso:country":"UA",
    "name:aze_x_preferred":[
        "Andreevka"
    ],
    "name:bel_x_preferred":[
        "\u0410\u043d\u0434\u0440\u044d\u0435\u045e\u043a\u0430"
    ],
    "name:ceb_x_preferred":[
        "\u0410\u043d\u0434\u0440\u0435\u0435\u0432\u043a\u0430"
    ],
    "name:deu_x_preferred":[
        "Andrijiwka"
    ],
    "name:est_x_preferred":[
        "Andrejevka"
    ],
    "name:hye_x_preferred":[
        "\u0531\u0576\u0564\u0580\u0565\u0587\u056f\u0561"
    ],
    "name:ita_x_preferred":[
        "Andreevka"
    ],
    "name:kat_x_preferred":[
        "\u10d0\u10dc\u10d3\u10e0\u10d4\u10d4\u10d5\u10d9\u10d0"
    ],
    "name:kaz_x_preferred":[
        "\u0410\u043d\u0434\u0440\u0435\u0435\u0432\u043a\u0430"
    ],
    "name:ron_x_preferred":[
        "Andreevca"
    ],
    "name:rus_x_preferred":[
        "\u0410\u043d\u0434\u0440\u0435\u0435\u0432\u043a\u0430"
    ],
    "name:ukr_x_preferred":[
        "Andriyivka"
    ],
    "name:ukr_x_variant":[
        "\u0410\u043d\u0434\u0440\u0456\u0457\u0432\u043a\u0430"
    ],
    "name:und_x_variant":[
        "Andryeyevka"
    ],
    "wof:name":"Andriyivka",
    "wof:placetype":"locality"
},
  "geometry": {"coordinates":[33.90547,48.25781],"type":"Point"}
}