{
  "type": "Feature",
  "properties": {
    "gn:admin1_code":"19.0",
    "gn:asciiname":"Vyshneve",
    "gn:country_code":"UA",
    "gn:dem":205,
    "gn:feature_class":"P",
    "gn:feature_code":"PPL",
    "gn:name":"Vyshneve",
    "gn:population":0,
    "gn:timezone":"Europe/Kiev",
    "iso:country":"UA",
    "name:ara_x_preferred":[
        "\u0641\u064a\u0634\u0646\u064a\u0641\u064a"
    ],
    "name:azb_x_preferred":[
        "\u0648\u06cc\u0634\u0646\u0641"
    ],
    "name:bel_x_preferred":[
        "\u0412\u044b\u0448\u043d\u044d\u0432\u044d"
    ],
    "name:ceb_x_preferred":[
        "Vyshneve"
    ],
    "name:ces_x_preferred":[
        "Vy\u0161neve"
    ],
    "name:crh_x_preferred":[
        "V\u0131\u015fneve"
    ],
    "name:deu_x_preferred":[
        "Wyschnewe"
    ],
    "name:fas_x_preferred":[
        "\u0648\u06cc\u0634\u0646\u0641"
    ],
    "name:fin_x_preferred":[
        "Vy\u0161neve"
    ],
    "name:fra_x_preferred":[
        "Vychneve"
    ],
    "name:hsb_x_preferred":[
        "Wy\u0161newe"
    ],
    "name:hye_x_preferred":[
        "\u054e\u056b\u0577\u0576\u0575\u0578\u057e\u0578\u0565"
    ],
    "name:ita_x_preferred":[
        "Vy\u0161neve"
    ],
    "name:kat_x_preferred":[
        "\u10d5\u10d8\u10e8\u10dc\u10d4\u10d5\u10dd\u10d4"
    ],
    "name:lit_x_preferred":[
        "Vy\u0161nev\u0117"
    ],
    "name:nno_x_preferred":[
        "Vysjneve"
    ],
    "name:pol_x_preferred":[
        "Wysznewe"
    ],
    "name:ron_x_preferred":[
        "V\u00ee\u0219neve"
    ],
    "name:rus_x_preferred":[
        "\u0412\u0438\u0448\u043d\u0451\u0432\u043e\u0435"
    ],
    "name:sah_x_preferred":[
        "\u0412\u0438\u0448\u043d\u0451\u0432\u043e\u0435"
    ],
    "name:srp_x_preferred":[
        "\u0412\u0438\u0448\u043d\u0435\u0432\u0435"
    ],
    "name:swe_x_preferred":[
        "Vysjneve"
    ],
    "name:ukr_x_preferred":[
        "Vyshneve"
    ],
    "name:ukr_x_variant":[
        "\u0412\u0438\u0448\u043d\u0435\u0432\u0435"
    ],
    "name:und_x_variant":[
        "Vishnevoye"
    ],
    "name:vie_x_preferred":[
        "Vyshneve"
    ],
    "name:zho_x_preferred":[
        "\u7dad\u4ec0\u6d85\u97cb"
    ],
    "wof:name":"Vyshneve",
    "wof:placetype":"locality"
},
  "geometry": {"coordinates":[25.34471,50.45419],"type":"Point"}
}