{
  "type": "Feature",
  "properties": {
    "gn:admin1_code":"21.0",
    "gn:asciiname":"Pyharivka",
    "gn:country_code":"UA",
    "gn:dem":172,
    "gn:feature_class":"P",
    "gn:feature_code":"PPL",
    "gn:name":"Pyharivka",
    "gn:population":0,
    "gn:timezone":"Europe/Kiev",
    "iso:country":"UA",
    "name:eng_x_preferred":[
        "Pyharivka"
    ],
    "name:rus_x_preferred":[
        "\u041f\u0438\u0433\u0430\u0440\u0435\u0432\u043a\u0430"
    ],
    "name:ukr_x_preferred":[
        "\u041f\u0438\u0433\u0430\u0440\u0456\u0432\u043a\u0430"
    ],
    "name:ukr_x_variant":[
        "Pisarevka",
        "Pigar\u00ebvka"
    ],
    "wof:name":"Pyharivka",
    "wof:placetype":"locality"
},
  "geometry": {"coordinates":[33.83213,52.14174000000001],"type":"Point"}
}