{
  "type": "Feature",
  "properties": {
    "gn:admin1_code":"15.0",
    "gn:asciiname":"Pidhorodtsi",
    "gn:country_code":"UA",
    "gn:dem":435,
    "gn:feature_class":"P",
    "gn:feature_code":"PPL",
    "gn:name":"Pidhorodtsi",
    "gn:population":0,
    "gn:timezone":"Europe/Kiev",
    "iso:country":"UA",
    "name:rus_x_preferred":[
        "\u041f\u043e\u0434\u0433\u043e\u0440\u043e\u0434\u0446\u044b"
    ],
    "name:ukr_x_preferred":[
        "Pidhorodtsi"
    ],
    "name:ukr_x_variant":[
        "\u041f\u0456\u0434\u0433\u043e\u0440\u043e\u0434\u0446\u0456"
    ],
    "name:und_x_variant":[
        "Podhorodce",
        "Podgorodtse",
        "Podgorodtsy"
    ],
    "wof:name":"Pidhorodtsi",
    "wof:placetype":"locality"
},
  "geometry": {"coordinates":[23.42235,49.15375],"type":"Point"}
}