{
  "type": "Feature",
  "properties": {
    "gn:admin1_code":"9.0",
    "gn:asciiname":"Kystivtsi",
    "gn:country_code":"UA",
    "gn:dem":268,
    "gn:feature_class":"P",
    "gn:feature_code":"PPL",
    "gn:name":"Kystivtsi",
    "gn:population":0,
    "gn:timezone":"Europe/Kiev",
    "iso:country":"UA",
    "name:ukr_x_preferred":[
        "Kystivtsi"
    ],
    "name:ukr_x_variant":[
        "\u041a\u0443\u0441\u0442\u0456\u0432\u0446\u0456"
    ],
    "name:und_x_variant":[
        "Kustovtsy"
    ],
    "wof:name":"Kystivtsi",
    "wof:placetype":"locality"
},
  "geometry": {"coordinates":[27.40586,49.92458],"type":"Point"}
}