{
  "type": "Feature",
  "properties": {
    "gn:admin1_code":"15.0",
    "gn:asciiname":"Shesherovichi",
    "gn:country_code":"UA",
    "gn:dem":254,
    "gn:feature_class":"P",
    "gn:feature_code":"PPL",
    "gn:name":"Shesherovichi",
    "gn:population":0,
    "gn:timezone":"Europe/Kiev",
    "iso:country":"UA",
    "name:und_x_variant":[
        "Shesherovitse",
        "Shesherovichi"
    ],
    "wof:name":"Shesherovichi",
    "wof:placetype":"locality"
},
  "geometry": {"coordinates":[23.33469,49.71243],"type":"Point"}
}