{
  "type": "Feature",
  "properties": {
    "gn:admin1_code":"19.0",
    "gn:asciiname":"Velyki Sady",
    "gn:country_code":"UA",
    "gn:dem":228,
    "gn:feature_class":"P",
    "gn:feature_code":"PPL",
    "gn:name":"Velyki Sady",
    "gn:population":0,
    "gn:timezone":"Europe/Kiev",
    "iso:country":"UA",
    "name:ukr_x_preferred":[
        "Velyki Sady"
    ],
    "name:ukr_x_variant":[
        "\u0412\u0435\u043b\u0438\u043a\u0456 \u0421\u0430\u0434\u0438"
    ],
    "name:und_x_variant":[
        "Sady Vel\u2019ke",
        "Velikiye Sady"
    ],
    "wof:name":"Velyki Sady",
    "wof:placetype":"locality"
},
  "geometry": {"coordinates":[25.59844,50.39125],"type":"Point"}
}