{
  "type": "Feature",
  "properties": {
    "gn:admin1_code":"11.0",
    "gn:admin2_code":"697572",
    "gn:admin3_code":"11152995",
    "gn:asciiname":"Vypasnoye",
    "gn:country_code":"UA",
    "gn:dem":60,
    "gn:elevation":"60.0",
    "gn:feature_class":"P",
    "gn:feature_code":"PPL",
    "gn:name":"Vypasnoye",
    "gn:population":119,
    "gn:timezone":"Europe/Simferopol",
    "iso:country":"UA",
    "name:eng_x_preferred":[
        "Vypasnoye"
    ],
    "name:rus_x_historical":[
        "\u042f\u043f\u0443\u043d\u0434\u0436\u0430\u0301"
    ],
    "name:rus_x_preferred":[
        "\u0412\u044b\u043f\u0430\u0441\u043d\u043e\u0435"
    ],
    "name:rus_x_variant":[
        "\u042f\u043f\u0443\u043d\u0434\u0436\u0430\u0301"
    ],
    "name:ukr_x_preferred":[
        "\u0412\u0438\u043f\u0430\u0441\u043d\u0435"
    ],
    "wof:name":"Vypasnoye",
    "wof:placetype":"locality",
    "wof:population":119
},
  "geometry": {"coordinates":[33.90318,45.62274],"type":"Point"}
}