{
  "type": "Feature",
  "properties": {
    "gn:admin1_code":"4.0",
    "gn:asciiname":"Alferovo",
    "gn:country_code":"UA",
    "gn:dem":123,
    "gn:feature_class":"P",
    "gn:feature_code":"PPL",
    "gn:name":"Alf\u00ebrovo",
    "gn:population":0,
    "gn:timezone":"Europe/Kiev",
    "iso:country":"UA",
    "wof:name":"Alferovo",
    "wof:placetype":"locality"
},
  "geometry": {"coordinates":[33.96667,48.38333],"type":"Point"}
}