{
  "type": "Feature",
  "properties": {
    "gn:admin1_code":"7.0",
    "gn:asciiname":"Klyuchevods'ke",
    "gn:country_code":"UA",
    "gn:dem":159,
    "gn:feature_class":"P",
    "gn:feature_code":"PPL",
    "gn:name":"Klyuchevods\u2019ke",
    "gn:population":0,
    "gn:timezone":"Europe/Kiev",
    "iso:country":"UA",
    "name:ukr_x_preferred":[
        "Klyuchevods\u2019ke"
    ],
    "name:ukr_x_variant":[
        "\u041a\u043b\u044e\u0447\u0435\u0432\u043e\u0434\u0441\u044c\u043a\u0435"
    ],
    "name:und_x_variant":[
        "Klyuchevonsk"
    ],
    "wof:name":"Klyuchevods'ke",
    "wof:placetype":"locality"
},
  "geometry": {"coordinates":[36.00048,49.67721],"type":"Point"}
}