{
  "type": "Feature",
  "properties": {
    "gn:admin1_code":"21.0",
    "gn:asciiname":"Filonove",
    "gn:country_code":"UA",
    "gn:dem":130,
    "gn:feature_class":"P",
    "gn:feature_code":"PPL",
    "gn:name":"Filonove",
    "gn:population":0,
    "gn:timezone":"Europe/Kiev",
    "iso:country":"UA",
    "name:ukr_x_preferred":[
        "Filonove"
    ],
    "name:ukr_x_variant":[
        "\u0424\u0456\u043b\u043e\u043d\u043e\u0432\u0435"
    ],
    "name:und_x_variant":[
        "Filonov",
        "Filonovo"
    ],
    "wof:name":"Filonove",
    "wof:placetype":"locality"
},
  "geometry": {"coordinates":[34.06003,50.8438],"type":"Point"}
}