{
  "type": "Feature",
  "properties": {
    "gn:population":2724,
    "iso:country":"UA",
    "name:bel_x_preferred":[
        "\u041d\u043e\u0432\u0430\u0432\u0430\u0441\u044b\u043b\u0456\u045e\u043a\u0430"
    ],
    "name:bul_x_preferred":[
        "\u041d\u043e\u0432\u043e\u0432\u0430\u0441\u0438\u043b\u0438\u0432\u043a\u0430"
    ],
    "name:ceb_x_preferred":[
        "Novovasylivka"
    ],
    "name:ces_x_preferred":[
        "Novovasylivka"
    ],
    "name:che_x_preferred":[
        "\u041d\u043e\u0432\u043e\u0432\u0430\u0441\u0438\u043b\u0435\u0432\u043a\u0430"
    ],
    "name:crh_x_preferred":[
        "Novovas\u0131livka"
    ],
    "name:deu_x_preferred":[
        "Nowowassyliwka"
    ],
    "name:eng_x_preferred":[
        "Novovasylivka"
    ],
    "name:fra_x_preferred":[
        "Novovassylivka"
    ],
    "name:hye_x_preferred":[
        "\u0546\u0578\u057e\u0578\u057e\u0561\u057d\u056b\u056c\u0587\u056f\u0561"
    ],
    "name:lav_x_preferred":[
        "Novovasi\u013civka"
    ],
    "name:pol_x_preferred":[
        "Nowowasyliwka"
    ],
    "name:ron_x_preferred":[
        "Novovas\u00eelivka"
    ],
    "name:rus_x_preferred":[
        "\u041d\u043e\u0432\u043e\u0432\u0430\u0441\u0438\u043b\u0456\u0432\u043a\u0430"
    ],
    "name:rus_x_variant":[
        "\u041d\u043e\u0432\u043e\u0432\u0430\u0441\u0438\u043b\u0435\u0432\u043a\u0430"
    ],
    "name:spa_x_preferred":[
        "Novovasilivka"
    ],
    "name:swe_x_preferred":[
        "Novovasylivka"
    ],
    "name:ukr_x_preferred":[
        "\u041d\u043e\u0432\u043e\u0432\u0430\u0441\u0438\u043b\u0456\u0432\u043a\u0430"
    ],
    "name:und_x_variant":[
        "Novovasilevka"
    ],
    "name:uzb_x_preferred":[
        "Novovasylivka"
    ],
    "name:zho_x_preferred":[
        "\u8afe\u6c83\u74e6\u897f\u5229\u592b\u5361"
    ],
    "name:zho_x_variant":[
        "\u65b0\u74e6\u897f\u5229\u592b\u5361"
    ],
    "qs:a0":"\u0423\u043a\u0440\u0430\u0457\u043d\u0430",
    "qs:a1":"*\u0417\u0430\u043f\u043e\u0440\u0456\u0437\u044c\u043a\u0430",
    "qs:a1_alt":"Zaporiz'ka",
    "qs:a1r":"0",
    "qs:a2":"\u041f\u0440\u0438\u0430\u0437\u043e\u0432\u0441\u044c\u043a\u0438\u0439",
    "qs:a2_alt":"Pryazovs'kyi",
    "qs:adm0":"\u0423\u043a\u0440\u0430\u0457\u043d\u0430",
    "qs:la_lc":"*",
    "qs:level":"locality",
    "qs:loc":"\u041d\u043e\u0432\u043e\u0432\u0430\u0441\u0438\u043b\u0456\u0432\u043a\u0430",
    "qs:loc_alt":"Novovasylivka",
    "qs:pop":0,
    "qs:type":"buffered point",
    "wof:name":"\u041d\u043e\u0432\u043e\u0432\u0430\u0441\u0438\u043b\u0456\u0432\u043a\u0430",
    "wof:placetype":"locality",
    "wof:population":2724
},
  "geometry": {"coordinates":[35.754072,46.834016],"type":"Point"}
}