{
  "type": "Feature",
  "properties": {
    "gn:admin1_code":"14.0",
    "gn:asciiname":"Oleksiyivka",
    "gn:country_code":"UA",
    "gn:dem":177,
    "gn:feature_class":"P",
    "gn:feature_code":"PPL",
    "gn:name":"Oleksiyivka",
    "gn:population":0,
    "gn:timezone":"Europe/Zaporozhye",
    "iso:country":"UA",
    "name:ukr_x_preferred":[
        "Oleksiyivka"
    ],
    "name:und_x_variant":[
        "\u041e\u043b\u0435\u043a\u0441\u0456\u0457\u0432\u043a\u0430"
    ],
    "wof:name":"Oleksiyivka",
    "wof:placetype":"locality"
},
  "geometry": {"coordinates":[40.05521,49.44302],"type":"Point"}
}