{
  "type": "Feature",
  "properties": {
    "gn:admin1_code":"4.0",
    "gn:asciiname":"Druzhba",
    "gn:country_code":"UA",
    "gn:dem":89,
    "gn:feature_class":"P",
    "gn:feature_code":"PPL",
    "gn:name":"Druzhba",
    "gn:population":0,
    "gn:timezone":"Europe/Kiev",
    "iso:country":"UA",
    "name:bel_x_preferred":[
        "\u0414\u0440\u0443\u0436\u0431\u0430"
    ],
    "name:bul_x_preferred":[
        "\u0414\u0440\u0443\u0436\u0431\u0430"
    ],
    "name:ceb_x_preferred":[
        "Druzhba"
    ],
    "name:ces_x_preferred":[
        "Dru\u017eba"
    ],
    "name:deu_x_preferred":[
        "Druschba"
    ],
    "name:est_x_preferred":[
        "Dru\u017eba"
    ],
    "name:fra_x_preferred":[
        "Droujba"
    ],
    "name:hye_x_preferred":[
        "\u0534\u0580\u0578\u0582\u056a\u0562\u0561"
    ],
    "name:ita_x_preferred":[
        "Druzhba"
    ],
    "name:kaz_x_preferred":[
        "\u0414\u0440\u0443\u0436\u0431\u0430"
    ],
    "name:rus_x_preferred":[
        "\u0414\u0440\u0443\u0436\u0431\u0430"
    ],
    "name:slk_x_preferred":[
        "Dru\u017eba"
    ],
    "name:spa_x_preferred":[
        "Druzhba"
    ],
    "name:swe_x_preferred":[
        "Druzhba"
    ],
    "name:tat_x_preferred":[
        "\u0414\u0440\u0443\u0436\u0431\u0430"
    ],
    "name:ukr_x_preferred":[
        "Druzhba"
    ],
    "name:ukr_x_variant":[
        "\u0414\u0440\u0443\u0436\u0431\u0430"
    ],
    "name:zho_x_preferred":[
        "\u5fb7\u9b6f\u65e5\u5df4"
    ],
    "wof:name":"Druzhba",
    "wof:placetype":"locality"
},
  "geometry": {"coordinates":[33.18645,47.9703],"type":"Point"}
}