{
  "type": "Feature",
  "properties": {
    "gn:admin1_code":"1.0",
    "gn:asciiname":"Orli",
    "gn:country_code":"UA",
    "gn:dem":207,
    "gn:feature_class":"P",
    "gn:feature_code":"PPL",
    "gn:name":"Orli",
    "gn:population":0,
    "gn:timezone":"Europe/Kiev",
    "iso:country":"UA",
    "name:rus_x_preferred":[
        "\u041e\u0440\u043b\u044b"
    ],
    "wof:name":"Orli",
    "wof:placetype":"locality"
},
  "geometry": {"coordinates":[30.84901,49.22659],"type":"Point"}
}