{
  "type": "Feature",
  "properties": {
    "gn:admin1_code":"14.0",
    "gn:asciiname":"Priyut",
    "gn:country_code":"UA",
    "gn:dem":79,
    "gn:feature_class":"P",
    "gn:feature_code":"PPL",
    "gn:name":"Priyut",
    "gn:population":0,
    "gn:timezone":"Europe/Zaporozhye",
    "iso:country":"UA",
    "wof:name":"Priyut",
    "wof:placetype":"locality"
},
  "geometry": {"coordinates":[38.95333,49.79472],"type":"Point"}
}