{
  "type": "Feature",
  "properties": {
    "gn:admin1_code":"18.0",
    "gn:asciiname":"Buryakivshchyna",
    "gn:country_code":"UA",
    "gn:dem":102,
    "gn:feature_class":"P",
    "gn:feature_code":"PPL",
    "gn:name":"Buryakivshchyna",
    "gn:population":0,
    "gn:timezone":"Europe/Kiev",
    "iso:country":"UA",
    "name:ukr_x_preferred":[
        "Buryakivshchyna"
    ],
    "name:ukr_x_variant":[
        "\u0411\u0443\u0440\u044f\u043a\u0456\u0432\u0449\u0438\u043d\u0430"
    ],
    "wof:name":"Buryakivshchyna",
    "wof:placetype":"locality"
},
  "geometry": {"coordinates":[33.70755,49.83305],"type":"Point"}
}