{
  "type": "Feature",
  "properties": {
    "gn:admin1_code":"1.0",
    "gn:asciiname":"Ashanivka",
    "gn:country_code":"UA",
    "gn:dem":113,
    "gn:feature_class":"P",
    "gn:feature_code":"PPL",
    "gn:name":"Ashanivka",
    "gn:population":0,
    "gn:timezone":"Europe/Kiev",
    "iso:country":"UA",
    "name:ukr_x_preferred":[
        "Ashanivka"
    ],
    "name:ukr_x_variant":[
        "\u0410\u0448\u0430\u043d\u0456\u0432\u043a\u0430"
    ],
    "wof:name":"Ashanivka",
    "wof:placetype":"locality"
},
  "geometry": {"coordinates":[32.06734,49.81096],"type":"Point"}
}