{
  "type": "Feature",
  "properties": {
    "gn:admin1_code":"7.0",
    "gn:asciiname":"Manyly",
    "gn:country_code":"UA",
    "gn:dem":179,
    "gn:feature_class":"P",
    "gn:feature_code":"PPL",
    "gn:name":"Manyly",
    "gn:population":0,
    "gn:timezone":"Europe/Kiev",
    "iso:country":"UA",
    "name:ukr_x_preferred":[
        "Manyly"
    ],
    "name:ukr_x_variant":[
        "\u041c\u0430\u043d\u0438\u043b\u0438"
    ],
    "name:und_x_variant":[
        "Khutor Prusovka",
        "Prusovka",
        "Prusov"
    ],
    "wof:name":"Manyly",
    "wof:placetype":"locality"
},
  "geometry": {"coordinates":[35.66979,49.73418],"type":"Point"}
}