{
  "type": "Feature",
  "properties": {
    "gn:admin1_code":"15.0",
    "gn:asciiname":"Voloshinovo",
    "gn:country_code":"UA",
    "gn:dem":517,
    "gn:feature_class":"P",
    "gn:feature_code":"PPL",
    "gn:name":"Voloshinovo",
    "gn:population":0,
    "gn:timezone":"Europe/Kiev",
    "iso:country":"UA",
    "name:ukr_x_preferred":[
        "\u0412\u043e\u043b\u043e\u0448\u0438\u043d\u043e\u0432\u043e"
    ],
    "name:und_x_variant":[
        "Voloshinova",
        "Voloshinovo"
    ],
    "wof:name":"Voloshinovo",
    "wof:placetype":"locality"
},
  "geometry": {"coordinates":[22.83107,49.42256],"type":"Point"}
}