{
  "type": "Feature",
  "properties": {
    "gn:admin1_code":"14.0",
    "gn:asciiname":"Novooleksandrivka",
    "gn:country_code":"UA",
    "gn:dem":147,
    "gn:feature_class":"P",
    "gn:feature_code":"PPL",
    "gn:name":"Novooleksandrivka",
    "gn:population":0,
    "gn:timezone":"Europe/Zaporozhye",
    "iso:country":"UA",
    "name:hye_x_preferred":[
        "\u0546\u0578\u057e\u0578\u0561\u056c\u0565\u056f\u057d\u0561\u0576\u0564\u0580\u0578\u057e\u056f\u0561"
    ],
    "name:rus_x_preferred":[
        "\u041d\u043e\u0432\u043e\u0430\u043b\u0435\u043a\u0441\u0430\u043d\u0434\u0440\u043e\u0432\u043a\u0430"
    ],
    "name:ukr_x_preferred":[
        "Novooleksandrivka"
    ],
    "name:ukr_x_variant":[
        "\u041d\u043e\u0432\u043e\u043e\u043b\u0435\u043a\u0441\u0430\u043d\u0434\u0440\u0456\u0432\u043a\u0430"
    ],
    "name:und_x_variant":[
        "Novoaleksandrovka"
    ],
    "wof:name":"Novooleksandrivka",
    "wof:placetype":"locality"
},
  "geometry": {"coordinates":[38.13828,49.78677],"type":"Point"}
}