{
  "type": "Feature",
  "properties": {
    "gn:gn_country":"UA",
    "gn:gn_fcode":"PPLX",
    "gn:gn_pop":20000,
    "gn:population":18649,
    "iso:country":"UA",
    "name:ara_x_preferred":[
        "\u0628\u0627\u0644\u0627\u0643\u0644\u0627\u0641\u0627"
    ],
    "name:aze_x_preferred":[
        "Balaklava"
    ],
    "name:bel_x_preferred":[
        "\u0411\u0430\u043b\u0430\u043a\u043b\u0430\u0432\u0430"
    ],
    "name:bul_x_preferred":[
        "\u0411\u0430\u043b\u0430\u043a\u043b\u0430\u0432\u0430"
    ],
    "name:cat_x_preferred":[
        "Balaklava"
    ],
    "name:ces_x_preferred":[
        "Balaklava"
    ],
    "name:crh_x_historical":[
        "Balyglava"
    ],
    "name:crh_x_preferred":[
        "Bal\u0131qlava"
    ],
    "name:crh_x_variant":[
        "Balyglava"
    ],
    "name:deu_x_preferred":[
        "Balaklawa"
    ],
    "name:eng_x_preferred":[
        "Balaklava"
    ],
    "name:epo_x_preferred":[
        "Balaklavo"
    ],
    "name:fin_x_preferred":[
        "Balaklava"
    ],
    "name:fra_x_preferred":[
        "Balaclava"
    ],
    "name:fra_x_variant":[
        "Balaklava"
    ],
    "name:gsw_x_preferred":[
        "Balaklawa"
    ],
    "name:hye_x_preferred":[
        "\u0532\u0561\u056c\u0561\u056f\u056c\u0561\u057e\u0561"
    ],
    "name:ind_x_preferred":[
        "Balaklava"
    ],
    "name:ita_x_preferred":[
        "Balaklava"
    ],
    "name:jpn_x_preferred":[
        "\u30d0\u30e9\u30af\u30e9\u30f4\u30a1"
    ],
    "name:kor_x_preferred":[
        "\ubc1c\ub77c\ud074\ub77c\ubc14"
    ],
    "name:lat_x_preferred":[
        "Balaclava"
    ],
    "name:lit_x_preferred":[
        "Balaklava"
    ],
    "name:nld_x_preferred":[
        "Balaklava"
    ],
    "name:nob_x_preferred":[
        "Balaklava"
    ],
    "name:nor_x_preferred":[
        "Balaklava"
    ],
    "name:pol_x_preferred":[
        "Ba\u0142ak\u0142awa"
    ],
    "name:por_x_preferred":[
        "Balaclava"
    ],
    "name:ron_x_preferred":[
        "Balaklava"
    ],
    "name:rus_x_preferred":[
        "\u0411\u0430\u043b\u0430\u043a\u043b\u0430\u0432\u0430"
    ],
    "name:slv_x_preferred":[
        "Balaklava"
    ],
    "name:spa_x_preferred":[
        "Balaklava"
    ],
    "name:srp_x_preferred":[
        "\u0411\u0430\u043b\u0430\u043a\u043b\u0430\u0432\u0430"
    ],
    "name:swe_x_preferred":[
        "Balaklava"
    ],
    "name:tur_x_preferred":[
        "Bal\u0131klava"
    ],
    "name:ukr_x_preferred":[
        "\u0411\u0430\u043b\u0430\u043a\u043b\u0430\u0432\u0430"
    ],
    "qs_pg:aaroncc":"UA",
    "qs_pg:gn_country":"UA",
    "qs_pg:gn_fcode":"PPLX",
    "qs_pg:gn_pop":20000,
    "qs_pg:name":"Balaklava",
    "qs_pg:photos_9r":0,
    "qs_pg:photos_sr":0,
    "qs_pg:pop_sr":6,
    "qs_pg:qs_pg_placetype":"neighbourhood",
    "wof:name":"Balaklava",
    "wof:placetype":"neighbourhood",
    "wof:population":18649
},
  "geometry": {"coordinates":[33.60013,44.51428],"type":"Point"}
}