{
  "type": "Feature",
  "properties": {
    "gn:admin1_code":"21.0",
    "gn:asciiname":"Zozulyne",
    "gn:country_code":"UA",
    "gn:dem":169,
    "gn:feature_class":"P",
    "gn:feature_code":"PPL",
    "gn:name":"Zozulyne",
    "gn:population":0,
    "gn:timezone":"Europe/Kiev",
    "iso:country":"UA",
    "name:ukr_x_preferred":[
        "Zozulyne"
    ],
    "name:ukr_x_variant":[
        "\u0417\u043e\u0437\u0443\u043b\u0438\u043d\u0435"
    ],
    "name:und_x_variant":[
        "Zezyulin",
        "Zozulino"
    ],
    "wof:name":"Zozulyne",
    "wof:placetype":"locality"
},
  "geometry": {"coordinates":[33.7877,51.3704],"type":"Point"}
}