{
  "type": "Feature",
  "properties": {
    "iso:country":"UA",
    "name:eng_x_preferred":[
        "Dusino"
    ],
    "name:epo_x_preferred":[
        "Dusino"
    ],
    "name:hun_x_preferred":[
        "Zajg\u00f3"
    ],
    "name:hye_x_preferred":[
        "\u0534\u0578\u0582\u057d\u056b\u0576\u0578"
    ],
    "name:nld_x_preferred":[
        "Zajg\u00f3"
    ],
    "name:ron_x_preferred":[
        "Dus\u00eeno"
    ],
    "name:rue_x_preferred":[
        "\u0414\u0443\u0441\u0438\u043d\u043e"
    ],
    "name:rus_x_preferred":[
        "\u0414\u0443\u0441\u0438\u043d\u043e"
    ],
    "name:ukr_x_preferred":[
        "\u0414\u0443\u0441\u0438\u043d\u0430"
    ],
    "name:ukr_x_variant":[
        "\u0414\u0443\u0441\u0438\u043d\u043e"
    ],
    "name:unk_x_variant":[
        "Dusyna"
    ],
    "qs:a0":"\u0423\u043a\u0440\u0430\u0457\u043d\u0430",
    "qs:a1":"*\u0417\u0430\u043a\u0430\u0440\u043f\u0430\u0442\u0441\u044c\u043a\u0430",
    "qs:a1_alt":"Zakarpats'ka",
    "qs:a1r":"0",
    "qs:a2":"\u0421\u0432\u0430\u043b\u044f\u0432\u0441\u044c\u043a\u0438\u0439",
    "qs:a2_alt":"Svaliavs'kyi",
    "qs:adm0":"\u0423\u043a\u0440\u0430\u0457\u043d\u0430",
    "qs:la_lc":"*",
    "qs:level":"locality",
    "qs:loc":"\u0414\u0443\u0441\u0438\u043d\u043e",
    "qs:loc_alt":"Dusyno",
    "qs:pop":0,
    "qs:type":"buffered point",
    "wof:name":"\u0414\u0443\u0441\u0438\u043d\u043e",
    "wof:placetype":"locality"
},
  "geometry": {"coordinates":[23.117203,48.510879],"type":"Point"}
}