{
  "type": "Feature",
  "properties": {
    "gn:admin1_code":"5.0",
    "gn:asciiname":"Ivanivka",
    "gn:country_code":"UA",
    "gn:dem":81,
    "gn:feature_class":"P",
    "gn:feature_code":"PPL",
    "gn:name":"Ivanivka",
    "gn:population":0,
    "gn:timezone":"Europe/Kiev",
    "iso:country":"UA",
    "name:rus_x_preferred":[
        "Bol\u2019shaya Ivanovka"
    ],
    "name:ukr_x_preferred":[
        "Ivanivka"
    ],
    "wof:name":"Ivanivka",
    "wof:placetype":"locality"
},
  "geometry": {"coordinates":[37.94667000000001,49.11417],"type":"Point"}
}