{
  "type": "Feature",
  "properties": {
    "iso:country":"UA",
    "name:eng_x_preferred":[
        "Khrestishche"
    ],
    "name:rus_x_preferred":[
        "\u0425\u0440\u0435\u0441\u0442\u0438\u0449\u0435"
    ],
    "name:ukr_x_preferred":[
        "Khrestyshche"
    ],
    "name:ukr_x_variant":[
        "\u0425\u0440\u0435\u0441\u0442\u0438\u0449\u0435"
    ],
    "name:unk_x_variant":[
        "Khristishche"
    ],
    "qs:a0":"\u0423\u043a\u0440\u0430\u0457\u043d\u0430",
    "qs:a1":"*\u0414\u043e\u043d\u0435\u0446\u044c\u043a\u0430",
    "qs:a1_alt":"Donets'ka",
    "qs:a1r":"0",
    "qs:a2":"\u0421\u043b\u043e\u0432'\u044f\u043d\u0441\u044c\u043a\u0438\u0439",
    "qs:a2_alt":"Slovyans'kyi",
    "qs:adm0":"\u0423\u043a\u0440\u0430\u0457\u043d\u0430",
    "qs:la_lc":"*",
    "qs:level":"locality",
    "qs:loc":"\u0425\u0440\u0435\u0441\u0442\u0438\u0449\u0435",
    "qs:loc_alt":"Khrestysche",
    "qs:pop":0,
    "qs:type":"buffered point",
    "wof:name":"\u0425\u0440\u0435\u0441\u0442\u0438\u0449\u0435",
    "wof:placetype":"locality"
},
  "geometry": {"coordinates":[37.489424,48.920437],"type":"Point"}
}