{
  "type": "Feature",
  "properties": {
    "gn:admin1_code":"26.0",
    "gn:admin2_code":"Chernihivka Raion (undefined)",
    "gn:asciiname":"Nyzhniy Tokmak",
    "gn:country_code":"UA",
    "gn:dem":195,
    "gn:feature_class":"P",
    "gn:feature_code":"PPL",
    "gn:name":"Nyzhniy Tokmak",
    "gn:population":0,
    "gn:timezone":"Europe/Zaporozhye",
    "iso:country":"UA",
    "name:ron_x_preferred":[
        "N\u00eejnii Tokmak"
    ],
    "name:rus_x_preferred":[
        "Nizhniy Tokmak"
    ],
    "name:rus_x_variant":[
        "\u041d\u0438\u0436\u043d\u0438\u0439 \u0422\u043e\u043a\u043c\u0430\u043a"
    ],
    "name:ukr_x_preferred":[
        "\u041d\u0438\u0436\u043d\u0456\u0439 \u0422\u043e\u043a\u043c\u0430\u043a"
    ],
    "name:ukr_x_variant":[
        "Nyzhniy Tokmak"
    ],
    "name:zho_x_preferred":[
        "\u4e0b\u6258\u514b\u99ac\u514b"
    ],
    "wof:name":"Nyzhniy Tokmak",
    "wof:placetype":"locality"
},
  "geometry": {"coordinates":[36.31389,47.19495],"type":"Point"}
}