{
  "type": "Feature",
  "properties": {
    "iso:country":"UA",
    "name:bel_x_preferred":[
        "\u0421\u043c\u043e\u043b\u044f\u043d\u043a\u0430"
    ],
    "name:che_x_preferred":[
        "\u0421\u043c\u043e\u043b\u044f\u043d\u043a\u0430"
    ],
    "name:deu_x_preferred":[
        "Smoljanka"
    ],
    "name:eng_x_preferred":[
        "Smolyanka"
    ],
    "name:eng_x_variant":[
        "Smolianka"
    ],
    "name:fin_x_preferred":[
        "Sm\u043eljank\u0430"
    ],
    "name:nan_x_preferred":[
        "Smolianka"
    ],
    "name:nno_x_preferred":[
        "Smoljanka"
    ],
    "name:nob_x_preferred":[
        "Smoljanka"
    ],
    "name:ron_x_preferred":[
        "Smoleanka"
    ],
    "name:rus_x_preferred":[
        "\u0421\u043c\u043e\u043b\u044f\u043d\u043a\u0430"
    ],
    "name:ukr_x_preferred":[
        "\u0421\u043c\u043e\u043b\u044f\u043d\u043a\u0430"
    ],
    "name:zho_x_preferred":[
        "\u65af\u83ab\u826f\u5361"
    ],
    "qs:a0":"\u0423\u043a\u0440\u0430\u0457\u043d\u0430",
    "qs:a1":"*\u0427\u0435\u0440\u043d\u0456\u0433\u0456\u0432\u0441\u044c\u043a\u0430",
    "qs:a1_alt":"Chernihivs'ka",
    "qs:a1r":"0",
    "qs:a2":"\u041a\u0443\u043b\u0438\u043a\u0456\u0432\u0441\u044c\u043a\u0438\u0439",
    "qs:a2_alt":"Kulykivs'kyi",
    "qs:adm0":"\u0423\u043a\u0440\u0430\u0457\u043d\u0430",
    "qs:la_lc":"*",
    "qs:level":"locality",
    "qs:loc":"\u0421\u043c\u043e\u043b\u044f\u043d\u043a\u0430",
    "qs:loc_alt":"Smolianka",
    "qs:pop":0,
    "qs:type":"buffered point",
    "wof:name":"\u0421\u043c\u043e\u043b\u044f\u043d\u043a\u0430",
    "wof:placetype":"locality"
},
  "geometry": {"coordinates":[31.465471,51.239186],"type":"Point"}
}