{
  "type": "Feature",
  "properties": {
    "gn:admin1_code":"14.0",
    "gn:asciiname":"Prosyane",
    "gn:country_code":"UA",
    "gn:dem":171,
    "gn:feature_class":"P",
    "gn:feature_code":"PPL",
    "gn:name":"Prosyane",
    "gn:population":0,
    "gn:timezone":"Europe/Zaporozhye",
    "iso:country":"UA",
    "name:ukr_x_preferred":[
        "Prosyane"
    ],
    "name:ukr_x_variant":[
        "\u041f\u0440\u043e\u0441\u044f\u043d\u0435"
    ],
    "name:und_x_variant":[
        "Prosyanka",
        "Prosyanaya",
        "Prosyanoye"
    ],
    "wof:name":"Prosyane",
    "wof:placetype":"locality"
},
  "geometry": {"coordinates":[39.66556,49.59222000000001],"type":"Point"}
}