{
  "type": "Feature",
  "properties": {
    "iso:country":"UA",
    "name:deu_x_preferred":[
        "Radensk"
    ],
    "name:eng_x_preferred":[
        "Radensk"
    ],
    "name:lav_x_preferred":[
        "Radenska"
    ],
    "name:ron_x_preferred":[
        "Radensk"
    ],
    "name:rus_x_preferred":[
        "\u0420\u0430\u0434\u0435\u043d\u0441\u043a"
    ],
    "name:ukr_x_preferred":[
        "\u0420\u0430\u0434\u0435\u043d\u0441\u044c\u043a"
    ],
    "name:ukr_x_variant":[
        "Radens\u2019k"
    ],
    "name:und_x_variant":[
        "Radenskoye"
    ],
    "name:zho_x_preferred":[
        "\u62c9\u5805\u897f\u514b"
    ],
    "qs:a0":"\u0423\u043a\u0440\u0430\u0457\u043d\u0430",
    "qs:a1":"*\u0425\u0435\u0440\u0441\u043e\u043d\u0441\u044c\u043a\u0430",
    "qs:a1_alt":"Khersons'ka",
    "qs:a1r":"0",
    "qs:a2":"\u0426\u044e\u0440\u0443\u043f\u0438\u043d\u0441\u044c\u043a\u0438\u0439",
    "qs:a2_alt":"Tsiurupyns'kyi",
    "qs:adm0":"\u0423\u043a\u0440\u0430\u0457\u043d\u0430",
    "qs:la_lc":"*",
    "qs:level":"locality",
    "qs:loc":"\u0420\u0430\u0434\u0435\u043d\u0441\u044c\u043a",
    "qs:loc_alt":"Radens'k",
    "qs:pop":0,
    "qs:type":"buffered point",
    "wof:name":"\u0420\u0430\u0434\u0435\u043d\u0441\u044c\u043a",
    "wof:placetype":"locality"
},
  "geometry": {"coordinates":[32.920338,46.551009],"type":"Point"}
}