{
  "type": "Feature",
  "properties": {
    "gn:admin1_code":"22.0",
    "gn:asciiname":"Shyshkovtse",
    "gn:country_code":"UA",
    "gn:dem":159,
    "gn:feature_class":"P",
    "gn:feature_code":"PPL",
    "gn:name":"Shyshkovtse",
    "gn:population":0,
    "gn:timezone":"Europe/Kiev",
    "iso:country":"UA",
    "name:und_x_variant":[
        "Shishkovtsy",
        "Szyszkowce",
        "Shyshkovtse"
    ],
    "wof:name":"Shyshkovtse",
    "wof:placetype":"locality"
},
  "geometry": {"coordinates":[26.02945,48.70815],"type":"Point"}
}