{
  "type": "Feature",
  "properties": {
    "gn:admin1_code":"26.0",
    "gn:asciiname":"Zahirne",
    "gn:country_code":"UA",
    "gn:dem":108,
    "gn:feature_class":"P",
    "gn:feature_code":"PPL",
    "gn:name":"Zahirne",
    "gn:population":0,
    "gn:timezone":"Europe/Zaporozhye",
    "iso:country":"UA",
    "name:ukr_x_preferred":[
        "Zahirne"
    ],
    "name:ukr_x_variant":[
        "\u0417\u0430\u0433\u0456\u0440\u043d\u0435"
    ],
    "name:und_x_variant":[
        "Petrovskiy"
    ],
    "wof:name":"Zahirne",
    "wof:placetype":"locality"
},
  "geometry": {"coordinates":[36.17356,47.56529000000001],"type":"Point"}
}