{
  "type": "Feature",
  "properties": {
    "gn:admin1_code":"2.0",
    "gn:asciiname":"Novoselytsya",
    "gn:country_code":"UA",
    "gn:dem":122,
    "gn:feature_class":"P",
    "gn:feature_code":"PPL",
    "gn:name":"Novoselytsya",
    "gn:population":0,
    "gn:timezone":"Europe/Kiev",
    "iso:country":"UA",
    "name:ukr_x_preferred":[
        "Novoselytsya"
    ],
    "name:ukr_x_variant":[
        "\u041d\u043e\u0432\u043e\u0441\u0435\u043b\u0438\u0446\u044f"
    ],
    "name:und_x_variant":[
        "Novoselytsa"
    ],
    "wof:name":"Novoselytsya",
    "wof:placetype":"locality"
},
  "geometry": {"coordinates":[33.02807,51.36387],"type":"Point"}
}