{
  "type": "Feature",
  "properties": {
    "gn:admin1_code":"15.0",
    "gn:asciiname":"Borove",
    "gn:cc2":"UA",
    "gn:country_code":"UA",
    "gn:dem":265,
    "gn:feature_class":"P",
    "gn:feature_code":"PPL",
    "gn:name":"Borove",
    "gn:population":0,
    "gn:timezone":"Europe/Kiev",
    "iso:country":"UA",
    "name:und_x_variant":[
        "Borova",
        "Borove"
    ],
    "wof:name":"Borove",
    "wof:placetype":"locality"
},
  "geometry": {"coordinates":[23.43333,50.06667],"type":"Point"}
}