{
  "type": "Feature",
  "properties": {
    "gn:admin1_code":"24.0",
    "gn:asciiname":"Marusya",
    "gn:country_code":"UA",
    "gn:dem":214,
    "gn:feature_class":"P",
    "gn:feature_code":"PPL",
    "gn:name":"Marusya",
    "gn:population":0,
    "gn:timezone":"Europe/Kiev",
    "iso:country":"UA",
    "name:ukr_x_preferred":[
        "Marusya"
    ],
    "name:ukr_x_variant":[
        "\u041c\u0430\u0440\u0443\u0441\u044f"
    ],
    "wof:name":"Marusya",
    "wof:placetype":"locality"
},
  "geometry": {"coordinates":[25.01878,50.61584000000001],"type":"Point"}
}