{
  "type": "Feature",
  "properties": {
    "gn:admin1_code":"22.0",
    "gn:asciiname":"Sadzhevka",
    "gn:country_code":"UA",
    "gn:dem":339,
    "gn:feature_class":"P",
    "gn:feature_code":"PPL",
    "gn:name":"Sadzhevka",
    "gn:population":0,
    "gn:timezone":"Europe/Kiev",
    "iso:country":"UA",
    "name:und_x_variant":[
        "Sadzavki",
        "Sadzhevka"
    ],
    "wof:name":"Sadzhevka",
    "wof:placetype":"locality"
},
  "geometry": {"coordinates":[26.15124,49.28061],"type":"Point"}
}