{
  "type": "Feature",
  "properties": {
    "gn:gn_country":"UA",
    "gn:gn_fcode":"PPL",
    "gn:gn_pop":300,
    "gn:population":327,
    "iso:country":"UA",
    "name:eng_x_preferred":[
        "Kurortnoye"
    ],
    "name:rus_x_historical":[
        "\u041d\u0438\u0301\u0436\u043d\u0438\u0439 \u041e\u0442\u0443\u0301\u0437"
    ],
    "name:rus_x_preferred":[
        "\u041a\u0443\u0440\u043e\u0440\u0442\u043d\u043e\u0435"
    ],
    "name:rus_x_variant":[
        "\u041d\u0438\u0301\u0436\u043d\u0438\u0439 \u041e\u0442\u0443\u0301\u0437"
    ],
    "name:ukr_x_preferred":[
        "\u041a\u0443\u0440\u043e\u0440\u0442\u043d\u0435"
    ],
    "qs_pg:aaroncc":"UA",
    "qs_pg:gn_country":"UA",
    "qs_pg:gn_fcode":"PPL",
    "qs_pg:gn_pop":300,
    "qs_pg:name":"Kurortnoye",
    "qs_pg:name_adm0":"Ukraine",
    "qs_pg:name_adm1":"Avtonomna Respublika Krym",
    "qs_pg:photos":176,
    "qs_pg:photos_1k":36,
    "qs_pg:photos_9k":1,
    "qs_pg:photos_9r":4,
    "qs_pg:photos_all":176,
    "qs_pg:photos_sr":4,
    "qs_pg:pop_sr":2,
    "qs_pg:qs_pg_placetype":"locality",
    "qs_pg:qs_pg_placetype_gp":"Town",
    "qs_pg:woe_adm0":23424976,
    "woe:adm0_id":23424976,
    "woe:name_adm0":"Ukraine",
    "woe:name_adm1":"Avtonomna Respublika Krym",
    "woe:placetype":"Town",
    "wof:name":"Kurortnoye",
    "wof:placetype":"locality",
    "wof:population":327
},
  "geometry": {"coordinates":[35.18938,44.91178],"type":"Point"}
}