{
  "type": "Feature",
  "properties": {
    "gn:population":17287,
    "iso:country":"UA",
    "name:ara_x_preferred":[
        "\u0623\u0648\u0631\u062e\u064a\u0641"
    ],
    "name:arm_x_preferred":[
        "\u0555\u0580\u0565\u056d\u0578\u057e"
    ],
    "name:bel_x_variant":[
        "\u0410\u0440\u044d\u0445\u0430\u045e"
    ],
    "name:bul_x_preferred":[
        "\u041e\u0440\u0438\u0445\u0438\u0432"
    ],
    "name:ces_x_preferred":[
        "Orichiv"
    ],
    "name:chi_x_preferred":[
        "\u5967\u5217\u970d\u592b"
    ],
    "name:crh_x_preferred":[
        "Orihiv"
    ],
    "name:cze_x_preferred":[
        "Orichiv"
    ],
    "name:deu_x_preferred":[
        "Orichiw"
    ],
    "name:dut_x_preferred":[
        "Orikhiv"
    ],
    "name:eng_x_preferred":[
        "Orikhiv"
    ],
    "name:fas_x_preferred":[
        "\u0627\u0648\u0631\u06cc\u062e\u06cc\u0641"
    ],
    "name:fra_x_preferred":[
        "Orikhiv"
    ],
    "name:fre_x_preferred":[
        "Orikhiv"
    ],
    "name:geo_x_preferred":[
        "\u10dd\u10e0\u10d4\u10ee\u10dd\u10d5\u10d8"
    ],
    "name:ger_x_preferred":[
        "Orichiw"
    ],
    "name:hsb_x_preferred":[
        "Orichiw"
    ],
    "name:hye_x_preferred":[
        "\u0555\u0580\u0565\u056d\u0578\u057e"
    ],
    "name:ita_x_preferred":[
        "Orichiv"
    ],
    "name:kat_x_preferred":[
        "\u10dd\u10e0\u10d4\u10ee\u10dd\u10d5\u10d8"
    ],
    "name:lav_x_preferred":[
        "Orihiva"
    ],
    "name:nno_x_preferred":[
        "Orikhiv"
    ],
    "name:per_x_preferred":[
        "\u0627\u0648\u0631\u06cc\u062e\u06cc\u0641"
    ],
    "name:pol_x_preferred":[
        "Orichiw"
    ],
    "name:ron_x_preferred":[
        "Orihiv"
    ],
    "name:rum_x_preferred":[
        "Orihiv"
    ],
    "name:rus_x_preferred":[
        "\u041e\u0440\u0435\u0445\u043e\u0432"
    ],
    "name:rus_x_variant":[
        "\u041e\u0440\u0456\u0445\u0456\u0432"
    ],
    "name:tat_x_preferred":[
        "\u041e\u0440\u0438\u0445\u0438\u0432"
    ],
    "name:ukr_x_preferred":[
        "\u041e\u0440\u0456\u0445\u0456\u0432"
    ],
    "name:unk_x_variant":[
        "Orechoff"
    ],
    "name:vie_x_preferred":[
        "Orikhiv"
    ],
    "name:zho_x_preferred":[
        "\u5967\u5217\u970d\u592b"
    ],
    "qs:a0":"\u0423\u043a\u0440\u0430\u0457\u043d\u0430",
    "qs:a1":"*\u0417\u0430\u043f\u043e\u0440\u0456\u0437\u044c\u043a\u0430",
    "qs:a1_alt":"Zaporiz'ka",
    "qs:a1r":"0",
    "qs:a2":"\u041e\u0440\u0456\u0445\u0456\u0432\u0441\u044c\u043a\u0438\u0439",
    "qs:a2_alt":"Orikhivs'kyi",
    "qs:adm0":"\u0423\u043a\u0440\u0430\u0457\u043d\u0430",
    "qs:la_lc":"*",
    "qs:level":"locality",
    "qs:loc":"\u041e\u0440\u0456\u0445\u0456\u0432",
    "qs:loc_alt":"Orikhiv",
    "qs:pop":0,
    "qs:type":"buffered point",
    "wd:wordcount":725,
    "wof:name":"\u041e\u0440\u0456\u0445\u0456\u0432",
    "wof:placetype":"locality",
    "wof:population":17287
},
  "geometry": {"coordinates":[35.803999,47.550492],"type":"Point"}
}