{
  "type": "Feature",
  "properties": {
    "gn:admin1_code":"5.0",
    "gn:asciiname":"Malaya Sedeyevka",
    "gn:country_code":"UA",
    "gn:dem":64,
    "gn:feature_class":"P",
    "gn:feature_code":"PPL",
    "gn:name":"Malaya Sedeyevka",
    "gn:population":0,
    "gn:timezone":"Europe/Kiev",
    "iso:country":"UA",
    "wof:name":"Malaya Sedeyevka",
    "wof:placetype":"locality"
},
  "geometry": {"coordinates":[38.05,47.15],"type":"Point"}
}