{
  "type": "Feature",
  "properties": {
    "gn:admin1_code":"21.0",
    "gn:asciiname":"Voroshilova",
    "gn:cc2":"UA",
    "gn:country_code":"UA",
    "gn:dem":155,
    "gn:feature_class":"P",
    "gn:feature_code":"PPL",
    "gn:name":"Voroshilova",
    "gn:population":0,
    "gn:timezone":"Europe/Kiev",
    "iso:country":"UA",
    "name:und_x_variant":[
        "Solontsy",
        "Voroshilova"
    ],
    "wof:name":"Voroshilova",
    "wof:placetype":"locality"
},
  "geometry": {"coordinates":[33.13333,51.11667],"type":"Point"}
}