{
  "type": "Feature",
  "properties": {
    "gn:admin1_code":"5.0",
    "gn:asciiname":"Korsunivka",
    "gn:country_code":"UA",
    "gn:dem":64,
    "gn:feature_class":"P",
    "gn:feature_code":"PPL",
    "gn:name":"Korsunivka",
    "gn:population":0,
    "gn:timezone":"Europe/Kiev",
    "iso:country":"UA",
    "name:und_x_variant":[
        "Lavrent\u2019yevka"
    ],
    "wof:name":"Korsunivka",
    "wof:placetype":"locality"
},
  "geometry": {"coordinates":[37.86667,48.88333],"type":"Point"}
}