{
  "type": "Feature",
  "properties": {
    "gn:admin1_code":"14.0",
    "gn:asciiname":"Anninskiy",
    "gn:country_code":"UA",
    "gn:dem":168,
    "gn:feature_class":"P",
    "gn:feature_code":"PPL",
    "gn:name":"Anninskiy",
    "gn:population":0,
    "gn:timezone":"Europe/Zaporozhye",
    "iso:country":"UA",
    "wof:name":"Anninskiy",
    "wof:placetype":"locality"
},
  "geometry": {"coordinates":[38.54583,48.64806],"type":"Point"}
}