{
  "type": "Feature",
  "properties": {
    "gn:admin1_code":"15.0",
    "gn:asciiname":"Malyy",
    "gn:country_code":"UA",
    "gn:dem":216,
    "gn:feature_class":"P",
    "gn:feature_code":"PPL",
    "gn:name":"Malyy",
    "gn:population":0,
    "gn:timezone":"Europe/Kiev",
    "iso:country":"UA",
    "name:ukr_x_preferred":[
        "\u041c\u0430\u043b\u0438\u0439"
    ],
    "name:und_x_variant":[
        "Gole-Male"
    ],
    "wof:name":"Malyy",
    "wof:placetype":"locality"
},
  "geometry": {"coordinates":[23.73533,50.21766],"type":"Point"}
}