{
  "type": "Feature",
  "properties": {
    "gn:admin1_code":"7.0",
    "gn:asciiname":"Dekreshevo",
    "gn:country_code":"UA",
    "gn:dem":149,
    "gn:feature_class":"P",
    "gn:feature_code":"PPL",
    "gn:name":"Dekreshevo",
    "gn:population":0,
    "gn:timezone":"Europe/Kiev",
    "iso:country":"UA",
    "wof:name":"Dekreshevo",
    "wof:placetype":"locality"
},
  "geometry": {"coordinates":[34.97111,50.11361],"type":"Point"}
}