{
  "type": "Feature",
  "properties": {
    "gn:admin1_code":"24.0",
    "gn:asciiname":"Kolpytiv",
    "gn:country_code":"UA",
    "gn:dem":224,
    "gn:feature_class":"P",
    "gn:feature_code":"PPL",
    "gn:name":"Kolpytiv",
    "gn:population":0,
    "gn:timezone":"Europe/Kiev",
    "iso:country":"UA",
    "name:ukr_x_preferred":[
        "Kolpytiv"
    ],
    "name:ukr_x_variant":[
        "\u041a\u043e\u043b\u043f\u0438\u0442\u0456\u0432"
    ],
    "name:und_x_variant":[
        "Kolpytuv",
        "Ko\u0142pyt\u00f3w",
        "Kolpytov"
    ],
    "wof:name":"Kolpytiv",
    "wof:placetype":"locality"
},
  "geometry": {"coordinates":[24.76475,50.59273],"type":"Point"}
}