{
  "type": "Feature",
  "properties": {
    "gn:admin1_code":"21.0",
    "gn:asciiname":"Cheremukhivka",
    "gn:country_code":"UA",
    "gn:dem":150,
    "gn:feature_class":"P",
    "gn:feature_code":"PPL",
    "gn:name":"Cheremukhivka",
    "gn:population":0,
    "gn:timezone":"Europe/Kiev",
    "iso:country":"UA",
    "name:ukr_x_preferred":[
        "Cheremukhivka"
    ],
    "name:ukr_x_variant":[
        "\u0427\u0435\u0440\u0435\u043c\u0443\u0445\u0456\u0432\u043a\u0430"
    ],
    "wof:name":"Cheremukhivka",
    "wof:placetype":"locality"
},
  "geometry": {"coordinates":[34.59601,50.47667],"type":"Point"}
}