{
  "type": "Feature",
  "properties": {
    "gn:admin1_code":"15.0",
    "gn:asciiname":"Ugartsberg",
    "gn:cc2":"UA",
    "gn:country_code":"UA",
    "gn:dem":254,
    "gn:feature_class":"P",
    "gn:feature_code":"PPL",
    "gn:name":"Ugartsberg",
    "gn:population":0,
    "gn:timezone":"Europe/Kiev",
    "iso:country":"UA",
    "name:und_x_variant":[
        "Vypuchki",
        "Ugartsberg"
    ],
    "wof:name":"Ugartsberg",
    "wof:placetype":"locality"
},
  "geometry": {"coordinates":[23.75,49.48333],"type":"Point"}
}