{
  "type": "Feature",
  "properties": {
    "gn:admin1_code":"11.0",
    "gn:admin2_code":"703233",
    "gn:admin3_code":"11131623",
    "gn:asciiname":"Zelyonyi Yar",
    "gn:country_code":"UA",
    "gn:dem":46,
    "gn:feature_class":"P",
    "gn:feature_code":"PPL",
    "gn:name":"Zelyonyi Yar",
    "gn:population":34,
    "gn:timezone":"Europe/Simferopol",
    "iso:country":"UA",
    "name:eng_x_preferred":[
        "Zelyonyi Yar"
    ],
    "name:rus_x_historical":[
        "\u0422\u0430\u0448\u043b\u044b\u0301-\u042f\u0440"
    ],
    "name:rus_x_preferred":[
        "\u0417\u0435\u043b\u0451\u043d\u044b\u0439 \u042f\u0440"
    ],
    "name:rus_x_variant":[
        "\u0422\u0430\u0448\u043b\u044b\u0301-\u042f\u0440"
    ],
    "name:ukr_x_preferred":[
        "\u0417\u0435\u043b\u0435\u043d\u0438\u0439 \u042f\u0440"
    ],
    "wof:name":"Zelyonyi Yar",
    "wof:placetype":"locality",
    "wof:population":34
},
  "geometry": {"coordinates":[35.98373,45.34402],"type":"Point"}
}