{
  "type": "Feature",
  "properties": {
    "gn:admin1_code":"23.0",
    "gn:asciiname":"Mervyntsi",
    "gn:country_code":"UA",
    "gn:dem":115,
    "gn:feature_class":"P",
    "gn:feature_code":"PPL",
    "gn:name":"Mervyntsi",
    "gn:population":0,
    "gn:timezone":"Europe/Kiev",
    "iso:country":"UA",
    "name:crh_x_preferred":[
        "Merv\u0131ntsi"
    ],
    "name:hye_x_preferred":[
        "\u0544\u0565\u0580\u057e\u056b\u0576\u0581\u056b"
    ],
    "name:pol_x_preferred":[
        "Mierzwi\u0144ce"
    ],
    "name:ron_x_preferred":[
        "Merv\u00een\u021bi"
    ],
    "name:rus_x_preferred":[
        "\u041c\u0435\u0440\u0432\u0438\u043d\u0446\u044b"
    ],
    "name:ukr_x_preferred":[
        "\u041c\u0435\u0440\u0432\u0438\u043d\u0446\u0456"
    ],
    "name:und_x_variant":[
        "Mervintsy"
    ],
    "name:zho_x_preferred":[
        "\u6885\u723e\u6eab\u9f4a"
    ],
    "wof:name":"Mervyntsi",
    "wof:placetype":"locality"
},
  "geometry": {"coordinates":[28.04965,48.37406],"type":"Point"}
}