{
  "type": "Feature",
  "properties": {
    "gn:admin1_code":"18.0",
    "gn:asciiname":"Bazylivshchyna",
    "gn:country_code":"UA",
    "gn:dem":96,
    "gn:feature_class":"P",
    "gn:feature_code":"PPL",
    "gn:name":"Bazylivshchyna",
    "gn:population":0,
    "gn:timezone":"Europe/Kiev",
    "iso:country":"UA",
    "name:eng_x_preferred":[
        "Bazilevshchina"
    ],
    "name:rus_x_preferred":[
        "\u0411\u0430\u0437\u0438\u043b\u0435\u0432\u0449\u0438\u043d\u0430"
    ],
    "name:ukr_x_preferred":[
        "Bazylivshchyna"
    ],
    "name:ukr_x_variant":[
        "\u0411\u0430\u0437\u0438\u043b\u0456\u0432\u0449\u0438\u043d\u0430"
    ],
    "name:und_x_variant":[
        "Mokryy Tagamlyk",
        "Bazylevshchina",
        "Bazilevshchina"
    ],
    "wof:name":"Bazylivshchyna",
    "wof:placetype":"locality"
},
  "geometry": {"coordinates":[34.88239,49.47732],"type":"Point"}
}