{
  "type": "Feature",
  "properties": {
    "gn:admin1_code":"27.0",
    "gn:asciiname":"Hrynivtsi",
    "gn:country_code":"UA",
    "gn:dem":233,
    "gn:feature_class":"P",
    "gn:feature_code":"PPL",
    "gn:name":"Hrynivtsi",
    "gn:population":0,
    "gn:timezone":"Europe/Kiev",
    "iso:country":"UA",
    "name:ukr_x_preferred":[
        "Hrynivtsi"
    ],
    "name:ukr_x_variant":[
        "\u0413\u0440\u0438\u043d\u0456\u0432\u0446\u0456"
    ],
    "name:und_x_variant":[
        "Grinovtsy"
    ],
    "wof:name":"Hrynivtsi",
    "wof:placetype":"locality"
},
  "geometry": {"coordinates":[27.74531,49.88665],"type":"Point"}
}