{
  "type": "Feature",
  "properties": {
    "gn:admin1_code":"15.0",
    "gn:asciiname":"Obortiv",
    "gn:country_code":"UA",
    "gn:dem":212,
    "gn:feature_class":"P",
    "gn:feature_code":"PPL",
    "gn:name":"Obortiv",
    "gn:population":0,
    "gn:timezone":"Europe/Kiev",
    "iso:country":"UA",
    "name:ukr_x_preferred":[
        "Obortiv"
    ],
    "name:ukr_x_variant":[
        "\u041e\u0431\u043e\u0440\u0442\u0456\u0432"
    ],
    "name:und_x_variant":[
        "Obortov"
    ],
    "wof:name":"Obortiv",
    "wof:placetype":"locality"
},
  "geometry": {"coordinates":[24.49486,50.33443],"type":"Point"}
}