{
  "type": "Feature",
  "properties": {
    "gn:admin1_code":"26.0",
    "gn:asciiname":"Mykhaylivs'ke",
    "gn:country_code":"UA",
    "gn:dem":42,
    "gn:feature_class":"P",
    "gn:feature_code":"PPL",
    "gn:name":"Mykhaylivs\u2019ke",
    "gn:population":0,
    "gn:timezone":"Europe/Zaporozhye",
    "iso:country":"UA",
    "name:rus_x_preferred":[
        "\u041c\u0438\u0445\u0430\u0439\u043b\u043e\u0432\u0441\u043a\u043e\u0435"
    ],
    "name:ukr_x_preferred":[
        "Mykhaylivs\u2019ke"
    ],
    "name:ukr_x_variant":[
        "\u041c\u0438\u0445\u0430\u0439\u043b\u0456\u0432\u0441\u044c\u043a\u0435"
    ],
    "name:und_x_variant":[
        "Mikhaylovskoye"
    ],
    "wof:name":"Mykhaylivs'ke",
    "wof:placetype":"locality"
},
  "geometry": {"coordinates":[34.82395,46.71275],"type":"Point"}
}