{
  "type": "Feature",
  "properties": {
    "iso:country":"UA",
    "name:eng_x_preferred":[
        "Fontany"
    ],
    "name:rus_x_historical":[
        "\u042f\u0433\u043c\u0443\u0440\u0447\u0430\u0301"
    ],
    "name:rus_x_preferred":[
        "\u0424\u043e\u043d\u0442\u0430\u043d\u044b"
    ],
    "name:rus_x_variant":[
        "\u042f\u0433\u043c\u0443\u0440\u0447\u0430\u0301"
    ],
    "name:ukr_x_preferred":[
        "\u0424\u043e\u043d\u0442\u0430\u043d\u0438"
    ],
    "qs:a0":"\u0423\u043a\u0440\u0430\u0457\u043d\u0430",
    "qs:a1":"*\u041a\u0440\u0438\u043c",
    "qs:a1_alt":"Krym",
    "qs:a1r":"0",
    "qs:a2":"\u0421\u0456\u043c\u0444\u0435\u0440\u043e\u043f\u043e\u043b\u044c\u0441\u044c\u043a\u0438\u0439",
    "qs:a2_alt":"Simferopol's'kyi",
    "qs:adm0":"\u0423\u043a\u0440\u0430\u0457\u043d\u0430",
    "qs:la_lc":"*",
    "qs:level":"locality",
    "qs:loc":"\u0424\u043e\u043d\u0442\u0430\u043d\u0438",
    "qs:loc_alt":"Fontany",
    "qs:pop":0,
    "qs:type":"buffered point",
    "wof:name":"\u0424\u043e\u043d\u0442\u0430\u043d\u0438",
    "wof:placetype":"locality"
},
  "geometry": {"coordinates":[34.07371,44.894626],"type":"Point"}
}