{
  "type": "Feature",
  "properties": {
    "gn:admin1_code":"5.0",
    "gn:asciiname":"Rohans'ke",
    "gn:country_code":"UA",
    "gn:dem":144,
    "gn:feature_class":"P",
    "gn:feature_code":"PPL",
    "gn:name":"Rohans\u2019ke",
    "gn:population":0,
    "gn:timezone":"Europe/Kiev",
    "iso:country":"UA",
    "name:ukr_x_preferred":[
        "Rohans\u2019ke"
    ],
    "name:ukr_x_variant":[
        "\u0420\u043e\u0433\u0430\u043d\u0441\u044c\u043a\u0435"
    ],
    "name:und_x_variant":[
        "Roganskoye"
    ],
    "wof:name":"Rohans'ke",
    "wof:placetype":"locality"
},
  "geometry": {"coordinates":[37.36318,48.64865],"type":"Point"}
}