{
  "type": "Feature",
  "properties": {
    "gn:population":5172,
    "iso:country":"UA",
    "name:eng_x_preferred":[
        "Berezna"
    ],
    "name:rus_x_preferred":[
        "\u0411\u0435\u0440\u0435\u0437\u043d\u0430"
    ],
    "name:ukr_x_preferred":[
        "\u0411\u0435\u0440\u0435\u0437\u043d\u0430"
    ],
    "name:und_x_variant":[
        "Beresna"
    ],
    "qs:a0":"\u0423\u043a\u0440\u0430\u0457\u043d\u0430",
    "qs:a1":"*\u0427\u0435\u0440\u043d\u0456\u0433\u0456\u0432\u0441\u044c\u043a\u0430",
    "qs:a1_alt":"Chernihivs'ka",
    "qs:a1r":"0",
    "qs:a2":"\u041c\u0435\u043d\u0441\u044c\u043a\u0438\u0439",
    "qs:a2_alt":"Mens'kyi",
    "qs:adm0":"\u0423\u043a\u0440\u0430\u0457\u043d\u0430",
    "qs:la_lc":"*",
    "qs:level":"locality",
    "qs:loc":"\u0411\u0435\u0440\u0435\u0437\u043d\u0430",
    "qs:loc_alt":"Berezna",
    "qs:pop":0,
    "qs:type":"buffered point",
    "wof:name":"\u0411\u0435\u0440\u0435\u0437\u043d\u0430",
    "wof:placetype":"locality",
    "wof:population":5172
},
  "geometry": {"coordinates":[31.785096,51.573691],"type":"Point"}
}