{
  "type": "Feature",
  "properties": {
    "gn:admin1_code":"15.0",
    "gn:asciiname":"Rykiv",
    "gn:country_code":"UA",
    "gn:dem":620,
    "gn:feature_class":"P",
    "gn:feature_code":"PPL",
    "gn:name":"Rykiv",
    "gn:population":0,
    "gn:timezone":"Europe/Kiev",
    "iso:country":"UA",
    "name:rus_x_preferred":[
        "\u0420\u044b\u043a\u043e\u0432"
    ],
    "name:ukr_x_preferred":[
        "Rykiv"
    ],
    "name:ukr_x_variant":[
        "\u0420\u0438\u043a\u0456\u0432"
    ],
    "name:und_x_variant":[
        "Bykov",
        "Rykov"
    ],
    "wof:name":"Rykiv",
    "wof:placetype":"locality"
},
  "geometry": {"coordinates":[23.12772,49.04607],"type":"Point"}
}