{
  "type": "Feature",
  "properties": {
    "iso:country":"UA",
    "name:crh_x_preferred":[
        "L\u0131sets"
    ],
    "name:deu_x_preferred":[
        "Lyssez"
    ],
    "name:deu_x_variant":[
        "Lisec"
    ],
    "name:eng_x_preferred":[
        "Lisec"
    ],
    "name:hye_x_preferred":[
        "\u053c\u056b\u057d\u0565\u0581"
    ],
    "name:pol_x_preferred":[
        "\u0141ysiec"
    ],
    "name:ron_x_preferred":[
        "L\u00eese\u021b"
    ],
    "name:rus_x_preferred":[
        "\u041b\u0438\u0441\u0435\u0446"
    ],
    "name:rus_x_variant":[
        "\u041b\u044b\u0441\u0435\u0446"
    ],
    "name:ukr_x_preferred":[
        "\u041b\u0438\u0441\u0435\u0446\u044c"
    ],
    "name:zho_x_preferred":[
        "\u5229\u8b1d\u9f4a"
    ],
    "qs:a0":"\u0423\u043a\u0440\u0430\u0457\u043d\u0430",
    "qs:a1":"*\u0425\u043c\u0435\u043b\u044c\u043d\u0438\u0446\u044c\u043a\u0430",
    "qs:a1_alt":"Khmel'nyts'ka",
    "qs:a1r":"0",
    "qs:a2":"\u0414\u0443\u043d\u0430\u0454\u0432\u0435\u0446\u044c\u043a\u0438\u0439",
    "qs:a2_alt":"Dunaievets'kyi",
    "qs:adm0":"\u0423\u043a\u0440\u0430\u0457\u043d\u0430",
    "qs:la_lc":"*",
    "qs:level":"locality",
    "qs:loc":"\u041b\u0438\u0441\u0435\u0446\u044c",
    "qs:loc_alt":"Lysets",
    "qs:pop":0,
    "qs:type":"buffered point",
    "wd:wordcount":87,
    "wof:name":"\u041b\u0438\u0441\u0435\u0446\u044c",
    "wof:placetype":"locality"
},
  "geometry": {"coordinates":[27.020186,48.789715],"type":"Point"}
}