{
  "type": "Feature",
  "properties": {
    "gn:admin1_code":"4.0",
    "gn:asciiname":"Radyans'ke",
    "gn:country_code":"UA",
    "gn:dem":96,
    "gn:feature_class":"P",
    "gn:feature_code":"PPL",
    "gn:name":"Radyans\u2019ke",
    "gn:population":0,
    "gn:timezone":"Europe/Kiev",
    "iso:country":"UA",
    "name:ukr_x_preferred":[
        "Radyans\u2019ke"
    ],
    "name:ukr_x_variant":[
        "\u0420\u0430\u0434\u044f\u043d\u0441\u044c\u043a\u0435"
    ],
    "wof:name":"Radyans'ke",
    "wof:placetype":"locality"
},
  "geometry": {"coordinates":[34.76727,48.14548],"type":"Point"}
}