{
  "type": "Feature",
  "properties": {
    "iso:country":"UA",
    "name:ara_x_preferred":[
        "\u0628\u0648\u0647\u062f\u0627\u0646\u064a\u0641\u0643\u0627"
    ],
    "name:eng_x_preferred":[
        "Bogdanovka"
    ],
    "name:hye_x_preferred":[
        "\u0532\u0578\u0563\u0564\u0561\u0576\u0578\u057e\u056f\u0561"
    ],
    "name:ron_x_preferred":[
        "Bohdanivka"
    ],
    "name:rus_x_preferred":[
        "\u0411\u043e\u0433\u0434\u0430\u043d\u043e\u0432\u043a\u0430"
    ],
    "name:ukr_x_preferred":[
        "\u0411\u043e\u0433\u0434\u0430\u043d\u0456\u0432\u043a\u0430"
    ],
    "name:ukr_x_variant":[
        "Bohdanivka"
    ],
    "name:unk_x_variant":[
        "Bogdanovka"
    ],
    "name:zho_x_preferred":[
        "\u535a\u683c\u9054\u5c3c\u592b\u5361"
    ],
    "qs:a0":"\u0423\u043a\u0440\u0430\u0457\u043d\u0430",
    "qs:a1":"*\u0414\u043d\u0456\u043f\u0440\u043e\u043f\u0435\u0442\u0440\u043e\u0432\u0441\u044c\u043a\u0430",
    "qs:a1_alt":"Dnipropetrovs'ka",
    "qs:a1r":"0",
    "qs:a2":"\u041f\u0430\u0432\u043b\u043e\u0433\u0440\u0430\u0434\u0441\u044c\u043a\u0438\u0439",
    "qs:a2_alt":"Pavlohrads'kyi",
    "qs:adm0":"\u0423\u043a\u0440\u0430\u0457\u043d\u0430",
    "qs:la_lc":"*",
    "qs:level":"locality",
    "qs:loc":"\u0411\u043e\u0433\u0434\u0430\u043d\u0456\u0432\u043a\u0430",
    "qs:loc_alt":"Bohdanivka",
    "qs:pop":0,
    "qs:type":"buffered point",
    "wd:wordcount":59,
    "wof:name":"\u0411\u043e\u0433\u0434\u0430\u043d\u0456\u0432\u043a\u0430",
    "wof:placetype":"locality"
},
  "geometry": {"coordinates":[36.107382,48.494478],"type":"Point"}
}