{
  "type": "Feature",
  "properties": {
    "gn:admin1_code":"21.0",
    "gn:asciiname":"Buhor",
    "gn:country_code":"UA",
    "gn:dem":187,
    "gn:feature_class":"P",
    "gn:feature_code":"PPL",
    "gn:name":"Buhor",
    "gn:population":0,
    "gn:timezone":"Europe/Kiev",
    "iso:country":"UA",
    "name:ukr_x_preferred":[
        "Buhor"
    ],
    "name:ukr_x_variant":[
        "\u0411\u0443\u0433\u043e\u0440"
    ],
    "name:und_x_variant":[
        "Bugor"
    ],
    "wof:name":"Buhor",
    "wof:placetype":"locality"
},
  "geometry": {"coordinates":[33.98125,52.03319000000001],"type":"Point"}
}