{
  "type": "Feature",
  "properties": {
    "gn:admin1_code":"11.0",
    "gn:admin2_code":"700018",
    "gn:admin3_code":"11152961.0",
    "gn:asciiname":"Luzhki",
    "gn:country_code":"UA",
    "gn:dem":10,
    "gn:elevation":"9.0",
    "gn:feature_class":"P",
    "gn:feature_code":"PPL",
    "gn:name":"Luzhki",
    "gn:population":228,
    "gn:timezone":"Europe/Simferopol",
    "iso:country":"UA",
    "name:eng_x_preferred":[
        "Luzhki"
    ],
    "name:rus_x_historical":[
        "\u0428\u0438\u0431\u0430\u0301\u043d"
    ],
    "name:rus_x_preferred":[
        "\u041b\u0443\u0436\u043a\u0438"
    ],
    "name:rus_x_variant":[
        "\u0428\u0438\u0431\u0430\u0301\u043d"
    ],
    "name:ukr_x_preferred":[
        "\u041b\u0443\u0436\u043a\u0438"
    ],
    "wof:name":"Luzhki",
    "wof:placetype":"locality",
    "wof:population":228
},
  "geometry": {"coordinates":[34.85422,45.54088],"type":"Point"}
}