{
  "type": "Feature",
  "properties": {
    "gn:admin1_code":"6.0",
    "gn:asciiname":"Yakhlush",
    "gn:country_code":"UA",
    "gn:dem":277,
    "gn:feature_class":"P",
    "gn:feature_code":"PPL",
    "gn:name":"Yakhlush",
    "gn:population":0,
    "gn:timezone":"Europe/Kiev",
    "iso:country":"UA",
    "wof:name":"Yakhlush",
    "wof:placetype":"locality"
},
  "geometry": {"coordinates":[24.48716,49.48403],"type":"Point"}
}