{
  "type": "Feature",
  "properties": {
    "gn:admin1_code":"2.0",
    "gn:asciiname":"Podil",
    "gn:country_code":"UA",
    "gn:dem":119,
    "gn:feature_class":"P",
    "gn:feature_code":"PPL",
    "gn:name":"Podil",
    "gn:population":0,
    "gn:timezone":"Europe/Kiev",
    "iso:country":"UA",
    "name:ukr_x_preferred":[
        "Podil"
    ],
    "name:ukr_x_variant":[
        "\u041f\u043e\u0434\u0456\u043b"
    ],
    "name:und_x_variant":[
        "Podol"
    ],
    "wof:name":"Podil",
    "wof:placetype":"locality"
},
  "geometry": {"coordinates":[32.91387,50.63947],"type":"Point"}
}