{
  "type": "Feature",
  "properties": {
    "gn:admin1_code":"14.0",
    "gn:asciiname":"Kononivka",
    "gn:country_code":"UA",
    "gn:dem":78,
    "gn:feature_class":"P",
    "gn:feature_code":"PPL",
    "gn:name":"Kononivka",
    "gn:population":0,
    "gn:timezone":"Europe/Zaporozhye",
    "iso:country":"UA",
    "name:ukr_x_preferred":[
        "\u041a\u043e\u043d\u043e\u043d\u0456\u0432\u043a\u0430"
    ],
    "name:und_x_variant":[
        "Kononovak",
        "Kononovka",
        "Kononivka"
    ],
    "wof:name":"Kononivka",
    "wof:placetype":"locality"
},
  "geometry": {"coordinates":[39.62558,49.33218],"type":"Point"}
}