{
  "type": "Feature",
  "properties": {
    "gn:admin1_code":"18.0",
    "gn:asciiname":"Shapky",
    "gn:country_code":"UA",
    "gn:dem":87,
    "gn:feature_class":"P",
    "gn:feature_code":"PPL",
    "gn:name":"Shapky",
    "gn:population":0,
    "gn:timezone":"Europe/Kiev",
    "iso:country":"UA",
    "name:ukr_x_preferred":[
        "Shapky"
    ],
    "name:ukr_x_variant":[
        "\u0428\u0430\u043f\u043a\u0438"
    ],
    "wof:name":"Shapky",
    "wof:placetype":"locality"
},
  "geometry": {"coordinates":[34.11387,49.27752],"type":"Point"}
}