{
  "type": "Feature",
  "properties": {
    "gn:admin1_code":"9.0",
    "gn:asciiname":"Agaki",
    "gn:cc2":"UA",
    "gn:country_code":"UA",
    "gn:dem":198,
    "gn:feature_class":"P",
    "gn:feature_code":"PPL",
    "gn:name":"Agaki",
    "gn:population":0,
    "gn:timezone":"Europe/Kiev",
    "iso:country":"UA",
    "name:und_x_variant":[
        "Ataki",
        "Atakhi",
        "Agaki"
    ],
    "wof:name":"Agaki",
    "wof:placetype":"locality"
},
  "geometry": {"coordinates":[26.93333,48.58333],"type":"Point"}
}