{
  "type": "Feature",
  "properties": {
    "iso:country":"UA",
    "name:deu_x_preferred":[
        "Neruschaj"
    ],
    "name:eng_x_preferred":[
        "Nerushai"
    ],
    "name:lav_x_preferred":[
        "Neru\u0161aja"
    ],
    "name:ron_x_preferred":[
        "Neru\u0219ai"
    ],
    "name:rus_x_preferred":[
        "\u041d\u0435\u0440\u0443\u0448\u0430\u0439"
    ],
    "name:spa_x_preferred":[
        "Nerushai"
    ],
    "name:ukr_x_preferred":[
        "\u041d\u0435\u0440\u0443\u0448\u0430\u0439"
    ],
    "name:und_x_variant":[
        "Neru\u015fai"
    ],
    "name:zho_x_preferred":[
        "\u6d85\u9b6f\u6c99\u4f0a"
    ],
    "qs:a0":"\u0423\u043a\u0440\u0430\u0457\u043d\u0430",
    "qs:a1":"*\u041e\u0434\u0435\u0441\u044c\u043a\u0430",
    "qs:a1_alt":"Odes'ka",
    "qs:a1r":"0",
    "qs:a2":"\u0422\u0430\u0442\u0430\u0440\u0431\u0443\u043d\u0430\u0440\u0441\u044c\u043a\u0438\u0439",
    "qs:a2_alt":"Tatarbunars'kyi",
    "qs:adm0":"\u0423\u043a\u0440\u0430\u0457\u043d\u0430",
    "qs:la_lc":"*",
    "qs:level":"locality",
    "qs:loc":"\u041d\u0435\u0440\u0443\u0448\u0430\u0439",
    "qs:loc_alt":"Nerushai",
    "qs:pop":0,
    "qs:type":"buffered point",
    "wof:name":"\u041d\u0435\u0440\u0443\u0448\u0430\u0439",
    "wof:placetype":"locality"
},
  "geometry": {"coordinates":[29.509779,45.655555],"type":"Point"}
}