{
  "type": "Feature",
  "properties": {
    "gn:admin1_code":"4.0",
    "gn:asciiname":"Kolkhozovka",
    "gn:country_code":"UA",
    "gn:dem":60,
    "gn:feature_class":"P",
    "gn:feature_code":"PPL",
    "gn:name":"Kolkhozovka",
    "gn:population":0,
    "gn:timezone":"Europe/Kiev",
    "iso:country":"UA",
    "name:und_x_variant":[
        "Loboykovskiye",
        "Kolkhozovka"
    ],
    "wof:name":"Kolkhozovka",
    "wof:placetype":"locality"
},
  "geometry": {"coordinates":[34.69994000000001,48.66436],"type":"Point"}
}