{
  "type": "Feature",
  "properties": {
    "gn:admin1_code":"4.0",
    "gn:asciiname":"Nerdustal'",
    "gn:country_code":"UA",
    "gn:dem":121,
    "gn:feature_class":"P",
    "gn:feature_code":"PPL",
    "gn:name":"Nerdustal\u2019",
    "gn:population":0,
    "gn:timezone":"Europe/Kiev",
    "iso:country":"UA",
    "name:rus_x_preferred":[
        "Nyerudstal\u2019"
    ],
    "name:rus_x_variant":[
        "\u041d\u0435\u0440\u0443\u0434\u0441\u0442\u0430\u043b\u044c"
    ],
    "name:ukr_x_preferred":[
        "Nerdustal\u2019"
    ],
    "name:ukr_x_variant":[
        "\u041d\u0435\u0440\u0434\u0443\u0441\u0442\u0430\u043b\u044c"
    ],
    "wof:name":"Nerdustal'",
    "wof:placetype":"locality"
},
  "geometry": {"coordinates":[33.7107,48.37565],"type":"Point"}
}