{
  "type": "Feature",
  "properties": {
    "gn:admin1_code":"19.0",
    "gn:asciiname":"Franivka",
    "gn:country_code":"UA",
    "gn:dem":195,
    "gn:feature_class":"P",
    "gn:feature_code":"PPL",
    "gn:name":"Franivka",
    "gn:population":0,
    "gn:timezone":"Europe/Kiev",
    "iso:country":"UA",
    "name:ukr_x_preferred":[
        "Franivka"
    ],
    "name:ukr_x_variant":[
        "\u0424\u0440\u0430\u043d\u0456\u0432\u043a\u0430"
    ],
    "name:und_x_variant":[
        "Franovka"
    ],
    "wof:name":"Franivka",
    "wof:placetype":"locality"
},
  "geometry": {"coordinates":[26.67273,50.56802],"type":"Point"}
}