{
  "type": "Feature",
  "properties": {
    "gn:admin1_code":"27.0",
    "gn:asciiname":"Rudnya Frankovka",
    "gn:country_code":"UA",
    "gn:dem":230,
    "gn:feature_class":"P",
    "gn:feature_code":"PPL",
    "gn:name":"Rudnya Frankovka",
    "gn:population":0,
    "gn:timezone":"Europe/Kiev",
    "iso:country":"UA",
    "wof:name":"Rudnya Frankovka",
    "wof:placetype":"locality"
},
  "geometry": {"coordinates":[28.35,51.31667],"type":"Point"}
}