{
  "type": "Feature",
  "properties": {
    "gn:admin1_code":"15.0",
    "gn:asciiname":"Loni",
    "gn:country_code":"UA",
    "gn:dem":372,
    "gn:feature_class":"P",
    "gn:feature_code":"PPL",
    "gn:name":"Loni",
    "gn:population":0,
    "gn:timezone":"Europe/Kiev",
    "iso:country":"UA",
    "name:bih_x_preferred":[
        "\u0932\u094b\u0928\u0940"
    ],
    "name:gom_x_preferred":[
        "\u0932\u094b\u0923\u0940"
    ],
    "name:pus_x_preferred":[
        "\u0644\u0648\u0646\u064a"
    ],
    "wof:name":"Loni",
    "wof:placetype":"locality"
},
  "geometry": {"coordinates":[24.66877,49.73076],"type":"Point"}
}