{
  "type": "Feature",
  "properties": {
    "gn:admin1_code":"4.0",
    "gn:asciiname":"Olefirivka",
    "gn:country_code":"UA",
    "gn:dem":71,
    "gn:feature_class":"P",
    "gn:feature_code":"PPL",
    "gn:name":"Olefirivka",
    "gn:population":0,
    "gn:timezone":"Europe/Kiev",
    "iso:country":"UA",
    "name:ukr_x_preferred":[
        "Olefirivka"
    ],
    "name:ukr_x_variant":[
        "\u041e\u043b\u0435\u0444\u0456\u0440\u0456\u0432\u043a\u0430"
    ],
    "name:und_x_variant":[
        "Alefirovka",
        "Olefirovka"
    ],
    "wof:name":"Olefirivka",
    "wof:placetype":"locality"
},
  "geometry": {"coordinates":[36.09582,48.43019],"type":"Point"}
}