{
  "type": "Feature",
  "properties": {
    "iso:country":"UA",
    "name:ukr_x_preferred":[
        "Yastrubychi"
    ],
    "name:ukr_x_variant":[
        "\u042f\u0441\u0442\u0440\u0443\u0431\u0438\u0447\u0456"
    ],
    "name:unk_x_variant":[
        "Jastrz\u0119bica"
    ],
    "qs:a0":"\u0423\u043a\u0440\u0430\u0457\u043d\u0430",
    "qs:a1":"*\u041b\u044c\u0432\u0456\u0432\u0441\u044c\u043a\u0430",
    "qs:a1_alt":"L'vivs'ka",
    "qs:a1r":"0",
    "qs:a2":"\u0420\u0430\u0434\u0435\u0445\u0456\u0432\u0441\u044c\u043a\u0438\u0439",
    "qs:a2_alt":"Radekhivs'kyi",
    "qs:adm0":"\u0423\u043a\u0440\u0430\u0457\u043d\u0430",
    "qs:la_lc":"*",
    "qs:level":"locality",
    "qs:loc":"\u042f\u0441\u0442\u0440\u0443\u0431\u0438\u0447\u0456",
    "qs:loc_alt":"Yastrubychi",
    "qs:pop":0,
    "qs:type":"buffered point",
    "wof:name":"\u042f\u0441\u0442\u0440\u0443\u0431\u0438\u0447\u0456",
    "wof:placetype":"locality"
},
  "geometry": {"coordinates":[24.340907,50.316815],"type":"Point"}
}