{
  "type": "Feature",
  "properties": {
    "gn:admin1_code":"24.0",
    "gn:asciiname":"Lukovychi",
    "gn:country_code":"UA",
    "gn:dem":204,
    "gn:feature_class":"P",
    "gn:feature_code":"PPL",
    "gn:name":"Lukovychi",
    "gn:population":0,
    "gn:timezone":"Europe/Kiev",
    "iso:country":"UA",
    "name:ukr_x_preferred":[
        "Lukovychi"
    ],
    "name:ukr_x_variant":[
        "\u041b\u0443\u043a\u043e\u0432\u0438\u0447\u0456"
    ],
    "name:und_x_variant":[
        "Lukovichi"
    ],
    "wof:name":"Lukovychi",
    "wof:placetype":"locality"
},
  "geometry": {"coordinates":[24.49011,50.7167],"type":"Point"}
}