{
  "type": "Feature",
  "properties": {
    "iso:country":"UA",
    "name:chi_x_preferred":[
        "\u4f0a\u5229\u5c3c\u9f4a\u4e9e"
    ],
    "name:dut_x_preferred":[
        "Ilnitsya"
    ],
    "name:eng_x_preferred":[
        "Ilnitsya"
    ],
    "name:epo_x_preferred":[
        "Iljnicja"
    ],
    "name:fre_x_preferred":[
        "Ilnitsya"
    ],
    "name:ger_x_preferred":[
        "Ilnyzja"
    ],
    "name:hun_x_preferred":[
        "Ilonca"
    ],
    "name:pol_x_preferred":[
        "Ilnycia"
    ],
    "name:rus_x_preferred":[
        "\u0418\u043b\u044c\u043d\u0438\u0446\u0430"
    ],
    "name:ukr_x_preferred":[
        "\u0406\u043b\u044c\u043d\u0438\u0446\u044f"
    ],
    "name:unk_x_variant":[
        "Il\u2019nitsa"
    ],
    "qs:a0":"\u0423\u043a\u0440\u0430\u0457\u043d\u0430",
    "qs:a1":"*\u0417\u0430\u043a\u0430\u0440\u043f\u0430\u0442\u0441\u044c\u043a\u0430",
    "qs:a1_alt":"Zakarpats'ka",
    "qs:a1r":"0",
    "qs:a2":"\u0406\u0440\u0448\u0430\u0432\u0441\u044c\u043a\u0438\u0439",
    "qs:a2_alt":"Irshavs'kyi",
    "qs:adm0":"\u0423\u043a\u0440\u0430\u0457\u043d\u0430",
    "qs:la_lc":"*",
    "qs:level":"locality",
    "qs:loc":"\u0406\u043b\u044c\u043d\u0438\u0446\u044f",
    "qs:loc_alt":"Il'nytsia",
    "qs:pop":0,
    "qs:type":"buffered point",
    "wd:wordcount":20505,
    "wof:name":"\u0406\u043b\u044c\u043d\u0438\u0446\u044f",
    "wof:placetype":"locality"
},
  "geometry": {"coordinates":[23.08593,48.347413],"type":"Point"}
}