{
  "type": "Feature",
  "properties": {
    "gn:admin1_code":"26.0",
    "gn:asciiname":"Kosivtseva Vtoraya",
    "gn:country_code":"UA",
    "gn:dem":88,
    "gn:feature_class":"P",
    "gn:feature_code":"PPL",
    "gn:name":"Kosivtseva Vtoraya",
    "gn:population":0,
    "gn:timezone":"Europe/Kiev",
    "iso:country":"UA",
    "name:und_x_variant":[
        "Rozyanka",
        "Kosivtseva Vtoraya"
    ],
    "wof:name":"Kosivtseva Vtoraya",
    "wof:placetype":"locality"
},
  "geometry": {"coordinates":[36.18333,47.85],"type":"Point"}
}