{
  "type": "Feature",
  "properties": {
    "gn:admin1_code":"10.0",
    "gn:asciiname":"Rozdollya",
    "gn:country_code":"UA",
    "gn:dem":167,
    "gn:feature_class":"P",
    "gn:feature_code":"PPL",
    "gn:name":"Rozdollya",
    "gn:population":0,
    "gn:timezone":"Europe/Kiev",
    "iso:country":"UA",
    "name:ukr_x_preferred":[
        "Rozdollya"
    ],
    "name:ukr_x_variant":[
        "\u0420\u043e\u0437\u0434\u043e\u043b\u043b\u044f"
    ],
    "wof:name":"Rozdollya",
    "wof:placetype":"locality"
},
  "geometry": {"coordinates":[32.22418,48.73307],"type":"Point"}
}