{
  "type": "Feature",
  "properties": {
    "gn:admin1_code":"26.0",
    "gn:asciiname":"Dniprovi Khvyli",
    "gn:country_code":"UA",
    "gn:dem":134,
    "gn:feature_class":"P",
    "gn:feature_code":"PPL",
    "gn:name":"Dniprovi Khvyli",
    "gn:population":0,
    "gn:timezone":"Europe/Zaporozhye",
    "iso:country":"UA",
    "name:ukr_x_preferred":[
        "Dniprovi Khvyli"
    ],
    "name:ukr_x_variant":[
        "\u0414\u043d\u0456\u043f\u0440\u043e\u0432\u0456 \u0425\u0432\u0438\u043b\u0456"
    ],
    "wof:name":"Dniprovi Khvyli",
    "wof:placetype":"locality"
},
  "geometry": {"coordinates":[34.94339,48.05933],"type":"Point"}
}