{
  "type": "Feature",
  "properties": {
    "gn:admin1_code":"11.0",
    "gn:admin2_code":"712585",
    "gn:admin3_code":"11152843.0",
    "gn:asciiname":"Kizilovka",
    "gn:country_code":"UA",
    "gn:dem":412,
    "gn:elevation":"404.0",
    "gn:feature_class":"P",
    "gn:feature_code":"PPL",
    "gn:name":"Kizilovka",
    "gn:population":76,
    "gn:timezone":"Europe/Simferopol",
    "iso:country":"UA",
    "name:crh_x_historical":[
        "\u011eemrik"
    ],
    "name:crh_x_preferred":[
        "\u011eemrik"
    ],
    "name:eng_x_preferred":[
        "Kizilovka"
    ],
    "name:rus_x_preferred":[
        "\u041a\u0438\u0437\u0438\u043b\u043e\u0432\u043a\u0430"
    ],
    "name:ukr_x_preferred":[
        "\u041a\u0438\u0437\u0438\u043b\u0456\u0432\u043a\u0430"
    ],
    "wof:name":"Kizilovka",
    "wof:placetype":"locality",
    "wof:population":76
},
  "geometry": {"coordinates":[34.67739,45.00165],"type":"Point"}
}