{
  "type": "Feature",
  "properties": {
    "gn:admin1_code":"5.0",
    "gn:asciiname":"Rivne",
    "gn:country_code":"UA",
    "gn:dem":191,
    "gn:feature_class":"P",
    "gn:feature_code":"PPL",
    "gn:name":"Rivne",
    "gn:population":0,
    "gn:timezone":"Europe/Kiev",
    "iso:country":"UA",
    "name:ukr_x_preferred":[
        "Rivne"
    ],
    "name:ukr_x_variant":[
        "\u0420\u0456\u0432\u043d\u0435"
    ],
    "wof:name":"Rivne",
    "wof:placetype":"locality"
},
  "geometry": {"coordinates":[37.22043,48.29888],"type":"Point"}
}