{
  "type": "Feature",
  "properties": {
    "gn:admin1_code":"21.0",
    "gn:asciiname":"Kholodnyk",
    "gn:country_code":"UA",
    "gn:dem":162,
    "gn:feature_class":"P",
    "gn:feature_code":"PPL",
    "gn:name":"Kholodnyk",
    "gn:population":0,
    "gn:timezone":"Europe/Kiev",
    "iso:country":"UA",
    "name:ukr_x_preferred":[
        "Kholodnyk"
    ],
    "name:ukr_x_variant":[
        "\u0425\u043e\u043b\u043e\u0434\u043d\u0438\u043a"
    ],
    "name:und_x_variant":[
        "Kholodnik"
    ],
    "wof:name":"Kholodnyk",
    "wof:placetype":"locality"
},
  "geometry": {"coordinates":[33.56741,50.533],"type":"Point"}
}