{
  "type": "Feature",
  "properties": {
    "gn:admin1_code":"22.0",
    "gn:asciiname":"Zarud'ye",
    "gn:country_code":"UA",
    "gn:dem":351,
    "gn:feature_class":"P",
    "gn:feature_code":"PPL",
    "gn:name":"Zarud\u2019ye",
    "gn:population":0,
    "gn:timezone":"Europe/Kiev",
    "iso:country":"UA",
    "name:und_x_variant":[
        "Zaruddya",
        "Zarudtsy",
        "Zarudze",
        "Zarudzie",
        "Zarud\u2019ye"
    ],
    "wof:name":"Zarud'ye",
    "wof:placetype":"locality"
},
  "geometry": {"coordinates":[25.06097,49.65776],"type":"Point"}
}