{
  "type": "Feature",
  "properties": {
    "gn:admin1_code":"7.0",
    "gn:asciiname":"Hrushuvakha",
    "gn:country_code":"UA",
    "gn:dem":74,
    "gn:feature_class":"P",
    "gn:feature_code":"PPL",
    "gn:name":"Hrushuvakha",
    "gn:population":0,
    "gn:timezone":"Europe/Kiev",
    "iso:country":"UA",
    "name:eng_x_preferred":[
        "Grushevakha"
    ],
    "name:rus_x_preferred":[
        "\u0413\u0440\u0443\u0448\u0435\u0432\u0430\u0445\u0430"
    ],
    "name:ukr_x_preferred":[
        "Hrushuvakha"
    ],
    "name:ukr_x_variant":[
        "\u0413\u0440\u0443\u0448\u0443\u0432\u0430\u0445\u0430"
    ],
    "wof:name":"Hrushuvakha",
    "wof:placetype":"locality"
},
  "geometry": {"coordinates":[36.89868,49.11517],"type":"Point"}
}