{
  "type": "Feature",
  "properties": {
    "gn:admin1_code":"24.0",
    "gn:asciiname":"Mlynove",
    "gn:country_code":"UA",
    "gn:dem":151,
    "gn:feature_class":"P",
    "gn:feature_code":"PPL",
    "gn:name":"Mlynove",
    "gn:population":0,
    "gn:timezone":"Europe/Kiev",
    "iso:country":"UA",
    "name:ukr_x_preferred":[
        "Mlynove"
    ],
    "name:ukr_x_variant":[
        "\u041c\u043b\u0438\u043d\u043e\u0432\u0435"
    ],
    "name:und_x_variant":[
        "Mlynovo"
    ],
    "wof:name":"Mlynove",
    "wof:placetype":"locality"
},
  "geometry": {"coordinates":[24.37929,51.84847],"type":"Point"}
}