{
  "type": "Feature",
  "properties": {
    "gn:admin1_code":"7.0",
    "gn:asciiname":"Kauchuk",
    "gn:country_code":"UA",
    "gn:dem":184,
    "gn:feature_class":"P",
    "gn:feature_code":"PPL",
    "gn:name":"Kauchuk",
    "gn:population":0,
    "gn:timezone":"Europe/Kiev",
    "iso:country":"UA",
    "name:msa_x_preferred":[
        "Kauchuk"
    ],
    "wof:name":"Kauchuk",
    "wof:placetype":"locality"
},
  "geometry": {"coordinates":[37.54889,49.94972],"type":"Point"}
}