{
  "type": "Feature",
  "properties": {
    "gn:admin1_code":"19.0",
    "gn:asciiname":"Dubchytsi",
    "gn:country_code":"UA",
    "gn:dem":138,
    "gn:feature_class":"P",
    "gn:feature_code":"PPL",
    "gn:name":"Dubchytsi",
    "gn:population":0,
    "gn:timezone":"Europe/Kiev",
    "iso:country":"UA",
    "name:ukr_x_preferred":[
        "Dubchytsi"
    ],
    "name:ukr_x_variant":[
        "\u0414\u0443\u0431\u0447\u0438\u0446\u0456"
    ],
    "name:und_x_variant":[
        "Dubchitsy"
    ],
    "wof:name":"Dubchytsi",
    "wof:placetype":"locality"
},
  "geometry": {"coordinates":[25.87522,51.89072],"type":"Point"}
}