{
  "type": "Feature",
  "properties": {
    "gn:gn_country":"UA",
    "gn:gn_fcode":"PPL",
    "gn:gn_pop":469,
    "gn:population":469,
    "iso:country":"UA",
    "name:arm_x_preferred":[
        "\u053f\u0565\u0580\u0561\u0574\u056b\u056f"
    ],
    "name:chi_x_preferred":[
        "\u514b\u62c9\u7c73\u514b"
    ],
    "name:cze_x_preferred":[
        "Keramik"
    ],
    "name:eng_x_preferred":[
        "Keramik"
    ],
    "name:ger_x_preferred":[
        "Keramik"
    ],
    "name:lav_x_preferred":[
        "Keramika"
    ],
    "name:rus_x_preferred":[
        "\u041a\u0435\u0440\u0430\u043c\u0438\u043a"
    ],
    "name:rus_x_variant":[
        "\u041a\u0435\u0440\u0430\u043c\u0456\u043a"
    ],
    "name:ukr_x_preferred":[
        "\u041a\u0435\u0440\u0430\u043c\u0456\u043a"
    ],
    "qs_pg:aaroncc":"UA",
    "qs_pg:gn_country":"UA",
    "qs_pg:gn_fcode":"PPL",
    "qs_pg:gn_pop":469,
    "qs_pg:name":"Keramik",
    "qs_pg:photos_9r":0,
    "qs_pg:photos_sr":0,
    "qs_pg:pop_sr":2,
    "qs_pg:qs_pg_placetype":"locality",
    "wof:name":"Keramik",
    "wof:placetype":"locality",
    "wof:population":469
},
  "geometry": {"coordinates":[37.68157,48.25303],"type":"Point"}
}