{
  "type": "Feature",
  "properties": {
    "gn:admin1_code":"2.0",
    "gn:asciiname":"Levkovychi",
    "gn:country_code":"UA",
    "gn:dem":148,
    "gn:feature_class":"P",
    "gn:feature_code":"PPL",
    "gn:name":"Levkovychi",
    "gn:population":0,
    "gn:timezone":"Europe/Kiev",
    "iso:country":"UA",
    "name:ukr_x_preferred":[
        "Levkovychi"
    ],
    "name:ukr_x_variant":[
        "\u041b\u0435\u0432\u043a\u043e\u0432\u0438\u0447\u0456"
    ],
    "name:und_x_variant":[
        "Levkovichi"
    ],
    "wof:name":"Levkovychi",
    "wof:placetype":"locality"
},
  "geometry": {"coordinates":[31.08616,51.49253],"type":"Point"}
}