{
  "type": "Feature",
  "properties": {
    "gn:admin1_code":"18.0",
    "gn:asciiname":"Svitlivshchyna",
    "gn:country_code":"UA",
    "gn:dem":94,
    "gn:feature_class":"P",
    "gn:feature_code":"PPL",
    "gn:name":"Svitlivshchyna",
    "gn:population":0,
    "gn:timezone":"Europe/Kiev",
    "iso:country":"UA",
    "name:ukr_x_preferred":[
        "Svitlivshchyna"
    ],
    "name:ukr_x_variant":[
        "\u0421\u0432\u0456\u0442\u043b\u0456\u0432\u0449\u0438\u043d\u0430"
    ],
    "wof:name":"Svitlivshchyna",
    "wof:placetype":"locality"
},
  "geometry": {"coordinates":[34.55141,49.20267],"type":"Point"}
}