{
  "type": "Feature",
  "properties": {
    "gn:admin1_code":"6.0",
    "gn:asciiname":"Petrashani",
    "gn:country_code":"UA",
    "gn:dem":473,
    "gn:feature_class":"P",
    "gn:feature_code":"PPL",
    "gn:name":"Petrashani",
    "gn:population":0,
    "gn:timezone":"Europe/Kiev",
    "iso:country":"UA",
    "name:und_x_variant":[
        "Petrashany",
        "Petrasheni",
        "Petrashani"
    ],
    "wof:name":"Petrashani",
    "wof:placetype":"locality"
},
  "geometry": {"coordinates":[25.07416,48.14587],"type":"Point"}
}