{
  "type": "Feature",
  "properties": {
    "gn:admin1_code":"15.0",
    "gn:asciiname":"Stara Ropa",
    "gn:country_code":"UA",
    "gn:dem":332,
    "gn:feature_class":"P",
    "gn:feature_code":"PPL",
    "gn:name":"Stara Ropa",
    "gn:population":0,
    "gn:timezone":"Europe/Kiev",
    "iso:country":"UA",
    "name:rus_x_preferred":[
        "\u0421\u0442\u0430\u0440\u0430\u044f \u0420\u043e\u043f\u0430"
    ],
    "name:ukr_x_preferred":[
        "Stara Ropa"
    ],
    "name:ukr_x_variant":[
        "\u0421\u0442\u0430\u0440\u0430 \u0420\u043e\u043f\u0430"
    ],
    "name:und_x_variant":[
        "Staraya Ropa"
    ],
    "wof:name":"Stara Ropa",
    "wof:placetype":"locality"
},
  "geometry": {"coordinates":[22.98076,49.49168],"type":"Point"}
}