{
  "type": "Feature",
  "properties": {
    "gn:admin1_code":"14.0",
    "gn:asciiname":"Berezivka",
    "gn:country_code":"UA",
    "gn:dem":133,
    "gn:feature_class":"P",
    "gn:feature_code":"PPL",
    "gn:name":"Berezivka",
    "gn:population":0,
    "gn:timezone":"Europe/Zaporozhye",
    "iso:country":"UA",
    "name:ara_x_preferred":[
        "\u0628\u064a\u0631\u064a\u0632\u064a\u0641\u0643\u0627"
    ],
    "name:bel_x_preferred":[
        "\u0411\u044d\u0440\u044d\u0437\u0456\u045e\u043a\u0430"
    ],
    "name:bul_x_preferred":[
        "\u0411\u0435\u0440\u0435\u0437\u043e\u0432\u043a\u0430"
    ],
    "name:ceb_x_preferred":[
        "Berezivka"
    ],
    "name:ces_x_preferred":[
        "Berezivka"
    ],
    "name:crh_x_preferred":[
        "Berezivka"
    ],
    "name:deu_x_preferred":[
        "Beresiwka"
    ],
    "name:fas_x_preferred":[
        "\u0628\u0631\u0632\u06cc\u0641\u06a9\u0627"
    ],
    "name:fra_x_preferred":[
        "Berezivka"
    ],
    "name:hsb_x_preferred":[
        "Bereziwka"
    ],
    "name:hye_x_preferred":[
        "\u0532\u0565\u0580\u0565\u0566\u0578\u057e\u056f\u0561"
    ],
    "name:ita_x_preferred":[
        "Berezivka"
    ],
    "name:kat_x_preferred":[
        "\u10d1\u10d4\u10e0\u10d8\u10dd\u10d6\u10dd\u10d5\u10d9\u10d0"
    ],
    "name:lit_x_preferred":[
        "Berezivka"
    ],
    "name:nno_x_preferred":[
        "Berezivka"
    ],
    "name:nor_x_preferred":[
        "Berezivka"
    ],
    "name:pol_x_preferred":[
        "Berez\u00f3wka"
    ],
    "name:ron_x_preferred":[
        "Berezivka"
    ],
    "name:rus_x_preferred":[
        "\u0411\u0435\u0440\u0435\u0437\u043e\u0432\u043a\u0430"
    ],
    "name:sah_x_preferred":[
        "\u0411\u0435\u0440\u0435\u0437\u043e\u0432\u043a\u0430"
    ],
    "name:swe_x_preferred":[
        "Berezivka"
    ],
    "name:ukr_x_preferred":[
        "Berezivka"
    ],
    "name:ukr_x_variant":[
        "\u0411\u0435\u0440\u0435\u0437\u0456\u0432\u043a\u0430"
    ],
    "name:und_x_variant":[
        "Solontsy"
    ],
    "name:vie_x_preferred":[
        "Berezivka"
    ],
    "name:zho_x_preferred":[
        "\u5225\u5217\u4f50\u592b\u5361"
    ],
    "wof:name":"Berezivka",
    "wof:placetype":"locality"
},
  "geometry": {"coordinates":[38.52444000000001,49.90583],"type":"Point"}
}