{
  "type": "Feature",
  "properties": {
    "gn:admin1_code":"14.0",
    "gn:asciiname":"Berezivka",
    "gn:country_code":"UA",
    "gn:dem":133,
    "gn:feature_class":"P",
    "gn:feature_code":"PPL",
    "gn:name":"Berezivka",
    "gn:population":0,
    "gn:timezone":"Europe/Zaporozhye",
    "iso:country":"UA",
    "name:ukr_x_preferred":[
        "Berezivka"
    ],
    "name:ukr_x_variant":[
        "\u0411\u0435\u0440\u0435\u0437\u0456\u0432\u043a\u0430"
    ],
    "name:und_x_variant":[
        "Solontsy"
    ],
    "wof:name":"Berezivka",
    "wof:placetype":"locality"
},
  "geometry": {"coordinates":[38.52444000000001,49.90583],"type":"Point"}
}