{
  "type": "Feature",
  "properties": {
    "iso:country":"UA",
    "qs:a0":"\u0423\u043a\u0440\u0430\u0457\u043d\u0430",
    "qs:a1":"*\u041c\u0438\u043a\u043e\u043b\u0430\u0457\u0432\u0441\u044c\u043a\u0430",
    "qs:a1_alt":"Mykolaivs'ka",
    "qs:a1r":"0",
    "qs:a2":"\u0411\u0430\u0448\u0442\u0430\u043d\u0441\u044c\u043a\u0438\u0439",
    "qs:a2_alt":"Bashtans'kyi",
    "qs:adm0":"\u0423\u043a\u0440\u0430\u0457\u043d\u0430",
    "qs:la_lc":"*",
    "qs:level":"locality",
    "qs:loc":"\u041f\u0440\u0438\u0432\u0456\u043b\u044c\u043d\u0435",
    "qs:loc_alt":"Pryvil'ne",
    "qs:pop":0,
    "qs:type":"buffered point",
    "wof:name":"\u041f\u0440\u0438\u0432\u0456\u043b\u044c\u043d\u0435",
    "wof:placetype":"locality"
},
  "geometry": {"coordinates":[32.289171,47.483679],"type":"Point"}
}