{
  "type": "Feature",
  "properties": {
    "gn:admin1_code":"08",
    "gn:asciiname":"Novyy Shlyakh",
    "gn:country_code":"UA",
    "gn:dem":51,
    "gn:feature_class":"P",
    "gn:feature_code":"PPL",
    "gn:name":"Novyy Shlyakh",
    "gn:population":0,
    "gn:timezone":"Europe/Kiev",
    "iso:country":"UA",
    "name:ukr_x_preferred":[
        "Novyy Shlyakh"
    ],
    "name:ukr_x_variant":[
        "\u041d\u043e\u0432\u0438\u0439 \u0428\u043b\u044f\u0445"
    ],
    "wof:name":"Novyy Shlyakh",
    "wof:placetype":"locality"
},
  "geometry": {"coordinates":[32.71321,46.99051],"type":"Point"}
}