{
  "type": "Feature",
  "properties": {
    "gn:admin1_code":"2.0",
    "gn:asciiname":"Zabolottya",
    "gn:country_code":"UA",
    "gn:dem":143,
    "gn:feature_class":"P",
    "gn:feature_code":"PPL",
    "gn:name":"Zabolottya",
    "gn:population":0,
    "gn:timezone":"Europe/Kiev",
    "iso:country":"UA",
    "name:rus_x_preferred":[
        "Zabolot\u2019ye"
    ],
    "name:ukr_x_preferred":[
        "Zabolottya"
    ],
    "name:ukr_x_variant":[
        "\u0417\u0430\u0431\u043e\u043b\u043e\u0442\u0442\u044f"
    ],
    "wof:name":"Zabolottya",
    "wof:placetype":"locality"
},
  "geometry": {"coordinates":[32.7962,50.94108],"type":"Point"}
}