{
  "type": "Feature",
  "properties": {
    "gn:admin1_code":"14.0",
    "gn:asciiname":"Sonyachne",
    "gn:country_code":"UA",
    "gn:dem":196,
    "gn:feature_class":"P",
    "gn:feature_code":"PPL",
    "gn:name":"Sonyachne",
    "gn:population":0,
    "gn:timezone":"Europe/Zaporozhye",
    "iso:country":"UA",
    "name:ukr_x_preferred":[
        "Sonyachne"
    ],
    "name:ukr_x_variant":[
        "\u0421\u043e\u043d\u044f\u0447\u043d\u0435"
    ],
    "wof:name":"Sonyachne",
    "wof:placetype":"locality"
},
  "geometry": {"coordinates":[38.92507,48.33229],"type":"Point"}
}