{
  "type": "Feature",
  "properties": {
    "gn:admin1_code":"15.0",
    "gn:asciiname":"Nakvasha",
    "gn:country_code":"UA",
    "gn:dem":289,
    "gn:feature_class":"P",
    "gn:feature_code":"PPL",
    "gn:name":"Nakvasha",
    "gn:population":0,
    "gn:timezone":"Europe/Kiev",
    "iso:country":"UA",
    "wof:name":"Nakvasha",
    "wof:placetype":"locality"
},
  "geometry": {"coordinates":[25.322,49.97254],"type":"Point"}
}