{
  "type": "Feature",
  "properties": {
    "gn:admin1_code":"15.0",
    "gn:asciiname":"Nakvasha",
    "gn:country_code":"UA",
    "gn:dem":289,
    "gn:feature_class":"P",
    "gn:feature_code":"PPL",
    "gn:name":"Nakvasha",
    "gn:population":0,
    "gn:timezone":"Europe/Kiev",
    "iso:country":"UA",
    "name:ceb_x_preferred":[
        "Nakvasha"
    ],
    "name:pol_x_preferred":[
        "Nakwasza"
    ],
    "name:ron_x_preferred":[
        "Nakva\u0219a"
    ],
    "name:rus_x_preferred":[
        "\u041d\u0430\u043a\u0432\u0430\u0448\u0430"
    ],
    "name:ukr_x_preferred":[
        "\u041d\u0430\u043a\u0432\u0430\u0448\u0430"
    ],
    "name:zho_x_preferred":[
        "\u7d0d\u514b\u74e6\u6c99"
    ],
    "wof:name":"Nakvasha",
    "wof:placetype":"locality"
},
  "geometry": {"coordinates":[25.322,49.97254],"type":"Point"}
}