{
  "type": "Feature",
  "properties": {
    "gn:admin1_code":"24.0",
    "gn:asciiname":"Torhovyshche",
    "gn:country_code":"UA",
    "gn:dem":194,
    "gn:feature_class":"P",
    "gn:feature_code":"PPL",
    "gn:name":"Torhovyshche",
    "gn:population":0,
    "gn:timezone":"Europe/Kiev",
    "iso:country":"UA",
    "name:ukr_x_preferred":[
        "Torhovyshche"
    ],
    "name:ukr_x_variant":[
        "\u0422\u043e\u0440\u0433\u043e\u0432\u0438\u0449\u0435"
    ],
    "name:und_x_variant":[
        "Turovichi",
        "Torgovyshche",
        "Targovishche",
        "Torgovishche"
    ],
    "wof:name":"Torhovyshche",
    "wof:placetype":"locality"
},
  "geometry": {"coordinates":[24.39344,51.17171],"type":"Point"}
}