{
  "type": "Feature",
  "properties": {
    "gn:admin1_code":"26.0",
    "gn:asciiname":"Klippenfel'd",
    "gn:country_code":"UA",
    "gn:dem":101,
    "gn:feature_class":"P",
    "gn:feature_code":"PPL",
    "gn:name":"Klippenfel\u2019d",
    "gn:population":0,
    "gn:timezone":"Europe/Zaporozhye",
    "iso:country":"UA",
    "wof:name":"Klippenfel'd",
    "wof:placetype":"locality"
},
  "geometry": {"coordinates":[36.06667,47.23333],"type":"Point"}
}