{
  "type": "Feature",
  "properties": {
    "gn:admin1_code":"23.0",
    "gn:asciiname":"Busha",
    "gn:country_code":"UA",
    "gn:dem":118,
    "gn:feature_class":"P",
    "gn:feature_code":"PPL",
    "gn:name":"Busha",
    "gn:population":0,
    "gn:timezone":"Europe/Kiev",
    "iso:country":"UA",
    "name:crh_x_preferred":[
        "Bu\u015fa"
    ],
    "name:deu_x_preferred":[
        "Buscha"
    ],
    "name:hye_x_preferred":[
        "\u0532\u0578\u0582\u0577\u0561"
    ],
    "name:pol_x_preferred":[
        "Busza"
    ],
    "name:ron_x_preferred":[
        "Bu\u0219a"
    ],
    "name:rus_x_preferred":[
        "\u0411\u0443\u0448\u0430"
    ],
    "name:sco_x_preferred":[
        "Busha"
    ],
    "name:ukr_x_preferred":[
        "\u0411\u0443\u0448\u0430"
    ],
    "wof:name":"Busha",
    "wof:placetype":"locality"
},
  "geometry": {"coordinates":[28.12234,48.34331],"type":"Point"}
}