{
  "type": "Feature",
  "properties": {
    "gn:admin1_code":"17.0",
    "gn:asciiname":"Selyshche Savy",
    "gn:cc2":"UA",
    "gn:country_code":"UA",
    "gn:dem":163,
    "gn:feature_class":"P",
    "gn:feature_code":"PPL",
    "gn:name":"Selyshche Savy",
    "gn:population":0,
    "gn:timezone":"Europe/Chisinau",
    "iso:country":"UA",
    "name:und_x_variant":[
        "Khutor Savvi",
        "Savvi",
        "Khutor Savvy"
    ],
    "wof:name":"Selyshche Savy",
    "wof:placetype":"locality"
},
  "geometry": {"coordinates":[29.50778,47.12361],"type":"Point"}
}