{
  "type": "Feature",
  "properties": {
    "gn:admin1_code":"14.0",
    "gn:asciiname":"Bohorodyts'ke",
    "gn:country_code":"UA",
    "gn:dem":154,
    "gn:feature_class":"P",
    "gn:feature_code":"PPL",
    "gn:name":"Bohorodyts\u2019ke",
    "gn:population":0,
    "gn:timezone":"Europe/Zaporozhye",
    "iso:country":"UA",
    "name:ukr_x_preferred":[
        "Bohorodyts\u2019ke"
    ],
    "name:ukr_x_variant":[
        "\u0411\u043e\u0433\u043e\u0440\u043e\u0434\u0438\u0446\u044c\u043a\u0435"
    ],
    "name:und_x_variant":[
        "Bogoroditskoye"
    ],
    "wof:name":"Bohorodyts'ke",
    "wof:placetype":"locality"
},
  "geometry": {"coordinates":[38.12038,49.7247],"type":"Point"}
}