{
  "type": "Feature",
  "properties": {
    "gn:admin1_code":"15.0",
    "gn:asciiname":"Ropavs'ke",
    "gn:country_code":"UA",
    "gn:dem":618,
    "gn:feature_class":"P",
    "gn:feature_code":"PPL",
    "gn:name":"Ropavs\u2019ke",
    "gn:population":0,
    "gn:timezone":"Europe/Kiev",
    "iso:country":"UA",
    "name:run_x_preferred":[
        "\u0420\u043e\u043f\u0430\u0432\u0441\u043a\u043e\u0435"
    ],
    "name:ukr_x_preferred":[
        "Ropavs\u2019ke"
    ],
    "name:ukr_x_variant":[
        "\u0420\u043e\u043f\u0430\u0432\u0441\u044c\u043a\u0435"
    ],
    "name:und_x_variant":[
        "Ropavskoye",
        "Ropavsko"
    ],
    "wof:name":"Ropavs'ke",
    "wof:placetype":"locality"
},
  "geometry": {"coordinates":[23.06774,49.07407],"type":"Point"}
}