{
  "type": "Feature",
  "properties": {
    "gn:admin1_code":"2.0",
    "gn:asciiname":"Hayvoron",
    "gn:country_code":"UA",
    "gn:dem":136,
    "gn:feature_class":"P",
    "gn:feature_code":"PPL",
    "gn:name":"Hayvoron",
    "gn:population":0,
    "gn:timezone":"Europe/Kiev",
    "iso:country":"UA",
    "name:eng_x_preferred":[
        "Gayvoron"
    ],
    "name:rus_x_preferred":[
        "\u0413\u0430\u0439\u0432\u043e\u0440\u043e\u043d"
    ],
    "name:ukr_x_preferred":[
        "Hayvoron"
    ],
    "name:ukr_x_variant":[
        "\u0413\u0430\u0439\u0432\u043e\u0440\u043e\u043d"
    ],
    "name:und_x_variant":[
        "Gayvoron"
    ],
    "wof:name":"Hayvoron",
    "wof:placetype":"locality"
},
  "geometry": {"coordinates":[32.92078,50.98478],"type":"Point"}
}