{
  "type": "Feature",
  "properties": {
    "iso:country":"UA",
    "name:che_x_preferred":[
        "\u041e\u043a\u043d\u043e"
    ],
    "name:eng_x_preferred":[
        "Vikno"
    ],
    "name:fin_x_preferred":[
        "V\u0456kn\u043e"
    ],
    "name:nan_x_preferred":[
        "Vikno"
    ],
    "name:nno_x_preferred":[
        "Vikno"
    ],
    "name:nob_x_preferred":[
        "Vikno"
    ],
    "name:pol_x_preferred":[
        "Okno"
    ],
    "name:ron_x_preferred":[
        "Vikno"
    ],
    "name:rus_x_preferred":[
        "\u041e\u043a\u043d\u043e"
    ],
    "name:ukr_x_preferred":[
        "\u0412\u0456\u043a\u043d\u043e"
    ],
    "name:zho_x_preferred":[
        "\u7dad\u514b\u8afe"
    ],
    "qs:a0":"\u0423\u043a\u0440\u0430\u0457\u043d\u0430",
    "qs:a1":"*\u0406\u0432\u0430\u043d\u043e-\u0424\u0440\u0430\u043d\u043a\u0456\u0432\u0441\u044c\u043a\u0430",
    "qs:a1_alt":"Ivano-Frankivs'ka",
    "qs:a1r":"0",
    "qs:a2":"\u0413\u043e\u0440\u043e\u0434\u0435\u043d\u043a\u0456\u0432\u0441\u044c\u043a\u0438\u0439",
    "qs:a2_alt":"Horodenkivs'kyi",
    "qs:adm0":"\u0423\u043a\u0440\u0430\u0457\u043d\u0430",
    "qs:la_lc":"*",
    "qs:level":"locality",
    "qs:loc":"\u0412\u0456\u043a\u043d\u043e",
    "qs:loc_alt":"Vikno",
    "qs:pop":0,
    "qs:type":"buffered point",
    "wd:wordcount":82,
    "wof:name":"\u0412\u0456\u043a\u043d\u043e",
    "wof:placetype":"locality"
},
  "geometry": {"coordinates":[25.369728,48.66685],"type":"Point"}
}