{
  "type": "Feature",
  "properties": {
    "iso:country":"UA",
    "qs:a0":"\u0423\u043a\u0440\u0430\u0457\u043d\u0430",
    "qs:a1":"*\u0414\u043d\u0456\u043f\u0440\u043e\u043f\u0435\u0442\u0440\u043e\u0432\u0441\u044c\u043a\u0430",
    "qs:a1_alt":"Dnipropetrovs'ka",
    "qs:a1r":"0",
    "qs:a2":"\u042e\u0440'\u0457\u0432\u0441\u044c\u043a\u0438\u0439",
    "qs:a2_alt":"Yuryivs'kyi",
    "qs:adm0":"\u0423\u043a\u0440\u0430\u0457\u043d\u0430",
    "qs:la_lc":"*",
    "qs:level":"locality",
    "qs:loc":"\u041d\u043e\u0432\u043e\u0432'\u044f\u0437\u0456\u0432\u0441\u044c\u043a\u0435",
    "qs:loc_alt":"Novoviazivs'ke",
    "qs:pop":0,
    "qs:type":"buffered point",
    "wof:name":"\u041d\u043e\u0432\u043e\u0432'\u044f\u0437\u0456\u0432\u0441\u044c\u043a\u0435",
    "wof:placetype":"locality"
},
  "geometry": {"coordinates":[35.829165,48.750054],"type":"Point"}
}