{
  "type": "Feature",
  "properties": {
    "iso:country":"UA",
    "name:chi_x_preferred":[
        "\u5225\u723e\u6d1b\u5409"
    ],
    "name:eng_x_preferred":[
        "Berlohy"
    ],
    "name:ron_x_preferred":[
        "Berloh\u00ee"
    ],
    "name:rum_x_preferred":[
        "Berloh\u00ee"
    ],
    "name:rus_x_preferred":[
        "\u0411\u0435\u0440\u043b\u043e\u0433\u0438"
    ],
    "name:ukr_x_preferred":[
        "\u0411\u0435\u0440\u043b\u043e\u0433\u0438"
    ],
    "name:ukr_x_variant":[
        "Berlohy"
    ],
    "name:unk_x_variant":[
        "Berloby"
    ],
    "qs:a0":"\u0423\u043a\u0440\u0430\u0457\u043d\u0430",
    "qs:a1":"*\u0406\u0432\u0430\u043d\u043e-\u0424\u0440\u0430\u043d\u043a\u0456\u0432\u0441\u044c\u043a\u0430",
    "qs:a1_alt":"Ivano-Frankivs'ka",
    "qs:a1r":"0",
    "qs:a2":"\u0420\u043e\u0436\u043d\u044f\u0442\u0456\u0432\u0441\u044c\u043a\u0438\u0439",
    "qs:a2_alt":"Rozhniativs'kyi",
    "qs:adm0":"\u0423\u043a\u0440\u0430\u0457\u043d\u0430",
    "qs:la_lc":"*",
    "qs:level":"locality",
    "qs:loc":"\u0411\u0435\u0440\u043b\u043e\u0433\u0438",
    "qs:loc_alt":"Berlohy",
    "qs:pop":0,
    "qs:type":"buffered point",
    "wd:wordcount":159,
    "wof:name":"\u0411\u0435\u0440\u043b\u043e\u0433\u0438",
    "wof:placetype":"locality"
},
  "geometry": {"coordinates":[24.247194,48.961384],"type":"Point"}
}