{
  "type": "Feature",
  "properties": {
    "gn:admin1_code":"13.0",
    "gn:asciiname":"Ovdiyeva Nyva",
    "gn:country_code":"UA",
    "gn:dem":124,
    "gn:feature_class":"P",
    "gn:feature_code":"PPL",
    "gn:name":"Ovdiyeva Nyva",
    "gn:population":0,
    "gn:timezone":"Europe/Kiev",
    "iso:country":"UA",
    "name:ukr_x_preferred":[
        "Ovdiyeva Nyva"
    ],
    "name:ukr_x_variant":[
        "\u041e\u0432\u0434\u0456\u0454\u0432\u0430 \u041d\u0438\u0432\u0430"
    ],
    "name:und_x_variant":[
        "Avdeyeva Hiva"
    ],
    "wof:name":"Ovdiyeva Nyva",
    "wof:placetype":"locality"
},
  "geometry": {"coordinates":[30.23377,50.97],"type":"Point"}
}