{
  "type": "Feature",
  "properties": {
    "gn:admin1_code":"06",
    "gn:asciiname":"Ivankova",
    "gn:country_code":"UA",
    "gn:dem":284,
    "gn:feature_class":"P",
    "gn:feature_code":"PPL",
    "gn:name":"Ivankova",
    "gn:population":0,
    "gn:timezone":"Europe/Kiev",
    "iso:country":"UA",
    "name:ukr_x_preferred":[
        "Ivankova"
    ],
    "name:ukr_x_variant":[
        "\u0406\u0432\u0430\u043d\u043a\u043e\u0432\u0430"
    ],
    "wof:name":"Ivankova",
    "wof:placetype":"locality"
},
  "geometry": {"coordinates":[24.31164,49.11217],"type":"Point"}
}