{
  "type": "Feature",
  "properties": {
    "iso:country":"UA",
    "name:bel_x_preferred":[
        "\u0411\u0430\u0448\u0442\u0430\u043d\u043a\u0456\u045e"
    ],
    "name:ces_x_preferred":[
        "Ba\u0161tankiv"
    ],
    "name:che_x_preferred":[
        "\u0411\u0430\u0448\u0442\u0430\u043d\u043a\u043e\u0432"
    ],
    "name:crh_x_preferred":[
        "Ba\u015ftankiv"
    ],
    "name:deu_x_preferred":[
        "Baschtankiw"
    ],
    "name:eng_x_preferred":[
        "Bashtankiv"
    ],
    "name:fin_x_preferred":[
        "B\u0430\u0161t\u0430nk\u0456v"
    ],
    "name:lav_x_preferred":[
        "Ba\u0161tankiva"
    ],
    "name:nan_x_preferred":[
        "Bashtankiv"
    ],
    "name:nno_x_preferred":[
        "Basjtankiv"
    ],
    "name:nob_x_preferred":[
        "Basjtankiv"
    ],
    "name:pol_x_preferred":[
        "Basztank\u00f3w"
    ],
    "name:ron_x_preferred":[
        "Ba\u0219tankiv"
    ],
    "name:rus_x_preferred":[
        "\u0411\u0430\u0448\u0442\u0430\u043d\u043a\u043e\u0432"
    ],
    "name:spa_x_preferred":[
        "Bashtanka"
    ],
    "name:ukr_x_preferred":[
        "\u0411\u0430\u0448\u0442\u0430\u043d\u043a\u0456\u0432"
    ],
    "name:und_x_variant":[
        "Bashtankovo"
    ],
    "name:zho_x_preferred":[
        "\u5df4\u4ec0\u5766\u57fa\u592b"
    ],
    "qs:a0":"\u0423\u043a\u0440\u0430\u0457\u043d\u0430",
    "qs:a1":"*\u041e\u0434\u0435\u0441\u044c\u043a\u0430",
    "qs:a1_alt":"Odes'ka",
    "qs:a1r":"0",
    "qs:a2":"\u041a\u043e\u0434\u0438\u043c\u0441\u044c\u043a\u0438\u0439",
    "qs:a2_alt":"Kodyms'kyi",
    "qs:adm0":"\u0423\u043a\u0440\u0430\u0457\u043d\u0430",
    "qs:la_lc":"*",
    "qs:level":"locality",
    "qs:loc":"\u0411\u0430\u0448\u0442\u0430\u043d\u043a\u0456\u0432",
    "qs:loc_alt":"Bashtankiv",
    "qs:pop":0,
    "qs:type":"buffered point",
    "wof:name":"\u0411\u0430\u0448\u0442\u0430\u043d\u043a\u0456\u0432",
    "wof:placetype":"locality"
},
  "geometry": {"coordinates":[29.001302,48.11098],"type":"Point"}
}