{
  "type": "Feature",
  "properties": {
    "gn:admin1_code":"6.0",
    "gn:asciiname":"Sloboda-Bolekhivs'ka",
    "gn:country_code":"UA",
    "gn:dem":525,
    "gn:feature_class":"P",
    "gn:feature_code":"PPL",
    "gn:name":"Sloboda-Bolekhivs\u2019ka",
    "gn:population":0,
    "gn:timezone":"Europe/Kiev",
    "iso:country":"UA",
    "name:ukr_x_preferred":[
        "\u0421\u043b\u043e\u0431\u043e\u0434\u0430-\u0411\u043e\u043b\u0435\u0445\u0456\u0432\u0441\u044c\u043a\u0430"
    ],
    "name:und_x_variant":[
        "Sloboda-Bolekhivs\u2019ka",
        "Sloboda-Bolekhovskaya"
    ],
    "wof:name":"Sloboda-Bolekhivs'ka",
    "wof:placetype":"locality"
},
  "geometry": {"coordinates":[23.73832,48.97533],"type":"Point"}
}