{
  "type": "Feature",
  "properties": {
    "gn:admin1_code":"18.0",
    "gn:asciiname":"Perevalovka",
    "gn:cc2":"UA",
    "gn:country_code":"UA",
    "gn:dem":145,
    "gn:feature_class":"P",
    "gn:feature_code":"PPL",
    "gn:name":"Perevalovka",
    "gn:population":0,
    "gn:timezone":"Europe/Kiev",
    "iso:country":"UA",
    "name:und_x_variant":[
        "Perevalivka",
        "Perevalovka"
    ],
    "wof:name":"Perevalovka",
    "wof:placetype":"locality"
},
  "geometry": {"coordinates":[33.41667,50.18333],"type":"Point"}
}