{
  "type": "Feature",
  "properties": {
    "iso:country":"UA",
    "name:nld_x_preferred":[
        "Czerce"
    ],
    "name:pol_x_preferred":[
        "Czerce"
    ],
    "name:ukr_x_preferred":[
        "\u0427\u0435\u0440\u0447\u0435"
    ],
    "name:ukr_x_variant":[
        "Cherche"
    ],
    "name:und_x_variant":[
        "Czorcze"
    ],
    "name:zho_min_nan_x_preferred":[
        "Czerce"
    ],
    "qs:a0":"\u0423\u043a\u0440\u0430\u0457\u043d\u0430",
    "qs:a1":"*\u0412\u043e\u043b\u0438\u043d\u0441\u044c\u043a\u0430",
    "qs:a1_alt":"Volyns'ka",
    "qs:a1r":"0",
    "qs:a2":"\u041a\u0430\u043c\u0456\u043d\u044c-\u041a\u0430\u0448\u0438\u0440\u0441\u044c\u043a\u0438\u0439",
    "qs:a2_alt":"Kamin'-Kashyrs'kyi",
    "qs:adm0":"\u0423\u043a\u0440\u0430\u0457\u043d\u0430",
    "qs:la_lc":"*",
    "qs:level":"locality",
    "qs:loc":"\u0427\u0435\u0440\u0447\u0435",
    "qs:loc_alt":"Cherche",
    "qs:pop":0,
    "qs:type":"buffered point",
    "wd:wordcount":95,
    "wof:name":"\u0427\u0435\u0440\u0447\u0435",
    "wof:placetype":"locality"
},
  "geometry": {"coordinates":[24.880368,51.740301],"type":"Point"}
}