{
  "type": "Feature",
  "properties": {
    "gn:admin1_code":"15",
    "gn:asciiname":"Pidhirtsi",
    "gn:country_code":"UA",
    "gn:dem":247,
    "gn:feature_class":"P",
    "gn:feature_code":"PPL",
    "gn:name":"Pidhirtsi",
    "gn:population":0,
    "gn:timezone":"Europe/Kiev",
    "iso:country":"UA",
    "name:bel_x_preferred":[
        "\u041f\u0430\u0434\u0433\u043e\u0440\u0446\u044b"
    ],
    "name:ceb_x_preferred":[
        "Podgortsy"
    ],
    "name:deu_x_preferred":[
        "Pidhirzi"
    ],
    "name:ita_x_preferred":[
        "Pidhirci"
    ],
    "name:pol_x_preferred":[
        "Podhorce"
    ],
    "name:ron_x_preferred":[
        "Pidhir\u021bi"
    ],
    "name:rus_x_preferred":[
        "\u041f\u043e\u0434\u0433\u043e\u0440\u0446\u044b"
    ],
    "name:ukr_x_preferred":[
        "Pidhirtsi"
    ],
    "name:ukr_x_variant":[
        "\u041f\u0456\u0434\u0433\u0456\u0440\u0446\u0456"
    ],
    "name:und_x_variant":[
        "Podgortsy"
    ],
    "name:zho_x_preferred":[
        "\u76ae\u5fb7\u5409\u723e\u9f4a"
    ],
    "wof:name":"Pidhirtsi",
    "wof:placetype":"locality"
},
  "geometry": {"coordinates":[24.15142,49.4426],"type":"Point"}
}