{
  "type": "Feature",
  "properties": {
    "iso:country":"UA",
    "qs:a0":"\u0423\u043a\u0440\u0430\u0457\u043d\u0430",
    "qs:a1":"*\u0425\u0435\u0440\u0441\u043e\u043d\u0441\u044c\u043a\u0430",
    "qs:a1_alt":"Khersons'ka",
    "qs:a1r":"0",
    "qs:a2":"\u0411\u0456\u043b\u043e\u0437\u0435\u0440\u0441\u044c\u043a\u0438\u0439",
    "qs:a2_alt":"Bilozers'kyi",
    "qs:adm0":"\u0423\u043a\u0440\u0430\u0457\u043d\u0430",
    "qs:la_lc":"*",
    "qs:level":"locality",
    "qs:loc":"\u041c\u043e\u043b\u043e\u0434\u0456\u0436\u043d\u0435",
    "qs:loc_alt":"Molodizhne",
    "qs:pop":0,
    "qs:type":"buffered point",
    "wd:wordcount":551,
    "wof:name":"\u041c\u043e\u043b\u043e\u0434\u0456\u0436\u043d\u0435",
    "wof:placetype":"locality"
},
  "geometry": {"coordinates":[32.691765,46.728706],"type":"Point"}
}