{
  "type": "Feature",
  "properties": {
    "gn:admin1_code":"5.0",
    "gn:asciiname":"Alekseyevskiy",
    "gn:country_code":"UA",
    "gn:dem":59,
    "gn:feature_class":"P",
    "gn:feature_code":"PPL",
    "gn:name":"Alekseyevskiy",
    "gn:population":0,
    "gn:timezone":"Europe/Kiev",
    "iso:country":"UA",
    "name:und_x_variant":[
        "Khutor Dolinskiy",
        "Khutor Alekseyevskiy",
        "Alekseyevskiy"
    ],
    "wof:name":"Alekseyevskiy",
    "wof:placetype":"locality"
},
  "geometry": {"coordinates":[37.76667,47.11667],"type":"Point"}
}