{
  "type": "Feature",
  "properties": {
    "gn:admin1_code":"9.0",
    "gn:asciiname":"Smorshki",
    "gn:country_code":"UA",
    "gn:dem":287,
    "gn:feature_class":"P",
    "gn:feature_code":"PPL",
    "gn:name":"Smorshki",
    "gn:population":0,
    "gn:timezone":"Europe/Kiev",
    "iso:country":"UA",
    "wof:name":"Smorshki",
    "wof:placetype":"locality"
},
  "geometry": {"coordinates":[26.69154,49.90988],"type":"Point"}
}