{
  "type": "Feature",
  "properties": {
    "gn:admin1_code":"2.0",
    "gn:asciiname":"Olbyn",
    "gn:country_code":"UA",
    "gn:dem":110,
    "gn:feature_class":"P",
    "gn:feature_code":"PPL",
    "gn:name":"Olbyn",
    "gn:population":0,
    "gn:timezone":"Europe/Kiev",
    "iso:country":"UA",
    "name:ukr_x_preferred":[
        "Olbyn"
    ],
    "name:ukr_x_variant":[
        "\u041e\u043b\u0431\u0438\u043d"
    ],
    "name:und_x_variant":[
        "Olbin\u2019",
        "Olbin"
    ],
    "wof:name":"Olbyn",
    "wof:placetype":"locality"
},
  "geometry": {"coordinates":[31.02998,51.07614],"type":"Point"}
}