{
  "type": "Feature",
  "properties": {
    "gn:admin1_code":"9.0",
    "gn:asciiname":"Andreyevka",
    "gn:country_code":"UA",
    "gn:dem":295,
    "gn:feature_class":"P",
    "gn:feature_code":"PPL",
    "gn:name":"Andreyevka",
    "gn:population":0,
    "gn:timezone":"Europe/Kiev",
    "iso:country":"UA",
    "name:und_x_variant":[
        "Kum Yuridinka",
        "Andreyevka"
    ],
    "wof:name":"Andreyevka",
    "wof:placetype":"locality"
},
  "geometry": {"coordinates":[26.42262,49.3558],"type":"Point"}
}