{
  "type": "Feature",
  "properties": {
    "gn:admin1_code":"21.0",
    "gn:asciiname":"Yanchenky",
    "gn:country_code":"UA",
    "gn:dem":153,
    "gn:feature_class":"P",
    "gn:feature_code":"PPL",
    "gn:name":"Yanchenky",
    "gn:population":0,
    "gn:timezone":"Europe/Kiev",
    "iso:country":"UA",
    "name:ukr_x_preferred":[
        "Yanchenky"
    ],
    "name:ukr_x_variant":[
        "\u042f\u043d\u0447\u0435\u043d\u043a\u0438"
    ],
    "name:und_x_variant":[
        "Yanchenkov",
        "Yanchenki"
    ],
    "wof:name":"Yanchenky",
    "wof:placetype":"locality"
},
  "geometry": {"coordinates":[34.26324,51.10907],"type":"Point"}
}