{
  "type": "Feature",
  "properties": {
    "gn:admin1_code":"21.0",
    "gn:asciiname":"Hor'kove",
    "gn:country_code":"UA",
    "gn:dem":178,
    "gn:feature_class":"P",
    "gn:feature_code":"PPL",
    "gn:name":"Hor\u2019kove",
    "gn:population":0,
    "gn:timezone":"Europe/Kiev",
    "iso:country":"UA",
    "name:rus_x_preferred":[
        "Gor\u2019khovo"
    ],
    "name:ukr_x_preferred":[
        "Hor\u2019kove"
    ],
    "name:ukr_x_variant":[
        "\u0413\u043e\u0440\u044c\u043a\u043e\u0432\u0435"
    ],
    "wof:name":"Hor'kove",
    "wof:placetype":"locality"
},
  "geometry": {"coordinates":[33.99941,50.72156],"type":"Point"}
}