{
  "type": "Feature",
  "properties": {
    "gn:admin1_code":"4.0",
    "gn:asciiname":"Surs'ke",
    "gn:country_code":"UA",
    "gn:dem":69,
    "gn:feature_class":"P",
    "gn:feature_code":"PPL",
    "gn:name":"Surs\u2019ke",
    "gn:population":0,
    "gn:timezone":"Europe/Kiev",
    "iso:country":"UA",
    "name:ukr_x_preferred":[
        "Surs\u2019ke"
    ],
    "name:ukr_x_variant":[
        "\u0421\u0443\u0440\u0441\u044c\u043a\u0435"
    ],
    "wof:name":"Surs'ke",
    "wof:placetype":"locality"
},
  "geometry": {"coordinates":[34.59455,48.31],"type":"Point"}
}