{
  "type": "Feature",
  "properties": {
    "gn:admin1_code":"18.0",
    "gn:asciiname":"Lutsenky",
    "gn:country_code":"UA",
    "gn:dem":132,
    "gn:feature_class":"P",
    "gn:feature_code":"PPL",
    "gn:name":"Lutsenky",
    "gn:population":0,
    "gn:timezone":"Europe/Kiev",
    "iso:country":"UA",
    "name:eng_x_preferred":[
        "Lutsenki"
    ],
    "name:rus_x_preferred":[
        "\u041b\u0443\u0446\u0435\u043d\u043a\u0438"
    ],
    "name:ukr_x_preferred":[
        "Lutsenky"
    ],
    "name:ukr_x_variant":[
        "\u041b\u0443\u0446\u0435\u043d\u043a\u0438"
    ],
    "name:und_x_variant":[
        "Zhabki",
        "Lutsenki"
    ],
    "wof:name":"Lutsenky",
    "wof:placetype":"locality"
},
  "geometry": {"coordinates":[33.06653,50.4434],"type":"Point"}
}