{
  "type": "Feature",
  "properties": {
    "gn:admin1_code":"15.0",
    "gn:asciiname":"Zubeyki",
    "gn:country_code":"UA",
    "gn:dem":242,
    "gn:feature_class":"P",
    "gn:feature_code":"PPL",
    "gn:name":"Zubeyki",
    "gn:population":0,
    "gn:timezone":"Europe/Kiev",
    "iso:country":"UA",
    "name:und_x_variant":[
        "Zubejki",
        "Zubeyki"
    ],
    "wof:name":"Zubeyki",
    "wof:placetype":"locality"
},
  "geometry": {"coordinates":[23.71531,50.15866],"type":"Point"}
}