{
  "type": "Feature",
  "properties": {
    "gn:admin1_code":"5.0",
    "gn:asciiname":"Naberezhne",
    "gn:country_code":"UA",
    "gn:dem":53,
    "gn:feature_class":"P",
    "gn:feature_code":"PPL",
    "gn:name":"Naberezhne",
    "gn:population":0,
    "gn:timezone":"Europe/Kiev",
    "iso:country":"UA",
    "name:deu_x_preferred":[
        "Nabereschne"
    ],
    "name:hye_x_preferred":[
        "\u0546\u0561\u0562\u0565\u0580\u0565\u056a\u0576\u0578\u0565"
    ],
    "name:pol_x_preferred":[
        "Nabere\u017cne"
    ],
    "name:rus_x_preferred":[
        "\u041d\u0430\u0431\u0435\u0440\u0435\u0436\u043d\u043e\u0435"
    ],
    "name:ukr_x_preferred":[
        "Naberezhne"
    ],
    "name:ukr_x_variant":[
        "\u041d\u0430\u0431\u0435\u0440\u0435\u0436\u043d\u0435"
    ],
    "wof:name":"Naberezhne",
    "wof:placetype":"locality"
},
  "geometry": {"coordinates":[37.84512,47.31462],"type":"Point"}
}