{
  "type": "Feature",
  "properties": {
    "gn:admin1_code":"27.0",
    "gn:asciiname":"Khutor Tynchin",
    "gn:cc2":"UA",
    "gn:country_code":"UA",
    "gn:dem":162,
    "gn:feature_class":"P",
    "gn:feature_code":"PPL",
    "gn:name":"Khutor Tynchin",
    "gn:population":0,
    "gn:timezone":"Europe/Kiev",
    "iso:country":"UA",
    "name:und_x_variant":[
        "Tynchin",
        "Khutor Tynchin"
    ],
    "wof:name":"Khutor Tynchin",
    "wof:placetype":"locality"
},
  "geometry": {"coordinates":[28.95,51.45],"type":"Point"}
}