{
  "type": "Feature",
  "properties": {
    "gn:admin1_code":"24.0",
    "gn:asciiname":"Zhuravnyky",
    "gn:country_code":"UA",
    "gn:dem":219,
    "gn:feature_class":"P",
    "gn:feature_code":"PPL",
    "gn:name":"Zhuravnyky",
    "gn:population":0,
    "gn:timezone":"Europe/Kiev",
    "iso:country":"UA",
    "name:ukr_x_preferred":[
        "\u0416\u0443\u0440\u0430\u0432\u043d\u0438\u043a\u0438"
    ],
    "name:und_x_variant":[
        "Zhuravniki"
    ],
    "wof:name":"Zhuravnyky",
    "wof:placetype":"locality"
},
  "geometry": {"coordinates":[24.68874,50.4299],"type":"Point"}
}