{
  "type": "Feature",
  "properties": {
    "gn:admin1_code":"27.0",
    "gn:asciiname":"Barvinky",
    "gn:country_code":"UA",
    "gn:dem":168,
    "gn:feature_class":"P",
    "gn:feature_code":"PPL",
    "gn:name":"Barvinky",
    "gn:population":0,
    "gn:timezone":"Europe/Kiev",
    "iso:country":"UA",
    "name:ukr_x_preferred":[
        "Barvinky"
    ],
    "name:ukr_x_variant":[
        "\u0411\u0430\u0440\u0432\u0456\u043d\u043a\u0438"
    ],
    "name:und_x_variant":[
        "Barvinki"
    ],
    "wof:name":"Barvinky",
    "wof:placetype":"locality"
},
  "geometry": {"coordinates":[28.97828,50.81777],"type":"Point"}
}