{
  "type": "Feature",
  "properties": {
    "gn:admin1_code":"4.0",
    "gn:asciiname":"Malooleksandrivka",
    "gn:country_code":"UA",
    "gn:dem":72,
    "gn:feature_class":"P",
    "gn:feature_code":"PPL",
    "gn:name":"Malooleksandrivka",
    "gn:population":0,
    "gn:timezone":"Europe/Kiev",
    "iso:country":"UA",
    "name:ukr_x_preferred":[
        "Malooleksandrivka"
    ],
    "name:ukr_x_variant":[
        "\u041c\u0430\u043b\u043e\u043e\u043b\u0435\u043a\u0441\u0430\u043d\u0434\u0440\u0456\u0432\u043a\u0430"
    ],
    "name:und_x_variant":[
        "Malo-Aleksandrovka"
    ],
    "wof:name":"Malooleksandrivka",
    "wof:placetype":"locality"
},
  "geometry": {"coordinates":[35.83769,48.47879],"type":"Point"}
}