{
  "type": "Feature",
  "properties": {
    "gn:admin1_code":"26.0",
    "gn:asciiname":"Chornozemne",
    "gn:country_code":"UA",
    "gn:dem":91,
    "gn:feature_class":"P",
    "gn:feature_code":"PPL",
    "gn:name":"Chornozemne",
    "gn:population":0,
    "gn:timezone":"Europe/Zaporozhye",
    "iso:country":"UA",
    "name:ukr_x_preferred":[
        "Chornozemne"
    ],
    "name:ukr_x_variant":[
        "\u0427\u043e\u0440\u043d\u043e\u0437\u0435\u043c\u043d\u0435"
    ],
    "name:und_x_variant":[
        "Andreburg",
        "Chernozemnoye"
    ],
    "wof:name":"Chornozemne",
    "wof:placetype":"locality"
},
  "geometry": {"coordinates":[35.47583,47.36105],"type":"Point"}
}