{
  "type": "Feature",
  "properties": {
    "gn:admin1_code":"26.0",
    "gn:asciiname":"Atmanay",
    "gn:country_code":"UA",
    "gn:dem":8,
    "gn:feature_class":"P",
    "gn:feature_code":"PPL",
    "gn:name":"Atmanay",
    "gn:population":0,
    "gn:timezone":"Europe/Zaporozhye",
    "iso:country":"UA",
    "name:ukr_x_preferred":[
        "Atmanay"
    ],
    "name:ukr_x_variant":[
        "\u0410\u0442\u043c\u0430\u043d\u0430\u0439"
    ],
    "name:und_x_variant":[
        "Sovkhoz Kommunist"
    ],
    "wof:name":"Atmanay",
    "wof:placetype":"locality"
},
  "geometry": {"coordinates":[35.18225,46.37694000000001],"type":"Point"}
}