{
  "type": "Feature",
  "properties": {
    "gn:admin1_code":"4.0",
    "gn:asciiname":"Taroms'ke",
    "gn:country_code":"UA",
    "gn:dem":170,
    "gn:feature_class":"P",
    "gn:feature_code":"PPL",
    "gn:name":"Taroms\u2019ke",
    "gn:population":0,
    "gn:timezone":"Europe/Kiev",
    "iso:country":"UA",
    "name:eng_x_preferred":[
        "Taroms'ke"
    ],
    "name:ron_x_preferred":[
        "Taromske"
    ],
    "name:rus_x_preferred":[
        "\u0422\u0430\u0440\u043e\u043c\u0441\u043a\u043e\u0435"
    ],
    "name:ukr_x_preferred":[
        "\u0422\u0430\u0440\u043e\u043c\u0441\u044c\u043a\u0435"
    ],
    "name:und_x_variant":[
        "Taromskoye",
        "Taramskoye",
        "Taroms\u2019ke"
    ],
    "wof:name":"Taroms'ke",
    "wof:placetype":"locality"
},
  "geometry": {"coordinates":[34.78581,48.44341],"type":"Point"}
}