{
  "type": "Feature",
  "properties": {
    "iso:country":"UA",
    "name:eng_x_preferred":[
        "Rybotin"
    ],
    "name:rus_x_preferred":[
        "\u0420\u044b\u0431\u043e\u0442\u0438\u043d"
    ],
    "name:ukr_x_preferred":[
        "Rybotyn"
    ],
    "name:ukr_x_variant":[
        "\u0420\u0438\u0431\u043e\u0442\u0438\u043d"
    ],
    "name:unk_x_variant":[
        "Rybotin"
    ],
    "qs:a0":"\u0423\u043a\u0440\u0430\u0457\u043d\u0430",
    "qs:a1":"*\u0427\u0435\u0440\u043d\u0456\u0433\u0456\u0432\u0441\u044c\u043a\u0430",
    "qs:a1_alt":"Chernihivs'ka",
    "qs:a1r":"0",
    "qs:a2":"\u041a\u043e\u0440\u043e\u043f\u0441\u044c\u043a\u0438\u0439",
    "qs:a2_alt":"Korops'kyi",
    "qs:adm0":"\u0423\u043a\u0440\u0430\u0457\u043d\u0430",
    "qs:la_lc":"*",
    "qs:level":"locality",
    "qs:loc":"\u0420\u0438\u0431\u043e\u0442\u0438\u043d",
    "qs:loc_alt":"Rybotyn",
    "qs:pop":0,
    "qs:type":"buffered point",
    "wof:name":"\u0420\u0438\u0431\u043e\u0442\u0438\u043d",
    "wof:placetype":"locality"
},
  "geometry": {"coordinates":[32.892417,51.556807],"type":"Point"}
}