{
  "type": "Feature",
  "properties": {
    "gn:population":6241,
    "iso:country":"UA",
    "name:aze_x_preferred":[
        "Mor\u015f\u0131n"
    ],
    "name:bel_x_preferred":[
        "\u041c\u043e\u0440\u0448\u044b\u043d"
    ],
    "name:ceb_x_preferred":[
        "Morshyn"
    ],
    "name:ces_x_preferred":[
        "Mor\u0161yn"
    ],
    "name:crh_x_preferred":[
        "Mor\u015f\u0131n"
    ],
    "name:deu_x_preferred":[
        "Morschyn"
    ],
    "name:eng_x_preferred":[
        "Morshyn"
    ],
    "name:epo_x_preferred":[
        "Mor\u015din"
    ],
    "name:fas_x_preferred":[
        "\u0645\u0648\u0634\u06cc\u0646"
    ],
    "name:fra_x_preferred":[
        "Morchyn"
    ],
    "name:hsb_x_preferred":[
        "Mor\u0161yn"
    ],
    "name:hye_x_preferred":[
        "\u0544\u0578\u0580\u0577\u056b\u0576"
    ],
    "name:ita_x_preferred":[
        "Mor\u0161yn"
    ],
    "name:kat_x_preferred":[
        "\u10db\u10dd\u10e0\u10e8\u10d8\u10dc\u10d8"
    ],
    "name:lav_x_preferred":[
        "Mor\u0161ina"
    ],
    "name:nld_x_preferred":[
        "Morshyn"
    ],
    "name:nno_x_preferred":[
        "Morsjyn"
    ],
    "name:pol_x_preferred":[
        "Morszyn"
    ],
    "name:ron_x_preferred":[
        "Mor\u0219\u00een"
    ],
    "name:rus_x_preferred":[
        "\u041c\u043e\u0440\u0448\u0438\u043d"
    ],
    "name:sco_x_preferred":[
        "Morshyn"
    ],
    "name:tat_x_preferred":[
        "\u041c\u043e\u0440\u0448\u0438\u043d"
    ],
    "name:tat_x_variant":[
        "\u041c\u043e\u0440\u0448\u044b\u043d"
    ],
    "name:ukr_x_preferred":[
        "\u041c\u043e\u0440\u0448\u0438\u043d"
    ],
    "name:vie_x_preferred":[
        "Morshyn"
    ],
    "name:yid_x_preferred":[
        "\u05de\u05d0\u05e8\u05e9\u05d9\u05df"
    ],
    "qs:a0":"\u0423\u043a\u0440\u0430\u0457\u043d\u0430",
    "qs:a1":"*\u041b\u044c\u0432\u0456\u0432\u0441\u044c\u043a\u0430",
    "qs:a1_alt":"L'vivs'ka",
    "qs:a1r":"0",
    "qs:a2":"\u0421\u0442\u0440\u0438\u0439\u0441\u044c\u043a\u0438\u0439",
    "qs:a2_alt":"Stryis'kyi",
    "qs:adm0":"\u0423\u043a\u0440\u0430\u0457\u043d\u0430",
    "qs:la_lc":"*",
    "qs:level":"locality",
    "qs:loc":"\u041c\u043e\u0440\u0448\u0438\u043d",
    "qs:loc_alt":"Morshyn",
    "qs:pop":0,
    "qs:type":"buffered point",
    "wd:wordcount":270,
    "wof:name":"\u041c\u043e\u0440\u0448\u0438\u043d",
    "wof:placetype":"locality",
    "wof:population":6241
},
  "geometry": {"coordinates":[23.864122,49.163774],"type":"Point"}
}