{
  "type": "Feature",
  "properties": {
    "gn:admin1_code":"18.0",
    "gn:asciiname":"Popivka",
    "gn:country_code":"UA",
    "gn:dem":180,
    "gn:feature_class":"P",
    "gn:feature_code":"PPL",
    "gn:name":"Popivka",
    "gn:population":0,
    "gn:timezone":"Europe/Kiev",
    "iso:country":"UA",
    "name:ukr_x_preferred":[
        "Popivka"
    ],
    "name:ukr_x_variant":[
        "\u041f\u043e\u043f\u0456\u0432\u043a\u0430"
    ],
    "name:und_x_variant":[
        "Popovka"
    ],
    "wof:name":"Popivka",
    "wof:placetype":"locality"
},
  "geometry": {"coordinates":[34.57789,49.97241],"type":"Point"}
}