{
  "type": "Feature",
  "properties": {
    "gn:admin1_code":"25.0",
    "gn:asciiname":"Bakosh",
    "gn:country_code":"UA",
    "gn:dem":103,
    "gn:feature_class":"P",
    "gn:feature_code":"PPL",
    "gn:name":"Bakosh",
    "gn:population":0,
    "gn:timezone":"Europe/Uzhgorod",
    "iso:country":"UA",
    "name:ukr_x_preferred":[
        "Bakosh"
    ],
    "name:ukr_x_variant":[
        "\u0411\u0430\u043a\u043e\u0448"
    ],
    "wof:name":"Bakosh",
    "wof:placetype":"locality"
},
  "geometry": {"coordinates":[22.35475,48.37778],"type":"Point"}
}