{
  "type": "Feature",
  "properties": {
    "gn:admin1_code":"8.0",
    "gn:asciiname":"Protas'yevka",
    "gn:country_code":"UA",
    "gn:dem":33,
    "gn:feature_class":"P",
    "gn:feature_code":"PPL",
    "gn:name":"Protas\u2019yevka",
    "gn:population":0,
    "gn:timezone":"Europe/Kiev",
    "iso:country":"UA",
    "wof:name":"Protas'yevka",
    "wof:placetype":"locality"
},
  "geometry": {"coordinates":[34.596,46.64992],"type":"Point"}
}