{
  "type": "Feature",
  "properties": {
    "iso:country":"UA",
    "qs:a0":"\u0423\u043a\u0440\u0430\u0457\u043d\u0430",
    "qs:a1":"*\u0422\u0435\u0440\u043d\u043e\u043f\u0456\u043b\u044c\u0441\u044c\u043a\u0430",
    "qs:a1_alt":"Ternopil's'ka",
    "qs:a1r":"0",
    "qs:a2":"\u0411\u043e\u0440\u0449\u0456\u0432\u0441\u044c\u043a\u0438\u0439",
    "qs:a2_alt":"Borschivs'kyi",
    "qs:adm0":"\u0423\u043a\u0440\u0430\u0457\u043d\u0430",
    "qs:la_lc":"*",
    "qs:level":"locality",
    "qs:loc":"\u041b\u043e\u0441\u044f\u0447",
    "qs:loc_alt":"Losiach",
    "qs:pop":0,
    "qs:type":"buffered point",
    "wof:name":"\u041b\u043e\u0441\u044f\u0447",
    "wof:placetype":"locality"
},
  "geometry": {"coordinates":[26.088767,48.907942],"type":"Point"}
}