{
  "type": "Feature",
  "properties": {
    "gn:gn_country":"UA",
    "gn:gn_fcode":"PPL",
    "gn:gn_pop":2885,
    "gn:population":2885,
    "iso:country":"UA",
    "name:arm_x_preferred":[
        "\u0532\u0565\u0580\u0575\u0578\u0566\u0578\u057e\u0578"
    ],
    "name:dut_x_preferred":[
        "Beresowo"
    ],
    "name:eng_x_preferred":[
        "Berezovo"
    ],
    "name:epo_x_preferred":[
        "Berezovo"
    ],
    "name:ger_x_preferred":[
        "Beresowo"
    ],
    "name:hun_x_preferred":[
        "Berezna"
    ],
    "name:rum_x_preferred":[
        "Berezovo"
    ],
    "name:rus_x_preferred":[
        "\u0411\u0435\u0440\u0435\u0437\u043e\u0432\u043e"
    ],
    "name:ukr_x_preferred":[
        "\u0411\u0435\u0440\u0435\u0437\u043e\u0432\u0435"
    ],
    "name:ukr_x_variant":[
        "\u0411\u0435\u0440\u0435\u0437\u043e\u0432\u043e"
    ],
    "name:unk_x_variant":[
        "Berezove"
    ],
    "name:yid_x_preferred":[
        "\u05d1\u05e2\u05e8\u05e2\u05d6\u05d9\u05d5\u05d5"
    ],
    "qs_pg:aaroncc":"UA",
    "qs_pg:gn_country":"UA",
    "qs_pg:gn_fcode":"PPL",
    "qs_pg:gn_pop":2885,
    "qs_pg:name":"Berezovo",
    "qs_pg:photos_9r":0,
    "qs_pg:photos_sr":0,
    "qs_pg:pop_sr":4,
    "qs_pg:qs_pg_placetype":"locality",
    "wof:name":"Berezovo",
    "wof:placetype":"locality",
    "wof:population":2885
},
  "geometry": {"coordinates":[23.474,48.30943],"type":"Point"}
}