{
  "type": "Feature",
  "properties": {
    "gn:admin1_code":"26.0",
    "gn:asciiname":"Chervonodniprovka",
    "gn:country_code":"UA",
    "gn:dem":36,
    "gn:feature_class":"P",
    "gn:feature_code":"PPL",
    "gn:name":"Chervonodniprovka",
    "gn:population":0,
    "gn:timezone":"Europe/Zaporozhye",
    "iso:country":"UA",
    "name:ron_x_preferred":[
        "Cervonodniprovka"
    ],
    "name:rus_x_preferred":[
        "\u0427\u0435\u0440\u0432\u043e\u043d\u043e\u0434\u043d\u0435\u043f\u0440\u043e\u0432\u043a\u0430"
    ],
    "name:ukr_x_preferred":[
        "Chervonodniprovka"
    ],
    "name:ukr_x_variant":[
        "\u0427\u0435\u0440\u0432\u043e\u043d\u043e\u0434\u043d\u0456\u043f\u0440\u043e\u0432\u043a\u0430"
    ],
    "name:und_x_variant":[
        "Krasno-Dneprovskiy",
        "Dneprovsk",
        "Dneprovskoye",
        "Chervonodneprovka"
    ],
    "name:zho_x_preferred":[
        "\u5207\u723e\u6c83\u8afe\u5fb7\u5c3c\u666e\u7f85\u592b\u5361"
    ],
    "wof:name":"Chervonodniprovka",
    "wof:placetype":"locality"
},
  "geometry": {"coordinates":[34.96667,47.56667],"type":"Point"}
}