{
  "type": "Feature",
  "properties": {
    "gn:admin1_code":"17.0",
    "gn:asciiname":"Petrivka",
    "gn:country_code":"UA",
    "gn:dem":192,
    "gn:feature_class":"P",
    "gn:feature_code":"PPL",
    "gn:name":"Petrivka",
    "gn:population":0,
    "gn:timezone":"Europe/Kiev",
    "iso:country":"UA",
    "name:ukr_x_preferred":[
        "Petrivka"
    ],
    "name:und_x_variant":[
        "Petrovka"
    ],
    "wof:name":"Petrivka",
    "wof:placetype":"locality"
},
  "geometry": {"coordinates":[29.47804,47.4878],"type":"Point"}
}