{
  "type": "Feature",
  "properties": {
    "gn:admin1_code":"17.0",
    "gn:asciiname":"Orikhivka",
    "gn:country_code":"UA",
    "gn:dem":61,
    "gn:feature_class":"P",
    "gn:feature_code":"PPL",
    "gn:name":"Orikhivka",
    "gn:population":0,
    "gn:timezone":"Europe/Kiev",
    "iso:country":"UA",
    "name:ukr_x_preferred":[
        "Orikhivka"
    ],
    "name:ukr_x_variant":[
        "\u041e\u0440\u0456\u0445\u0456\u0432\u043a\u0430"
    ],
    "name:und_x_variant":[
        "Pandaclia",
        "Pandakliya",
        "Orekhovka"
    ],
    "wof:name":"Orikhivka",
    "wof:placetype":"locality"
},
  "geometry": {"coordinates":[28.90461,45.8087],"type":"Point"}
}