{
  "type": "Feature",
  "properties": {
    "gn:gn_country":"UA",
    "gn:gn_fcode":"PPL",
    "gn:gn_pop":4926,
    "gn:population":4926,
    "iso:country":"UA",
    "name:ceb_x_preferred":[
        "Toshkivka"
    ],
    "name:crh_x_preferred":[
        "To\u015fkivka"
    ],
    "name:deu_x_preferred":[
        "Toschkiwka"
    ],
    "name:eng_x_preferred":[
        "Toshkivka"
    ],
    "name:est_x_preferred":[
        "To\u0161kivka"
    ],
    "name:lav_x_preferred":[
        "To\u0161kivka"
    ],
    "name:ron_x_preferred":[
        "To\u0219kivka"
    ],
    "name:rus_x_preferred":[
        "\u0422\u043e\u0448\u043a\u0456\u0432\u043a\u0430"
    ],
    "name:rus_x_variant":[
        "\u0422\u043e\u0448\u043a\u043e\u0432\u043a\u0430"
    ],
    "name:ukr_x_preferred":[
        "\u0422\u043e\u0448\u043a\u0456\u0432\u043a\u0430"
    ],
    "name:unk_x_variant":[
        "Rudnik Toshkovka"
    ],
    "name:zho_x_preferred":[
        "\u6258\u4ec0\u57fa\u592b\u5361"
    ],
    "qs_pg:aaroncc":"UA",
    "qs_pg:gn_country":"UA",
    "qs_pg:gn_fcode":"PPL",
    "qs_pg:gn_pop":4926,
    "qs_pg:name":"Toshkovka",
    "qs_pg:photos_9r":0,
    "qs_pg:photos_sr":0,
    "qs_pg:pop_sr":4,
    "qs_pg:qs_pg_placetype":"locality",
    "wof:name":"Toshkovka",
    "wof:placetype":"locality",
    "wof:population":4926
},
  "geometry": {"coordinates":[38.57903,48.77914],"type":"Point"}
}