{
  "type": "Feature",
  "properties": {
    "gn:admin1_code":"24.0",
    "gn:asciiname":"Mizhlissya",
    "gn:country_code":"UA",
    "gn:dem":211,
    "gn:feature_class":"P",
    "gn:feature_code":"PPL",
    "gn:name":"Mizhlissya",
    "gn:population":0,
    "gn:timezone":"Europe/Kiev",
    "iso:country":"UA",
    "name:rus_x_preferred":[
        "Mezhles\u2019ye"
    ],
    "name:ukr_x_preferred":[
        "Mizhlissya"
    ],
    "name:ukr_x_variant":[
        "\u041c\u0456\u0436\u043b\u0456\u0441\u0441\u044f"
    ],
    "wof:name":"Mizhlissya",
    "wof:placetype":"locality"
},
  "geometry": {"coordinates":[24.53014,50.84037],"type":"Point"}
}