{
  "type": "Feature",
  "properties": {
    "gn:admin1_code":"2.0",
    "gn:asciiname":"Smolyhivka",
    "gn:country_code":"UA",
    "gn:dem":145,
    "gn:feature_class":"P",
    "gn:feature_code":"PPL",
    "gn:name":"Smolyhivka",
    "gn:population":0,
    "gn:timezone":"Europe/Kiev",
    "iso:country":"UA",
    "name:eng_x_preferred":[
        "Smoligovka"
    ],
    "name:rus_x_preferred":[
        "\u0421\u043c\u043e\u043b\u0438\u0433\u043e\u0432\u043a\u0430"
    ],
    "name:ukr_x_preferred":[
        "Smolyhivka"
    ],
    "name:ukr_x_variant":[
        "\u0421\u043c\u043e\u043b\u0438\u0433\u0456\u0432\u043a\u0430"
    ],
    "name:und_x_variant":[
        "Smolegovka",
        "Smoligovka"
    ],
    "wof:name":"Smolyhivka",
    "wof:placetype":"locality"
},
  "geometry": {"coordinates":[30.75195,51.6762],"type":"Point"}
}