{
  "type": "Feature",
  "properties": {
    "gn:admin1_code":"24.0",
    "gn:asciiname":"Berezhtsi",
    "gn:country_code":"UA",
    "gn:dem":175,
    "gn:feature_class":"P",
    "gn:feature_code":"PPL",
    "gn:name":"Berezhtsi",
    "gn:population":0,
    "gn:timezone":"Europe/Kiev",
    "iso:country":"UA",
    "name:ukr_x_preferred":[
        "Berezhtsi"
    ],
    "name:ukr_x_variant":[
        "\u0411\u0435\u0440\u0435\u0436\u0446\u0456"
    ],
    "name:und_x_variant":[
        "Berozhtse",
        "Bere\u017ace",
        "Berezhtsy"
    ],
    "wof:name":"Berezhtsi",
    "wof:placetype":"locality"
},
  "geometry": {"coordinates":[23.87155,51.16841],"type":"Point"}
}