{
  "type": "Feature",
  "properties": {
    "gn:admin1_code":"4.0",
    "gn:asciiname":"Pryyut",
    "gn:country_code":"UA",
    "gn:dem":104,
    "gn:feature_class":"P",
    "gn:feature_code":"PPL",
    "gn:name":"Pryyut",
    "gn:population":0,
    "gn:timezone":"Europe/Kiev",
    "iso:country":"UA",
    "name:ukr_x_preferred":[
        "Pryyut"
    ],
    "name:ukr_x_variant":[
        "\u041f\u0440\u0438\u044e\u0442"
    ],
    "name:und_x_variant":[
        "Priyut"
    ],
    "wof:name":"Pryyut",
    "wof:placetype":"locality"
},
  "geometry": {"coordinates":[34.88772,48.75608],"type":"Point"}
}