{
  "type": "Feature",
  "properties": {
    "iso:country":"UA",
    "name:ukr_x_preferred":[
        "\u0421\u043e\u043b\u043e\u043c\u2019\u044f\u043d\u043a\u0430"
    ],
    "wof:name":"Solomianka",
    "wof:placetype":"neighbourhood"
},
  "geometry": {"coordinates":[30.47438790235151,50.4329232785798],"type":"Point"}
}