{
  "type": "Feature",
  "properties": {
    "gn:admin1_code":"18.0",
    "gn:asciiname":"Snityn",
    "gn:country_code":"UA",
    "gn:dem":92,
    "gn:feature_class":"P",
    "gn:feature_code":"PPL",
    "gn:name":"Snityn",
    "gn:population":0,
    "gn:timezone":"Europe/Kiev",
    "iso:country":"UA",
    "name:eng_x_preferred":[
        "Snitin"
    ],
    "name:rus_x_preferred":[
        "\u0421\u043d\u0438\u0442\u0438\u043d"
    ],
    "name:ukr_x_preferred":[
        "Snityn"
    ],
    "name:ukr_x_variant":[
        "\u0421\u043d\u0456\u0442\u0438\u043d"
    ],
    "name:und_x_variant":[
        "Snyatin",
        "Snitin"
    ],
    "wof:name":"Snityn",
    "wof:placetype":"locality"
},
  "geometry": {"coordinates":[33.24582,50.10512],"type":"Point"}
}