{
  "type": "Feature",
  "properties": {
    "gn:admin1_code":"7.0",
    "gn:asciiname":"Komsomol's'ke",
    "gn:country_code":"UA",
    "gn:dem":167,
    "gn:feature_class":"P",
    "gn:feature_code":"PPL",
    "gn:name":"Komsomol\u2019s\u2019ke",
    "gn:population":0,
    "gn:timezone":"Europe/Kiev",
    "iso:country":"UA",
    "name:ukr_x_preferred":[
        "Komsomol\u2019s\u2019ke"
    ],
    "name:ukr_x_variant":[
        "\u041a\u043e\u043c\u0441\u043e\u043c\u043e\u043b\u044c\u0441\u044c\u043a\u0435"
    ],
    "wof:name":"Komsomol's'ke",
    "wof:placetype":"locality"
},
  "geometry": {"coordinates":[35.23284,49.96513],"type":"Point"}
}