{
  "type": "Feature",
  "properties": {
    "gn:admin1_code":"19.0",
    "gn:asciiname":"Mostyshche",
    "gn:country_code":"UA",
    "gn:dem":168,
    "gn:feature_class":"P",
    "gn:feature_code":"PPL",
    "gn:name":"Mostyshche",
    "gn:population":0,
    "gn:timezone":"Europe/Kiev",
    "iso:country":"UA",
    "name:pol_x_preferred":[
        "Mo\u015bciska"
    ],
    "name:ron_x_preferred":[
        "Most\u00ee\u0219ce"
    ],
    "name:rus_x_preferred":[
        "\u041c\u043e\u0441\u0442\u0438\u0449\u0435"
    ],
    "name:ukr_x_preferred":[
        "Mostyshche"
    ],
    "name:ukr_x_variant":[
        "\u041c\u043e\u0441\u0442\u0438\u0449\u0435"
    ],
    "name:und_x_variant":[
        "Mostishche"
    ],
    "name:zho_x_preferred":[
        "\u83ab\u65af\u5b63\u8b1d"
    ],
    "wof:name":"Mostyshche",
    "wof:placetype":"locality"
},
  "geometry": {"coordinates":[26.08531,51.31676],"type":"Point"}
}