{
  "type": "Feature",
  "properties": {
    "gn:admin1_code":"21.0",
    "gn:asciiname":"Stepanivka",
    "gn:country_code":"UA",
    "gn:dem":149,
    "gn:feature_class":"P",
    "gn:feature_code":"PPL",
    "gn:name":"Stepanivka",
    "gn:population":0,
    "gn:timezone":"Europe/Kiev",
    "iso:country":"UA",
    "name:eng_x_preferred":[
        "Stepanovka"
    ],
    "name:ron_x_preferred":[
        "Stepanivka"
    ],
    "name:rus_x_preferred":[
        "\u0421\u0442\u0435\u043f\u0430\u043d\u043e\u0432\u043a\u0430"
    ],
    "name:ukr_x_preferred":[
        "Stepanivka"
    ],
    "name:ukr_x_variant":[
        "\u0421\u0442\u0435\u043f\u0430\u043d\u0456\u0432\u043a\u0430"
    ],
    "name:und_x_variant":[
        "Stepanovka"
    ],
    "name:zho_x_preferred":[
        "\u65af\u6377\u5e15\u5c3c\u592b\u5361"
    ],
    "wof:name":"Stepanivka",
    "wof:placetype":"locality"
},
  "geometry": {"coordinates":[34.60583,50.95591],"type":"Point"}
}