{
  "type": "Feature",
  "properties": {
    "gn:country":"UA",
    "gn:fcode":"PPL",
    "gn:population":4070,
    "iso:country":"UA",
    "name:eng_x_preferred":[
        "Boromlya"
    ],
    "name:rus_x_preferred":[
        "\u0411\u043e\u0440\u043e\u043c\u043b\u044f"
    ],
    "name:ukr_x_preferred":[
        "\u0411\u043e\u0440\u043e\u043c\u043b\u044f"
    ],
    "qs_pg:aaroncc":"UA",
    "qs_pg:gn_country":"UA",
    "qs_pg:gn_fcode":"PPL",
    "qs_pg:gn_pop":4070,
    "qs_pg:name":"Boromlya",
    "qs_pg:name_adm0":"Ukraine",
    "qs_pg:name_adm1":"Sums\u00b4ka Oblast\u00b4",
    "qs_pg:photos_9r":0,
    "qs_pg:photos_sr":0,
    "qs_pg:pop_sr":4,
    "qs_pg:qs_pg_placetype":"locality",
    "qs_pg:qs_pg_placetype_gp":"Town",
    "qs_pg:woe_adm0":23424976,
    "woe:adm0_id":23424976,
    "woe:name_adm0":"Ukraine",
    "woe:name_adm1":"Sums\u00b4ka Oblast\u00b4",
    "woe:placetype":"Town",
    "wof:name":"Boromlya",
    "wof:placetype":"locality",
    "wof:population":4070
},
  "geometry": {"coordinates":[34.97042,50.61838],"type":"Point"}
}