{
  "type": "Feature",
  "properties": {
    "gn:admin1_code":"13.0",
    "gn:asciiname":"Laput'ky",
    "gn:country_code":"UA",
    "gn:dem":106,
    "gn:feature_class":"P",
    "gn:feature_code":"PPL",
    "gn:name":"Laput\u2019ky",
    "gn:population":0,
    "gn:timezone":"Europe/Kiev",
    "iso:country":"UA",
    "name:rus_x_preferred":[
        "Laput\u2019ki"
    ],
    "name:ukr_x_preferred":[
        "Laput\u2019ky"
    ],
    "name:ukr_x_variant":[
        "\u041b\u0430\u043f\u0443\u0442\u044c\u043a\u0438"
    ],
    "wof:name":"Laput'ky",
    "wof:placetype":"locality"
},
  "geometry": {"coordinates":[30.26602,51.05447],"type":"Point"}
}