{
  "type": "Feature",
  "properties": {
    "iso:country":"UA",
    "qs:a0":"\u0423\u043a\u0440\u0430\u0457\u043d\u0430",
    "qs:a1":"*\u041e\u0434\u0435\u0441\u044c\u043a\u0430",
    "qs:a1_alt":"Odes'ka",
    "qs:a1r":"0",
    "qs:a2":"\u041a\u043e\u043c\u0456\u043d\u0442\u0435\u0440\u043d\u0456\u0432\u0441\u044c\u043a\u0438\u0439",
    "qs:a2_alt":"Kominternivs'kyi",
    "qs:adm0":"\u0423\u043a\u0440\u0430\u0457\u043d\u0430",
    "qs:la_lc":"*",
    "qs:level":"locality",
    "qs:loc":"\u0427\u043e\u0440\u043d\u043e\u043c\u043e\u0440\u0441\u044c\u043a\u0435",
    "qs:loc_alt":"Chornomors'ke",
    "qs:pop":0,
    "qs:type":"buffered point",
    "wd:wordcount":427,
    "wof:name":"\u0427\u043e\u0440\u043d\u043e\u043c\u043e\u0440\u0441\u044c\u043a\u0435",
    "wof:placetype":"locality"
},
  "geometry": {"coordinates":[30.941408,46.588018],"type":"Point"}
}