{
  "type": "Feature",
  "properties": {
    "gn:admin1_code":"7.0",
    "gn:asciiname":"Zarubynka",
    "gn:country_code":"UA",
    "gn:dem":153,
    "gn:feature_class":"P",
    "gn:feature_code":"PPL",
    "gn:name":"Zarubynka",
    "gn:population":0,
    "gn:timezone":"Europe/Kiev",
    "iso:country":"UA",
    "name:ukr_x_preferred":[
        "Zarubynka"
    ],
    "name:ukr_x_variant":[
        "\u0417\u0430\u0440\u0443\u0431\u0438\u043d\u043a\u0430"
    ],
    "name:und_x_variant":[
        "Zarubinka"
    ],
    "wof:name":"Zarubynka",
    "wof:placetype":"locality"
},
  "geometry": {"coordinates":[37.55286,50.16618],"type":"Point"}
}