{
  "type": "Feature",
  "properties": {
    "gn:admin1_code":"9.0",
    "gn:asciiname":"Mikhnov",
    "gn:country_code":"UA",
    "gn:dem":235,
    "gn:feature_class":"P",
    "gn:feature_code":"PPL",
    "gn:name":"Mikhnov",
    "gn:population":0,
    "gn:timezone":"Europe/Kiev",
    "iso:country":"UA",
    "wof:name":"Mikhnov",
    "wof:placetype":"locality"
},
  "geometry": {"coordinates":[26.69362000000001,50.0609],"type":"Point"}
}