{
  "type": "Feature",
  "properties": {
    "gn:admin1_code":"9.0",
    "gn:asciiname":"Bakhmatovtsy",
    "gn:country_code":"UA",
    "gn:dem":305,
    "gn:feature_class":"P",
    "gn:feature_code":"PPL",
    "gn:name":"Bakhmatovtsy",
    "gn:population":0,
    "gn:timezone":"Europe/Kiev",
    "iso:country":"UA",
    "wof:name":"Bakhmatovtsy",
    "wof:placetype":"locality"
},
  "geometry": {"coordinates":[27.20439,49.41988],"type":"Point"}
}