{
  "type": "Feature",
  "properties": {
    "gn:admin1_code":"23.0",
    "gn:asciiname":"Adamivka",
    "gn:country_code":"UA",
    "gn:dem":254,
    "gn:feature_class":"P",
    "gn:feature_code":"PPL",
    "gn:name":"Adamivka",
    "gn:population":0,
    "gn:timezone":"Europe/Kiev",
    "iso:country":"UA",
    "name:rus_x_preferred":[
        "\u0410\u0434\u0430\u043c\u043e\u0432\u043a\u0430"
    ],
    "name:ukr_x_preferred":[
        "\u0410\u0434\u0430\u043c\u0456\u0432\u043a\u0430"
    ],
    "name:und_x_variant":[
        "Adamovka"
    ],
    "wof:name":"Adamivka",
    "wof:placetype":"locality"
},
  "geometry": {"coordinates":[29.31962,49.43441],"type":"Point"}
}