{
  "type": "Feature",
  "properties": {
    "gn:admin1_code":"26.0",
    "gn:asciiname":"Valentinovka",
    "gn:country_code":"UA",
    "gn:dem":109,
    "gn:feature_class":"P",
    "gn:feature_code":"PPL",
    "gn:name":"Valentinovka",
    "gn:population":0,
    "gn:timezone":"Europe/Zaporozhye",
    "iso:country":"UA",
    "wof:name":"Valentinovka",
    "wof:placetype":"locality"
},
  "geometry": {"coordinates":[35.95,47.73333],"type":"Point"}
}