{
  "type": "Feature",
  "properties": {
    "gn:admin1_code":"21.0",
    "gn:asciiname":"Loknya",
    "gn:country_code":"UA",
    "gn:dem":169,
    "gn:feature_class":"P",
    "gn:feature_code":"PPL",
    "gn:name":"Loknya",
    "gn:population":0,
    "gn:timezone":"Europe/Kiev",
    "iso:country":"UA",
    "name:eng_x_preferred":[
        "Loknya"
    ],
    "name:rus_x_preferred":[
        "\u041b\u043e\u043a\u043d\u044f"
    ],
    "wof:name":"Loknya",
    "wof:placetype":"locality"
},
  "geometry": {"coordinates":[33.18474000000001,50.70192],"type":"Point"}
}