{
  "type": "Feature",
  "properties": {
    "gn:admin1_code":"18.0",
    "gn:asciiname":"Bilenchenkivka",
    "gn:country_code":"UA",
    "gn:dem":147,
    "gn:feature_class":"P",
    "gn:feature_code":"PPL",
    "gn:name":"Bilenchenkivka",
    "gn:population":0,
    "gn:timezone":"Europe/Kiev",
    "iso:country":"UA",
    "name:ukr_x_preferred":[
        "Bilenchenkivka"
    ],
    "name:ukr_x_variant":[
        "\u0411\u0456\u043b\u0435\u043d\u0447\u0435\u043d\u043a\u0456\u0432\u043a\u0430"
    ],
    "name:und_x_variant":[
        "Stashevshchina",
        "Bilenchenkovka",
        "Belochinkovka",
        "Belonchenkovka"
    ],
    "wof:name":"Bilenchenkivka",
    "wof:placetype":"locality"
},
  "geometry": {"coordinates":[33.92748,50.36256],"type":"Point"}
}