{
  "type": "Feature",
  "properties": {
    "gn:admin1_code":"14.0",
    "gn:asciiname":"Zorykivka",
    "gn:country_code":"UA",
    "gn:dem":90,
    "gn:feature_class":"P",
    "gn:feature_code":"PPL",
    "gn:name":"Zorykivka",
    "gn:population":0,
    "gn:timezone":"Europe/Zaporozhye",
    "iso:country":"UA",
    "name:eng_x_preferred":[
        "Zorynivka"
    ],
    "name:rus_x_preferred":[
        "\u0417\u043e\u0440\u0438\u043a\u043e\u0432\u043a\u0430"
    ],
    "name:ukr_x_preferred":[
        "Zorykivka"
    ],
    "name:ukr_x_variant":[
        "\u0417\u043e\u0440\u0438\u043a\u0456\u0432\u043a\u0430"
    ],
    "name:und_x_variant":[
        "Zorikovka",
        "Zorikova"
    ],
    "wof:name":"Zorykivka",
    "wof:placetype":"locality"
},
  "geometry": {"coordinates":[39.84056,49.3963],"type":"Point"}
}