{
  "type": "Feature",
  "properties": {
    "gn:admin1_code":"18.0",
    "gn:asciiname":"Malyutyntsi",
    "gn:country_code":"UA",
    "gn:dem":118,
    "gn:feature_class":"P",
    "gn:feature_code":"PPL",
    "gn:name":"Malyutyntsi",
    "gn:population":0,
    "gn:timezone":"Europe/Kiev",
    "iso:country":"UA",
    "name:ukr_x_preferred":[
        "Malyutyntsi"
    ],
    "name:ukr_x_variant":[
        "\u041c\u0430\u043b\u044e\u0442\u0438\u043d\u0446\u0456"
    ],
    "name:und_x_variant":[
        "Malyutintsy"
    ],
    "wof:name":"Malyutyntsi",
    "wof:placetype":"locality"
},
  "geometry": {"coordinates":[32.195,50.25473],"type":"Point"}
}