{
  "type": "Feature",
  "properties": {
    "iso:country":"UA",
    "name:eng_x_preferred":[
        "Mikhaylovka"
    ],
    "name:rus_x_preferred":[
        "\u041c\u0438\u0445\u0430\u0439\u043b\u043e\u0432\u043a\u0430"
    ],
    "name:ukr_x_preferred":[
        "Mykhaylivka"
    ],
    "name:ukr_x_variant":[
        "\u041c\u0438\u0445\u0430\u0439\u043b\u0456\u0432\u043a\u0430"
    ],
    "qs:a0":"\u0423\u043a\u0440\u0430\u0457\u043d\u0430",
    "qs:a1":"*\u0421\u0443\u043c\u0441\u044c\u043a\u0430",
    "qs:a1_alt":"Sums'ka",
    "qs:a1r":"0",
    "qs:a2":"\u0411\u0443\u0440\u0438\u043d\u0441\u044c\u043a\u0438\u0439",
    "qs:a2_alt":"Buryns'kyi",
    "qs:adm0":"\u0423\u043a\u0440\u0430\u0457\u043d\u0430",
    "qs:la_lc":"*",
    "qs:level":"locality",
    "qs:loc":"\u041c\u0438\u0445\u0430\u0439\u043b\u0456\u0432\u043a\u0430",
    "qs:loc_alt":"Mykhailivka",
    "qs:pop":0,
    "qs:type":"buffered point",
    "wd:wordcount":93,
    "wof:name":"\u041c\u0438\u0445\u0430\u0439\u043b\u0456\u0432\u043a\u0430",
    "wof:placetype":"locality"
},
  "geometry": {"coordinates":[33.882057,51.144648],"type":"Point"}
}