{
  "type": "Feature",
  "properties": {
    "iso:country":"UA",
    "name:rus_x_preferred":[
        "Prisluch\u2019"
    ],
    "name:ukr_x_preferred":[
        "Prysluch"
    ],
    "name:ukr_x_variant":[
        "\u041f\u0440\u0438\u0441\u043b\u0443\u0447"
    ],
    "name:und_x_variant":[
        "Kholopy"
    ],
    "qs:a0":"\u0423\u043a\u0440\u0430\u0457\u043d\u0430",
    "qs:a1":"*\u0420\u0456\u0432\u043d\u0435\u043d\u0441\u044c\u043a\u0430",
    "qs:a1_alt":"Rivnens'ka",
    "qs:a1r":"0",
    "qs:a2":"\u0411\u0435\u0440\u0435\u0437\u043d\u0456\u0432\u0441\u044c\u043a\u0438\u0439",
    "qs:a2_alt":"Bereznivs'kyi",
    "qs:adm0":"\u0423\u043a\u0440\u0430\u0457\u043d\u0430",
    "qs:la_lc":"*",
    "qs:level":"locality",
    "qs:loc":"\u041f\u0440\u0438\u0441\u043b\u0443\u0447",
    "qs:loc_alt":"Prysluch",
    "qs:pop":0,
    "qs:type":"buffered point",
    "wof:name":"\u041f\u0440\u0438\u0441\u043b\u0443\u0447",
    "wof:placetype":"locality"
},
  "geometry": {"coordinates":[26.853858,50.926506],"type":"Point"}
}