{
  "type": "Feature",
  "properties": {
    "gn:admin1_code":"7.0",
    "gn:asciiname":"Odrynka",
    "gn:country_code":"UA",
    "gn:dem":130,
    "gn:feature_class":"P",
    "gn:feature_code":"PPL",
    "gn:name":"Odrynka",
    "gn:population":0,
    "gn:timezone":"Europe/Kiev",
    "iso:country":"UA",
    "name:ukr_x_preferred":[
        "Odrynka"
    ],
    "name:ukr_x_variant":[
        "\u041e\u0434\u0440\u0438\u043d\u043a\u0430"
    ],
    "wof:name":"Odrynka",
    "wof:placetype":"locality"
},
  "geometry": {"coordinates":[35.86284000000001,49.84594],"type":"Point"}
}