{
  "type": "Feature",
  "properties": {
    "gn:admin1_code":"5.0",
    "gn:asciiname":"Min'kivka",
    "gn:country_code":"UA",
    "gn:dem":191,
    "gn:feature_class":"P",
    "gn:feature_code":"PPL",
    "gn:name":"Min\u2019kivka",
    "gn:population":0,
    "gn:timezone":"Europe/Kiev",
    "iso:country":"UA",
    "name:rus_x_preferred":[
        "Min\u2019kovka"
    ],
    "name:ukr_x_preferred":[
        "Min\u2019kivka"
    ],
    "name:ukr_x_variant":[
        "\u041c\u0456\u043d\u044c\u043a\u0456\u0432\u043a\u0430"
    ],
    "wof:name":"Min'kivka",
    "wof:placetype":"locality"
},
  "geometry": {"coordinates":[37.85387,48.7032],"type":"Point"}
}