{
  "type": "Feature",
  "properties": {
    "gn:admin1_code":"21.0",
    "gn:asciiname":"Holubivka",
    "gn:country_code":"UA",
    "gn:dem":172,
    "gn:feature_class":"P",
    "gn:feature_code":"PPL",
    "gn:name":"Holubivka",
    "gn:population":0,
    "gn:timezone":"Europe/Kiev",
    "iso:country":"UA",
    "name:ukr_x_preferred":[
        "Holubivka"
    ],
    "name:ukr_x_variant":[
        "\u0413\u043e\u043b\u0443\u0431\u0456\u0432\u043a\u0430"
    ],
    "name:und_x_variant":[
        "Golubovka"
    ],
    "wof:name":"Holubivka",
    "wof:placetype":"locality"
},
  "geometry": {"coordinates":[34.419,50.79977],"type":"Point"}
}