{
  "type": "Feature",
  "properties": {
    "gn:admin1_code":"4.0",
    "gn:asciiname":"Kovaleve",
    "gn:country_code":"UA",
    "gn:dem":121,
    "gn:feature_class":"P",
    "gn:feature_code":"PPL",
    "gn:name":"Kovaleve",
    "gn:population":0,
    "gn:timezone":"Europe/Kiev",
    "iso:country":"UA",
    "name:rus_x_preferred":[
        "\u041a\u043e\u0432\u0430\u043b\u0435\u0432\u043e"
    ],
    "name:ukr_x_preferred":[
        "Kovaleve"
    ],
    "name:ukr_x_variant":[
        "\u041a\u043e\u0432\u0430\u043b\u0435\u0432\u0435"
    ],
    "name:und_x_variant":[
        "Kovalyevo"
    ],
    "wof:name":"Kovaleve",
    "wof:placetype":"locality"
},
  "geometry": {"coordinates":[33.79095,48.15079],"type":"Point"}
}