{
  "type": "Feature",
  "properties": {
    "iso:country":"UA",
    "name:eng_x_preferred":[
        "Babchintsi"
    ],
    "name:est_x_preferred":[
        "Babt\u0161\u00f5ntsi"
    ],
    "name:hye_x_preferred":[
        "\u0532\u0561\u0562\u0579\u056b\u0576\u0581\u056b"
    ],
    "name:kat_x_preferred":[
        "\u10d1\u10d0\u10d1\u10e9\u10d8\u10dc\u10ea\u10d8"
    ],
    "name:ron_x_preferred":[
        "Babci\u00een\u021bi"
    ],
    "name:rus_x_preferred":[
        "\u0411\u0430\u0431\u0447\u0438\u043d\u0446\u044b"
    ],
    "name:ukr_x_preferred":[
        "\u0411\u0430\u0431\u0447\u0438\u043d\u0446\u0456"
    ],
    "name:und_x_variant":[
        "Bobchintsy"
    ],
    "name:zho_x_preferred":[
        "\u5df4\u5e03\u6b3d\u9f4a"
    ],
    "qs:a0":"\u0423\u043a\u0440\u0430\u0457\u043d\u0430",
    "qs:a1":"*\u0412\u0456\u043d\u043d\u0438\u0446\u044c\u043a\u0430",
    "qs:a1_alt":"Vinnyts'ka",
    "qs:a1r":"0",
    "qs:a2":"\u0427\u0435\u0440\u043d\u0456\u0432\u0435\u0446\u044c\u043a\u0438\u0439",
    "qs:a2_alt":"Chernivets'kyi",
    "qs:adm0":"\u0423\u043a\u0440\u0430\u0457\u043d\u0430",
    "qs:la_lc":"*",
    "qs:level":"locality",
    "qs:loc":"\u0411\u0430\u0431\u0447\u0438\u043d\u0446\u0456",
    "qs:loc_alt":"Babchyntsi",
    "qs:pop":0,
    "qs:type":"buffered point",
    "wof:name":"\u0411\u0430\u0431\u0447\u0438\u043d\u0446\u0456",
    "wof:placetype":"locality"
},
  "geometry": {"coordinates":[28.171641,48.413532],"type":"Point"}
}