{
  "type": "Feature",
  "properties": {
    "gn:admin1_code":"19.0",
    "gn:asciiname":"Kurhany",
    "gn:country_code":"UA",
    "gn:dem":191,
    "gn:feature_class":"P",
    "gn:feature_code":"PPL",
    "gn:name":"Kurhany",
    "gn:population":0,
    "gn:timezone":"Europe/Kiev",
    "iso:country":"UA",
    "name:ukr_x_preferred":[
        "Kurhany"
    ],
    "name:ukr_x_variant":[
        "\u041a\u0443\u0440\u0433\u0430\u043d\u0438"
    ],
    "name:und_x_variant":[
        "Kurgany"
    ],
    "wof:name":"Kurhany",
    "wof:placetype":"locality"
},
  "geometry": {"coordinates":[26.54017,50.39272],"type":"Point"}
}