{
  "type": "Feature",
  "properties": {
    "iso:country":"UA",
    "name:crh_x_preferred":[
        "Ka\u00e7kivka"
    ],
    "name:eng_x_preferred":[
        "Kachkivka"
    ],
    "name:est_x_preferred":[
        "Kat\u0161kivka"
    ],
    "name:hye_x_preferred":[
        "\u053f\u0561\u0579\u056f\u0578\u057e\u056f\u0561"
    ],
    "name:pol_x_preferred":[
        "Kaczk\u00f3wka"
    ],
    "name:ron_x_preferred":[
        "Kacikivka"
    ],
    "name:rus_x_preferred":[
        "\u041a\u0430\u0447\u043a\u043e\u0432\u043a\u0430"
    ],
    "name:ukr_x_preferred":[
        "\u041a\u0430\u0447\u043a\u0456\u0432\u043a\u0430"
    ],
    "name:unk_x_variant":[
        "Kachkivka"
    ],
    "name:zho_x_preferred":[
        "\u5361\u5947\u57fa\u592b\u5361"
    ],
    "qs:a0":"\u0423\u043a\u0440\u0430\u0457\u043d\u0430",
    "qs:a1":"*\u0412\u0456\u043d\u043d\u0438\u0446\u044c\u043a\u0430",
    "qs:a1_alt":"Vinnyts'ka",
    "qs:a1r":"0",
    "qs:a2":"\u042f\u043c\u043f\u0456\u043b\u044c\u0441\u044c\u043a\u0438\u0439",
    "qs:a2_alt":"Yampil's'kyi",
    "qs:adm0":"\u0423\u043a\u0440\u0430\u0457\u043d\u0430",
    "qs:la_lc":"*",
    "qs:level":"locality",
    "qs:loc":"\u041a\u0430\u0447\u043a\u0456\u0432\u043a\u0430",
    "qs:loc_alt":"Kachkivka",
    "qs:pop":0,
    "qs:type":"buffered point",
    "wof:name":"\u041a\u0430\u0447\u043a\u0456\u0432\u043a\u0430",
    "wof:placetype":"locality"
},
  "geometry": {"coordinates":[28.457336,48.28554],"type":"Point"}
}