{
  "type": "Feature",
  "properties": {
    "gn:admin1_code":"7.0",
    "gn:asciiname":"Syn'kivka",
    "gn:country_code":"UA",
    "gn:dem":87,
    "gn:feature_class":"P",
    "gn:feature_code":"PPL",
    "gn:name":"Syn\u2019kivka",
    "gn:population":0,
    "gn:timezone":"Europe/Kiev",
    "iso:country":"UA",
    "name:ukr_x_preferred":[
        "Syn\u2019kivka"
    ],
    "name:ukr_x_variant":[
        "\u0421\u0438\u043d\u044c\u043a\u0456\u0432\u043a\u0430"
    ],
    "name:und_x_variant":[
        "Sen\u2019kovka",
        "Sin\u2019kovka"
    ],
    "wof:name":"Syn'kivka",
    "wof:placetype":"locality"
},
  "geometry": {"coordinates":[37.6921,49.76267],"type":"Point"}
}