{
  "type": "Feature",
  "properties": {
    "gn:admin1_code":"2.0",
    "gn:asciiname":"Zolotnitskoye",
    "gn:country_code":"UA",
    "gn:dem":159,
    "gn:feature_class":"P",
    "gn:feature_code":"PPL",
    "gn:name":"Zolotnitskoye",
    "gn:population":0,
    "gn:timezone":"Europe/Kiev",
    "iso:country":"UA",
    "name:rus_x_preferred":[
        "\u0417\u043e\u043b\u043e\u0442\u043d\u0438\u0446\u043a\u043e\u0435"
    ],
    "wof:name":"Zolotnitskoye",
    "wof:placetype":"locality"
},
  "geometry": {"coordinates":[32.41284,51.86752],"type":"Point"}
}