{
  "type": "Feature",
  "properties": {
    "iso:country":"UA",
    "name:deu_x_preferred":[
        "Sawodiwka"
    ],
    "name:eng_x_preferred":[
        "Zavodivka"
    ],
    "name:hye_x_preferred":[
        "\u0536\u0561\u057e\u0578\u0564\u0578\u057e\u056f\u0561"
    ],
    "name:lav_x_preferred":[
        "Zavodivka"
    ],
    "name:ron_x_preferred":[
        "Zavodivka"
    ],
    "name:rus_x_preferred":[
        "\u0417\u0430\u0432\u043e\u0434\u043e\u0432\u043a\u0430"
    ],
    "name:spa_x_preferred":[
        "Zavodivka"
    ],
    "name:ukr_x_preferred":[
        "Zavodivka"
    ],
    "name:ukr_x_variant":[
        "\u0417\u0430\u0432\u043e\u0434\u0456\u0432\u043a\u0430"
    ],
    "name:und_x_variant":[
        "Zavodovka"
    ],
    "name:zho_x_preferred":[
        "\u624e\u6c83\u5b63\u592b\u5361"
    ],
    "qs:a0":"\u0423\u043a\u0440\u0430\u0457\u043d\u0430",
    "qs:a1":"*\u041e\u0434\u0435\u0441\u044c\u043a\u0430",
    "qs:a1_alt":"Odes'ka",
    "qs:a1r":"0",
    "qs:a2":"\u0411\u0435\u0440\u0435\u0437\u0456\u0432\u0441\u044c\u043a\u0438\u0439",
    "qs:a2_alt":"Berezivs'kyi",
    "qs:adm0":"\u0423\u043a\u0440\u0430\u0457\u043d\u0430",
    "qs:la_lc":"*",
    "qs:level":"locality",
    "qs:loc":"\u0417\u0430\u0432\u043e\u0434\u0456\u0432\u043a\u0430",
    "qs:loc_alt":"Zavodivka",
    "qs:pop":0,
    "qs:type":"buffered point",
    "wof:name":"\u0417\u0430\u0432\u043e\u0434\u0456\u0432\u043a\u0430",
    "wof:placetype":"locality"
},
  "geometry": {"coordinates":[30.801279,47.223562],"type":"Point"}
}