{
  "type": "Feature",
  "properties": {
    "gn:admin1_code":"11.0",
    "gn:admin2_code":"710690",
    "gn:admin3_code":"11153135.0",
    "gn:asciiname":"Kuznetskoye",
    "gn:country_code":"UA",
    "gn:dem":69,
    "gn:elevation":"68.0",
    "gn:feature_class":"P",
    "gn:feature_code":"PPL",
    "gn:name":"Kuznetskoye",
    "gn:population":391,
    "gn:timezone":"Europe/Simferopol",
    "iso:country":"UA",
    "name:eng_x_preferred":[
        "Kuznetskoye"
    ],
    "name:rus_x_historical":[
        "\u0427\u0435\u0433\u0435\u043b\u0435\u0301\u043a"
    ],
    "name:rus_x_preferred":[
        "\u041a\u0443\u0437\u043d\u0435\u0446\u043a\u043e\u0435"
    ],
    "name:rus_x_variant":[
        "\u0427\u0435\u0433\u0435\u043b\u0435\u0301\u043a"
    ],
    "name:ukr_x_preferred":[
        "\u041a\u0443\u0437\u043d\u0435\u0446\u044c\u043a\u0435"
    ],
    "wof:name":"Kuznetskoye",
    "wof:placetype":"locality",
    "wof:population":391
},
  "geometry": {"coordinates":[32.88625,45.46737],"type":"Point"}
}