{
  "type": "Feature",
  "properties": {
    "gn:admin1_code":"4.0",
    "gn:asciiname":"Svobodnoye",
    "gn:country_code":"UA",
    "gn:dem":64,
    "gn:feature_class":"P",
    "gn:feature_code":"PPL",
    "gn:name":"Svobodnoye",
    "gn:population":0,
    "gn:timezone":"Europe/Kiev",
    "iso:country":"UA",
    "wof:name":"Svobodnoye",
    "wof:placetype":"locality"
},
  "geometry": {"coordinates":[35.31667,48.75],"type":"Point"}
}