{
  "type": "Feature",
  "properties": {
    "iso:country":"UA",
    "qs:a0":"\u0423\u043a\u0440\u0430\u0457\u043d\u0430",
    "qs:a1":"*\u0425\u043c\u0435\u043b\u044c\u043d\u0438\u0446\u044c\u043a\u0430",
    "qs:a1_alt":"Khmel'nyts'ka",
    "qs:a1r":"0",
    "qs:a2":"\u0406\u0437\u044f\u0441\u043b\u0430\u0432\u0441\u044c\u043a\u0438\u0439",
    "qs:a2_alt":"Iziaslavs'kyi",
    "qs:adm0":"\u0423\u043a\u0440\u0430\u0457\u043d\u0430",
    "qs:la_lc":"*",
    "qs:level":"locality",
    "qs:loc":"\u041c'\u044f\u043a\u043e\u0442\u0438",
    "qs:loc_alt":"Miakoty",
    "qs:pop":0,
    "qs:type":"buffered point",
    "wof:name":"\u041c'\u044f\u043a\u043e\u0442\u0438",
    "wof:placetype":"locality"
},
  "geometry": {"coordinates":[26.497259,50.18173],"type":"Point"}
}