{
  "type": "Feature",
  "properties": {
    "gn:admin1_code":"7.0",
    "gn:asciiname":"Seredovka",
    "gn:country_code":"UA",
    "gn:dem":126,
    "gn:feature_class":"P",
    "gn:feature_code":"PPL",
    "gn:name":"Seredovka",
    "gn:population":0,
    "gn:timezone":"Europe/Kiev",
    "iso:country":"UA",
    "wof:name":"Seredovka",
    "wof:placetype":"locality"
},
  "geometry": {"coordinates":[36.06639000000001,49.29972],"type":"Point"}
}