{
  "type": "Feature",
  "properties": {
    "gn:population":1301,
    "iso:country":"UA",
    "name:eng_x_preferred":[
        "Chernopolye"
    ],
    "name:rus_x_historical":[
        "\u041a\u0430\u0440\u0430\u0447\u0451\u0301\u043b\u044c"
    ],
    "name:rus_x_preferred":[
        "\u041a\u0430\u0440\u0430\u0447\u0451\u0301\u043b\u044c"
    ],
    "name:rus_x_variant":[
        "\u0427\u0435\u0440\u043d\u043e\u043f\u043e\u043b\u044c\u0435"
    ],
    "name:ukr_x_preferred":[
        "\u0427\u043e\u0440\u043d\u043e\u043f\u0456\u043b\u043b\u044f"
    ],
    "qs:a0":"\u0423\u043a\u0440\u0430\u0457\u043d\u0430",
    "qs:a1":"*\u041a\u0440\u0438\u043c",
    "qs:a1_alt":"Krym",
    "qs:a1r":"0",
    "qs:a2":"\u0411\u0456\u043b\u043e\u0433\u0456\u0440\u0441\u044c\u043a\u0438\u0439",
    "qs:a2_alt":"Bilohirs'kyi",
    "qs:adm0":"\u0423\u043a\u0440\u0430\u0457\u043d\u0430",
    "qs:la_lc":"*",
    "qs:level":"locality",
    "qs:loc":"\u0427\u043e\u0440\u043d\u043e\u043f\u0456\u043b\u043b\u044f",
    "qs:loc_alt":"Chornopillia",
    "qs:pop":0,
    "qs:type":"buffered point",
    "wof:name":"\u0427\u043e\u0440\u043d\u043e\u043f\u0456\u043b\u043b\u044f",
    "wof:placetype":"locality",
    "wof:population":1301
},
  "geometry": {"coordinates":[34.646792,45.044492],"type":"Point"}
}