{
  "type": "Feature",
  "properties": {
    "gn:admin1_code":"21.0",
    "gn:asciiname":"Khvostovtsy",
    "gn:cc2":"UA",
    "gn:country_code":"UA",
    "gn:dem":161,
    "gn:feature_class":"P",
    "gn:feature_code":"PPL",
    "gn:name":"Khvostovtsy",
    "gn:population":0,
    "gn:timezone":"Europe/Kiev",
    "iso:country":"UA",
    "name:und_x_variant":[
        "Khvostivtsy",
        "Khvostovtsy"
    ],
    "wof:name":"Khvostovtsy",
    "wof:placetype":"locality"
},
  "geometry": {"coordinates":[33.65,51.03333],"type":"Point"}
}