{
  "type": "Feature",
  "properties": {
    "gn:admin1_code":"2.0",
    "gn:asciiname":"Zaliznyy Mist",
    "gn:country_code":"UA",
    "gn:dem":156,
    "gn:feature_class":"P",
    "gn:feature_code":"PPL",
    "gn:name":"Zaliznyy Mist",
    "gn:population":0,
    "gn:timezone":"Europe/Kiev",
    "iso:country":"UA",
    "name:eng_x_preferred":[
        "Zheleznyy Most"
    ],
    "name:rus_x_preferred":[
        "\u0416\u0435\u043b\u0435\u0437\u043d\u044b\u0439 \u041c\u043e\u0441\u0442"
    ],
    "name:ukr_x_preferred":[
        "Zaliznyy Mist"
    ],
    "name:ukr_x_variant":[
        "\u0417\u0430\u043b\u0456\u0437\u043d\u0438\u0439 \u041c\u0456\u0441\u0442",
        "Zheleznyy Most",
        "Zhelezny Most"
    ],
    "wof:name":"Zaliznyy Mist",
    "wof:placetype":"locality"
},
  "geometry": {"coordinates":[32.70139,52.21333],"type":"Point"}
}