{
  "type": "Feature",
  "properties": {
    "gn:admin1_code":"7.0",
    "gn:asciiname":"Skovorodynivka",
    "gn:country_code":"UA",
    "gn:dem":182,
    "gn:feature_class":"P",
    "gn:feature_code":"PPL",
    "gn:name":"Skovorodynivka",
    "gn:population":0,
    "gn:timezone":"Europe/Kiev",
    "iso:country":"UA",
    "name:ukr_x_preferred":[
        "Skovorodynivka"
    ],
    "name:ukr_x_variant":[
        "\u0421\u043a\u043e\u0432\u043e\u0440\u043e\u0434\u0438\u043d\u0456\u0432\u043a\u0430"
    ],
    "name:und_x_variant":[
        "Skovorodinovka"
    ],
    "wof:name":"Skovorodynivka",
    "wof:placetype":"locality"
},
  "geometry": {"coordinates":[35.77338,50.15787],"type":"Point"}
}