{
  "type": "Feature",
  "properties": {
    "gn:admin1_code":"14.0",
    "gn:asciiname":"Krynychne",
    "gn:country_code":"UA",
    "gn:dem":107,
    "gn:feature_class":"P",
    "gn:feature_code":"PPL",
    "gn:name":"Krynychne",
    "gn:population":0,
    "gn:timezone":"Europe/Zaporozhye",
    "iso:country":"UA",
    "name:ukr_x_preferred":[
        "Krynychne"
    ],
    "name:ukr_x_variant":[
        "\u041a\u0440\u0438\u043d\u0438\u0447\u043d\u0435"
    ],
    "name:und_x_variant":[
        "Krinichnaya"
    ],
    "wof:name":"Krynychne",
    "wof:placetype":"locality"
},
  "geometry": {"coordinates":[38.71567,48.60399],"type":"Point"}
}