{
  "type": "Feature",
  "properties": {
    "iso:country":"UA",
    "name:deu_x_preferred":[
        "Turji Remety"
    ],
    "name:eng_x_preferred":[
        "Turi Remety"
    ],
    "name:epo_x_preferred":[
        "Turji Remeti"
    ],
    "name:hun_x_preferred":[
        "Turjaremete"
    ],
    "name:hye_x_preferred":[
        "\u054f\u0578\u0582\u0580\u0575\u056b \u054c\u0565\u0574\u0565\u057f\u056b"
    ],
    "name:nld_x_preferred":[
        "Turi Remety"
    ],
    "name:pol_x_preferred":[
        "Turji Remety"
    ],
    "name:ron_x_preferred":[
        "Turii Remet\u00ee"
    ],
    "name:rus_x_preferred":[
        "\u0422\u0443\u0440\u044c\u0438 \u0420\u0435\u043c\u0435\u0442\u044b"
    ],
    "name:slk_x_preferred":[
        "Turie Remety"
    ],
    "name:ukr_x_preferred":[
        "\u0422\u0443\u0440'\u0457 \u0420\u0435\u043c\u0435\u0442\u0438"
    ],
    "name:ukr_x_variant":[
        "\u0422\u0443\u0440\u2019 \u0457 \u0420\u0435\u043c\u0435\u0442\u0438"
    ],
    "name:unk_x_variant":[
        "Tur\u201dyi Remety"
    ],
    "name:zho_x_preferred":[
        "\u5716\u91cc\u4f69\u6885\u5b63"
    ],
    "qs:a0":"\u0423\u043a\u0440\u0430\u0457\u043d\u0430",
    "qs:a1":"*\u0417\u0430\u043a\u0430\u0440\u043f\u0430\u0442\u0441\u044c\u043a\u0430",
    "qs:a1_alt":"Zakarpats'ka",
    "qs:a1r":"0",
    "qs:a2":"\u041f\u0435\u0440\u0435\u0447\u0438\u043d\u0441\u044c\u043a\u0438\u0439",
    "qs:a2_alt":"Perechyns'kyi",
    "qs:adm0":"\u0423\u043a\u0440\u0430\u0457\u043d\u0430",
    "qs:la_lc":"*",
    "qs:level":"locality",
    "qs:loc":"\u0422\u0443\u0440'\u0457 \u0420\u0435\u043c\u0435\u0442\u0438",
    "qs:loc_alt":"Turi Remety",
    "qs:pop":0,
    "qs:type":"buffered point",
    "wd:wordcount":155,
    "wof:name":"\u0422\u0443\u0440'\u0457 \u0420\u0435\u043c\u0435\u0442\u0438",
    "wof:placetype":"locality"
},
  "geometry": {"coordinates":[22.582834,48.724044],"type":"Point"}
}