{
  "type": "Feature",
  "properties": {
    "gn:admin1_code":"15",
    "gn:asciiname":"Antonivka",
    "gn:country_code":"UA",
    "gn:dem":257,
    "gn:feature_class":"P",
    "gn:feature_code":"PPL",
    "gn:name":"Antonivka",
    "gn:population":0,
    "gn:timezone":"Europe/Kiev",
    "iso:country":"UA",
    "name:rus_x_preferred":[
        "\u0410\u043d\u0442\u043e\u043d\u043e\u0432\u043a\u0430"
    ],
    "name:ukr_x_preferred":[
        "Antonivka"
    ],
    "name:ukr_x_variant":[
        "\u0410\u043d\u0442\u043e\u043d\u0456\u0432\u043a\u0430"
    ],
    "name:und_x_variant":[
        "Antonovka"
    ],
    "wof:name":"Antonivka",
    "wof:placetype":"locality"
},
  "geometry": {"coordinates":[24.18771,49.27561],"type":"Point"}
}