{
  "type": "Feature",
  "properties": {
    "gn:admin1_code":"18.0",
    "gn:asciiname":"Novayazhizn'",
    "gn:country_code":"UA",
    "gn:dem":119,
    "gn:feature_class":"P",
    "gn:feature_code":"PPL",
    "gn:name":"Novayazhizn\u2019",
    "gn:population":0,
    "gn:timezone":"Europe/Kiev",
    "iso:country":"UA",
    "wof:name":"Novayazhizn'",
    "wof:placetype":"locality"
},
  "geometry": {"coordinates":[34.50389000000001,50.19139000000001],"type":"Point"}
}