{
  "type": "Feature",
  "properties": {
    "gn:admin1_code":"17.0",
    "gn:asciiname":"Rybal's'ke",
    "gn:country_code":"UA",
    "gn:dem":4,
    "gn:feature_class":"P",
    "gn:feature_code":"PPL",
    "gn:name":"Rybal\u2019s\u2019ke",
    "gn:population":0,
    "gn:timezone":"Europe/Kiev",
    "iso:country":"UA",
    "name:ukr_x_preferred":[
        "Rybal\u2019s\u2019ke"
    ],
    "name:ukr_x_variant":[
        "\u0420\u0438\u0431\u0430\u043b\u044c\u0441\u044c\u043a\u0435"
    ],
    "name:und_x_variant":[
        "Martaza",
        "Rybatskoye",
        "Rybal\u2019skoye"
    ],
    "wof:name":"Rybal's'ke",
    "wof:placetype":"locality"
},
  "geometry": {"coordinates":[29.82996,45.77882],"type":"Point"}
}