{
  "type": "Feature",
  "properties": {
    "gn:admin1_code":"19.0",
    "gn:asciiname":"Velykyy Zholuds'k",
    "gn:country_code":"UA",
    "gn:dem":164,
    "gn:feature_class":"P",
    "gn:feature_code":"PPL",
    "gn:name":"Velykyy Zholuds\u2019k",
    "gn:population":0,
    "gn:timezone":"Europe/Kiev",
    "iso:country":"UA",
    "name:ukr_x_preferred":[
        "Velykyy Zholuds\u2019k"
    ],
    "name:ukr_x_variant":[
        "\u0412\u0435\u043b\u0438\u043a\u0438\u0439 \u0416\u043e\u043b\u0443\u0434\u0441\u044c\u043a"
    ],
    "name:und_x_variant":[
        "Vel\u2019ke Zholudsk",
        "Zholudek",
        "Wielki \u017bo\u0142udzk",
        "Bol\u2019shoy Zh\u00eblutsk",
        "Velikiy Zholudsk"
    ],
    "wof:name":"Velykyy Zholuds'k",
    "wof:placetype":"locality"
},
  "geometry": {"coordinates":[26.10692,51.32024000000001],"type":"Point"}
}