{
  "type": "Feature",
  "properties": {
    "gn:admin1_code":"21.0",
    "gn:asciiname":"Kyryyakivshchyna",
    "gn:country_code":"UA",
    "gn:dem":162,
    "gn:feature_class":"P",
    "gn:feature_code":"PPL",
    "gn:name":"Kyryyakivshchyna",
    "gn:population":0,
    "gn:timezone":"Europe/Kiev",
    "iso:country":"UA",
    "name:ukr_x_preferred":[
        "Kyryyakivshchyna"
    ],
    "name:ukr_x_variant":[
        "\u041a\u0438\u0440\u0438\u044f\u043a\u0456\u0432\u0449\u0438\u043d\u0430"
    ],
    "name:und_x_variant":[
        "Kiriyakovshchina"
    ],
    "wof:name":"Kyryyakivshchyna",
    "wof:placetype":"locality"
},
  "geometry": {"coordinates":[34.84328,50.99135],"type":"Point"}
}