{
  "type": "Feature",
  "properties": {
    "iso:country":"UA",
    "qs:a0":"\u0423\u043a\u0440\u0430\u0457\u043d\u0430",
    "qs:a1":"*\u0406\u0432\u0430\u043d\u043e-\u0424\u0440\u0430\u043d\u043a\u0456\u0432\u0441\u044c\u043a\u0430",
    "qs:a1_alt":"Ivano-Frankivs'ka",
    "qs:a1r":"0",
    "qs:a2":"\u0422\u043b\u0443\u043c\u0430\u0446\u044c\u043a\u0438\u0439",
    "qs:a2_alt":"Tlumats'kyi",
    "qs:adm0":"\u0423\u043a\u0440\u0430\u0457\u043d\u0430",
    "qs:la_lc":"*",
    "qs:level":"locality",
    "qs:loc":"\u041f\u0440\u0438\u0431\u0438\u043b\u0456\u0432",
    "qs:loc_alt":"Prybyliv",
    "qs:pop":0,
    "qs:type":"buffered point",
    "wof:name":"\u041f\u0440\u0438\u0431\u0438\u043b\u0456\u0432",
    "wof:placetype":"locality"
},
  "geometry": {"coordinates":[24.993238,48.778327],"type":"Point"}
}