{
  "type": "Feature",
  "properties": {
    "iso:country":"UA",
    "qs:a0":"\u0423\u043a\u0440\u0430\u0457\u043d\u0430",
    "qs:a1":"*\u041f\u043e\u043b\u0442\u0430\u0432\u0441\u044c\u043a\u0430",
    "qs:a1_alt":"Poltavs'ka",
    "qs:a1r":"0",
    "qs:a2":"\u041b\u0443\u0431\u0435\u043d\u0441\u044c\u043a\u0438\u0439",
    "qs:a2_alt":"Lubens'kyi",
    "qs:adm0":"\u0423\u043a\u0440\u0430\u0457\u043d\u0430",
    "qs:la_lc":"*",
    "qs:level":"locality",
    "qs:loc":"\u0417\u0430\u0441\u0443\u043b\u043b\u044f",
    "qs:loc_alt":"Zasullia",
    "qs:pop":0,
    "qs:type":"buffered point",
    "wof:name":"\u0417\u0430\u0441\u0443\u043b\u043b\u044f",
    "wof:placetype":"locality"
},
  "geometry": {"coordinates":[33.028099,49.984778],"type":"Point"}
}