{
  "type": "Feature",
  "properties": {
    "gn:admin1_code":"2.0",
    "gn:asciiname":"Chervoni Partyzany",
    "gn:country_code":"UA",
    "gn:dem":149,
    "gn:feature_class":"P",
    "gn:feature_code":"PPL",
    "gn:name":"Chervoni Partyzany",
    "gn:population":0,
    "gn:timezone":"Europe/Kiev",
    "iso:country":"UA",
    "name:ukr_x_preferred":[
        "Chervoni Partyzany"
    ],
    "name:ukr_x_variant":[
        "\u0427\u0435\u0440\u0432\u043e\u043d\u0456 \u041f\u0430\u0440\u0442\u0438\u0437\u0430\u043d\u0438"
    ],
    "name:und_x_variant":[
        "Chervonye Partizany"
    ],
    "wof:name":"Chervoni Partyzany",
    "wof:placetype":"locality"
},
  "geometry": {"coordinates":[32.07165999999999,51.57906],"type":"Point"}
}