{
  "type": "Feature",
  "properties": {
    "gn:admin1_code":"7.0",
    "gn:asciiname":"Internatsional'ne",
    "gn:country_code":"UA",
    "gn:dem":177,
    "gn:feature_class":"P",
    "gn:feature_code":"PPL",
    "gn:name":"Internatsional\u2019ne",
    "gn:population":0,
    "gn:timezone":"Europe/Kiev",
    "iso:country":"UA",
    "name:rus_x_preferred":[
        "Internatsional\u2019noye"
    ],
    "name:ukr_x_preferred":[
        "Internatsional\u2019ne"
    ],
    "name:ukr_x_variant":[
        "\u0406\u043d\u0442\u0435\u0440\u043d\u0430\u0446\u0456\u043e\u043d\u0430\u043b\u044c\u043d\u0435"
    ],
    "wof:name":"Internatsional'ne",
    "wof:placetype":"locality"
},
  "geometry": {"coordinates":[36.53246,48.87033],"type":"Point"}
}