{
  "type": "Feature",
  "properties": {
    "gn:admin1_code":"14.0",
    "gn:asciiname":"Khryashchuvate",
    "gn:country_code":"UA",
    "gn:dem":137,
    "gn:feature_class":"P",
    "gn:feature_code":"PPL",
    "gn:name":"Khryashchuvate",
    "gn:population":0,
    "gn:timezone":"Europe/Zaporozhye",
    "iso:country":"UA",
    "name:ukr_x_preferred":[
        "Khryashchuvate"
    ],
    "name:ukr_x_variant":[
        "\u0425\u0440\u044f\u0449\u0443\u0432\u0430\u0442\u0435"
    ],
    "wof:name":"Khryashchuvate",
    "wof:placetype":"locality"
},
  "geometry": {"coordinates":[39.4259,48.51412],"type":"Point"}
}