{
  "type": "Feature",
  "properties": {
    "iso:country":"UA",
    "name:ara_x_preferred":[
        "\u0628\u0648\u0633\u0643"
    ],
    "name:bel_x_preferred":[
        "\u0413\u043e\u0440\u0430\u0434 \u0411\u0443\u0441\u043a"
    ],
    "name:bel_x_variant":[
        "\u0411\u0443\u0441\u043a"
    ],
    "name:ces_x_preferred":[
        "Busk"
    ],
    "name:crh_x_preferred":[
        "Busk"
    ],
    "name:deu_x_preferred":[
        "Busk"
    ],
    "name:eng_x_preferred":[
        "Busk"
    ],
    "name:est_x_preferred":[
        "Busk"
    ],
    "name:fas_x_preferred":[
        "\u0628\u0648\u0633\u06a9\u060c \u0627\u0648\u06a9\u0631\u0627\u06cc\u0646"
    ],
    "name:fas_x_variant":[
        "\u0628\u0648\u0633\u06a9"
    ],
    "name:fra_x_preferred":[
        "Bousk"
    ],
    "name:heb_x_preferred":[
        "\u05d1\u05d5\u05e1\u05e7"
    ],
    "name:hsb_x_preferred":[
        "Busk"
    ],
    "name:hye_x_preferred":[
        "\u0532\u0578\u0582\u057d\u056f"
    ],
    "name:ita_x_preferred":[
        "Busk"
    ],
    "name:jpn_x_preferred":[
        "\u30d6\u30b7\u30af"
    ],
    "name:kat_x_preferred":[
        "\u10d1\u10e3\u10e1\u10d9\u10d8"
    ],
    "name:lav_x_preferred":[
        "Buska"
    ],
    "name:lit_x_preferred":[
        "Buskas"
    ],
    "name:nld_x_preferred":[
        "Busk"
    ],
    "name:nno_x_preferred":[
        "Busk i Ukraina"
    ],
    "name:pol_x_preferred":[
        "Busk"
    ],
    "name:por_x_preferred":[
        "Busk"
    ],
    "name:ron_x_preferred":[
        "Busk"
    ],
    "name:rus_x_preferred":[
        "\u0411\u0443\u0441\u043a"
    ],
    "name:sco_x_preferred":[
        "Busk"
    ],
    "name:spa_x_preferred":[
        "Busk"
    ],
    "name:srp_x_preferred":[
        "\u0411\u0443\u0441\u043a"
    ],
    "name:swe_x_preferred":[
        "Busk"
    ],
    "name:szl_x_preferred":[
        "Bu\u015bk"
    ],
    "name:tat_x_preferred":[
        "\u0411\u0443\u0441\u043a"
    ],
    "name:ukr_x_preferred":[
        "\u0411\u0443\u0441\u044c\u043a"
    ],
    "name:ukr_x_variant":[
        "Bus\u2019k"
    ],
    "name:vie_x_preferred":[
        "Busk"
    ],
    "name:yid_x_preferred":[
        "\u05d1\u05d5\u05e1\u05e7"
    ],
    "name:zho_x_preferred":[
        "\u5e03\u65af\u514b"
    ],
    "qs:a0":"\u0423\u043a\u0440\u0430\u0457\u043d\u0430",
    "qs:a1":"*\u041b\u044c\u0432\u0456\u0432\u0441\u044c\u043a\u0430",
    "qs:a1_alt":"L'vivs'ka",
    "qs:a1r":"0",
    "qs:a2":"\u0411\u0443\u0441\u044c\u043a\u0438\u0439",
    "qs:a2_alt":"Bus'kyi",
    "qs:adm0":"\u0423\u043a\u0440\u0430\u0457\u043d\u0430",
    "qs:la_lc":"*",
    "qs:level":"locality",
    "qs:loc":"\u0411\u0443\u0441\u044c\u043a",
    "qs:loc_alt":"Bus'k",
    "qs:pop":0,
    "qs:type":"buffered point",
    "wd:wordcount":383,
    "wof:name":"\u0411\u0443\u0441\u044c\u043a",
    "wof:placetype":"locality"
},
  "geometry": {"coordinates":[24.592284,49.965252],"type":"Point"}
}