{
  "type": "Feature",
  "properties": {
    "gn:admin1_code":"27.0",
    "gn:asciiname":"Rudnya-Horodishche",
    "gn:country_code":"UA",
    "gn:dem":219,
    "gn:feature_class":"P",
    "gn:feature_code":"PPL",
    "gn:name":"Rudnya-Horodishche",
    "gn:population":0,
    "gn:timezone":"Europe/Kiev",
    "iso:country":"UA",
    "name:ukr_x_preferred":[
        "Rudnya-Horodishche"
    ],
    "name:ukr_x_variant":[
        "\u0420\u0443\u0434\u043d\u044f-\u0413\u043e\u0440\u043e\u0434\u0438\u0449\u0435"
    ],
    "name:und_x_variant":[
        "Rudnya-Gorodishche"
    ],
    "wof:name":"Rudnya-Horodishche",
    "wof:placetype":"locality"
},
  "geometry": {"coordinates":[28.46538,50.0953],"type":"Point"}
}