{
  "type": "Feature",
  "properties": {
    "gn:admin1_code":"27.0",
    "gn:asciiname":"Derzhanivka",
    "gn:country_code":"UA",
    "gn:dem":207,
    "gn:feature_class":"P",
    "gn:feature_code":"PPL",
    "gn:name":"Derzhanivka",
    "gn:population":0,
    "gn:timezone":"Europe/Kiev",
    "iso:country":"UA",
    "name:ukr_x_preferred":[
        "Derzhanivka"
    ],
    "name:ukr_x_variant":[
        "\u0414\u0435\u0440\u0436\u0430\u043d\u0456\u0432\u043a\u0430"
    ],
    "name:und_x_variant":[
        "Derzhanovka"
    ],
    "wof:name":"Derzhanivka",
    "wof:placetype":"locality"
},
  "geometry": {"coordinates":[27.79615,51.06797],"type":"Point"}
}