{
  "type": "Feature",
  "properties": {
    "gn:admin1_code":"15.0",
    "gn:asciiname":"Nestanychi",
    "gn:country_code":"UA",
    "gn:dem":214,
    "gn:feature_class":"P",
    "gn:feature_code":"PPL",
    "gn:name":"Nestanychi",
    "gn:population":0,
    "gn:timezone":"Europe/Kiev",
    "iso:country":"UA",
    "name:ukr_x_preferred":[
        "\u041d\u0435\u0441\u0442\u0430\u043d\u0438\u0447\u0456"
    ],
    "name:und_x_variant":[
        "Nestanitse",
        "Niestanice",
        "Nestanitsy",
        "Nestanichi"
    ],
    "wof:name":"Nestanychi",
    "wof:placetype":"locality"
},
  "geometry": {"coordinates":[24.4916,50.2441],"type":"Point"}
}