{
  "type": "Feature",
  "properties": {
    "gn:admin1_code":"2.0",
    "gn:asciiname":"Kukharka",
    "gn:country_code":"UA",
    "gn:dem":164,
    "gn:feature_class":"P",
    "gn:feature_code":"PPL",
    "gn:name":"Kukharka",
    "gn:population":0,
    "gn:timezone":"Europe/Kiev",
    "iso:country":"UA",
    "name:ukr_x_preferred":[
        "Kukharka"
    ],
    "name:ukr_x_variant":[
        "\u041a\u0443\u0445\u0430\u0440\u043a\u0430"
    ],
    "wof:name":"Kukharka",
    "wof:placetype":"locality"
},
  "geometry": {"coordinates":[32.9077,50.44899],"type":"Point"}
}