{
  "type": "Feature",
  "properties": {
    "gn:admin1_code":"14.0",
    "gn:asciiname":"Dubivs'kyy",
    "gn:country_code":"UA",
    "gn:dem":256,
    "gn:feature_class":"P",
    "gn:feature_code":"PPL",
    "gn:name":"Dubivs\u2019kyy",
    "gn:population":0,
    "gn:timezone":"Europe/Zaporozhye",
    "iso:country":"UA",
    "name:rus_x_preferred":[
        "Vasil\u2019yevka"
    ],
    "name:ukr_x_preferred":[
        "Dubivs\u2019kyy"
    ],
    "name:ukr_x_variant":[
        "\u0414\u0443\u0431\u0456\u0432\u0441\u044c\u043a\u0438\u0439"
    ],
    "name:und_x_variant":[
        "Dubovskiy"
    ],
    "wof:name":"Dubivs'kyy",
    "wof:placetype":"locality"
},
  "geometry": {"coordinates":[39.14889,48.08333],"type":"Point"}
}