{
  "type": "Feature",
  "properties": {
    "gn:admin1_code":"24.0",
    "gn:asciiname":"Byten'",
    "gn:country_code":"UA",
    "gn:dem":184,
    "gn:feature_class":"P",
    "gn:feature_code":"PPL",
    "gn:name":"Byten\u2019",
    "gn:population":0,
    "gn:timezone":"Europe/Kiev",
    "iso:country":"UA",
    "name:rus_x_preferred":[
        "Biten\u2019"
    ],
    "name:ukr_x_preferred":[
        "Byten\u2019"
    ],
    "name:ukr_x_variant":[
        "\u0411\u0438\u0442\u0435\u043d\u044c"
    ],
    "wof:name":"Byten'",
    "wof:placetype":"locality"
},
  "geometry": {"coordinates":[24.97718,51.13025],"type":"Point"}
}