{
  "type": "Feature",
  "properties": {
    "gn:admin1_code":"19.0",
    "gn:asciiname":"Bilyatychi",
    "gn:country_code":"UA",
    "gn:dem":145,
    "gn:feature_class":"P",
    "gn:feature_code":"PPL",
    "gn:name":"Bilyatychi",
    "gn:population":0,
    "gn:timezone":"Europe/Kiev",
    "iso:country":"UA",
    "name:ukr_x_preferred":[
        "Bilyatychi"
    ],
    "name:ukr_x_variant":[
        "\u0411\u0456\u043b\u044f\u0442\u0438\u0447\u0456"
    ],
    "name:und_x_variant":[
        "Belyatyche",
        "Belyatichi"
    ],
    "wof:name":"Bilyatychi",
    "wof:placetype":"locality"
},
  "geometry": {"coordinates":[26.56598,51.46478],"type":"Point"}
}