{
  "type": "Feature",
  "properties": {
    "gn:admin1_code":"24.0",
    "gn:asciiname":"Martselyuvka Pervaya",
    "gn:cc2":"UA",
    "gn:country_code":"UA",
    "gn:dem":231,
    "gn:feature_class":"P",
    "gn:feature_code":"PPL",
    "gn:name":"Martselyuvka Pervaya",
    "gn:population":0,
    "gn:timezone":"Europe/Kiev",
    "iso:country":"UA",
    "name:und_x_variant":[
        "Martselyuvka",
        "Martselyuvka Pervaya"
    ],
    "wof:name":"Martselyuvka Pervaya",
    "wof:placetype":"locality"
},
  "geometry": {"coordinates":[24.38333,50.88333],"type":"Point"}
}