{
  "type": "Feature",
  "properties": {
    "gn:admin1_code":"15.0",
    "gn:asciiname":"Pervyatyche",
    "gn:country_code":"UA",
    "gn:dem":221,
    "gn:feature_class":"P",
    "gn:feature_code":"PPL",
    "gn:name":"Pervyatyche",
    "gn:population":0,
    "gn:timezone":"Europe/Kiev",
    "iso:country":"UA",
    "name:ukr_x_preferred":[
        "Perv\u201dyatychi"
    ],
    "name:ukr_x_variant":[
        "\u041f\u0435\u0440\u0432\u2019\u044f\u0442\u0438\u0447\u0456"
    ],
    "name:und_x_variant":[
        "Perev\u201dyatychi",
        "Pervyatyche",
        "Perevyatichi"
    ],
    "wof:name":"Pervyatyche",
    "wof:placetype":"locality"
},
  "geometry": {"coordinates":[24.45732000000001,50.4567],"type":"Point"}
}