{
  "type": "Feature",
  "properties": {
    "iso:country":"UA",
    "name:ukr_x_preferred":[
        "\u041a\u043e\u0440\u0447\u0443\u0432\u0430\u0442\u0435"
    ],
    "wof:name":"Korchuvate",
    "wof:placetype":"neighbourhood"
},
  "geometry": {"coordinates":[30.55449658523636,50.36493475962952],"type":"Point"}
}