{
  "type": "Feature",
  "properties": {
    "gn:admin1_code":"15.0",
    "gn:asciiname":"Sasiv",
    "gn:country_code":"UA",
    "gn:dem":272,
    "gn:elevation":"265.0",
    "gn:feature_class":"P",
    "gn:feature_code":"PPL",
    "gn:name":"Sasiv",
    "gn:population":0,
    "gn:timezone":"Europe/Kiev",
    "iso:country":"UA",
    "name:deu_x_preferred":[
        "Sassiw"
    ],
    "name:heb_x_preferred":[
        "\u05e1\u05d0\u05e1\u05d5\u05d1"
    ],
    "name:pol_x_preferred":[
        "Sas\u00f3w"
    ],
    "name:ron_x_preferred":[
        "Sasiv"
    ],
    "name:rus_x_preferred":[
        "\u0421\u0430\u0441\u043e\u0432"
    ],
    "name:ukr_x_preferred":[
        "\u0421\u0430\u0441\u0456\u0432"
    ],
    "name:und_x_variant":[
        "Sas\u00f3w",
        "Sasuv",
        "Sasov"
    ],
    "name:zho_x_preferred":[
        "\u85a9\u897f\u592b"
    ],
    "wof:name":"Sasiv",
    "wof:placetype":"locality"
},
  "geometry": {"coordinates":[24.94696,49.8736],"type":"Point"}
}