{
  "type": "Feature",
  "properties": {
    "gn:admin1_code":"15.0",
    "gn:asciiname":"Sasiv",
    "gn:country_code":"UA",
    "gn:dem":272,
    "gn:elevation":"265.0",
    "gn:feature_class":"P",
    "gn:feature_code":"PPL",
    "gn:name":"Sasiv",
    "gn:population":0,
    "gn:timezone":"Europe/Kiev",
    "iso:country":"UA",
    "name:und_x_variant":[
        "Sas\u00f3w",
        "Sasuv",
        "Sasov"
    ],
    "wof:name":"Sasiv",
    "wof:placetype":"locality"
},
  "geometry": {"coordinates":[24.94696,49.8736],"type":"Point"}
}