{
  "type": "Feature",
  "properties": {
    "gn:population":5977,
    "iso:country":"UA",
    "name:deu_x_preferred":[
        "Staryj Krym"
    ],
    "name:eng_x_preferred":[
        "Staryy Krym"
    ],
    "name:hye_x_preferred":[
        "\u054d\u057f\u0561\u0580\u056b\u0575 \u053f\u0580\u056b\u0574"
    ],
    "name:lav_x_preferred":[
        "Starijkrima"
    ],
    "name:rus_x_preferred":[
        "\u0421\u0442\u0430\u0440\u044b\u0439 \u041a\u0440\u044b\u043c"
    ],
    "name:ukr_x_preferred":[
        "\u0421\u0442\u0430\u0440\u0438\u0439 \u041a\u0440\u0438\u043c"
    ],
    "name:unk_x_variant":[
        "Stary Krym"
    ],
    "name:zho_x_preferred":[
        "\u820a\u514b\u91cc\u59c6"
    ],
    "qs:a0":"\u0423\u043a\u0440\u0430\u0457\u043d\u0430",
    "qs:a1":"*\u0414\u043e\u043d\u0435\u0446\u044c\u043a\u0430",
    "qs:a1_alt":"Donets'ka",
    "qs:a1r":"0",
    "qs:a2":"\u041d\u043e\u0432\u043e\u0430\u0437\u043e\u0432\u0441\u044c\u043a\u0438\u0439",
    "qs:a2_alt":"Novoazovs'kyi",
    "qs:adm0":"\u0423\u043a\u0440\u0430\u0457\u043d\u0430",
    "qs:la_lc":"*",
    "qs:level":"locality",
    "qs:loc":"\u0421\u0442\u0430\u0440\u0438\u0439 \u041a\u0440\u0438\u043c",
    "qs:loc_alt":"Staryi Krym",
    "qs:pop":0,
    "qs:type":"buffered point",
    "wd:elevation":300.0,
    "wd:wordcount":1229,
    "wof:name":"\u0421\u0442\u0430\u0440\u0438\u0439 \u041a\u0440\u0438\u043c",
    "wof:placetype":"locality",
    "wof:population":5977
},
  "geometry": {"coordinates":[37.494117,47.157976],"type":"Point"}
}