{
  "type": "Feature",
  "properties": {
    "gn:admin1_code":"21.0",
    "gn:asciiname":"Pishkove",
    "gn:country_code":"UA",
    "gn:dem":148,
    "gn:feature_class":"P",
    "gn:feature_code":"PPL",
    "gn:name":"Pishkove",
    "gn:population":0,
    "gn:timezone":"Europe/Kiev",
    "iso:country":"UA",
    "name:ukr_x_preferred":[
        "Pishkove"
    ],
    "name:ukr_x_variant":[
        "\u041f\u0456\u0448\u043a\u043e\u0432\u0435"
    ],
    "name:und_x_variant":[
        "Peshkovo"
    ],
    "wof:name":"Pishkove",
    "wof:placetype":"locality"
},
  "geometry": {"coordinates":[33.91828,51.29799000000001],"type":"Point"}
}