{
  "type": "Feature",
  "properties": {
    "gn:country":"UA",
    "gn:fcode":"PPL",
    "gn:population":1135,
    "iso:country":"UA",
    "name:bel_x_preferred":[
        "\u041f\u0430\u045e\u043b\u0430\u045e\u043a\u0430"
    ],
    "name:ceb_x_preferred":[
        "Pavlivka"
    ],
    "name:crh_x_preferred":[
        "Pavlivka"
    ],
    "name:eng_x_preferred":[
        "Pavlivka"
    ],
    "name:fra_x_preferred":[
        "Paw\u0142\u00f3wka"
    ],
    "name:hye_x_preferred":[
        "\u054a\u0561\u057e\u056c\u0578\u057e\u056f\u0561"
    ],
    "name:pol_x_preferred":[
        "Paw\u0142\u00f3wka"
    ],
    "name:rus_x_preferred":[
        "\u041f\u0430\u0432\u043b\u043e\u0432\u043a\u0430"
    ],
    "name:ukr_x_preferred":[
        "\u041f\u0430\u0432\u043b\u0456\u0432\u043a\u0430"
    ],
    "name:ukr_x_variant":[
        "\u041f\u0430\u0432\u043b\u0443\u0432\u043a\u0430"
    ],
    "name:und_x_variant":[
        "Pavlovka"
    ],
    "qs_pg:aaroncc":"UA",
    "qs_pg:gn_country":"UA",
    "qs_pg:gn_fcode":"PPL",
    "qs_pg:gn_pop":1135,
    "qs_pg:name":"Pavlivka",
    "qs_pg:photos_9r":0,
    "qs_pg:photos_sr":0,
    "qs_pg:pop_sr":3,
    "qs_pg:qs_pg_placetype":"locality",
    "wof:name":"Pavlivka",
    "wof:placetype":"locality",
    "wof:population":1135
},
  "geometry": {"coordinates":[38.70917,49.60864],"type":"Point"}
}