{
  "type": "Feature",
  "properties": {
    "gn:gn_country":"UA",
    "gn:gn_fcode":"PPL",
    "gn:gn_pop":1135,
    "gn:population":1135,
    "iso:country":"UA",
    "name:eng_x_preferred":[
        "Pavlivka"
    ],
    "name:rus_x_preferred":[
        "\u041f\u0430\u0432\u043b\u043e\u0432\u043a\u0430"
    ],
    "name:ukr_x_preferred":[
        "\u041f\u0430\u0432\u043b\u0456\u0432\u043a\u0430"
    ],
    "name:unk_x_variant":[
        "Pavlovka"
    ],
    "qs_pg:aaroncc":"UA",
    "qs_pg:gn_country":"UA",
    "qs_pg:gn_fcode":"PPL",
    "qs_pg:gn_pop":1135,
    "qs_pg:name":"Pavlivka",
    "qs_pg:photos_9r":0,
    "qs_pg:photos_sr":0,
    "qs_pg:pop_sr":3,
    "qs_pg:qs_pg_placetype":"locality",
    "wof:name":"Pavlivka",
    "wof:placetype":"locality",
    "wof:population":1135
},
  "geometry": {"coordinates":[38.70917,49.60864],"type":"Point"}
}