{
  "type": "Feature",
  "properties": {
    "gn:admin1_code":"7.0",
    "gn:asciiname":"Shchurivka",
    "gn:country_code":"UA",
    "gn:dem":92,
    "gn:feature_class":"P",
    "gn:feature_code":"PPL",
    "gn:name":"Shchurivka",
    "gn:population":0,
    "gn:timezone":"Europe/Kiev",
    "iso:country":"UA",
    "name:ukr_x_preferred":[
        "\u0429\u0443\u0440\u0456\u0432\u043a\u0430"
    ],
    "name:und_x_variant":[
        "Shurovka",
        "Shchurovka"
    ],
    "wof:name":"Shchurivka",
    "wof:placetype":"locality"
},
  "geometry": {"coordinates":[36.93253,49.39852],"type":"Point"}
}