{
  "type": "Feature",
  "properties": {
    "gn:admin1_code":"2.0",
    "gn:asciiname":"Slobidka",
    "gn:country_code":"UA",
    "gn:dem":118,
    "gn:feature_class":"P",
    "gn:feature_code":"PPL",
    "gn:name":"Slobidka",
    "gn:population":0,
    "gn:timezone":"Europe/Kiev",
    "iso:country":"UA",
    "name:ukr_x_preferred":[
        "Slobidka"
    ],
    "name:ukr_x_variant":[
        "\u0421\u043b\u043e\u0431\u0456\u0434\u043a\u0430"
    ],
    "name:und_x_variant":[
        "Slobodka"
    ],
    "wof:name":"Slobidka",
    "wof:placetype":"locality"
},
  "geometry": {"coordinates":[32.846,51.36459],"type":"Point"}
}