{
  "type": "Feature",
  "properties": {
    "gn:admin1_code":"27.0",
    "gn:asciiname":"Serednya",
    "gn:country_code":"UA",
    "gn:dem":231,
    "gn:feature_class":"P",
    "gn:feature_code":"PPL",
    "gn:name":"Serednya",
    "gn:population":0,
    "gn:timezone":"Europe/Kiev",
    "iso:country":"UA",
    "name:ukr_x_preferred":[
        "Serednya"
    ],
    "name:ukr_x_variant":[
        "\u0421\u0435\u0440\u0435\u0434\u043d\u044f"
    ],
    "wof:name":"Serednya",
    "wof:placetype":"locality"
},
  "geometry": {"coordinates":[27.55826,50.33626],"type":"Point"}
}