{
  "type": "Feature",
  "properties": {
    "gn:admin1_code":"18.0",
    "gn:asciiname":"Bytakove Ozero",
    "gn:country_code":"UA",
    "gn:dem":94,
    "gn:feature_class":"P",
    "gn:feature_code":"PPL",
    "gn:name":"Bytakove Ozero",
    "gn:population":0,
    "gn:timezone":"Europe/Kiev",
    "iso:country":"UA",
    "name:ukr_x_preferred":[
        "Bytakove Ozero"
    ],
    "name:ukr_x_variant":[
        "\u0411\u0438\u0442\u0430\u043a\u043e\u0432\u0435 \u041e\u0437\u0435\u0440\u043e"
    ],
    "wof:name":"Bytakove Ozero",
    "wof:placetype":"locality"
},
  "geometry": {"coordinates":[33.12487,49.39594],"type":"Point"}
}