{
  "type": "Feature",
  "properties": {
    "iso:country":"UA",
    "qs_pg:aaroncc":"UA",
    "qs_pg:name":"Nezhin",
    "qs_pg:name_adm0":"Ukraine",
    "qs_pg:name_adm1":"Chernihivs\u00b4ka Oblast\u00b4",
    "qs_pg:photos":24,
    "qs_pg:photos_1k":5,
    "qs_pg:photos_9k":1,
    "qs_pg:photos_9r":1,
    "qs_pg:photos_all":24,
    "qs_pg:photos_sr":1,
    "qs_pg:pop_sr":0,
    "qs_pg:qs_pg_placetype":"locality",
    "qs_pg:qs_pg_placetype_gp":"Town",
    "qs_pg:woe_adm0":23424976,
    "woe:adm0_id":23424976,
    "woe:name_adm0":"Ukraine",
    "woe:name_adm1":"Chernihivs\u00b4ka Oblast\u00b4",
    "woe:placetype":"Town",
    "wof:name":"Nezhin",
    "wof:placetype":"locality"
},
  "geometry": {"coordinates":[31.886701,51.047653],"type":"Point"}
}