{
  "type": "Feature",
  "properties": {
    "gn:admin1_code":"27.0",
    "gn:asciiname":"Zhurzhevychi",
    "gn:country_code":"UA",
    "gn:dem":170,
    "gn:feature_class":"P",
    "gn:feature_code":"PPL",
    "gn:name":"Zhurzhevychi",
    "gn:population":0,
    "gn:timezone":"Europe/Kiev",
    "iso:country":"UA",
    "name:ukr_x_preferred":[
        "Zhurzhevychi"
    ],
    "name:ukr_x_variant":[
        "\u0416\u0443\u0440\u0436\u0435\u0432\u0438\u0447\u0456"
    ],
    "name:und_x_variant":[
        "Zhurzhevichi"
    ],
    "wof:name":"Zhurzhevychi",
    "wof:placetype":"locality"
},
  "geometry": {"coordinates":[27.71111,51.41248],"type":"Point"}
}