{
  "type": "Feature",
  "properties": {
    "gn:admin1_code":"26.0",
    "gn:asciiname":"Mykil's'ke",
    "gn:country_code":"UA",
    "gn:dem":89,
    "gn:feature_class":"P",
    "gn:feature_code":"PPL",
    "gn:name":"Mykil\u2019s\u2019ke",
    "gn:population":0,
    "gn:timezone":"Europe/Zaporozhye",
    "iso:country":"UA",
    "name:ukr_x_preferred":[
        "Mykil\u2019s\u2019ke"
    ],
    "name:ukr_x_variant":[
        "\u041c\u0438\u043a\u0456\u043b\u044c\u0441\u044c\u043a\u0435"
    ],
    "name:und_x_variant":[
        "Nikol\u2019skiy",
        "Nikol\u2019skoye"
    ],
    "wof:name":"Mykil's'ke",
    "wof:placetype":"locality"
},
  "geometry": {"coordinates":[35.56335,47.90285],"type":"Point"}
}