{
  "type": "Feature",
  "properties": {
    "iso:country":"UA",
    "name:ukr_x_preferred":[
        "\u041c\u0438\u043a\u043e\u043b\u0430\u0457\u0432\u043a\u0430"
    ],
    "qs:a0":"\u0423\u043a\u0440\u0430\u0457\u043d\u0430",
    "qs:a1":"*\u0414\u043e\u043d\u0435\u0446\u044c\u043a\u0430",
    "qs:a1_alt":"Donets'ka",
    "qs:a1r":"0",
    "qs:a2":"\u0421\u043b\u043e\u0432'\u044f\u043d\u0441\u044c\u043a\u0438\u0439",
    "qs:a2_alt":"Slovyans'kyi",
    "qs:adm0":"\u0423\u043a\u0440\u0430\u0457\u043d\u0430",
    "qs:la_lc":"*",
    "qs:level":"locality",
    "qs:loc":"\u041c\u0438\u043a\u043e\u043b\u0430\u0457\u0432\u043a\u0430",
    "qs:loc_alt":"Mykolaivka",
    "qs:pop":0,
    "qs:type":"buffered point",
    "wd:wordcount":110,
    "wof:name":"\u041c\u0438\u043a\u043e\u043b\u0430\u0457\u0432\u043a\u0430",
    "wof:placetype":"locality"
},
  "geometry": {"coordinates":[37.752075,48.864465],"type":"Point"}
}