{
  "type": "Feature",
  "properties": {
    "iso:country":"UA",
    "name:eng_x_preferred":[
        "Peski"
    ],
    "name:rus_x_preferred":[
        "\u041f\u0435\u0441\u043a\u0438"
    ],
    "name:ukr_x_preferred":[
        "Pisky"
    ],
    "name:ukr_x_variant":[
        "\u041f\u0456\u0441\u043a\u0438"
    ],
    "qs:a0":"\u0423\u043a\u0440\u0430\u0457\u043d\u0430",
    "qs:a1":"*\u041f\u043e\u043b\u0442\u0430\u0432\u0441\u044c\u043a\u0430",
    "qs:a1_alt":"Poltavs'ka",
    "qs:a1r":"0",
    "qs:a2":"\u041b\u043e\u0445\u0432\u0438\u0446\u044c\u043a\u0438\u0439",
    "qs:a2_alt":"Lokhvyts'kyi",
    "qs:adm0":"\u0423\u043a\u0440\u0430\u0457\u043d\u0430",
    "qs:la_lc":"*",
    "qs:level":"locality",
    "qs:loc":"\u041f\u0456\u0441\u043a\u0438",
    "qs:loc_alt":"Pisky",
    "qs:pop":0,
    "qs:type":"buffered point",
    "wd:wordcount":524,
    "wof:name":"\u041f\u0456\u0441\u043a\u0438",
    "wof:placetype":"locality"
},
  "geometry": {"coordinates":[33.437829,50.372343],"type":"Point"}
}