{
  "type": "Feature",
  "properties": {
    "gn:admin1_code":"17.0",
    "gn:asciiname":"Samarka",
    "gn:country_code":"UA",
    "gn:dem":129,
    "gn:feature_class":"P",
    "gn:feature_code":"PPL",
    "gn:name":"Samarka",
    "gn:population":0,
    "gn:timezone":"Europe/Kiev",
    "iso:country":"UA",
    "name:ukr_x_preferred":[
        "\u0421\u0430\u043c\u0430\u0440\u043a\u0430"
    ],
    "wof:name":"Samarka",
    "wof:placetype":"locality"
},
  "geometry": {"coordinates":[29.31357,47.49183],"type":"Point"}
}