{
  "type": "Feature",
  "properties": {
    "gn:admin1_code":"7.0",
    "gn:asciiname":"Birky",
    "gn:country_code":"UA",
    "gn:dem":183,
    "gn:feature_class":"P",
    "gn:feature_code":"PPL",
    "gn:name":"Birky",
    "gn:population":0,
    "gn:timezone":"Europe/Kiev",
    "iso:country":"UA",
    "name:deu_x_preferred":[
        "Birky"
    ],
    "name:hye_x_preferred":[
        "\u0532\u0578\u0580\u056f\u056b"
    ],
    "name:rus_x_preferred":[
        "\u0411\u043e\u0440\u043a\u0438"
    ],
    "name:swe_x_preferred":[
        "Birky"
    ],
    "name:ukr_x_preferred":[
        "Birky"
    ],
    "name:ukr_x_variant":[
        "\u0411\u0456\u0440\u043a\u0438"
    ],
    "name:zho_x_preferred":[
        "\u6bd4\u723e\u57fa"
    ],
    "wof:name":"Birky",
    "wof:placetype":"locality"
},
  "geometry": {"coordinates":[36.05046,49.7224],"type":"Point"}
}