{
  "type": "Feature",
  "properties": {
    "gn:admin1_code":"21.0",
    "gn:asciiname":"Dihtyarivka",
    "gn:country_code":"UA",
    "gn:dem":129,
    "gn:feature_class":"P",
    "gn:feature_code":"PPL",
    "gn:name":"Dihtyarivka",
    "gn:population":0,
    "gn:timezone":"Europe/Kiev",
    "iso:country":"UA",
    "name:ukr_x_preferred":[
        "Dihtyarivka"
    ],
    "name:ukr_x_variant":[
        "\u0414\u0456\u0433\u0442\u044f\u0440\u0456\u0432\u043a\u0430"
    ],
    "name:und_x_variant":[
        "Degtyarevka"
    ],
    "wof:name":"Dihtyarivka",
    "wof:placetype":"locality"
},
  "geometry": {"coordinates":[33.71384,50.812],"type":"Point"}
}