{
  "type": "Feature",
  "properties": {
    "gn:admin1_code":"15.0",
    "gn:asciiname":"Zavydche",
    "gn:country_code":"UA",
    "gn:dem":205,
    "gn:feature_class":"P",
    "gn:feature_code":"PPL",
    "gn:name":"Zavydche",
    "gn:population":0,
    "gn:timezone":"Europe/Kiev",
    "iso:country":"UA",
    "name:ukr_x_preferred":[
        "Zavydche"
    ],
    "name:ukr_x_variant":[
        "\u0417\u0430\u0432\u0438\u0434\u0447\u0435"
    ],
    "name:und_x_variant":[
        "Zawidcze",
        "Zavidche"
    ],
    "wof:name":"Zavydche",
    "wof:placetype":"locality"
},
  "geometry": {"coordinates":[24.9339,50.29589],"type":"Point"}
}