{
  "type": "Feature",
  "properties": {
    "gn:admin1_code":"21.0",
    "gn:asciiname":"Hudivshchyna",
    "gn:country_code":"UA",
    "gn:dem":172,
    "gn:feature_class":"P",
    "gn:feature_code":"PPL",
    "gn:name":"Hudivshchyna",
    "gn:population":0,
    "gn:timezone":"Europe/Kiev",
    "iso:country":"UA",
    "name:ukr_x_preferred":[
        "Hudivshchyna"
    ],
    "name:ukr_x_variant":[
        "\u0413\u0443\u0434\u0456\u0432\u0449\u0438\u043d\u0430"
    ],
    "name:und_x_variant":[
        "Gudovshchina"
    ],
    "wof:name":"Hudivshchyna",
    "wof:placetype":"locality"
},
  "geometry": {"coordinates":[33.60145,52.05783],"type":"Point"}
}