{
  "type": "Feature",
  "properties": {
    "gn:admin1_code":"24.0",
    "gn:asciiname":"Nosovychi",
    "gn:country_code":"UA",
    "gn:dem":225,
    "gn:feature_class":"P",
    "gn:feature_code":"PPL",
    "gn:name":"Nosovychi",
    "gn:population":0,
    "gn:timezone":"Europe/Kiev",
    "iso:country":"UA",
    "name:ukr_x_preferred":[
        "Nosovychi"
    ],
    "name:ukr_x_variant":[
        "\u041d\u043e\u0441\u043e\u0432\u0438\u0447\u0456"
    ],
    "name:und_x_variant":[
        "Nosovichi"
    ],
    "wof:name":"Nosovychi",
    "wof:placetype":"locality"
},
  "geometry": {"coordinates":[25.75953,50.68795],"type":"Point"}
}