{
  "type": "Feature",
  "properties": {
    "gn:admin1_code":"7.0",
    "gn:asciiname":"Kazachenkivka",
    "gn:country_code":"UA",
    "gn:dem":171,
    "gn:feature_class":"P",
    "gn:feature_code":"PPL",
    "gn:name":"Kazachenkivka",
    "gn:population":0,
    "gn:timezone":"Europe/Kiev",
    "iso:country":"UA",
    "name:ukr_x_preferred":[
        "Kazachenkivka"
    ],
    "name:ukr_x_variant":[
        "\u041a\u0430\u0437\u0430\u0447\u0435\u043d\u043a\u0456\u0432\u043a\u0430"
    ],
    "wof:name":"Kazachenkivka",
    "wof:placetype":"locality"
},
  "geometry": {"coordinates":[35.64435,49.78206],"type":"Point"}
}