{
  "type": "Feature",
  "properties": {
    "gn:admin1_code":"26.0",
    "gn:asciiname":"Bekarivka",
    "gn:country_code":"UA",
    "gn:dem":64,
    "gn:feature_class":"P",
    "gn:feature_code":"PPL",
    "gn:name":"Bekarivka",
    "gn:population":0,
    "gn:timezone":"Europe/Zaporozhye",
    "iso:country":"UA",
    "name:ukr_x_preferred":[
        "Bekarivka"
    ],
    "name:ukr_x_variant":[
        "\u0411\u0435\u043a\u0430\u0440\u0456\u0432\u043a\u0430"
    ],
    "name:und_x_variant":[
        "Bekkerovka",
        "Bekarovka"
    ],
    "wof:name":"Bekarivka",
    "wof:placetype":"locality"
},
  "geometry": {"coordinates":[35.43235,47.8592],"type":"Point"}
}