{
  "type": "Feature",
  "properties": {
    "iso:country":"UA",
    "name:che_x_preferred":[
        "\u0412\u0435\u043f\u0440\u0438\u043a"
    ],
    "name:deu_x_preferred":[
        "Alexander Moissejewitsch Weprik"
    ],
    "name:deu_x_variant":[
        "Wepryk"
    ],
    "name:eng_x_preferred":[
        "Veprik"
    ],
    "name:eng_x_variant":[
        "Vepryk"
    ],
    "name:fin_x_preferred":[
        "V\u0435pryk"
    ],
    "name:fra_x_preferred":[
        "Veprik"
    ],
    "name:heb_x_preferred":[
        "\u05d5\u05e4\u05e8\u05d9\u05e7"
    ],
    "name:hye_x_preferred":[
        "\u054e\u0565\u057a\u0580\u056b\u056f"
    ],
    "name:kat_x_preferred":[
        "\u10d5\u10d4\u10de\u10e0\u10d8\u10d9\u10d8"
    ],
    "name:lav_x_preferred":[
        "Veprika"
    ],
    "name:nan_x_preferred":[
        "Vepryk"
    ],
    "name:nno_x_preferred":[
        "Vepryk"
    ],
    "name:nob_x_preferred":[
        "Vepryk"
    ],
    "name:pol_x_preferred":[
        "Wepryk"
    ],
    "name:ron_x_preferred":[
        "Vepr\u00eek"
    ],
    "name:rus_x_preferred":[
        "\u0412\u0435\u043f\u0440\u0438\u043a"
    ],
    "name:swe_x_preferred":[
        "Veprik"
    ],
    "name:ukr_x_preferred":[
        "Vepryk"
    ],
    "name:ukr_x_variant":[
        "\u0412\u0435\u043f\u0440\u0438\u043a"
    ],
    "name:zho_x_preferred":[
        "\u97cb\u666e\u91cc\u514b"
    ],
    "qs:a0":"\u0423\u043a\u0440\u0430\u0457\u043d\u0430",
    "qs:a1":"*\u041f\u043e\u043b\u0442\u0430\u0432\u0441\u044c\u043a\u0430",
    "qs:a1_alt":"Poltavs'ka",
    "qs:a1r":"0",
    "qs:a2":"\u0413\u0430\u0434\u044f\u0446\u044c\u043a\u0438\u0439",
    "qs:a2_alt":"Hadiats'kyi",
    "qs:adm0":"\u0423\u043a\u0440\u0430\u0457\u043d\u0430",
    "qs:la_lc":"*",
    "qs:level":"locality",
    "qs:loc":"\u0412\u0435\u043f\u0440\u0438\u043a",
    "qs:loc_alt":"Vepryk",
    "qs:pop":0,
    "qs:type":"buffered point",
    "wd:wordcount":1070,
    "wof:name":"\u0412\u0435\u043f\u0440\u0438\u043a",
    "wof:placetype":"locality"
},
  "geometry": {"coordinates":[34.190863,50.375103],"type":"Point"}
}