{
  "type": "Feature",
  "properties": {
    "gn:admin1_code":"18.0",
    "gn:asciiname":"Yosypivka",
    "gn:country_code":"UA",
    "gn:dem":73,
    "gn:feature_class":"P",
    "gn:feature_code":"PPL",
    "gn:name":"Yosypivka",
    "gn:population":0,
    "gn:timezone":"Europe/Kiev",
    "iso:country":"UA",
    "name:ukr_x_preferred":[
        "Yosypivka"
    ],
    "name:ukr_x_variant":[
        "\u0419\u043e\u0441\u0438\u043f\u0456\u0432\u043a\u0430"
    ],
    "name:und_x_variant":[
        "Osinovka",
        "Iosipiv",
        "Iosipivka"
    ],
    "wof:name":"Yosypivka",
    "wof:placetype":"locality"
},
  "geometry": {"coordinates":[33.62758,49.24527],"type":"Point"}
}