{
  "type": "Feature",
  "properties": {
    "gn:admin1_code":"17.0",
    "gn:asciiname":"Maloyaroslavets' Druhyy",
    "gn:country_code":"UA",
    "gn:dem":112,
    "gn:feature_class":"P",
    "gn:feature_code":"PPL",
    "gn:name":"Maloyaroslavets\u2019 Druhyy",
    "gn:population":0,
    "gn:timezone":"Europe/Kiev",
    "iso:country":"UA",
    "name:ukr_x_preferred":[
        "\u041c\u0430\u043b\u043e\u044f\u0440\u043e\u0441\u043b\u0430\u0432\u0435\u0446\u044c \u0414\u0440\u0443\u0433\u0438\u0439"
    ],
    "name:und_x_variant":[
        "Borshtal\u2019",
        "Malul Mic",
        "Malul Mik",
        "Maloyaroslavets Vtoroy",
        "Maloyaroslavets\u2019 Druhyy"
    ],
    "wof:name":"Maloyaroslavets' Druhyy",
    "wof:placetype":"locality"
},
  "geometry": {"coordinates":[29.08628,46.15631],"type":"Point"}
}