{
  "type": "Feature",
  "properties": {
    "gn:admin1_code":"5.0",
    "gn:asciiname":"Novoyelyzavetivka",
    "gn:country_code":"UA",
    "gn:dem":145,
    "gn:feature_class":"P",
    "gn:feature_code":"PPL",
    "gn:name":"Novoyelyzavetivka",
    "gn:population":0,
    "gn:timezone":"Europe/Kiev",
    "iso:country":"UA",
    "name:ukr_x_preferred":[
        "\u041d\u043e\u0432\u043e\u0454\u043b\u0438\u0437\u0430\u0432\u0435\u0442\u0456\u0432\u043a\u0430"
    ],
    "name:und_x_variant":[
        "Novo-Yelizovetovka",
        "Novoyelizavetovka"
    ],
    "wof:name":"Novoyelyzavetivka",
    "wof:placetype":"locality"
},
  "geometry": {"coordinates":[37.04094,48.13683],"type":"Point"}
}