{
  "type": "Feature",
  "properties": {
    "gn:admin1_code":"15.0",
    "gn:asciiname":"Kavs'ke",
    "gn:country_code":"UA",
    "gn:dem":289,
    "gn:feature_class":"P",
    "gn:feature_code":"PPL",
    "gn:name":"Kavs\u2019ke",
    "gn:population":0,
    "gn:timezone":"Europe/Kiev",
    "iso:country":"UA",
    "name:rus_x_preferred":[
        "\u041a\u0430\u0432\u0441\u043a\u043e\u0435"
    ],
    "name:ukr_x_preferred":[
        "Kavs\u2019ke"
    ],
    "name:ukr_x_variant":[
        "\u041a\u0430\u0432\u0441\u044c\u043a\u0435"
    ],
    "name:und_x_variant":[
        "Kavsko",
        "Kavskoye"
    ],
    "wof:name":"Kavs'ke",
    "wof:placetype":"locality"
},
  "geometry": {"coordinates":[23.80576,49.35856],"type":"Point"}
}