{
  "type": "Feature",
  "properties": {
    "iso:country":"UA",
    "qs:a0":"\u0423\u043a\u0440\u0430\u0457\u043d\u0430",
    "qs:a1":"*\u0412\u0456\u043d\u043d\u0438\u0446\u044c\u043a\u0430",
    "qs:a1_alt":"Vinnyts'ka",
    "qs:a1r":"0",
    "qs:a2":"\u0411\u0430\u0440\u0441\u044c\u043a\u0438\u0439",
    "qs:a2_alt":"Bars'kyi",
    "qs:adm0":"\u0423\u043a\u0440\u0430\u0457\u043d\u0430",
    "qs:la_lc":"*",
    "qs:level":"locality",
    "qs:loc":"\u041c\u0456\u0436\u043b\u0456\u0441\u0441\u044f",
    "qs:loc_alt":"Mizhlissia",
    "qs:pop":0,
    "qs:type":"buffered point",
    "wof:name":"\u041c\u0456\u0436\u043b\u0456\u0441\u0441\u044f",
    "wof:placetype":"locality"
},
  "geometry": {"coordinates":[27.737748,49.04325],"type":"Point"}
}