{
  "type": "Feature",
  "properties": {
    "gn:admin1_code":"18.0",
    "gn:asciiname":"Patlayivka",
    "gn:country_code":"UA",
    "gn:dem":99,
    "gn:feature_class":"P",
    "gn:feature_code":"PPL",
    "gn:name":"Patlayivka",
    "gn:population":0,
    "gn:timezone":"Europe/Kiev",
    "iso:country":"UA",
    "name:ukr_x_preferred":[
        "Patlayivka"
    ],
    "name:ukr_x_variant":[
        "\u041f\u0430\u0442\u043b\u0430\u0457\u0432\u043a\u0430"
    ],
    "name:und_x_variant":[
        "Patlayevka"
    ],
    "wof:name":"Patlayivka",
    "wof:placetype":"locality"
},
  "geometry": {"coordinates":[34.5828,49.64729000000001],"type":"Point"}
}