{
  "type": "Feature",
  "properties": {
    "iso:country":"UA",
    "name:ukr_x_preferred":[
        "\u0412\u0435\u0440\u0445\u043d\u044f \u0442\u0435\u043b\u0438\u0447\u043a\u0430"
    ],
    "wof:name":"Verkhnia Telychka",
    "wof:placetype":"neighbourhood"
},
  "geometry": {"coordinates":[30.5566709637718,50.41236193412458],"type":"Point"}
}