{
  "type": "Feature",
  "properties": {
    "iso:country":"UA",
    "name:che_x_preferred":[
        "\u0424\u043e\u0440\u043d\u043e\u0441\u043e\u0432\u043e"
    ],
    "name:fin_x_preferred":[
        "Vornasuo"
    ],
    "name:hye_x_preferred":[
        "\u0556\u0578\u0580\u0576\u0578\u057d\u0578\u057e\u0578"
    ],
    "name:ita_x_preferred":[
        "Fornosovo"
    ],
    "name:rus_x_preferred":[
        "\u0424\u043e\u0440\u043d\u043e\u0441\u043e\u0432\u043e"
    ],
    "name:srp_x_preferred":[
        "\u0424\u043e\u0440\u043d\u043e\u0441\u043e\u0432\u043e"
    ],
    "name:und_x_variant":[
        "Knyazh\u2019ye"
    ],
    "qs:a0":"\u0423\u043a\u0440\u0430\u0457\u043d\u0430",
    "qs:a1":"*\u0406\u0432\u0430\u043d\u043e-\u0424\u0440\u0430\u043d\u043a\u0456\u0432\u0441\u044c\u043a\u0430",
    "qs:a1_alt":"Ivano-Frankivs'ka",
    "qs:a1r":"0",
    "qs:a2":"\u0421\u043d\u044f\u0442\u0438\u043d\u0441\u044c\u043a\u0438\u0439",
    "qs:a2_alt":"Sniatyns'kyi",
    "qs:adm0":"\u0423\u043a\u0440\u0430\u0457\u043d\u0430",
    "qs:la_lc":"*",
    "qs:level":"locality",
    "qs:loc":"\u041a\u043d\u044f\u0436\u0435",
    "qs:loc_alt":"Kniazhe",
    "qs:pop":0,
    "qs:type":"buffered point",
    "wd:wordcount":1251,
    "wof:name":"\u041a\u043d\u044f\u0436\u0435",
    "wof:placetype":"locality"
},
  "geometry": {"coordinates":[25.449144,48.406209],"type":"Point"}
}