{
  "type": "Feature",
  "properties": {
    "gn:admin1_code":"17.0",
    "gn:asciiname":"Yehorivka",
    "gn:country_code":"UA",
    "gn:dem":5,
    "gn:feature_class":"P",
    "gn:feature_code":"PPL",
    "gn:name":"Yehorivka",
    "gn:population":0,
    "gn:timezone":"Europe/Kiev",
    "iso:country":"UA",
    "name:ukr_x_preferred":[
        "Yehorivka"
    ],
    "name:ukr_x_variant":[
        "\u0404\u0433\u043e\u0440\u0456\u0432\u043a\u0430"
    ],
    "name:und_x_variant":[
        "Bol\u2019shoye Festerovo",
        "Bol\u2019shaye Festerovo",
        "Yegorovka"
    ],
    "wof:name":"Yehorivka",
    "wof:placetype":"locality"
},
  "geometry": {"coordinates":[30.40587,46.7201],"type":"Point"}
}