{
  "type": "Feature",
  "properties": {
    "gn:admin1_code":"7.0",
    "gn:asciiname":"Velyka Andriyivka",
    "gn:country_code":"UA",
    "gn:dem":138,
    "gn:feature_class":"P",
    "gn:feature_code":"PPL",
    "gn:name":"Velyka Andriyivka",
    "gn:population":0,
    "gn:timezone":"Europe/Kiev",
    "iso:country":"UA",
    "name:rus_x_preferred":[
        "Bol\u2019shaya Andreyevka"
    ],
    "name:ukr_x_preferred":[
        "Velyka Andriyivka"
    ],
    "name:ukr_x_variant":[
        "\u0412\u0435\u043b\u0438\u043a\u0430 \u0410\u043d\u0434\u0440\u0456\u0457\u0432\u043a\u0430"
    ],
    "name:und_x_variant":[
        "Velikaya Andreyevka"
    ],
    "wof:name":"Velyka Andriyivka",
    "wof:placetype":"locality"
},
  "geometry": {"coordinates":[36.79176,48.99811],"type":"Point"}
}