{
  "type": "Feature",
  "properties": {
    "gn:admin1_code":"5.0",
    "gn:asciiname":"Zori",
    "gn:country_code":"UA",
    "gn:dem":30,
    "gn:feature_class":"P",
    "gn:feature_code":"PPL",
    "gn:name":"Zori",
    "gn:population":0,
    "gn:timezone":"Europe/Kiev",
    "iso:country":"UA",
    "name:ukr_x_preferred":[
        "Zori"
    ],
    "name:ukr_x_variant":[
        "\u0417\u043e\u0440\u0456"
    ],
    "wof:name":"Zori",
    "wof:placetype":"locality"
},
  "geometry": {"coordinates":[38.19755,47.36936],"type":"Point"}
}