{
  "type": "Feature",
  "properties": {
    "gn:admin1_code":"27.0",
    "gn:asciiname":"Stantsiyne",
    "gn:country_code":"UA",
    "gn:dem":191,
    "gn:feature_class":"P",
    "gn:feature_code":"PPL",
    "gn:name":"Stantsiyne",
    "gn:population":0,
    "gn:timezone":"Europe/Kiev",
    "iso:country":"UA",
    "name:ukr_x_preferred":[
        "Stantsiyne"
    ],
    "name:ukr_x_variant":[
        "\u0421\u0442\u0430\u043d\u0446\u0456\u0439\u043d\u0435"
    ],
    "name:und_x_variant":[
        "Luginy"
    ],
    "wof:name":"Stantsiyne",
    "wof:placetype":"locality"
},
  "geometry": {"coordinates":[28.38414,51.03574],"type":"Point"}
}