{
  "type": "Feature",
  "properties": {
    "gn:admin1_code":"14.0",
    "gn:asciiname":"Bondareve",
    "gn:country_code":"UA",
    "gn:dem":155,
    "gn:feature_class":"P",
    "gn:feature_code":"PPL",
    "gn:name":"Bondareve",
    "gn:population":0,
    "gn:timezone":"Europe/Zaporozhye",
    "iso:country":"UA",
    "name:rus_x_preferred":[
        "Bondar\u00ebvka"
    ],
    "name:rus_x_variant":[
        "Bondar\u00ebvo"
    ],
    "name:ukr_x_preferred":[
        "\u0411\u043e\u043d\u0434\u0430\u0440\u0435\u0432\u0435"
    ],
    "name:und_x_variant":[
        "Bondar\u00ebv",
        "Bondareve"
    ],
    "wof:name":"Bondareve",
    "wof:placetype":"locality"
},
  "geometry": {"coordinates":[39.19137,49.3804],"type":"Point"}
}