{
  "type": "Feature",
  "properties": {
    "gn:admin1_code":"15.0",
    "gn:asciiname":"Rokitno",
    "gn:country_code":"UA",
    "gn:dem":294,
    "gn:elevation":"303.0",
    "gn:feature_class":"P",
    "gn:feature_code":"PPL",
    "gn:name":"Rokitno",
    "gn:population":266,
    "gn:timezone":"Europe/Kiev",
    "iso:country":"UA",
    "name:rus_x_preferred":[
        "\u0420\u0430\u043a\u0438\u0442\u043d\u043e\u0435"
    ],
    "name:ukr_x_preferred":[
        "\u0420\u043e\u043a\u0438\u0442\u043d\u0435"
    ],
    "wof:name":"Rokitno",
    "wof:placetype":"locality",
    "wof:population":266
},
  "geometry": {"coordinates":[23.90108,49.95393],"type":"Point"}
}