{
  "type": "Feature",
  "properties": {
    "iso:country":"UA",
    "name:eng_x_preferred":[
        "Kotovka"
    ],
    "name:rus_x_preferred":[
        "\u041a\u043e\u0442\u043e\u0432\u043a\u0430"
    ],
    "name:ukr_x_preferred":[
        "\u041a\u043e\u0442\u043e\u0432\u043a\u0430"
    ],
    "name:unk_x_variant":[
        "Kotovka"
    ],
    "qs:a0":"\u0423\u043a\u0440\u0430\u0457\u043d\u0430",
    "qs:a1":"*\u0414\u043d\u0456\u043f\u0440\u043e\u043f\u0435\u0442\u0440\u043e\u0432\u0441\u044c\u043a\u0430",
    "qs:a1_alt":"Dnipropetrovs'ka",
    "qs:a1r":"0",
    "qs:a2":"\u041c\u0430\u0433\u0434\u0430\u043b\u0438\u043d\u0456\u0432\u0441\u044c\u043a\u0438\u0439",
    "qs:a2_alt":"Mahdalynivs'kyi",
    "qs:adm0":"\u0423\u043a\u0440\u0430\u0457\u043d\u0430",
    "qs:la_lc":"*",
    "qs:level":"locality",
    "qs:loc":"\u041a\u043e\u0442\u043e\u0432\u043a\u0430",
    "qs:loc_alt":"Kotovka",
    "qs:pop":0,
    "qs:type":"buffered point",
    "wd:wordcount":74,
    "wof:name":"\u041a\u043e\u0442\u043e\u0432\u043a\u0430",
    "wof:placetype":"locality"
},
  "geometry": {"coordinates":[34.95349,49.123041],"type":"Point"}
}