{
  "type": "Feature",
  "properties": {
    "iso:country":"UA",
    "name:deu_x_preferred":[
        "Wwedenka"
    ],
    "name:eng_x_preferred":[
        "Vvedenka"
    ],
    "name:lav_x_preferred":[
        "Vvedenka"
    ],
    "name:ron_x_preferred":[
        "V\u0103deni"
    ],
    "name:rus_x_preferred":[
        "\u0412\u0432\u0435\u0434\u0435\u043d\u043a\u0430"
    ],
    "name:spa_x_preferred":[
        "Vvedenka"
    ],
    "name:ukr_x_preferred":[
        "\u0412\u0432\u0435\u0434\u0435\u043d\u043a\u0430"
    ],
    "name:und_x_variant":[
        "Tamur"
    ],
    "name:zho_x_preferred":[
        "\u5f17\u97cb\u5805\u5361"
    ],
    "qs:a0":"\u0423\u043a\u0440\u0430\u0457\u043d\u0430",
    "qs:a1":"*\u041e\u0434\u0435\u0441\u044c\u043a\u0430",
    "qs:a1_alt":"Odes'ka",
    "qs:a1r":"0",
    "qs:a2":"\u0421\u0430\u0440\u0430\u0442\u0441\u044c\u043a\u0438\u0439",
    "qs:a2_alt":"Sarats'kyi",
    "qs:adm0":"\u0423\u043a\u0440\u0430\u0457\u043d\u0430",
    "qs:la_lc":"*",
    "qs:level":"locality",
    "qs:loc":"\u0412\u0432\u0435\u0434\u0435\u043d\u043a\u0430",
    "qs:loc_alt":"Vvedenka",
    "qs:pop":0,
    "qs:type":"buffered point",
    "wof:name":"\u0412\u0432\u0435\u0434\u0435\u043d\u043a\u0430",
    "wof:placetype":"locality"
},
  "geometry": {"coordinates":[29.538515,46.171925],"type":"Point"}
}