{
  "type": "Feature",
  "properties": {
    "gn:admin1_code":"15.0",
    "gn:asciiname":"Cheremushna",
    "gn:country_code":"UA",
    "gn:dem":232,
    "gn:feature_class":"P",
    "gn:feature_code":"PPL",
    "gn:name":"Cheremushna",
    "gn:population":0,
    "gn:timezone":"Europe/Kiev",
    "iso:country":"UA",
    "name:und_x_variant":[
        "Cher\u00ebmushka"
    ],
    "wof:name":"Cheremushna",
    "wof:placetype":"locality"
},
  "geometry": {"coordinates":[23.91667,50.06667],"type":"Point"}
}