{
  "type": "Feature",
  "properties": {
    "gn:admin1_code":"11.0",
    "gn:admin2_code":"712968",
    "gn:admin3_code":"11152810.0",
    "gn:asciiname":"Schastlivoye",
    "gn:country_code":"UA",
    "gn:dem":381,
    "gn:elevation":"387.0",
    "gn:feature_class":"P",
    "gn:feature_code":"PPL",
    "gn:name":"Schastlivoye",
    "gn:population":348,
    "gn:timezone":"Europe/Simferopol",
    "iso:country":"UA",
    "name:eng_x_preferred":[
        "Schastlivoye"
    ],
    "name:rus_x_historical":[
        "\u0411\u0438\u044e\u0301\u043a-\u041e\u0437\u0435\u043d\u0431\u0430\u0301\u0448"
    ],
    "name:rus_x_preferred":[
        "\u0421\u0447\u0430\u0441\u0442\u043b\u0438\u0432\u043e\u0435"
    ],
    "name:rus_x_variant":[
        "\u0411\u0438\u044e\u0301\u043a-\u041e\u0437\u0435\u043d\u0431\u0430\u0301\u0448"
    ],
    "name:ukr_x_preferred":[
        "\u0429\u0430\u0441\u043b\u0438\u0432\u0435"
    ],
    "wof:name":"Schastlivoye",
    "wof:placetype":"locality",
    "wof:population":348
},
  "geometry": {"coordinates":[34.06727,44.57565],"type":"Point"}
}