{
  "type": "Feature",
  "properties": {
    "gn:admin1_code":"8.0",
    "gn:asciiname":"Kosa",
    "gn:country_code":"UA",
    "gn:dem":16,
    "gn:feature_class":"P",
    "gn:feature_code":"PPL",
    "gn:name":"Kosa",
    "gn:population":0,
    "gn:timezone":"Europe/Kiev",
    "iso:country":"UA",
    "name:swe_x_preferred":[
        "Kosa"
    ],
    "wof:name":"Kosa",
    "wof:placetype":"locality"
},
  "geometry": {"coordinates":[34.03333,46.15],"type":"Point"}
}