{
  "type": "Feature",
  "properties": {
    "iso:country":"UA",
    "qs:a0":"\u0423\u043a\u0440\u0430\u0457\u043d\u0430",
    "qs:a1":"*\u041a\u0456\u0440\u043e\u0432\u043e\u0433\u0440\u0430\u0434\u0441\u044c\u043a\u0430",
    "qs:a1_alt":"Kirovohrads'ka",
    "qs:a1r":"0",
    "qs:a2":"\u0413\u0430\u0439\u0432\u043e\u0440\u043e\u043d\u0441\u044c\u043a\u0438\u0439",
    "qs:a2_alt":"Haivorons'kyi",
    "qs:adm0":"\u0423\u043a\u0440\u0430\u0457\u043d\u0430",
    "qs:la_lc":"*",
    "qs:level":"locality",
    "qs:loc":"\u0427\u0435\u0440\u0432\u043e\u043d\u0435",
    "qs:loc_alt":"Chervone",
    "qs:pop":0,
    "qs:type":"buffered point",
    "wd:wordcount":95,
    "wof:name":"\u0427\u0435\u0440\u0432\u043e\u043d\u0435",
    "wof:placetype":"locality"
},
  "geometry": {"coordinates":[29.964526,48.415816],"type":"Point"}
}