{
  "type": "Feature",
  "properties": {
    "gn:admin1_code":"22.0",
    "gn:asciiname":"Staromeshchizna",
    "gn:country_code":"UA",
    "gn:dem":293,
    "gn:feature_class":"P",
    "gn:feature_code":"PPL",
    "gn:name":"Staromeshchizna",
    "gn:population":0,
    "gn:timezone":"Europe/Kiev",
    "iso:country":"UA",
    "wof:name":"Staromeshchizna",
    "wof:placetype":"locality"
},
  "geometry": {"coordinates":[26.16166,49.54796],"type":"Point"}
}