{
  "type": "Feature",
  "properties": {
    "gn:admin1_code":"25.0",
    "gn:asciiname":"Stare Davydkovo",
    "gn:country_code":"UA",
    "gn:dem":116,
    "gn:feature_class":"P",
    "gn:feature_code":"PPL",
    "gn:name":"Stare Davydkovo",
    "gn:population":0,
    "gn:timezone":"Europe/Uzhgorod",
    "iso:country":"UA",
    "name:ukr_x_preferred":[
        "\u0421\u0442\u0430\u0440\u0435 \u0414\u0430\u0432\u0438\u0434\u043a\u043e\u0432\u043e"
    ],
    "name:und_x_variant":[
        "Staroye Davydkovo",
        "Staroye Davidkovo",
        "Stare Davydkove",
        "Stare Davydkovo"
    ],
    "wof:name":"Stare Davydkovo",
    "wof:placetype":"locality"
},
  "geometry": {"coordinates":[22.63424,48.4559],"type":"Point"}
}