{
  "type": "Feature",
  "properties": {
    "gn:admin1_code":"25.0",
    "gn:asciiname":"Stare Davydkovo",
    "gn:country_code":"UA",
    "gn:dem":116,
    "gn:feature_class":"P",
    "gn:feature_code":"PPL",
    "gn:name":"Stare Davydkovo",
    "gn:population":0,
    "gn:timezone":"Europe/Uzhgorod",
    "iso:country":"UA",
    "name:epo_x_preferred":[
        "Stare Davidkovo"
    ],
    "name:hun_x_preferred":[
        "\u00d3d\u00e1vidh\u00e1za"
    ],
    "name:hye_x_preferred":[
        "\u054d\u057f\u0561\u0580\u0578\u0565 \u0534\u0561\u057e\u056b\u0564\u056f\u0578\u057e\u0578"
    ],
    "name:ron_x_preferred":[
        "Stare Dav\u00eedkovo"
    ],
    "name:rus_x_preferred":[
        "\u0421\u0442\u0430\u0440\u043e\u0435 \u0414\u0430\u0432\u044b\u0434\u043a\u043e\u0432\u043e"
    ],
    "name:ukr_x_preferred":[
        "\u0421\u0442\u0430\u0440\u0435 \u0414\u0430\u0432\u0438\u0434\u043a\u043e\u0432\u043e"
    ],
    "name:und_x_variant":[
        "Staroye Davydkovo",
        "Staroye Davidkovo",
        "Stare Davydkove",
        "Stare Davydkovo"
    ],
    "name:zho_x_preferred":[
        "\u820a\u9054\u7dad\u5fb7\u79d1\u6c83"
    ],
    "wof:name":"Stare Davydkovo",
    "wof:placetype":"locality"
},
  "geometry": {"coordinates":[22.63424,48.4559],"type":"Point"}
}