{
  "type": "Feature",
  "properties": {
    "gn:admin1_code":"9.0",
    "gn:asciiname":"Myslyatin",
    "gn:country_code":"UA",
    "gn:dem":246,
    "gn:feature_class":"P",
    "gn:feature_code":"PPL",
    "gn:name":"Myslyatin",
    "gn:population":0,
    "gn:timezone":"Europe/Kiev",
    "iso:country":"UA",
    "wof:name":"Myslyatin",
    "wof:placetype":"locality"
},
  "geometry": {"coordinates":[26.713,50.08909],"type":"Point"}
}