{
  "type": "Feature",
  "properties": {
    "gn:admin1_code":"9.0",
    "gn:asciiname":"Zhuravlintsy",
    "gn:country_code":"UA",
    "gn:dem":281,
    "gn:feature_class":"P",
    "gn:feature_code":"PPL",
    "gn:name":"Zhuravlintsy",
    "gn:population":0,
    "gn:timezone":"Europe/Kiev",
    "iso:country":"UA",
    "wof:name":"Zhuravlintsy",
    "wof:placetype":"locality"
},
  "geometry": {"coordinates":[26.43968,49.31994],"type":"Point"}
}