{
  "type": "Feature",
  "properties": {
    "gn:admin1_code":"15.0",
    "gn:asciiname":"Potik",
    "gn:country_code":"UA",
    "gn:dem":536,
    "gn:feature_class":"P",
    "gn:feature_code":"PPL",
    "gn:name":"Potik",
    "gn:population":0,
    "gn:timezone":"Europe/Kiev",
    "iso:country":"UA",
    "name:ukr_x_preferred":[
        "Potik"
    ],
    "name:ukr_x_variant":[
        "\u041f\u043e\u0442\u0456\u043a"
    ],
    "wof:name":"Potik",
    "wof:placetype":"locality"
},
  "geometry": {"coordinates":[22.83649,49.37426],"type":"Point"}
}