{
  "type": "Feature",
  "properties": {
    "gn:admin1_code":"21.0",
    "gn:asciiname":"Zhovtnevyy",
    "gn:country_code":"UA",
    "gn:dem":118,
    "gn:feature_class":"P",
    "gn:feature_code":"PPL",
    "gn:name":"Zhovtnevyy",
    "gn:population":0,
    "gn:timezone":"Europe/Kiev",
    "iso:country":"UA",
    "wof:name":"Zhovtnevyy",
    "wof:placetype":"locality"
},
  "geometry": {"coordinates":[34.88028,50.19528],"type":"Point"}
}