{
  "type": "Feature",
  "properties": {
    "gn:admin1_code":"16.0",
    "gn:asciiname":"Veseley Khutor",
    "gn:country_code":"UA",
    "gn:dem":77,
    "gn:feature_class":"P",
    "gn:feature_code":"PPL",
    "gn:name":"Veseley Khutor",
    "gn:population":0,
    "gn:timezone":"Europe/Kiev",
    "iso:country":"UA",
    "name:und_x_variant":[
        "Ves\u00eblyy Khutor"
    ],
    "wof:name":"Veseley Khutor",
    "wof:placetype":"locality"
},
  "geometry": {"coordinates":[30.78333,47.75],"type":"Point"}
}