{
  "type": "Feature",
  "properties": {
    "gn:admin1_code":"18.0",
    "gn:asciiname":"Syvtsi",
    "gn:country_code":"UA",
    "gn:dem":116,
    "gn:feature_class":"P",
    "gn:feature_code":"PPL",
    "gn:name":"Syvtsi",
    "gn:population":0,
    "gn:timezone":"Europe/Kiev",
    "iso:country":"UA",
    "name:ukr_x_preferred":[
        "Syvtsi"
    ],
    "name:ukr_x_variant":[
        "\u0421\u0438\u0432\u0446\u0456"
    ],
    "wof:name":"Syvtsi",
    "wof:placetype":"locality"
},
  "geometry": {"coordinates":[34.26527,49.84242],"type":"Point"}
}