{
  "type": "Feature",
  "properties": {
    "gn:admin1_code":"21.0",
    "gn:asciiname":"Bilytsya",
    "gn:country_code":"UA",
    "gn:dem":165,
    "gn:feature_class":"P",
    "gn:feature_code":"PPL",
    "gn:name":"Bilytsya",
    "gn:population":0,
    "gn:timezone":"Europe/Kiev",
    "iso:country":"UA",
    "name:ukr_x_preferred":[
        "Belitsa"
    ],
    "name:ukr_x_variant":[
        "\u0411\u0456\u043b\u0438\u0446\u044f"
    ],
    "name:und_x_variant":[
        "Bilytsya"
    ],
    "wof:name":"Bilytsya",
    "wof:placetype":"locality"
},
  "geometry": {"coordinates":[33.76521,52.00622],"type":"Point"}
}