{
  "type": "Feature",
  "properties": {
    "iso:country":"UA",
    "name:rus_x_preferred":[
        "Ptich\u2019ya"
    ],
    "name:ukr_x_preferred":[
        "\u041f\u0442\u0438\u0447\u0430"
    ],
    "name:und_x_variant":[
        "Ptycha"
    ],
    "qs:a0":"\u0423\u043a\u0440\u0430\u0457\u043d\u0430",
    "qs:a1":"*\u0420\u0456\u0432\u043d\u0435\u043d\u0441\u044c\u043a\u0430",
    "qs:a1_alt":"Rivnens'ka",
    "qs:a1r":"0",
    "qs:a2":"\u0414\u0443\u0431\u0435\u043d\u0441\u044c\u043a\u0438\u0439",
    "qs:a2_alt":"Dubens'kyi",
    "qs:adm0":"\u0423\u043a\u0440\u0430\u0457\u043d\u0430",
    "qs:la_lc":"*",
    "qs:level":"locality",
    "qs:loc":"\u041f\u0442\u0438\u0447\u0430",
    "qs:loc_alt":"Ptycha",
    "qs:pop":0,
    "qs:type":"buffered point",
    "wof:name":"\u041f\u0442\u0438\u0447\u0430",
    "wof:placetype":"locality"
},
  "geometry": {"coordinates":[25.620477,50.304196],"type":"Point"}
}