{
  "type": "Feature",
  "properties": {
    "gn:admin1_code":"11.0",
    "gn:admin2_code":"712585",
    "gn:admin3_code":"11152831.0",
    "gn:asciiname":"Yelenovka",
    "gn:country_code":"UA",
    "gn:dem":314,
    "gn:elevation":"320.0",
    "gn:feature_class":"P",
    "gn:feature_code":"PPL",
    "gn:name":"Yelenovka",
    "gn:population":19,
    "gn:timezone":"Europe/Simferopol",
    "iso:country":"UA",
    "name:aze_x_preferred":[
        "Yelenovka"
    ],
    "name:eng_x_preferred":[
        "Yelenovka"
    ],
    "name:rus_x_preferred":[
        "\u0415\u043b\u0435\u043d\u043e\u0432\u043a\u0430"
    ],
    "name:ukr_x_preferred":[
        "\u041e\u043b\u0435\u043d\u0456\u0432\u043a\u0430"
    ],
    "wof:name":"Yelenovka",
    "wof:placetype":"locality",
    "wof:population":19
},
  "geometry": {"coordinates":[34.82843,44.98868],"type":"Point"}
}