{
  "type": "Feature",
  "properties": {
    "gn:admin1_code":"24.0",
    "gn:asciiname":"Lychyny",
    "gn:country_code":"UA",
    "gn:dem":162,
    "gn:feature_class":"P",
    "gn:feature_code":"PPL",
    "gn:name":"Lychyny",
    "gn:population":0,
    "gn:timezone":"Europe/Kiev",
    "iso:country":"UA",
    "name:ukr_x_preferred":[
        "Lychyny"
    ],
    "name:ukr_x_variant":[
        "\u041b\u0438\u0447\u0438\u043d\u0438"
    ],
    "name:und_x_variant":[
        "Lichiny"
    ],
    "wof:name":"Lychyny",
    "wof:placetype":"locality"
},
  "geometry": {"coordinates":[24.78353,51.45113],"type":"Point"}
}