{
  "type": "Feature",
  "properties": {
    "gn:admin1_code":"21.0",
    "gn:asciiname":"Pishchane",
    "gn:country_code":"UA",
    "gn:dem":182,
    "gn:feature_class":"P",
    "gn:feature_code":"PPL",
    "gn:name":"Pishchane",
    "gn:population":0,
    "gn:timezone":"Europe/Kiev",
    "iso:country":"UA",
    "name:ukr_x_preferred":[
        "Pishchane"
    ],
    "name:ukr_x_variant":[
        "\u041f\u0456\u0449\u0430\u043d\u0435"
    ],
    "name:und_x_variant":[
        "Peschanoye"
    ],
    "wof:name":"Pishchane",
    "wof:placetype":"locality"
},
  "geometry": {"coordinates":[34.07011,50.95234],"type":"Point"}
}