{
  "type": "Feature",
  "properties": {
    "gn:admin1_code":"2.0",
    "gn:asciiname":"Butivka",
    "gn:country_code":"UA",
    "gn:dem":144,
    "gn:feature_class":"P",
    "gn:feature_code":"PPL",
    "gn:name":"Butivka",
    "gn:population":0,
    "gn:timezone":"Europe/Kiev",
    "iso:country":"UA",
    "name:ukr_x_preferred":[
        "Butivka"
    ],
    "name:ukr_x_variant":[
        "\u0411\u0443\u0442\u0456\u0432\u043a\u0430"
    ],
    "name:und_x_variant":[
        "Butovka"
    ],
    "wof:name":"Butivka",
    "wof:placetype":"locality"
},
  "geometry": {"coordinates":[31.67454,51.93657],"type":"Point"}
}