{
  "type": "Feature",
  "properties": {
    "gn:admin1_code":"9.0",
    "gn:asciiname":"Demshin",
    "gn:country_code":"UA",
    "gn:dem":264,
    "gn:feature_class":"P",
    "gn:feature_code":"PPL",
    "gn:name":"D\u00ebmshin",
    "gn:population":0,
    "gn:timezone":"Europe/Kiev",
    "iso:country":"UA",
    "wof:name":"Demshin",
    "wof:placetype":"locality"
},
  "geometry": {"coordinates":[26.81892,48.62191],"type":"Point"}
}