{
  "type": "Feature",
  "properties": {
    "gn:population":3309,
    "iso:country":"UA",
    "name:ara_x_preferred":[
        "\u0623\u0633\u0643\u0627\u0646\u064a\u0627-\u0646\u0648\u0641\u0627"
    ],
    "name:aze_x_preferred":[
        "Askaniya-Nova"
    ],
    "name:bak_x_preferred":[
        "\u0410\u0441\u043a\u0430\u043d\u0438\u044f-\u041d\u043e\u0432\u0430 \u04a1\u0443\u0440\u0441\u0430\u0443\u043b\u044b\u0493\u044b"
    ],
    "name:bel_x_preferred":[
        "\u0410\u0441\u043a\u0430\u043d\u0456\u044f-\u041d\u043e\u0432\u0430"
    ],
    "name:bel_x_variant":[
        "\u0410\u0441\u043a\u0430\u043d\u0456\u044f-\u041d\u043e\u0432\u0430"
    ],
    "name:bul_x_preferred":[
        "\u0410\u0441\u043a\u0430\u043d\u0438\u044f \u041d\u043e\u0432\u0430"
    ],
    "name:ces_x_preferred":[
        "Askania-Nova"
    ],
    "name:deu_x_preferred":[
        "Askanija-Nowa"
    ],
    "name:eng_x_preferred":[
        "Askania-Nova"
    ],
    "name:fra_x_preferred":[
        "Ascania-Nova"
    ],
    "name:hrv_x_preferred":[
        "NP Askanija Nova"
    ],
    "name:hye_x_preferred":[
        "\u0531\u057d\u056f\u0561\u0576\u056b\u0561-\u0546\u0578\u057e\u0561"
    ],
    "name:kaz_x_preferred":[
        "\u0410\u0441\u043a\u0430\u043d\u0438\u044f-\u041d\u043e\u0432\u0430"
    ],
    "name:lav_x_preferred":[
        "Askanija-Nova"
    ],
    "name:lit_x_preferred":[
        "Askanija Nova"
    ],
    "name:nld_x_preferred":[
        "Biosfeerreservaat Askania-Nova"
    ],
    "name:pol_x_preferred":[
        "Askania Nowa"
    ],
    "name:ron_x_preferred":[
        "Askania-Nova"
    ],
    "name:rus_x_preferred":[
        "\u0410\u0441\u043a\u0430\u043d\u0438\u044f-\u041d\u043e\u0432\u0430"
    ],
    "name:rus_x_variant":[
        "\u0410\u0441\u043a\u0430\u043d\u0456\u044f-\u041d\u043e\u0432\u0430"
    ],
    "name:spa_x_preferred":[
        "Askania-Nova"
    ],
    "name:swe_x_preferred":[
        "Askanija-nova"
    ],
    "name:ukr_x_preferred":[
        "\u0410\u0441\u043a\u0430\u043d\u0456\u044f-\u041d\u043e\u0432\u0430"
    ],
    "name:ukr_x_variant":[
        "Askaniya-Nova"
    ],
    "name:unk_x_variant":[
        "Chapli"
    ],
    "name:uzb_x_preferred":[
        "Askaniya-nova"
    ],
    "name:zho_x_preferred":[
        "\u963f\u65af\u5361\u5c3c\u4e9e-\u8afe\u74e6"
    ],
    "qs:a0":"\u0423\u043a\u0440\u0430\u0457\u043d\u0430",
    "qs:a1":"*\u0425\u0435\u0440\u0441\u043e\u043d\u0441\u044c\u043a\u0430",
    "qs:a1_alt":"Khersons'ka",
    "qs:a1r":"0",
    "qs:a2":"\u0427\u0430\u043f\u043b\u0438\u043d\u0441\u044c\u043a\u0438\u0439",
    "qs:a2_alt":"Chaplyns'kyi",
    "qs:adm0":"\u0423\u043a\u0440\u0430\u0457\u043d\u0430",
    "qs:la_lc":"*",
    "qs:level":"locality",
    "qs:loc":"\u0410\u0441\u043a\u0430\u043d\u0456\u044f-\u041d\u043e\u0432\u0430",
    "qs:loc_alt":"Askaniia-Nova",
    "qs:pop":0,
    "qs:type":"buffered point",
    "wd:wordcount":823,
    "wof:name":"\u0410\u0441\u043a\u0430\u043d\u0456\u044f-\u041d\u043e\u0432\u0430",
    "wof:placetype":"locality",
    "wof:population":3309
},
  "geometry": {"coordinates":[33.872039,46.456274],"type":"Point"}
}