{
  "type": "Feature",
  "properties": {
    "iso:country":"UA",
    "name:ukr_x_preferred":[
        "Komunist"
    ],
    "name:ukr_x_variant":[
        "\u041a\u043e\u043c\u0443\u043d\u0456\u0441\u0442"
    ],
    "name:und_x_variant":[
        "Kommunist"
    ],
    "qs:a0":"\u0423\u043a\u0440\u0430\u0457\u043d\u0430",
    "qs:a1":"*\u0425\u0430\u0440\u043a\u0456\u0432\u0441\u044c\u043a\u0430",
    "qs:a1_alt":"Kharkivs'ka",
    "qs:a1r":"0",
    "qs:a2":"\u0425\u0430\u0440\u043a\u0456\u0432\u0441\u044c\u043a\u0438\u0439",
    "qs:a2_alt":"Kharkivs'kyi",
    "qs:adm0":"\u0423\u043a\u0440\u0430\u0457\u043d\u0430",
    "qs:la_lc":"*",
    "qs:level":"locality",
    "qs:loc":"\u041a\u043e\u043c\u0443\u043d\u0456\u0441\u0442",
    "qs:loc_alt":"Komunist",
    "qs:pop":0,
    "qs:type":"buffered point",
    "wof:name":"\u041a\u043e\u043c\u0443\u043d\u0456\u0441\u0442",
    "wof:placetype":"locality"
},
  "geometry": {"coordinates":[36.448715,49.894565],"type":"Point"}
}