{
  "type": "Feature",
  "properties": {
    "gn:admin1_code":"15.0",
    "gn:asciiname":"Kopytiv",
    "gn:country_code":"UA",
    "gn:dem":202,
    "gn:feature_class":"P",
    "gn:feature_code":"PPL",
    "gn:name":"Kopytiv",
    "gn:population":0,
    "gn:timezone":"Europe/Kiev",
    "iso:country":"UA",
    "name:ukr_x_preferred":[
        "Kopytiv"
    ],
    "name:ukr_x_variant":[
        "\u041a\u043e\u043f\u0438\u0442\u0456\u0432"
    ],
    "name:und_x_variant":[
        "Kopytov"
    ],
    "wof:name":"Kopytiv",
    "wof:placetype":"locality"
},
  "geometry": {"coordinates":[24.39291,50.47897],"type":"Point"}
}