{
  "type": "Feature",
  "properties": {
    "gn:admin1_code":"11.0",
    "gn:admin2_code":"703233",
    "gn:admin3_code":"11128406.0",
    "gn:asciiname":"Osoviny",
    "gn:country_code":"UA",
    "gn:dem":61,
    "gn:feature_class":"P",
    "gn:feature_code":"PPL",
    "gn:name":"Osoviny",
    "gn:population":235,
    "gn:timezone":"Europe/Simferopol",
    "iso:country":"UA",
    "name:eng_x_preferred":[
        "Osoviny"
    ],
    "name:rus_x_preferred":[
        "\u041e\u0441\u043e\u0432\u0438\u043d\u044b"
    ],
    "name:ukr_x_preferred":[
        "\u041e\u0441\u043e\u0432\u0438\u043d\u0438"
    ],
    "wof:name":"Osoviny",
    "wof:placetype":"locality",
    "wof:population":235
},
  "geometry": {"coordinates":[36.59231,45.43323],"type":"Point"}
}