{
  "type": "Feature",
  "properties": {
    "gn:admin1_code":"18.0",
    "gn:asciiname":"Lyubka",
    "gn:country_code":"UA",
    "gn:dem":102,
    "gn:feature_class":"P",
    "gn:feature_code":"PPL",
    "gn:name":"Lyubka",
    "gn:population":0,
    "gn:timezone":"Europe/Kiev",
    "iso:country":"UA",
    "name:ukr_x_preferred":[
        "Lyubka"
    ],
    "name:ukr_x_variant":[
        "\u041b\u044e\u0431\u043a\u0430"
    ],
    "wof:name":"Lyubka",
    "wof:placetype":"locality"
},
  "geometry": {"coordinates":[34.76825,50.00413],"type":"Point"}
}