{
  "type": "Feature",
  "properties": {
    "gn:admin1_code":"27.0",
    "gn:asciiname":"Nova Rudnya",
    "gn:country_code":"UA",
    "gn:dem":210,
    "gn:feature_class":"P",
    "gn:feature_code":"PPL",
    "gn:name":"Nova Rudnya",
    "gn:population":0,
    "gn:timezone":"Europe/Kiev",
    "iso:country":"UA",
    "name:ukr_x_preferred":[
        "Nova Rudnya"
    ],
    "name:ukr_x_variant":[
        "\u041d\u043e\u0432\u0430 \u0420\u0443\u0434\u043d\u044f"
    ],
    "name:und_x_variant":[
        "Novorudnya"
    ],
    "wof:name":"Nova Rudnya",
    "wof:placetype":"locality"
},
  "geometry": {"coordinates":[28.31274,50.18939],"type":"Point"}
}