{
  "type": "Feature",
  "properties": {
    "iso:country":"UA",
    "qs:a0":"\u0423\u043a\u0440\u0430\u0457\u043d\u0430",
    "qs:a1":"*\u0414\u043d\u0456\u043f\u0440\u043e\u043f\u0435\u0442\u0440\u043e\u0432\u0441\u044c\u043a\u0430",
    "qs:a1_alt":"Dnipropetrovs'ka",
    "qs:a1r":"0",
    "qs:a2":"\u041f'\u044f\u0442\u0438\u0445\u0430\u0442\u0441\u044c\u043a\u0438\u0439",
    "qs:a2_alt":"Pyatykhats'kyi",
    "qs:adm0":"\u0423\u043a\u0440\u0430\u0457\u043d\u0430",
    "qs:la_lc":"*",
    "qs:level":"locality",
    "qs:loc":"\u041c\u0430\u0440'\u044f\u043d\u0456\u0432\u043a\u0430",
    "qs:loc_alt":"Marianivka",
    "qs:pop":0,
    "qs:type":"buffered point",
    "wd:wordcount":59,
    "wof:name":"\u041c\u0430\u0440'\u044f\u043d\u0456\u0432\u043a\u0430",
    "wof:placetype":"locality"
},
  "geometry": {"coordinates":[33.52844,48.322095],"type":"Point"}
}