{
  "type": "Feature",
  "properties": {
    "gn:admin1_code":"14.0",
    "gn:asciiname":"Novofedorivka",
    "gn:country_code":"UA",
    "gn:dem":148,
    "gn:feature_class":"P",
    "gn:feature_code":"PPL",
    "gn:name":"Novofedorivka",
    "gn:population":0,
    "gn:timezone":"Europe/Zaporozhye",
    "iso:country":"UA",
    "name:ukr_x_preferred":[
        "Novofedorivka"
    ],
    "name:ukr_x_variant":[
        "\u041d\u043e\u0432\u043e\u0444\u0435\u0434\u043e\u0440\u0456\u0432\u043a\u0430"
    ],
    "name:und_x_variant":[
        "Novofederovka"
    ],
    "wof:name":"Novofedorivka",
    "wof:placetype":"locality"
},
  "geometry": {"coordinates":[39.29978,48.35396],"type":"Point"}
}