{
  "type": "Feature",
  "properties": {
    "gn:admin1_code":"14.0",
    "gn:asciiname":"Novofedorivka",
    "gn:country_code":"UA",
    "gn:dem":148,
    "gn:feature_class":"P",
    "gn:feature_code":"PPL",
    "gn:name":"Novofedorivka",
    "gn:population":0,
    "gn:timezone":"Europe/Zaporozhye",
    "iso:country":"UA",
    "name:crh_x_preferred":[
        "Novof\u00f6dorovka"
    ],
    "name:deu_x_preferred":[
        "Nowofedoriwka"
    ],
    "name:epo_x_preferred":[
        "Novofedorovko"
    ],
    "name:est_x_preferred":[
        "Sak\u00f5 merelennuv\u00e4ebaas"
    ],
    "name:fra_x_preferred":[
        "Novofedorivka"
    ],
    "name:hye_x_preferred":[
        "\u0546\u0578\u057e\u0578\u0586\u0575\u0578\u0564\u0578\u0580\u0578\u057e\u056f\u0561"
    ],
    "name:ron_x_preferred":[
        "Novofedorivka"
    ],
    "name:rus_x_preferred":[
        "\u041d\u043e\u0432\u043e\u0444\u0451\u0434\u043e\u0440\u043e\u0432\u043a\u0430"
    ],
    "name:ukr_x_preferred":[
        "Novofedorivka"
    ],
    "name:ukr_x_variant":[
        "\u041d\u043e\u0432\u043e\u0444\u0435\u0434\u043e\u0440\u0456\u0432\u043a\u0430"
    ],
    "name:und_x_variant":[
        "Novofederovka"
    ],
    "name:zho_x_preferred":[
        "\u8afe\u6c83\u8cbb\u591a\u91cc\u592b\u5361"
    ],
    "wof:name":"Novofedorivka",
    "wof:placetype":"locality"
},
  "geometry": {"coordinates":[39.29978,48.35396],"type":"Point"}
}