{
  "type": "Feature",
  "properties": {
    "gn:admin1_code":"14.0",
    "gn:asciiname":"Tr'okhizbenka",
    "gn:country_code":"UA",
    "gn:dem":49,
    "gn:feature_class":"P",
    "gn:feature_code":"PPL",
    "gn:name":"Tr\u2019okhizbenka",
    "gn:population":2054,
    "gn:timezone":"Europe/Zaporozhye",
    "iso:country":"UA",
    "name:eng_x_preferred":[
        "Tr\u00ebkhizbenka"
    ],
    "name:rus_x_preferred":[
        "\u0422\u0440\u0435\u0445\u0438\u0437\u0431\u0435\u043d\u043a\u0430"
    ],
    "name:ukr_x_preferred":[
        "Tr\u2019okhizbenka"
    ],
    "name:ukr_x_variant":[
        "\u0422\u0440\u044c\u043e\u0445\u0456\u0437\u0431\u0435\u043d\u043a\u0430"
    ],
    "wof:name":"Tr'okhizbenka",
    "wof:placetype":"locality",
    "wof:population":2054
},
  "geometry": {"coordinates":[38.96333,48.75751],"type":"Point"}
}