{
  "type": "Feature",
  "properties": {
    "gn:admin1_code":"4.0",
    "gn:asciiname":"Kytayhorodka",
    "gn:country_code":"UA",
    "gn:dem":128,
    "gn:feature_class":"P",
    "gn:feature_code":"PPL",
    "gn:name":"Kytayhorodka",
    "gn:population":0,
    "gn:timezone":"Europe/Kiev",
    "iso:country":"UA",
    "name:ukr_x_preferred":[
        "Kytayhorodka"
    ],
    "name:ukr_x_variant":[
        "\u041a\u0438\u0442\u0430\u0439\u0433\u043e\u0440\u043e\u0434\u043a\u0430"
    ],
    "name:und_x_variant":[
        "Kitaygorodka"
    ],
    "wof:name":"Kytayhorodka",
    "wof:placetype":"locality"
},
  "geometry": {"coordinates":[34.57128,47.91177],"type":"Point"}
}