{
  "type": "Feature",
  "properties": {
    "gn:admin1_code":"27.0",
    "gn:asciiname":"Bolyarka",
    "gn:country_code":"UA",
    "gn:dem":186,
    "gn:feature_class":"P",
    "gn:feature_code":"PPL",
    "gn:name":"Bolyarka",
    "gn:population":0,
    "gn:timezone":"Europe/Kiev",
    "iso:country":"UA",
    "name:ukr_x_preferred":[
        "Bolyarka"
    ],
    "name:ukr_x_variant":[
        "\u0411\u043e\u043b\u044f\u0440\u043a\u0430"
    ],
    "name:und_x_variant":[
        "Balyarka",
        "Khutor Balyarka"
    ],
    "wof:name":"Bolyarka",
    "wof:placetype":"locality"
},
  "geometry": {"coordinates":[28.83165,50.89081],"type":"Point"}
}