{
  "type": "Feature",
  "properties": {
    "gn:admin1_code":"26.0",
    "gn:asciiname":"Luhivs'ke",
    "gn:country_code":"UA",
    "gn:dem":77,
    "gn:feature_class":"P",
    "gn:feature_code":"PPL",
    "gn:name":"Luhivs\u2019ke",
    "gn:population":0,
    "gn:timezone":"Europe/Zaporozhye",
    "iso:country":"UA",
    "name:ukr_x_preferred":[
        "Luhivs\u2019ke"
    ],
    "name:ukr_x_variant":[
        "\u041b\u0443\u0433\u0456\u0432\u0441\u044c\u043a\u0435"
    ],
    "name:und_x_variant":[
        "Lesnoy"
    ],
    "wof:name":"Luhivs'ke",
    "wof:placetype":"locality"
},
  "geometry": {"coordinates":[36.03552,47.52463],"type":"Point"}
}