{
  "type": "Feature",
  "properties": {
    "gn:admin1_code":"9.0",
    "gn:asciiname":"Ordintsy",
    "gn:country_code":"UA",
    "gn:dem":314,
    "gn:feature_class":"P",
    "gn:feature_code":"PPL",
    "gn:name":"Ordintsy",
    "gn:population":0,
    "gn:timezone":"Europe/Kiev",
    "iso:country":"UA",
    "name:und_x_variant":[
        "Ordyntsy",
        "Ordintsy"
    ],
    "wof:name":"Ordintsy",
    "wof:placetype":"locality"
},
  "geometry": {"coordinates":[26.61018,49.74498],"type":"Point"}
}