{
  "type": "Feature",
  "properties": {
    "gn:admin1_code":"18.0",
    "gn:asciiname":"Taverivka",
    "gn:country_code":"UA",
    "gn:dem":144,
    "gn:feature_class":"P",
    "gn:feature_code":"PPL",
    "gn:name":"Taverivka",
    "gn:population":0,
    "gn:timezone":"Europe/Kiev",
    "iso:country":"UA",
    "name:ukr_x_preferred":[
        "Taverivka"
    ],
    "name:ukr_x_variant":[
        "\u0422\u0430\u0432\u0435\u0440\u0456\u0432\u043a\u0430"
    ],
    "wof:name":"Taverivka",
    "wof:placetype":"locality"
},
  "geometry": {"coordinates":[35.22637,49.68488],"type":"Point"}
}