{
  "type": "Feature",
  "properties": {
    "gn:admin1_code":"17.0",
    "gn:asciiname":"Mykolayivka",
    "gn:cc2":"UA",
    "gn:country_code":"UA",
    "gn:dem":210,
    "gn:feature_class":"P",
    "gn:feature_code":"PPL",
    "gn:name":"Mykolayivka",
    "gn:population":0,
    "gn:timezone":"Europe/Kiev",
    "iso:country":"UA",
    "name:und_x_variant":[
        "Nikolayevka"
    ],
    "wof:name":"Mykolayivka",
    "wof:placetype":"locality"
},
  "geometry": {"coordinates":[29.48472000000001,47.50167],"type":"Point"}
}