{
  "type": "Feature",
  "properties": {
    "gn:admin1_code":"7.0",
    "gn:asciiname":"Zauddya",
    "gn:country_code":"UA",
    "gn:dem":103,
    "gn:feature_class":"P",
    "gn:feature_code":"PPL",
    "gn:name":"Zauddya",
    "gn:population":0,
    "gn:timezone":"Europe/Kiev",
    "iso:country":"UA",
    "name:ukr_x_preferred":[
        "Zauddya"
    ],
    "name:ukr_x_variant":[
        "\u0417\u0430\u0443\u0434\u0434\u044f"
    ],
    "wof:name":"Zauddya",
    "wof:placetype":"locality"
},
  "geometry": {"coordinates":[36.45549000000001,49.80037],"type":"Point"}
}