{
  "type": "Feature",
  "properties": {
    "iso:country":"UA",
    "name:ukr_x_preferred":[
        "Mohylyany"
    ],
    "name:ukr_x_variant":[
        "\u041c\u043e\u0433\u0438\u043b\u044f\u043d\u0438"
    ],
    "name:und_x_variant":[
        "Mohylany"
    ],
    "qs:a0":"\u0423\u043a\u0440\u0430\u0457\u043d\u0430",
    "qs:a1":"*\u0420\u0456\u0432\u043d\u0435\u043d\u0441\u044c\u043a\u0430",
    "qs:a1_alt":"Rivnens'ka",
    "qs:a1r":"0",
    "qs:a2":"\u041e\u0441\u0442\u0440\u043e\u0437\u044c\u043a\u0438\u0439",
    "qs:a2_alt":"Ostroz'kyi",
    "qs:adm0":"\u0423\u043a\u0440\u0430\u0457\u043d\u0430",
    "qs:la_lc":"*",
    "qs:level":"locality",
    "qs:loc":"\u041c\u043e\u0433\u0438\u043b\u044f\u043d\u0438",
    "qs:loc_alt":"Mohyliany",
    "qs:pop":0,
    "qs:type":"buffered point",
    "wof:name":"\u041c\u043e\u0433\u0438\u043b\u044f\u043d\u0438",
    "wof:placetype":"locality"
},
  "geometry": {"coordinates":[26.547261,50.416892],"type":"Point"}
}