{
  "type": "Feature",
  "properties": {
    "gn:admin1_code":"22.0",
    "gn:asciiname":"Volosuvka",
    "gn:country_code":"UA",
    "gn:dem":357,
    "gn:feature_class":"P",
    "gn:feature_code":"PPL",
    "gn:name":"Volosuvka",
    "gn:population":0,
    "gn:timezone":"Europe/Kiev",
    "iso:country":"UA",
    "wof:name":"Volosuvka",
    "wof:placetype":"locality"
},
  "geometry": {"coordinates":[25.22158,49.67158],"type":"Point"}
}