{
  "type": "Feature",
  "properties": {
    "gn:admin1_code":"22.0",
    "gn:asciiname":"Lesechniki",
    "gn:country_code":"UA",
    "gn:dem":239,
    "gn:feature_class":"P",
    "gn:feature_code":"PPL",
    "gn:name":"Lesechniki",
    "gn:population":0,
    "gn:timezone":"Europe/Kiev",
    "iso:country":"UA",
    "name:und_x_variant":[
        "Lisichniki",
        "Lesechniki"
    ],
    "wof:name":"Lesechniki",
    "wof:placetype":"locality"
},
  "geometry": {"coordinates":[25.85113,48.69353],"type":"Point"}
}