{
  "type": "Feature",
  "properties": {
    "gn:admin1_code":"7.0",
    "gn:asciiname":"Hnylytsya Persha",
    "gn:country_code":"UA",
    "gn:dem":141,
    "gn:feature_class":"P",
    "gn:feature_code":"PPL",
    "gn:name":"Hnylytsya Persha",
    "gn:population":0,
    "gn:timezone":"Europe/Kiev",
    "iso:country":"UA",
    "name:ukr_x_preferred":[
        "Hnylytsya Persha"
    ],
    "name:ukr_x_variant":[
        "\u0413\u043d\u0438\u043b\u0438\u0446\u0430 \u041f\u0435\u0440\u0448\u0430"
    ],
    "name:und_x_variant":[
        "Gnilitsa Pervaya"
    ],
    "wof:name":"Hnylytsya Persha",
    "wof:placetype":"locality"
},
  "geometry": {"coordinates":[37.2042,50.03866],"type":"Point"}
}