{
  "type": "Feature",
  "properties": {
    "iso:country":"UA",
    "qs:a0":"\u0423\u043a\u0440\u0430\u0457\u043d\u0430",
    "qs:a1":"*\u0412\u0456\u043d\u043d\u0438\u0446\u044c\u043a\u0430",
    "qs:a1_alt":"Vinnyts'ka",
    "qs:a1r":"0",
    "qs:a2":"\u0425\u043c\u0456\u043b\u044c\u043d\u0438\u0446\u044c\u043a\u0438\u0439",
    "qs:a2_alt":"Khmil'nyts'kyi",
    "qs:adm0":"\u0423\u043a\u0440\u0430\u0457\u043d\u0430",
    "qs:la_lc":"*",
    "qs:level":"locality",
    "qs:loc":"\u0428\u0438\u0440\u043e\u043a\u0430 \u0413\u0440\u0435\u0431\u043b\u044f",
    "qs:loc_alt":"Shyroka Hreblia",
    "qs:pop":0,
    "qs:type":"buffered point",
    "wof:name":"\u0428\u0438\u0440\u043e\u043a\u0430 \u0413\u0440\u0435\u0431\u043b\u044f",
    "wof:placetype":"locality"
},
  "geometry": {"coordinates":[28.011904,49.516734],"type":"Point"}
}