{
  "type": "Feature",
  "properties": {
    "gn:admin1_code":"14.0",
    "gn:asciiname":"Rubashkino",
    "gn:country_code":"UA",
    "gn:dem":193,
    "gn:feature_class":"P",
    "gn:feature_code":"PPL",
    "gn:name":"Rubashkino",
    "gn:population":0,
    "gn:timezone":"Europe/Zaporozhye",
    "iso:country":"UA",
    "wof:name":"Rubashkino",
    "wof:placetype":"locality"
},
  "geometry": {"coordinates":[38.43333,48.61667],"type":"Point"}
}