{
  "type": "Feature",
  "properties": {
    "gn:admin1_code":"10.0",
    "gn:asciiname":"Vysoki Bayraky",
    "gn:country_code":"UA",
    "gn:dem":143,
    "gn:feature_class":"P",
    "gn:feature_code":"PPL",
    "gn:name":"Vysoki Bayraky",
    "gn:population":0,
    "gn:timezone":"Europe/Kiev",
    "iso:country":"UA",
    "name:eng_x_preferred":[
        "Vysokiye Bayraki"
    ],
    "name:rus_x_preferred":[
        "\u0412\u044b\u0441\u043e\u043a\u0438\u0435 \u0411\u0430\u0439\u0440\u0430\u043a\u0438"
    ],
    "name:ukr_x_preferred":[
        "Vysoki Bayraky"
    ],
    "name:ukr_x_variant":[
        "\u0412\u0438\u0441\u043e\u043a\u0456 \u0411\u0430\u0439\u0440\u0430\u043a\u0438"
    ],
    "name:und_x_variant":[
        "Kremenetskoye",
        "Vyselok Buyerak",
        "Vysokiye Bayraki"
    ],
    "wof:name":"Vysoki Bayraky",
    "wof:placetype":"locality"
},
  "geometry": {"coordinates":[32.33692,48.60695],"type":"Point"}
}