{
  "type": "Feature",
  "properties": {
    "iso:country":"UA",
    "name:aze_x_preferred":[
        "Sankt-Peterburq D\u00f6vl\u0259t Telekommunikasiya Universiteti"
    ],
    "name:rus_x_preferred":[
        "\u0421\u0430\u043d\u043a\u0442-\u041f\u0435\u0442\u0435\u0440\u0431\u0443\u0440\u0433\u0441\u043a\u0438\u0439 \u0433\u043e\u0441\u0443\u0434\u0430\u0440\u0441\u0442\u0432\u0435\u043d\u043d\u044b\u0439 \u0443\u043d\u0438\u0432\u0435\u0440\u0441\u0438\u0442\u0435\u0442 \u0442\u0435\u043b\u0435\u043a\u043e\u043c\u043c\u0443\u043d\u0438\u043a\u0430\u0446\u0438\u0439 \u0438\u043c\u0435\u043d\u0438 \u043f\u0440\u043e\u0444\u0435\u0441\u0441\u043e\u0440\u0430 \u041c. \u0410. \u0411\u043e\u043d\u0447-\u0411\u0440\u0443\u0435\u0432\u0438\u0447\u0430"
    ],
    "name:ukr_x_preferred":[
        "\u0413\u0443\u0442"
    ],
    "name:und_x_variant":[
        "Velikaya Gorazdovka"
    ],
    "qs:a0":"\u0423\u043a\u0440\u0430\u0457\u043d\u0430",
    "qs:a1":"*\u0417\u0430\u043a\u0430\u0440\u043f\u0430\u0442\u0441\u044c\u043a\u0430",
    "qs:a1_alt":"Zakarpats'ka",
    "qs:a1r":"0",
    "qs:a2":"\u0411\u0435\u0440\u0435\u0433\u0456\u0432\u0441\u044c\u043a\u0438\u0439",
    "qs:a2_alt":"Berehivs'kyi",
    "qs:adm0":"\u0423\u043a\u0440\u0430\u0457\u043d\u0430",
    "qs:la_lc":"*",
    "qs:level":"locality",
    "qs:loc":"\u0413\u0443\u0442",
    "qs:loc_alt":"Hut",
    "qs:pop":0,
    "qs:type":"buffered point",
    "wd:wordcount":520,
    "wof:name":"\u0413\u0443\u0442",
    "wof:placetype":"locality"
},
  "geometry": {"coordinates":[22.582253,48.311949],"type":"Point"}
}