{
  "type": "Feature",
  "properties": {
    "gn:admin1_code":"3.0",
    "gn:asciiname":"Novyy Vovchynets'",
    "gn:country_code":"UA",
    "gn:dem":317,
    "gn:feature_class":"P",
    "gn:feature_code":"PPL",
    "gn:name":"Novyy Vovchynets\u2019",
    "gn:population":0,
    "gn:timezone":"Europe/Kiev",
    "iso:country":"UA",
    "name:ukr_x_preferred":[
        "Novyy Vovchynets\u2019"
    ],
    "name:und_x_variant":[
        "Novyy Volchinets"
    ],
    "wof:name":"Novyy Vovchynets'",
    "wof:placetype":"locality"
},
  "geometry": {"coordinates":[26.00022,47.99244],"type":"Point"}
}