{
  "type": "Feature",
  "properties": {
    "gn:admin1_code":"5.0",
    "gn:asciiname":"Nadezhdynka",
    "gn:country_code":"UA",
    "gn:dem":135,
    "gn:feature_class":"P",
    "gn:feature_code":"PPL",
    "gn:name":"Nadezhdynka",
    "gn:population":0,
    "gn:timezone":"Europe/Kiev",
    "iso:country":"UA",
    "name:ukr_x_preferred":[
        "Nadezhdynka"
    ],
    "name:ukr_x_variant":[
        "\u041d\u0430\u0434\u0435\u0436\u0434\u0438\u043d\u043a\u0430"
    ],
    "name:und_x_variant":[
        "Nadezhdinka"
    ],
    "wof:name":"Nadezhdynka",
    "wof:placetype":"locality"
},
  "geometry": {"coordinates":[37.00579000000001,48.13991],"type":"Point"}
}