{
  "type": "Feature",
  "properties": {
    "gn:admin1_code":"21.0",
    "gn:asciiname":"Karpenkove",
    "gn:country_code":"UA",
    "gn:dem":157,
    "gn:feature_class":"P",
    "gn:feature_code":"PPL",
    "gn:name":"Karpenkove",
    "gn:population":0,
    "gn:timezone":"Europe/Kiev",
    "iso:country":"UA",
    "name:ukr_x_preferred":[
        "Karpenkove"
    ],
    "name:ukr_x_variant":[
        "\u041a\u0430\u0440\u043f\u0435\u043d\u043a\u043e\u0432\u0435"
    ],
    "name:und_x_variant":[
        "Karpenkovo"
    ],
    "wof:name":"Karpenkove",
    "wof:placetype":"locality"
},
  "geometry": {"coordinates":[33.91351,51.07377],"type":"Point"}
}