{
  "type": "Feature",
  "properties": {
    "gn:admin1_code":"14.0",
    "gn:asciiname":"Pugachevka",
    "gn:country_code":"UA",
    "gn:dem":165,
    "gn:feature_class":"P",
    "gn:feature_code":"PPL",
    "gn:name":"Pugachevka",
    "gn:population":0,
    "gn:timezone":"Europe/Zaporozhye",
    "iso:country":"UA",
    "wof:name":"Pugachevka",
    "wof:placetype":"locality"
},
  "geometry": {"coordinates":[38.67472,48.7075],"type":"Point"}
}