{
  "type": "Feature",
  "properties": {
    "gn:admin1_code":"2.0",
    "gn:asciiname":"Vyr",
    "gn:country_code":"UA",
    "gn:dem":116,
    "gn:feature_class":"P",
    "gn:feature_code":"PPL",
    "gn:name":"Vyr",
    "gn:population":0,
    "gn:timezone":"Europe/Kiev",
    "iso:country":"UA",
    "name:ukr_x_preferred":[
        "Vyr"
    ],
    "name:ukr_x_variant":[
        "\u0412\u0438\u0440"
    ],
    "name:und_x_variant":[
        "Vir\u2019"
    ],
    "wof:name":"Vyr",
    "wof:placetype":"locality"
},
  "geometry": {"coordinates":[30.96534,51.91708],"type":"Point"}
}