{
  "type": "Feature",
  "properties": {
    "gn:admin1_code":"4.0",
    "gn:asciiname":"Kryvbas",
    "gn:country_code":"UA",
    "gn:dem":120,
    "gn:feature_class":"P",
    "gn:feature_code":"PPL",
    "gn:name":"Kryvbas",
    "gn:population":0,
    "gn:timezone":"Europe/Kiev",
    "iso:country":"UA",
    "name:deu_x_preferred":[
        "Krywbas"
    ],
    "name:nno_x_preferred":[
        "Kryvbas"
    ],
    "name:rus_x_preferred":[
        "\u041a\u0440\u0438\u0432\u0431\u0430\u0441\u0441"
    ],
    "name:ukr_x_preferred":[
        "Kryvbas"
    ],
    "name:ukr_x_variant":[
        "\u041a\u0440\u0438\u0432\u0431\u0430\u0441"
    ],
    "name:und_x_variant":[
        "Krivbass"
    ],
    "wof:name":"Kryvbas",
    "wof:placetype":"locality"
},
  "geometry": {"coordinates":[33.06173,47.93439],"type":"Point"}
}