{
  "type": "Feature",
  "properties": {
    "gn:admin1_code":"5.0",
    "gn:asciiname":"Samsonove",
    "gn:country_code":"UA",
    "gn:dem":11,
    "gn:feature_class":"P",
    "gn:feature_code":"PPL",
    "gn:name":"Samsonove",
    "gn:population":0,
    "gn:timezone":"Europe/Kiev",
    "iso:country":"UA",
    "name:ukr_x_preferred":[
        "Samsonove"
    ],
    "name:ukr_x_variant":[
        "\u0421\u0430\u043c\u0441\u043e\u043d\u043e\u0432\u0435"
    ],
    "name:und_x_variant":[
        "Samsonov",
        "Samsonovo"
    ],
    "wof:name":"Samsonove",
    "wof:placetype":"locality"
},
  "geometry": {"coordinates":[38.00313,47.09982],"type":"Point"}
}