{
  "type": "Feature",
  "properties": {
    "gn:admin1_code":"21.0",
    "gn:asciiname":"Dovha Luka",
    "gn:country_code":"UA",
    "gn:dem":159,
    "gn:feature_class":"P",
    "gn:feature_code":"PPL",
    "gn:name":"Dovha Luka",
    "gn:population":0,
    "gn:timezone":"Europe/Kiev",
    "iso:country":"UA",
    "name:ukr_x_preferred":[
        "Dovha Luka"
    ],
    "name:ukr_x_variant":[
        "\u0414\u043e\u0432\u0433\u0430 \u041b\u0443\u043a\u0430"
    ],
    "name:und_x_variant":[
        "Dolgaya Luka"
    ],
    "wof:name":"Dovha Luka",
    "wof:placetype":"locality"
},
  "geometry": {"coordinates":[33.70805,50.62255],"type":"Point"}
}