{
  "type": "Feature",
  "properties": {
    "gn:admin1_code":"7.0",
    "gn:asciiname":"Mostove",
    "gn:country_code":"UA",
    "gn:dem":100,
    "gn:feature_class":"P",
    "gn:feature_code":"PPL",
    "gn:name":"Mostove",
    "gn:population":0,
    "gn:timezone":"Europe/Kiev",
    "iso:country":"UA",
    "name:ukr_x_preferred":[
        "Mostove"
    ],
    "name:ukr_x_variant":[
        "\u041c\u043e\u0441\u0442\u043e\u0432\u0435"
    ],
    "name:und_x_variant":[
        "Mostovyy"
    ],
    "wof:name":"Mostove",
    "wof:placetype":"locality"
},
  "geometry": {"coordinates":[37.12972,49.74333],"type":"Point"}
}