{
  "type": "Feature",
  "properties": {
    "gn:admin1_code":"8.0",
    "gn:asciiname":"Lyubymivka",
    "gn:country_code":"UA",
    "gn:dem":78,
    "gn:feature_class":"P",
    "gn:feature_code":"PPL",
    "gn:name":"Lyubymivka",
    "gn:population":0,
    "gn:timezone":"Europe/Kiev",
    "iso:country":"UA",
    "name:ukr_x_preferred":[
        "Lyubymivka"
    ],
    "name:ukr_x_variant":[
        "\u041b\u044e\u0431\u0438\u043c\u0456\u0432\u043a\u0430"
    ],
    "name:und_x_variant":[
        "Lyubimovka"
    ],
    "wof:name":"Lyubymivka",
    "wof:placetype":"locality"
},
  "geometry": {"coordinates":[33.71606,47.39412],"type":"Point"}
}