{
  "type": "Feature",
  "properties": {
    "gn:admin1_code":"3.0",
    "gn:asciiname":"Mikhucheny",
    "gn:country_code":"UA",
    "gn:dem":342,
    "gn:feature_class":"P",
    "gn:feature_code":"PPL",
    "gn:name":"Mikhucheny",
    "gn:population":0,
    "gn:timezone":"Europe/Kiev",
    "iso:country":"UA",
    "wof:name":"Mikhucheny",
    "wof:placetype":"locality"
},
  "geometry": {"coordinates":[25.96667,48.11667],"type":"Point"}
}