{
  "type": "Feature",
  "properties": {
    "gn:admin1_code":"21.0",
    "gn:asciiname":"Kalyuzhne",
    "gn:country_code":"UA",
    "gn:dem":147,
    "gn:feature_class":"P",
    "gn:feature_code":"PPL",
    "gn:name":"Kalyuzhne",
    "gn:population":0,
    "gn:timezone":"Europe/Kiev",
    "iso:country":"UA",
    "name:ukr_x_preferred":[
        "Kalyuzhne"
    ],
    "name:ukr_x_variant":[
        "\u041a\u0430\u043b\u044e\u0436\u043d\u0435"
    ],
    "name:und_x_variant":[
        "Kalyuzhnoye"
    ],
    "wof:name":"Kalyuzhne",
    "wof:placetype":"locality"
},
  "geometry": {"coordinates":[33.94247,51.59775],"type":"Point"}
}