{
  "type": "Feature",
  "properties": {
    "gn:admin1_code":"18.0",
    "gn:asciiname":"Kyselykha",
    "gn:country_code":"UA",
    "gn:dem":131,
    "gn:feature_class":"P",
    "gn:feature_code":"PPL",
    "gn:name":"Kyselykha",
    "gn:population":0,
    "gn:timezone":"Europe/Kiev",
    "iso:country":"UA",
    "name:ukr_x_preferred":[
        "Kyselykha"
    ],
    "name:ukr_x_variant":[
        "\u041a\u0438\u0441\u0435\u043b\u0438\u0445\u0430"
    ],
    "name:und_x_variant":[
        "Serbenovka"
    ],
    "wof:name":"Kyselykha",
    "wof:placetype":"locality"
},
  "geometry": {"coordinates":[34.16903,49.91025],"type":"Point"}
}