{
  "type": "Feature",
  "properties": {
    "gn:admin1_code":"21.0",
    "gn:asciiname":"Buyvalove",
    "gn:country_code":"UA",
    "gn:dem":204,
    "gn:feature_class":"P",
    "gn:feature_code":"PPL",
    "gn:name":"Buyvalove",
    "gn:population":0,
    "gn:timezone":"Europe/Kiev",
    "iso:country":"UA",
    "name:ukr_x_preferred":[
        "Buyvalove"
    ],
    "name:ukr_x_variant":[
        "\u0411\u0443\u0439\u0432\u0430\u043b\u043e\u0432\u0435"
    ],
    "name:und_x_variant":[
        "Buyvolovo Vtoroye",
        "Buyvalovo"
    ],
    "wof:name":"Buyvalove",
    "wof:placetype":"locality"
},
  "geometry": {"coordinates":[33.41694,51.49292],"type":"Point"}
}