{
  "type": "Feature",
  "properties": {
    "gn:admin1_code":"15.0",
    "gn:asciiname":"Dvirtsi",
    "gn:country_code":"UA",
    "gn:dem":205,
    "gn:feature_class":"P",
    "gn:feature_code":"PPL",
    "gn:name":"Dvirtsi",
    "gn:population":0,
    "gn:timezone":"Europe/Kiev",
    "iso:country":"UA",
    "name:ukr_x_preferred":[
        "Dvirtsi"
    ],
    "name:ukr_x_variant":[
        "\u0414\u0432\u0456\u0440\u0446\u0456"
    ],
    "name:und_x_variant":[
        "Dworce",
        "Dvortse",
        "Dvortsy"
    ],
    "wof:name":"Dvirtsi",
    "wof:placetype":"locality"
},
  "geometry": {"coordinates":[24.07973,50.23057],"type":"Point"}
}