{
  "type": "Feature",
  "properties": {
    "iso:country":"UA",
    "name:ukr_x_preferred":[
        "\u041a\u043e\u0436\u0443\u043c'\u044f\u043a\u0430 \u0421\u0442\u0435\u043f\u0430\u043d \u0414\u0435\u043c\u0438\u0434\u043e\u0432\u0438\u0447"
    ],
    "qs:a0":"\u0423\u043a\u0440\u0430\u0457\u043d\u0430",
    "qs:a1":"*\u0425\u0430\u0440\u043a\u0456\u0432\u0441\u044c\u043a\u0430",
    "qs:a1_alt":"Kharkivs'ka",
    "qs:a1r":"0",
    "qs:a2":"\u0425\u0430\u0440\u043a\u0456\u0432\u0441\u044c\u043a\u0438\u0439",
    "qs:a2_alt":"Kharkivs'kyi",
    "qs:adm0":"\u0423\u043a\u0440\u0430\u0457\u043d\u0430",
    "qs:la_lc":"*",
    "qs:level":"locality",
    "qs:loc":"\u041a\u043e\u043c\u0443\u043d\u0430\u0440",
    "qs:loc_alt":"Komunar",
    "qs:pop":0,
    "qs:type":"buffered point",
    "wd:wordcount":1017,
    "wof:name":"\u041a\u043e\u043c\u0443\u043d\u0430\u0440",
    "wof:placetype":"locality"
},
  "geometry": {"coordinates":[36.294411,49.914003],"type":"Point"}
}