{
  "type": "Feature",
  "properties": {
    "gn:admin1_code":"15",
    "gn:asciiname":"Pyla",
    "gn:country_code":"UA",
    "gn:dem":315,
    "gn:feature_class":"P",
    "gn:feature_code":"PPL",
    "gn:name":"Pyla",
    "gn:population":0,
    "gn:timezone":"Europe/Kiev",
    "iso:country":"UA",
    "name:ukr_x_preferred":[
        "Pyla"
    ],
    "name:ukr_x_variant":[
        "\u041f\u0438\u043b\u0430"
    ],
    "wof:name":"Pyla",
    "wof:placetype":"locality"
},
  "geometry": {"coordinates":[23.89248,49.1874],"type":"Point"}
}