{
  "type": "Feature",
  "properties": {
    "gn:admin1_code":"15",
    "gn:asciiname":"Pyla",
    "gn:country_code":"UA",
    "gn:dem":315,
    "gn:feature_class":"P",
    "gn:feature_code":"PPL",
    "gn:name":"Pyla",
    "gn:population":0,
    "gn:timezone":"Europe/Kiev",
    "iso:country":"UA",
    "name:bul_x_preferred":[
        "\u041f\u0438\u043b\u0430"
    ],
    "name:ceb_x_preferred":[
        "P\u00fdla"
    ],
    "name:deu_x_preferred":[
        "Pyla"
    ],
    "name:ell_x_preferred":[
        "\u03a0\u03cd\u03bb\u03b1"
    ],
    "name:fas_x_preferred":[
        "\u067e\u0627\u06cc\u0644\u0627"
    ],
    "name:fra_x_preferred":[
        "P\u00fdla"
    ],
    "name:hye_x_preferred":[
        "\u054a\u056b\u056c\u0561"
    ],
    "name:nld_x_preferred":[
        "Pyla"
    ],
    "name:nno_x_preferred":[
        "P\u00fdla"
    ],
    "name:pol_x_preferred":[
        "Pila"
    ],
    "name:rus_x_preferred":[
        "\u041f\u0438\u043b\u0430"
    ],
    "name:sco_x_preferred":[
        "Pyla"
    ],
    "name:snd_x_preferred":[
        "\u067e\u0627\u067e\u0644\u0627"
    ],
    "name:spa_x_preferred":[
        "Pyla"
    ],
    "name:swe_x_preferred":[
        "Pyla"
    ],
    "name:tur_x_preferred":[
        "Pile"
    ],
    "name:ukr_x_preferred":[
        "Pyla"
    ],
    "name:ukr_x_variant":[
        "\u041f\u0438\u043b\u0430"
    ],
    "name:urd_x_preferred":[
        "\u067e\u0627\u06cc\u0644\u0627"
    ],
    "wof:name":"Pyla",
    "wof:placetype":"locality"
},
  "geometry": {"coordinates":[23.89248,49.1874],"type":"Point"}
}