{
  "type": "Feature",
  "properties": {
    "gn:admin1_code":"18.0",
    "gn:asciiname":"Hrebenyaky",
    "gn:country_code":"UA",
    "gn:dem":154,
    "gn:feature_class":"P",
    "gn:feature_code":"PPL",
    "gn:name":"Hrebenyaky",
    "gn:population":0,
    "gn:timezone":"Europe/Kiev",
    "iso:country":"UA",
    "name:ukr_x_preferred":[
        "Hrebenyaky"
    ],
    "name:ukr_x_variant":[
        "\u0413\u0440\u0435\u0431\u0435\u043d\u044f\u043a\u0438"
    ],
    "wof:name":"Hrebenyaky",
    "wof:placetype":"locality"
},
  "geometry": {"coordinates":[34.14151,49.93539000000001],"type":"Point"}
}