{
  "type": "Feature",
  "properties": {
    "gn:admin1_code":"24.0",
    "gn:asciiname":"Pidsynivka",
    "gn:country_code":"UA",
    "gn:dem":159,
    "gn:feature_class":"P",
    "gn:feature_code":"PPL",
    "gn:name":"Pidsynivka",
    "gn:population":0,
    "gn:timezone":"Europe/Kiev",
    "iso:country":"UA",
    "name:ukr_x_preferred":[
        "Pidsynivka"
    ],
    "name:ukr_x_variant":[
        "\u041f\u0456\u0434\u0441\u0438\u043d\u0456\u0432\u043a\u0430"
    ],
    "name:und_x_variant":[
        "Podsynuvka",
        "Podsynovka"
    ],
    "wof:name":"Pidsynivka",
    "wof:placetype":"locality"
},
  "geometry": {"coordinates":[24.7488,51.48043],"type":"Point"}
}