{
  "type": "Feature",
  "properties": {
    "gn:admin1_code":"9.0",
    "gn:asciiname":"Brykulya",
    "gn:country_code":"UA",
    "gn:dem":264,
    "gn:feature_class":"P",
    "gn:feature_code":"PPL",
    "gn:name":"Brykulya",
    "gn:population":0,
    "gn:timezone":"Europe/Kiev",
    "iso:country":"UA",
    "name:ukr_x_preferred":[
        "Brykulya"
    ],
    "name:ukr_x_variant":[
        "\u0411\u0440\u0438\u043a\u0443\u043b\u044f"
    ],
    "name:und_x_variant":[
        "Brikulya"
    ],
    "wof:name":"Brykulya",
    "wof:placetype":"locality"
},
  "geometry": {"coordinates":[27.0157,49.95014000000001],"type":"Point"}
}