{
  "type": "Feature",
  "properties": {
    "gn:admin1_code":"5.0",
    "gn:asciiname":"Pervaya Balka",
    "gn:country_code":"UA",
    "gn:dem":97,
    "gn:feature_class":"P",
    "gn:feature_code":"PPL",
    "gn:name":"Pervaya Balka",
    "gn:population":0,
    "gn:timezone":"Europe/Kiev",
    "iso:country":"UA",
    "wof:name":"Pervaya Balka",
    "wof:placetype":"locality"
},
  "geometry": {"coordinates":[38.08333,47.65],"type":"Point"}
}