{
  "type": "Feature",
  "properties": {
    "gn:admin1_code":"23.0",
    "gn:asciiname":"Luka Nemirovskaya",
    "gn:country_code":"UA",
    "gn:dem":290,
    "gn:feature_class":"P",
    "gn:feature_code":"PPL",
    "gn:name":"Luka Nemirovskaya",
    "gn:population":0,
    "gn:timezone":"Europe/Kiev",
    "iso:country":"UA",
    "wof:name":"Luka Nemirovskaya",
    "wof:placetype":"locality"
},
  "geometry": {"coordinates":[28.71667,49.01667],"type":"Point"}
}