{
  "type": "Feature",
  "properties": {
    "iso:country":"UA",
    "name:ukr_x_preferred":[
        "Ihnatpil\u2019"
    ],
    "name:ukr_x_variant":[
        "\u0406\u0433\u043d\u0430\u0442\u043f\u0456\u043b\u044c"
    ],
    "name:und_x_variant":[
        "Ignatopol\u2019"
    ],
    "qs:a0":"\u0423\u043a\u0440\u0430\u0457\u043d\u0430",
    "qs:a1":"*\u0416\u0438\u0442\u043e\u043c\u0438\u0440\u0441\u044c\u043a\u0430",
    "qs:a1_alt":"Zhytomyrs'ka",
    "qs:a1r":"0",
    "qs:a2":"\u041e\u0432\u0440\u0443\u0446\u044c\u043a\u0438\u0439",
    "qs:a2_alt":"Ovruts'kyi",
    "qs:adm0":"\u0423\u043a\u0440\u0430\u0457\u043d\u0430",
    "qs:la_lc":"*",
    "qs:level":"locality",
    "qs:loc":"\u0406\u0433\u043d\u0430\u0442\u043f\u0456\u043b\u044c",
    "qs:loc_alt":"Ihnatpil",
    "qs:pop":0,
    "qs:type":"buffered point",
    "wof:name":"\u0406\u0433\u043d\u0430\u0442\u043f\u0456\u043b\u044c",
    "wof:placetype":"locality"
},
  "geometry": {"coordinates":[28.728394,51.140326],"type":"Point"}
}