{
  "type": "Feature",
  "properties": {
    "gn:admin1_code":"19.0",
    "gn:asciiname":"Chemerne",
    "gn:country_code":"UA",
    "gn:dem":151,
    "gn:feature_class":"P",
    "gn:feature_code":"PPL",
    "gn:name":"Chemerne",
    "gn:population":0,
    "gn:timezone":"Europe/Kiev",
    "iso:country":"UA",
    "name:ukr_x_preferred":[
        "Chemerne"
    ],
    "name:ukr_x_variant":[
        "\u0427\u0435\u043c\u0435\u0440\u043d\u0435"
    ],
    "name:und_x_variant":[
        "Chemernoye"
    ],
    "wof:name":"Chemerne",
    "wof:placetype":"locality"
},
  "geometry": {"coordinates":[26.50271,51.32724],"type":"Point"}
}