{
  "type": "Feature",
  "properties": {
    "gn:admin1_code":"7.0",
    "gn:asciiname":"Bohdanove",
    "gn:country_code":"UA",
    "gn:dem":191,
    "gn:feature_class":"P",
    "gn:feature_code":"PPL",
    "gn:name":"Bohdanove",
    "gn:population":0,
    "gn:timezone":"Europe/Kiev",
    "iso:country":"UA",
    "name:ukr_x_preferred":[
        "Bohdanove"
    ],
    "name:ukr_x_variant":[
        "\u0411\u043e\u0433\u0434\u0430\u043d\u043e\u0432\u0435"
    ],
    "name:und_x_variant":[
        "Bogdanovka",
        "Bogdanovo"
    ],
    "wof:name":"Bohdanove",
    "wof:placetype":"locality"
},
  "geometry": {"coordinates":[36.82023,48.80649],"type":"Point"}
}