{
  "type": "Feature",
  "properties": {
    "gn:admin1_code":"7.0",
    "gn:asciiname":"Afrykanivka",
    "gn:country_code":"UA",
    "gn:dem":165,
    "gn:feature_class":"P",
    "gn:feature_code":"PPL",
    "gn:name":"Afrykanivka",
    "gn:population":0,
    "gn:timezone":"Europe/Kiev",
    "iso:country":"UA",
    "name:ukr_x_preferred":[
        "Afrykanivka"
    ],
    "name:ukr_x_variant":[
        "\u0410\u0444\u0440\u0456\u043a\u0430\u043d\u0456\u0432\u043a\u0430"
    ],
    "name:und_x_variant":[
        "Afrikanovka"
    ],
    "wof:name":"Afrykanivka",
    "wof:placetype":"locality"
},
  "geometry": {"coordinates":[36.81026,48.88476],"type":"Point"}
}