{
  "type": "Feature",
  "properties": {
    "gn:admin1_code":"14.0",
    "gn:asciiname":"Lysevka",
    "gn:country_code":"UA",
    "gn:dem":46,
    "gn:feature_class":"P",
    "gn:feature_code":"PPL",
    "gn:name":"Lysevka",
    "gn:population":0,
    "gn:timezone":"Europe/Zaporozhye",
    "iso:country":"UA",
    "name:und_x_variant":[
        "Novos\u00eblovka"
    ],
    "wof:name":"Lysevka",
    "wof:placetype":"locality"
},
  "geometry": {"coordinates":[39.83194,48.83972],"type":"Point"}
}