{
  "type": "Feature",
  "properties": {
    "gn:admin1_code":"2.0",
    "gn:asciiname":"Murivka",
    "gn:country_code":"UA",
    "gn:dem":127,
    "gn:feature_class":"P",
    "gn:feature_code":"PPL",
    "gn:name":"Murivka",
    "gn:population":0,
    "gn:timezone":"Europe/Kiev",
    "iso:country":"UA",
    "name:ukr_x_preferred":[
        "Murivka"
    ],
    "name:ukr_x_variant":[
        "\u041c\u0443\u0440\u0456\u0432\u043a\u0430"
    ],
    "name:und_x_variant":[
        "Murovka"
    ],
    "wof:name":"Murivka",
    "wof:placetype":"locality"
},
  "geometry": {"coordinates":[31.82438,51.47425],"type":"Point"}
}