{
  "type": "Feature",
  "properties": {
    "iso:country":"UA",
    "name:und_x_variant":[
        "Telepino"
    ],
    "qs:a0":"\u0423\u043a\u0440\u0430\u0457\u043d\u0430",
    "qs:a1":"*\u0427\u0435\u0440\u043a\u0430\u0441\u044c\u043a\u0430",
    "qs:a1_alt":"Cherkas'ka",
    "qs:a1r":"0",
    "qs:a2":"\u041a\u0430\u043c'\u044f\u043d\u0441\u044c\u043a\u0438\u0439",
    "qs:a2_alt":"Kamyans'kyi",
    "qs:adm0":"\u0423\u043a\u0440\u0430\u0457\u043d\u0430",
    "qs:la_lc":"*",
    "qs:level":"locality",
    "qs:loc":"\u0422\u0435\u043b\u0435\u043f\u0438\u043d\u0435",
    "qs:loc_alt":"Telepyne",
    "qs:pop":0,
    "qs:type":"buffered point",
    "wof:name":"\u0422\u0435\u043b\u0435\u043f\u0438\u043d\u0435",
    "wof:placetype":"locality"
},
  "geometry": {"coordinates":[31.891377,48.992216],"type":"Point"}
}