{
  "type": "Feature",
  "properties": {
    "gn:gn_country":"UA",
    "gn:gn_fcode":"PPL",
    "gn:gn_pop":19719,
    "gn:population":19719,
    "iso:country":"UA",
    "name:bel_x_preferred":[
        "\u0420\u044d\u043d\u0456"
    ],
    "name:bul_x_preferred":[
        "\u0420\u0435\u043d\u0438"
    ],
    "name:ces_x_preferred":[
        "Reni"
    ],
    "name:deu_x_preferred":[
        "Reni"
    ],
    "name:eng_x_preferred":[
        "Reni"
    ],
    "name:fas_x_preferred":[
        "\u0631\u0646\u06cc\u060c \u0627\u0648\u06a9\u0631\u0627\u06cc\u0646"
    ],
    "name:fra_x_preferred":[
        "Reni"
    ],
    "name:heb_x_preferred":[
        "\u05e8\u05e0\u05d9"
    ],
    "name:hun_x_preferred":[
        "Renyi"
    ],
    "name:hye_x_preferred":[
        "\u054c\u0565\u0576\u056b"
    ],
    "name:ita_x_preferred":[
        "Reni"
    ],
    "name:jpn_x_preferred":[
        "\u30ec\u30cb"
    ],
    "name:kat_x_preferred":[
        "\u10e0\u10d4\u10dc\u10d8"
    ],
    "name:lav_x_preferred":[
        "Re\u0146i"
    ],
    "name:nld_x_preferred":[
        "Reni"
    ],
    "name:nno_x_preferred":[
        "Reni"
    ],
    "name:pol_x_preferred":[
        "Reni"
    ],
    "name:ron_x_preferred":[
        "Reni"
    ],
    "name:rus_x_preferred":[
        "\u0420\u0435\u043d\u0438"
    ],
    "name:sah_x_preferred":[
        "\u0420\u0435\u043d\u0438"
    ],
    "name:spa_x_preferred":[
        "Reni"
    ],
    "name:srp_x_preferred":[
        "\u0420\u0435\u043d\u0438"
    ],
    "name:swe_x_preferred":[
        "Reni"
    ],
    "name:szl_x_preferred":[
        "Reni"
    ],
    "name:tat_x_preferred":[
        "\u0420\u0435\u043d\u0438"
    ],
    "name:ukr_x_preferred":[
        "\u0420\u0435\u043d\u0456"
    ],
    "name:vie_x_preferred":[
        "Reni"
    ],
    "name:zho_x_preferred":[
        "\u5217\u5c3c"
    ],
    "qs_pg:aaroncc":"UA",
    "qs_pg:gn_country":"UA",
    "qs_pg:gn_fcode":"PPL",
    "qs_pg:gn_pop":19719,
    "qs_pg:name":"Reni",
    "qs_pg:photos_9r":0,
    "qs_pg:photos_sr":0,
    "qs_pg:pop_sr":6,
    "qs_pg:qs_pg_placetype":"locality",
    "wof:name":"Reni",
    "wof:placetype":"locality",
    "wof:population":19719
},
  "geometry": {"coordinates":[28.29317,45.45727],"type":"Point"}
}