{
  "type": "Feature",
  "properties": {
    "gn:admin1_code":"2.0",
    "gn:asciiname":"Khrypivka",
    "gn:country_code":"UA",
    "gn:dem":130,
    "gn:feature_class":"P",
    "gn:feature_code":"PPL",
    "gn:name":"Khrypivka",
    "gn:population":0,
    "gn:timezone":"Europe/Kiev",
    "iso:country":"UA",
    "name:ukr_x_preferred":[
        "Khrypivka"
    ],
    "name:ukr_x_variant":[
        "\u0425\u0440\u0438\u043f\u0456\u0432\u043a\u0430"
    ],
    "name:und_x_variant":[
        "Khripovka"
    ],
    "wof:name":"Khrypivka",
    "wof:placetype":"locality"
},
  "geometry": {"coordinates":[31.61716,51.86607],"type":"Point"}
}