{
  "type": "Feature",
  "properties": {
    "gn:population":9877,
    "iso:country":"UA",
    "name:bel_x_variant":[
        "\u0421\u0430\u043a\u0456\u0440\u0430\u043d\u044b"
    ],
    "name:crh_x_preferred":[
        "Sok\u0131r\u00e2n\u0131"
    ],
    "name:deu_x_preferred":[
        "Sokyrjany"
    ],
    "name:eng_x_preferred":[
        "Sokyriany"
    ],
    "name:fas_x_preferred":[
        "\u0633\u0648\u06a9\u0631\u06cc\u0627\u0646\u06cc"
    ],
    "name:fra_x_preferred":[
        "Sokyriany"
    ],
    "name:heb_x_preferred":[
        "\u05e1\u05e7\u05d5\u05e8\u05e0\u05d9"
    ],
    "name:hye_x_preferred":[
        "\u054d\u0578\u056f\u056b\u0580\u0575\u0561\u0576\u056b"
    ],
    "name:ita_x_preferred":[
        "Sokyrjany"
    ],
    "name:kat_x_preferred":[
        "\u10e1\u10dd\u10d9\u10d8\u10e0\u10d8\u10d0\u10dc\u10d8"
    ],
    "name:lav_x_preferred":[
        "Sokirjani"
    ],
    "name:nld_x_preferred":[
        "Sokyriany"
    ],
    "name:nno_x_preferred":[
        "Sokyrjany"
    ],
    "name:pol_x_preferred":[
        "Sokiriany"
    ],
    "name:ron_x_preferred":[
        "Secureni"
    ],
    "name:rus_x_preferred":[
        "\u0421\u043e\u043a\u0438\u0440\u044f\u043d\u044b"
    ],
    "name:rus_x_variant":[
        "\u0421\u043e\u043a\u0438\u0440\u044f\u043d\u0438"
    ],
    "name:sco_x_preferred":[
        "Sokyriany"
    ],
    "name:tat_x_preferred":[
        "\u0421\u043e\u043a\u044b\u0440\u04d9\u043d\u044b"
    ],
    "name:ukr_x_preferred":[
        "\u0421\u043e\u043a\u0438\u0440\u044f\u043d\u0438"
    ],
    "name:unk_x_variant":[
        "Secureni"
    ],
    "name:vie_x_preferred":[
        "Sokyriany"
    ],
    "name:zho_x_preferred":[
        "\u7d22\u57fa\u91cc\u4e9e\u5c3c"
    ],
    "qs:a0":"\u0423\u043a\u0440\u0430\u0457\u043d\u0430",
    "qs:a1":"*\u0427\u0435\u0440\u043d\u0456\u0432\u0435\u0446\u044c\u043a\u0430",
    "qs:a1_alt":"Chernivets'ka",
    "qs:a1r":"0",
    "qs:a2":"\u0421\u043e\u043a\u0438\u0440\u044f\u043d\u0441\u044c\u043a\u0438\u0439",
    "qs:a2_alt":"Sokyrians'kyi",
    "qs:adm0":"\u0423\u043a\u0440\u0430\u0457\u043d\u0430",
    "qs:la_lc":"*",
    "qs:level":"locality",
    "qs:loc":"\u0421\u043e\u043a\u0438\u0440\u044f\u043d\u0438",
    "qs:loc_alt":"Sokyriany",
    "qs:pop":0,
    "qs:type":"buffered point",
    "wd:wordcount":33,
    "wof:name":"\u0421\u043e\u043a\u0438\u0440\u044f\u043d\u0438",
    "wof:placetype":"locality",
    "wof:population":9877
},
  "geometry": {"coordinates":[27.406053,48.459822],"type":"Point"}
}