{
  "type": "Feature",
  "properties": {
    "gn:admin1_code":"13.0",
    "gn:asciiname":"Sloboda",
    "gn:country_code":"UA",
    "gn:dem":216,
    "gn:feature_class":"P",
    "gn:feature_code":"PPL",
    "gn:name":"Sloboda",
    "gn:population":0,
    "gn:timezone":"Europe/Kiev",
    "iso:country":"UA",
    "wof:name":"Sloboda",
    "wof:placetype":"locality"
},
  "geometry": {"coordinates":[29.66667,49.71667],"type":"Point"}
}