{
  "type": "Feature",
  "properties": {
    "gn:admin1_code":"1.0",
    "gn:asciiname":"Kovtunivka",
    "gn:country_code":"UA",
    "gn:dem":110,
    "gn:feature_class":"P",
    "gn:feature_code":"PPL",
    "gn:name":"Kovtunivka",
    "gn:population":0,
    "gn:timezone":"Europe/Kiev",
    "iso:country":"UA",
    "name:ukr_x_preferred":[
        "Kovtunivka"
    ],
    "name:ukr_x_variant":[
        "\u041a\u043e\u0432\u0442\u0443\u043d\u0456\u0432\u043a\u0430"
    ],
    "wof:name":"Kovtunivka",
    "wof:placetype":"locality"
},
  "geometry": {"coordinates":[32.26674000000001,50.01341],"type":"Point"}
}