{
  "type": "Feature",
  "properties": {
    "iso:country":"UA",
    "name:ukr_x_preferred":[
        "\u0411\u0440\u043e\u043d\u0438\u0446\u044c\u043a\u0430 \u0413\u0443\u0442\u0430"
    ],
    "name:und_x_variant":[
        "Bronits\u2019ka Guta"
    ],
    "qs:a0":"\u0423\u043a\u0440\u0430\u0457\u043d\u0430",
    "qs:a1":"*\u0416\u0438\u0442\u043e\u043c\u0438\u0440\u0441\u044c\u043a\u0430",
    "qs:a1_alt":"Zhytomyrs'ka",
    "qs:a1r":"0",
    "qs:a2":"\u041d\u043e\u0432\u043e\u0433\u0440\u0430\u0434-\u0412\u043e\u043b\u0438\u043d\u0441\u044c\u043a\u0438\u0439",
    "qs:a2_alt":"Novohrad-Volyns'kyi",
    "qs:adm0":"\u0423\u043a\u0440\u0430\u0457\u043d\u0430",
    "qs:la_lc":"*",
    "qs:level":"locality",
    "qs:loc":"\u0411\u0440\u043e\u043d\u0438\u0446\u044c\u043a\u0430 \u0413\u0443\u0442\u0430",
    "qs:loc_alt":"Bronyts'ka Huta",
    "qs:pop":0,
    "qs:type":"buffered point",
    "wof:name":"\u0411\u0440\u043e\u043d\u0438\u0446\u044c\u043a\u0430 \u0413\u0443\u0442\u0430",
    "wof:placetype":"locality"
},
  "geometry": {"coordinates":[27.321324,50.926627],"type":"Point"}
}