{
  "type": "Feature",
  "properties": {
    "gn:admin1_code":"22.0",
    "gn:asciiname":"Novosyulka-Gzhymaluvska",
    "gn:country_code":"UA",
    "gn:dem":294,
    "gn:feature_class":"P",
    "gn:feature_code":"PPL",
    "gn:name":"Novosyulka-Gzhymaluvska",
    "gn:population":0,
    "gn:timezone":"Europe/Kiev",
    "iso:country":"UA",
    "name:und_x_variant":[
        "Novosyulka-Gzhymalovska",
        "Novos\u00eblka"
    ],
    "wof:name":"Novosyulka-Gzhymaluvska",
    "wof:placetype":"locality"
},
  "geometry": {"coordinates":[26.09947,49.25377],"type":"Point"}
}