{
  "type": "Feature",
  "properties": {
    "gn:admin1_code":"11.0",
    "gn:admin2_code":"704383",
    "gn:admin3_code":"11152924.0",
    "gn:asciiname":"Blizhneye",
    "gn:country_code":"UA",
    "gn:dem":36,
    "gn:elevation":"38.0",
    "gn:feature_class":"P",
    "gn:feature_code":"PPL",
    "gn:name":"Blizhneye",
    "gn:population":963,
    "gn:timezone":"Europe/Simferopol",
    "iso:country":"UA",
    "name:eng_x_preferred":[
        "Blizhneye"
    ],
    "name:rus_x_historical":[
        "\u041a\u0438\u044f\u0301\u0442",
        "\u041a\u043e\u043a\u0447\u043e\u0440\u0430\u0301-\u041a\u044b\u044f\u0301\u0442"
    ],
    "name:rus_x_preferred":[
        "\u0411\u043b\u0438\u0436\u043d\u0435\u0435"
    ],
    "name:rus_x_variant":[
        "\u041a\u0438\u044f\u0301\u0442",
        "\u041a\u043e\u043a\u0447\u043e\u0440\u0430\u0301-\u041a\u044b\u044f\u0301\u0442"
    ],
    "wof:name":"Blizhneye",
    "wof:placetype":"locality",
    "wof:population":963
},
  "geometry": {"coordinates":[34.29907,45.52261],"type":"Point"}
}