{
  "type": "Feature",
  "properties": {
    "gn:admin1_code":"2.0",
    "gn:asciiname":"Berylivka",
    "gn:country_code":"UA",
    "gn:dem":138,
    "gn:feature_class":"P",
    "gn:feature_code":"PPL",
    "gn:name":"Berylivka",
    "gn:population":0,
    "gn:timezone":"Europe/Kiev",
    "iso:country":"UA",
    "name:ukr_x_preferred":[
        "Berylivka"
    ],
    "name:ukr_x_variant":[
        "\u0411\u0435\u0440\u0438\u043b\u0456\u0432\u043a\u0430"
    ],
    "name:und_x_variant":[
        "Berilovka"
    ],
    "wof:name":"Berylivka",
    "wof:placetype":"locality"
},
  "geometry": {"coordinates":[31.74255,52.07469],"type":"Point"}
}