{
  "type": "Feature",
  "properties": {
    "gn:country":"UA",
    "gn:fcode":"PPL",
    "gn:population":3619,
    "iso:country":"UA",
    "name:rus_x_preferred":[
        "\u041d\u043e\u0432\u0435 \u041c\u0456\u0441\u0442\u043e"
    ],
    "name:ukr_x_preferred":[
        "\u041d\u043e\u0432\u0435 \u041c\u0456\u0441\u0442\u043e"
    ],
    "qs_pg:aaroncc":"UA",
    "qs_pg:gn_country":"UA",
    "qs_pg:gn_fcode":"PPL",
    "qs_pg:gn_pop":3619,
    "qs_pg:name":"Nove-Misto",
    "qs_pg:photos_9r":0,
    "qs_pg:photos_sr":0,
    "qs_pg:pop_sr":4,
    "qs_pg:qs_pg_placetype":"locality",
    "wof:name":"Nove-Misto",
    "wof:placetype":"locality",
    "wof:population":3619
},
  "geometry": {"coordinates":[29.82813,48.98113],"type":"Point"}
}