{
  "type": "Feature",
  "properties": {
    "gn:admin1_code":"22.0",
    "gn:asciiname":"Ol'shamazhur",
    "gn:country_code":"UA",
    "gn:dem":361,
    "gn:feature_class":"P",
    "gn:feature_code":"PPL",
    "gn:name":"Ol\u2019shamazhur",
    "gn:population":0,
    "gn:timezone":"Europe/Kiev",
    "iso:country":"UA",
    "wof:name":"Ol'shamazhur",
    "wof:placetype":"locality"
},
  "geometry": {"coordinates":[25.15,49.63333],"type":"Point"}
}