{
  "type": "Feature",
  "properties": {
    "iso:country":"UA",
    "name:bel_x_preferred":[
        "\u0421\u0430\u0442\u0430\u043d\u0456\u045e"
    ],
    "name:crh_x_preferred":[
        "Sataniv"
    ],
    "name:deu_x_preferred":[
        "Sataniw"
    ],
    "name:eng_x_preferred":[
        "Sataniv"
    ],
    "name:fra_x_preferred":[
        "Sataniv"
    ],
    "name:heb_x_preferred":[
        "\u05e1\u05d8\u05e0\u05d9\u05d1"
    ],
    "name:hye_x_preferred":[
        "\u054d\u0561\u057f\u0561\u0576\u0578\u057e"
    ],
    "name:nld_x_preferred":[
        "Sataniv"
    ],
    "name:pol_x_preferred":[
        "Satan\u00f3w"
    ],
    "name:ron_x_preferred":[
        "Sataniv"
    ],
    "name:rus_x_preferred":[
        "\u0421\u0430\u0442\u0430\u043d\u043e\u0432"
    ],
    "name:ukr_x_preferred":[
        "\u0421\u0430\u0442\u0430\u043d\u0456\u0432"
    ],
    "name:ukr_x_variant":[
        "Sataniv"
    ],
    "name:zho_x_preferred":[
        "\u85a9\u5854\u5c3c\u592b"
    ],
    "qs:a0":"\u0423\u043a\u0440\u0430\u0457\u043d\u0430",
    "qs:a1":"*\u0425\u043c\u0435\u043b\u044c\u043d\u0438\u0446\u044c\u043a\u0430",
    "qs:a1_alt":"Khmel'nyts'ka",
    "qs:a1r":"0",
    "qs:a2":"\u0413\u043e\u0440\u043e\u0434\u043e\u0446\u044c\u043a\u0438\u0439",
    "qs:a2_alt":"Horodots'kyi",
    "qs:adm0":"\u0423\u043a\u0440\u0430\u0457\u043d\u0430",
    "qs:la_lc":"*",
    "qs:level":"locality",
    "qs:loc":"\u0421\u0430\u0442\u0430\u043d\u0456\u0432",
    "qs:loc_alt":"Sataniv",
    "qs:pop":0,
    "qs:type":"buffered point",
    "wd:wordcount":470,
    "wof:name":"\u0421\u0430\u0442\u0430\u043d\u0456\u0432",
    "wof:placetype":"locality"
},
  "geometry": {"coordinates":[26.261492,49.249131],"type":"Point"}
}