{
  "type": "Feature",
  "properties": {
    "gn:admin1_code":"21.0",
    "gn:asciiname":"Tovchenykove",
    "gn:country_code":"UA",
    "gn:dem":186,
    "gn:feature_class":"P",
    "gn:feature_code":"PPL",
    "gn:name":"Tovchenykove",
    "gn:population":0,
    "gn:timezone":"Europe/Kiev",
    "iso:country":"UA",
    "name:ukr_x_preferred":[
        "Tovchenykove"
    ],
    "name:ukr_x_variant":[
        "\u0422\u043e\u0432\u0447\u0435\u043d\u0438\u043a\u043e\u0432\u0435"
    ],
    "name:und_x_variant":[
        "Tolchenikovo"
    ],
    "wof:name":"Tovchenykove",
    "wof:placetype":"locality"
},
  "geometry": {"coordinates":[33.91741,51.34852],"type":"Point"}
}