{
  "type": "Feature",
  "properties": {
    "iso:country":"UA",
    "name:eng_x_preferred":[
        "Korogod"
    ],
    "name:rus_x_preferred":[
        "\u041a\u043e\u0440\u043e\u0433\u043e\u0434"
    ],
    "name:ukr_x_preferred":[
        "Korohod"
    ],
    "name:ukr_x_variant":[
        "\u041a\u043e\u0440\u043e\u0433\u043e\u0434"
    ],
    "name:unk_x_variant":[
        "Korogod"
    ],
    "qs:a0":"\u0423\u043a\u0440\u0430\u0457\u043d\u0430",
    "qs:a1":"*\u041a\u0438\u0457\u0432\u0441\u044c\u043a\u0430",
    "qs:a1_alt":"Kyivs'ka",
    "qs:a1r":"0",
    "qs:a2":"\u0406\u0432\u0430\u043d\u043a\u0456\u0432\u0441\u044c\u043a\u0438\u0439",
    "qs:a2_alt":"Ivankivs'kyi",
    "qs:adm0":"\u0423\u043a\u0440\u0430\u0457\u043d\u0430",
    "qs:la_lc":"*",
    "qs:level":"locality",
    "qs:loc":"\u041a\u043e\u0440\u043e\u0433\u043e\u0434",
    "qs:loc_alt":"Korohod",
    "qs:pop":0,
    "qs:type":"buffered point",
    "wof:name":"\u041a\u043e\u0440\u043e\u0433\u043e\u0434",
    "wof:placetype":"locality"
},
  "geometry": {"coordinates":[30.010094,51.271626],"type":"Point"}
}