{
  "type": "Feature",
  "properties": {
    "gn:admin1_code":"11.0",
    "gn:admin2_code":"704383",
    "gn:admin3_code":"11152909.0",
    "gn:asciiname":"Dokhodnoye",
    "gn:country_code":"UA",
    "gn:dem":42,
    "gn:elevation":"43.0",
    "gn:feature_class":"P",
    "gn:feature_code":"PPL",
    "gn:name":"Dokhodnoye",
    "gn:population":155,
    "gn:timezone":"Europe/Simferopol",
    "iso:country":"UA",
    "name:eng_x_preferred":[
        "Dokhodnoye"
    ],
    "name:rus_x_historical":[
        "\u0427\u043e\u043b\u0431\u0430\u0301\u0448\u0438"
    ],
    "name:rus_x_preferred":[
        "\u0414\u043e\u0445\u043e\u0434\u043d\u043e\u0435"
    ],
    "name:rus_x_variant":[
        "\u0427\u043e\u043b\u0431\u0430\u0301\u0448\u0438"
    ],
    "name:ukr_x_preferred":[
        "\u0414\u043e\u0445\u043e\u0434\u043d\u0435"
    ],
    "wof:name":"Dokhodnoye",
    "wof:placetype":"locality",
    "wof:population":155
},
  "geometry": {"coordinates":[34.38634,45.48166],"type":"Point"}
}