{
  "type": "Feature",
  "properties": {
    "gn:admin1_code":"17.0",
    "gn:asciiname":"Spas'ke",
    "gn:country_code":"UA",
    "gn:dem":29,
    "gn:feature_class":"P",
    "gn:feature_code":"PPL",
    "gn:name":"Spas\u2019ke",
    "gn:population":0,
    "gn:timezone":"Europe/Kiev",
    "iso:country":"UA",
    "name:ukr_x_preferred":[
        "Spas\u2019ke"
    ],
    "name:ukr_x_variant":[
        "\u0421\u043f\u0430\u0441\u044c\u043a\u0435"
    ],
    "name:und_x_variant":[
        "Spaska",
        "Spasskaya",
        "Spasca",
        "Spasskoye"
    ],
    "wof:name":"Spas'ke",
    "wof:placetype":"locality"
},
  "geometry": {"coordinates":[29.43988,45.76301],"type":"Point"}
}