{
  "type": "Feature",
  "properties": {
    "gn:gn_country":"UA",
    "gn:gn_fcode":"PPL",
    "gn:gn_pop":2421,
    "gn:population":2377,
    "iso:country":"UA",
    "name:eng_x_preferred":[
        "Beregovoye"
    ],
    "name:rus_x_historical":[
        "\u041a\u043e\u0440\u043e\u043d\u0435\u043b\u044c"
    ],
    "name:rus_x_preferred":[
        "\u041a\u043e\u0440\u043e\u043d\u0435\u043b\u044c"
    ],
    "name:rus_x_variant":[
        "\u0411\u0435\u0440\u0435\u0433\u043e\u0432\u043e\u0435"
    ],
    "name:ukr_x_preferred":[
        "\u0411\u0435\u0440\u0435\u0433\u043e\u0432\u0435"
    ],
    "qs_pg:aaroncc":"UA",
    "qs_pg:gn_country":"UA",
    "qs_pg:gn_fcode":"PPL",
    "qs_pg:gn_pop":2421,
    "qs_pg:name":"Berehove",
    "qs_pg:photos_9r":0,
    "qs_pg:photos_sr":0,
    "qs_pg:pop_sr":4,
    "qs_pg:qs_pg_placetype":"locality",
    "wof:name":"Berehove",
    "wof:placetype":"locality",
    "wof:population":2377
},
  "geometry": {"coordinates":[35.43385,45.0947],"type":"Point"}
}