{
  "type": "Feature",
  "properties": {
    "gn:admin1_code":"15.0",
    "gn:asciiname":"Artasuv",
    "gn:country_code":"UA",
    "gn:dem":249,
    "gn:feature_class":"P",
    "gn:feature_code":"PPL",
    "gn:name":"Artasuv",
    "gn:population":0,
    "gn:timezone":"Europe/Kiev",
    "iso:country":"UA",
    "name:pol_x_historical":[
        "Artas\u00f3w"
    ],
    "name:pol_x_preferred":[
        "Artas\u00f3w"
    ],
    "name:ukr_x_preferred":[
        "Artasiv"
    ],
    "wof:name":"Artasuv",
    "wof:placetype":"locality"
},
  "geometry": {"coordinates":[24.12858,50.01008],"type":"Point"}
}