{
  "type": "Feature",
  "properties": {
    "gn:admin1_code":"8.0",
    "gn:asciiname":"Semykhatka",
    "gn:country_code":"UA",
    "gn:dem":13,
    "gn:feature_class":"P",
    "gn:feature_code":"PPL",
    "gn:name":"Semykhatka",
    "gn:population":0,
    "gn:timezone":"Europe/Kiev",
    "iso:country":"UA",
    "name:ukr_x_preferred":[
        "\u0421\u0435\u043c\u0438\u0445\u0442\u0430\u043a\u0430"
    ],
    "name:und_x_variant":[
        "Semikhatka",
        "Semykhatka"
    ],
    "wof:name":"Semykhatka",
    "wof:placetype":"locality"
},
  "geometry": {"coordinates":[34.7326,46.17207],"type":"Point"}
}