{
  "type": "Feature",
  "properties": {
    "gn:admin1_code":"17.0",
    "gn:asciiname":"Aheyivka",
    "gn:country_code":"UA",
    "gn:dem":170,
    "gn:feature_class":"P",
    "gn:feature_code":"PPL",
    "gn:name":"Aheyivka",
    "gn:population":0,
    "gn:timezone":"Europe/Kiev",
    "iso:country":"UA",
    "name:ukr_x_preferred":[
        "Aheyivka"
    ],
    "name:ukr_x_variant":[
        "\u0410\u0433\u0435\u0457\u0432\u043a\u0430"
    ],
    "name:und_x_variant":[
        "Mayorska",
        "Ageyevka"
    ],
    "wof:name":"Aheyivka",
    "wof:placetype":"locality"
},
  "geometry": {"coordinates":[30.29235,47.91436],"type":"Point"}
}