{
  "type": "Feature",
  "properties": {
    "iso:country":"UA",
    "name:ukr_x_preferred":[
        "Bovyshche"
    ],
    "name:ukr_x_variant":[
        "\u0411\u043e\u0432\u0438\u0449\u0435"
    ],
    "name:unk_x_variant":[
        "Bovishchi"
    ],
    "qs:a0":"\u0423\u043a\u0440\u0430\u0457\u043d\u0430",
    "qs:a1":"*\u041a\u0438\u0457\u0432\u0441\u044c\u043a\u0430",
    "qs:a1_alt":"Kyivs'ka",
    "qs:a1r":"0",
    "qs:a2":"\u041f\u043e\u043b\u0456\u0441\u044c\u043a\u0438\u0439",
    "qs:a2_alt":"Polis'kyi",
    "qs:adm0":"\u0423\u043a\u0440\u0430\u0457\u043d\u0430",
    "qs:la_lc":"*",
    "qs:level":"locality",
    "qs:loc":"\u0411\u043e\u0432\u0438\u0449\u0435",
    "qs:loc_alt":"Bovysche",
    "qs:pop":0,
    "qs:type":"buffered point",
    "wof:name":"\u0411\u043e\u0432\u0438\u0449\u0435",
    "wof:placetype":"locality"
},
  "geometry": {"coordinates":[29.738472,51.341192],"type":"Point"}
}