{
  "type": "Feature",
  "properties": {
    "iso:country":"UA",
    "name:bel_x_preferred":[
        "\u041d\u0430\u0433\u043e\u0440\u043d\u0430\u0435"
    ],
    "name:deu_x_preferred":[
        "Nahirne"
    ],
    "name:eng_x_preferred":[
        "Nahirne"
    ],
    "name:kaz_x_preferred":[
        "\u041d\u0430\u0433\u043e\u0440\u043d\u043e\u0435"
    ],
    "name:pol_x_preferred":[
        "Nahirne"
    ],
    "name:rus_x_preferred":[
        "\u041d\u0430\u0433\u043e\u0440\u043d\u043e\u0435"
    ],
    "name:tat_x_preferred":[
        "\u041d\u0430\u0433\u043e\u0440\u043d\u043e\u0435"
    ],
    "name:ukr_x_preferred":[
        "\u041d\u0430\u0433\u0456\u0440\u043d\u0435"
    ],
    "qs:a0":"\u0423\u043a\u0440\u0430\u0457\u043d\u0430",
    "qs:a1":"*\u041b\u044c\u0432\u0456\u0432\u0441\u044c\u043a\u0430",
    "qs:a1_alt":"L'vivs'ka",
    "qs:a1r":"0",
    "qs:a2":"\u0421\u0430\u043c\u0431\u0456\u0440\u0441\u044c\u043a\u0438\u0439",
    "qs:a2_alt":"Sambirs'kyi",
    "qs:adm0":"\u0423\u043a\u0440\u0430\u0457\u043d\u0430",
    "qs:la_lc":"*",
    "qs:level":"locality",
    "qs:loc":"\u041d\u0430\u0433\u0456\u0440\u043d\u0435",
    "qs:loc_alt":"Nahirne",
    "qs:pop":0,
    "qs:type":"buffered point",
    "wd:wordcount":37,
    "wof:name":"\u041d\u0430\u0433\u0456\u0440\u043d\u0435",
    "wof:placetype":"locality"
},
  "geometry": {"coordinates":[23.209681,49.478709],"type":"Point"}
}