{
  "type": "Feature",
  "properties": {
    "gn:admin1_code":"4.0",
    "gn:asciiname":"Chuvylyne",
    "gn:country_code":"UA",
    "gn:dem":111,
    "gn:feature_class":"P",
    "gn:feature_code":"PPL",
    "gn:name":"Chuvylyne",
    "gn:population":0,
    "gn:timezone":"Europe/Kiev",
    "iso:country":"UA",
    "name:ukr_x_preferred":[
        "Chuvylyne"
    ],
    "name:ukr_x_variant":[
        "\u0427\u0443\u0432\u0438\u043b\u0438\u043d\u0435"
    ],
    "wof:name":"Chuvylyne",
    "wof:placetype":"locality"
},
  "geometry": {"coordinates":[34.88766,48.26017],"type":"Point"}
}