{
  "type": "Feature",
  "properties": {
    "gn:admin1_code":"19.0",
    "gn:asciiname":"Huta-Pereyma",
    "gn:country_code":"UA",
    "gn:dem":156,
    "gn:feature_class":"P",
    "gn:feature_code":"PPL",
    "gn:name":"Huta-Pereyma",
    "gn:population":0,
    "gn:timezone":"Europe/Kiev",
    "iso:country":"UA",
    "name:ukr_x_preferred":[
        "Huta-Pereyma"
    ],
    "name:ukr_x_variant":[
        "\u0413\u0443\u0442\u0430-\u041f\u0435\u0440\u0435\u0439\u043c\u0430"
    ],
    "name:und_x_variant":[
        "Guta-Pereyma"
    ],
    "wof:name":"Huta-Pereyma",
    "wof:placetype":"locality"
},
  "geometry": {"coordinates":[26.58059,51.21088],"type":"Point"}
}