{
  "type": "Feature",
  "properties": {
    "gn:admin1_code":"9.0",
    "gn:asciiname":"Napadivka",
    "gn:country_code":"UA",
    "gn:dem":310,
    "gn:feature_class":"P",
    "gn:feature_code":"PPL",
    "gn:name":"Napadivka",
    "gn:population":0,
    "gn:timezone":"Europe/Kiev",
    "iso:country":"UA",
    "name:ukr_x_preferred":[
        "Napadivka"
    ],
    "name:ukr_x_variant":[
        "\u041d\u0430\u043f\u0430\u0434\u0456\u0432\u043a\u0430"
    ],
    "name:und_x_variant":[
        "Napadovka"
    ],
    "wof:name":"Napadivka",
    "wof:placetype":"locality"
},
  "geometry": {"coordinates":[27.06116,49.8572],"type":"Point"}
}