{
  "type": "Feature",
  "properties": {
    "gn:admin1_code":"27.0",
    "gn:asciiname":"Novyna",
    "gn:country_code":"UA",
    "gn:dem":216,
    "gn:feature_class":"P",
    "gn:feature_code":"PPL",
    "gn:name":"Novyna",
    "gn:population":0,
    "gn:timezone":"Europe/Kiev",
    "iso:country":"UA",
    "name:ukr_x_preferred":[
        "Novyna"
    ],
    "name:ukr_x_variant":[
        "\u041d\u043e\u0432\u0438\u043d\u0430"
    ],
    "name:und_x_variant":[
        "Novina"
    ],
    "wof:name":"Novyna",
    "wof:placetype":"locality"
},
  "geometry": {"coordinates":[28.29198,50.77204],"type":"Point"}
}