{
  "type": "Feature",
  "properties": {
    "gn:admin1_code":"13.0",
    "gn:asciiname":"Pologi-Verguny",
    "gn:country_code":"UA",
    "gn:dem":103,
    "gn:feature_class":"P",
    "gn:feature_code":"PPL",
    "gn:name":"Pologi-Verguny",
    "gn:population":0,
    "gn:timezone":"Europe/Kiev",
    "iso:country":"UA",
    "name:eng_x_preferred":[
        "Pologi-Verguny"
    ],
    "name:rus_x_preferred":[
        "\u041f\u043e\u043b\u043e\u0433\u0438-\u0412\u0435\u0440\u0433\u0443\u043d\u044b"
    ],
    "name:und_x_variant":[
        "Verguny",
        "Vertuny",
        "Verguny-Pologi"
    ],
    "wof:name":"Pologi-Verguny",
    "wof:placetype":"locality"
},
  "geometry": {"coordinates":[31.72548,50.00057],"type":"Point"}
}