{
  "type": "Feature",
  "properties": {
    "gn:admin1_code":"21.0",
    "gn:asciiname":"Ryabivka",
    "gn:country_code":"UA",
    "gn:dem":118,
    "gn:feature_class":"P",
    "gn:feature_code":"PPL",
    "gn:name":"Ryabivka",
    "gn:population":0,
    "gn:timezone":"Europe/Kiev",
    "iso:country":"UA",
    "name:ukr_x_preferred":[
        "Ryabivka"
    ],
    "name:ukr_x_variant":[
        "\u0420\u044f\u0431\u0456\u0432\u043a\u0430"
    ],
    "name:und_x_variant":[
        "Ryabovka"
    ],
    "wof:name":"Ryabivka",
    "wof:placetype":"locality"
},
  "geometry": {"coordinates":[35.25478,50.47788],"type":"Point"}
}