{
  "type": "Feature",
  "properties": {
    "gn:admin1_code":"13.0",
    "gn:asciiname":"Dubovka",
    "gn:country_code":"UA",
    "gn:dem":228,
    "gn:feature_class":"P",
    "gn:feature_code":"PPL",
    "gn:name":"Dubovka",
    "gn:population":0,
    "gn:timezone":"Europe/Kiev",
    "iso:country":"UA",
    "wof:name":"Dubovka",
    "wof:placetype":"locality"
},
  "geometry": {"coordinates":[30.47704,49.42549],"type":"Point"}
}