{
  "type": "Feature",
  "properties": {
    "gn:admin1_code":"27",
    "gn:asciiname":"Krynychky",
    "gn:country_code":"UA",
    "gn:dem":188,
    "gn:feature_class":"P",
    "gn:feature_code":"PPL",
    "gn:name":"Krynychky",
    "gn:population":0,
    "gn:timezone":"Europe/Kiev",
    "iso:country":"UA",
    "name:ceb_x_preferred":[
        "Krynychky"
    ],
    "name:crh_x_preferred":[
        "Kr\u0131n\u0131\u00e7k\u0131"
    ],
    "name:deu_x_preferred":[
        "Krynytschky"
    ],
    "name:fra_x_preferred":[
        "Krynytchky"
    ],
    "name:hye_x_preferred":[
        "\u053f\u0580\u056b\u0576\u056b\u0579\u056f\u056b"
    ],
    "name:ita_x_preferred":[
        "Kryny\u010dky"
    ],
    "name:pol_x_preferred":[
        "Krynyczky"
    ],
    "name:ron_x_preferred":[
        "Kr\u00een\u00eecik\u00ee"
    ],
    "name:rus_x_preferred":[
        "\u041a\u0440\u0438\u043d\u0438\u0447\u043a\u0438"
    ],
    "name:ukr_x_preferred":[
        "Krynychky"
    ],
    "name:ukr_x_variant":[
        "\u041a\u0440\u0438\u043d\u0438\u0447\u043a\u0438"
    ],
    "name:zho_x_preferred":[
        "\u514b\u91cc\u5c3c\u5947\u57fa"
    ],
    "wof:name":"Krynychky",
    "wof:placetype":"locality"
},
  "geometry": {"coordinates":[28.95006,50.22504],"type":"Point"}
}