{
  "type": "Feature",
  "properties": {
    "gn:admin1_code":"27",
    "gn:asciiname":"Krynychky",
    "gn:country_code":"UA",
    "gn:dem":188,
    "gn:feature_class":"P",
    "gn:feature_code":"PPL",
    "gn:name":"Krynychky",
    "gn:population":0,
    "gn:timezone":"Europe/Kiev",
    "iso:country":"UA",
    "name:ukr_x_preferred":[
        "Krynychky"
    ],
    "name:ukr_x_variant":[
        "\u041a\u0440\u0438\u043d\u0438\u0447\u043a\u0438"
    ],
    "wof:name":"Krynychky",
    "wof:placetype":"locality"
},
  "geometry": {"coordinates":[28.95006,50.22504],"type":"Point"}
}