{
  "type": "Feature",
  "properties": {
    "gn:admin1_code":"09",
    "gn:asciiname":"Pryhorivka",
    "gn:country_code":"UA",
    "gn:dem":264,
    "gn:feature_class":"P",
    "gn:feature_code":"PPL",
    "gn:name":"Pryhorivka",
    "gn:population":0,
    "gn:timezone":"Europe/Kiev",
    "iso:country":"UA",
    "name:ukr_x_preferred":[
        "Pryhorivka"
    ],
    "name:ukr_x_variant":[
        "\u041f\u0440\u0438\u0433\u043e\u0440\u0456\u0432\u043a\u0430"
    ],
    "wof:name":"Pryhorivka",
    "wof:placetype":"locality"
},
  "geometry": {"coordinates":[26.95398,49.97702],"type":"Point"}
}