{
  "type": "Feature",
  "properties": {
    "gn:admin1_code":"6.0",
    "gn:asciiname":"Sarniki",
    "gn:country_code":"UA",
    "gn:dem":259,
    "gn:feature_class":"P",
    "gn:feature_code":"PPL",
    "gn:name":"Sarniki",
    "gn:population":0,
    "gn:timezone":"Europe/Kiev",
    "iso:country":"UA",
    "name:und_x_variant":[
        "Sarnyky",
        "Sarnki",
        "Sarnki Gurne",
        "Sarniki"
    ],
    "wof:name":"Sarniki",
    "wof:placetype":"locality"
},
  "geometry": {"coordinates":[24.73625,49.31229],"type":"Point"}
}