{
  "type": "Feature",
  "properties": {
    "gn:admin1_code":"8.0",
    "gn:asciiname":"Novoyelyzavetivka",
    "gn:country_code":"UA",
    "gn:dem":50,
    "gn:feature_class":"P",
    "gn:feature_code":"PPL",
    "gn:name":"Novoyelyzavetivka",
    "gn:population":0,
    "gn:timezone":"Europe/Kiev",
    "iso:country":"UA",
    "name:rus_x_preferred":[
        "\u041d\u043e\u0432\u043e\u0435\u043b\u0438\u0437\u0430\u0432\u0435\u0442\u043e\u0432\u043a\u0430"
    ],
    "name:ukr_x_preferred":[
        "Novoyelyzavetivka"
    ],
    "name:ukr_x_variant":[
        "\u041d\u043e\u0432\u043e\u0454\u043b\u0438\u0437\u0430\u0432\u0435\u0442\u0456\u0432\u043a\u0430"
    ],
    "name:und_x_variant":[
        "Novo-Yelizavetovka"
    ],
    "wof:name":"Novoyelyzavetivka",
    "wof:placetype":"locality"
},
  "geometry": {"coordinates":[34.01587,46.80757],"type":"Point"}
}