{
  "type": "Feature",
  "properties": {
    "gn:admin1_code":"15.0",
    "gn:asciiname":"Lodyna Nova",
    "gn:country_code":"UA",
    "gn:dem":220,
    "gn:feature_class":"P",
    "gn:feature_code":"PPL",
    "gn:name":"Lodyna Nova",
    "gn:population":0,
    "gn:timezone":"Europe/Kiev",
    "iso:country":"UA",
    "wof:name":"Lodyna Nova",
    "wof:placetype":"locality"
},
  "geometry": {"coordinates":[24.38936,50.03086],"type":"Point"}
}