{
  "type": "Feature",
  "properties": {
    "gn:admin1_code":"18.0",
    "gn:asciiname":"Krokhmal'tsi",
    "gn:country_code":"UA",
    "gn:dem":128,
    "gn:feature_class":"P",
    "gn:feature_code":"PPL",
    "gn:name":"Krokhmal\u2019tsi",
    "gn:population":0,
    "gn:timezone":"Europe/Kiev",
    "iso:country":"UA",
    "name:ukr_x_preferred":[
        "Krokhmal\u2019tsi"
    ],
    "name:ukr_x_variant":[
        "\u041a\u0440\u043e\u0445\u043c\u0430\u043b\u044c\u0446\u0456"
    ],
    "wof:name":"Krokhmal'tsi",
    "wof:placetype":"locality"
},
  "geometry": {"coordinates":[33.94439000000001,49.64817],"type":"Point"}
}