{
  "type": "Feature",
  "properties": {
    "gn:admin1_code":"26.0",
    "gn:asciiname":"Kalynivka",
    "gn:country_code":"UA",
    "gn:dem":75,
    "gn:feature_class":"P",
    "gn:feature_code":"PPL",
    "gn:name":"Kalynivka",
    "gn:population":0,
    "gn:timezone":"Europe/Zaporozhye",
    "iso:country":"UA",
    "name:ukr_x_preferred":[
        "Kalynivka"
    ],
    "name:ukr_x_variant":[
        "\u041a\u0430\u043b\u0438\u043d\u0456\u0432\u043a\u0430"
    ],
    "name:und_x_variant":[
        "Yelizavettal\u2019"
    ],
    "wof:name":"Kalynivka",
    "wof:placetype":"locality"
},
  "geometry": {"coordinates":[35.99756,47.0243],"type":"Point"}
}