{
  "type": "Feature",
  "properties": {
    "gn:admin1_code":"24.0",
    "gn:asciiname":"Kropyvshchyna",
    "gn:country_code":"UA",
    "gn:dem":219,
    "gn:feature_class":"P",
    "gn:feature_code":"PPL",
    "gn:name":"Kropyvshchyna",
    "gn:population":0,
    "gn:timezone":"Europe/Kiev",
    "iso:country":"UA",
    "name:ukr_x_preferred":[
        "Kropyvshchyna"
    ],
    "name:ukr_x_variant":[
        "\u041a\u0440\u043e\u043f\u0438\u0432\u0449\u0438\u043d\u0430"
    ],
    "name:und_x_variant":[
        "Kropivshchyzna",
        "Krapivshchina"
    ],
    "wof:name":"Kropyvshchyna",
    "wof:placetype":"locality"
},
  "geometry": {"coordinates":[24.22858,50.71657],"type":"Point"}
}