{
  "type": "Feature",
  "properties": {
    "gn:admin1_code":"7.0",
    "gn:asciiname":"Dvorichnyy Kut",
    "gn:country_code":"UA",
    "gn:dem":116,
    "gn:feature_class":"P",
    "gn:feature_code":"PPL",
    "gn:name":"Dvorichnyy Kut",
    "gn:population":0,
    "gn:timezone":"Europe/Kiev",
    "iso:country":"UA",
    "name:ukr_x_preferred":[
        "Dvorichnyy Kut"
    ],
    "name:ukr_x_variant":[
        "\u0414\u0432\u043e\u0440\u0456\u0447\u043d\u0438\u0439 \u041a\u0443\u0442"
    ],
    "wof:name":"Dvorichnyy Kut",
    "wof:placetype":"locality"
},
  "geometry": {"coordinates":[35.93291,50.04262],"type":"Point"}
}