{
  "type": "Feature",
  "properties": {
    "gn:admin1_code":"14.0",
    "gn:asciiname":"Pereshchepnaya",
    "gn:cc2":"UA",
    "gn:country_code":"UA",
    "gn:dem":187,
    "gn:feature_class":"P",
    "gn:feature_code":"PPL",
    "gn:name":"Pereshchepnaya",
    "gn:population":0,
    "gn:timezone":"Europe/Zaporozhye",
    "iso:country":"UA",
    "name:und_x_variant":[
        "Pereshchepnoye",
        "Pereshchepnaya"
    ],
    "wof:name":"Pereshchepnaya",
    "wof:placetype":"locality"
},
  "geometry": {"coordinates":[38.43917,48.76389],"type":"Point"}
}