{
  "type": "Feature",
  "properties": {
    "gn:admin1_code":"5.0",
    "gn:asciiname":"Torets'ke",
    "gn:country_code":"UA",
    "gn:dem":82,
    "gn:feature_class":"P",
    "gn:feature_code":"PPL",
    "gn:name":"Torets\u2019ke",
    "gn:population":0,
    "gn:timezone":"Europe/Kiev",
    "iso:country":"UA",
    "name:ukr_x_preferred":[
        "Torets\u2019ke"
    ],
    "name:ukr_x_variant":[
        "\u0422\u043e\u0440\u0435\u0446\u044c\u043a\u0435"
    ],
    "wof:name":"Torets'ke",
    "wof:placetype":"locality"
},
  "geometry": {"coordinates":[37.42498,48.56071],"type":"Point"}
}