{
  "type": "Feature",
  "properties": {
    "gn:admin1_code":"4.0",
    "gn:asciiname":"Kytayhorod",
    "gn:country_code":"UA",
    "gn:dem":65,
    "gn:feature_class":"P",
    "gn:feature_code":"PPL",
    "gn:name":"Kytayhorod",
    "gn:population":0,
    "gn:timezone":"Europe/Kiev",
    "iso:country":"UA",
    "name:ukr_x_preferred":[
        "Kytayhorod"
    ],
    "name:ukr_x_variant":[
        "\u041a\u0438\u0442\u0430\u0439\u0433\u043e\u0440\u043e\u0434"
    ],
    "name:und_x_variant":[
        "Kitaygorod"
    ],
    "wof:name":"Kytayhorod",
    "wof:placetype":"locality"
},
  "geometry": {"coordinates":[34.44665,48.89992],"type":"Point"}
}