{
  "type": "Feature",
  "properties": {
    "gn:admin1_code":"9.0",
    "gn:asciiname":"Kashchentsy",
    "gn:country_code":"UA",
    "gn:dem":277,
    "gn:feature_class":"P",
    "gn:feature_code":"PPL",
    "gn:name":"Kashchentsy",
    "gn:population":0,
    "gn:timezone":"Europe/Kiev",
    "iso:country":"UA",
    "name:und_x_variant":[
        "Kashintsy",
        "Kashchentsy"
    ],
    "wof:name":"Kashchentsy",
    "wof:placetype":"locality"
},
  "geometry": {"coordinates":[26.30029,50.03625],"type":"Point"}
}