{
  "type": "Feature",
  "properties": {
    "gn:admin1_code":"11.0",
    "gn:admin2_code":"700018",
    "gn:admin3_code":"11152966.0",
    "gn:asciiname":"Nezhinskoye",
    "gn:country_code":"UA",
    "gn:dem":18,
    "gn:elevation":"15.0",
    "gn:feature_class":"P",
    "gn:feature_code":"PPL",
    "gn:name":"Nezhinskoye",
    "gn:population":87,
    "gn:timezone":"Europe/Simferopol",
    "iso:country":"UA",
    "name:eng_x_preferred":[
        "Nezhinskoye"
    ],
    "name:rus_x_historical":[
        "\u041a\u0443\u043b\u0442\u0430\u043c\u0430\u0301\u043a"
    ],
    "name:rus_x_preferred":[
        "\u041d\u0435\u0436\u0438\u043d\u0441\u043a\u043e\u0435"
    ],
    "name:rus_x_variant":[
        "\u041a\u0443\u043b\u0442\u0430\u043c\u0430\u0301\u043a"
    ],
    "name:ukr_x_preferred":[
        "\u041d\u0456\u0436\u0438\u043d\u0441\u044c\u043a\u0435"
    ],
    "wof:name":"Nezhinskoye",
    "wof:placetype":"locality",
    "wof:population":87
},
  "geometry": {"coordinates":[34.72828,45.57823],"type":"Point"}
}