{
  "type": "Feature",
  "properties": {
    "gn:admin1_code":"9.0",
    "gn:asciiname":"Novyy Maydan",
    "gn:country_code":"UA",
    "gn:dem":346,
    "gn:feature_class":"P",
    "gn:feature_code":"PPL",
    "gn:name":"Novyy Maydan",
    "gn:population":0,
    "gn:timezone":"Europe/Kiev",
    "iso:country":"UA",
    "name:und_x_variant":[
        "Novy Maydan",
        "Novyy Maydan"
    ],
    "wof:name":"Novyy Maydan",
    "wof:placetype":"locality"
},
  "geometry": {"coordinates":[27.57017,49.23662],"type":"Point"}
}