{
  "type": "Feature",
  "properties": {
    "gn:admin1_code":"11.0",
    "gn:admin2_code":"8449683",
    "gn:asciiname":"Krasnokamenka",
    "gn:country_code":"UA",
    "gn:dem":230,
    "gn:elevation":"334.0",
    "gn:feature_class":"P",
    "gn:feature_code":"PPL",
    "gn:name":"Krasnokamenka",
    "gn:population":1150,
    "gn:timezone":"Europe/Simferopol",
    "iso:country":"UA",
    "name:deu_x_preferred":[
        "Krasnokamjanka"
    ],
    "name:eng_x_preferred":[
        "Krasnokamenka"
    ],
    "name:rus_x_preferred":[
        "\u041a\u0440\u0430\u0441\u043d\u043e\u043a\u0430\u043c\u0435\u043d\u043a\u0430"
    ],
    "name:ukr_x_preferred":[
        "\u041a\u0440\u0430\u0441\u043d\u043e\u043a\u0430\u043c\u2019\u044f\u043d\u043a\u0430"
    ],
    "name:ukr_x_variant":[
        "\u041a\u0440\u0430\u0441\u043d\u043e\u043a\u0430\u043c'\u044f\u043d\u043a\u0430"
    ],
    "wof:name":"Krasnokamenka",
    "wof:placetype":"locality",
    "wof:population":1150
},
  "geometry": {"coordinates":[35.0754,44.92446],"type":"Point"}
}