{
  "type": "Feature",
  "properties": {
    "gn:admin1_code":"5.0",
    "gn:asciiname":"Vodobud",
    "gn:country_code":"UA",
    "gn:dem":172,
    "gn:feature_class":"P",
    "gn:feature_code":"PPL",
    "gn:name":"Vodobud",
    "gn:population":0,
    "gn:timezone":"Europe/Kiev",
    "iso:country":"UA",
    "name:ukr_x_preferred":[
        "Vodobud"
    ],
    "name:ukr_x_variant":[
        "\u0412\u043e\u0434\u043e\u0431\u0443\u0434"
    ],
    "wof:name":"Vodobud",
    "wof:placetype":"locality"
},
  "geometry": {"coordinates":[38.21381,48.02099000000001],"type":"Point"}
}