{
  "type": "Feature",
  "properties": {
    "gn:admin1_code":"27.0",
    "gn:asciiname":"Yalynivka",
    "gn:country_code":"UA",
    "gn:dem":223,
    "gn:feature_class":"P",
    "gn:feature_code":"PPL",
    "gn:name":"Yalynivka",
    "gn:population":0,
    "gn:timezone":"Europe/Kiev",
    "iso:country":"UA",
    "name:ukr_x_preferred":[
        "Yalynivka"
    ],
    "name:ukr_x_variant":[
        "\u042f\u043b\u0438\u043d\u0456\u0432\u043a\u0430"
    ],
    "name:und_x_variant":[
        "Yalinovka"
    ],
    "wof:name":"Yalynivka",
    "wof:placetype":"locality"
},
  "geometry": {"coordinates":[28.43131,50.40145],"type":"Point"}
}