{
  "type": "Feature",
  "properties": {
    "gn:admin1_code":"17.0",
    "gn:asciiname":"Vikent'yevka",
    "gn:country_code":"UA",
    "gn:dem":90,
    "gn:feature_class":"P",
    "gn:feature_code":"PPL",
    "gn:name":"Vikent'yevka",
    "gn:population":0,
    "gn:timezone":"Europe/Kiev",
    "iso:country":"UA",
    "wof:name":"Vikent'yevka",
    "wof:placetype":"locality"
},
  "geometry": {"coordinates":[29.745,47.38972],"type":"Point"}
}