{
  "type": "Feature",
  "properties": {
    "gn:admin1_code":"24.0",
    "gn:asciiname":"Vil'khivka",
    "gn:country_code":"UA",
    "gn:dem":215,
    "gn:feature_class":"P",
    "gn:feature_code":"PPL",
    "gn:name":"Vil\u2019khivka",
    "gn:population":0,
    "gn:timezone":"Europe/Kiev",
    "iso:country":"UA",
    "name:ukr_x_preferred":[
        "Vil\u2019khivka"
    ],
    "name:ukr_x_variant":[
        "\u0412\u0456\u043b\u044c\u0445\u0456\u0432\u043a\u0430"
    ],
    "name:und_x_variant":[
        "Ul\u2019govka",
        "Olch\u00f3wka",
        "Ol\u2019khuvka",
        "Ol\u2019khovka"
    ],
    "wof:name":"Vil'khivka",
    "wof:placetype":"locality"
},
  "geometry": {"coordinates":[24.92655,50.5336],"type":"Point"}
}