{
  "type": "Feature",
  "properties": {
    "gn:admin1_code":"4.0",
    "gn:asciiname":"Boltyshka",
    "gn:country_code":"UA",
    "gn:dem":84,
    "gn:feature_class":"P",
    "gn:feature_code":"PPL",
    "gn:name":"Boltyshka",
    "gn:population":0,
    "gn:timezone":"Europe/Kiev",
    "iso:country":"UA",
    "name:ukr_x_preferred":[
        "Boltyshka"
    ],
    "name:ukr_x_variant":[
        "\u0411\u043e\u043b\u0442\u0438\u0448\u043a\u0430"
    ],
    "name:und_x_variant":[
        "Nikolayevka"
    ],
    "wof:name":"Boltyshka",
    "wof:placetype":"locality"
},
  "geometry": {"coordinates":[34.16667,48.23333],"type":"Point"}
}