{
  "type": "Feature",
  "properties": {
    "gn:admin1_code":"21.0",
    "gn:asciiname":"Khreshchatyk",
    "gn:country_code":"UA",
    "gn:dem":170,
    "gn:feature_class":"P",
    "gn:feature_code":"PPL",
    "gn:name":"Khreshchatyk",
    "gn:population":0,
    "gn:timezone":"Europe/Kiev",
    "iso:country":"UA",
    "name:bel_x_preferred":[
        "\u0425\u0440\u044d\u0448\u0447\u0430\u0442\u044b\u043a"
    ],
    "name:chv_x_preferred":[
        "\u0425\u0440\u0435\u00e7\u0430\u0442\u0438\u043a"
    ],
    "name:deu_x_preferred":[
        "Chreschtschatyk"
    ],
    "name:est_x_preferred":[
        "Hre\u0161t\u0161at\u00f5k"
    ],
    "name:fin_x_preferred":[
        "H\u2019re\u0161t\u0161atyk"
    ],
    "name:fra_x_preferred":[
        "Krechtchatyk"
    ],
    "name:heb_x_preferred":[
        "\u05e8\u05d7\u05d5\u05d1 \u05d7\u05e8\u05e9\u05e6'\u05d0\u05d8\u05d9\u05e7"
    ],
    "name:hrv_x_preferred":[
        "Hre\u0161\u010datik"
    ],
    "name:ita_x_preferred":[
        "Chre\u0161\u010datyk"
    ],
    "name:jpn_x_preferred":[
        "\u30d5\u30ec\u30b7\u30c1\u30e3\u30fc\u30c6\u30a3\u30af"
    ],
    "name:kor_x_preferred":[
        "\ud750\ub808\uc0e4\ud2f0\ud06c"
    ],
    "name:mkd_x_preferred":[
        "\u0423\u043b\u0438\u0446\u0430 \u041a\u0440\u0435\u0448\u0442\u0430\u0442\u0438\u043a"
    ],
    "name:pol_x_preferred":[
        "Chreszczatyk"
    ],
    "name:rus_x_preferred":[
        "\u041a\u0440\u0435\u0449\u0430\u0442\u0438\u043a"
    ],
    "name:spa_x_preferred":[
        "Khreshchatyk"
    ],
    "name:swe_x_preferred":[
        "Chresjtjatyk"
    ],
    "name:ukr_x_preferred":[
        "Khreshchatyk"
    ],
    "name:ukr_x_variant":[
        "\u0425\u0440\u0435\u0449\u0430\u0442\u0438\u043a"
    ],
    "name:und_x_variant":[
        "Kreshchatik"
    ],
    "name:vie_x_preferred":[
        "Khreshchatyk"
    ],
    "name:zho_x_preferred":[
        "\u8d6b\u96f7\u590f\u8482\u514b\u8857"
    ],
    "wof:name":"Khreshchatyk",
    "wof:placetype":"locality"
},
  "geometry": {"coordinates":[33.32508,50.93117],"type":"Point"}
}