{
  "type": "Feature",
  "properties": {
    "gn:admin1_code":"21.0",
    "gn:asciiname":"Khreshchatyk",
    "gn:country_code":"UA",
    "gn:dem":170,
    "gn:feature_class":"P",
    "gn:feature_code":"PPL",
    "gn:name":"Khreshchatyk",
    "gn:population":0,
    "gn:timezone":"Europe/Kiev",
    "iso:country":"UA",
    "name:ukr_x_preferred":[
        "Khreshchatyk"
    ],
    "name:ukr_x_variant":[
        "\u0425\u0440\u0435\u0449\u0430\u0442\u0438\u043a"
    ],
    "name:und_x_variant":[
        "Kreshchatik"
    ],
    "wof:name":"Khreshchatyk",
    "wof:placetype":"locality"
},
  "geometry": {"coordinates":[33.32508,50.93117],"type":"Point"}
}