{
  "type": "Feature",
  "properties": {
    "gn:admin1_code":"7.0",
    "gn:asciiname":"Vorovs'koho",
    "gn:country_code":"UA",
    "gn:dem":162,
    "gn:feature_class":"P",
    "gn:feature_code":"PPL",
    "gn:name":"Vorovs\u2019koho",
    "gn:population":0,
    "gn:timezone":"Europe/Kiev",
    "iso:country":"UA",
    "name:ukr_x_preferred":[
        "Vorovs\u2019koho"
    ],
    "name:ukr_x_variant":[
        "\u0412\u043e\u0440\u043e\u0432\u0441\u044c\u043a\u043e\u0433\u043e"
    ],
    "name:und_x_variant":[
        "Vorovskogo"
    ],
    "wof:name":"Vorovs'koho",
    "wof:placetype":"locality"
},
  "geometry": {"coordinates":[36.36937,48.87561],"type":"Point"}
}