{
  "type": "Feature",
  "properties": {
    "iso:country":"UA",
    "qs:a0":"\u0423\u043a\u0440\u0430\u0457\u043d\u0430",
    "qs:a1":"*\u0427\u0435\u0440\u043a\u0430\u0441\u044c\u043a\u0430",
    "qs:a1_alt":"Cherkas'ka",
    "qs:a1r":"0",
    "qs:a2":"\u0427\u0435\u0440\u043a\u0430\u0441\u044c\u043a\u0438\u0439",
    "qs:a2_alt":"Cherkas'kyi",
    "qs:adm0":"\u0423\u043a\u0440\u0430\u0457\u043d\u0430",
    "qs:la_lc":"*",
    "qs:level":"locality",
    "qs:loc":"\u0422\u0443\u0431\u0456\u043b\u044c\u0446\u0456",
    "qs:loc_alt":"Tubil'tsi",
    "qs:pop":0,
    "qs:type":"buffered point",
    "wof:name":"\u0422\u0443\u0431\u0456\u043b\u044c\u0446\u0456",
    "wof:placetype":"locality"
},
  "geometry": {"coordinates":[31.674688,49.558074],"type":"Point"}
}