{
  "type": "Feature",
  "properties": {
    "gn:admin1_code":"7.0",
    "gn:asciiname":"Zarozhne",
    "gn:country_code":"UA",
    "gn:dem":165,
    "gn:feature_class":"P",
    "gn:feature_code":"PPL",
    "gn:name":"Zarozhne",
    "gn:population":0,
    "gn:timezone":"Europe/Kiev",
    "iso:country":"UA",
    "name:eng_x_preferred":[
        "Zarozhnoye"
    ],
    "name:rus_x_preferred":[
        "\u0417\u0430\u0440\u043e\u0436\u043d\u043e\u0435"
    ],
    "name:ukr_x_preferred":[
        "Zarozhne"
    ],
    "name:ukr_x_variant":[
        "\u0417\u0430\u0440\u043e\u0436\u043d\u0435"
    ],
    "name:und_x_variant":[
        "Zaporozhnoye",
        "Zarozhnoe"
    ],
    "wof:name":"Zarozhne",
    "wof:placetype":"locality"
},
  "geometry": {"coordinates":[36.6894,49.93826],"type":"Point"}
}