{
  "type": "Feature",
  "properties": {
    "gn:admin1_code":"19.0",
    "gn:asciiname":"Svitanok",
    "gn:country_code":"UA",
    "gn:dem":223,
    "gn:feature_class":"P",
    "gn:feature_code":"PPL",
    "gn:name":"Svitanok",
    "gn:population":0,
    "gn:timezone":"Europe/Kiev",
    "iso:country":"UA",
    "name:ukr_x_preferred":[
        "\u0421\u0432\u0456\u0442\u0430\u043d\u043e\u043a"
    ],
    "name:und_x_variant":[
        "Bludov",
        "Bludiv",
        "Bluduv",
        "Svitanok"
    ],
    "wof:name":"Svitanok",
    "wof:placetype":"locality"
},
  "geometry": {"coordinates":[26.82868,50.62856],"type":"Point"}
}