{
  "type": "Feature",
  "properties": {
    "gn:admin1_code":"10.0",
    "gn:asciiname":"Chervonyy Yar",
    "gn:country_code":"UA",
    "gn:dem":150,
    "gn:feature_class":"P",
    "gn:feature_code":"PPL",
    "gn:name":"Chervonyy Yar",
    "gn:population":0,
    "gn:timezone":"Europe/Kiev",
    "iso:country":"UA",
    "name:ukr_x_preferred":[
        "\u0427\u0435\u0440\u0432\u043e\u043d\u0438\u0439 \u042f\u0440"
    ],
    "name:und_x_variant":[
        "Krasnyy Yar",
        "Chervonyy Yar"
    ],
    "wof:name":"Chervonyy Yar",
    "wof:placetype":"locality"
},
  "geometry": {"coordinates":[32.60688,48.51175],"type":"Point"}
}