{
  "type": "Feature",
  "properties": {
    "gn:admin1_code":"7.0",
    "gn:asciiname":"Rudayeve",
    "gn:country_code":"UA",
    "gn:dem":118,
    "gn:feature_class":"P",
    "gn:feature_code":"PPL",
    "gn:name":"Rudayeve",
    "gn:population":0,
    "gn:timezone":"Europe/Kiev",
    "iso:country":"UA",
    "name:ukr_x_preferred":[
        "Rudayeve"
    ],
    "name:ukr_x_variant":[
        "\u0420\u0443\u0434\u0430\u0454\u0432\u0435"
    ],
    "name:und_x_variant":[
        "Pos\u00eblok Rudayevskiy",
        "Rudayevo"
    ],
    "wof:name":"Rudayeve",
    "wof:placetype":"locality"
},
  "geometry": {"coordinates":[36.46464,48.83993],"type":"Point"}
}