{
  "type": "Feature",
  "properties": {
    "gn:gn_country":"UA",
    "gn:gn_fcode":"PPL",
    "gn:gn_pop":4203,
    "gn:population":4203,
    "iso:country":"UA",
    "name:ara_x_preferred":[
        "\u0647\u0648\u0644\u0648\u0628\u064a"
    ],
    "name:deu_x_preferred":[
        "Holoby"
    ],
    "name:eng_x_preferred":[
        "Holoby"
    ],
    "name:heb_x_preferred":[
        "\u05d4\u05d5\u05dc\u05d5\u05d1\u05d9"
    ],
    "name:pol_x_preferred":[
        "Ho\u0142oby"
    ],
    "name:ron_x_preferred":[
        "Holob\u00ee"
    ],
    "name:rue_x_preferred":[
        "\u0413\u043e\u043b\u043e\u0431\u044b"
    ],
    "name:rus_x_preferred":[
        "\u0413\u043e\u043b\u043e\u0431\u044b"
    ],
    "name:ukr_x_preferred":[
        "\u0413\u043e\u043b\u043e\u0431\u0438"
    ],
    "name:unk_x_variant":[
        "Kholoby"
    ],
    "name:yid_x_preferred":[
        "\u05d4\u05d0\u05dc\u05d0\u05d1\u05d9"
    ],
    "name:zho_x_preferred":[
        "\u6208\u6d1b\u6bd4"
    ],
    "qs_pg:aaroncc":"UA",
    "qs_pg:gn_country":"UA",
    "qs_pg:gn_fcode":"PPL",
    "qs_pg:gn_pop":4203,
    "qs_pg:name":"Ho\u0142oby",
    "qs_pg:photos_9r":0,
    "qs_pg:photos_sr":0,
    "qs_pg:pop_sr":4,
    "qs_pg:qs_pg_placetype":"locality",
    "wof:name":"Ho\u0142oby",
    "wof:placetype":"locality",
    "wof:population":4203
},
  "geometry": {"coordinates":[25.00767,51.08651],"type":"Point"}
}