{
  "type": "Feature",
  "properties": {
    "gn:admin1_code":"24.0",
    "gn:asciiname":"Hulivka",
    "gn:country_code":"UA",
    "gn:dem":163,
    "gn:feature_class":"P",
    "gn:feature_code":"PPL",
    "gn:name":"Hulivka",
    "gn:population":0,
    "gn:timezone":"Europe/Kiev",
    "iso:country":"UA",
    "name:ukr_x_preferred":[
        "Hulivka"
    ],
    "name:ukr_x_variant":[
        "\u0413\u0443\u043b\u0456\u0432\u043a\u0430"
    ],
    "name:und_x_variant":[
        "Gulevich",
        "Hulewicze",
        "Guleviche",
        "Khuleviche",
        "Gulevichi",
        "Gulevka"
    ],
    "wof:name":"Hulivka",
    "wof:placetype":"locality"
},
  "geometry": {"coordinates":[25.21916,51.2584],"type":"Point"}
}