{
  "type": "Feature",
  "properties": {
    "gn:admin1_code":"18.0",
    "gn:asciiname":"Hlyns'ke",
    "gn:country_code":"UA",
    "gn:dem":116,
    "gn:feature_class":"P",
    "gn:feature_code":"PPL",
    "gn:name":"Hlyns\u2019ke",
    "gn:population":0,
    "gn:timezone":"Europe/Kiev",
    "iso:country":"UA",
    "name:ukr_x_preferred":[
        "Hlyns\u2019ke"
    ],
    "name:ukr_x_variant":[
        "\u0413\u043b\u0438\u043d\u0441\u044c\u043a\u0435"
    ],
    "name:und_x_variant":[
        "Glinsk",
        "Glinskoye"
    ],
    "wof:name":"Hlyns'ke",
    "wof:placetype":"locality"
},
  "geometry": {"coordinates":[34.66275,50.01784],"type":"Point"}
}