{
  "type": "Feature",
  "properties": {
    "gn:admin1_code":"27.0",
    "gn:asciiname":"Mokhnachka",
    "gn:country_code":"UA",
    "gn:dem":189,
    "gn:feature_class":"P",
    "gn:feature_code":"PPL",
    "gn:name":"Mokhnachka",
    "gn:population":0,
    "gn:timezone":"Europe/Kiev",
    "iso:country":"UA",
    "name:ukr_x_preferred":[
        "Mokhnachka"
    ],
    "name:ukr_x_variant":[
        "\u041c\u043e\u0445\u043d\u0430\u0447\u043a\u0430"
    ],
    "wof:name":"Mokhnachka",
    "wof:placetype":"locality"
},
  "geometry": {"coordinates":[29.63,50.06204],"type":"Point"}
}