{
  "type": "Feature",
  "properties": {
    "gn:admin1_code":"3.0",
    "gn:asciiname":"Nelipovtsy",
    "gn:country_code":"UA",
    "gn:dem":252,
    "gn:feature_class":"P",
    "gn:feature_code":"PPL",
    "gn:name":"Nelipovtsy",
    "gn:population":0,
    "gn:timezone":"Europe/Kiev",
    "iso:country":"UA",
    "name:und_x_variant":[
        "Nelipauts\u2019",
        "Nelipovtsy"
    ],
    "wof:name":"Nelipovtsy",
    "wof:placetype":"locality"
},
  "geometry": {"coordinates":[26.92207,48.4183],"type":"Point"}
}