{
  "type": "Feature",
  "properties": {
    "gn:admin1_code":"4.0",
    "gn:asciiname":"Lebedyns'ke",
    "gn:country_code":"UA",
    "gn:dem":111,
    "gn:feature_class":"P",
    "gn:feature_code":"PPL",
    "gn:name":"Lebedyns\u2019ke",
    "gn:population":0,
    "gn:timezone":"Europe/Kiev",
    "iso:country":"UA",
    "name:rus_x_preferred":[
        "\u041b\u0435\u0431\u0435\u0434\u0438\u043d\u0441\u043a\u043e\u0435"
    ],
    "name:ukr_x_preferred":[
        "Lebedyns\u2019ke"
    ],
    "name:ukr_x_variant":[
        "\u041b\u0435\u0431\u0435\u0434\u0438\u043d\u0441\u044c\u043a\u0435"
    ],
    "name:und_x_variant":[
        "Lebedinskiy",
        "Lebedinskoye"
    ],
    "wof:name":"Lebedyns'ke",
    "wof:placetype":"locality"
},
  "geometry": {"coordinates":[34.43942,47.89717],"type":"Point"}
}