{
  "type": "Feature",
  "properties": {
    "gn:admin1_code":"21.0",
    "gn:asciiname":"Cherevativka",
    "gn:country_code":"UA",
    "gn:dem":164,
    "gn:feature_class":"P",
    "gn:feature_code":"PPL",
    "gn:name":"Cherevativka",
    "gn:population":0,
    "gn:timezone":"Europe/Kiev",
    "iso:country":"UA",
    "name:ukr_x_preferred":[
        "Cherevativka"
    ],
    "name:ukr_x_variant":[
        "\u0427\u0435\u0440\u0435\u0432\u0430\u0442\u0456\u0432\u043a\u0430"
    ],
    "name:und_x_variant":[
        "Cherevatenkov",
        "Cherevatovka"
    ],
    "wof:name":"Cherevativka",
    "wof:placetype":"locality"
},
  "geometry": {"coordinates":[34.16568,51.16428],"type":"Point"}
}