{
  "type": "Feature",
  "properties": {
    "gn:admin1_code":"14.0",
    "gn:asciiname":"Proletars'kyy",
    "gn:country_code":"UA",
    "gn:dem":281,
    "gn:feature_class":"P",
    "gn:feature_code":"PPL",
    "gn:name":"Proletars\u2019kyy",
    "gn:population":0,
    "gn:timezone":"Europe/Zaporozhye",
    "iso:country":"UA",
    "name:ukr_x_preferred":[
        "Proletars\u2019kyy"
    ],
    "name:ukr_x_variant":[
        "\u041f\u0440\u043e\u043b\u0435\u0442\u0430\u0440\u0441\u044c\u043a\u0438\u0439"
    ],
    "name:und_x_variant":[
        "Neygofnung",
        "Proletarskiy"
    ],
    "wof:name":"Proletars'kyy",
    "wof:placetype":"locality"
},
  "geometry": {"coordinates":[39.256,48.1339],"type":"Point"}
}