{
  "type": "Feature",
  "properties": {
    "gn:admin1_code":"19.0",
    "gn:asciiname":"Lyubyn'",
    "gn:country_code":"UA",
    "gn:dem":141,
    "gn:feature_class":"P",
    "gn:feature_code":"PPL",
    "gn:name":"Lyubyn\u2019",
    "gn:population":0,
    "gn:timezone":"Europe/Kiev",
    "iso:country":"UA",
    "name:ukr_x_preferred":[
        "Lyubyn\u2019"
    ],
    "name:ukr_x_variant":[
        "\u041b\u044e\u0431\u0438\u043d\u044c"
    ],
    "name:und_x_variant":[
        "Lyubin"
    ],
    "wof:name":"Lyubyn'",
    "wof:placetype":"locality"
},
  "geometry": {"coordinates":[25.78202000000001,51.82692],"type":"Point"}
}