{
  "type": "Feature",
  "properties": {
    "gn:admin1_code":"10.0",
    "gn:asciiname":"Oleksandro-Stepanivka",
    "gn:country_code":"UA",
    "gn:dem":83,
    "gn:feature_class":"P",
    "gn:feature_code":"PPL",
    "gn:name":"Oleksandro-Stepanivka",
    "gn:population":0,
    "gn:timezone":"Europe/Kiev",
    "iso:country":"UA",
    "name:ukr_x_preferred":[
        "Oleksandro-Stepanivka"
    ],
    "name:ukr_x_variant":[
        "\u041e\u043b\u0435\u043a\u0441\u0430\u043d\u0434\u0440\u043e-\u0421\u0442\u0435\u043f\u0430\u043d\u0456\u0432\u043a\u0430"
    ],
    "wof:name":"Oleksandro-Stepanivka",
    "wof:placetype":"locality"
},
  "geometry": {"coordinates":[33.1555,48.60413],"type":"Point"}
}