{
  "type": "Feature",
  "properties": {
    "gn:admin1_code":"17.0",
    "gn:asciiname":"Ryasnopol'",
    "gn:country_code":"UA",
    "gn:dem":20,
    "gn:feature_class":"P",
    "gn:feature_code":"PPL",
    "gn:name":"Ryasnopol\u2019",
    "gn:population":0,
    "gn:timezone":"Europe/Kiev",
    "iso:country":"UA",
    "name:und_x_variant":[
        "Rasnopol\u2019",
        "Roskopol\u2019",
        "Rosnopol\u2019",
        "Ryasnopol\u2019"
    ],
    "wof:name":"Ryasnopol'",
    "wof:placetype":"locality"
},
  "geometry": {"coordinates":[31.18876,47.06981],"type":"Point"}
}