{
  "type": "Feature",
  "properties": {
    "gn:admin1_code":"25.0",
    "gn:asciiname":"Puznyakivtsi",
    "gn:country_code":"UA",
    "gn:dem":517,
    "gn:feature_class":"P",
    "gn:feature_code":"PPL",
    "gn:name":"Puznyakivtsi",
    "gn:population":0,
    "gn:timezone":"Europe/Uzhgorod",
    "iso:country":"UA",
    "name:ukr_x_preferred":[
        "Puznyakivtsi"
    ],
    "name:ukr_x_variant":[
        "\u041f\u0443\u0437\u043d\u044f\u043a\u0456\u0432\u0446\u0456"
    ],
    "name:und_x_variant":[
        "Puznyakovtse",
        "Puznyakovtsy"
    ],
    "wof:name":"Puznyakivtsi",
    "wof:placetype":"locality"
},
  "geometry": {"coordinates":[22.72152,48.62209],"type":"Point"}
}