{
  "type": "Feature",
  "properties": {
    "gn:admin1_code":"2.0",
    "gn:asciiname":"Horodyshche",
    "gn:country_code":"UA",
    "gn:dem":152,
    "gn:feature_class":"P",
    "gn:feature_code":"PPL",
    "gn:name":"Horodyshche",
    "gn:population":0,
    "gn:timezone":"Europe/Kiev",
    "iso:country":"UA",
    "name:ukr_x_preferred":[
        "Horodyshche"
    ],
    "name:ukr_x_variant":[
        "\u0413\u043e\u0440\u043e\u0434\u0438\u0449\u0435",
        "Roshcha"
    ],
    "wof:name":"Horodyshche",
    "wof:placetype":"locality"
},
  "geometry": {"coordinates":[33.12306,52.32667],"type":"Point"}
}