{
  "type": "Feature",
  "properties": {
    "gn:admin1_code":"8.0",
    "gn:asciiname":"Kolchakovka",
    "gn:country_code":"UA",
    "gn:dem":28,
    "gn:feature_class":"P",
    "gn:feature_code":"PPL",
    "gn:name":"Kolchakovka",
    "gn:population":0,
    "gn:timezone":"Europe/Kiev",
    "iso:country":"UA",
    "name:und_x_variant":[
        "Kolchanovka",
        "Kolchakovka"
    ],
    "wof:name":"Kolchakovka",
    "wof:placetype":"locality"
},
  "geometry": {"coordinates":[34.22986,46.60986],"type":"Point"}
}