{
  "type": "Feature",
  "properties": {
    "iso:country":"UA",
    "name:ara_x_preferred":[
        "\u0641\u064a\u0644\u064a\u0643\u0648\u062f\u0648\u0644\u064a\u0646\u0633\u0643\u064a\u060c \u0623\u0648\u062f\u064a\u0633\u0643\u0627"
    ],
    "name:ara_x_variant":[
        "\u0641\u064a\u0644\u064a\u0643\u0648\u062f\u0648\u0644\u064a\u0646\u0633\u0643\u064a"
    ],
    "name:bel_x_preferred":[
        "\u0412\u044f\u043b\u0456\u043a\u0430\u0434\u0430\u043b\u0456\u043d\u0441\u043a\u0430\u0435"
    ],
    "name:bul_x_preferred":[
        "\u0412\u0435\u043b\u0438\u043a\u043e\u0434\u043e\u043b\u0438\u043d\u0441\u043a\u0435"
    ],
    "name:crh_x_preferred":[
        "Vel\u0131kodol\u0131nske"
    ],
    "name:deu_x_preferred":[
        "Welykodolynske"
    ],
    "name:eng_x_preferred":[
        "Velykodolynske"
    ],
    "name:lav_x_preferred":[
        "Velikodolinske"
    ],
    "name:pol_x_preferred":[
        "We\u0142ykodo\u0142yn\u015bke"
    ],
    "name:ron_x_preferred":[
        "Vel\u00eekodol\u00eenske"
    ],
    "name:rus_x_preferred":[
        "\u0412\u0435\u043b\u0438\u043a\u043e\u0434\u043e\u043b\u0438\u043d\u0441\u043a\u043e\u0435"
    ],
    "name:sah_x_preferred":[
        "\u0412\u0435\u043b\u0438\u043a\u043e\u0434\u043e\u043b\u0438\u043d\u0441\u043a\u043e\u0435"
    ],
    "name:spa_x_preferred":[
        "Velykodolyns'ke"
    ],
    "name:ukr_x_preferred":[
        "\u0412\u0435\u043b\u0438\u043a\u043e\u0434\u043e\u043b\u0438\u043d\u0441\u044c\u043a\u0435"
    ],
    "name:und_x_variant":[
        "Spartakovka"
    ],
    "name:zho_x_preferred":[
        "\u5225\u5229\u79d1\u591a\u6797\u897f\u79d1"
    ],
    "qs:a0":"\u0423\u043a\u0440\u0430\u0457\u043d\u0430",
    "qs:a1":"*\u041e\u0434\u0435\u0441\u044c\u043a\u0430",
    "qs:a1_alt":"Odes'ka",
    "qs:a1r":"0",
    "qs:a2":"\u041e\u0432\u0456\u0434\u0456\u043e\u043f\u043e\u043b\u044c\u0441\u044c\u043a\u0438\u0439",
    "qs:a2_alt":"Ovidiopol's'kyi",
    "qs:adm0":"\u0423\u043a\u0440\u0430\u0457\u043d\u0430",
    "qs:la_lc":"*",
    "qs:level":"locality",
    "qs:loc":"\u0412\u0435\u043b\u0438\u043a\u043e\u0434\u043e\u043b\u0438\u043d\u0441\u044c\u043a\u0435",
    "qs:loc_alt":"Velykodolyns'ke",
    "qs:pop":0,
    "qs:type":"buffered point",
    "wof:name":"\u0412\u0435\u043b\u0438\u043a\u043e\u0434\u043e\u043b\u0438\u043d\u0441\u044c\u043a\u0435",
    "wof:placetype":"locality"
},
  "geometry": {"coordinates":[30.565515,46.338814],"type":"Point"}
}