{
  "type": "Feature",
  "properties": {
    "gn:admin1_code":"2.0",
    "gn:asciiname":"Kalenikov",
    "gn:country_code":"UA",
    "gn:dem":175,
    "gn:feature_class":"P",
    "gn:feature_code":"PPL",
    "gn:name":"Kalenikov",
    "gn:population":0,
    "gn:timezone":"Europe/Kiev",
    "iso:country":"UA",
    "name:ukr_x_preferred":[
        "Kalenikov"
    ],
    "wof:name":"Kalenikov",
    "wof:placetype":"locality"
},
  "geometry": {"coordinates":[32.74778,52.01194],"type":"Point"}
}