{
  "type": "Feature",
  "properties": {
    "gn:gn_country":"UA",
    "gn:gn_fcode":"PPL",
    "gn:gn_pop":4623,
    "gn:population":4623,
    "iso:country":"UA",
    "name:arm_x_preferred":[
        "\u054d\u056b\u0576\u0587\u056b\u0580"
    ],
    "name:chi_x_preferred":[
        "\u897f\u6d85\u7dad\u723e"
    ],
    "name:cze_x_preferred":[
        "Sin\u011bvir"
    ],
    "name:dut_x_preferred":[
        "Synevyr"
    ],
    "name:eng_x_preferred":[
        "Synevyr"
    ],
    "name:epo_x_preferred":[
        "Sinevir"
    ],
    "name:ger_x_preferred":[
        "Synewyr"
    ],
    "name:hun_x_preferred":[
        "Als\u00f3szinev\u00e9r"
    ],
    "name:rum_x_preferred":[
        "S\u00eenev\u00eer"
    ],
    "name:rus_x_preferred":[
        "\u0421\u0438\u043d\u0435\u0432\u0438\u0440"
    ],
    "name:ukr_x_preferred":[
        "\u0421\u0438\u043d\u0435\u0432\u0438\u0440"
    ],
    "name:unk_x_variant":[
        "Siniyvir"
    ],
    "qs_pg:aaroncc":"UA",
    "qs_pg:gn_country":"UA",
    "qs_pg:gn_fcode":"PPL",
    "qs_pg:gn_pop":4623,
    "qs_pg:name":"Synevyr",
    "qs_pg:photos_9r":0,
    "qs_pg:photos_sr":0,
    "qs_pg:pop_sr":4,
    "qs_pg:qs_pg_placetype":"locality",
    "wof:name":"Synevyr",
    "wof:placetype":"locality",
    "wof:population":4623
},
  "geometry": {"coordinates":[23.62575,48.48745],"type":"Point"}
}