{
  "type": "Feature",
  "properties": {
    "gn:admin1_code":"15.0",
    "gn:asciiname":"Shumyna",
    "gn:country_code":"UA",
    "gn:dem":374,
    "gn:feature_class":"P",
    "gn:feature_code":"PPL",
    "gn:name":"Shumyna",
    "gn:population":0,
    "gn:timezone":"Europe/Kiev",
    "iso:country":"UA",
    "name:run_x_preferred":[
        "Shumina"
    ],
    "name:ukr_x_preferred":[
        "Shumyna"
    ],
    "name:ukr_x_variant":[
        "\u0428\u0443\u043c\u0438\u043d\u0430"
    ],
    "wof:name":"Shumyna",
    "wof:placetype":"locality"
},
  "geometry": {"coordinates":[22.93678,49.50357],"type":"Point"}
}