{
  "type": "Feature",
  "properties": {
    "iso:country":"UA",
    "name:deu_x_preferred":[
        "Tahantscha"
    ],
    "name:eng_x_preferred":[
        "Tagancha"
    ],
    "name:eng_x_variant":[
        "Tahancha"
    ],
    "name:pol_x_preferred":[
        "Tahancza"
    ],
    "name:ron_x_preferred":[
        "Tahancea"
    ],
    "name:rus_x_preferred":[
        "\u0422\u0430\u0433\u0430\u043d\u0447\u0430"
    ],
    "name:ukr_x_preferred":[
        "\u0422\u0430\u0433\u0430\u043d\u0447\u0430"
    ],
    "name:zho_x_preferred":[
        "\u5854\u7518\u6070"
    ],
    "qs:a0":"\u0423\u043a\u0440\u0430\u0457\u043d\u0430",
    "qs:a1":"*\u0427\u0435\u0440\u043a\u0430\u0441\u044c\u043a\u0430",
    "qs:a1_alt":"Cherkas'ka",
    "qs:a1r":"0",
    "qs:a2":"\u041a\u0430\u043d\u0456\u0432\u0441\u044c\u043a\u0438\u0439",
    "qs:a2_alt":"Kanivs'kyi",
    "qs:adm0":"\u0423\u043a\u0440\u0430\u0457\u043d\u0430",
    "qs:la_lc":"*",
    "qs:level":"locality",
    "qs:loc":"\u0422\u0430\u0433\u0430\u043d\u0447\u0430",
    "qs:loc_alt":"Tahancha",
    "qs:pop":0,
    "qs:type":"buffered point",
    "wof:name":"\u0422\u0430\u0433\u0430\u043d\u0447\u0430",
    "wof:placetype":"locality"
},
  "geometry": {"coordinates":[31.250751,49.571449],"type":"Point"}
}