{
  "type": "Feature",
  "properties": {
    "gn:admin1_code":"15.0",
    "gn:asciiname":"Krasnosel'tse",
    "gn:country_code":"UA",
    "gn:dem":385,
    "gn:feature_class":"P",
    "gn:feature_code":"PPL",
    "gn:name":"Krasnosel\u2019tse",
    "gn:population":0,
    "gn:timezone":"Europe/Kiev",
    "iso:country":"UA",
    "wof:name":"Krasnosel'tse",
    "wof:placetype":"locality"
},
  "geometry": {"coordinates":[24.96909,49.7193],"type":"Point"}
}