{
  "type": "Feature",
  "properties": {
    "gn:admin1_code":"16.0",
    "gn:asciiname":"Mayty",
    "gn:country_code":"UA",
    "gn:dem":33,
    "gn:feature_class":"P",
    "gn:feature_code":"PPL",
    "gn:name":"Mayty",
    "gn:population":0,
    "gn:timezone":"Europe/Kiev",
    "iso:country":"UA",
    "wof:name":"Mayty",
    "wof:placetype":"locality"
},
  "geometry": {"coordinates":[30.93333,47.46667],"type":"Point"}
}