{
  "type": "Feature",
  "properties": {
    "gn:admin1_code":"15.0",
    "gn:asciiname":"Zboyivs'ka",
    "gn:country_code":"UA",
    "gn:dem":215,
    "gn:feature_class":"P",
    "gn:feature_code":"PPL",
    "gn:name":"Zboyivs\u2019ka",
    "gn:population":0,
    "gn:timezone":"Europe/Kiev",
    "iso:country":"UA",
    "name:ukr_x_preferred":[
        "Zboyivs\u2019ka"
    ],
    "name:ukr_x_variant":[
        "\u0417\u0431\u043e\u0457\u0432\u0441\u044c\u043a\u0430"
    ],
    "name:und_x_variant":[
        "Zboyska",
        "Zboyevskaya"
    ],
    "wof:name":"Zboyivs'ka",
    "wof:placetype":"locality"
},
  "geometry": {"coordinates":[24.57237000000001,50.38059000000001],"type":"Point"}
}