{
  "type": "Feature",
  "properties": {
    "gn:admin1_code":"18.0",
    "gn:asciiname":"Tarandyntsi",
    "gn:country_code":"UA",
    "gn:dem":157,
    "gn:feature_class":"P",
    "gn:feature_code":"PPL",
    "gn:name":"Tarandyntsi",
    "gn:population":0,
    "gn:timezone":"Europe/Kiev",
    "iso:country":"UA",
    "name:ukr_x_preferred":[
        "Tarandyntsi"
    ],
    "name:ukr_x_variant":[
        "\u0422\u0430\u0440\u0430\u043d\u0434\u0438\u043d\u0446\u0456"
    ],
    "name:und_x_variant":[
        "Tarandintsy"
    ],
    "wof:name":"Tarandyntsi",
    "wof:placetype":"locality"
},
  "geometry": {"coordinates":[32.84252,50.07908],"type":"Point"}
}