{
  "type": "Feature",
  "properties": {
    "gn:admin1_code":"1.0",
    "gn:asciiname":"Zarubentsy",
    "gn:country_code":"UA",
    "gn:dem":202,
    "gn:feature_class":"P",
    "gn:feature_code":"PPL",
    "gn:name":"Zarubentsy",
    "gn:population":0,
    "gn:timezone":"Europe/Kiev",
    "iso:country":"UA",
    "name:und_x_variant":[
        "Zarubintsy",
        "Zarubentsi",
        "Zarubentsy"
    ],
    "wof:name":"Zarubentsy",
    "wof:placetype":"locality"
},
  "geometry": {"coordinates":[29.95335,49.12481],"type":"Point"}
}