{
  "type": "Feature",
  "properties": {
    "gn:admin1_code":"7.0",
    "gn:asciiname":"Lozova",
    "gn:country_code":"UA",
    "gn:dem":147,
    "gn:feature_class":"P",
    "gn:feature_code":"PPL",
    "gn:name":"Lozova",
    "gn:population":0,
    "gn:timezone":"Europe/Kiev",
    "iso:country":"UA",
    "name:eng_x_preferred":[
        "Lozovaya"
    ],
    "name:rus_x_preferred":[
        "\u041b\u043e\u0437\u043e\u0432\u0430\u044f"
    ],
    "name:ukr_x_preferred":[
        "Lozova"
    ],
    "name:ukr_x_variant":[
        "\u041b\u043e\u0437\u043e\u0432\u0430"
    ],
    "name:und_x_variant":[
        "Lozovaya"
    ],
    "wof:name":"Lozova",
    "wof:placetype":"locality"
},
  "geometry": {"coordinates":[35.91815,49.46285],"type":"Point"}
}