{
  "type": "Feature",
  "properties": {
    "gn:admin1_code":"7.0",
    "gn:asciiname":"Lozova",
    "gn:country_code":"UA",
    "gn:dem":147,
    "gn:feature_class":"P",
    "gn:feature_code":"PPL",
    "gn:name":"Lozova",
    "gn:population":0,
    "gn:timezone":"Europe/Kiev",
    "iso:country":"UA",
    "name:aze_x_preferred":[
        "Lozova"
    ],
    "name:bel_x_preferred":[
        "\u041b\u0430\u0437\u0430\u0432\u0430"
    ],
    "name:bul_x_preferred":[
        "\u041b\u043e\u0437\u043e\u0432\u0430"
    ],
    "name:ceb_x_preferred":[
        "Lozova"
    ],
    "name:ces_x_preferred":[
        "Lozova"
    ],
    "name:crh_x_preferred":[
        "Lozova"
    ],
    "name:deu_x_preferred":[
        "Losowa"
    ],
    "name:eng_x_preferred":[
        "Lozovaya"
    ],
    "name:est_x_preferred":[
        "Lozova"
    ],
    "name:fas_x_preferred":[
        "\u0644\u0648\u0632\u0648\u0648\u0627"
    ],
    "name:fin_x_preferred":[
        "Lozova"
    ],
    "name:fra_x_preferred":[
        "Lozova"
    ],
    "name:heb_x_preferred":[
        "\u05dc\u05d5\u05d6\u05d5\u05d1\u05d4"
    ],
    "name:hrv_x_preferred":[
        "Lozova"
    ],
    "name:hsb_x_preferred":[
        "Lozowa"
    ],
    "name:hye_x_preferred":[
        "\u053c\u0578\u0566\u0578\u057e\u0561\u0575\u0561"
    ],
    "name:ita_x_preferred":[
        "Lozova"
    ],
    "name:kat_x_preferred":[
        "\u10da\u10dd\u10d6\u10dd\u10d5\u10d0\u10d8\u10d0"
    ],
    "name:lav_x_preferred":[
        "Lozova"
    ],
    "name:lit_x_preferred":[
        "Lozova"
    ],
    "name:nno_x_preferred":[
        "Lozova"
    ],
    "name:pol_x_preferred":[
        "\u0141ozowa"
    ],
    "name:rus_x_preferred":[
        "\u041b\u043e\u0437\u043e\u0432\u0430\u044f"
    ],
    "name:sco_x_preferred":[
        "Lozova"
    ],
    "name:srp_x_preferred":[
        "\u041b\u043e\u0437\u043e\u0432\u0430"
    ],
    "name:tur_x_preferred":[
        "Lozova"
    ],
    "name:ukr_x_preferred":[
        "Lozova"
    ],
    "name:ukr_x_variant":[
        "\u041b\u043e\u0437\u043e\u0432\u0430"
    ],
    "name:vie_x_preferred":[
        "Lozova"
    ],
    "name:zho_x_preferred":[
        "\u6d1b\u4f50\u74e6"
    ],
    "wof:name":"Lozova",
    "wof:placetype":"locality"
},
  "geometry": {"coordinates":[35.91815,49.46285],"type":"Point"}
}