{
  "type": "Feature",
  "properties": {
    "iso:country":"UA",
    "name:ceb_x_preferred":[
        "Tr'okhizbenka"
    ],
    "name:deu_x_preferred":[
        "Trochisbenka"
    ],
    "name:eng_x_preferred":[
        "Trokhizbenka"
    ],
    "name:est_x_preferred":[
        "Trjohhizbenka"
    ],
    "name:lav_x_preferred":[
        "Trohizbenka"
    ],
    "name:ron_x_preferred":[
        "Trohizbenka"
    ],
    "name:rus_x_preferred":[
        "\u0422\u0440\u0451\u0445\u0438\u0437\u0431\u0435\u043d\u043a\u0430"
    ],
    "name:rus_x_variant":[
        "\u0422\u0440\u0435\u0445\u0438\u0437\u0431\u0435\u043d\u043a\u0430"
    ],
    "name:ukr_x_preferred":[
        "\u0422\u0440\u044c\u043e\u0445\u0456\u0437\u0431\u0435\u043d\u043a\u0430"
    ],
    "name:zho_x_preferred":[
        "\u7279\u91cc\u5967\u5e0c\u8332\u908a\u5361"
    ],
    "qs:a0":"\u0423\u043a\u0440\u0430\u0457\u043d\u0430",
    "qs:a1":"*\u041b\u0443\u0433\u0430\u043d\u0441\u044c\u043a\u0430",
    "qs:a1_alt":"Luhans'ka",
    "qs:a1r":"0",
    "qs:a2":"\u0421\u043b\u043e\u0432'\u044f\u043d\u043e\u0441\u0435\u0440\u0431\u0441\u044c\u043a\u0438\u0439",
    "qs:a2_alt":"Slovyanoserbs'kyi",
    "qs:adm0":"\u0423\u043a\u0440\u0430\u0457\u043d\u0430",
    "qs:la_lc":"*",
    "qs:level":"locality",
    "qs:loc":"\u0422\u0440\u044c\u043e\u0445\u0456\u0437\u0431\u0435\u043d\u043a\u0430",
    "qs:loc_alt":"Tr'okhizbenka",
    "qs:pop":0,
    "qs:type":"buffered point",
    "wd:wordcount":171,
    "wof:name":"\u0422\u0440\u044c\u043e\u0445\u0456\u0437\u0431\u0435\u043d\u043a\u0430",
    "wof:placetype":"locality"
},
  "geometry": {"coordinates":[38.978109,48.74838],"type":"Point"}
}