{
  "type": "Feature",
  "properties": {
    "gn:admin1_code":"6.0",
    "gn:asciiname":"Stratin",
    "gn:country_code":"UA",
    "gn:dem":281,
    "gn:feature_class":"P",
    "gn:feature_code":"PPL",
    "gn:name":"Stratin",
    "gn:population":0,
    "gn:timezone":"Europe/Kiev",
    "iso:country":"UA",
    "name:deu_x_preferred":[
        "Stratyn"
    ],
    "name:heb_x_preferred":[
        "\u05e1\u05d8\u05e8\u05d8\u05d9\u05df"
    ],
    "name:pol_x_preferred":[
        "Stratyn"
    ],
    "name:ron_x_preferred":[
        "Strat\u00een"
    ],
    "name:rus_x_preferred":[
        "\u0421\u0442\u0440\u0430\u0442\u0438\u043d"
    ],
    "name:ukr_x_preferred":[
        "\u0421\u0442\u0440\u0430\u0442\u0438\u043d"
    ],
    "name:und_x_variant":[
        "Straty\u0144",
        "Stratyn Myasto",
        "Stratin"
    ],
    "name:zho_x_preferred":[
        "\u65af\u7279\u62c9\u4eac"
    ],
    "wof:name":"Stratin",
    "wof:placetype":"locality"
},
  "geometry": {"coordinates":[24.70485,49.46802],"type":"Point"}
}