{
  "type": "Feature",
  "properties": {
    "gn:admin1_code":"01",
    "gn:asciiname":"Nebelevka",
    "gn:country_code":"UA",
    "gn:dem":164,
    "gn:feature_class":"P",
    "gn:feature_code":"PPL",
    "gn:name":"Nebelevka",
    "gn:population":0,
    "gn:timezone":"Europe/Kiev",
    "iso:country":"UA",
    "name:ukr_x_preferred":[
        "\u041d\u0435\u0431\u0435\u043b\u0435\u0432\u043a\u0430"
    ],
    "wof:name":"Nebelevka",
    "wof:placetype":"locality"
},
  "geometry": {"coordinates":[30.57564,48.63336],"type":"Point"}
}