{
  "type": "Feature",
  "properties": {
    "gn:admin1_code":"13.0",
    "gn:asciiname":"Golod'ki",
    "gn:country_code":"UA",
    "gn:dem":234,
    "gn:feature_class":"P",
    "gn:feature_code":"PPL",
    "gn:name":"Golod\u2019ki",
    "gn:population":0,
    "gn:timezone":"Europe/Kiev",
    "iso:country":"UA",
    "wof:name":"Golod'ki",
    "wof:placetype":"locality"
},
  "geometry": {"coordinates":[29.65624,49.27552],"type":"Point"}
}