{
  "type": "Feature",
  "properties": {
    "iso:country":"UA",
    "name:deu_x_preferred":[
        "Uspeniwka"
    ],
    "name:eng_x_preferred":[
        "Uspenivka"
    ],
    "name:lav_x_preferred":[
        "Uspe\u0146ivka"
    ],
    "name:ron_x_preferred":[
        "Uspenea"
    ],
    "name:rus_x_preferred":[
        "\u0423\u0441\u043f\u0435\u043d\u043e\u0432\u043a\u0430"
    ],
    "name:spa_x_preferred":[
        "Uspenivka"
    ],
    "name:ukr_x_preferred":[
        "\u0423\u0441\u043f\u0435\u043d\u0456\u0432\u043a\u0430"
    ],
    "name:und_x_variant":[
        "Uspenska"
    ],
    "name:zho_x_preferred":[
        "\u70cf\u65af\u4f69\u5c3c\u592b\u5361"
    ],
    "qs:a0":"\u0423\u043a\u0440\u0430\u0457\u043d\u0430",
    "qs:a1":"*\u041e\u0434\u0435\u0441\u044c\u043a\u0430",
    "qs:a1_alt":"Odes'ka",
    "qs:a1r":"0",
    "qs:a2":"\u0421\u0430\u0440\u0430\u0442\u0441\u044c\u043a\u0438\u0439",
    "qs:a2_alt":"Sarats'kyi",
    "qs:adm0":"\u0423\u043a\u0440\u0430\u0457\u043d\u0430",
    "qs:la_lc":"*",
    "qs:level":"locality",
    "qs:loc":"\u0423\u0441\u043f\u0435\u043d\u0456\u0432\u043a\u0430",
    "qs:loc_alt":"Uspenivka",
    "qs:pop":0,
    "qs:type":"buffered point",
    "wof:name":"\u0423\u0441\u043f\u0435\u043d\u0456\u0432\u043a\u0430",
    "wof:placetype":"locality"
},
  "geometry": {"coordinates":[29.869038,46.174962],"type":"Point"}
}