{
  "type": "Feature",
  "properties": {
    "gn:admin1_code":"15.0",
    "gn:asciiname":"Blazhiv",
    "gn:country_code":"UA",
    "gn:dem":365,
    "gn:feature_class":"P",
    "gn:feature_code":"PPL",
    "gn:name":"Blazhiv",
    "gn:population":0,
    "gn:timezone":"Europe/Kiev",
    "iso:country":"UA",
    "name:ukr_x_preferred":[
        "\u0411\u043b\u0430\u0436\u0456\u0432"
    ],
    "name:ukr_x_variant":[
        "\u0411\u043b\u0430\u0436\u043e\u0432"
    ],
    "name:und_x_variant":[
        "Blazhov Nizhniy",
        "Blazhov Verkhniy",
        "Blazhov",
        "Blazhev"
    ],
    "wof:name":"Blazhiv",
    "wof:placetype":"locality"
},
  "geometry": {"coordinates":[23.15456,49.42602],"type":"Point"}
}