{
  "type": "Feature",
  "properties": {
    "gn:admin1_code":"24.0",
    "gn:asciiname":"Hushcha",
    "gn:country_code":"UA",
    "gn:dem":171,
    "gn:feature_class":"P",
    "gn:feature_code":"PPL",
    "gn:name":"Hushcha",
    "gn:population":0,
    "gn:timezone":"Europe/Kiev",
    "iso:country":"UA",
    "name:ukr_x_preferred":[
        "\u0413\u0443\u0449\u0430"
    ],
    "name:und_x_variant":[
        "Gushcha",
        "Hushcha"
    ],
    "wof:name":"Hushcha",
    "wof:placetype":"locality"
},
  "geometry": {"coordinates":[23.75184,51.27271],"type":"Point"}
}