{
  "type": "Feature",
  "properties": {
    "gn:admin1_code":"7.0",
    "gn:asciiname":"Kommuna Imeni",
    "gn:country_code":"UA",
    "gn:dem":145,
    "gn:feature_class":"P",
    "gn:feature_code":"PPL",
    "gn:name":"Kommuna Imeni",
    "gn:population":0,
    "gn:timezone":"Europe/Kiev",
    "iso:country":"UA",
    "wof:name":"Kommuna Imeni",
    "wof:placetype":"locality"
},
  "geometry": {"coordinates":[36.18167,49.09694],"type":"Point"}
}