{
  "type": "Feature",
  "properties": {
    "gn:admin1_code":"17.0",
    "gn:asciiname":"Vasylivka",
    "gn:country_code":"UA",
    "gn:dem":22,
    "gn:feature_class":"P",
    "gn:feature_code":"PPL",
    "gn:name":"Vasylivka",
    "gn:population":0,
    "gn:timezone":"Europe/Kiev",
    "iso:country":"UA",
    "name:rus_x_preferred":[
        "Vasyl\u2019evka"
    ],
    "name:ukr_x_preferred":[
        "Vasylivka"
    ],
    "name:ukr_x_variant":[
        "\u0412\u0430\u0441\u0438\u043b\u0456\u0432\u043a\u0430"
    ],
    "name:und_x_variant":[
        "Abrodul Purice",
        "Veshisashki",
        "Vasiea\u015f-Aprodu-Purice",
        "Vasilevka"
    ],
    "wof:name":"Vasylivka",
    "wof:placetype":"locality"
},
  "geometry": {"coordinates":[29.16462000000001,45.52359000000001],"type":"Point"}
}