{
  "type": "Feature",
  "properties": {
    "gn:admin1_code":"7.0",
    "gn:asciiname":"Vil'shans'ke",
    "gn:country_code":"UA",
    "gn:dem":130,
    "gn:feature_class":"P",
    "gn:feature_code":"PPL",
    "gn:name":"Vil\u2019shans\u2019ke",
    "gn:population":0,
    "gn:timezone":"Europe/Kiev",
    "iso:country":"UA",
    "name:ukr_x_preferred":[
        "Vil\u2019shans\u2019ke"
    ],
    "name:ukr_x_variant":[
        "\u0412\u0456\u043b\u044c\u0448\u0430\u043d\u0441\u044c\u043a\u0435"
    ],
    "wof:name":"Vil'shans'ke",
    "wof:placetype":"locality"
},
  "geometry": {"coordinates":[35.907,50.11397],"type":"Point"}
}