{
  "type": "Feature",
  "properties": {
    "gn:admin1_code":"9.0",
    "gn:asciiname":"Vyazovets",
    "gn:country_code":"UA",
    "gn:dem":250,
    "gn:feature_class":"P",
    "gn:feature_code":"PPL",
    "gn:name":"Vyazovets",
    "gn:population":0,
    "gn:timezone":"Europe/Kiev",
    "iso:country":"UA",
    "wof:name":"Vyazovets",
    "wof:placetype":"locality"
},
  "geometry": {"coordinates":[26.18328,49.9108],"type":"Point"}
}