{
  "type": "Feature",
  "properties": {
    "gn:population":4245,
    "iso:country":"UA",
    "name:hun_x_preferred":[
        "Wojtk\u00f3wka"
    ],
    "name:pol_x_preferred":[
        "Wojtk\u00f3wka"
    ],
    "name:rus_x_preferred":[
        "\u0412\u0456\u0439\u0442\u0456\u0432\u043a\u0430"
    ],
    "name:ukr_x_preferred":[
        "\u0412\u0456\u0439\u0442\u0456\u0432\u043a\u0430"
    ],
    "name:und_x_variant":[
        "Chapayevka"
    ],
    "qs:a0":"\u0423\u043a\u0440\u0430\u0457\u043d\u0430",
    "qs:a1":"*\u0412\u0456\u043d\u043d\u0438\u0446\u044c\u043a\u0430",
    "qs:a1_alt":"Vinnyts'ka",
    "qs:a1r":"0",
    "qs:a2":"\u0411\u0435\u0440\u0448\u0430\u0434\u0441\u044c\u043a\u0438\u0439",
    "qs:a2_alt":"Bershads'kyi",
    "qs:adm0":"\u0423\u043a\u0440\u0430\u0457\u043d\u0430",
    "qs:la_lc":"*",
    "qs:level":"locality",
    "qs:loc":"\u0412\u0456\u0439\u0442\u0456\u0432\u043a\u0430",
    "qs:loc_alt":"Viitivka",
    "qs:pop":0,
    "qs:type":"buffered point",
    "wd:wordcount":82,
    "wof:name":"\u0412\u0456\u0439\u0442\u0456\u0432\u043a\u0430",
    "wof:placetype":"locality",
    "wof:population":4245
},
  "geometry": {"coordinates":[29.542602,48.423392],"type":"Point"}
}