{
  "type": "Feature",
  "properties": {
    "gn:admin1_code":"17.0",
    "gn:asciiname":"Del'zhyler",
    "gn:country_code":"UA",
    "gn:dem":41,
    "gn:feature_class":"P",
    "gn:feature_code":"PPL",
    "gn:name":"Del\u2019zhyler",
    "gn:population":0,
    "gn:timezone":"Europe/Kiev",
    "iso:country":"UA",
    "name:ukr_x_preferred":[
        "Dmytrivka"
    ],
    "name:ukr_x_variant":[
        "\u0414\u043c\u0438\u0442\u0440\u0456\u0432\u043a\u0430",
        "Del\u2019zhyler",
        "\u0414\u0435\u043b\u044c\u0436\u0438\u043b\u0435\u0440"
    ],
    "name:und_x_variant":[
        "Deljiler",
        "Deligiler",
        "Dmitriyevka",
        "Del\u2019zhiler",
        "Dmitrovka"
    ],
    "wof:name":"Del'zhyler",
    "wof:placetype":"locality"
},
  "geometry": {"coordinates":[29.4849,45.83937],"type":"Point"}
}