{
  "type": "Feature",
  "properties": {
    "gn:admin1_code":"6.0",
    "gn:asciiname":"Zhichka",
    "gn:cc2":"UA",
    "gn:country_code":"UA",
    "gn:dem":346,
    "gn:feature_class":"P",
    "gn:feature_code":"PPL",
    "gn:name":"Zhichka",
    "gn:population":0,
    "gn:timezone":"Europe/Kiev",
    "iso:country":"UA",
    "name:und_x_variant":[
        "Rechka",
        "Zhichka"
    ],
    "wof:name":"Zhichka",
    "wof:placetype":"locality"
},
  "geometry": {"coordinates":[24.66667,48.71667],"type":"Point"}
}