{
  "type": "Feature",
  "properties": {
    "gn:admin1_code":"18.0",
    "gn:asciiname":"Surzhky",
    "gn:country_code":"UA",
    "gn:dem":134,
    "gn:feature_class":"P",
    "gn:feature_code":"PPL",
    "gn:name":"Surzhky",
    "gn:population":0,
    "gn:timezone":"Europe/Kiev",
    "iso:country":"UA",
    "name:ukr_x_preferred":[
        "Surzhky"
    ],
    "name:ukr_x_variant":[
        "\u0421\u0443\u0440\u0436\u043a\u0438"
    ],
    "wof:name":"Surzhky",
    "wof:placetype":"locality"
},
  "geometry": {"coordinates":[33.67785,49.85738],"type":"Point"}
}