{
  "type": "Feature",
  "properties": {
    "gn:admin1_code":"2.0",
    "gn:asciiname":"Lypivka",
    "gn:country_code":"UA",
    "gn:dem":138,
    "gn:feature_class":"P",
    "gn:feature_code":"PPL",
    "gn:name":"Lypivka",
    "gn:population":0,
    "gn:timezone":"Europe/Kiev",
    "iso:country":"UA",
    "name:ukr_x_preferred":[
        "Lypivka"
    ],
    "name:ukr_x_variant":[
        "\u041b\u0438\u043f\u0456\u0432\u043a\u0430"
    ],
    "name:und_x_variant":[
        "Lipovka"
    ],
    "wof:name":"Lypivka",
    "wof:placetype":"locality"
},
  "geometry": {"coordinates":[31.85732,52.10599000000001],"type":"Point"}
}