{
  "type": "Feature",
  "properties": {
    "gn:admin1_code":"9.0",
    "gn:asciiname":"Pryputni",
    "gn:country_code":"UA",
    "gn:dem":244,
    "gn:feature_class":"P",
    "gn:feature_code":"PPL",
    "gn:name":"Pryputni",
    "gn:population":0,
    "gn:timezone":"Europe/Kiev",
    "iso:country":"UA",
    "name:ukr_x_preferred":[
        "Pryputni"
    ],
    "name:ukr_x_variant":[
        "\u041f\u0440\u0438\u043f\u0443\u0442\u043d\u0456"
    ],
    "name:und_x_variant":[
        "Priputnya"
    ],
    "wof:name":"Pryputni",
    "wof:placetype":"locality"
},
  "geometry": {"coordinates":[26.92161,50.10671],"type":"Point"}
}