{
  "type": "Feature",
  "properties": {
    "gn:gn_country":"UA",
    "gn:gn_fcode":"PPL",
    "gn:gn_pop":20271,
    "gn:population":20271,
    "iso:country":"UA",
    "name:ara_x_preferred":[
        "\u062f\u0646\u0628\u0631\u0627\u0631\u0648\u062f\u0646\u064a"
    ],
    "name:bul_x_preferred":[
        "\u0414\u043d\u0438\u043f\u0440\u043e\u0440\u0443\u0434\u043d\u0435"
    ],
    "name:ces_x_preferred":[
        "Dniprorudne"
    ],
    "name:deu_x_preferred":[
        "Dniprorudne"
    ],
    "name:eng_x_preferred":[
        "Dniprorudne"
    ],
    "name:fas_x_preferred":[
        "\u062f\u0646\u06cc\u067e\u0631\u0648\u0631\u0648\u062f\u0646\u0647"
    ],
    "name:fra_x_preferred":[
        "Dniproroudne"
    ],
    "name:hsb_x_preferred":[
        "Dniprorudne"
    ],
    "name:hye_x_preferred":[
        "\u0534\u0576\u0565\u057a\u0580\u0578\u0580\u0578\u0582\u0564\u0576\u0578\u0565"
    ],
    "name:ita_x_preferred":[
        "Dniprorudne"
    ],
    "name:kat_x_preferred":[
        "\u10d3\u10dc\u10d4\u10de\u10e0\u10dd\u10e0\u10e3\u10d3\u10dc\u10dd\u10d4"
    ],
    "name:lav_x_preferred":[
        "D\u0146iprorudne"
    ],
    "name:nld_x_preferred":[
        "Dniprorudne"
    ],
    "name:nno_x_preferred":[
        "Dniprorudne"
    ],
    "name:pol_x_preferred":[
        "Dniprorudne"
    ],
    "name:ron_x_preferred":[
        "Dniprorudne"
    ],
    "name:rus_x_preferred":[
        "\u0414\u043d\u0435\u043f\u0440\u043e\u0440\u0443\u0434\u043d\u043e\u0435"
    ],
    "name:srp_x_preferred":[
        "\u0414\u045a\u0438\u043f\u0440\u043e\u0440\u0443\u0434\u043d\u0435"
    ],
    "name:tat_x_preferred":[
        "\u0414\u043d\u0438\u043f\u0440\u043e\u0440\u0443\u0434\u043d\u0435"
    ],
    "name:ukr_x_preferred":[
        "\u0414\u043d\u0456\u043f\u0440\u043e\u0440\u0443\u0434\u043d\u0435"
    ],
    "name:unk_x_variant":[
        "Dneprograd"
    ],
    "name:vie_x_preferred":[
        "Dniprorudne"
    ],
    "name:zho_x_preferred":[
        "\u7b2c\u8076\u4f2f\u7f85\u9b6f\u5fb7\u5167"
    ],
    "qs_pg:aaroncc":"UA",
    "qs_pg:gn_country":"UA",
    "qs_pg:gn_fcode":"PPL",
    "qs_pg:gn_pop":20271,
    "qs_pg:name":"Dneprorudnoye",
    "qs_pg:name_adm0":"Ukraine",
    "qs_pg:name_adm1":"Zaporiz\u00b4ka Oblast\u00b4",
    "qs_pg:photos_9k":1,
    "qs_pg:photos_9r":1,
    "qs_pg:photos_all":5,
    "qs_pg:photos_sr":0,
    "qs_pg:pop_sr":7,
    "qs_pg:qs_pg_placetype":"locality",
    "qs_pg:qs_pg_placetype_gp":"Town",
    "qs_pg:woe_adm0":23424976,
    "woe:adm0_id":23424976,
    "woe:name_adm0":"Ukraine",
    "woe:name_adm1":"Zaporiz\u00b4ka Oblast\u00b4",
    "woe:placetype":"Town",
    "wof:name":"Dneprorudnoye",
    "wof:placetype":"locality",
    "wof:population":20271
},
  "geometry": {"coordinates":[34.97652,47.38169],"type":"Point"}
}