{
  "type": "Feature",
  "properties": {
    "gn:admin1_code":"11.0",
    "gn:admin2_code":"8449683",
    "gn:asciiname":"Solnechnoye",
    "gn:country_code":"UA",
    "gn:dem":64,
    "gn:elevation":"53.0",
    "gn:feature_class":"P",
    "gn:feature_code":"PPL",
    "gn:name":"Solnechnoye",
    "gn:population":885,
    "gn:timezone":"Europe/Simferopol",
    "iso:country":"UA",
    "name:eng_x_preferred":[
        "Solnechnoye"
    ],
    "name:rus_x_preferred":[
        "\u0421\u043e\u043b\u043d\u0435\u0447\u043d\u043e\u0435"
    ],
    "name:ukr_x_preferred":[
        "\u0421\u043e\u043d\u044f\u0447\u043d\u0435"
    ],
    "wof:name":"Solnechnoye",
    "wof:placetype":"locality",
    "wof:population":885
},
  "geometry": {"coordinates":[35.34538,45.04726],"type":"Point"}
}