{
  "type": "Feature",
  "properties": {
    "gn:admin1_code":"13.0",
    "gn:asciiname":"Stadnitsa",
    "gn:country_code":"UA",
    "gn:dem":237,
    "gn:feature_class":"P",
    "gn:feature_code":"PPL",
    "gn:name":"Stadnitsa",
    "gn:population":0,
    "gn:timezone":"Europe/Kiev",
    "iso:country":"UA",
    "wof:name":"Stadnitsa",
    "wof:placetype":"locality"
},
  "geometry": {"coordinates":[29.74219,49.24452],"type":"Point"}
}