{
  "type": "Feature",
  "properties": {
    "gn:gn_country":"UA",
    "gn:gn_fcode":"PPL",
    "gn:gn_pop":3044,
    "gn:population":3044,
    "iso:country":"UA",
    "name:arm_x_preferred":[
        "\u0546\u056b\u056a\u0576\u0565\u0565 \u054d\u0565\u056c\u056b\u0577\u0579\u0565"
    ],
    "name:chi_x_preferred":[
        "\u4e0b\u8b1d\u5229\u8b1d"
    ],
    "name:dut_x_preferred":[
        "Als\u00f3szeliscse"
    ],
    "name:eng_x_preferred":[
        "Nizhnie Selishche"
    ],
    "name:epo_x_preferred":[
        "Ni\u0135ne Seli\u015d\u0109e"
    ],
    "name:hun_x_preferred":[
        "Als\u00f3szeliscse"
    ],
    "name:rum_x_preferred":[
        "N\u00eejnie Sel\u00ee\u0219ce"
    ],
    "name:rus_x_preferred":[
        "\u041d\u0438\u0436\u043d\u0435\u0435 \u0421\u0435\u043b\u0438\u0449\u0435"
    ],
    "name:ukr_x_preferred":[
        "Nyzhnye Selyshche"
    ],
    "name:ukr_x_variant":[
        "\u041d\u0438\u0436\u043d\u0454 \u0421\u0435\u043b\u0438\u0449\u0435"
    ],
    "name:unk_x_variant":[
        "Nizhne Selisht\u2019ye"
    ],
    "qs_pg:aaroncc":"UA",
    "qs_pg:gn_country":"UA",
    "qs_pg:gn_fcode":"PPL",
    "qs_pg:gn_pop":3044,
    "qs_pg:name":"Nyzhnye Selyshche",
    "qs_pg:photos_9r":0,
    "qs_pg:photos_sr":0,
    "qs_pg:pop_sr":4,
    "qs_pg:qs_pg_placetype":"locality",
    "wof:name":"Nyzhnye Selyshche",
    "wof:placetype":"locality",
    "wof:population":3044
},
  "geometry": {"coordinates":[23.44757,48.19911],"type":"Point"}
}