{
  "type": "Feature",
  "properties": {
    "gn:admin1_code":"26.0",
    "gn:asciiname":"Ukrayinka",
    "gn:country_code":"UA",
    "gn:dem":73,
    "gn:feature_class":"P",
    "gn:feature_code":"PPL",
    "gn:name":"Ukrayinka",
    "gn:population":0,
    "gn:timezone":"Europe/Zaporozhye",
    "iso:country":"UA",
    "name:ukr_x_preferred":[
        "Ukrayinka"
    ],
    "name:ukr_x_variant":[
        "\u0423\u043a\u0440\u0430\u0457\u043d\u043a\u0430"
    ],
    "name:und_x_variant":[
        "Ukrainka"
    ],
    "wof:name":"Ukrayinka",
    "wof:placetype":"locality"
},
  "geometry": {"coordinates":[35.68678,47.15154],"type":"Point"}
}