{
  "type": "Feature",
  "properties": {
    "gn:gn_country":"UA",
    "gn:gn_fcode":"PPL",
    "gn:gn_pop":0,
    "gn:population":1051,
    "iso:country":"UA",
    "name:crh_x_preferred":[
        "Q\u0131z\u0131lta\u015f"
    ],
    "name:eng_x_preferred":[
        "Krasnokamenka"
    ],
    "name:eng_x_variant":[
        "Krasnokamianka"
    ],
    "name:epo_x_preferred":[
        "Krasnokamenko"
    ],
    "name:nld_x_preferred":[
        "Krasnokamianka"
    ],
    "name:ron_x_preferred":[
        "Krasnokameanka"
    ],
    "name:rus_x_historical":[
        "\u041a\u0438\u0437\u0438\u043b\u0442\u0430\u0301\u0448"
    ],
    "name:rus_x_preferred":[
        "\u041a\u0438\u0437\u0438\u043b\u0442\u0430\u0301\u0448"
    ],
    "name:rus_x_variant":[
        "\u041a\u0440\u0430\u0441\u043d\u043e\u043a\u0430\u043c\u0435\u043d\u043a\u0430"
    ],
    "name:ukr_x_preferred":[
        "\u041a\u0440\u0430\u0441\u043d\u043e\u043a\u0430\u043c\u2019\u044f\u043d\u043a\u0430"
    ],
    "name:ukr_x_variant":[
        "\u041a\u0440\u0430\u0441\u043d\u043e\u043a\u0430\u043c'\u044f\u043d\u043a\u0430"
    ],
    "name:urd_x_preferred":[
        "\u06a9\u0631\u0627\u0633\u0646\u0648\u06a9\u0627\u0645\u06cc\u0627\u0646\u06a9\u0627"
    ],
    "name:vep_x_preferred":[
        "Krasnokamenk"
    ],
    "name:zho_x_preferred":[
        "\u514b\u62c9\u65af\u8afe\u5361\u59c6\u63da\u5361"
    ],
    "qs_pg:aaroncc":"UA",
    "qs_pg:gn_country":"UA",
    "qs_pg:gn_fcode":"PPL",
    "qs_pg:gn_pop":0,
    "qs_pg:name":"Krasnokamenka",
    "qs_pg:name_adm0":"Ukraine",
    "qs_pg:name_adm1":"Avtonomna Respublika Krym",
    "qs_pg:photos":55,
    "qs_pg:photos_1k":11,
    "qs_pg:photos_9k":1,
    "qs_pg:photos_9r":2,
    "qs_pg:photos_all":55,
    "qs_pg:photos_sr":2,
    "qs_pg:pop_sr":0,
    "qs_pg:qs_pg_placetype":"locality",
    "qs_pg:qs_pg_placetype_gp":"Town",
    "qs_pg:woe_adm0":23424976,
    "woe:adm0_id":23424976,
    "woe:name_adm0":"Ukraine",
    "woe:name_adm1":"Avtonomna Respublika Krym",
    "woe:placetype":"Town",
    "wof:name":"Krasnokamenka",
    "wof:placetype":"locality",
    "wof:population":1051
},
  "geometry": {"coordinates":[34.28877,44.56383],"type":"Point"}
}