{
  "type": "Feature",
  "properties": {
    "gn:admin1_code":"8.0",
    "gn:asciiname":"Chystopillya",
    "gn:country_code":"UA",
    "gn:dem":63,
    "gn:feature_class":"P",
    "gn:feature_code":"PPL",
    "gn:name":"Chystopillya",
    "gn:population":0,
    "gn:timezone":"Europe/Kiev",
    "iso:country":"UA",
    "name:ukr_x_preferred":[
        "Chystopillya"
    ],
    "name:ukr_x_variant":[
        "\u0427\u0438\u0441\u0442\u043e\u043f\u0456\u043b\u043b\u044f"
    ],
    "wof:name":"Chystopillya",
    "wof:placetype":"locality"
},
  "geometry": {"coordinates":[34.19384,47.29487],"type":"Point"}
}