{
  "type": "Feature",
  "properties": {
    "gn:country":"UA",
    "gn:fcode":"PPL",
    "gn:population":10082,
    "iso:country":"UA",
    "name:bel_x_preferred":[
        "\u0427\u044d\u0440\u043d\u044f\u0445\u0456\u045e"
    ],
    "name:ceb_x_preferred":[
        "Chernyakhiv"
    ],
    "name:chu_x_preferred":[
        "\u0427\u0440\u044c\u043d\ua657\u0445\u043e\u0432\u044a \u00b7 \u0416\u0438\u0442\u043e\u043c\u0438\u0440\u044c\u0441\u043a\ua651 \u043e\u0431\u043b\u0430\u0441\u0442\u0438"
    ],
    "name:crh_x_preferred":[
        "\u00c7ern\u00e2hiv"
    ],
    "name:deu_x_preferred":[
        "Tschernjachiw"
    ],
    "name:eng_x_preferred":[
        "Cherniakhiv"
    ],
    "name:fra_x_preferred":[
        "Tcherniakhiv"
    ],
    "name:hun_x_preferred":[
        "Csernyahiv"
    ],
    "name:pol_x_preferred":[
        "Czerniach\u00f3w"
    ],
    "name:ron_x_preferred":[
        "Cerneahiv"
    ],
    "name:rus_x_preferred":[
        "\u0427\u0435\u0440\u043d\u044f\u0445\u0456\u0432"
    ],
    "name:rus_x_variant":[
        "\u0427\u0435\u0440\u043d\u044f\u0445\u043e\u0432"
    ],
    "name:sah_x_preferred":[
        "\u0427\u0435\u0440\u043d\u044f\u0445\u043e\u0432"
    ],
    "name:ukr_x_preferred":[
        "\u0427\u0435\u0440\u043d\u044f\u0445\u0456\u0432"
    ],
    "name:und_x_variant":[
        "Chernyakhov"
    ],
    "name:zho_x_preferred":[
        "\u5207\u723e\u5c3c\u4e9e\u5e0c\u592b"
    ],
    "qs_pg:aaroncc":"UA",
    "qs_pg:gn_country":"UA",
    "qs_pg:gn_fcode":"PPL",
    "qs_pg:gn_pop":10082,
    "qs_pg:name":"Chernyakhiv",
    "qs_pg:photos_9r":0,
    "qs_pg:photos_sr":0,
    "qs_pg:pop_sr":6,
    "qs_pg:qs_pg_placetype":"locality",
    "wof:name":"Chernyakhiv",
    "wof:placetype":"locality",
    "wof:population":10082
},
  "geometry": {"coordinates":[28.67018,50.45652],"type":"Point"}
}