{
  "type": "Feature",
  "properties": {
    "gn:admin1_code":"13.0",
    "gn:asciiname":"Yabluneve",
    "gn:country_code":"UA",
    "gn:dem":128,
    "gn:feature_class":"P",
    "gn:feature_code":"PPL",
    "gn:name":"Yabluneve",
    "gn:population":0,
    "gn:timezone":"Europe/Kiev",
    "iso:country":"UA",
    "name:ukr_x_preferred":[
        "Yabluneve"
    ],
    "name:ukr_x_variant":[
        "\u042f\u0431\u043b\u0443\u043d\u0435\u0432\u0435"
    ],
    "name:und_x_variant":[
        "Yablonevoye"
    ],
    "wof:name":"Yabluneve",
    "wof:placetype":"locality"
},
  "geometry": {"coordinates":[31.63959,50.28814000000001],"type":"Point"}
}