{
  "type": "Feature",
  "properties": {
    "iso:country":"UA",
    "name:eng_x_preferred":[
        "Kazatskoye"
    ],
    "name:fra_x_preferred":[
        "Cosaques d'Azov"
    ],
    "name:jpn_x_preferred":[
        "\u30a2\u30be\u30d5\u30fb\u30b3\u30b5\u30c3\u30af\u8ecd"
    ],
    "name:pol_x_preferred":[
        "Kozacy azowscy"
    ],
    "name:rus_x_preferred":[
        "\u041a\u0430\u0437\u0430\u0446\u043a\u043e\u0435"
    ],
    "name:ukr_x_preferred":[
        "Kozats\u2019ke"
    ],
    "name:ukr_x_variant":[
        "\u041a\u043e\u0437\u0430\u0446\u044c\u043a\u0435"
    ],
    "qs:a0":"\u0423\u043a\u0440\u0430\u0457\u043d\u0430",
    "qs:a1":"*\u0421\u0443\u043c\u0441\u044c\u043a\u0430",
    "qs:a1_alt":"Sums'ka",
    "qs:a1r":"0",
    "qs:a2":"\u041a\u043e\u043d\u043e\u0442\u043e\u043f\u0441\u044c\u043a\u0438\u0439",
    "qs:a2_alt":"Konotops'kyi",
    "qs:adm0":"\u0423\u043a\u0440\u0430\u0457\u043d\u0430",
    "qs:la_lc":"*",
    "qs:level":"locality",
    "qs:loc":"\u041a\u043e\u0437\u0430\u0446\u044c\u043a\u0435",
    "qs:loc_alt":"Kozats'ke",
    "qs:pop":0,
    "qs:type":"buffered point",
    "wd:wordcount":1753,
    "wof:name":"\u041a\u043e\u0437\u0430\u0446\u044c\u043a\u0435",
    "wof:placetype":"locality"
},
  "geometry": {"coordinates":[33.519757,51.295043],"type":"Point"}
}