{
  "type": "Feature",
  "properties": {
    "iso:country":"UA",
    "name:bel_x_preferred":[
        "\u0423\u0441\u0442\u044b\u043b\u0443\u0433"
    ],
    "name:bel_x_variant":[
        "\u0423\u0441\u044c\u0446\u0456\u043b\u0443\u0433"
    ],
    "name:ces_x_preferred":[
        "Ustyluh"
    ],
    "name:crh_x_preferred":[
        "Ust\u0131lug"
    ],
    "name:deu_x_preferred":[
        "Ustyluh"
    ],
    "name:eng_x_preferred":[
        "Ustyluh"
    ],
    "name:fas_x_preferred":[
        "\u0627\u0648\u0633\u062a\u06cc\u0644\u0648\u0647"
    ],
    "name:fra_x_preferred":[
        "Oustylouh"
    ],
    "name:heb_x_preferred":[
        "\u05d0\u05d5\u05e1\u05d8\u05d9\u05dc\u05d5\u05d2"
    ],
    "name:hsb_x_preferred":[
        "Ustyluh"
    ],
    "name:hye_x_preferred":[
        "\u0548\u0582\u057d\u057f\u056b\u056c\u0578\u0582\u0563"
    ],
    "name:ita_x_preferred":[
        "Ustyluh"
    ],
    "name:jpn_x_preferred":[
        "\u30a6\u30b9\u30c6\u30a3\u30eb\u30fc\u30d5"
    ],
    "name:kat_x_preferred":[
        "\u10e3\u10e1\u10e2\u10d8\u10da\u10e3\u10d2\u10d8"
    ],
    "name:lav_x_preferred":[
        "Ustiluha"
    ],
    "name:lit_x_preferred":[
        "Ustyluhas"
    ],
    "name:nld_x_preferred":[
        "Ustyluh"
    ],
    "name:nno_x_preferred":[
        "Ustyluh"
    ],
    "name:pol_x_preferred":[
        "U\u015bci\u0142ug"
    ],
    "name:ron_x_preferred":[
        "Ust\u00eeluh"
    ],
    "name:rue_x_preferred":[
        "\u0423\u0441\u0442\u0438\u043b\u0443\u0433"
    ],
    "name:rus_x_preferred":[
        "\u0423\u0441\u0442\u0438\u043b\u0443\u0433"
    ],
    "name:tat_x_preferred":[
        "\u0423\u0441\u0442\u044b\u043b\u0443\u04bb"
    ],
    "name:ukr_x_preferred":[
        "\u0423\u0441\u0442\u0438\u043b\u0443\u0433"
    ],
    "name:ukr_x_variant":[
        "Ustyluh"
    ],
    "name:vie_x_preferred":[
        "Ustyluh"
    ],
    "name:yid_x_preferred":[
        "\u05d0\u05d5\u05e1\u05d8\u05d9\u05dc\u05e2"
    ],
    "name:zho_x_preferred":[
        "\u70cf\u65af\u5b63\u53e4\u683c"
    ],
    "qs:a0":"\u0423\u043a\u0440\u0430\u0457\u043d\u0430",
    "qs:a1":"*\u0412\u043e\u043b\u0438\u043d\u0441\u044c\u043a\u0430",
    "qs:a1_alt":"Volyns'ka",
    "qs:a1r":"0",
    "qs:a2":"\u0412\u043e\u043b\u043e\u0434\u0438\u043c\u0438\u0440-\u0412\u043e\u043b\u0438\u043d\u0441\u044c\u043a\u0438\u0439",
    "qs:a2_alt":"Volodymyr-Volyns'kyi",
    "qs:adm0":"\u0423\u043a\u0440\u0430\u0457\u043d\u0430",
    "qs:la_lc":"*",
    "qs:level":"locality",
    "qs:loc":"\u0423\u0441\u0442\u0438\u043b\u0443\u0433",
    "qs:loc_alt":"Ustyluh",
    "qs:pop":0,
    "qs:type":"buffered point",
    "wd:wordcount":71,
    "wof:name":"\u0423\u0441\u0442\u0438\u043b\u0443\u0433",
    "wof:placetype":"locality"
},
  "geometry": {"coordinates":[24.162741,50.852877],"type":"Point"}
}