{
  "type": "Feature",
  "properties": {
    "gn:admin1_code":"25.0",
    "gn:asciiname":"Hlybivtsi",
    "gn:country_code":"UA",
    "gn:dem":189,
    "gn:feature_class":"P",
    "gn:feature_code":"PPL",
    "gn:name":"Hlybivtsi",
    "gn:population":0,
    "gn:timezone":"Europe/Uzhgorod",
    "iso:country":"UA",
    "name:ukr_x_preferred":[
        "Hlybivtsi"
    ],
    "name:ukr_x_variant":[
        "\u0413\u043b\u0438\u0431\u0456\u0432\u0446\u0456"
    ],
    "wof:name":"Hlybivtsi",
    "wof:placetype":"locality"
},
  "geometry": {"coordinates":[22.69354,48.53881],"type":"Point"}
}