{
  "type": "Feature",
  "properties": {
    "gn:admin1_code":"3.0",
    "gn:asciiname":"Nedoboyevtsy",
    "gn:country_code":"UA",
    "gn:dem":228,
    "gn:feature_class":"P",
    "gn:feature_code":"PPL",
    "gn:name":"Nedoboyevtsy",
    "gn:population":0,
    "gn:timezone":"Europe/Kiev",
    "iso:country":"UA",
    "name:und_x_variant":[
        "Nedebeutsy",
        "Nedobauts\u2019",
        "Nedoboutsy",
        "Ned\u0103b\u0103u\u0163i",
        "Nedoboyevtsy"
    ],
    "wof:name":"Nedoboyevtsy",
    "wof:placetype":"locality"
},
  "geometry": {"coordinates":[26.36724,48.43181],"type":"Point"}
}