{
  "type": "Feature",
  "properties": {
    "iso:country":"UA",
    "name:deu_x_preferred":[
        "Uspenka"
    ],
    "name:eng_x_preferred":[
        "Uspenka"
    ],
    "name:est_x_preferred":[
        "Uspenka"
    ],
    "name:hye_x_preferred":[
        "\u0548\u0582\u057d\u057a\u0565\u0576\u056f\u0561"
    ],
    "name:lav_x_preferred":[
        "Uspenka"
    ],
    "name:rus_x_preferred":[
        "\u0423\u0441\u043f\u0435\u043d\u043a\u0430"
    ],
    "name:ukr_x_preferred":[
        "\u0423\u0441\u043f\u0435\u043d\u043a\u0430"
    ],
    "name:unk_x_variant":[
        "Usnenskoye"
    ],
    "qs:a0":"\u0423\u043a\u0440\u0430\u0457\u043d\u0430",
    "qs:a1":"*\u0414\u043e\u043d\u0435\u0446\u044c\u043a\u0430",
    "qs:a1_alt":"Donets'ka",
    "qs:a1r":"0",
    "qs:a2":"\u0410\u043c\u0432\u0440\u043e\u0441\u0456\u0457\u0432\u0441\u044c\u043a\u0438\u0439",
    "qs:a2_alt":"Amvrosiivs'kyi",
    "qs:adm0":"\u0423\u043a\u0440\u0430\u0457\u043d\u0430",
    "qs:la_lc":"*",
    "qs:level":"locality",
    "qs:loc":"\u0423\u0441\u043f\u0435\u043d\u043a\u0430",
    "qs:loc_alt":"Uspenka",
    "qs:pop":0,
    "qs:type":"buffered point",
    "wd:wordcount":258,
    "wof:name":"\u0423\u0441\u043f\u0435\u043d\u043a\u0430",
    "wof:placetype":"locality"
},
  "geometry": {"coordinates":[38.716129,47.729622],"type":"Point"}
}