{
  "type": "Feature",
  "properties": {
    "gn:admin1_code":"7.0",
    "gn:asciiname":"Lebedivka",
    "gn:country_code":"UA",
    "gn:dem":132,
    "gn:feature_class":"P",
    "gn:feature_code":"PPL",
    "gn:name":"Lebedivka",
    "gn:population":0,
    "gn:timezone":"Europe/Kiev",
    "iso:country":"UA",
    "name:ukr_x_preferred":[
        "Lebedivka"
    ],
    "name:ukr_x_variant":[
        "\u041b\u0435\u0431\u0435\u0434\u0456\u0432\u043a\u0430"
    ],
    "wof:name":"Lebedivka",
    "wof:placetype":"locality"
},
  "geometry": {"coordinates":[37.33958,50.01263],"type":"Point"}
}