{
  "type": "Feature",
  "properties": {
    "gn:admin1_code":"3.0",
    "gn:asciiname":"Vatra",
    "gn:country_code":"UA",
    "gn:dem":145,
    "gn:feature_class":"P",
    "gn:feature_code":"PPL",
    "gn:name":"Vatra",
    "gn:population":0,
    "gn:timezone":"Europe/Kiev",
    "iso:country":"UA",
    "name:bos_x_preferred":[
        "Vatra"
    ],
    "name:deu_x_preferred":[
        "Vatra"
    ],
    "name:hrv_x_preferred":[
        "Vatra"
    ],
    "name:ita_x_preferred":[
        "Vatra"
    ],
    "name:pol_x_preferred":[
        "Watra"
    ],
    "name:ron_x_preferred":[
        "Vatra"
    ],
    "name:rus_x_preferred":[
        "\u0412\u0430\u0442\u0440\u0430"
    ],
    "name:srp_x_preferred":[
        "\u0412\u0430\u0442\u0440\u0430"
    ],
    "name:ukr_x_preferred":[
        "\u0412\u0430\u0442\u0440\u0430"
    ],
    "wof:name":"Vatra",
    "wof:placetype":"locality"
},
  "geometry": {"coordinates":[26.11667000000001,48.26667],"type":"Point"}
}