{
  "type": "Feature",
  "properties": {
    "gn:admin1_code":"23.0",
    "gn:asciiname":"Chukiv",
    "gn:country_code":"UA",
    "gn:dem":255,
    "gn:feature_class":"P",
    "gn:feature_code":"PPL",
    "gn:name":"Chukiv",
    "gn:population":0,
    "gn:timezone":"Europe/Kiev",
    "iso:country":"UA",
    "name:ukr_x_preferred":[
        "\u0427\u0443\u043a\u0456\u0432"
    ],
    "name:und_x_variant":[
        "Chukov"
    ],
    "wof:name":"Chukiv",
    "wof:placetype":"locality"
},
  "geometry": {"coordinates":[28.88362,48.89435],"type":"Point"}
}