{
  "type": "Feature",
  "properties": {
    "gn:admin1_code":"17.0",
    "gn:asciiname":"Bilyari",
    "gn:country_code":"UA",
    "gn:dem":18,
    "gn:feature_class":"P",
    "gn:feature_code":"PPL",
    "gn:name":"Bilyari",
    "gn:population":0,
    "gn:timezone":"Europe/Kiev",
    "iso:country":"UA",
    "name:ukr_x_preferred":[
        "Bilyari"
    ],
    "name:ukr_x_variant":[
        "\u0411\u0456\u043b\u044f\u0440\u0456"
    ],
    "name:und_x_variant":[
        "Staryye Belyary",
        "Belyary"
    ],
    "wof:name":"Bilyari",
    "wof:placetype":"locality"
},
  "geometry": {"coordinates":[31.03181,46.6232],"type":"Point"}
}