{
  "type": "Feature",
  "properties": {
    "gn:population":4272,
    "iso:country":"UA",
    "name:eng_x_preferred":[
        "Lypnyazhka"
    ],
    "name:rus_x_preferred":[
        "\u041b\u0438\u043f\u043d\u044f\u0436\u043a\u0430"
    ],
    "name:und_x_variant":[
        "Lipnyazhka"
    ],
    "qs:a0":"\u0423\u043a\u0440\u0430\u0457\u043d\u0430",
    "qs:a1":"*\u041a\u0456\u0440\u043e\u0432\u043e\u0433\u0440\u0430\u0434\u0441\u044c\u043a\u0430",
    "qs:a1_alt":"Kirovohrads'ka",
    "qs:a1r":"0",
    "qs:a2":"\u0414\u043e\u0431\u0440\u043e\u0432\u0435\u043b\u0438\u0447\u043a\u0456\u0432\u0441\u044c\u043a\u0438\u0439",
    "qs:a2_alt":"Dobrovelychkivs'kyi",
    "qs:adm0":"\u0423\u043a\u0440\u0430\u0457\u043d\u0430",
    "qs:la_lc":"*",
    "qs:level":"locality",
    "qs:loc":"\u041b\u0438\u043f\u043d\u044f\u0436\u043a\u0430",
    "qs:loc_alt":"Lypniazhka",
    "qs:pop":0,
    "qs:type":"buffered point",
    "wof:name":"\u041b\u0438\u043f\u043d\u044f\u0436\u043a\u0430",
    "wof:placetype":"locality",
    "wof:population":4272
},
  "geometry": {"coordinates":[31.075435,48.445657],"type":"Point"}
}