{
  "type": "Feature",
  "properties": {
    "gn:admin1_code":"21.0",
    "gn:asciiname":"Borodanove",
    "gn:country_code":"UA",
    "gn:dem":158,
    "gn:feature_class":"P",
    "gn:feature_code":"PPL",
    "gn:name":"Borodanove",
    "gn:population":0,
    "gn:timezone":"Europe/Kiev",
    "iso:country":"UA",
    "name:ukr_x_preferred":[
        "Borodanove"
    ],
    "name:ukr_x_variant":[
        "\u0411\u043e\u0440\u043e\u0434\u0430\u043d\u043e\u0432\u0435"
    ],
    "name:und_x_variant":[
        "Borodanovo"
    ],
    "wof:name":"Borodanove",
    "wof:placetype":"locality"
},
  "geometry": {"coordinates":[33.73225,50.76939],"type":"Point"}
}