{
  "type": "Feature",
  "properties": {
    "gn:admin1_code":"17.0",
    "gn:asciiname":"Pidhirne",
    "gn:country_code":"UA",
    "gn:dem":141,
    "gn:feature_class":"P",
    "gn:feature_code":"PPL",
    "gn:name":"Pidhirne",
    "gn:population":0,
    "gn:timezone":"Europe/Kiev",
    "iso:country":"UA",
    "name:ukr_x_preferred":[
        "Pidhirne"
    ],
    "name:ukr_x_variant":[
        "\u041f\u0456\u0434\u0433\u0456\u0440\u043d\u0435"
    ],
    "name:und_x_variant":[
        "Podgornoye"
    ],
    "wof:name":"Pidhirne",
    "wof:placetype":"locality"
},
  "geometry": {"coordinates":[29.13491,46.44135],"type":"Point"}
}