{
  "type": "Feature",
  "properties": {
    "gn:admin1_code":"5.0",
    "gn:asciiname":"Lozove",
    "gn:country_code":"UA",
    "gn:dem":176,
    "gn:feature_class":"P",
    "gn:feature_code":"PPL",
    "gn:name":"Lozove",
    "gn:population":0,
    "gn:timezone":"Europe/Kiev",
    "iso:country":"UA",
    "name:rus_x_preferred":[
        "\u041b\u043e\u0437\u043e\u0432\u0435"
    ],
    "name:ukr_x_preferred":[
        "\u041b\u043e\u0437\u043e\u0432\u0435"
    ],
    "name:und_x_variant":[
        "Lozevskoy",
        "Lozovskoy",
        "Lozove",
        "Lozovoye"
    ],
    "wof:name":"Lozove",
    "wof:placetype":"locality"
},
  "geometry": {"coordinates":[38.24126,48.37845],"type":"Point"}
}