{
  "type": "Feature",
  "properties": {
    "gn:admin1_code":"4.0",
    "gn:asciiname":"Shakhtar",
    "gn:country_code":"UA",
    "gn:dem":17,
    "gn:feature_class":"P",
    "gn:feature_code":"PPL",
    "gn:name":"Shakhtar",
    "gn:population":0,
    "gn:timezone":"Europe/Kiev",
    "iso:country":"UA",
    "name:rus_x_preferred":[
        "Shakht\u00ebr"
    ],
    "name:rus_x_variant":[
        "\u0428\u0430\u0445\u0442\u0451\u0440"
    ],
    "name:ukr_x_preferred":[
        "Shakhtar"
    ],
    "name:ukr_x_variant":[
        "\u0428\u0430\u0445\u0442\u0430\u0440"
    ],
    "wof:name":"Shakhtar",
    "wof:placetype":"locality"
},
  "geometry": {"coordinates":[34.19413,47.73403],"type":"Point"}
}