{
  "type": "Feature",
  "properties": {
    "gn:population":3094,
    "iso:country":"UA",
    "qs:a0":"\u0423\u043a\u0440\u0430\u0457\u043d\u0430",
    "qs:a1":"*\u041e\u0434\u0435\u0441\u044c\u043a\u0430",
    "qs:a1_alt":"Odes'ka",
    "qs:a1r":"0",
    "qs:a2":"\u0411\u0430\u043b\u0442\u0441\u044c\u043a\u0438\u0439",
    "qs:a2_alt":"Balts'kyi",
    "qs:adm0":"\u0423\u043a\u0440\u0430\u0457\u043d\u0430",
    "qs:la_lc":"*",
    "qs:level":"locality",
    "qs:loc":"\u041f\u0456\u0449\u0430\u043d\u0430",
    "qs:loc_alt":"Pischana",
    "qs:pop":0,
    "qs:type":"buffered point",
    "wof:name":"\u041f\u0456\u0449\u0430\u043d\u0430",
    "wof:placetype":"locality",
    "wof:population":3094
},
  "geometry": {"coordinates":[29.732897,48.130239],"type":"Point"}
}