{
  "type": "Feature",
  "properties": {
    "gn:admin1_code":"19.0",
    "gn:asciiname":"Shkariv",
    "gn:country_code":"UA",
    "gn:dem":185,
    "gn:feature_class":"P",
    "gn:feature_code":"PPL",
    "gn:name":"Shkariv",
    "gn:population":0,
    "gn:timezone":"Europe/Kiev",
    "iso:country":"UA",
    "name:ukr_x_preferred":[
        "Shkariv"
    ],
    "name:ukr_x_variant":[
        "\u0428\u043a\u0430\u0440\u0456\u0432"
    ],
    "name:und_x_variant":[
        "Shkarov"
    ],
    "wof:name":"Shkariv",
    "wof:placetype":"locality"
},
  "geometry": {"coordinates":[26.61675,50.5891],"type":"Point"}
}