{
  "type": "Feature",
  "properties": {
    "iso:country":"UA",
    "name:bel_x_preferred":[
        "\u0421\u0442\u0430\u0440\u0430 \u041e\u0440\u0436\u044b\u0446\u044f"
    ],
    "name:deu_x_preferred":[
        "Stara Orschyzja"
    ],
    "name:eng_x_preferred":[
        "Stara Orzhytsia"
    ],
    "name:ron_x_preferred":[
        "Stara Orj\u00ee\u021bea"
    ],
    "name:rus_x_preferred":[
        "\u0421\u0442\u0430\u0440\u0430\u044f \u041e\u0440\u0436\u0438\u0446\u0430"
    ],
    "name:ukr_x_preferred":[
        "Stara Orzhytsya"
    ],
    "name:ukr_x_variant":[
        "\u0421\u0442\u0430\u0440\u0430 \u041e\u0440\u0436\u0438\u0446\u044f"
    ],
    "name:und_x_variant":[
        "Orzhitsa"
    ],
    "name:zho_x_preferred":[
        "\u820a\u5967\u723e\u65e5\u9f4a\u4e9e"
    ],
    "qs:a0":"\u0423\u043a\u0440\u0430\u0457\u043d\u0430",
    "qs:a1":"*\u041a\u0438\u0457\u0432\u0441\u044c\u043a\u0430",
    "qs:a1_alt":"Kyivs'ka",
    "qs:a1r":"0",
    "qs:a2":"\u0417\u0433\u0443\u0440\u0456\u0432\u0441\u044c\u043a\u0438\u0439",
    "qs:a2_alt":"Zghurivs'kyi",
    "qs:adm0":"\u0423\u043a\u0440\u0430\u0457\u043d\u0430",
    "qs:la_lc":"*",
    "qs:level":"locality",
    "qs:loc":"\u0421\u0442\u0430\u0440\u0430 \u041e\u0440\u0436\u0438\u0446\u044f",
    "qs:loc_alt":"Stara Orzhytsia",
    "qs:pop":0,
    "qs:type":"buffered point",
    "wof:name":"\u0421\u0442\u0430\u0440\u0430 \u041e\u0440\u0436\u0438\u0446\u044f",
    "wof:placetype":"locality"
},
  "geometry": {"coordinates":[31.908085,50.459929],"type":"Point"}
}