{
  "type": "Feature",
  "properties": {
    "gn:admin1_code":"3.0",
    "gn:asciiname":"Kreshchatik",
    "gn:country_code":"UA",
    "gn:dem":274,
    "gn:feature_class":"P",
    "gn:feature_code":"PPL",
    "gn:name":"Kreshchatik",
    "gn:population":0,
    "gn:timezone":"Europe/Kiev",
    "iso:country":"UA",
    "name:und_x_variant":[
        "Crisceatec",
        "Krischatek",
        "Krishchatik",
        "Kryszczatyk",
        "Kryshchatyk",
        "Kreshchatik"
    ],
    "wof:name":"Kreshchatik",
    "wof:placetype":"locality"
},
  "geometry": {"coordinates":[25.74527,48.62854],"type":"Point"}
}