{
  "type": "Feature",
  "properties": {
    "gn:admin1_code":"26.0",
    "gn:asciiname":"Novovoznesenka",
    "gn:country_code":"UA",
    "gn:dem":126,
    "gn:feature_class":"P",
    "gn:feature_code":"PPL",
    "gn:name":"Novovoznesenka",
    "gn:population":0,
    "gn:timezone":"Europe/Zaporozhye",
    "iso:country":"UA",
    "name:ukr_x_preferred":[
        "Novovoznesenka"
    ],
    "name:ukr_x_variant":[
        "\u041d\u043e\u0432\u043e\u0432\u043e\u0437\u043d\u0435\u0441\u0435\u043d\u043a\u0430"
    ],
    "wof:name":"Novovoznesenka",
    "wof:placetype":"locality"
},
  "geometry": {"coordinates":[34.87017,48.01425],"type":"Point"}
}