{
  "type": "Feature",
  "properties": {
    "gn:admin1_code":"19.0",
    "gn:asciiname":"Ledne",
    "gn:country_code":"UA",
    "gn:dem":184,
    "gn:feature_class":"P",
    "gn:feature_code":"PPL",
    "gn:name":"Ledne",
    "gn:population":0,
    "gn:timezone":"Europe/Kiev",
    "iso:country":"UA",
    "name:ukr_x_preferred":[
        "Ledne"
    ],
    "name:ukr_x_variant":[
        "\u041b\u0435\u0434\u043d\u0435"
    ],
    "name:und_x_variant":[
        "Ledno"
    ],
    "wof:name":"Ledne",
    "wof:placetype":"locality"
},
  "geometry": {"coordinates":[26.21306,51.06524],"type":"Point"}
}