{
  "type": "Feature",
  "properties": {
    "gn:admin1_code":"21.0",
    "gn:asciiname":"Kubareve",
    "gn:country_code":"UA",
    "gn:dem":174,
    "gn:feature_class":"P",
    "gn:feature_code":"PPL",
    "gn:name":"Kubareve",
    "gn:population":0,
    "gn:timezone":"Europe/Kiev",
    "iso:country":"UA",
    "name:ukr_x_preferred":[
        "Kubareve"
    ],
    "name:ukr_x_variant":[
        "\u041a\u0443\u0431\u0430\u0440\u0435\u0432\u0435"
    ],
    "name:und_x_variant":[
        "Kubarevo"
    ],
    "wof:name":"Kubareve",
    "wof:placetype":"locality"
},
  "geometry": {"coordinates":[33.87911,51.48174],"type":"Point"}
}