{
  "type": "Feature",
  "properties": {
    "gn:admin1_code":"6.0",
    "gn:asciiname":"Priozernoye",
    "gn:country_code":"UA",
    "gn:dem":262,
    "gn:feature_class":"P",
    "gn:feature_code":"PPL",
    "gn:name":"Priozernoye",
    "gn:population":0,
    "gn:timezone":"Europe/Kiev",
    "iso:country":"UA",
    "name:und_x_variant":[
        "Psary",
        "Priozernoye"
    ],
    "wof:name":"Priozernoye",
    "wof:placetype":"locality"
},
  "geometry": {"coordinates":[24.46812000000001,49.41414],"type":"Point"}
}