{
  "type": "Feature",
  "properties": {
    "iso:country":"UA",
    "name:chi_x_preferred":[
        "\u79d1\u723e\u7d0d\u6d1b\u7dad\u5947"
    ],
    "name:eng_x_preferred":[
        "Kornalovychi"
    ],
    "name:pol_x_preferred":[
        "Kornalowice"
    ],
    "name:ron_x_preferred":[
        "Kornalov\u00eeci"
    ],
    "name:rum_x_preferred":[
        "Kornalov\u00eeci"
    ],
    "name:rus_x_preferred":[
        "\u041a\u043e\u0440\u043d\u0430\u043b\u043e\u0432\u0438\u0447\u0438"
    ],
    "name:ukr_x_preferred":[
        "\u041a\u043e\u0440\u043d\u0430\u043b\u043e\u0432\u0438\u0447\u0456"
    ],
    "qs:a0":"\u0423\u043a\u0440\u0430\u0457\u043d\u0430",
    "qs:a1":"*\u041b\u044c\u0432\u0456\u0432\u0441\u044c\u043a\u0430",
    "qs:a1_alt":"L'vivs'ka",
    "qs:a1r":"0",
    "qs:a2":"\u0421\u0430\u043c\u0431\u0456\u0440\u0441\u044c\u043a\u0438\u0439",
    "qs:a2_alt":"Sambirs'kyi",
    "qs:adm0":"\u0423\u043a\u0440\u0430\u0457\u043d\u0430",
    "qs:la_lc":"*",
    "qs:level":"locality",
    "qs:loc":"\u041a\u043e\u0440\u043d\u0430\u043b\u043e\u0432\u0438\u0447\u0456",
    "qs:loc_alt":"Kornalovychi",
    "qs:pop":0,
    "qs:type":"buffered point",
    "wd:wordcount":80,
    "wof:name":"\u041a\u043e\u0440\u043d\u0430\u043b\u043e\u0432\u0438\u0447\u0456",
    "wof:placetype":"locality"
},
  "geometry": {"coordinates":[23.354195,49.538371],"type":"Point"}
}