{
  "type": "Feature",
  "properties": {
    "gn:admin1_code":"25.0",
    "gn:asciiname":"Podgornoye",
    "gn:country_code":"UA",
    "gn:dem":364,
    "gn:feature_class":"P",
    "gn:feature_code":"PPL",
    "gn:name":"Podgornoye",
    "gn:population":0,
    "gn:timezone":"Europe/Uzhgorod",
    "iso:country":"UA",
    "name:und_x_variant":[
        "Voloske",
        "Podgornoye"
    ],
    "wof:name":"Podgornoye",
    "wof:placetype":"locality"
},
  "geometry": {"coordinates":[23.02832,48.39773],"type":"Point"}
}