{
  "type": "Feature",
  "properties": {
    "gn:admin1_code":"25.0",
    "gn:asciiname":"Podgornoye",
    "gn:country_code":"UA",
    "gn:dem":364,
    "gn:feature_class":"P",
    "gn:feature_code":"PPL",
    "gn:name":"Podgornoye",
    "gn:population":0,
    "gn:timezone":"Europe/Uzhgorod",
    "iso:country":"UA",
    "name:che_x_preferred":[
        "\u041f\u043e\u0434\u0433\u043e\u0440\u043d\u0438"
    ],
    "name:rus_x_preferred":[
        "\u041f\u043e\u0434\u0433\u043e\u0440\u043d\u043e\u0435"
    ],
    "name:tat_x_preferred":[
        "\u041f\u043e\u0434\u0433\u043e\u0440\u043d\u043e\u0435"
    ],
    "name:ukr_x_preferred":[
        "\u041f\u0456\u0434\u0433\u0456\u0440\u043d\u0435"
    ],
    "name:und_x_variant":[
        "Voloske",
        "Podgornoye"
    ],
    "wof:name":"Podgornoye",
    "wof:placetype":"locality"
},
  "geometry": {"coordinates":[23.02832,48.39773],"type":"Point"}
}