{
  "type": "Feature",
  "properties": {
    "gn:admin1_code":"7.0",
    "gn:asciiname":"Velyka Rohozyanka",
    "gn:country_code":"UA",
    "gn:dem":144,
    "gn:feature_class":"P",
    "gn:feature_code":"PPL",
    "gn:name":"Velyka Rohozyanka",
    "gn:population":0,
    "gn:timezone":"Europe/Kiev",
    "iso:country":"UA",
    "name:ukr_x_preferred":[
        "Velyka Rohozyanka"
    ],
    "name:ukr_x_variant":[
        "\u0412\u0435\u043b\u0438\u043a\u0430 \u0420\u043e\u0433\u043e\u0437\u044f\u043d\u043a\u0430"
    ],
    "name:und_x_variant":[
        "Bol\u2019shaya Rogozyanka",
        "Velikaya Rogozyanka"
    ],
    "wof:name":"Velyka Rohozyanka",
    "wof:placetype":"locality"
},
  "geometry": {"coordinates":[35.83779000000001,50.18778],"type":"Point"}
}