{
  "type": "Feature",
  "properties": {
    "gn:admin1_code":"2.0",
    "gn:asciiname":"Lemeshivka",
    "gn:country_code":"UA",
    "gn:dem":164,
    "gn:feature_class":"P",
    "gn:feature_code":"PPL",
    "gn:name":"Lemeshivka",
    "gn:population":0,
    "gn:timezone":"Europe/Kiev",
    "iso:country":"UA",
    "name:eng_x_preferred":[
        "Lemeshevka"
    ],
    "name:rus_x_preferred":[
        "\u041b\u0435\u043c\u0435\u0448\u043e\u0432\u043a\u0430"
    ],
    "name:ukr_x_preferred":[
        "Lemeshivka"
    ],
    "name:ukr_x_variant":[
        "\u041b\u0435\u043c\u0435\u0448\u0456\u0432\u043a\u0430"
    ],
    "name:und_x_variant":[
        "Lemeshovka"
    ],
    "wof:name":"Lemeshivka",
    "wof:placetype":"locality"
},
  "geometry": {"coordinates":[31.63471,52.0773],"type":"Point"}
}