{
  "type": "Feature",
  "properties": {
    "gn:admin1_code":"15.0",
    "gn:asciiname":"Dobryanichi",
    "gn:country_code":"UA",
    "gn:dem":313,
    "gn:feature_class":"P",
    "gn:feature_code":"PPL",
    "gn:name":"Dobryanichi",
    "gn:population":0,
    "gn:timezone":"Europe/Kiev",
    "iso:country":"UA",
    "name:und_x_variant":[
        "Dobzhanitsa",
        "Dobryanichi"
    ],
    "wof:name":"Dobryanichi",
    "wof:placetype":"locality"
},
  "geometry": {"coordinates":[24.52317,49.5625],"type":"Point"}
}