{
  "type": "Feature",
  "properties": {
    "gn:admin1_code":"13.0",
    "gn:asciiname":"Pidhayne",
    "gn:country_code":"UA",
    "gn:dem":140,
    "gn:feature_class":"P",
    "gn:feature_code":"PPL",
    "gn:name":"Pidhayne",
    "gn:population":0,
    "gn:timezone":"Europe/Kiev",
    "iso:country":"UA",
    "name:ukr_x_preferred":[
        "Pidhayne"
    ],
    "name:ukr_x_variant":[
        "\u041f\u0456\u0434\u0433\u0430\u0439\u043d\u0435"
    ],
    "name:und_x_variant":[
        "Khanev",
        "Podgaynoye"
    ],
    "wof:name":"Pidhayne",
    "wof:placetype":"locality"
},
  "geometry": {"coordinates":[29.66452,50.83904],"type":"Point"}
}