{
  "type": "Feature",
  "properties": {
    "iso:country":"UA",
    "qs:a0":"\u0423\u043a\u0440\u0430\u0457\u043d\u0430",
    "qs:a1":"*\u041b\u0443\u0433\u0430\u043d\u0441\u044c\u043a\u0430",
    "qs:a1_alt":"Luhans'ka",
    "qs:a1r":"0",
    "qs:a2":"\u0410\u043d\u0442\u0440\u0430\u0446\u0438\u0442\u0456\u0432\u0441\u044c\u043a\u0438\u0439",
    "qs:a2_alt":"Antratsytivs'kyi",
    "qs:adm0":"\u0423\u043a\u0440\u0430\u0457\u043d\u0430",
    "qs:la_lc":"*",
    "qs:level":"locality",
    "qs:loc":"\u041d\u0438\u0436\u043d\u0456\u0439 \u041d\u0430\u0433\u043e\u043b\u044c\u0447\u0438\u043a",
    "qs:loc_alt":"Nyzhnii Nahol'chyk",
    "qs:pop":0,
    "qs:type":"buffered point",
    "wof:name":"\u041d\u0438\u0436\u043d\u0456\u0439 \u041d\u0430\u0433\u043e\u043b\u044c\u0447\u0438\u043a",
    "wof:placetype":"locality"
},
  "geometry": {"coordinates":[39.065046,48.016595],"type":"Point"}
}