{
  "type": "Feature",
  "properties": {
    "gn:admin1_code":"22.0",
    "gn:asciiname":"Lisechyn'tse",
    "gn:country_code":"UA",
    "gn:dem":333,
    "gn:feature_class":"P",
    "gn:feature_code":"PPL",
    "gn:name":"Lisechyn\u2019tse",
    "gn:population":0,
    "gn:timezone":"Europe/Kiev",
    "iso:country":"UA",
    "wof:name":"Lisechyn'tse",
    "wof:placetype":"locality"
},
  "geometry": {"coordinates":[26.00954,49.68362],"type":"Point"}
}