{
  "type": "Feature",
  "properties": {
    "gn:admin1_code":"13.0",
    "gn:asciiname":"Kozyn",
    "gn:country_code":"UA",
    "gn:dem":123,
    "gn:feature_class":"P",
    "gn:feature_code":"PPL",
    "gn:name":"Kozyn",
    "gn:population":0,
    "gn:timezone":"Europe/Kiev",
    "iso:country":"UA",
    "name:bel_x_preferred":[
        "\u041a\u0430\u0437\u044b\u043d"
    ],
    "name:crh_x_preferred":[
        "Koz\u0131n"
    ],
    "name:deu_x_preferred":[
        "Kosyn"
    ],
    "name:hye_x_preferred":[
        "\u053f\u0578\u0566\u056b\u0576"
    ],
    "name:pol_x_preferred":[
        "Kozyn"
    ],
    "name:rus_x_preferred":[
        "\u041a\u043e\u0437\u0438\u043d"
    ],
    "name:sah_x_preferred":[
        "\u041a\u043e\u0437\u0438\u043d"
    ],
    "name:ukr_x_preferred":[
        "Kozyn"
    ],
    "name:ukr_x_variant":[
        "\u041a\u043e\u0437\u0438\u043d"
    ],
    "name:und_x_variant":[
        "Kozin"
    ],
    "wof:name":"Kozyn",
    "wof:placetype":"locality"
},
  "geometry": {"coordinates":[32.21923,50.36659],"type":"Point"}
}