{
  "type": "Feature",
  "properties": {
    "gn:admin1_code":"23.0",
    "gn:asciiname":"Sonyachne",
    "gn:country_code":"UA",
    "gn:dem":295,
    "gn:feature_class":"P",
    "gn:feature_code":"PPL",
    "gn:name":"Sonyachne",
    "gn:population":0,
    "gn:timezone":"Europe/Kiev",
    "iso:country":"UA",
    "name:ukr_x_preferred":[
        "\u0421\u043e\u043d\u044f\u0447\u043d\u0435"
    ],
    "name:und_x_variant":[
        "Solnechnoye"
    ],
    "wof:name":"Sonyachne",
    "wof:placetype":"locality"
},
  "geometry": {"coordinates":[28.83284,48.40777],"type":"Point"}
}