{
  "type": "Feature",
  "properties": {
    "gn:admin1_code":"14.0",
    "gn:asciiname":"Solontsi",
    "gn:country_code":"UA",
    "gn:dem":173,
    "gn:feature_class":"P",
    "gn:feature_code":"PPL",
    "gn:name":"Solontsi",
    "gn:population":0,
    "gn:timezone":"Europe/Zaporozhye",
    "iso:country":"UA",
    "name:ukr_x_preferred":[
        "Solontsi"
    ],
    "name:ukr_x_variant":[
        "\u0421\u043e\u043b\u043e\u043d\u0446\u0456"
    ],
    "name:und_x_variant":[
        "Solontsy"
    ],
    "wof:name":"Solontsi",
    "wof:placetype":"locality"
},
  "geometry": {"coordinates":[38.14364000000001,49.90341],"type":"Point"}
}