{
  "type": "Feature",
  "properties": {
    "gn:admin1_code":"8.0",
    "gn:asciiname":"Radyans'ke",
    "gn:country_code":"UA",
    "gn:dem":30,
    "gn:feature_class":"P",
    "gn:feature_code":"PPL",
    "gn:name":"Radyans\u2019ke",
    "gn:population":0,
    "gn:timezone":"Europe/Kiev",
    "iso:country":"UA",
    "name:rus_x_preferred":[
        "\u0420\u0430\u0434\u044f\u043d\u0441\u043a\u043e\u0435"
    ],
    "name:ukr_x_preferred":[
        "Radyans\u2019ke"
    ],
    "name:ukr_x_variant":[
        "\u0420\u0430\u0434\u044f\u043d\u0441\u044c\u043a\u0435"
    ],
    "name:und_x_variant":[
        "Radyanskoye"
    ],
    "wof:name":"Radyans'ke",
    "wof:placetype":"locality"
},
  "geometry": {"coordinates":[34.7818,46.5067],"type":"Point"}
}