{
  "type": "Feature",
  "properties": {
    "gn:admin1_code":"4.0",
    "gn:asciiname":"Levadky",
    "gn:country_code":"UA",
    "gn:dem":71,
    "gn:feature_class":"P",
    "gn:feature_code":"PPL",
    "gn:name":"Levadky",
    "gn:population":0,
    "gn:timezone":"Europe/Kiev",
    "iso:country":"UA",
    "name:ukr_x_preferred":[
        "Levadky"
    ],
    "name:ukr_x_variant":[
        "\u041b\u0435\u0432\u0430\u0434\u043a\u0438"
    ],
    "name:und_x_variant":[
        "Levadki"
    ],
    "wof:name":"Levadky",
    "wof:placetype":"locality"
},
  "geometry": {"coordinates":[35.97284000000001,48.3937],"type":"Point"}
}