{
  "type": "Feature",
  "properties": {
    "gn:admin1_code":"21.0",
    "gn:asciiname":"Notariusivka",
    "gn:country_code":"UA",
    "gn:dem":154,
    "gn:feature_class":"P",
    "gn:feature_code":"PPL",
    "gn:name":"Notariusivka",
    "gn:population":0,
    "gn:timezone":"Europe/Kiev",
    "iso:country":"UA",
    "name:ukr_x_preferred":[
        "Notariusivka"
    ],
    "name:ukr_x_variant":[
        "\u041d\u043e\u0442\u0430\u0440\u0456\u0443\u0441\u0456\u0432\u043a\u0430"
    ],
    "name:und_x_variant":[
        "Notariusovka"
    ],
    "wof:name":"Notariusivka",
    "wof:placetype":"locality"
},
  "geometry": {"coordinates":[33.78699,51.0637],"type":"Point"}
}