{
  "type": "Feature",
  "properties": {
    "gn:admin1_code":"27.0",
    "gn:asciiname":"Khutor Zaveshnya",
    "gn:country_code":"UA",
    "gn:dem":185,
    "gn:feature_class":"P",
    "gn:feature_code":"PPL",
    "gn:name":"Khutor Zaveshnya",
    "gn:population":0,
    "gn:timezone":"Europe/Kiev",
    "iso:country":"UA",
    "wof:name":"Khutor Zaveshnya",
    "wof:placetype":"locality"
},
  "geometry": {"coordinates":[27.56667,51.31667],"type":"Point"}
}