{
  "type": "Feature",
  "properties": {
    "gn:admin1_code":"4.0",
    "gn:asciiname":"Vodyane",
    "gn:country_code":"UA",
    "gn:dem":118,
    "gn:feature_class":"P",
    "gn:feature_code":"PPL",
    "gn:name":"Vodyane",
    "gn:population":0,
    "gn:timezone":"Europe/Kiev",
    "iso:country":"UA",
    "name:eng_x_preferred":[
        "Vodyanov"
    ],
    "name:rus_x_preferred":[
        "\u0412\u043e\u0434\u044f\u043d\u043e\u0435"
    ],
    "name:ukr_x_preferred":[
        "Vodyane"
    ],
    "name:ukr_x_variant":[
        "\u0412\u043e\u0434\u044f\u043d\u0435"
    ],
    "name:und_x_variant":[
        "Vodyany",
        "Vodyano",
        "Vodyanov",
        "Vodyanoye"
    ],
    "wof:name":"Vodyane",
    "wof:placetype":"locality"
},
  "geometry": {"coordinates":[35.89493,48.74526],"type":"Point"}
}