{
  "type": "Feature",
  "properties": {
    "gn:population":7980,
    "iso:country":"UA",
    "name:ara_x_preferred":[
        "\u062f\u064a\u0644\u064a\u0627\u062a\u064a\u0646"
    ],
    "name:bel_x_preferred":[
        "\u0414\u044d\u043b\u044f\u0442\u044b\u043d"
    ],
    "name:ceb_x_preferred":[
        "Delyatyn"
    ],
    "name:crh_x_preferred":[
        "Del\u00e2t\u0131n"
    ],
    "name:deu_x_preferred":[
        "Deljatyn"
    ],
    "name:eng_x_preferred":[
        "Deliatyn"
    ],
    "name:fra_x_preferred":[
        "Deliatyn"
    ],
    "name:heb_x_preferred":[
        "\u05d3\u05dc\u05d0\u05d8\u05d9\u05df"
    ],
    "name:hun_x_preferred":[
        "Deljatin"
    ],
    "name:pol_x_preferred":[
        "Delatyn"
    ],
    "name:ron_x_preferred":[
        "Deleat\u00een"
    ],
    "name:rus_x_preferred":[
        "\u0414\u0435\u043b\u044f\u0442\u0438\u043d"
    ],
    "name:swe_x_preferred":[
        "Deljatyn"
    ],
    "name:szl_x_preferred":[
        "Delatyn"
    ],
    "name:ukr_x_preferred":[
        "\u0414\u0435\u043b\u044f\u0442\u0438\u043d"
    ],
    "name:yid_x_preferred":[
        "\u05d3\u05e2\u05dc\u05d0\u05d8\u05d9\u05df"
    ],
    "name:zho_x_preferred":[
        "\u5091\u5229\u4e9e\u4eac"
    ],
    "qs:a0":"\u0423\u043a\u0440\u0430\u0457\u043d\u0430",
    "qs:a1":"*\u0406\u0432\u0430\u043d\u043e-\u0424\u0440\u0430\u043d\u043a\u0456\u0432\u0441\u044c\u043a\u0430",
    "qs:a1_alt":"Ivano-Frankivs'ka",
    "qs:a1r":"0",
    "qs:a2":"\u041d\u0430\u0434\u0432\u0456\u0440\u043d\u044f\u043d\u0441\u044c\u043a\u0438\u0439",
    "qs:a2_alt":"Nadvirnians'kyi",
    "qs:adm0":"\u0423\u043a\u0440\u0430\u0457\u043d\u0430",
    "qs:la_lc":"*",
    "qs:level":"locality",
    "qs:loc":"\u0414\u0435\u043b\u044f\u0442\u0438\u043d",
    "qs:loc_alt":"Deliatyn",
    "qs:pop":0,
    "qs:type":"buffered point",
    "wd:wordcount":422,
    "wof:name":"\u0414\u0435\u043b\u044f\u0442\u0438\u043d",
    "wof:placetype":"locality",
    "wof:population":7980
},
  "geometry": {"coordinates":[24.623716,48.524573],"type":"Point"}
}