{
  "type": "Feature",
  "properties": {
    "gn:admin1_code":"18.0",
    "gn:asciiname":"Konyusheve",
    "gn:country_code":"UA",
    "gn:dem":140,
    "gn:feature_class":"P",
    "gn:feature_code":"PPL",
    "gn:name":"Konyusheve",
    "gn:population":0,
    "gn:timezone":"Europe/Kiev",
    "iso:country":"UA",
    "name:ukr_x_preferred":[
        "Konyusheve"
    ],
    "name:ukr_x_variant":[
        "\u041a\u043e\u043d\u044e\u0448\u0435\u0432\u0435"
    ],
    "wof:name":"Konyusheve",
    "wof:placetype":"locality"
},
  "geometry": {"coordinates":[33.37969,49.9841],"type":"Point"}
}