{
  "type": "Feature",
  "properties": {
    "gn:admin1_code":"15.0",
    "gn:asciiname":"Iosipovka",
    "gn:country_code":"UA",
    "gn:dem":232,
    "gn:feature_class":"P",
    "gn:feature_code":"PPL",
    "gn:name":"Iosipovka",
    "gn:population":0,
    "gn:timezone":"Europe/Kiev",
    "iso:country":"UA",
    "name:und_x_variant":[
        "Yushkovitse",
        "Iosipovka"
    ],
    "wof:name":"Iosipovka",
    "wof:placetype":"locality"
},
  "geometry": {"coordinates":[24.86047,49.96931],"type":"Point"}
}