{
  "type": "Feature",
  "properties": {
    "gn:admin1_code":"27.0",
    "gn:asciiname":"Velyki Moshky",
    "gn:country_code":"UA",
    "gn:dem":143,
    "gn:feature_class":"P",
    "gn:feature_code":"PPL",
    "gn:name":"Velyki Moshky",
    "gn:population":0,
    "gn:timezone":"Europe/Kiev",
    "iso:country":"UA",
    "name:ukr_x_preferred":[
        "Velyki Moshky"
    ],
    "name:ukr_x_variant":[
        "\u0412\u0435\u043b\u0438\u043a\u0456 \u041c\u043e\u0448\u043a\u0438"
    ],
    "name:und_x_variant":[
        "Bol\u2019shiye Moshki",
        "Velikiye Moshki"
    ],
    "wof:name":"Velyki Moshky",
    "wof:placetype":"locality"
},
  "geometry": {"coordinates":[28.86836,51.26457],"type":"Point"}
}