{
  "type": "Feature",
  "properties": {
    "gn:admin1_code":"7.0",
    "gn:asciiname":"Vasylivka",
    "gn:country_code":"UA",
    "gn:dem":97,
    "gn:feature_class":"P",
    "gn:feature_code":"PPL",
    "gn:name":"Vasylivka",
    "gn:population":0,
    "gn:timezone":"Europe/Kiev",
    "iso:country":"UA",
    "name:ara_x_preferred":[
        "\u0641\u0627\u0633\u064a\u0644\u064a\u0641\u0643\u0627"
    ],
    "name:bel_x_preferred":[
        "\u0412\u0430\u0441\u044b\u043b\u0456\u045e\u043a\u0430"
    ],
    "name:bul_x_preferred":[
        "\u0412\u0430\u0441\u0438\u043b\u0438\u0432\u043a\u0430"
    ],
    "name:ceb_x_preferred":[
        "Vasylivka"
    ],
    "name:ces_x_preferred":[
        "Vasylivka"
    ],
    "name:crh_x_preferred":[
        "Vas\u0131livka"
    ],
    "name:deu_x_preferred":[
        "Wassyliwka"
    ],
    "name:est_x_preferred":[
        "Vass\u00f5livka"
    ],
    "name:fas_x_preferred":[
        "\u0648\u0627\u0633\u06cc\u0644\u06cc\u0641\u06a9\u0627"
    ],
    "name:fra_x_preferred":[
        "Vassylivka"
    ],
    "name:hsb_x_preferred":[
        "Wasyliwka"
    ],
    "name:hye_x_preferred":[
        "\u054e\u0561\u057d\u056b\u056c\u056b\u0587\u056f\u0561"
    ],
    "name:ita_x_preferred":[
        "Vasylivka"
    ],
    "name:kat_x_preferred":[
        "\u10d5\u10d0\u10e1\u10d8\u10da\u10d8\u10d4\u10d5\u10d9\u10d0"
    ],
    "name:lit_x_preferred":[
        "Vasylivka"
    ],
    "name:nno_x_preferred":[
        "Vasylivka"
    ],
    "name:pol_x_preferred":[
        "Wasyliwka"
    ],
    "name:ron_x_preferred":[
        "Vas\u00eelivka"
    ],
    "name:rus_x_preferred":[
        "\u0412\u0430\u0441\u0438\u043b\u044c\u0435\u0432\u043a\u0430"
    ],
    "name:ukr_x_preferred":[
        "Vasylivka"
    ],
    "name:ukr_x_variant":[
        "\u0412\u0430\u0441\u0438\u043b\u0456\u0432\u043a\u0430"
    ],
    "name:vie_x_preferred":[
        "Vasylivka"
    ],
    "name:zho_x_preferred":[
        "\u74e6\u897f\u5229\u592b\u5361"
    ],
    "wof:name":"Vasylivka",
    "wof:placetype":"locality"
},
  "geometry": {"coordinates":[37.50429000000001,49.66336],"type":"Point"}
}