{
  "type": "Feature",
  "properties": {
    "gn:admin1_code":"19.0",
    "gn:asciiname":"Zarits'k",
    "gn:country_code":"UA",
    "gn:dem":191,
    "gn:feature_class":"P",
    "gn:feature_code":"PPL",
    "gn:name":"Zarits\u2019k",
    "gn:population":0,
    "gn:timezone":"Europe/Kiev",
    "iso:country":"UA",
    "name:ukr_x_preferred":[
        "Zarits\u2019k"
    ],
    "name:ukr_x_variant":[
        "\u0417\u0430\u0440\u0456\u0446\u044c\u043a"
    ],
    "name:und_x_variant":[
        "Zaretsk"
    ],
    "wof:name":"Zarits'k",
    "wof:placetype":"locality"
},
  "geometry": {"coordinates":[25.92004,50.60941],"type":"Point"}
}