{
  "type": "Feature",
  "properties": {
    "gn:admin1_code":"7.0",
    "gn:asciiname":"Pan'kovka",
    "gn:country_code":"UA",
    "gn:dem":146,
    "gn:feature_class":"P",
    "gn:feature_code":"PPL",
    "gn:name":"Pan\u2019kovka",
    "gn:population":0,
    "gn:timezone":"Europe/Kiev",
    "iso:country":"UA",
    "wof:name":"Pan'kovka",
    "wof:placetype":"locality"
},
  "geometry": {"coordinates":[35.81667,49.83333],"type":"Point"}
}