{
  "type": "Feature",
  "properties": {
    "gn:admin1_code":"7.0",
    "gn:asciiname":"Lyashovka",
    "gn:country_code":"UA",
    "gn:dem":184,
    "gn:feature_class":"P",
    "gn:feature_code":"PPL",
    "gn:name":"Lyashovka",
    "gn:population":0,
    "gn:timezone":"Europe/Kiev",
    "iso:country":"UA",
    "name:rus_x_preferred":[
        "\u041b\u044f\u0448\u043e\u0432\u043a\u0430"
    ],
    "name:und_x_variant":[
        "Khutor Lyashova",
        "Lyakhovki",
        "Lyashovka"
    ],
    "wof:name":"Lyashovka",
    "wof:placetype":"locality"
},
  "geometry": {"coordinates":[35.7003,49.67402],"type":"Point"}
}