{
  "type": "Feature",
  "properties": {
    "gn:admin1_code":"6.0",
    "gn:asciiname":"Khotimir",
    "gn:country_code":"UA",
    "gn:dem":262,
    "gn:feature_class":"P",
    "gn:feature_code":"PPL",
    "gn:name":"Khotimir",
    "gn:population":0,
    "gn:timezone":"Europe/Kiev",
    "iso:country":"UA",
    "name:und_x_variant":[
        "Khotsimezh",
        "Khotimir"
    ],
    "wof:name":"Khotimir",
    "wof:placetype":"locality"
},
  "geometry": {"coordinates":[25.10627,48.75697],"type":"Point"}
}