{
  "type": "Feature",
  "properties": {
    "gn:admin1_code":"15.0",
    "gn:asciiname":"Lindenau",
    "gn:country_code":"UA",
    "gn:dem":224,
    "gn:feature_class":"P",
    "gn:feature_code":"PPL",
    "gn:name":"Lindenau",
    "gn:population":0,
    "gn:timezone":"Europe/Kiev",
    "iso:country":"UA",
    "name:ceb_x_preferred":[
        "Lindenau"
    ],
    "name:dan_x_preferred":[
        "Lindenau"
    ],
    "name:deu_x_preferred":[
        "Lindenau"
    ],
    "name:fra_x_preferred":[
        "Lindenau"
    ],
    "name:pol_x_preferred":[
        "Lindenau"
    ],
    "name:rus_x_preferred":[
        "\u041b\u0438\u043d\u0434\u0435\u043d\u0430\u0443"
    ],
    "name:swe_x_preferred":[
        "Lindenau"
    ],
    "wof:name":"Lindenau",
    "wof:placetype":"locality"
},
  "geometry": {"coordinates":[23.25,50.03333],"type":"Point"}
}