{
  "type": "Feature",
  "properties": {
    "gn:admin1_code":"11.0",
    "gn:admin2_code":"712585",
    "gn:admin3_code":"11152831",
    "gn:asciiname":"Zemlyanichnoye",
    "gn:country_code":"UA",
    "gn:dem":330,
    "gn:elevation":"330.0",
    "gn:feature_class":"P",
    "gn:feature_code":"PPLA3",
    "gn:name":"Zemlyanichnoye",
    "gn:population":660,
    "gn:timezone":"Europe/Simferopol",
    "iso:country":"UA",
    "name:eng_x_preferred":[
        "Zemlyanichnoye"
    ],
    "name:rus_x_historical":[
        "\u041e\u0440\u0442\u0430\u043b\u0430\u0301\u043d"
    ],
    "name:rus_x_preferred":[
        "\u0417\u0435\u043c\u043b\u044f\u043d\u0438\u0447\u043d\u043e\u0435"
    ],
    "name:rus_x_variant":[
        "\u041e\u0440\u0442\u0430\u043b\u0430\u0301\u043d"
    ],
    "name:ukr_x_preferred":[
        "\u0417\u0435\u043c\u043b\u044f\u043d\u0438\u0447\u043d\u0435"
    ],
    "wof:name":"Zemlyanichnoye",
    "wof:placetype":"locality",
    "wof:population":660
},
  "geometry": {"coordinates":[34.83553,44.97444],"type":"Point"}
}