{
  "type": "Feature",
  "properties": {
    "gn:admin1_code":"4.0",
    "gn:asciiname":"Uspenivka",
    "gn:country_code":"UA",
    "gn:dem":155,
    "gn:feature_class":"P",
    "gn:feature_code":"PPL",
    "gn:name":"Uspenivka",
    "gn:population":0,
    "gn:timezone":"Europe/Kiev",
    "iso:country":"UA",
    "name:ukr_x_preferred":[
        "Uspenivka"
    ],
    "name:ukr_x_variant":[
        "\u0423\u0441\u043f\u0435\u043d\u0456\u0432\u043a\u0430"
    ],
    "name:und_x_variant":[
        "Uspenovka"
    ],
    "wof:name":"Uspenivka",
    "wof:placetype":"locality"
},
  "geometry": {"coordinates":[36.63578,48.55135],"type":"Point"}
}