{
  "type": "Feature",
  "properties": {
    "gn:admin1_code":"19.0",
    "gn:asciiname":"Smykiv",
    "gn:country_code":"UA",
    "gn:dem":209,
    "gn:feature_class":"P",
    "gn:feature_code":"PPL",
    "gn:name":"Smykiv",
    "gn:population":0,
    "gn:timezone":"Europe/Kiev",
    "iso:country":"UA",
    "name:ukr_x_preferred":[
        "Smykiv"
    ],
    "name:ukr_x_variant":[
        "\u0421\u043c\u0438\u043a\u0456\u0432"
    ],
    "name:und_x_variant":[
        "Smykov"
    ],
    "wof:name":"Smykiv",
    "wof:placetype":"locality"
},
  "geometry": {"coordinates":[25.16482,50.46103],"type":"Point"}
}