{
  "type": "Feature",
  "properties": {
    "gn:admin1_code":"27.0",
    "gn:asciiname":"Kovalenky",
    "gn:country_code":"UA",
    "gn:dem":254,
    "gn:feature_class":"P",
    "gn:feature_code":"PPL",
    "gn:name":"Kovalenky",
    "gn:population":0,
    "gn:timezone":"Europe/Kiev",
    "iso:country":"UA",
    "name:ukr_x_preferred":[
        "Kovalenky"
    ],
    "name:ukr_x_variant":[
        "\u041a\u043e\u0432\u0430\u043b\u0435\u043d\u043a\u0443"
    ],
    "name:und_x_variant":[
        "Koval\u00ebnki"
    ],
    "wof:name":"Kovalenky",
    "wof:placetype":"locality"
},
  "geometry": {"coordinates":[27.90813,49.8976],"type":"Point"}
}