{
  "type": "Feature",
  "properties": {
    "gn:admin1_code":"6.0",
    "gn:asciiname":"Tatariv",
    "gn:country_code":"UA",
    "gn:dem":686,
    "gn:feature_class":"P",
    "gn:feature_code":"PPL",
    "gn:name":"Tatariv",
    "gn:population":0,
    "gn:timezone":"Europe/Kiev",
    "iso:country":"UA",
    "name:rus_x_preferred":[
        "\u0422\u0430\u0442\u0430\u0440\u043e\u0432"
    ],
    "name:ukr_x_preferred":[
        "\u0422\u0430\u0442\u0430\u0440\u0456\u0432"
    ],
    "wof:name":"Tatariv",
    "wof:placetype":"locality"
},
  "geometry": {"coordinates":[24.57427,48.34089],"type":"Point"}
}