{
  "type": "Feature",
  "properties": {
    "gn:admin1_code":"27.0",
    "gn:asciiname":"Malyy Brataliv",
    "gn:country_code":"UA",
    "gn:dem":251,
    "gn:feature_class":"P",
    "gn:feature_code":"PPL",
    "gn:name":"Malyy Brataliv",
    "gn:population":0,
    "gn:timezone":"Europe/Kiev",
    "iso:country":"UA",
    "name:ukr_x_preferred":[
        "Malyy Brataliv"
    ],
    "name:ukr_x_variant":[
        "\u041c\u0430\u043b\u0438\u0439 \u0411\u0440\u0430\u0442\u0430\u043b\u0456\u0432"
    ],
    "name:und_x_variant":[
        "Maly Bratalov",
        "Malyy Bratalov"
    ],
    "wof:name":"Malyy Brataliv",
    "wof:placetype":"locality"
},
  "geometry": {"coordinates":[27.79688,49.86085],"type":"Point"}
}