{
  "type": "Feature",
  "properties": {
    "gn:admin1_code":"27.0",
    "gn:asciiname":"Sonyachne",
    "gn:country_code":"UA",
    "gn:dem":219,
    "gn:feature_class":"P",
    "gn:feature_code":"PPL",
    "gn:name":"Sonyachne",
    "gn:population":0,
    "gn:timezone":"Europe/Kiev",
    "iso:country":"UA",
    "name:ukr_x_preferred":[
        "Sonyachne"
    ],
    "name:ukr_x_variant":[
        "\u0421\u043e\u043d\u044f\u0447\u043d\u0435"
    ],
    "name:und_x_variant":[
        "Andreyevka",
        "Andriivka",
        "Solnechnoye"
    ],
    "wof:name":"Sonyachne",
    "wof:placetype":"locality"
},
  "geometry": {"coordinates":[28.64263,50.31621],"type":"Point"}
}