{
  "type": "Feature",
  "properties": {
    "gn:admin1_code":"3.0",
    "gn:asciiname":"Mega",
    "gn:country_code":"UA",
    "gn:dem":447,
    "gn:feature_class":"P",
    "gn:feature_code":"PPL",
    "gn:name":"Mega",
    "gn:population":0,
    "gn:timezone":"Europe/Kiev",
    "iso:country":"UA",
    "name:cat_x_preferred":[
        "Mega"
    ],
    "name:ceb_x_preferred":[
        "Mega"
    ],
    "name:deu_x_preferred":[
        "Mega"
    ],
    "name:est_x_preferred":[
        "Mega"
    ],
    "name:fas_x_preferred":[
        "\u0645\u06af\u0627"
    ],
    "name:fin_x_preferred":[
        "Mega"
    ],
    "name:fra_x_preferred":[
        "Mega"
    ],
    "name:glg_x_preferred":[
        "Mega"
    ],
    "name:ind_x_preferred":[
        "Mega"
    ],
    "name:ita_x_preferred":[
        "Mega"
    ],
    "name:jpn_x_preferred":[
        "Mega"
    ],
    "name:kor_x_preferred":[
        "\uba54\uac00"
    ],
    "name:nld_x_preferred":[
        "Mega"
    ],
    "name:por_x_preferred":[
        "Mega"
    ],
    "name:ron_x_preferred":[
        "Mega"
    ],
    "name:rus_x_preferred":[
        "\u041c\u0435\u0433\u0430"
    ],
    "name:spa_x_preferred":[
        "Mega"
    ],
    "name:swe_x_preferred":[
        "Mega"
    ],
    "name:ukr_x_preferred":[
        "\u041c\u0435\u0433\u0430"
    ],
    "name:vie_x_preferred":[
        "Mega"
    ],
    "wof:name":"Mega",
    "wof:placetype":"locality"
},
  "geometry": {"coordinates":[25.43333,48.13333],"type":"Point"}
}