{
  "type": "Feature",
  "properties": {
    "gn:admin1_code":"18.0",
    "gn:asciiname":"Mushty",
    "gn:country_code":"UA",
    "gn:dem":94,
    "gn:feature_class":"P",
    "gn:feature_code":"PPL",
    "gn:name":"Mushty",
    "gn:population":0,
    "gn:timezone":"Europe/Kiev",
    "iso:country":"UA",
    "name:eng_x_preferred":[
        "Mushty"
    ],
    "name:rus_x_preferred":[
        "\u041c\u0443\u0448\u0442\u044b"
    ],
    "name:ukr_x_preferred":[
        "\u041c\u0443\u0448\u0442\u0438"
    ],
    "wof:name":"Mushty",
    "wof:placetype":"locality"
},
  "geometry": {"coordinates":[33.87475999999999,49.61675],"type":"Point"}
}