{
  "type": "Feature",
  "properties": {
    "gn:admin1_code":"14.0",
    "gn:asciiname":"Rayhorodka",
    "gn:country_code":"UA",
    "gn:dem":108,
    "gn:feature_class":"P",
    "gn:feature_code":"PPL",
    "gn:name":"Rayhorodka",
    "gn:population":0,
    "gn:timezone":"Europe/Zaporozhye",
    "iso:country":"UA",
    "name:ukr_x_preferred":[
        "Rayhorodka"
    ],
    "name:und_x_variant":[
        "Raygorodskoye",
        "Raygorodka"
    ],
    "wof:name":"Rayhorodka",
    "wof:placetype":"locality"
},
  "geometry": {"coordinates":[37.95972,49.37944],"type":"Point"}
}