{
  "type": "Feature",
  "properties": {
    "gn:admin1_code":"21.0",
    "gn:asciiname":"Malyy Bobryk",
    "gn:country_code":"UA",
    "gn:dem":180,
    "gn:feature_class":"P",
    "gn:feature_code":"PPL",
    "gn:name":"Malyy Bobryk",
    "gn:population":0,
    "gn:timezone":"Europe/Kiev",
    "iso:country":"UA",
    "name:ukr_x_preferred":[
        "Malyy Bobryk"
    ],
    "name:ukr_x_variant":[
        "\u041c\u0430\u043b\u0438\u0439 \u0411\u043e\u0431\u0440\u0438\u043a"
    ],
    "name:und_x_variant":[
        "Malyy Bobrik"
    ],
    "wof:name":"Malyy Bobryk",
    "wof:placetype":"locality"
},
  "geometry": {"coordinates":[35.07926,50.73894],"type":"Point"}
}