{
  "type": "Feature",
  "properties": {
    "gn:admin1_code":"14.0",
    "gn:asciiname":"Khvorostyanivka",
    "gn:country_code":"UA",
    "gn:dem":56,
    "gn:feature_class":"P",
    "gn:feature_code":"PPL",
    "gn:name":"Khvorostyanivka",
    "gn:population":0,
    "gn:timezone":"Europe/Zaporozhye",
    "iso:country":"UA",
    "name:ukr_x_preferred":[
        "Khvorostyanivka"
    ],
    "name:und_x_variant":[
        "Khvorostyanovka"
    ],
    "wof:name":"Khvorostyanivka",
    "wof:placetype":"locality"
},
  "geometry": {"coordinates":[38.88212,49.13753],"type":"Point"}
}