{
  "type": "Feature",
  "properties": {
    "iso:country":"UA",
    "name:und_x_variant":[
        "Dubrivka"
    ],
    "qs:a0":"\u0423\u043a\u0440\u0430\u0457\u043d\u0430",
    "qs:a1":"*\u041a\u0438\u0457\u0432\u0441\u044c\u043a\u0430",
    "qs:a1_alt":"Kyivs'ka",
    "qs:a1r":"0",
    "qs:a2":"\u0422\u0435\u0442\u0456\u0457\u0432\u0441\u044c\u043a\u0438\u0439",
    "qs:a2_alt":"Tetiivs'kyi",
    "qs:adm0":"\u0423\u043a\u0440\u0430\u0457\u043d\u0430",
    "qs:la_lc":"*",
    "qs:level":"locality",
    "qs:loc":"\u0414\u0456\u0431\u0440\u0456\u0432\u043a\u0430",
    "qs:loc_alt":"Dibrivka",
    "qs:pop":0,
    "qs:type":"buffered point",
    "wd:wordcount":60,
    "wof:name":"\u0414\u0456\u0431\u0440\u0456\u0432\u043a\u0430",
    "wof:placetype":"locality"
},
  "geometry": {"coordinates":[29.770536,49.317694],"type":"Point"}
}