{
  "type": "Feature",
  "properties": {
    "gn:admin1_code":"7.0",
    "gn:asciiname":"Khrushchova Mykytivka",
    "gn:country_code":"UA",
    "gn:dem":138,
    "gn:feature_class":"P",
    "gn:feature_code":"PPL",
    "gn:name":"Khrushchova Mykytivka",
    "gn:population":0,
    "gn:timezone":"Europe/Kiev",
    "iso:country":"UA",
    "name:ukr_x_preferred":[
        "Khrushchova Mykytivka"
    ],
    "name:ukr_x_variant":[
        "\u0425\u0440\u0443\u0449\u043e\u0432\u0430 \u041c\u0438\u043a\u0438\u0442\u0456\u0432\u043a\u0430"
    ],
    "name:und_x_variant":[
        "Nikitovka",
        "Krushch\u00ebvaya Nikitovka"
    ],
    "wof:name":"Khrushchova Mykytivka",
    "wof:placetype":"locality"
},
  "geometry": {"coordinates":[35.48969,50.0576],"type":"Point"}
}