{
  "type": "Feature",
  "properties": {
    "gn:admin1_code":"18.0",
    "gn:asciiname":"Shramky",
    "gn:country_code":"UA",
    "gn:dem":128,
    "gn:feature_class":"P",
    "gn:feature_code":"PPL",
    "gn:name":"Shramky",
    "gn:population":0,
    "gn:timezone":"Europe/Kiev",
    "iso:country":"UA",
    "name:ukr_x_preferred":[
        "Shramky"
    ],
    "name:ukr_x_variant":[
        "\u0428\u0440\u0430\u043c\u043a\u0438"
    ],
    "wof:name":"Shramky",
    "wof:placetype":"locality"
},
  "geometry": {"coordinates":[33.9992,49.54381],"type":"Point"}
}