{
  "type": "Feature",
  "properties": {
    "gn:admin1_code":"9.0",
    "gn:asciiname":"Krasnoselki",
    "gn:country_code":"UA",
    "gn:dem":316,
    "gn:feature_class":"P",
    "gn:feature_code":"PPL",
    "gn:name":"Krasnos\u00eblki",
    "gn:population":0,
    "gn:timezone":"Europe/Kiev",
    "iso:country":"UA",
    "wof:name":"Krasnoselki",
    "wof:placetype":"locality"
},
  "geometry": {"coordinates":[27.2692,49.26209],"type":"Point"}
}