{
  "type": "Feature",
  "properties": {
    "gn:admin1_code":"17.0",
    "gn:asciiname":"Khutor Veselyy",
    "gn:cc2":"UA",
    "gn:country_code":"UA",
    "gn:dem":43,
    "gn:feature_class":"P",
    "gn:feature_code":"PPL",
    "gn:name":"Khutor Ves\u00eblyy",
    "gn:population":0,
    "gn:timezone":"Europe/Kiev",
    "iso:country":"UA",
    "name:und_x_variant":[
        "Veselyy"
    ],
    "wof:name":"Khutor Veselyy",
    "wof:placetype":"locality"
},
  "geometry": {"coordinates":[29.83333,47.18333],"type":"Point"}
}