{
  "type": "Feature",
  "properties": {
    "gn:admin1_code":"23.0",
    "gn:asciiname":"Obukhov",
    "gn:country_code":"UA",
    "gn:dem":284,
    "gn:feature_class":"P",
    "gn:feature_code":"PPL",
    "gn:name":"Obukhov",
    "gn:population":0,
    "gn:timezone":"Europe/Kiev",
    "iso:country":"UA",
    "name:und_x_variant":[
        "Obuchovo",
        "Obukhovo",
        "Obukhov"
    ],
    "wof:name":"Obukhov",
    "wof:placetype":"locality"
},
  "geometry": {"coordinates":[27.76457000000001,48.79693],"type":"Point"}
}