{
  "type": "Feature",
  "properties": {
    "gn:admin1_code":"6.0",
    "gn:asciiname":"Letsivka",
    "gn:country_code":"UA",
    "gn:dem":524,
    "gn:feature_class":"P",
    "gn:feature_code":"PPL",
    "gn:name":"Letsivka",
    "gn:population":0,
    "gn:timezone":"Europe/Kiev",
    "iso:country":"UA",
    "name:ukr_x_preferred":[
        "Letsivka"
    ],
    "name:ukr_x_variant":[
        "\u041b\u0435\u0446\u0456\u0432\u043a\u0430"
    ],
    "name:und_x_variant":[
        "Letovka",
        "Letsuvka",
        "Letsovka"
    ],
    "wof:name":"Letsivka",
    "wof:placetype":"locality"
},
  "geometry": {"coordinates":[24.10976,48.82309],"type":"Point"}
}