{
  "type": "Feature",
  "properties": {
    "gn:admin1_code":"27.0",
    "gn:asciiname":"Ivankivtsi",
    "gn:country_code":"UA",
    "gn:dem":277,
    "gn:feature_class":"P",
    "gn:feature_code":"PPL",
    "gn:name":"Ivankivtsi",
    "gn:population":0,
    "gn:timezone":"Europe/Kiev",
    "iso:country":"UA",
    "name:ukr_x_preferred":[
        "Ivankivtsi"
    ],
    "name:ukr_x_variant":[
        "\u0406\u0432\u0430\u043d\u043a\u0456\u0432\u0446\u0456"
    ],
    "name:und_x_variant":[
        "Ivankovtsy"
    ],
    "wof:name":"Ivankivtsi",
    "wof:placetype":"locality"
},
  "geometry": {"coordinates":[28.67789,49.84671],"type":"Point"}
}