{
  "type": "Feature",
  "properties": {
    "iso:country":"UA",
    "qs:a0":"\u0423\u043a\u0440\u0430\u0457\u043d\u0430",
    "qs:a1":"*\u041f\u043e\u043b\u0442\u0430\u0432\u0441\u044c\u043a\u0430",
    "qs:a1_alt":"Poltavs'ka",
    "qs:a1r":"0",
    "qs:a2":"\u041f\u043e\u043b\u0442\u0430\u0432\u0441\u044c\u043a\u0438\u0439",
    "qs:a2_alt":"Poltavs'kyi",
    "qs:adm0":"\u0423\u043a\u0440\u0430\u0457\u043d\u0430",
    "qs:la_lc":"*",
    "qs:level":"locality",
    "qs:loc":"\u0411\u043e\u0436\u043a\u0456\u0432\u0441\u044c\u043a\u0435",
    "qs:loc_alt":"Bozhkivs'ke",
    "qs:pop":0,
    "qs:type":"buffered point",
    "wof:name":"\u0411\u043e\u0436\u043a\u0456\u0432\u0441\u044c\u043a\u0435",
    "wof:placetype":"locality"
},
  "geometry": {"coordinates":[34.757242,49.67362],"type":"Point"}
}