{
  "type": "Feature",
  "properties": {
    "gn:admin1_code":"21.0",
    "gn:asciiname":"Bardanovka",
    "gn:cc2":"UA",
    "gn:country_code":"UA",
    "gn:dem":126,
    "gn:feature_class":"P",
    "gn:feature_code":"PPL",
    "gn:name":"Bardanovka",
    "gn:population":0,
    "gn:timezone":"Europe/Kiev",
    "iso:country":"UA",
    "name:und_x_variant":[
        "Bardakov",
        "Bardanovka"
    ],
    "wof:name":"Bardanovka",
    "wof:placetype":"locality"
},
  "geometry": {"coordinates":[34.63333,50.41667],"type":"Point"}
}