{
  "type": "Feature",
  "properties": {
    "iso:country":"UA",
    "name:eng_x_preferred":[
        "Medvyn"
    ],
    "name:pol_x_preferred":[
        "Medwin"
    ],
    "name:rus_x_preferred":[
        "\u041c\u0435\u0434\u0432\u0438\u043d"
    ],
    "name:ukr_x_preferred":[
        "\u041c\u0435\u0434\u0432\u0438\u043d"
    ],
    "name:unk_x_variant":[
        "Medvin"
    ],
    "qs:a0":"\u0423\u043a\u0440\u0430\u0457\u043d\u0430",
    "qs:a1":"*\u041a\u0438\u0457\u0432\u0441\u044c\u043a\u0430",
    "qs:a1_alt":"Kyivs'ka",
    "qs:a1r":"0",
    "qs:a2":"\u0411\u043e\u0433\u0443\u0441\u043b\u0430\u0432\u0441\u044c\u043a\u0438\u0439",
    "qs:a2_alt":"Bohuslavs'kyi",
    "qs:adm0":"\u0423\u043a\u0440\u0430\u0457\u043d\u0430",
    "qs:la_lc":"*",
    "qs:level":"locality",
    "qs:loc":"\u041c\u0435\u0434\u0432\u0438\u043d",
    "qs:loc_alt":"Medvyn",
    "qs:pop":0,
    "qs:type":"buffered point",
    "wd:wordcount":359,
    "wof:name":"\u041c\u0435\u0434\u0432\u0438\u043d",
    "wof:placetype":"locality"
},
  "geometry": {"coordinates":[30.781239,49.38527],"type":"Point"}
}