{
  "type": "Feature",
  "properties": {
    "gn:admin1_code":"2.0",
    "gn:asciiname":"Sokhachi",
    "gn:country_code":"UA",
    "gn:dem":123,
    "gn:feature_class":"P",
    "gn:feature_code":"PPL",
    "gn:name":"Sokhachi",
    "gn:population":0,
    "gn:timezone":"Europe/Kiev",
    "iso:country":"UA",
    "name:ukr_x_preferred":[
        "Sokhachi"
    ],
    "name:ukr_x_variant":[
        "\u0421\u043e\u0445\u0430\u0447\u0456"
    ],
    "wof:name":"Sokhachi",
    "wof:placetype":"locality"
},
  "geometry": {"coordinates":[32.85327,51.55602],"type":"Point"}
}