{
  "type": "Feature",
  "properties": {
    "iso:country":"UA",
    "name:bel_x_variant":[
        "\u041c\u0435\u043b\u0430\u0432\u0430\u0435"
    ],
    "name:ces_x_preferred":[
        "Milove"
    ],
    "name:chi_x_preferred":[
        "\u7c73\u6d1b\u97cb"
    ],
    "name:crh_x_preferred":[
        "Milove"
    ],
    "name:cze_x_preferred":[
        "Milove"
    ],
    "name:deu_x_preferred":[
        "Milowe"
    ],
    "name:dut_x_preferred":[
        "Milove"
    ],
    "name:eng_x_preferred":[
        "Milove"
    ],
    "name:est_x_preferred":[
        "Milove"
    ],
    "name:fra_x_preferred":[
        "Milove"
    ],
    "name:fre_x_preferred":[
        "Milove"
    ],
    "name:ger_x_preferred":[
        "Milowe"
    ],
    "name:hun_x_preferred":[
        "Milove"
    ],
    "name:lav_x_preferred":[
        "Milove"
    ],
    "name:nld_x_preferred":[
        "Milove"
    ],
    "name:nob_x_preferred":[
        "Milove"
    ],
    "name:pol_x_preferred":[
        "Mi\u0142owe"
    ],
    "name:ron_x_preferred":[
        "Milove"
    ],
    "name:rum_x_preferred":[
        "Milove"
    ],
    "name:rus_x_preferred":[
        "\u041c\u0435\u043b\u043e\u0432\u043e\u0435"
    ],
    "name:rus_x_variant":[
        "\u041c\u0456\u043b\u043e\u0432\u0435"
    ],
    "name:ukr_x_preferred":[
        "\u041c\u0456\u043b\u043e\u0432\u0435"
    ],
    "name:unk_x_variant":[
        "Melovoy"
    ],
    "name:zho_x_preferred":[
        "\u7c73\u6d1b\u97cb"
    ],
    "qs:a0":"\u0423\u043a\u0440\u0430\u0457\u043d\u0430",
    "qs:a1":"*\u041b\u0443\u0433\u0430\u043d\u0441\u044c\u043a\u0430",
    "qs:a1_alt":"Luhans'ka",
    "qs:a1r":"0",
    "qs:a2":"\u041c\u0456\u043b\u043e\u0432\u0441\u044c\u043a\u0438\u0439",
    "qs:a2_alt":"Milovs'kyi",
    "qs:adm0":"\u0423\u043a\u0440\u0430\u0457\u043d\u0430",
    "qs:la_lc":"*",
    "qs:level":"locality",
    "qs:loc":"\u041c\u0456\u043b\u043e\u0432\u0435",
    "qs:loc_alt":"Milove",
    "qs:pop":0,
    "qs:type":"buffered point",
    "wd:wordcount":221,
    "wof:name":"\u041c\u0456\u043b\u043e\u0432\u0435",
    "wof:placetype":"locality"
},
  "geometry": {"coordinates":[40.134432,49.372112],"type":"Point"}
}