{
  "type": "Feature",
  "properties": {
    "gn:admin1_code":"25.0",
    "gn:asciiname":"Barvinok",
    "gn:country_code":"UA",
    "gn:dem":112,
    "gn:feature_class":"P",
    "gn:feature_code":"PPL",
    "gn:name":"Barvinok",
    "gn:population":0,
    "gn:timezone":"Europe/Uzhgorod",
    "iso:country":"UA",
    "name:ukr_x_preferred":[
        "Barvinok"
    ],
    "name:ukr_x_variant":[
        "\u0411\u0430\u0440\u0432\u0456\u043d\u043e\u043a"
    ],
    "name:und_x_variant":[
        "Barvinkosh"
    ],
    "wof:name":"Barvinok",
    "wof:placetype":"locality"
},
  "geometry": {"coordinates":[22.34957,48.56722],"type":"Point"}
}