{
  "type": "Feature",
  "properties": {
    "gn:admin1_code":"15.0",
    "gn:asciiname":"Novoshychi",
    "gn:country_code":"UA",
    "gn:dem":309,
    "gn:feature_class":"P",
    "gn:feature_code":"PPL",
    "gn:name":"Novoshychi",
    "gn:population":0,
    "gn:timezone":"Europe/Kiev",
    "iso:country":"UA",
    "name:pol_x_preferred":[
        "Nowoszyce"
    ],
    "name:ron_x_preferred":[
        "Novo\u0219\u00eeci"
    ],
    "name:rus_x_preferred":[
        "\u041d\u043e\u0432\u043e\u0448\u0438\u0447\u0438"
    ],
    "name:ukr_x_preferred":[
        "Novoshychi"
    ],
    "name:ukr_x_variant":[
        "\u041d\u043e\u0432\u043e\u0448\u0438\u0447\u0456"
    ],
    "name:und_x_variant":[
        "Novoshitsy",
        "Novoshitse",
        "Novoshichi"
    ],
    "name:zho_x_preferred":[
        "\u65b0\u4ec0\u5947"
    ],
    "wof:name":"Novoshychi",
    "wof:placetype":"locality"
},
  "geometry": {"coordinates":[23.42153,49.46603],"type":"Point"}
}