{
  "type": "Feature",
  "properties": {
    "gn:admin1_code":"25.0",
    "gn:asciiname":"Sasovo",
    "gn:country_code":"UA",
    "gn:dem":341,
    "gn:feature_class":"P",
    "gn:feature_code":"PPL",
    "gn:name":"Sasovo",
    "gn:population":0,
    "gn:timezone":"Europe/Uzhgorod",
    "iso:country":"UA",
    "name:ukr_x_preferred":[
        "\u0421\u0430\u0441\u043e\u0432\u043e"
    ],
    "name:ukr_x_variant":[
        "Sasovo"
    ],
    "name:und_x_variant":[
        "Sasovoye"
    ],
    "name:urd_x_preferred":[
        "\u0633\u0627\u0633\u0648\u0648"
    ],
    "wof:name":"Sasovo",
    "wof:placetype":"locality"
},
  "geometry": {"coordinates":[23.70161,48.09526],"type":"Point"}
}