{
  "type": "Feature",
  "properties": {
    "iso:country":"UA",
    "name:eng_x_preferred":[
        "Zubovka"
    ],
    "name:eng_x_variant":[
        "zubivka"
    ],
    "name:rus_x_preferred":[
        "\u0417\u0443\u0431\u043e\u0432\u043a\u0430"
    ],
    "name:ukr_x_preferred":[
        "Zubivka"
    ],
    "name:ukr_x_variant":[
        "\u0417\u0443\u0431\u0456\u0432\u043a\u0430"
    ],
    "qs:a0":"\u0423\u043a\u0440\u0430\u0457\u043d\u0430",
    "qs:a1":"*\u041f\u043e\u043b\u0442\u0430\u0432\u0441\u044c\u043a\u0430",
    "qs:a1_alt":"Poltavs'ka",
    "qs:a1r":"0",
    "qs:a2":"\u041c\u0438\u0440\u0433\u043e\u0440\u043e\u0434\u0441\u044c\u043a\u0438\u0439",
    "qs:a2_alt":"Myrhorods'kyi",
    "qs:adm0":"\u0423\u043a\u0440\u0430\u0457\u043d\u0430",
    "qs:la_lc":"*",
    "qs:level":"locality",
    "qs:loc":"\u0417\u0443\u0431\u0456\u0432\u043a\u0430",
    "qs:loc_alt":"Zubivka",
    "qs:pop":0,
    "qs:type":"buffered point",
    "wd:wordcount":163,
    "wof:name":"\u0417\u0443\u0431\u0456\u0432\u043a\u0430",
    "wof:placetype":"locality"
},
  "geometry": {"coordinates":[33.703548,50.013191],"type":"Point"}
}