{
  "type": "Feature",
  "properties": {
    "gn:admin1_code":"23.0",
    "gn:asciiname":"Ometintsy",
    "gn:country_code":"UA",
    "gn:dem":268,
    "gn:feature_class":"P",
    "gn:feature_code":"PPL",
    "gn:name":"Ometintsy",
    "gn:population":0,
    "gn:timezone":"Europe/Kiev",
    "iso:country":"UA",
    "wof:name":"Ometintsy",
    "wof:placetype":"locality"
},
  "geometry": {"coordinates":[29.1028,48.9651],"type":"Point"}
}