{
  "type": "Feature",
  "properties": {
    "gn:admin1_code":"7.0",
    "gn:asciiname":"Monachynivka",
    "gn:country_code":"UA",
    "gn:dem":151,
    "gn:feature_class":"P",
    "gn:feature_code":"PPL",
    "gn:name":"Monachynivka",
    "gn:population":0,
    "gn:timezone":"Europe/Kiev",
    "iso:country":"UA",
    "name:ukr_x_preferred":[
        "Monachynivka"
    ],
    "name:ukr_x_variant":[
        "\u041c\u043e\u043d\u0430\u0447\u0438\u043d\u0456\u0432\u043a\u0430"
    ],
    "name:und_x_variant":[
        "Monochinovka",
        "Monachinovka"
    ],
    "wof:name":"Monachynivka",
    "wof:placetype":"locality"
},
  "geometry": {"coordinates":[37.52556,49.81944],"type":"Point"}
}