{
  "type": "Feature",
  "properties": {
    "gn:admin1_code":"27.0",
    "gn:asciiname":"Vykhlya",
    "gn:country_code":"UA",
    "gn:dem":188,
    "gn:feature_class":"P",
    "gn:feature_code":"PPL",
    "gn:name":"Vykhlya",
    "gn:population":0,
    "gn:timezone":"Europe/Kiev",
    "iso:country":"UA",
    "name:ukr_x_preferred":[
        "Vykhlya"
    ],
    "name:ukr_x_variant":[
        "\u0412\u0438\u0445\u043b\u044f"
    ],
    "name:und_x_variant":[
        "Vikhlya"
    ],
    "wof:name":"Vykhlya",
    "wof:placetype":"locality"
},
  "geometry": {"coordinates":[28.84688,50.66095],"type":"Point"}
}