{
  "type": "Feature",
  "properties": {
    "gn:admin1_code":"17.0",
    "gn:asciiname":"Tykhe",
    "gn:country_code":"UA",
    "gn:dem":50,
    "gn:feature_class":"P",
    "gn:feature_code":"PPL",
    "gn:name":"Tykhe",
    "gn:population":0,
    "gn:timezone":"Europe/Kiev",
    "iso:country":"UA",
    "name:ukr_x_preferred":[
        "Chapayeve"
    ],
    "name:ukr_x_variant":[
        "\u0427\u0430\u043f\u0430\u0454\u0432\u0435",
        "Tykhe",
        "\u0422\u0438\u0445\u0435"
    ],
    "name:und_x_variant":[
        "Chapayevo"
    ],
    "wof:name":"Tykhe",
    "wof:placetype":"locality"
},
  "geometry": {"coordinates":[30.59379,46.67529],"type":"Point"}
}