{
  "type": "Feature",
  "properties": {
    "gn:admin1_code":"4.0",
    "gn:asciiname":"Kovalivka",
    "gn:country_code":"UA",
    "gn:dem":148,
    "gn:feature_class":"P",
    "gn:feature_code":"PPL",
    "gn:name":"Kovalivka",
    "gn:population":0,
    "gn:timezone":"Europe/Kiev",
    "iso:country":"UA",
    "name:ukr_x_preferred":[
        "Kovalivka"
    ],
    "name:ukr_x_variant":[
        "\u041a\u043e\u0432\u0430\u043b\u0456\u0432\u043a\u0430"
    ],
    "wof:name":"Kovalivka",
    "wof:placetype":"locality"
},
  "geometry": {"coordinates":[34.05995,48.28378],"type":"Point"}
}