{
  "type": "Feature",
  "properties": {
    "gn:admin1_code":"19.0",
    "gn:asciiname":"Ivanychi",
    "gn:country_code":"UA",
    "gn:dem":187,
    "gn:feature_class":"P",
    "gn:feature_code":"PPL",
    "gn:name":"Ivanychi",
    "gn:population":0,
    "gn:timezone":"Europe/Kiev",
    "iso:country":"UA",
    "name:bel_x_preferred":[
        "\u0406\u0432\u0430\u043d\u044b\u0447\u044b"
    ],
    "name:crh_x_preferred":[
        "\u0130van\u0131\u00e7i"
    ],
    "name:deu_x_preferred":[
        "Iwanytschi"
    ],
    "name:fra_x_preferred":[
        "Ivanytchi"
    ],
    "name:ita_x_preferred":[
        "Ivany\u010di"
    ],
    "name:lit_x_preferred":[
        "Ivany\u010diai"
    ],
    "name:pol_x_preferred":[
        "Iwanicze"
    ],
    "name:ron_x_preferred":[
        "Ivan\u00eeci"
    ],
    "name:rus_x_preferred":[
        "\u0418\u0432\u0430\u043d\u0438\u0447\u0438"
    ],
    "name:ukr_x_preferred":[
        "Ivanychi"
    ],
    "name:ukr_x_variant":[
        "\u0406\u0432\u0430\u043d\u0438\u0447\u0456"
    ],
    "name:und_x_variant":[
        "Yankeviche",
        "Ivanichi"
    ],
    "name:yid_x_preferred":[
        "\u05d0\u05d9\u05d5\u05d5\u05d0\u05e0\u05d9\u05d8\u05e9"
    ],
    "name:zho_x_preferred":[
        "\u4f0a\u74e6\u5c3c\u5947"
    ],
    "wof:name":"Ivanychi",
    "wof:placetype":"locality"
},
  "geometry": {"coordinates":[26.376,50.89227],"type":"Point"}
}