{
  "type": "Feature",
  "properties": {
    "gn:admin1_code":"19.0",
    "gn:asciiname":"Ivanychi",
    "gn:country_code":"UA",
    "gn:dem":187,
    "gn:feature_class":"P",
    "gn:feature_code":"PPL",
    "gn:name":"Ivanychi",
    "gn:population":0,
    "gn:timezone":"Europe/Kiev",
    "iso:country":"UA",
    "name:ukr_x_preferred":[
        "Ivanychi"
    ],
    "name:ukr_x_variant":[
        "\u0406\u0432\u0430\u043d\u0438\u0447\u0456"
    ],
    "name:und_x_variant":[
        "Yankeviche",
        "Ivanichi"
    ],
    "wof:name":"Ivanychi",
    "wof:placetype":"locality"
},
  "geometry": {"coordinates":[26.376,50.89227],"type":"Point"}
}