{
  "type": "Feature",
  "properties": {
    "gn:admin1_code":"18.0",
    "gn:asciiname":"Kurchanovka",
    "gn:cc2":"UA",
    "gn:country_code":"UA",
    "gn:dem":68,
    "gn:feature_class":"P",
    "gn:feature_code":"PPL",
    "gn:name":"Kurchanovka",
    "gn:population":0,
    "gn:timezone":"Europe/Kiev",
    "iso:country":"UA",
    "name:und_x_variant":[
        "Kalantyr\u2019",
        "Kurchanovka"
    ],
    "wof:name":"Kurchanovka",
    "wof:placetype":"locality"
},
  "geometry": {"coordinates":[33.43333,49.01667],"type":"Point"}
}