{
  "type": "Feature",
  "properties": {
    "gn:admin1_code":"7.0",
    "gn:asciiname":"Pokrovka",
    "gn:country_code":"UA",
    "gn:dem":175,
    "gn:feature_class":"P",
    "gn:feature_code":"PPL",
    "gn:name":"Pokrovka",
    "gn:population":0,
    "gn:timezone":"Europe/Kiev",
    "iso:country":"UA",
    "name:ukr_x_preferred":[
        "Pokrovka"
    ],
    "name:ukr_x_variant":[
        "\u041f\u043e\u043a\u0440\u043e\u0432\u043a\u0430"
    ],
    "name:und_x_variant":[
        "Pokrovskaya"
    ],
    "wof:name":"Pokrovka",
    "wof:placetype":"locality"
},
  "geometry": {"coordinates":[35.28374,49.91338],"type":"Point"}
}