{
  "type": "Feature",
  "properties": {
    "gn:admin1_code":"26.0",
    "gn:asciiname":"Bohunivka",
    "gn:country_code":"UA",
    "gn:dem":141,
    "gn:feature_class":"P",
    "gn:feature_code":"PPL",
    "gn:name":"Bohunivka",
    "gn:population":0,
    "gn:timezone":"Europe/Zaporozhye",
    "iso:country":"UA",
    "name:ukr_x_preferred":[
        "Bohunivka"
    ],
    "name:ukr_x_variant":[
        "\u0411\u043e\u0433\u0443\u043d\u0456\u0432\u043a\u0430"
    ],
    "name:und_x_variant":[
        "Bogunovka"
    ],
    "wof:name":"Bohunivka",
    "wof:placetype":"locality"
},
  "geometry": {"coordinates":[35.75413,48.047],"type":"Point"}
}