{
  "type": "Feature",
  "properties": {
    "gn:admin1_code":"18.0",
    "gn:asciiname":"Ol'hivka",
    "gn:country_code":"UA",
    "gn:dem":111,
    "gn:feature_class":"P",
    "gn:feature_code":"PPL",
    "gn:name":"Ol\u2019hivka",
    "gn:population":0,
    "gn:timezone":"Europe/Kiev",
    "iso:country":"UA",
    "name:ukr_x_preferred":[
        "Ol\u2019hivka"
    ],
    "name:ukr_x_variant":[
        "\u041e\u043b\u044c\u0433\u0456\u0432\u043a\u0430"
    ],
    "wof:name":"Ol'hivka",
    "wof:placetype":"locality"
},
  "geometry": {"coordinates":[33.83435,49.16902],"type":"Point"}
}