{
  "type": "Feature",
  "properties": {
    "gn:admin1_code":"4.0",
    "gn:asciiname":"Novopodil's'ke",
    "gn:country_code":"UA",
    "gn:dem":76,
    "gn:feature_class":"P",
    "gn:feature_code":"PPL",
    "gn:name":"Novopodil\u2019s\u2019ke",
    "gn:population":0,
    "gn:timezone":"Europe/Kiev",
    "iso:country":"UA",
    "name:ukr_x_preferred":[
        "Novopodil\u2019s\u2019ke"
    ],
    "name:ukr_x_variant":[
        "\u041d\u043e\u0432\u043e\u043f\u043e\u0434\u0456\u043b\u044c\u0441\u044c\u043a\u0435"
    ],
    "name:und_x_variant":[
        "Kushchinskaya",
        "Novo-Podol\u2019sk"
    ],
    "wof:name":"Novopodil's'ke",
    "wof:placetype":"locality"
},
  "geometry": {"coordinates":[33.89949,47.92421],"type":"Point"}
}