{
  "type": "Feature",
  "properties": {
    "gn:admin1_code":"22.0",
    "gn:asciiname":"Volkovtse",
    "gn:country_code":"UA",
    "gn:dem":279,
    "gn:feature_class":"P",
    "gn:feature_code":"PPL",
    "gn:name":"Volkovtse",
    "gn:population":0,
    "gn:timezone":"Europe/Kiev",
    "iso:country":"UA",
    "wof:name":"Volkovtse",
    "wof:placetype":"locality"
},
  "geometry": {"coordinates":[26.13263,50.03802],"type":"Point"}
}