{
  "type": "Feature",
  "properties": {
    "gn:admin1_code":"21.0",
    "gn:asciiname":"Doroshenkove",
    "gn:country_code":"UA",
    "gn:dem":190,
    "gn:feature_class":"P",
    "gn:feature_code":"PPL",
    "gn:name":"Doroshenkove",
    "gn:population":0,
    "gn:timezone":"Europe/Kiev",
    "iso:country":"UA",
    "name:ukr_x_preferred":[
        "Doroshenkove"
    ],
    "name:ukr_x_variant":[
        "\u0414\u043e\u0440\u043e\u0448\u0435\u043d\u043a\u043e\u0432\u0435"
    ],
    "name:und_x_variant":[
        "Doroshenkov"
    ],
    "wof:name":"Doroshenkove",
    "wof:placetype":"locality"
},
  "geometry": {"coordinates":[33.83947,52.06593],"type":"Point"}
}