{
  "type": "Feature",
  "properties": {
    "gn:admin1_code":"7.0",
    "gn:asciiname":"Borivs'ka Andriyivka",
    "gn:country_code":"UA",
    "gn:dem":97,
    "gn:feature_class":"P",
    "gn:feature_code":"PPL",
    "gn:name":"Borivs\u2019ka Andriyivka",
    "gn:population":0,
    "gn:timezone":"Europe/Kiev",
    "iso:country":"UA",
    "name:ukr_x_preferred":[
        "Borivs\u2019ka Andriyivka"
    ],
    "name:und_x_variant":[
        "Andreyevka"
    ],
    "wof:name":"Borivs'ka Andriyivka",
    "wof:placetype":"locality"
},
  "geometry": {"coordinates":[37.73056,49.41333],"type":"Point"}
}