{
  "type": "Feature",
  "properties": {
    "iso:country":"UA",
    "name:ces_x_preferred":[
        "Velk\u00e1 Beha\u0148"
    ],
    "name:che_x_preferred":[
        "\u0412\u0435\u043b\u0438\u043a\u0430\u044f \u0411\u0438\u0439\u0433\u0430\u043d\u044c"
    ],
    "name:deu_x_preferred":[
        "Welyka Byjhan"
    ],
    "name:eng_x_preferred":[
        "Velika Bihany"
    ],
    "name:eng_x_variant":[
        "Velyka Byihan"
    ],
    "name:epo_x_preferred":[
        "Velika Bijhanj"
    ],
    "name:fas_x_preferred":[
        "\u0648\u0644\u06cc\u06a9\u0627 \u0628\u06cc\u0647\u0646\u06cc"
    ],
    "name:fin_x_preferred":[
        "V\u0435lyk\u0430 Byih\u0430n"
    ],
    "name:hun_x_preferred":[
        "Nagyb\u00e9g\u00e1ny"
    ],
    "name:hye_x_preferred":[
        "\u054e\u0565\u056c\u056b\u056f\u0561\u0575\u0561 \u0532\u056b\u0575\u0563\u0561\u0576"
    ],
    "name:nld_x_preferred":[
        "Velika Bihany"
    ],
    "name:nno_x_preferred":[
        "Velyka Byjhan"
    ],
    "name:nob_x_preferred":[
        "Velyka Byjhan"
    ],
    "name:pol_x_preferred":[
        "We\u0142yka Biga\u0144"
    ],
    "name:ron_x_preferred":[
        "Vel\u00eeka B\u00eeihan"
    ],
    "name:rus_x_preferred":[
        "\u0412\u0435\u043b\u0438\u043a\u0430\u044f \u0411\u044b\u0439\u0433\u0430\u043d\u044c"
    ],
    "name:ukr_x_preferred":[
        "\u0412\u0435\u043b\u0438\u043a\u0430 \u0411\u0438\u0439\u0433\u0430\u043d\u044c"
    ],
    "name:und_x_variant":[
        "Velyka Bigan\u2019"
    ],
    "name:zho_x_preferred":[
        "\u5927\u6bd4\u7518"
    ],
    "qs:a0":"\u0423\u043a\u0440\u0430\u0457\u043d\u0430",
    "qs:a1":"*\u0417\u0430\u043a\u0430\u0440\u043f\u0430\u0442\u0441\u044c\u043a\u0430",
    "qs:a1_alt":"Zakarpats'ka",
    "qs:a1r":"0",
    "qs:a2":"\u0411\u0435\u0440\u0435\u0433\u0456\u0432\u0441\u044c\u043a\u0438\u0439",
    "qs:a2_alt":"Berehivs'kyi",
    "qs:adm0":"\u0423\u043a\u0440\u0430\u0457\u043d\u0430",
    "qs:la_lc":"*",
    "qs:level":"locality",
    "qs:loc":"\u0412\u0435\u043b\u0438\u043a\u0430 \u0411\u0438\u0439\u0433\u0430\u043d\u044c",
    "qs:loc_alt":"Velyka Byihan",
    "qs:pop":0,
    "qs:type":"buffered point",
    "wof:name":"\u0412\u0435\u043b\u0438\u043a\u0430 \u0411\u0438\u0439\u0433\u0430\u043d\u044c",
    "wof:placetype":"locality"
},
  "geometry": {"coordinates":[22.576021,48.247529],"type":"Point"}
}