{
  "type": "Feature",
  "properties": {
    "gn:admin1_code":"4.0",
    "gn:asciiname":"Kruten'kiy",
    "gn:country_code":"UA",
    "gn:dem":67,
    "gn:feature_class":"P",
    "gn:feature_code":"PPL",
    "gn:name":"Kruten\u2019kiy",
    "gn:population":0,
    "gn:timezone":"Europe/Kiev",
    "iso:country":"UA",
    "name:rus_x_preferred":[
        "Kruten\u2019koye"
    ],
    "name:rus_x_variant":[
        "\u041a\u0440\u0443\u0442\u0435\u043d\u044c\u043a\u043e\u0435"
    ],
    "name:und_x_variant":[
        "Kruten\u2019kiy"
    ],
    "wof:name":"Kruten'kiy",
    "wof:placetype":"locality"
},
  "geometry": {"coordinates":[34.14367,47.67383],"type":"Point"}
}