{
  "type": "Feature",
  "properties": {
    "gn:admin1_code":"7.0",
    "gn:asciiname":"Tymchenky",
    "gn:country_code":"UA",
    "gn:dem":93,
    "gn:feature_class":"P",
    "gn:feature_code":"PPL",
    "gn:name":"Tymchenky",
    "gn:population":0,
    "gn:timezone":"Europe/Kiev",
    "iso:country":"UA",
    "name:ukr_x_preferred":[
        "Tymchenky"
    ],
    "name:ukr_x_variant":[
        "\u0422\u0438\u043c\u0447\u0435\u043d\u043a\u0438"
    ],
    "name:und_x_variant":[
        "Tymchenki",
        "Timchenkov"
    ],
    "wof:name":"Tymchenky",
    "wof:placetype":"locality"
},
  "geometry": {"coordinates":[36.15251,49.75352],"type":"Point"}
}