{
  "type": "Feature",
  "properties": {
    "gn:admin1_code":"1.0",
    "gn:asciiname":"Pavlovka",
    "gn:country_code":"UA",
    "gn:dem":217,
    "gn:feature_class":"P",
    "gn:feature_code":"PPL",
    "gn:name":"Pavlovka",
    "gn:population":0,
    "gn:timezone":"Europe/Kiev",
    "iso:country":"UA",
    "name:eng_x_preferred":[
        "Pavlovka"
    ],
    "name:rus_x_preferred":[
        "\u041f\u0430\u0432\u043b\u043e\u0432\u043a\u0430"
    ],
    "wof:name":"Pavlovka",
    "wof:placetype":"locality"
},
  "geometry": {"coordinates":[30.4828,49.24819],"type":"Point"}
}