{
  "type": "Feature",
  "properties": {
    "gn:admin1_code":"2.0",
    "gn:asciiname":"Khutor Shursha",
    "gn:cc2":"UA",
    "gn:country_code":"UA",
    "gn:dem":115,
    "gn:feature_class":"P",
    "gn:feature_code":"PPL",
    "gn:name":"Khutor Shursha",
    "gn:population":0,
    "gn:timezone":"Europe/Kiev",
    "iso:country":"UA",
    "name:und_x_variant":[
        "Shursha",
        "Khutor Shursha"
    ],
    "wof:name":"Khutor Shursha",
    "wof:placetype":"locality"
},
  "geometry": {"coordinates":[31.71667,51.06667],"type":"Point"}
}