{
  "type": "Feature",
  "properties": {
    "gn:admin1_code":"15.0",
    "gn:asciiname":"Babyno",
    "gn:country_code":"UA",
    "gn:dem":474,
    "gn:feature_class":"P",
    "gn:feature_code":"PPL",
    "gn:name":"Babyno",
    "gn:population":0,
    "gn:timezone":"Europe/Kiev",
    "iso:country":"UA",
    "name:rus_x_preferred":[
        "\u0411\u0430\u0431\u0438\u043d\u0430"
    ],
    "name:ukr_x_preferred":[
        "Babyno"
    ],
    "name:ukr_x_variant":[
        "\u0411\u0430\u0431\u0438\u043d\u043e"
    ],
    "name:und_x_variant":[
        "Babino",
        "Babina"
    ],
    "wof:name":"Babyno",
    "wof:placetype":"locality"
},
  "geometry": {"coordinates":[22.84889,49.31406],"type":"Point"}
}