{
  "type": "Feature",
  "properties": {
    "gn:admin1_code":"14.0",
    "gn:asciiname":"Myrna Dolyna",
    "gn:country_code":"UA",
    "gn:dem":147,
    "gn:feature_class":"P",
    "gn:feature_code":"PPL",
    "gn:name":"Myrna Dolyna",
    "gn:population":0,
    "gn:timezone":"Europe/Zaporozhye",
    "iso:country":"UA",
    "name:eng_x_preferred":[
        "Mirnaya Dolina"
    ],
    "name:rus_x_preferred":[
        "\u041c\u0438\u0440\u043d\u0430\u044f \u0414\u043e\u043b\u0438\u043d\u0430"
    ],
    "name:ukr_x_preferred":[
        "Myrna Dolyna"
    ],
    "name:ukr_x_variant":[
        "\u041c\u0438\u0440\u043d\u0430 \u0414\u043e\u043b\u0438\u043d\u0430"
    ],
    "name:und_x_variant":[
        "Mirnaya Dolina"
    ],
    "wof:name":"Myrna Dolyna",
    "wof:placetype":"locality"
},
  "geometry": {"coordinates":[38.47902,48.80996],"type":"Point"}
}