{
  "type": "Feature",
  "properties": {
    "iso:country":"UA",
    "name:chi_x_preferred":[
        "\u7d0d\u52a0\u5947\u592b"
    ],
    "name:eng_x_preferred":[
        "Nahachiv"
    ],
    "name:pol_x_preferred":[
        "Nahacz\u00f3w"
    ],
    "name:ron_x_preferred":[
        "Nahaciv"
    ],
    "name:rum_x_preferred":[
        "Nahaciv"
    ],
    "name:rus_x_preferred":[
        "\u041d\u0430\u0433\u0430\u0447\u0435\u0432"
    ],
    "name:ukr_x_preferred":[
        "\u041d\u0430\u0433\u0430\u0447\u0456\u0432"
    ],
    "name:zho_x_preferred":[
        "\u7d0d\u52a0\u5947\u592b"
    ],
    "qs:a0":"\u0423\u043a\u0440\u0430\u0457\u043d\u0430",
    "qs:a1":"*\u041b\u044c\u0432\u0456\u0432\u0441\u044c\u043a\u0430",
    "qs:a1_alt":"L'vivs'ka",
    "qs:a1r":"0",
    "qs:a2":"\u042f\u0432\u043e\u0440\u0456\u0432\u0441\u044c\u043a\u0438\u0439",
    "qs:a2_alt":"Yavorivs'kyi",
    "qs:adm0":"\u0423\u043a\u0440\u0430\u0457\u043d\u0430",
    "qs:la_lc":"*",
    "qs:level":"locality",
    "qs:loc":"\u041d\u0430\u0433\u0430\u0447\u0456\u0432",
    "qs:loc_alt":"Nahachiv",
    "qs:pop":0,
    "qs:type":"buffered point",
    "wd:wordcount":119,
    "wof:name":"\u041d\u0430\u0433\u0430\u0447\u0456\u0432",
    "wof:placetype":"locality"
},
  "geometry": {"coordinates":[23.27211,50.005531],"type":"Point"}
}