{
  "type": "Feature",
  "properties": {
    "gn:admin1_code":"21.0",
    "gn:asciiname":"Herasymivka",
    "gn:country_code":"UA",
    "gn:dem":119,
    "gn:feature_class":"P",
    "gn:feature_code":"PPL",
    "gn:name":"Herasymivka",
    "gn:population":0,
    "gn:timezone":"Europe/Kiev",
    "iso:country":"UA",
    "name:ukr_x_preferred":[
        "Herasymivka"
    ],
    "name:ukr_x_variant":[
        "\u0413\u0435\u0440\u0430\u0441\u0438\u043c\u0456\u0432\u043a\u0430"
    ],
    "name:und_x_variant":[
        "Gerasimovka"
    ],
    "wof:name":"Herasymivka",
    "wof:placetype":"locality"
},
  "geometry": {"coordinates":[33.53391,50.75429000000001],"type":"Point"}
}