{
  "type": "Feature",
  "properties": {
    "iso:country":"UA",
    "qs:a0":"\u0423\u043a\u0440\u0430\u0457\u043d\u0430",
    "qs:a1":"*\u041a\u0440\u0438\u043c",
    "qs:a1_alt":"Krym",
    "qs:a1r":"0",
    "qs:a2":"\u0411\u0430\u0445\u0447\u0438\u0441\u0430\u0440\u0430\u0439\u0441\u044c\u043a\u0438\u0439",
    "qs:a2_alt":"Bakhchysarais'kyi",
    "qs:adm0":"\u0423\u043a\u0440\u0430\u0457\u043d\u0430",
    "qs:la_lc":"*",
    "qs:level":"locality",
    "qs:loc":"\u041a\u0430\u0448\u0442\u0430\u043d\u0438",
    "qs:loc_alt":"Kashtany",
    "qs:pop":0,
    "qs:type":"buffered point",
    "wd:elevation":179.0,
    "wd:population":2845023,
    "wd:wordcount":11163,
    "wof:name":"\u041a\u0430\u0448\u0442\u0430\u043d\u0438",
    "wof:placetype":"locality",
    "wof:population":2845023
},
  "geometry": {"coordinates":[33.777408,44.869842],"type":"Point"}
}