{
  "type": "Feature",
  "properties": {
    "gn:admin1_code":"4.0",
    "gn:asciiname":"Mala Kalynivka",
    "gn:country_code":"UA",
    "gn:dem":122,
    "gn:feature_class":"P",
    "gn:feature_code":"PPL",
    "gn:name":"Mala Kalynivka",
    "gn:population":0,
    "gn:timezone":"Europe/Kiev",
    "iso:country":"UA",
    "name:ukr_x_preferred":[
        "Mala Kalynivka"
    ],
    "name:ukr_x_variant":[
        "\u041c\u0430\u043b\u0430 \u041a\u0430\u043b\u0438\u043d\u0456\u0432\u043a\u0430"
    ],
    "wof:name":"Mala Kalynivka",
    "wof:placetype":"locality"
},
  "geometry": {"coordinates":[34.31329,48.02902],"type":"Point"}
}