{
  "type": "Feature",
  "properties": {
    "gn:admin1_code":"14.0",
    "gn:asciiname":"Kuzemivka",
    "gn:country_code":"UA",
    "gn:dem":119,
    "gn:feature_class":"P",
    "gn:feature_code":"PPL",
    "gn:name":"Kuzemivka",
    "gn:population":0,
    "gn:timezone":"Europe/Zaporozhye",
    "iso:country":"UA",
    "name:eng_x_preferred":[
        "Kuzemovka"
    ],
    "name:rus_x_preferred":[
        "\u041a\u0443\u0437\u0435\u043c\u043e\u0432\u043a\u0430"
    ],
    "name:ukr_x_preferred":[
        "Kuzemivka"
    ],
    "name:und_x_variant":[
        "Kuzemovka"
    ],
    "wof:name":"Kuzemivka",
    "wof:placetype":"locality"
},
  "geometry": {"coordinates":[37.98316,49.51969],"type":"Point"}
}