{
  "type": "Feature",
  "properties": {
    "gn:admin1_code":"23.0",
    "gn:asciiname":"Severinovka",
    "gn:country_code":"UA",
    "gn:dem":312,
    "gn:feature_class":"P",
    "gn:feature_code":"PPL",
    "gn:name":"Severinovka",
    "gn:population":0,
    "gn:timezone":"Europe/Kiev",
    "iso:country":"UA",
    "wof:name":"Severinovka",
    "wof:placetype":"locality"
},
  "geometry": {"coordinates":[27.9465,49.05027000000001],"type":"Point"}
}