{
  "type": "Feature",
  "properties": {
    "gn:admin1_code":"27.0",
    "gn:asciiname":"Slavkovytsi",
    "gn:country_code":"UA",
    "gn:dem":168,
    "gn:feature_class":"P",
    "gn:feature_code":"PPL",
    "gn:name":"Slavkovytsi",
    "gn:population":0,
    "gn:timezone":"Europe/Kiev",
    "iso:country":"UA",
    "name:ukr_x_preferred":[
        "Slavkovytsi"
    ],
    "name:ukr_x_variant":[
        "\u0421\u043b\u0430\u0432\u043a\u043e\u0432\u0438\u0446\u0456"
    ],
    "name:und_x_variant":[
        "Slavkovitsy"
    ],
    "wof:name":"Slavkovytsi",
    "wof:placetype":"locality"
},
  "geometry": {"coordinates":[29.42475,51.05464],"type":"Point"}
}