{
  "type": "Feature",
  "properties": {
    "gn:admin1_code":"27.0",
    "gn:asciiname":"Snytyshche",
    "gn:country_code":"UA",
    "gn:dem":133,
    "gn:feature_class":"P",
    "gn:feature_code":"PPL",
    "gn:name":"Snytyshche",
    "gn:population":0,
    "gn:timezone":"Europe/Kiev",
    "iso:country":"UA",
    "name:ukr_x_preferred":[
        "Snytyshche"
    ],
    "name:ukr_x_variant":[
        "\u0421\u043d\u0438\u0442\u0438\u0449\u0435"
    ],
    "name:und_x_variant":[
        "Snitishchi",
        "Snitishche"
    ],
    "wof:name":"Snytyshche",
    "wof:placetype":"locality"
},
  "geometry": {"coordinates":[29.07398,51.26317],"type":"Point"}
}