{
  "type": "Feature",
  "properties": {
    "gn:admin1_code":"14.0",
    "gn:asciiname":"Bogdanovka",
    "gn:country_code":"UA",
    "gn:dem":173,
    "gn:feature_class":"P",
    "gn:feature_code":"PPL",
    "gn:name":"Bogdanovka",
    "gn:population":0,
    "gn:timezone":"Europe/Zaporozhye",
    "iso:country":"UA",
    "wof:name":"Bogdanovka",
    "wof:placetype":"locality"
},
  "geometry": {"coordinates":[38.32639,48.86444],"type":"Point"}
}