{
  "type": "Feature",
  "properties": {
    "gn:admin1_code":"24.0",
    "gn:asciiname":"Boryskovychi",
    "gn:country_code":"UA",
    "gn:dem":228,
    "gn:feature_class":"P",
    "gn:feature_code":"PPL",
    "gn:name":"Boryskovychi",
    "gn:population":0,
    "gn:timezone":"Europe/Kiev",
    "iso:country":"UA",
    "name:ukr_x_preferred":[
        "Boryskovychi"
    ],
    "name:ukr_x_variant":[
        "\u0411\u043e\u0440\u0438\u0441\u043a\u043e\u0432\u0438\u0447\u0456"
    ],
    "name:und_x_variant":[
        "Boriskovichi"
    ],
    "wof:name":"Boryskovychi",
    "wof:placetype":"locality"
},
  "geometry": {"coordinates":[24.7821,50.41962],"type":"Point"}
}