{
  "type": "Feature",
  "properties": {
    "gn:admin1_code":"14.0",
    "gn:asciiname":"Novo-Klinovo",
    "gn:country_code":"UA",
    "gn:dem":182,
    "gn:feature_class":"P",
    "gn:feature_code":"PPL",
    "gn:name":"Novo-Klinovo",
    "gn:population":0,
    "gn:timezone":"Europe/Zaporozhye",
    "iso:country":"UA",
    "wof:name":"Novo-Klinovo",
    "wof:placetype":"locality"
},
  "geometry": {"coordinates":[39.42361,48.30278],"type":"Point"}
}