{
  "type": "Feature",
  "properties": {
    "gn:admin1_code":"4.0",
    "gn:asciiname":"Tsikove",
    "gn:country_code":"UA",
    "gn:dem":81,
    "gn:feature_class":"P",
    "gn:feature_code":"PPL",
    "gn:name":"Tsikove",
    "gn:population":0,
    "gn:timezone":"Europe/Kiev",
    "iso:country":"UA",
    "name:ukr_x_preferred":[
        "Tsikove"
    ],
    "name:ukr_x_variant":[
        "\u0426\u0438\u043a\u043e\u0432\u0435"
    ],
    "name:und_x_variant":[
        "Tsikova"
    ],
    "wof:name":"Tsikove",
    "wof:placetype":"locality"
},
  "geometry": {"coordinates":[36.18116,47.99656],"type":"Point"}
}