{
  "type": "Feature",
  "properties": {
    "gn:admin1_code":"13.0",
    "gn:asciiname":"Svoboda",
    "gn:country_code":"UA",
    "gn:dem":129,
    "gn:feature_class":"P",
    "gn:feature_code":"PPL",
    "gn:name":"Svoboda",
    "gn:population":0,
    "gn:timezone":"Europe/Kiev",
    "iso:country":"UA",
    "name:ukr_x_preferred":[
        "Svoboda"
    ],
    "name:ukr_x_variant":[
        "\u0421\u0432\u043e\u0431\u043e\u0434\u0430"
    ],
    "name:und_x_variant":[
        "Sloboda"
    ],
    "wof:name":"Svoboda",
    "wof:placetype":"locality"
},
  "geometry": {"coordinates":[31.77192,50.43452],"type":"Point"}
}