{
  "type": "Feature",
  "properties": {
    "gn:gn_country":"UA",
    "gn:gn_fcode":"PPL",
    "gn:gn_pop":25000,
    "gn:population":25000,
    "iso:country":"UA",
    "name:arm_x_preferred":[
        "\u0545\u0578\u0582\u056a\u0576\u056b\u0575"
    ],
    "name:bul_x_preferred":[
        "\u042e\u0436\u043d\u0435"
    ],
    "name:chi_x_preferred":[
        "\u5c24\u65e5\u5167"
    ],
    "name:cze_x_preferred":[
        "Ju\u017ene"
    ],
    "name:dut_x_preferred":[
        "Yuzhne"
    ],
    "name:eng_x_preferred":[
        "Yuzhne"
    ],
    "name:fin_x_preferred":[
        "Ju\u017ene"
    ],
    "name:fre_x_preferred":[
        "Youjne"
    ],
    "name:geo_x_preferred":[
        "\u10d8\u10e3\u10df\u10dc\u10d8"
    ],
    "name:ger_x_preferred":[
        "Juschne"
    ],
    "name:heb_x_preferred":[
        "\u05d9\u05d5\u05d6'\u05e0\u05d9"
    ],
    "name:ita_x_preferred":[
        "Ju\u017ene"
    ],
    "name:lav_x_preferred":[
        "Ju\u017ene"
    ],
    "name:lit_x_preferred":[
        "Ju\u017enas"
    ],
    "name:nno_x_preferred":[
        "Juzjne"
    ],
    "name:nob_x_preferred":[
        "Juzjne"
    ],
    "name:per_x_preferred":[
        "\u06cc\u0648\u0698\u0646\u0647"
    ],
    "name:pol_x_preferred":[
        "Ju\u017cne"
    ],
    "name:rum_x_preferred":[
        "Iujne"
    ],
    "name:rus_x_preferred":[
        "\u042e\u0436\u043d\u044b\u0439"
    ],
    "name:rus_x_variant":[
        "\u042e\u0436\u043d\u0435",
        "\u042e\u0436\u043d\u043e\u0435"
    ],
    "name:sah_x_preferred":[
        "\u042e\u0436\u043d\u0435"
    ],
    "name:srp_x_preferred":[
        "\u0408\u0443\u0436\u043d\u0435"
    ],
    "name:swe_x_preferred":[
        "Juzjne"
    ],
    "name:tat_x_preferred":[
        "\u042e\u0436\u043d\u0435"
    ],
    "name:ukr_x_preferred":[
        "\u042e\u0436\u043d\u0435"
    ],
    "name:vie_x_preferred":[
        "Yuzhne"
    ],
    "qs_pg:aaroncc":"UA",
    "qs_pg:gn_country":"UA",
    "qs_pg:gn_fcode":"PPL",
    "qs_pg:gn_pop":25000,
    "qs_pg:name":"Yuzhne",
    "qs_pg:name_adm0":"Ukraine",
    "qs_pg:name_adm1":"Odes\u00b4ka Oblast\u00b4",
    "qs_pg:photos":46,
    "qs_pg:photos_1k":9,
    "qs_pg:photos_9k":1,
    "qs_pg:photos_9r":2,
    "qs_pg:photos_all":46,
    "qs_pg:photos_sr":2,
    "qs_pg:pop_sr":7,
    "qs_pg:qs_pg_placetype":"locality",
    "qs_pg:qs_pg_placetype_gp":"Town",
    "qs_pg:woe_adm0":23424976,
    "woe:adm0_id":23424976,
    "woe:name_adm0":"Ukraine",
    "woe:name_adm1":"Odes\u00b4ka Oblast\u00b4",
    "woe:placetype":"Town",
    "wof:name":"Yuzhne",
    "wof:placetype":"locality",
    "wof:population":25000
},
  "geometry": {"coordinates":[31.10131,46.62211],"type":"Point"}
}