{
  "type": "Feature",
  "properties": {
    "gn:admin1_code":"15.0",
    "gn:asciiname":"Uhers'ko",
    "gn:country_code":"UA",
    "gn:dem":281,
    "gn:feature_class":"P",
    "gn:feature_code":"PPL",
    "gn:name":"Uhers\u2019ko",
    "gn:population":0,
    "gn:timezone":"Europe/Kiev",
    "iso:country":"UA",
    "name:rus_x_preferred":[
        "\u042f\u0431\u043b\u043e\u043d\u043e\u0432\u043a\u0430"
    ],
    "name:ukr_x_preferred":[
        "Uhers\u2019ko"
    ],
    "name:ukr_x_variant":[
        "\u0423\u0433\u0435\u0440\u0441\u044c\u043a\u043e"
    ],
    "name:und_x_variant":[
        "Yablonevka",
        "Yablunivka",
        "Yablonovka"
    ],
    "wof:name":"Uhers'ko",
    "wof:placetype":"locality"
},
  "geometry": {"coordinates":[23.91051,49.30053],"type":"Point"}
}