{
  "type": "Feature",
  "properties": {
    "iso:country":"UA",
    "qs:a0":"\u0423\u043a\u0440\u0430\u0457\u043d\u0430",
    "qs:a1":"*\u041c\u0438\u043a\u043e\u043b\u0430\u0457\u0432\u0441\u044c\u043a\u0430",
    "qs:a1_alt":"Mykolaivs'ka",
    "qs:a1r":"0",
    "qs:a2":"\u0416\u043e\u0432\u0442\u043d\u0435\u0432\u0438\u0439",
    "qs:a2_alt":"Zhovtnevyi",
    "qs:adm0":"\u0423\u043a\u0440\u0430\u0457\u043d\u0430",
    "qs:la_lc":"*",
    "qs:level":"locality",
    "qs:loc":"\u0413\u0440\u0435\u0439\u0433\u043e\u0432\u0435",
    "qs:loc_alt":"Hreihove",
    "qs:pop":0,
    "qs:type":"buffered point",
    "wof:name":"\u0413\u0440\u0435\u0439\u0433\u043e\u0432\u0435",
    "wof:placetype":"locality"
},
  "geometry": {"coordinates":[32.299253,47.115308],"type":"Point"}
}