{
  "type": "Feature",
  "properties": {
    "gn:admin1_code":"27.0",
    "gn:asciiname":"Vystupovychi",
    "gn:country_code":"UA",
    "gn:dem":132,
    "gn:feature_class":"P",
    "gn:feature_code":"PPL",
    "gn:name":"Vystupovychi",
    "gn:population":0,
    "gn:timezone":"Europe/Kiev",
    "iso:country":"UA",
    "name:rus_x_preferred":[
        "\u0412\u044b\u0441\u0442\u0443\u043f\u043e\u0432\u0438\u0447\u0438"
    ],
    "name:ukr_x_preferred":[
        "Vystupovychi"
    ],
    "name:ukr_x_variant":[
        "\u0412\u0438\u0441\u0442\u0443\u043f\u043e\u0432\u0438\u0447\u0456"
    ],
    "name:und_x_variant":[
        "Vystupovichi"
    ],
    "wof:name":"Vystupovychi",
    "wof:placetype":"locality"
},
  "geometry": {"coordinates":[29.07769,51.5671],"type":"Point"}
}