{
  "type": "Feature",
  "properties": {
    "gn:population":2230,
    "iso:country":"UA",
    "name:ara_x_preferred":[
        "\u0628\u0648\u0643\u064a"
    ],
    "name:crh_x_preferred":[
        "Buk\u0131"
    ],
    "name:deu_x_preferred":[
        "Buky"
    ],
    "name:eng_x_preferred":[
        "Buki"
    ],
    "name:hye_x_preferred":[
        "\u0532\u0578\u0582\u056f\u056b"
    ],
    "name:ita_x_preferred":[
        "Buky"
    ],
    "name:ron_x_preferred":[
        "Buk\u00ee"
    ],
    "name:rus_x_preferred":[
        "\u0411\u0443\u043a\u0438"
    ],
    "name:ukr_x_preferred":[
        "\u0411\u0443\u043a\u0438"
    ],
    "name:unk_x_variant":[
        "Buki"
    ],
    "name:zho_x_preferred":[
        "\u5e03\u57fa"
    ],
    "qs:a0":"\u0423\u043a\u0440\u0430\u0457\u043d\u0430",
    "qs:a1":"*\u0427\u0435\u0440\u043a\u0430\u0441\u044c\u043a\u0430",
    "qs:a1_alt":"Cherkas'ka",
    "qs:a1r":"0",
    "qs:a2":"\u041c\u0430\u043d\u044c\u043a\u0456\u0432\u0441\u044c\u043a\u0438\u0439",
    "qs:a2_alt":"Man'kivs'kyi",
    "qs:adm0":"\u0423\u043a\u0440\u0430\u0457\u043d\u0430",
    "qs:la_lc":"*",
    "qs:level":"locality",
    "qs:loc":"\u0411\u0443\u043a\u0438",
    "qs:loc_alt":"Buky",
    "qs:pop":0,
    "qs:type":"buffered point",
    "wd:wordcount":29,
    "wof:name":"\u0411\u0443\u043a\u0438",
    "wof:placetype":"locality",
    "wof:population":2230
},
  "geometry": {"coordinates":[30.407289,49.088603],"type":"Point"}
}