{
  "type": "Feature",
  "properties": {
    "gn:admin1_code":"17.0",
    "gn:asciiname":"Kyslytsya",
    "gn:country_code":"UA",
    "gn:dem":10,
    "gn:feature_class":"P",
    "gn:feature_code":"PPL",
    "gn:name":"Kyslytsya",
    "gn:population":0,
    "gn:timezone":"Europe/Kiev",
    "iso:country":"UA",
    "name:ukr_x_preferred":[
        "Kyslytsya"
    ],
    "name:ukr_x_variant":[
        "\u041a\u0438\u0441\u043b\u0438\u0446\u044f"
    ],
    "name:und_x_variant":[
        "C\u00e2\u015fli\u0163a-Dun\u0103re",
        "Kyshlitsa-Dunare",
        "C\u00e2slita",
        "Kyslitsa",
        "Kislitsa"
    ],
    "wof:name":"Kyslytsya",
    "wof:placetype":"locality"
},
  "geometry": {"coordinates":[29.03946,45.41358],"type":"Point"}
}