{
  "type": "Feature",
  "properties": {
    "gn:admin1_code":"21.0",
    "gn:asciiname":"Pershe Travnya",
    "gn:country_code":"UA",
    "gn:dem":153,
    "gn:feature_class":"P",
    "gn:feature_code":"PPL",
    "gn:name":"Pershe Travnya",
    "gn:population":0,
    "gn:timezone":"Europe/Kiev",
    "iso:country":"UA",
    "name:ukr_x_preferred":[
        "Pershe Travnya"
    ],
    "name:ukr_x_variant":[
        "\u041f\u0435\u0440\u0448\u0435 \u0422\u0440\u0430\u0432\u043d\u044f"
    ],
    "name:und_x_variant":[
        "Pervomayskiy"
    ],
    "wof:name":"Pershe Travnya",
    "wof:placetype":"locality"
},
  "geometry": {"coordinates":[34.44806,50.86694],"type":"Point"}
}