{
  "type": "Feature",
  "properties": {
    "gn:admin1_code":"15.0",
    "gn:asciiname":"Sushno",
    "gn:country_code":"UA",
    "gn:dem":212,
    "gn:feature_class":"P",
    "gn:feature_code":"PPL",
    "gn:name":"Sushno",
    "gn:population":0,
    "gn:timezone":"Europe/Kiev",
    "iso:country":"UA",
    "name:ukr_x_preferred":[
        "\u0421\u0443\u0448\u043d\u043e"
    ],
    "name:und_x_variant":[
        "Suszno",
        "Sushno",
        "Sushnoye"
    ],
    "wof:name":"Sushno",
    "wof:placetype":"locality"
},
  "geometry": {"coordinates":[24.54401,50.33312],"type":"Point"}
}