{
  "type": "Feature",
  "properties": {
    "gn:admin1_code":"7.0",
    "gn:asciiname":"Myronivka",
    "gn:country_code":"UA",
    "gn:dem":153,
    "gn:feature_class":"P",
    "gn:feature_code":"PPL",
    "gn:name":"Myronivka",
    "gn:population":0,
    "gn:timezone":"Europe/Kiev",
    "iso:country":"UA",
    "name:rus_x_preferred":[
        "\u041c\u0438\u0440\u043e\u043d\u043e\u0432\u043a\u0430"
    ],
    "name:ukr_x_preferred":[
        "\u041c\u0438\u0440\u043e\u043d\u0456\u0432\u043a\u0430"
    ],
    "name:und_x_variant":[
        "Mironovka",
        "Myronivka"
    ],
    "wof:name":"Myronivka",
    "wof:placetype":"locality"
},
  "geometry": {"coordinates":[36.04906,50.19258],"type":"Point"}
}