{
  "type": "Feature",
  "properties": {
    "gn:country":"UA",
    "gn:fcode":"PPL",
    "gn:population":362,
    "iso:country":"UA",
    "name:rus_x_preferred":[
        "\u0411\u044b\u0441\u0442\u0440\u0435\u0446"
    ],
    "name:und_x_variant":[
        "Bystshets"
    ],
    "qs_pg:aaroncc":"UA",
    "qs_pg:gn_country":"UA",
    "qs_pg:gn_fcode":"PPL",
    "qs_pg:gn_pop":362,
    "qs_pg:name":"Bystrets",
    "qs_pg:photos_9r":0,
    "qs_pg:photos_sr":0,
    "qs_pg:pop_sr":2,
    "qs_pg:qs_pg_placetype":"locality",
    "wof:name":"Bystrets",
    "wof:placetype":"locality",
    "wof:population":362
},
  "geometry": {"coordinates":[24.69435,48.12262],"type":"Point"}
}