{
  "type": "Feature",
  "properties": {
    "gn:admin1_code":"21.0",
    "gn:asciiname":"Sliporid",
    "gn:country_code":"UA",
    "gn:dem":168,
    "gn:feature_class":"P",
    "gn:feature_code":"PPL",
    "gn:name":"Sliporid",
    "gn:population":0,
    "gn:timezone":"Europe/Kiev",
    "iso:country":"UA",
    "name:ukr_x_preferred":[
        "Sliporid"
    ],
    "name:ukr_x_variant":[
        "\u0421\u043b\u0456\u043f\u043e\u0440\u0456\u0434"
    ],
    "name:und_x_variant":[
        "Sleporod"
    ],
    "wof:name":"Sliporid",
    "wof:placetype":"locality"
},
  "geometry": {"coordinates":[33.85037,51.64809],"type":"Point"}
}