{
  "type": "Feature",
  "properties": {
    "gn:admin1_code":"7.0",
    "gn:asciiname":"Nyzhniy Byshkyn",
    "gn:country_code":"UA",
    "gn:dem":97,
    "gn:feature_class":"P",
    "gn:feature_code":"PPL",
    "gn:name":"Nyzhniy Byshkyn",
    "gn:population":0,
    "gn:timezone":"Europe/Kiev",
    "iso:country":"UA",
    "name:ukr_x_preferred":[
        "Nyzhniy Byshkyn"
    ],
    "name:ukr_x_variant":[
        "\u041d\u0438\u0436\u043d\u0456\u0439 \u0411\u0438\u0448\u043a\u0438\u043d"
    ],
    "name:und_x_variant":[
        "Nizhniy Byshkin",
        "Nizhniy Russkiy Bishkin",
        "Nizhniy Bishkin"
    ],
    "wof:name":"Nyzhniy Byshkyn",
    "wof:placetype":"locality"
},
  "geometry": {"coordinates":[36.40732,49.53017],"type":"Point"}
}