{
  "type": "Feature",
  "properties": {
    "iso:country":"UA",
    "name:eng_x_preferred":[
        "Skalistoye"
    ],
    "name:rus_x_historical":[
        "\u0422\u0430\u0432-\u0411\u043e\u0434\u0440\u0430\u0301\u043a"
    ],
    "name:rus_x_preferred":[
        "\u0422\u0430\u0432-\u0411\u043e\u0434\u0440\u0430\u0301\u043a"
    ],
    "name:rus_x_variant":[
        "\u0421\u043a\u0430\u043b\u0438\u0441\u0442\u043e\u0435"
    ],
    "name:ukr_x_preferred":[
        "\u0421\u043a\u0430\u043b\u0438\u0441\u0442\u0435"
    ],
    "qs:a0":"\u0423\u043a\u0440\u0430\u0457\u043d\u0430",
    "qs:a1":"*\u041a\u0440\u0438\u043c",
    "qs:a1_alt":"Krym",
    "qs:a1r":"0",
    "qs:a2":"\u0411\u0430\u0445\u0447\u0438\u0441\u0430\u0440\u0430\u0439\u0441\u044c\u043a\u0438\u0439",
    "qs:a2_alt":"Bakhchysarais'kyi",
    "qs:adm0":"\u0423\u043a\u0440\u0430\u0457\u043d\u0430",
    "qs:la_lc":"*",
    "qs:level":"locality",
    "qs:loc":"\u0421\u043a\u0430\u043b\u0438\u0441\u0442\u0435",
    "qs:loc_alt":"Skalyste",
    "qs:pop":0,
    "qs:type":"buffered point",
    "wof:name":"\u0421\u043a\u0430\u043b\u0438\u0441\u0442\u0435",
    "wof:placetype":"locality"
},
  "geometry": {"coordinates":[33.978564,44.803296],"type":"Point"}
}