{
  "type": "Feature",
  "properties": {
    "gn:admin1_code":"9.0",
    "gn:asciiname":"Pogorel'tsy",
    "gn:country_code":"UA",
    "gn:dem":253,
    "gn:feature_class":"P",
    "gn:feature_code":"PPL",
    "gn:name":"Pogorel\u2019tsy",
    "gn:population":0,
    "gn:timezone":"Europe/Kiev",
    "iso:country":"UA",
    "wof:name":"Pogorel'tsy",
    "wof:placetype":"locality"
},
  "geometry": {"coordinates":[26.31399,49.93005],"type":"Point"}
}