{
  "type": "Feature",
  "properties": {
    "gn:admin1_code":"13.0",
    "gn:asciiname":"Chervona Sloboda",
    "gn:country_code":"UA",
    "gn:dem":160,
    "gn:feature_class":"P",
    "gn:feature_code":"PPL",
    "gn:name":"Chervona Sloboda",
    "gn:population":0,
    "gn:timezone":"Europe/Kiev",
    "iso:country":"UA",
    "name:ukr_x_preferred":[
        "\u0427\u0435\u0440\u0432\u043e\u043d\u0430 \u0421\u043b\u043e\u0431\u043e\u0434\u0430"
    ],
    "name:und_x_variant":[
        "Charvona Sloboda",
        "Chervonaya Sloboda"
    ],
    "wof:name":"Chervona Sloboda",
    "wof:placetype":"locality"
},
  "geometry": {"coordinates":[29.68407,50.38856],"type":"Point"}
}