{
  "type": "Feature",
  "properties": {
    "gn:admin1_code":"22.0",
    "gn:asciiname":"Ponikva",
    "gn:country_code":"UA",
    "gn:dem":341,
    "gn:feature_class":"P",
    "gn:feature_code":"PPL",
    "gn:name":"Ponikva",
    "gn:population":0,
    "gn:timezone":"Europe/Kiev",
    "iso:country":"UA",
    "name:bos_x_preferred":[
        "Ponikva"
    ],
    "name:ceb_x_preferred":[
        "Ponikva"
    ],
    "name:hrv_x_preferred":[
        "Ponikva"
    ],
    "name:nld_x_preferred":[
        "Ponikva"
    ],
    "name:pol_x_preferred":[
        "Ponikva"
    ],
    "name:ron_x_preferred":[
        "Ponikva"
    ],
    "name:sco_x_preferred":[
        "Ponikva"
    ],
    "name:slv_x_preferred":[
        "Ponikva"
    ],
    "name:szl_x_preferred":[
        "Ponikva"
    ],
    "name:ukr_x_preferred":[
        "\u041f\u043e\u043d\u0438\u043a\u0432\u0430"
    ],
    "wof:name":"Ponikva",
    "wof:placetype":"locality"
},
  "geometry": {"coordinates":[25.13333,49.81667],"type":"Point"}
}