{
  "type": "Feature",
  "properties": {
    "gn:admin1_code":"22.0",
    "gn:asciiname":"Ponikva",
    "gn:country_code":"UA",
    "gn:dem":341,
    "gn:feature_class":"P",
    "gn:feature_code":"PPL",
    "gn:name":"Ponikva",
    "gn:population":0,
    "gn:timezone":"Europe/Kiev",
    "iso:country":"UA",
    "wof:name":"Ponikva",
    "wof:placetype":"locality"
},
  "geometry": {"coordinates":[25.13333,49.81667],"type":"Point"}
}