{
  "type": "Feature",
  "properties": {
    "gn:admin1_code":"17.0",
    "gn:asciiname":"Tkachenka",
    "gn:country_code":"UA",
    "gn:dem":146,
    "gn:feature_class":"P",
    "gn:feature_code":"PPL",
    "gn:name":"Tkachenka",
    "gn:population":0,
    "gn:timezone":"Europe/Kiev",
    "iso:country":"UA",
    "name:ukr_x_preferred":[
        "Tkachenka"
    ],
    "name:ukr_x_variant":[
        "\u0422\u043a\u0430\u0447\u0435\u043d\u043a\u0430"
    ],
    "name:und_x_variant":[
        "Mirony",
        "Imeni Tkachenko",
        "Tkachenko"
    ],
    "wof:name":"Tkachenka",
    "wof:placetype":"locality"
},
  "geometry": {"coordinates":[29.30322,47.47281],"type":"Point"}
}