{
  "type": "Feature",
  "properties": {
    "gn:admin1_code":"5.0",
    "gn:admin2_code":"713172",
    "gn:asciiname":"Khromove",
    "gn:country_code":"UA",
    "gn:dem":126,
    "gn:elevation":"95.0",
    "gn:feature_class":"P",
    "gn:feature_code":"PPL",
    "gn:name":"Khromove",
    "gn:population":0,
    "gn:timezone":"Europe/Kiev",
    "iso:country":"UA",
    "name:deu_x_preferred":[
        "Chromowe"
    ],
    "name:hye_x_historical":[
        "\u0531\u0580\u057f\u0575\u0578\u0574\u0578\u057e\u057d\u056f\u0578\u0565"
    ],
    "name:hye_x_preferred":[
        "\u0531\u0580\u057f\u0575\u0578\u0574\u0578\u057e\u057d\u056f\u0578\u0565"
    ],
    "name:rus_x_historical":[
        "\u0410\u0440\u0442\u0435\u043c\u043e\u0432\u0441\u043a\u043e\u0435"
    ],
    "name:rus_x_preferred":[
        "\u0410\u0440\u0442\u0435\u043c\u043e\u0432\u0441\u043a\u043e\u0435"
    ],
    "name:rus_x_variant":[
        "\u0425\u0440\u043e\u043c\u043e\u0432\u043e"
    ],
    "name:ukr_x_historical":[
        "Artemivs'ke",
        "\u0410\u0440\u0442\u0435\u043c\u0456\u0432\u0441\u044c\u043a\u0435"
    ],
    "name:ukr_x_preferred":[
        "\u0425\u0440\u043e\u043c\u043e\u0432\u0435"
    ],
    "name:ukr_x_variant":[
        "Artemivs'ke",
        "\u0410\u0440\u0442\u0435\u043c\u0456\u0432\u0441\u044c\u043a\u0435"
    ],
    "wof:name":"Khromove",
    "wof:placetype":"locality"
},
  "geometry": {"coordinates":[37.94858,48.60057000000001],"type":"Point"}
}