{
  "type": "Feature",
  "properties": {
    "gn:admin1_code":"25.0",
    "gn:asciiname":"Shyshlivtsi",
    "gn:country_code":"UA",
    "gn:dem":106,
    "gn:feature_class":"P",
    "gn:feature_code":"PPL",
    "gn:name":"Shyshlivtsi",
    "gn:population":0,
    "gn:timezone":"Europe/Uzhgorod",
    "iso:country":"UA",
    "name:ukr_x_preferred":[
        "Shyshlivtsi"
    ],
    "name:ukr_x_variant":[
        "\u0428\u0438\u0448\u043b\u0456\u0432\u0446\u0456"
    ],
    "name:und_x_variant":[
        "Shishlovtsy"
    ],
    "wof:name":"Shyshlivtsi",
    "wof:placetype":"locality"
},
  "geometry": {"coordinates":[22.20507000000001,48.57021],"type":"Point"}
}