{
  "type": "Feature",
  "properties": {
    "gn:population":3512,
    "iso:country":"UA",
    "name:ara_x_preferred":[
        "\u0628\u0644\u0627\u0647\u0648\u062f\u0627\u062a\u0646\u064a\u060c \u062f\u0648\u0646\u064a\u062a\u0633 \u0643\u0627"
    ],
    "name:deu_x_preferred":[
        "Blahodatne"
    ],
    "name:eng_x_preferred":[
        "Blahodatne"
    ],
    "name:hye_x_preferred":[
        "\u0532\u056c\u0561\u0563\u0578\u0564\u0561\u057f\u0576\u0578\u0565"
    ],
    "name:lav_x_preferred":[
        "Blahodatne"
    ],
    "name:rus_x_preferred":[
        "\u0411\u043b\u0430\u0433\u043e\u0434\u0430\u0442\u043d\u043e\u0435"
    ],
    "name:ukr_x_preferred":[
        "\u0411\u043b\u0430\u0433\u043e\u0434\u0430\u0442\u043d\u0435"
    ],
    "name:unk_x_variant":[
        "Donetsko-Amvrosiyevka"
    ],
    "qs:a0":"\u0423\u043a\u0440\u0430\u0457\u043d\u0430",
    "qs:a1":"*\u0414\u043e\u043d\u0435\u0446\u044c\u043a\u0430",
    "qs:a1_alt":"Donets'ka",
    "qs:a1r":"0",
    "qs:a2":"\u0410\u043c\u0432\u0440\u043e\u0441\u0456\u0457\u0432\u0441\u044c\u043a\u0438\u0439",
    "qs:a2_alt":"Amvrosiivs'kyi",
    "qs:adm0":"\u0423\u043a\u0440\u0430\u0457\u043d\u0430",
    "qs:la_lc":"*",
    "qs:level":"locality",
    "qs:loc":"\u0411\u043b\u0430\u0433\u043e\u0434\u0430\u0442\u043d\u0435",
    "qs:loc_alt":"Blahodatne",
    "qs:pop":0,
    "qs:type":"buffered point",
    "wd:wordcount":125,
    "wof:name":"\u0411\u043b\u0430\u0433\u043e\u0434\u0430\u0442\u043d\u0435",
    "wof:placetype":"locality",
    "wof:population":3512
},
  "geometry": {"coordinates":[38.483569,47.874087],"type":"Point"}
}