{
  "type": "Feature",
  "properties": {
    "gn:admin1_code":"3.0",
    "gn:asciiname":"Nova-Lyashkuvka",
    "gn:cc2":"UA",
    "gn:country_code":"UA",
    "gn:dem":194,
    "gn:feature_class":"P",
    "gn:feature_code":"PPL",
    "gn:name":"Nova-Lyashkuvka",
    "gn:population":0,
    "gn:timezone":"Europe/Kiev",
    "iso:country":"UA",
    "name:und_x_variant":[
        "Novaya Lyashkovka",
        "Nova-Lyashkuvka"
    ],
    "wof:name":"Nova-Lyashkuvka",
    "wof:placetype":"locality"
},
  "geometry": {"coordinates":[25.78333,48.41667],"type":"Point"}
}