{
  "type": "Feature",
  "properties": {
    "gn:admin1_code":"9.0",
    "gn:asciiname":"Miklashi",
    "gn:country_code":"UA",
    "gn:dem":251,
    "gn:feature_class":"P",
    "gn:feature_code":"PPL",
    "gn:name":"Miklashi",
    "gn:population":0,
    "gn:timezone":"Europe/Kiev",
    "iso:country":"UA",
    "wof:name":"Miklashi",
    "wof:placetype":"locality"
},
  "geometry": {"coordinates":[26.35946,49.9537],"type":"Point"}
}