{
  "type": "Feature",
  "properties": {
    "gn:admin1_code":"24.0",
    "gn:asciiname":"Polis'ke",
    "gn:country_code":"UA",
    "gn:dem":162,
    "gn:feature_class":"P",
    "gn:feature_code":"PPL",
    "gn:name":"Polis\u2019ke",
    "gn:population":0,
    "gn:timezone":"Europe/Kiev",
    "iso:country":"UA",
    "name:ukr_x_preferred":[
        "Polis\u2019ke"
    ],
    "name:ukr_x_variant":[
        "\u041f\u043e\u043b\u0456\u0441\u044c\u043a\u0435"
    ],
    "name:und_x_variant":[
        "Pyasechno",
        "Polesskoye"
    ],
    "wof:name":"Polis'ke",
    "wof:placetype":"locality"
},
  "geometry": {"coordinates":[24.51248,51.47908],"type":"Point"}
}