{
  "type": "Feature",
  "properties": {
    "gn:admin1_code":"24.0",
    "gn:asciiname":"Samovolya",
    "gn:country_code":"UA",
    "gn:dem":215,
    "gn:feature_class":"P",
    "gn:feature_code":"PPL",
    "gn:name":"Samovolya",
    "gn:population":0,
    "gn:timezone":"Europe/Kiev",
    "iso:country":"UA",
    "name:ukr_x_preferred":[
        "Samovolya"
    ],
    "name:ukr_x_variant":[
        "\u0421\u0430\u043c\u043e\u0432\u043e\u043b\u044f"
    ],
    "wof:name":"Samovolya",
    "wof:placetype":"locality"
},
  "geometry": {"coordinates":[24.41892,50.57393],"type":"Point"}
}