{
  "type": "Feature",
  "properties": {
    "gn:admin1_code":"15.0",
    "gn:asciiname":"Martsiny",
    "gn:cc2":"UA",
    "gn:country_code":"UA",
    "gn:dem":204,
    "gn:feature_class":"P",
    "gn:feature_code":"PPL",
    "gn:name":"Martsiny",
    "gn:population":0,
    "gn:timezone":"Europe/Kiev",
    "iso:country":"UA",
    "name:und_x_variant":[
        "Marciny",
        "Martsiny"
    ],
    "wof:name":"Martsiny",
    "wof:placetype":"locality"
},
  "geometry": {"coordinates":[24.88333,50.13333],"type":"Point"}
}