{
  "type": "Feature",
  "properties": {
    "gn:admin1_code":"7.0",
    "gn:asciiname":"Podol'okh",
    "gn:country_code":"UA",
    "gn:dem":101,
    "gn:feature_class":"P",
    "gn:feature_code":"PPL",
    "gn:name":"Podol\u2019okh",
    "gn:population":0,
    "gn:timezone":"Europe/Kiev",
    "iso:country":"UA",
    "name:ukr_x_preferred":[
        "Podol\u2019okh"
    ],
    "name:ukr_x_variant":[
        "\u041f\u043e\u0434\u043e\u043b\u044c\u043e\u0445"
    ],
    "wof:name":"Podol'okh",
    "wof:placetype":"locality"
},
  "geometry": {"coordinates":[36.36554,49.82853],"type":"Point"}
}