{
  "type": "Feature",
  "properties": {
    "gn:admin1_code":"18.0",
    "gn:asciiname":"Pylypenky",
    "gn:country_code":"UA",
    "gn:dem":89,
    "gn:feature_class":"P",
    "gn:feature_code":"PPL",
    "gn:name":"Pylypenky",
    "gn:population":0,
    "gn:timezone":"Europe/Kiev",
    "iso:country":"UA",
    "name:ukr_x_preferred":[
        "Pylypenky"
    ],
    "name:ukr_x_variant":[
        "\u041f\u0438\u043b\u0438\u043f\u0435\u043d\u043a\u0438"
    ],
    "wof:name":"Pylypenky",
    "wof:placetype":"locality"
},
  "geometry": {"coordinates":[33.96136,49.03442],"type":"Point"}
}