{
  "type": "Feature",
  "properties": {
    "gn:admin1_code":"27.0",
    "gn:asciiname":"Horikhove",
    "gn:country_code":"UA",
    "gn:dem":214,
    "gn:feature_class":"P",
    "gn:feature_code":"PPL",
    "gn:name":"Horikhove",
    "gn:population":0,
    "gn:timezone":"Europe/Kiev",
    "iso:country":"UA",
    "name:rus_x_historical":[
        "\u041e\u0440\u0435\u0445\u043e\u0432"
    ],
    "name:rus_x_preferred":[
        "\u041e\u0440\u0435\u0445\u043e\u0432"
    ],
    "name:ukr_x_preferred":[
        "Horikhove"
    ],
    "name:ukr_x_variant":[
        "\u0413\u043e\u0440\u0456\u0445\u043e\u0432\u0435"
    ],
    "name:und_x_variant":[
        "Novoye Stroyeniye"
    ],
    "wof:name":"Horikhove",
    "wof:placetype":"locality"
},
  "geometry": {"coordinates":[29.15,50.21667],"type":"Point"}
}