{
  "type": "Feature",
  "properties": {
    "gn:admin1_code":"27.0",
    "gn:asciiname":"Bat'kivshchyna",
    "gn:country_code":"UA",
    "gn:dem":145,
    "gn:feature_class":"P",
    "gn:feature_code":"PPL",
    "gn:name":"Bat\u2019kivshchyna",
    "gn:population":0,
    "gn:timezone":"Europe/Kiev",
    "iso:country":"UA",
    "name:rus_x_preferred":[
        "Bat\u2019kovshchina"
    ],
    "name:ukr_x_preferred":[
        "Bat\u2019kivshchyna"
    ],
    "name:ukr_x_variant":[
        "\u0411\u0430\u0442\u044c\u043a\u0456\u0432\u0449\u0438\u043d\u0430"
    ],
    "wof:name":"Bat'kivshchyna",
    "wof:placetype":"locality"
},
  "geometry": {"coordinates":[28.98161,51.06914],"type":"Point"}
}