{
  "type": "Feature",
  "properties": {
    "gn:admin1_code":"27.0",
    "gn:asciiname":"Prykhid",
    "gn:country_code":"UA",
    "gn:dem":198,
    "gn:feature_class":"P",
    "gn:feature_code":"PPL",
    "gn:name":"Prykhid",
    "gn:population":0,
    "gn:timezone":"Europe/Kiev",
    "iso:country":"UA",
    "name:ukr_x_preferred":[
        "Prykhid"
    ],
    "name:ukr_x_variant":[
        "\u041f\u0440\u0438\u0445\u0456\u0434"
    ],
    "name:und_x_variant":[
        "Prikhod"
    ],
    "wof:name":"Prykhid",
    "wof:placetype":"locality"
},
  "geometry": {"coordinates":[27.36522,50.9698],"type":"Point"}
}