{
  "type": "Feature",
  "properties": {
    "iso:country":"UA",
    "name:arm_x_preferred":[
        "\u0533\u0580\u0561\u0576\u056b\u057f\u0576\u0578\u0565"
    ],
    "name:chi_x_preferred":[
        "\u683c\u62c9\u5c3c\u7279\u6d85"
    ],
    "name:crh_x_preferred":[
        "Granitne"
    ],
    "name:deu_x_preferred":[
        "Hranitne"
    ],
    "name:dut_x_preferred":[
        "Hranitne"
    ],
    "name:eng_x_preferred":[
        "Hranitne"
    ],
    "name:fra_x_preferred":[
        "Hranitne"
    ],
    "name:fre_x_preferred":[
        "Hranitne"
    ],
    "name:ger_x_preferred":[
        "Hranitne"
    ],
    "name:hye_x_preferred":[
        "\u0533\u0580\u0561\u0576\u056b\u057f\u0576\u0578\u0565"
    ],
    "name:pol_x_preferred":[
        "Hranitne"
    ],
    "name:ron_x_preferred":[
        "Hranitne"
    ],
    "name:rum_x_preferred":[
        "Hranitne"
    ],
    "name:rus_x_preferred":[
        "\u0413\u0440\u0430\u043d\u0438\u0442\u043d\u043e\u0435"
    ],
    "name:sah_x_preferred":[
        "\u0413\u0440\u0430\u043d\u0438\u0442\u043d\u043e\u0435"
    ],
    "name:ukr_x_preferred":[
        "\u0413\u0440\u0430\u043d\u0456\u0442\u043d\u0435"
    ],
    "name:zho_x_preferred":[
        "\u683c\u62c9\u5c3c\u7279\u6d85"
    ],
    "qs:a0":"\u0423\u043a\u0440\u0430\u0457\u043d\u0430",
    "qs:a1":"*\u0416\u0438\u0442\u043e\u043c\u0438\u0440\u0441\u044c\u043a\u0430",
    "qs:a1_alt":"Zhytomyrs'ka",
    "qs:a1r":"0",
    "qs:a2":"\u041c\u0430\u043b\u0438\u043d\u0441\u044c\u043a\u0438\u0439",
    "qs:a2_alt":"Malyns'kyi",
    "qs:adm0":"\u0423\u043a\u0440\u0430\u0457\u043d\u0430",
    "qs:la_lc":"*",
    "qs:level":"locality",
    "qs:loc":"\u0413\u0440\u0430\u043d\u0456\u0442\u043d\u0435",
    "qs:loc_alt":"Hranitne",
    "qs:pop":0,
    "qs:type":"buffered point",
    "wd:wordcount":88,
    "wof:name":"\u0413\u0440\u0430\u043d\u0456\u0442\u043d\u0435",
    "wof:placetype":"locality"
},
  "geometry": {"coordinates":[29.346545,50.745298],"type":"Point"}
}