{
  "type": "Feature",
  "properties": {
    "gn:admin1_code":"27.0",
    "gn:asciiname":"Ocheretyanka",
    "gn:country_code":"UA",
    "gn:dem":225,
    "gn:feature_class":"P",
    "gn:feature_code":"PPL",
    "gn:name":"Ocheretyanka",
    "gn:population":0,
    "gn:timezone":"Europe/Kiev",
    "iso:country":"UA",
    "name:ukr_x_preferred":[
        "\u041e\u0447\u0435\u0440\u0435\u0442\u044f\u043d\u043a\u0430"
    ],
    "name:und_x_variant":[
        "Ocheretenka",
        "Ocheretyanka",
        "Ocheretyana"
    ],
    "wof:name":"Ocheretyanka",
    "wof:placetype":"locality"
},
  "geometry": {"coordinates":[28.15282,50.50908],"type":"Point"}
}