{
  "type": "Feature",
  "properties": {
    "gn:admin1_code":"4.0",
    "gn:asciiname":"Desyatin'shchina",
    "gn:country_code":"UA",
    "gn:dem":125,
    "gn:feature_class":"P",
    "gn:feature_code":"PPL",
    "gn:name":"Desyatin\u2019shchina",
    "gn:population":0,
    "gn:timezone":"Europe/Kiev",
    "iso:country":"UA",
    "name:rus_x_preferred":[
        "Desyatin\u2019shchina"
    ],
    "wof:name":"Desyatin'shchina",
    "wof:placetype":"locality"
},
  "geometry": {"coordinates":[35.65,48.21667],"type":"Point"}
}