{
  "type": "Feature",
  "properties": {
    "gn:admin1_code":"5.0",
    "gn:asciiname":"Strelka",
    "gn:country_code":"UA",
    "gn:dem":-1,
    "gn:feature_class":"P",
    "gn:feature_code":"PPL",
    "gn:name":"Strelka",
    "gn:population":0,
    "gn:timezone":"Europe/Kiev",
    "iso:country":"UA",
    "name:ceb_x_preferred":[
        "Strelka"
    ],
    "name:deu_x_preferred":[
        "Strelka"
    ],
    "name:est_x_preferred":[
        "Strelka"
    ],
    "name:hye_x_preferred":[
        "\u054d\u057f\u0580\u0565\u056c\u056f\u0561"
    ],
    "name:ita_x_preferred":[
        "Strelka"
    ],
    "name:rus_x_preferred":[
        "\u0421\u0442\u0440\u0435\u043b\u043a\u0430"
    ],
    "name:slk_x_preferred":[
        "Strelka"
    ],
    "name:swe_x_preferred":[
        "Strelka"
    ],
    "name:ukr_x_preferred":[
        "\u0421\u0442\u0440\u0456\u043b\u043a\u0430"
    ],
    "name:und_x_variant":[
        "Strela"
    ],
    "wof:name":"Strelka",
    "wof:placetype":"locality"
},
  "geometry": {"coordinates":[38.13472,47.05194],"type":"Point"}
}