{
  "type": "Feature",
  "properties": {
    "gn:admin1_code":"5.0",
    "gn:asciiname":"Strelka",
    "gn:country_code":"UA",
    "gn:dem":-1,
    "gn:feature_class":"P",
    "gn:feature_code":"PPL",
    "gn:name":"Strelka",
    "gn:population":0,
    "gn:timezone":"Europe/Kiev",
    "iso:country":"UA",
    "name:und_x_variant":[
        "Strela",
        "Strelka"
    ],
    "wof:name":"Strelka",
    "wof:placetype":"locality"
},
  "geometry": {"coordinates":[38.13472,47.05194],"type":"Point"}
}