{
  "type": "Feature",
  "properties": {
    "iso:country":"UA",
    "name:ast_x_preferred":[
        "Borki"
    ],
    "name:ces_x_preferred":[
        "Borki"
    ],
    "name:che_x_preferred":[
        "\u0411\u043e\u0440\u043a\u0438"
    ],
    "name:eng_x_preferred":[
        "Borki"
    ],
    "name:fra_x_preferred":[
        "Borki"
    ],
    "name:nan_x_preferred":[
        "Borki"
    ],
    "name:pol_x_preferred":[
        "Borki"
    ],
    "name:rus_x_preferred":[
        "\u0411\u043e\u0440\u043a\u0438"
    ],
    "name:tat_x_preferred":[
        "\u0411\u043e\u0440\u043a\u0438"
    ],
    "name:ukr_x_preferred":[
        "Birky"
    ],
    "name:ukr_x_variant":[
        "\u0411\u0456\u0440\u043a\u0438",
        "\u0411\u043e\u0440\u043a\u0438"
    ],
    "qs:a0":"\u0423\u043a\u0440\u0430\u0457\u043d\u0430",
    "qs:a1":"*\u041f\u043e\u043b\u0442\u0430\u0432\u0441\u044c\u043a\u0430",
    "qs:a1_alt":"Poltavs'ka",
    "qs:a1r":"0",
    "qs:a2":"\u0417\u0456\u043d\u044c\u043a\u0456\u0432\u0441\u044c\u043a\u0438\u0439",
    "qs:a2_alt":"Zin'kivs'kyi",
    "qs:adm0":"\u0423\u043a\u0440\u0430\u0457\u043d\u0430",
    "qs:la_lc":"*",
    "qs:level":"locality",
    "qs:loc":"\u0411\u0456\u0440\u043a\u0438",
    "qs:loc_alt":"Birky",
    "qs:pop":0,
    "qs:type":"buffered point",
    "wd:wordcount":98,
    "wof:name":"\u0411\u0456\u0440\u043a\u0438",
    "wof:placetype":"locality"
},
  "geometry": {"coordinates":[34.174773,50.122124],"type":"Point"}
}