{
  "type": "Feature",
  "properties": {
    "gn:admin1_code":"26.0",
    "gn:asciiname":"Vershyna Druha",
    "gn:country_code":"UA",
    "gn:dem":214,
    "gn:feature_class":"P",
    "gn:feature_code":"PPL",
    "gn:name":"Vershyna Druha",
    "gn:population":0,
    "gn:timezone":"Europe/Zaporozhye",
    "iso:country":"UA",
    "name:ukr_x_preferred":[
        "Vershyna Druha"
    ],
    "name:ukr_x_variant":[
        "\u0412\u0435\u0440\u0448\u0438\u043d\u0430 \u0414\u0440\u0443\u0433\u0430"
    ],
    "name:und_x_variant":[
        "Vershino",
        "Vershyna Druga",
        "Vershina Vtoraya"
    ],
    "wof:name":"Vershyna Druha",
    "wof:placetype":"locality"
},
  "geometry": {"coordinates":[36.49669,47.22835],"type":"Point"}
}