{
  "type": "Feature",
  "properties": {
    "iso:country":"UA",
    "name:rus_x_preferred":[
        "Ol\u2019khovatyy"
    ],
    "name:ukr_x_preferred":[
        "Vil\u2019khovatyy"
    ],
    "name:ukr_x_variant":[
        "\u0412\u0456\u043b\u044c\u0445\u043e\u0432\u0430\u0442\u0438\u0439"
    ],
    "name:und_x_variant":[
        "Vil\u2019khovati"
    ],
    "qs:a0":"\u0423\u043a\u0440\u0430\u0457\u043d\u0430",
    "qs:a1":"*\u0417\u0430\u043a\u0430\u0440\u043f\u0430\u0442\u0441\u044c\u043a\u0430",
    "qs:a1_alt":"Zakarpats'ka",
    "qs:a1r":"0",
    "qs:a2":"\u0420\u0430\u0445\u0456\u0432\u0441\u044c\u043a\u0438\u0439",
    "qs:a2_alt":"Rakhivs'kyi",
    "qs:adm0":"\u0423\u043a\u0440\u0430\u0457\u043d\u0430",
    "qs:la_lc":"*",
    "qs:level":"locality",
    "qs:loc":"\u0412\u0456\u043b\u044c\u0445\u043e\u0432\u0430\u0442\u0438\u0439",
    "qs:loc_alt":"Vil'khovatyi",
    "qs:pop":0,
    "qs:type":"buffered point",
    "wof:name":"\u0412\u0456\u043b\u044c\u0445\u043e\u0432\u0430\u0442\u0438\u0439",
    "wof:placetype":"locality"
},
  "geometry": {"coordinates":[24.163226,48.019578],"type":"Point"}
}