{
  "type": "Feature",
  "properties": {
    "gn:admin1_code":"7.0",
    "gn:asciiname":"Morokyne",
    "gn:country_code":"UA",
    "gn:dem":179,
    "gn:feature_class":"P",
    "gn:feature_code":"PPL",
    "gn:name":"Morokyne",
    "gn:population":0,
    "gn:timezone":"Europe/Kiev",
    "iso:country":"UA",
    "name:ukr_x_preferred":[
        "Morokyne"
    ],
    "name:ukr_x_variant":[
        "\u041c\u043e\u0440\u043e\u043a\u0438\u043d\u0435"
    ],
    "name:und_x_variant":[
        "Morokino"
    ],
    "wof:name":"Morokyne",
    "wof:placetype":"locality"
},
  "geometry": {"coordinates":[36.64177,48.94403],"type":"Point"}
}