{
  "type": "Feature",
  "properties": {
    "gn:admin1_code":"19.0",
    "gn:asciiname":"Vereteno",
    "gn:country_code":"UA",
    "gn:dem":172,
    "gn:feature_class":"P",
    "gn:feature_code":"PPL",
    "gn:name":"Vereteno",
    "gn:population":0,
    "gn:timezone":"Europe/Kiev",
    "iso:country":"UA",
    "name:ukr_x_preferred":[
        "Vereteno"
    ],
    "name:ukr_x_variant":[
        "\u0412\u0435\u0440\u0435\u0442\u0435\u043d\u043e"
    ],
    "name:und_x_variant":[
        "Vereteniche",
        "Veretyno"
    ],
    "wof:name":"Vereteno",
    "wof:placetype":"locality"
},
  "geometry": {"coordinates":[26.02512,51.25796],"type":"Point"}
}