{
  "type": "Feature",
  "properties": {
    "gn:admin1_code":"1.0",
    "gn:asciiname":"Cherneche",
    "gn:country_code":"UA",
    "gn:dem":96,
    "gn:feature_class":"P",
    "gn:feature_code":"PPL",
    "gn:name":"Cherneche",
    "gn:population":0,
    "gn:timezone":"Europe/Kiev",
    "iso:country":"UA",
    "name:ukr_x_preferred":[
        "Cherneche"
    ],
    "name:ukr_x_variant":[
        "\u0427\u0435\u0440\u043d\u0435\u0447\u0435"
    ],
    "wof:name":"Cherneche",
    "wof:placetype":"locality"
},
  "geometry": {"coordinates":[32.67264,49.04238],"type":"Point"}
}