{
  "type": "Feature",
  "properties": {
    "iso:country":"UA",
    "name:ukr_x_preferred":[
        "\u042f\u0441\u0435\u043d\u0456\u0432-\u041f\u0456\u043b\u044c\u043d\u0438\u0439"
    ],
    "name:und_x_variant":[
        "Yasenuv Pol\u2019ny"
    ],
    "qs:a0":"\u0423\u043a\u0440\u0430\u0457\u043d\u0430",
    "qs:a1":"*\u0406\u0432\u0430\u043d\u043e-\u0424\u0440\u0430\u043d\u043a\u0456\u0432\u0441\u044c\u043a\u0430",
    "qs:a1_alt":"Ivano-Frankivs'ka",
    "qs:a1r":"0",
    "qs:a2":"\u0413\u043e\u0440\u043e\u0434\u0435\u043d\u043a\u0456\u0432\u0441\u044c\u043a\u0438\u0439",
    "qs:a2_alt":"Horodenkivs'kyi",
    "qs:adm0":"\u0423\u043a\u0440\u0430\u0457\u043d\u0430",
    "qs:la_lc":"*",
    "qs:level":"locality",
    "qs:loc":"\u042f\u0441\u0435\u043d\u0456\u0432-\u041f\u0456\u043b\u044c\u043d\u0438\u0439",
    "qs:loc_alt":"Yaseniv-Pil'nyi",
    "qs:pop":0,
    "qs:type":"buffered point",
    "wof:name":"\u042f\u0441\u0435\u043d\u0456\u0432-\u041f\u0456\u043b\u044c\u043d\u0438\u0439",
    "wof:placetype":"locality"
},
  "geometry": {"coordinates":[25.518581,48.625799],"type":"Point"}
}