{
  "type": "Feature",
  "properties": {
    "gn:admin1_code":"23.0",
    "gn:asciiname":"Belyy Kamen'",
    "gn:country_code":"UA",
    "gn:dem":166,
    "gn:feature_class":"P",
    "gn:feature_code":"PPL",
    "gn:name":"Belyy Kamen\u2019",
    "gn:population":0,
    "gn:timezone":"Europe/Kiev",
    "iso:country":"UA",
    "name:und_x_variant":[
        "Bely Kamen\u2019",
        "Belyy Kamen\u2019"
    ],
    "wof:name":"Belyy Kamen'",
    "wof:placetype":"locality"
},
  "geometry": {"coordinates":[29.37025,48.27041],"type":"Point"}
}