{
  "type": "Feature",
  "properties": {
    "gn:admin1_code":"9.0",
    "gn:asciiname":"Maydan-Labun'",
    "gn:country_code":"UA",
    "gn:dem":232,
    "gn:feature_class":"P",
    "gn:feature_code":"PPL",
    "gn:name":"Maydan-Labun\u2019",
    "gn:population":0,
    "gn:timezone":"Europe/Kiev",
    "iso:country":"UA",
    "name:ukr_x_preferred":[
        "\u041c\u0430\u0439\u0434\u0430\u043d-\u041b\u0430\u0431\u0443\u043d\u044c"
    ],
    "name:und_x_variant":[
        "Maydan Labunskiy",
        "Maydan-Labun\u2019"
    ],
    "wof:name":"Maydan-Labun'",
    "wof:placetype":"locality"
},
  "geometry": {"coordinates":[27.38548,50.30502],"type":"Point"}
}