{
  "type": "Feature",
  "properties": {
    "gn:admin1_code":"24.0",
    "gn:asciiname":"Pidhattya",
    "gn:country_code":"UA",
    "gn:dem":183,
    "gn:feature_class":"P",
    "gn:feature_code":"PPL",
    "gn:name":"Pidhattya",
    "gn:population":0,
    "gn:timezone":"Europe/Kiev",
    "iso:country":"UA",
    "name:rus_x_preferred":[
        "Podhat\u2019ye"
    ],
    "name:ukr_x_preferred":[
        "Pidhattya"
    ],
    "name:ukr_x_variant":[
        "\u041f\u0456\u0434\u0433\u0430\u0442\u0442\u044f"
    ],
    "name:und_x_variant":[
        "Podkhvache",
        "Podkhache"
    ],
    "wof:name":"Pidhattya",
    "wof:placetype":"locality"
},
  "geometry": {"coordinates":[25.78898,51.27121],"type":"Point"}
}