{
  "type": "Feature",
  "properties": {
    "gn:country":"UA",
    "gn:fcode":"PPL",
    "gn:population":3115,
    "iso:country":"UA",
    "name:bel_x_preferred":[
        "\u0420\u044b\u0445\u0442\u044b\u0447\u044b"
    ],
    "name:ceb_x_preferred":[
        "Rykhtichi"
    ],
    "name:ceb_x_variant":[
        "Rykhtychi"
    ],
    "name:che_x_preferred":[
        "\u0420\u0438\u0445\u0442\u0438\u0447\u0438"
    ],
    "name:eng_x_preferred":[
        "Rykhtychi"
    ],
    "name:fin_x_preferred":[
        "Ryh\u2019tyt\u0161\u0456"
    ],
    "name:nan_x_preferred":[
        "Rykhtychi"
    ],
    "name:nno_x_preferred":[
        "Rykhtytsji"
    ],
    "name:nob_x_preferred":[
        "Rykhtytsji"
    ],
    "name:pol_x_preferred":[
        "Rychcice"
    ],
    "name:ron_x_preferred":[
        "R\u00eeht\u00eeci"
    ],
    "name:rus_x_preferred":[
        "\u0420\u0438\u0445\u0442\u0438\u0447\u0456"
    ],
    "name:rus_x_variant":[
        "\u0420\u0438\u0445\u0442\u0438\u0447\u0438",
        "\u0420\u044b\u0445\u0442\u0438\u0447\u0438"
    ],
    "name:ukr_x_preferred":[
        "\u0420\u0438\u0445\u0442\u0438\u0447\u0456"
    ],
    "name:und_x_variant":[
        "Rikhtichi"
    ],
    "name:zho_x_preferred":[
        "\u91cc\u8d6b\u5b63\u5947"
    ],
    "qs_pg:aaroncc":"UA",
    "qs_pg:gn_country":"UA",
    "qs_pg:gn_fcode":"PPL",
    "qs_pg:gn_pop":3115,
    "qs_pg:name":"Rykhtichi",
    "qs_pg:photos_9r":0,
    "qs_pg:photos_sr":0,
    "qs_pg:pop_sr":4,
    "qs_pg:qs_pg_placetype":"locality",
    "wof:name":"Rykhtichi",
    "wof:placetype":"locality",
    "wof:population":3115
},
  "geometry": {"coordinates":[23.55662,49.38511],"type":"Point"}
}