{
  "type": "Feature",
  "properties": {
    "gn:admin1_code":"14.0",
    "gn:asciiname":"Malynove",
    "gn:country_code":"UA",
    "gn:dem":74,
    "gn:feature_class":"P",
    "gn:feature_code":"PPL",
    "gn:name":"Malynove",
    "gn:population":0,
    "gn:timezone":"Europe/Zaporozhye",
    "iso:country":"UA",
    "name:ukr_x_preferred":[
        "Malynove"
    ],
    "name:ukr_x_variant":[
        "\u041c\u0430\u043b\u0438\u043d\u043e\u0432\u0435"
    ],
    "name:und_x_variant":[
        "Malinov",
        "Malinovyy"
    ],
    "wof:name":"Malynove",
    "wof:placetype":"locality"
},
  "geometry": {"coordinates":[39.42554000000001,48.72044],"type":"Point"}
}