{
  "type": "Feature",
  "properties": {
    "gn:admin1_code":"2.0",
    "gn:asciiname":"Vol'nytsya",
    "gn:country_code":"UA",
    "gn:dem":135,
    "gn:feature_class":"P",
    "gn:feature_code":"PPL",
    "gn:name":"Vol\u2019nytsya",
    "gn:population":0,
    "gn:timezone":"Europe/Kiev",
    "iso:country":"UA",
    "name:rus_x_preferred":[
        "Vol\u2019nitsa"
    ],
    "name:ukr_x_preferred":[
        "Vol\u2019nytsya"
    ],
    "name:ukr_x_variant":[
        "\u0412\u043e\u043b\u044c\u043d\u0438\u0446\u044f"
    ],
    "name:und_x_variant":[
        "Zagorovka",
        "Lebedin",
        "Lendin"
    ],
    "wof:name":"Vol'nytsya",
    "wof:placetype":"locality"
},
  "geometry": {"coordinates":[32.39811,51.17126],"type":"Point"}
}