{
  "type": "Feature",
  "properties": {
    "gn:admin1_code":"21.0",
    "gn:asciiname":"Korolivshchyna",
    "gn:country_code":"UA",
    "gn:dem":172,
    "gn:feature_class":"P",
    "gn:feature_code":"PPL",
    "gn:name":"Korolivshchyna",
    "gn:population":0,
    "gn:timezone":"Europe/Kiev",
    "iso:country":"UA",
    "name:ukr_x_preferred":[
        "Korolivshchyna"
    ],
    "name:ukr_x_variant":[
        "\u041a\u043e\u0440\u043e\u043b\u0456\u0432\u0449\u0438\u043d\u0430"
    ],
    "name:und_x_variant":[
        "Korolevshchina"
    ],
    "wof:name":"Korolivshchyna",
    "wof:placetype":"locality"
},
  "geometry": {"coordinates":[33.19124,50.7962],"type":"Point"}
}