{
  "type": "Feature",
  "properties": {
    "gn:admin1_code":"21.0",
    "gn:asciiname":"Yahanivka",
    "gn:country_code":"UA",
    "gn:dem":169,
    "gn:feature_class":"P",
    "gn:feature_code":"PPL",
    "gn:name":"Yahanivka",
    "gn:population":0,
    "gn:timezone":"Europe/Kiev",
    "iso:country":"UA",
    "name:ukr_x_preferred":[
        "Yahanivka"
    ],
    "name:ukr_x_variant":[
        "\u042f\u0433\u0430\u043d\u0456\u0432\u043a\u0430"
    ],
    "name:und_x_variant":[
        "Yaganovka"
    ],
    "wof:name":"Yahanivka",
    "wof:placetype":"locality"
},
  "geometry": {"coordinates":[33.57383,50.51294],"type":"Point"}
}