{
  "type": "Feature",
  "properties": {
    "gn:admin1_code":"21.0",
    "gn:asciiname":"Vil'shana",
    "gn:country_code":"UA",
    "gn:dem":127,
    "gn:feature_class":"P",
    "gn:feature_code":"PPL",
    "gn:name":"Vil\u2019shana",
    "gn:population":0,
    "gn:timezone":"Europe/Kiev",
    "iso:country":"UA",
    "name:eng_x_preferred":[
        "Ol'shana"
    ],
    "name:rus_x_preferred":[
        "\u041e\u043b\u044c\u0448\u0430\u043d\u0430"
    ],
    "name:ukr_x_preferred":[
        "Vil\u2019shana"
    ],
    "name:ukr_x_variant":[
        "\u0412\u0456\u043b\u044c\u0448\u0430\u043d\u0430"
    ],
    "name:und_x_variant":[
        "Oleshnya",
        "Ol\u2019shana"
    ],
    "wof:name":"Vil'shana",
    "wof:placetype":"locality"
},
  "geometry": {"coordinates":[34.02231,50.82055],"type":"Point"}
}