{
  "type": "Feature",
  "properties": {
    "gn:admin1_code":"3.0",
    "gn:asciiname":"Nyzhni Synivtsi",
    "gn:country_code":"UA",
    "gn:dem":365,
    "gn:feature_class":"P",
    "gn:feature_code":"PPL",
    "gn:name":"Nyzhni Synivtsi",
    "gn:population":0,
    "gn:timezone":"Europe/Kiev",
    "iso:country":"UA",
    "name:und_x_variant":[
        "Nizhniye Sinevtsy",
        "Nyzhni Synivtsi"
    ],
    "wof:name":"Nyzhni Synivtsi",
    "wof:placetype":"locality"
},
  "geometry": {"coordinates":[26.13191,48.00888],"type":"Point"}
}