{
  "type": "Feature",
  "properties": {
    "gn:admin1_code":"13.0",
    "gn:asciiname":"Potashnya",
    "gn:country_code":"UA",
    "gn:dem":150,
    "gn:feature_class":"P",
    "gn:feature_code":"PPL",
    "gn:name":"Potashnya",
    "gn:population":0,
    "gn:timezone":"Europe/Kiev",
    "iso:country":"UA",
    "name:ukr_x_preferred":[
        "Potashnya"
    ],
    "name:ukr_x_variant":[
        "\u041f\u043e\u0442\u0430\u0448\u043d\u044f"
    ],
    "wof:name":"Potashnya",
    "wof:placetype":"locality"
},
  "geometry": {"coordinates":[29.75587,50.69661],"type":"Point"}
}