{
  "type": "Feature",
  "properties": {
    "iso:country":"UA",
    "name:ceb_x_preferred":[
        "Pukov"
    ],
    "name:eng_x_preferred":[
        "Pukiv"
    ],
    "name:pol_x_preferred":[
        "Puk\u00f3w"
    ],
    "name:ron_x_preferred":[
        "Pukiv"
    ],
    "name:rus_x_preferred":[
        "\u041f\u0443\u043a\u043e\u0432"
    ],
    "name:ukr_x_preferred":[
        "\u041f\u0443\u043a\u0456\u0432"
    ],
    "name:unk_x_variant":[
        "Pukuv"
    ],
    "name:zho_x_preferred":[
        "\u666e\u57fa\u592b"
    ],
    "qs:a0":"\u0423\u043a\u0440\u0430\u0457\u043d\u0430",
    "qs:a1":"*\u0406\u0432\u0430\u043d\u043e-\u0424\u0440\u0430\u043d\u043a\u0456\u0432\u0441\u044c\u043a\u0430",
    "qs:a1_alt":"Ivano-Frankivs'ka",
    "qs:a1r":"0",
    "qs:a2":"\u0420\u043e\u0433\u0430\u0442\u0438\u043d\u0441\u044c\u043a\u0438\u0439",
    "qs:a2_alt":"Rohatyns'kyi",
    "qs:adm0":"\u0423\u043a\u0440\u0430\u0457\u043d\u0430",
    "qs:la_lc":"*",
    "qs:level":"locality",
    "qs:loc":"\u041f\u0443\u043a\u0456\u0432",
    "qs:loc_alt":"Pukiv",
    "qs:pop":0,
    "qs:type":"buffered point",
    "wd:wordcount":25,
    "wof:name":"\u041f\u0443\u043a\u0456\u0432",
    "wof:placetype":"locality"
},
  "geometry": {"coordinates":[24.687561,49.397534],"type":"Point"}
}