{
  "type": "Feature",
  "properties": {
    "gn:admin1_code":"18.0",
    "gn:asciiname":"Podozirka",
    "gn:country_code":"UA",
    "gn:dem":113,
    "gn:feature_class":"P",
    "gn:feature_code":"PPL",
    "gn:name":"Podozirka",
    "gn:population":0,
    "gn:timezone":"Europe/Kiev",
    "iso:country":"UA",
    "name:rus_x_preferred":[
        "Podoz\u00ebrka"
    ],
    "name:ukr_x_preferred":[
        "Podozirka"
    ],
    "name:ukr_x_variant":[
        "\u041f\u043e\u0434\u043e\u0437\u0456\u0440\u043a\u0430"
    ],
    "name:und_x_variant":[
        "Pidozerka",
        "Pidozirka"
    ],
    "wof:name":"Podozirka",
    "wof:placetype":"locality"
},
  "geometry": {"coordinates":[34.35042,50.11396],"type":"Point"}
}