{
  "type": "Feature",
  "properties": {
    "gn:admin1_code":"5.0",
    "gn:asciiname":"Shaloshnykove",
    "gn:country_code":"UA",
    "gn:dem":167,
    "gn:feature_class":"P",
    "gn:feature_code":"PPL",
    "gn:name":"Shaloshnykove",
    "gn:population":0,
    "gn:timezone":"Europe/Kiev",
    "iso:country":"UA",
    "name:ukr_x_preferred":[
        "Shaloshnykove"
    ],
    "name:ukr_x_variant":[
        "\u0428\u0430\u043b\u043e\u0448\u043d\u0438\u043a\u043e\u0432\u0435"
    ],
    "name:und_x_variant":[
        "Pitchnikova"
    ],
    "wof:name":"Shaloshnykove",
    "wof:placetype":"locality"
},
  "geometry": {"coordinates":[38.45462,47.95975],"type":"Point"}
}