{
  "type": "Feature",
  "properties": {
    "gn:admin1_code":"16.0",
    "gn:asciiname":"Privol'nyanskiy",
    "gn:country_code":"UA",
    "gn:dem":89,
    "gn:feature_class":"P",
    "gn:feature_code":"PPL",
    "gn:name":"Privol\u2019nyanskiy",
    "gn:population":0,
    "gn:timezone":"Europe/Kiev",
    "iso:country":"UA",
    "name:und_x_variant":[
        "Khutor Privol\u2019nyanskiy",
        "Privol\u2019nyanskiy"
    ],
    "wof:name":"Privol'nyanskiy",
    "wof:placetype":"locality"
},
  "geometry": {"coordinates":[32.23479,47.70016],"type":"Point"}
}