{
  "type": "Feature",
  "properties": {
    "gn:admin1_code":"18.0",
    "gn:asciiname":"Honchari",
    "gn:country_code":"UA",
    "gn:dem":137,
    "gn:feature_class":"P",
    "gn:feature_code":"PPL",
    "gn:name":"Honchari",
    "gn:population":0,
    "gn:timezone":"Europe/Kiev",
    "iso:country":"UA",
    "name:ukr_x_preferred":[
        "Honchari"
    ],
    "name:ukr_x_variant":[
        "\u0413\u043e\u043d\u0447\u0430\u0440\u0456"
    ],
    "wof:name":"Honchari",
    "wof:placetype":"locality"
},
  "geometry": {"coordinates":[33.95646,49.75977],"type":"Point"}
}