{
  "type": "Feature",
  "properties": {
    "gn:population":4530,
    "iso:country":"UA",
    "name:rus_x_preferred":[
        "\u041f\u0430\u0441\u0456\u0447\u043d\u0430"
    ],
    "name:ukr_x_preferred":[
        "\u041f\u0430\u0441\u0456\u0447\u043d\u0430"
    ],
    "name:und_x_variant":[
        "Pasechna"
    ],
    "qs:a0":"\u0423\u043a\u0440\u0430\u0457\u043d\u0430",
    "qs:a1":"*\u0406\u0432\u0430\u043d\u043e-\u0424\u0440\u0430\u043d\u043a\u0456\u0432\u0441\u044c\u043a\u0430",
    "qs:a1_alt":"Ivano-Frankivs'ka",
    "qs:a1r":"0",
    "qs:a2":"\u041d\u0430\u0434\u0432\u0456\u0440\u043d\u044f\u043d\u0441\u044c\u043a\u0438\u0439",
    "qs:a2_alt":"Nadvirnians'kyi",
    "qs:adm0":"\u0423\u043a\u0440\u0430\u0457\u043d\u0430",
    "qs:la_lc":"*",
    "qs:level":"locality",
    "qs:loc":"\u041f\u0430\u0441\u0456\u0447\u043d\u0430",
    "qs:loc_alt":"Pasichna",
    "qs:pop":0,
    "qs:type":"buffered point",
    "wof:name":"\u041f\u0430\u0441\u0456\u0447\u043d\u0430",
    "wof:placetype":"locality",
    "wof:population":4530
},
  "geometry": {"coordinates":[24.408161,48.563615],"type":"Point"}
}