{
  "type": "Feature",
  "properties": {
    "gn:admin1_code":"15.0",
    "gn:asciiname":"Repekhuv",
    "gn:country_code":"UA",
    "gn:dem":306,
    "gn:feature_class":"P",
    "gn:feature_code":"PPL",
    "gn:name":"Repekhuv",
    "gn:population":0,
    "gn:timezone":"Europe/Kiev",
    "iso:country":"UA",
    "wof:name":"Repekhuv",
    "wof:placetype":"locality"
},
  "geometry": {"coordinates":[24.34521,49.54395],"type":"Point"}
}