{
  "type": "Feature",
  "properties": {
    "gn:admin1_code":"5.0",
    "gn:asciiname":"Krasnopillya",
    "gn:country_code":"UA",
    "gn:dem":128,
    "gn:feature_class":"P",
    "gn:feature_code":"PPL",
    "gn:name":"Krasnopillya",
    "gn:population":0,
    "gn:timezone":"Europe/Kiev",
    "iso:country":"UA",
    "name:ukr_x_preferred":[
        "\u041a\u0440\u0430\u0441\u043d\u043e\u043f\u0456\u043b\u043b\u044f"
    ],
    "name:und_x_variant":[
        "Krasnopol\u2019ye",
        "Krasnopillya"
    ],
    "wof:name":"Krasnopillya",
    "wof:placetype":"locality"
},
  "geometry": {"coordinates":[38.11069000000001,47.53944],"type":"Point"}
}