{
  "type": "Feature",
  "properties": {
    "gn:admin1_code":"27.0",
    "gn:asciiname":"Zhytyntsi",
    "gn:country_code":"UA",
    "gn:dem":249,
    "gn:feature_class":"P",
    "gn:feature_code":"PPL",
    "gn:name":"Zhytyntsi",
    "gn:population":0,
    "gn:timezone":"Europe/Kiev",
    "iso:country":"UA",
    "name:ukr_x_preferred":[
        "Zhytyntsi"
    ],
    "name:ukr_x_variant":[
        "\u0416\u0438\u0442\u0438\u043d\u0446\u0456"
    ],
    "name:und_x_variant":[
        "Zhitentsy"
    ],
    "wof:name":"Zhytyntsi",
    "wof:placetype":"locality"
},
  "geometry": {"coordinates":[28.54164,49.84936],"type":"Point"}
}