{
  "type": "Feature",
  "properties": {
    "gn:admin1_code":"4.0",
    "gn:asciiname":"Vasylivka-na-Dnipri",
    "gn:country_code":"UA",
    "gn:dem":74,
    "gn:feature_class":"P",
    "gn:feature_code":"PPL",
    "gn:name":"Vasylivka-na-Dnipri",
    "gn:population":0,
    "gn:timezone":"Europe/Kiev",
    "iso:country":"UA",
    "name:eng_x_preferred":[
        "Vasil'yevka-na Dnepre"
    ],
    "name:rus_x_preferred":[
        "\u0412\u0430\u0441\u0438\u043b\u0435\u0432\u043a\u0430 \u043d\u0430 \u0414\u043d\u0435\u043f\u0440\u0435"
    ],
    "name:ukr_x_preferred":[
        "Vasylivka-na-Dnipri"
    ],
    "name:ukr_x_variant":[
        "\u0412\u0430\u0441\u0438\u043b\u0456\u0432\u043a\u0430-\u043d\u0430-\u0414\u043d\u0456\u043f\u0440\u0456"
    ],
    "name:und_x_variant":[
        "Vasil\u2019yevka",
        "Vasil\u2019yevka-na Dnepre"
    ],
    "wof:name":"Vasylivka-na-Dnipri",
    "wof:placetype":"locality"
},
  "geometry": {"coordinates":[35.2075,48.19833],"type":"Point"}
}