{
  "type": "Feature",
  "properties": {
    "gn:admin1_code":"27.0",
    "gn:asciiname":"Litky",
    "gn:country_code":"UA",
    "gn:dem":190,
    "gn:feature_class":"P",
    "gn:feature_code":"PPL",
    "gn:name":"Litky",
    "gn:population":0,
    "gn:timezone":"Europe/Kiev",
    "iso:country":"UA",
    "name:bel_x_preferred":[
        "\u041b\u0456\u0442\u043a\u044b"
    ],
    "name:ceb_x_preferred":[
        "Litky"
    ],
    "name:deu_x_preferred":[
        "Litky"
    ],
    "name:fra_x_preferred":[
        "Litky"
    ],
    "name:pol_x_preferred":[
        "Litky"
    ],
    "name:ron_x_preferred":[
        "Litk\u00ee"
    ],
    "name:rus_x_preferred":[
        "\u041b\u0435\u0442\u043a\u0438"
    ],
    "name:ukr_x_preferred":[
        "Litky"
    ],
    "name:ukr_x_variant":[
        "\u041b\u0456\u0442\u043a\u0438"
    ],
    "name:und_x_variant":[
        "Litki",
        "Letki"
    ],
    "name:zho_x_preferred":[
        "\u5229\u7279\u57fa"
    ],
    "wof:name":"Litky",
    "wof:placetype":"locality"
},
  "geometry": {"coordinates":[28.42095,51.05073],"type":"Point"}
}