{
  "type": "Feature",
  "properties": {
    "gn:admin1_code":"8.0",
    "gn:asciiname":"Havrylivka Persha",
    "gn:country_code":"UA",
    "gn:dem":5,
    "gn:feature_class":"P",
    "gn:feature_code":"PPL",
    "gn:name":"Havrylivka Persha",
    "gn:population":0,
    "gn:timezone":"Europe/Kiev",
    "iso:country":"UA",
    "name:ukr_x_preferred":[
        "\u0413\u0430\u0432\u043f\u0438\u043b\u0456\u0432\u043a\u0430 \u041f\u0435\u0440\u0448\u0430"
    ],
    "wof:name":"Havrylivka Persha",
    "wof:placetype":"locality"
},
  "geometry": {"coordinates":[33.41492,46.18514],"type":"Point"}
}