{
  "type": "Feature",
  "properties": {
    "gn:admin1_code":"24.0",
    "gn:asciiname":"Zapol'ye",
    "gn:country_code":"UA",
    "gn:dem":163,
    "gn:feature_class":"P",
    "gn:feature_code":"PPL",
    "gn:name":"Zapol\u2019ye",
    "gn:population":0,
    "gn:timezone":"Europe/Kiev",
    "iso:country":"UA",
    "name:rus_x_preferred":[
        "Zapol\u2019ye"
    ],
    "name:rus_x_variant":[
        "\u0417\u0430\u043f\u043e\u043b\u044c\u0435"
    ],
    "wof:name":"Zapol'ye",
    "wof:placetype":"locality"
},
  "geometry": {"coordinates":[24.69609,51.52831],"type":"Point"}
}