{
  "type": "Feature",
  "properties": {
    "iso:country":"UA",
    "name:eng_x_preferred":[
        "Ber\u00ebzovaya Rudka"
    ],
    "name:rus_x_preferred":[
        "\u0411\u0435\u0440\u0435\u0437\u043e\u0432\u0430\u044f \u0420\u0443\u0434\u043a\u0430"
    ],
    "name:ukr_x_preferred":[
        "Berezova Rudka"
    ],
    "name:ukr_x_variant":[
        "\u0411\u0435\u0440\u0435\u0437\u043e\u0432\u0430 \u0420\u0443\u0434\u043a\u0430"
    ],
    "name:unk_x_variant":[
        "Ber\u00ebzovaya Rudka"
    ],
    "qs:a0":"\u0423\u043a\u0440\u0430\u0457\u043d\u0430",
    "qs:a1":"*\u041f\u043e\u043b\u0442\u0430\u0432\u0441\u044c\u043a\u0430",
    "qs:a1_alt":"Poltavs'ka",
    "qs:a1r":"0",
    "qs:a2":"\u041f\u0438\u0440\u044f\u0442\u0438\u043d\u0441\u044c\u043a\u0438\u0439",
    "qs:a2_alt":"Pyriatyns'kyi",
    "qs:adm0":"\u0423\u043a\u0440\u0430\u0457\u043d\u0430",
    "qs:la_lc":"*",
    "qs:level":"locality",
    "qs:loc":"\u0411\u0435\u0440\u0435\u0437\u043e\u0432\u0430 \u0420\u0443\u0434\u043a\u0430",
    "qs:loc_alt":"Berezova Rudka",
    "qs:pop":0,
    "qs:type":"buffered point",
    "wof:name":"\u0411\u0435\u0440\u0435\u0437\u043e\u0432\u0430 \u0420\u0443\u0434\u043a\u0430",
    "wof:placetype":"locality"
},
  "geometry": {"coordinates":[32.249173,50.309657],"type":"Point"}
}