{
  "type": "Feature",
  "properties": {
    "gn:admin1_code":"24.0",
    "gn:asciiname":"Brunetivka",
    "gn:country_code":"UA",
    "gn:dem":166,
    "gn:feature_class":"P",
    "gn:feature_code":"PPL",
    "gn:name":"Brunetivka",
    "gn:population":0,
    "gn:timezone":"Europe/Kiev",
    "iso:country":"UA",
    "name:ukr_x_preferred":[
        "Brunetivka"
    ],
    "name:ukr_x_variant":[
        "\u0411\u0440\u0443\u043d\u0435\u0442\u0456\u0432\u043a\u0430"
    ],
    "name:und_x_variant":[
        "Brunetuvka",
        "Brunetovka"
    ],
    "wof:name":"Brunetivka",
    "wof:placetype":"locality"
},
  "geometry": {"coordinates":[24.54472,51.47865],"type":"Point"}
}