{
  "type": "Feature",
  "properties": {
    "gn:admin1_code":"7.0",
    "gn:asciiname":"Lukashivka",
    "gn:country_code":"UA",
    "gn:dem":97,
    "gn:feature_class":"P",
    "gn:feature_code":"PPL",
    "gn:name":"Lukashivka",
    "gn:population":0,
    "gn:timezone":"Europe/Kiev",
    "iso:country":"UA",
    "name:rus_x_preferred":[
        "\u041b\u0443\u043a\u0430\u0448\u043e\u0432\u043a\u0430"
    ],
    "name:ukr_x_preferred":[
        "Lukashivka"
    ],
    "name:ukr_x_variant":[
        "\u041b\u0443\u043a\u0430\u0448\u0456\u0432\u043a\u0430"
    ],
    "name:und_x_variant":[
        "Lukashevka",
        "Lukashovka"
    ],
    "wof:name":"Lukashivka",
    "wof:placetype":"locality"
},
  "geometry": {"coordinates":[35.47775,49.18367],"type":"Point"}
}