{
  "type": "Feature",
  "properties": {
    "gn:admin1_code":"23.0",
    "gn:asciiname":"Zarudyntsi",
    "gn:country_code":"UA",
    "gn:dem":245,
    "gn:feature_class":"P",
    "gn:feature_code":"PPL",
    "gn:name":"Zarudyntsi",
    "gn:population":0,
    "gn:timezone":"Europe/Kiev",
    "iso:country":"UA",
    "name:ukr_x_preferred":[
        "\u0417\u0430\u0440\u0443\u0434\u0438\u043d\u0446\u0456"
    ],
    "name:und_x_variant":[
        "Zarudintsy"
    ],
    "wof:name":"Zarudyntsi",
    "wof:placetype":"locality"
},
  "geometry": {"coordinates":[28.93133,48.92666],"type":"Point"}
}