{
  "type": "Feature",
  "properties": {
    "gn:admin1_code":"2.0",
    "gn:asciiname":"Kopachiv",
    "gn:country_code":"UA",
    "gn:dem":114,
    "gn:feature_class":"P",
    "gn:feature_code":"PPL",
    "gn:name":"Kopachiv",
    "gn:population":0,
    "gn:timezone":"Europe/Kiev",
    "iso:country":"UA",
    "name:rus_x_preferred":[
        "Kopach\u00ebv"
    ],
    "name:ukr_x_preferred":[
        "Kopachiv"
    ],
    "name:ukr_x_variant":[
        "\u041a\u043e\u043f\u0430\u0447\u0456\u0432"
    ],
    "name:und_x_variant":[
        "Kopach\u00ebva"
    ],
    "wof:name":"Kopachiv",
    "wof:placetype":"locality"
},
  "geometry": {"coordinates":[31.07574,51.22149],"type":"Point"}
}