{
  "type": "Feature",
  "properties": {
    "gn:admin1_code":"8.0",
    "gn:asciiname":"Babenkivka Druha",
    "gn:country_code":"UA",
    "gn:dem":7,
    "gn:feature_class":"P",
    "gn:feature_code":"PPL",
    "gn:name":"Babenkivka Druha",
    "gn:population":0,
    "gn:timezone":"Europe/Kiev",
    "iso:country":"UA",
    "name:ukr_x_preferred":[
        "\u0411\u0430\u0431\u0435\u043d\u043a\u0456\u0432\u043a\u0430 \u0414\u0440\u0443\u0433\u0430"
    ],
    "name:und_x_variant":[
        "Babenkovka Vtoraya",
        "Babenkivka Druha"
    ],
    "wof:name":"Babenkivka Druha",
    "wof:placetype":"locality"
},
  "geometry": {"coordinates":[33.36389,46.20193],"type":"Point"}
}