{
  "type": "Feature",
  "properties": {
    "iso:country":"UA",
    "name:ara_x_preferred":[
        "\u0623\u0646\u0627\u0646\u064a\u0641"
    ],
    "name:bel_x_preferred":[
        "\u0410\u043d\u0430\u043d\u044c\u0435\u045e"
    ],
    "name:bul_x_preferred":[
        "\u0410\u043d\u0430\u043d\u0438\u0435\u0432"
    ],
    "name:ces_x_preferred":[
        "Ananjiv"
    ],
    "name:crh_x_preferred":[
        "Ananyiv"
    ],
    "name:deu_x_preferred":[
        "Ananjiw"
    ],
    "name:eng_x_preferred":[
        "Ananyiv"
    ],
    "name:fas_x_preferred":[
        "\u0622\u0646\u0627\u0646\u0626\u06cc\u0648"
    ],
    "name:fas_x_variant":[
        "\u0622\u0646\u0627\u0646\u0626\u06cc\u0641"
    ],
    "name:fra_x_preferred":[
        "Ananiv"
    ],
    "name:heb_x_preferred":[
        "\u05d0\u05e0\u05e0\u05d9\u05d9\u05d1"
    ],
    "name:hsb_x_preferred":[
        "Ananjiw"
    ],
    "name:hye_x_preferred":[
        "\u0531\u0576\u0561\u0576\u056b\u0587"
    ],
    "name:ita_x_preferred":[
        "Anan'\u00efv"
    ],
    "name:kat_x_preferred":[
        "\u10d0\u10dc\u10d0\u10dc\u10d8\u10d4\u10d5\u10d8"
    ],
    "name:kaz_x_preferred":[
        "\u0410\u043d\u0430\u043d\u044c\u0435\u0432"
    ],
    "name:lav_x_preferred":[
        "Ana\u0146jiva"
    ],
    "name:lit_x_preferred":[
        "Ananjivas"
    ],
    "name:nno_x_preferred":[
        "Ananjiv"
    ],
    "name:nob_x_preferred":[
        "Ananjiv"
    ],
    "name:nor_x_preferred":[
        "Ananjiv"
    ],
    "name:pol_x_preferred":[
        "Ana\u0144jiw"
    ],
    "name:pol_x_variant":[
        "Ananiw"
    ],
    "name:ron_x_preferred":[
        "Ananiev"
    ],
    "name:rus_x_preferred":[
        "\u0410\u043d\u0430\u043d\u044c\u0435\u0432"
    ],
    "name:rus_x_variant":[
        "Anan\u2019yev"
    ],
    "name:sah_x_preferred":[
        "\u0410\u043d\u0430\u043d\u044c\u0435\u0432"
    ],
    "name:spa_x_preferred":[
        "Ananiv"
    ],
    "name:tat_x_preferred":[
        "\u0410\u043d\u0430\u043d\u044c\u0438\u0432"
    ],
    "name:ukr_x_preferred":[
        "\u0410\u043d\u0430\u043d\u044c\u0457\u0432"
    ],
    "name:ukr_x_variant":[
        "Anan\u2019yiv"
    ],
    "name:und_x_variant":[
        "Ananjew"
    ],
    "name:vie_x_preferred":[
        "Ananiv"
    ],
    "name:zho_x_preferred":[
        "\u963f\u7d0d\u5c3c\u8036\u592b"
    ],
    "qs:a0":"\u0423\u043a\u0440\u0430\u0457\u043d\u0430",
    "qs:a1":"*\u041e\u0434\u0435\u0441\u044c\u043a\u0430",
    "qs:a1_alt":"Odes'ka",
    "qs:a1r":"0",
    "qs:a2":"\u0410\u043d\u0430\u043d\u044c\u0457\u0432\u0441\u044c\u043a\u0438\u0439",
    "qs:a2_alt":"Anan'ivs'kyi",
    "qs:adm0":"\u0423\u043a\u0440\u0430\u0457\u043d\u0430",
    "qs:la_lc":"*",
    "qs:level":"locality",
    "qs:loc":"\u0410\u043d\u0430\u043d\u044c\u0457\u0432",
    "qs:loc_alt":"Anan'iv",
    "qs:pop":0,
    "qs:type":"buffered point",
    "wd:wordcount":282,
    "wof:name":"\u0410\u043d\u0430\u043d\u044c\u0457\u0432",
    "wof:placetype":"locality"
},
  "geometry": {"coordinates":[30.06073,47.686972],"type":"Point"}
}