{
  "type": "Feature",
  "properties": {
    "gn:admin1_code":"9.0",
    "gn:asciiname":"Vasilevka",
    "gn:country_code":"UA",
    "gn:dem":305,
    "gn:feature_class":"P",
    "gn:feature_code":"PPL",
    "gn:name":"Vasil\u00ebvka",
    "gn:population":0,
    "gn:timezone":"Europe/Kiev",
    "iso:country":"UA",
    "wof:name":"Vasilevka",
    "wof:placetype":"locality"
},
  "geometry": {"coordinates":[26.57679000000001,49.76172],"type":"Point"}
}