{
  "type": "Feature",
  "properties": {
    "gn:admin1_code":"24.0",
    "gn:asciiname":"Stril'che",
    "gn:country_code":"UA",
    "gn:dem":236,
    "gn:feature_class":"P",
    "gn:feature_code":"PPL",
    "gn:name":"Stril\u2019che",
    "gn:population":0,
    "gn:timezone":"Europe/Kiev",
    "iso:country":"UA",
    "name:rus_x_preferred":[
        "Strel\u2019che"
    ],
    "name:ukr_x_preferred":[
        "Stril\u2019che"
    ],
    "name:ukr_x_variant":[
        "\u0421\u0442\u0440\u0456\u043b\u044c\u0447\u0435"
    ],
    "name:und_x_variant":[
        "Stshel\u2019tse",
        "Strzelce",
        "Strel\u2019cha"
    ],
    "wof:name":"Stril'che",
    "wof:placetype":"locality"
},
  "geometry": {"coordinates":[24.57646,50.51177],"type":"Point"}
}