{
  "type": "Feature",
  "properties": {
    "gn:gn_country":"UA",
    "gn:gn_fcode":"PPL",
    "gn:gn_pop":12273,
    "gn:population":12273,
    "iso:country":"UA",
    "name:bel_x_preferred":[
        "\u0413\u043e\u0440\u0430\u0434 \u0421\u0432\u0456\u0442\u043b\u0430\u0434\u0430\u0440\u0441\u043a"
    ],
    "name:bul_x_preferred":[
        "\u0421\u0432\u0438\u0442\u043b\u043e\u0434\u0430\u0440\u0441\u043a"
    ],
    "name:deu_x_preferred":[
        "Switlodarsk"
    ],
    "name:eng_x_preferred":[
        "Svetlodarsk"
    ],
    "name:est_x_preferred":[
        "Svitlodarsk"
    ],
    "name:fas_x_preferred":[
        "\u0633\u0648\u06cc\u062a\u0644\u0648\u062f\u0627\u0631\u0633\u06a9"
    ],
    "name:fra_x_preferred":[
        "Svitlodarsk"
    ],
    "name:hsb_x_preferred":[
        "Switlodarsk"
    ],
    "name:hye_x_preferred":[
        "\u054d\u057e\u0565\u057f\u056c\u0578\u0564\u0561\u0580\u057d\u056f"
    ],
    "name:ita_x_preferred":[
        "Svitlodars'k"
    ],
    "name:kat_x_preferred":[
        "\u10e1\u10d5\u10d4\u10e2\u10da\u10dd\u10d3\u10d0\u10e0\u10e1\u10d9\u10d8"
    ],
    "name:lav_x_preferred":[
        "Svitlodarska"
    ],
    "name:nld_x_preferred":[
        "Svitlodarsk"
    ],
    "name:nno_x_preferred":[
        "Svitlodarsk"
    ],
    "name:nob_x_preferred":[
        "Svitlodarsk"
    ],
    "name:pol_x_preferred":[
        "Swit\u0142odarsk"
    ],
    "name:ron_x_preferred":[
        "Svitlodarsk"
    ],
    "name:rus_x_preferred":[
        "\u0421\u0432\u0435\u0442\u043b\u043e\u0434\u0430\u0440\u0441\u043a"
    ],
    "name:sco_x_preferred":[
        "Svitlodarsk"
    ],
    "name:sgs_x_preferred":[
        "Svietlodarskos"
    ],
    "name:tat_x_preferred":[
        "\u0421\u0432\u0438\u0442\u043b\u043e\u0434\u0430\u0440\u0441\u043a"
    ],
    "name:ukr_x_preferred":[
        "\u0421\u0432\u0456\u0442\u043b\u043e\u0434\u0430\u0440\u0441\u044c\u043a"
    ],
    "name:vie_x_preferred":[
        "Svitlodarsk"
    ],
    "name:zho_x_preferred":[
        "\u65af\u7dad\u7279\u6d1b\u9054\u723e\u897f\u514b"
    ],
    "qs_pg:aaroncc":"UA",
    "qs_pg:gn_country":"UA",
    "qs_pg:gn_fcode":"PPL",
    "qs_pg:gn_pop":12273,
    "qs_pg:name":"Svetlodarsk",
    "qs_pg:photos_9r":0,
    "qs_pg:photos_sr":0,
    "qs_pg:pop_sr":6,
    "qs_pg:qs_pg_placetype":"locality",
    "wof:name":"Svetlodarsk",
    "wof:placetype":"locality",
    "wof:population":12273
},
  "geometry": {"coordinates":[38.22331,48.43374],"type":"Point"}
}