{
  "type": "Feature",
  "properties": {
    "iso:country":"UA",
    "qs:a0":"\u0423\u043a\u0440\u0430\u0457\u043d\u0430",
    "qs:a1":"*\u041a\u0440\u0438\u043c",
    "qs:a1_alt":"Krym",
    "qs:a1r":"0",
    "qs:a2":"\u0421\u0456\u043c\u0444\u0435\u0440\u043e\u043f\u043e\u043b\u044c\u0441\u044c\u043a\u0438\u0439",
    "qs:a2_alt":"Simferopol's'kyi",
    "qs:adm0":"\u0423\u043a\u0440\u0430\u0457\u043d\u0430",
    "qs:la_lc":"*",
    "qs:level":"locality",
    "qs:loc":"\u041b\u0456\u043a\u0430\u0440\u0441\u0442\u0432\u0435\u043d\u043d\u0435",
    "qs:loc_alt":"Likarstvenne",
    "qs:pop":0,
    "qs:type":"buffered point",
    "wof:name":"\u041b\u0456\u043a\u0430\u0440\u0441\u0442\u0432\u0435\u043d\u043d\u0435",
    "wof:placetype":"locality"
},
  "geometry": {"coordinates":[33.819739,44.944158],"type":"Point"}
}