{
  "type": "Feature",
  "properties": {
    "gn:admin1_code":"15.0",
    "gn:asciiname":"Berteshuv",
    "gn:country_code":"UA",
    "gn:dem":300,
    "gn:feature_class":"P",
    "gn:feature_code":"PPL",
    "gn:name":"Berteshuv",
    "gn:population":0,
    "gn:timezone":"Europe/Kiev",
    "iso:country":"UA",
    "wof:name":"Berteshuv",
    "wof:placetype":"locality"
},
  "geometry": {"coordinates":[24.32638,49.53608],"type":"Point"}
}