{
  "type": "Feature",
  "properties": {
    "gn:admin1_code":"9.0",
    "gn:asciiname":"Stryhany",
    "gn:country_code":"UA",
    "gn:dem":210,
    "gn:feature_class":"P",
    "gn:feature_code":"PPL",
    "gn:name":"Stryhany",
    "gn:population":0,
    "gn:timezone":"Europe/Kiev",
    "iso:country":"UA",
    "name:ukr_x_preferred":[
        "Stryhany"
    ],
    "name:ukr_x_variant":[
        "\u0421\u0442\u0440\u0438\u0433\u0430\u043d\u0438"
    ],
    "name:und_x_variant":[
        "Strigany"
    ],
    "wof:name":"Stryhany",
    "wof:placetype":"locality"
},
  "geometry": {"coordinates":[26.78524,50.32149],"type":"Point"}
}