{
  "type": "Feature",
  "properties": {
    "gn:admin1_code":"21.0",
    "gn:asciiname":"Plotnykove",
    "gn:country_code":"UA",
    "gn:dem":166,
    "gn:feature_class":"P",
    "gn:feature_code":"PPL",
    "gn:name":"Plotnykove",
    "gn:population":0,
    "gn:timezone":"Europe/Kiev",
    "iso:country":"UA",
    "name:ukr_x_preferred":[
        "Plotnykove"
    ],
    "name:ukr_x_variant":[
        "\u041f\u043b\u043e\u0442\u043d\u0438\u043a\u043e\u0432\u0435"
    ],
    "name:und_x_variant":[
        "Plotnikovo"
    ],
    "wof:name":"Plotnykove",
    "wof:placetype":"locality"
},
  "geometry": {"coordinates":[33.85415,51.38404],"type":"Point"}
}