{
  "type": "Feature",
  "properties": {
    "gn:population":3364,
    "iso:country":"UA",
    "name:ceb_x_preferred":[
        "Kayiry"
    ],
    "name:deu_x_preferred":[
        "Kajiry"
    ],
    "name:eng_x_preferred":[
        "Kairy"
    ],
    "name:lav_x_preferred":[
        "Kajiri"
    ],
    "name:ron_x_preferred":[
        "Kaiir\u00ee"
    ],
    "name:rus_x_preferred":[
        "\u041a\u0430\u0457\u0440\u0438"
    ],
    "name:rus_x_variant":[
        "\u041a\u0430\u0438\u0440\u044b"
    ],
    "name:ukr_x_preferred":[
        "\u041a\u0430\u0457\u0440\u0438"
    ],
    "name:und_x_variant":[
        "Zapadnyye Kairy"
    ],
    "name:zho_x_preferred":[
        "\u5361\u4f0a\u91cc"
    ],
    "qs:a0":"\u0423\u043a\u0440\u0430\u0457\u043d\u0430",
    "qs:a1":"*\u0425\u0435\u0440\u0441\u043e\u043d\u0441\u044c\u043a\u0430",
    "qs:a1_alt":"Khersons'ka",
    "qs:a1r":"0",
    "qs:a2":"\u0413\u043e\u0440\u043d\u043e\u0441\u0442\u0430\u0457\u0432\u0441\u044c\u043a\u0438\u0439",
    "qs:a2_alt":"Hornostaivs'kyi",
    "qs:adm0":"\u0423\u043a\u0440\u0430\u0457\u043d\u0430",
    "qs:la_lc":"*",
    "qs:level":"locality",
    "qs:loc":"\u041a\u0430\u0457\u0440\u0438",
    "qs:loc_alt":"Kairy",
    "qs:pop":0,
    "qs:type":"buffered point",
    "wof:name":"\u041a\u0430\u0457\u0440\u0438",
    "wof:placetype":"locality",
    "wof:population":3364
},
  "geometry": {"coordinates":[33.703357,46.946789],"type":"Point"}
}