{
  "type": "Feature",
  "properties": {
    "gn:admin1_code":"15.0",
    "gn:asciiname":"Sukhodoly",
    "gn:country_code":"UA",
    "gn:dem":236,
    "gn:feature_class":"P",
    "gn:feature_code":"PPL",
    "gn:name":"Sukhodoly",
    "gn:population":0,
    "gn:timezone":"Europe/Kiev",
    "iso:country":"UA",
    "name:ceb_x_preferred":[
        "Sukhodoly"
    ],
    "name:pol_x_preferred":[
        "Suchodo\u0142y"
    ],
    "name:ron_x_preferred":[
        "Suhodol\u00ee"
    ],
    "name:rus_x_preferred":[
        "\u0421\u0443\u0445\u043e\u0434\u043e\u043b\u044b"
    ],
    "name:ukr_x_preferred":[
        "\u0421\u0443\u0445\u043e\u0434\u043e\u043b\u0438"
    ],
    "name:zho_x_preferred":[
        "\u8607\u970d\u591a\u5229"
    ],
    "wof:name":"Sukhodoly",
    "wof:placetype":"locality"
},
  "geometry": {"coordinates":[25.1109,50.0063],"type":"Point"}
}