{
  "type": "Feature",
  "properties": {
    "gn:population":9962,
    "iso:country":"UA",
    "name:rus_x_preferred":[
        "\u041f\u043e\u043a\u043e\u0442\u0438\u043b\u0456\u0432\u043a\u0430"
    ],
    "name:ukr_x_preferred":[
        "\u041f\u043e\u043a\u043e\u0442\u0438\u043b\u0456\u0432\u043a\u0430"
    ],
    "name:und_x_variant":[
        "Pokotilovka"
    ],
    "qs:a0":"\u0423\u043a\u0440\u0430\u0457\u043d\u0430",
    "qs:a1":"*\u0425\u0430\u0440\u043a\u0456\u0432\u0441\u044c\u043a\u0430",
    "qs:a1_alt":"Kharkivs'ka",
    "qs:a1r":"0",
    "qs:a2":"\u0425\u0430\u0440\u043a\u0456\u0432\u0441\u044c\u043a\u0438\u0439",
    "qs:a2_alt":"Kharkivs'kyi",
    "qs:adm0":"\u0423\u043a\u0440\u0430\u0457\u043d\u0430",
    "qs:la_lc":"*",
    "qs:level":"locality",
    "qs:loc":"\u041f\u043e\u043a\u043e\u0442\u0438\u043b\u0456\u0432\u043a\u0430",
    "qs:loc_alt":"Pokotylivka",
    "qs:pop":0,
    "qs:type":"buffered point",
    "wof:name":"\u041f\u043e\u043a\u043e\u0442\u0438\u043b\u0456\u0432\u043a\u0430",
    "wof:placetype":"locality",
    "wof:population":9962
},
  "geometry": {"coordinates":[36.173458,49.906474],"type":"Point"}
}