{
  "type": "Feature",
  "properties": {
    "gn:admin1_code":"17.0",
    "gn:asciiname":"Blonskoye",
    "gn:country_code":"UA",
    "gn:dem":10,
    "gn:feature_class":"P",
    "gn:feature_code":"PPL",
    "gn:name":"Blonskoye",
    "gn:population":0,
    "gn:timezone":"Europe/Kiev",
    "iso:country":"UA",
    "wof:name":"Blonskoye",
    "wof:placetype":"locality"
},
  "geometry": {"coordinates":[30.44443,46.86502],"type":"Point"}
}