{
  "type": "Feature",
  "properties": {
    "gn:admin1_code":"14.0",
    "gn:asciiname":"Novolymarivka",
    "gn:country_code":"UA",
    "gn:dem":70,
    "gn:feature_class":"P",
    "gn:feature_code":"PPL",
    "gn:name":"Novolymarivka",
    "gn:population":0,
    "gn:timezone":"Europe/Zaporozhye",
    "iso:country":"UA",
    "name:rus_x_preferred":[
        "Novolimar\u00ebvka"
    ],
    "name:ukr_x_preferred":[
        "\u041d\u043e\u0432\u043e\u043b\u0438\u043c\u0430\u0440\u0456\u0432\u043a\u0430"
    ],
    "wof:name":"Novolymarivka",
    "wof:placetype":"locality"
},
  "geometry": {"coordinates":[39.60333,49.27891],"type":"Point"}
}