{
  "type": "Feature",
  "properties": {
    "gn:admin1_code":"9.0",
    "gn:asciiname":"Shel'vov",
    "gn:country_code":"UA",
    "gn:dem":244,
    "gn:feature_class":"P",
    "gn:feature_code":"PPL",
    "gn:name":"Shel\u2019vov",
    "gn:population":0,
    "gn:timezone":"Europe/Kiev",
    "iso:country":"UA",
    "name:und_x_variant":[
        "Shel\u2019vovo",
        "Shel\u2019vov"
    ],
    "wof:name":"Shel'vov",
    "wof:placetype":"locality"
},
  "geometry": {"coordinates":[26.57948,50.07138],"type":"Point"}
}