{
  "type": "Feature",
  "properties": {
    "gn:admin1_code":"11.0",
    "gn:admin2_code":"705800",
    "gn:admin3_code":"11152899.0",
    "gn:asciiname":"Izobil'noye",
    "gn:country_code":"UA",
    "gn:dem":107,
    "gn:elevation":"101.0",
    "gn:feature_class":"P",
    "gn:feature_code":"PPL",
    "gn:name":"Izobil'noye",
    "gn:population":233,
    "gn:timezone":"Europe/Simferopol",
    "iso:country":"UA",
    "name:eng_x_preferred":[
        "Izobil'noye"
    ],
    "name:rus_x_historical":[
        "\u0410\u0441\u0430\u0301\u043d-\u0411\u0430\u0439 \u0422\u0430\u0442\u0430\u0301\u0440\u0441\u043a\u0438\u0439"
    ],
    "name:rus_x_preferred":[
        "\u0418\u0437\u043e\u0431\u0438\u043b\u044c\u043d\u043e\u0435"
    ],
    "name:rus_x_variant":[
        "\u0410\u0441\u0430\u0301\u043d-\u0411\u0430\u0439 \u0422\u0430\u0442\u0430\u0301\u0440\u0441\u043a\u0438\u0439"
    ],
    "name:ukr_x_preferred":[
        "\u0406\u0437\u043e\u0431\u0456\u043b\u044c\u043d\u0435"
    ],
    "wof:name":"Izobil'noye",
    "wof:placetype":"locality",
    "wof:population":233
},
  "geometry": {"coordinates":[35.20316,45.10845],"type":"Point"}
}