{
  "type": "Feature",
  "properties": {
    "gn:admin1_code":"09",
    "gn:asciiname":"Dubyna",
    "gn:country_code":"UA",
    "gn:dem":338,
    "gn:feature_class":"P",
    "gn:feature_code":"PPL",
    "gn:name":"Dubyna",
    "gn:population":0,
    "gn:timezone":"Europe/Kiev",
    "iso:country":"UA",
    "name:deu_x_preferred":[
        "Dubyna"
    ],
    "name:hye_x_preferred":[
        "\u0534\u0578\u0582\u0562\u056b\u0576\u0561"
    ],
    "name:rus_x_preferred":[
        "\u0414\u0443\u0431\u0438\u043d\u0430"
    ],
    "name:ukr_x_preferred":[
        "Dubyna"
    ],
    "name:ukr_x_variant":[
        "\u0414\u0443\u0431\u0438\u043d\u0430"
    ],
    "wof:name":"Dubyna",
    "wof:placetype":"locality"
},
  "geometry": {"coordinates":[26.79221,49.73077],"type":"Point"}
}