{
  "type": "Feature",
  "properties": {
    "gn:admin1_code":"23.0",
    "gn:asciiname":"Semaki",
    "gn:country_code":"UA",
    "gn:dem":267,
    "gn:feature_class":"P",
    "gn:feature_code":"PPL",
    "gn:name":"Semaki",
    "gn:population":0,
    "gn:timezone":"Europe/Kiev",
    "iso:country":"UA",
    "name:und_x_variant":[
        "Simaki",
        "Semaki"
    ],
    "wof:name":"Semaki",
    "wof:placetype":"locality"
},
  "geometry": {"coordinates":[28.09459,49.1123],"type":"Point"}
}