{
  "type": "Feature",
  "properties": {
    "iso:country":"UA",
    "qs_pg:aaroncc":"UA",
    "qs_pg:name":"Aklenz",
    "qs_pg:name_adm0":"Ukraine",
    "qs_pg:name_adm1":"Avtonomna Respublika Krym",
    "qs_pg:photos":67,
    "qs_pg:photos_1k":14,
    "qs_pg:photos_9k":1,
    "qs_pg:photos_9r":2,
    "qs_pg:photos_all":67,
    "qs_pg:photos_sr":2,
    "qs_pg:pop_sr":0,
    "qs_pg:qs_pg_placetype":"locality",
    "qs_pg:qs_pg_placetype_gp":"Town",
    "qs_pg:woe_adm0":23424976,
    "woe:adm0_id":23424976,
    "woe:name_adm0":"Ukraine",
    "woe:name_adm1":"Avtonomna Respublika Krym",
    "woe:placetype":"Town",
    "wof:name":"Aklenz",
    "wof:placetype":"locality"
},
  "geometry": {"coordinates":[33.587951,44.845585],"type":"Point"}
}