{
  "type": "Feature",
  "properties": {
    "gn:admin1_code":"9.0",
    "gn:asciiname":"Filyanovka",
    "gn:country_code":"UA",
    "gn:dem":274,
    "gn:feature_class":"P",
    "gn:feature_code":"PPL",
    "gn:name":"Filyanovka",
    "gn:population":0,
    "gn:timezone":"Europe/Kiev",
    "iso:country":"UA",
    "wof:name":"Filyanovka",
    "wof:placetype":"locality"
},
  "geometry": {"coordinates":[27.25075,48.83491],"type":"Point"}
}