{
  "type": "Feature",
  "properties": {
    "gn:admin1_code":"27.0",
    "gn:asciiname":"Krasnovolytsya",
    "gn:country_code":"UA",
    "gn:dem":255,
    "gn:feature_class":"P",
    "gn:feature_code":"PPL",
    "gn:name":"Krasnovolytsya",
    "gn:population":0,
    "gn:timezone":"Europe/Kiev",
    "iso:country":"UA",
    "name:ukr_x_preferred":[
        "Krasnovolytsya"
    ],
    "name:ukr_x_variant":[
        "\u041a\u0440\u0430\u0441\u043d\u043e\u0432\u043e\u043b\u0438\u0446\u044f"
    ],
    "name:und_x_variant":[
        "Krasnovul\u2019ka"
    ],
    "wof:name":"Krasnovolytsya",
    "wof:placetype":"locality"
},
  "geometry": {"coordinates":[28.0123,50.02906],"type":"Point"}
}