{
  "type": "Feature",
  "properties": {
    "gn:admin1_code":"7.0",
    "gn:asciiname":"Okip",
    "gn:country_code":"UA",
    "gn:dem":152,
    "gn:feature_class":"P",
    "gn:feature_code":"PPL",
    "gn:name":"Okip",
    "gn:population":0,
    "gn:timezone":"Europe/Kiev",
    "iso:country":"UA",
    "name:rus_x_preferred":[
        "\u041e\u043a\u043e\u043f"
    ],
    "name:ukr_x_preferred":[
        "\u041e\u043a\u0456\u043f"
    ],
    "name:und_x_variant":[
        "Okop",
        "Okip"
    ],
    "wof:name":"Okip",
    "wof:placetype":"locality"
},
  "geometry": {"coordinates":[36.1455,50.42122],"type":"Point"}
}