{
  "type": "Feature",
  "properties": {
    "gn:admin1_code":"23.0",
    "gn:asciiname":"Dakhtaliya",
    "gn:country_code":"UA",
    "gn:dem":229,
    "gn:feature_class":"P",
    "gn:feature_code":"PPL",
    "gn:name":"Dakhtaliya",
    "gn:population":0,
    "gn:timezone":"Europe/Kiev",
    "iso:country":"UA",
    "name:ukr_x_preferred":[
        "\u0414\u0430\u0445\u0442\u0430\u043b\u0456\u044f"
    ],
    "wof:name":"Dakhtaliya",
    "wof:placetype":"locality"
},
  "geometry": {"coordinates":[28.57966,48.39641],"type":"Point"}
}