{
  "type": "Feature",
  "properties": {
    "gn:admin1_code":"25.0",
    "gn:asciiname":"Horonhlab",
    "gn:country_code":"UA",
    "gn:dem":102,
    "gn:feature_class":"P",
    "gn:feature_code":"PPL",
    "gn:name":"Horonhlab",
    "gn:population":0,
    "gn:timezone":"Europe/Uzhgorod",
    "iso:country":"UA",
    "name:ukr_x_preferred":[
        "Horonhlab"
    ],
    "name:ukr_x_variant":[
        "\u0413\u043e\u0440\u043e\u043d\u0433\u043b\u0430\u0431"
    ],
    "name:und_x_variant":[
        "Zvonkovoye"
    ],
    "wof:name":"Horonhlab",
    "wof:placetype":"locality"
},
  "geometry": {"coordinates":[22.36225,48.312],"type":"Point"}
}