{
  "type": "Feature",
  "properties": {
    "gn:admin1_code":"13.0",
    "gn:asciiname":"Malaya Berezyanka",
    "gn:country_code":"UA",
    "gn:dem":219,
    "gn:feature_class":"P",
    "gn:feature_code":"PPL",
    "gn:name":"Malaya Berezyanka",
    "gn:population":0,
    "gn:timezone":"Europe/Kiev",
    "iso:country":"UA",
    "wof:name":"Malaya Berezyanka",
    "wof:placetype":"locality"
},
  "geometry": {"coordinates":[30.46902,49.46186],"type":"Point"}
}