{
  "type": "Feature",
  "properties": {
    "iso:country":"UA",
    "name:bel_x_preferred":[
        "\u041f\u0440\u0430\u0430\u0431\u0440\u0430\u0436\u044d\u043d\u0441\u043a\u0456\u044f \u043c\u043e\u0433\u0456\u043b\u043a\u0456"
    ],
    "name:deu_x_preferred":[
        "Preobraschenskoje-Friedhof"
    ],
    "name:eng_x_preferred":[
        "Preobrazhenskoye Cemetery"
    ],
    "name:epo_x_preferred":[
        "Preobra\u0135enka"
    ],
    "name:nld_x_preferred":[
        "Preobrazjenskoe kladbisjtsje"
    ],
    "name:rus_x_preferred":[
        "\u041f\u0440\u0435\u043e\u0431\u0440\u0430\u0436\u0435\u043d\u0441\u043a\u043e\u0435 \u043a\u043b\u0430\u0434\u0431\u0438\u0449\u0435"
    ],
    "name:tat_x_preferred":[
        "\u041f\u0440\u0435\u043e\u0431\u0440\u0430\u0436\u0435\u043d\u0441\u043a\u0438 \u0437\u0438\u0440\u0430\u0442\u044b"
    ],
    "name:ukr_x_preferred":[
        "\u041f\u0440\u0435\u043e\u0431\u0440\u0430\u0436\u0435\u043d\u043a\u0430"
    ],
    "name:ukr_x_variant":[
        "\u041f\u0440\u0435\u043e\u0431\u0440\u0430\u0436\u0435\u043d\u0441\u044c\u043a\u0435 \u043a\u043b\u0430\u0434\u043e\u0432\u0438\u0449\u0435"
    ],
    "name:und_x_variant":[
        "Praobrazhenka"
    ],
    "qs:a0":"\u0423\u043a\u0440\u0430\u0457\u043d\u0430",
    "qs:a1":"*\u0425\u0435\u0440\u0441\u043e\u043d\u0441\u044c\u043a\u0430",
    "qs:a1_alt":"Khersons'ka",
    "qs:a1r":"0",
    "qs:a2":"\u0427\u0430\u043f\u043b\u0438\u043d\u0441\u044c\u043a\u0438\u0439",
    "qs:a2_alt":"Chaplyns'kyi",
    "qs:adm0":"\u0423\u043a\u0440\u0430\u0457\u043d\u0430",
    "qs:la_lc":"*",
    "qs:level":"locality",
    "qs:loc":"\u041f\u0440\u0435\u043e\u0431\u0440\u0430\u0436\u0435\u043d\u043a\u0430",
    "qs:loc_alt":"Preobrazhenka",
    "qs:pop":0,
    "qs:type":"buffered point",
    "wd:wordcount":444,
    "wof:name":"\u041f\u0440\u0435\u043e\u0431\u0440\u0430\u0436\u0435\u043d\u043a\u0430",
    "wof:placetype":"locality"
},
  "geometry": {"coordinates":[33.487068,46.397316],"type":"Point"}
}