{
  "type": "Feature",
  "properties": {
    "iso:country":"UA",
    "name:ukr_x_preferred":[
        "\u041f\u0440\u0435\u043e\u0431\u0440\u0430\u0436\u0435\u043d\u043a\u0430"
    ],
    "name:unk_x_variant":[
        "Praobrazhenka"
    ],
    "qs:a0":"\u0423\u043a\u0440\u0430\u0457\u043d\u0430",
    "qs:a1":"*\u0425\u0435\u0440\u0441\u043e\u043d\u0441\u044c\u043a\u0430",
    "qs:a1_alt":"Khersons'ka",
    "qs:a1r":"0",
    "qs:a2":"\u0427\u0430\u043f\u043b\u0438\u043d\u0441\u044c\u043a\u0438\u0439",
    "qs:a2_alt":"Chaplyns'kyi",
    "qs:adm0":"\u0423\u043a\u0440\u0430\u0457\u043d\u0430",
    "qs:la_lc":"*",
    "qs:level":"locality",
    "qs:loc":"\u041f\u0440\u0435\u043e\u0431\u0440\u0430\u0436\u0435\u043d\u043a\u0430",
    "qs:loc_alt":"Preobrazhenka",
    "qs:pop":0,
    "qs:type":"buffered point",
    "wd:wordcount":444,
    "wof:name":"\u041f\u0440\u0435\u043e\u0431\u0440\u0430\u0436\u0435\u043d\u043a\u0430",
    "wof:placetype":"locality"
},
  "geometry": {"coordinates":[33.487068,46.397316],"type":"Point"}
}