{
  "type": "Feature",
  "properties": {
    "gn:admin1_code":"19.0",
    "gn:asciiname":"Bohushivka",
    "gn:country_code":"UA",
    "gn:dem":225,
    "gn:feature_class":"P",
    "gn:feature_code":"PPL",
    "gn:name":"Bohushivka",
    "gn:population":0,
    "gn:timezone":"Europe/Kiev",
    "iso:country":"UA",
    "name:ukr_x_preferred":[
        "Bohushivka"
    ],
    "name:ukr_x_variant":[
        "\u0411\u043e\u0433\u0443\u0448\u0456\u0432\u043a\u0430"
    ],
    "name:und_x_variant":[
        "Bogushevka"
    ],
    "wof:name":"Bohushivka",
    "wof:placetype":"locality"
},
  "geometry": {"coordinates":[25.72314,50.58383],"type":"Point"}
}