{
  "type": "Feature",
  "properties": {
    "gn:admin1_code":"4.0",
    "gn:asciiname":"Buzuluky",
    "gn:country_code":"UA",
    "gn:dem":57,
    "gn:feature_class":"P",
    "gn:feature_code":"PPL",
    "gn:name":"Buzuluky",
    "gn:population":0,
    "gn:timezone":"Europe/Kiev",
    "iso:country":"UA",
    "name:ukr_x_preferred":[
        "Buzuluky"
    ],
    "name:ukr_x_variant":[
        "\u0411\u0443\u0437\u0443\u043b\u0443\u043a\u0438"
    ],
    "name:und_x_variant":[
        "Zal\u2019bakhovka"
    ],
    "wof:name":"Buzuluky",
    "wof:placetype":"locality"
},
  "geometry": {"coordinates":[34.18148,48.08818],"type":"Point"}
}