{
  "type": "Feature",
  "properties": {
    "gn:admin1_code":"16.0",
    "gn:asciiname":"Novo-Fontanka",
    "gn:country_code":"UA",
    "gn:dem":8,
    "gn:feature_class":"P",
    "gn:feature_code":"PPL",
    "gn:name":"Novo-Fontanka",
    "gn:population":0,
    "gn:timezone":"Europe/Kiev",
    "iso:country":"UA",
    "wof:name":"Novo-Fontanka",
    "wof:placetype":"locality"
},
  "geometry": {"coordinates":[32.20493,47.32323],"type":"Point"}
}