{
  "type": "Feature",
  "properties": {
    "gn:admin1_code":"5.0",
    "gn:asciiname":"Izmaylivka",
    "gn:country_code":"UA",
    "gn:dem":180,
    "gn:feature_class":"P",
    "gn:feature_code":"PPL",
    "gn:name":"Izmaylivka",
    "gn:population":0,
    "gn:timezone":"Europe/Kiev",
    "iso:country":"UA",
    "name:ukr_x_preferred":[
        "Izmaylivka"
    ],
    "name:ukr_x_variant":[
        "\u0406\u0437\u043c\u0430\u0439\u043b\u0456\u0432\u043a\u0430"
    ],
    "name:und_x_variant":[
        "Izmaylovka"
    ],
    "wof:name":"Izmaylivka",
    "wof:placetype":"locality"
},
  "geometry": {"coordinates":[37.34124,48.05463],"type":"Point"}
}