{
  "type": "Feature",
  "properties": {
    "gn:admin1_code":"4.0",
    "gn:asciiname":"Sydorenko",
    "gn:country_code":"UA",
    "gn:dem":129,
    "gn:feature_class":"P",
    "gn:feature_code":"PPL",
    "gn:name":"Sydorenko",
    "gn:population":0,
    "gn:timezone":"Europe/Kiev",
    "iso:country":"UA",
    "name:ukr_x_preferred":[
        "Sydorenko"
    ],
    "name:ukr_x_variant":[
        "\u0421\u0438\u0434\u043e\u0440\u0435\u043d\u043a\u043e"
    ],
    "name:und_x_variant":[
        "Sidorenkov",
        "Sidorenkoye",
        "Sidorenko"
    ],
    "wof:name":"Sydorenko",
    "wof:placetype":"locality"
},
  "geometry": {"coordinates":[36.40136,48.28584],"type":"Point"}
}