{
  "type": "Feature",
  "properties": {
    "gn:admin1_code":"2.0",
    "gn:asciiname":"Petrova Sloboda",
    "gn:country_code":"UA",
    "gn:dem":130,
    "gn:feature_class":"P",
    "gn:feature_code":"PPL",
    "gn:name":"Petrova Sloboda",
    "gn:population":0,
    "gn:timezone":"Europe/Kiev",
    "iso:country":"UA",
    "name:ukr_x_preferred":[
        "Petrova Sloboda"
    ],
    "name:ukr_x_variant":[
        "\u041f\u0435\u0442\u0440\u043e\u0432\u0430 \u0421\u043b\u043e\u0431\u043e\u0434\u0430"
    ],
    "wof:name":"Petrova Sloboda",
    "wof:placetype":"locality"
},
  "geometry": {"coordinates":[32.19006,51.75458],"type":"Point"}
}