{
  "type": "Feature",
  "properties": {
    "gn:admin1_code":"14.0",
    "gn:asciiname":"Vivcharove",
    "gn:country_code":"UA",
    "gn:dem":100,
    "gn:feature_class":"P",
    "gn:feature_code":"PPL",
    "gn:name":"Vivcharove",
    "gn:population":0,
    "gn:timezone":"Europe/Zaporozhye",
    "iso:country":"UA",
    "name:eng_x_preferred":[
        "Ovcharovo"
    ],
    "name:rus_x_preferred":[
        "\u041e\u0432\u0447\u0430\u0440\u043e\u0432\u043e"
    ],
    "name:ukr_x_preferred":[
        "Vivcharove"
    ],
    "name:ukr_x_variant":[
        "\u0412\u0456\u0432\u0447\u0430\u0440\u043e\u0432\u0435"
    ],
    "name:und_x_variant":[
        "Ovcharov"
    ],
    "wof:name":"Vivcharove",
    "wof:placetype":"locality"
},
  "geometry": {"coordinates":[38.58465,49.85415],"type":"Point"}
}