{
  "type": "Feature",
  "properties": {
    "gn:admin1_code":"26.0",
    "gn:asciiname":"Sokolivka",
    "gn:country_code":"UA",
    "gn:dem":97,
    "gn:feature_class":"P",
    "gn:feature_code":"PPL",
    "gn:name":"Sokolivka",
    "gn:population":0,
    "gn:timezone":"Europe/Zaporozhye",
    "iso:country":"UA",
    "name:ukr_x_preferred":[
        "Sokolivka"
    ],
    "name:ukr_x_variant":[
        "\u0421\u043e\u043a\u043e\u043b\u0456\u0432\u043a\u0430"
    ],
    "name:und_x_variant":[
        "Sokolovka"
    ],
    "wof:name":"Sokolivka",
    "wof:placetype":"locality"
},
  "geometry": {"coordinates":[35.22907,47.99451],"type":"Point"}
}