{
  "type": "Feature",
  "properties": {
    "gn:admin1_code":"7.0",
    "gn:asciiname":"Ryzhove",
    "gn:country_code":"UA",
    "gn:dem":174,
    "gn:feature_class":"P",
    "gn:feature_code":"PPL",
    "gn:name":"Ryzhove",
    "gn:population":0,
    "gn:timezone":"Europe/Kiev",
    "iso:country":"UA",
    "name:ukr_x_preferred":[
        "Ryzhove"
    ],
    "name:ukr_x_variant":[
        "\u0420\u0438\u0436\u043e\u0432\u0435"
    ],
    "name:und_x_variant":[
        "Pyzhkovo",
        "Ryzhovo"
    ],
    "wof:name":"Ryzhove",
    "wof:placetype":"locality"
},
  "geometry": {"coordinates":[36.71352,48.93867],"type":"Point"}
}