{
  "type": "Feature",
  "properties": {
    "iso:country":"UA",
    "name:arm_x_preferred":[
        "\u054d\u057f\u0561\u0580\u056b\u0575 \u054d\u0578\u056c\u0578\u057f\u057e\u056b\u0576"
    ],
    "name:chi_x_preferred":[
        "\u820a\u7d22\u6d1b\u7279\u6eab"
    ],
    "name:eng_x_preferred":[
        "Staryi Solotvyn"
    ],
    "name:ger_x_preferred":[
        "Staryj Solotwyn"
    ],
    "name:rum_x_preferred":[
        "Star\u00eei Solotv\u00een"
    ],
    "name:rus_x_preferred":[
        "\u0421\u0442\u0430\u0440\u044b\u0439 \u0421\u043e\u043b\u043e\u0442\u0432\u0438\u043d"
    ],
    "name:ukr_x_preferred":[
        "Staryy Solotvyn"
    ],
    "name:ukr_x_variant":[
        "\u0421\u0442\u0430\u0440\u0438\u0439 \u0421\u043e\u043b\u043e\u0442\u0432\u0438\u043d"
    ],
    "name:unk_x_variant":[
        "Solotvin"
    ],
    "qs:a0":"\u0423\u043a\u0440\u0430\u0457\u043d\u0430",
    "qs:a1":"*\u0416\u0438\u0442\u043e\u043c\u0438\u0440\u0441\u044c\u043a\u0430",
    "qs:a1_alt":"Zhytomyrs'ka",
    "qs:a1r":"0",
    "qs:a2":"\u0411\u0435\u0440\u0434\u0438\u0447\u0456\u0432\u0441\u044c\u043a\u0438\u0439",
    "qs:a2_alt":"Berdychivs'kyi",
    "qs:adm0":"\u0423\u043a\u0440\u0430\u0457\u043d\u0430",
    "qs:la_lc":"*",
    "qs:level":"locality",
    "qs:loc":"\u0421\u0442\u0430\u0440\u0438\u0439 \u0421\u043e\u043b\u043e\u0442\u0432\u0438\u043d",
    "qs:loc_alt":"Staryi Solotvyn",
    "qs:pop":0,
    "qs:type":"buffered point",
    "wof:name":"\u0421\u0442\u0430\u0440\u0438\u0439 \u0421\u043e\u043b\u043e\u0442\u0432\u0438\u043d",
    "wof:placetype":"locality"
},
  "geometry": {"coordinates":[28.678718,50.041367],"type":"Point"}
}