{
  "type": "Feature",
  "properties": {
    "iso:country":"UA",
    "name:ara_x_preferred":[
        "\u0625\u064a\u0627\u0644\u0629 \u0627\u0644\u0628\u0648\u0633\u0646\u0629"
    ],
    "name:bel_x_preferred":[
        "\u0411\u0430\u0441\u043d\u0456\u0439\u0441\u043a\u0456 \u044d\u044f\u043b\u0435\u0442"
    ],
    "name:bos_x_preferred":[
        "Bosanski pa\u0161aluk"
    ],
    "name:bul_x_preferred":[
        "\u0411\u043e\u0441\u043d\u0435\u043d\u0441\u043a\u0438 \u0435\u044f\u043b\u0435\u0442"
    ],
    "name:deu_x_preferred":[
        "Ey\u00e2let Bosnien"
    ],
    "name:diq_x_preferred":[
        "Bosna"
    ],
    "name:ell_x_preferred":[
        "\u0392\u03b9\u03bb\u03b1\u03ad\u03c4\u03b9 \u03c4\u03b7\u03c2 \u0392\u03bf\u03c3\u03bd\u03af\u03b1\u03c2"
    ],
    "name:eng_x_preferred":[
        "Klishki"
    ],
    "name:est_x_preferred":[
        "Bosnia ejalet"
    ],
    "name:fra_x_preferred":[
        "Pachalik de Bosnie"
    ],
    "name:hrv_x_preferred":[
        "Bosanski pa\u0161aluk"
    ],
    "name:ind_x_preferred":[
        "Eyalet Bosnia"
    ],
    "name:ita_x_preferred":[
        "Eyalet di Bosnia"
    ],
    "name:lav_x_preferred":[
        "Bosnijas ej\u0101lets"
    ],
    "name:nld_x_preferred":[
        "Eyalet Bosni\u00eb"
    ],
    "name:rus_x_preferred":[
        "\u0411\u043e\u0441\u043d\u0438\u0439\u0441\u043a\u0438\u0439 \u044d\u044f\u043b\u0435\u0442"
    ],
    "name:rus_x_variant":[
        "\u041a\u043b\u0438\u0448\u043a\u0438"
    ],
    "name:spa_x_preferred":[
        "Eyalato de Bosnia"
    ],
    "name:srp_x_preferred":[
        "\u0411\u043e\u0441\u0430\u043d\u0441\u043a\u0438 \u043f\u0430\u0448\u0430\u043b\u0443\u043a"
    ],
    "name:tur_x_preferred":[
        "Bosna Eyaleti"
    ],
    "name:ukr_x_preferred":[
        "Klyshky"
    ],
    "name:ukr_x_variant":[
        "\u041a\u043b\u0438\u0448\u043a\u0438"
    ],
    "name:unk_x_variant":[
        "Klishki"
    ],
    "name:urd_x_preferred":[
        "\u0627\u06cc\u0627\u0644\u062a \u0628\u0648\u0633\u0646\u06cc\u0627"
    ],
    "qs:a0":"\u0423\u043a\u0440\u0430\u0457\u043d\u0430",
    "qs:a1":"*\u0421\u0443\u043c\u0441\u044c\u043a\u0430",
    "qs:a1_alt":"Sums'ka",
    "qs:a1r":"0",
    "qs:a2":"\u0428\u043e\u0441\u0442\u043a\u0438\u043d\u0441\u044c\u043a\u0438\u0439",
    "qs:a2_alt":"Shostkyns'kyi",
    "qs:adm0":"\u0423\u043a\u0440\u0430\u0457\u043d\u0430",
    "qs:la_lc":"*",
    "qs:level":"locality",
    "qs:loc":"\u041a\u043b\u0438\u0448\u043a\u0438",
    "qs:loc_alt":"Klyshky",
    "qs:pop":0,
    "qs:type":"buffered point",
    "wd:wordcount":894,
    "wof:name":"\u041a\u043b\u0438\u0448\u043a\u0438",
    "wof:placetype":"locality"
},
  "geometry": {"coordinates":[33.291329,51.759597],"type":"Point"}
}