{
  "type": "Feature",
  "properties": {
    "gn:admin1_code":"7.0",
    "gn:asciiname":"Zabrody",
    "gn:country_code":"UA",
    "gn:dem":146,
    "gn:feature_class":"P",
    "gn:feature_code":"PPL",
    "gn:name":"Zabrody",
    "gn:population":0,
    "gn:timezone":"Europe/Kiev",
    "iso:country":"UA",
    "name:eng_x_preferred":[
        "Zabrody"
    ],
    "name:pol_x_preferred":[
        "Zabrody"
    ],
    "name:rus_x_preferred":[
        "\u0417\u0430\u0431\u0440\u043e\u0434\u044b"
    ],
    "name:ukr_x_preferred":[
        "\u0417\u0430\u0431\u0440\u043e\u0434\u0438"
    ],
    "wof:name":"Zabrody",
    "wof:placetype":"locality"
},
  "geometry": {"coordinates":[35.63969,50.176],"type":"Point"}
}