{
  "type": "Feature",
  "properties": {
    "gn:admin1_code":"3.0",
    "gn:asciiname":"Sokoliy",
    "gn:country_code":"UA",
    "gn:dem":785,
    "gn:feature_class":"P",
    "gn:feature_code":"PPL",
    "gn:name":"Sokoliy",
    "gn:population":0,
    "gn:timezone":"Europe/Kiev",
    "iso:country":"UA",
    "name:ukr_x_preferred":[
        "Sokoliy"
    ],
    "wof:name":"Sokoliy",
    "wof:placetype":"locality"
},
  "geometry": {"coordinates":[25.05181,48.021],"type":"Point"}
}