{
  "type": "Feature",
  "properties": {
    "gn:admin1_code":"24.0",
    "gn:asciiname":"Smolyarze",
    "gn:country_code":"UA",
    "gn:dem":192,
    "gn:feature_class":"P",
    "gn:feature_code":"PPL",
    "gn:name":"Smolyarze",
    "gn:population":0,
    "gn:timezone":"Europe/Kiev",
    "iso:country":"UA",
    "name:und_x_variant":[
        "Smolyary",
        "Smolarze",
        "Smolyarze"
    ],
    "wof:name":"Smolyarze",
    "wof:placetype":"locality"
},
  "geometry": {"coordinates":[24.29099,50.9567],"type":"Point"}
}