{
  "type": "Feature",
  "properties": {
    "iso:country":"UA",
    "name:bel_x_preferred":[
        "\u0421\u0442\u0440\u044b\u043b\u043a\u0456\u045e"
    ],
    "name:che_x_preferred":[
        "\u0421\u0442\u0440\u0435\u043b\u043a\u043e\u0432"
    ],
    "name:deu_x_preferred":[
        "Strilkiw"
    ],
    "name:eng_x_preferred":[
        "Strilkiv"
    ],
    "name:fin_x_preferred":[
        "Str\u0456lk\u0456v"
    ],
    "name:nan_x_preferred":[
        "Strilkiv"
    ],
    "name:nno_x_preferred":[
        "Strilkiv"
    ],
    "name:nob_x_preferred":[
        "Strilkiv"
    ],
    "name:pol_x_preferred":[
        "Strza\u0142k\u00f3w"
    ],
    "name:ron_x_preferred":[
        "Strilkiv"
    ],
    "name:rus_x_preferred":[
        "\u0421\u0442\u0440\u0435\u043b\u043a\u043e\u0432"
    ],
    "name:ukr_x_preferred":[
        "\u0421\u0442\u0440\u0456\u043b\u043a\u0456\u0432"
    ],
    "name:zho_x_preferred":[
        "\u65af\u7279\u91cc\u723e\u57fa\u592b"
    ],
    "qs:a0":"\u0423\u043a\u0440\u0430\u0457\u043d\u0430",
    "qs:a1":"*\u041b\u044c\u0432\u0456\u0432\u0441\u044c\u043a\u0430",
    "qs:a1_alt":"L'vivs'ka",
    "qs:a1r":"0",
    "qs:a2":"\u0421\u0442\u0440\u0438\u0439\u0441\u044c\u043a\u0438\u0439",
    "qs:a2_alt":"Stryis'kyi",
    "qs:adm0":"\u0423\u043a\u0440\u0430\u0457\u043d\u0430",
    "qs:la_lc":"*",
    "qs:level":"locality",
    "qs:loc":"\u0421\u0442\u0440\u0456\u043b\u043a\u0456\u0432",
    "qs:loc_alt":"Strilkiv",
    "qs:pop":0,
    "qs:type":"buffered point",
    "wof:name":"\u0421\u0442\u0440\u0456\u043b\u043a\u0456\u0432",
    "wof:placetype":"locality"
},
  "geometry": {"coordinates":[23.88892,49.225824],"type":"Point"}
}