{
  "type": "Feature",
  "properties": {
    "gn:admin1_code":"18.0",
    "gn:asciiname":"Kolosivka",
    "gn:country_code":"UA",
    "gn:dem":76,
    "gn:feature_class":"P",
    "gn:feature_code":"PPL",
    "gn:name":"Kolosivka",
    "gn:population":0,
    "gn:timezone":"Europe/Kiev",
    "iso:country":"UA",
    "name:ukr_x_preferred":[
        "Kolosivka"
    ],
    "name:ukr_x_variant":[
        "\u041a\u043e\u043b\u043e\u0441\u0456\u0432\u043a\u0430"
    ],
    "wof:name":"Kolosivka",
    "wof:placetype":"locality"
},
  "geometry": {"coordinates":[33.77353,49.60814],"type":"Point"}
}