{
  "type": "Feature",
  "properties": {
    "gn:population":10354,
    "iso:country":"UA",
    "name:bel_x_variant":[
        "\u041f\u0430\u0433\u0440\u0430\u0431\u0456\u0448\u0447\u0430"
    ],
    "name:crh_x_preferred":[
        "Pogreb\u0131\u015f\u00e7e"
    ],
    "name:deu_x_preferred":[
        "Pohrebyschtsche"
    ],
    "name:eng_x_preferred":[
        "Pohrebyshche"
    ],
    "name:fas_x_preferred":[
        "\u067e\u0648\u0647\u0631\u0628\u06cc\u0634\u0686\u0647"
    ],
    "name:fra_x_preferred":[
        "Pohrebychtche"
    ],
    "name:heb_x_preferred":[
        "\u05e4\u05d5\u05d4\u05e8\u05d1\u05d9\u05e9\u05e6'\u05d4"
    ],
    "name:hsb_x_preferred":[
        "Pohreby\u0161\u0107e"
    ],
    "name:hye_x_preferred":[
        "\u054a\u0578\u0563\u0580\u0565\u0562\u056b\u0577\u0579\u0565"
    ],
    "name:ita_x_preferred":[
        "Pohreby\u0161\u010de"
    ],
    "name:jpn_x_preferred":[
        "\u30dd\u30d5\u30ec\u30d6\u30a3\u30fc\u30b7\u30c1\u30a7"
    ],
    "name:kat_x_preferred":[
        "\u10de\u10dd\u10d2\u10e0\u10d4\u10d1\u10d8\u10e8\u10e9\u10d4"
    ],
    "name:nno_x_preferred":[
        "Pohrebysjtsje"
    ],
    "name:pol_x_preferred":[
        "Pohrebyszcze"
    ],
    "name:ron_x_preferred":[
        "Pohreb\u00ee\u0219ce"
    ],
    "name:rus_x_preferred":[
        "\u041f\u043e\u0433\u0440\u0435\u0431\u0438\u0449\u0435"
    ],
    "name:sah_x_preferred":[
        "\u041f\u043e\u0433\u0440\u0435\u0431\u0438\u0449\u0435"
    ],
    "name:tat_x_preferred":[
        "\u041f\u043e\u04bb\u0440\u0435\u0431\u044b\u0447\u0447\u0435"
    ],
    "name:ukr_x_preferred":[
        "\u041f\u043e\u0433\u0440\u0435\u0431\u0438\u0449\u0435"
    ],
    "name:unk_x_variant":[
        "Pogrebischtsche"
    ],
    "name:vie_x_preferred":[
        "Pohrebysche"
    ],
    "name:zho_x_preferred":[
        "\u6ce2\u683c\u5217\u6bd4\u8b1d"
    ],
    "qs:a0":"\u0423\u043a\u0440\u0430\u0457\u043d\u0430",
    "qs:a1":"*\u0412\u0456\u043d\u043d\u0438\u0446\u044c\u043a\u0430",
    "qs:a1_alt":"Vinnyts'ka",
    "qs:a1r":"0",
    "qs:a2":"\u041f\u043e\u0433\u0440\u0435\u0431\u0438\u0449\u0435\u043d\u0441\u044c\u043a\u0438\u0439",
    "qs:a2_alt":"Pohrebyschens'kyi",
    "qs:adm0":"\u0423\u043a\u0440\u0430\u0457\u043d\u0430",
    "qs:la_lc":"*",
    "qs:level":"locality",
    "qs:loc":"\u041f\u043e\u0433\u0440\u0435\u0431\u0438\u0449\u0435",
    "qs:loc_alt":"Pohrebysche",
    "qs:pop":0,
    "qs:type":"buffered point",
    "wd:wordcount":379,
    "wof:name":"\u041f\u043e\u0433\u0440\u0435\u0431\u0438\u0449\u0435",
    "wof:placetype":"locality",
    "wof:population":10354
},
  "geometry": {"coordinates":[29.279571,49.48771],"type":"Point"}
}