{
  "type": "Feature",
  "properties": {
    "gn:country":"UA",
    "gn:fcode":"PPL",
    "gn:population":6250,
    "iso:country":"UA",
    "name:rus_x_preferred":[
        "\u041a\u0440\u0430\u0441\u043d\u043e\u0435"
    ],
    "name:ukr_x_preferred":[
        "\u041a\u0440\u0430\u0441\u043d\u0435"
    ],
    "name:und_x_variant":[
        "Krasne"
    ],
    "qs_pg:aaroncc":"UA",
    "qs_pg:gn_country":"UA",
    "qs_pg:gn_fcode":"PPL",
    "qs_pg:gn_pop":6250,
    "qs_pg:name":"Krasnoye",
    "qs_pg:name_adm0":"Ukraine",
    "qs_pg:name_adm1":"L\u00b4vivs\u00b4ka Oblast\u00b4",
    "qs_pg:photos_9r":0,
    "qs_pg:photos_sr":0,
    "qs_pg:pop_sr":5,
    "qs_pg:qs_pg_placetype":"locality",
    "qs_pg:qs_pg_placetype_gp":"Town",
    "qs_pg:woe_adm0":23424976,
    "woe:adm0_id":23424976,
    "woe:name_adm0":"Ukraine",
    "woe:name_adm1":"L\u00b4vivs\u00b4ka Oblast\u00b4",
    "woe:placetype":"Town",
    "wof:name":"Krasnoye",
    "wof:placetype":"locality",
    "wof:population":6250
},
  "geometry": {"coordinates":[24.6134,49.91447],"type":"Point"}
}