{
  "type": "Feature",
  "properties": {
    "gn:admin1_code":"27.0",
    "gn:asciiname":"Bilka",
    "gn:country_code":"UA",
    "gn:dem":213,
    "gn:feature_class":"P",
    "gn:feature_code":"PPL",
    "gn:name":"Bilka",
    "gn:population":0,
    "gn:timezone":"Europe/Kiev",
    "iso:country":"UA",
    "name:dan_x_preferred":[
        "Bilka"
    ],
    "name:deu_x_preferred":[
        "Bilka"
    ],
    "name:fra_x_preferred":[
        "Bilka"
    ],
    "name:isl_x_preferred":[
        "Bilka"
    ],
    "name:ukr_x_preferred":[
        "Bilka"
    ],
    "name:ukr_x_variant":[
        "\u0411\u0456\u043b\u043a\u0430"
    ],
    "name:und_x_variant":[
        "Belka"
    ],
    "wof:name":"Bilka",
    "wof:placetype":"locality"
},
  "geometry": {"coordinates":[28.41692,51.33837],"type":"Point"}
}