{
  "type": "Feature",
  "properties": {
    "gn:admin1_code":"7.0",
    "gn:asciiname":"Nikopol'",
    "gn:country_code":"UA",
    "gn:dem":90,
    "gn:feature_class":"P",
    "gn:feature_code":"PPL",
    "gn:name":"Nikopol\u2019",
    "gn:population":0,
    "gn:timezone":"Europe/Kiev",
    "iso:country":"UA",
    "name:ukr_x_preferred":[
        "Nikopol\u2019"
    ],
    "name:ukr_x_variant":[
        "\u041d\u0456\u043a\u043e\u043f\u043e\u043b\u044c"
    ],
    "wof:name":"Nikopol'",
    "wof:placetype":"locality"
},
  "geometry": {"coordinates":[37.12443,48.88551],"type":"Point"}
}