{
  "type": "Feature",
  "properties": {
    "iso:country":"UA",
    "name:eng_x_preferred":[
        "Checheleve"
    ],
    "name:hye_x_preferred":[
        "\u0549\u0565\u0579\u0565\u056c\u0587\u0578"
    ],
    "name:ron_x_preferred":[
        "Ceceleve"
    ],
    "name:rus_x_preferred":[
        "\u0427\u0435\u0447\u0435\u043b\u0435\u0432\u043e"
    ],
    "name:ukr_x_preferred":[
        "Checheleve"
    ],
    "name:ukr_x_variant":[
        "\u0427\u0435\u0447\u0435\u043b\u0435\u0432\u0435"
    ],
    "name:und_x_variant":[
        "Chechelevo"
    ],
    "qs:a0":"\u0423\u043a\u0440\u0430\u0457\u043d\u0430",
    "qs:a1":"*\u041f\u043e\u043b\u0442\u0430\u0432\u0441\u044c\u043a\u0430",
    "qs:a1_alt":"Poltavs'ka",
    "qs:a1r":"0",
    "qs:a2":"\u041a\u0440\u0435\u043c\u0435\u043d\u0447\u0443\u0446\u044c\u043a\u0438\u0439",
    "qs:a2_alt":"Kremenchuts'kyi",
    "qs:adm0":"\u0423\u043a\u0440\u0430\u0457\u043d\u0430",
    "qs:la_lc":"*",
    "qs:level":"locality",
    "qs:loc":"\u0427\u0435\u0447\u0435\u043b\u0435\u0432\u0435",
    "qs:loc_alt":"Checheleve",
    "qs:pop":0,
    "qs:type":"buffered point",
    "wof:name":"\u0427\u0435\u0447\u0435\u043b\u0435\u0432\u0435",
    "wof:placetype":"locality"
},
  "geometry": {"coordinates":[33.394398,49.017085],"type":"Point"}
}