{
  "type": "Feature",
  "properties": {
    "gn:admin1_code":"24.0",
    "gn:asciiname":"Zaverkhlitse",
    "gn:cc2":"UA",
    "gn:country_code":"UA",
    "gn:dem":157,
    "gn:feature_class":"P",
    "gn:feature_code":"PPL",
    "gn:name":"Zaverkhlitse",
    "gn:population":0,
    "gn:timezone":"Europe/Kiev",
    "iso:country":"UA",
    "name:und_x_variant":[
        "Zaverkhditse",
        "Zaverkhlitse"
    ],
    "wof:name":"Zaverkhlitse",
    "wof:placetype":"locality"
},
  "geometry": {"coordinates":[25.46667,51.66667],"type":"Point"}
}