{
  "type": "Feature",
  "properties": {
    "gn:admin1_code":"26.0",
    "gn:asciiname":"Veselyy Hay",
    "gn:country_code":"UA",
    "gn:dem":121,
    "gn:feature_class":"P",
    "gn:feature_code":"PPL",
    "gn:name":"Veselyy Hay",
    "gn:population":0,
    "gn:timezone":"Europe/Zaporozhye",
    "iso:country":"UA",
    "name:ukr_x_preferred":[
        "Veselyy Hay"
    ],
    "name:ukr_x_variant":[
        "\u0412\u0435\u0441\u0435\u043b\u0438\u0439 \u0413\u0430\u0439"
    ],
    "name:und_x_variant":[
        "Pervomayskiy",
        "Veselyy Gay"
    ],
    "wof:name":"Veselyy Hay",
    "wof:placetype":"locality"
},
  "geometry": {"coordinates":[35.81808,47.99186],"type":"Point"}
}