{
  "type": "Feature",
  "properties": {
    "gn:admin1_code":"3.0",
    "gn:asciiname":"Kostintsy",
    "gn:country_code":"UA",
    "gn:dem":358,
    "gn:feature_class":"P",
    "gn:feature_code":"PPL",
    "gn:name":"Kostintsy",
    "gn:population":0,
    "gn:timezone":"Europe/Kiev",
    "iso:country":"UA",
    "name:und_x_variant":[
        "Kosteshti",
        "Kostovtsy",
        "Kostintsy"
    ],
    "wof:name":"Kostintsy",
    "wof:placetype":"locality"
},
  "geometry": {"coordinates":[25.6356,48.28046],"type":"Point"}
}