{
  "type": "Feature",
  "properties": {
    "gn:admin1_code":"2.0",
    "gn:asciiname":"Il'mivka",
    "gn:country_code":"UA",
    "gn:dem":158,
    "gn:feature_class":"P",
    "gn:feature_code":"PPL",
    "gn:name":"Il\u2019mivka",
    "gn:population":0,
    "gn:timezone":"Europe/Kiev",
    "iso:country":"UA",
    "name:rus_x_preferred":[
        "Il\u2019movka"
    ],
    "name:ukr_x_preferred":[
        "Il\u2019mivka"
    ],
    "name:ukr_x_variant":[
        "\u0406\u043b\u044c\u043c\u0456\u0432\u043a\u0430"
    ],
    "name:und_x_variant":[
        "Il\u2019mivka",
        "Il\u2019movka"
    ],
    "wof:name":"Il'mivka",
    "wof:placetype":"locality"
},
  "geometry": {"coordinates":[31.32800000000001,52.04769],"type":"Point"}
}