{
  "type": "Feature",
  "properties": {
    "gn:admin1_code":"4.0",
    "gn:asciiname":"Rayivka",
    "gn:country_code":"UA",
    "gn:dem":144,
    "gn:feature_class":"P",
    "gn:feature_code":"PPL",
    "gn:name":"Rayivka",
    "gn:population":0,
    "gn:timezone":"Europe/Kiev",
    "iso:country":"UA",
    "name:rus_x_preferred":[
        "Ray\u00ebvka"
    ],
    "name:ukr_x_preferred":[
        "Rayivka"
    ],
    "name:ukr_x_variant":[
        "\u0420\u0430\u0457\u0432\u043a\u0430"
    ],
    "wof:name":"Rayivka",
    "wof:placetype":"locality"
},
  "geometry": {"coordinates":[35.45503,48.35324],"type":"Point"}
}