{
  "type": "Feature",
  "properties": {
    "gn:admin1_code":"7.0",
    "gn:asciiname":"Oparino",
    "gn:country_code":"UA",
    "gn:dem":153,
    "gn:feature_class":"P",
    "gn:feature_code":"PPL",
    "gn:name":"Oparino",
    "gn:population":0,
    "gn:timezone":"Europe/Kiev",
    "iso:country":"UA",
    "name:deu_x_preferred":[
        "Oparino"
    ],
    "name:rus_x_preferred":[
        "\u041e\u043f\u0430\u0440\u0438\u043d\u043e"
    ],
    "wof:name":"Oparino",
    "wof:placetype":"locality"
},
  "geometry": {"coordinates":[37.615,49.76389],"type":"Point"}
}