{
  "type": "Feature",
  "properties": {
    "gn:admin1_code":"7.0",
    "gn:asciiname":"Oparino",
    "gn:country_code":"UA",
    "gn:dem":153,
    "gn:feature_class":"P",
    "gn:feature_code":"PPL",
    "gn:name":"Oparino",
    "gn:population":0,
    "gn:timezone":"Europe/Kiev",
    "iso:country":"UA",
    "wof:name":"Oparino",
    "wof:placetype":"locality"
},
  "geometry": {"coordinates":[37.615,49.76389],"type":"Point"}
}