{
  "type": "Feature",
  "properties": {
    "gn:country":"UA",
    "gn:fcode":"PPL",
    "gn:population":4090,
    "iso:country":"UA",
    "name:ara_x_preferred":[
        "\u0628\u064a\u0631\u064a\u0632\u0627\u0646\u0643\u0627\u060c \u0645\u064a\u0643\u0648\u0644\u0627\u064a\u064a\u0641\u0633\u0643\u0627"
    ],
    "name:ara_x_variant":[
        "\u0628\u064a\u0631\u064a\u0632\u0627\u0646\u0643\u0627"
    ],
    "name:bul_x_preferred":[
        "\u0411\u0435\u0440\u0435\u0437\u0430\u043d\u043a\u0430"
    ],
    "name:ceb_x_preferred":[
        "Berezanka"
    ],
    "name:crh_x_preferred":[
        "Berezanka"
    ],
    "name:deu_x_preferred":[
        "Beresanka"
    ],
    "name:eng_x_preferred":[
        "Berezanka"
    ],
    "name:hye_x_preferred":[
        "\u0532\u0565\u0580\u0565\u0566\u0561\u0576\u056f\u0561"
    ],
    "name:lav_x_preferred":[
        "Berezanka"
    ],
    "name:pol_x_preferred":[
        "Berezanka"
    ],
    "name:ron_x_preferred":[
        "Berezanka"
    ],
    "name:rus_x_preferred":[
        "\u0411\u0435\u0440\u0435\u0437\u0430\u043d\u043a\u0430"
    ],
    "name:ukr_x_preferred":[
        "\u0411\u0435\u0440\u0435\u0437\u0430\u043d\u043a\u0430"
    ],
    "name:und_x_variant":[
        "Tiligulo-Berezannya"
    ],
    "name:zho_x_preferred":[
        "\u5225\u5217\u8d0a\u5361"
    ],
    "qs_pg:aaroncc":"UA",
    "qs_pg:gn_country":"UA",
    "qs_pg:gn_fcode":"PPL",
    "qs_pg:gn_pop":4090,
    "qs_pg:name":"Berezanka",
    "qs_pg:photos_9r":0,
    "qs_pg:photos_sr":0,
    "qs_pg:pop_sr":4,
    "qs_pg:qs_pg_placetype":"locality",
    "wof:name":"Berezanka",
    "wof:placetype":"locality",
    "wof:population":4090
},
  "geometry": {"coordinates":[31.38802,46.85262],"type":"Point"}
}