{
  "type": "Feature",
  "properties": {
    "gn:admin1_code":"7.0",
    "gn:asciiname":"Svynari",
    "gn:country_code":"UA",
    "gn:dem":194,
    "gn:feature_class":"P",
    "gn:feature_code":"PPL",
    "gn:name":"Svynari",
    "gn:population":0,
    "gn:timezone":"Europe/Kiev",
    "iso:country":"UA",
    "name:ukr_x_preferred":[
        "Svynari"
    ],
    "name:ukr_x_variant":[
        "\u0421\u0432\u0438\u043d\u0430\u0440\u0456"
    ],
    "wof:name":"Svynari",
    "wof:placetype":"locality"
},
  "geometry": {"coordinates":[35.74792,49.93789],"type":"Point"}
}