{
  "type": "Feature",
  "properties": {
    "gn:admin1_code":"13.0",
    "gn:asciiname":"Polyanichentsy",
    "gn:country_code":"UA",
    "gn:dem":189,
    "gn:feature_class":"P",
    "gn:feature_code":"PPL",
    "gn:name":"Polyanichentsy",
    "gn:population":0,
    "gn:timezone":"Europe/Kiev",
    "iso:country":"UA",
    "name:und_x_variant":[
        "Palenichentsy",
        "Palyanichentsy",
        "Polyanichentsy"
    ],
    "wof:name":"Polyanichentsy",
    "wof:placetype":"locality"
},
  "geometry": {"coordinates":[29.9855,49.99708],"type":"Point"}
}