{
  "type": "Feature",
  "properties": {
    "gn:admin1_code":"19.0",
    "gn:asciiname":"Nobel'",
    "gn:country_code":"UA",
    "gn:dem":142,
    "gn:feature_class":"P",
    "gn:feature_code":"PPL",
    "gn:name":"Nobel\u2019",
    "gn:population":0,
    "gn:timezone":"Europe/Kiev",
    "iso:country":"UA",
    "name:ukr_x_preferred":[
        "Nobel\u2019"
    ],
    "name:ukr_x_variant":[
        "\u041d\u043e\u0431\u0435\u043b\u044c"
    ],
    "name:und_x_variant":[
        "Nobel\u2019",
        "Nebel\u2019"
    ],
    "wof:name":"Nobel'",
    "wof:placetype":"locality"
},
  "geometry": {"coordinates":[25.76566,51.86691],"type":"Point"}
}