{
  "type": "Feature",
  "properties": {
    "gn:admin1_code":"3.0",
    "gn:asciiname":"Staneshti De-Sus",
    "gn:country_code":"UA",
    "gn:dem":358,
    "gn:feature_class":"P",
    "gn:feature_code":"PPL",
    "gn:name":"Staneshti De-Sus",
    "gn:population":0,
    "gn:timezone":"Europe/Kiev",
    "iso:country":"UA",
    "wof:name":"Staneshti De-Sus",
    "wof:placetype":"locality"
},
  "geometry": {"coordinates":[26.06667,48.08333],"type":"Point"}
}