{
  "type": "Feature",
  "properties": {
    "gn:admin1_code":"5.0",
    "gn:admin2_code":"709904",
    "gn:asciiname":"Novotroyits'ke",
    "gn:country_code":"UA",
    "gn:dem":196,
    "gn:feature_class":"P",
    "gn:feature_code":"PPL",
    "gn:name":"Novotroyits\u2019ke",
    "gn:population":0,
    "gn:timezone":"Europe/Kiev",
    "iso:country":"UA",
    "name:deu_x_preferred":[
        "Nowotrojizke"
    ],
    "name:hye_x_preferred":[
        "\u0546\u0578\u057e\u0578\u057f\u0580\u0578\u056b\u0581\u056f\u0578\u0565"
    ],
    "name:rus_x_preferred":[
        "Novo-Troitskiy"
    ],
    "name:rus_x_variant":[
        "Novotroitskoye",
        "\u041d\u043e\u0432\u043e\u0442\u0440\u043e\u0438\u0446\u043a\u043e\u0435"
    ],
    "name:ukr_x_preferred":[
        "\u041d\u043e\u0432\u043e\u0442\u0440\u043e\u0457\u0446\u044c\u043a\u0435"
    ],
    "name:ukr_x_variant":[
        "Novotroyits\u2019ke"
    ],
    "name:und_x_variant":[
        "Novotrojic'ke"
    ],
    "wof:name":"Novotroyits'ke",
    "wof:placetype":"locality"
},
  "geometry": {"coordinates":[37.21584,48.57797],"type":"Point"}
}