{
  "type": "Feature",
  "properties": {
    "gn:admin1_code":"2.0",
    "gn:asciiname":"Bohdanove",
    "gn:country_code":"UA",
    "gn:dem":139,
    "gn:feature_class":"P",
    "gn:feature_code":"PPL",
    "gn:name":"Bohdanove",
    "gn:population":0,
    "gn:timezone":"Europe/Kiev",
    "iso:country":"UA",
    "name:ukr_x_preferred":[
        "Bohdanove"
    ],
    "wof:name":"Bohdanove",
    "wof:placetype":"locality"
},
  "geometry": {"coordinates":[33.29858,52.31592],"type":"Point"}
}