{
  "type": "Feature",
  "properties": {
    "gn:gn_country":"UA",
    "gn:gn_fcode":"PPL",
    "gn:gn_pop":0,
    "iso:country":"UA",
    "name:unk_x_variant":[
        "Bryukhovychi"
    ],
    "qs_pg:aaroncc":"UA",
    "qs_pg:gn_country":"UA",
    "qs_pg:gn_fcode":"PPL",
    "qs_pg:gn_pop":0,
    "qs_pg:name":"Bryukhovichi",
    "qs_pg:name_adm0":"Ukraine",
    "qs_pg:name_adm1":"L\u00b4vivs\u00b4ka Oblast\u00b4",
    "qs_pg:photos":42,
    "qs_pg:photos_1k":9,
    "qs_pg:photos_9k":1,
    "qs_pg:photos_9r":2,
    "qs_pg:photos_all":42,
    "qs_pg:photos_sr":2,
    "qs_pg:pop_sr":0,
    "qs_pg:qs_pg_placetype":"locality",
    "qs_pg:qs_pg_placetype_gp":"Town",
    "qs_pg:woe_adm0":23424976,
    "woe:adm0_id":23424976,
    "woe:name_adm0":"Ukraine",
    "woe:name_adm1":"L\u00b4vivs\u00b4ka Oblast\u00b4",
    "woe:placetype":"Town",
    "wof:name":"Bryukhovichi",
    "wof:placetype":"locality"
},
  "geometry": {"coordinates":[24.57964,49.58441],"type":"Point"}
}