{
  "type": "Feature",
  "properties": {
    "gn:admin1_code":"7.0",
    "gn:asciiname":"Ternova",
    "gn:country_code":"UA",
    "gn:dem":155,
    "gn:feature_class":"P",
    "gn:feature_code":"PPL",
    "gn:name":"Ternova",
    "gn:population":0,
    "gn:timezone":"Europe/Kiev",
    "iso:country":"UA",
    "name:ukr_x_preferred":[
        "Ternova"
    ],
    "name:ukr_x_variant":[
        "\u0422\u0435\u0440\u043d\u043e\u0432\u0430"
    ],
    "wof:name":"Ternova",
    "wof:placetype":"locality"
},
  "geometry": {"coordinates":[35.8106,50.03132],"type":"Point"}
}