{
  "type": "Feature",
  "properties": {
    "gn:admin1_code":"7.0",
    "gn:asciiname":"Velikaya Garazhevka",
    "gn:country_code":"UA",
    "gn:dem":86,
    "gn:feature_class":"P",
    "gn:feature_code":"PPL",
    "gn:name":"Velikaya Garazhevka",
    "gn:population":0,
    "gn:timezone":"Europe/Kiev",
    "iso:country":"UA",
    "wof:name":"Velikaya Garazhevka",
    "wof:placetype":"locality"
},
  "geometry": {"coordinates":[36.99639000000001,49.16861],"type":"Point"}
}