{
  "type": "Feature",
  "properties": {
    "gn:admin1_code":"8.0",
    "gn:asciiname":"Gordovatka",
    "gn:country_code":"UA",
    "gn:dem":31,
    "gn:feature_class":"P",
    "gn:feature_code":"PPL",
    "gn:name":"Gordovatka",
    "gn:population":0,
    "gn:timezone":"Europe/Kiev",
    "iso:country":"UA",
    "name:und_x_variant":[
        "Sidorovka",
        "Gordovatka"
    ],
    "wof:name":"Gordovatka",
    "wof:placetype":"locality"
},
  "geometry": {"coordinates":[33.17371,47.57113],"type":"Point"}
}