{
  "type": "Feature",
  "properties": {
    "gn:country":"UA",
    "gn:fcode":"PPL",
    "gn:population":5602,
    "iso:country":"UA",
    "qs_pg:aaroncc":"UA",
    "qs_pg:gn_country":"UA",
    "qs_pg:gn_fcode":"PPL",
    "qs_pg:gn_pop":5602,
    "qs_pg:name":"Makiv",
    "qs_pg:photos_9r":0,
    "qs_pg:photos_sr":0,
    "qs_pg:pop_sr":5,
    "qs_pg:qs_pg_placetype":"locality",
    "wof:name":"Makiv",
    "wof:placetype":"locality",
    "wof:population":5602
},
  "geometry": {"coordinates":[26.69188,48.79487],"type":"Point"}
}