{
  "type": "Feature",
  "properties": {
    "gn:admin1_code":"21.0",
    "gn:asciiname":"Sobycheve",
    "gn:country_code":"UA",
    "gn:dem":166,
    "gn:feature_class":"P",
    "gn:feature_code":"PPL",
    "gn:name":"Sobycheve",
    "gn:population":0,
    "gn:timezone":"Europe/Kiev",
    "iso:country":"UA",
    "name:eng_x_preferred":[
        "Sobichevo"
    ],
    "name:rus_x_preferred":[
        "\u0421\u043e\u0431\u0438\u0447\u0435\u0432\u043e"
    ],
    "name:ukr_x_preferred":[
        "Sobycheve"
    ],
    "name:ukr_x_variant":[
        "\u0421\u043e\u0431\u0438\u0447\u0435\u0432\u0435"
    ],
    "name:und_x_variant":[
        "Sobychevo",
        "Sobachev",
        "Sobichev"
    ],
    "wof:name":"Sobycheve",
    "wof:placetype":"locality"
},
  "geometry": {"coordinates":[33.69224000000001,51.81651],"type":"Point"}
}