{
  "type": "Feature",
  "properties": {
    "gn:population":3213,
    "iso:country":"UA",
    "name:eng_x_preferred":[
        "Shchebetovka"
    ],
    "name:eng_x_variant":[
        "Otus",
        "Otuz",
        "Otuzy",
        "Shchebetivka",
        "Shebetovka"
    ],
    "name:jpn_x_preferred":[
        "\u30af\u30ea\u30df\u30a2\u306e\u884c\u653f\u533a\u753b"
    ],
    "name:rus_x_preferred":[
        "\u0429\u0435\u0431\u0435\u0442\u043e\u0432\u043a\u0430"
    ],
    "name:ukr_x_preferred":[
        "\u0429\u0435\u0431\u0435\u0442\u043e\u0432\u043a\u0430"
    ],
    "name:unk_x_variant":[
        "Otuzy"
    ],
    "name:zho_x_preferred":[
        "\u514b\u91cc\u7c73\u4e9e\u884c\u653f\u5340\u5283"
    ],
    "qs:a0":"\u0423\u043a\u0440\u0430\u0457\u043d\u0430",
    "qs:a1":"*\u041a\u0440\u0438\u043c",
    "qs:a1_alt":"Krym",
    "qs:a1r":"0",
    "qs:a2":"\u0424\u0435\u043e\u0434\u043e\u0441\u0456\u044f",
    "qs:a2_alt":"Feodosiia",
    "qs:adm0":"\u0423\u043a\u0440\u0430\u0457\u043d\u0430",
    "qs:la_lc":"*",
    "qs:level":"locality",
    "qs:loc":"\u0429\u0435\u0431\u0435\u0442\u043e\u0432\u043a\u0430",
    "qs:loc_alt":"Schebetovka",
    "qs:pop":0,
    "qs:type":"buffered point",
    "wd:wordcount":821,
    "wof:lang":[
        "eng"
    ],
    "wof:name":"\u0429\u0435\u0431\u0435\u0442\u043e\u0432\u043a\u0430",
    "wof:placetype":"locality",
    "wof:population":3213
},
  "geometry": {"coordinates":[35.159903,44.93971],"type":"Point"}
}