{
  "type": "Feature",
  "properties": {
    "gn:admin1_code":"4.0",
    "gn:asciiname":"Kramarka",
    "gn:country_code":"UA",
    "gn:dem":108,
    "gn:feature_class":"P",
    "gn:feature_code":"PPL",
    "gn:name":"Kramarka",
    "gn:population":0,
    "gn:timezone":"Europe/Kiev",
    "iso:country":"UA",
    "name:pol_x_preferred":[
        "Kramarka"
    ],
    "name:ukr_x_preferred":[
        "Kramarka"
    ],
    "name:ukr_x_variant":[
        "\u041a\u0440\u0430\u043c\u0430\u0440\u043a\u0430"
    ],
    "name:vie_x_preferred":[
        "Kramarka"
    ],
    "wof:name":"Kramarka",
    "wof:placetype":"locality"
},
  "geometry": {"coordinates":[35.10394,48.94278],"type":"Point"}
}