{
  "type": "Feature",
  "properties": {
    "gn:admin1_code":"16.0",
    "gn:asciiname":"Khutora Sukhaya Greblya",
    "gn:country_code":"UA",
    "gn:dem":59,
    "gn:feature_class":"P",
    "gn:feature_code":"PPL",
    "gn:name":"Khutora Sukhaya Greblya",
    "gn:population":0,
    "gn:timezone":"Europe/Kiev",
    "iso:country":"UA",
    "name:und_x_variant":[
        "Novos\u00eblovka"
    ],
    "wof:name":"Khutora Sukhaya Greblya",
    "wof:placetype":"locality"
},
  "geometry": {"coordinates":[31.65,46.98333],"type":"Point"}
}