{
  "type": "Feature",
  "properties": {
    "gn:admin1_code":"17.0",
    "gn:asciiname":"Andriyevo-Ivanove",
    "gn:country_code":"UA",
    "gn:dem":45,
    "gn:feature_class":"P",
    "gn:feature_code":"PPL",
    "gn:name":"Andriyevo-Ivanove",
    "gn:population":0,
    "gn:timezone":"Europe/Kiev",
    "iso:country":"UA",
    "name:ukr_x_preferred":[
        "Andriyevo-Ivanove"
    ],
    "name:ukr_x_variant":[
        "\u0410\u043d\u0434\u0440\u0456\u0454\u0432\u043e-\u0406\u0432\u0430\u043d\u043e\u0432\u0435"
    ],
    "name:und_x_variant":[
        "Andreyevo-Ivanovo"
    ],
    "wof:name":"Andriyevo-Ivanove",
    "wof:placetype":"locality"
},
  "geometry": {"coordinates":[30.33248,46.75314],"type":"Point"}
}