{
  "type": "Feature",
  "properties": {
    "gn:population":7355,
    "iso:country":"UA",
    "name:ara_x_preferred":[
        "\u0641\u0648\u0644\u0648\u062f\u0627\u0631\u0643\u0627"
    ],
    "name:bel_x_preferred":[
        "\u0412\u0430\u043b\u043e\u0434\u0430\u0440\u043a\u0430"
    ],
    "name:ceb_x_preferred":[
        "Volodarka"
    ],
    "name:crh_x_preferred":[
        "Volodarka"
    ],
    "name:deu_x_preferred":[
        "Wolodarka"
    ],
    "name:eng_x_preferred":[
        "Volodarka"
    ],
    "name:jpn_x_preferred":[
        "\u30f4\u30a9\u30ed\u30c0\u30eb\u30ab"
    ],
    "name:nob_x_preferred":[
        "Volodarka"
    ],
    "name:nor_x_preferred":[
        "Volodarka"
    ],
    "name:pol_x_preferred":[
        "Wo\u0142odarka"
    ],
    "name:ron_x_preferred":[
        "Volodarka"
    ],
    "name:rus_x_preferred":[
        "\u0412\u043e\u043b\u043e\u0434\u0430\u0440\u043a\u0430"
    ],
    "name:sah_x_preferred":[
        "\u0412\u043e\u043b\u043e\u0434\u0430\u0440\u043a\u0430"
    ],
    "name:sco_x_preferred":[
        "Volodarka"
    ],
    "name:spa_x_preferred":[
        "Volodarka"
    ],
    "name:ukr_x_preferred":[
        "\u0412\u043e\u043b\u043e\u0434\u0430\u0440\u043a\u0430"
    ],
    "name:unk_x_variant":[
        "Volodarka"
    ],
    "name:zho_x_preferred":[
        "\u6c83\u6d1b\u9054\u723e\u5361"
    ],
    "qs:a0":"\u0423\u043a\u0440\u0430\u0457\u043d\u0430",
    "qs:a1":"*\u041a\u0438\u0457\u0432\u0441\u044c\u043a\u0430",
    "qs:a1_alt":"Kyivs'ka",
    "qs:a1r":"0",
    "qs:a2":"\u0412\u043e\u043b\u043e\u0434\u0430\u0440\u0441\u044c\u043a\u0438\u0439",
    "qs:a2_alt":"Volodars'kyi",
    "qs:adm0":"\u0423\u043a\u0440\u0430\u0457\u043d\u0430",
    "qs:la_lc":"*",
    "qs:level":"locality",
    "qs:loc":"\u0412\u043e\u043b\u043e\u0434\u0430\u0440\u043a\u0430",
    "qs:loc_alt":"Volodarka",
    "qs:pop":0,
    "qs:type":"buffered point",
    "wd:wordcount":83,
    "wof:name":"\u0412\u043e\u043b\u043e\u0434\u0430\u0440\u043a\u0430",
    "wof:placetype":"locality",
    "wof:population":7355
},
  "geometry": {"coordinates":[29.92452,49.520761],"type":"Point"}
}