{
  "type": "Feature",
  "properties": {
    "gn:admin1_code":"7.0",
    "gn:asciiname":"Novomykolayivka",
    "gn:country_code":"UA",
    "gn:dem":173,
    "gn:feature_class":"P",
    "gn:feature_code":"PPL",
    "gn:name":"Novomykolayivka",
    "gn:population":0,
    "gn:timezone":"Europe/Kiev",
    "iso:country":"UA",
    "name:ukr_x_preferred":[
        "Novomykolayivka"
    ],
    "name:ukr_x_variant":[
        "\u041d\u043e\u0432\u043e\u043c\u0438\u043a\u043e\u043b\u0430\u0457\u0432\u043a\u0430"
    ],
    "name:und_x_variant":[
        "Novonikolayevka"
    ],
    "wof:name":"Novomykolayivka",
    "wof:placetype":"locality"
},
  "geometry": {"coordinates":[36.50918,48.72094],"type":"Point"}
}