{
  "type": "Feature",
  "properties": {
    "gn:admin1_code":"7.0",
    "gn:asciiname":"Latyshevka",
    "gn:cc2":"UA",
    "gn:country_code":"UA",
    "gn:dem":160,
    "gn:feature_class":"P",
    "gn:feature_code":"PPL",
    "gn:name":"Latysh\u00ebvka",
    "gn:population":0,
    "gn:timezone":"Europe/Kiev",
    "iso:country":"UA",
    "name:und_x_variant":[
        "Latyshov",
        "Latysh\u00ebvka"
    ],
    "wof:name":"Latyshevka",
    "wof:placetype":"locality"
},
  "geometry": {"coordinates":[35.32388,49.80631],"type":"Point"}
}