{
  "type": "Feature",
  "properties": {
    "gn:admin1_code":"17.0",
    "gn:asciiname":"Vil'ne",
    "gn:country_code":"UA",
    "gn:dem":52,
    "gn:feature_class":"P",
    "gn:feature_code":"PPL",
    "gn:name":"Vil\u2019ne",
    "gn:population":0,
    "gn:timezone":"Europe/Kiev",
    "iso:country":"UA",
    "name:ukr_x_preferred":[
        "Vil\u2019ne"
    ],
    "name:ukr_x_variant":[
        "\u0412\u0456\u043b\u044c\u043d\u0435"
    ],
    "name:und_x_variant":[
        "Isirliya",
        "Iserliya",
        "Iserlia",
        "Vol\u2019noye"
    ],
    "wof:name":"Vil'ne",
    "wof:placetype":"locality"
},
  "geometry": {"coordinates":[29.04815,45.985],"type":"Point"}
}