{
  "type": "Feature",
  "properties": {
    "gn:admin1_code":"26.0",
    "gn:asciiname":"Petrivka",
    "gn:country_code":"UA",
    "gn:dem":91,
    "gn:feature_class":"P",
    "gn:feature_code":"PPL",
    "gn:name":"Petrivka",
    "gn:population":0,
    "gn:timezone":"Europe/Zaporozhye",
    "iso:country":"UA",
    "name:ukr_x_preferred":[
        "Petrivka"
    ],
    "name:ukr_x_variant":[
        "\u041f\u0435\u0442\u0440\u0456\u0432\u043a\u0430"
    ],
    "name:und_x_variant":[
        "Orekhovskiy",
        "Petrovka"
    ],
    "wof:name":"Petrivka",
    "wof:placetype":"locality"
},
  "geometry": {"coordinates":[35.31511,47.33216],"type":"Point"}
}