{
  "type": "Feature",
  "properties": {
    "iso:country":"UA",
    "qs:a0":"\u0423\u043a\u0440\u0430\u0457\u043d\u0430",
    "qs:a1":"*\u041b\u0443\u0433\u0430\u043d\u0441\u044c\u043a\u0430",
    "qs:a1_alt":"Luhans'ka",
    "qs:a1r":"0",
    "qs:a2":"\u041a\u0440\u0430\u0441\u043d\u043e\u0434\u043e\u043d\u0441\u044c\u043a\u0438\u0439",
    "qs:a2_alt":"Krasnodons'kyi",
    "qs:adm0":"\u0423\u043a\u0440\u0430\u0457\u043d\u0430",
    "qs:la_lc":"*",
    "qs:level":"locality",
    "qs:loc":"\u0415\u043d\u0433\u0435\u043b\u044c\u0441\u043e\u0432\u0435",
    "qs:loc_alt":"Enhel'sove",
    "qs:pop":0,
    "qs:type":"buffered point",
    "wof:name":"\u0415\u043d\u0433\u0435\u043b\u044c\u0441\u043e\u0432\u0435",
    "wof:placetype":"locality"
},
  "geometry": {"coordinates":[39.613141,48.301061],"type":"Point"}
}