{
  "type": "Feature",
  "properties": {
    "gn:admin1_code":"7.0",
    "gn:asciiname":"Zamist",
    "gn:country_code":"UA",
    "gn:dem":164,
    "gn:feature_class":"P",
    "gn:feature_code":"PPL",
    "gn:name":"Zamist",
    "gn:population":0,
    "gn:timezone":"Europe/Kiev",
    "iso:country":"UA",
    "name:ukr_x_preferred":[
        "Zamist"
    ],
    "name:ukr_x_variant":[
        "\u0417\u0430\u043c\u0456\u0441\u0442"
    ],
    "wof:name":"Zamist",
    "wof:placetype":"locality"
},
  "geometry": {"coordinates":[37.39808,50.06885],"type":"Point"}
}