{
  "type": "Feature",
  "properties": {
    "gn:admin1_code":"7.0",
    "gn:asciiname":"Hubarivka",
    "gn:country_code":"UA",
    "gn:dem":197,
    "gn:feature_class":"P",
    "gn:feature_code":"PPL",
    "gn:name":"Hubarivka",
    "gn:population":0,
    "gn:timezone":"Europe/Kiev",
    "iso:country":"UA",
    "name:ukr_x_preferred":[
        "Hubarivka"
    ],
    "name:ukr_x_variant":[
        "\u0413\u0443\u0431\u0430\u0440\u0456\u0432\u043a\u0430"
    ],
    "name:und_x_variant":[
        "Gubarevka",
        "Gubarovka"
    ],
    "wof:name":"Hubarivka",
    "wof:placetype":"locality"
},
  "geometry": {"coordinates":[35.36492,50.16693],"type":"Point"}
}