{
  "type": "Feature",
  "properties": {
    "gn:gn_country":"UA",
    "gn:gn_fcode":"PPL",
    "gn:gn_pop":5243,
    "gn:population":5243,
    "iso:country":"UA",
    "name:deu_x_preferred":[
        "Sorja"
    ],
    "name:eng_x_preferred":[
        "Zoria"
    ],
    "name:lav_x_preferred":[
        "Zorja"
    ],
    "name:ron_x_preferred":[
        "Camcic"
    ],
    "name:rus_x_preferred":[
        "\u0417\u043e\u0440\u044f"
    ],
    "name:spa_x_preferred":[
        "Zoria"
    ],
    "name:ukr_x_preferred":[
        "\u0417\u043e\u0440\u044f"
    ],
    "name:unk_x_variant":[
        "Camcic"
    ],
    "qs_pg:aaroncc":"UA",
    "qs_pg:gn_country":"UA",
    "qs_pg:gn_fcode":"PPL",
    "qs_pg:gn_pop":5243,
    "qs_pg:name":"Zarya",
    "qs_pg:photos_9r":0,
    "qs_pg:photos_sr":0,
    "qs_pg:pop_sr":5,
    "qs_pg:qs_pg_placetype":"locality",
    "wof:name":"Zarya",
    "wof:placetype":"locality",
    "wof:population":5243
},
  "geometry": {"coordinates":[29.69672,45.9908],"type":"Point"}
}