{
  "type": "Feature",
  "properties": {
    "gn:admin1_code":"24.0",
    "gn:asciiname":"Kiselin",
    "gn:cc2":"UA",
    "gn:country_code":"UA",
    "gn:dem":208,
    "gn:feature_class":"P",
    "gn:feature_code":"PPL",
    "gn:name":"Kiselin",
    "gn:population":0,
    "gn:timezone":"Europe/Kiev",
    "iso:country":"UA",
    "name:bel_x_preferred":[
        "\u041a\u044b\u0441\u044b\u043b\u044b\u043d"
    ],
    "name:deu_x_preferred":[
        "Kyssylyn"
    ],
    "name:fra_x_preferred":[
        "Kysylyn"
    ],
    "name:hye_x_preferred":[
        "\u053f\u056b\u057d\u056b\u056c\u056b\u0576"
    ],
    "name:pol_x_preferred":[
        "Kisielin"
    ],
    "name:ron_x_preferred":[
        "K\u00ees\u00eel\u00een"
    ],
    "name:rus_x_preferred":[
        "\u041a\u0438\u0441\u0438\u043b\u0438\u043d"
    ],
    "name:ukr_x_preferred":[
        "\u041a\u0438\u0441\u0438\u043b\u0438\u043d"
    ],
    "name:und_x_variant":[
        "Kisilien",
        "Kiselin"
    ],
    "name:zho_x_preferred":[
        "\u57fa\u897f\u6797"
    ],
    "wof:name":"Kiselin",
    "wof:placetype":"locality"
},
  "geometry": {"coordinates":[24.80301,50.85299000000001],"type":"Point"}
}