{
  "type": "Feature",
  "properties": {
    "gn:admin1_code":"24.0",
    "gn:asciiname":"Kiselin",
    "gn:cc2":"UA",
    "gn:country_code":"UA",
    "gn:dem":208,
    "gn:feature_class":"P",
    "gn:feature_code":"PPL",
    "gn:name":"Kiselin",
    "gn:population":0,
    "gn:timezone":"Europe/Kiev",
    "iso:country":"UA",
    "name:und_x_variant":[
        "Kysylyn",
        "Kisilien",
        "Kisielin",
        "Kiselin"
    ],
    "wof:name":"Kiselin",
    "wof:placetype":"locality"
},
  "geometry": {"coordinates":[24.80301,50.85299000000001],"type":"Point"}
}