{
  "type": "Feature",
  "properties": {
    "gn:country":"UA",
    "gn:fcode":"PPL",
    "gn:population":2102,
    "iso:country":"UA",
    "name:ceb_x_preferred":[
        "Dudchany"
    ],
    "name:deu_x_preferred":[
        "Dudtschany"
    ],
    "name:eng_x_preferred":[
        "Dudchany"
    ],
    "name:lav_x_preferred":[
        "Dud\u010dani"
    ],
    "name:ron_x_preferred":[
        "Dudcean\u00ee"
    ],
    "name:rus_x_preferred":[
        "\u0414\u0443\u0434\u0447\u0430\u043d\u044b"
    ],
    "name:ukr_x_preferred":[
        "\u0414\u0443\u0434\u0447\u0430\u043d\u0438"
    ],
    "name:und_x_variant":[
        "Dudchino"
    ],
    "name:zho_x_preferred":[
        "\u675c\u5fb7\u6070\u5c3c"
    ],
    "qs_pg:aaroncc":"UA",
    "qs_pg:gn_country":"UA",
    "qs_pg:gn_fcode":"PPL",
    "qs_pg:gn_pop":2102,
    "qs_pg:name":"Dudchany",
    "qs_pg:photos_9r":0,
    "qs_pg:photos_sr":0,
    "qs_pg:pop_sr":4,
    "qs_pg:qs_pg_placetype":"locality",
    "wof:name":"Dudchany",
    "wof:placetype":"locality",
    "wof:population":2102
},
  "geometry": {"coordinates":[33.7639,47.18557],"type":"Point"}
}