{
  "type": "Feature",
  "properties": {
    "gn:admin1_code":"2.0",
    "gn:asciiname":"Kukovyts'ke",
    "gn:country_code":"UA",
    "gn:dem":111,
    "gn:feature_class":"P",
    "gn:feature_code":"PPL",
    "gn:name":"Kukovyts\u2019ke",
    "gn:population":0,
    "gn:timezone":"Europe/Kiev",
    "iso:country":"UA",
    "name:ukr_x_preferred":[
        "Kukovyts\u2019ke"
    ],
    "name:ukr_x_variant":[
        "\u041a\u0443\u043a\u043e\u0432\u0438\u0446\u044c\u043a\u0435"
    ],
    "name:und_x_variant":[
        "Khutora Kukovitskiye",
        "Kukovitskoye"
    ],
    "wof:name":"Kukovyts'ke",
    "wof:placetype":"locality"
},
  "geometry": {"coordinates":[32.26667,51.43333],"type":"Point"}
}