{
  "type": "Feature",
  "properties": {
    "gn:admin1_code":"26.0",
    "gn:asciiname":"Orlivs'ke",
    "gn:country_code":"UA",
    "gn:dem":99,
    "gn:feature_class":"P",
    "gn:feature_code":"PPL",
    "gn:name":"Orlivs\u2019ke",
    "gn:population":0,
    "gn:timezone":"Europe/Zaporozhye",
    "iso:country":"UA",
    "name:ukr_x_preferred":[
        "Orlivs\u2019ke"
    ],
    "name:ukr_x_variant":[
        "\u041e\u0440\u043b\u0456\u0432\u0441\u044c\u043a\u0435"
    ],
    "wof:name":"Orlivs'ke",
    "wof:placetype":"locality"
},
  "geometry": {"coordinates":[35.08450999999999,48.09166],"type":"Point"}
}