{
  "type": "Feature",
  "properties": {
    "gn:admin1_code":"18.0",
    "gn:asciiname":"Chervonyy Kut",
    "gn:country_code":"UA",
    "gn:dem":103,
    "gn:feature_class":"P",
    "gn:feature_code":"PPL",
    "gn:name":"Chervonyy Kut",
    "gn:population":0,
    "gn:timezone":"Europe/Kiev",
    "iso:country":"UA",
    "name:ukr_x_preferred":[
        "Chervonyy Kut"
    ],
    "name:ukr_x_variant":[
        "\u0427\u0435\u0440\u0432\u043e\u043d\u0438\u0439 \u041a\u0443\u0442"
    ],
    "wof:name":"Chervonyy Kut",
    "wof:placetype":"locality"
},
  "geometry": {"coordinates":[33.97518,50.32498],"type":"Point"}
}