{
  "type": "Feature",
  "properties": {
    "gn:admin1_code":"23.0",
    "gn:asciiname":"Guta",
    "gn:country_code":"UA",
    "gn:dem":191,
    "gn:feature_class":"P",
    "gn:feature_code":"PPL",
    "gn:name":"Guta",
    "gn:population":0,
    "gn:timezone":"Europe/Kiev",
    "iso:country":"UA",
    "name:bul_x_preferred":[
        "\u0413\u0443\u0442\u0430"
    ],
    "name:ceb_x_preferred":[
        "Guta"
    ],
    "name:deu_x_preferred":[
        "Guta"
    ],
    "name:ita_x_preferred":[
        "Guta"
    ],
    "name:lav_x_preferred":[
        "Guta"
    ],
    "name:rus_x_preferred":[
        "\u0413\u0443\u0442\u0430"
    ],
    "name:slk_x_preferred":[
        "Guta"
    ],
    "name:spa_x_preferred":[
        "Guta"
    ],
    "wof:name":"Guta",
    "wof:placetype":"locality"
},
  "geometry": {"coordinates":[29.10317,48.66804000000001],"type":"Point"}
}