{
  "type": "Feature",
  "properties": {
    "gn:admin1_code":"23.0",
    "gn:asciiname":"Guta",
    "gn:country_code":"UA",
    "gn:dem":191,
    "gn:feature_class":"P",
    "gn:feature_code":"PPL",
    "gn:name":"Guta",
    "gn:population":0,
    "gn:timezone":"Europe/Kiev",
    "iso:country":"UA",
    "wof:name":"Guta",
    "wof:placetype":"locality"
},
  "geometry": {"coordinates":[29.10317,48.66804000000001],"type":"Point"}
}