{
  "type": "Feature",
  "properties": {
    "gn:admin1_code":"7.0",
    "gn:asciiname":"Ray-Olenivka",
    "gn:country_code":"UA",
    "gn:dem":141,
    "gn:feature_class":"P",
    "gn:feature_code":"PPL",
    "gn:name":"Ray-Olenivka",
    "gn:population":0,
    "gn:timezone":"Europe/Kiev",
    "iso:country":"UA",
    "name:ukr_x_preferred":[
        "Ray-Olenivka"
    ],
    "name:ukr_x_variant":[
        "\u0420\u0430\u0439-\u041e\u043b\u0435\u043d\u0456\u0432\u043a\u0430"
    ],
    "name:und_x_variant":[
        "Rayyelenovka"
    ],
    "wof:name":"Ray-Olenivka",
    "wof:placetype":"locality"
},
  "geometry": {"coordinates":[36.06978,49.94317],"type":"Point"}
}