{
  "type": "Feature",
  "properties": {
    "gn:admin1_code":"9.0",
    "gn:asciiname":"Brazhyntsi",
    "gn:country_code":"UA",
    "gn:dem":250,
    "gn:feature_class":"P",
    "gn:feature_code":"PPL",
    "gn:name":"Brazhyntsi",
    "gn:population":0,
    "gn:timezone":"Europe/Kiev",
    "iso:country":"UA",
    "name:ukr_x_preferred":[
        "Brazhyntsi"
    ],
    "name:ukr_x_variant":[
        "\u0411\u0440\u0430\u0436\u0438\u043d\u0446\u0456"
    ],
    "name:und_x_variant":[
        "Brazhentsy",
        "Brazhintsy"
    ],
    "wof:name":"Brazhyntsi",
    "wof:placetype":"locality"
},
  "geometry": {"coordinates":[27.51868,49.9686],"type":"Point"}
}