{
  "type": "Feature",
  "properties": {
    "gn:admin1_code":"9.0",
    "gn:asciiname":"Novyye Netechintsy",
    "gn:cc2":"UA",
    "gn:country_code":"UA",
    "gn:dem":297,
    "gn:feature_class":"P",
    "gn:feature_code":"PPL",
    "gn:name":"Novyye Netechintsy",
    "gn:population":0,
    "gn:timezone":"Europe/Kiev",
    "iso:country":"UA",
    "name:und_x_variant":[
        "Netechintsy Novyye",
        "Novyye Netechintsy"
    ],
    "wof:name":"Novyye Netechintsy",
    "wof:placetype":"locality"
},
  "geometry": {"coordinates":[27.35,49.06667],"type":"Point"}
}