{
  "type": "Feature",
  "properties": {
    "gn:admin1_code":"9.0",
    "gn:asciiname":"Hnatky",
    "gn:country_code":"UA",
    "gn:dem":301,
    "gn:feature_class":"P",
    "gn:feature_code":"PPL",
    "gn:name":"Hnatky",
    "gn:population":0,
    "gn:timezone":"Europe/Kiev",
    "iso:country":"UA",
    "name:ukr_x_preferred":[
        "Hnatky"
    ],
    "name:ukr_x_variant":[
        "\u0413\u043d\u0430\u0442\u043a\u0438"
    ],
    "name:und_x_variant":[
        "Ignatki"
    ],
    "wof:name":"Hnatky",
    "wof:placetype":"locality"
},
  "geometry": {"coordinates":[27.36564000000001,49.68457],"type":"Point"}
}