{
  "type": "Feature",
  "properties": {
    "gn:admin1_code":"7.0",
    "gn:asciiname":"Buhayivka",
    "gn:country_code":"UA",
    "gn:dem":171,
    "gn:feature_class":"P",
    "gn:feature_code":"PPL",
    "gn:name":"Buhayivka",
    "gn:population":0,
    "gn:timezone":"Europe/Kiev",
    "iso:country":"UA",
    "name:ukr_x_preferred":[
        "Buhayivka"
    ],
    "name:ukr_x_variant":[
        "\u0411\u0443\u0433\u0430\u0457\u0432\u043a\u0430"
    ],
    "wof:name":"Buhayivka",
    "wof:placetype":"locality"
},
  "geometry": {"coordinates":[35.53907,49.76307],"type":"Point"}
}