{
  "type": "Feature",
  "properties": {
    "gn:admin1_code":"17.0",
    "gn:asciiname":"Fedorivka",
    "gn:country_code":"UA",
    "gn:dem":73,
    "gn:feature_class":"P",
    "gn:feature_code":"PPL",
    "gn:name":"Fedorivka",
    "gn:population":0,
    "gn:timezone":"Europe/Kiev",
    "iso:country":"UA",
    "name:rus_x_preferred":[
        "F\u00ebdorovka"
    ],
    "name:ukr_x_preferred":[
        "Fedorivka"
    ],
    "name:ukr_x_variant":[
        "\u0424\u0435\u0434\u043e\u0440\u0456\u0432\u043a\u0430"
    ],
    "wof:name":"Fedorivka",
    "wof:placetype":"locality"
},
  "geometry": {"coordinates":[29.35029,47.39368],"type":"Point"}
}