{
  "type": "Feature",
  "properties": {
    "gn:admin1_code":"7.0",
    "gn:asciiname":"Bile",
    "gn:country_code":"UA",
    "gn:dem":97,
    "gn:feature_class":"P",
    "gn:feature_code":"PPL",
    "gn:name":"Bile",
    "gn:population":0,
    "gn:timezone":"Europe/Kiev",
    "iso:country":"UA",
    "name:ukr_x_preferred":[
        "Bile"
    ],
    "name:und_x_variant":[
        "Belaya",
        "Beloye"
    ],
    "wof:name":"Bile",
    "wof:placetype":"locality"
},
  "geometry": {"coordinates":[37.56972,49.48806],"type":"Point"}
}