{
  "type": "Feature",
  "properties": {
    "iso:country":"UA",
    "name:ukr_x_preferred":[
        "Hlushytsya"
    ],
    "name:ukr_x_variant":[
        "\u0413\u043b\u0443\u0448\u0438\u0446\u044f"
    ],
    "name:unk_x_variant":[
        "Glushytsa"
    ],
    "qs:a0":"\u0423\u043a\u0440\u0430\u0457\u043d\u0430",
    "qs:a1":"*\u0420\u0456\u0432\u043d\u0435\u043d\u0441\u044c\u043a\u0430",
    "qs:a1_alt":"Rivnens'ka",
    "qs:a1r":"0",
    "qs:a2":"\u0421\u0430\u0440\u043d\u0435\u043d\u0441\u044c\u043a\u0438\u0439",
    "qs:a2_alt":"Sarnens'kyi",
    "qs:adm0":"\u0423\u043a\u0440\u0430\u0457\u043d\u0430",
    "qs:la_lc":"*",
    "qs:level":"locality",
    "qs:loc":"\u0413\u043b\u0443\u0448\u0438\u0446\u044f",
    "qs:loc_alt":"Hlushytsia",
    "qs:pop":0,
    "qs:type":"buffered point",
    "wof:name":"\u0413\u043b\u0443\u0448\u0438\u0446\u044f",
    "wof:placetype":"locality"
},
  "geometry": {"coordinates":[26.643926,51.395055],"type":"Point"}
}