{
  "type": "Feature",
  "properties": {
    "iso:country":"UA",
    "name:und_x_variant":[
        "Rude Selo"
    ],
    "qs:a0":"\u0423\u043a\u0440\u0430\u0457\u043d\u0430",
    "qs:a1":"*\u041a\u0438\u0457\u0432\u0441\u044c\u043a\u0430",
    "qs:a1_alt":"Kyivs'ka",
    "qs:a1r":"0",
    "qs:a2":"\u0412\u043e\u043b\u043e\u0434\u0430\u0440\u0441\u044c\u043a\u0438\u0439",
    "qs:a2_alt":"Volodars'kyi",
    "qs:adm0":"\u0423\u043a\u0440\u0430\u0457\u043d\u0430",
    "qs:la_lc":"*",
    "qs:level":"locality",
    "qs:loc":"\u0420\u0443\u0434\u0435 \u0421\u0435\u043b\u043e",
    "qs:loc_alt":"Rude Selo",
    "qs:pop":0,
    "qs:type":"buffered point",
    "wof:name":"\u0420\u0443\u0434\u0435 \u0421\u0435\u043b\u043e",
    "wof:placetype":"locality"
},
  "geometry": {"coordinates":[29.717198,49.498717],"type":"Point"}
}