{
  "type": "Feature",
  "properties": {
    "gn:admin1_code":"23.0",
    "gn:asciiname":"Dubyna",
    "gn:country_code":"UA",
    "gn:dem":294,
    "gn:feature_class":"P",
    "gn:feature_code":"PPL",
    "gn:name":"Dubyna",
    "gn:population":0,
    "gn:timezone":"Europe/Kiev",
    "iso:country":"UA",
    "name:ukr_x_preferred":[
        "Dubyna"
    ],
    "name:und_x_variant":[
        "\u0414\u0443\u0431\u0438\u043d\u0430",
        "Dubina"
    ],
    "wof:name":"Dubyna",
    "wof:placetype":"locality"
},
  "geometry": {"coordinates":[28.31294,48.84891],"type":"Point"}
}