{
  "type": "Feature",
  "properties": {
    "gn:admin1_code":"3.0",
    "gn:asciiname":"Becheshti",
    "gn:country_code":"UA",
    "gn:dem":248,
    "gn:feature_class":"P",
    "gn:feature_code":"PPL",
    "gn:name":"Becheshti",
    "gn:population":0,
    "gn:timezone":"Europe/Kiev",
    "iso:country":"UA",
    "wof:name":"Becheshti",
    "wof:placetype":"locality"
},
  "geometry": {"coordinates":[26.15,48.13333],"type":"Point"}
}