{
  "type": "Feature",
  "properties": {
    "gn:admin1_code":"7.0",
    "gn:asciiname":"Zolochivs'ke",
    "gn:country_code":"UA",
    "gn:dem":161,
    "gn:feature_class":"P",
    "gn:feature_code":"PPL",
    "gn:name":"Zolochivs\u2019ke",
    "gn:population":0,
    "gn:timezone":"Europe/Kiev",
    "iso:country":"UA",
    "name:ukr_x_preferred":[
        "Zolochivs\u2019ke"
    ],
    "name:ukr_x_variant":[
        "\u0417\u043e\u043b\u043e\u0447\u0456\u0432\u0441\u044c\u043a\u0435"
    ],
    "wof:name":"Zolochivs'ke",
    "wof:placetype":"locality"
},
  "geometry": {"coordinates":[35.74953,49.95399999999999],"type":"Point"}
}