{
  "type": "Feature",
  "properties": {
    "gn:admin1_code":"13.0",
    "gn:asciiname":"Malynivka",
    "gn:country_code":"UA",
    "gn:dem":200,
    "gn:feature_class":"P",
    "gn:feature_code":"PPL",
    "gn:name":"Malynivka",
    "gn:population":0,
    "gn:timezone":"Europe/Kiev",
    "iso:country":"UA",
    "name:deu_x_preferred":[
        "Malyniwka"
    ],
    "name:ukr_x_preferred":[
        "Malynivka"
    ],
    "name:ukr_x_variant":[
        "\u041c\u0430\u043b\u0438\u043d\u0456\u0432\u043a\u0430"
    ],
    "name:und_x_variant":[
        "Malinovka"
    ],
    "wof:name":"Malynivka",
    "wof:placetype":"locality"
},
  "geometry": {"coordinates":[29.51981,50.21724],"type":"Point"}
}