{
  "type": "Feature",
  "properties": {
    "iso:country":"UA",
    "qs:a0":"\u0423\u043a\u0440\u0430\u0457\u043d\u0430",
    "qs:a1":"*\u0427\u0435\u0440\u043d\u0456\u0433\u0456\u0432\u0441\u044c\u043a\u0430",
    "qs:a1_alt":"Chernihivs'ka",
    "qs:a1r":"0",
    "qs:a2":"\u0421\u0440\u0456\u0431\u043d\u044f\u043d\u0441\u044c\u043a\u0438\u0439",
    "qs:a2_alt":"Sribnians'kyi",
    "qs:adm0":"\u0423\u043a\u0440\u0430\u0457\u043d\u0430",
    "qs:la_lc":"*",
    "qs:level":"locality",
    "qs:loc":"\u0414\u0456\u0433\u0442\u044f\u0440\u0456",
    "qs:loc_alt":"Dihtiari",
    "qs:pop":0,
    "qs:type":"buffered point",
    "wof:name":"\u0414\u0456\u0433\u0442\u044f\u0440\u0456",
    "wof:placetype":"locality"
},
  "geometry": {"coordinates":[32.768154,50.581135],"type":"Point"}
}