{
  "type": "Feature",
  "properties": {
    "gn:admin1_code":"27.0",
    "gn:asciiname":"Yablunivka",
    "gn:country_code":"UA",
    "gn:dem":175,
    "gn:feature_class":"P",
    "gn:feature_code":"PPL",
    "gn:name":"Yablunivka",
    "gn:population":0,
    "gn:timezone":"Europe/Kiev",
    "iso:country":"UA",
    "name:pol_x_preferred":[
        "Jab\u0142on\u00f3wka"
    ],
    "name:ron_x_preferred":[
        "Iablunivka"
    ],
    "name:rus_x_preferred":[
        "\u042f\u0431\u043b\u043e\u043d\u043e\u0432\u043a\u0430"
    ],
    "name:ukr_x_preferred":[
        "Yablunivka"
    ],
    "name:ukr_x_variant":[
        "\u042f\u0431\u043b\u0443\u043d\u0456\u0432\u043a\u0430"
    ],
    "name:urd_x_preferred":[
        "\u06cc\u0628\u0644\u0646\u0648\u06a9\u0627"
    ],
    "name:zho_x_preferred":[
        "\u4e9e\u5e03\u76e7\u5c3c\u592b\u5361"
    ],
    "wof:name":"Yablunivka",
    "wof:placetype":"locality"
},
  "geometry": {"coordinates":[29.6116,49.9896],"type":"Point"}
}