{
  "type": "Feature",
  "properties": {
    "gn:gn_country":"UA",
    "gn:gn_fcode":"PPL",
    "gn:gn_pop":1109,
    "gn:population":1109,
    "iso:country":"UA",
    "name:arm_x_preferred":[
        "\u054f\u0578\u057a\u0578\u0580\u056b"
    ],
    "name:eng_x_preferred":[
        "Topory"
    ],
    "name:ger_x_preferred":[
        "Topory"
    ],
    "name:lav_x_preferred":[
        "Topori"
    ],
    "name:pol_x_preferred":[
        "Topory"
    ],
    "name:rum_x_preferred":[
        "Topor\u00ee"
    ],
    "name:rus_x_preferred":[
        "\u0422\u043e\u043f\u043e\u0440\u044b"
    ],
    "name:ukr_x_preferred":[
        "\u0422\u043e\u043f\u043e\u0440\u0438"
    ],
    "qs_pg:aaroncc":"UA",
    "qs_pg:gn_country":"UA",
    "qs_pg:gn_fcode":"PPL",
    "qs_pg:gn_pop":1109,
    "qs_pg:name":"Topory",
    "qs_pg:photos_9r":0,
    "qs_pg:photos_sr":0,
    "qs_pg:pop_sr":3,
    "qs_pg:qs_pg_placetype":"locality",
    "wof:name":"Topory",
    "wof:placetype":"locality",
    "wof:population":1109
},
  "geometry": {"coordinates":[29.3174,49.65186],"type":"Point"}
}