{
  "type": "Feature",
  "properties": {
    "gn:admin1_code":"4.0",
    "gn:asciiname":"Vil'ne",
    "gn:country_code":"UA",
    "gn:dem":134,
    "gn:feature_class":"P",
    "gn:feature_code":"PPL",
    "gn:name":"Vil\u2019ne",
    "gn:population":0,
    "gn:timezone":"Europe/Kiev",
    "iso:country":"UA",
    "name:rus_x_preferred":[
        "Vol\u2019noye"
    ],
    "name:rus_x_variant":[
        "\u0412\u043e\u043b\u044c\u043d\u043e\u0435"
    ],
    "name:ukr_x_preferred":[
        "Vil\u2019ne"
    ],
    "name:ukr_x_variant":[
        "\u0412\u0456\u043b\u044c\u043d\u0435"
    ],
    "wof:name":"Vil'ne",
    "wof:placetype":"locality"
},
  "geometry": {"coordinates":[33.65708,48.29764],"type":"Point"}
}