{
  "type": "Feature",
  "properties": {
    "gn:admin1_code":"19.0",
    "gn:asciiname":"Sobishchytsi",
    "gn:country_code":"UA",
    "gn:dem":160,
    "gn:feature_class":"P",
    "gn:feature_code":"PPL",
    "gn:name":"Sobishchytsi",
    "gn:population":0,
    "gn:timezone":"Europe/Kiev",
    "iso:country":"UA",
    "name:ukr_x_preferred":[
        "Sobishchytsi"
    ],
    "name:ukr_x_variant":[
        "\u0421\u043e\u0431\u0456\u0449\u0438\u0446\u0456"
    ],
    "name:und_x_variant":[
        "Sobeshchytse",
        "Sobeshchitsa",
        "Sobeshchitsy"
    ],
    "wof:name":"Sobishchytsi",
    "wof:placetype":"locality"
},
  "geometry": {"coordinates":[25.85128,51.40409],"type":"Point"}
}