{
  "type": "Feature",
  "properties": {
    "gn:admin1_code":"21.0",
    "gn:asciiname":"Grafs'ke",
    "gn:country_code":"UA",
    "gn:dem":153,
    "gn:feature_class":"P",
    "gn:feature_code":"PPL",
    "gn:name":"Grafs\u2019ke",
    "gn:population":0,
    "gn:timezone":"Europe/Kiev",
    "iso:country":"UA",
    "name:ukr_x_preferred":[
        "Grafs\u2019ke"
    ],
    "name:ukr_x_variant":[
        "\u0413\u0440\u0430\u0444\u0441\u044c\u043a\u0435"
    ],
    "name:und_x_variant":[
        "Garfskiy",
        "Grafskiy",
        "Grafskoye"
    ],
    "wof:name":"Grafs'ke",
    "wof:placetype":"locality"
},
  "geometry": {"coordinates":[34.60865,51.10228],"type":"Point"}
}