{
  "type": "Feature",
  "properties": {
    "gn:admin1_code":"21.0",
    "gn:asciiname":"Hrebenykivka",
    "gn:country_code":"UA",
    "gn:dem":163,
    "gn:feature_class":"P",
    "gn:feature_code":"PPL",
    "gn:name":"Hrebenykivka",
    "gn:population":0,
    "gn:timezone":"Europe/Kiev",
    "iso:country":"UA",
    "name:eng_x_preferred":[
        "Grebennikovka"
    ],
    "name:rus_x_preferred":[
        "\u0413\u0440\u0435\u0431\u0435\u043d\u0438\u043a\u043e\u0432\u043a\u0430"
    ],
    "name:ukr_x_preferred":[
        "Hrebenykivka"
    ],
    "name:ukr_x_variant":[
        "\u0413\u0440\u0435\u0431\u0435\u043d\u0438\u043a\u0456\u0432\u043a\u0430"
    ],
    "name:und_x_variant":[
        "Greben\u2019kovka",
        "Grebenikovka",
        "Grebennikovka"
    ],
    "wof:name":"Hrebenykivka",
    "wof:placetype":"locality"
},
  "geometry": {"coordinates":[35.00509,50.73333],"type":"Point"}
}