{
  "type": "Feature",
  "properties": {
    "gn:admin1_code":"8.0",
    "gn:asciiname":"Shilova Balka",
    "gn:country_code":"UA",
    "gn:dem":35,
    "gn:feature_class":"P",
    "gn:feature_code":"PPL",
    "gn:name":"Shilova Balka",
    "gn:population":0,
    "gn:timezone":"Europe/Kiev",
    "iso:country":"UA",
    "wof:name":"Shilova Balka",
    "wof:placetype":"locality"
},
  "geometry": {"coordinates":[33.31667,46.81667],"type":"Point"}
}