{
  "type": "Feature",
  "properties": {
    "gn:admin1_code":"15.0",
    "gn:asciiname":"Svyatoslav",
    "gn:country_code":"UA",
    "gn:dem":469,
    "gn:feature_class":"P",
    "gn:feature_code":"PPL",
    "gn:name":"Svyatoslav",
    "gn:population":0,
    "gn:timezone":"Europe/Kiev",
    "iso:country":"UA",
    "name:ukr_x_preferred":[
        "Svyatoslav"
    ],
    "name:ukr_x_variant":[
        "\u0421\u0432\u044f\u0442\u043e\u0441\u043b\u0430\u0432"
    ],
    "wof:name":"Svyatoslav",
    "wof:placetype":"locality"
},
  "geometry": {"coordinates":[23.47152,49.00627],"type":"Point"}
}