{
  "type": "Feature",
  "properties": {
    "gn:admin1_code":"16.0",
    "gn:asciiname":"Sukhaya Balka Pervyy Uchastok",
    "gn:country_code":"UA",
    "gn:dem":43,
    "gn:feature_class":"P",
    "gn:feature_code":"PPL",
    "gn:name":"Sukhaya Balka Pervyy Uchastok",
    "gn:population":0,
    "gn:timezone":"Europe/Kiev",
    "iso:country":"UA",
    "name:und_x_variant":[
        "Sukhaya Balka",
        "Sukhaya Balka Pervyy Uchastok"
    ],
    "wof:name":"Sukhaya Balka Pervyy Uchastok",
    "wof:placetype":"locality"
},
  "geometry": {"coordinates":[31.17809,47.43223],"type":"Point"}
}