{
  "type": "Feature",
  "properties": {
    "gn:admin1_code":"14.0",
    "gn:asciiname":"Shaparivka",
    "gn:country_code":"UA",
    "gn:dem":84,
    "gn:feature_class":"P",
    "gn:feature_code":"PPL",
    "gn:name":"Shaparivka",
    "gn:population":0,
    "gn:timezone":"Europe/Zaporozhye",
    "iso:country":"UA",
    "name:ukr_x_preferred":[
        "Shaparivka"
    ],
    "name:und_x_variant":[
        "Shaparskoye",
        "Shaparovka"
    ],
    "wof:name":"Shaparivka",
    "wof:placetype":"locality"
},
  "geometry": {"coordinates":[38.85277,49.49636],"type":"Point"}
}