{
  "type": "Feature",
  "properties": {
    "gn:admin1_code":"22.0",
    "gn:asciiname":"Mendzyguzhe",
    "gn:country_code":"UA",
    "gn:dem":202,
    "gn:feature_class":"P",
    "gn:feature_code":"PPL",
    "gn:name":"Mendzyguzhe",
    "gn:population":0,
    "gn:timezone":"Europe/Kiev",
    "iso:country":"UA",
    "wof:name":"Mendzyguzhe",
    "wof:placetype":"locality"
},
  "geometry": {"coordinates":[24.96667,49.03333],"type":"Point"}
}