{
  "type": "Feature",
  "properties": {
    "iso:country":"UA",
    "name:eng_x_preferred":[
        "Pechenegi"
    ],
    "name:rus_x_preferred":[
        "\u041f\u0435\u0447\u0435\u043d\u0435\u0433\u0438"
    ],
    "name:ukr_x_preferred":[
        "Pechenihy"
    ],
    "name:ukr_x_variant":[
        "\u041f\u0435\u0447\u0435\u043d\u0456\u0433\u0438"
    ],
    "qs:a0":"\u0423\u043a\u0440\u0430\u0457\u043d\u0430",
    "qs:a1":"*\u0425\u0430\u0440\u043a\u0456\u0432\u0441\u044c\u043a\u0430",
    "qs:a1_alt":"Kharkivs'ka",
    "qs:a1r":"0",
    "qs:a2":"\u041f\u0435\u0447\u0435\u043d\u0456\u0437\u044c\u043a\u0438\u0439",
    "qs:a2_alt":"Pecheniz'kyi",
    "qs:adm0":"\u0423\u043a\u0440\u0430\u0457\u043d\u0430",
    "qs:la_lc":"*",
    "qs:level":"locality",
    "qs:loc":"\u041f\u0435\u0447\u0435\u043d\u0456\u0433\u0438",
    "qs:loc_alt":"Pechenihy",
    "qs:pop":0,
    "qs:type":"buffered point",
    "wof:name":"\u041f\u0435\u0447\u0435\u043d\u0456\u0433\u0438",
    "wof:placetype":"locality"
},
  "geometry": {"coordinates":[36.914416,49.877271],"type":"Point"}
}