{
  "type": "Feature",
  "properties": {
    "gn:admin1_code":"22.0",
    "gn:asciiname":"Byalkovtse",
    "gn:country_code":"UA",
    "gn:dem":375,
    "gn:feature_class":"P",
    "gn:feature_code":"PPL",
    "gn:name":"Byalkovtse",
    "gn:population":0,
    "gn:timezone":"Europe/Kiev",
    "iso:country":"UA",
    "wof:name":"Byalkovtse",
    "wof:placetype":"locality"
},
  "geometry": {"coordinates":[25.30806,49.69001],"type":"Point"}
}