{
  "type": "Feature",
  "properties": {
    "gn:admin1_code":"23.0",
    "gn:asciiname":"Obozivka",
    "gn:country_code":"UA",
    "gn:dem":196,
    "gn:feature_class":"P",
    "gn:feature_code":"PPL",
    "gn:name":"Obozivka",
    "gn:population":0,
    "gn:timezone":"Europe/Kiev",
    "iso:country":"UA",
    "name:ukr_x_preferred":[
        "\u041e\u0431\u043e\u0437\u0456\u0432\u043a\u0430"
    ],
    "name:und_x_variant":[
        "Obozovka"
    ],
    "wof:name":"Obozivka",
    "wof:placetype":"locality"
},
  "geometry": {"coordinates":[29.4735,49.46022],"type":"Point"}
}