{
  "type": "Feature",
  "properties": {
    "gn:admin1_code":"23.0",
    "gn:asciiname":"Mal'ovnyche",
    "gn:country_code":"UA",
    "gn:dem":278,
    "gn:feature_class":"P",
    "gn:feature_code":"PPL",
    "gn:name":"Mal\u2019ovnyche",
    "gn:population":0,
    "gn:timezone":"Europe/Kiev",
    "iso:country":"UA",
    "name:rus_x_preferred":[
        "Mal\u00ebvnich\u2019ye"
    ],
    "name:ukr_x_preferred":[
        "\u041c\u0430\u043b\u044c\u043e\u0432\u043d\u0438\u0447\u0435"
    ],
    "name:und_x_variant":[
        "Mal\u2019ovnyche",
        "Patserovo"
    ],
    "wof:name":"Mal'ovnyche",
    "wof:placetype":"locality"
},
  "geometry": {"coordinates":[28.14315,48.78751],"type":"Point"}
}