{
  "type": "Feature",
  "properties": {
    "gn:admin1_code":"9.0",
    "gn:asciiname":"Podfilip'ye",
    "gn:country_code":"UA",
    "gn:dem":197,
    "gn:feature_class":"P",
    "gn:feature_code":"PPL",
    "gn:name":"Podfilip\u2019ye",
    "gn:population":0,
    "gn:timezone":"Europe/Kiev",
    "iso:country":"UA",
    "name:und_x_variant":[
        "Podfilipe",
        "Podfilip\u2019ye"
    ],
    "wof:name":"Podfilip'ye",
    "wof:placetype":"locality"
},
  "geometry": {"coordinates":[26.23716,48.76233],"type":"Point"}
}