{
  "type": "Feature",
  "properties": {
    "gn:admin1_code":"15.0",
    "gn:asciiname":"Starhorod",
    "gn:country_code":"UA",
    "gn:dem":189,
    "gn:feature_class":"P",
    "gn:feature_code":"PPL",
    "gn:name":"Starhorod",
    "gn:population":0,
    "gn:timezone":"Europe/Kiev",
    "iso:country":"UA",
    "name:ukr_x_preferred":[
        "Starhorod"
    ],
    "name:ukr_x_variant":[
        "\u0421\u0442\u0430\u0440\u0433\u043e\u0440\u043e\u0434"
    ],
    "name:und_x_variant":[
        "Stargorod"
    ],
    "wof:name":"Starhorod",
    "wof:placetype":"locality"
},
  "geometry": {"coordinates":[24.21459,50.58843],"type":"Point"}
}