{
  "type": "Feature",
  "properties": {
    "gn:admin1_code":"2.0",
    "gn:asciiname":"Trudovyk",
    "gn:country_code":"UA",
    "gn:dem":139,
    "gn:feature_class":"P",
    "gn:feature_code":"PPL",
    "gn:name":"Trudovyk",
    "gn:population":0,
    "gn:timezone":"Europe/Kiev",
    "iso:country":"UA",
    "name:ukr_x_preferred":[
        "Trudovyk"
    ],
    "name:ukr_x_variant":[
        "\u0422\u0440\u0443\u0434\u043e\u0432\u0438\u043a"
    ],
    "name:und_x_variant":[
        "Trudovik"
    ],
    "wof:name":"Trudovyk",
    "wof:placetype":"locality"
},
  "geometry": {"coordinates":[32.30974000000001,51.7573],"type":"Point"}
}