{
  "type": "Feature",
  "properties": {
    "gn:admin1_code":"15",
    "gn:asciiname":"Dobryany",
    "gn:country_code":"UA",
    "gn:dem":287,
    "gn:feature_class":"P",
    "gn:feature_code":"PPL",
    "gn:name":"Dobryany",
    "gn:population":0,
    "gn:timezone":"Europe/Kiev",
    "iso:country":"UA",
    "name:ukr_x_preferred":[
        "Dobryany"
    ],
    "name:ukr_x_variant":[
        "\u0414\u043e\u0431\u0440\u044f\u043d\u0438"
    ],
    "wof:name":"Dobryany",
    "wof:placetype":"locality"
},
  "geometry": {"coordinates":[23.88755,49.2847],"type":"Point"}
}