{
  "type": "Feature",
  "properties": {
    "gn:admin1_code":"1.0",
    "gn:asciiname":"Chubivka",
    "gn:country_code":"UA",
    "gn:dem":78,
    "gn:feature_class":"P",
    "gn:feature_code":"PPL",
    "gn:name":"Chubivka",
    "gn:population":0,
    "gn:timezone":"Europe/Kiev",
    "iso:country":"UA",
    "name:ukr_x_preferred":[
        "Chubivka"
    ],
    "name:ukr_x_variant":[
        "\u0427\u0443\u0431\u0456\u0432\u043a\u0430"
    ],
    "wof:name":"Chubivka",
    "wof:placetype":"locality"
},
  "geometry": {"coordinates":[32.20457,49.23605],"type":"Point"}
}