{
  "type": "Feature",
  "properties": {
    "gn:admin1_code":"17.0",
    "gn:asciiname":"Mikhaylopol'",
    "gn:country_code":"UA",
    "gn:dem":23,
    "gn:feature_class":"P",
    "gn:feature_code":"PPL",
    "gn:name":"Mikhaylopol\u2019",
    "gn:population":0,
    "gn:timezone":"Europe/Kiev",
    "iso:country":"UA",
    "wof:name":"Mikhaylopol'",
    "wof:placetype":"locality"
},
  "geometry": {"coordinates":[30.43152000000001,47.08998],"type":"Point"}
}