{
  "type": "Feature",
  "properties": {
    "gn:admin1_code":"26.0",
    "gn:asciiname":"Richne",
    "gn:country_code":"UA",
    "gn:dem":28,
    "gn:feature_class":"P",
    "gn:feature_code":"PPL",
    "gn:name":"Richne",
    "gn:population":0,
    "gn:timezone":"Europe/Zaporozhye",
    "iso:country":"UA",
    "name:ukr_x_preferred":[
        "Richne"
    ],
    "name:ukr_x_variant":[
        "\u0420\u0456\u0447\u043d\u0435"
    ],
    "name:und_x_variant":[
        "Rechnoye"
    ],
    "wof:name":"Richne",
    "wof:placetype":"locality"
},
  "geometry": {"coordinates":[35.31986,47.67406],"type":"Point"}
}