{
  "type": "Feature",
  "properties": {
    "gn:admin1_code":"27.0",
    "gn:asciiname":"Obyshche",
    "gn:country_code":"UA",
    "gn:dem":184,
    "gn:feature_class":"P",
    "gn:feature_code":"PPL",
    "gn:name":"Obyshche",
    "gn:population":0,
    "gn:timezone":"Europe/Kiev",
    "iso:country":"UA",
    "name:ukr_x_preferred":[
        "Obyshche"
    ],
    "name:ukr_x_variant":[
        "\u041e\u0431\u0438\u0449\u0435"
    ],
    "wof:name":"Obyshche",
    "wof:placetype":"locality"
},
  "geometry": {"coordinates":[27.79237,51.26944],"type":"Point"}
}