{
  "type": "Feature",
  "properties": {
    "iso:country":"UA",
    "name:eng_x_preferred":[
        "Pochapintsy"
    ],
    "name:rus_x_preferred":[
        "\u041f\u043e\u0447\u0430\u043f\u0438\u043d\u0446\u044b"
    ],
    "name:unk_x_variant":[
        "Pochapintsy"
    ],
    "qs:a0":"\u0423\u043a\u0440\u0430\u0457\u043d\u0430",
    "qs:a1":"*\u0427\u0435\u0440\u043a\u0430\u0441\u044c\u043a\u0430",
    "qs:a1_alt":"Cherkas'ka",
    "qs:a1r":"0",
    "qs:a2":"\u041b\u0438\u0441\u044f\u043d\u0441\u044c\u043a\u0438\u0439",
    "qs:a2_alt":"Lysians'kyi",
    "qs:adm0":"\u0423\u043a\u0440\u0430\u0457\u043d\u0430",
    "qs:la_lc":"*",
    "qs:level":"locality",
    "qs:loc":"\u041f\u043e\u0447\u0430\u043f\u0438\u043d\u0446\u0456",
    "qs:loc_alt":"Pochapyntsi",
    "qs:pop":0,
    "qs:type":"buffered point",
    "wof:name":"\u041f\u043e\u0447\u0430\u043f\u0438\u043d\u0446\u0456",
    "wof:placetype":"locality"
},
  "geometry": {"coordinates":[30.949963,49.273171],"type":"Point"}
}