{
  "type": "Feature",
  "properties": {
    "gn:admin1_code":"21.0",
    "gn:asciiname":"Pshinchyne",
    "gn:country_code":"UA",
    "gn:dem":180,
    "gn:feature_class":"P",
    "gn:feature_code":"PPL",
    "gn:name":"Pshinchyne",
    "gn:population":0,
    "gn:timezone":"Europe/Kiev",
    "iso:country":"UA",
    "name:ukr_x_preferred":[
        "Pshinchyne"
    ],
    "name:ukr_x_variant":[
        "\u041f\u0448\u0456\u043d\u0447\u0438\u043d\u0435"
    ],
    "name:und_x_variant":[
        "Pshonchino"
    ],
    "wof:name":"Pshinchyne",
    "wof:placetype":"locality"
},
  "geometry": {"coordinates":[33.57631,50.82441],"type":"Point"}
}