{
  "type": "Feature",
  "properties": {
    "gn:admin1_code":"15.0",
    "gn:asciiname":"Boldury",
    "gn:country_code":"UA",
    "gn:dem":203,
    "gn:feature_class":"P",
    "gn:feature_code":"PPL",
    "gn:name":"Boldury",
    "gn:population":0,
    "gn:timezone":"Europe/Kiev",
    "iso:country":"UA",
    "name:ceb_x_preferred":[
        "Boldury"
    ],
    "name:pol_x_preferred":[
        "Bo\u0142dury"
    ],
    "name:ron_x_preferred":[
        "Bovdur\u00ee"
    ],
    "name:rus_x_preferred":[
        "\u0411\u043e\u043b\u0434\u0443\u0440\u044b"
    ],
    "name:ukr_x_preferred":[
        "\u0411\u043e\u0432\u0434\u0443\u0440\u0438"
    ],
    "name:zho_x_preferred":[
        "\u535a\u592b\u675c\u91cc"
    ],
    "wof:name":"Boldury",
    "wof:placetype":"locality"
},
  "geometry": {"coordinates":[25.07487,50.18145],"type":"Point"}
}