{
  "type": "Feature",
  "properties": {
    "gn:admin1_code":"18.0",
    "gn:asciiname":"Shcherbukhy",
    "gn:country_code":"UA",
    "gn:dem":97,
    "gn:feature_class":"P",
    "gn:feature_code":"PPL",
    "gn:name":"Shcherbukhy",
    "gn:population":0,
    "gn:timezone":"Europe/Kiev",
    "iso:country":"UA",
    "name:ukr_x_preferred":[
        "Shcherbukhy"
    ],
    "name:ukr_x_variant":[
        "\u0429\u0435\u0440\u0431\u0443\u0445\u0438"
    ],
    "wof:name":"Shcherbukhy",
    "wof:placetype":"locality"
},
  "geometry": {"coordinates":[33.5115,49.30788],"type":"Point"}
}