{
  "type": "Feature",
  "properties": {
    "gn:admin1_code":"14.0",
    "gn:asciiname":"Okhyno",
    "gn:country_code":"UA",
    "gn:dem":144,
    "gn:feature_class":"P",
    "gn:feature_code":"PPL",
    "gn:name":"Okhyno",
    "gn:population":0,
    "gn:timezone":"Europe/Zaporozhye",
    "iso:country":"UA",
    "name:ukr_x_preferred":[
        "Okhyno"
    ],
    "name:ukr_x_variant":[
        "\u041e\u0445\u043d\u0438\u043d\u043e"
    ],
    "name:und_x_variant":[
        "Oknino"
    ],
    "wof:name":"Okhyno",
    "wof:placetype":"locality"
},
  "geometry": {"coordinates":[38.86939,48.93172],"type":"Point"}
}