{
  "type": "Feature",
  "properties": {
    "gn:admin1_code":"18.0",
    "gn:asciiname":"Osove",
    "gn:country_code":"UA",
    "gn:dem":143,
    "gn:feature_class":"P",
    "gn:feature_code":"PPL",
    "gn:name":"Osove",
    "gn:population":0,
    "gn:timezone":"Europe/Kiev",
    "iso:country":"UA",
    "name:ukr_x_preferred":[
        "Osove"
    ],
    "name:ukr_x_variant":[
        "\u041e\u0441\u043e\u0432\u0435"
    ],
    "wof:name":"Osove",
    "wof:placetype":"locality"
},
  "geometry": {"coordinates":[33.39475,49.91907],"type":"Point"}
}