{
  "type": "Feature",
  "properties": {
    "gn:admin1_code":"27.0",
    "gn:asciiname":"Hardyshivka",
    "gn:country_code":"UA",
    "gn:dem":267,
    "gn:feature_class":"P",
    "gn:feature_code":"PPL",
    "gn:name":"Hardyshivka",
    "gn:population":0,
    "gn:timezone":"Europe/Kiev",
    "iso:country":"UA",
    "name:ukr_x_preferred":[
        "Hardyshivka"
    ],
    "name:ukr_x_variant":[
        "\u0413\u0430\u0440\u0434\u0456\u0448\u0456\u0432\u043a\u0430"
    ],
    "name:und_x_variant":[
        "Gardysh\u00ebvka"
    ],
    "wof:name":"Hardyshivka",
    "wof:placetype":"locality"
},
  "geometry": {"coordinates":[28.43416,49.90835],"type":"Point"}
}