{
  "type": "Feature",
  "properties": {
    "gn:admin1_code":"1.0",
    "gn:asciiname":"Bogdany",
    "gn:country_code":"UA",
    "gn:dem":102,
    "gn:feature_class":"P",
    "gn:feature_code":"PPL",
    "gn:name":"Bogdany",
    "gn:population":0,
    "gn:timezone":"Europe/Kiev",
    "iso:country":"UA",
    "wof:name":"Bogdany",
    "wof:placetype":"locality"
},
  "geometry": {"coordinates":[31.87567,49.93057],"type":"Point"}
}