{
  "type": "Feature",
  "properties": {
    "gn:admin1_code":"23.0",
    "gn:asciiname":"Mervin",
    "gn:country_code":"UA",
    "gn:dem":257,
    "gn:feature_class":"P",
    "gn:feature_code":"PPL",
    "gn:name":"Mervin",
    "gn:population":0,
    "gn:timezone":"Europe/Kiev",
    "iso:country":"UA",
    "name:rus_x_preferred":[
        "\u041c\u0435\u0440\u0432\u0438\u043d"
    ],
    "wof:name":"Mervin",
    "wof:placetype":"locality"
},
  "geometry": {"coordinates":[29.35642,49.19326],"type":"Point"}
}