{
  "type": "Feature",
  "properties": {
    "gn:admin1_code":"9.0",
    "gn:asciiname":"Rylivka",
    "gn:country_code":"UA",
    "gn:dem":234,
    "gn:feature_class":"P",
    "gn:feature_code":"PPL",
    "gn:name":"Rylivka",
    "gn:population":0,
    "gn:timezone":"Europe/Kiev",
    "iso:country":"UA",
    "name:ukr_x_preferred":[
        "Rylivka"
    ],
    "name:ukr_x_variant":[
        "\u0420\u0438\u043b\u0456\u0432\u043a\u0430"
    ],
    "name:und_x_variant":[
        "Rylovka"
    ],
    "wof:name":"Rylivka",
    "wof:placetype":"locality"
},
  "geometry": {"coordinates":[27.2861,50.36171],"type":"Point"}
}