{
  "type": "Feature",
  "properties": {
    "gn:admin1_code":"5.0",
    "gn:asciiname":"Novobakhmutovka",
    "gn:country_code":"UA",
    "gn:dem":144,
    "gn:feature_class":"P",
    "gn:feature_code":"PPL",
    "gn:name":"Novobakhmutovka",
    "gn:population":0,
    "gn:timezone":"Europe/Kiev",
    "iso:country":"UA",
    "wof:name":"Novobakhmutovka",
    "wof:placetype":"locality"
},
  "geometry": {"coordinates":[37.78541,48.24894000000001],"type":"Point"}
}