{
  "type": "Feature",
  "properties": {
    "gn:admin1_code":"17.0",
    "gn:asciiname":"Balanyny",
    "gn:country_code":"UA",
    "gn:dem":96,
    "gn:feature_class":"P",
    "gn:feature_code":"PPL",
    "gn:name":"Balanyny",
    "gn:population":0,
    "gn:timezone":"Europe/Kiev",
    "iso:country":"UA",
    "name:ukr_x_preferred":[
        "Balanyny"
    ],
    "name:ukr_x_variant":[
        "\u0411\u0430\u043b\u0430\u043d\u0438\u043d\u0438"
    ],
    "name:und_x_variant":[
        "Balanino",
        "Balaniny"
    ],
    "wof:name":"Balanyny",
    "wof:placetype":"locality"
},
  "geometry": {"coordinates":[30.6051,46.97337],"type":"Point"}
}