{
  "type": "Feature",
  "properties": {
    "gn:admin1_code":"17.0",
    "gn:asciiname":"Kachurivka",
    "gn:country_code":"UA",
    "gn:dem":128,
    "gn:feature_class":"P",
    "gn:feature_code":"PPL",
    "gn:name":"Kachurivka",
    "gn:population":0,
    "gn:timezone":"Europe/Kiev",
    "iso:country":"UA",
    "name:ukr_x_preferred":[
        "Kachurivka"
    ],
    "name:ukr_x_variant":[
        "\u041a\u0430\u0447\u0443\u0440\u0456\u0432\u043a\u0430"
    ],
    "name:und_x_variant":[
        "Kochurovka",
        "Kachurovka"
    ],
    "wof:name":"Kachurivka",
    "wof:placetype":"locality"
},
  "geometry": {"coordinates":[29.78051,47.6307],"type":"Point"}
}