{
  "type": "Feature",
  "properties": {
    "iso:country":"UA",
    "name:ukr_x_preferred":[
        "Lyshche"
    ],
    "name:ukr_x_variant":[
        "\u041b\u0438\u0449\u0435"
    ],
    "qs:a0":"\u0423\u043a\u0440\u0430\u0457\u043d\u0430",
    "qs:a1":"*\u0412\u043e\u043b\u0438\u043d\u0441\u044c\u043a\u0430",
    "qs:a1_alt":"Volyns'ka",
    "qs:a1r":"0",
    "qs:a2":"\u041b\u0443\u0446\u044c\u043a\u0438\u0439",
    "qs:a2_alt":"Luts'kyi",
    "qs:adm0":"\u0423\u043a\u0440\u0430\u0457\u043d\u0430",
    "qs:la_lc":"*",
    "qs:level":"locality",
    "qs:loc":"\u041b\u0438\u0449\u0435",
    "qs:loc_alt":"Lysche",
    "qs:pop":0,
    "qs:type":"buffered point",
    "wof:name":"\u041b\u0438\u0449\u0435",
    "wof:placetype":"locality"
},
  "geometry": {"coordinates":[25.446974,50.707976],"type":"Point"}
}