{
  "type": "Feature",
  "properties": {
    "gn:admin1_code":"9.0",
    "gn:asciiname":"Lozny",
    "gn:country_code":"UA",
    "gn:dem":313,
    "gn:feature_class":"P",
    "gn:feature_code":"PPL",
    "gn:name":"Lozny",
    "gn:population":0,
    "gn:timezone":"Europe/Kiev",
    "iso:country":"UA",
    "wof:name":"Lozny",
    "wof:placetype":"locality"
},
  "geometry": {"coordinates":[27.82146,49.31359000000001],"type":"Point"}
}