{
  "type": "Feature",
  "properties": {
    "gn:admin1_code":"9.0",
    "gn:asciiname":"Nagoryane",
    "gn:country_code":"UA",
    "gn:dem":261,
    "gn:feature_class":"P",
    "gn:feature_code":"PPL",
    "gn:name":"Nagoryane",
    "gn:population":0,
    "gn:timezone":"Europe/Kiev",
    "iso:country":"UA",
    "name:und_x_variant":[
        "Nagoryany",
        "Nag\u00f3rzany",
        "Nagoriani",
        "Nagoryane"
    ],
    "wof:name":"Nagoryane",
    "wof:placetype":"locality"
},
  "geometry": {"coordinates":[26.45693,48.63794],"type":"Point"}
}