{
  "type": "Feature",
  "properties": {
    "gn:admin1_code":"24.0",
    "gn:asciiname":"Lychky",
    "gn:country_code":"UA",
    "gn:dem":191,
    "gn:feature_class":"P",
    "gn:feature_code":"PPL",
    "gn:name":"Lychky",
    "gn:population":0,
    "gn:timezone":"Europe/Kiev",
    "iso:country":"UA",
    "name:ukr_x_preferred":[
        "Lychky"
    ],
    "name:ukr_x_variant":[
        "\u041b\u0438\u0447\u043a\u0438"
    ],
    "name:und_x_variant":[
        "Lychki"
    ],
    "wof:name":"Lychky",
    "wof:placetype":"locality"
},
  "geometry": {"coordinates":[25.55984,50.96863],"type":"Point"}
}