{
  "type": "Feature",
  "properties": {
    "gn:admin1_code":"26.0",
    "gn:asciiname":"Peremozhne",
    "gn:country_code":"UA",
    "gn:dem":36,
    "gn:feature_class":"P",
    "gn:feature_code":"PPL",
    "gn:name":"Peremozhne",
    "gn:population":0,
    "gn:timezone":"Europe/Zaporozhye",
    "iso:country":"UA",
    "name:rus_x_preferred":[
        "\u041f\u0435\u0440\u0435\u043c\u043e\u0436\u043d\u043e\u0435"
    ],
    "name:ukr_x_preferred":[
        "\u041f\u0435\u0440\u0435\u043c\u043e\u0436\u043d\u0435"
    ],
    "name:und_x_variant":[
        "Svinolupovka",
        "Peremozhnoye",
        "Peremozhets",
        "Peremozhne"
    ],
    "wof:name":"Peremozhne",
    "wof:placetype":"locality"
},
  "geometry": {"coordinates":[34.78858,46.67766],"type":"Point"}
}