{
  "type": "Feature",
  "properties": {
    "gn:admin1_code":"22.0",
    "gn:asciiname":"Velikiy Glubochek",
    "gn:country_code":"UA",
    "gn:dem":316,
    "gn:feature_class":"P",
    "gn:feature_code":"PPL",
    "gn:name":"Velikiy Glubochek",
    "gn:population":0,
    "gn:timezone":"Europe/Kiev",
    "iso:country":"UA",
    "name:und_x_variant":[
        "Glubochek Velikiy",
        "Velikiy Glubochek"
    ],
    "wof:name":"Velikiy Glubochek",
    "wof:placetype":"locality"
},
  "geometry": {"coordinates":[25.53167,49.61939],"type":"Point"}
}