{
  "type": "Feature",
  "properties": {
    "gn:admin1_code":"19.0",
    "gn:asciiname":"Stavriv",
    "gn:country_code":"UA",
    "gn:dem":184,
    "gn:feature_class":"P",
    "gn:feature_code":"PPL",
    "gn:name":"Stavriv",
    "gn:population":0,
    "gn:timezone":"Europe/Kiev",
    "iso:country":"UA",
    "name:ukr_x_preferred":[
        "Stavriv"
    ],
    "name:ukr_x_variant":[
        "\u0421\u0442\u0430\u0432\u0440\u0456\u0432"
    ],
    "name:und_x_variant":[
        "Stavrov"
    ],
    "wof:name":"Stavriv",
    "wof:placetype":"locality"
},
  "geometry": {"coordinates":[25.35488,50.56132],"type":"Point"}
}