{
  "type": "Feature",
  "properties": {
    "gn:admin1_code":"18.0",
    "gn:asciiname":"Bozhkove",
    "gn:country_code":"UA",
    "gn:dem":121,
    "gn:feature_class":"P",
    "gn:feature_code":"PPL",
    "gn:name":"Bozhkove",
    "gn:population":0,
    "gn:timezone":"Europe/Kiev",
    "iso:country":"UA",
    "name:ukr_x_preferred":[
        "Bozhkove"
    ],
    "name:ukr_x_variant":[
        "\u0411\u043e\u0436\u043a\u043e\u0432\u0435"
    ],
    "wof:name":"Bozhkove",
    "wof:placetype":"locality"
},
  "geometry": {"coordinates":[34.79188,49.65874],"type":"Point"}
}