{
  "type": "Feature",
  "properties": {
    "gn:admin1_code":"11.0",
    "gn:admin2_code":"710690",
    "gn:admin3_code":"11153138.0",
    "gn:asciiname":"Zaytsevo",
    "gn:country_code":"UA",
    "gn:dem":34,
    "gn:elevation":"34.0",
    "gn:feature_class":"P",
    "gn:feature_code":"PPL",
    "gn:name":"Zaytsevo",
    "gn:population":96,
    "gn:timezone":"Europe/Simferopol",
    "iso:country":"UA",
    "name:eng_x_preferred":[
        "Zaytsevo"
    ],
    "name:rus_x_historical":[
        "\u041c\u0443\u0441\u0441\u0430\u043b\u0438\u0301"
    ],
    "name:rus_x_preferred":[
        "\u0417\u0430\u0439\u0446\u0435\u0432\u043e"
    ],
    "name:rus_x_variant":[
        "\u041c\u0443\u0441\u0441\u0430\u043b\u0438\u0301"
    ],
    "name:ukr_x_preferred":[
        "\u0417\u0430\u0439\u0446\u0435\u0432\u0435"
    ],
    "wof:name":"Zaytsevo",
    "wof:placetype":"locality",
    "wof:population":96
},
  "geometry": {"coordinates":[32.88249,45.53953],"type":"Point"}
}