{
  "type": "Feature",
  "properties": {
    "gn:admin1_code":"27.0",
    "gn:asciiname":"Rudnya-Horodets'ka",
    "gn:country_code":"UA",
    "gn:dem":152,
    "gn:feature_class":"P",
    "gn:feature_code":"PPL",
    "gn:name":"Rudnya-Horodets\u2019ka",
    "gn:population":0,
    "gn:timezone":"Europe/Kiev",
    "iso:country":"UA",
    "name:ukr_x_preferred":[
        "Rudnya-Horodets\u2019ka"
    ],
    "name:ukr_x_variant":[
        "\u0420\u0443\u0434\u043d\u044f-\u0413\u043e\u0440\u043e\u0434\u0435\u0446\u044c\u043a\u0430"
    ],
    "name:und_x_variant":[
        "Rudnya-Gorodetskaya"
    ],
    "wof:name":"Rudnya-Horodets'ka",
    "wof:placetype":"locality"
},
  "geometry": {"coordinates":[29.22559,50.37739000000001],"type":"Point"}
}