{
  "type": "Feature",
  "properties": {
    "gn:admin1_code":"6.0",
    "gn:asciiname":"Pidlyvche",
    "gn:country_code":"UA",
    "gn:dem":434,
    "gn:feature_class":"P",
    "gn:feature_code":"PPL",
    "gn:name":"Pidlyvche",
    "gn:population":0,
    "gn:timezone":"Europe/Kiev",
    "iso:country":"UA",
    "name:ukr_x_preferred":[
        "Pidlyvche"
    ],
    "name:ukr_x_variant":[
        "\u041f\u0456\u0434\u043b\u0438\u0432\u0447\u0435"
    ],
    "wof:name":"Pidlyvche",
    "wof:placetype":"locality"
},
  "geometry": {"coordinates":[24.00597,48.98866],"type":"Point"}
}