{
  "type": "Feature",
  "properties": {
    "gn:admin1_code":"18.0",
    "gn:asciiname":"Sulymy",
    "gn:country_code":"UA",
    "gn:dem":153,
    "gn:feature_class":"P",
    "gn:feature_code":"PPL",
    "gn:name":"Sulymy",
    "gn:population":0,
    "gn:timezone":"Europe/Kiev",
    "iso:country":"UA",
    "name:ukr_x_preferred":[
        "Sulymy"
    ],
    "name:ukr_x_variant":[
        "\u0421\u0443\u043b\u0438\u043c\u0438"
    ],
    "name:und_x_variant":[
        "Sulimen",
        "Sulimy",
        "Sulimov"
    ],
    "wof:name":"Sulymy",
    "wof:placetype":"locality"
},
  "geometry": {"coordinates":[34.19173,50.0476],"type":"Point"}
}