{
  "type": "Feature",
  "properties": {
    "gn:admin1_code":"19.0",
    "gn:asciiname":"Soloniv",
    "gn:country_code":"UA",
    "gn:dem":193,
    "gn:feature_class":"P",
    "gn:feature_code":"PPL",
    "gn:name":"Soloniv",
    "gn:population":0,
    "gn:timezone":"Europe/Kiev",
    "iso:country":"UA",
    "name:ukr_x_preferred":[
        "Soloniv"
    ],
    "name:ukr_x_variant":[
        "\u0421\u043e\u043b\u043e\u043d\u0456\u0432"
    ],
    "name:und_x_variant":[
        "Solonev"
    ],
    "wof:name":"Soloniv",
    "wof:placetype":"locality"
},
  "geometry": {"coordinates":[25.16132,50.37003],"type":"Point"}
}