{
  "type": "Feature",
  "properties": {
    "gn:admin1_code":"21.0",
    "gn:asciiname":"Kerdylivshchyna",
    "gn:country_code":"UA",
    "gn:dem":133,
    "gn:feature_class":"P",
    "gn:feature_code":"PPL",
    "gn:name":"Kerdylivshchyna",
    "gn:population":0,
    "gn:timezone":"Europe/Kiev",
    "iso:country":"UA",
    "name:ukr_x_preferred":[
        "Kerdylivshchyna"
    ],
    "name:ukr_x_variant":[
        "\u041a\u0435\u0440\u0434\u0438\u043b\u0456\u0432\u0449\u0438\u043d\u0430"
    ],
    "name:und_x_variant":[
        "Kardelivshchina"
    ],
    "wof:name":"Kerdylivshchyna",
    "wof:placetype":"locality"
},
  "geometry": {"coordinates":[34.68537,50.68207],"type":"Point"}
}