{
  "type": "Feature",
  "properties": {
    "gn:admin1_code":"7.0",
    "gn:asciiname":"Vysoke",
    "gn:country_code":"UA",
    "gn:dem":181,
    "gn:feature_class":"P",
    "gn:feature_code":"PPL",
    "gn:name":"Vysoke",
    "gn:population":0,
    "gn:timezone":"Europe/Kiev",
    "iso:country":"UA",
    "name:rus_x_preferred":[
        "Oktyabr\u2019skiy"
    ],
    "name:ukr_x_preferred":[
        "Vysoke"
    ],
    "name:ukr_x_variant":[
        "\u0412\u0438\u0441\u043e\u043a\u0435"
    ],
    "wof:name":"Vysoke",
    "wof:placetype":"locality"
},
  "geometry": {"coordinates":[36.19833,49.41],"type":"Point"}
}