{
  "type": "Feature",
  "properties": {
    "iso:country":"UA",
    "name:unk_x_variant":[
        "Kal\u2019nytsk"
    ],
    "qs:a0":"\u0423\u043a\u0440\u0430\u0457\u043d\u0430",
    "qs:a1":"*\u0412\u0456\u043d\u043d\u0438\u0446\u044c\u043a\u0430",
    "qs:a1_alt":"Vinnyts'ka",
    "qs:a1r":"0",
    "qs:a2":"\u0406\u043b\u043b\u0456\u043d\u0435\u0446\u044c\u043a\u0438\u0439",
    "qs:a2_alt":"Illinets'kyi",
    "qs:adm0":"\u0423\u043a\u0440\u0430\u0457\u043d\u0430",
    "qs:la_lc":"*",
    "qs:level":"locality",
    "qs:loc":"\u041a\u0430\u043b\u044c\u043d\u0438\u043a",
    "qs:loc_alt":"Kal'nyk",
    "qs:pop":0,
    "qs:type":"buffered point",
    "wd:wordcount":84,
    "wof:name":"\u041a\u0430\u043b\u044c\u043d\u0438\u043a",
    "wof:placetype":"locality"
},
  "geometry": {"coordinates":[29.398231,49.034801],"type":"Point"}
}