{
  "type": "Feature",
  "properties": {
    "gn:admin1_code":"26.0",
    "gn:asciiname":"Radyvonivka",
    "gn:country_code":"UA",
    "gn:dem":30,
    "gn:feature_class":"P",
    "gn:feature_code":"PPL",
    "gn:name":"Radyvonivka",
    "gn:population":0,
    "gn:timezone":"Europe/Zaporozhye",
    "iso:country":"UA",
    "name:ukr_x_preferred":[
        "Radyvonivka"
    ],
    "name:ukr_x_variant":[
        "\u0420\u0430\u0434\u0438\u0432\u043e\u043d\u0456\u0432\u043a\u0430"
    ],
    "name:und_x_variant":[
        "Rodinovka",
        "Rodionovka",
        "Radivonovka"
    ],
    "wof:name":"Radyvonivka",
    "wof:placetype":"locality"
},
  "geometry": {"coordinates":[36.85675,46.98742],"type":"Point"}
}