{
  "type": "Feature",
  "properties": {
    "gn:admin1_code":"15.0",
    "gn:asciiname":"Beloye",
    "gn:country_code":"UA",
    "gn:dem":320,
    "gn:feature_class":"P",
    "gn:feature_code":"PPL",
    "gn:name":"Beloye",
    "gn:population":0,
    "gn:timezone":"Europe/Kiev",
    "iso:country":"UA",
    "name:und_x_variant":[
        "Byala",
        "Bile",
        "Belaya",
        "Beloye"
    ],
    "wof:name":"Beloye",
    "wof:placetype":"locality"
},
  "geometry": {"coordinates":[24.76544,49.6097],"type":"Point"}
}