{
  "type": "Feature",
  "properties": {
    "gn:admin1_code":"27.0",
    "gn:asciiname":"Noryntsi",
    "gn:country_code":"UA",
    "gn:dem":135,
    "gn:feature_class":"P",
    "gn:feature_code":"PPL",
    "gn:name":"Noryntsi",
    "gn:population":0,
    "gn:timezone":"Europe/Kiev",
    "iso:country":"UA",
    "name:ukr_x_preferred":[
        "Noryntsi"
    ],
    "name:ukr_x_variant":[
        "\u041d\u043e\u0440\u0438\u043d\u0446\u0456"
    ],
    "name:und_x_variant":[
        "Norintsy"
    ],
    "wof:name":"Noryntsi",
    "wof:placetype":"locality"
},
  "geometry": {"coordinates":[28.99059,51.27195],"type":"Point"}
}