{
  "type": "Feature",
  "properties": {
    "iso:country":"UA",
    "name:eng_x_preferred":[
        "Nechiporovka"
    ],
    "name:rus_x_preferred":[
        "\u041d\u0438\u0447\u0438\u043f\u043e\u0440\u043e\u0432\u043a\u0430"
    ],
    "name:und_x_variant":[
        "Nichiporovka"
    ],
    "qs:a0":"\u0423\u043a\u0440\u0430\u0457\u043d\u0430",
    "qs:a1":"*\u041a\u0438\u0457\u0432\u0441\u044c\u043a\u0430",
    "qs:a1_alt":"Kyivs'ka",
    "qs:a1r":"0",
    "qs:a2":"\u042f\u0433\u043e\u0442\u0438\u043d\u0441\u044c\u043a\u0438\u0439",
    "qs:a2_alt":"Yahotyns'kyi",
    "qs:adm0":"\u0423\u043a\u0440\u0430\u0457\u043d\u0430",
    "qs:la_lc":"*",
    "qs:level":"locality",
    "qs:loc":"\u041d\u0438\u0447\u0438\u043f\u043e\u0440\u0456\u0432\u043a\u0430",
    "qs:loc_alt":"Nychyporivka",
    "qs:pop":0,
    "qs:type":"buffered point",
    "wof:name":"\u041d\u0438\u0447\u0438\u043f\u043e\u0440\u0456\u0432\u043a\u0430",
    "wof:placetype":"locality"
},
  "geometry": {"coordinates":[31.821552,50.182818],"type":"Point"}
}