{
  "type": "Feature",
  "properties": {
    "gn:admin1_code":"15.0",
    "gn:asciiname":"Grusyatichi",
    "gn:country_code":"UA",
    "gn:dem":280,
    "gn:feature_class":"P",
    "gn:feature_code":"PPL",
    "gn:name":"Grusyatichi",
    "gn:population":0,
    "gn:timezone":"Europe/Kiev",
    "iso:country":"UA",
    "name:und_x_variant":[
        "Grusyatychi",
        "Khrusyatyche",
        "Grusyatichi"
    ],
    "wof:name":"Grusyatichi",
    "wof:placetype":"locality"
},
  "geometry": {"coordinates":[24.38651,49.47951],"type":"Point"}
}