{
  "type": "Feature",
  "properties": {
    "iso:country":"UA",
    "name:und_x_variant":[
        "Dmitruv"
    ],
    "qs:a0":"\u0423\u043a\u0440\u0430\u0457\u043d\u0430",
    "qs:a1":"*\u041b\u044c\u0432\u0456\u0432\u0441\u044c\u043a\u0430",
    "qs:a1_alt":"L'vivs'ka",
    "qs:a1r":"0",
    "qs:a2":"\u0420\u0430\u0434\u0435\u0445\u0456\u0432\u0441\u044c\u043a\u0438\u0439",
    "qs:a2_alt":"Radekhivs'kyi",
    "qs:adm0":"\u0423\u043a\u0440\u0430\u0457\u043d\u0430",
    "qs:la_lc":"*",
    "qs:level":"locality",
    "qs:loc":"\u0414\u043c\u0438\u0442\u0440\u0456\u0432",
    "qs:loc_alt":"Dmytriv",
    "qs:pop":0,
    "qs:type":"buffered point",
    "wof:name":"\u0414\u043c\u0438\u0442\u0440\u0456\u0432",
    "wof:placetype":"locality"
},
  "geometry": {"coordinates":[24.629685,50.206688],"type":"Point"}
}