{
  "type": "Feature",
  "properties": {
    "iso:country":"UA",
    "name:deu_x_preferred":[
        "Pisky"
    ],
    "name:eng_x_preferred":[
        "Peski"
    ],
    "name:eng_x_variant":[
        "Pisky"
    ],
    "name:lav_x_preferred":[
        "Piski"
    ],
    "name:ron_x_preferred":[
        "Pisk\u00ee"
    ],
    "name:rus_x_preferred":[
        "\u041f\u0435\u0441\u043a\u0438"
    ],
    "name:ukr_x_preferred":[
        "Pisky"
    ],
    "name:ukr_x_variant":[
        "\u041f\u0456\u0441\u043a\u0438"
    ],
    "name:unk_x_variant":[
        "Peski"
    ],
    "name:zho_x_preferred":[
        "\u76ae\u65af\u57fa"
    ],
    "qs:a0":"\u0423\u043a\u0440\u0430\u0457\u043d\u0430",
    "qs:a1":"*\u041b\u0443\u0433\u0430\u043d\u0441\u044c\u043a\u0430",
    "qs:a1_alt":"Luhans'ka",
    "qs:a1r":"0",
    "qs:a2":"\u041d\u043e\u0432\u043e\u043f\u0441\u043a\u043e\u0432\u0441\u044c\u043a\u0438\u0439",
    "qs:a2_alt":"Novopskovs'kyi",
    "qs:adm0":"\u0423\u043a\u0440\u0430\u0457\u043d\u0430",
    "qs:la_lc":"*",
    "qs:level":"locality",
    "qs:loc":"\u041f\u0456\u0441\u043a\u0438",
    "qs:loc_alt":"Pisky",
    "qs:pop":0,
    "qs:type":"buffered point",
    "wd:wordcount":524,
    "wof:name":"\u041f\u0456\u0441\u043a\u0438",
    "wof:placetype":"locality"
},
  "geometry": {"coordinates":[38.998636,49.458059],"type":"Point"}
}