{
  "type": "Feature",
  "properties": {
    "gn:admin1_code":"18.0",
    "gn:asciiname":"Slobodo-Petrivka",
    "gn:country_code":"UA",
    "gn:dem":108,
    "gn:feature_class":"P",
    "gn:feature_code":"PPL",
    "gn:name":"Slobodo-Petrivka",
    "gn:population":0,
    "gn:timezone":"Europe/Kiev",
    "iso:country":"UA",
    "name:ukr_x_preferred":[
        "Slobodo-Petrivka"
    ],
    "name:ukr_x_variant":[
        "\u0421\u043b\u043e\u0431\u043e\u0434\u043e-\u041f\u0435\u0442\u0440\u0456\u0432\u043a\u0430"
    ],
    "name:und_x_variant":[
        "Sloboda-Petrovka Pervaya",
        "Slobodo-Petrovka"
    ],
    "wof:name":"Slobodo-Petrivka",
    "wof:placetype":"locality"
},
  "geometry": {"coordinates":[32.38397,50.11745],"type":"Point"}
}