{
  "type": "Feature",
  "properties": {
    "gn:admin1_code":"26.0",
    "gn:asciiname":"Berehove",
    "gn:country_code":"UA",
    "gn:dem":27,
    "gn:feature_class":"P",
    "gn:feature_code":"PPL",
    "gn:name":"Berehove",
    "gn:population":0,
    "gn:timezone":"Europe/Zaporozhye",
    "iso:country":"UA",
    "name:ukr_x_preferred":[
        "Berehove"
    ],
    "name:ukr_x_variant":[
        "\u0411\u0435\u0440\u0435\u0433\u043e\u0432\u0435"
    ],
    "name:und_x_variant":[
        "Beregovoye"
    ],
    "wof:name":"Berehove",
    "wof:placetype":"locality"
},
  "geometry": {"coordinates":[35.51904000000001,47.00292],"type":"Point"}
}