{
  "type": "Feature",
  "properties": {
    "gn:admin1_code":"5.0",
    "gn:asciiname":"Kurlyandskiy",
    "gn:country_code":"UA",
    "gn:dem":73,
    "gn:feature_class":"P",
    "gn:feature_code":"PPL",
    "gn:name":"Kurlyandskiy",
    "gn:population":0,
    "gn:timezone":"Europe/Kiev",
    "iso:country":"UA",
    "wof:name":"Kurlyandskiy",
    "wof:placetype":"locality"
},
  "geometry": {"coordinates":[38.09194,47.28417],"type":"Point"}
}