{
  "type": "Feature",
  "properties": {
    "gn:admin1_code":"25.0",
    "gn:asciiname":"Kid'osh",
    "gn:country_code":"UA",
    "gn:dem":115,
    "gn:feature_class":"P",
    "gn:feature_code":"PPL",
    "gn:name":"Kid\u2019osh",
    "gn:population":0,
    "gn:timezone":"Europe/Uzhgorod",
    "iso:country":"UA",
    "name:ukr_x_preferred":[
        "Kid\u2019osh"
    ],
    "name:ukr_x_variant":[
        "\u041a\u0456\u0434\u044c\u043e\u0448"
    ],
    "name:und_x_variant":[
        "Zmiyevka"
    ],
    "wof:name":"Kid'osh",
    "wof:placetype":"locality"
},
  "geometry": {"coordinates":[22.69699,48.218],"type":"Point"}
}