{
  "type": "Feature",
  "properties": {
    "gn:admin1_code":"4.0",
    "gn:asciiname":"Promin'",
    "gn:country_code":"UA",
    "gn:dem":137,
    "gn:feature_class":"P",
    "gn:feature_code":"PPL",
    "gn:name":"Promin\u2019",
    "gn:population":0,
    "gn:timezone":"Europe/Kiev",
    "iso:country":"UA",
    "name:ukr_x_preferred":[
        "Promin\u2019"
    ],
    "name:ukr_x_variant":[
        "\u041f\u0440\u043e\u043c\u0456\u043d\u044c"
    ],
    "wof:name":"Promin'",
    "wof:placetype":"locality"
},
  "geometry": {"coordinates":[34.86484,48.41745],"type":"Point"}
}