{
  "type": "Feature",
  "properties": {
    "gn:admin1_code":"2.0",
    "gn:asciiname":"Bakhany",
    "gn:country_code":"UA",
    "gn:dem":150,
    "gn:feature_class":"P",
    "gn:feature_code":"PPL",
    "gn:name":"Bakhany",
    "gn:population":0,
    "gn:timezone":"Europe/Kiev",
    "iso:country":"UA",
    "name:ukr_x_preferred":[
        "Bakhany"
    ],
    "name:ukr_x_variant":[
        "\u0411\u0430\u0445\u0430\u043d\u0438"
    ],
    "wof:name":"Bakhany",
    "wof:placetype":"locality"
},
  "geometry": {"coordinates":[30.85376,51.76024],"type":"Point"}
}