{
  "type": "Feature",
  "properties": {
    "gn:admin1_code":"8.0",
    "gn:asciiname":"Novodmytrivka Druha",
    "gn:country_code":"UA",
    "gn:dem":37,
    "gn:feature_class":"P",
    "gn:feature_code":"PPL",
    "gn:name":"Novodmytrivka Druha",
    "gn:population":0,
    "gn:timezone":"Europe/Kiev",
    "iso:country":"UA",
    "name:rus_x_preferred":[
        "\u041d\u043e\u0432\u043e\u0434\u043c\u0438\u0442\u0440\u043e\u0432\u043a\u0430 \u0412\u0442\u043e\u0440\u0430\u044f"
    ],
    "name:ukr_x_preferred":[
        "Novodmytrivka Druha"
    ],
    "name:ukr_x_variant":[
        "\u041d\u043e\u0432\u043e\u0434\u043c\u0438\u0442\u0440\u0456\u0432\u043a\u0430 \u0414\u0440\u0443\u0433\u0430"
    ],
    "name:und_x_variant":[
        "Novodmitrovka Vtoraya"
    ],
    "wof:name":"Novodmytrivka Druha",
    "wof:placetype":"locality"
},
  "geometry": {"coordinates":[34.3191,46.594],"type":"Point"}
}