{
  "type": "Feature",
  "properties": {
    "iso:country":"UA",
    "name:eng_x_preferred":[
        "Kirovskoye"
    ],
    "name:rus_x_preferred":[
        "\u041a\u0438\u0440\u043e\u0432\u0441\u043a\u043e\u0435"
    ],
    "name:ukr_x_preferred":[
        "\u041a\u0456\u0440\u043e\u0432\u0441\u044c\u043a\u0435"
    ],
    "qs:a0":"\u0423\u043a\u0440\u0430\u0457\u043d\u0430",
    "qs:a1":"*\u041a\u0440\u0438\u043c",
    "qs:a1_alt":"Krym",
    "qs:a1r":"0",
    "qs:a2":"\u0427\u043e\u0440\u043d\u043e\u043c\u043e\u0440\u0441\u044c\u043a\u0438\u0439",
    "qs:a2_alt":"Chornomors'kyi",
    "qs:adm0":"\u0423\u043a\u0440\u0430\u0457\u043d\u0430",
    "qs:la_lc":"*",
    "qs:level":"locality",
    "qs:loc":"\u041a\u0456\u0440\u043e\u0432\u0441\u044c\u043a\u0435",
    "qs:loc_alt":"Kirovs'ke",
    "qs:pop":0,
    "qs:type":"buffered point",
    "wd:wordcount":148,
    "wof:lang":[
        "eng"
    ],
    "wof:name":"\u041a\u0456\u0440\u043e\u0432\u0441\u044c\u043a\u0435",
    "wof:placetype":"locality"
},
  "geometry": {"coordinates":[33.075784,45.544217],"type":"Point"}
}