{
  "type": "Feature",
  "properties": {
    "gn:population":1016,
    "iso:country":"UA",
    "name:ceb_x_preferred":[
        "Bystritsa"
    ],
    "name:cym_x_preferred":[
        "Afon Bystrytsia"
    ],
    "name:deu_x_preferred":[
        "Bystryzja"
    ],
    "name:eng_x_preferred":[
        "Bystrytsia River"
    ],
    "name:fas_x_preferred":[
        "\u0631\u0648\u062f\u062e\u0627\u0646\u0647 \u0628\u06cc\u0633\u062a\u0631\u06cc\u062a\u0633\u06cc\u0627"
    ],
    "name:fra_x_preferred":[
        "Bystrytsia"
    ],
    "name:heb_x_preferred":[
        "\u0412\u0456\u043b\u044c\u0445\u0456\u0432\u0446\u0456"
    ],
    "name:nno_x_preferred":[
        "Bystrytsja"
    ],
    "name:pol_x_preferred":[
        "Bystrzyca"
    ],
    "name:rus_x_preferred":[
        "\u0411\u044b\u0441\u0442\u0440\u0438\u0446\u0430"
    ],
    "name:spa_x_preferred":[
        "R\u00edo Bystrytsia"
    ],
    "name:tgk_x_preferred":[
        "\u0411\u0438\u0441\u0442\u0440\u0438\u0442\u0441\u0430"
    ],
    "name:tgk_x_variant":[
        "\u0414\u0430\u0440\u0451\u0438 \u0431\u0438\u0441\u0442\u0440\u0438\u0442\u0441\u0438\u043e"
    ],
    "name:ukr_x_preferred":[
        "\u0411\u0438\u0441\u0442\u0440\u0438\u0446\u044f"
    ],
    "name:unk_x_variant":[
        "Bystritsa"
    ],
    "name:zho_x_preferred":[
        "\u6bd4\u65af\u7279\u91cc\u9f4a\u4e9e\u6cb3"
    ],
    "qs:a0":"\u0423\u043a\u0440\u0430\u0457\u043d\u0430",
    "qs:a1":"*\u0406\u0432\u0430\u043d\u043e-\u0424\u0440\u0430\u043d\u043a\u0456\u0432\u0441\u044c\u043a\u0430",
    "qs:a1_alt":"Ivano-Frankivs'ka",
    "qs:a1r":"0",
    "qs:a2":"\u041d\u0430\u0434\u0432\u0456\u0440\u043d\u044f\u043d\u0441\u044c\u043a\u0438\u0439",
    "qs:a2_alt":"Nadvirnians'kyi",
    "qs:adm0":"\u0423\u043a\u0440\u0430\u0457\u043d\u0430",
    "qs:la_lc":"*",
    "qs:level":"locality",
    "qs:loc":"\u0411\u0438\u0441\u0442\u0440\u0438\u0446\u044f",
    "qs:loc_alt":"Bystrytsia",
    "qs:pop":0,
    "qs:type":"buffered point",
    "wd:wordcount":213,
    "wof:name":"\u0411\u0438\u0441\u0442\u0440\u0438\u0446\u044f",
    "wof:placetype":"locality",
    "wof:population":1016
},
  "geometry": {"coordinates":[24.230061,48.450257],"type":"Point"}
}