{
  "type": "Feature",
  "properties": {
    "gn:admin1_code":"26.0",
    "gn:asciiname":"Dorozhnyanka",
    "gn:country_code":"UA",
    "gn:dem":157,
    "gn:feature_class":"P",
    "gn:feature_code":"PPL",
    "gn:name":"Dorozhnyanka",
    "gn:population":0,
    "gn:timezone":"Europe/Zaporozhye",
    "iso:country":"UA",
    "name:eng_x_preferred":[
        "Dorozhnyanka"
    ],
    "name:rus_x_preferred":[
        "\u0414\u043e\u0440\u043e\u0436\u043d\u044f\u043d\u043a\u0430"
    ],
    "name:ukr_x_preferred":[
        "\u0414\u043e\u0440\u043e\u0436\u043d\u044f\u043d\u043a\u0430"
    ],
    "name:und_x_variant":[
        "Dorozhnyy"
    ],
    "wof:name":"Dorozhnyanka",
    "wof:placetype":"locality"
},
  "geometry": {"coordinates":[36.26109,47.58861],"type":"Point"}
}