{
  "type": "Feature",
  "properties": {
    "gn:admin1_code":"19.0",
    "gn:asciiname":"Pidhay",
    "gn:country_code":"UA",
    "gn:dem":243,
    "gn:feature_class":"P",
    "gn:feature_code":"PPL",
    "gn:name":"Pidhay",
    "gn:population":0,
    "gn:timezone":"Europe/Kiev",
    "iso:country":"UA",
    "name:ukr_x_preferred":[
        "Pidhay"
    ],
    "name:ukr_x_variant":[
        "\u041f\u0456\u0434\u0433\u0430\u0439"
    ],
    "name:und_x_variant":[
        "Podgay"
    ],
    "wof:name":"Pidhay",
    "wof:placetype":"locality"
},
  "geometry": {"coordinates":[25.61685,50.6676],"type":"Point"}
}