{
  "type": "Feature",
  "properties": {
    "gn:admin1_code":"27.0",
    "gn:asciiname":"Khutor Vin'kov",
    "gn:country_code":"UA",
    "gn:dem":195,
    "gn:feature_class":"P",
    "gn:feature_code":"PPL",
    "gn:name":"Khutor Vin\u2019kov",
    "gn:population":0,
    "gn:timezone":"Europe/Kiev",
    "iso:country":"UA",
    "name:und_x_variant":[
        "Vin\u2019kov",
        "Khutor Vin\u2019kov"
    ],
    "wof:name":"Khutor Vin'kov",
    "wof:placetype":"locality"
},
  "geometry": {"coordinates":[28.85,51.38333],"type":"Point"}
}