{
  "type": "Feature",
  "properties": {
    "gn:admin1_code":"10.0",
    "gn:asciiname":"Serebryane",
    "gn:country_code":"UA",
    "gn:dem":124,
    "gn:feature_class":"P",
    "gn:feature_code":"PPL",
    "gn:name":"Serebryane",
    "gn:population":0,
    "gn:timezone":"Europe/Kiev",
    "iso:country":"UA",
    "name:ukr_x_preferred":[
        "Serebryane"
    ],
    "name:ukr_x_variant":[
        "\u0421\u0435\u0440\u0435\u0431\u0440\u044f\u043d\u0435"
    ],
    "name:und_x_variant":[
        "Serebryanaya"
    ],
    "wof:name":"Serebryane",
    "wof:placetype":"locality"
},
  "geometry": {"coordinates":[32.99978,48.87723],"type":"Point"}
}