{
  "type": "Feature",
  "properties": {
    "gn:admin1_code":"2.0",
    "gn:asciiname":"Terebishche",
    "gn:country_code":"UA",
    "gn:dem":162,
    "gn:feature_class":"P",
    "gn:feature_code":"PPL",
    "gn:name":"Terebishche",
    "gn:population":0,
    "gn:timezone":"Europe/Kiev",
    "iso:country":"UA",
    "name:rus_x_preferred":[
        "\u0422\u0435\u0440\u0435\u0431\u0438\u0449\u0435"
    ],
    "wof:name":"Terebishche",
    "wof:placetype":"locality"
},
  "geometry": {"coordinates":[32.35601,51.91605],"type":"Point"}
}