{
  "type": "Feature",
  "properties": {
    "gn:admin1_code":"13.0",
    "gn:asciiname":"Karpylivka",
    "gn:country_code":"UA",
    "gn:dem":118,
    "gn:feature_class":"P",
    "gn:feature_code":"PPL",
    "gn:name":"Karpylivka",
    "gn:population":0,
    "gn:timezone":"Europe/Kiev",
    "iso:country":"UA",
    "name:bel_x_preferred":[
        "\u041a\u0430\u0440\u043f\u044b\u043b\u0456\u045e\u043a\u0430"
    ],
    "name:ron_x_preferred":[
        "Karp\u00eelivka"
    ],
    "name:rus_x_preferred":[
        "\u041a\u0430\u0440\u043f\u0438\u043b\u043e\u0432\u043a\u0430"
    ],
    "name:ukr_x_preferred":[
        "Karpylivka"
    ],
    "name:ukr_x_variant":[
        "\u041a\u0430\u0440\u043f\u0438\u043b\u0456\u0432\u043a\u0430"
    ],
    "name:und_x_variant":[
        "Karpilovka"
    ],
    "name:zho_x_preferred":[
        "\u5361\u723e\u76ae\u5229\u592b\u5361"
    ],
    "wof:name":"Karpylivka",
    "wof:placetype":"locality"
},
  "geometry": {"coordinates":[30.01665,51.12018],"type":"Point"}
}