{
  "type": "Feature",
  "properties": {
    "gn:admin1_code":"5.0",
    "gn:asciiname":"Krasnyy Kut",
    "gn:country_code":"UA",
    "gn:dem":141,
    "gn:feature_class":"P",
    "gn:feature_code":"PPL",
    "gn:name":"Krasnyy Kut",
    "gn:population":0,
    "gn:timezone":"Europe/Kiev",
    "iso:country":"UA",
    "name:und_x_variant":[
        "Krasny Kut",
        "Krasnyy Kut"
    ],
    "wof:name":"Krasnyy Kut",
    "wof:placetype":"locality"
},
  "geometry": {"coordinates":[36.67161,47.93435],"type":"Point"}
}