{
  "type": "Feature",
  "properties": {
    "gn:admin1_code":"27.0",
    "gn:asciiname":"Obykhodivka",
    "gn:country_code":"UA",
    "gn:dem":168,
    "gn:feature_class":"P",
    "gn:feature_code":"PPL",
    "gn:name":"Obykhodivka",
    "gn:population":0,
    "gn:timezone":"Europe/Kiev",
    "iso:country":"UA",
    "name:ukr_x_preferred":[
        "Obykhodivka"
    ],
    "name:ukr_x_variant":[
        "\u041e\u0431\u0438\u0445\u043e\u0434\u0456\u0432\u043a\u0430"
    ],
    "name:und_x_variant":[
        "Obikhodovka"
    ],
    "wof:name":"Obykhodivka",
    "wof:placetype":"locality"
},
  "geometry": {"coordinates":[28.96818,50.99418],"type":"Point"}
}