{
  "type": "Feature",
  "properties": {
    "iso:country":"UA",
    "name:bul_x_preferred":[
        "\u041b\u0430\u0440\u0436\u0430\u043d\u043a\u0430"
    ],
    "name:deu_x_preferred":[
        "Larschanka"
    ],
    "name:eng_x_preferred":[
        "Larzhanka"
    ],
    "name:lav_x_preferred":[
        "Lar\u017eanka"
    ],
    "name:ron_x_preferred":[
        "L\u0103rgeanca"
    ],
    "name:rus_x_preferred":[
        "\u041b\u0430\u0440\u0436\u0430\u043d\u043a\u0430"
    ],
    "name:spa_x_preferred":[
        "Larzhanka"
    ],
    "name:ukr_x_preferred":[
        "Larzhanka"
    ],
    "name:ukr_x_variant":[
        "\u041b\u0430\u0440\u0436\u0430\u043d\u043a\u0430"
    ],
    "name:und_x_variant":[
        "Orshanka"
    ],
    "name:zho_x_preferred":[
        "\u62c9\u723e\u7136\u5361"
    ],
    "qs:a0":"\u0423\u043a\u0440\u0430\u0457\u043d\u0430",
    "qs:a1":"*\u041e\u0434\u0435\u0441\u044c\u043a\u0430",
    "qs:a1_alt":"Odes'ka",
    "qs:a1r":"0",
    "qs:a2":"\u0406\u0437\u043c\u0430\u0457\u043b\u044c\u0441\u044c\u043a\u0438\u0439",
    "qs:a2_alt":"Izmail's'kyi",
    "qs:adm0":"\u0423\u043a\u0440\u0430\u0457\u043d\u0430",
    "qs:la_lc":"*",
    "qs:level":"locality",
    "qs:loc":"\u041b\u0430\u0440\u0436\u0430\u043d\u043a\u0430",
    "qs:loc_alt":"Larzhanka",
    "qs:pop":0,
    "qs:type":"buffered point",
    "wof:name":"\u041b\u0430\u0440\u0436\u0430\u043d\u043a\u0430",
    "wof:placetype":"locality"
},
  "geometry": {"coordinates":[28.716377,45.359341],"type":"Point"}
}