{
  "type": "Feature",
  "properties": {
    "gn:admin1_code":"7.0",
    "gn:asciiname":"Huzhvyns'ke",
    "gn:country_code":"UA",
    "gn:dem":144,
    "gn:feature_class":"P",
    "gn:feature_code":"PPL",
    "gn:name":"Huzhvyns\u2019ke",
    "gn:population":0,
    "gn:timezone":"Europe/Kiev",
    "iso:country":"UA",
    "name:ukr_x_preferred":[
        "Huzhvyns\u2019ke"
    ],
    "name:ukr_x_variant":[
        "\u0425\u0443\u0436\u0432\u0438\u043d\u0441\u044c\u043a\u0435"
    ],
    "wof:name":"Huzhvyns'ke",
    "wof:placetype":"locality"
},
  "geometry": {"coordinates":[36.03486,49.73459],"type":"Point"}
}