{
  "type": "Feature",
  "properties": {
    "gn:population":5242,
    "iso:country":"UA",
    "name:ara_x_preferred":[
        "\u0628\u0631\u0648\u0633\u064a\u0644\u064a\u0641"
    ],
    "name:bel_x_variant":[
        "\u0411\u0440\u0443\u0441\u0456\u043b\u0430\u045e"
    ],
    "name:crh_x_preferred":[
        "Brus\u0131liv"
    ],
    "name:deu_x_preferred":[
        "Brussyliw"
    ],
    "name:eng_x_preferred":[
        "Brusyliv"
    ],
    "name:fra_x_preferred":[
        "Broussyliv"
    ],
    "name:nld_x_preferred":[
        "Brusyliv"
    ],
    "name:pol_x_preferred":[
        "Brusi\u0142\u00f3w"
    ],
    "name:ron_x_preferred":[
        "Brus\u00eeliv"
    ],
    "name:rus_x_preferred":[
        "\u0411\u0440\u0443\u0441\u0438\u043b\u043e\u0432"
    ],
    "name:rus_x_variant":[
        "\u0411\u0440\u0443\u0441\u0438\u043b\u0456\u0432"
    ],
    "name:sah_x_preferred":[
        "\u0411\u0440\u0443\u0441\u0438\u043b\u043e\u0432"
    ],
    "name:tat_x_preferred":[
        "\u0411\u0440\u0443\u0441\u044b\u043b\u0438\u0432"
    ],
    "name:ukr_x_preferred":[
        "\u0411\u0440\u0443\u0441\u0438\u043b\u0456\u0432"
    ],
    "name:unk_x_variant":[
        "Brusilov"
    ],
    "name:zho_x_preferred":[
        "\u5e03\u9b6f\u897f\u5229\u592b"
    ],
    "qs:a0":"\u0423\u043a\u0440\u0430\u0457\u043d\u0430",
    "qs:a1":"*\u0416\u0438\u0442\u043e\u043c\u0438\u0440\u0441\u044c\u043a\u0430",
    "qs:a1_alt":"Zhytomyrs'ka",
    "qs:a1r":"0",
    "qs:a2":"\u0411\u0440\u0443\u0441\u0438\u043b\u0456\u0432\u0441\u044c\u043a\u0438\u0439",
    "qs:a2_alt":"Brusylivs'kyi",
    "qs:adm0":"\u0423\u043a\u0440\u0430\u0457\u043d\u0430",
    "qs:la_lc":"*",
    "qs:level":"locality",
    "qs:loc":"\u0411\u0440\u0443\u0441\u0438\u043b\u0456\u0432",
    "qs:loc_alt":"Brusyliv",
    "qs:pop":0,
    "qs:type":"buffered point",
    "wd:wordcount":155,
    "wof:name":"\u0411\u0440\u0443\u0441\u0438\u043b\u0456\u0432",
    "wof:placetype":"locality",
    "wof:population":5242
},
  "geometry": {"coordinates":[29.54313,50.2805],"type":"Point"}
}