{
  "type": "Feature",
  "properties": {
    "gn:gn_country":"UA",
    "gn:gn_fcode":"PPL",
    "gn:gn_pop":3377,
    "gn:population":3377,
    "iso:country":"UA",
    "name:bel_x_preferred":[
        "\u0412\u044f\u0440\u0431\u043e\u045e\u043a\u0430"
    ],
    "name:ceb_x_preferred":[
        "\u0412\u0435\u0440\u0431\u043e\u0432\u043a\u0430"
    ],
    "name:deu_x_preferred":[
        "Werbiwka"
    ],
    "name:est_x_preferred":[
        "Verbivka"
    ],
    "name:hye_x_preferred":[
        "\u054e\u0565\u0580\u0562\u0578\u057e\u056f\u0561"
    ],
    "name:pol_x_preferred":[
        "Werbiwka"
    ],
    "name:rus_x_preferred":[
        "\u0412\u0435\u0440\u0431\u0456\u0432\u043a\u0430"
    ],
    "name:rus_x_variant":[
        "\u0412\u0435\u0440\u0431\u043e\u0432\u043a\u0430"
    ],
    "name:ukr_x_preferred":[
        "\u0412\u0435\u0440\u0431\u0456\u0432\u043a\u0430"
    ],
    "name:unk_x_variant":[
        "Verbovka"
    ],
    "qs_pg:aaroncc":"UA",
    "qs_pg:gn_country":"UA",
    "qs_pg:gn_fcode":"PPL",
    "qs_pg:gn_pop":3377,
    "qs_pg:name":"Verbivka",
    "qs_pg:photos_9r":0,
    "qs_pg:photos_sr":0,
    "qs_pg:pop_sr":4,
    "qs_pg:qs_pg_placetype":"locality",
    "wof:name":"Verbivka",
    "wof:placetype":"locality",
    "wof:population":3377
},
  "geometry": {"coordinates":[35.53333,49.41667],"type":"Point"}
}