{
  "type": "Feature",
  "properties": {
    "gn:admin1_code":"22.0",
    "gn:asciiname":"Urman'",
    "gn:country_code":"UA",
    "gn:dem":309,
    "gn:feature_class":"P",
    "gn:feature_code":"PPL",
    "gn:name":"Urman\u2019",
    "gn:population":0,
    "gn:timezone":"Europe/Kiev",
    "iso:country":"UA",
    "name:und_x_variant":[
        "Urman\u2019"
    ],
    "wof:name":"Urman'",
    "wof:placetype":"locality"
},
  "geometry": {"coordinates":[24.95539,49.56996],"type":"Point"}
}