{
  "type": "Feature",
  "properties": {
    "gn:admin1_code":"8.0",
    "gn:asciiname":"Novyy Hay",
    "gn:country_code":"UA",
    "gn:dem":33,
    "gn:feature_class":"P",
    "gn:feature_code":"PPL",
    "gn:name":"Novyy Hay",
    "gn:population":0,
    "gn:timezone":"Europe/Kiev",
    "iso:country":"UA",
    "name:rus_x_preferred":[
        "\u041d\u043e\u0432\u044b\u0439 \u0413\u0430\u0439"
    ],
    "name:ukr_x_preferred":[
        "\u041d\u043e\u0432\u0438\u0439 \u0413\u0430\u0439"
    ],
    "name:und_x_variant":[
        "Novy Gay",
        "Novyy Gay",
        "Novyy Hay"
    ],
    "wof:name":"Novyy Hay",
    "wof:placetype":"locality"
},
  "geometry": {"coordinates":[33.52064,46.46181],"type":"Point"}
}