{
  "type": "Feature",
  "properties": {
    "gn:country":"UA",
    "gn:fcode":"PPL",
    "gn:population":912,
    "iso:country":"UA",
    "name:crh_x_historical":[
        "Quru \u00d6zen"
    ],
    "name:crh_x_preferred":[
        "Quru \u00d6zen"
    ],
    "name:eng_x_preferred":[
        "Solnechnogorskoye"
    ],
    "name:rus_x_historical":[
        "\u041a\u0443\u0440\u0443\u0301-\u0423\u0437\u0435\u0301\u043d\u044c"
    ],
    "name:rus_x_preferred":[
        "\u0421\u043e\u043b\u043d\u0435\u0447\u043d\u043e\u0433\u043e\u0440\u0441\u043a\u043e\u0435"
    ],
    "name:rus_x_variant":[
        "\u041a\u0443\u0440\u0443\u0301-\u0423\u0437\u0435\u0301\u043d\u044c"
    ],
    "name:ukr_x_preferred":[
        "\u0421\u043e\u043d\u044f\u0447\u043d\u043e\u0433\u0456\u0440\u0441\u044c\u043a\u0435"
    ],
    "qs_pg:aaroncc":"UA",
    "qs_pg:gn_country":"UA",
    "qs_pg:gn_fcode":"PPL",
    "qs_pg:gn_pop":912,
    "qs_pg:name":"Sonyachnohirs\u2019ke",
    "qs_pg:photos_9r":0,
    "qs_pg:photos_sr":0,
    "qs_pg:pop_sr":2,
    "qs_pg:qs_pg_placetype":"locality",
    "wof:name":"Sonyachnohirs\u2019ke",
    "wof:placetype":"locality",
    "wof:population":1150
},
  "geometry": {"coordinates":[34.53999,44.74722],"type":"Point"}
}