{
  "type": "Feature",
  "properties": {
    "gn:admin1_code":"21.0",
    "gn:asciiname":"Plavynyshche",
    "gn:country_code":"UA",
    "gn:dem":116,
    "gn:feature_class":"P",
    "gn:feature_code":"PPL",
    "gn:name":"Plavynyshche",
    "gn:population":0,
    "gn:timezone":"Europe/Kiev",
    "iso:country":"UA",
    "name:ukr_x_preferred":[
        "Plavynyshche"
    ],
    "name:ukr_x_variant":[
        "\u041f\u043b\u0430\u0432\u0438\u043d\u0438\u0449\u0435"
    ],
    "name:und_x_variant":[
        "Plavinishche"
    ],
    "wof:name":"Plavynyshche",
    "wof:placetype":"locality"
},
  "geometry": {"coordinates":[33.53474,50.77311],"type":"Point"}
}