{
  "type": "Feature",
  "properties": {
    "gn:admin1_code":"23.0",
    "gn:asciiname":"Hrynenky",
    "gn:country_code":"UA",
    "gn:dem":276,
    "gn:feature_class":"P",
    "gn:feature_code":"PPL",
    "gn:name":"Hrynenky",
    "gn:population":0,
    "gn:timezone":"Europe/Kiev",
    "iso:country":"UA",
    "name:rus_x_preferred":[
        "Grin\u00ebnki"
    ],
    "name:ukr_x_preferred":[
        "Hrynenky"
    ],
    "name:und_x_variant":[
        "\u0413\u0440\u0438\u043d\u0435\u043d\u043a\u0438"
    ],
    "wof:name":"Hrynenky",
    "wof:placetype":"locality"
},
  "geometry": {"coordinates":[28.9092,48.77363],"type":"Point"}
}