{
  "type": "Feature",
  "properties": {
    "iso:country":"UA",
    "name:bel_x_variant":[
        "\u041b\u044c\u0432\u043e\u045e"
    ],
    "name:ces_x_preferred":[
        "FK Lviv"
    ],
    "name:deu_x_preferred":[
        "FK Lwiw"
    ],
    "name:epo_x_preferred":[
        "Lvivo FK"
    ],
    "name:ita_x_preferred":[
        "Futbol'nyj Klub L'viv"
    ],
    "name:lit_x_preferred":[
        "FK L\u02b9v\u00ecv"
    ],
    "name:nld_x_preferred":[
        "FK Lviv"
    ],
    "name:pol_x_preferred":[
        "FK Lw\u00f3w"
    ],
    "name:por_x_preferred":[
        "FC Lviv"
    ],
    "name:rus_x_preferred":[
        "\u041b\u044c\u0432\u043e\u0432"
    ],
    "name:spa_x_preferred":[
        "FC Lviv"
    ],
    "name:ukr_x_preferred":[
        "\u041b\u044c\u0432\u0456\u0432"
    ],
    "name:zho_x_preferred":[
        "\u5229\u6c83\u592b\u8db3\u7403\u6703"
    ],
    "qs:a0":"\u0423\u043a\u0440\u0430\u0457\u043d\u0430",
    "qs:a1":"*\u0427\u0435\u0440\u043a\u0430\u0441\u044c\u043a\u0430",
    "qs:a1_alt":"Cherkas'ka",
    "qs:a1r":"0",
    "qs:a2":"\u0417\u0432\u0435\u043d\u0438\u0433\u043e\u0440\u043e\u0434\u0441\u044c\u043a\u0438\u0439",
    "qs:a2_alt":"Zvenyhorods'kyi",
    "qs:adm0":"\u0423\u043a\u0440\u0430\u0457\u043d\u0430",
    "qs:la_lc":"*",
    "qs:level":"locality",
    "qs:loc":"\u041a\u043d\u044f\u0436\u0430",
    "qs:loc_alt":"Kniazha",
    "qs:pop":0,
    "qs:type":"buffered point",
    "wd:wordcount":578,
    "wof:name":"\u041a\u043d\u044f\u0436\u0430",
    "wof:placetype":"locality"
},
  "geometry": {"coordinates":[31.217687,49.068063],"type":"Point"}
}