{
  "type": "Feature",
  "properties": {
    "gn:admin1_code":"5.0",
    "gn:asciiname":"Petropavlivka",
    "gn:country_code":"UA",
    "gn:dem":279,
    "gn:feature_class":"P",
    "gn:feature_code":"PPL",
    "gn:name":"Petropavlivka",
    "gn:population":0,
    "gn:timezone":"Europe/Kiev",
    "iso:country":"UA",
    "name:ceb_x_preferred":[
        "Petropavlivka"
    ],
    "name:crh_x_preferred":[
        "Petropavlivka"
    ],
    "name:deu_x_preferred":[
        "Petropawliwka"
    ],
    "name:fra_x_preferred":[
        "Petropavlivka"
    ],
    "name:hye_x_preferred":[
        "\u054a\u0565\u057f\u0580\u0578\u057a\u0561\u057e\u056c\u0578\u057e\u056f\u0561"
    ],
    "name:pol_x_preferred":[
        "Petropawliwka"
    ],
    "name:ron_x_preferred":[
        "Petropavlivka"
    ],
    "name:rus_x_preferred":[
        "\u041f\u0435\u0442\u0440\u043e\u043f\u0430\u0432\u043b\u043e\u0432\u043a\u0430"
    ],
    "name:ukr_x_preferred":[
        "Petropavlivka"
    ],
    "name:ukr_x_variant":[
        "\u041f\u0435\u0442\u0440\u043e\u043f\u0430\u0432\u043b\u0456\u0432\u043a\u0430"
    ],
    "name:und_x_variant":[
        "Petropavlovka"
    ],
    "name:zho_x_preferred":[
        "\u4f69\u7279\u7f85\u62c9\u592b\u5229\u592b\u5361"
    ],
    "wof:name":"Petropavlivka",
    "wof:placetype":"locality"
},
  "geometry": {"coordinates":[38.53353,48.13944],"type":"Point"}
}