{
  "type": "Feature",
  "properties": {
    "gn:admin1_code":"5.0",
    "gn:asciiname":"Petropavlivka",
    "gn:country_code":"UA",
    "gn:dem":279,
    "gn:feature_class":"P",
    "gn:feature_code":"PPL",
    "gn:name":"Petropavlivka",
    "gn:population":0,
    "gn:timezone":"Europe/Kiev",
    "iso:country":"UA",
    "name:ukr_x_preferred":[
        "Petropavlivka"
    ],
    "name:ukr_x_variant":[
        "\u041f\u0435\u0442\u0440\u043e\u043f\u0430\u0432\u043b\u0456\u0432\u043a\u0430"
    ],
    "name:und_x_variant":[
        "Petropavlovka"
    ],
    "wof:name":"Petropavlivka",
    "wof:placetype":"locality"
},
  "geometry": {"coordinates":[38.53353,48.13944],"type":"Point"}
}