{
  "type": "Feature",
  "properties": {
    "iso:country":"UA",
    "name:ukr_x_preferred":[
        "\u041c\u043e\u0457\u0432\u043a\u0430"
    ],
    "name:und_x_variant":[
        "Moyivka"
    ],
    "qs:a0":"\u0423\u043a\u0440\u0430\u0457\u043d\u0430",
    "qs:a1":"*\u0412\u0456\u043d\u043d\u0438\u0446\u044c\u043a\u0430",
    "qs:a1_alt":"Vinnyts'ka",
    "qs:a1r":"0",
    "qs:a2":"\u0427\u0435\u0440\u043d\u0456\u0432\u0435\u0446\u044c\u043a\u0438\u0439",
    "qs:a2_alt":"Chernivets'kyi",
    "qs:adm0":"\u0423\u043a\u0440\u0430\u0457\u043d\u0430",
    "qs:la_lc":"*",
    "qs:level":"locality",
    "qs:loc":"\u041c\u043e\u0457\u0432\u043a\u0430",
    "qs:loc_alt":"Moivka",
    "qs:pop":0,
    "qs:type":"buffered point",
    "wof:name":"\u041c\u043e\u0457\u0432\u043a\u0430",
    "wof:placetype":"locality"
},
  "geometry": {"coordinates":[28.210371,48.462819],"type":"Point"}
}