{
  "type": "Feature",
  "properties": {
    "gn:admin1_code":"24.0",
    "gn:asciiname":"Chemeryn",
    "gn:country_code":"UA",
    "gn:dem":217,
    "gn:feature_class":"P",
    "gn:feature_code":"PPL",
    "gn:name":"Chemeryn",
    "gn:population":0,
    "gn:timezone":"Europe/Kiev",
    "iso:country":"UA",
    "name:ukr_x_preferred":[
        "Chemeryn"
    ],
    "name:ukr_x_variant":[
        "\u0427\u0435\u043c\u0435\u0440\u0438\u043d"
    ],
    "name:und_x_variant":[
        "Chemerin"
    ],
    "wof:name":"Chemeryn",
    "wof:placetype":"locality"
},
  "geometry": {"coordinates":[25.77791,50.70669],"type":"Point"}
}