{
  "type": "Feature",
  "properties": {
    "gn:admin1_code":"9.0",
    "gn:asciiname":"Yukhimovtsy",
    "gn:country_code":"UA",
    "gn:dem":321,
    "gn:feature_class":"P",
    "gn:feature_code":"PPL",
    "gn:name":"Yukhimovtsy",
    "gn:population":0,
    "gn:timezone":"Europe/Kiev",
    "iso:country":"UA",
    "wof:name":"Yukhimovtsy",
    "wof:placetype":"locality"
},
  "geometry": {"coordinates":[26.63055,49.50613],"type":"Point"}
}