{
  "type": "Feature",
  "properties": {
    "gn:admin1_code":"15.0",
    "gn:asciiname":"Zavodskoye",
    "gn:country_code":"UA",
    "gn:dem":235,
    "gn:feature_class":"P",
    "gn:feature_code":"PPL",
    "gn:name":"Zavodskoye",
    "gn:population":0,
    "gn:timezone":"Europe/Kiev",
    "iso:country":"UA",
    "name:und_x_variant":[
        "Varkholy",
        "Zavodskoye"
    ],
    "wof:name":"Zavodskoye",
    "wof:placetype":"locality"
},
  "geometry": {"coordinates":[24.68165,50.05749],"type":"Point"}
}