{
  "type": "Feature",
  "properties": {
    "gn:admin1_code":"10",
    "gn:asciiname":"Rozsokhuvatets",
    "gn:country_code":"UA",
    "gn:dem":148,
    "gn:feature_class":"P",
    "gn:feature_code":"PPL",
    "gn:name":"Rozsokhuvatets",
    "gn:population":0,
    "gn:timezone":"Europe/Kiev",
    "iso:country":"UA",
    "name:pol_x_preferred":[
        "Rosochowatec"
    ],
    "name:rus_x_preferred":[
        "\u0420\u0430\u0441\u0441\u043e\u0445\u043e\u0432\u0430\u0442\u0435\u0446"
    ],
    "name:ukr_x_preferred":[
        "\u0420\u043e\u0437\u0441\u043e\u0445\u0443\u0432\u0430\u0442\u0435\u0446\u044c"
    ],
    "name:und_x_variant":[
        "Rassokhovatets"
    ],
    "wof:name":"Rozsokhuvatets",
    "wof:placetype":"locality"
},
  "geometry": {"coordinates":[30.69031,48.52684],"type":"Point"}
}