{
  "type": "Feature",
  "properties": {
    "gn:admin1_code":"18.0",
    "gn:asciiname":"Balyuky",
    "gn:country_code":"UA",
    "gn:dem":103,
    "gn:feature_class":"P",
    "gn:feature_code":"PPL",
    "gn:name":"Balyuky",
    "gn:population":0,
    "gn:timezone":"Europe/Kiev",
    "iso:country":"UA",
    "name:ukr_x_preferred":[
        "Balyuky"
    ],
    "name:ukr_x_variant":[
        "\u0411\u0430\u043b\u044e\u043a\u0438"
    ],
    "wof:name":"Balyuky",
    "wof:placetype":"locality"
},
  "geometry": {"coordinates":[33.61773,49.73289000000001],"type":"Point"}
}