{
  "type": "Feature",
  "properties": {
    "gn:admin1_code":"16.0",
    "gn:asciiname":"Novoselovka",
    "gn:country_code":"UA",
    "gn:dem":83,
    "gn:feature_class":"P",
    "gn:feature_code":"PPL",
    "gn:name":"Novos\u00eblovka",
    "gn:population":0,
    "gn:timezone":"Europe/Kiev",
    "iso:country":"UA",
    "wof:name":"Novoselovka",
    "wof:placetype":"locality"
},
  "geometry": {"coordinates":[30.89142,47.63666],"type":"Point"}
}