{
  "type": "Feature",
  "properties": {
    "gn:admin1_code":"4.0",
    "gn:asciiname":"Dniprovs'ke",
    "gn:country_code":"UA",
    "gn:dem":87,
    "gn:feature_class":"P",
    "gn:feature_code":"PPL",
    "gn:name":"Dniprovs\u2019ke",
    "gn:population":0,
    "gn:timezone":"Europe/Kiev",
    "iso:country":"UA",
    "name:ukr_x_preferred":[
        "Dniprovs\u2019ke"
    ],
    "name:ukr_x_variant":[
        "\u0414\u043d\u0456\u043f\u0440\u043e\u0432\u0441\u044c\u043a\u0435"
    ],
    "wof:name":"Dniprovs'ke",
    "wof:placetype":"locality"
},
  "geometry": {"coordinates":[34.81748,48.19455],"type":"Point"}
}