{
  "type": "Feature",
  "properties": {
    "gn:admin1_code":"9.0",
    "gn:asciiname":"Glinki",
    "gn:country_code":"UA",
    "gn:dem":254,
    "gn:feature_class":"P",
    "gn:feature_code":"PPL",
    "gn:name":"Glinki",
    "gn:population":0,
    "gn:timezone":"Europe/Kiev",
    "iso:country":"UA",
    "name:deu_x_preferred":[
        "Glinki"
    ],
    "name:fra_x_preferred":[
        "Glinki"
    ],
    "name:lit_x_preferred":[
        "Glinkai"
    ],
    "name:pol_x_preferred":[
        "Glinki"
    ],
    "name:ukr_x_preferred":[
        "\u0490\u043b\u0456\u043d\u043a\u0456"
    ],
    "wof:name":"Glinki",
    "wof:placetype":"locality"
},
  "geometry": {"coordinates":[27.45,50.23333],"type":"Point"}
}