{
  "type": "Feature",
  "properties": {
    "gn:admin1_code":"22.0",
    "gn:asciiname":"Bonovka",
    "gn:country_code":"UA",
    "gn:dem":365,
    "gn:feature_class":"P",
    "gn:feature_code":"PPL",
    "gn:name":"Bonovka",
    "gn:population":0,
    "gn:timezone":"Europe/Kiev",
    "iso:country":"UA",
    "wof:name":"Bonovka",
    "wof:placetype":"locality"
},
  "geometry": {"coordinates":[25.76255,50.08629000000001],"type":"Point"}
}