{
  "type": "Feature",
  "properties": {
    "gn:admin1_code":"21.0",
    "gn:asciiname":"Khomyntsi",
    "gn:country_code":"UA",
    "gn:dem":123,
    "gn:feature_class":"P",
    "gn:feature_code":"PPL",
    "gn:name":"Khomyntsi",
    "gn:population":0,
    "gn:timezone":"Europe/Kiev",
    "iso:country":"UA",
    "name:ukr_x_preferred":[
        "Khomyntsi"
    ],
    "name:ukr_x_variant":[
        "\u0425\u043e\u043c\u0438\u043d\u0446\u0456"
    ],
    "name:und_x_variant":[
        "Fomintsy",
        "Khomintsy"
    ],
    "wof:name":"Khomyntsi",
    "wof:placetype":"locality"
},
  "geometry": {"coordinates":[33.2271,50.64032],"type":"Point"}
}