{
  "type": "Feature",
  "properties": {
    "gn:admin1_code":"5.0",
    "gn:asciiname":"Staryy Karavan",
    "gn:country_code":"UA",
    "gn:dem":72,
    "gn:feature_class":"P",
    "gn:feature_code":"PPL",
    "gn:name":"Staryy Karavan",
    "gn:population":0,
    "gn:timezone":"Europe/Kiev",
    "iso:country":"UA",
    "name:ukr_x_preferred":[
        "Staryy Karavan"
    ],
    "name:ukr_x_variant":[
        "\u0421\u0442\u0430\u0440\u0438\u0439 \u041a\u0430\u0440\u0430\u0432\u0430\u043d"
    ],
    "wof:name":"Staryy Karavan",
    "wof:placetype":"locality"
},
  "geometry": {"coordinates":[37.78296,48.92012],"type":"Point"}
}