{
  "type": "Feature",
  "properties": {
    "gn:admin1_code":"18.0",
    "gn:asciiname":"Dandasivka",
    "gn:country_code":"UA",
    "gn:dem":159,
    "gn:feature_class":"P",
    "gn:feature_code":"PPL",
    "gn:name":"Dandasivka",
    "gn:population":0,
    "gn:timezone":"Europe/Kiev",
    "iso:country":"UA",
    "name:ukr_x_preferred":[
        "Dandasivka"
    ],
    "name:ukr_x_variant":[
        "\u0414\u0430\u043d\u0434\u0430\u0441\u0456\u0432\u043a\u0430"
    ],
    "name:und_x_variant":[
        "Khutor Dandasovka",
        "Dandasovka"
    ],
    "wof:name":"Dandasivka",
    "wof:placetype":"locality"
},
  "geometry": {"coordinates":[35.45321,49.57862],"type":"Point"}
}