{
  "type": "Feature",
  "properties": {
    "iso:country":"UA",
    "name:rus_x_preferred":[
        "\u041b\u044e\u0431\u0438\u043d\u0446\u044b"
    ],
    "name:ukr_x_preferred":[
        "\u041b\u044e\u0431\u0438\u043d\u0446\u0456"
    ],
    "name:unk_x_variant":[
        "Lyubyntsi"
    ],
    "qs:a0":"\u0423\u043a\u0440\u0430\u0457\u043d\u0430",
    "qs:a1":"*\u041b\u044c\u0432\u0456\u0432\u0441\u044c\u043a\u0430",
    "qs:a1_alt":"L'vivs'ka",
    "qs:a1r":"0",
    "qs:a2":"\u0421\u0442\u0440\u0438\u0439\u0441\u044c\u043a\u0438\u0439",
    "qs:a2_alt":"Stryis'kyi",
    "qs:adm0":"\u0423\u043a\u0440\u0430\u0457\u043d\u0430",
    "qs:la_lc":"*",
    "qs:level":"locality",
    "qs:loc":"\u041b\u044e\u0431\u0438\u043d\u0446\u0456",
    "qs:loc_alt":"Liubyntsi",
    "qs:pop":0,
    "qs:type":"buffered point",
    "wof:name":"\u041b\u044e\u0431\u0438\u043d\u0446\u0456",
    "wof:placetype":"locality"
},
  "geometry": {"coordinates":[23.693539,49.142924],"type":"Point"}
}