{
  "type": "Feature",
  "properties": {
    "gn:admin1_code":"27.0",
    "gn:asciiname":"Mar'yanovka",
    "gn:country_code":"UA",
    "gn:dem":269,
    "gn:feature_class":"P",
    "gn:feature_code":"PPL",
    "gn:name":"Mar\u2019yanovka",
    "gn:population":0,
    "gn:timezone":"Europe/Kiev",
    "iso:country":"UA",
    "wof:name":"Mar'yanovka",
    "wof:placetype":"locality"
},
  "geometry": {"coordinates":[29.06577,49.65483],"type":"Point"}
}