{
  "type": "Feature",
  "properties": {
    "iso:country":"UA",
    "name:deu_x_preferred":[
        "Staryj Jarytschiw"
    ],
    "name:eng_x_preferred":[
        "Staryiy Yarychiv"
    ],
    "name:pol_x_preferred":[
        "Jarycz\u00f3w Stary"
    ],
    "name:ron_x_preferred":[
        "Star\u00eei Iar\u00eeciv"
    ],
    "name:rus_x_preferred":[
        "\u0421\u0442\u0430\u0440\u044b\u0439 \u042f\u0440\u044b\u0447\u0435\u0432"
    ],
    "name:ukr_x_preferred":[
        "\u0421\u0442\u0430\u0440\u0438\u0439 \u042f\u0440\u0438\u0447\u0456\u0432"
    ],
    "name:unk_x_variant":[
        "Staryy Yarychiv"
    ],
    "name:zho_x_preferred":[
        "\u820a\u4e9e\u91cc\u5947\u592b"
    ],
    "qs:a0":"\u0423\u043a\u0440\u0430\u0457\u043d\u0430",
    "qs:a1":"*\u041b\u044c\u0432\u0456\u0432\u0441\u044c\u043a\u0430",
    "qs:a1_alt":"L'vivs'ka",
    "qs:a1r":"0",
    "qs:a2":"\u041a\u0430\u043c'\u044f\u043d\u043a\u0430-\u0411\u0443\u0437\u044c\u043a\u0438\u0439",
    "qs:a2_alt":"Kamyanka-Buz'kyi",
    "qs:adm0":"\u0423\u043a\u0440\u0430\u0457\u043d\u0430",
    "qs:la_lc":"*",
    "qs:level":"locality",
    "qs:loc":"\u0421\u0442\u0430\u0440\u0438\u0439 \u042f\u0440\u0438\u0447\u0456\u0432",
    "qs:loc_alt":"Staryi Yarychiv",
    "qs:pop":0,
    "qs:type":"buffered point",
    "wd:wordcount":63,
    "wof:name":"\u0421\u0442\u0430\u0440\u0438\u0439 \u042f\u0440\u0438\u0447\u0456\u0432",
    "wof:placetype":"locality"
},
  "geometry": {"coordinates":[24.269604,49.913118],"type":"Point"}
}