{
  "type": "Feature",
  "properties": {
    "iso:country":"UA",
    "name:bel_x_preferred":[
        "\u041a\u0440\u044b\u043c\u043d\u044d"
    ],
    "name:che_x_preferred":[
        "\u041a\u0440\u044b\u043c\u043d\u043e"
    ],
    "name:deu_x_preferred":[
        "Krymne"
    ],
    "name:eng_x_preferred":[
        "Krimne"
    ],
    "name:eng_x_variant":[
        "Krymne"
    ],
    "name:fin_x_preferred":[
        "Krymn\u0435"
    ],
    "name:heb_x_preferred":[
        "\u05e7\u05e8\u05d9\u05de\u05e0\u05d5"
    ],
    "name:hye_x_preferred":[
        "\u053f\u0580\u056b\u0574\u0576\u0578"
    ],
    "name:lav_x_preferred":[
        "Krimne"
    ],
    "name:nan_x_preferred":[
        "Krymne"
    ],
    "name:nno_x_preferred":[
        "Krymne"
    ],
    "name:nob_x_preferred":[
        "Krymne"
    ],
    "name:pol_x_preferred":[
        "Krymno"
    ],
    "name:ron_x_preferred":[
        "Kr\u00eemne"
    ],
    "name:rus_x_preferred":[
        "\u041a\u0440\u044b\u043c\u043d\u043e"
    ],
    "name:ukr_x_preferred":[
        "Krymne"
    ],
    "name:ukr_x_variant":[
        "\u041a\u0440\u0438\u043c\u043d\u0435"
    ],
    "name:zho_x_preferred":[
        "\u514b\u91cc\u59c6\u6d85"
    ],
    "qs:a0":"\u0423\u043a\u0440\u0430\u0457\u043d\u0430",
    "qs:a1":"*\u0412\u043e\u043b\u0438\u043d\u0441\u044c\u043a\u0430",
    "qs:a1_alt":"Volyns'ka",
    "qs:a1r":"0",
    "qs:a2":"\u0421\u0442\u0430\u0440\u043e\u0432\u0438\u0436\u0456\u0432\u0441\u044c\u043a\u0438\u0439",
    "qs:a2_alt":"Starovyzhivs'kyi",
    "qs:adm0":"\u0423\u043a\u0440\u0430\u0457\u043d\u0430",
    "qs:la_lc":"*",
    "qs:level":"locality",
    "qs:loc":"\u041a\u0440\u0438\u043c\u043d\u0435",
    "qs:loc_alt":"Krymne",
    "qs:pop":0,
    "qs:type":"buffered point",
    "wof:name":"\u041a\u0440\u0438\u043c\u043d\u0435",
    "wof:placetype":"locality"
},
  "geometry": {"coordinates":[24.292383,51.505655],"type":"Point"}
}