{
  "type": "Feature",
  "properties": {
    "gn:admin1_code":"2.0",
    "gn:asciiname":"Chervonyy Pakhar",
    "gn:country_code":"UA",
    "gn:dem":128,
    "gn:feature_class":"P",
    "gn:feature_code":"PPL",
    "gn:name":"Chervonyy Pakhar",
    "gn:population":0,
    "gn:timezone":"Europe/Kiev",
    "iso:country":"UA",
    "name:rus_x_preferred":[
        "Chervonyy Pakhar\u2019"
    ],
    "name:ukr_x_preferred":[
        "Chervonyy Pakhar"
    ],
    "name:ukr_x_variant":[
        "\u0427\u0435\u0440\u0432\u043e\u043d\u0438\u0439 \u041f\u0430\u0445\u0430\u0440"
    ],
    "wof:name":"Chervonyy Pakhar",
    "wof:placetype":"locality"
},
  "geometry": {"coordinates":[31.95163,50.76535],"type":"Point"}
}