{
  "type": "Feature",
  "properties": {
    "gn:admin1_code":"27.0",
    "gn:asciiname":"Malyy Dyvlyn",
    "gn:country_code":"UA",
    "gn:dem":194,
    "gn:feature_class":"P",
    "gn:feature_code":"PPL",
    "gn:name":"Malyy Dyvlyn",
    "gn:population":0,
    "gn:timezone":"Europe/Kiev",
    "iso:country":"UA",
    "name:ukr_x_preferred":[
        "Malyy Dyvlyn"
    ],
    "name:ukr_x_variant":[
        "\u041c\u0430\u043b\u0438\u0439 \u0414\u0438\u0432\u043b\u0438\u043d"
    ],
    "name:und_x_variant":[
        "Maly Divlin",
        "Malyy Divlin"
    ],
    "wof:name":"Malyy Dyvlyn",
    "wof:placetype":"locality"
},
  "geometry": {"coordinates":[28.11781,51.09831],"type":"Point"}
}