{
  "type": "Feature",
  "properties": {
    "gn:admin1_code":"10.0",
    "gn:asciiname":"Novo-Gomel'skiy",
    "gn:country_code":"UA",
    "gn:dem":120,
    "gn:feature_class":"P",
    "gn:feature_code":"PPL",
    "gn:name":"Novo-Gomel\u2019skiy",
    "gn:population":0,
    "gn:timezone":"Europe/Kiev",
    "iso:country":"UA",
    "wof:name":"Novo-Gomel'skiy",
    "wof:placetype":"locality"
},
  "geometry": {"coordinates":[32.2738,47.93026],"type":"Point"}
}