{
  "type": "Feature",
  "properties": {
    "gn:admin1_code":"2.0",
    "gn:asciiname":"Velykyy Dyrchyn",
    "gn:country_code":"UA",
    "gn:dem":116,
    "gn:feature_class":"P",
    "gn:feature_code":"PPL",
    "gn:name":"Velykyy Dyrchyn",
    "gn:population":0,
    "gn:timezone":"Europe/Kiev",
    "iso:country":"UA",
    "name:ukr_x_preferred":[
        "\u0412\u0435\u043b\u0438\u043a\u0438\u0439 \u0414\u0438\u0440\u0447\u0438\u043d"
    ],
    "name:und_x_variant":[
        "Bol\u2019shoy Dyrchin",
        "Velikiy Dyrchin"
    ],
    "wof:name":"Velykyy Dyrchyn",
    "wof:placetype":"locality"
},
  "geometry": {"coordinates":[31.69433,51.71887],"type":"Point"}
}