{
  "type": "Feature",
  "properties": {
    "gn:admin1_code":"9.0",
    "gn:asciiname":"Lisova Volytsya",
    "gn:country_code":"UA",
    "gn:dem":291,
    "gn:feature_class":"P",
    "gn:feature_code":"PPL",
    "gn:name":"Lisova Volytsya",
    "gn:population":0,
    "gn:timezone":"Europe/Kiev",
    "iso:country":"UA",
    "name:ukr_x_preferred":[
        "Lisova Volytsya"
    ],
    "name:ukr_x_variant":[
        "\u041b\u0456\u0441\u043e\u0432\u0430 \u0412\u043e\u043b\u0438\u0446\u044f"
    ],
    "name:und_x_variant":[
        "Volitsa Tatarskaya"
    ],
    "wof:name":"Lisova Volytsya",
    "wof:placetype":"locality"
},
  "geometry": {"coordinates":[26.95,49.81667],"type":"Point"}
}