{
  "type": "Feature",
  "properties": {
    "gn:admin1_code":"19.0",
    "gn:asciiname":"Richytsya",
    "gn:country_code":"UA",
    "gn:dem":186,
    "gn:feature_class":"P",
    "gn:feature_code":"PPL",
    "gn:name":"Richytsya",
    "gn:population":0,
    "gn:timezone":"Europe/Kiev",
    "iso:country":"UA",
    "name:ukr_x_preferred":[
        "Richytsya"
    ],
    "name:ukr_x_variant":[
        "\u0420\u0456\u0447\u0438\u0446\u044f"
    ],
    "name:und_x_variant":[
        "Rzhechitsa",
        "Rzhechikha",
        "Rechitsa"
    ],
    "wof:name":"Richytsya",
    "wof:placetype":"locality"
},
  "geometry": {"coordinates":[26.51828,50.73291],"type":"Point"}
}