{
  "type": "Feature",
  "properties": {
    "gn:admin1_code":"11.0",
    "gn:admin2_code":"693803",
    "gn:admin3_code":"11152620",
    "gn:asciiname":"Kolodeznoye",
    "gn:country_code":"UA",
    "gn:dem":112,
    "gn:elevation":"114.0",
    "gn:feature_class":"P",
    "gn:feature_code":"PPL",
    "gn:name":"Kolodeznoye",
    "gn:population":505,
    "gn:timezone":"Europe/Simferopol",
    "iso:country":"UA",
    "name:eng_x_preferred":[
        "Kolodeznoye"
    ],
    "name:rus_x_historical":[
        "\u0423\u0447\u043a\u0443\u0301\u0439-\u0422\u0430\u0440\u0445\u0430\u0301\u043d"
    ],
    "name:rus_x_preferred":[
        "\u041a\u043e\u043b\u043e\u0434\u0435\u0437\u043d\u043e\u0435"
    ],
    "name:rus_x_variant":[
        "\u0423\u0447\u043a\u0443\u0301\u0439-\u0422\u0430\u0440\u0445\u0430\u0301\u043d"
    ],
    "name:ukr_x_preferred":[
        "\u041a\u043e\u043b\u043e\u0434\u044f\u0437\u043d\u0435"
    ],
    "wof:name":"Kolodeznoye",
    "wof:placetype":"locality",
    "wof:population":505
},
  "geometry": {"coordinates":[33.83184,45.02221],"type":"Point"}
}