{
  "type": "Feature",
  "properties": {
    "iso:country":"UA",
    "name:ara_x_preferred":[
        "\u0625\u0641\u062c\u064a\u0646\u064a \u0628\u0648\u0643\u064a\u062a"
    ],
    "name:arq_x_preferred":[
        "\u0625\u0641\u06a4\u064a\u0646\u064a \u0628\u0648\u0643\u064a\u062a"
    ],
    "name:arz_x_preferred":[
        "\u0627\u0641\u062c\u064a\u0646\u0649 \u0628\u0648\u0643\u064a\u062a"
    ],
    "name:bak_x_preferred":[
        "\u0411\u0443\u043a\u0435\u0442 \u0415\u0432\u0433\u0435\u043d\u0438\u0439 \u0412\u0430\u0441\u0438\u043b\u044c\u0435\u0432\u0438\u0447"
    ],
    "name:deu_x_preferred":[
        "Jewhen Buket"
    ],
    "name:eng_x_preferred":[
        "Gruzskoye"
    ],
    "name:eng_x_variant":[
        "Yevgen Buket",
        "Yevhen Buket"
    ],
    "name:est_x_preferred":[
        "Jevgen Buket"
    ],
    "name:est_x_variant":[
        "Jevhen Buket"
    ],
    "name:fra_x_preferred":[
        "Yevgen Buket"
    ],
    "name:gle_x_preferred":[
        "Yevhen Buket"
    ],
    "name:mkd_x_preferred":[
        "\u0415\u0432\u0433\u0435\u043d\u0438\u0458 \u0411\u0443\u043a\u0435\u0442"
    ],
    "name:nld_x_preferred":[
        "Yevhen Buket"
    ],
    "name:pol_x_preferred":[
        "Eugeniusz Bukiet"
    ],
    "name:ron_x_preferred":[
        "Eugen Buchet"
    ],
    "name:ron_x_variant":[
        "Evhen Buket"
    ],
    "name:rus_x_preferred":[
        "\u0411\u0443\u043a\u0435\u0442"
    ],
    "name:rus_x_variant":[
        "\u0413\u0440\u0443\u0437\u0441\u043a\u043e\u0435",
        "\u0415\u0432\u0433\u0435\u043d\u0438\u0439 \u0411\u0443\u043a\u0435\u0442"
    ],
    "name:spa_x_preferred":[
        "Yevgen Buket"
    ],
    "name:sqi_x_preferred":[
        "Yevgen Buket"
    ],
    "name:tat_x_preferred":[
        "\u0411\u0443\u043a\u0435\u0442 \u0415\u0432\u0433\u0435\u043d \u0412\u0430\u0441\u0438\u043b\u0438\u0439 \u0443\u043b\u044b"
    ],
    "name:ukr_x_preferred":[
        "\u0411\u0443\u043a\u0435\u0442 \u0404\u0432\u0433\u0435\u043d \u0412\u0430\u0441\u0438\u043b\u044c\u043e\u0432\u0438\u0447"
    ],
    "name:ukr_x_variant":[
        "Hruz\u2019ke",
        "\u0413\u0440\u0443\u0437\u044c\u043a\u0435"
    ],
    "qs:a0":"\u0423\u043a\u0440\u0430\u0457\u043d\u0430",
    "qs:a1":"*\u0421\u0443\u043c\u0441\u044c\u043a\u0430",
    "qs:a1_alt":"Sums'ka",
    "qs:a1r":"0",
    "qs:a2":"\u041a\u043e\u043d\u043e\u0442\u043e\u043f\u0441\u044c\u043a\u0438\u0439",
    "qs:a2_alt":"Konotops'kyi",
    "qs:adm0":"\u0423\u043a\u0440\u0430\u0457\u043d\u0430",
    "qs:la_lc":"*",
    "qs:level":"locality",
    "qs:loc":"\u0413\u0440\u0443\u0437\u044c\u043a\u0435",
    "qs:loc_alt":"Hruz'ke",
    "qs:pop":0,
    "qs:type":"buffered point",
    "wd:wordcount":636,
    "wof:name":"\u0413\u0440\u0443\u0437\u044c\u043a\u0435",
    "wof:placetype":"locality"
},
  "geometry": {"coordinates":[33.516079,51.207433],"type":"Point"}
}