{
  "type": "Feature",
  "properties": {
    "iso:country":"UA",
    "name:bel_x_preferred":[
        "\u0421\u043a\u0430\u043c\u0430\u0440\u043e\u0448\u043a\u044b"
    ],
    "name:che_x_preferred":[
        "\u0421\u043a\u043e\u043c\u043e\u0440\u043e\u0448\u043a\u0438"
    ],
    "name:crh_x_preferred":[
        "Skomoro\u015fk\u0131"
    ],
    "name:deu_x_preferred":[
        "Skomoroschky"
    ],
    "name:eng_x_preferred":[
        "Skomoroshky"
    ],
    "name:fin_x_preferred":[
        "Sk\u043em\u043er\u043e\u0161ky"
    ],
    "name:hye_x_preferred":[
        "\u054d\u056f\u0578\u0574\u0578\u0580\u0578\u0577\u056f\u056b"
    ],
    "name:nan_x_preferred":[
        "Skomoroshky"
    ],
    "name:nno_x_preferred":[
        "Skomorosjky"
    ],
    "name:nob_x_preferred":[
        "Skomorosjky"
    ],
    "name:pol_x_preferred":[
        "Skomoroszky"
    ],
    "name:ron_x_preferred":[
        "Skomoro\u0219k\u00ee"
    ],
    "name:rus_x_preferred":[
        "\u0421\u043a\u043e\u043c\u043e\u0440\u043e\u0448\u043a\u0438"
    ],
    "name:ukr_x_preferred":[
        "\u0421\u043a\u043e\u043c\u043e\u0440\u043e\u0448\u043a\u0438"
    ],
    "name:und_x_variant":[
        "Skomoroshni"
    ],
    "name:zho_x_preferred":[
        "\u65af\u79d1\u83ab\u7f85\u4ec0\u57fa"
    ],
    "qs:a0":"\u0423\u043a\u0440\u0430\u0457\u043d\u0430",
    "qs:a1":"*\u0412\u0456\u043d\u043d\u0438\u0446\u044c\u043a\u0430",
    "qs:a1_alt":"Vinnyts'ka",
    "qs:a1r":"0",
    "qs:a2":"\u041e\u0440\u0430\u0442\u0456\u0432\u0441\u044c\u043a\u0438\u0439",
    "qs:a2_alt":"Orativs'kyi",
    "qs:adm0":"\u0423\u043a\u0440\u0430\u0457\u043d\u0430",
    "qs:la_lc":"*",
    "qs:level":"locality",
    "qs:loc":"\u0421\u043a\u043e\u043c\u043e\u0440\u043e\u0448\u043a\u0438",
    "qs:loc_alt":"Skomoroshky",
    "qs:pop":0,
    "qs:type":"buffered point",
    "wof:name":"\u0421\u043a\u043e\u043c\u043e\u0440\u043e\u0448\u043a\u0438",
    "wof:placetype":"locality"
},
  "geometry": {"coordinates":[29.443791,49.329935],"type":"Point"}
}