{
  "type": "Feature",
  "properties": {
    "gn:admin1_code":"21.0",
    "gn:asciiname":"Lyubytove",
    "gn:country_code":"UA",
    "gn:dem":125,
    "gn:feature_class":"P",
    "gn:feature_code":"PPL",
    "gn:name":"Lyubytove",
    "gn:population":0,
    "gn:timezone":"Europe/Kiev",
    "iso:country":"UA",
    "name:ukr_x_preferred":[
        "Lyubytove"
    ],
    "name:ukr_x_variant":[
        "\u041b\u044e\u0431\u0438\u0442\u043e\u0432\u0435"
    ],
    "name:und_x_variant":[
        "Lyubitov",
        "Lyubatov",
        "Lyubitovo"
    ],
    "wof:name":"Lyubytove",
    "wof:placetype":"locality"
},
  "geometry": {"coordinates":[33.24903,51.38217],"type":"Point"}
}