{
  "type": "Feature",
  "properties": {
    "gn:admin1_code":"27.0",
    "gn:asciiname":"Ukrayins'ke",
    "gn:country_code":"UA",
    "gn:dem":221,
    "gn:feature_class":"P",
    "gn:feature_code":"PPL",
    "gn:name":"Ukrayins\u2019ke",
    "gn:population":0,
    "gn:timezone":"Europe/Kiev",
    "iso:country":"UA",
    "name:ukr_x_preferred":[
        "Ukrayins\u2019ke"
    ],
    "name:ukr_x_variant":[
        "\u0423\u043a\u0440\u0430\u0457\u043d\u0441\u044c\u043a\u0435"
    ],
    "name:und_x_variant":[
        "Ukraynskoye"
    ],
    "wof:name":"Ukrayins'ke",
    "wof:placetype":"locality"
},
  "geometry": {"coordinates":[27.67867,50.43983],"type":"Point"}
}