{
  "type": "Feature",
  "properties": {
    "gn:admin1_code":"15.0",
    "gn:asciiname":"Slavshchizna",
    "gn:cc2":"UA",
    "gn:country_code":"UA",
    "gn:dem":259,
    "gn:feature_class":"P",
    "gn:feature_code":"PPL",
    "gn:name":"Slavshchizna",
    "gn:population":0,
    "gn:timezone":"Europe/Kiev",
    "iso:country":"UA",
    "name:und_x_variant":[
        "Slavshchina",
        "Slavshchizna"
    ],
    "wof:name":"Slavshchizna",
    "wof:placetype":"locality"
},
  "geometry": {"coordinates":[23.86667000000001,49.43333],"type":"Point"}
}