{
  "type": "Feature",
  "properties": {
    "gn:gn_country":"UA",
    "gn:gn_fcode":"PPL",
    "gn:gn_pop":795,
    "gn:population":795,
    "iso:country":"UA",
    "name:eng_x_preferred":[
        "Svirzh"
    ],
    "name:ger_x_preferred":[
        "Swirsch"
    ],
    "name:pol_x_preferred":[
        "\u015awirz"
    ],
    "name:rum_x_preferred":[
        "Svirj"
    ],
    "name:rus_x_preferred":[
        "\u0421\u0432\u0438\u0440\u0436"
    ],
    "name:ukr_x_preferred":[
        "\u0421\u0432\u0456\u0440\u0436"
    ],
    "name:unk_x_variant":[
        "S\u2019vizh"
    ],
    "qs_pg:aaroncc":"UA",
    "qs_pg:gn_country":"UA",
    "qs_pg:gn_fcode":"PPL",
    "qs_pg:gn_pop":795,
    "qs_pg:name":"Svirzh",
    "qs_pg:photos_9r":0,
    "qs_pg:photos_sr":0,
    "qs_pg:pop_sr":2,
    "qs_pg:qs_pg_placetype":"locality",
    "wof:name":"Svirzh",
    "wof:placetype":"locality",
    "wof:population":795
},
  "geometry": {"coordinates":[24.43953,49.64876],"type":"Point"}
}