{
  "type": "Feature",
  "properties": {
    "gn:country":"UA",
    "gn:fcode":"PPL",
    "gn:population":795,
    "iso:country":"UA",
    "name:bel_x_preferred":[
        "\u0421\u0432\u0456\u0440\u0436"
    ],
    "name:ceb_x_preferred":[
        "Svirzh"
    ],
    "name:che_x_preferred":[
        "\u0421\u0432\u0438\u0440\u0436"
    ],
    "name:deu_x_preferred":[
        "Swirsch"
    ],
    "name:eng_x_preferred":[
        "Svirzh"
    ],
    "name:fin_x_preferred":[
        "Sv\u0456r\u017e"
    ],
    "name:nan_x_preferred":[
        "Svirzh"
    ],
    "name:nno_x_preferred":[
        "Svirzj"
    ],
    "name:nob_x_preferred":[
        "Svirzj"
    ],
    "name:pol_x_preferred":[
        "\u015awirz"
    ],
    "name:ron_x_preferred":[
        "Svirj"
    ],
    "name:rus_x_preferred":[
        "\u0421\u0432\u0438\u0440\u0436"
    ],
    "name:szl_x_preferred":[
        "Swir\u017c"
    ],
    "name:ukr_x_preferred":[
        "\u0421\u0432\u0456\u0440\u0436"
    ],
    "name:und_x_variant":[
        "S\u2019vizh"
    ],
    "name:zho_x_preferred":[
        "\u65af\u7dad\u723e\u65e5"
    ],
    "qs_pg:aaroncc":"UA",
    "qs_pg:gn_country":"UA",
    "qs_pg:gn_fcode":"PPL",
    "qs_pg:gn_pop":795,
    "qs_pg:name":"Svirzh",
    "qs_pg:photos_9r":0,
    "qs_pg:photos_sr":0,
    "qs_pg:pop_sr":2,
    "qs_pg:qs_pg_placetype":"locality",
    "wof:name":"Svirzh",
    "wof:placetype":"locality",
    "wof:population":795
},
  "geometry": {"coordinates":[24.43953,49.64876],"type":"Point"}
}