{
  "type": "Feature",
  "properties": {
    "gn:admin1_code":"2.0",
    "gn:asciiname":"Parnya",
    "gn:country_code":"UA",
    "gn:dem":139,
    "gn:feature_class":"P",
    "gn:feature_code":"PPL",
    "gn:name":"Parnya",
    "gn:population":0,
    "gn:timezone":"Europe/Kiev",
    "iso:country":"UA",
    "name:ukr_x_preferred":[
        "Parnya"
    ],
    "wof:name":"Parnya",
    "wof:placetype":"locality"
},
  "geometry": {"coordinates":[32.41445,52.18865],"type":"Point"}
}