{
  "type": "Feature",
  "properties": {
    "gn:admin1_code":"10.0",
    "gn:asciiname":"Markovo",
    "gn:country_code":"UA",
    "gn:dem":173,
    "gn:feature_class":"P",
    "gn:feature_code":"PPL",
    "gn:name":"Markovo",
    "gn:population":0,
    "gn:timezone":"Europe/Kiev",
    "iso:country":"UA",
    "name:und_x_variant":[
        "Viktorshtadt",
        "Markovo"
    ],
    "wof:name":"Markovo",
    "wof:placetype":"locality"
},
  "geometry": {"coordinates":[31.10576,48.58029000000001],"type":"Point"}
}