{
  "type": "Feature",
  "properties": {
    "gn:admin1_code":"6.0",
    "gn:asciiname":"Slupeyka",
    "gn:cc2":"UA",
    "gn:country_code":"UA",
    "gn:dem":838,
    "gn:feature_class":"P",
    "gn:feature_code":"PPL",
    "gn:name":"Slupeyka",
    "gn:population":0,
    "gn:timezone":"Europe/Kiev",
    "iso:country":"UA",
    "name:und_x_variant":[
        "Zabie S\u0142upejka",
        "S\u0142upejka",
        "Stupejka",
        "Slupeyka"
    ],
    "wof:name":"Slupeyka",
    "wof:placetype":"locality"
},
  "geometry": {"coordinates":[24.81667,48.16667],"type":"Point"}
}