{
  "type": "Feature",
  "properties": {
    "iso:country":"UA",
    "qs:a0":"\u0423\u043a\u0440\u0430\u0457\u043d\u0430",
    "qs:a1":"*\u041b\u0443\u0433\u0430\u043d\u0441\u044c\u043a\u0430",
    "qs:a1_alt":"Luhans'ka",
    "qs:a1r":"0",
    "qs:a2":"\u041b\u0443\u0442\u0443\u0433\u0438\u043d\u0441\u043a\u0438\u0439",
    "qs:a2_alt":"Lutuhynskyi",
    "qs:adm0":"\u0423\u043a\u0440\u0430\u0457\u043d\u0430",
    "qs:la_lc":"*",
    "qs:level":"locality",
    "qs:loc":"\u0413\u0435\u043e\u0440\u0433\u0456\u0457\u0432\u043a\u0430",
    "qs:loc_alt":"Heorhiivka",
    "qs:pop":0,
    "qs:type":"buffered point",
    "wof:name":"\u0413\u0435\u043e\u0440\u0433\u0456\u0457\u0432\u043a\u0430",
    "wof:placetype":"locality"
},
  "geometry": {"coordinates":[39.267918,48.43008],"type":"Point"}
}