{
  "type": "Feature",
  "properties": {
    "gn:admin1_code":"22.0",
    "gn:asciiname":"Kozina",
    "gn:country_code":"UA",
    "gn:dem":269,
    "gn:feature_class":"P",
    "gn:feature_code":"PPL",
    "gn:name":"Kozina",
    "gn:population":0,
    "gn:timezone":"Europe/Kiev",
    "iso:country":"UA",
    "wof:name":"Kozina",
    "wof:placetype":"locality"
},
  "geometry": {"coordinates":[26.23889,49.29863],"type":"Point"}
}