{
  "type": "Feature",
  "properties": {
    "gn:admin1_code":"1.0",
    "gn:asciiname":"Kislin",
    "gn:country_code":"UA",
    "gn:dem":185,
    "gn:feature_class":"P",
    "gn:feature_code":"PPL",
    "gn:name":"Kislin",
    "gn:population":0,
    "gn:timezone":"Europe/Kiev",
    "iso:country":"UA",
    "wof:name":"Kislin",
    "wof:placetype":"locality"
},
  "geometry": {"coordinates":[30.39368,49.1272],"type":"Point"}
}