{
  "type": "Feature",
  "properties": {
    "gn:admin1_code":"26.0",
    "gn:asciiname":"Krinichevatyy",
    "gn:country_code":"UA",
    "gn:dem":83,
    "gn:feature_class":"P",
    "gn:feature_code":"PPL",
    "gn:name":"Krinichevatyy",
    "gn:population":0,
    "gn:timezone":"Europe/Zaporozhye",
    "iso:country":"UA",
    "name:und_x_variant":[
        "Krinichevaty",
        "Krinichevatyy"
    ],
    "wof:name":"Krinichevatyy",
    "wof:placetype":"locality"
},
  "geometry": {"coordinates":[35.38333,47.49999],"type":"Point"}
}