{
  "type": "Feature",
  "properties": {
    "gn:admin1_code":"24.0",
    "gn:asciiname":"Dubova Korchma",
    "gn:country_code":"UA",
    "gn:dem":247,
    "gn:feature_class":"P",
    "gn:feature_code":"PPL",
    "gn:name":"Dubova Korchma",
    "gn:population":0,
    "gn:timezone":"Europe/Kiev",
    "iso:country":"UA",
    "name:ukr_x_preferred":[
        "Dubova Korchma"
    ],
    "name:ukr_x_variant":[
        "\u0414\u0443\u0431\u043e\u0432\u0430 \u041a\u043e\u0440\u0447\u043c\u0430"
    ],
    "name:und_x_variant":[
        "Dubovaya Korchma"
    ],
    "wof:name":"Dubova Korchma",
    "wof:placetype":"locality"
},
  "geometry": {"coordinates":[25.11906,50.5508],"type":"Point"}
}