{
  "type": "Feature",
  "properties": {
    "gn:admin1_code":"19.0",
    "gn:asciiname":"Lopavshe",
    "gn:country_code":"UA",
    "gn:dem":191,
    "gn:feature_class":"P",
    "gn:feature_code":"PPL",
    "gn:name":"Lopavshe",
    "gn:population":0,
    "gn:timezone":"Europe/Kiev",
    "iso:country":"UA",
    "name:ukr_x_preferred":[
        "Lopavshe"
    ],
    "name:ukr_x_variant":[
        "\u041b\u043e\u043f\u0430\u0432\u0448\u0435"
    ],
    "wof:name":"Lopavshe",
    "wof:placetype":"locality"
},
  "geometry": {"coordinates":[25.28156,50.45318],"type":"Point"}
}