{
  "type": "Feature",
  "properties": {
    "gn:admin1_code":"4.0",
    "gn:asciiname":"Nova Sich",
    "gn:country_code":"UA",
    "gn:dem":97,
    "gn:feature_class":"P",
    "gn:feature_code":"PPL",
    "gn:name":"Nova Sich",
    "gn:population":0,
    "gn:timezone":"Europe/Kiev",
    "iso:country":"UA",
    "name:ukr_x_preferred":[
        "Nova Sich"
    ],
    "name:ukr_x_variant":[
        "\u041d\u043e\u0432\u0430 \u0421\u0456\u0447"
    ],
    "wof:name":"Nova Sich",
    "wof:placetype":"locality"
},
  "geometry": {"coordinates":[33.78021,47.60864],"type":"Point"}
}