{
  "type": "Feature",
  "properties": {
    "gn:admin1_code":"13.0",
    "gn:asciiname":"Lyzohubova Sloboda",
    "gn:country_code":"UA",
    "gn:dem":131,
    "gn:feature_class":"P",
    "gn:feature_code":"PPL",
    "gn:name":"Lyzohubova Sloboda",
    "gn:population":0,
    "gn:timezone":"Europe/Kiev",
    "iso:country":"UA",
    "name:ukr_x_preferred":[
        "Lyzohubova Sloboda"
    ],
    "name:ukr_x_variant":[
        "\u041b\u0438\u0437\u043e\u0433\u0443\u0431\u043e\u0432\u0430 \u0421\u043b\u043e\u0431\u043e\u0434\u0430"
    ],
    "name:und_x_variant":[
        "Lizogubova Sloboda"
    ],
    "wof:name":"Lyzohubova Sloboda",
    "wof:placetype":"locality"
},
  "geometry": {"coordinates":[31.91246,50.40727],"type":"Point"}
}