{
  "type": "Feature",
  "properties": {
    "gn:admin1_code":"22.0",
    "gn:asciiname":"Khartanove",
    "gn:country_code":"UA",
    "gn:dem":244,
    "gn:feature_class":"P",
    "gn:feature_code":"PPL",
    "gn:name":"Khartanove",
    "gn:population":0,
    "gn:timezone":"Europe/Kiev",
    "iso:country":"UA",
    "name:und_x_variant":[
        "Kharitonovtsy",
        "Khartonovtse",
        "Khartanove"
    ],
    "wof:name":"Khartanove",
    "wof:placetype":"locality"
},
  "geometry": {"coordinates":[25.75068,48.76409],"type":"Point"}
}