{
  "type": "Feature",
  "properties": {
    "gn:admin1_code":"2.0",
    "gn:asciiname":"Nyzkivka",
    "gn:country_code":"UA",
    "gn:dem":137,
    "gn:feature_class":"P",
    "gn:feature_code":"PPL",
    "gn:name":"Nyzkivka",
    "gn:population":0,
    "gn:timezone":"Europe/Kiev",
    "iso:country":"UA",
    "name:ukr_x_preferred":[
        "Nyzkivka"
    ],
    "name:ukr_x_variant":[
        "\u041d\u0438\u0437\u043a\u0456\u0432\u043a\u0430"
    ],
    "name:und_x_variant":[
        "Nizkovka"
    ],
    "wof:name":"Nyzkivka",
    "wof:placetype":"locality"
},
  "geometry": {"coordinates":[32.03257,51.65774],"type":"Point"}
}