{
  "type": "Feature",
  "properties": {
    "iso:country":"UA",
    "name:und_x_variant":[
        "Negovtse"
    ],
    "qs:a0":"\u0423\u043a\u0440\u0430\u0457\u043d\u0430",
    "qs:a1":"*\u0406\u0432\u0430\u043d\u043e-\u0424\u0440\u0430\u043d\u043a\u0456\u0432\u0441\u044c\u043a\u0430",
    "qs:a1_alt":"Ivano-Frankivs'ka",
    "qs:a1r":"0",
    "qs:a2":"\u041a\u0430\u043b\u0443\u0441\u044c\u043a\u0438\u0439",
    "qs:a2_alt":"Kalus'kyi",
    "qs:adm0":"\u0423\u043a\u0440\u0430\u0457\u043d\u0430",
    "qs:la_lc":"*",
    "qs:level":"locality",
    "qs:loc":"\u041d\u0435\u0433\u0456\u0432\u0446\u0456",
    "qs:loc_alt":"Nehivtsi",
    "qs:pop":0,
    "qs:type":"buffered point",
    "wof:name":"\u041d\u0435\u0433\u0456\u0432\u0446\u0456",
    "wof:placetype":"locality"
},
  "geometry": {"coordinates":[24.367625,49.132462],"type":"Point"}
}