{
  "type": "Feature",
  "properties": {
    "gn:admin1_code":"9.0",
    "gn:asciiname":"Lodzyanivka",
    "gn:country_code":"UA",
    "gn:dem":238,
    "gn:feature_class":"P",
    "gn:feature_code":"PPL",
    "gn:name":"Lodzyanivka",
    "gn:population":0,
    "gn:timezone":"Europe/Kiev",
    "iso:country":"UA",
    "name:ukr_x_preferred":[
        "Lodzyanivka"
    ],
    "name:ukr_x_variant":[
        "\u041b\u043e\u0434\u0437\u044f\u043d\u0456\u0432\u043a\u0430"
    ],
    "name:und_x_variant":[
        "Lodzyanovka"
    ],
    "wof:name":"Lodzyanivka",
    "wof:placetype":"locality"
},
  "geometry": {"coordinates":[27.58071,50.24435],"type":"Point"}
}