{
  "type": "Feature",
  "properties": {
    "gn:admin1_code":"16.0",
    "gn:asciiname":"Pantazlovka",
    "gn:cc2":"UA",
    "gn:country_code":"UA",
    "gn:dem":28,
    "gn:feature_class":"P",
    "gn:feature_code":"PPL",
    "gn:name":"Pantazlovka",
    "gn:population":0,
    "gn:timezone":"Europe/Kiev",
    "iso:country":"UA",
    "name:und_x_variant":[
        "Zhenevka",
        "Pantazlovka"
    ],
    "wof:name":"Pantazlovka",
    "wof:placetype":"locality"
},
  "geometry": {"coordinates":[31.76667,47.35],"type":"Point"}
}