{
  "type": "Feature",
  "properties": {
    "gn:admin1_code":"5.0",
    "gn:asciiname":"Zavitne Bazhannya",
    "gn:country_code":"UA",
    "gn:dem":115,
    "gn:feature_class":"P",
    "gn:feature_code":"PPL",
    "gn:name":"Zavitne Bazhannya",
    "gn:population":0,
    "gn:timezone":"Europe/Kiev",
    "iso:country":"UA",
    "name:ukr_x_preferred":[
        "\u0417\u0430\u0432\u0456\u0442\u043d\u0435 \u0411\u0430\u0436\u0430\u043d\u043d\u044f"
    ],
    "name:und_x_variant":[
        "Zavetne Bazhannya",
        "Zavitne Bazhannya"
    ],
    "wof:name":"Zavitne Bazhannya",
    "wof:placetype":"locality"
},
  "geometry": {"coordinates":[36.81878,47.72046],"type":"Point"}
}