{
  "type": "Feature",
  "properties": {
    "gn:admin1_code":"24.0",
    "gn:asciiname":"Zhukovets'",
    "gn:country_code":"UA",
    "gn:dem":200,
    "gn:feature_class":"P",
    "gn:feature_code":"PPL",
    "gn:name":"Zhukovets\u2019",
    "gn:population":0,
    "gn:timezone":"Europe/Kiev",
    "iso:country":"UA",
    "name:ukr_x_preferred":[
        "Zhukovets\u2019"
    ],
    "name:ukr_x_variant":[
        "\u0416\u0443\u043a\u043e\u0432\u0435\u0446\u044c"
    ],
    "name:und_x_variant":[
        "Zhukovets"
    ],
    "wof:name":"Zhukovets'",
    "wof:placetype":"locality"
},
  "geometry": {"coordinates":[24.93953,50.66353],"type":"Point"}
}