{
  "type": "Feature",
  "properties": {
    "gn:admin1_code":"25.0",
    "gn:asciiname":"Karpaty",
    "gn:country_code":"UA",
    "gn:dem":209,
    "gn:feature_class":"P",
    "gn:feature_code":"PPL",
    "gn:name":"Karpaty",
    "gn:population":235,
    "gn:timezone":"Europe/Uzhgorod",
    "iso:country":"UA",
    "name:bar_x_preferred":[
        "Karpaty"
    ],
    "name:ceb_x_preferred":[
        "Karpaty"
    ],
    "name:deu_x_preferred":[
        "Karpaty"
    ],
    "name:eng_x_preferred":[
        "Karpaty"
    ],
    "name:ita_x_preferred":[
        "Karpaty"
    ],
    "name:pol_x_preferred":[
        "Karpaty"
    ],
    "name:rus_x_preferred":[
        "\u041a\u0430\u0440\u043f\u0430\u0442\u044b"
    ],
    "name:slk_x_preferred":[
        "Karpaty"
    ],
    "name:ukr_x_preferred":[
        "\u041a\u0430\u0440\u043f\u0430\u0442\u0438"
    ],
    "wof:name":"Karpaty",
    "wof:placetype":"locality",
    "wof:population":235
},
  "geometry": {"coordinates":[22.87498,48.52488],"type":"Point"}
}