{
  "type": "Feature",
  "properties": {
    "gn:admin1_code":"10.0",
    "gn:asciiname":"Dubivka",
    "gn:country_code":"UA",
    "gn:dem":159,
    "gn:feature_class":"P",
    "gn:feature_code":"PPL",
    "gn:name":"Dubivka",
    "gn:population":0,
    "gn:timezone":"Europe/Kiev",
    "iso:country":"UA",
    "name:ukr_x_preferred":[
        "\u0414\u0443\u0431\u0456\u0432\u043a\u0430"
    ],
    "name:und_x_variant":[
        "Dubovyy",
        "Dubivka"
    ],
    "wof:name":"Dubivka",
    "wof:placetype":"locality"
},
  "geometry": {"coordinates":[33.01865,48.46713],"type":"Point"}
}