{
  "type": "Feature",
  "properties": {
    "gn:admin1_code":"26.0",
    "gn:asciiname":"Solodke",
    "gn:country_code":"UA",
    "gn:dem":73,
    "gn:feature_class":"P",
    "gn:feature_code":"PPL",
    "gn:name":"Solodke",
    "gn:population":0,
    "gn:timezone":"Europe/Zaporozhye",
    "iso:country":"UA",
    "name:ukr_x_preferred":[
        "Solodke"
    ],
    "name:ukr_x_variant":[
        "\u0421\u043e\u043b\u043e\u0434\u043a\u0435"
    ],
    "name:und_x_variant":[
        "Solodkiy",
        "Sladkiy",
        "Sladkoye"
    ],
    "wof:name":"Solodke",
    "wof:placetype":"locality"
},
  "geometry": {"coordinates":[35.19559,47.14713],"type":"Point"}
}