{
  "type": "Feature",
  "properties": {
    "gn:admin1_code":"27.0",
    "gn:asciiname":"Ulashanivka",
    "gn:country_code":"UA",
    "gn:dem":218,
    "gn:feature_class":"P",
    "gn:feature_code":"PPL",
    "gn:name":"Ulashanivka",
    "gn:population":0,
    "gn:timezone":"Europe/Kiev",
    "iso:country":"UA",
    "name:ukr_x_preferred":[
        "Ulashanivka"
    ],
    "name:ukr_x_variant":[
        "\u0423\u043b\u0430\u0448\u0430\u043d\u0456\u0432\u043a\u0430"
    ],
    "name:und_x_variant":[
        "Ulashinovka",
        "Ulashanovka"
    ],
    "wof:name":"Ulashanivka",
    "wof:placetype":"locality"
},
  "geometry": {"coordinates":[27.97635,50.50366],"type":"Point"}
}