{
  "type": "Feature",
  "properties": {
    "gn:admin1_code":"7.0",
    "gn:asciiname":"Kostiv",
    "gn:country_code":"UA",
    "gn:dem":185,
    "gn:feature_class":"P",
    "gn:feature_code":"PPL",
    "gn:name":"Kostiv",
    "gn:population":0,
    "gn:timezone":"Europe/Kiev",
    "iso:country":"UA",
    "name:ukr_x_preferred":[
        "Kostiv"
    ],
    "name:ukr_x_variant":[
        "\u041a\u043e\u0441\u0442\u0456\u0432"
    ],
    "name:und_x_variant":[
        "Kostev"
    ],
    "wof:name":"Kostiv",
    "wof:placetype":"locality"
},
  "geometry": {"coordinates":[35.63321,49.86309],"type":"Point"}
}