{
  "type": "Feature",
  "properties": {
    "gn:admin1_code":"27.0",
    "gn:asciiname":"Kotlyarka",
    "gn:country_code":"UA",
    "gn:dem":212,
    "gn:feature_class":"P",
    "gn:feature_code":"PPL",
    "gn:name":"Kotlyarka",
    "gn:population":0,
    "gn:timezone":"Europe/Kiev",
    "iso:country":"UA",
    "name:ukr_x_preferred":[
        "Kotlyarka"
    ],
    "name:ukr_x_variant":[
        "\u041a\u043e\u0442\u043b\u044f\u0440\u043a\u0430"
    ],
    "wof:name":"Kotlyarka",
    "wof:placetype":"locality"
},
  "geometry": {"coordinates":[29.33635,50.02717],"type":"Point"}
}