{
  "type": "Feature",
  "properties": {
    "gn:admin1_code":"26.0",
    "gn:asciiname":"Tul'ga",
    "gn:country_code":"UA",
    "gn:dem":6,
    "gn:feature_class":"P",
    "gn:feature_code":"PPL",
    "gn:name":"Tul\u2019ga",
    "gn:population":0,
    "gn:timezone":"Europe/Zaporozhye",
    "iso:country":"UA",
    "name:und_x_variant":[
        "Tul\u2019ga Nomer Tretiy",
        "Tul\u2019ga"
    ],
    "wof:name":"Tul'ga",
    "wof:placetype":"locality"
},
  "geometry": {"coordinates":[35.36667,46.66667],"type":"Point"}
}