{
  "type": "Feature",
  "properties": {
    "gn:admin1_code":"5.0",
    "gn:asciiname":"Dachnyy",
    "gn:country_code":"UA",
    "gn:dem":270,
    "gn:feature_class":"P",
    "gn:feature_code":"PPL",
    "gn:name":"Dachnyy",
    "gn:population":0,
    "gn:timezone":"Europe/Kiev",
    "iso:country":"UA",
    "wof:name":"Dachnyy",
    "wof:placetype":"locality"
},
  "geometry": {"coordinates":[38.53111,48.12611],"type":"Point"}
}