{
  "type": "Feature",
  "properties": {
    "iso:country":"UA",
    "qs:a0":"\u0423\u043a\u0440\u0430\u0457\u043d\u0430",
    "qs:a1":"*\u041f\u043e\u043b\u0442\u0430\u0432\u0441\u044c\u043a\u0430",
    "qs:a1_alt":"Poltavs'ka",
    "qs:a1r":"0",
    "qs:a2":"\u041a\u0440\u0435\u043c\u0435\u043d\u0447\u0443\u0446\u044c\u043a\u0438\u0439",
    "qs:a2_alt":"Kremenchuts'kyi",
    "qs:adm0":"\u0423\u043a\u0440\u0430\u0457\u043d\u0430",
    "qs:la_lc":"*",
    "qs:level":"locality",
    "qs:loc":"\u041c\u0430\u043b\u0430 \u041a\u043e\u0445\u043d\u0456\u0432\u043a\u0430",
    "qs:loc_alt":"Mala Kokhnivka",
    "qs:pop":0,
    "qs:type":"buffered point",
    "wof:name":"\u041c\u0430\u043b\u0430 \u041a\u043e\u0445\u043d\u0456\u0432\u043a\u0430",
    "wof:placetype":"locality"
},
  "geometry": {"coordinates":[33.490769,49.072092],"type":"Point"}
}