{
  "type": "Feature",
  "properties": {
    "gn:admin1_code":"17.0",
    "gn:asciiname":"Saratove",
    "gn:cc2":"UA",
    "gn:country_code":"UA",
    "gn:dem":207,
    "gn:feature_class":"P",
    "gn:feature_code":"PPL",
    "gn:name":"Saratove",
    "gn:population":0,
    "gn:timezone":"Europe/Kiev",
    "iso:country":"UA",
    "name:und_x_variant":[
        "Khutor Saratovo",
        "Saratovo"
    ],
    "wof:name":"Saratove",
    "wof:placetype":"locality"
},
  "geometry": {"coordinates":[29.63389,47.50917000000001],"type":"Point"}
}