{
  "type": "Feature",
  "properties": {
    "gn:admin1_code":"27.0",
    "gn:asciiname":"Lukishky",
    "gn:country_code":"UA",
    "gn:dem":144,
    "gn:feature_class":"P",
    "gn:feature_code":"PPL",
    "gn:name":"Lukishky",
    "gn:population":0,
    "gn:timezone":"Europe/Kiev",
    "iso:country":"UA",
    "name:ukr_x_preferred":[
        "Lukishky"
    ],
    "name:ukr_x_variant":[
        "\u041b\u0443\u043a\u0456\u0448\u043a\u0438"
    ],
    "name:und_x_variant":[
        "Lukoshki"
    ],
    "wof:name":"Lukishky",
    "wof:placetype":"locality"
},
  "geometry": {"coordinates":[28.77671,51.3127],"type":"Point"}
}