{
  "type": "Feature",
  "properties": {
    "gn:admin1_code":"21.0",
    "gn:asciiname":"Likars'ke",
    "gn:country_code":"UA",
    "gn:dem":151,
    "gn:feature_class":"P",
    "gn:feature_code":"PPL",
    "gn:name":"Likars\u2019ke",
    "gn:population":0,
    "gn:timezone":"Europe/Kiev",
    "iso:country":"UA",
    "name:ukr_x_preferred":[
        "Likars\u2019ke"
    ],
    "name:ukr_x_variant":[
        "\u041b\u0456\u043a\u0430\u0440\u0441\u044c\u043a\u0435"
    ],
    "name:und_x_variant":[
        "Lekarskiy",
        "Lekarskoye"
    ],
    "wof:name":"Likars'ke",
    "wof:placetype":"locality"
},
  "geometry": {"coordinates":[34.53205999999999,50.99567],"type":"Point"}
}