{
  "type": "Feature",
  "properties": {
    "gn:admin1_code":"21.0",
    "gn:asciiname":"Dyakivka",
    "gn:country_code":"UA",
    "gn:dem":162,
    "gn:feature_class":"P",
    "gn:feature_code":"PPL",
    "gn:name":"Dyakivka",
    "gn:population":0,
    "gn:timezone":"Europe/Kiev",
    "iso:country":"UA",
    "name:ukr_x_preferred":[
        "\u0414\u044f\u043a\u0456\u0432\u043a\u0430"
    ],
    "name:und_x_variant":[
        "D\u2019yakovka",
        "Dyakivka"
    ],
    "wof:name":"Dyakivka",
    "wof:placetype":"locality"
},
  "geometry": {"coordinates":[34.02466,51.17711],"type":"Point"}
}