{
  "type": "Feature",
  "properties": {
    "gn:admin1_code":"9.0",
    "gn:asciiname":"Veselovka",
    "gn:country_code":"UA",
    "gn:dem":347,
    "gn:feature_class":"P",
    "gn:feature_code":"PPL",
    "gn:name":"Veselovka",
    "gn:population":0,
    "gn:timezone":"Europe/Kiev",
    "iso:country":"UA",
    "name:aze_x_preferred":[
        "Veselovka"
    ],
    "name:bak_x_preferred":[
        "\u0412\u0435\u0441\u0435\u043b\u043e\u0432\u043a\u0430"
    ],
    "name:che_x_preferred":[
        "\u0412\u0435\u044d\u0432\u043b\u0430"
    ],
    "name:chv_x_preferred":[
        "\u0412\u0435\u0441\u0435\u043b\u043e\u0432\u043a\u0430"
    ],
    "name:hye_x_preferred":[
        "\u054e\u0565\u057d\u0565\u056c\u0578"
    ],
    "name:kaz_x_preferred":[
        "\u0412\u0435\u0430\u0443\u044b\u043b"
    ],
    "name:kir_x_preferred":[
        "\u0412\u0435\u0430\u0439\u044b\u043b"
    ],
    "name:rus_x_preferred":[
        "\u0412\u0435\u0441\u0435\u043b\u043e\u0432\u043a\u0430"
    ],
    "name:tat_x_preferred":[
        "\u0412\u0435\u0441\u0435\u043b\u043e\u0435"
    ],
    "name:ukr_x_preferred":[
        "\u0412\u0435\u0441\u0435\u043b\u043e\u0432\u043a\u0430"
    ],
    "name:und_x_variant":[
        "Kobyl\u2019ye",
        "Veselovka"
    ],
    "wof:name":"Veselovka",
    "wof:placetype":"locality"
},
  "geometry": {"coordinates":[27.10162,49.58745],"type":"Point"}
}