{
  "type": "Feature",
  "properties": {
    "gn:admin1_code":"9.0",
    "gn:asciiname":"Veselovka",
    "gn:country_code":"UA",
    "gn:dem":347,
    "gn:feature_class":"P",
    "gn:feature_code":"PPL",
    "gn:name":"Veselovka",
    "gn:population":0,
    "gn:timezone":"Europe/Kiev",
    "iso:country":"UA",
    "name:und_x_variant":[
        "Kobyl\u2019ye",
        "Veselovka"
    ],
    "wof:name":"Veselovka",
    "wof:placetype":"locality"
},
  "geometry": {"coordinates":[27.10162,49.58745],"type":"Point"}
}