{
  "type": "Feature",
  "properties": {
    "iso:country":"UA",
    "name:eng_x_preferred":[
        "Molochnoye"
    ],
    "name:rus_x_historical":[
        "\u0422\u0435\u0440\u0435\u043a\u043b\u044b-\u041a\u043e\u043d\u0440\u0430\u0301\u0442"
    ],
    "name:rus_x_preferred":[
        "\u0422\u0435\u0440\u0435\u043a\u043b\u044b-\u041a\u043e\u043d\u0440\u0430\u0301\u0442"
    ],
    "name:rus_x_variant":[
        "\u041c\u043e\u043b\u043e\u0447\u043d\u043e\u0435"
    ],
    "name:ukr_x_preferred":[
        "\u041c\u043e\u043b\u043e\u0447\u043d\u0435"
    ],
    "qs:a0":"\u0423\u043a\u0440\u0430\u0457\u043d\u0430",
    "qs:a1":"*\u041a\u0440\u0438\u043c",
    "qs:a1_alt":"Krym",
    "qs:a1r":"0",
    "qs:a2":"\u0421\u0430\u043a\u0441\u044c\u043a\u0438\u0439",
    "qs:a2_alt":"Saks'kyi",
    "qs:adm0":"\u0423\u043a\u0440\u0430\u0457\u043d\u0430",
    "qs:la_lc":"*",
    "qs:level":"locality",
    "qs:loc":"\u041c\u043e\u043b\u043e\u0447\u043d\u0435",
    "qs:loc_alt":"Molochne",
    "qs:pop":0,
    "qs:type":"buffered point",
    "wof:name":"\u041c\u043e\u043b\u043e\u0447\u043d\u0435",
    "wof:placetype":"locality"
},
  "geometry": {"coordinates":[33.221142,45.199426],"type":"Point"}
}