{
  "type": "Feature",
  "properties": {
    "gn:admin1_code":"2.0",
    "gn:asciiname":"Loshakova Huta",
    "gn:country_code":"UA",
    "gn:dem":108,
    "gn:feature_class":"P",
    "gn:feature_code":"PPL",
    "gn:name":"Loshakova Huta",
    "gn:population":0,
    "gn:timezone":"Europe/Kiev",
    "iso:country":"UA",
    "name:ukr_x_preferred":[
        "Loshakova Huta"
    ],
    "name:ukr_x_variant":[
        "\u041b\u043e\u0448\u0430\u043a\u043e\u0432\u0430 \u0413\u0443\u0442\u0430"
    ],
    "name:und_x_variant":[
        "Staraya Karpilovskaya Guta",
        "Staro-Karpilovskaya Guta",
        "Staraya Loshakova Guta",
        "Loshakova Guta"
    ],
    "wof:name":"Loshakova Huta",
    "wof:placetype":"locality"
},
  "geometry": {"coordinates":[30.65551,51.03074],"type":"Point"}
}