{
  "type": "Feature",
  "properties": {
    "gn:admin1_code":"24.0",
    "gn:asciiname":"Stolyns'ki Smolyary",
    "gn:country_code":"UA",
    "gn:dem":170,
    "gn:feature_class":"P",
    "gn:feature_code":"PPL",
    "gn:name":"Stolyns\u2019ki Smolyary",
    "gn:population":0,
    "gn:timezone":"Europe/Kiev",
    "iso:country":"UA",
    "name:ukr_x_preferred":[
        "Stolyns\u2019ki Smolyary"
    ],
    "name:ukr_x_variant":[
        "\u0421\u0442\u043e\u043b\u0438\u043d\u0441\u044c\u043a\u0456 \u0421\u043c\u043e\u043b\u044f\u0440\u0438"
    ],
    "name:und_x_variant":[
        "Stolyns\u2019ki Smolyari",
        "Stolenskiye-Smolyary",
        "Stolinskiye-Smolyary"
    ],
    "wof:name":"Stolyns'ki Smolyary",
    "wof:placetype":"locality"
},
  "geometry": {"coordinates":[23.78367,51.38643],"type":"Point"}
}