{
  "type": "Feature",
  "properties": {
    "gn:admin1_code":"1.0",
    "gn:asciiname":"Bogachevka",
    "gn:country_code":"UA",
    "gn:dem":144,
    "gn:feature_class":"P",
    "gn:feature_code":"PPL",
    "gn:name":"Bogach\u00ebvka",
    "gn:population":0,
    "gn:timezone":"Europe/Kiev",
    "iso:country":"UA",
    "wof:name":"Bogachevka",
    "wof:placetype":"locality"
},
  "geometry": {"coordinates":[31.0977,49.05196],"type":"Point"}
}