{
  "type": "Feature",
  "properties": {
    "gn:admin1_code":"15.0",
    "gn:asciiname":"Andriyivka",
    "gn:country_code":"UA",
    "gn:dem":207,
    "gn:feature_class":"P",
    "gn:feature_code":"PPL",
    "gn:name":"Andriyivka",
    "gn:population":0,
    "gn:timezone":"Europe/Kiev",
    "iso:country":"UA",
    "name:ukr_x_preferred":[
        "Andriyivka"
    ],
    "name:ukr_x_variant":[
        "\u0410\u043d\u0434\u0440\u0456\u0457\u0432\u043a\u0430"
    ],
    "name:und_x_variant":[
        "Andrzj\u00f3wka",
        "Andzheyuvka",
        "Andreyevka"
    ],
    "wof:name":"Andriyivka",
    "wof:placetype":"locality"
},
  "geometry": {"coordinates":[24.43615,50.36081],"type":"Point"}
}