{
  "type": "Feature",
  "properties": {
    "gn:population":12657,
    "iso:country":"UA",
    "name:ara_x_preferred":[
        "\u0628\u0627\u0634\u062a\u0627\u0646\u0643\u0627"
    ],
    "name:arm_x_preferred":[
        "\u0532\u0561\u0577\u057f\u0561\u0576\u056f\u0561"
    ],
    "name:bel_x_variant":[
        "\u0411\u0430\u0448\u0442\u0430\u043d\u043a\u0430"
    ],
    "name:bul_x_preferred":[
        "\u0411\u0430\u0449\u0430\u043d\u043a\u0430"
    ],
    "name:ces_x_preferred":[
        "Ba\u0161tanka"
    ],
    "name:chi_x_preferred":[
        "\u5df4\u4ec0\u5766\u5361"
    ],
    "name:crh_x_preferred":[
        "Ba\u015ftanka"
    ],
    "name:cze_x_preferred":[
        "Ba\u0161tanka"
    ],
    "name:deu_x_preferred":[
        "Baschtanka"
    ],
    "name:eng_x_preferred":[
        "Bashtanka"
    ],
    "name:fas_x_preferred":[
        "\u0628\u0627\u0634\u062a\u0627\u0646\u06a9\u0627"
    ],
    "name:fra_x_preferred":[
        "Bachtanka"
    ],
    "name:fre_x_preferred":[
        "Bachtanka"
    ],
    "name:geo_x_preferred":[
        "\u10d1\u10d0\u10e8\u10e2\u10d0\u10dc\u10d9\u10d0"
    ],
    "name:ger_x_preferred":[
        "Baschtanka"
    ],
    "name:hye_x_preferred":[
        "\u0532\u0561\u0577\u057f\u0561\u0576\u056f\u0561"
    ],
    "name:ita_x_preferred":[
        "Ba\u0161tanka"
    ],
    "name:kat_x_preferred":[
        "\u10d1\u10d0\u10e8\u10e2\u10d0\u10dc\u10d9\u10d0"
    ],
    "name:lav_x_preferred":[
        "Ba\u0161tanka"
    ],
    "name:nno_x_preferred":[
        "Basjtanka"
    ],
    "name:per_x_preferred":[
        "\u0628\u0627\u0634\u062a\u0627\u0646\u06a9\u0627"
    ],
    "name:pol_x_preferred":[
        "Basztanka"
    ],
    "name:ron_x_preferred":[
        "Ba\u0219tanka"
    ],
    "name:rum_x_preferred":[
        "Ba\u0219tanka"
    ],
    "name:rus_x_preferred":[
        "\u0411\u0430\u0448\u0442\u0430\u043d\u043a\u0430"
    ],
    "name:sco_x_preferred":[
        "Bashtanka"
    ],
    "name:tat_x_preferred":[
        "\u0411\u0430\u0448\u0442\u0430\u043d\u043a\u0430"
    ],
    "name:ukr_x_preferred":[
        "\u0411\u0430\u0448\u0442\u0430\u043d\u043a\u0430"
    ],
    "name:unk_x_variant":[
        "Bashtanka"
    ],
    "name:vie_x_preferred":[
        "Bashtanka"
    ],
    "name:zho_x_preferred":[
        "\u5df4\u4ec0\u5766\u5361"
    ],
    "qs:a0":"\u0423\u043a\u0440\u0430\u0457\u043d\u0430",
    "qs:a1":"*\u041c\u0438\u043a\u043e\u043b\u0430\u0457\u0432\u0441\u044c\u043a\u0430",
    "qs:a1_alt":"Mykolaivs'ka",
    "qs:a1r":"0",
    "qs:a2":"\u0411\u0430\u0448\u0442\u0430\u043d\u0441\u044c\u043a\u0438\u0439",
    "qs:a2_alt":"Bashtans'kyi",
    "qs:adm0":"\u0423\u043a\u0440\u0430\u0457\u043d\u0430",
    "qs:la_lc":"*",
    "qs:level":"locality",
    "qs:loc":"\u0411\u0430\u0448\u0442\u0430\u043d\u043a\u0430",
    "qs:loc_alt":"Bashtanka",
    "qs:pop":0,
    "qs:type":"buffered point",
    "wd:wordcount":88,
    "wof:name":"\u0411\u0430\u0448\u0442\u0430\u043d\u043a\u0430",
    "wof:placetype":"locality",
    "wof:population":12657
},
  "geometry": {"coordinates":[32.447432,47.396884],"type":"Point"}
}