{
  "type": "Feature",
  "properties": {
    "gn:population":9426,
    "iso:country":"UA",
    "name:bel_x_preferred":[
        "\u041b\u044e\u0431\u0430\u0448\u044b\u045e\u043a\u0430"
    ],
    "name:bel_x_variant":[
        "\u041b\u044e\u0431\u0430\u0448\u043e\u045e\u043a\u0430"
    ],
    "name:bul_x_preferred":[
        "\u041b\u044e\u0431\u0430\u0448\u0438\u0432\u043a\u0430"
    ],
    "name:ceb_x_preferred":[
        "Lyubashivka"
    ],
    "name:ces_x_preferred":[
        "Ljuba\u0161ivka"
    ],
    "name:crh_x_preferred":[
        "L\u00fcba\u015fivka"
    ],
    "name:deu_x_preferred":[
        "Ljubaschiwka"
    ],
    "name:eng_x_preferred":[
        "Liubashivka"
    ],
    "name:heb_x_preferred":[
        "\u05dc\u05d9\u05d5\u05d1\u05e9\u05d9\u05d1\u05e7\u05d4"
    ],
    "name:jpn_x_preferred":[
        "\u30ea\u30e5\u30d0\u30b7\u30e7\u30d5\u30ab"
    ],
    "name:lav_x_preferred":[
        "\u013buba\u0161ivka"
    ],
    "name:pol_x_preferred":[
        "Lubasziwka"
    ],
    "name:pol_x_variant":[
        "Liubasziwka"
    ],
    "name:ron_x_preferred":[
        "Liuba\u0219ivka"
    ],
    "name:rus_x_preferred":[
        "\u041b\u044e\u0431\u0430\u0448\u0451\u0432\u043a\u0430"
    ],
    "name:rus_x_variant":[
        "\u041b\u044e\u0431\u0430\u0448\u0456\u0432\u043a\u0430"
    ],
    "name:sah_x_preferred":[
        "\u041b\u044e\u0431\u0430\u0448\u0451\u0432\u043a\u0430"
    ],
    "name:spa_x_preferred":[
        "Liubashivka"
    ],
    "name:ukr_x_preferred":[
        "\u041b\u044e\u0431\u0430\u0448\u0456\u0432\u043a\u0430"
    ],
    "name:und_x_variant":[
        "Lyubash\u00ebvka"
    ],
    "name:zho_x_preferred":[
        "\u67f3\u5df4\u5e0c\u592b\u5361"
    ],
    "qs:a0":"\u0423\u043a\u0440\u0430\u0457\u043d\u0430",
    "qs:a1":"*\u041e\u0434\u0435\u0441\u044c\u043a\u0430",
    "qs:a1_alt":"Odes'ka",
    "qs:a1r":"0",
    "qs:a2":"\u041b\u044e\u0431\u0430\u0448\u0456\u0432\u0441\u044c\u043a\u0438\u0439",
    "qs:a2_alt":"Liubashivs'kyi",
    "qs:adm0":"\u0423\u043a\u0440\u0430\u0457\u043d\u0430",
    "qs:la_lc":"*",
    "qs:level":"locality",
    "qs:loc":"\u041b\u044e\u0431\u0430\u0448\u0456\u0432\u043a\u0430",
    "qs:loc_alt":"Liubashivka",
    "qs:pop":0,
    "qs:type":"buffered point",
    "wd:wordcount":308,
    "wof:name":"\u041b\u044e\u0431\u0430\u0448\u0456\u0432\u043a\u0430",
    "wof:placetype":"locality",
    "wof:population":9426
},
  "geometry": {"coordinates":[30.25491,47.831516],"type":"Point"}
}