{
  "type": "Feature",
  "properties": {
    "gn:admin1_code":"27.0",
    "gn:asciiname":"Nikonovka",
    "gn:country_code":"UA",
    "gn:dem":239,
    "gn:feature_class":"P",
    "gn:feature_code":"PPL",
    "gn:name":"Nikonovka",
    "gn:population":0,
    "gn:timezone":"Europe/Kiev",
    "iso:country":"UA",
    "name:ukr_x_preferred":[
        "Nykonivka"
    ],
    "name:ukr_x_variant":[
        "\u041d\u0438\u043a\u043e\u043d\u0456\u0432\u043a\u0430"
    ],
    "wof:name":"Nikonovka",
    "wof:placetype":"locality"
},
  "geometry": {"coordinates":[28.78498,49.99891],"type":"Point"}
}