{
  "type": "Feature",
  "properties": {
    "gn:admin1_code":"9.0",
    "gn:asciiname":"Tsmivka",
    "gn:country_code":"UA",
    "gn:dem":242,
    "gn:feature_class":"P",
    "gn:feature_code":"PPL",
    "gn:name":"Tsmivka",
    "gn:population":0,
    "gn:timezone":"Europe/Kiev",
    "iso:country":"UA",
    "name:ukr_x_preferred":[
        "Tsmivka"
    ],
    "name:ukr_x_variant":[
        "\u0426\u043c\u0456\u0432\u043a\u0430"
    ],
    "name:und_x_variant":[
        "Tsmovka"
    ],
    "wof:name":"Tsmivka",
    "wof:placetype":"locality"
},
  "geometry": {"coordinates":[27.3081,50.25619],"type":"Point"}
}