{
  "type": "Feature",
  "properties": {
    "gn:admin1_code":"19.0",
    "gn:asciiname":"Mantyn",
    "gn:country_code":"UA",
    "gn:dem":212,
    "gn:feature_class":"P",
    "gn:feature_code":"PPL",
    "gn:name":"Mantyn",
    "gn:population":0,
    "gn:timezone":"Europe/Kiev",
    "iso:country":"UA",
    "name:ukr_x_preferred":[
        "Mantyn"
    ],
    "name:ukr_x_variant":[
        "\u041c\u0430\u043d\u0442\u0438\u043d"
    ],
    "wof:name":"Mantyn",
    "wof:placetype":"locality"
},
  "geometry": {"coordinates":[25.59956,50.53213],"type":"Point"}
}