{
  "type": "Feature",
  "properties": {
    "gn:admin1_code":"2.0",
    "gn:asciiname":"Mochalyshche",
    "gn:country_code":"UA",
    "gn:dem":116,
    "gn:feature_class":"P",
    "gn:feature_code":"PPL",
    "gn:name":"Mochalyshche",
    "gn:population":0,
    "gn:timezone":"Europe/Kiev",
    "iso:country":"UA",
    "name:ukr_x_preferred":[
        "Mochalyshche"
    ],
    "name:ukr_x_variant":[
        "\u041c\u043e\u0447\u0430\u043b\u0438\u0449\u0435"
    ],
    "name:und_x_variant":[
        "Mochalishche"
    ],
    "wof:name":"Mochalyshche",
    "wof:placetype":"locality"
},
  "geometry": {"coordinates":[31.3237,50.56641],"type":"Point"}
}