{
  "type": "Feature",
  "properties": {
    "gn:admin1_code":"2.0",
    "gn:asciiname":"Mochalyshche",
    "gn:country_code":"UA",
    "gn:dem":116,
    "gn:feature_class":"P",
    "gn:feature_code":"PPL",
    "gn:name":"Mochalyshche",
    "gn:population":0,
    "gn:timezone":"Europe/Kiev",
    "iso:country":"UA",
    "name:bel_x_preferred":[
        "\u041c\u0430\u0447\u0430\u043b\u044b\u0448\u0447\u044d"
    ],
    "name:hye_x_preferred":[
        "\u0544\u0578\u0579\u0561\u056c\u056b\u0577\u0579\u0565"
    ],
    "name:ron_x_preferred":[
        "Moceal\u00ee\u0219ce"
    ],
    "name:rus_x_preferred":[
        "\u041c\u043e\u0447\u0430\u043b\u0438\u0449\u0435"
    ],
    "name:ukr_x_preferred":[
        "Mochalyshche"
    ],
    "name:ukr_x_variant":[
        "\u041c\u043e\u0447\u0430\u043b\u0438\u0449\u0435"
    ],
    "name:und_x_variant":[
        "Mochalishche"
    ],
    "name:zho_x_preferred":[
        "\u83ab\u6070\u5229\u8b1d"
    ],
    "wof:name":"Mochalyshche",
    "wof:placetype":"locality"
},
  "geometry": {"coordinates":[31.3237,50.56641],"type":"Point"}
}