{
  "type": "Feature",
  "properties": {
    "gn:admin1_code":"21.0",
    "gn:asciiname":"Papkyne",
    "gn:country_code":"UA",
    "gn:dem":143,
    "gn:feature_class":"P",
    "gn:feature_code":"PPL",
    "gn:name":"Papkyne",
    "gn:population":0,
    "gn:timezone":"Europe/Kiev",
    "iso:country":"UA",
    "name:ukr_x_preferred":[
        "Papkyne"
    ],
    "name:ukr_x_variant":[
        "\u041f\u0430\u043f\u043a\u0438\u043d\u0435"
    ],
    "name:und_x_variant":[
        "Papkino"
    ],
    "wof:name":"Papkyne",
    "wof:placetype":"locality"
},
  "geometry": {"coordinates":[33.51617,51.58231],"type":"Point"}
}