{
  "type": "Feature",
  "properties": {
    "iso:country":"UA",
    "name:deu_x_preferred":[
        "Nowopetriwka"
    ],
    "name:eng_x_preferred":[
        "Novopetrivka"
    ],
    "name:hye_x_preferred":[
        "\u0546\u0578\u057e\u0578\u057a\u0565\u057f\u0580\u0578\u057e\u056f\u0561"
    ],
    "name:lav_x_preferred":[
        "Novopetrivka"
    ],
    "name:ron_x_preferred":[
        "Novopetrivka"
    ],
    "name:rus_x_preferred":[
        "\u041d\u043e\u0432\u043e\u043f\u0435\u0442\u0440\u043e\u0432\u043a\u0430"
    ],
    "name:ukr_x_preferred":[
        "\u041d\u043e\u0432\u043e\u043f\u0435\u0442\u0440\u0456\u0432\u043a\u0430"
    ],
    "name:und_x_variant":[
        "Pyetrovskoye"
    ],
    "name:zho_x_preferred":[
        "\u65b0\u4f69\u7279\u91cc\u592b\u5361"
    ],
    "qs:a0":"\u0423\u043a\u0440\u0430\u0457\u043d\u0430",
    "qs:a1":"*\u0417\u0430\u043f\u043e\u0440\u0456\u0437\u044c\u043a\u0430",
    "qs:a1_alt":"Zaporiz'ka",
    "qs:a1r":"0",
    "qs:a2":"\u0411\u0435\u0440\u0434\u044f\u043d\u0441\u044c\u043a\u0438\u0439",
    "qs:a2_alt":"Berdians'kyi",
    "qs:adm0":"\u0423\u043a\u0440\u0430\u0457\u043d\u0430",
    "qs:la_lc":"*",
    "qs:level":"locality",
    "qs:loc":"\u041d\u043e\u0432\u043e\u043f\u0435\u0442\u0440\u0456\u0432\u043a\u0430",
    "qs:loc_alt":"Novopetrivka",
    "qs:pop":0,
    "qs:type":"buffered point",
    "wof:name":"\u041d\u043e\u0432\u043e\u043f\u0435\u0442\u0440\u0456\u0432\u043a\u0430",
    "wof:placetype":"locality"
},
  "geometry": {"coordinates":[36.867688,46.836385],"type":"Point"}
}