{
  "type": "Feature",
  "properties": {
    "gn:admin1_code":"7.0",
    "gn:asciiname":"Pody",
    "gn:country_code":"UA",
    "gn:dem":91,
    "gn:feature_class":"P",
    "gn:feature_code":"PPL",
    "gn:name":"Pody",
    "gn:population":0,
    "gn:timezone":"Europe/Kiev",
    "iso:country":"UA",
    "name:che_x_preferred":[
        "\u041f\u043e\u0434\u0438"
    ],
    "name:rus_x_preferred":[
        "\u041f\u043e\u0434\u044b"
    ],
    "name:tgk_x_preferred":[
        "\u041f\u043e\u0434\u0438"
    ],
    "name:ukr_x_preferred":[
        "Pody"
    ],
    "name:ukr_x_variant":[
        "\u041f\u043e\u0434\u0438"
    ],
    "wof:name":"Pody",
    "wof:placetype":"locality"
},
  "geometry": {"coordinates":[36.5644,49.82609],"type":"Point"}
}