{
  "type": "Feature",
  "properties": {
    "gn:admin1_code":"27.0",
    "gn:asciiname":"Morohivka",
    "gn:country_code":"UA",
    "gn:dem":174,
    "gn:feature_class":"P",
    "gn:feature_code":"PPL",
    "gn:name":"Morohivka",
    "gn:population":0,
    "gn:timezone":"Europe/Kiev",
    "iso:country":"UA",
    "name:ukr_x_preferred":[
        "Morohivka"
    ],
    "name:ukr_x_variant":[
        "\u041c\u043e\u0440\u043e\u0433\u0456\u0432\u043a\u0430"
    ],
    "name:und_x_variant":[
        "Morogovka"
    ],
    "wof:name":"Morohivka",
    "wof:placetype":"locality"
},
  "geometry": {"coordinates":[29.1048,50.64932],"type":"Point"}
}