{
  "type": "Feature",
  "properties": {
    "gn:admin1_code":"09",
    "gn:asciiname":"Novodubyshche",
    "gn:country_code":"UA",
    "gn:dem":314,
    "gn:feature_class":"P",
    "gn:feature_code":"PPL",
    "gn:name":"Novodubyshche",
    "gn:population":0,
    "gn:timezone":"Europe/Kiev",
    "iso:country":"UA",
    "name:ukr_x_preferred":[
        "Novodubyshche"
    ],
    "name:ukr_x_variant":[
        "\u041d\u043e\u0432\u043e\u0434\u0443\u0431\u0438\u0449\u0435"
    ],
    "wof:name":"Novodubyshche",
    "wof:placetype":"locality"
},
  "geometry": {"coordinates":[26.86329000000001,49.71838],"type":"Point"}
}