{
  "type": "Feature",
  "properties": {
    "gn:admin1_code":"8.0",
    "gn:asciiname":"Naddnipryans'ke",
    "gn:country_code":"UA",
    "gn:dem":49,
    "gn:feature_class":"P",
    "gn:feature_code":"PPL",
    "gn:name":"Naddnipryans\u2019ke",
    "gn:population":0,
    "gn:timezone":"Europe/Kiev",
    "iso:country":"UA",
    "name:ukr_x_preferred":[
        "Naddnipryans\u2019ke"
    ],
    "name:ukr_x_variant":[
        "\u041d\u0430\u0434\u0434\u043d\u0456\u043f\u0440\u044f\u043d\u0441\u044c\u043a\u0435"
    ],
    "name:und_x_variant":[
        "Naddnepryanskoye"
    ],
    "wof:name":"Naddnipryans'ke",
    "wof:placetype":"locality"
},
  "geometry": {"coordinates":[32.70821,46.74786],"type":"Point"}
}