{
  "type": "Feature",
  "properties": {
    "gn:admin1_code":"5.0",
    "gn:asciiname":"Merlinka",
    "gn:cc2":"UA",
    "gn:country_code":"UA",
    "gn:dem":27,
    "gn:feature_class":"P",
    "gn:feature_code":"PPL",
    "gn:name":"Merlinka",
    "gn:population":0,
    "gn:timezone":"Europe/Zaporozhye",
    "iso:country":"UA",
    "name:und_x_variant":[
        "Merlika",
        "Merlinka"
    ],
    "wof:name":"Merlinka",
    "wof:placetype":"locality"
},
  "geometry": {"coordinates":[36.72972,46.78833],"type":"Point"}
}