{
  "type": "Feature",
  "properties": {
    "gn:admin1_code":"27.0",
    "gn:asciiname":"Zahreblya",
    "gn:country_code":"UA",
    "gn:dem":158,
    "gn:feature_class":"P",
    "gn:feature_code":"PPL",
    "gn:name":"Zahreblya",
    "gn:population":0,
    "gn:timezone":"Europe/Kiev",
    "iso:country":"UA",
    "name:ukr_x_preferred":[
        "Zahreblya"
    ],
    "name:ukr_x_variant":[
        "\u0417\u0430\u0433\u0440\u0435\u0431\u043b\u044f"
    ],
    "name:und_x_variant":[
        "Zagreblya"
    ],
    "wof:name":"Zahreblya",
    "wof:placetype":"locality"
},
  "geometry": {"coordinates":[28.97777,50.80161],"type":"Point"}
}