{
  "type": "Feature",
  "properties": {
    "gn:admin1_code":"2.0",
    "gn:asciiname":"Lovyn'",
    "gn:country_code":"UA",
    "gn:dem":134,
    "gn:feature_class":"P",
    "gn:feature_code":"PPL",
    "gn:name":"Lovyn\u2019",
    "gn:population":0,
    "gn:timezone":"Europe/Kiev",
    "iso:country":"UA",
    "name:eng_x_preferred":[
        "Lovyn'"
    ],
    "name:rus_x_preferred":[
        "\u041b\u043e\u0432\u044b\u043d\u044c"
    ],
    "name:ukr_x_preferred":[
        "Lovyn\u2019"
    ],
    "name:ukr_x_variant":[
        "\u041b\u043e\u0432\u0438\u043d\u044c"
    ],
    "name:und_x_variant":[
        "Lovin\u2019",
        "Lovyn\u2019"
    ],
    "wof:name":"Lovyn'",
    "wof:placetype":"locality"
},
  "geometry": {"coordinates":[31.18673,51.8886],"type":"Point"}
}