{
  "type": "Feature",
  "properties": {
    "gn:admin1_code":"14.0",
    "gn:asciiname":"Podgornoye",
    "gn:country_code":"UA",
    "gn:dem":91,
    "gn:feature_class":"P",
    "gn:feature_code":"PPL",
    "gn:name":"Podgornoye",
    "gn:population":0,
    "gn:timezone":"Europe/Zaporozhye",
    "iso:country":"UA",
    "name:che_x_preferred":[
        "\u041f\u043e\u0434\u0433\u043e\u0440\u043d\u0438"
    ],
    "name:rus_x_preferred":[
        "\u041f\u043e\u0434\u0433\u043e\u0440\u043d\u043e\u0435"
    ],
    "name:tat_x_preferred":[
        "\u041f\u043e\u0434\u0433\u043e\u0440\u043d\u043e\u0435"
    ],
    "name:ukr_x_preferred":[
        "\u041f\u0456\u0434\u0433\u0456\u0440\u043d\u0435"
    ],
    "wof:name":"Podgornoye",
    "wof:placetype":"locality"
},
  "geometry": {"coordinates":[39.19722,48.60083],"type":"Point"}
}