{
  "type": "Feature",
  "properties": {
    "gn:admin1_code":"9.0",
    "gn:asciiname":"Pecheski",
    "gn:country_code":"UA",
    "gn:dem":342,
    "gn:feature_class":"P",
    "gn:feature_code":"PPL",
    "gn:name":"Pecheski",
    "gn:population":0,
    "gn:timezone":"Europe/Kiev",
    "iso:country":"UA",
    "name:und_x_variant":[
        "Pechiski",
        "Pecheski"
    ],
    "wof:name":"Pecheski",
    "wof:placetype":"locality"
},
  "geometry": {"coordinates":[27.10014,49.52759],"type":"Point"}
}