{
  "type": "Feature",
  "properties": {
    "gn:admin1_code":"7.0",
    "gn:asciiname":"Sukhyy Yar",
    "gn:country_code":"UA",
    "gn:dem":169,
    "gn:feature_class":"P",
    "gn:feature_code":"PPL",
    "gn:name":"Sukhyy Yar",
    "gn:population":0,
    "gn:timezone":"Europe/Kiev",
    "iso:country":"UA",
    "name:ukr_x_preferred":[
        "Sukhyy Yar"
    ],
    "name:und_x_variant":[
        "Sukhoy Yar"
    ],
    "wof:name":"Sukhyy Yar",
    "wof:placetype":"locality"
},
  "geometry": {"coordinates":[37.31056,49.49194],"type":"Point"}
}