{
  "type": "Feature",
  "properties": {
    "gn:admin1_code":"5.0",
    "gn:admin2_code":"11886883",
    "gn:asciiname":"Yampolivka",
    "gn:country_code":"UA",
    "gn:dem":79,
    "gn:feature_class":"P",
    "gn:feature_code":"PPL",
    "gn:name":"Yampolivka",
    "gn:population":0,
    "gn:timezone":"Europe/Kiev",
    "iso:country":"UA",
    "name:rus_x_preferred":[
        "Yampolovka"
    ],
    "name:rus_x_variant":[
        "\u042f\u043c\u043f\u043e\u043b\u043e\u0432\u043a\u0430"
    ],
    "name:ukr_x_preferred":[
        "\u042f\u043c\u043f\u043e\u043b\u0456\u0432\u043a\u0430"
    ],
    "name:ukr_x_variant":[
        "Yampolivka"
    ],
    "wof:name":"Yampolivka",
    "wof:placetype":"locality"
},
  "geometry": {"coordinates":[37.95826,49.07077],"type":"Point"}
}