{
  "type": "Feature",
  "properties": {
    "gn:admin1_code":"4.0",
    "gn:asciiname":"Novohryhorivka",
    "gn:country_code":"UA",
    "gn:dem":91,
    "gn:feature_class":"P",
    "gn:feature_code":"PPL",
    "gn:name":"Novohryhorivka",
    "gn:population":0,
    "gn:timezone":"Europe/Kiev",
    "iso:country":"UA",
    "name:ukr_x_preferred":[
        "Novohryhorivka"
    ],
    "name:ukr_x_variant":[
        "\u041d\u043e\u0432\u043e\u0433\u0440\u0438\u0433\u043e\u0440\u0456\u0432\u043a\u0430"
    ],
    "name:und_x_variant":[
        "Novaya Grigor\u2019yevka",
        "Novo-Grigor\u2019yevka",
        "Novogrigorovka"
    ],
    "wof:name":"Novohryhorivka",
    "wof:placetype":"locality"
},
  "geometry": {"coordinates":[36.64027,48.43221],"type":"Point"}
}