{
  "type": "Feature",
  "properties": {
    "gn:admin1_code":"15.0",
    "gn:asciiname":"Shtukovets'",
    "gn:country_code":"UA",
    "gn:dem":612,
    "gn:feature_class":"P",
    "gn:feature_code":"PPL",
    "gn:name":"Shtukovets\u2019",
    "gn:population":0,
    "gn:timezone":"Europe/Kiev",
    "iso:country":"UA",
    "name:ukr_x_preferred":[
        "Shtukovets\u2019"
    ],
    "name:ukr_x_variant":[
        "\u0428\u0442\u0443\u043a\u043e\u0432\u0435\u0446\u044c"
    ],
    "wof:name":"Shtukovets'",
    "wof:placetype":"locality"
},
  "geometry": {"coordinates":[23.03392,49.05543],"type":"Point"}
}