{
  "type": "Feature",
  "properties": {
    "gn:admin1_code":"22.0",
    "gn:asciiname":"Veshkhnyakovtse",
    "gn:country_code":"UA",
    "gn:dem":211,
    "gn:feature_class":"P",
    "gn:feature_code":"PPL",
    "gn:name":"Veshkhnyakovtse",
    "gn:population":0,
    "gn:timezone":"Europe/Kiev",
    "iso:country":"UA",
    "name:und_x_variant":[
        "Vierhniakovtsy",
        "Wierzchniakowce",
        "Vishnyakovtsy",
        "Veshkhnyakovtse"
    ],
    "wof:name":"Veshkhnyakovtse",
    "wof:placetype":"locality"
},
  "geometry": {"coordinates":[26.00124,48.81436],"type":"Point"}
}