{
  "type": "Feature",
  "properties": {
    "gn:admin1_code":"7.0",
    "gn:asciiname":"Krasne",
    "gn:country_code":"UA",
    "gn:dem":191,
    "gn:feature_class":"P",
    "gn:feature_code":"PPL",
    "gn:name":"Krasne",
    "gn:population":0,
    "gn:timezone":"Europe/Kiev",
    "iso:country":"UA",
    "name:ukr_x_preferred":[
        "Krasne"
    ],
    "name:ukr_x_variant":[
        "\u041a\u0440\u0430\u0441\u043d\u0435"
    ],
    "name:und_x_variant":[
        "Krasny",
        "Krasnoye",
        "Krasnyy"
    ],
    "wof:name":"Krasne",
    "wof:placetype":"locality"
},
  "geometry": {"coordinates":[36.45585,50.28508],"type":"Point"}
}