{
  "type": "Feature",
  "properties": {
    "gn:admin1_code":"7.0",
    "gn:asciiname":"Krasne",
    "gn:country_code":"UA",
    "gn:dem":191,
    "gn:feature_class":"P",
    "gn:feature_code":"PPL",
    "gn:name":"Krasne",
    "gn:population":0,
    "gn:timezone":"Europe/Kiev",
    "iso:country":"UA",
    "name:ceb_x_preferred":[
        "Krasne"
    ],
    "name:deu_x_preferred":[
        "Krasne"
    ],
    "name:est_x_preferred":[
        "Krasne"
    ],
    "name:fra_x_preferred":[
        "Krasne"
    ],
    "name:ita_x_preferred":[
        "Krasne"
    ],
    "name:jpn_x_preferred":[
        "\u30af\u30e9\u30fc\u30b9\u30cd"
    ],
    "name:lit_x_preferred":[
        "Krasn\u0117"
    ],
    "name:nld_x_preferred":[
        "Krasne"
    ],
    "name:pol_x_preferred":[
        "Krasne"
    ],
    "name:spa_x_preferred":[
        "Krasne"
    ],
    "name:srp_x_preferred":[
        "\u041a\u0440\u0430\u0441\u043d\u0435"
    ],
    "name:swe_x_preferred":[
        "Krasne"
    ],
    "name:ukr_x_preferred":[
        "Krasne"
    ],
    "name:ukr_x_variant":[
        "\u041a\u0440\u0430\u0441\u043d\u0435"
    ],
    "name:und_x_variant":[
        "Krasny",
        "Krasnoye",
        "Krasnyy"
    ],
    "name:zho_x_preferred":[
        "\u514b\u62c9\u65af\u5185"
    ],
    "wof:name":"Krasne",
    "wof:placetype":"locality"
},
  "geometry": {"coordinates":[36.45585,50.28508],"type":"Point"}
}