{
  "type": "Feature",
  "properties": {
    "iso:country":"UA",
    "name:deu_x_preferred":[
        "Dobropillja"
    ],
    "name:eng_x_preferred":[
        "Dobropillia"
    ],
    "name:lav_x_preferred":[
        "Dobropi\u013c\u013ca"
    ],
    "name:ron_x_preferred":[
        "Dobropillea"
    ],
    "name:rus_x_preferred":[
        "\u0414\u043e\u0431\u0440\u043e\u043f\u0456\u043b\u043b\u044f"
    ],
    "name:rus_x_variant":[
        "\u0414\u043e\u0431\u0440\u043e\u043f\u043e\u043b\u044c\u0435"
    ],
    "name:ukr_x_preferred":[
        "\u0414\u043e\u0431\u0440\u043e\u043f\u0456\u043b\u043b\u044f"
    ],
    "name:unk_x_variant":[
        "Dobropillya"
    ],
    "name:zho_x_preferred":[
        "\u591a\u5e03\u7f85\u76ae\u723e\u5229\u4e9e"
    ],
    "qs:a0":"\u0423\u043a\u0440\u0430\u0457\u043d\u0430",
    "qs:a1":"*\u0425\u0435\u0440\u0441\u043e\u043d\u0441\u044c\u043a\u0430",
    "qs:a1_alt":"Khersons'ka",
    "qs:a1r":"0",
    "qs:a2":"\u0413\u043e\u043b\u043e\u043f\u0440\u0438\u0441\u0442\u0430\u043d\u0441\u044c\u043a\u0438\u0439",
    "qs:a2_alt":"Holoprystans'kyi",
    "qs:adm0":"\u0423\u043a\u0440\u0430\u0457\u043d\u0430",
    "qs:la_lc":"*",
    "qs:level":"locality",
    "qs:loc":"\u0414\u043e\u0431\u0440\u043e\u043f\u0456\u043b\u043b\u044f",
    "qs:loc_alt":"Dobropillia",
    "qs:pop":0,
    "qs:type":"buffered point",
    "wd:wordcount":117,
    "wof:name":"\u0414\u043e\u0431\u0440\u043e\u043f\u0456\u043b\u043b\u044f",
    "wof:placetype":"locality"
},
  "geometry": {"coordinates":[32.579319,46.237443],"type":"Point"}
}