{
  "type": "Feature",
  "properties": {
    "iso:country":"UA",
    "name:ukr_x_preferred":[
        "\u0412\u0430\u0441\u0438\u043b\u0456\u0432\u043a\u0430"
    ],
    "name:und_x_variant":[
        "Vasil\u2019yevka"
    ],
    "qs:a0":"\u0423\u043a\u0440\u0430\u0457\u043d\u0430",
    "qs:a1":"*\u0414\u043e\u043d\u0435\u0446\u044c\u043a\u0430",
    "qs:a1_alt":"Donets'ka",
    "qs:a1r":"0",
    "qs:a2":"\u0421\u0442\u0430\u0440\u043e\u0431\u0435\u0448\u0456\u0432\u0441\u044c\u043a\u0438\u0439",
    "qs:a2_alt":"Starobeshivs'kyi",
    "qs:adm0":"\u0423\u043a\u0440\u0430\u0457\u043d\u0430",
    "qs:la_lc":"*",
    "qs:level":"locality",
    "qs:loc":"\u0412\u0430\u0441\u0438\u043b\u0456\u0432\u043a\u0430",
    "qs:loc_alt":"Vasylivka",
    "qs:pop":0,
    "qs:type":"buffered point",
    "wd:wordcount":146,
    "wof:name":"\u0412\u0430\u0441\u0438\u043b\u0456\u0432\u043a\u0430",
    "wof:placetype":"locality"
},
  "geometry": {"coordinates":[38.022416,47.594243],"type":"Point"}
}