{
  "type": "Feature",
  "properties": {
    "gn:admin1_code":"26.0",
    "gn:asciiname":"Novoivanivka",
    "gn:country_code":"UA",
    "gn:dem":84,
    "gn:feature_class":"P",
    "gn:feature_code":"PPL",
    "gn:name":"Novoivanivka",
    "gn:population":0,
    "gn:timezone":"Europe/Zaporozhye",
    "iso:country":"UA",
    "name:ukr_x_preferred":[
        "\u041d\u043e\u0432\u043e\u0456\u0432\u0430\u043d\u0456\u0432\u043a\u0430"
    ],
    "name:und_x_variant":[
        "Novaya Ivanovka",
        "Novoivanovka",
        "Novoivanivka"
    ],
    "wof:name":"Novoivanivka",
    "wof:placetype":"locality"
},
  "geometry": {"coordinates":[35.64554000000001,47.79849],"type":"Point"}
}