{
  "type": "Feature",
  "properties": {
    "gn:admin1_code":"23.0",
    "gn:asciiname":"Kalytynka",
    "gn:country_code":"UA",
    "gn:dem":239,
    "gn:feature_class":"P",
    "gn:feature_code":"PPL",
    "gn:name":"Kalytynka",
    "gn:population":0,
    "gn:timezone":"Europe/Kiev",
    "iso:country":"UA",
    "name:ukr_x_preferred":[
        "\u041a\u0430\u043b\u0438\u0442\u0438\u043d\u043a\u0430"
    ],
    "name:und_x_variant":[
        "Kalitinka"
    ],
    "wof:name":"Kalytynka",
    "wof:placetype":"locality"
},
  "geometry": {"coordinates":[28.25441,48.62754],"type":"Point"}
}