{
  "type": "Feature",
  "properties": {
    "gn:admin1_code":"16.0",
    "gn:asciiname":"Petrovka",
    "gn:country_code":"UA",
    "gn:dem":14,
    "gn:feature_class":"P",
    "gn:feature_code":"PPL",
    "gn:name":"Petrovka",
    "gn:population":0,
    "gn:timezone":"Europe/Kiev",
    "iso:country":"UA",
    "wof:name":"Petrovka",
    "wof:placetype":"locality"
},
  "geometry": {"coordinates":[31.32485,47.34683],"type":"Point"}
}