{
  "type": "Feature",
  "properties": {
    "gn:admin1_code":"7.0",
    "gn:asciiname":"Hvozd'ove",
    "gn:country_code":"UA",
    "gn:dem":128,
    "gn:feature_class":"P",
    "gn:feature_code":"PPL",
    "gn:name":"Hvozd\u2019ove",
    "gn:population":0,
    "gn:timezone":"Europe/Kiev",
    "iso:country":"UA",
    "name:ukr_x_preferred":[
        "Hvozd\u2019ove"
    ],
    "name:ukr_x_variant":[
        "\u0413\u0432\u043e\u0437\u0434\u044c\u043e\u0432\u0435"
    ],
    "wof:name":"Hvozd'ove",
    "wof:placetype":"locality"
},
  "geometry": {"coordinates":[35.36646,49.88945],"type":"Point"}
}