{
  "type": "Feature",
  "properties": {
    "gn:admin1_code":"08",
    "gn:asciiname":"Novovasylivka",
    "gn:country_code":"UA",
    "gn:dem":12,
    "gn:feature_class":"P",
    "gn:feature_code":"PPL",
    "gn:name":"Novovasylivka",
    "gn:population":0,
    "gn:timezone":"Europe/Kiev",
    "iso:country":"UA",
    "name:ukr_x_preferred":[
        "Novovasylivka"
    ],
    "name:ukr_x_variant":[
        "\u041d\u043e\u0432\u043e\u0432\u0430\u0441\u0438\u043b\u0456\u0432\u043a\u0430"
    ],
    "wof:name":"Novovasylivka",
    "wof:placetype":"locality"
},
  "geometry": {"coordinates":[32.80893,47.00308],"type":"Point"}
}