{
  "type": "Feature",
  "properties": {
    "gn:admin1_code":"24.0",
    "gn:asciiname":"Budy Ossovske",
    "gn:cc2":"UA",
    "gn:country_code":"UA",
    "gn:dem":201,
    "gn:feature_class":"P",
    "gn:feature_code":"PPL",
    "gn:name":"Budy Ossovske",
    "gn:population":0,
    "gn:timezone":"Europe/Kiev",
    "iso:country":"UA",
    "name:und_x_variant":[
        "Ossowskie Budy",
        "Budy Ossowskie",
        "Budy Ossovske"
    ],
    "wof:name":"Budy Ossovske",
    "wof:placetype":"locality"
},
  "geometry": {"coordinates":[24.56667,50.95],"type":"Point"}
}