{
  "type": "Feature",
  "properties": {
    "gn:admin1_code":"3.0",
    "gn:asciiname":"Petrouts",
    "gn:cc2":"UA",
    "gn:country_code":"UA",
    "gn:dem":389,
    "gn:feature_class":"P",
    "gn:feature_code":"PPL",
    "gn:name":"Petrouts",
    "gn:population":0,
    "gn:timezone":"Europe/Kiev",
    "iso:country":"UA",
    "name:und_x_variant":[
        "Petrovtsy",
        "Petrouts"
    ],
    "wof:name":"Petrouts",
    "wof:placetype":"locality"
},
  "geometry": {"coordinates":[25.71667,48.03333],"type":"Point"}
}