{
  "type": "Feature",
  "properties": {
    "gn:admin1_code":"11.0",
    "gn:admin2_code":"694905",
    "gn:admin3_code":"11153097",
    "gn:asciiname":"Abrikosovka",
    "gn:country_code":"UA",
    "gn:dem":34,
    "gn:elevation":"33.0",
    "gn:feature_class":"P",
    "gn:feature_code":"PPL",
    "gn:name":"Abrikosovka",
    "gn:population":506,
    "gn:timezone":"Europe/Simferopol",
    "iso:country":"UA",
    "name:eng_x_preferred":[
        "Abrikosovka"
    ],
    "name:rus_x_historical":[
        "\u0423\u043d\u0433\u0443\u0301\u0442"
    ],
    "name:rus_x_preferred":[
        "\u0410\u0431\u0440\u0438\u043a\u043e\u0441\u043e\u0432\u043a\u0430"
    ],
    "name:rus_x_variant":[
        "\u0423\u043d\u0433\u0443\u0301\u0442"
    ],
    "name:ukr_x_preferred":[
        "\u0410\u0431\u0440\u0438\u043a\u043e\u0441\u0456\u0432\u043a\u0430"
    ],
    "wof:name":"Abrikosovka",
    "wof:placetype":"locality",
    "wof:population":506
},
  "geometry": {"coordinates":[33.19125,45.27058],"type":"Point"}
}