{
  "type": "Feature",
  "properties": {
    "gn:admin1_code":"18.0",
    "gn:asciiname":"Zabaryany",
    "gn:country_code":"UA",
    "gn:dem":92,
    "gn:feature_class":"P",
    "gn:feature_code":"PPL",
    "gn:name":"Zabaryany",
    "gn:population":0,
    "gn:timezone":"Europe/Kiev",
    "iso:country":"UA",
    "name:ukr_x_preferred":[
        "Zabaryany"
    ],
    "name:ukr_x_variant":[
        "\u0417\u0430\u0431\u0430\u0440\u044f\u043d\u0438"
    ],
    "wof:name":"Zabaryany",
    "wof:placetype":"locality"
},
  "geometry": {"coordinates":[34.66295,49.69232],"type":"Point"}
}