{
  "type": "Feature",
  "properties": {
    "gn:admin1_code":"17.0",
    "gn:asciiname":"Davydivka",
    "gn:country_code":"UA",
    "gn:dem":80,
    "gn:feature_class":"P",
    "gn:feature_code":"PPL",
    "gn:name":"Davydivka",
    "gn:population":0,
    "gn:timezone":"Europe/Kiev",
    "iso:country":"UA",
    "name:ukr_x_preferred":[
        "Davydivka"
    ],
    "name:ukr_x_variant":[
        "\u0414\u0430\u0432\u0438\u0434\u0456\u0432\u043a\u0430"
    ],
    "name:und_x_variant":[
        "Davydovka"
    ],
    "wof:name":"Davydivka",
    "wof:placetype":"locality"
},
  "geometry": {"coordinates":[29.72609000000001,47.41214],"type":"Point"}
}