{
  "type": "Feature",
  "properties": {
    "gn:admin1_code":"25.0",
    "gn:asciiname":"Vuchkove",
    "gn:country_code":"UA",
    "gn:dem":360,
    "gn:feature_class":"P",
    "gn:feature_code":"PPL",
    "gn:name":"Vuchkove",
    "gn:population":0,
    "gn:timezone":"Europe/Uzhgorod",
    "iso:country":"UA",
    "name:hun_x_preferred":[
        "Vucsk\u00f3mez\u0151"
    ],
    "name:ukr_x_preferred":[
        "\u0412\u0443\u0447\u043a\u043e\u0432\u0435"
    ],
    "name:und_x_variant":[
        "Vichkovo",
        "Vu\u010dkovo",
        "Vuchkove",
        "Vuchkovo",
        "Vuchkovoye"
    ],
    "wof:name":"Vuchkove",
    "wof:placetype":"locality"
},
  "geometry": {"coordinates":[23.53843,48.44949],"type":"Point"}
}