{
  "type": "Feature",
  "properties": {
    "gn:admin1_code":"24.0",
    "gn:asciiname":"Rudka-Kozyns'ka",
    "gn:country_code":"UA",
    "gn:dem":187,
    "gn:feature_class":"P",
    "gn:feature_code":"PPL",
    "gn:name":"Rudka-Kozyns\u2019ka",
    "gn:population":0,
    "gn:timezone":"Europe/Kiev",
    "iso:country":"UA",
    "name:ukr_x_preferred":[
        "Rudka-Kozyns\u2019ka"
    ],
    "name:ukr_x_variant":[
        "\u0420\u0443\u0434\u043a\u0430-\u041a\u043e\u0437\u0438\u043d\u0441\u044c\u043a\u0430"
    ],
    "name:und_x_variant":[
        "Rudka Kozinska",
        "Rudka-Kozinskaya"
    ],
    "wof:name":"Rudka-Kozyns'ka",
    "wof:placetype":"locality"
},
  "geometry": {"coordinates":[25.16216,50.93609],"type":"Point"}
}