{
  "type": "Feature",
  "properties": {
    "gn:population":7211,
    "iso:country":"UA",
    "name:eng_x_preferred":[
        "Mala Danylivka"
    ],
    "name:rus_x_preferred":[
        "\u041c\u0430\u043b.\u0414\u0430\u043d\u0438\u043b\u043e\u0432\u043a\u0430"
    ],
    "name:rus_x_variant":[
        "\u041c\u0430\u043b\u0430 \u0414\u0430\u043d\u0438\u043b\u0456\u0432\u043a\u0430"
    ],
    "name:ukr_x_preferred":[
        "\u041c\u0430\u043b\u0430 \u0414\u0430\u043d\u0438\u043b\u0456\u0432\u043a\u0430"
    ],
    "name:ukr_x_variant":[
        "Mala Danylivka"
    ],
    "name:und_x_variant":[
        "Malaya Danilovka"
    ],
    "qs:a0":"\u0423\u043a\u0440\u0430\u0457\u043d\u0430",
    "qs:a1":"*\u0425\u0430\u0440\u043a\u0456\u0432\u0441\u044c\u043a\u0430",
    "qs:a1_alt":"Kharkivs'ka",
    "qs:a1r":"0",
    "qs:a2":"\u0425\u0430\u0440\u043a\u0456\u0432\u0441\u044c\u043a\u0438\u0439",
    "qs:a2_alt":"Kharkivs'kyi",
    "qs:adm0":"\u0423\u043a\u0440\u0430\u0457\u043d\u0430",
    "qs:la_lc":"*",
    "qs:level":"locality",
    "qs:loc":"\u041c\u0430\u043b\u0430 \u0414\u0430\u043d\u0438\u043b\u0456\u0432\u043a\u0430",
    "qs:loc_alt":"Mala Danylivka",
    "qs:pop":0,
    "qs:type":"buffered point",
    "wof:name":"\u041c\u0430\u043b\u0430 \u0414\u0430\u043d\u0438\u043b\u0456\u0432\u043a\u0430",
    "wof:placetype":"locality",
    "wof:population":7211
},
  "geometry": {"coordinates":[36.179229,50.050008],"type":"Point"}
}