{
  "type": "Feature",
  "properties": {
    "iso:country":"UA",
    "name:deu_x_preferred":[
        "Tyssowez"
    ],
    "name:eng_x_preferred":[
        "Tysovets"
    ],
    "name:hye_x_preferred":[
        "\u054f\u056b\u057d\u0578\u057e\u0565\u0581"
    ],
    "name:pol_x_preferred":[
        "Tysowiec"
    ],
    "name:ron_x_preferred":[
        "T\u00eesove\u021b"
    ],
    "name:ron_x_variant":[
        "Ti\u0219\u0103u\u021bi"
    ],
    "name:rus_x_preferred":[
        "\u0422\u0438\u0441\u043e\u0432\u0435\u0446"
    ],
    "name:ukr_x_preferred":[
        "\u0422\u0438\u0441\u043e\u0432\u0435\u0446\u044c"
    ],
    "qs:a0":"\u0423\u043a\u0440\u0430\u0457\u043d\u0430",
    "qs:a1":"*\u0427\u0435\u0440\u043d\u0456\u0432\u0435\u0446\u044c\u043a\u0430",
    "qs:a1_alt":"Chernivets'ka",
    "qs:a1r":"0",
    "qs:a2":"\u0421\u0442\u043e\u0440\u043e\u0436\u0438\u043d\u0435\u0446\u044c\u043a\u0438\u0439",
    "qs:a2_alt":"Storozhynets'kyi",
    "qs:adm0":"\u0423\u043a\u0440\u0430\u0457\u043d\u0430",
    "qs:la_lc":"*",
    "qs:level":"locality",
    "qs:loc":"\u0422\u0438\u0441\u043e\u0432\u0435\u0446\u044c",
    "qs:loc_alt":"Tysovets",
    "qs:pop":0,
    "qs:type":"buffered point",
    "wd:wordcount":52,
    "wof:name":"\u0422\u0438\u0441\u043e\u0432\u0435\u0446\u044c",
    "wof:placetype":"locality"
},
  "geometry": {"coordinates":[25.912604,48.159722],"type":"Point"}
}