{
  "type": "Feature",
  "properties": {
    "gn:admin1_code":"17.0",
    "gn:asciiname":"Novo-Aleksandrovka",
    "gn:country_code":"UA",
    "gn:dem":100,
    "gn:feature_class":"P",
    "gn:feature_code":"PPL",
    "gn:name":"Novo-Aleksandrovka",
    "gn:population":0,
    "gn:timezone":"Europe/Kiev",
    "iso:country":"UA",
    "name:und_x_variant":[
        "Borshchevko",
        "Novo-Aleksandrovka"
    ],
    "wof:name":"Novo-Aleksandrovka",
    "wof:placetype":"locality"
},
  "geometry": {"coordinates":[30.03986,47.54002],"type":"Point"}
}