{
  "type": "Feature",
  "properties": {
    "gn:admin1_code":"7.0",
    "gn:asciiname":"Sosonivka",
    "gn:country_code":"UA",
    "gn:dem":176,
    "gn:feature_class":"P",
    "gn:feature_code":"PPL",
    "gn:name":"Sosonivka",
    "gn:population":0,
    "gn:timezone":"Europe/Kiev",
    "iso:country":"UA",
    "name:ukr_x_preferred":[
        "Sosonivka"
    ],
    "name:ukr_x_variant":[
        "\u0421\u043e\u0441\u043e\u043d\u0456\u0432\u043a\u0430"
    ],
    "wof:name":"Sosonivka",
    "wof:placetype":"locality"
},
  "geometry": {"coordinates":[35.8832,49.63884],"type":"Point"}
}