{
  "type": "Feature",
  "properties": {
    "iso:country":"UA",
    "name:deu_x_preferred":[
        "Stawne"
    ],
    "name:eng_x_preferred":[
        "Stavne"
    ],
    "name:epo_x_preferred":[
        "Stavne"
    ],
    "name:gsw_x_preferred":[
        "Stawne"
    ],
    "name:hun_x_preferred":[
        "Sztavna"
    ],
    "name:hun_x_variant":[
        "Fenyvesv\u00f6lgy"
    ],
    "name:hye_x_preferred":[
        "\u054d\u057f\u0561\u057e\u0576\u0578\u0565"
    ],
    "name:nld_x_preferred":[
        "Stavne"
    ],
    "name:ron_x_preferred":[
        "Stavne"
    ],
    "name:rus_x_preferred":[
        "\u0421\u0442\u0430\u0432\u043d\u043e\u0435"
    ],
    "name:ukr_x_preferred":[
        "\u0421\u0442\u0430\u0432\u043d\u0435"
    ],
    "name:unk_x_variant":[
        "Stavna"
    ],
    "name:zho_x_preferred":[
        "\u65af\u5854\u592b\u6d85"
    ],
    "qs:a0":"\u0423\u043a\u0440\u0430\u0457\u043d\u0430",
    "qs:a1":"*\u0417\u0430\u043a\u0430\u0440\u043f\u0430\u0442\u0441\u044c\u043a\u0430",
    "qs:a1_alt":"Zakarpats'ka",
    "qs:a1r":"0",
    "qs:a2":"\u0412\u0435\u043b\u0438\u043a\u043e\u0431\u0435\u0440\u0435\u0437\u043d\u044f\u043d\u0441\u044c\u043a\u0438\u0439",
    "qs:a2_alt":"Velykobereznians'kyi",
    "qs:adm0":"\u0423\u043a\u0440\u0430\u0457\u043d\u0430",
    "qs:la_lc":"*",
    "qs:level":"locality",
    "qs:loc":"\u0421\u0442\u0430\u0432\u043d\u0435",
    "qs:loc_alt":"Stavne",
    "qs:pop":0,
    "qs:type":"buffered point",
    "wof:name":"\u0421\u0442\u0430\u0432\u043d\u0435",
    "wof:placetype":"locality"
},
  "geometry": {"coordinates":[22.708632,48.992257],"type":"Point"}
}