{
  "type": "Feature",
  "properties": {
    "gn:admin1_code":"16.0",
    "gn:asciiname":"Maloukrainka",
    "gn:country_code":"UA",
    "gn:dem":104,
    "gn:feature_class":"P",
    "gn:feature_code":"PPL",
    "gn:name":"Maloukrainka",
    "gn:population":0,
    "gn:timezone":"Europe/Kiev",
    "iso:country":"UA",
    "name:und_x_variant":[
        "Plaksiyevka",
        "Maloukrainka"
    ],
    "wof:name":"Maloukrainka",
    "wof:placetype":"locality"
},
  "geometry": {"coordinates":[31.94909,47.67049],"type":"Point"}
}