{
  "type": "Feature",
  "properties": {
    "gn:admin1_code":"26.0",
    "gn:asciiname":"Karl-Marks",
    "gn:country_code":"UA",
    "gn:dem":138,
    "gn:feature_class":"P",
    "gn:feature_code":"PPL",
    "gn:name":"Karl-Marks",
    "gn:population":0,
    "gn:timezone":"Europe/Zaporozhye",
    "iso:country":"UA",
    "name:und_x_variant":[
        "Marksa",
        "Karl-Marks"
    ],
    "wof:name":"Karl-Marks",
    "wof:placetype":"locality"
},
  "geometry": {"coordinates":[35.74637,47.8948],"type":"Point"}
}