{
  "type": "Feature",
  "properties": {
    "gn:admin1_code":"19.0",
    "gn:asciiname":"Zoziv",
    "gn:country_code":"UA",
    "gn:dem":181,
    "gn:feature_class":"P",
    "gn:feature_code":"PPL",
    "gn:name":"Zoziv",
    "gn:population":0,
    "gn:timezone":"Europe/Kiev",
    "iso:country":"UA",
    "name:ukr_x_preferred":[
        "Zoziv"
    ],
    "name:ukr_x_variant":[
        "\u0417\u043e\u0437\u0456\u0432"
    ],
    "name:und_x_variant":[
        "Zozov"
    ],
    "wof:name":"Zoziv",
    "wof:placetype":"locality"
},
  "geometry": {"coordinates":[26.21103,50.67663],"type":"Point"}
}