{
  "type": "Feature",
  "properties": {
    "gn:admin1_code":"10.0",
    "gn:asciiname":"Razumovka",
    "gn:country_code":"UA",
    "gn:dem":161,
    "gn:feature_class":"P",
    "gn:feature_code":"PPL",
    "gn:name":"Razumovka",
    "gn:population":0,
    "gn:timezone":"Europe/Kiev",
    "iso:country":"UA",
    "name:und_x_variant":[
        "Yerazmovka",
        "Rozumivka",
        "Yerazmovka Rozumivka",
        "Razumovka"
    ],
    "wof:name":"Razumovka",
    "wof:placetype":"locality"
},
  "geometry": {"coordinates":[32.15101,48.83039],"type":"Point"}
}