{
  "type": "Feature",
  "properties": {
    "gn:admin1_code":"2.0",
    "gn:asciiname":"Studenets'",
    "gn:country_code":"UA",
    "gn:dem":138,
    "gn:feature_class":"P",
    "gn:feature_code":"PPL",
    "gn:name":"Studenets\u2019",
    "gn:population":0,
    "gn:timezone":"Europe/Kiev",
    "iso:country":"UA",
    "name:ukr_x_preferred":[
        "Studenets\u2019"
    ],
    "name:ukr_x_variant":[
        "\u0421\u0442\u0443\u0434\u0435\u043d\u0435\u0446\u044c"
    ],
    "name:und_x_variant":[
        "Studenets"
    ],
    "wof:name":"Studenets'",
    "wof:placetype":"locality"
},
  "geometry": {"coordinates":[31.45648,51.89989],"type":"Point"}
}