{
  "type": "Feature",
  "properties": {
    "gn:admin1_code":"7.0",
    "gn:asciiname":"Nakaznoye",
    "gn:cc2":"UA",
    "gn:country_code":"UA",
    "gn:dem":158,
    "gn:feature_class":"P",
    "gn:feature_code":"PPL",
    "gn:name":"Nakaznoye",
    "gn:population":0,
    "gn:timezone":"Europe/Kiev",
    "iso:country":"UA",
    "name:und_x_variant":[
        "Khutor Nakaznyye",
        "Nakaznoye"
    ],
    "wof:name":"Nakaznoye",
    "wof:placetype":"locality"
},
  "geometry": {"coordinates":[35.59444000000001,50.30556],"type":"Point"}
}