{
  "type": "Feature",
  "properties": {
    "gn:admin1_code":"8.0",
    "gn:asciiname":"Kozachi Laheri",
    "gn:country_code":"UA",
    "gn:dem":71,
    "gn:feature_class":"P",
    "gn:feature_code":"PPL",
    "gn:name":"Kozachi Laheri",
    "gn:population":0,
    "gn:timezone":"Europe/Kiev",
    "iso:country":"UA",
    "name:ukr_x_preferred":[
        "\u041a\u043e\u0437\u0430\u0447\u0456 \u041b\u0430\u0433\u0435\u0440\u0456"
    ],
    "name:und_x_variant":[
        "Kazach\u2019i Lageri",
        "Kazach\u2019i Lageri Pervyye",
        "Kozachi Laheri"
    ],
    "wof:name":"Kozachi Laheri",
    "wof:placetype":"locality"
},
  "geometry": {"coordinates":[34.0523,46.94733],"type":"Point"}
}