{
  "type": "Feature",
  "properties": {
    "gn:admin1_code":"8.0",
    "gn:asciiname":"Tomaryne",
    "gn:country_code":"UA",
    "gn:dem":48,
    "gn:feature_class":"P",
    "gn:feature_code":"PPL",
    "gn:name":"Tomaryne",
    "gn:population":0,
    "gn:timezone":"Europe/Kiev",
    "iso:country":"UA",
    "name:ukr_x_preferred":[
        "Tomaryne"
    ],
    "name:ukr_x_variant":[
        "\u0422\u043e\u043c\u0430\u0440\u0438\u043d\u0435"
    ],
    "wof:name":"Tomaryne",
    "wof:placetype":"locality"
},
  "geometry": {"coordinates":[33.3071,46.8773],"type":"Point"}
}