{
  "type": "Feature",
  "properties": {
    "gn:admin1_code":"21.0",
    "gn:asciiname":"Pershotravneve",
    "gn:country_code":"UA",
    "gn:dem":126,
    "gn:feature_class":"P",
    "gn:feature_code":"PPL",
    "gn:name":"Pershotravneve",
    "gn:population":0,
    "gn:timezone":"Europe/Kiev",
    "iso:country":"UA",
    "name:bel_x_preferred":[
        "\u041f\u044d\u0440\u0448\u0430\u0442\u0440\u0430\u045e\u043d\u044d\u0432\u044d"
    ],
    "name:ceb_x_preferred":[
        "Pershotravneve"
    ],
    "name:ces_x_preferred":[
        "Per\u0161otravneve"
    ],
    "name:crh_x_preferred":[
        "Per\u015fotravneve"
    ],
    "name:deu_x_preferred":[
        "Perschotrawnewe"
    ],
    "name:fra_x_preferred":[
        "Perchotravneve"
    ],
    "name:pol_x_preferred":[
        "Perszotrawnewe"
    ],
    "name:ron_x_preferred":[
        "Per\u0219otravneve"
    ],
    "name:rus_x_preferred":[
        "\u041f\u0435\u0440\u0448\u043e\u0442\u0440\u0430\u0432\u043d\u0435\u0432\u043e\u0435"
    ],
    "name:sah_x_preferred":[
        "\u041f\u0435\u0440\u0448\u043e\u0442\u0440\u0430\u0432\u043d\u0435\u0432\u043e\u0435"
    ],
    "name:ukr_x_preferred":[
        "Pershotravneve"
    ],
    "name:ukr_x_variant":[
        "\u041f\u0435\u0440\u0448\u043e\u0442\u0440\u0430\u0432\u043d\u0435\u0432\u0435"
    ],
    "name:und_x_variant":[
        "Pervomayskiy"
    ],
    "name:zho_x_preferred":[
        "\u4f69\u723e\u7d39\u7279\u62c9\u592b\u6d85\u97cb"
    ],
    "wof:name":"Pershotravneve",
    "wof:placetype":"locality"
},
  "geometry": {"coordinates":[34.92872,50.59302],"type":"Point"}
}