{
  "type": "Feature",
  "properties": {
    "gn:admin1_code":"22.0",
    "gn:asciiname":"Mushkaruv",
    "gn:country_code":"UA",
    "gn:dem":193,
    "gn:feature_class":"P",
    "gn:feature_code":"PPL",
    "gn:name":"Mushkaruv",
    "gn:population":0,
    "gn:timezone":"Europe/Kiev",
    "iso:country":"UA",
    "name:und_x_variant":[
        "Mushkarov",
        "Mushkaruv"
    ],
    "wof:name":"Mushkaruv",
    "wof:placetype":"locality"
},
  "geometry": {"coordinates":[25.82839,48.7871],"type":"Point"}
}