{
  "type": "Feature",
  "properties": {
    "gn:admin1_code":"5.0",
    "gn:asciiname":"Slyusarevo-Shurupovo",
    "gn:country_code":"UA",
    "gn:dem":75,
    "gn:feature_class":"P",
    "gn:feature_code":"PPL",
    "gn:name":"Slyusar\u00ebvo-Shurupovo",
    "gn:population":0,
    "gn:timezone":"Europe/Kiev",
    "iso:country":"UA",
    "wof:name":"Slyusarevo-Shurupovo",
    "wof:placetype":"locality"
},
  "geometry": {"coordinates":[38.26667,47.58333],"type":"Point"}
}