{
  "type": "Feature",
  "properties": {
    "gn:admin1_code":"21.0",
    "gn:asciiname":"Stanychne",
    "gn:country_code":"UA",
    "gn:dem":125,
    "gn:feature_class":"P",
    "gn:feature_code":"PPL",
    "gn:name":"Stanychne",
    "gn:population":0,
    "gn:timezone":"Europe/Kiev",
    "iso:country":"UA",
    "name:ukr_x_preferred":[
        "Stanychne"
    ],
    "name:ukr_x_variant":[
        "\u0421\u0442\u0430\u043d\u0438\u0447\u043d\u0435"
    ],
    "name:und_x_variant":[
        "Stanichnoye"
    ],
    "wof:name":"Stanychne",
    "wof:placetype":"locality"
},
  "geometry": {"coordinates":[35.37773,50.49575],"type":"Point"}
}