{
  "type": "Feature",
  "properties": {
    "gn:admin1_code":"5.0",
    "gn:asciiname":"Krasnyy Luch",
    "gn:country_code":"UA",
    "gn:dem":268,
    "gn:feature_class":"P",
    "gn:feature_code":"PPL",
    "gn:name":"Krasnyy Luch",
    "gn:population":0,
    "gn:timezone":"Europe/Kiev",
    "iso:country":"UA",
    "name:ukr_x_preferred":[
        "Krasnyy Luch"
    ],
    "name:ukr_x_variant":[
        "\u041a\u0440\u0430\u0441\u043d\u0438\u0439 \u041b\u0443\u0447"
    ],
    "wof:name":"Krasnyy Luch",
    "wof:placetype":"locality"
},
  "geometry": {"coordinates":[38.53192,48.12237],"type":"Point"}
}