{
  "type": "Feature",
  "properties": {
    "gn:admin1_code":"3.0",
    "gn:asciiname":"Ogrody",
    "gn:country_code":"UA",
    "gn:dem":888,
    "gn:feature_class":"P",
    "gn:feature_code":"PPL",
    "gn:name":"Ogrody",
    "gn:population":0,
    "gn:timezone":"Europe/Kiev",
    "iso:country":"UA",
    "name:und_x_variant":[
        "Ogorody",
        "Ogrody"
    ],
    "wof:name":"Ogrody",
    "wof:placetype":"locality"
},
  "geometry": {"coordinates":[24.93333,48.01667],"type":"Point"}
}