{
  "type": "Feature",
  "properties": {
    "gn:admin1_code":"18.0",
    "gn:asciiname":"Kramarenky",
    "gn:country_code":"UA",
    "gn:dem":69,
    "gn:feature_class":"P",
    "gn:feature_code":"PPL",
    "gn:name":"Kramarenky",
    "gn:population":0,
    "gn:timezone":"Europe/Kiev",
    "iso:country":"UA",
    "name:ukr_x_preferred":[
        "Kramarenky"
    ],
    "name:ukr_x_variant":[
        "\u041a\u0440\u0430\u043c\u0430\u0440\u0435\u043d\u043a\u0438"
    ],
    "wof:name":"Kramarenky",
    "wof:placetype":"locality"
},
  "geometry": {"coordinates":[33.60117,49.17922],"type":"Point"}
}