{
  "type": "Feature",
  "properties": {
    "gn:admin1_code":"9.0",
    "gn:asciiname":"Tashky",
    "gn:country_code":"UA",
    "gn:dem":215,
    "gn:feature_class":"P",
    "gn:feature_code":"PPL",
    "gn:name":"Tashky",
    "gn:population":0,
    "gn:timezone":"Europe/Kiev",
    "iso:country":"UA",
    "name:ukr_x_preferred":[
        "Tashky"
    ],
    "name:ukr_x_variant":[
        "\u0422\u0430\u0448\u043a\u0438"
    ],
    "name:und_x_variant":[
        "Tashki"
    ],
    "wof:name":"Tashky",
    "wof:placetype":"locality"
},
  "geometry": {"coordinates":[26.89549,50.25291],"type":"Point"}
}