{
  "type": "Feature",
  "properties": {
    "gn:admin1_code":"26.0",
    "gn:asciiname":"Yakobinskiy",
    "gn:country_code":"UA",
    "gn:dem":79,
    "gn:feature_class":"P",
    "gn:feature_code":"PPL",
    "gn:name":"Yakobinskiy",
    "gn:population":0,
    "gn:timezone":"Europe/Zaporozhye",
    "iso:country":"UA",
    "wof:name":"Yakobinskiy",
    "wof:placetype":"locality"
},
  "geometry": {"coordinates":[34.68333,47.01667],"type":"Point"}
}