{
  "type": "Feature",
  "properties": {
    "gn:admin1_code":"27.0",
    "gn:asciiname":"Dovhynychi",
    "gn:country_code":"UA",
    "gn:dem":191,
    "gn:feature_class":"P",
    "gn:feature_code":"PPL",
    "gn:name":"Dovhynychi",
    "gn:population":0,
    "gn:timezone":"Europe/Kiev",
    "iso:country":"UA",
    "name:ukr_x_preferred":[
        "Dovhynychi"
    ],
    "name:ukr_x_variant":[
        "\u0414\u043e\u0432\u0433\u0438\u043d\u0438\u0447\u0456"
    ],
    "name:und_x_variant":[
        "Dovginichi",
        "Dolginichi"
    ],
    "wof:name":"Dovhynychi",
    "wof:placetype":"locality"
},
  "geometry": {"coordinates":[28.66726,51.30229],"type":"Point"}
}