{
  "type": "Feature",
  "properties": {
    "gn:admin1_code":"18.0",
    "gn:asciiname":"Solokha",
    "gn:country_code":"UA",
    "gn:dem":167,
    "gn:feature_class":"P",
    "gn:feature_code":"PPL",
    "gn:name":"Solokha",
    "gn:population":0,
    "gn:timezone":"Europe/Kiev",
    "iso:country":"UA",
    "name:hun_x_preferred":[
        "Szoloha-kurg\u00e1n"
    ],
    "name:pol_x_preferred":[
        "So\u0142ocha"
    ],
    "name:rus_x_preferred":[
        "\u0421\u043e\u043b\u043e\u0445\u0430"
    ],
    "name:ukr_x_preferred":[
        "\u0421\u043e\u043b\u043e\u0445\u0430"
    ],
    "name:uzb_x_preferred":[
        "Soloxa"
    ],
    "wof:name":"Solokha",
    "wof:placetype":"locality"
},
  "geometry": {"coordinates":[34.33333,49.96667],"type":"Point"}
}