{
  "type": "Feature",
  "properties": {
    "gn:population":1984,
    "iso:country":"UA",
    "name:rus_x_preferred":[
        "\u0428\u0435\u0448\u043e\u0440\u044b"
    ],
    "name:ukr_x_preferred":[
        "\u0428\u0435\u0448\u043e\u0440\u0438"
    ],
    "name:und_x_variant":[
        "Sheshory"
    ],
    "qs:a0":"\u0423\u043a\u0440\u0430\u0457\u043d\u0430",
    "qs:a1":"*\u0406\u0432\u0430\u043d\u043e-\u0424\u0440\u0430\u043d\u043a\u0456\u0432\u0441\u044c\u043a\u0430",
    "qs:a1_alt":"Ivano-Frankivs'ka",
    "qs:a1r":"0",
    "qs:a2":"\u041a\u043e\u0441\u0456\u0432\u0441\u044c\u043a\u0438\u0439",
    "qs:a2_alt":"Kosivs'kyi",
    "qs:adm0":"\u0423\u043a\u0440\u0430\u0457\u043d\u0430",
    "qs:la_lc":"*",
    "qs:level":"locality",
    "qs:loc":"\u0428\u0435\u0448\u043e\u0440\u0438",
    "qs:loc_alt":"Sheshory",
    "qs:pop":0,
    "qs:type":"buffered point",
    "wof:name":"\u0428\u0435\u0448\u043e\u0440\u0438",
    "wof:placetype":"locality",
    "wof:population":1984
},
  "geometry": {"coordinates":[24.980242,48.332589],"type":"Point"}
}