{
  "type": "Feature",
  "properties": {
    "gn:admin1_code":"7.0",
    "gn:asciiname":"Donets'ke",
    "gn:country_code":"UA",
    "gn:dem":83,
    "gn:feature_class":"P",
    "gn:feature_code":"PPL",
    "gn:name":"Donets\u2019ke",
    "gn:population":0,
    "gn:timezone":"Europe/Kiev",
    "iso:country":"UA",
    "name:ukr_x_preferred":[
        "Donets\u2019ke"
    ],
    "name:und_x_variant":[
        "Donetskiy",
        "Donetskoye"
    ],
    "wof:name":"Donets'ke",
    "wof:placetype":"locality"
},
  "geometry": {"coordinates":[37.25473,49.14988],"type":"Point"}
}