{
  "type": "Feature",
  "properties": {
    "iso:country":"UA",
    "name:ara_x_preferred":[
        "\u0625\u0641\u062c\u064a\u0646\u064a \u0628\u0648\u0643\u064a\u062a"
    ],
    "name:arq_x_preferred":[
        "\u0625\u0641\u06a4\u064a\u0646\u064a \u0628\u0648\u0643\u064a\u062a"
    ],
    "name:eng_x_preferred":[
        "Yevgen Buket"
    ],
    "name:est_x_preferred":[
        "Jevgen Buket"
    ],
    "name:fra_x_preferred":[
        "Yevgen Buket"
    ],
    "name:mkd_x_preferred":[
        "\u0415\u0432\u0433\u0435\u043d\u0438\u0458 \u0411\u0443\u043a\u0435\u0442"
    ],
    "name:nld_x_preferred":[
        "Yevhen Buket"
    ],
    "name:pol_x_preferred":[
        "Eugeniusz Bukiet"
    ],
    "name:ron_x_preferred":[
        "Eugen Buchet"
    ],
    "name:rus_x_preferred":[
        "\u0411\u0443\u043a\u0435\u0442"
    ],
    "name:spa_x_preferred":[
        "Yevgen Buket"
    ],
    "name:sqi_x_preferred":[
        "Yevgen Buket"
    ],
    "qs:a0":"\u0423\u043a\u0440\u0430\u0457\u043d\u0430",
    "qs:a1":"*\u041a\u0456\u0440\u043e\u0432\u043e\u0433\u0440\u0430\u0434\u0441\u044c\u043a\u0430",
    "qs:a1_alt":"Kirovohrads'ka",
    "qs:a1r":"0",
    "qs:a2":"\u0413\u043e\u043b\u043e\u0432\u0430\u043d\u0456\u0432\u0441\u044c\u043a\u0438\u0439",
    "qs:a2_alt":"Holovanivs'kyi",
    "qs:adm0":"\u0423\u043a\u0440\u0430\u0457\u043d\u0430",
    "qs:la_lc":"*",
    "qs:level":"locality",
    "qs:loc":"\u0413\u0440\u0443\u0437\u044c\u043a\u0435",
    "qs:loc_alt":"Hruz'ke",
    "qs:pop":0,
    "qs:type":"buffered point",
    "wd:wordcount":636,
    "wof:name":"\u0413\u0440\u0443\u0437\u044c\u043a\u0435",
    "wof:placetype":"locality"
},
  "geometry": {"coordinates":[30.401453,48.442013],"type":"Point"}
}