{
  "type": "Feature",
  "properties": {
    "gn:admin1_code":"21.0",
    "gn:asciiname":"Strilets'ka Pushkarka",
    "gn:country_code":"UA",
    "gn:dem":143,
    "gn:feature_class":"P",
    "gn:feature_code":"PPL",
    "gn:name":"Strilets\u2019ka Pushkarka",
    "gn:population":0,
    "gn:timezone":"Europe/Kiev",
    "iso:country":"UA",
    "name:ukr_x_preferred":[
        "Strilets\u2019ka Pushkarka"
    ],
    "name:ukr_x_variant":[
        "\u0421\u0442\u0440\u0456\u043b\u0435\u0446\u044c\u043a\u0430 \u041f\u0443\u0448\u043a\u0430\u0440\u043a\u0430"
    ],
    "name:und_x_variant":[
        "Streletskaya"
    ],
    "wof:name":"Strilets'ka Pushkarka",
    "wof:placetype":"locality"
},
  "geometry": {"coordinates":[35.43111,50.43972],"type":"Point"}
}