{
  "type": "Feature",
  "properties": {
    "gn:admin1_code":"2.0",
    "gn:asciiname":"Korshaky",
    "gn:country_code":"UA",
    "gn:dem":117,
    "gn:feature_class":"P",
    "gn:feature_code":"PPL",
    "gn:name":"Korshaky",
    "gn:population":0,
    "gn:timezone":"Europe/Kiev",
    "iso:country":"UA",
    "name:ukr_x_preferred":[
        "Korshaky"
    ],
    "name:ukr_x_variant":[
        "\u041a\u043e\u0440\u0448\u0430\u043a\u0438"
    ],
    "name:und_x_variant":[
        "Korshaki"
    ],
    "wof:name":"Korshaky",
    "wof:placetype":"locality"
},
  "geometry": {"coordinates":[32.20429,50.80852],"type":"Point"}
}