{
  "type": "Feature",
  "properties": {
    "gn:admin1_code":"17.0",
    "gn:asciiname":"Tamarovka",
    "gn:cc2":"UA",
    "gn:country_code":"UA",
    "gn:dem":130,
    "gn:feature_class":"P",
    "gn:feature_code":"PPL",
    "gn:name":"Tamarovka",
    "gn:population":0,
    "gn:timezone":"Europe/Kiev",
    "iso:country":"UA",
    "name:und_x_variant":[
        "Tamarivka",
        "Tamarovka"
    ],
    "wof:name":"Tamarovka",
    "wof:placetype":"locality"
},
  "geometry": {"coordinates":[30.08333,46.78333],"type":"Point"}
}