{
  "type": "Feature",
  "properties": {
    "gn:admin1_code":"4.0",
    "gn:asciiname":"Emmes",
    "gn:country_code":"UA",
    "gn:dem":82,
    "gn:feature_class":"P",
    "gn:feature_code":"PPL",
    "gn:name":"Emmes",
    "gn:population":0,
    "gn:timezone":"Europe/Kiev",
    "iso:country":"UA",
    "wof:name":"Emmes",
    "wof:placetype":"locality"
},
  "geometry": {"coordinates":[33.68333,47.86667],"type":"Point"}
}