{
  "type": "Feature",
  "properties": {
    "gn:admin1_code":"27.0",
    "gn:asciiname":"Mali Kosharyshcha",
    "gn:country_code":"UA",
    "gn:dem":175,
    "gn:feature_class":"P",
    "gn:feature_code":"PPL",
    "gn:name":"Mali Kosharyshcha",
    "gn:population":0,
    "gn:timezone":"Europe/Kiev",
    "iso:country":"UA",
    "name:ukr_x_preferred":[
        "Mali Kosharyshcha"
    ],
    "name:ukr_x_variant":[
        "\u041c\u0430\u043b\u0456 \u041a\u043e\u0448\u0430\u0440\u0438\u0449\u0430"
    ],
    "name:und_x_variant":[
        "Kosharishcha",
        "Kosharishche",
        "Malyye Kosharishcha"
    ],
    "wof:name":"Mali Kosharyshcha",
    "wof:placetype":"locality"
},
  "geometry": {"coordinates":[28.88721,50.27056],"type":"Point"}
}