{
  "type": "Feature",
  "properties": {
    "gn:admin1_code":"18.0",
    "gn:asciiname":"Pustovary",
    "gn:country_code":"UA",
    "gn:dem":89,
    "gn:feature_class":"P",
    "gn:feature_code":"PPL",
    "gn:name":"Pustovary",
    "gn:population":0,
    "gn:timezone":"Europe/Kiev",
    "iso:country":"UA",
    "name:ukr_x_preferred":[
        "Pustovary"
    ],
    "name:ukr_x_variant":[
        "\u041f\u0443\u0441\u0442\u043e\u0432\u0430\u0440\u0438"
    ],
    "wof:name":"Pustovary",
    "wof:placetype":"locality"
},
  "geometry": {"coordinates":[34.1757,49.54213],"type":"Point"}
}