{
  "type": "Feature",
  "properties": {
    "iso:country":"UA",
    "name:rus_x_preferred":[
        "\u041d\u0438\u0432\u043a\u0438"
    ],
    "name:ukr_x_preferred":[
        "\u041d\u0438\u0432\u043a\u0438"
    ],
    "wof:name":"Nyvky",
    "wof:placetype":"neighbourhood"
},
  "geometry": {"coordinates":[30.40984319214146,50.46899341609748],"type":"Point"}
}