{
  "type": "Feature",
  "properties": {
    "gn:admin1_code":"27.0",
    "gn:asciiname":"Osykove",
    "gn:country_code":"UA",
    "gn:dem":267,
    "gn:feature_class":"P",
    "gn:feature_code":"PPL",
    "gn:name":"Osykove",
    "gn:population":0,
    "gn:timezone":"Europe/Kiev",
    "iso:country":"UA",
    "name:ukr_x_preferred":[
        "Osykove"
    ],
    "name:ukr_x_variant":[
        "\u041e\u0441\u0438\u043a\u043e\u0432\u0435"
    ],
    "name:und_x_variant":[
        "Osykova"
    ],
    "wof:name":"Osykove",
    "wof:placetype":"locality"
},
  "geometry": {"coordinates":[28.61541,49.96783],"type":"Point"}
}