{
  "type": "Feature",
  "properties": {
    "gn:admin1_code":"23.0",
    "gn:asciiname":"Gushchintsy",
    "gn:country_code":"UA",
    "gn:dem":247,
    "gn:feature_class":"P",
    "gn:feature_code":"PPL",
    "gn:name":"Gushchintsy",
    "gn:population":0,
    "gn:timezone":"Europe/Kiev",
    "iso:country":"UA",
    "wof:name":"Gushchintsy",
    "wof:placetype":"locality"
},
  "geometry": {"coordinates":[28.34988,49.45172],"type":"Point"}
}