{
  "type": "Feature",
  "properties": {
    "gn:admin1_code":"15.0",
    "gn:asciiname":"Donbrova",
    "gn:cc2":"UA",
    "gn:country_code":"UA",
    "gn:dem":201,
    "gn:feature_class":"P",
    "gn:feature_code":"PPL",
    "gn:name":"Donbrova",
    "gn:population":0,
    "gn:timezone":"Europe/Kiev",
    "iso:country":"UA",
    "name:und_x_variant":[
        "D\u0105browa",
        "Donbrova"
    ],
    "wof:name":"Donbrova",
    "wof:placetype":"locality"
},
  "geometry": {"coordinates":[24.78333,50.33333],"type":"Point"}
}