{
  "type": "Feature",
  "properties": {
    "gn:admin1_code":"17.0",
    "gn:asciiname":"Balkovka",
    "gn:country_code":"UA",
    "gn:dem":11,
    "gn:feature_class":"P",
    "gn:feature_code":"PPL",
    "gn:name":"Balkovka",
    "gn:population":0,
    "gn:timezone":"Europe/Kiev",
    "iso:country":"UA",
    "name:und_x_variant":[
        "Russkaya Sloboda",
        "Balkovka"
    ],
    "wof:name":"Balkovka",
    "wof:placetype":"locality"
},
  "geometry": {"coordinates":[30.5978,46.84904],"type":"Point"}
}