{
  "type": "Feature",
  "properties": {
    "gn:admin1_code":"18.0",
    "gn:asciiname":"Breusivka",
    "gn:country_code":"UA",
    "gn:dem":98,
    "gn:feature_class":"P",
    "gn:feature_code":"PPL",
    "gn:name":"Breusivka",
    "gn:population":0,
    "gn:timezone":"Europe/Kiev",
    "iso:country":"UA",
    "name:eng_x_preferred":[
        "Breusovka"
    ],
    "name:rus_x_preferred":[
        "\u0411\u0440\u0435\u0443\u0441\u043e\u0432\u043a\u0430"
    ],
    "name:ukr_x_preferred":[
        "Breusivka"
    ],
    "name:ukr_x_variant":[
        "\u0411\u0440\u0435\u0443\u0441\u0456\u0432\u043a\u0430"
    ],
    "name:und_x_variant":[
        "Breusovka"
    ],
    "wof:name":"Breusivka",
    "wof:placetype":"locality"
},
  "geometry": {"coordinates":[34.00433,49.14581],"type":"Point"}
}