{
  "type": "Feature",
  "properties": {
    "iso:country":"UA",
    "name:bel_x_preferred":[
        "\u0421\u0430\u043c\u0430\u0441\u0451\u043b\u044b"
    ],
    "name:bul_x_preferred":[
        "\u0421\u0430\u043c\u043e\u0441\u0435\u043b\u0438"
    ],
    "name:cat_x_preferred":[
        "Samosely"
    ],
    "name:ces_x_preferred":[
        "Samosely"
    ],
    "name:deu_x_preferred":[
        "Samosely"
    ],
    "name:eng_x_preferred":[
        "Lubyanka"
    ],
    "name:eng_x_variant":[
        "Samosely"
    ],
    "name:jpn_x_preferred":[
        "\u30b5\u30de\u30b7\u30e7\u30fc\u30eb"
    ],
    "name:por_x_preferred":[
        "Samosely"
    ],
    "name:rus_x_preferred":[
        "\u041b\u0443\u0431\u044f\u043d\u043a\u0430"
    ],
    "name:rus_x_variant":[
        "\u0421\u0430\u043c\u043e\u0441\u0451\u043b\u044b"
    ],
    "name:spa_x_preferred":[
        "Samosely"
    ],
    "name:srp_x_preferred":[
        "\u0421\u0430\u043c\u043e\u0441\u0435\u043b\u0438"
    ],
    "name:ukr_x_preferred":[
        "Lub\u201dyanka"
    ],
    "name:ukr_x_variant":[
        "\u041b\u0443\u0431\u2019\u044f\u043d\u043a\u0430"
    ],
    "name:unk_x_variant":[
        "Lubyanka"
    ],
    "qs:a0":"\u0423\u043a\u0440\u0430\u0457\u043d\u0430",
    "qs:a1":"*\u041a\u0438\u0457\u0432\u0441\u044c\u043a\u0430",
    "qs:a1_alt":"Kyivs'ka",
    "qs:a1r":"0",
    "qs:a2":"\u0411\u043e\u0440\u043e\u0434\u044f\u043d\u0441\u044c\u043a\u0438\u0439",
    "qs:a2_alt":"Borodians'kyi",
    "qs:adm0":"\u0423\u043a\u0440\u0430\u0457\u043d\u0430",
    "qs:la_lc":"*",
    "qs:level":"locality",
    "qs:loc":"\u041b\u0443\u0431'\u044f\u043d\u043a\u0430",
    "qs:loc_alt":"Lubianka",
    "qs:pop":0,
    "qs:type":"buffered point",
    "wd:wordcount":567,
    "wof:name":"\u041b\u0443\u0431'\u044f\u043d\u043a\u0430",
    "wof:placetype":"locality"
},
  "geometry": {"coordinates":[30.168908,50.642735],"type":"Point"}
}