{
  "type": "Feature",
  "properties": {
    "gn:admin1_code":"19.0",
    "gn:asciiname":"Mochulky",
    "gn:country_code":"UA",
    "gn:dem":175,
    "gn:feature_class":"P",
    "gn:feature_code":"PPL",
    "gn:name":"Mochulky",
    "gn:population":0,
    "gn:timezone":"Europe/Kiev",
    "iso:country":"UA",
    "name:ukr_x_preferred":[
        "Mochulky"
    ],
    "name:ukr_x_variant":[
        "\u041c\u043e\u0447\u0443\u043b\u043a\u0438"
    ],
    "name:und_x_variant":[
        "Mochulki"
    ],
    "wof:name":"Mochulky",
    "wof:placetype":"locality"
},
  "geometry": {"coordinates":[25.96328,50.82216],"type":"Point"}
}