{
  "type": "Feature",
  "properties": {
    "gn:admin1_code":"6.0",
    "gn:asciiname":"Boyky",
    "gn:country_code":"UA",
    "gn:dem":603,
    "gn:feature_class":"P",
    "gn:feature_code":"PPL",
    "gn:name":"Boyky",
    "gn:population":0,
    "gn:timezone":"Europe/Kiev",
    "iso:country":"UA",
    "name:ukr_x_preferred":[
        "Boyky"
    ],
    "name:ukr_x_variant":[
        "\u0411\u043e\u0439\u043a\u0438"
    ],
    "name:und_x_variant":[
        "Boyki"
    ],
    "wof:name":"Boyky",
    "wof:placetype":"locality"
},
  "geometry": {"coordinates":[24.34522,48.62893],"type":"Point"}
}