{
  "type": "Feature",
  "properties": {
    "gn:admin1_code":"26.0",
    "gn:asciiname":"Zelena Dibrova",
    "gn:country_code":"UA",
    "gn:dem":112,
    "gn:feature_class":"P",
    "gn:feature_code":"PPL",
    "gn:name":"Zelena Dibrova",
    "gn:population":0,
    "gn:timezone":"Europe/Zaporozhye",
    "iso:country":"UA",
    "name:ukr_x_preferred":[
        "\u0417\u0435\u043b\u0435\u043d\u0430 \u0414\u0456\u0431\u0440\u043e\u0432\u0430"
    ],
    "name:und_x_variant":[
        "Zel\u00ebnaya Dubrova"
    ],
    "wof:name":"Zelena Dibrova",
    "wof:placetype":"locality"
},
  "geometry": {"coordinates":[35.96017,47.84103],"type":"Point"}
}