{
  "type": "Feature",
  "properties": {
    "gn:admin1_code":"11.0",
    "gn:admin2_code":"704383",
    "gn:admin3_code":"11152907.0",
    "gn:asciiname":"Krasnodarka",
    "gn:country_code":"UA",
    "gn:dem":27,
    "gn:elevation":"25.0",
    "gn:feature_class":"P",
    "gn:feature_code":"PPL",
    "gn:name":"Krasnodarka",
    "gn:population":422,
    "gn:timezone":"Europe/Simferopol",
    "iso:country":"UA",
    "name:eng_x_preferred":[
        "Krasnodarka"
    ],
    "name:rus_x_preferred":[
        "\u041a\u0440\u0430\u0441\u043d\u043e\u0434\u0430\u0440\u043a\u0430"
    ],
    "name:ukr_x_preferred":[
        "\u041a\u0440\u0430\u0441\u043d\u043e\u0434\u0430\u0440\u043a\u0430"
    ],
    "name:und_x_variant":[
        "Konchi-Shavva"
    ],
    "wof:name":"Krasnodarka",
    "wof:placetype":"locality",
    "wof:population":422
},
  "geometry": {"coordinates":[34.08393,45.60617],"type":"Point"}
}