{
  "type": "Feature",
  "properties": {
    "gn:admin1_code":"7.0",
    "gn:asciiname":"Sadki",
    "gn:country_code":"UA",
    "gn:dem":181,
    "gn:feature_class":"P",
    "gn:feature_code":"PPL",
    "gn:name":"Sadki",
    "gn:population":0,
    "gn:timezone":"Europe/Kiev",
    "iso:country":"UA",
    "name:ceb_x_preferred":[
        "Sadki"
    ],
    "name:nld_x_preferred":[
        "Sadki"
    ],
    "name:pol_x_preferred":[
        "Sadki"
    ],
    "name:ukr_x_preferred":[
        "\u0421\u0430\u0434\u043a\u0456"
    ],
    "wof:name":"Sadki",
    "wof:placetype":"locality"
},
  "geometry": {"coordinates":[36.73199,49.2894],"type":"Point"}
}