{
  "type": "Feature",
  "properties": {
    "gn:admin1_code":"5.0",
    "gn:asciiname":"Nelipivka",
    "gn:country_code":"UA",
    "gn:dem":115,
    "gn:feature_class":"P",
    "gn:feature_code":"PPL",
    "gn:name":"Nelipivka",
    "gn:population":0,
    "gn:timezone":"Europe/Kiev",
    "iso:country":"UA",
    "name:ukr_x_preferred":[
        "Nelipivka"
    ],
    "name:ukr_x_variant":[
        "\u041d\u0435\u043b\u0456\u043f\u0456\u0432\u043a\u0430"
    ],
    "name:und_x_variant":[
        "Nelepovka"
    ],
    "wof:name":"Nelipivka",
    "wof:placetype":"locality"
},
  "geometry": {"coordinates":[37.83451,48.3534],"type":"Point"}
}