{
  "type": "Feature",
  "properties": {
    "gn:admin1_code":"11.0",
    "gn:admin2_code":"712585",
    "gn:admin3_code":"11152840.0",
    "gn:asciiname":"Annovka",
    "gn:country_code":"UA",
    "gn:dem":89,
    "gn:elevation":"85.0",
    "gn:feature_class":"P",
    "gn:feature_code":"PPL",
    "gn:name":"Annovka",
    "gn:population":294,
    "gn:timezone":"Europe/Simferopol",
    "iso:country":"UA",
    "name:eng_x_preferred":[
        "Annovka"
    ],
    "name:rus_x_historical":[
        "\u0410\u043b\u0435\u0432\u043a\u0435\u0301"
    ],
    "name:rus_x_preferred":[
        "\u0410\u043d\u043d\u043e\u0432\u043a\u0430"
    ],
    "name:rus_x_variant":[
        "\u0410\u043b\u0435\u0432\u043a\u0435\u0301"
    ],
    "name:ukr_x_preferred":[
        "\u0410\u043d\u043d\u0456\u0432\u043a\u0430"
    ],
    "wof:name":"Annovka",
    "wof:placetype":"locality",
    "wof:population":294
},
  "geometry": {"coordinates":[34.30387,45.25605],"type":"Point"}
}