{
  "type": "Feature",
  "properties": {
    "iso:country":"UA",
    "name:eng_x_preferred":[
        "Kovpyn Stavok"
    ],
    "name:pol_x_preferred":[
        "Ko\u0142pin"
    ],
    "name:ron_x_preferred":[
        "Kovp\u00een Stavok"
    ],
    "name:rus_x_preferred":[
        "\u041a\u043e\u043b\u043f\u0438\u043d \u0421\u0442\u0430\u0432\u043e\u043a"
    ],
    "name:ukr_x_preferred":[
        "\u041a\u043e\u0432\u043f\u0438\u043d \u0421\u0442\u0430\u0432\u043e\u043a"
    ],
    "name:ukr_x_variant":[
        "Stavok",
        "\u0421\u0442\u0430\u0432\u043e\u043a"
    ],
    "name:zho_x_preferred":[
        "\u79d1\u592b\u6797\u65af\u5854\u6c83\u514b"
    ],
    "qs:a0":"\u0423\u043a\u0440\u0430\u0457\u043d\u0430",
    "qs:a1":"*\u0420\u0456\u0432\u043d\u0435\u043d\u0441\u044c\u043a\u0430",
    "qs:a1_alt":"Rivnens'ka",
    "qs:a1r":"0",
    "qs:a2":"\u041a\u043e\u0441\u0442\u043e\u043f\u0456\u043b\u044c\u0441\u044c\u043a\u0438\u0439",
    "qs:a2_alt":"Kostopil's'kyi",
    "qs:adm0":"\u0423\u043a\u0440\u0430\u0457\u043d\u0430",
    "qs:la_lc":"*",
    "qs:level":"locality",
    "qs:loc":"\u0421\u0442\u0430\u0432\u043e\u043a",
    "qs:loc_alt":"Stavok",
    "qs:pop":0,
    "qs:type":"buffered point",
    "wd:wordcount":51,
    "wof:name":"\u0421\u0442\u0430\u0432\u043e\u043a",
    "wof:placetype":"locality"
},
  "geometry": {"coordinates":[26.197841,50.912458],"type":"Point"}
}