{
  "type": "Feature",
  "properties": {
    "gn:admin1_code":"7.0",
    "gn:asciiname":"Illichivka",
    "gn:country_code":"UA",
    "gn:dem":182,
    "gn:feature_class":"P",
    "gn:feature_code":"PPL",
    "gn:name":"Illichivka",
    "gn:population":0,
    "gn:timezone":"Europe/Kiev",
    "iso:country":"UA",
    "name:rus_x_preferred":[
        "Il\u2019ichovka"
    ],
    "name:ukr_x_preferred":[
        "Illichivka"
    ],
    "name:ukr_x_variant":[
        "\u0406\u043b\u043b\u0456\u0447\u0456\u0432\u043a\u0430"
    ],
    "wof:name":"Illichivka",
    "wof:placetype":"locality"
},
  "geometry": {"coordinates":[37.07202,48.98354000000001],"type":"Point"}
}