{
  "type": "Feature",
  "properties": {
    "gn:admin1_code":"21.0",
    "gn:asciiname":"Dudchenky",
    "gn:country_code":"UA",
    "gn:dem":149,
    "gn:feature_class":"P",
    "gn:feature_code":"PPL",
    "gn:name":"Dudchenky",
    "gn:population":0,
    "gn:timezone":"Europe/Kiev",
    "iso:country":"UA",
    "name:ukr_x_preferred":[
        "Dudchenky"
    ],
    "name:ukr_x_variant":[
        "\u0414\u0443\u0434\u0447\u0435\u043d\u043a\u0438"
    ],
    "name:und_x_variant":[
        "Dudchenkov",
        "Dudchenkov Khutor",
        "Dudchenki"
    ],
    "wof:name":"Dudchenky",
    "wof:placetype":"locality"
},
  "geometry": {"coordinates":[34.31942,51.06485],"type":"Point"}
}