{
  "type": "Feature",
  "properties": {
    "gn:admin1_code":"24.0",
    "gn:asciiname":"Motashivka",
    "gn:country_code":"UA",
    "gn:dem":200,
    "gn:feature_class":"P",
    "gn:feature_code":"PPL",
    "gn:name":"Motashivka",
    "gn:population":0,
    "gn:timezone":"Europe/Kiev",
    "iso:country":"UA",
    "name:ukr_x_preferred":[
        "Motashivka"
    ],
    "name:ukr_x_variant":[
        "\u041c\u043e\u0442\u0430\u0448\u0456\u0432\u043a\u0430"
    ],
    "name:und_x_variant":[
        "Motashovka"
    ],
    "wof:name":"Motashivka",
    "wof:placetype":"locality"
},
  "geometry": {"coordinates":[25.20936,50.79941],"type":"Point"}
}