{
  "type": "Feature",
  "properties": {
    "gn:admin1_code":"23.0",
    "gn:asciiname":"Topolevka",
    "gn:country_code":"UA",
    "gn:dem":217,
    "gn:feature_class":"P",
    "gn:feature_code":"PPL",
    "gn:name":"Topol\u00ebvka",
    "gn:population":0,
    "gn:timezone":"Europe/Kiev",
    "iso:country":"UA",
    "wof:name":"Topolevka",
    "wof:placetype":"locality"
},
  "geometry": {"coordinates":[29.73877,48.75232000000001],"type":"Point"}
}