{
  "type": "Feature",
  "properties": {
    "gn:admin1_code":"27.0",
    "gn:asciiname":"Budyshcha",
    "gn:country_code":"UA",
    "gn:dem":227,
    "gn:feature_class":"P",
    "gn:feature_code":"PPL",
    "gn:name":"Budyshcha",
    "gn:population":0,
    "gn:timezone":"Europe/Kiev",
    "iso:country":"UA",
    "name:ukr_x_preferred":[
        "Budyshcha"
    ],
    "name:ukr_x_variant":[
        "\u0411\u0443\u0434\u0438\u0449\u0430"
    ],
    "name:und_x_variant":[
        "Budishcha"
    ],
    "wof:name":"Budyshcha",
    "wof:placetype":"locality"
},
  "geometry": {"coordinates":[27.31602,50.48216],"type":"Point"}
}