{
  "type": "Feature",
  "properties": {
    "gn:admin1_code":"16.0",
    "gn:asciiname":"Horokhivs'ke",
    "gn:country_code":"UA",
    "gn:dem":55,
    "gn:feature_class":"P",
    "gn:feature_code":"PPL",
    "gn:name":"Horokhivs\u2019ke",
    "gn:population":0,
    "gn:timezone":"Europe/Kiev",
    "iso:country":"UA",
    "name:ukr_x_preferred":[
        "Horokhivs\u2019ke"
    ],
    "name:ukr_x_variant":[
        "\u0413\u043e\u0440\u043e\u0445\u0456\u0432\u0441\u044c\u043a\u0435"
    ],
    "name:und_x_variant":[
        "Khutor Gorokhovka",
        "Gorokhovka",
        "Gorokhovskiy"
    ],
    "wof:name":"Horokhivs'ke",
    "wof:placetype":"locality"
},
  "geometry": {"coordinates":[32.70372,46.95742],"type":"Point"}
}