{
  "type": "Feature",
  "properties": {
    "gn:admin1_code":"15.0",
    "gn:asciiname":"Zhuravin",
    "gn:country_code":"UA",
    "gn:dem":609,
    "gn:feature_class":"P",
    "gn:feature_code":"PPL",
    "gn:name":"Zhuravin",
    "gn:population":0,
    "gn:timezone":"Europe/Kiev",
    "iso:country":"UA",
    "name:und_x_variant":[
        "Zuravin",
        "\u017burawin",
        "Zhuravna",
        "Zhuravin"
    ],
    "wof:name":"Zhuravin",
    "wof:placetype":"locality"
},
  "geometry": {"coordinates":[22.71667,49.23333],"type":"Point"}
}