{
  "type": "Feature",
  "properties": {
    "gn:admin1_code":"27.0",
    "gn:asciiname":"Stara Oleksandrivka",
    "gn:country_code":"UA",
    "gn:dem":238,
    "gn:feature_class":"P",
    "gn:feature_code":"PPL",
    "gn:name":"Stara Oleksandrivka",
    "gn:population":0,
    "gn:timezone":"Europe/Kiev",
    "iso:country":"UA",
    "name:ukr_x_preferred":[
        "Stara Oleksandrivka"
    ],
    "name:ukr_x_variant":[
        "\u0421\u0442\u0430\u0440\u0430 \u041e\u043b\u0435\u043a\u0441\u0430\u043d\u0434\u0440\u0456\u0432\u043a\u0430"
    ],
    "name:und_x_variant":[
        "Staraya Aleksandrovka"
    ],
    "wof:name":"Stara Oleksandrivka",
    "wof:placetype":"locality"
},
  "geometry": {"coordinates":[28.38742,50.42026],"type":"Point"}
}