{
  "type": "Feature",
  "properties": {
    "gn:admin1_code":"2.0",
    "gn:asciiname":"Voloskovtsy",
    "gn:country_code":"UA",
    "gn:dem":133,
    "gn:feature_class":"P",
    "gn:feature_code":"PPL",
    "gn:name":"Voloskovtsy",
    "gn:population":0,
    "gn:timezone":"Europe/Kiev",
    "iso:country":"UA",
    "name:eng_x_preferred":[
        "Voloskovtsy"
    ],
    "name:rus_x_preferred":[
        "\u0412\u043e\u043b\u043e\u0441\u043a\u043e\u0432\u0446\u044b"
    ],
    "wof:name":"Voloskovtsy",
    "wof:placetype":"locality"
},
  "geometry": {"coordinates":[32.015,51.54818],"type":"Point"}
}