{
  "type": "Feature",
  "properties": {
    "gn:admin1_code":"27.0",
    "gn:asciiname":"Omelusha",
    "gn:country_code":"UA",
    "gn:dem":200,
    "gn:feature_class":"P",
    "gn:feature_code":"PPL",
    "gn:name":"Omelusha",
    "gn:population":0,
    "gn:timezone":"Europe/Kiev",
    "iso:country":"UA",
    "name:ukr_x_preferred":[
        "Omelusha"
    ],
    "name:ukr_x_variant":[
        "\u041e\u043c\u0435\u043b\u0443\u0448\u0430"
    ],
    "name:und_x_variant":[
        "Amelusha"
    ],
    "wof:name":"Omelusha",
    "wof:placetype":"locality"
},
  "geometry": {"coordinates":[28.10552,51.01695],"type":"Point"}
}