{
  "type": "Feature",
  "properties": {
    "gn:admin1_code":"22.0",
    "gn:asciiname":"Strosuvka",
    "gn:cc2":"UA",
    "gn:country_code":"UA",
    "gn:dem":265,
    "gn:feature_class":"P",
    "gn:feature_code":"PPL",
    "gn:name":"Strosuvka",
    "gn:population":0,
    "gn:timezone":"Europe/Kiev",
    "iso:country":"UA",
    "name:und_x_variant":[
        "Strosovka",
        "Strosuvka"
    ],
    "wof:name":"Strosuvka",
    "wof:placetype":"locality"
},
  "geometry": {"coordinates":[25.93333,48.98333],"type":"Point"}
}