{
  "type": "Feature",
  "properties": {
    "gn:admin1_code":"9.0",
    "gn:asciiname":"Korchevka",
    "gn:country_code":"UA",
    "gn:dem":310,
    "gn:feature_class":"P",
    "gn:feature_code":"PPL",
    "gn:name":"Korch\u00ebvka",
    "gn:population":0,
    "gn:timezone":"Europe/Kiev",
    "iso:country":"UA",
    "name:und_x_variant":[
        "Karchevka",
        "Korch\u00ebvka"
    ],
    "wof:name":"Korchevka",
    "wof:placetype":"locality"
},
  "geometry": {"coordinates":[26.66115,49.78947],"type":"Point"}
}