{
  "type": "Feature",
  "properties": {
    "gn:admin1_code":"13.0",
    "gn:asciiname":"Shovkove",
    "gn:country_code":"UA",
    "gn:dem":101,
    "gn:feature_class":"P",
    "gn:feature_code":"PPL",
    "gn:name":"Shovkove",
    "gn:population":0,
    "gn:timezone":"Europe/Kiev",
    "iso:country":"UA",
    "name:ukr_x_preferred":[
        "Shovkove"
    ],
    "name:ukr_x_variant":[
        "\u0428\u043e\u0432\u043a\u043e\u0432\u0435"
    ],
    "name:und_x_variant":[
        "Shelkovoye"
    ],
    "wof:name":"Shovkove",
    "wof:placetype":"locality"
},
  "geometry": {"coordinates":[31.30894,50.33006],"type":"Point"}
}