{
  "type": "Feature",
  "properties": {
    "gn:admin1_code":"17.0",
    "gn:asciiname":"Bohdanivka",
    "gn:country_code":"UA",
    "gn:dem":74,
    "gn:feature_class":"P",
    "gn:feature_code":"PPL",
    "gn:name":"Bohdanivka",
    "gn:population":0,
    "gn:timezone":"Europe/Kiev",
    "iso:country":"UA",
    "name:bel_x_preferred":[
        "\u0411\u0430\u0433\u0434\u0430\u043d\u0430\u045e\u043a\u0430"
    ],
    "name:ceb_x_preferred":[
        "\u0411\u043e\u0433\u0434\u0430\u043d\u043e\u0432\u043a\u0430"
    ],
    "name:hye_x_preferred":[
        "\u0532\u0578\u0563\u0564\u0561\u0576\u0578\u057e\u056f\u0561"
    ],
    "name:kaz_x_preferred":[
        "\u0411\u043e\u0433\u0434\u0430\u043d\u043e\u0432\u043a\u0430"
    ],
    "name:pol_x_preferred":[
        "Bohdaniwka"
    ],
    "name:rus_x_preferred":[
        "\u0411\u043e\u0433\u0434\u0430\u043d\u043e\u0432\u043a\u0430"
    ],
    "name:slk_x_preferred":[
        "Bohdanivka"
    ],
    "name:ukr_x_preferred":[
        "Bohdanivka"
    ],
    "name:ukr_x_variant":[
        "\u0411\u043e\u0433\u0434\u0430\u043d\u0456\u0432\u043a\u0430",
        "\u0411\u043e\u0433\u0434\u0430\u043d\u043e\u0432\u043a\u0430"
    ],
    "name:und_x_variant":[
        "Bogdan-Hajdeu",
        "Bogdanovka",
        "Bogdin Khayden"
    ],
    "wof:name":"Bohdanivka",
    "wof:placetype":"locality"
},
  "geometry": {"coordinates":[29.27976,46.35461],"type":"Point"}
}