{
  "type": "Feature",
  "properties": {
    "gn:admin1_code":"18.0",
    "gn:asciiname":"Patsaly",
    "gn:country_code":"UA",
    "gn:dem":119,
    "gn:feature_class":"P",
    "gn:feature_code":"PPL",
    "gn:name":"Patsaly",
    "gn:population":0,
    "gn:timezone":"Europe/Kiev",
    "iso:country":"UA",
    "name:ukr_x_preferred":[
        "Patsaly"
    ],
    "name:ukr_x_variant":[
        "\u041f\u0430\u0446\u0430\u043b\u0438"
    ],
    "wof:name":"Patsaly",
    "wof:placetype":"locality"
},
  "geometry": {"coordinates":[32.90228,50.22264000000001],"type":"Point"}
}