{
  "type": "Feature",
  "properties": {
    "gn:admin1_code":"4.0",
    "gn:asciiname":"Vesele",
    "gn:country_code":"UA",
    "gn:dem":103,
    "gn:feature_class":"P",
    "gn:feature_code":"PPL",
    "gn:name":"Vesele",
    "gn:population":0,
    "gn:timezone":"Europe/Kiev",
    "iso:country":"UA",
    "name:ukr_x_preferred":[
        "Vesele"
    ],
    "name:ukr_x_variant":[
        "\u0412\u0435\u0441\u0435\u043b\u0435"
    ],
    "name:und_x_variant":[
        "Veseloye"
    ],
    "wof:name":"Vesele",
    "wof:placetype":"locality"
},
  "geometry": {"coordinates":[34.87044,48.77232],"type":"Point"}
}