{
  "type": "Feature",
  "properties": {
    "gn:admin1_code":"14.0",
    "gn:asciiname":"Bondarne",
    "gn:country_code":"UA",
    "gn:dem":179,
    "gn:feature_class":"P",
    "gn:feature_code":"PPL",
    "gn:name":"Bondarne",
    "gn:population":0,
    "gn:timezone":"Europe/Zaporozhye",
    "iso:country":"UA",
    "name:ukr_x_preferred":[
        "Bondarne"
    ],
    "name:ukr_x_variant":[
        "\u0411\u043e\u043d\u0434\u0430\u0440\u043d\u0435"
    ],
    "name:und_x_variant":[
        "Bondarnyy"
    ],
    "wof:name":"Bondarne",
    "wof:placetype":"locality"
},
  "geometry": {"coordinates":[39.38333,49.43333],"type":"Point"}
}