{
  "type": "Feature",
  "properties": {
    "gn:admin1_code":"26.0",
    "gn:asciiname":"Hanno-Opanlynka",
    "gn:country_code":"UA",
    "gn:dem":63,
    "gn:feature_class":"P",
    "gn:feature_code":"PPL",
    "gn:name":"Hanno-Opanlynka",
    "gn:population":0,
    "gn:timezone":"Europe/Zaporozhye",
    "iso:country":"UA",
    "name:ukr_x_preferred":[
        "\u0413\u0430\u043d\u043d\u043e-\u041e\u043f\u0430\u043d\u043b\u0438\u043d\u043a\u0430"
    ],
    "name:und_x_variant":[
        "Anno-Apanly",
        "Anno-Opanlinka",
        "Hanno-Opanlynka"
    ],
    "wof:name":"Hanno-Opanlynka",
    "wof:placetype":"locality"
},
  "geometry": {"coordinates":[35.90008,46.8888],"type":"Point"}
}