{
  "type": "Feature",
  "properties": {
    "gn:admin1_code":"18.0",
    "gn:asciiname":"Voskobiynyky",
    "gn:country_code":"UA",
    "gn:dem":157,
    "gn:feature_class":"P",
    "gn:feature_code":"PPL",
    "gn:name":"Voskobiynyky",
    "gn:population":0,
    "gn:timezone":"Europe/Kiev",
    "iso:country":"UA",
    "name:ukr_x_preferred":[
        "Voskobiynyky"
    ],
    "name:ukr_x_variant":[
        "\u0412\u043e\u0441\u043a\u043e\u0431\u0456\u0439\u043d\u0438\u043a\u0438"
    ],
    "name:und_x_variant":[
        "Voskoboyniki"
    ],
    "wof:name":"Voskobiynyky",
    "wof:placetype":"locality"
},
  "geometry": {"coordinates":[34.15729,50.02924],"type":"Point"}
}