{
  "type": "Feature",
  "properties": {
    "gn:admin1_code":"13.0",
    "gn:asciiname":"Gorokhovatka",
    "gn:country_code":"UA",
    "gn:dem":179,
    "gn:feature_class":"P",
    "gn:feature_code":"PPL",
    "gn:name":"Gorokhovatka",
    "gn:population":0,
    "gn:timezone":"Europe/Kiev",
    "iso:country":"UA",
    "wof:name":"Gorokhovatka",
    "wof:placetype":"locality"
},
  "geometry": {"coordinates":[30.6989,49.91527],"type":"Point"}
}