{
  "type": "Feature",
  "properties": {
    "iso:country":"UA",
    "name:nld_x_preferred":[
        "Lavriv"
    ],
    "name:pol_x_preferred":[
        "\u0141awr\u00f3w"
    ],
    "name:ron_x_preferred":[
        "Lavriv"
    ],
    "name:rus_x_preferred":[
        "\u041b\u0430\u0432\u0440\u043e\u0432"
    ],
    "name:ukr_x_preferred":[
        "\u041b\u0430\u0432\u0440\u0456\u0432"
    ],
    "name:ukr_x_variant":[
        "Lavriv"
    ],
    "name:unk_x_variant":[
        "\u0141awr\u00f3w"
    ],
    "name:zho_x_preferred":[
        "\u62c9\u592b\u91cc\u592b"
    ],
    "qs:a0":"\u0423\u043a\u0440\u0430\u0457\u043d\u0430",
    "qs:a1":"*\u0412\u043e\u043b\u0438\u043d\u0441\u044c\u043a\u0430",
    "qs:a1_alt":"Volyns'ka",
    "qs:a1r":"0",
    "qs:a2":"\u041b\u0443\u0446\u044c\u043a\u0438\u0439",
    "qs:a2_alt":"Luts'kyi",
    "qs:adm0":"\u0423\u043a\u0440\u0430\u0457\u043d\u0430",
    "qs:la_lc":"*",
    "qs:level":"locality",
    "qs:loc":"\u041b\u0430\u0432\u0440\u0456\u0432",
    "qs:loc_alt":"Lavriv",
    "qs:pop":0,
    "qs:type":"buffered point",
    "wd:wordcount":234,
    "wof:name":"\u041b\u0430\u0432\u0440\u0456\u0432",
    "wof:placetype":"locality"
},
  "geometry": {"coordinates":[25.264977,50.613185],"type":"Point"}
}