{
  "type": "Feature",
  "properties": {
    "gn:admin1_code":"27.0",
    "gn:asciiname":"Hlybochok",
    "gn:country_code":"UA",
    "gn:dem":234,
    "gn:feature_class":"P",
    "gn:feature_code":"PPL",
    "gn:name":"Hlybochok",
    "gn:population":0,
    "gn:timezone":"Europe/Kiev",
    "iso:country":"UA",
    "name:ukr_x_preferred":[
        "Hlybochok"
    ],
    "name:ukr_x_variant":[
        "\u0413\u043b\u0438\u0431\u043e\u0447\u043e\u043a"
    ],
    "name:und_x_variant":[
        "Glubochok",
        "Glubochek"
    ],
    "wof:name":"Hlybochok",
    "wof:placetype":"locality"
},
  "geometry": {"coordinates":[28.3331,50.09626],"type":"Point"}
}