{
  "type": "Feature",
  "properties": {
    "iso:country":"UA",
    "qs:a0":"\u0423\u043a\u0440\u0430\u0457\u043d\u0430",
    "qs:a1":"*\u0414\u043d\u0456\u043f\u0440\u043e\u043f\u0435\u0442\u0440\u043e\u0432\u0441\u044c\u043a\u0430",
    "qs:a1_alt":"Dnipropetrovs'ka",
    "qs:a1r":"0",
    "qs:a2":"\u041d\u043e\u0432\u043e\u043c\u043e\u0441\u043a\u043e\u0432\u0441\u044c\u043a\u0438\u0439",
    "qs:a2_alt":"Novomoskovs'kyi",
    "qs:adm0":"\u0423\u043a\u0440\u0430\u0457\u043d\u0430",
    "qs:la_lc":"*",
    "qs:level":"locality",
    "qs:loc":"\u0412\u0456\u043b\u044c\u043d\u0435",
    "qs:loc_alt":"Vil'ne",
    "qs:pop":0,
    "qs:type":"buffered point",
    "wd:wordcount":320,
    "wof:name":"\u0412\u0456\u043b\u044c\u043d\u0435",
    "wof:placetype":"locality"
},
  "geometry": {"coordinates":[35.286113,48.746773],"type":"Point"}
}