{
  "type": "Feature",
  "properties": {
    "gn:admin1_code":"18.0",
    "gn:asciiname":"Sheky",
    "gn:country_code":"UA",
    "gn:dem":125,
    "gn:feature_class":"P",
    "gn:feature_code":"PPL",
    "gn:name":"Sheky",
    "gn:population":0,
    "gn:timezone":"Europe/Kiev",
    "iso:country":"UA",
    "name:ukr_x_preferred":[
        "Sheky"
    ],
    "name:ukr_x_variant":[
        "\u0428\u0435\u043a\u0438"
    ],
    "name:und_x_variant":[
        "Shcheki"
    ],
    "wof:name":"Sheky",
    "wof:placetype":"locality"
},
  "geometry": {"coordinates":[33.25769,50.16168],"type":"Point"}
}