{
  "type": "Feature",
  "properties": {
    "gn:admin1_code":"2.0",
    "gn:asciiname":"Smolyn",
    "gn:country_code":"UA",
    "gn:dem":110,
    "gn:feature_class":"P",
    "gn:feature_code":"PPL",
    "gn:name":"Smolyn",
    "gn:population":0,
    "gn:timezone":"Europe/Kiev",
    "iso:country":"UA",
    "name:eng_x_preferred":[
        "Smolin"
    ],
    "name:rus_x_preferred":[
        "\u0421\u043c\u043e\u043b\u0438\u043d"
    ],
    "name:ukr_x_preferred":[
        "Smolyn"
    ],
    "name:ukr_x_variant":[
        "\u0421\u043c\u043e\u043b\u0438\u043d"
    ],
    "name:und_x_variant":[
        "Smolino"
    ],
    "wof:name":"Smolyn",
    "wof:placetype":"locality"
},
  "geometry": {"coordinates":[31.00052,51.28801],"type":"Point"}
}