{
  "type": "Feature",
  "properties": {
    "gn:admin1_code":"19.0",
    "gn:asciiname":"Metkiv",
    "gn:country_code":"UA",
    "gn:dem":171,
    "gn:feature_class":"P",
    "gn:feature_code":"PPL",
    "gn:name":"Metkiv",
    "gn:population":0,
    "gn:timezone":"Europe/Kiev",
    "iso:country":"UA",
    "name:ukr_x_preferred":[
        "Metkiv"
    ],
    "name:ukr_x_variant":[
        "\u041c\u0435\u0442\u043a\u0456\u0432"
    ],
    "name:und_x_variant":[
        "Metkov"
    ],
    "wof:name":"Metkiv",
    "wof:placetype":"locality"
},
  "geometry": {"coordinates":[26.17728,50.72648],"type":"Point"}
}