{
  "type": "Feature",
  "properties": {
    "gn:admin1_code":"10.0",
    "gn:asciiname":"Nastyne",
    "gn:country_code":"UA",
    "gn:dem":217,
    "gn:feature_class":"P",
    "gn:feature_code":"PPL",
    "gn:name":"Nastyne",
    "gn:population":0,
    "gn:timezone":"Europe/Kiev",
    "iso:country":"UA",
    "name:ukr_x_preferred":[
        "Nastyne"
    ],
    "name:ukr_x_variant":[
        "\u041d\u0430\u0441\u0442\u0438\u043d\u0435"
    ],
    "wof:name":"Nastyne",
    "wof:placetype":"locality"
},
  "geometry": {"coordinates":[32.45332,49.0144],"type":"Point"}
}