{
  "type": "Feature",
  "properties": {
    "gn:admin1_code":"5.0",
    "gn:asciiname":"Syedovo-Vasylivka",
    "gn:country_code":"UA",
    "gn:dem":30,
    "gn:feature_class":"P",
    "gn:feature_code":"PPL",
    "gn:name":"Syedovo-Vasylivka",
    "gn:population":0,
    "gn:timezone":"Europe/Kiev",
    "iso:country":"UA",
    "name:ukr_x_preferred":[
        "\u0421\u0454\u0434\u043e\u0432\u043e-\u0412\u0430\u0441\u0438\u043b\u0456\u0432\u043a\u0430"
    ],
    "name:und_x_variant":[
        "Sid-Vasil\u2019yevka",
        "Syedovo-Vasylivka",
        "Sedovo-Vasil\u2019yevka",
        "Sedovo-Vasilevka"
    ],
    "wof:name":"Syedovo-Vasylivka",
    "wof:placetype":"locality"
},
  "geometry": {"coordinates":[38.11315,47.22315],"type":"Point"}
}