{
  "type": "Feature",
  "properties": {
    "gn:admin1_code":"5.0",
    "gn:asciiname":"Chernyavskiy",
    "gn:cc2":"UA",
    "gn:country_code":"UA",
    "gn:dem":191,
    "gn:feature_class":"P",
    "gn:feature_code":"PPL",
    "gn:name":"Chernyavskiy",
    "gn:population":0,
    "gn:timezone":"Europe/Kiev",
    "iso:country":"UA",
    "name:und_x_variant":[
        "Khutor Chernyavskiy",
        "Chernyavskiy"
    ],
    "wof:name":"Chernyavskiy",
    "wof:placetype":"locality"
},
  "geometry": {"coordinates":[37.25,48.46667],"type":"Point"}
}