{
  "type": "Feature",
  "properties": {
    "iso:country":"UA",
    "qs:a0":"\u0423\u043a\u0440\u0430\u0457\u043d\u0430",
    "qs:a1":"*\u0425\u0430\u0440\u043a\u0456\u0432\u0441\u044c\u043a\u0430",
    "qs:a1_alt":"Kharkivs'ka",
    "qs:a1r":"0",
    "qs:a2":"\u0427\u0443\u0433\u0443\u0457\u0432\u0441\u044c\u043a\u0438\u0439",
    "qs:a2_alt":"Chuhuivs'kyi",
    "qs:adm0":"\u0423\u043a\u0440\u0430\u0457\u043d\u0430",
    "qs:la_lc":"*",
    "qs:level":"locality",
    "qs:loc":"\u041b\u0435\u0431'\u044f\u0436\u0435",
    "qs:loc_alt":"Lebiazhe",
    "qs:pop":0,
    "qs:type":"buffered point",
    "wof:name":"\u041b\u0435\u0431'\u044f\u0436\u0435",
    "wof:placetype":"locality"
},
  "geometry": {"coordinates":[36.904646,49.802387],"type":"Point"}
}