{
  "type": "Feature",
  "properties": {
    "iso:country":"UA",
    "name:ukr_x_preferred":[
        "\u041f\u0443\u0441\u0442\u043e\u0432\u0430\u0440\u0456\u0432\u043a\u0430"
    ],
    "name:unk_x_variant":[
        "Pustovarivka"
    ],
    "qs:a0":"\u0423\u043a\u0440\u0430\u0457\u043d\u0430",
    "qs:a1":"*\u041a\u0438\u0457\u0432\u0441\u044c\u043a\u0430",
    "qs:a1_alt":"Kyivs'ka",
    "qs:a1r":"0",
    "qs:a2":"\u0421\u043a\u0432\u0438\u0440\u0441\u044c\u043a\u0438\u0439",
    "qs:a2_alt":"Skvyrs'kyi",
    "qs:adm0":"\u0423\u043a\u0440\u0430\u0457\u043d\u0430",
    "qs:la_lc":"*",
    "qs:level":"locality",
    "qs:loc":"\u041f\u0443\u0441\u0442\u043e\u0432\u0430\u0440\u0456\u0432\u043a\u0430",
    "qs:loc_alt":"Pustovarivka",
    "qs:pop":0,
    "qs:type":"buffered point",
    "wof:name":"\u041f\u0443\u0441\u0442\u043e\u0432\u0430\u0440\u0456\u0432\u043a\u0430",
    "wof:placetype":"locality"
},
  "geometry": {"coordinates":[29.820793,49.703949],"type":"Point"}
}