{
  "type": "Feature",
  "properties": {
    "gn:population":157,
    "iso:country":"UA",
    "name:eng_x_preferred":[
        "Tysovets"
    ],
    "name:rus_x_preferred":[
        "\u0422\u0438\u0441\u043e\u0432\u0435\u0446"
    ],
    "name:rus_x_variant":[
        "\u0422\u0438\u0441\u043e\u0432"
    ],
    "name:ukr_x_preferred":[
        "\u0422\u0438\u0441\u0456\u0432"
    ],
    "name:und_x_variant":[
        "Tysiv"
    ],
    "qs:a0":"\u0423\u043a\u0440\u0430\u0457\u043d\u0430",
    "qs:a1":"*\u0406\u0432\u0430\u043d\u043e-\u0424\u0440\u0430\u043d\u043a\u0456\u0432\u0441\u044c\u043a\u0430",
    "qs:a1_alt":"Ivano-Frankivs'ka",
    "qs:a1r":"0",
    "qs:a2":"\u0414\u043e\u043b\u0438\u043d\u0441\u044c\u043a\u0438\u0439",
    "qs:a2_alt":"Dolyns'kyi",
    "qs:adm0":"\u0423\u043a\u0440\u0430\u0457\u043d\u0430",
    "qs:la_lc":"*",
    "qs:level":"locality",
    "qs:loc":"\u0422\u0438\u0441\u0456\u0432",
    "qs:loc_alt":"Tysiv",
    "qs:pop":0,
    "qs:type":"buffered point",
    "wof:name":"\u0422\u0438\u0441\u0456\u0432",
    "wof:placetype":"locality",
    "wof:population":157
},
  "geometry": {"coordinates":[23.77281,49.048723],"type":"Point"}
}