{
  "type": "Feature",
  "properties": {
    "gn:admin1_code":"7.0",
    "gn:asciiname":"Serafymivka",
    "gn:country_code":"UA",
    "gn:dem":164,
    "gn:feature_class":"P",
    "gn:feature_code":"PPL",
    "gn:name":"Serafymivka",
    "gn:population":0,
    "gn:timezone":"Europe/Kiev",
    "iso:country":"UA",
    "name:ukr_x_preferred":[
        "Serafymivka"
    ],
    "name:ukr_x_variant":[
        "\u0421\u0435\u0440\u0430\u0444\u0438\u043c\u0456\u0432\u043a\u0430"
    ],
    "name:und_x_variant":[
        "Serafimovka"
    ],
    "wof:name":"Serafymivka",
    "wof:placetype":"locality"
},
  "geometry": {"coordinates":[36.57541,49.42218],"type":"Point"}
}