{
  "type": "Feature",
  "properties": {
    "gn:admin1_code":"17.0",
    "gn:asciiname":"Khutor Ideya",
    "gn:cc2":"UA",
    "gn:country_code":"UA",
    "gn:dem":208,
    "gn:feature_class":"P",
    "gn:feature_code":"PPL",
    "gn:name":"Khutor Ideya",
    "gn:population":0,
    "gn:timezone":"Europe/Kiev",
    "iso:country":"UA",
    "name:und_x_variant":[
        "Ideya"
    ],
    "wof:name":"Khutor Ideya",
    "wof:placetype":"locality"
},
  "geometry": {"coordinates":[29.65639,47.58056],"type":"Point"}
}