{
  "type": "Feature",
  "properties": {
    "gn:admin1_code":"19.0",
    "gn:asciiname":"Kosmachiv",
    "gn:country_code":"UA",
    "gn:dem":166,
    "gn:feature_class":"P",
    "gn:feature_code":"PPL",
    "gn:name":"Kosmachiv",
    "gn:population":0,
    "gn:timezone":"Europe/Kiev",
    "iso:country":"UA",
    "name:ukr_x_preferred":[
        "Kosmachiv"
    ],
    "name:ukr_x_variant":[
        "\u041a\u043e\u0441\u043c\u0430\u0447\u0456\u0432"
    ],
    "name:und_x_variant":[
        "Kosmachuv",
        "Kosmach\u00ebv"
    ],
    "wof:name":"Kosmachiv",
    "wof:placetype":"locality"
},
  "geometry": {"coordinates":[26.33882,51.00975],"type":"Point"}
}