{
  "type": "Feature",
  "properties": {
    "gn:admin1_code":"21.0",
    "gn:asciiname":"Klyn",
    "gn:country_code":"UA",
    "gn:dem":189,
    "gn:feature_class":"P",
    "gn:feature_code":"PPL",
    "gn:name":"Klyn",
    "gn:population":0,
    "gn:timezone":"Europe/Kiev",
    "iso:country":"UA",
    "name:ukr_x_preferred":[
        "Klyn"
    ],
    "name:ukr_x_variant":[
        "\u041a\u043b\u0438\u043d"
    ],
    "name:und_x_variant":[
        "Klin"
    ],
    "wof:name":"Klyn",
    "wof:placetype":"locality"
},
  "geometry": {"coordinates":[33.95061,50.88708],"type":"Point"}
}