{
  "type": "Feature",
  "properties": {
    "gn:admin1_code":"27.0",
    "gn:asciiname":"Tovkachi",
    "gn:country_code":"UA",
    "gn:dem":158,
    "gn:feature_class":"P",
    "gn:feature_code":"PPL",
    "gn:name":"Tovkachi",
    "gn:population":0,
    "gn:timezone":"Europe/Kiev",
    "iso:country":"UA",
    "name:ukr_x_preferred":[
        "Tovkachi"
    ],
    "name:ukr_x_variant":[
        "\u0422\u043e\u0432\u043a\u0430\u0447\u0456"
    ],
    "name:und_x_variant":[
        "Tolkachi"
    ],
    "wof:name":"Tovkachi",
    "wof:placetype":"locality"
},
  "geometry": {"coordinates":[28.8338,51.34628],"type":"Point"}
}