{
  "type": "Feature",
  "properties": {
    "gn:admin1_code":"26.0",
    "gn:asciiname":"Vidrodzhennya",
    "gn:country_code":"UA",
    "gn:dem":76,
    "gn:feature_class":"P",
    "gn:feature_code":"PPL",
    "gn:name":"Vidrodzhennya",
    "gn:population":0,
    "gn:timezone":"Europe/Zaporozhye",
    "iso:country":"UA",
    "name:ukr_x_preferred":[
        "Vidrodzhennya"
    ],
    "name:ukr_x_variant":[
        "\u0412\u0456\u0434\u0440\u043e\u0434\u0436\u0435\u043d\u043d\u044f"
    ],
    "name:und_x_variant":[
        "Vozrozhdeniye"
    ],
    "wof:name":"Vidrodzhennya",
    "wof:placetype":"locality"
},
  "geometry": {"coordinates":[35.23863,47.08063],"type":"Point"}
}