{
  "type": "Feature",
  "properties": {
    "iso:country":"UA",
    "name:eng_x_preferred":[
        "Klenovets'"
    ],
    "name:epo_x_preferred":[
        "Klenovec"
    ],
    "name:hun_x_preferred":[
        "Frigyesfalva"
    ],
    "name:hye_x_preferred":[
        "\u053f\u056c\u0565\u0576\u0578\u057e\u0565\u0581"
    ],
    "name:nld_x_preferred":[
        "Frigyesfalva"
    ],
    "name:ron_x_preferred":[
        "Klenove\u021b"
    ],
    "name:rus_x_preferred":[
        "\u041a\u043b\u0435\u043d\u043e\u0432\u0435\u0446"
    ],
    "name:ukr_x_preferred":[
        "Klenovets\u2019"
    ],
    "name:ukr_x_variant":[
        "\u041a\u043b\u0435\u043d\u043e\u0432\u0435\u0446\u044c"
    ],
    "name:und_x_variant":[
        "Novoye Klenovtse"
    ],
    "name:zho_x_preferred":[
        "\u514b\u5217\u8afe\u97cb\u9f4a"
    ],
    "qs:a0":"\u0423\u043a\u0440\u0430\u0457\u043d\u0430",
    "qs:a1":"*\u0417\u0430\u043a\u0430\u0440\u043f\u0430\u0442\u0441\u044c\u043a\u0430",
    "qs:a1_alt":"Zakarpats'ka",
    "qs:a1r":"0",
    "qs:a2":"\u041c\u0443\u043a\u0430\u0447\u0456\u0432\u0441\u044c\u043a\u0438\u0439",
    "qs:a2_alt":"Mukachivs'kyi",
    "qs:adm0":"\u0423\u043a\u0440\u0430\u0457\u043d\u0430",
    "qs:la_lc":"*",
    "qs:level":"locality",
    "qs:loc":"\u041a\u043b\u0435\u043d\u043e\u0432\u0435\u0446\u044c",
    "qs:loc_alt":"Klenovets",
    "qs:pop":0,
    "qs:type":"buffered point",
    "wd:wordcount":84,
    "wof:name":"\u041a\u043b\u0435\u043d\u043e\u0432\u0435\u0446\u044c",
    "wof:placetype":"locality"
},
  "geometry": {"coordinates":[22.759636,48.510959],"type":"Point"}
}