{
  "type": "Feature",
  "properties": {
    "iso:country":"UA",
    "name:deu_x_preferred":[
        "Moschnjakiwka"
    ],
    "name:eng_x_preferred":[
        "Mozhnyakovka"
    ],
    "name:eng_x_variant":[
        "Mozhniakivka"
    ],
    "name:lav_x_preferred":[
        "Mo\u017e\u0146akivka"
    ],
    "name:ron_x_preferred":[
        "Mojneakivka"
    ],
    "name:rus_x_preferred":[
        "\u041c\u043e\u0436\u043d\u044f\u043a\u043e\u0432\u043a\u0430"
    ],
    "name:ukr_x_preferred":[
        "Mozhnyakivka"
    ],
    "name:ukr_x_variant":[
        "\u041c\u043e\u0436\u043d\u044f\u043a\u0456\u0432\u043a\u0430"
    ],
    "name:und_x_variant":[
        "Mozhnyakova"
    ],
    "name:zho_x_preferred":[
        "\u83ab\u65e5\u5c3c\u4e9e\u57fa\u592b\u5361"
    ],
    "qs:a0":"\u0423\u043a\u0440\u0430\u0457\u043d\u0430",
    "qs:a1":"*\u041b\u0443\u0433\u0430\u043d\u0441\u044c\u043a\u0430",
    "qs:a1_alt":"Luhans'ka",
    "qs:a1r":"0",
    "qs:a2":"\u041d\u043e\u0432\u043e\u043f\u0441\u043a\u043e\u0432\u0441\u044c\u043a\u0438\u0439",
    "qs:a2_alt":"Novopskovs'kyi",
    "qs:adm0":"\u0423\u043a\u0440\u0430\u0457\u043d\u0430",
    "qs:la_lc":"*",
    "qs:level":"locality",
    "qs:loc":"\u041c\u043e\u0436\u043d\u044f\u043a\u0456\u0432\u043a\u0430",
    "qs:loc_alt":"Mozhniakivka",
    "qs:pop":0,
    "qs:type":"buffered point",
    "wof:name":"\u041c\u043e\u0436\u043d\u044f\u043a\u0456\u0432\u043a\u0430",
    "wof:placetype":"locality"
},
  "geometry": {"coordinates":[39.058299,49.672256],"type":"Point"}
}