{
  "type": "Feature",
  "properties": {
    "gn:admin1_code":"15.0",
    "gn:asciiname":"Bahnuvate",
    "gn:country_code":"UA",
    "gn:dem":695,
    "gn:feature_class":"P",
    "gn:feature_code":"PPL",
    "gn:name":"Bahnuvate",
    "gn:population":0,
    "gn:timezone":"Europe/Kiev",
    "iso:country":"UA",
    "name:hye_x_preferred":[
        "\u0532\u0561\u0563\u0576\u0578\u057e\u0561\u057f\u0578\u0565"
    ],
    "name:kat_x_preferred":[
        "\u10d1\u10d0\u10d2\u10dc\u10dd\u10d5\u10d0\u10e2\u10dd\u10d4"
    ],
    "name:pol_x_preferred":[
        "Bachnowate"
    ],
    "name:ron_x_preferred":[
        "Bahnuvate"
    ],
    "name:rus_x_preferred":[
        "\u0411\u0430\u0433\u043d\u043e\u0432\u0430\u0442\u043e\u0435"
    ],
    "name:ukr_x_preferred":[
        "Bahnuvate"
    ],
    "name:ukr_x_variant":[
        "\u0411\u0430\u0433\u043d\u0443\u0432\u0430\u0442\u0435"
    ],
    "name:und_x_variant":[
        "Bakhnovate",
        "Bagnovatyy",
        "Bagnovatoye"
    ],
    "name:zho_x_preferred":[
        "\u5df4\u683c\u52aa\u74e6\u6377"
    ],
    "wof:name":"Bahnuvate",
    "wof:placetype":"locality"
},
  "geometry": {"coordinates":[23.15398,49.06116],"type":"Point"}
}