{
  "type": "Feature",
  "properties": {
    "gn:admin1_code":"15.0",
    "gn:asciiname":"Bahnuvate",
    "gn:country_code":"UA",
    "gn:dem":695,
    "gn:feature_class":"P",
    "gn:feature_code":"PPL",
    "gn:name":"Bahnuvate",
    "gn:population":0,
    "gn:timezone":"Europe/Kiev",
    "iso:country":"UA",
    "name:rus_x_preferred":[
        "\u0411\u0430\u0433\u043d\u043e\u0432\u0430\u0442\u043e\u0435"
    ],
    "name:ukr_x_preferred":[
        "Bahnuvate"
    ],
    "name:ukr_x_variant":[
        "\u0411\u0430\u0433\u043d\u0443\u0432\u0430\u0442\u0435"
    ],
    "name:und_x_variant":[
        "Bakhnovate",
        "Bagnovatyy",
        "Bagnovatoye"
    ],
    "wof:name":"Bahnuvate",
    "wof:placetype":"locality"
},
  "geometry": {"coordinates":[23.15398,49.06116],"type":"Point"}
}