{
  "type": "Feature",
  "properties": {
    "gn:admin1_code":"13.0",
    "gn:asciiname":"Kozychanka",
    "gn:country_code":"UA",
    "gn:dem":167,
    "gn:feature_class":"P",
    "gn:feature_code":"PPL",
    "gn:name":"Kozychanka",
    "gn:population":0,
    "gn:timezone":"Europe/Kiev",
    "iso:country":"UA",
    "name:ukr_x_preferred":[
        "Kozychanka"
    ],
    "name:ukr_x_variant":[
        "\u041a\u043e\u0437\u0438\u0447\u0430\u043d\u043a\u0430"
    ],
    "name:und_x_variant":[
        "Kozichanka"
    ],
    "wof:name":"Kozychanka",
    "wof:placetype":"locality"
},
  "geometry": {"coordinates":[29.77271,50.26043],"type":"Point"}
}