{
  "type": "Feature",
  "properties": {
    "gn:admin1_code":"26.0",
    "gn:asciiname":"Petropil'",
    "gn:country_code":"UA",
    "gn:dem":120,
    "gn:feature_class":"P",
    "gn:feature_code":"PPL",
    "gn:name":"Petropil\u2019",
    "gn:population":0,
    "gn:timezone":"Europe/Zaporozhye",
    "iso:country":"UA",
    "name:ukr_x_preferred":[
        "Petropil\u2019"
    ],
    "name:ukr_x_variant":[
        "\u041f\u0435\u0442\u0440\u043e\u043f\u0456\u043b\u044c"
    ],
    "wof:name":"Petropil'",
    "wof:placetype":"locality"
},
  "geometry": {"coordinates":[34.94967,48.01539],"type":"Point"}
}