{
  "type": "Feature",
  "properties": {
    "gn:admin1_code":"9.0",
    "gn:asciiname":"Yakymivtsi",
    "gn:country_code":"UA",
    "gn:dem":296,
    "gn:feature_class":"P",
    "gn:feature_code":"PPL",
    "gn:name":"Yakymivtsi",
    "gn:population":0,
    "gn:timezone":"Europe/Kiev",
    "iso:country":"UA",
    "name:ukr_x_preferred":[
        "Yakymivtsi"
    ],
    "name:ukr_x_variant":[
        "\u042f\u043a\u0438\u043c\u0456\u0432\u0446\u0456"
    ],
    "name:und_x_variant":[
        "Yakimovtsy"
    ],
    "wof:name":"Yakymivtsi",
    "wof:placetype":"locality"
},
  "geometry": {"coordinates":[26.7922,49.82599],"type":"Point"}
}