{
  "type": "Feature",
  "properties": {
    "iso:country":"UA",
    "name:ukr_x_preferred":[
        "Zabir\u201dya"
    ],
    "name:ukr_x_variant":[
        "\u0417\u0430\u0431\u0456\u0440\u2019\u044f"
    ],
    "name:und_x_variant":[
        "Zabozhe"
    ],
    "qs:a0":"\u0423\u043a\u0440\u0430\u0457\u043d\u0430",
    "qs:a1":"*\u041b\u044c\u0432\u0456\u0432\u0441\u044c\u043a\u0430",
    "qs:a1_alt":"L'vivs'ka",
    "qs:a1r":"0",
    "qs:a2":"\u0416\u043e\u0432\u043a\u0456\u0432\u0441\u044c\u043a\u0438\u0439",
    "qs:a2_alt":"Zhovkivs'kyi",
    "qs:adm0":"\u0423\u043a\u0440\u0430\u0457\u043d\u0430",
    "qs:la_lc":"*",
    "qs:level":"locality",
    "qs:loc":"\u0417\u0430\u0431\u0456\u0440'\u044f",
    "qs:loc_alt":"Zabiria",
    "qs:pop":0,
    "qs:type":"buffered point",
    "wof:name":"\u0417\u0430\u0431\u0456\u0440'\u044f",
    "wof:placetype":"locality"
},
  "geometry": {"coordinates":[23.714656,50.271942],"type":"Point"}
}