{
  "type": "Feature",
  "properties": {
    "gn:admin1_code":"11.0",
    "gn:admin2_code":"693803",
    "gn:admin3_code":"11152624",
    "gn:asciiname":"Novozburyevka",
    "gn:country_code":"UA",
    "gn:dem":247,
    "gn:elevation":"262.0",
    "gn:feature_class":"P",
    "gn:feature_code":"PPL",
    "gn:name":"Novozburyevka",
    "gn:population":407,
    "gn:timezone":"Europe/Simferopol",
    "iso:country":"UA",
    "name:eng_x_preferred":[
        "Novozburyevka"
    ],
    "name:rus_x_historical":[
        "\u0417\u0431\u0443\u0301\u0440\u044c\u0435\u0432\u043a\u0430",
        "\u0412\u0435\u0301\u0440\u0445\u043d\u0438\u0439 \u0421\u0435\u0439\u043c\u0430\u043d\u043b\u0430\u0440\u043a\u043e\u0301\u0439"
    ],
    "name:rus_x_preferred":[
        "\u041d\u043e\u0432\u043e\u0437\u0431\u0443\u0440\u044c\u0435\u0432\u043a\u0430"
    ],
    "name:rus_x_variant":[
        "\u0417\u0431\u0443\u0301\u0440\u044c\u0435\u0432\u043a\u0430",
        "\u0412\u0435\u0301\u0440\u0445\u043d\u0438\u0439 \u0421\u0435\u0439\u043c\u0430\u043d\u043b\u0430\u0440\u043a\u043e\u0301\u0439"
    ],
    "name:ukr_x_preferred":[
        "\u041d\u043e\u0432\u043e\u0437\u0431\u0443\u0440\u2019\u0457\u0432\u043a\u0430"
    ],
    "wof:name":"Novozburyevka",
    "wof:placetype":"locality",
    "wof:population":407
},
  "geometry": {"coordinates":[33.97174,44.91867],"type":"Point"}
}