{
  "type": "Feature",
  "properties": {
    "gn:gn_country":"UA",
    "gn:gn_fcode":"PPL",
    "gn:gn_pop":66400,
    "gn:population":66400,
    "iso:country":"UA",
    "name:ara_x_preferred":[
        "\u0643\u0648\u0641\u0644"
    ],
    "name:arm_x_preferred":[
        "\u053f\u0578\u057e\u0565\u056c"
    ],
    "name:bel_x_preferred":[
        "\u041a\u043e\u0432\u0435\u043b\u044c"
    ],
    "name:bul_x_preferred":[
        "\u041a\u043e\u0432\u0435\u043b"
    ],
    "name:cat_x_preferred":[
        "K\u00f2vel"
    ],
    "name:chi_x_preferred":[
        "\u79d1\u97cb\u5229"
    ],
    "name:cze_x_preferred":[
        "Kovel"
    ],
    "name:deu_x_preferred":[
        "Kowel"
    ],
    "name:dut_x_preferred":[
        "Kovel"
    ],
    "name:eng_x_preferred":[
        "Kovel"
    ],
    "name:fin_x_preferred":[
        "Kovel"
    ],
    "name:fre_x_preferred":[
        "Kovel"
    ],
    "name:geo_x_preferred":[
        "\u10d9\u10dd\u10d5\u10d4\u10da\u10d8"
    ],
    "name:ger_x_preferred":[
        "Kowel"
    ],
    "name:heb_x_preferred":[
        "\u05e7\u05d5\u05d1\u05dc"
    ],
    "name:hsb_x_preferred":[
        "Kowel"
    ],
    "name:hun_x_preferred":[
        "Kovel"
    ],
    "name:ita_x_preferred":[
        "Kovel'"
    ],
    "name:jpn_x_preferred":[
        "\u30b3\u30fc\u30f4\u30a7\u30ea"
    ],
    "name:kor_x_preferred":[
        "\ucf54\ubca8"
    ],
    "name:lav_x_preferred":[
        "Kove\u013ca"
    ],
    "name:lit_x_preferred":[
        "Kovelis"
    ],
    "name:nno_x_preferred":[
        "Kovel"
    ],
    "name:nob_x_preferred":[
        "Kovel"
    ],
    "name:nor_x_preferred":[
        "Kovel"
    ],
    "name:per_x_preferred":[
        "\u06a9\u0648\u0648\u0644"
    ],
    "name:pol_x_preferred":[
        "Kowel"
    ],
    "name:por_x_preferred":[
        "Kovel"
    ],
    "name:rue_x_preferred":[
        "\u041a\u043e\u0432\u0435\u043b\u044c"
    ],
    "name:rum_x_preferred":[
        "Kovel"
    ],
    "name:rus_x_preferred":[
        "\u041a\u043e\u0432\u0435\u043b\u044c"
    ],
    "name:slv_x_preferred":[
        "Kovel"
    ],
    "name:spa_x_preferred":[
        "Kovel"
    ],
    "name:srp_x_preferred":[
        "\u041a\u043e\u0432\u0435\u0459"
    ],
    "name:swe_x_preferred":[
        "Kovel"
    ],
    "name:tat_x_preferred":[
        "\u041a\u043e\u0432\u0435\u043b"
    ],
    "name:ukr_x_preferred":[
        "\u041a\u043e\u0432\u0435\u043b\u044c"
    ],
    "name:unk_x_variant":[
        "Kowel"
    ],
    "name:vie_x_preferred":[
        "Kovel"
    ],
    "name:wel_x_preferred":[
        "Kovel"
    ],
    "name:yid_x_preferred":[
        "\u05e7\u05d0\u05d5\u05d5\u05dc\u05e2"
    ],
    "qs_pg:aaroncc":"UA",
    "qs_pg:gn_country":"UA",
    "qs_pg:gn_fcode":"PPL",
    "qs_pg:gn_pop":66400,
    "qs_pg:name":"Kovel\u2019",
    "qs_pg:photos_9r":0,
    "qs_pg:photos_sr":0,
    "qs_pg:pop_sr":8,
    "qs_pg:qs_pg_placetype":"locality",
    "wof:name":"Kovel\u2019",
    "wof:placetype":"locality",
    "wof:population":66400
},
  "geometry": {"coordinates":[24.70867,51.21526],"type":"Point"}
}