{
  "type": "Feature",
  "properties": {
    "gn:admin1_code":"21.0",
    "gn:asciiname":"Pavlenkove",
    "gn:country_code":"UA",
    "gn:dem":178,
    "gn:feature_class":"P",
    "gn:feature_code":"PPL",
    "gn:name":"Pavlenkove",
    "gn:population":0,
    "gn:timezone":"Europe/Kiev",
    "iso:country":"UA",
    "name:ukr_x_preferred":[
        "Pavlenkove"
    ],
    "name:ukr_x_variant":[
        "\u041f\u0430\u0432\u043b\u0435\u043d\u043a\u043e\u0432\u0435"
    ],
    "name:und_x_variant":[
        "Pavlenkov",
        "Pavlenkovo"
    ],
    "wof:name":"Pavlenkove",
    "wof:placetype":"locality"
},
  "geometry": {"coordinates":[34.33381,50.75264],"type":"Point"}
}