{
  "type": "Feature",
  "properties": {
    "gn:admin1_code":"18.0",
    "gn:asciiname":"Sydoryache",
    "gn:country_code":"UA",
    "gn:dem":117,
    "gn:feature_class":"P",
    "gn:feature_code":"PPL",
    "gn:name":"Sydoryache",
    "gn:population":0,
    "gn:timezone":"Europe/Kiev",
    "iso:country":"UA",
    "name:rus_x_preferred":[
        "Sidoryach\u2019ye"
    ],
    "name:ukr_x_preferred":[
        "Sydoryache"
    ],
    "name:ukr_x_variant":[
        "\u0421\u0438\u0434\u043e\u0440\u044f\u0447\u0435"
    ],
    "wof:name":"Sydoryache",
    "wof:placetype":"locality"
},
  "geometry": {"coordinates":[34.91357,50.12269000000001],"type":"Point"}
}