{
  "type": "Feature",
  "properties": {
    "iso:country":"UA",
    "qs:a0":"\u0423\u043a\u0440\u0430\u0457\u043d\u0430",
    "qs:a1":"*\u0425\u043c\u0435\u043b\u044c\u043d\u0438\u0446\u044c\u043a\u0430",
    "qs:a1_alt":"Khmel'nyts'ka",
    "qs:a1r":"0",
    "qs:a2":"\u0421\u0442\u0430\u0440\u043e\u0441\u0438\u043d\u044f\u0432\u0441\u044c\u043a\u0438\u0439",
    "qs:a2_alt":"Starosyniavs'kyi",
    "qs:adm0":"\u0423\u043a\u0440\u0430\u0457\u043d\u0430",
    "qs:la_lc":"*",
    "qs:level":"locality",
    "qs:loc":"\u041d\u043e\u0432\u0430 \u0421\u0438\u043d\u044f\u0432\u043a\u0430",
    "qs:loc_alt":"Nova Syniavka",
    "qs:pop":0,
    "qs:type":"buffered point",
    "wof:name":"\u041d\u043e\u0432\u0430 \u0421\u0438\u043d\u044f\u0432\u043a\u0430",
    "wof:placetype":"locality"
},
  "geometry": {"coordinates":[27.730158,49.557165],"type":"Point"}
}