{
  "type": "Feature",
  "properties": {
    "gn:admin1_code":"27.0",
    "gn:asciiname":"Hannopil'",
    "gn:country_code":"UA",
    "gn:dem":224,
    "gn:feature_class":"P",
    "gn:feature_code":"PPL",
    "gn:name":"Hannopil\u2019",
    "gn:population":0,
    "gn:timezone":"Europe/Kiev",
    "iso:country":"UA",
    "name:rus_x_preferred":[
        "Annopol\u2019"
    ],
    "name:ukr_x_preferred":[
        "Hannopil\u2019"
    ],
    "name:ukr_x_variant":[
        "\u0413\u0430\u043d\u043d\u043e\u043f\u0456\u043b\u044c"
    ],
    "wof:name":"Hannopil'",
    "wof:placetype":"locality"
},
  "geometry": {"coordinates":[28.04025,50.60407],"type":"Point"}
}