{
  "type": "Feature",
  "properties": {
    "gn:admin1_code":"2.0",
    "gn:asciiname":"Krysky",
    "gn:country_code":"UA",
    "gn:dem":163,
    "gn:feature_class":"P",
    "gn:feature_code":"PPL",
    "gn:name":"Krysky",
    "gn:population":0,
    "gn:timezone":"Europe/Kiev",
    "iso:country":"UA",
    "name:eng_x_preferred":[
        "Kriski"
    ],
    "name:rus_x_preferred":[
        "\u041a\u0440\u0438\u0441\u043a\u0438"
    ],
    "name:ukr_x_preferred":[
        "Krysky"
    ],
    "name:ukr_x_variant":[
        "\u041a\u0440\u0438\u0441\u043a\u0438"
    ],
    "name:und_x_variant":[
        "Kriski"
    ],
    "wof:name":"Krysky",
    "wof:placetype":"locality"
},
  "geometry": {"coordinates":[32.95231,51.7396],"type":"Point"}
}