{
  "type": "Feature",
  "properties": {
    "gn:admin1_code":"4.0",
    "gn:asciiname":"Prohres",
    "gn:country_code":"UA",
    "gn:dem":71,
    "gn:feature_class":"P",
    "gn:feature_code":"PPL",
    "gn:name":"Prohres",
    "gn:population":0,
    "gn:timezone":"Europe/Kiev",
    "iso:country":"UA",
    "name:rus_x_preferred":[
        "\u041f\u0440\u043e\u0433\u0440\u0435\u0441\u0441"
    ],
    "name:ukr_x_preferred":[
        "Prohres"
    ],
    "name:ukr_x_variant":[
        "\u041f\u0440\u043e\u0433\u0440\u0435\u0441"
    ],
    "name:und_x_variant":[
        "Progress"
    ],
    "wof:name":"Prohres",
    "wof:placetype":"locality"
},
  "geometry": {"coordinates":[34.71346,47.67916],"type":"Point"}
}