{
  "type": "Feature",
  "properties": {
    "gn:admin1_code":"15.0",
    "gn:asciiname":"Khashchiv",
    "gn:country_code":"UA",
    "gn:dem":543,
    "gn:feature_class":"P",
    "gn:feature_code":"PPL",
    "gn:name":"Khashchiv",
    "gn:population":0,
    "gn:timezone":"Europe/Kiev",
    "iso:country":"UA",
    "name:pol_x_preferred":[
        "Chaszcz\u00f3w"
    ],
    "name:ron_x_preferred":[
        "Ha\u0219civ"
    ],
    "name:rus_x_preferred":[
        "\u0425\u0430\u0449\u0435\u0432"
    ],
    "name:ukr_x_preferred":[
        "Khashchiv"
    ],
    "name:ukr_x_variant":[
        "\u0425\u0430\u0449\u0456\u0432"
    ],
    "name:und_x_variant":[
        "Chaszcz\u00f3w",
        "Khaschuv",
        "Khvoshchev",
        "Khashchuv",
        "Khashchev"
    ],
    "name:zho_x_preferred":[
        "\u54c8\u5e0c\u592b"
    ],
    "wof:name":"Khashchiv",
    "wof:placetype":"locality"
},
  "geometry": {"coordinates":[22.78392,49.26177],"type":"Point"}
}