{
  "type": "Feature",
  "properties": {
    "gn:country":"UA",
    "gn:fcode":"PPL",
    "gn:population":4050,
    "iso:country":"UA",
    "name:ara_x_preferred":[
        "\u0641\u064a\u0644\u064a\u0643\u064a \u0633\u0648\u0631\u0648\u062a\u0634\u064a\u0646\u062a\u0633\u064a"
    ],
    "name:ceb_x_preferred":[
        "Velyki Sorochyntsi"
    ],
    "name:ces_x_preferred":[
        "Velyki Soro\u010dynci"
    ],
    "name:dan_x_preferred":[
        "Velikije Sorotjintsy"
    ],
    "name:deu_x_preferred":[
        "Welyki Sorotschynzi"
    ],
    "name:eng_x_preferred":[
        "Velyki Sorochyntsi"
    ],
    "name:fas_x_preferred":[
        "\u0648\u0644\u06cc\u06a9\u06cc \u0633\u0631\u0686\u06cc\u0646\u062a\u0633\u06cc"
    ],
    "name:fra_x_preferred":[
        "Velyki Sorochyntsi"
    ],
    "name:hye_x_preferred":[
        "\u054e\u0565\u056c\u056b\u056f\u056b\u0565 \u054d\u0578\u0580\u0578\u0579\u056b\u0576\u0581\u056b"
    ],
    "name:ita_x_preferred":[
        "Velyki Soro\u010dynci"
    ],
    "name:jpn_x_preferred":[
        "\u30f4\u30a7\u30eb\u30a3\u30fc\u30ad\u30fb\u30bd\u30ed\u30fc\u30c1\u30f3\u30c4\u30a3"
    ],
    "name:kat_x_preferred":[
        "\u10d5\u10d4\u10da\u10d8\u10d9\u10d8\u10d4-\u10e1\u10dd\u10e0\u10dd\u10e9\u10d8\u10dc\u10ea\u10d8"
    ],
    "name:lav_x_preferred":[
        "Veliki Soro\u010dinci"
    ],
    "name:nld_x_preferred":[
        "Velyki Sorochyntsi"
    ],
    "name:pol_x_preferred":[
        "Wielkie Soroczy\u0144ce"
    ],
    "name:ron_x_preferred":[
        "Vel\u00eeki Soroci\u00een\u021bi"
    ],
    "name:rus_x_preferred":[
        "\u0411\u043e\u043b\u044c\u0448\u0438\u0435 \u0421\u043e\u0440\u043e\u0447\u0438\u043d\u0446\u044b"
    ],
    "name:rus_x_variant":[
        "\u0412\u0435\u043b\u0438\u043a\u0438\u0435 \u0421\u043e\u0440\u043e\u0447\u0438\u043d\u0446\u044b"
    ],
    "name:slv_x_preferred":[
        "Veliki Soro\u010dnici"
    ],
    "name:ukr_x_preferred":[
        "Velyki Sorochyntsi"
    ],
    "name:ukr_x_variant":[
        "\u0412\u0435\u043b\u0438\u043a\u0456 \u0421\u043e\u0440\u043e\u0447\u0438\u043d\u0446\u0456"
    ],
    "name:und_x_variant":[
        "Bol\u2019shiye Sorochintsy"
    ],
    "name:zho_x_preferred":[
        "\u5927\u7d22\u7f85\u6b3d\u9f4a"
    ],
    "qs_pg:aaroncc":"UA",
    "qs_pg:gn_country":"UA",
    "qs_pg:gn_fcode":"PPL",
    "qs_pg:gn_pop":4050,
    "qs_pg:name":"Velikiye Sorochintsy",
    "qs_pg:name_adm0":"Ukraine",
    "qs_pg:name_adm1":"Poltavs\u00b4ka Oblast\u00b4",
    "qs_pg:photos_9k":1,
    "qs_pg:photos_9r":1,
    "qs_pg:photos_all":19,
    "qs_pg:photos_sr":0,
    "qs_pg:pop_sr":4,
    "qs_pg:qs_pg_placetype":"locality",
    "qs_pg:qs_pg_placetype_gp":"Town",
    "qs_pg:woe_adm0":23424976,
    "woe:adm0_id":23424976,
    "woe:name_adm0":"Ukraine",
    "woe:name_adm1":"Poltavs\u00b4ka Oblast\u00b4",
    "woe:placetype":"Town",
    "wof:name":"Velikiye Sorochintsy",
    "wof:placetype":"locality",
    "wof:population":4050
},
  "geometry": {"coordinates":[33.94144,50.02314],"type":"Point"}
}