{
  "type": "Feature",
  "properties": {
    "gn:admin1_code":"4.0",
    "gn:asciiname":"Malokozyrshchyna",
    "gn:country_code":"UA",
    "gn:dem":83,
    "gn:feature_class":"P",
    "gn:feature_code":"PPL",
    "gn:name":"Malokozyrshchyna",
    "gn:population":0,
    "gn:timezone":"Europe/Kiev",
    "iso:country":"UA",
    "name:ukr_x_preferred":[
        "Malokozyrshchyna"
    ],
    "name:ukr_x_variant":[
        "\u041c\u0430\u043b\u043e\u043a\u043e\u0437\u0438\u0440\u0449\u0438\u043d\u0430"
    ],
    "name:und_x_variant":[
        "Krivets",
        "Malaya Kozyrshchina",
        "Malokozyrshchina"
    ],
    "wof:name":"Malokozyrshchyna",
    "wof:placetype":"locality"
},
  "geometry": {"coordinates":[35.2822,49.04271],"type":"Point"}
}