{
  "type": "Feature",
  "properties": {
    "gn:admin1_code":"13.0",
    "gn:asciiname":"Targan",
    "gn:country_code":"UA",
    "gn:dem":178,
    "gn:feature_class":"P",
    "gn:feature_code":"PPL",
    "gn:name":"Targan",
    "gn:population":0,
    "gn:timezone":"Europe/Kiev",
    "iso:country":"UA",
    "name:und_x_variant":[
        "Torgan",
        "Targan"
    ],
    "wof:name":"Targan",
    "wof:placetype":"locality"
},
  "geometry": {"coordinates":[29.99162,49.54668],"type":"Point"}
}