{
  "type": "Feature",
  "properties": {
    "gn:admin1_code":"16.0",
    "gn:asciiname":"Maksimovka",
    "gn:country_code":"UA",
    "gn:dem":47,
    "gn:feature_class":"P",
    "gn:feature_code":"PPL",
    "gn:name":"Maksimovka",
    "gn:population":0,
    "gn:timezone":"Europe/Kiev",
    "iso:country":"UA",
    "name:lav_x_preferred":[
        "Maksimovka"
    ],
    "name:ukr_x_preferred":[
        "\u041c\u0430\u043a\u0441\u0438\u043c\u043e\u0432\u043a\u0430"
    ],
    "name:und_x_variant":[
        "Chernopol\u2019ye"
    ],
    "wof:name":"Maksimovka",
    "wof:placetype":"locality"
},
  "geometry": {"coordinates":[32.48141,46.964],"type":"Point"}
}