{
  "type": "Feature",
  "properties": {
    "gn:admin1_code":"2.0",
    "gn:asciiname":"Kalynivka",
    "gn:country_code":"UA",
    "gn:dem":133,
    "gn:feature_class":"P",
    "gn:feature_code":"PPL",
    "gn:name":"Kalynivka",
    "gn:population":0,
    "gn:timezone":"Europe/Kiev",
    "iso:country":"UA",
    "name:ceb_x_preferred":[
        "Kalynivka"
    ],
    "name:ces_x_preferred":[
        "Kalynivka"
    ],
    "name:deu_x_preferred":[
        "Kalyniwka"
    ],
    "name:slk_x_preferred":[
        "Kalynivka"
    ],
    "name:ukr_x_preferred":[
        "Kalynivka"
    ],
    "name:ukr_x_variant":[
        "\u041a\u0430\u043b\u0438\u043d\u0456\u0432\u043a\u0430"
    ],
    "name:und_x_variant":[
        "Kalinovka"
    ],
    "wof:name":"Kalynivka",
    "wof:placetype":"locality"
},
  "geometry": {"coordinates":[31.77646,50.77895],"type":"Point"}
}