{
  "type": "Feature",
  "properties": {
    "gn:admin1_code":"21.0",
    "gn:asciiname":"Gaydukov",
    "gn:country_code":"UA",
    "gn:dem":171,
    "gn:feature_class":"P",
    "gn:feature_code":"PPL",
    "gn:name":"Gaydukov",
    "gn:population":0,
    "gn:timezone":"Europe/Kiev",
    "iso:country":"UA",
    "wof:name":"Gaydukov",
    "wof:placetype":"locality"
},
  "geometry": {"coordinates":[34.14305,50.93503],"type":"Point"}
}