{
  "type": "Feature",
  "properties": {
    "gn:country":"UA",
    "gn:fcode":"PPL",
    "gn:population":1809,
    "iso:country":"UA",
    "name:bel_x_preferred":[
        "\u0427\u044d\u0440\u043d\u044d\u043b\u044b\u0446\u044f"
    ],
    "name:ceb_x_preferred":[
        "Chernelytsya"
    ],
    "name:ces_x_preferred":[
        "\u010cernelycja"
    ],
    "name:che_x_preferred":[
        "\u0427\u0435\u0440\u043d\u0435\u043b\u0438\u0446\u0430"
    ],
    "name:crh_x_preferred":[
        "\u00c7ernel\u0131ts\u00e2"
    ],
    "name:deu_x_preferred":[
        "Tschernelyzja"
    ],
    "name:eng_x_preferred":[
        "Chernelytsia"
    ],
    "name:fra_x_preferred":[
        "Tchernelytsia"
    ],
    "name:jpn_x_preferred":[
        "\u30c1\u30a7\u30eb\u30cd\u30ea\u30c4\u30a3\u30a2"
    ],
    "name:lit_x_preferred":[
        "\u010cernelicia"
    ],
    "name:pol_x_preferred":[
        "Czernelica"
    ],
    "name:ron_x_preferred":[
        "Cernel\u00ee\u021bea"
    ],
    "name:rus_x_preferred":[
        "\u0427\u0435\u0440\u043d\u0435\u043b\u0438\u0446\u044f"
    ],
    "name:rus_x_variant":[
        "\u0427\u0435\u0440\u043d\u0435\u043b\u0438\u0446\u0430"
    ],
    "name:ukr_x_preferred":[
        "\u0427\u0435\u0440\u043d\u0435\u043b\u0438\u0446\u044f"
    ],
    "name:uzb_x_preferred":[
        "Chernelitsa"
    ],
    "name:zho_x_preferred":[
        "\u5207\u723e\u6d85\u5229\u9f4a\u4e9e"
    ],
    "qs_pg:aaroncc":"UA",
    "qs_pg:gn_country":"UA",
    "qs_pg:gn_fcode":"PPL",
    "qs_pg:gn_pop":1809,
    "qs_pg:name":"Chernelytsya",
    "qs_pg:photos_9r":0,
    "qs_pg:photos_sr":0,
    "qs_pg:pop_sr":3,
    "qs_pg:qs_pg_placetype":"locality",
    "wof:name":"Chernelytsya",
    "wof:placetype":"locality",
    "wof:population":1809
},
  "geometry": {"coordinates":[25.42477,48.81207],"type":"Point"}
}