{
  "type": "Feature",
  "properties": {
    "gn:gn_country":"UA",
    "gn:gn_fcode":"PPL",
    "gn:gn_pop":1809,
    "gn:population":1809,
    "iso:country":"UA",
    "name:deu_x_preferred":[
        "Tschernelyzja"
    ],
    "name:eng_x_preferred":[
        "Chernelytsia"
    ],
    "name:pol_x_preferred":[
        "Czernelica"
    ],
    "name:ron_x_preferred":[
        "Cernel\u00ee\u021bea"
    ],
    "name:rus_x_preferred":[
        "\u0427\u0435\u0440\u043d\u0435\u043b\u0438\u0446\u044f"
    ],
    "name:ukr_x_preferred":[
        "\u0427\u0435\u0440\u043d\u0435\u043b\u0438\u0446\u044f"
    ],
    "name:unk_x_variant":[
        "Czernelica"
    ],
    "name:zho_x_preferred":[
        "\u5207\u723e\u6d85\u5229\u9f4a\u4e9e"
    ],
    "qs_pg:aaroncc":"UA",
    "qs_pg:gn_country":"UA",
    "qs_pg:gn_fcode":"PPL",
    "qs_pg:gn_pop":1809,
    "qs_pg:name":"Chernelytsya",
    "qs_pg:photos_9r":0,
    "qs_pg:photos_sr":0,
    "qs_pg:pop_sr":3,
    "qs_pg:qs_pg_placetype":"locality",
    "wof:name":"Chernelytsya",
    "wof:placetype":"locality",
    "wof:population":1809
},
  "geometry": {"coordinates":[25.42477,48.81207],"type":"Point"}
}