{
  "type": "Feature",
  "properties": {
    "gn:admin1_code":"24.0",
    "gn:asciiname":"Buzhanka",
    "gn:country_code":"UA",
    "gn:dem":218,
    "gn:feature_class":"P",
    "gn:feature_code":"PPL",
    "gn:name":"Buzhanka",
    "gn:population":0,
    "gn:timezone":"Europe/Kiev",
    "iso:country":"UA",
    "name:ukr_x_preferred":[
        "\u0411\u0443\u0436\u0430\u043d\u043a\u0430"
    ],
    "name:und_x_variant":[
        "Bozhanka",
        "Buzhanka"
    ],
    "wof:name":"Buzhanka",
    "wof:placetype":"locality"
},
  "geometry": {"coordinates":[24.12697,50.74886],"type":"Point"}
}