{
  "type": "Feature",
  "properties": {
    "gn:admin1_code":"24.0",
    "gn:asciiname":"Svalovychi",
    "gn:country_code":"UA",
    "gn:dem":142,
    "gn:feature_class":"P",
    "gn:feature_code":"PPL",
    "gn:name":"Svalovychi",
    "gn:population":0,
    "gn:timezone":"Europe/Kiev",
    "iso:country":"UA",
    "name:ukr_x_preferred":[
        "Svalovychi"
    ],
    "name:ukr_x_variant":[
        "\u0421\u0432\u0430\u043b\u043e\u0432\u0438\u0447\u0456"
    ],
    "name:und_x_variant":[
        "Svalovichi"
    ],
    "wof:name":"Svalovychi",
    "wof:placetype":"locality"
},
  "geometry": {"coordinates":[25.63394,51.86727],"type":"Point"}
}