{
  "type": "Feature",
  "properties": {
    "gn:admin1_code":"21.0",
    "gn:asciiname":"Vovkivka",
    "gn:country_code":"UA",
    "gn:dem":194,
    "gn:feature_class":"P",
    "gn:feature_code":"PPL",
    "gn:name":"Vovkivka",
    "gn:population":0,
    "gn:timezone":"Europe/Kiev",
    "iso:country":"UA",
    "name:ukr_x_preferred":[
        "Vovkivka"
    ],
    "name:ukr_x_variant":[
        "\u0412\u043e\u0432\u043a\u0456\u0432\u043a\u0430"
    ],
    "name:und_x_variant":[
        "Volkovka"
    ],
    "wof:name":"Vovkivka",
    "wof:placetype":"locality"
},
  "geometry": {"coordinates":[34.25859000000001,51.51437],"type":"Point"}
}