{
  "type": "Feature",
  "properties": {
    "iso:country":"UA",
    "name:deu_x_preferred":[
        "Trypillja"
    ],
    "name:eng_x_preferred":[
        "Trypillia"
    ],
    "name:fas_x_preferred":[
        "\u062a\u0631\u06cc\u067e\u06cc\u0644\u06cc\u0627"
    ],
    "name:jpn_x_preferred":[
        "\u30c8\u30ea\u30d4\u30fc\u30c3\u30ea\u30e3"
    ],
    "name:kor_x_preferred":[
        "\ud2b8\ub9ac\ud544\ub7b4"
    ],
    "name:nld_x_preferred":[
        "Trypillia"
    ],
    "name:pol_x_preferred":[
        "Trypol"
    ],
    "name:ron_x_preferred":[
        "Tr\u00eepillea"
    ],
    "name:rus_x_preferred":[
        "\u0422\u0440\u0438\u043f\u043e\u043b\u044c\u0435"
    ],
    "name:spa_x_preferred":[
        "Trypillia"
    ],
    "name:srp_x_preferred":[
        "\u0422\u0440\u0438\u043f\u043e\u0459\u0435"
    ],
    "name:ukr_x_preferred":[
        "\u0422\u0440\u0438\u043f\u0456\u043b\u043b\u044f"
    ],
    "name:vie_x_preferred":[
        "Tripillia"
    ],
    "name:zho_x_preferred":[
        "\u7279\u91cc\u76ae\u723e\u5229\u4e9e"
    ],
    "qs:a0":"\u0423\u043a\u0440\u0430\u0457\u043d\u0430",
    "qs:a1":"*\u041a\u0438\u0457\u0432\u0441\u044c\u043a\u0430",
    "qs:a1_alt":"Kyivs'ka",
    "qs:a1r":"0",
    "qs:a2":"\u041e\u0431\u0443\u0445\u0456\u0432\u0441\u044c\u043a\u0438\u0439",
    "qs:a2_alt":"Obukhivs'kyi",
    "qs:adm0":"\u0423\u043a\u0440\u0430\u0457\u043d\u0430",
    "qs:la_lc":"*",
    "qs:level":"locality",
    "qs:loc":"\u0422\u0440\u0438\u043f\u0456\u043b\u043b\u044f",
    "qs:loc_alt":"Trypillia",
    "qs:pop":0,
    "qs:type":"buffered point",
    "wd:wordcount":426,
    "wof:name":"\u0422\u0440\u0438\u043f\u0456\u043b\u043b\u044f",
    "wof:placetype":"locality"
},
  "geometry": {"coordinates":[30.776076,50.109276],"type":"Point"}
}