{
  "type": "Feature",
  "properties": {
    "gn:admin1_code":"19.0",
    "gn:asciiname":"Molodizhne",
    "gn:country_code":"UA",
    "gn:dem":222,
    "gn:feature_class":"P",
    "gn:feature_code":"PPL",
    "gn:name":"Molodizhne",
    "gn:population":0,
    "gn:timezone":"Europe/Kiev",
    "iso:country":"UA",
    "name:ukr_x_preferred":[
        "Molodizhne"
    ],
    "name:ukr_x_variant":[
        "\u041c\u043e\u043b\u043e\u0434\u0456\u0436\u043d\u0435"
    ],
    "wof:name":"Molodizhne",
    "wof:placetype":"locality"
},
  "geometry": {"coordinates":[26.01246,50.44187],"type":"Point"}
}