{
  "type": "Feature",
  "properties": {
    "gn:admin1_code":"5.0",
    "gn:admin2_code":"713172",
    "gn:asciiname":"Kalynivka",
    "gn:country_code":"UA",
    "gn:dem":218,
    "gn:feature_class":"P",
    "gn:feature_code":"PPL",
    "gn:name":"Kalynivka",
    "gn:population":0,
    "gn:timezone":"Europe/Kiev",
    "iso:country":"UA",
    "name:ceb_x_preferred":[
        "Kalynivka"
    ],
    "name:ces_x_preferred":[
        "Kalynivka"
    ],
    "name:deu_x_preferred":[
        "Kalyniwka"
    ],
    "name:hye_x_historical":[
        "\u053f\u0561\u056c\u056b\u0576\u056b\u0576\u0561"
    ],
    "name:hye_x_preferred":[
        "\u053f\u0561\u056c\u056b\u0576\u056b\u0576\u0561"
    ],
    "name:rus_x_preferred":[
        "\u041a\u0430\u043b\u0438\u043d\u043e\u0432\u043a\u0430"
    ],
    "name:slk_x_preferred":[
        "Kalynivka"
    ],
    "name:ukr_x_historical":[
        "Kalinina",
        "\u041a\u0430\u043b\u0456\u043d\u0456\u043d\u0430"
    ],
    "name:ukr_x_preferred":[
        "Kalinina"
    ],
    "name:ukr_x_variant":[
        "\u041a\u0430\u043b\u0456\u043d\u0456\u043d\u0430",
        "\u041a\u0430\u043b\u0438\u043d\u0456\u0432\u043a\u0430",
        "Kalynivka"
    ],
    "wof:name":"Kalynivka",
    "wof:placetype":"locality"
},
  "geometry": {"coordinates":[37.85991,48.61103],"type":"Point"}
}