{
  "type": "Feature",
  "properties": {
    "gn:admin1_code":"4.0",
    "gn:asciiname":"Prysten'",
    "gn:country_code":"UA",
    "gn:dem":79,
    "gn:feature_class":"P",
    "gn:feature_code":"PPL",
    "gn:name":"Prysten\u2019",
    "gn:population":0,
    "gn:timezone":"Europe/Kiev",
    "iso:country":"UA",
    "name:rus_x_preferred":[
        "Pristen\u2019"
    ],
    "name:ukr_x_preferred":[
        "Prysten\u2019"
    ],
    "name:ukr_x_variant":[
        "\u041f\u0440\u0438\u0441\u0442\u0435\u043d\u044c"
    ],
    "wof:name":"Prysten'",
    "wof:placetype":"locality"
},
  "geometry": {"coordinates":[35.76631,48.35991],"type":"Point"}
}