{
  "type": "Feature",
  "properties": {
    "gn:admin1_code":"15.0",
    "gn:asciiname":"Selisko",
    "gn:country_code":"UA",
    "gn:dem":321,
    "gn:feature_class":"P",
    "gn:feature_code":"PPL",
    "gn:name":"Selisko",
    "gn:population":0,
    "gn:timezone":"Europe/Kiev",
    "iso:country":"UA",
    "name:und_x_variant":[
        "Sedliska",
        "Selisko"
    ],
    "wof:name":"Selisko",
    "wof:placetype":"locality"
},
  "geometry": {"coordinates":[24.12768,49.66651],"type":"Point"}
}