{
  "type": "Feature",
  "properties": {
    "gn:admin1_code":"06",
    "gn:asciiname":"Vylky",
    "gn:country_code":"UA",
    "gn:dem":287,
    "gn:feature_class":"P",
    "gn:feature_code":"PPL",
    "gn:name":"Vylky",
    "gn:population":0,
    "gn:timezone":"Europe/Kiev",
    "iso:country":"UA",
    "name:ukr_x_preferred":[
        "Vylky"
    ],
    "name:ukr_x_variant":[
        "\u0412\u0438\u043b\u043a\u0438"
    ],
    "wof:name":"Vylky",
    "wof:placetype":"locality"
},
  "geometry": {"coordinates":[24.30078,49.13156],"type":"Point"}
}