{
  "type": "Feature",
  "properties": {
    "gn:admin1_code":"21.0",
    "gn:asciiname":"Zhuravka",
    "gn:country_code":"UA",
    "gn:dem":177,
    "gn:feature_class":"P",
    "gn:feature_code":"PPL",
    "gn:name":"Zhuravka",
    "gn:population":0,
    "gn:timezone":"Europe/Kiev",
    "iso:country":"UA",
    "name:ukr_x_preferred":[
        "Zhuravka"
    ],
    "name:ukr_x_variant":[
        "\u0416\u0443\u0440\u0430\u0432\u043a\u0430"
    ],
    "wof:name":"Zhuravka",
    "wof:placetype":"locality"
},
  "geometry": {"coordinates":[34.98771,51.22181],"type":"Point"}
}