{
  "type": "Feature",
  "properties": {
    "gn:admin1_code":"5.0",
    "gn:asciiname":"Blyzhnye",
    "gn:country_code":"UA",
    "gn:dem":226,
    "gn:feature_class":"P",
    "gn:feature_code":"PPL",
    "gn:name":"Blyzhnye",
    "gn:population":0,
    "gn:timezone":"Europe/Kiev",
    "iso:country":"UA",
    "name:ukr_x_preferred":[
        "Blyzhnye"
    ],
    "name:ukr_x_variant":[
        "\u0411\u043b\u0438\u0436\u043d\u0454"
    ],
    "wof:name":"Blyzhnye",
    "wof:placetype":"locality"
},
  "geometry": {"coordinates":[37.54734000000001,47.60286],"type":"Point"}
}