{
  "type": "Feature",
  "properties": {
    "gn:admin1_code":"8.0",
    "gn:asciiname":"Malaya Znamenka",
    "gn:country_code":"UA",
    "gn:dem":39,
    "gn:feature_class":"P",
    "gn:feature_code":"PPL",
    "gn:name":"Malaya Znamenka",
    "gn:population":0,
    "gn:timezone":"Europe/Kiev",
    "iso:country":"UA",
    "wof:name":"Malaya Znamenka",
    "wof:placetype":"locality"
},
  "geometry": {"coordinates":[32.93185,46.79643],"type":"Point"}
}