{
  "type": "Feature",
  "properties": {
    "gn:admin1_code":"18.0",
    "gn:asciiname":"Yemtsi",
    "gn:country_code":"UA",
    "gn:dem":146,
    "gn:feature_class":"P",
    "gn:feature_code":"PPL",
    "gn:name":"Yemtsi",
    "gn:population":0,
    "gn:timezone":"Europe/Kiev",
    "iso:country":"UA",
    "name:ukr_x_preferred":[
        "Yemtsi"
    ],
    "name:ukr_x_variant":[
        "\u0404\u043c\u0446\u0456"
    ],
    "wof:name":"Yemtsi",
    "wof:placetype":"locality"
},
  "geometry": {"coordinates":[33.40363,49.92748],"type":"Point"}
}