{
  "type": "Feature",
  "properties": {
    "gn:admin1_code":"4.0",
    "gn:asciiname":"Andrusivka",
    "gn:country_code":"UA",
    "gn:dem":82,
    "gn:feature_class":"P",
    "gn:feature_code":"PPL",
    "gn:name":"Andrusivka",
    "gn:population":0,
    "gn:timezone":"Europe/Kiev",
    "iso:country":"UA",
    "name:ukr_x_preferred":[
        "Andrusivka"
    ],
    "name:ukr_x_variant":[
        "\u0410\u043d\u0434\u0440\u0443\u0441\u0456\u0432\u043a\u0430"
    ],
    "name:und_x_variant":[
        "Andrusovka"
    ],
    "wof:name":"Andrusivka",
    "wof:placetype":"locality"
},
  "geometry": {"coordinates":[33.65046,47.88112],"type":"Point"}
}