{
  "type": "Feature",
  "properties": {
    "gn:admin1_code":"2.0",
    "gn:asciiname":"Horbove",
    "gn:country_code":"UA",
    "gn:dem":125,
    "gn:feature_class":"P",
    "gn:feature_code":"PPL",
    "gn:name":"Horbove",
    "gn:population":0,
    "gn:timezone":"Europe/Kiev",
    "iso:country":"UA",
    "name:eng_x_preferred":[
        "Gorbovo"
    ],
    "name:rus_x_preferred":[
        "\u0413\u043e\u0440\u0431\u043e\u0432\u043e"
    ],
    "name:ukr_x_preferred":[
        "Horbove"
    ],
    "name:ukr_x_variant":[
        "\u0413\u043e\u0440\u0431\u043e\u0432\u0435"
    ],
    "name:und_x_variant":[
        "Gorbov",
        "Gorbovo"
    ],
    "wof:name":"Horbove",
    "wof:placetype":"locality"
},
  "geometry": {"coordinates":[33.22743,51.93857],"type":"Point"}
}