{
  "type": "Feature",
  "properties": {
    "iso:country":"UA",
    "name:arz_x_preferred":[
        "\u0646\u0647\u0631 \u0643\u0648\u062f\u064a\u0645\u0627"
    ],
    "name:ast_x_preferred":[
        "R\u00edu Kodyma"
    ],
    "name:avk_x_preferred":[
        "Kodima"
    ],
    "name:bar_x_preferred":[
        "Kodyma"
    ],
    "name:bel_x_variant":[
        "\u041a\u0430\u0434\u044b\u043c\u0430"
    ],
    "name:ceb_x_preferred":[
        "Kodyma"
    ],
    "name:cym_x_preferred":[
        "Afon Kodyma"
    ],
    "name:deu_x_preferred":[
        "Kodyma"
    ],
    "name:eng_x_preferred":[
        "Kodyma River"
    ],
    "name:est_x_preferred":[
        "Kod\u00f5ma j\u00f5gi"
    ],
    "name:est_x_variant":[
        "Kod\u00f5ma"
    ],
    "name:gle_x_preferred":[
        "Abhainn Kodyma"
    ],
    "name:nno_x_preferred":[
        "Kodyma"
    ],
    "name:nno_x_variant":[
        "Kodymaelva"
    ],
    "name:pol_x_preferred":[
        "Kodyma"
    ],
    "name:rus_x_preferred":[
        "\u041a\u043e\u0434\u044b\u043c\u0430"
    ],
    "name:ukr_x_preferred":[
        "\u041a\u043e\u0434\u0438\u043c\u0430"
    ],
    "name:uzb_x_preferred":[
        "Kodima"
    ],
    "name:zho_x_preferred":[
        "\u79d1\u5b63\u99ac\u6cb3"
    ],
    "name:zho_x_variant":[
        "\u79d1\u8fea\u9a6c\u6cb3"
    ],
    "qs:a0":"\u0423\u043a\u0440\u0430\u0457\u043d\u0430",
    "qs:a1":"*\u041e\u0434\u0435\u0441\u044c\u043a\u0430",
    "qs:a1_alt":"Odes'ka",
    "qs:a1r":"0",
    "qs:a2":"\u0411\u0430\u043b\u0442\u0441\u044c\u043a\u0438\u0439",
    "qs:a2_alt":"Balts'kyi",
    "qs:adm0":"\u0423\u043a\u0440\u0430\u0457\u043d\u0430",
    "qs:la_lc":"*",
    "qs:level":"locality",
    "qs:loc":"\u0413\u043e\u043b\u044c\u043c\u0430",
    "qs:loc_alt":"Hol'ma",
    "qs:pop":0,
    "qs:type":"buffered point",
    "wd:wordcount":105,
    "wof:name":"\u0413\u043e\u043b\u044c\u043c\u0430",
    "wof:placetype":"locality"
},
  "geometry": {"coordinates":[29.835783,47.925975],"type":"Point"}
}