{
  "type": "Feature",
  "properties": {
    "gn:admin1_code":"19.0",
    "gn:asciiname":"Khotyn",
    "gn:country_code":"UA",
    "gn:dem":186,
    "gn:feature_class":"P",
    "gn:feature_code":"PPL",
    "gn:name":"Khotyn",
    "gn:population":0,
    "gn:timezone":"Europe/Kiev",
    "iso:country":"UA",
    "name:ukr_x_preferred":[
        "Khotyn"
    ],
    "name:ukr_x_variant":[
        "\u0425\u043e\u0442\u0438\u043d"
    ],
    "name:und_x_variant":[
        "Khotsin",
        "Khotin"
    ],
    "wof:name":"Khotyn",
    "wof:placetype":"locality"
},
  "geometry": {"coordinates":[26.22431,50.70817],"type":"Point"}
}