{
  "type": "Feature",
  "properties": {
    "gn:admin1_code":"19.0",
    "gn:asciiname":"Khotyn",
    "gn:country_code":"UA",
    "gn:dem":186,
    "gn:feature_class":"P",
    "gn:feature_code":"PPL",
    "gn:name":"Khotyn",
    "gn:population":0,
    "gn:timezone":"Europe/Kiev",
    "iso:country":"UA",
    "name:ara_x_preferred":[
        "\u062e\u0648\u062a\u064a\u0646"
    ],
    "name:aze_x_preferred":[
        "Xot\u0131n"
    ],
    "name:bak_x_preferred":[
        "\u0425\u043e\u0442\u0438\u043d"
    ],
    "name:bel_x_preferred":[
        "\u0425\u0430\u0446\u0456\u043d"
    ],
    "name:bul_x_preferred":[
        "\u0425\u043e\u0442\u0438\u043d"
    ],
    "name:cat_x_preferred":[
        "Khot\u00edn"
    ],
    "name:ceb_x_preferred":[
        "Khotyn"
    ],
    "name:ces_x_preferred":[
        "Chotyn"
    ],
    "name:crh_x_preferred":[
        "Hot\u0131n"
    ],
    "name:dan_x_preferred":[
        "Khotin"
    ],
    "name:deu_x_preferred":[
        "Chotyn"
    ],
    "name:epo_x_preferred":[
        "\u0124otin"
    ],
    "name:fas_x_preferred":[
        "\u062e\u0648\u062a\u06cc\u0646"
    ],
    "name:fin_x_preferred":[
        "H\u2019otyn"
    ],
    "name:fra_x_preferred":[
        "Khotyn"
    ],
    "name:glg_x_preferred":[
        "Khotin"
    ],
    "name:heb_x_preferred":[
        "\u05d7\u05d5\u05d8\u05d9\u05df"
    ],
    "name:hrv_x_preferred":[
        "Hotin"
    ],
    "name:hsb_x_preferred":[
        "Chotyn"
    ],
    "name:hun_x_preferred":[
        "Hotin"
    ],
    "name:hye_x_preferred":[
        "\u053d\u0578\u057f\u056b\u0576"
    ],
    "name:ita_x_preferred":[
        "Chotyn"
    ],
    "name:kat_x_preferred":[
        "\u10ee\u10dd\u10e2\u10d8\u10dc\u10d8"
    ],
    "name:lav_x_preferred":[
        "Hotina"
    ],
    "name:lit_x_preferred":[
        "Chotynas"
    ],
    "name:nld_x_preferred":[
        "Chotyn"
    ],
    "name:nno_x_preferred":[
        "Khotyn"
    ],
    "name:pol_x_preferred":[
        "Chocim"
    ],
    "name:ron_x_preferred":[
        "Hotin"
    ],
    "name:rus_x_preferred":[
        "\u0425\u043e\u0442\u0438\u043d"
    ],
    "name:sco_x_preferred":[
        "Khotyn"
    ],
    "name:spa_x_preferred":[
        "Jot\u00edn"
    ],
    "name:srp_x_preferred":[
        "\u0425\u043e\u0442\u0438\u043d"
    ],
    "name:swe_x_preferred":[
        "Chotyn"
    ],
    "name:tur_x_preferred":[
        "Hotin"
    ],
    "name:ukr_x_preferred":[
        "Khotyn"
    ],
    "name:ukr_x_variant":[
        "\u0425\u043e\u0442\u0438\u043d"
    ],
    "name:und_x_variant":[
        "Khotsin"
    ],
    "name:vie_x_preferred":[
        "Khotyn"
    ],
    "wof:name":"Khotyn",
    "wof:placetype":"locality"
},
  "geometry": {"coordinates":[26.22431,50.70817],"type":"Point"}
}