{
  "type": "Feature",
  "properties": {
    "gn:admin1_code":"5.0",
    "gn:asciiname":"Myrolyubivka",
    "gn:country_code":"UA",
    "gn:dem":127,
    "gn:feature_class":"P",
    "gn:feature_code":"PPL",
    "gn:name":"Myrolyubivka",
    "gn:population":0,
    "gn:timezone":"Europe/Kiev",
    "iso:country":"UA",
    "name:ukr_x_preferred":[
        "Myrolyubivka"
    ],
    "name:ukr_x_variant":[
        "\u041c\u0438\u0440\u043e\u043b\u044e\u0431\u0456\u0432\u043a\u0430"
    ],
    "wof:name":"Myrolyubivka",
    "wof:placetype":"locality"
},
  "geometry": {"coordinates":[37.37625,48.30105],"type":"Point"}
}