{
  "type": "Feature",
  "properties": {
    "gn:admin1_code":"4.0",
    "gn:asciiname":"Vynohradivka",
    "gn:country_code":"UA",
    "gn:dem":165,
    "gn:feature_class":"P",
    "gn:feature_code":"PPL",
    "gn:name":"Vynohradivka",
    "gn:population":0,
    "gn:timezone":"Europe/Kiev",
    "iso:country":"UA",
    "name:eng_x_preferred":[
        "Vynohradivka"
    ],
    "name:rus_x_preferred":[
        "\u0412\u0438\u043d\u043e\u0433\u0440\u0430\u0434\u043e\u0432\u043a\u0430"
    ],
    "name:ukr_x_preferred":[
        "\u0412\u0438\u043d\u043e\u0433\u0440\u0430\u0434\u0456\u0432\u043a\u0430"
    ],
    "name:und_x_variant":[
        "Vinogradovka"
    ],
    "wof:name":"Vynohradivka",
    "wof:placetype":"locality"
},
  "geometry": {"coordinates":[33.72752,48.5525],"type":"Point"}
}