{
  "type": "Feature",
  "properties": {
    "gn:admin1_code":"23.0",
    "gn:asciiname":"Belikovtsy",
    "gn:country_code":"UA",
    "gn:dem":300,
    "gn:feature_class":"P",
    "gn:feature_code":"PPL",
    "gn:name":"Belikovtsy",
    "gn:population":0,
    "gn:timezone":"Europe/Kiev",
    "iso:country":"UA",
    "name:und_x_variant":[
        "Bel\u2019kovtsy",
        "Belikovtsy"
    ],
    "wof:name":"Belikovtsy",
    "wof:placetype":"locality"
},
  "geometry": {"coordinates":[28.03339,49.12276],"type":"Point"}
}