{
  "type": "Feature",
  "properties": {
    "gn:admin1_code":"23.0",
    "gn:asciiname":"Trostyanets'",
    "gn:country_code":"UA",
    "gn:dem":284,
    "gn:feature_class":"P",
    "gn:feature_code":"PPL",
    "gn:name":"Trostyanets\u2019",
    "gn:population":0,
    "gn:timezone":"Europe/Kiev",
    "iso:country":"UA",
    "wof:name":"Trostyanets'",
    "wof:placetype":"locality"
},
  "geometry": {"coordinates":[28.61023,49.09694],"type":"Point"}
}