{
  "type": "Feature",
  "properties": {
    "iso:country":"UA",
    "qs:a0":"\u0423\u043a\u0440\u0430\u0457\u043d\u0430",
    "qs:a1":"*\u0425\u043c\u0435\u043b\u044c\u043d\u0438\u0446\u044c\u043a\u0430",
    "qs:a1_alt":"Khmel'nyts'ka",
    "qs:a1r":"0",
    "qs:a2":"\u041a\u0430\u043c'\u044f\u043d\u0435\u0446\u044c-\u041f\u043e\u0434\u0456\u043b\u044c\u0441\u044c\u043a\u0438\u0439",
    "qs:a2_alt":"Kamyanets'-Podil's'kyi",
    "qs:adm0":"\u0423\u043a\u0440\u0430\u0457\u043d\u0430",
    "qs:la_lc":"*",
    "qs:level":"locality",
    "qs:loc":"\u0416\u043e\u0432\u0442\u043d\u0435\u0432\u0435",
    "qs:loc_alt":"Zhovtneve",
    "qs:pop":0,
    "qs:type":"buffered point",
    "wd:wordcount":105,
    "wof:name":"\u0416\u043e\u0432\u0442\u043d\u0435\u0432\u0435",
    "wof:placetype":"locality"
},
  "geometry": {"coordinates":[26.621978,48.66677],"type":"Point"}
}