{
  "type": "Feature",
  "properties": {
    "gn:admin1_code":"2.0",
    "gn:asciiname":"Voskresens'ke",
    "gn:country_code":"UA",
    "gn:dem":108,
    "gn:feature_class":"P",
    "gn:feature_code":"PPL",
    "gn:name":"Voskresens\u2019ke",
    "gn:population":0,
    "gn:timezone":"Europe/Kiev",
    "iso:country":"UA",
    "name:ukr_x_preferred":[
        "Voskresens\u2019ke"
    ],
    "name:ukr_x_variant":[
        "\u0412\u043e\u0441\u043a\u0440\u0435\u0441\u0435\u043d\u0441\u044c\u043a\u0435"
    ],
    "name:und_x_variant":[
        "Voskresenskoye"
    ],
    "wof:name":"Voskresens'ke",
    "wof:placetype":"locality"
},
  "geometry": {"coordinates":[32.65446,50.48545],"type":"Point"}
}