{
  "type": "Feature",
  "properties": {
    "gn:admin1_code":"22.0",
    "gn:asciiname":"Budilov",
    "gn:country_code":"UA",
    "gn:dem":351,
    "gn:feature_class":"P",
    "gn:feature_code":"PPL",
    "gn:name":"Budilov",
    "gn:population":0,
    "gn:timezone":"Europe/Kiev",
    "iso:country":"UA",
    "name:und_x_variant":[
        "Budy\u0142\u00f3w",
        "Budyluv",
        "Budylov",
        "Budyliv",
        "Budilov"
    ],
    "wof:name":"Budilov",
    "wof:placetype":"locality"
},
  "geometry": {"coordinates":[25.24209,49.52841],"type":"Point"}
}