{
  "type": "Feature",
  "properties": {
    "gn:admin1_code":"5.0",
    "gn:asciiname":"Dniproenerhiya",
    "gn:country_code":"UA",
    "gn:dem":104,
    "gn:feature_class":"P",
    "gn:feature_code":"PPL",
    "gn:name":"Dniproenerhiya",
    "gn:population":0,
    "gn:timezone":"Europe/Kiev",
    "iso:country":"UA",
    "name:ukr_x_preferred":[
        "Dniproenerhiya"
    ],
    "name:ukr_x_variant":[
        "\u0414\u043d\u0456\u043f\u0440\u043e\u0435\u043d\u0435\u0440\u0433\u0456\u044f"
    ],
    "name:und_x_variant":[
        "Dneproznergiya"
    ],
    "wof:name":"Dniproenerhiya",
    "wof:placetype":"locality"
},
  "geometry": {"coordinates":[36.79926,47.92105],"type":"Point"}
}