{
  "type": "Feature",
  "properties": {
    "gn:admin1_code":"19.0",
    "gn:asciiname":"Zhalyn",
    "gn:country_code":"UA",
    "gn:dem":169,
    "gn:feature_class":"P",
    "gn:feature_code":"PPL",
    "gn:name":"Zhalyn",
    "gn:population":0,
    "gn:timezone":"Europe/Kiev",
    "iso:country":"UA",
    "name:ukr_x_preferred":[
        "Zhalyn"
    ],
    "name:ukr_x_variant":[
        "\u0416\u0430\u043b\u0438\u043d"
    ],
    "name:und_x_variant":[
        "Zhalin"
    ],
    "wof:name":"Zhalyn",
    "wof:placetype":"locality"
},
  "geometry": {"coordinates":[26.30034,50.96044000000001],"type":"Point"}
}