{
  "type": "Feature",
  "properties": {
    "gn:admin1_code":"26.0",
    "gn:asciiname":"Novo-Kirillovskiy",
    "gn:cc2":"UA",
    "gn:country_code":"UA",
    "gn:dem":135,
    "gn:feature_class":"P",
    "gn:feature_code":"PPL",
    "gn:name":"Novo-Kirillovskiy",
    "gn:population":0,
    "gn:timezone":"Europe/Zaporozhye",
    "iso:country":"UA",
    "name:und_x_variant":[
        "Kirilovskiy",
        "Yagodnyy",
        "Novo-Kirillovskiy"
    ],
    "wof:name":"Novo-Kirillovskiy",
    "wof:placetype":"locality"
},
  "geometry": {"coordinates":[36.11667,47.55],"type":"Point"}
}