{
  "type": "Feature",
  "properties": {
    "gn:country":"UA",
    "gn:fcode":"PPL",
    "gn:population":0,
    "iso:country":"UA",
    "name:crh_x_historical":[
        "B\u00fcj\u00fck Lambat"
    ],
    "name:crh_x_preferred":[
        "B\u00fcj\u00fck Lambat"
    ],
    "name:eng_x_preferred":[
        "Maly Mayak"
    ],
    "name:rus_x_historical":[
        "\u0411\u0438\u044e\u0301\u043a-\u041b\u0430\u043c\u0431\u0430\u0301\u0442"
    ],
    "name:rus_x_preferred":[
        "\u0411\u0438\u044e\u0301\u043a-\u041b\u0430\u043c\u0431\u0430\u0301\u0442"
    ],
    "name:rus_x_variant":[
        "\u041c\u0430\u043b\u044b\u0439 \u041c\u0430\u044f\u043a"
    ],
    "name:ukr_x_preferred":[
        "\u041c\u0430\u043b\u0438\u0439 \u041c\u0430\u044f\u043a"
    ],
    "qs_pg:aaroncc":"UA",
    "qs_pg:gn_country":"UA",
    "qs_pg:gn_fcode":"PPL",
    "qs_pg:gn_pop":0,
    "qs_pg:name":"Malyy Mayak",
    "qs_pg:name_adm0":"Ukraine",
    "qs_pg:name_adm1":"Avtonomna Respublika Krym",
    "qs_pg:photos":184,
    "qs_pg:photos_1k":37,
    "qs_pg:photos_9k":1,
    "qs_pg:photos_9r":4,
    "qs_pg:photos_all":184,
    "qs_pg:photos_sr":4,
    "qs_pg:pop_sr":0,
    "qs_pg:qs_pg_placetype":"locality",
    "qs_pg:qs_pg_placetype_gp":"Town",
    "qs_pg:woe_adm0":23424976,
    "woe:adm0_id":23424976,
    "woe:name_adm0":"Ukraine",
    "woe:name_adm1":"Avtonomna Respublika Krym",
    "woe:placetype":"Town",
    "wof:name":"Malyy Mayak",
    "wof:placetype":"locality",
    "wof:population":2298
},
  "geometry": {"coordinates":[34.36421,44.61508],"type":"Point"}
}