{
  "type": "Feature",
  "properties": {
    "gn:admin1_code":"2.0",
    "gn:asciiname":"Khutora Ryabushinskiye",
    "gn:cc2":"UA",
    "gn:country_code":"UA",
    "gn:dem":125,
    "gn:feature_class":"P",
    "gn:feature_code":"PPL",
    "gn:name":"Khutora Ryabushinskiye",
    "gn:population":0,
    "gn:timezone":"Europe/Kiev",
    "iso:country":"UA",
    "name:und_x_variant":[
        "Ryabushinskiye",
        "Khutora Ryabushinskiye"
    ],
    "wof:name":"Khutora Ryabushinskiye",
    "wof:placetype":"locality"
},
  "geometry": {"coordinates":[32.06667,51.01667],"type":"Point"}
}