{
  "type": "Feature",
  "properties": {
    "gn:admin1_code":"18.0",
    "gn:asciiname":"Perevodchykove",
    "gn:country_code":"UA",
    "gn:dem":139,
    "gn:feature_class":"P",
    "gn:feature_code":"PPL",
    "gn:name":"Perevodchykove",
    "gn:population":0,
    "gn:timezone":"Europe/Kiev",
    "iso:country":"UA",
    "name:ukr_x_preferred":[
        "Perevodchykove"
    ],
    "name:ukr_x_variant":[
        "\u041f\u0435\u0440\u0435\u0432\u043e\u0434\u0447\u0438\u043a\u043e\u0432\u0435"
    ],
    "wof:name":"Perevodchykove",
    "wof:placetype":"locality"
},
  "geometry": {"coordinates":[34.16055,49.84344],"type":"Point"}
}