{
  "type": "Feature",
  "properties": {
    "gn:admin1_code":"15.0",
    "gn:asciiname":"Bolyanovichi",
    "gn:country_code":"UA",
    "gn:dem":244,
    "gn:feature_class":"P",
    "gn:feature_code":"PPL",
    "gn:name":"Bolyanovichi",
    "gn:population":0,
    "gn:timezone":"Europe/Kiev",
    "iso:country":"UA",
    "name:und_x_variant":[
        "Balanovichi",
        "Bolyanovitse",
        "Bolyanovichi"
    ],
    "wof:name":"Bolyanovichi",
    "wof:placetype":"locality"
},
  "geometry": {"coordinates":[23.07346,49.68052],"type":"Point"}
}