{
  "type": "Feature",
  "properties": {
    "gn:admin1_code":"19.0",
    "gn:asciiname":"Klyntsi",
    "gn:country_code":"UA",
    "gn:dem":290,
    "gn:feature_class":"P",
    "gn:feature_code":"PPL",
    "gn:name":"Klyntsi",
    "gn:population":0,
    "gn:timezone":"Europe/Kiev",
    "iso:country":"UA",
    "name:ukr_x_preferred":[
        "Klyntsi"
    ],
    "name:ukr_x_variant":[
        "\u041a\u043b\u0438\u043d\u0446\u0456"
    ],
    "name:und_x_variant":[
        "Klintsy"
    ],
    "wof:name":"Klyntsi",
    "wof:placetype":"locality"
},
  "geometry": {"coordinates":[25.91572,50.37774],"type":"Point"}
}