{
  "type": "Feature",
  "properties": {
    "iso:country":"UA",
    "name:eng_x_preferred":[
        "Keleberda"
    ],
    "name:rus_x_preferred":[
        "\u041a\u0435\u043b\u0435\u0431\u0435\u0440\u0434\u0430"
    ],
    "qs:a0":"\u0423\u043a\u0440\u0430\u0457\u043d\u0430",
    "qs:a1":"*\u0427\u0435\u0440\u043a\u0430\u0441\u044c\u043a\u0430",
    "qs:a1_alt":"Cherkas'ka",
    "qs:a1r":"0",
    "qs:a2":"\u041a\u0430\u043d\u0456\u0432\u0441\u044c\u043a\u0438\u0439",
    "qs:a2_alt":"Kanivs'kyi",
    "qs:adm0":"\u0423\u043a\u0440\u0430\u0457\u043d\u0430",
    "qs:la_lc":"*",
    "qs:level":"locality",
    "qs:loc":"\u041a\u0435\u043b\u0435\u0431\u0435\u0440\u0434\u0430",
    "qs:loc_alt":"Keleberda",
    "qs:pop":0,
    "qs:type":"buffered point",
    "wof:name":"\u041a\u0435\u043b\u0435\u0431\u0435\u0440\u0434\u0430",
    "wof:placetype":"locality"
},
  "geometry": {"coordinates":[31.56077,49.738515],"type":"Point"}
}