{
  "type": "Feature",
  "properties": {
    "gn:admin1_code":"15.0",
    "gn:asciiname":"Karolyuvka",
    "gn:cc2":"UA",
    "gn:country_code":"UA",
    "gn:dem":493,
    "gn:feature_class":"P",
    "gn:feature_code":"PPL",
    "gn:name":"Karolyuvka",
    "gn:population":0,
    "gn:timezone":"Europe/Kiev",
    "iso:country":"UA",
    "name:und_x_variant":[
        "Karolevka",
        "Karolyuvka"
    ],
    "wof:name":"Karolyuvka",
    "wof:placetype":"locality"
},
  "geometry": {"coordinates":[23.08333,49.28333],"type":"Point"}
}