{
  "type": "Feature",
  "properties": {
    "gn:admin1_code":"18.0",
    "gn:asciiname":"Yablunivka",
    "gn:country_code":"UA",
    "gn:dem":70,
    "gn:feature_class":"P",
    "gn:feature_code":"PPL",
    "gn:name":"Yablunivka",
    "gn:population":0,
    "gn:timezone":"Europe/Kiev",
    "iso:country":"UA",
    "name:ukr_x_preferred":[
        "Yablunivka"
    ],
    "name:ukr_x_variant":[
        "\u042f\u0431\u043b\u0443\u043d\u0456\u0432\u043a\u0430"
    ],
    "wof:name":"Yablunivka",
    "wof:placetype":"locality"
},
  "geometry": {"coordinates":[34.19334,49.19191],"type":"Point"}
}