{
  "type": "Feature",
  "properties": {
    "gn:admin1_code":"17.0",
    "gn:asciiname":"Nove",
    "gn:country_code":"UA",
    "gn:dem":58,
    "gn:feature_class":"P",
    "gn:feature_code":"PPL",
    "gn:name":"Nove",
    "gn:population":0,
    "gn:timezone":"Europe/Kiev",
    "iso:country":"UA",
    "name:bel_x_preferred":[
        "\u041d\u043e\u0432\u044d"
    ],
    "name:bul_x_preferred":[
        "\u041d\u043e\u0432\u0435"
    ],
    "name:ceb_x_preferred":[
        "Nove"
    ],
    "name:deu_x_preferred":[
        "Nove"
    ],
    "name:epo_x_preferred":[
        "Nove"
    ],
    "name:eus_x_preferred":[
        "Nove"
    ],
    "name:fra_x_preferred":[
        "Nove"
    ],
    "name:hun_x_preferred":[
        "Nove"
    ],
    "name:hye_x_preferred":[
        "\u0546\u0578\u057e\u0565"
    ],
    "name:ita_x_preferred":[
        "Nove"
    ],
    "name:jpn_x_preferred":[
        "\u30ce\u30fc\u30f4\u30a7"
    ],
    "name:lat_x_preferred":[
        "Novae"
    ],
    "name:lmo_x_preferred":[
        "Nove"
    ],
    "name:msa_x_preferred":[
        "Nove"
    ],
    "name:nap_x_preferred":[
        "Nove"
    ],
    "name:nld_x_preferred":[
        "Nove"
    ],
    "name:nor_x_preferred":[
        "Nove"
    ],
    "name:pol_x_preferred":[
        "Nove"
    ],
    "name:por_x_preferred":[
        "Nove"
    ],
    "name:ron_x_preferred":[
        "Nove"
    ],
    "name:rus_x_preferred":[
        "\u041d\u043e\u0432\u0435"
    ],
    "name:scn_x_preferred":[
        "Nove"
    ],
    "name:spa_x_preferred":[
        "Nove"
    ],
    "name:srp_x_preferred":[
        "\u041d\u043e\u0432\u0435"
    ],
    "name:tgl_x_preferred":[
        "Nove"
    ],
    "name:ukr_x_preferred":[
        "Nove"
    ],
    "name:ukr_x_variant":[
        "\u041d\u043e\u0432\u0435"
    ],
    "name:und_x_variant":[
        "Burkovskiy",
        "Novyy",
        "Novoye"
    ],
    "name:uzb_x_preferred":[
        "Nove"
    ],
    "name:vec_x_preferred":[
        "\u0141e N\u00f3ve"
    ],
    "name:vol_x_preferred":[
        "Nove"
    ],
    "name:war_x_preferred":[
        "Nove"
    ],
    "name:zho_x_preferred":[
        "\u8bfa\u97e6"
    ],
    "wof:name":"Nove",
    "wof:placetype":"locality"
},
  "geometry": {"coordinates":[30.12784000000001,46.64686],"type":"Point"}
}