{
  "type": "Feature",
  "properties": {
    "gn:admin1_code":"17.0",
    "gn:asciiname":"Nove",
    "gn:country_code":"UA",
    "gn:dem":58,
    "gn:feature_class":"P",
    "gn:feature_code":"PPL",
    "gn:name":"Nove",
    "gn:population":0,
    "gn:timezone":"Europe/Kiev",
    "iso:country":"UA",
    "name:ukr_x_preferred":[
        "Nove"
    ],
    "name:ukr_x_variant":[
        "\u041d\u043e\u0432\u0435"
    ],
    "name:und_x_variant":[
        "Burkovskiy",
        "Novyy",
        "Novoye"
    ],
    "wof:name":"Nove",
    "wof:placetype":"locality"
},
  "geometry": {"coordinates":[30.12784000000001,46.64686],"type":"Point"}
}