{
  "type": "Feature",
  "properties": {
    "gn:admin1_code":"18.0",
    "gn:asciiname":"Hlushkove Druge",
    "gn:country_code":"UA",
    "gn:dem":121,
    "gn:feature_class":"P",
    "gn:feature_code":"PPL",
    "gn:name":"Hlushkove Druge",
    "gn:population":0,
    "gn:timezone":"Europe/Kiev",
    "iso:country":"UA",
    "name:ukr_x_preferred":[
        "Hlushkove Druge"
    ],
    "name:ukr_x_variant":[
        "\u0413\u043b\u0443\u0448\u043a\u043e\u0432\u0435 \u0414\u0440\u0443\u0433\u0435"
    ],
    "name:und_x_variant":[
        "Glushkovo"
    ],
    "wof:name":"Hlushkove Druge",
    "wof:placetype":"locality"
},
  "geometry": {"coordinates":[33.71061,49.43993],"type":"Point"}
}