{
  "type": "Feature",
  "properties": {
    "gn:admin1_code":"15.0",
    "gn:asciiname":"Ruda Brodska",
    "gn:country_code":"UA",
    "gn:dem":209,
    "gn:feature_class":"P",
    "gn:feature_code":"PPL",
    "gn:name":"Ruda Brodska",
    "gn:population":0,
    "gn:timezone":"Europe/Kiev",
    "iso:country":"UA",
    "name:und_x_variant":[
        "Ruda Brodzha",
        "Ruda Brodzka",
        "Ruda",
        "Ruda Brodska"
    ],
    "wof:name":"Ruda Brodska",
    "wof:placetype":"locality"
},
  "geometry": {"coordinates":[24.93629,50.08788],"type":"Point"}
}