{
  "type": "Feature",
  "properties": {
    "iso:country":"UA",
    "qs:a0":"\u0423\u043a\u0440\u0430\u0457\u043d\u0430",
    "qs:a1":"*\u0425\u0430\u0440\u043a\u0456\u0432\u0441\u044c\u043a\u0430",
    "qs:a1_alt":"Kharkivs'ka",
    "qs:a1r":"0",
    "qs:a2":"\u0412\u043e\u0432\u0447\u0430\u043d\u0441\u044c\u043a\u0438\u0439",
    "qs:a2_alt":"Vovchans'kyi",
    "qs:adm0":"\u0423\u043a\u0440\u0430\u0457\u043d\u0430",
    "qs:la_lc":"*",
    "qs:level":"locality",
    "qs:loc":"\u0412\u0456\u043b\u044c\u0447\u0430",
    "qs:loc_alt":"Vil'cha",
    "qs:pop":0,
    "qs:type":"buffered point",
    "wd:wordcount":312,
    "wof:name":"\u0412\u0456\u043b\u044c\u0447\u0430",
    "wof:placetype":"locality"
},
  "geometry": {"coordinates":[36.943832,50.245217],"type":"Point"}
}