{
  "type": "Feature",
  "properties": {
    "iso:country":"UA",
    "qs:a0":"\u0423\u043a\u0440\u0430\u0457\u043d\u0430",
    "qs:a1":"*\u0414\u043d\u0456\u043f\u0440\u043e\u043f\u0435\u0442\u0440\u043e\u0432\u0441\u044c\u043a\u0430",
    "qs:a1_alt":"Dnipropetrovs'ka",
    "qs:a1r":"0",
    "qs:a2":"\u0421\u0438\u043d\u0435\u043b\u044c\u043d\u0438\u043a\u0456\u0432\u0441\u044c\u043a\u0438\u0439",
    "qs:a2_alt":"Synel'nykivs'kyi",
    "qs:adm0":"\u0423\u043a\u0440\u0430\u0457\u043d\u0430",
    "qs:la_lc":"*",
    "qs:level":"locality",
    "qs:loc":"\u0406\u043b\u0430\u0440\u0456\u043e\u043d\u043e\u0432\u0435",
    "qs:loc_alt":"Ilarionove",
    "qs:pop":0,
    "qs:type":"buffered point",
    "wof:name":"\u0406\u043b\u0430\u0440\u0456\u043e\u043d\u043e\u0432\u0435",
    "wof:placetype":"locality"
},
  "geometry": {"coordinates":[35.285566,48.41479],"type":"Point"}
}