{
  "type": "Feature",
  "properties": {
    "gn:admin1_code":"11.0",
    "gn:admin2_code":"712585",
    "gn:admin3_code":"11152830.0",
    "gn:asciiname":"Ovrazhki",
    "gn:country_code":"UA",
    "gn:dem":386,
    "gn:elevation":"441.0",
    "gn:feature_class":"P",
    "gn:feature_code":"PPL",
    "gn:name":"Ovrazhki",
    "gn:population":36,
    "gn:timezone":"Europe/Simferopol",
    "iso:country":"UA",
    "name:eng_x_preferred":[
        "Ovrazhki"
    ],
    "name:rus_x_historical":[
        "\u041a\u0430\u0439\u043d\u0430\u0443\u0301\u0442"
    ],
    "name:rus_x_preferred":[
        "\u041e\u0432\u0440\u0430\u0436\u043a\u0438"
    ],
    "name:rus_x_variant":[
        "\u041a\u0430\u0439\u043d\u0430\u0443\u0301\u0442"
    ],
    "name:ukr_x_preferred":[
        "\u041e\u0432\u0440\u0430\u0436\u043a\u0438"
    ],
    "wof:name":"Ovrazhki",
    "wof:placetype":"locality",
    "wof:population":36
},
  "geometry": {"coordinates":[34.41744,44.97182],"type":"Point"}
}