{
  "type": "Feature",
  "properties": {
    "iso:country":"UA",
    "name:eng_x_preferred":[
        "Petrivka"
    ],
    "name:rus_x_preferred":[
        "\u041f\u0435\u0442\u0440\u043e\u0432\u043a\u0430"
    ],
    "name:ukr_x_preferred":[
        "Petrivka"
    ],
    "name:ukr_x_variant":[
        "\u041f\u0435\u0442\u0440\u0456\u0432\u043a\u0430"
    ],
    "name:und_x_variant":[
        "Pos\u00eblok Petrovskogo"
    ],
    "name:zho_x_preferred":[
        "\u5f7c\u5f97\u7f57\u592b\u5361"
    ],
    "qs:a0":"\u0423\u043a\u0440\u0430\u0457\u043d\u0430",
    "qs:a1":"*\u041e\u0434\u0435\u0441\u044c\u043a\u0430",
    "qs:a1_alt":"Odes'ka",
    "qs:a1r":"0",
    "qs:a2":"\u0406\u0432\u0430\u043d\u0456\u0432\u0441\u044c\u043a\u0438\u0439",
    "qs:a2_alt":"Ivanivs'kyi",
    "qs:adm0":"\u0423\u043a\u0440\u0430\u0457\u043d\u0430",
    "qs:la_lc":"*",
    "qs:level":"locality",
    "qs:loc":"\u041f\u0435\u0442\u0440\u0456\u0432\u043a\u0430",
    "qs:loc_alt":"Petrivka",
    "qs:pop":0,
    "qs:type":"buffered point",
    "wd:wordcount":82,
    "wof:name":"\u041f\u0435\u0442\u0440\u0456\u0432\u043a\u0430",
    "wof:placetype":"locality"
},
  "geometry": {"coordinates":[30.721615,46.901172],"type":"Point"}
}