{
  "type": "Feature",
  "properties": {
    "gn:admin1_code":"2.0",
    "gn:asciiname":"Kostobobr",
    "gn:country_code":"UA",
    "gn:dem":168,
    "gn:feature_class":"P",
    "gn:feature_code":"PPL",
    "gn:name":"Kostobobr",
    "gn:population":0,
    "gn:timezone":"Europe/Kiev",
    "iso:country":"UA",
    "name:eng_x_preferred":[
        "Kostobobr"
    ],
    "name:rus_x_preferred":[
        "\u041a\u043e\u0441\u0442\u043e\u0431\u043e\u0431\u0440\u043e\u0432"
    ],
    "name:ukr_x_preferred":[
        "Kostobobriv"
    ],
    "name:ukr_x_variant":[
        "\u041a\u043e\u0441\u0442\u043e\u0431\u043e\u0431\u0440\u0456\u0432",
        "Kostobober",
        "Kostobobrov"
    ],
    "name:und_x_variant":[
        "Kostobober",
        "Kostobobrov",
        "Kostobobr"
    ],
    "wof:name":"Kostobobr",
    "wof:placetype":"locality"
},
  "geometry": {"coordinates":[32.93895999999999,52.2343],"type":"Point"}
}