{
  "type": "Feature",
  "properties": {
    "gn:admin1_code":"2.0",
    "gn:asciiname":"Kuty Pershi",
    "gn:country_code":"UA",
    "gn:dem":148,
    "gn:feature_class":"P",
    "gn:feature_code":"PPL",
    "gn:name":"Kuty Pershi",
    "gn:population":0,
    "gn:timezone":"Europe/Kiev",
    "iso:country":"UA",
    "name:ukr_x_preferred":[
        "Kuty Pershi"
    ],
    "name:ukr_x_variant":[
        "\u041a\u0443\u0442\u0438 \u041f\u0435\u0440\u0448\u0456",
        "Kut Tretiy",
        "Ivanovskiy Put\u2019"
    ],
    "wof:name":"Kuty Pershi",
    "wof:placetype":"locality"
},
  "geometry": {"coordinates":[32.59833,52.12667],"type":"Point"}
}