{
  "type": "Feature",
  "properties": {
    "gn:admin1_code":"24.0",
    "gn:asciiname":"Trylistsi",
    "gn:country_code":"UA",
    "gn:dem":181,
    "gn:feature_class":"P",
    "gn:feature_code":"PPL",
    "gn:name":"Trylistsi",
    "gn:population":0,
    "gn:timezone":"Europe/Kiev",
    "iso:country":"UA",
    "name:ukr_x_preferred":[
        "Trylistsi"
    ],
    "name:ukr_x_variant":[
        "\u0422\u0440\u0438\u043b\u0456\u0441\u0446\u0456"
    ],
    "name:und_x_variant":[
        "Trilisitsa",
        "Trilestsy"
    ],
    "wof:name":"Trylistsi",
    "wof:placetype":"locality"
},
  "geometry": {"coordinates":[25.14119,51.01085],"type":"Point"}
}