{
  "type": "Feature",
  "properties": {
    "gn:admin1_code":"19.0",
    "gn:asciiname":"Velyke",
    "gn:country_code":"UA",
    "gn:dem":188,
    "gn:feature_class":"P",
    "gn:feature_code":"PPL",
    "gn:name":"Velyke",
    "gn:population":0,
    "gn:timezone":"Europe/Kiev",
    "iso:country":"UA",
    "name:ukr_x_preferred":[
        "Velyke"
    ],
    "name:ukr_x_variant":[
        "\u0412\u0435\u043b\u0438\u043a\u0435"
    ],
    "name:und_x_variant":[
        "Vel\u2019ke Rykane",
        "Velikoye"
    ],
    "wof:name":"Velyke",
    "wof:placetype":"locality"
},
  "geometry": {"coordinates":[25.30474,50.61163],"type":"Point"}
}