{
  "type": "Feature",
  "properties": {
    "gn:admin1_code":"11.0",
    "gn:admin2_code":"703233",
    "gn:admin3_code":"11128724.0",
    "gn:asciiname":"Novosyolovka",
    "gn:country_code":"UA",
    "gn:dem":115,
    "gn:feature_class":"P",
    "gn:feature_code":"PPL",
    "gn:name":"Novosyolovka",
    "gn:population":29,
    "gn:timezone":"Europe/Simferopol",
    "iso:country":"UA",
    "name:eng_x_preferred":[
        "Novosyolovka"
    ],
    "name:rus_x_historical":[
        "\u0428\u0435\u043f\u0435\u0442\u0435\u0435\u0432\u043a\u0430",
        "\u041d\u043e\u0432\u043e-\u0428\u0435\u0431\u0435\u0442\u0435\u0435\u0432\u043a\u0430"
    ],
    "name:rus_x_preferred":[
        "\u041d\u043e\u0432\u043e\u0441\u0451\u043b\u043e\u0432\u043a\u0430"
    ],
    "name:rus_x_variant":[
        "\u0428\u0435\u043f\u0435\u0442\u0435\u0435\u0432\u043a\u0430",
        "\u041d\u043e\u0432\u043e-\u0428\u0435\u0431\u0435\u0442\u0435\u0435\u0432\u043a\u0430"
    ],
    "name:ukr_x_preferred":[
        "\u041d\u043e\u0432\u043e\u0441\u0435\u043b\u0456\u0432\u043a\u0430"
    ],
    "wof:name":"Novosyolovka",
    "wof:placetype":"locality",
    "wof:population":29
},
  "geometry": {"coordinates":[36.09817,45.24826],"type":"Point"}
}