{
  "type": "Feature",
  "properties": {
    "gn:admin1_code":"7.0",
    "gn:asciiname":"Zemlyanyy Yar",
    "gn:country_code":"UA",
    "gn:dem":126,
    "gn:feature_class":"P",
    "gn:feature_code":"PPL",
    "gn:name":"Zemlyanyy Yar",
    "gn:population":0,
    "gn:timezone":"Europe/Kiev",
    "iso:country":"UA",
    "name:ukr_x_preferred":[
        "Zemlyanyy Yar"
    ],
    "name:ukr_x_variant":[
        "\u0417\u0435\u043c\u043b\u044f\u043d\u0438\u0439 \u042f\u0440"
    ],
    "name:und_x_variant":[
        "Zemlyanoy Yar"
    ],
    "wof:name":"Zemlyanyy Yar",
    "wof:placetype":"locality"
},
  "geometry": {"coordinates":[36.96693,50.19858],"type":"Point"}
}