{
  "type": "Feature",
  "properties": {
    "gn:admin1_code":"24.0",
    "gn:asciiname":"Verbayiv",
    "gn:country_code":"UA",
    "gn:dem":188,
    "gn:feature_class":"P",
    "gn:feature_code":"PPL",
    "gn:name":"Verbayiv",
    "gn:population":0,
    "gn:timezone":"Europe/Kiev",
    "iso:country":"UA",
    "name:ukr_x_preferred":[
        "Verbayiv"
    ],
    "name:ukr_x_variant":[
        "\u0412\u0435\u0440\u0431\u0430\u0457\u0432"
    ],
    "name:und_x_variant":[
        "Verbayev"
    ],
    "wof:name":"Verbayiv",
    "wof:placetype":"locality"
},
  "geometry": {"coordinates":[25.35628,50.65108],"type":"Point"}
}