{
  "type": "Feature",
  "properties": {
    "gn:admin1_code":"22.0",
    "gn:asciiname":"Beremyany",
    "gn:country_code":"UA",
    "gn:dem":346,
    "gn:feature_class":"P",
    "gn:feature_code":"PPL",
    "gn:name":"Beremyany",
    "gn:population":0,
    "gn:timezone":"Europe/Kiev",
    "iso:country":"UA",
    "wof:name":"Beremyany",
    "wof:placetype":"locality"
},
  "geometry": {"coordinates":[25.44652,48.88739],"type":"Point"}
}