{
  "type": "Feature",
  "properties": {
    "gn:admin1_code":"7.0",
    "gn:asciiname":"Lozivs'ke",
    "gn:country_code":"UA",
    "gn:dem":92,
    "gn:feature_class":"P",
    "gn:feature_code":"PPL",
    "gn:name":"Lozivs\u2019ke",
    "gn:population":0,
    "gn:timezone":"Europe/Kiev",
    "iso:country":"UA",
    "name:ukr_x_preferred":[
        "Lozivs\u2019ke"
    ],
    "name:ukr_x_variant":[
        "\u041b\u043e\u0437\u0456\u0432\u0441\u044c\u043a\u0435"
    ],
    "name:und_x_variant":[
        "Lazovskiy",
        "Lozovskiy"
    ],
    "wof:name":"Lozivs'ke",
    "wof:placetype":"locality"
},
  "geometry": {"coordinates":[36.56207,49.21604],"type":"Point"}
}