{
  "type": "Feature",
  "properties": {
    "iso:country":"UA",
    "name:arm_x_preferred":[
        "\u054d\u057f\u0561\u0580\u056b\u0575 \u0549\u0561\u0580\u057f\u0578\u0580\u056b\u057d\u056f"
    ],
    "name:bel_x_preferred":[
        "\u0421\u044f\u043b\u043e \u0421\u0442\u0430\u0440\u044b \u0427\u0430\u0440\u0442\u0430\u0440\u044b\u0439\u0441\u043a"
    ],
    "name:chi_x_preferred":[
        "\u820a\u55ac\u723e\u6258\u91cc\u897f\u514b"
    ],
    "name:deu_x_preferred":[
        "Staryj Tschortoryjsk"
    ],
    "name:eng_x_preferred":[
        "Staryi Chortoryisk"
    ],
    "name:geo_x_preferred":[
        "\u10e1\u10e2\u10d0\u10e0\u10d8 \u10e9\u10d0\u10e0\u10e2\u10dd\u10e0\u10d8\u10e1\u10d9\u10d8"
    ],
    "name:ger_x_preferred":[
        "Staryj Tschortoryjsk"
    ],
    "name:gre_x_preferred":[
        "\u03a3\u03c4\u03ac\u03c1\u03c5 \u03a7\u03bf\u03c1\u03c4\u03cc\u03c1\u03b9\u03c3\u03ba"
    ],
    "name:heb_x_preferred":[
        "\u05e1\u05d8\u05d0\u05e8\u05d9 \u05e6'\u05d5\u05e8\u05d8\u05d5\u05e8\u05d9\u05e1\u05e7"
    ],
    "name:hye_x_preferred":[
        "\u054d\u057f\u0561\u0580\u056b \u0549\u0561\u0580\u057f\u0578\u0580\u056b\u057d\u056f"
    ],
    "name:jpn_x_preferred":[
        "\u30b9\u30bf\u30eb\u30a3\u30fc\uff1d\u30c1\u30e7\u30eb\u30c8\u30eb\u30a3\u30fc\u30b7\u30af"
    ],
    "name:pol_x_preferred":[
        "Czartorysk"
    ],
    "name:ron_x_preferred":[
        "Star\u00eei Ciortor\u00eeisk"
    ],
    "name:rum_x_preferred":[
        "Star\u00eei Ciortor\u00eeisk"
    ],
    "name:rus_x_preferred":[
        "\u0421\u0442\u0430\u0440\u044b\u0439 \u0427\u0430\u0440\u0442\u043e\u0440\u0438\u0439\u0441\u043a"
    ],
    "name:ukr_x_preferred":[
        "\u0421\u0442\u0430\u0440\u0438\u0439 \u0427\u043e\u0440\u0442\u043e\u0440\u0438\u0439\u0441\u044c\u043a"
    ],
    "name:ukr_x_variant":[
        "Staryy Chortoryys\u2019k"
    ],
    "name:unk_x_variant":[
        "Chartoriysk"
    ],
    "name:zho_x_preferred":[
        "\u820a\u55ac\u723e\u6258\u91cc\u897f\u514b"
    ],
    "qs:a0":"\u0423\u043a\u0440\u0430\u0457\u043d\u0430",
    "qs:a1":"*\u0412\u043e\u043b\u0438\u043d\u0441\u044c\u043a\u0430",
    "qs:a1_alt":"Volyns'ka",
    "qs:a1r":"0",
    "qs:a2":"\u041c\u0430\u043d\u0435\u0432\u0438\u0446\u044c\u043a\u0438\u0439",
    "qs:a2_alt":"Manevyts'kyi",
    "qs:adm0":"\u0423\u043a\u0440\u0430\u0457\u043d\u0430",
    "qs:la_lc":"*",
    "qs:level":"locality",
    "qs:loc":"\u0421\u0442\u0430\u0440\u0438\u0439 \u0427\u043e\u0440\u0442\u043e\u0440\u0438\u0439\u0441\u044c\u043a",
    "qs:loc_alt":"Staryi Chortoryis'k",
    "qs:pop":0,
    "qs:type":"buffered point",
    "wd:wordcount":312,
    "wof:name":"\u0421\u0442\u0430\u0440\u0438\u0439 \u0427\u043e\u0440\u0442\u043e\u0440\u0438\u0439\u0441\u044c\u043a",
    "wof:placetype":"locality"
},
  "geometry": {"coordinates":[25.877436,51.224714],"type":"Point"}
}