{
  "type": "Feature",
  "properties": {
    "gn:admin1_code":"8.0",
    "gn:asciiname":"Novovasylivka",
    "gn:country_code":"UA",
    "gn:dem":35,
    "gn:feature_class":"P",
    "gn:feature_code":"PPL",
    "gn:name":"Novovasylivka",
    "gn:population":0,
    "gn:timezone":"Europe/Kiev",
    "iso:country":"UA",
    "name:rus_x_preferred":[
        "\u041d\u043e\u0432\u043e\u0432\u0430\u0441\u0438\u043b\u0435\u0432\u043a\u0430"
    ],
    "name:ukr_x_preferred":[
        "\u041d\u043e\u0432\u043e\u0432\u0430\u0441\u0438\u043b\u0456\u0432\u043a\u0430"
    ],
    "name:und_x_variant":[
        "Vasil\u2019yevka",
        "Novo-Vasil\u2019yevka",
        "Novovasylivka",
        "Novovasilevka"
    ],
    "wof:name":"Novovasylivka",
    "wof:placetype":"locality"
},
  "geometry": {"coordinates":[34.54633,46.64984000000001],"type":"Point"}
}