{
  "type": "Feature",
  "properties": {
    "gn:gn_country":"UA",
    "gn:gn_fcode":"PPL",
    "gn:gn_pop":3127,
    "gn:population":3127,
    "iso:country":"UA",
    "name:bul_x_preferred":[
        "\u041b\u0430\u0437\u0443\u0440\u043d\u0435"
    ],
    "name:chi_x_preferred":[
        "\u62c9\u7956\u723e\u6d85"
    ],
    "name:eng_x_preferred":[
        "Lazurne"
    ],
    "name:ger_x_preferred":[
        "Lasurne"
    ],
    "name:lav_x_preferred":[
        "Lazurne"
    ],
    "name:rus_x_preferred":[
        "\u041b\u0430\u0437\u0443\u0440\u043d\u0435"
    ],
    "name:ukr_x_preferred":[
        "\u041b\u0430\u0437\u0443\u0440\u043d\u0435"
    ],
    "name:unk_x_variant":[
        "Novoalekseyevka"
    ],
    "qs_pg:aaroncc":"UA",
    "qs_pg:gn_country":"UA",
    "qs_pg:gn_fcode":"PPL",
    "qs_pg:gn_pop":3127,
    "qs_pg:name":"Lazurnoye",
    "qs_pg:name_adm0":"Ukraine",
    "qs_pg:name_adm1":"Khersons\u00b4ka Oblast\u00b4",
    "qs_pg:photos_9k":1,
    "qs_pg:photos_9r":1,
    "qs_pg:photos_all":6,
    "qs_pg:photos_sr":0,
    "qs_pg:pop_sr":4,
    "qs_pg:qs_pg_placetype":"locality",
    "qs_pg:qs_pg_placetype_gp":"Town",
    "qs_pg:woe_adm0":23424976,
    "woe:adm0_id":23424976,
    "woe:name_adm0":"Ukraine",
    "woe:name_adm1":"Khersons\u00b4ka Oblast\u00b4",
    "woe:placetype":"Town",
    "wof:name":"Lazurnoye",
    "wof:placetype":"locality",
    "wof:population":3127
},
  "geometry": {"coordinates":[32.52955,46.084],"type":"Point"}
}