{
  "type": "Feature",
  "properties": {
    "gn:country":"UA",
    "gn:fcode":"PPL",
    "gn:population":3127,
    "iso:country":"UA",
    "name:bel_x_preferred":[
        "\u041b\u0430\u0437\u0443\u0440\u043d\u044d"
    ],
    "name:bul_x_preferred":[
        "\u041b\u0430\u0437\u0443\u0440\u043d\u0435"
    ],
    "name:cat_x_preferred":[
        "Lazurne"
    ],
    "name:ceb_x_preferred":[
        "Lazurne"
    ],
    "name:che_x_preferred":[
        "\u041b\u0430\u0437\u0443\u0440\u043d\u043e\u0435"
    ],
    "name:crh_x_preferred":[
        "Lazurne"
    ],
    "name:deu_x_preferred":[
        "Lasurne"
    ],
    "name:eng_x_preferred":[
        "Lazurne"
    ],
    "name:fra_x_preferred":[
        "Lazourne"
    ],
    "name:kat_x_preferred":[
        "\u10da\u10d0\u10d6\u10e3\u10e0\u10dc\u10d4"
    ],
    "name:lav_x_preferred":[
        "Lazurne"
    ],
    "name:pol_x_preferred":[
        "Lazurne"
    ],
    "name:ron_x_preferred":[
        "Lazurne"
    ],
    "name:rus_x_preferred":[
        "\u041b\u0430\u0437\u0443\u0440\u043d\u0435"
    ],
    "name:rus_x_variant":[
        "\u041b\u0430\u0437\u0443\u0440\u043d\u043e\u0435"
    ],
    "name:spa_x_preferred":[
        "Lazurne"
    ],
    "name:ukr_x_preferred":[
        "\u041b\u0430\u0437\u0443\u0440\u043d\u0435"
    ],
    "name:und_x_variant":[
        "Novoalekseyevka"
    ],
    "name:uzb_x_preferred":[
        "Lazurne"
    ],
    "name:zho_x_preferred":[
        "\u62c9\u7956\u723e\u6d85"
    ],
    "name:zho_x_variant":[
        "\u62c9\u7956\u5c14\u5185"
    ],
    "qs_pg:aaroncc":"UA",
    "qs_pg:gn_country":"UA",
    "qs_pg:gn_fcode":"PPL",
    "qs_pg:gn_pop":3127,
    "qs_pg:name":"Lazurnoye",
    "qs_pg:name_adm0":"Ukraine",
    "qs_pg:name_adm1":"Khersons\u00b4ka Oblast\u00b4",
    "qs_pg:photos_9k":1,
    "qs_pg:photos_9r":1,
    "qs_pg:photos_all":6,
    "qs_pg:photos_sr":0,
    "qs_pg:pop_sr":4,
    "qs_pg:qs_pg_placetype":"locality",
    "qs_pg:qs_pg_placetype_gp":"Town",
    "qs_pg:woe_adm0":23424976,
    "woe:adm0_id":23424976,
    "woe:name_adm0":"Ukraine",
    "woe:name_adm1":"Khersons\u00b4ka Oblast\u00b4",
    "woe:placetype":"Town",
    "wof:name":"Lazurnoye",
    "wof:placetype":"locality",
    "wof:population":3127
},
  "geometry": {"coordinates":[32.52955,46.084],"type":"Point"}
}