{
  "type": "Feature",
  "properties": {
    "gn:admin1_code":"2.0",
    "gn:asciiname":"Budyshche",
    "gn:country_code":"UA",
    "gn:dem":148,
    "gn:feature_class":"P",
    "gn:feature_code":"PPL",
    "gn:name":"Budyshche",
    "gn:population":0,
    "gn:timezone":"Europe/Kiev",
    "iso:country":"UA",
    "name:ukr_x_preferred":[
        "Budyshche"
    ],
    "name:ukr_x_variant":[
        "\u0411\u0443\u0434\u0438\u0449\u0435"
    ],
    "wof:name":"Budyshche",
    "wof:placetype":"locality"
},
  "geometry": {"coordinates":[32.36639,51.79705],"type":"Point"}
}