{
  "type": "Feature",
  "properties": {
    "gn:admin1_code":"21.0",
    "gn:asciiname":"Rog",
    "gn:country_code":"UA",
    "gn:dem":114,
    "gn:feature_class":"P",
    "gn:feature_code":"PPL",
    "gn:name":"Rog",
    "gn:population":0,
    "gn:timezone":"Europe/Kiev",
    "iso:country":"UA",
    "wof:name":"Rog",
    "wof:placetype":"locality"
},
  "geometry": {"coordinates":[35.34139000000001,50.37778],"type":"Point"}
}