{
  "type": "Feature",
  "properties": {
    "gn:admin1_code":"18.0",
    "gn:asciiname":"Vasylivka",
    "gn:country_code":"UA",
    "gn:dem":75,
    "gn:feature_class":"P",
    "gn:feature_code":"PPL",
    "gn:name":"Vasylivka",
    "gn:population":0,
    "gn:timezone":"Europe/Kiev",
    "iso:country":"UA",
    "name:eng_x_preferred":[
        "Vasil'yevka"
    ],
    "name:rus_x_preferred":[
        "\u0412\u0430\u0441\u0438\u043b\u0435\u0432\u043a\u0430"
    ],
    "name:ukr_x_preferred":[
        "Vasylivka"
    ],
    "name:ukr_x_variant":[
        "\u0412\u0430\u0441\u0438\u043b\u0456\u0432\u043a\u0430"
    ],
    "name:und_x_variant":[
        "Vasilivka",
        "Vasil\u2019yevka"
    ],
    "wof:name":"Vasylivka",
    "wof:placetype":"locality"
},
  "geometry": {"coordinates":[33.75921,49.22677],"type":"Point"}
}