{
  "type": "Feature",
  "properties": {
    "gn:admin1_code":"23.0",
    "gn:asciiname":"Karmalyukovo",
    "gn:country_code":"UA",
    "gn:dem":338,
    "gn:feature_class":"P",
    "gn:feature_code":"PPL",
    "gn:name":"Karmalyukovo",
    "gn:population":0,
    "gn:timezone":"Europe/Kiev",
    "iso:country":"UA",
    "name:und_x_variant":[
        "Golovchintsy",
        "Karmalyukovo"
    ],
    "wof:name":"Karmalyukovo",
    "wof:placetype":"locality"
},
  "geometry": {"coordinates":[27.95458,49.15221],"type":"Point"}
}