{
  "type": "Feature",
  "properties": {
    "gn:admin1_code":"10.0",
    "gn:asciiname":"Ryadove",
    "gn:country_code":"UA",
    "gn:dem":145,
    "gn:feature_class":"P",
    "gn:feature_code":"PPL",
    "gn:name":"Ryadove",
    "gn:population":0,
    "gn:timezone":"Europe/Kiev",
    "iso:country":"UA",
    "name:eng_x_preferred":[
        "Ryadove"
    ],
    "name:rus_x_preferred":[
        "\u0420\u044f\u0434\u043e\u0432\u043e\u0435"
    ],
    "name:ukr_x_preferred":[
        "\u0420\u044f\u0434\u043e\u0432\u0435"
    ],
    "name:und_x_variant":[
        "Ryadovoye"
    ],
    "wof:name":"Ryadove",
    "wof:placetype":"locality"
},
  "geometry": {"coordinates":[33.53093,48.23121],"type":"Point"}
}