{
  "type": "Feature",
  "properties": {
    "iso:country":"UA",
    "qs:a0":"\u0423\u043a\u0440\u0430\u0457\u043d\u0430",
    "qs:a1":"*\u0427\u0435\u0440\u043a\u0430\u0441\u044c\u043a\u0430",
    "qs:a1_alt":"Cherkas'ka",
    "qs:a1r":"0",
    "qs:a2":"\u041a\u043e\u0440\u0441\u0443\u043d\u044c-\u0428\u0435\u0432\u0447\u0435\u043d\u043a\u0456\u0432\u0441\u044c\u043a\u0438\u0439",
    "qs:a2_alt":"Korsun'-Shevchenkivs'kyi",
    "qs:adm0":"\u0423\u043a\u0440\u0430\u0457\u043d\u0430",
    "qs:la_lc":"*",
    "qs:level":"locality",
    "qs:loc":"\u0414\u0435\u0440\u0435\u043d\u043a\u043e\u0432\u0435\u0446\u044c",
    "qs:loc_alt":"Derenkovets",
    "qs:pop":0,
    "qs:type":"buffered point",
    "wof:name":"\u0414\u0435\u0440\u0435\u043d\u043a\u043e\u0432\u0435\u0446\u044c",
    "wof:placetype":"locality"
},
  "geometry": {"coordinates":[31.432688,49.429491],"type":"Point"}
}