{
  "type": "Feature",
  "properties": {
    "gn:admin1_code":"27.0",
    "gn:asciiname":"Prybutok",
    "gn:country_code":"UA",
    "gn:dem":176,
    "gn:feature_class":"P",
    "gn:feature_code":"PPL",
    "gn:name":"Prybutok",
    "gn:population":0,
    "gn:timezone":"Europe/Kiev",
    "iso:country":"UA",
    "name:ukr_x_preferred":[
        "Prybutok"
    ],
    "name:ukr_x_variant":[
        "\u041f\u0440\u0438\u0431\u0443\u0442\u043e\u043a"
    ],
    "name:und_x_variant":[
        "Pributok"
    ],
    "wof:name":"Prybutok",
    "wof:placetype":"locality"
},
  "geometry": {"coordinates":[29.06919000000001,50.61169],"type":"Point"}
}