{
  "type": "Feature",
  "properties": {
    "gn:admin1_code":"2.0",
    "gn:asciiname":"Kupchenkiv",
    "gn:country_code":"UA",
    "gn:dem":122,
    "gn:feature_class":"P",
    "gn:feature_code":"PPL",
    "gn:name":"Kupchenkiv",
    "gn:population":0,
    "gn:timezone":"Europe/Kiev",
    "iso:country":"UA",
    "name:ukr_x_preferred":[
        "Kupchenkiv"
    ],
    "name:ukr_x_variant":[
        "\u041a\u0443\u043f\u0447\u0435\u043d\u043a\u0456\u0432"
    ],
    "name:und_x_variant":[
        "Kupchenkov"
    ],
    "wof:name":"Kupchenkiv",
    "wof:placetype":"locality"
},
  "geometry": {"coordinates":[32.48085,51.34845],"type":"Point"}
}