{
  "type": "Feature",
  "properties": {
    "gn:admin1_code":"6.0",
    "gn:asciiname":"Dubovitsa",
    "gn:country_code":"UA",
    "gn:dem":261,
    "gn:feature_class":"P",
    "gn:feature_code":"PPL",
    "gn:name":"Dubovitsa",
    "gn:population":0,
    "gn:timezone":"Europe/Kiev",
    "iso:country":"UA",
    "wof:name":"Dubovitsa",
    "wof:placetype":"locality"
},
  "geometry": {"coordinates":[24.48177,49.15501],"type":"Point"}
}