{
  "type": "Feature",
  "properties": {
    "gn:admin1_code":"18.0",
    "gn:asciiname":"Krivoy Bereg",
    "gn:country_code":"UA",
    "gn:dem":83,
    "gn:feature_class":"P",
    "gn:feature_code":"PPL",
    "gn:name":"Krivoy Bereg",
    "gn:population":0,
    "gn:timezone":"Europe/Kiev",
    "iso:country":"UA",
    "name:und_x_variant":[
        "Krutoy-Bereg",
        "Krivoy Bereg"
    ],
    "wof:name":"Krivoy Bereg",
    "wof:placetype":"locality"
},
  "geometry": {"coordinates":[34.59695,49.61959],"type":"Point"}
}