{
  "type": "Feature",
  "properties": {
    "gn:admin1_code":"18.0",
    "gn:asciiname":"Proletar",
    "gn:country_code":"UA",
    "gn:dem":107,
    "gn:feature_class":"P",
    "gn:feature_code":"PPL",
    "gn:name":"Proletar",
    "gn:population":0,
    "gn:timezone":"Europe/Kiev",
    "iso:country":"UA",
    "name:ukr_x_preferred":[
        "Proletar"
    ],
    "name:ukr_x_variant":[
        "\u041f\u0440\u043e\u043b\u0435\u0442\u0430\u0440"
    ],
    "name:und_x_variant":[
        "Proletariy"
    ],
    "wof:name":"Proletar",
    "wof:placetype":"locality"
},
  "geometry": {"coordinates":[33.44105,50.43973],"type":"Point"}
}