{
  "type": "Feature",
  "properties": {
    "iso:country":"UA",
    "name:chi_x_preferred":[
        "\u79d1\u83ab\u723e\u5c3c\u57fa"
    ],
    "name:deu_x_preferred":[
        "Komarnyky"
    ],
    "name:eng_x_preferred":[
        "Komarnyky"
    ],
    "name:ger_x_preferred":[
        "Komarnyky"
    ],
    "name:pol_x_preferred":[
        "Komarniki"
    ],
    "name:ron_x_preferred":[
        "Komarn\u00eek\u00ee"
    ],
    "name:rum_x_preferred":[
        "Komarn\u00eek\u00ee"
    ],
    "name:rus_x_preferred":[
        "\u041a\u043e\u043c\u0430\u0440\u043d\u0438\u043a\u0438"
    ],
    "name:ukr_x_preferred":[
        "\u041a\u043e\u043c\u0430\u0440\u043d\u0438\u043a\u0438"
    ],
    "name:ukr_x_variant":[
        "Komarnyky"
    ],
    "name:unk_x_variant":[
        "Komarniki"
    ],
    "qs:a0":"\u0423\u043a\u0440\u0430\u0457\u043d\u0430",
    "qs:a1":"*\u041b\u044c\u0432\u0456\u0432\u0441\u044c\u043a\u0430",
    "qs:a1_alt":"L'vivs'ka",
    "qs:a1r":"0",
    "qs:a2":"\u0422\u0443\u0440\u043a\u0456\u0432\u0441\u044c\u043a\u0438\u0439",
    "qs:a2_alt":"Turkivs'kyi",
    "qs:adm0":"\u0423\u043a\u0440\u0430\u0457\u043d\u0430",
    "qs:la_lc":"*",
    "qs:level":"locality",
    "qs:loc":"\u041a\u043e\u043c\u0430\u0440\u043d\u0438\u043a\u0438",
    "qs:loc_alt":"Komarnyky",
    "qs:pop":0,
    "qs:type":"buffered point",
    "wd:wordcount":66,
    "wof:name":"\u041a\u043e\u043c\u0430\u0440\u043d\u0438\u043a\u0438",
    "wof:placetype":"locality"
},
  "geometry": {"coordinates":[23.049248,48.972193],"type":"Point"}
}