{
  "type": "Feature",
  "properties": {
    "gn:admin1_code":"4.0",
    "gn:asciiname":"Polovitsy",
    "gn:country_code":"UA",
    "gn:dem":53,
    "gn:feature_class":"P",
    "gn:feature_code":"PPL",
    "gn:name":"Polovitsy",
    "gn:population":0,
    "gn:timezone":"Europe/Kiev",
    "iso:country":"UA",
    "wof:name":"Polovitsy",
    "wof:placetype":"locality"
},
  "geometry": {"coordinates":[35.15,48.55],"type":"Point"}
}