{
  "type": "Feature",
  "properties": {
    "gn:admin1_code":"1.0",
    "gn:asciiname":"Veselyy Podil",
    "gn:country_code":"UA",
    "gn:dem":120,
    "gn:feature_class":"P",
    "gn:feature_code":"PPL",
    "gn:name":"Veselyy Podil",
    "gn:population":0,
    "gn:timezone":"Europe/Kiev",
    "iso:country":"UA",
    "name:ukr_x_preferred":[
        "Veselyy Podil"
    ],
    "name:ukr_x_variant":[
        "\u0412\u0435\u0441\u0435\u043b\u0438\u0439 \u041f\u043e\u0434\u0456\u043b"
    ],
    "wof:name":"Veselyy Podil",
    "wof:placetype":"locality"
},
  "geometry": {"coordinates":[32.53785999999999,49.62827],"type":"Point"}
}