{
  "type": "Feature",
  "properties": {
    "iso:country":"UA",
    "name:arm_x_preferred":[
        "\u0532\u0578\u0562\u0578\u057e\u0581\u056b"
    ],
    "name:eng_x_preferred":[
        "Bobivtsi"
    ],
    "name:hye_x_preferred":[
        "\u0532\u0578\u0562\u0578\u057e\u0581\u056b"
    ],
    "name:ron_x_preferred":[
        "Bobe\u0219ti"
    ],
    "name:rum_x_preferred":[
        "Bobe\u0219ti"
    ],
    "name:rus_x_preferred":[
        "\u0411\u043e\u0431\u043e\u0432\u0446\u044b"
    ],
    "name:ukr_x_preferred":[
        "\u0411\u043e\u0431\u0456\u0432\u0446\u0456"
    ],
    "name:unk_x_variant":[
        "Bobeshti"
    ],
    "qs:a0":"\u0423\u043a\u0440\u0430\u0457\u043d\u0430",
    "qs:a1":"*\u0427\u0435\u0440\u043d\u0456\u0432\u0435\u0446\u044c\u043a\u0430",
    "qs:a1_alt":"Chernivets'ka",
    "qs:a1r":"0",
    "qs:a2":"\u0421\u0442\u043e\u0440\u043e\u0436\u0438\u043d\u0435\u0446\u044c\u043a\u0438\u0439",
    "qs:a2_alt":"Storozhynets'kyi",
    "qs:adm0":"\u0423\u043a\u0440\u0430\u0457\u043d\u0430",
    "qs:la_lc":"*",
    "qs:level":"locality",
    "qs:loc":"\u0411\u043e\u0431\u0456\u0432\u0446\u0456",
    "qs:loc_alt":"Bobivtsi",
    "qs:pop":0,
    "qs:type":"buffered point",
    "wd:wordcount":42,
    "wof:name":"\u0411\u043e\u0431\u0456\u0432\u0446\u0456",
    "wof:placetype":"locality"
},
  "geometry": {"coordinates":[25.692163,48.262915],"type":"Point"}
}