{
  "type": "Feature",
  "properties": {
    "gn:admin1_code":"18.0",
    "gn:asciiname":"Porskalivka",
    "gn:country_code":"UA",
    "gn:dem":159,
    "gn:feature_class":"P",
    "gn:feature_code":"PPL",
    "gn:name":"Porskalivka",
    "gn:population":0,
    "gn:timezone":"Europe/Kiev",
    "iso:country":"UA",
    "name:ukr_x_preferred":[
        "Porskalivka"
    ],
    "name:ukr_x_variant":[
        "\u041f\u043e\u0440\u0441\u043a\u0430\u043b\u0456\u0432\u043a\u0430"
    ],
    "name:und_x_variant":[
        "Proskolovka",
        "Porskal\u00ebvka"
    ],
    "wof:name":"Porskalivka",
    "wof:placetype":"locality"
},
  "geometry": {"coordinates":[34.21408,49.98485],"type":"Point"}
}