{
  "type": "Feature",
  "properties": {
    "gn:admin1_code":"14.0",
    "gn:asciiname":"Voroshilovka",
    "gn:cc2":"UA",
    "gn:country_code":"UA",
    "gn:dem":114,
    "gn:feature_class":"P",
    "gn:feature_code":"PPL",
    "gn:name":"Voroshilovka",
    "gn:population":0,
    "gn:timezone":"Europe/Kiev",
    "iso:country":"UA",
    "name:ceb_x_preferred":[
        "Voroshilovka"
    ],
    "name:hye_x_preferred":[
        "\u054e\u0578\u0580\u0578\u0577\u056b\u056c\u0578\u057e\u056f\u0561"
    ],
    "name:rus_x_preferred":[
        "\u0412\u043e\u0440\u043e\u0448\u0438\u043b\u043e\u0432\u043a\u0430"
    ],
    "name:swe_x_preferred":[
        "Voroshilovka"
    ],
    "name:und_x_variant":[
        "Voroshilovo Pervoye"
    ],
    "wof:name":"Voroshilovka",
    "wof:placetype":"locality"
},
  "geometry": {"coordinates":[38.23417,48.855],"type":"Point"}
}