{
  "type": "Feature",
  "properties": {
    "gn:admin1_code":"14.0",
    "gn:asciiname":"Voroshilovka",
    "gn:cc2":"UA",
    "gn:country_code":"UA",
    "gn:dem":114,
    "gn:feature_class":"P",
    "gn:feature_code":"PPL",
    "gn:name":"Voroshilovka",
    "gn:population":0,
    "gn:timezone":"Europe/Kiev",
    "iso:country":"UA",
    "name:und_x_variant":[
        "Voroshilovo Pervoye",
        "Voroshilovka"
    ],
    "wof:name":"Voroshilovka",
    "wof:placetype":"locality"
},
  "geometry": {"coordinates":[38.23417,48.855],"type":"Point"}
}