{
  "type": "Feature",
  "properties": {
    "gn:admin1_code":"4.0",
    "gn:asciiname":"Kyslychuvata",
    "gn:country_code":"UA",
    "gn:dem":63,
    "gn:feature_class":"P",
    "gn:feature_code":"PPL",
    "gn:name":"Kyslychuvata",
    "gn:population":0,
    "gn:timezone":"Europe/Kiev",
    "iso:country":"UA",
    "name:rus_x_preferred":[
        "\u041a\u0438\u0441\u043b\u0438\u0447\u0435\u0432\u0430\u0442\u0430\u044f"
    ],
    "name:ukr_x_preferred":[
        "Kyslychuvata"
    ],
    "name:ukr_x_variant":[
        "\u041a\u0438\u0441\u043b\u0438\u0447\u0443\u0432\u0430\u0442\u0430"
    ],
    "name:und_x_variant":[
        "Kislichevata",
        "Kislichevataya"
    ],
    "wof:name":"Kyslychuvata",
    "wof:placetype":"locality"
},
  "geometry": {"coordinates":[34.71283,47.85929],"type":"Point"}
}