{
  "type": "Feature",
  "properties": {
    "gn:admin1_code":"3.0",
    "gn:asciiname":"Bila",
    "gn:country_code":"UA",
    "gn:dem":198,
    "gn:feature_class":"P",
    "gn:feature_code":"PPL",
    "gn:name":"Bila",
    "gn:population":0,
    "gn:timezone":"Europe/Kiev",
    "iso:country":"UA",
    "name:und_x_variant":[
        "Belaya",
        "Bila"
    ],
    "wof:name":"Bila",
    "wof:placetype":"locality"
},
  "geometry": {"coordinates":[25.88124,48.31803],"type":"Point"}
}