{
  "type": "Feature",
  "properties": {
    "iso:country":"UA",
    "name:bel_x_preferred":[
        "\u0413\u0440\u0430\u0434\u044d\u043d\u044b\u0446\u0456"
    ],
    "name:che_x_preferred":[
        "\u0413\u0440\u0430\u0434\u0435\u043d\u0438\u0446\u044b"
    ],
    "name:crh_x_preferred":[
        "Graden\u0131tsi"
    ],
    "name:deu_x_preferred":[
        "Hradenyzi"
    ],
    "name:eng_x_preferred":[
        "Hradenytsi"
    ],
    "name:fin_x_preferred":[
        "Hr\u0430d\u0435nyts\u0456"
    ],
    "name:lav_x_preferred":[
        "Hradenici"
    ],
    "name:nan_x_preferred":[
        "Hradenytsi"
    ],
    "name:nno_x_preferred":[
        "Hradenytsi"
    ],
    "name:nob_x_preferred":[
        "Hradenytsi"
    ],
    "name:pol_x_preferred":[
        "Hradenyci"
    ],
    "name:ron_x_preferred":[
        "Hraden\u00ee\u021bi"
    ],
    "name:ron_x_variant":[
        "Gr\u0103dini\u021ba"
    ],
    "name:rus_x_preferred":[
        "\u0413\u0440\u0430\u0434\u0435\u043d\u0438\u0446\u0456"
    ],
    "name:rus_x_variant":[
        "\u0413\u0440\u0430\u0434\u0435\u043d\u0438\u0446\u044b"
    ],
    "name:spa_x_preferred":[
        "Hradenytsi"
    ],
    "name:ukr_x_preferred":[
        "\u0413\u0440\u0430\u0434\u0435\u043d\u0438\u0446\u0456"
    ],
    "name:ukr_x_variant":[
        "Hradenytsi"
    ],
    "name:und_x_variant":[
        "Gradenitsa"
    ],
    "name:zho_x_preferred":[
        "\u683c\u62c9\u5091\u5c3c\u9f4a"
    ],
    "qs:a0":"\u0423\u043a\u0440\u0430\u0457\u043d\u0430",
    "qs:a1":"*\u041e\u0434\u0435\u0441\u044c\u043a\u0430",
    "qs:a1_alt":"Odes'ka",
    "qs:a1r":"0",
    "qs:a2":"\u0411\u0456\u043b\u044f\u0457\u0432\u0441\u044c\u043a\u0438\u0439",
    "qs:a2_alt":"Biliaivs'kyi",
    "qs:adm0":"\u0423\u043a\u0440\u0430\u0457\u043d\u0430",
    "qs:la_lc":"*",
    "qs:level":"locality",
    "qs:loc":"\u0413\u0440\u0430\u0434\u0435\u043d\u0438\u0446\u0456",
    "qs:loc_alt":"Hradenytsi",
    "qs:pop":0,
    "qs:type":"buffered point",
    "wof:name":"\u0413\u0440\u0430\u0434\u0435\u043d\u0438\u0446\u0456",
    "wof:placetype":"locality"
},
  "geometry": {"coordinates":[29.988983,46.605084],"type":"Point"}
}