{
  "type": "Feature",
  "properties": {
    "iso:country":"UA",
    "name:srp_x_preferred":[
        "\u0420\u043e\u043c\u0438 \u0443 \u0421\u0440\u0431\u0438\u0458\u0438"
    ],
    "name:und_x_variant":[
        "Tsygany"
    ],
    "qs:a0":"\u0423\u043a\u0440\u0430\u0457\u043d\u0430",
    "qs:a1":"*\u0422\u0435\u0440\u043d\u043e\u043f\u0456\u043b\u044c\u0441\u044c\u043a\u0430",
    "qs:a1_alt":"Ternopil's'ka",
    "qs:a1r":"0",
    "qs:a2":"\u0411\u043e\u0440\u0449\u0456\u0432\u0441\u044c\u043a\u0438\u0439",
    "qs:a2_alt":"Borschivs'kyi",
    "qs:adm0":"\u0423\u043a\u0440\u0430\u0457\u043d\u0430",
    "qs:la_lc":"*",
    "qs:level":"locality",
    "qs:loc":"\u0426\u0438\u0433\u0430\u043d\u0438",
    "qs:loc_alt":"Tsyhany",
    "qs:pop":0,
    "qs:type":"buffered point",
    "wd:wordcount":1194,
    "wof:name":"\u0426\u0438\u0433\u0430\u043d\u0438",
    "wof:placetype":"locality"
},
  "geometry": {"coordinates":[26.09931,48.868562],"type":"Point"}
}