{
  "type": "Feature",
  "properties": {
    "gn:admin1_code":"2.0",
    "gn:asciiname":"Sergeyevskiy",
    "gn:country_code":"UA",
    "gn:dem":163,
    "gn:feature_class":"P",
    "gn:feature_code":"PPL",
    "gn:name":"Sergeyevskiy",
    "gn:population":0,
    "gn:timezone":"Europe/Kiev",
    "iso:country":"UA",
    "name:ukr_x_preferred":[
        "Serhiyivs\u2019ke"
    ],
    "name:ukr_x_variant":[
        "\u0421\u0435\u0440\u0433\u0456\u0457\u0432\u0441\u044c\u043a\u0435"
    ],
    "wof:name":"Sergeyevskiy",
    "wof:placetype":"locality"
},
  "geometry": {"coordinates":[32.87864,52.22464],"type":"Point"}
}