{
  "type": "Feature",
  "properties": {
    "gn:admin1_code":"11.0",
    "gn:admin2_code":"709333",
    "gn:admin3_code":"11152862",
    "gn:asciiname":"Zernovoye",
    "gn:country_code":"UA",
    "gn:dem":37,
    "gn:elevation":"35.0",
    "gn:feature_class":"P",
    "gn:feature_code":"PPL",
    "gn:name":"Zernovoye",
    "gn:population":627,
    "gn:timezone":"Europe/Simferopol",
    "iso:country":"UA",
    "name:eng_x_preferred":[
        "Zernovoye"
    ],
    "name:rus_x_historical":[
        "\u0422\u044e\u0431\u0435\u0301\u0439"
    ],
    "name:rus_x_preferred":[
        "\u0417\u0435\u0440\u043d\u043e\u0432\u043e\u0435"
    ],
    "name:rus_x_variant":[
        "\u0422\u044e\u0431\u0435\u0301\u0439"
    ],
    "name:ukr_x_preferred":[
        "\u0417\u0435\u0440\u043d\u043e\u0432\u0435"
    ],
    "wof:name":"Zernovoye",
    "wof:placetype":"locality",
    "wof:population":627
},
  "geometry": {"coordinates":[34.14355,45.62962],"type":"Point"}
}