{
  "type": "Feature",
  "properties": {
    "gn:admin1_code":"16.0",
    "gn:asciiname":"Novyy Fontan",
    "gn:cc2":"UA",
    "gn:country_code":"UA",
    "gn:dem":98,
    "gn:feature_class":"P",
    "gn:feature_code":"PPL",
    "gn:name":"Novyy Fontan",
    "gn:population":0,
    "gn:timezone":"Europe/Kiev",
    "iso:country":"UA",
    "name:und_x_variant":[
        "Novy Fontan",
        "Novyy Fontan"
    ],
    "wof:name":"Novyy Fontan",
    "wof:placetype":"locality"
},
  "geometry": {"coordinates":[31.41667,47.78333],"type":"Point"}
}