{
  "type": "Feature",
  "properties": {
    "gn:admin1_code":"27.0",
    "gn:asciiname":"Onyshpil'",
    "gn:country_code":"UA",
    "gn:dem":183,
    "gn:feature_class":"P",
    "gn:feature_code":"PPL",
    "gn:name":"Onyshpil\u2019",
    "gn:population":0,
    "gn:timezone":"Europe/Kiev",
    "iso:country":"UA",
    "name:ukr_x_preferred":[
        "Onyshpil\u2019"
    ],
    "name:ukr_x_variant":[
        "\u041e\u043d\u0438\u0448\u043f\u0456\u043b\u044c"
    ],
    "name:und_x_variant":[
        "Onishpol\u2019"
    ],
    "wof:name":"Onyshpil'",
    "wof:placetype":"locality"
},
  "geometry": {"coordinates":[29.30895,50.21353],"type":"Point"}
}