{
  "type": "Feature",
  "properties": {
    "gn:admin1_code":"16.0",
    "gn:asciiname":"Kamennoye",
    "gn:country_code":"UA",
    "gn:dem":91,
    "gn:feature_class":"P",
    "gn:feature_code":"PPL",
    "gn:name":"Kamennoye",
    "gn:population":0,
    "gn:timezone":"Europe/Kiev",
    "iso:country":"UA",
    "name:und_x_variant":[
        "Kamyana",
        "Kamennoye"
    ],
    "wof:name":"Kamennoye",
    "wof:placetype":"locality"
},
  "geometry": {"coordinates":[32.33845,47.76995],"type":"Point"}
}