{
  "type": "Feature",
  "properties": {
    "gn:admin1_code":"27.0",
    "gn:asciiname":"Tseberka",
    "gn:country_code":"UA",
    "gn:dem":236,
    "gn:feature_class":"P",
    "gn:feature_code":"PPL",
    "gn:name":"Tseberka",
    "gn:population":0,
    "gn:timezone":"Europe/Kiev",
    "iso:country":"UA",
    "name:ukr_x_preferred":[
        "\u0426\u0435\u0431\u0435\u0440\u043a\u0430"
    ],
    "name:und_x_variant":[
        "Syaberki",
        "Tseberka"
    ],
    "wof:name":"Tseberka",
    "wof:placetype":"locality"
},
  "geometry": {"coordinates":[27.8369,50.213],"type":"Point"}
}