{
  "type": "Feature",
  "properties": {
    "gn:admin1_code":"21.0",
    "gn:asciiname":"Novoukrainka",
    "gn:country_code":"UA",
    "gn:dem":149,
    "gn:feature_class":"P",
    "gn:feature_code":"PPL",
    "gn:name":"Novoukrainka",
    "gn:population":0,
    "gn:timezone":"Europe/Kiev",
    "iso:country":"UA",
    "name:ukr_x_preferred":[
        "Novoukrainka"
    ],
    "name:ukr_x_variant":[
        "\u041d\u043e\u0432\u043e\u0443\u043a\u0440\u0430\u0456\u043d\u043a\u0430"
    ],
    "name:und_x_variant":[
        "Budy"
    ],
    "wof:name":"Novoukrainka",
    "wof:placetype":"locality"
},
  "geometry": {"coordinates":[35.13831,50.47991],"type":"Point"}
}