{
  "type": "Feature",
  "properties": {
    "gn:admin1_code":"21.0",
    "gn:asciiname":"Novoukrainka",
    "gn:country_code":"UA",
    "gn:dem":149,
    "gn:feature_class":"P",
    "gn:feature_code":"PPL",
    "gn:name":"Novoukrainka",
    "gn:population":0,
    "gn:timezone":"Europe/Kiev",
    "iso:country":"UA",
    "name:azb_x_preferred":[
        "\u0646\u0648\u0648\u06a9\u0631\u0627\u0626\u06cc\u0646\u06a9\u0627"
    ],
    "name:bel_x_preferred":[
        "\u041d\u043e\u0432\u0430\u045e\u043a\u0440\u0430\u0456\u043d\u043a\u0430"
    ],
    "name:ceb_x_preferred":[
        "Novoukrayinka"
    ],
    "name:ces_x_preferred":[
        "Novoukrajinka"
    ],
    "name:crh_x_preferred":[
        "Novoukrayinka"
    ],
    "name:deu_x_preferred":[
        "Nowoukrajinka"
    ],
    "name:fas_x_preferred":[
        "\u0646\u0648\u0648\u06a9\u0631\u0627\u0626\u06cc\u0646\u06a9\u0627"
    ],
    "name:fra_x_preferred":[
        "Novooukra\u00efnka"
    ],
    "name:heb_x_preferred":[
        "\u05e0\u05d5\u05d1\u05d5\u05d0\u05d5\u05e7\u05e8\u05d0\u05d9\u05e0\u05e7\u05d4"
    ],
    "name:hsb_x_preferred":[
        "Nowoukrajinka"
    ],
    "name:hye_x_preferred":[
        "\u0546\u0578\u057e\u0578\u0578\u0582\u056f\u0580\u0561\u056b\u0576\u056f\u0561"
    ],
    "name:ita_x_preferred":[
        "Novoukra\u00efnka"
    ],
    "name:kat_x_preferred":[
        "\u10dc\u10dd\u10d5\u10dd\u10e3\u10d9\u10e0\u10d0\u10d8\u10dc\u10d9\u10d0"
    ],
    "name:lez_x_preferred":[
        "\u041d\u043e\u0432\u043e\u0443\u043a\u0440\u0430\u0438\u043d\u043a\u0430"
    ],
    "name:nno_x_preferred":[
        "Novoukrajinka"
    ],
    "name:pol_x_preferred":[
        "Nowoukrajinka"
    ],
    "name:ron_x_preferred":[
        "Novoukraiinka"
    ],
    "name:rus_x_preferred":[
        "\u041d\u043e\u0432\u043e\u0443\u043a\u0440\u0430\u0438\u043d\u043a\u0430"
    ],
    "name:swe_x_preferred":[
        "Novoukrajinka"
    ],
    "name:ukr_x_preferred":[
        "Novoukrainka"
    ],
    "name:ukr_x_variant":[
        "\u041d\u043e\u0432\u043e\u0443\u043a\u0440\u0430\u0456\u043d\u043a\u0430",
        "\u041d\u043e\u0432\u043e\u0443\u043a\u0440\u0430\u0457\u043d\u043a\u0430"
    ],
    "name:und_x_variant":[
        "Budy"
    ],
    "name:vie_x_preferred":[
        "Novoukrainka"
    ],
    "name:zho_x_preferred":[
        "\u65b0\u70cf\u514b\u862d\u5361"
    ],
    "wof:name":"Novoukrainka",
    "wof:placetype":"locality"
},
  "geometry": {"coordinates":[35.13831,50.47991],"type":"Point"}
}