{
  "type": "Feature",
  "properties": {
    "gn:admin1_code":"6.0",
    "gn:asciiname":"Kubayuvka",
    "gn:country_code":"UA",
    "gn:dem":407,
    "gn:feature_class":"P",
    "gn:feature_code":"PPL",
    "gn:name":"Kubayuvka",
    "gn:population":0,
    "gn:timezone":"Europe/Kiev",
    "iso:country":"UA",
    "name:und_x_variant":[
        "Kubayevka",
        "Kubayuvka"
    ],
    "wof:name":"Kubayuvka",
    "wof:placetype":"locality"
},
  "geometry": {"coordinates":[24.79921,48.61201],"type":"Point"}
}