{
  "type": "Feature",
  "properties": {
    "gn:admin1_code":"6.0",
    "gn:asciiname":"Podgorod'ye",
    "gn:country_code":"UA",
    "gn:dem":265,
    "gn:feature_class":"P",
    "gn:feature_code":"PPL",
    "gn:name":"Podgorod\u2019ye",
    "gn:population":0,
    "gn:timezone":"Europe/Kiev",
    "iso:country":"UA",
    "name:und_x_variant":[
        "Podgrodzie",
        "Pidgoroddya",
        "Podgrodze",
        "Podgorod\u2019ye"
    ],
    "wof:name":"Podgorod'ye",
    "wof:placetype":"locality"
},
  "geometry": {"coordinates":[24.59584,49.44266],"type":"Point"}
}