{
  "type": "Feature",
  "properties": {
    "gn:admin1_code":"17.0",
    "gn:asciiname":"Bol'shaya Vasil'yevka",
    "gn:country_code":"UA",
    "gn:dem":61,
    "gn:feature_class":"P",
    "gn:feature_code":"PPL",
    "gn:name":"Bol\u2019shaya Vasil\u2019yevka",
    "gn:population":0,
    "gn:timezone":"Europe/Kiev",
    "iso:country":"UA",
    "wof:name":"Bol'shaya Vasil'yevka",
    "wof:placetype":"locality"
},
  "geometry": {"coordinates":[30.23381,47.64341],"type":"Point"}
}