{
  "type": "Feature",
  "properties": {
    "gn:admin1_code":"24.0",
    "gn:asciiname":"Okhotyn",
    "gn:country_code":"UA",
    "gn:dem":232,
    "gn:feature_class":"P",
    "gn:feature_code":"PPL",
    "gn:name":"Okhotyn",
    "gn:population":0,
    "gn:timezone":"Europe/Kiev",
    "iso:country":"UA",
    "name:ukr_x_preferred":[
        "Okhotyn"
    ],
    "name:ukr_x_variant":[
        "\u041e\u0445\u043e\u0442\u0438\u043d"
    ],
    "name:und_x_variant":[
        "Okhotin"
    ],
    "wof:name":"Okhotyn",
    "wof:placetype":"locality"
},
  "geometry": {"coordinates":[25.11065,50.75435],"type":"Point"}
}