{
  "type": "Feature",
  "properties": {
    "gn:admin1_code":"26.0",
    "gn:asciiname":"Rozivka",
    "gn:country_code":"UA",
    "gn:dem":119,
    "gn:feature_class":"P",
    "gn:feature_code":"PPL",
    "gn:name":"Rozivka",
    "gn:population":0,
    "gn:timezone":"Europe/Zaporozhye",
    "iso:country":"UA",
    "name:ukr_x_preferred":[
        "Rozivka"
    ],
    "name:ukr_x_variant":[
        "\u0420\u043e\u0437\u0456\u0432\u043a\u0430"
    ],
    "wof:name":"Rozivka",
    "wof:placetype":"locality"
},
  "geometry": {"coordinates":[35.98639,47.84406],"type":"Point"}
}