{
  "type": "Feature",
  "properties": {
    "gn:admin1_code":"26.0",
    "gn:asciiname":"Zaporozhskiy",
    "gn:country_code":"UA",
    "gn:dem":85,
    "gn:feature_class":"P",
    "gn:feature_code":"PPL",
    "gn:name":"Zaporozhskiy",
    "gn:population":0,
    "gn:timezone":"Europe/Zaporozhye",
    "iso:country":"UA",
    "wof:name":"Zaporozhskiy",
    "wof:placetype":"locality"
},
  "geometry": {"coordinates":[35.36667,47.78333],"type":"Point"}
}