{
  "type": "Feature",
  "properties": {
    "gn:admin1_code":"14.0",
    "gn:asciiname":"Kochyne-Rozpasiyivka",
    "gn:country_code":"UA",
    "gn:dem":171,
    "gn:feature_class":"P",
    "gn:feature_code":"PPL",
    "gn:name":"Kochyne-Rozpasiyivka",
    "gn:population":0,
    "gn:timezone":"Europe/Zaporozhye",
    "iso:country":"UA",
    "name:ukr_x_preferred":[
        "Kochyne-Rozpasiyivka"
    ],
    "name:ukr_x_variant":[
        "\u041a\u043e\u0447\u0438\u043d\u0435-\u0420\u043e\u0437\u043f\u0430\u0441\u0456\u0457\u0432\u043a\u0430"
    ],
    "name:und_x_variant":[
        "Kochino-Raspaseyevka"
    ],
    "wof:name":"Kochyne-Rozpasiyivka",
    "wof:placetype":"locality"
},
  "geometry": {"coordinates":[38.59373,49.77137000000001],"type":"Point"}
}