{
  "type": "Feature",
  "properties": {
    "gn:admin1_code":"2.0",
    "gn:asciiname":"Ladynka",
    "gn:country_code":"UA",
    "gn:dem":108,
    "gn:feature_class":"P",
    "gn:feature_code":"PPL",
    "gn:name":"Ladynka",
    "gn:population":0,
    "gn:timezone":"Europe/Kiev",
    "iso:country":"UA",
    "name:eng_x_preferred":[
        "Ladinka"
    ],
    "name:rus_x_preferred":[
        "\u041b\u0430\u0434\u0438\u043d\u043a\u0430"
    ],
    "name:ukr_x_preferred":[
        "Ladynka"
    ],
    "name:ukr_x_variant":[
        "\u041b\u0430\u0434\u0438\u043d\u043a\u0430"
    ],
    "name:und_x_variant":[
        "Ladinka"
    ],
    "wof:name":"Ladynka",
    "wof:placetype":"locality"
},
  "geometry": {"coordinates":[31.14444,51.28621],"type":"Point"}
}