{
  "type": "Feature",
  "properties": {
    "gn:admin1_code":"9.0",
    "gn:asciiname":"Ruzha",
    "gn:country_code":"UA",
    "gn:dem":258,
    "gn:feature_class":"P",
    "gn:feature_code":"PPL",
    "gn:name":"Ruzha",
    "gn:population":0,
    "gn:timezone":"Europe/Kiev",
    "iso:country":"UA",
    "wof:name":"Ruzha",
    "wof:placetype":"locality"
},
  "geometry": {"coordinates":[26.33875,48.86122],"type":"Point"}
}