{
  "type": "Feature",
  "properties": {
    "gn:admin1_code":"18.0",
    "gn:asciiname":"Lisova Slobidka",
    "gn:country_code":"UA",
    "gn:dem":96,
    "gn:feature_class":"P",
    "gn:feature_code":"PPL",
    "gn:name":"Lisova Slobidka",
    "gn:population":0,
    "gn:timezone":"Europe/Kiev",
    "iso:country":"UA",
    "name:ukr_x_preferred":[
        "Lisova Slobidka"
    ],
    "name:ukr_x_variant":[
        "\u041b\u0456\u0441\u043e\u0432\u0430 \u0421\u043b\u043e\u0431\u0456\u0434\u043a\u0430"
    ],
    "wof:name":"Lisova Slobidka",
    "wof:placetype":"locality"
},
  "geometry": {"coordinates":[32.98303,50.15816],"type":"Point"}
}