{
  "type": "Feature",
  "properties": {
    "gn:admin1_code":"7.0",
    "gn:asciiname":"Aleksandrovka",
    "gn:country_code":"UA",
    "gn:dem":108,
    "gn:feature_class":"P",
    "gn:feature_code":"PPL",
    "gn:name":"Aleksandrovka",
    "gn:population":0,
    "gn:timezone":"Europe/Kiev",
    "iso:country":"UA",
    "name:rus_x_preferred":[
        "\u0410\u043b\u0435\u043a\u0441\u0430\u043d\u0434\u0440\u043e\u0432\u043a\u0430-\u041f\u0435\u0440\u0432\u0430\u044f"
    ],
    "name:und_x_variant":[
        "Aleksandrovka-Pervaya"
    ],
    "wof:name":"Aleksandrovka",
    "wof:placetype":"locality"
},
  "geometry": {"coordinates":[36.12361,49.04417],"type":"Point"}
}