{
  "type": "Feature",
  "properties": {
    "gn:admin1_code":"23.0",
    "gn:asciiname":"Chernyatintsy",
    "gn:country_code":"UA",
    "gn:dem":257,
    "gn:feature_class":"P",
    "gn:feature_code":"PPL",
    "gn:name":"Chernyatintsy",
    "gn:population":0,
    "gn:timezone":"Europe/Kiev",
    "iso:country":"UA",
    "wof:name":"Chernyatintsy",
    "wof:placetype":"locality"
},
  "geometry": {"coordinates":[28.16651,49.64017],"type":"Point"}
}