{
  "type": "Feature",
  "properties": {
    "gn:admin1_code":"24.0",
    "gn:asciiname":"Rudka-Chervyns'ka",
    "gn:country_code":"UA",
    "gn:dem":153,
    "gn:feature_class":"P",
    "gn:feature_code":"PPL",
    "gn:name":"Rudka-Chervyns\u2019ka",
    "gn:population":0,
    "gn:timezone":"Europe/Kiev",
    "iso:country":"UA",
    "name:ukr_x_preferred":[
        "Rudka-Chervyns\u2019ka"
    ],
    "name:ukr_x_variant":[
        "\u0420\u0443\u0434\u043a\u0430-\u0427\u0435\u0440\u0432\u0438\u043d\u0441\u044c\u043a\u0430"
    ],
    "name:und_x_variant":[
        "Rudka",
        "Rudka Chervinskaya"
    ],
    "wof:name":"Rudka-Chervyns'ka",
    "wof:placetype":"locality"
},
  "geometry": {"coordinates":[25.3509,51.57011],"type":"Point"}
}