{
  "type": "Feature",
  "properties": {
    "gn:admin1_code":"21.0",
    "gn:asciiname":"Retyk",
    "gn:country_code":"UA",
    "gn:dem":148,
    "gn:feature_class":"P",
    "gn:feature_code":"PPL",
    "gn:name":"Retyk",
    "gn:population":0,
    "gn:timezone":"Europe/Kiev",
    "iso:country":"UA",
    "name:ukr_x_preferred":[
        "Retyk"
    ],
    "name:ukr_x_variant":[
        "\u0420\u0435\u0442\u0438\u043a"
    ],
    "name:und_x_variant":[
        "Retik"
    ],
    "wof:name":"Retyk",
    "wof:placetype":"locality"
},
  "geometry": {"coordinates":[33.50913,51.59446],"type":"Point"}
}