{
  "type": "Feature",
  "properties": {
    "gn:admin1_code":"5.0",
    "gn:asciiname":"Samiylove",
    "gn:country_code":"UA",
    "gn:dem":76,
    "gn:feature_class":"P",
    "gn:feature_code":"PPL",
    "gn:name":"Samiylove",
    "gn:population":0,
    "gn:timezone":"Europe/Kiev",
    "iso:country":"UA",
    "name:ukr_x_preferred":[
        "\u0421\u0430\u043c\u0456\u0439\u043b\u043e\u0432\u0435"
    ],
    "name:und_x_variant":[
        "Samoylovo",
        "Samoylov",
        "Samiylove"
    ],
    "wof:name":"Samiylove",
    "wof:placetype":"locality"
},
  "geometry": {"coordinates":[38.24353,47.25492],"type":"Point"}
}