{
  "type": "Feature",
  "properties": {
    "gn:admin1_code":"23.0",
    "gn:asciiname":"Glinyanka",
    "gn:country_code":"UA",
    "gn:dem":266,
    "gn:feature_class":"P",
    "gn:feature_code":"PPL",
    "gn:name":"Glinyanka",
    "gn:population":0,
    "gn:timezone":"Europe/Kiev",
    "iso:country":"UA",
    "wof:name":"Glinyanka",
    "wof:placetype":"locality"
},
  "geometry": {"coordinates":[27.78468,49.07351],"type":"Point"}
}