{
  "type": "Feature",
  "properties": {
    "gn:admin1_code":"17.0",
    "gn:asciiname":"Sherovo",
    "gn:country_code":"UA",
    "gn:dem":18,
    "gn:feature_class":"P",
    "gn:feature_code":"PPL",
    "gn:name":"Sherovo",
    "gn:population":0,
    "gn:timezone":"Europe/Kiev",
    "iso:country":"UA",
    "name:und_x_variant":[
        "Sharovo",
        "Sherovo"
    ],
    "wof:name":"Sherovo",
    "wof:placetype":"locality"
},
  "geometry": {"coordinates":[30.4803,47.01067000000001],"type":"Point"}
}