{
  "type": "Feature",
  "properties": {
    "gn:admin1_code":"25.0",
    "gn:asciiname":"Shcherbovets'",
    "gn:country_code":"UA",
    "gn:dem":549,
    "gn:feature_class":"P",
    "gn:feature_code":"PPL",
    "gn:name":"Shcherbovets\u2019",
    "gn:population":0,
    "gn:timezone":"Europe/Uzhgorod",
    "iso:country":"UA",
    "name:ukr_x_preferred":[
        "Shcherbovets\u2019"
    ],
    "name:ukr_x_variant":[
        "\u0429\u0435\u0440\u0431\u043e\u0432\u0435\u0446\u044c"
    ],
    "name:und_x_variant":[
        "Sherbovtsy",
        "Shcherbovets"
    ],
    "wof:name":"Shcherbovets'",
    "wof:placetype":"locality"
},
  "geometry": {"coordinates":[22.95875,48.80744],"type":"Point"}
}