{
  "type": "Feature",
  "properties": {
    "gn:admin1_code":"6.0",
    "gn:asciiname":"Ustechko",
    "gn:country_code":"UA",
    "gn:dem":162,
    "gn:feature_class":"P",
    "gn:feature_code":"PPL",
    "gn:name":"Ustechko",
    "gn:population":0,
    "gn:timezone":"Europe/Kiev",
    "iso:country":"UA",
    "name:und_x_variant":[
        "U\u015bcieczko",
        "Usechko",
        "Us\u2019tsechko",
        "Ustechko"
    ],
    "wof:name":"Ustechko",
    "wof:placetype":"locality"
},
  "geometry": {"coordinates":[25.59759,48.77493],"type":"Point"}
}