{
  "type": "Feature",
  "properties": {
    "gn:admin1_code":"11.0",
    "gn:admin2_code":"705800",
    "gn:admin3_code":"11152901",
    "gn:asciiname":"Vasil'kovoye",
    "gn:country_code":"UA",
    "gn:dem":12,
    "gn:elevation":"14.0",
    "gn:feature_class":"P",
    "gn:feature_code":"PPL",
    "gn:name":"Vasil\u2019kovoye",
    "gn:population":281,
    "gn:timezone":"Europe/Simferopol",
    "iso:country":"UA",
    "name:rus_x_historical":[
        "\u0410\u043f\u043f\u0430\u0301\u043a-\u0414\u0436\u0430\u043d\u043a\u043e\u0301\u0439"
    ],
    "name:rus_x_preferred":[
        "\u0412\u0430\u0441\u0438\u043b\u044c\u043a\u043e\u0432\u043e\u0435"
    ],
    "name:rus_x_variant":[
        "\u0410\u043f\u043f\u0430\u0301\u043a-\u0414\u0436\u0430\u043d\u043a\u043e\u0301\u0439",
        "Vasil\u2019kovo"
    ],
    "name:ukr_x_preferred":[
        "\u0412\u0430\u0441\u0438\u043b\u044c\u043a\u043e\u0432\u0435"
    ],
    "wof:name":"Vasil'kovoye",
    "wof:placetype":"locality",
    "wof:population":281
},
  "geometry": {"coordinates":[35.31061,45.2031],"type":"Point"}
}