{
  "type": "Feature",
  "properties": {
    "gn:admin1_code":"23.0",
    "gn:asciiname":"Ksaverovka",
    "gn:country_code":"UA",
    "gn:dem":262,
    "gn:feature_class":"P",
    "gn:feature_code":"PPL",
    "gn:name":"Ksaverovka",
    "gn:population":0,
    "gn:timezone":"Europe/Kiev",
    "iso:country":"UA",
    "wof:name":"Ksaverovka",
    "wof:placetype":"locality"
},
  "geometry": {"coordinates":[28.98333,49.26667],"type":"Point"}
}