{
  "type": "Feature",
  "properties": {
    "gn:admin1_code":"5.0",
    "gn:asciiname":"Oleksiyevo-Druzhkivka",
    "gn:country_code":"UA",
    "gn:dem":76,
    "gn:feature_class":"P",
    "gn:feature_code":"PPL",
    "gn:name":"Oleksiyevo-Druzhkivka",
    "gn:population":0,
    "gn:timezone":"Europe/Kiev",
    "iso:country":"UA",
    "name:eng_x_preferred":[
        "Alekseyevo-Druzhkovka"
    ],
    "name:rus_x_preferred":[
        "\u0410\u043b\u0435\u043a\u0441\u0435\u0435\u0432\u043e-\u0414\u0440\u0443\u0436\u043a\u043e\u0432\u043a\u0430"
    ],
    "name:ukr_x_preferred":[
        "Oleksiyevo-Druzhkivka"
    ],
    "name:ukr_x_variant":[
        "\u041e\u043b\u0435\u043a\u0441\u0456\u0454\u0432\u043e-\u0414\u0440\u0443\u0436\u043a\u0456\u0432\u043a\u0430"
    ],
    "name:und_x_variant":[
        "Drushkowka",
        "Druzhkovka",
        "Druzhovka",
        "Alekseyevo-Druzhkovka"
    ],
    "wof:name":"Oleksiyevo-Druzhkivka",
    "wof:placetype":"locality"
},
  "geometry": {"coordinates":[37.60941,48.57909],"type":"Point"}
}