{
  "type": "Feature",
  "properties": {
    "iso:country":"UA",
    "name:bul_x_preferred":[
        "\u0424\u0430\u0432\u043e\u0440\u043a\u0438"
    ],
    "name:dan_x_preferred":[
        "Klejner"
    ],
    "name:eng_x_preferred":[
        "Verguny"
    ],
    "name:fra_x_preferred":[
        "Bugne"
    ],
    "name:ita_x_preferred":[
        "Chiacchiere"
    ],
    "name:lit_x_preferred":[
        "\u017dagar\u0117lis"
    ],
    "name:pol_x_preferred":[
        "Faworki"
    ],
    "name:por_x_preferred":[
        "Cueca virada"
    ],
    "name:rus_x_preferred":[
        "\u0425\u0432\u043e\u0440\u043e\u0441\u0442"
    ],
    "name:rus_x_variant":[
        "\u0412\u0435\u0440\u0433\u0443\u043d\u044b"
    ],
    "name:spa_x_preferred":[
        "Sfrappole"
    ],
    "name:srd_x_preferred":[
        "Maravillas"
    ],
    "name:szl_x_preferred":[
        "Chrustki"
    ],
    "name:ukr_x_preferred":[
        "Verhuny"
    ],
    "name:ukr_x_variant":[
        "\u0412\u0435\u0440\u0433\u0443\u043d\u0438"
    ],
    "name:unk_x_variant":[
        "Verguny"
    ],
    "name:vec_x_preferred":[
        "Gr\u00f3sto\u0142i"
    ],
    "qs:a0":"\u0423\u043a\u0440\u0430\u0457\u043d\u0430",
    "qs:a1":"*\u0427\u0435\u0440\u043a\u0430\u0441\u044c\u043a\u0430",
    "qs:a1_alt":"Cherkas'ka",
    "qs:a1r":"0",
    "qs:a2":"\u0427\u0435\u0440\u043a\u0430\u0441\u044c\u043a\u0438\u0439",
    "qs:a2_alt":"Cherkas'kyi",
    "qs:adm0":"\u0423\u043a\u0440\u0430\u0457\u043d\u0430",
    "qs:la_lc":"*",
    "qs:level":"locality",
    "qs:loc":"\u0412\u0435\u0440\u0433\u0443\u043d\u0438",
    "qs:loc_alt":"Verhuny",
    "qs:pop":0,
    "qs:type":"buffered point",
    "wd:wordcount":761,
    "wof:name":"\u0412\u0435\u0440\u0433\u0443\u043d\u0438",
    "wof:placetype":"locality"
},
  "geometry": {"coordinates":[32.077528,49.314814],"type":"Point"}
}