{
  "type": "Feature",
  "properties": {
    "gn:admin1_code":"18.0",
    "gn:asciiname":"Yerkivtsi",
    "gn:country_code":"UA",
    "gn:dem":89,
    "gn:feature_class":"P",
    "gn:feature_code":"PPL",
    "gn:name":"Yerkivtsi",
    "gn:population":0,
    "gn:timezone":"Europe/Kiev",
    "iso:country":"UA",
    "name:ukr_x_preferred":[
        "Yerkivtsi"
    ],
    "name:ukr_x_variant":[
        "\u0404\u0440\u043a\u0456\u0432\u0446\u0456"
    ],
    "wof:name":"Yerkivtsi",
    "wof:placetype":"locality"
},
  "geometry": {"coordinates":[33.00457,49.92155],"type":"Point"}
}