{
  "type": "Feature",
  "properties": {
    "iso:country":"UA",
    "name:bel_x_variant":[
        "\u0428\u0443\u043b\u044f\u045e\u0441\u043a\u0430\u044f"
    ],
    "name:ita_x_preferred":[
        "\u0160uljavs'ka"
    ],
    "name:nld_x_preferred":[
        "Sjoeljavska"
    ],
    "name:pol_x_preferred":[
        "Szulaw\u015bka"
    ],
    "name:rus_x_preferred":[
        "\u0428\u0443\u043b\u044f\u0432\u0441\u043a\u0430\u044f"
    ],
    "name:ukr_x_preferred":[
        "\u0428\u0443\u043b\u044f\u0432\u0441\u044c\u043a\u0430"
    ],
    "name:zho_x_preferred":[
        "\u8212\u91cc\u4e9e\u592b\u5361\u7ad9"
    ],
    "qs:a0":"\u0423\u043a\u0440\u0430\u0457\u043d\u0430",
    "qs:a1":"*\u0425\u0430\u0440\u043a\u0456\u0432\u0441\u044c\u043a\u0430",
    "qs:a1_alt":"Kharkivs'ka",
    "qs:a1r":"0",
    "qs:a2":"\u041f\u0435\u0440\u0432\u043e\u043c\u0430\u0439\u0441\u044c\u043a\u0438\u0439",
    "qs:a2_alt":"Pervomais'kyi",
    "qs:adm0":"\u0423\u043a\u0440\u0430\u0457\u043d\u0430",
    "qs:la_lc":"*",
    "qs:level":"locality",
    "qs:loc":"\u0411\u0456\u043b\u044c\u0448\u043e\u0432\u0438\u043a",
    "qs:loc_alt":"Bil'shovyk",
    "qs:pop":0,
    "qs:type":"buffered point",
    "wd:wordcount":141,
    "wof:name":"\u0411\u0456\u043b\u044c\u0448\u043e\u0432\u0438\u043a",
    "wof:placetype":"locality"
},
  "geometry": {"coordinates":[36.14259,49.490311],"type":"Point"}
}