{
  "type": "Feature",
  "properties": {
    "iso:country":"UA",
    "qs:a0":"\u0423\u043a\u0440\u0430\u0457\u043d\u0430",
    "qs:a1":"*\u041a\u0456\u0440\u043e\u0432\u043e\u0433\u0440\u0430\u0434\u0441\u044c\u043a\u0430",
    "qs:a1_alt":"Kirovohrads'ka",
    "qs:a1r":"0",
    "qs:a2":"\u041e\u043b\u0435\u043a\u0441\u0430\u043d\u0434\u0440\u0456\u0439\u0441\u044c\u043a\u0438\u0439",
    "qs:a2_alt":"Oleksandriis'kyi",
    "qs:adm0":"\u0423\u043a\u0440\u0430\u0457\u043d\u0430",
    "qs:la_lc":"*",
    "qs:level":"locality",
    "qs:loc":"\u041c\u0430\u0440\u0442\u043e-\u0406\u0432\u0430\u043d\u0456\u0432\u043a\u0430",
    "qs:loc_alt":"Marto-Ivanivka",
    "qs:pop":0,
    "qs:type":"buffered point",
    "wof:name":"\u041c\u0430\u0440\u0442\u043e-\u0406\u0432\u0430\u043d\u0456\u0432\u043a\u0430",
    "wof:placetype":"locality"
},
  "geometry": {"coordinates":[33.096737,48.643623],"type":"Point"}
}