{
  "type": "Feature",
  "properties": {
    "gn:admin1_code":"18.0",
    "gn:asciiname":"Hlyboka Dolyna",
    "gn:country_code":"UA",
    "gn:dem":127,
    "gn:feature_class":"P",
    "gn:feature_code":"PPL",
    "gn:name":"Hlyboka Dolyna",
    "gn:population":0,
    "gn:timezone":"Europe/Kiev",
    "iso:country":"UA",
    "name:ukr_x_preferred":[
        "Hlyboka Dolyna"
    ],
    "name:ukr_x_variant":[
        "\u0413\u043b\u0438\u0431\u043e\u043a\u0430 \u0414\u043e\u043b\u0438\u043d\u0430"
    ],
    "wof:name":"Hlyboka Dolyna",
    "wof:placetype":"locality"
},
  "geometry": {"coordinates":[33.75752,49.42373],"type":"Point"}
}