{
  "type": "Feature",
  "properties": {
    "gn:admin1_code":"9.0",
    "gn:asciiname":"Lyubomyrka",
    "gn:country_code":"UA",
    "gn:dem":236,
    "gn:feature_class":"P",
    "gn:feature_code":"PPL",
    "gn:name":"Lyubomyrka",
    "gn:population":0,
    "gn:timezone":"Europe/Kiev",
    "iso:country":"UA",
    "name:ukr_x_preferred":[
        "Lyubomyrka"
    ],
    "name:ukr_x_variant":[
        "\u041b\u044e\u0431\u043e\u043c\u0438\u0440\u043a\u0430"
    ],
    "name:und_x_variant":[
        "Lyubomirka"
    ],
    "wof:name":"Lyubomyrka",
    "wof:placetype":"locality"
},
  "geometry": {"coordinates":[27.6735,50.03829],"type":"Point"}
}