{
  "type": "Feature",
  "properties": {
    "gn:admin1_code":"11.0",
    "gn:admin2_code":"693803",
    "gn:admin3_code":"11152586.0",
    "gn:asciiname":"Novyi Sad",
    "gn:country_code":"UA",
    "gn:dem":135,
    "gn:feature_class":"P",
    "gn:feature_code":"PPL",
    "gn:name":"Novyi Sad",
    "gn:population":386,
    "gn:timezone":"Europe/Simferopol",
    "iso:country":"UA",
    "name:eng_x_preferred":[
        "Novyi Sad"
    ],
    "name:rus_x_preferred":[
        "\u041d\u043e\u0432\u044b\u0439 \u0421\u0430\u0434"
    ],
    "name:ukr_x_preferred":[
        "\u041d\u043e\u0432\u0438\u0439 \u0421\u0430\u0434"
    ],
    "wof:name":"Novyi Sad",
    "wof:placetype":"locality",
    "wof:population":386
},
  "geometry": {"coordinates":[33.99868,45.14675],"type":"Point"}
}