{
  "type": "Feature",
  "properties": {
    "gn:admin1_code":"9.0",
    "gn:asciiname":"Knyazhpol'",
    "gn:country_code":"UA",
    "gn:dem":288,
    "gn:feature_class":"P",
    "gn:feature_code":"PPL",
    "gn:name":"Knyazhpol\u2019",
    "gn:population":0,
    "gn:timezone":"Europe/Kiev",
    "iso:country":"UA",
    "wof:name":"Knyazhpol'",
    "wof:placetype":"locality"
},
  "geometry": {"coordinates":[26.76689,48.70524],"type":"Point"}
}