{
  "type": "Feature",
  "properties": {
    "gn:admin1_code":"19.0",
    "gn:asciiname":"Pereroslya",
    "gn:country_code":"UA",
    "gn:dem":205,
    "gn:feature_class":"P",
    "gn:feature_code":"PPL",
    "gn:name":"Pereroslya",
    "gn:population":0,
    "gn:timezone":"Europe/Kiev",
    "iso:country":"UA",
    "name:ukr_x_preferred":[
        "Pereroslya"
    ],
    "name:ukr_x_variant":[
        "\u041f\u0435\u0440\u0435\u0440\u043e\u0441\u043b\u044f"
    ],
    "name:und_x_variant":[
        "Pereros\u2019le"
    ],
    "wof:name":"Pereroslya",
    "wof:placetype":"locality"
},
  "geometry": {"coordinates":[25.77696,50.30199],"type":"Point"}
}