{
  "type": "Feature",
  "properties": {
    "gn:admin1_code":"19.0",
    "gn:asciiname":"Mushni",
    "gn:country_code":"UA",
    "gn:dem":161,
    "gn:feature_class":"P",
    "gn:feature_code":"PPL",
    "gn:name":"Mushni",
    "gn:population":0,
    "gn:timezone":"Europe/Kiev",
    "iso:country":"UA",
    "name:ukr_x_preferred":[
        "Mushni"
    ],
    "name:ukr_x_variant":[
        "\u041c\u0443\u0448\u043d\u0456"
    ],
    "wof:name":"Mushni",
    "wof:placetype":"locality"
},
  "geometry": {"coordinates":[27.48529000000001,51.43812],"type":"Point"}
}