{
  "type": "Feature",
  "properties": {
    "gn:admin1_code":"18.0",
    "gn:asciiname":"Lytvynivka",
    "gn:country_code":"UA",
    "gn:dem":89,
    "gn:feature_class":"P",
    "gn:feature_code":"PPL",
    "gn:name":"Lytvynivka",
    "gn:population":0,
    "gn:timezone":"Europe/Kiev",
    "iso:country":"UA",
    "name:ukr_x_preferred":[
        "Lytvynivka"
    ],
    "name:ukr_x_variant":[
        "\u041b\u0438\u0442\u0432\u0438\u043d\u0456\u0432\u043a\u0430"
    ],
    "wof:name":"Lytvynivka",
    "wof:placetype":"locality"
},
  "geometry": {"coordinates":[34.15117,49.55832],"type":"Point"}
}