{
  "type": "Feature",
  "properties": {
    "gn:admin1_code":"24.0",
    "gn:asciiname":"Tertky",
    "gn:country_code":"UA",
    "gn:dem":188,
    "gn:feature_class":"P",
    "gn:feature_code":"PPL",
    "gn:name":"Tertky",
    "gn:population":0,
    "gn:timezone":"Europe/Kiev",
    "iso:country":"UA",
    "name:ukr_x_preferred":[
        "Tertky"
    ],
    "name:ukr_x_variant":[
        "\u0422\u0435\u0440\u0442\u043a\u0438"
    ],
    "name:und_x_variant":[
        "Ternki"
    ],
    "wof:name":"Tertky",
    "wof:placetype":"locality"
},
  "geometry": {"coordinates":[25.06667,50.68333],"type":"Point"}
}