{
  "type": "Feature",
  "properties": {
    "gn:admin1_code":"4.0",
    "gn:asciiname":"Zelenyy Hay",
    "gn:country_code":"UA",
    "gn:dem":99,
    "gn:feature_class":"P",
    "gn:feature_code":"PPL",
    "gn:name":"Zelenyy Hay",
    "gn:population":0,
    "gn:timezone":"Europe/Kiev",
    "iso:country":"UA",
    "name:rus_x_preferred":[
        "\u0417\u0435\u043b\u0451\u043d\u044b\u0439 \u0413\u0430\u0439"
    ],
    "name:ukr_x_preferred":[
        "Zelenyy Hay"
    ],
    "name:ukr_x_variant":[
        "\u0417\u0435\u043b\u0435\u043d\u0438\u0439 \u0413\u0430\u0439"
    ],
    "name:und_x_variant":[
        "Zeleny Gay",
        "Zel\u00ebnyy Gay"
    ],
    "wof:name":"Zelenyy Hay",
    "wof:placetype":"locality"
},
  "geometry": {"coordinates":[33.20149,47.88067],"type":"Point"}
}