{
  "type": "Feature",
  "properties": {
    "gn:admin1_code":"4.0",
    "gn:asciiname":"Dal'nye",
    "gn:country_code":"UA",
    "gn:dem":131,
    "gn:feature_class":"P",
    "gn:feature_code":"PPL",
    "gn:name":"Dal\u2019nye",
    "gn:population":0,
    "gn:timezone":"Europe/Kiev",
    "iso:country":"UA",
    "name:ukr_x_preferred":[
        "Dal\u2019nye"
    ],
    "name:ukr_x_variant":[
        "\u0414\u0430\u043b\u044c\u043d\u0454"
    ],
    "wof:name":"Dal'nye",
    "wof:placetype":"locality"
},
  "geometry": {"coordinates":[34.48028,48.15555],"type":"Point"}
}