{
  "type": "Feature",
  "properties": {
    "gn:admin1_code":"27.0",
    "gn:asciiname":"Dubovyy Hay",
    "gn:country_code":"UA",
    "gn:dem":198,
    "gn:feature_class":"P",
    "gn:feature_code":"PPL",
    "gn:name":"Dubovyy Hay",
    "gn:population":0,
    "gn:timezone":"Europe/Kiev",
    "iso:country":"UA",
    "name:ukr_x_preferred":[
        "Dubovyy Hay"
    ],
    "name:ukr_x_variant":[
        "\u0414\u0443\u0431\u043e\u0432\u0438\u0439 \u0413\u0430\u0439"
    ],
    "name:und_x_variant":[
        "Norbertov",
        "Khutor Norbertov"
    ],
    "wof:name":"Dubovyy Hay",
    "wof:placetype":"locality"
},
  "geometry": {"coordinates":[28.80574,51.36696],"type":"Point"}
}