{
  "type": "Feature",
  "properties": {
    "gn:admin1_code":"11.0",
    "gn:admin2_code":"703233",
    "gn:admin3_code":"11128519",
    "gn:asciiname":"Yerofeyevo",
    "gn:country_code":"UA",
    "gn:dem":53,
    "gn:feature_class":"P",
    "gn:feature_code":"PPL",
    "gn:name":"Yerofeyevo",
    "gn:population":129,
    "gn:timezone":"Europe/Simferopol",
    "iso:country":"UA",
    "name:eng_x_preferred":[
        "Yerofeyevo"
    ],
    "name:rus_x_historical":[
        "\u041c\u0438\u043d\u0430\u0440\u0435\u043b\u0438\u0301-\u0428\u0438\u0431\u0430\u0301\u043d"
    ],
    "name:rus_x_preferred":[
        "\u0415\u0440\u043e\u0444\u0435\u0435\u0432\u043e"
    ],
    "name:rus_x_variant":[
        "\u041c\u0438\u043d\u0430\u0440\u0435\u043b\u0438\u0301-\u0428\u0438\u0431\u0430\u0301\u043d"
    ],
    "name:ukr_x_preferred":[
        "\u0404\u0440\u043e\u0444\u0454\u0454\u0432\u0435"
    ],
    "wof:name":"Yerofeyevo",
    "wof:placetype":"locality",
    "wof:population":129
},
  "geometry": {"coordinates":[35.65417,45.20404],"type":"Point"}
}