{
  "type": "Feature",
  "properties": {
    "iso:country":"UA",
    "name:ces_x_preferred":[
        "Vy\u0161n\u00fd Koropec"
    ],
    "name:che_x_preferred":[
        "\u0412\u0435\u0440\u0445\u043d\u0438\u0439 \u041a\u043e\u0440\u043e\u043f\u0435\u0446"
    ],
    "name:deu_x_preferred":[
        "Werchnij Koropez"
    ],
    "name:eng_x_preferred":[
        "Verkhnii Koropets'"
    ],
    "name:epo_x_preferred":[
        "Ver\u0125nij Koropec"
    ],
    "name:est_x_preferred":[
        "Verhni Koropets"
    ],
    "name:fin_x_preferred":[
        "V\u0435rh\u2019ni K\u043er\u043ep\u0435ts"
    ],
    "name:hun_x_preferred":[
        "Fels\u0151kerepec"
    ],
    "name:hye_x_preferred":[
        "\u054e\u0565\u0580\u056d\u0576\u056b\u0575 \u053f\u0578\u0580\u0578\u057a\u0565\u0581"
    ],
    "name:nan_x_preferred":[
        "Verkhnii Koropets"
    ],
    "name:nld_x_preferred":[
        "Koropiec Werchni"
    ],
    "name:nno_x_preferred":[
        "Verkhnij Koropets"
    ],
    "name:nob_x_preferred":[
        "Verkhnij Koropets"
    ],
    "name:pol_x_preferred":[
        "Koropiec Werchni"
    ],
    "name:ron_x_preferred":[
        "Verhnii Korope\u021b"
    ],
    "name:rus_x_preferred":[
        "\u0412\u0435\u0440\u0445\u043d\u0438\u0439 \u041a\u043e\u0440\u043e\u043f\u0435\u0446"
    ],
    "name:ukr_x_preferred":[
        "Verkhniy Koropets\u2019"
    ],
    "name:ukr_x_variant":[
        "\u0412\u0435\u0440\u0445\u043d\u0456\u0439 \u041a\u043e\u0440\u043e\u043f\u0435\u0446\u044c"
    ],
    "name:und_x_variant":[
        "Felshe Kerepets"
    ],
    "name:zho_x_preferred":[
        "\u4e0a\u79d1\u7f85\u4f69\u9f4a"
    ],
    "qs:a0":"\u0423\u043a\u0440\u0430\u0457\u043d\u0430",
    "qs:a1":"*\u0417\u0430\u043a\u0430\u0440\u043f\u0430\u0442\u0441\u044c\u043a\u0430",
    "qs:a1_alt":"Zakarpats'ka",
    "qs:a1r":"0",
    "qs:a2":"\u041c\u0443\u043a\u0430\u0447\u0456\u0432\u0441\u044c\u043a\u0438\u0439",
    "qs:a2_alt":"Mukachivs'kyi",
    "qs:adm0":"\u0423\u043a\u0440\u0430\u0457\u043d\u0430",
    "qs:la_lc":"*",
    "qs:level":"locality",
    "qs:loc":"\u0412\u0435\u0440\u0445\u043d\u0456\u0439 \u041a\u043e\u0440\u043e\u043f\u0435\u0446\u044c",
    "qs:loc_alt":"Verkhnii Koropets",
    "qs:pop":0,
    "qs:type":"buffered point",
    "wd:wordcount":84,
    "wof:name":"\u0412\u0435\u0440\u0445\u043d\u0456\u0439 \u041a\u043e\u0440\u043e\u043f\u0435\u0446\u044c",
    "wof:placetype":"locality"
},
  "geometry": {"coordinates":[22.78255,48.430819],"type":"Point"}
}