{
  "type": "Feature",
  "properties": {
    "gn:admin1_code":"17.0",
    "gn:asciiname":"Hrushka",
    "gn:country_code":"UA",
    "gn:dem":202,
    "gn:feature_class":"P",
    "gn:feature_code":"PPL",
    "gn:name":"Hrushka",
    "gn:population":0,
    "gn:timezone":"Europe/Kiev",
    "iso:country":"UA",
    "name:ukr_x_preferred":[
        "Hrushka"
    ],
    "name:und_x_variant":[
        "Novo Gruska",
        "Grushka",
        "Novo-Grushka"
    ],
    "wof:name":"Hrushka",
    "wof:placetype":"locality"
},
  "geometry": {"coordinates":[29.64344,47.14492],"type":"Point"}
}