{
  "type": "Feature",
  "properties": {
    "gn:population":2000,
    "iso:country":"UA",
    "name:ceb_x_preferred":[
        "Lutovynivka"
    ],
    "name:che_x_preferred":[
        "\u041b\u0443\u0442\u043e\u0432\u0438\u043d\u043e\u0432\u043a\u0430"
    ],
    "name:eng_x_preferred":[
        "Lutovinovka"
    ],
    "name:eng_x_variant":[
        "Lutovynivka"
    ],
    "name:fin_x_preferred":[
        "Lut\u043evyn\u0456vk\u0430"
    ],
    "name:hye_x_preferred":[
        "\u053c\u0578\u0582\u057f\u0578\u057e\u056b\u0576\u0578\u057e\u056f\u0561"
    ],
    "name:nan_x_preferred":[
        "Lutovynivka"
    ],
    "name:nno_x_preferred":[
        "Lutovynivka"
    ],
    "name:nob_x_preferred":[
        "Lutovynivka"
    ],
    "name:por_x_preferred":[
        "Lutovynivka"
    ],
    "name:ron_x_preferred":[
        "Lutov\u00eenivka"
    ],
    "name:rus_x_preferred":[
        "\u041b\u0443\u0442\u043e\u0432\u0438\u043d\u043e\u0432\u043a\u0430"
    ],
    "name:ukr_x_preferred":[
        "\u041b\u0443\u0442\u043e\u0432\u0438\u043d\u0456\u0432\u043a\u0430"
    ],
    "name:ukr_x_variant":[
        "Lutovynivka"
    ],
    "name:zho_x_preferred":[
        "\u76e7\u6258\u7dad\u5c3c\u592b\u5361"
    ],
    "qs:a0":"\u0423\u043a\u0440\u0430\u0457\u043d\u0430",
    "qs:a1":"*\u041f\u043e\u043b\u0442\u0430\u0432\u0441\u044c\u043a\u0430",
    "qs:a1_alt":"Poltavs'ka",
    "qs:a1r":"0",
    "qs:a2":"\u041a\u043e\u0437\u0435\u043b\u044c\u0449\u0438\u043d\u0441\u044c\u043a\u0438\u0439",
    "qs:a2_alt":"Kozel'schyns'kyi",
    "qs:adm0":"\u0423\u043a\u0440\u0430\u0457\u043d\u0430",
    "qs:la_lc":"*",
    "qs:level":"locality",
    "qs:loc":"\u041b\u0443\u0442\u043e\u0432\u0438\u043d\u0456\u0432\u043a\u0430",
    "qs:loc_alt":"Lutovynivka",
    "qs:pop":0,
    "qs:type":"buffered point",
    "wd:wordcount":65,
    "wof:name":"\u041b\u0443\u0442\u043e\u0432\u0438\u043d\u0456\u0432\u043a\u0430",
    "wof:placetype":"locality",
    "wof:population":2000
},
  "geometry": {"coordinates":[33.902581,49.237199],"type":"Point"}
}