{
  "type": "Feature",
  "properties": {
    "gn:admin1_code":"18.0",
    "gn:asciiname":"Bukhalove",
    "gn:country_code":"UA",
    "gn:dem":157,
    "gn:feature_class":"P",
    "gn:feature_code":"PPL",
    "gn:name":"Bukhalove",
    "gn:population":0,
    "gn:timezone":"Europe/Kiev",
    "iso:country":"UA",
    "name:ukr_x_preferred":[
        "Bukhalove"
    ],
    "name:ukr_x_variant":[
        "\u0411\u0443\u0445\u0430\u043b\u043e\u0432\u0435"
    ],
    "wof:name":"Bukhalove",
    "wof:placetype":"locality"
},
  "geometry": {"coordinates":[33.90209,50.42097],"type":"Point"}
}