{
  "type": "Feature",
  "properties": {
    "gn:admin1_code":"15.0",
    "gn:asciiname":"Yosypovychi",
    "gn:country_code":"UA",
    "gn:dem":285,
    "gn:feature_class":"P",
    "gn:feature_code":"PPL",
    "gn:name":"Yosypovychi",
    "gn:population":0,
    "gn:timezone":"Europe/Kiev",
    "iso:country":"UA",
    "name:rus_x_preferred":[
        "\u0419\u043e\u0441\u0438\u043f\u043e\u0432\u0438\u0447\u0438"
    ],
    "name:ukr_x_preferred":[
        "Yosypovychi"
    ],
    "name:ukr_x_variant":[
        "\u0419\u043e\u0441\u0438\u043f\u043e\u0432\u0438\u0447\u0456"
    ],
    "name:und_x_variant":[
        "Yuseptyche",
        "Oseptyche",
        "Yosipovichi"
    ],
    "wof:name":"Yosypovychi",
    "wof:placetype":"locality"
},
  "geometry": {"coordinates":[24.02873,49.2723],"type":"Point"}
}