{
  "type": "Feature",
  "properties": {
    "gn:admin1_code":"19.0",
    "gn:asciiname":"Stolbets",
    "gn:country_code":"UA",
    "gn:dem":210,
    "gn:feature_class":"P",
    "gn:feature_code":"PPL",
    "gn:name":"Stolbets",
    "gn:population":0,
    "gn:timezone":"Europe/Kiev",
    "iso:country":"UA",
    "wof:name":"Stolbets",
    "wof:placetype":"locality"
},
  "geometry": {"coordinates":[25.61004,50.24599],"type":"Point"}
}