{
  "type": "Feature",
  "properties": {
    "iso:country":"UA",
    "qs:a0":"\u0423\u043a\u0440\u0430\u0457\u043d\u0430",
    "qs:a1":"*\u041f\u043e\u043b\u0442\u0430\u0432\u0441\u044c\u043a\u0430",
    "qs:a1_alt":"Poltavs'ka",
    "qs:a1r":"0",
    "qs:a2":"\u041f\u043e\u043b\u0442\u0430\u0432\u0441\u044c\u043a\u0438\u0439",
    "qs:a2_alt":"Poltavs'kyi",
    "qs:adm0":"\u0423\u043a\u0440\u0430\u0457\u043d\u0430",
    "qs:la_lc":"*",
    "qs:level":"locality",
    "qs:loc":"\u0412\u0435\u043b\u0438\u043a\u0438\u0439 \u0422\u0440\u043e\u0441\u0442\u044f\u043d\u0435\u0446\u044c",
    "qs:loc_alt":"Velykyi Trostianets",
    "qs:pop":0,
    "qs:type":"buffered point",
    "wof:name":"\u0412\u0435\u043b\u0438\u043a\u0438\u0439 \u0422\u0440\u043e\u0441\u0442\u044f\u043d\u0435\u0446\u044c",
    "wof:placetype":"locality"
},
  "geometry": {"coordinates":[34.540464,49.498305],"type":"Point"}
}