{
  "type": "Feature",
  "properties": {
    "gn:admin1_code":"26.0",
    "gn:asciiname":"Lozuvatka",
    "gn:country_code":"UA",
    "gn:dem":20,
    "gn:feature_class":"P",
    "gn:feature_code":"PPL",
    "gn:name":"Lozuvatka",
    "gn:population":0,
    "gn:timezone":"Europe/Zaporozhye",
    "iso:country":"UA",
    "name:ukr_x_preferred":[
        "\u041b\u043e\u0437\u0443\u0432\u0430\u0442\u043a\u0430"
    ],
    "name:und_x_variant":[
        "Lozovatka",
        "Lozuvatka",
        "Dianovka"
    ],
    "wof:name":"Lozuvatka",
    "wof:placetype":"locality"
},
  "geometry": {"coordinates":[36.17534000000001,46.78297],"type":"Point"}
}