{
  "type": "Feature",
  "properties": {
    "gn:admin1_code":"27.0",
    "gn:asciiname":"Yalyshiv",
    "gn:country_code":"UA",
    "gn:dem":220,
    "gn:feature_class":"P",
    "gn:feature_code":"PPL",
    "gn:name":"Yalyshiv",
    "gn:population":0,
    "gn:timezone":"Europe/Kiev",
    "iso:country":"UA",
    "name:ukr_x_preferred":[
        "Yalyshiv"
    ],
    "name:ukr_x_variant":[
        "\u042f\u043b\u0438\u0448\u0456\u0432"
    ],
    "name:und_x_variant":[
        "Yalyshev"
    ],
    "wof:name":"Yalyshiv",
    "wof:placetype":"locality"
},
  "geometry": {"coordinates":[27.80274,50.30132],"type":"Point"}
}