{
  "type": "Feature",
  "properties": {
    "gn:admin1_code":"22.0",
    "gn:asciiname":"Gayvoronka",
    "gn:country_code":"UA",
    "gn:dem":315,
    "gn:feature_class":"P",
    "gn:feature_code":"PPL",
    "gn:name":"Gayvoronka",
    "gn:population":0,
    "gn:timezone":"Europe/Kiev",
    "iso:country":"UA",
    "name:und_x_variant":[
        "Hayvoronka",
        "Gayvoronka"
    ],
    "wof:name":"Gayvoronka",
    "wof:placetype":"locality"
},
  "geometry": {"coordinates":[25.38134,49.25278],"type":"Point"}
}