{
  "type": "Feature",
  "properties": {
    "gn:admin1_code":"13.0",
    "gn:asciiname":"Vintsentovka",
    "gn:cc2":"UA",
    "gn:country_code":"UA",
    "gn:dem":166,
    "gn:feature_class":"P",
    "gn:feature_code":"PPL",
    "gn:name":"Vintsentovka",
    "gn:population":0,
    "gn:timezone":"Europe/Kiev",
    "iso:country":"UA",
    "name:und_x_variant":[
        "Vintsetovka",
        "Vintsentovka"
    ],
    "wof:name":"Vintsentovka",
    "wof:placetype":"locality"
},
  "geometry": {"coordinates":[30.65,49.81667],"type":"Point"}
}