{
  "type": "Feature",
  "properties": {
    "gn:admin1_code":"13.0",
    "gn:asciiname":"Khutor Grabok",
    "gn:cc2":"UA",
    "gn:country_code":"UA",
    "gn:dem":156,
    "gn:feature_class":"P",
    "gn:feature_code":"PPL",
    "gn:name":"Khutor Grabok",
    "gn:population":0,
    "gn:timezone":"Europe/Kiev",
    "iso:country":"UA",
    "name:und_x_variant":[
        "Grabok",
        "Khutor Grabok"
    ],
    "wof:name":"Khutor Grabok",
    "wof:placetype":"locality"
},
  "geometry": {"coordinates":[29.96667,50.76667],"type":"Point"}
}