{
  "type": "Feature",
  "properties": {
    "gn:admin1_code":"1.0",
    "gn:asciiname":"Pleskachivka",
    "gn:country_code":"UA",
    "gn:dem":121,
    "gn:feature_class":"P",
    "gn:feature_code":"PPL",
    "gn:name":"Pleskachivka",
    "gn:population":0,
    "gn:timezone":"Europe/Kiev",
    "iso:country":"UA",
    "name:eng_x_preferred":[
        "Pliskachevka"
    ],
    "name:rus_x_preferred":[
        "\u041f\u043b\u0435\u0441\u043a\u0430\u0447\u043e\u0432\u043a\u0430"
    ],
    "name:ukr_x_preferred":[
        "Pleskachivka"
    ],
    "name:ukr_x_variant":[
        "\u041f\u043b\u0435\u0441\u043a\u0430\u0447\u0456\u0432\u043a\u0430"
    ],
    "name:und_x_variant":[
        "Pliskachovka"
    ],
    "wof:name":"Pleskachivka",
    "wof:placetype":"locality"
},
  "geometry": {"coordinates":[32.13727,49.20811],"type":"Point"}
}