{
  "type": "Feature",
  "properties": {
    "gn:admin1_code":"10.0",
    "gn:asciiname":"Plishky",
    "gn:country_code":"UA",
    "gn:dem":210,
    "gn:feature_class":"P",
    "gn:feature_code":"PPL",
    "gn:name":"Plishky",
    "gn:population":0,
    "gn:timezone":"Europe/Kiev",
    "iso:country":"UA",
    "name:ukr_x_preferred":[
        "Plishky"
    ],
    "name:ukr_x_variant":[
        "\u041f\u043b\u0456\u0448\u043a\u0438"
    ],
    "name:und_x_variant":[
        "Pleshkovo",
        "Pleshki"
    ],
    "wof:name":"Plishky",
    "wof:placetype":"locality"
},
  "geometry": {"coordinates":[32.31489000000001,48.76801],"type":"Point"}
}