{
  "type": "Feature",
  "properties": {
    "gn:admin1_code":"4.0",
    "gn:asciiname":"Osypenko",
    "gn:country_code":"UA",
    "gn:dem":159,
    "gn:feature_class":"P",
    "gn:feature_code":"PPL",
    "gn:name":"Osypenko",
    "gn:population":0,
    "gn:timezone":"Europe/Kiev",
    "iso:country":"UA",
    "name:ukr_x_preferred":[
        "Osypenko"
    ],
    "name:ukr_x_variant":[
        "\u041e\u0441\u0438\u043f\u0435\u043d\u043a\u043e"
    ],
    "wof:name":"Osypenko",
    "wof:placetype":"locality"
},
  "geometry": {"coordinates":[34.37683,48.04127],"type":"Point"}
}