{
  "type": "Feature",
  "properties": {
    "iso:country":"UA",
    "name:eng_x_preferred":[
        "Kholmovka"
    ],
    "name:rus_x_historical":[
        "\u0417\u0430\u043b\u0430\u043d\u043a\u043e\u0301\u0439"
    ],
    "name:rus_x_preferred":[
        "\u0425\u043e\u043b\u043c\u043e\u0432\u043a\u0430"
    ],
    "name:rus_x_variant":[
        "\u0417\u0430\u043b\u0430\u043d\u043a\u043e\u0301\u0439"
    ],
    "name:ukr_x_preferred":[
        "\u0425\u043e\u043b\u043c\u0456\u0432\u043a\u0430"
    ],
    "qs:a0":"\u0423\u043a\u0440\u0430\u0457\u043d\u0430",
    "qs:a1":"*\u041a\u0440\u0438\u043c",
    "qs:a1_alt":"Krym",
    "qs:a1r":"0",
    "qs:a2":"\u0411\u0430\u0445\u0447\u0438\u0441\u0430\u0440\u0430\u0439\u0441\u044c\u043a\u0438\u0439",
    "qs:a2_alt":"Bakhchysarais'kyi",
    "qs:adm0":"\u0423\u043a\u0440\u0430\u0457\u043d\u0430",
    "qs:la_lc":"*",
    "qs:level":"locality",
    "qs:loc":"\u0425\u043e\u043b\u043c\u0456\u0432\u043a\u0430",
    "qs:loc_alt":"Kholmivka",
    "qs:pop":0,
    "qs:type":"buffered point",
    "wof:name":"\u0425\u043e\u043b\u043c\u0456\u0432\u043a\u0430",
    "wof:placetype":"locality"
},
  "geometry": {"coordinates":[33.758279,44.659515],"type":"Point"}
}