{
  "type": "Feature",
  "properties": {
    "iso:country":"UA",
    "name:ukr_x_preferred":[
        "Pushkino"
    ],
    "name:ukr_x_variant":[
        "\u041f\u0443\u0448\u043a\u0456\u043d\u043e"
    ],
    "qs:a0":"\u0423\u043a\u0440\u0430\u0457\u043d\u0430",
    "qs:a1":"*\u0417\u0430\u043a\u0430\u0440\u043f\u0430\u0442\u0441\u044c\u043a\u0430",
    "qs:a1_alt":"Zakarpats'ka",
    "qs:a1r":"0",
    "qs:a2":"\u0412\u0438\u043d\u043e\u0433\u0440\u0430\u0434\u0456\u0432\u0441\u044c\u043a\u0438\u0439",
    "qs:a2_alt":"Vynohradivs'kyi",
    "qs:adm0":"\u0423\u043a\u0440\u0430\u0457\u043d\u0430",
    "qs:la_lc":"*",
    "qs:level":"locality",
    "qs:loc":"\u041f\u0443\u0448\u043a\u0456\u043d\u043e",
    "qs:loc_alt":"Pushkino",
    "qs:pop":0,
    "qs:type":"buffered point",
    "wof:name":"\u041f\u0443\u0448\u043a\u0456\u043d\u043e",
    "wof:placetype":"locality"
},
  "geometry": {"coordinates":[22.866652,48.176017],"type":"Point"}
}