{
  "type": "Feature",
  "properties": {
    "gn:admin1_code":"25.0",
    "gn:asciiname":"Ploskanovytsya",
    "gn:country_code":"UA",
    "gn:dem":461,
    "gn:feature_class":"P",
    "gn:feature_code":"PPL",
    "gn:name":"Ploskanovytsya",
    "gn:population":0,
    "gn:timezone":"Europe/Uzhgorod",
    "iso:country":"UA",
    "name:ukr_x_preferred":[
        "Ploskanovytsya"
    ],
    "name:ukr_x_variant":[
        "\u041f\u043b\u043e\u0441\u043a\u0430\u043d\u043e\u0432\u0438\u0446\u044f"
    ],
    "name:und_x_variant":[
        "Ploskanovitsa"
    ],
    "wof:name":"Ploskanovytsya",
    "wof:placetype":"locality"
},
  "geometry": {"coordinates":[22.8944,48.48383],"type":"Point"}
}