{
  "type": "Feature",
  "properties": {
    "gn:gn_country":"UA",
    "gn:gn_fcode":"PPL",
    "gn:gn_pop":2259,
    "gn:population":2259,
    "iso:country":"UA",
    "name:ceb_x_preferred":[
        "Klenovyy"
    ],
    "name:crh_x_preferred":[
        "Klenov\u0131y"
    ],
    "name:deu_x_preferred":[
        "Klenowyj"
    ],
    "name:eng_x_preferred":[
        "Klenovyi"
    ],
    "name:lav_x_preferred":[
        "Klenova"
    ],
    "name:ron_x_preferred":[
        "Klenov\u00eei"
    ],
    "name:rus_x_preferred":[
        "\u041a\u043b\u0435\u043d\u043e\u0432\u0438\u0439"
    ],
    "name:rus_x_variant":[
        "\u041a\u043b\u0435\u043d\u043e\u0432\u044b\u0439"
    ],
    "name:ukr_x_preferred":[
        "\u041a\u043b\u0435\u043d\u043e\u0432\u0438\u0439"
    ],
    "name:zho_x_preferred":[
        "\u514b\u5217\u8afe\u7dad"
    ],
    "qs_pg:aaroncc":"UA",
    "qs_pg:gn_country":"UA",
    "qs_pg:gn_fcode":"PPL",
    "qs_pg:gn_pop":2259,
    "qs_pg:name":"Klenovyy",
    "qs_pg:name_adm0":"Ukraine",
    "qs_pg:name_adm1":"Luhans\u00b4ka Oblast\u00b4",
    "qs_pg:photos_9r":0,
    "qs_pg:photos_sr":0,
    "qs_pg:pop_sr":4,
    "qs_pg:qs_pg_placetype":"locality",
    "qs_pg:qs_pg_placetype_gp":"Town",
    "qs_pg:woe_adm0":23424976,
    "woe:adm0_id":23424976,
    "woe:name_adm0":"Ukraine",
    "woe:name_adm1":"Luhans\u00b4ka Oblast\u00b4",
    "woe:placetype":"Town",
    "wof:name":"Klenovyy",
    "wof:placetype":"locality",
    "wof:population":2259
},
  "geometry": {"coordinates":[39.4588,48.11934],"type":"Point"}
}