{
  "type": "Feature",
  "properties": {
    "gn:admin1_code":"15.0",
    "gn:asciiname":"Poverhiv",
    "gn:country_code":"UA",
    "gn:dem":258,
    "gn:feature_class":"P",
    "gn:feature_code":"PPL",
    "gn:name":"Poverhiv",
    "gn:population":0,
    "gn:timezone":"Europe/Kiev",
    "iso:country":"UA",
    "name:rus_x_preferred":[
        "\u041f\u043e\u0432\u0435\u0440\u0433\u043e\u0432"
    ],
    "name:ukr_x_preferred":[
        "Poverhiv"
    ],
    "name:ukr_x_variant":[
        "\u041f\u043e\u0432\u0435\u0440\u0433\u0456\u0432"
    ],
    "name:und_x_variant":[
        "Poverkhuv",
        "Povergov"
    ],
    "wof:name":"Poverhiv",
    "wof:placetype":"locality"
},
  "geometry": {"coordinates":[23.76457000000001,49.52168],"type":"Point"}
}