{
  "type": "Feature",
  "properties": {
    "gn:admin1_code":"26.0",
    "gn:asciiname":"Rozivka",
    "gn:country_code":"UA",
    "gn:dem":23,
    "gn:feature_class":"P",
    "gn:feature_code":"PPL",
    "gn:name":"Rozivka",
    "gn:population":0,
    "gn:timezone":"Europe/Zaporozhye",
    "iso:country":"UA",
    "name:rus_x_preferred":[
        "\u0420\u043e\u0437\u043e\u0432\u043a\u0430"
    ],
    "name:ukr_x_preferred":[
        "\u0420\u043e\u0437\u0456\u0432\u043a\u0430"
    ],
    "name:und_x_variant":[
        "Venera",
        "Rozivka",
        "Rozovka"
    ],
    "wof:name":"Rozivka",
    "wof:placetype":"locality"
},
  "geometry": {"coordinates":[34.95997,46.50714],"type":"Point"}
}