{
  "type": "Feature",
  "properties": {
    "gn:admin1_code":"18.0",
    "gn:asciiname":"Znamovka",
    "gn:cc2":"UA",
    "gn:country_code":"UA",
    "gn:dem":126,
    "gn:feature_class":"P",
    "gn:feature_code":"PPL",
    "gn:name":"Znamovka",
    "gn:population":0,
    "gn:timezone":"Europe/Kiev",
    "iso:country":"UA",
    "name:und_x_variant":[
        "Znamenka",
        "Znamovka"
    ],
    "wof:name":"Znamovka",
    "wof:placetype":"locality"
},
  "geometry": {"coordinates":[34.15,49.45],"type":"Point"}
}