{
  "type": "Feature",
  "properties": {
    "gn:admin1_code":"27.0",
    "gn:asciiname":"Cherepynky",
    "gn:country_code":"UA",
    "gn:dem":180,
    "gn:feature_class":"P",
    "gn:feature_code":"PPL",
    "gn:name":"Cherepynky",
    "gn:population":0,
    "gn:timezone":"Europe/Kiev",
    "iso:country":"UA",
    "name:ukr_x_preferred":[
        "Cherepynky"
    ],
    "name:ukr_x_variant":[
        "\u0427\u0435\u0440\u0435\u043f\u0438\u043d\u043a\u0438"
    ],
    "name:und_x_variant":[
        "Cherepinki"
    ],
    "wof:name":"Cherepynky",
    "wof:placetype":"locality"
},
  "geometry": {"coordinates":[28.70253,51.32093],"type":"Point"}
}