{
  "type": "Feature",
  "properties": {
    "gn:admin1_code":"7.0",
    "gn:asciiname":"Proletars'ke",
    "gn:country_code":"UA",
    "gn:dem":91,
    "gn:feature_class":"P",
    "gn:feature_code":"PPL",
    "gn:name":"Proletars\u2019ke",
    "gn:population":0,
    "gn:timezone":"Europe/Kiev",
    "iso:country":"UA",
    "name:ukr_x_preferred":[
        "Proletars\u2019ke"
    ],
    "name:ukr_x_variant":[
        "\u041f\u0440\u043e\u043b\u0435\u0442\u0430\u0440\u0441\u044c\u043a\u0435"
    ],
    "name:und_x_variant":[
        "Proletarskoye"
    ],
    "wof:name":"Proletars'ke",
    "wof:placetype":"locality"
},
  "geometry": {"coordinates":[36.29376,49.69538],"type":"Point"}
}