{
  "type": "Feature",
  "properties": {
    "gn:admin1_code":"5.0",
    "gn:asciiname":"Starodubivka",
    "gn:country_code":"UA",
    "gn:dem":60,
    "gn:feature_class":"P",
    "gn:feature_code":"PPL",
    "gn:name":"Starodubivka",
    "gn:population":0,
    "gn:timezone":"Europe/Kiev",
    "iso:country":"UA",
    "name:eng_x_preferred":[
        "Starodubovka"
    ],
    "name:rus_x_preferred":[
        "\u0421\u0442\u0430\u0440\u043e\u0434\u0443\u0431\u043e\u0432\u043a\u0430"
    ],
    "name:ukr_x_preferred":[
        "Starodubivka"
    ],
    "name:ukr_x_variant":[
        "\u0421\u0442\u0430\u0440\u043e\u0434\u0443\u0431\u0456\u0432\u043a\u0430"
    ],
    "wof:name":"Starodubivka",
    "wof:placetype":"locality"
},
  "geometry": {"coordinates":[37.03855,47.10422],"type":"Point"}
}