{
  "type": "Feature",
  "properties": {
    "gn:admin1_code":"4.0",
    "gn:asciiname":"Hannivka",
    "gn:country_code":"UA",
    "gn:dem":89,
    "gn:feature_class":"P",
    "gn:feature_code":"PPL",
    "gn:name":"Hannivka",
    "gn:population":0,
    "gn:timezone":"Europe/Kiev",
    "iso:country":"UA",
    "name:rus_x_preferred":[
        "\u0410\u043d\u043d\u043e\u0432\u043a\u0430"
    ],
    "name:ukr_x_preferred":[
        "Hannivka"
    ],
    "name:ukr_x_variant":[
        "\u0413\u0430\u043d\u043d\u0456\u0432\u043a\u0430"
    ],
    "name:und_x_variant":[
        "Anninka",
        "Anninskaya",
        "Annovka"
    ],
    "wof:name":"Hannivka",
    "wof:placetype":"locality"
},
  "geometry": {"coordinates":[35.66591,48.97135],"type":"Point"}
}