{
  "type": "Feature",
  "properties": {
    "gn:admin1_code":"27.0",
    "gn:admin2_code":"702091",
    "gn:asciiname":"Hamarnya",
    "gn:country_code":"UA",
    "gn:dem":139,
    "gn:feature_class":"P",
    "gn:feature_code":"PPL",
    "gn:name":"Hamarnya",
    "gn:population":0,
    "gn:timezone":"Europe/Kiev",
    "iso:country":"UA",
    "name:ukr_x_preferred":[
        "Hamarnya"
    ],
    "name:ukr_x_variant":[
        "\u0413\u0430\u043c\u0430\u0440\u043d\u044f"
    ],
    "name:und_x_variant":[
        "Gamarnya"
    ],
    "wof:name":"Hamarnya",
    "wof:placetype":"locality"
},
  "geometry": {"coordinates":[29.17324,50.77585],"type":"Point"}
}