{
  "type": "Feature",
  "properties": {
    "gn:admin1_code":"16.0",
    "gn:asciiname":"Mykhailivka",
    "gn:country_code":"UA",
    "gn:dem":110,
    "gn:feature_class":"P",
    "gn:feature_code":"PPL",
    "gn:name":"Mykhailivka",
    "gn:population":0,
    "gn:timezone":"Europe/Kiev",
    "iso:country":"UA",
    "name:aze_x_preferred":[
        "Mixaylovka"
    ],
    "name:bel_x_preferred":[
        "\u041c\u0456\u0445\u0430\u0439\u043b\u0430\u045e\u043a\u0430"
    ],
    "name:ceb_x_preferred":[
        "Mykhaylivka"
    ],
    "name:ces_x_preferred":[
        "Mychajlivka"
    ],
    "name:deu_x_preferred":[
        "Mychajliwka"
    ],
    "name:hun_x_preferred":[
        "Mihajlovka"
    ],
    "name:ita_x_preferred":[
        "Michajlovka"
    ],
    "name:jpn_x_preferred":[
        "\u30e0\u30a3\u30cf\u30fc\u30a4\u30ea\u30a6\u30ab"
    ],
    "name:kat_x_preferred":[
        "\u10db\u10d8\u10ee\u10d0\u10d8\u10da\u10dd\u10d5\u10d9\u10d0"
    ],
    "name:kaz_x_preferred":[
        "\u041c\u0438\u0445\u0430\u0439\u043b\u043e\u0432\u043a\u0430"
    ],
    "name:myv_x_preferred":[
        "\u041c\u0438\u0445\u0430\u0439\u043b\u043e\u0432\u043a\u0430"
    ],
    "name:pol_x_preferred":[
        "Mychajliwka"
    ],
    "name:rus_x_preferred":[
        "\u041c\u0438\u0445\u0430\u0439\u043b\u043e\u0432\u043a\u0430"
    ],
    "name:tat_x_preferred":[
        "\u041c\u0438\u0445\u0430\u0439\u043b\u043e\u0432\u043a\u0430"
    ],
    "name:ukr_x_preferred":[
        "Mykhailivka"
    ],
    "name:ukr_x_variant":[
        "\u041c\u0438\u0445\u0430\u0439\u043b\u0456\u0432\u043a\u0430"
    ],
    "name:und_x_variant":[
        "Mikhaylovka"
    ],
    "name:vep_x_preferred":[
        "Mihailovk"
    ],
    "wof:name":"Mykhailivka",
    "wof:placetype":"locality"
},
  "geometry": {"coordinates":[33.00714,47.85875],"type":"Point"}
}