{
  "type": "Feature",
  "properties": {
    "gn:admin1_code":"11.0",
    "gn:admin2_code":"709333",
    "gn:admin3_code":"11152867.0",
    "gn:asciiname":"Koloski",
    "gn:country_code":"UA",
    "gn:dem":12,
    "gn:elevation":"13.0",
    "gn:feature_class":"P",
    "gn:feature_code":"PPL",
    "gn:name":"Koloski",
    "gn:population":327,
    "gn:timezone":"Europe/Simferopol",
    "iso:country":"UA",
    "name:eng_x_preferred":[
        "Koloski"
    ],
    "name:rus_x_historical":[
        "\u0428\u043e\u043b\u043e\u0301\u043c-\u0410\u043b\u0435\u0301\u0439\u0445\u0435\u043c"
    ],
    "name:rus_x_preferred":[
        "\u041a\u043e\u043b\u043e\u0441\u043a\u0438"
    ],
    "name:rus_x_variant":[
        "\u0428\u043e\u043b\u043e\u0301\u043c-\u0410\u043b\u0435\u0301\u0439\u0445\u0435\u043c"
    ],
    "name:ukr_x_preferred":[
        "\u041a\u043e\u043b\u043e\u0441\u043a\u0438"
    ],
    "wof:name":"Koloski",
    "wof:placetype":"locality",
    "wof:population":327
},
  "geometry": {"coordinates":[34.23294,45.87737],"type":"Point"}
}