{
  "type": "Feature",
  "properties": {
    "gn:admin1_code":"9.0",
    "gn:asciiname":"Ksaverovka",
    "gn:country_code":"UA",
    "gn:dem":307,
    "gn:feature_class":"P",
    "gn:feature_code":"PPL",
    "gn:name":"Ksaverovka",
    "gn:population":0,
    "gn:timezone":"Europe/Kiev",
    "iso:country":"UA",
    "wof:name":"Ksaverovka",
    "wof:placetype":"locality"
},
  "geometry": {"coordinates":[26.84448,48.75782],"type":"Point"}
}