{
  "type": "Feature",
  "properties": {
    "gn:admin1_code":"2.0",
    "gn:asciiname":"Krasnosil's'ke",
    "gn:country_code":"UA",
    "gn:dem":127,
    "gn:feature_class":"P",
    "gn:feature_code":"PPL",
    "gn:name":"Krasnosil\u2019s\u2019ke",
    "gn:population":0,
    "gn:timezone":"Europe/Kiev",
    "iso:country":"UA",
    "name:ukr_x_preferred":[
        "Krasnosil\u2019s\u2019ke"
    ],
    "name:ukr_x_variant":[
        "\u041a\u0440\u0430\u0441\u043d\u043e\u0441\u0456\u043b\u044c\u0441\u044c\u043a\u0435"
    ],
    "name:und_x_variant":[
        "Krasnosel\u2019skoye",
        "Yevlashevka",
        "Yevlashovka"
    ],
    "wof:name":"Krasnosil's'ke",
    "wof:placetype":"locality"
},
  "geometry": {"coordinates":[32.11137,51.20166],"type":"Point"}
}