{
  "type": "Feature",
  "properties": {
    "gn:admin1_code":"9.0",
    "gn:asciiname":"Topory",
    "gn:country_code":"UA",
    "gn:dem":263,
    "gn:feature_class":"P",
    "gn:feature_code":"PPL",
    "gn:name":"Topory",
    "gn:population":0,
    "gn:timezone":"Europe/Kiev",
    "iso:country":"UA",
    "name:ukr_x_preferred":[
        "Topory"
    ],
    "name:ukr_x_variant":[
        "\u0422\u043e\u043f\u043e\u0440\u0438"
    ],
    "wof:name":"Topory",
    "wof:placetype":"locality"
},
  "geometry": {"coordinates":[26.85829,50.03672],"type":"Point"}
}