{
  "type": "Feature",
  "properties": {
    "gn:admin1_code":"16.0",
    "gn:asciiname":"Zelenyy Gay",
    "gn:country_code":"UA",
    "gn:dem":51,
    "gn:feature_class":"P",
    "gn:feature_code":"PPL",
    "gn:name":"Zel\u00ebnyy Gay",
    "gn:population":0,
    "gn:timezone":"Europe/Kiev",
    "iso:country":"UA",
    "wof:name":"Zelenyy Gay",
    "wof:placetype":"locality"
},
  "geometry": {"coordinates":[30.98609,47.74537],"type":"Point"}
}