{
  "type": "Feature",
  "properties": {
    "gn:admin1_code":"24.0",
    "gn:asciiname":"Vilytsya",
    "gn:country_code":"UA",
    "gn:dem":162,
    "gn:feature_class":"P",
    "gn:feature_code":"PPL",
    "gn:name":"Vilytsya",
    "gn:population":0,
    "gn:timezone":"Europe/Kiev",
    "iso:country":"UA",
    "name:ukr_x_preferred":[
        "Vilytsya"
    ],
    "name:ukr_x_variant":[
        "\u0412\u0456\u043b\u0438\u0446\u044f"
    ],
    "name:und_x_variant":[
        "Wilica",
        "Vilitsa",
        "Volitsa"
    ],
    "wof:name":"Vilytsya",
    "wof:placetype":"locality"
},
  "geometry": {"coordinates":[24.0547,51.49191],"type":"Point"}
}