{
  "type": "Feature",
  "properties": {
    "gn:admin1_code":"27.0",
    "gn:asciiname":"Volyanshchyna",
    "gn:country_code":"UA",
    "gn:dem":192,
    "gn:feature_class":"P",
    "gn:feature_code":"PPL",
    "gn:name":"Volyanshchyna",
    "gn:population":0,
    "gn:timezone":"Europe/Kiev",
    "iso:country":"UA",
    "name:ukr_x_preferred":[
        "Volyanshchyna"
    ],
    "name:ukr_x_variant":[
        "\u0412\u043e\u043b\u044f\u043d\u0449\u0438\u043d\u0430"
    ],
    "name:und_x_variant":[
        "Valyanshchina",
        "Volyanshchina"
    ],
    "wof:name":"Volyanshchyna",
    "wof:placetype":"locality"
},
  "geometry": {"coordinates":[28.47725,50.6281],"type":"Point"}
}