{
  "type": "Feature",
  "properties": {
    "gn:admin1_code":"27.0",
    "gn:asciiname":"Gat",
    "gn:country_code":"UA",
    "gn:dem":221,
    "gn:feature_class":"P",
    "gn:feature_code":"PPL",
    "gn:name":"Gat",
    "gn:population":0,
    "gn:timezone":"Europe/Kiev",
    "iso:country":"UA",
    "name:und_x_variant":[
        "Khutor Gat\u2019"
    ],
    "wof:name":"Gat",
    "wof:placetype":"locality"
},
  "geometry": {"coordinates":[28.46667,51.38333],"type":"Point"}
}