{
  "type": "Feature",
  "properties": {
    "iso:country":"UA",
    "name:ara_x_preferred":[
        "\u0623\u0644\u0645\u0627\u0632\u0646\u0627"
    ],
    "name:ces_x_preferred":[
        "Almazna"
    ],
    "name:crh_x_preferred":[
        "Almazna"
    ],
    "name:deu_x_preferred":[
        "Almasna"
    ],
    "name:eng_x_preferred":[
        "Almazna"
    ],
    "name:fas_x_preferred":[
        "\u0622\u0644\u0645\u0627\u0632\u0646\u0627"
    ],
    "name:fra_x_preferred":[
        "Almazna"
    ],
    "name:hsb_x_preferred":[
        "Almazna"
    ],
    "name:hye_x_preferred":[
        "\u0531\u056c\u0574\u0561\u0566\u0576\u0561\u0575\u0561"
    ],
    "name:ita_x_preferred":[
        "Almazna"
    ],
    "name:kat_x_preferred":[
        "\u10d0\u10da\u10db\u10d0\u10d6\u10dc\u10d0\u10d8\u10d0"
    ],
    "name:lav_x_preferred":[
        "Almazna"
    ],
    "name:lit_x_preferred":[
        "Almazna"
    ],
    "name:mhr_x_preferred":[
        "\u0410\u043b\u043c\u0430\u0437\u043d\u044b\u0439"
    ],
    "name:nld_x_preferred":[
        "Almazna"
    ],
    "name:nno_x_preferred":[
        "Almazna"
    ],
    "name:nob_x_preferred":[
        "Almazna"
    ],
    "name:nor_x_preferred":[
        "Almazna"
    ],
    "name:pol_x_preferred":[
        "A\u0142mazna"
    ],
    "name:ron_x_preferred":[
        "Almazna"
    ],
    "name:rus_x_preferred":[
        "\u0410\u043b\u043c\u0430\u0437\u043d\u0430\u044f"
    ],
    "name:spa_x_preferred":[
        "Almazna"
    ],
    "name:tat_x_preferred":[
        "\u0410\u043b\u043c\u0430\u0437\u043d\u0430"
    ],
    "name:udm_x_preferred":[
        "\u0410\u043b\u043c\u0430\u0437\u043d\u0430\u044f"
    ],
    "name:ukr_x_preferred":[
        "\u0410\u043b\u043c\u0430\u0437\u043d\u0430"
    ],
    "name:ukr_x_variant":[
        "Almazna"
    ],
    "name:unk_x_variant":[
        "Almaznoye"
    ],
    "name:vie_x_preferred":[
        "Almazna"
    ],
    "name:zho_x_preferred":[
        "\u963f\u723e\u7c73\u8332\u7d0d"
    ],
    "qs:a0":"\u0423\u043a\u0440\u0430\u0457\u043d\u0430",
    "qs:a1":"*\u041b\u0443\u0433\u0430\u043d\u0441\u044c\u043a\u0430",
    "qs:a1_alt":"Luhans'ka",
    "qs:a1r":"0",
    "qs:a2":"\u0421\u043b\u043e\u0432'\u044f\u043d\u043e\u0441\u0435\u0440\u0431\u0441\u044c\u043a\u0438\u0439",
    "qs:a2_alt":"Slovyanoserbs'kyi",
    "qs:adm0":"\u0423\u043a\u0440\u0430\u0457\u043d\u0430",
    "qs:la_lc":"*",
    "qs:level":"locality",
    "qs:loc":"\u0410\u043b\u043c\u0430\u0437\u043d\u0430",
    "qs:loc_alt":"Almazna",
    "qs:pop":0,
    "qs:type":"buffered point",
    "wd:wordcount":100,
    "wof:name":"\u0410\u043b\u043c\u0430\u0437\u043d\u0430",
    "wof:placetype":"locality"
},
  "geometry": {"coordinates":[38.589145,48.518369],"type":"Point"}
}