{
  "type": "Feature",
  "properties": {
    "gn:admin1_code":"5.0",
    "gn:asciiname":"Novodvirs'ke",
    "gn:country_code":"UA",
    "gn:dem":188,
    "gn:feature_class":"P",
    "gn:feature_code":"PPL",
    "gn:name":"Novodvirs\u2019ke",
    "gn:population":0,
    "gn:timezone":"Europe/Kiev",
    "iso:country":"UA",
    "name:ukr_x_preferred":[
        "Novodvirs\u2019ke"
    ],
    "name:ukr_x_variant":[
        "\u041d\u043e\u0432\u043e\u0434\u0432\u0456\u0440\u0441\u044c\u043a\u0435"
    ],
    "name:und_x_variant":[
        "Novostroy"
    ],
    "wof:name":"Novodvirs'ke",
    "wof:placetype":"locality"
},
  "geometry": {"coordinates":[38.14629,47.84302],"type":"Point"}
}