{
  "type": "Feature",
  "properties": {
    "gn:admin1_code":"9.0",
    "gn:asciiname":"Verkhnyaky",
    "gn:country_code":"UA",
    "gn:dem":314,
    "gn:feature_class":"P",
    "gn:feature_code":"PPL",
    "gn:name":"Verkhnyaky",
    "gn:population":0,
    "gn:timezone":"Europe/Kiev",
    "iso:country":"UA",
    "name:ukr_x_preferred":[
        "Verkhnyaky"
    ],
    "name:ukr_x_variant":[
        "\u0412\u0435\u0440\u0445\u043d\u044f\u043a\u0438"
    ],
    "name:und_x_variant":[
        "Verkhnyaki"
    ],
    "wof:name":"Verkhnyaky",
    "wof:placetype":"locality"
},
  "geometry": {"coordinates":[27.1568,49.66628],"type":"Point"}
}