{
  "type": "Feature",
  "properties": {
    "iso:country":"UA",
    "name:crh_x_historical":[
        "Toqul\u010daq"
    ],
    "name:crh_x_preferred":[
        "Toqul\u010daq"
    ],
    "name:eng_x_preferred":[
        "Grishino"
    ],
    "name:eng_x_variant":[
        "Tokul'chak"
    ],
    "name:rus_x_historical":[
        "\u0422\u043e\u043a\u0443\u043b\u0447\u0430\u0301\u043a"
    ],
    "name:rus_x_preferred":[
        "\u0422\u043e\u043a\u0443\u043b\u0447\u0430\u0301\u043a"
    ],
    "name:rus_x_variant":[
        "\u0413\u0440\u0438\u0448\u0438\u043d\u043e"
    ],
    "name:ukr_x_preferred":[
        "\u0413\u0440\u0438\u0448\u0438\u043d\u0435"
    ],
    "qs:a0":"\u0423\u043a\u0440\u0430\u0457\u043d\u0430",
    "qs:a1":"*\u041a\u0440\u0438\u043c",
    "qs:a1_alt":"Krym",
    "qs:a1r":"0",
    "qs:a2":"\u041f\u0435\u0440\u0432\u043e\u043c\u0430\u0439\u0441\u044c\u043a\u0438\u0439",
    "qs:a2_alt":"Pervomais'kyi",
    "qs:adm0":"\u0423\u043a\u0440\u0430\u0457\u043d\u0430",
    "qs:la_lc":"*",
    "qs:level":"locality",
    "qs:loc":"\u0413\u0440\u0438\u0448\u0438\u043d\u0435",
    "qs:loc_alt":"Hryshyne",
    "qs:pop":0,
    "qs:type":"buffered point",
    "wof:lang":[
        "eng"
    ],
    "wof:name":"\u0413\u0440\u0438\u0448\u0438\u043d\u0435",
    "wof:placetype":"locality"
},
  "geometry": {"coordinates":[33.836484,45.646142],"type":"Point"}
}