{
  "type": "Feature",
  "properties": {
    "gn:country":"UA",
    "gn:fcode":"PPL",
    "gn:population":1142,
    "iso:country":"UA",
    "name:eng_x_preferred":[
        "Belogorovka"
    ],
    "name:rus_x_preferred":[
        "\u0411\u0435\u043b\u043e\u0433\u043e\u0440\u043e\u0432\u043a\u0430"
    ],
    "name:ukr_x_preferred":[
        "Bilohorivka"
    ],
    "name:ukr_x_variant":[
        "\u0411\u0456\u043b\u043e\u0433\u043e\u0440\u0456\u0432\u043a\u0430"
    ],
    "qs_pg:aaroncc":"UA",
    "qs_pg:gn_country":"UA",
    "qs_pg:gn_fcode":"PPL",
    "qs_pg:gn_pop":1142,
    "qs_pg:name":"Belogorovka",
    "qs_pg:photos_9r":0,
    "qs_pg:photos_sr":0,
    "qs_pg:pop_sr":3,
    "qs_pg:qs_pg_placetype":"locality",
    "wof:name":"Belogorovka",
    "wof:placetype":"locality",
    "wof:population":1142
},
  "geometry": {"coordinates":[38.24822,48.92503],"type":"Point"}
}