{
  "type": "Feature",
  "properties": {
    "gn:population":5797,
    "iso:country":"UA",
    "name:bul_x_preferred":[
        "\u041d\u0438\u0436\u043d\u0438 \u0421\u0438\u0440\u0433\u043e\u0437\u0438"
    ],
    "name:ceb_x_preferred":[
        "Nyzhni Sirohozy"
    ],
    "name:crh_x_preferred":[
        "N\u0131jni Sirogoz\u0131"
    ],
    "name:deu_x_preferred":[
        "Nyschni Sirohosy"
    ],
    "name:eng_x_preferred":[
        "Nyzhni Sirohozy"
    ],
    "name:lav_x_preferred":[
        "Ni\u017e\u0146i Sirohozi"
    ],
    "name:pol_x_preferred":[
        "Ny\u017cni Sirohozy"
    ],
    "name:ron_x_preferred":[
        "N\u00eejni Sirohoz\u00ee"
    ],
    "name:rus_x_preferred":[
        "\u041d\u0438\u0436\u043d\u0456 \u0421\u0456\u0440\u043e\u0433\u043e\u0437\u0438"
    ],
    "name:rus_x_variant":[
        "\u041d\u0438\u0436\u043d\u0438\u0435 \u0421\u0435\u0440\u043e\u0433\u043e\u0437\u044b"
    ],
    "name:ukr_x_preferred":[
        "\u041d\u0438\u0436\u043d\u0456 \u0421\u0456\u0440\u043e\u0433\u043e\u0437\u0438"
    ],
    "name:unk_x_variant":[
        "Nizhniye Serogozy"
    ],
    "name:zho_x_preferred":[
        "\u4e0b\u897f\u7f85\u6208\u6fdf"
    ],
    "qs:a0":"\u0423\u043a\u0440\u0430\u0457\u043d\u0430",
    "qs:a1":"*\u0425\u0435\u0440\u0441\u043e\u043d\u0441\u044c\u043a\u0430",
    "qs:a1_alt":"Khersons'ka",
    "qs:a1r":"0",
    "qs:a2":"\u041d\u0438\u0436\u043d\u044c\u043e\u0441\u0456\u0440\u043e\u0433\u043e\u0437\u044c\u043a\u0438\u0439",
    "qs:a2_alt":"Nyzhn'osirohoz'kyi",
    "qs:adm0":"\u0423\u043a\u0440\u0430\u0457\u043d\u0430",
    "qs:la_lc":"*",
    "qs:level":"locality",
    "qs:loc":"\u041d\u0438\u0436\u043d\u0456 \u0421\u0456\u0440\u043e\u0433\u043e\u0437\u0438",
    "qs:loc_alt":"Nyzhni Sirohozy",
    "qs:pop":0,
    "qs:type":"buffered point",
    "wof:name":"\u041d\u0438\u0436\u043d\u0456 \u0421\u0456\u0440\u043e\u0433\u043e\u0437\u0438",
    "wof:placetype":"locality",
    "wof:population":5797
},
  "geometry": {"coordinates":[34.386241,46.841266],"type":"Point"}
}