{
  "type": "Feature",
  "properties": {
    "gn:admin1_code":"17.0",
    "gn:asciiname":"Kalistrativka",
    "gn:country_code":"UA",
    "gn:dem":229,
    "gn:feature_class":"P",
    "gn:feature_code":"PPL",
    "gn:name":"Kalistrativka",
    "gn:population":0,
    "gn:timezone":"Europe/Kiev",
    "iso:country":"UA",
    "name:ukr_x_preferred":[
        "Kalistrativka"
    ],
    "name:ukr_x_variant":[
        "\u041a\u0430\u043b\u0456\u0441\u0442\u0440\u0430\u0442\u0456\u0432\u043a\u0430"
    ],
    "name:und_x_variant":[
        "Kalistratovka"
    ],
    "wof:name":"Kalistrativka",
    "wof:placetype":"locality"
},
  "geometry": {"coordinates":[29.6179,47.61637],"type":"Point"}
}