{
  "type": "Feature",
  "properties": {
    "gn:admin1_code":"27.0",
    "gn:asciiname":"Puhachivka",
    "gn:country_code":"UA",
    "gn:dem":191,
    "gn:feature_class":"P",
    "gn:feature_code":"PPL",
    "gn:name":"Puhachivka",
    "gn:population":0,
    "gn:timezone":"Europe/Kiev",
    "iso:country":"UA",
    "name:rus_x_preferred":[
        "Pugach\u00ebvka"
    ],
    "name:ukr_x_preferred":[
        "Puhachivka"
    ],
    "name:ukr_x_variant":[
        "\u041f\u0443\u0433\u0430\u0447\u0456\u0432\u043a\u0430"
    ],
    "wof:name":"Puhachivka",
    "wof:placetype":"locality"
},
  "geometry": {"coordinates":[28.39242,50.8659],"type":"Point"}
}