{
  "type": "Feature",
  "properties": {
    "gn:admin1_code":"4.0",
    "gn:asciiname":"Yagodnaya Pervaya",
    "gn:country_code":"UA",
    "gn:dem":129,
    "gn:feature_class":"P",
    "gn:feature_code":"PPL",
    "gn:name":"Yagodnaya Pervaya",
    "gn:population":0,
    "gn:timezone":"Europe/Kiev",
    "iso:country":"UA",
    "name:ukr_x_preferred":[
        "Yahidne"
    ],
    "wof:name":"Yagodnaya Pervaya",
    "wof:placetype":"locality"
},
  "geometry": {"coordinates":[36.36513,47.99538],"type":"Point"}
}