{
  "type": "Feature",
  "properties": {
    "gn:admin1_code":"5.0",
    "gn:asciiname":"Blyumental' Nomer Devyatnadtsatyy",
    "gn:country_code":"UA",
    "gn:dem":126,
    "gn:feature_class":"P",
    "gn:feature_code":"PPL",
    "gn:name":"Blyumental\u2019 Nomer Devyatnadtsatyy",
    "gn:population":0,
    "gn:timezone":"Europe/Kiev",
    "iso:country":"UA",
    "wof:name":"Blyumental' Nomer Devyatnadtsatyy",
    "wof:placetype":"locality"
},
  "geometry": {"coordinates":[37.03333,47.58333],"type":"Point"}
}