{
  "type": "Feature",
  "properties": {
    "gn:admin1_code":"19.0",
    "gn:asciiname":"Zolochivka",
    "gn:country_code":"UA",
    "gn:dem":214,
    "gn:feature_class":"P",
    "gn:feature_code":"PPL",
    "gn:name":"Zolochivka",
    "gn:population":0,
    "gn:timezone":"Europe/Kiev",
    "iso:country":"UA",
    "name:ukr_x_preferred":[
        "Zolochivka"
    ],
    "name:ukr_x_variant":[
        "\u0417\u043e\u043b\u043e\u0447\u0456\u0432\u043a\u0430"
    ],
    "name:und_x_variant":[
        "Z\u0142ocz\u00f3wka",
        "Zlochevka",
        "Zlochuvka",
        "Zoloch\u00ebvka",
        "Zolochovka"
    ],
    "wof:name":"Zolochivka",
    "wof:placetype":"locality"
},
  "geometry": {"coordinates":[25.21769,50.51823],"type":"Point"}
}