{
  "type": "Feature",
  "properties": {
    "gn:population":2421,
    "iso:country":"UA",
    "name:eng_x_preferred":[
        "Beregovoye"
    ],
    "name:eng_x_variant":[
        "Beregove",
        "Korokel'"
    ],
    "name:rus_x_historical":[
        "\u041a\u043e\u0440\u043e\u043d\u0435\u043b\u044c"
    ],
    "name:rus_x_preferred":[
        "\u041a\u043e\u0440\u043e\u043d\u0435\u043b\u044c"
    ],
    "name:rus_x_variant":[
        "\u0411\u0435\u0440\u0435\u0433\u043e\u0432\u043e\u0435"
    ],
    "name:ukr_x_preferred":[
        "\u0411\u0435\u0440\u0435\u0433\u043e\u0432\u0435"
    ],
    "qs:a0":"\u0423\u043a\u0440\u0430\u0457\u043d\u0430",
    "qs:a1":"*\u041a\u0440\u0438\u043c",
    "qs:a1_alt":"Krym",
    "qs:a1r":"0",
    "qs:a2":"\u0424\u0435\u043e\u0434\u043e\u0441\u0456\u044f",
    "qs:a2_alt":"Feodosiia",
    "qs:adm0":"\u0423\u043a\u0440\u0430\u0457\u043d\u0430",
    "qs:la_lc":"*",
    "qs:level":"locality",
    "qs:loc":"\u0411\u0435\u0440\u0435\u0433\u043e\u0432\u0435",
    "qs:loc_alt":"Berehove",
    "qs:pop":0,
    "qs:type":"buffered point",
    "wd:wordcount":627,
    "wof:lang":[
        "eng"
    ],
    "wof:name":"\u0411\u0435\u0440\u0435\u0433\u043e\u0432\u0435",
    "wof:placetype":"locality",
    "wof:population":2421
},
  "geometry": {"coordinates":[35.432233,45.098957],"type":"Point"}
}