{
  "type": "Feature",
  "properties": {
    "gn:admin1_code":"27.0",
    "gn:asciiname":"Kvitneve",
    "gn:country_code":"UA",
    "gn:dem":170,
    "gn:feature_class":"P",
    "gn:feature_code":"PPL",
    "gn:name":"Kvitneve",
    "gn:population":0,
    "gn:timezone":"Europe/Kiev",
    "iso:country":"UA",
    "name:ukr_x_preferred":[
        "Kvitneve"
    ],
    "name:ukr_x_variant":[
        "\u041a\u0432\u0456\u0442\u043d\u0435\u0432\u0435"
    ],
    "name:und_x_variant":[
        "Voytashevka",
        "Dubovets",
        "Kvitnevoye",
        "Wojtaszewka"
    ],
    "wof:name":"Kvitneve",
    "wof:placetype":"locality"
},
  "geometry": {"coordinates":[29.25,50.31667],"type":"Point"}
}