{
  "type": "Feature",
  "properties": {
    "gn:admin1_code":"5.0",
    "gn:asciiname":"Sukhivs'ke",
    "gn:country_code":"UA",
    "gn:dem":297,
    "gn:feature_class":"P",
    "gn:feature_code":"PPL",
    "gn:name":"Sukhivs\u2019ke",
    "gn:population":0,
    "gn:timezone":"Europe/Kiev",
    "iso:country":"UA",
    "name:ukr_x_preferred":[
        "Sukhivs\u2019ke"
    ],
    "name:ukr_x_variant":[
        "\u0421\u0443\u0445\u0456\u0432\u0441\u044c\u043a\u0435"
    ],
    "name:und_x_variant":[
        "Sukhovskoy"
    ],
    "wof:name":"Sukhivs'ke",
    "wof:placetype":"locality"
},
  "geometry": {"coordinates":[38.70556,48.06292],"type":"Point"}
}