{
  "type": "Feature",
  "properties": {
    "gn:admin1_code":"09",
    "gn:asciiname":"Mon'ky",
    "gn:country_code":"UA",
    "gn:dem":305,
    "gn:feature_class":"P",
    "gn:feature_code":"PPL",
    "gn:name":"Mon\u2019ky",
    "gn:population":0,
    "gn:timezone":"Europe/Kiev",
    "iso:country":"UA",
    "name:ukr_x_preferred":[
        "Mon\u2019ky"
    ],
    "name:ukr_x_variant":[
        "\u041c\u043e\u043d\u044c\u043a\u0438"
    ],
    "wof:name":"Mon'ky",
    "wof:placetype":"locality"
},
  "geometry": {"coordinates":[26.80076,49.68873],"type":"Point"}
}