{
  "type": "Feature",
  "properties": {
    "gn:admin1_code":"2.0",
    "gn:asciiname":"Zelenyy Hay",
    "gn:country_code":"UA",
    "gn:dem":172,
    "gn:feature_class":"P",
    "gn:feature_code":"PPL",
    "gn:name":"Zelenyy Hay",
    "gn:population":0,
    "gn:timezone":"Europe/Kiev",
    "iso:country":"UA",
    "name:rus_x_preferred":[
        "Zel\u00ebnyy Gay"
    ],
    "name:ukr_x_preferred":[
        "Zelenyy Hay"
    ],
    "name:ukr_x_variant":[
        "\u0417\u0435\u043b\u0435\u043d\u0438\u0439 \u0413\u0430\u0439"
    ],
    "wof:name":"Zelenyy Hay",
    "wof:placetype":"locality"
},
  "geometry": {"coordinates":[32.82066,51.87464],"type":"Point"}
}