{
  "type": "Feature",
  "properties": {
    "gn:admin1_code":"5.0",
    "gn:asciiname":"Oktyabrs'ke",
    "gn:country_code":"UA",
    "gn:dem":96,
    "gn:feature_class":"P",
    "gn:feature_code":"PPL",
    "gn:name":"Oktyabrs\u2019ke",
    "gn:population":0,
    "gn:timezone":"Europe/Kiev",
    "iso:country":"UA",
    "name:rus_x_preferred":[
        "Oktyabr\u2019skoye"
    ],
    "name:ukr_x_preferred":[
        "Oktyabrs\u2019ke"
    ],
    "name:ukr_x_variant":[
        "\u041e\u043a\u0442\u044f\u0431\u0440\u0441\u044c\u043a\u0435"
    ],
    "wof:name":"Oktyabrs'ke",
    "wof:placetype":"locality"
},
  "geometry": {"coordinates":[37.33639,48.77045],"type":"Point"}
}