{
  "type": "Feature",
  "properties": {
    "iso:country":"UA",
    "name:deu_x_preferred":[
        "Uschkalka"
    ],
    "name:eng_x_preferred":[
        "Ushkalka"
    ],
    "name:lav_x_preferred":[
        "U\u0161kalka"
    ],
    "name:ron_x_preferred":[
        "U\u0219kalka"
    ],
    "name:rus_x_preferred":[
        "\u0423\u0448\u043a\u0430\u043b\u043a\u0430"
    ],
    "name:ukr_x_preferred":[
        "Ushkalka"
    ],
    "name:ukr_x_variant":[
        "\u0423\u0448\u043a\u0430\u043b\u043a\u0430"
    ],
    "qs:a0":"\u0423\u043a\u0440\u0430\u0457\u043d\u0430",
    "qs:a1":"*\u0425\u0435\u0440\u0441\u043e\u043d\u0441\u044c\u043a\u0430",
    "qs:a1_alt":"Khersons'ka",
    "qs:a1r":"0",
    "qs:a2":"\u0412\u0435\u0440\u0445\u043d\u044c\u043e\u0440\u043e\u0433\u0430\u0447\u0438\u0446\u044c\u043a\u0438\u0439",
    "qs:a2_alt":"Verkhn'orohachyts'kyi",
    "qs:adm0":"\u0423\u043a\u0440\u0430\u0457\u043d\u0430",
    "qs:la_lc":"*",
    "qs:level":"locality",
    "qs:loc":"\u0423\u0448\u043a\u0430\u043b\u043a\u0430",
    "qs:loc_alt":"Ushkalka",
    "qs:pop":0,
    "qs:type":"buffered point",
    "wof:name":"\u0423\u0448\u043a\u0430\u043b\u043a\u0430",
    "wof:placetype":"locality"
},
  "geometry": {"coordinates":[34.120242,47.412356],"type":"Point"}
}