{
  "type": "Feature",
  "properties": {
    "gn:admin1_code":"17.0",
    "gn:asciiname":"Rus'ka Slobidka",
    "gn:country_code":"UA",
    "gn:dem":18,
    "gn:feature_class":"P",
    "gn:feature_code":"PPL",
    "gn:name":"Rus\u2019ka Slobidka",
    "gn:population":0,
    "gn:timezone":"Europe/Kiev",
    "iso:country":"UA",
    "name:ukr_x_preferred":[
        "Rus\u2019ka Slobidka"
    ],
    "name:ukr_x_variant":[
        "\u0420\u0443\u0441\u044c\u043a\u0430 \u0421\u043b\u043e\u0431\u0456\u0434\u043a\u0430"
    ],
    "name:und_x_variant":[
        "Russkaya Slobodka"
    ],
    "wof:name":"Rus'ka Slobidka",
    "wof:placetype":"locality"
},
  "geometry": {"coordinates":[30.59573,46.8535],"type":"Point"}
}