{
  "type": "Feature",
  "properties": {
    "gn:admin1_code":"23.0",
    "gn:asciiname":"Kukuly",
    "gn:country_code":"UA",
    "gn:dem":106,
    "gn:feature_class":"P",
    "gn:feature_code":"PPL",
    "gn:name":"Kukuly",
    "gn:population":0,
    "gn:timezone":"Europe/Kiev",
    "iso:country":"UA",
    "name:ukr_x_preferred":[
        "\u041a\u0443\u043a\u0443\u043b\u0438"
    ],
    "name:und_x_variant":[
        "Kukul\u2019"
    ],
    "wof:name":"Kukuly",
    "wof:placetype":"locality"
},
  "geometry": {"coordinates":[28.75667,48.18103],"type":"Point"}
}