{
  "type": "Feature",
  "properties": {
    "gn:admin1_code":"22.0",
    "gn:asciiname":"Dobropole",
    "gn:country_code":"UA",
    "gn:dem":368,
    "gn:feature_class":"P",
    "gn:feature_code":"PPL",
    "gn:name":"Dobropole",
    "gn:population":0,
    "gn:timezone":"Europe/Kiev",
    "iso:country":"UA",
    "name:deu_x_preferred":[
        "Dobropole"
    ],
    "name:pol_x_preferred":[
        "Dobropole"
    ],
    "name:ukr_x_preferred":[
        "\u0414\u043e\u0431\u0440\u043e\u043f\u043e\u043b\u0435"
    ],
    "wof:name":"Dobropole",
    "wof:placetype":"locality"
},
  "geometry": {"coordinates":[25.42877,49.19597],"type":"Point"}
}