{
  "type": "Feature",
  "properties": {
    "gn:admin1_code":"22.0",
    "gn:asciiname":"Dobropole",
    "gn:country_code":"UA",
    "gn:dem":368,
    "gn:feature_class":"P",
    "gn:feature_code":"PPL",
    "gn:name":"Dobropole",
    "gn:population":0,
    "gn:timezone":"Europe/Kiev",
    "iso:country":"UA",
    "wof:name":"Dobropole",
    "wof:placetype":"locality"
},
  "geometry": {"coordinates":[25.42877,49.19597],"type":"Point"}
}