{
  "type": "Feature",
  "properties": {
    "gn:admin1_code":"19.0",
    "gn:asciiname":"Nyvy-Zolochivs'ki",
    "gn:country_code":"UA",
    "gn:dem":210,
    "gn:feature_class":"P",
    "gn:feature_code":"PPL",
    "gn:name":"Nyvy-Zolochivs\u2019ki",
    "gn:population":0,
    "gn:timezone":"Europe/Kiev",
    "iso:country":"UA",
    "name:ukr_x_preferred":[
        "Nyvy-Zolochivs\u2019ki"
    ],
    "name:ukr_x_variant":[
        "\u041d\u0438\u0432\u0438-\u0417\u043e\u043b\u043e\u0447\u0456\u0432\u0441\u044c\u043a\u0456"
    ],
    "name:und_x_variant":[
        "Nivy-Zolichivskiye"
    ],
    "wof:name":"Nyvy-Zolochivs'ki",
    "wof:placetype":"locality"
},
  "geometry": {"coordinates":[25.16272,50.53466],"type":"Point"}
}