{
  "type": "Feature",
  "properties": {
    "gn:gn_country":"UA",
    "gn:gn_fcode":"PPL",
    "gn:gn_pop":4272,
    "gn:population":4272,
    "iso:country":"UA",
    "name:eng_x_preferred":[
        "Lypnyazhka"
    ],
    "name:rus_x_preferred":[
        "\u041b\u0438\u043f\u043d\u044f\u0436\u043a\u0430"
    ],
    "name:unk_x_variant":[
        "Lipnyazhka"
    ],
    "qs_pg:aaroncc":"UA",
    "qs_pg:gn_country":"UA",
    "qs_pg:gn_fcode":"PPL",
    "qs_pg:gn_pop":4272,
    "qs_pg:name":"Lypnyazhka",
    "qs_pg:photos_9r":0,
    "qs_pg:photos_sr":0,
    "qs_pg:pop_sr":4,
    "qs_pg:qs_pg_placetype":"locality",
    "wof:name":"Lypnyazhka",
    "wof:placetype":"locality",
    "wof:population":4272
},
  "geometry": {"coordinates":[31.07611,48.44694],"type":"Point"}
}