{
  "type": "Feature",
  "properties": {
    "gn:admin1_code":"21.0",
    "gn:asciiname":"Marukhy",
    "gn:country_code":"UA",
    "gn:dem":150,
    "gn:feature_class":"P",
    "gn:feature_code":"PPL",
    "gn:name":"Marukhy",
    "gn:population":0,
    "gn:timezone":"Europe/Kiev",
    "iso:country":"UA",
    "name:ukr_x_preferred":[
        "Marukhy"
    ],
    "name:ukr_x_variant":[
        "\u041c\u0430\u0440\u0443\u0445\u0438"
    ],
    "name:und_x_variant":[
        "Marukhi"
    ],
    "wof:name":"Marukhy",
    "wof:placetype":"locality"
},
  "geometry": {"coordinates":[33.5303,51.58056],"type":"Point"}
}