{
  "type": "Feature",
  "properties": {
    "iso:country":"UA",
    "name:eng_x_preferred":[
        "Omel'nik"
    ],
    "name:eng_x_variant":[
        "Omelnyk"
    ],
    "name:hye_x_preferred":[
        "\u0555\u0574\u0565\u056c\u0576\u056b\u056f"
    ],
    "name:ron_x_preferred":[
        "Omeln\u00eek"
    ],
    "name:rus_x_preferred":[
        "\u041e\u043c\u0435\u043b\u044c\u043d\u0438\u043a"
    ],
    "name:ukr_x_preferred":[
        "Omel\u2019nyk"
    ],
    "name:ukr_x_variant":[
        "\u041e\u043c\u0435\u043b\u044c\u043d\u0438\u043a"
    ],
    "name:unk_x_variant":[
        "Omel\u2019nik"
    ],
    "name:zho_x_preferred":[
        "\u5967\u6885\u5229\u5c3c\u514b"
    ],
    "qs:a0":"\u0423\u043a\u0440\u0430\u0457\u043d\u0430",
    "qs:a1":"*\u041f\u043e\u043b\u0442\u0430\u0432\u0441\u044c\u043a\u0430",
    "qs:a1_alt":"Poltavs'ka",
    "qs:a1r":"0",
    "qs:a2":"\u041a\u0440\u0435\u043c\u0435\u043d\u0447\u0443\u0446\u044c\u043a\u0438\u0439",
    "qs:a2_alt":"Kremenchuts'kyi",
    "qs:adm0":"\u0423\u043a\u0440\u0430\u0457\u043d\u0430",
    "qs:la_lc":"*",
    "qs:level":"locality",
    "qs:loc":"\u041e\u043c\u0435\u043b\u044c\u043d\u0438\u043a",
    "qs:loc_alt":"Omel'nyk",
    "qs:pop":0,
    "qs:type":"buffered point",
    "wof:name":"\u041e\u043c\u0435\u043b\u044c\u043d\u0438\u043a",
    "wof:placetype":"locality"
},
  "geometry": {"coordinates":[33.544705,49.208256],"type":"Point"}
}