{
  "type": "Feature",
  "properties": {
    "gn:admin1_code":"1.0",
    "gn:asciiname":"Shevchenkovskiy",
    "gn:country_code":"UA",
    "gn:dem":111,
    "gn:feature_class":"P",
    "gn:feature_code":"PPL",
    "gn:name":"Shevchenkovskiy",
    "gn:population":0,
    "gn:timezone":"Europe/Kiev",
    "iso:country":"UA",
    "name:und_x_variant":[
        "Pos\u00eblok Shevchenkovskiy",
        "Shevchenkovskiy"
    ],
    "wof:name":"Shevchenkovskiy",
    "wof:placetype":"locality"
},
  "geometry": {"coordinates":[31.89319,49.18753],"type":"Point"}
}