{
  "type": "Feature",
  "properties": {
    "gn:admin1_code":"18.0",
    "gn:asciiname":"Podluky",
    "gn:country_code":"UA",
    "gn:dem":91,
    "gn:feature_class":"P",
    "gn:feature_code":"PPL",
    "gn:name":"Podluky",
    "gn:population":0,
    "gn:timezone":"Europe/Kiev",
    "iso:country":"UA",
    "name:ukr_x_preferred":[
        "Podluky"
    ],
    "name:ukr_x_variant":[
        "\u041f\u043e\u0434\u043b\u0443\u043a\u0438"
    ],
    "wof:name":"Podluky",
    "wof:placetype":"locality"
},
  "geometry": {"coordinates":[33.85043,49.86701],"type":"Point"}
}