{
  "type": "Feature",
  "properties": {
    "gn:admin1_code":"5.0",
    "gn:asciiname":"Yelanchik",
    "gn:country_code":"UA",
    "gn:dem":5,
    "gn:feature_class":"P",
    "gn:feature_code":"PPL",
    "gn:name":"Yelanchik",
    "gn:population":0,
    "gn:timezone":"Europe/Kiev",
    "iso:country":"UA",
    "wof:name":"Yelanchik",
    "wof:placetype":"locality"
},
  "geometry": {"coordinates":[38.05556,47.11139],"type":"Point"}
}