{
  "type": "Feature",
  "properties": {
    "gn:admin1_code":"17.0",
    "gn:asciiname":"Durbayly",
    "gn:country_code":"UA",
    "gn:dem":119,
    "gn:feature_class":"P",
    "gn:feature_code":"PPL",
    "gn:name":"Durbayly",
    "gn:population":0,
    "gn:timezone":"Europe/Kiev",
    "iso:country":"UA",
    "name:und_x_variant":[
        "Durbailovka",
        "Durbayly"
    ],
    "wof:name":"Durbayly",
    "wof:placetype":"locality"
},
  "geometry": {"coordinates":[29.92041,47.16396],"type":"Point"}
}