{
  "type": "Feature",
  "properties": {
    "gn:admin1_code":"18.0",
    "gn:asciiname":"Butovyches'ke",
    "gn:country_code":"UA",
    "gn:dem":162,
    "gn:feature_class":"P",
    "gn:feature_code":"PPL",
    "gn:name":"Butovyches\u2019ke",
    "gn:population":0,
    "gn:timezone":"Europe/Kiev",
    "iso:country":"UA",
    "name:ukr_x_preferred":[
        "Butovyches\u2019ke"
    ],
    "name:ukr_x_variant":[
        "\u0411\u0443\u0442\u043e\u0432\u0438\u0447\u0435\u0441\u044c\u043a\u0435"
    ],
    "wof:name":"Butovyches'ke",
    "wof:placetype":"locality"
},
  "geometry": {"coordinates":[33.83448,50.31305],"type":"Point"}
}