{
  "type": "Feature",
  "properties": {
    "gn:admin1_code":"7.0",
    "gn:asciiname":"Dmitrenkov",
    "gn:country_code":"UA",
    "gn:dem":152,
    "gn:feature_class":"P",
    "gn:feature_code":"PPL",
    "gn:name":"Dmitrenkov",
    "gn:population":0,
    "gn:timezone":"Europe/Kiev",
    "iso:country":"UA",
    "wof:name":"Dmitrenkov",
    "wof:placetype":"locality"
},
  "geometry": {"coordinates":[35.23333,50.03333],"type":"Point"}
}