{
  "type": "Feature",
  "properties": {
    "gn:admin1_code":"2.0",
    "gn:asciiname":"Parystivka",
    "gn:country_code":"UA",
    "gn:dem":120,
    "gn:feature_class":"P",
    "gn:feature_code":"PPL",
    "gn:name":"Parystivka",
    "gn:population":0,
    "gn:timezone":"Europe/Kiev",
    "iso:country":"UA",
    "name:ukr_x_preferred":[
        "Parystivka"
    ],
    "name:ukr_x_variant":[
        "\u041f\u0430\u0440\u0438\u0441\u0442\u0456\u0432\u043a\u0430"
    ],
    "name:und_x_variant":[
        "Paristovka"
    ],
    "wof:name":"Parystivka",
    "wof:placetype":"locality"
},
  "geometry": {"coordinates":[32.63711,51.40857000000001],"type":"Point"}
}