{
  "type": "Feature",
  "properties": {
    "gn:admin1_code":"18.0",
    "gn:asciiname":"Paskivka",
    "gn:country_code":"UA",
    "gn:dem":90,
    "gn:feature_class":"P",
    "gn:feature_code":"PPL",
    "gn:name":"Paskivka",
    "gn:population":0,
    "gn:timezone":"Europe/Kiev",
    "iso:country":"UA",
    "name:ukr_x_preferred":[
        "Paskivka"
    ],
    "name:ukr_x_variant":[
        "\u041f\u0430\u0441\u043a\u0456\u0432\u043a\u0430"
    ],
    "wof:name":"Paskivka",
    "wof:placetype":"locality"
},
  "geometry": {"coordinates":[34.66886,49.63011],"type":"Point"}
}