{
  "type": "Feature",
  "properties": {
    "gn:gn_country":"UA",
    "gn:gn_fcode":"PPL",
    "gn:gn_pop":3145,
    "gn:population":3145,
    "iso:country":"UA",
    "name:arm_x_preferred":[
        "\u054c\u0561\u056f\u0578\u0577\u056b\u0576\u0578"
    ],
    "name:chi_x_preferred":[
        "\u62c9\u79d1\u4ec0\u8afe"
    ],
    "name:dut_x_preferred":[
        "Rakoszyno"
    ],
    "name:eng_x_preferred":[
        "Rakoshino"
    ],
    "name:epo_x_preferred":[
        "Rako\u015dino"
    ],
    "name:hun_x_preferred":[
        "Beregr\u00e1kos"
    ],
    "name:pol_x_preferred":[
        "Rakoszyno"
    ],
    "name:rum_x_preferred":[
        "Rako\u0219\u00eeno"
    ],
    "name:rus_x_preferred":[
        "\u0420\u0430\u043a\u043e\u0448\u0438\u043d\u043e"
    ],
    "name:ukr_x_preferred":[
        "\u0420\u0430\u043a\u043e\u0448\u0438\u043d"
    ],
    "name:ukr_x_variant":[
        "\u0420\u0430\u043a\u043e\u0448\u0438\u043d\u043e"
    ],
    "name:unk_x_variant":[
        "Rakoshyn"
    ],
    "qs_pg:aaroncc":"UA",
    "qs_pg:gn_country":"UA",
    "qs_pg:gn_fcode":"PPL",
    "qs_pg:gn_pop":3145,
    "qs_pg:name":"Rakoshyno",
    "qs_pg:photos_9r":0,
    "qs_pg:photos_sr":0,
    "qs_pg:pop_sr":4,
    "qs_pg:qs_pg_placetype":"locality",
    "wof:name":"Rakoshyno",
    "wof:placetype":"locality",
    "wof:population":3145
},
  "geometry": {"coordinates":[22.59687,48.46713],"type":"Point"}
}