{
  "type": "Feature",
  "properties": {
    "iso:country":"UA",
    "name:ceb_x_preferred":[
        "Zahattya"
    ],
    "name:eng_x_preferred":[
        "Zahattya"
    ],
    "name:epo_x_preferred":[
        "Zahattja"
    ],
    "name:hun_x_preferred":[
        "H\u00e1tmeg"
    ],
    "name:hye_x_preferred":[
        "\u0536\u0561\u0563\u0561\u057f\u056b\u0565"
    ],
    "name:nld_x_preferred":[
        "Zahattya"
    ],
    "name:ron_x_preferred":[
        "Zahattea"
    ],
    "name:rus_x_preferred":[
        "\u0417\u0430\u0433\u0430\u0442\u044c\u0435"
    ],
    "name:rus_x_variant":[
        "Zagat\u2019ye"
    ],
    "name:ukr_x_preferred":[
        "\u0417\u0430\u0433\u0430\u0442\u0442\u044f"
    ],
    "name:ukr_x_variant":[
        "Zahattya"
    ],
    "name:urd_x_preferred":[
        "\u0632\u06c1\u062a\u062a\u06cc\u06c1"
    ],
    "name:zho_x_preferred":[
        "\u624e\u52a0\u7279\u5b63\u4e9e"
    ],
    "qs:a0":"\u0423\u043a\u0440\u0430\u0457\u043d\u0430",
    "qs:a1":"*\u0417\u0430\u043a\u0430\u0440\u043f\u0430\u0442\u0441\u044c\u043a\u0430",
    "qs:a1_alt":"Zakarpats'ka",
    "qs:a1r":"0",
    "qs:a2":"\u0406\u0440\u0448\u0430\u0432\u0441\u044c\u043a\u0438\u0439",
    "qs:a2_alt":"Irshavs'kyi",
    "qs:adm0":"\u0423\u043a\u0440\u0430\u0457\u043d\u0430",
    "qs:la_lc":"*",
    "qs:level":"locality",
    "qs:loc":"\u0417\u0430\u0433\u0430\u0442\u0442\u044f",
    "qs:loc_alt":"Zahattia",
    "qs:pop":0,
    "qs:type":"buffered point",
    "wd:wordcount":94,
    "wof:name":"\u0417\u0430\u0433\u0430\u0442\u0442\u044f",
    "wof:placetype":"locality"
},
  "geometry": {"coordinates":[22.959003,48.386056],"type":"Point"}
}