{
  "type": "Feature",
  "properties": {
    "gn:country":"UA",
    "gn:fcode":"PPL",
    "gn:population":19220,
    "iso:country":"UA",
    "name:ara_x_preferred":[
        "\u0628\u0627\u0644\u062a\u0627"
    ],
    "name:azb_x_preferred":[
        "\u0628\u0627\u0644\u062a\u0627"
    ],
    "name:bel_x_preferred":[
        "\u0411\u0430\u043b\u0442\u0430"
    ],
    "name:bul_x_preferred":[
        "\u0411\u0430\u043b\u0442\u0430"
    ],
    "name:ceb_x_preferred":[
        "Balta"
    ],
    "name:ces_x_preferred":[
        "Balta"
    ],
    "name:che_x_preferred":[
        "\u0411\u0430\u043b\u0442\u0430"
    ],
    "name:crh_x_preferred":[
        "Balta"
    ],
    "name:deu_x_preferred":[
        "Balta"
    ],
    "name:eng_x_preferred":[
        "Balta"
    ],
    "name:epo_x_preferred":[
        "Balta"
    ],
    "name:fas_x_preferred":[
        "\u0628\u0627\u0644\u062a\u0627\u060c \u0627\u0648\u06a9\u0631\u0627\u06cc\u0646"
    ],
    "name:fas_x_variant":[
        "\u0628\u0627\u0644\u062a\u0627"
    ],
    "name:fra_x_preferred":[
        "Balta"
    ],
    "name:heb_x_preferred":[
        "\u05d1\u05d0\u05dc\u05d8\u05d4"
    ],
    "name:hsb_x_preferred":[
        "Balta"
    ],
    "name:hye_x_preferred":[
        "\u0532\u0561\u056c\u057f\u0561"
    ],
    "name:ita_x_preferred":[
        "Balta"
    ],
    "name:jpn_x_preferred":[
        "\u30d0\u30eb\u30bf"
    ],
    "name:kat_x_preferred":[
        "\u10d1\u10d0\u10da\u10e2\u10d0"
    ],
    "name:lav_x_preferred":[
        "Balta"
    ],
    "name:lit_x_preferred":[
        "Balta"
    ],
    "name:nld_x_preferred":[
        "Balta"
    ],
    "name:nno_x_preferred":[
        "Balta i Ukraina"
    ],
    "name:nob_x_preferred":[
        "Balta"
    ],
    "name:pol_x_preferred":[
        "Ba\u0142ta"
    ],
    "name:por_x_preferred":[
        "Balta"
    ],
    "name:ron_x_preferred":[
        "Balta"
    ],
    "name:rus_x_preferred":[
        "\u0411\u0430\u043b\u0442\u0430"
    ],
    "name:sah_x_preferred":[
        "\u0411\u0430\u043b\u0442\u0430"
    ],
    "name:slv_x_preferred":[
        "Balta"
    ],
    "name:spa_x_preferred":[
        "Balta"
    ],
    "name:srp_x_preferred":[
        "\u0411\u0430\u043b\u0442\u0430"
    ],
    "name:swe_x_preferred":[
        "Balta"
    ],
    "name:tat_x_preferred":[
        "\u0411\u0430\u043b\u0442\u0430"
    ],
    "name:ukr_x_preferred":[
        "\u0411\u0430\u043b\u0442\u0430"
    ],
    "name:urd_x_preferred":[
        "\u0628\u0627\u0644\u062a\u0627\u060c \u0627\u0648\u062f\u06cc\u0633\u0627 \u0627\u0648\u0628\u0644\u0627\u0633\u062a"
    ],
    "name:urd_x_variant":[
        "\u0628\u0627\u0644\u062a\u0627"
    ],
    "name:vie_x_preferred":[
        "Balta"
    ],
    "name:zho_x_preferred":[
        "\u5df4\u723e\u5854"
    ],
    "qs_pg:aaroncc":"UA",
    "qs_pg:gn_country":"UA",
    "qs_pg:gn_fcode":"PPL",
    "qs_pg:gn_pop":19220,
    "qs_pg:name":"Balta",
    "qs_pg:photos_9r":0,
    "qs_pg:photos_sr":0,
    "qs_pg:pop_sr":6,
    "qs_pg:qs_pg_placetype":"locality",
    "wof:name":"Balta",
    "wof:placetype":"locality",
    "wof:population":19220
},
  "geometry": {"coordinates":[29.61982,47.93548],"type":"Point"}
}