{
  "type": "Feature",
  "properties": {
    "gn:admin1_code":"21.0",
    "gn:asciiname":"Chervone Ozero",
    "gn:country_code":"UA",
    "gn:dem":128,
    "gn:feature_class":"P",
    "gn:feature_code":"PPL",
    "gn:name":"Chervone Ozero",
    "gn:population":0,
    "gn:timezone":"Europe/Kiev",
    "iso:country":"UA",
    "name:ukr_x_preferred":[
        "Chervone Ozero"
    ],
    "name:ukr_x_variant":[
        "\u0427\u0435\u0440\u0432\u043e\u043d\u0435 \u041e\u0437\u0435\u0440\u043e"
    ],
    "name:und_x_variant":[
        "Krasnoye Ozero",
        "Chervonoye Ozero"
    ],
    "wof:name":"Chervone Ozero",
    "wof:placetype":"locality"
},
  "geometry": {"coordinates":[33.95,51.25],"type":"Point"}
}