{
  "type": "Feature",
  "properties": {
    "gn:admin1_code":"19.0",
    "gn:asciiname":"Mlyn",
    "gn:country_code":"UA",
    "gn:dem":140,
    "gn:feature_class":"P",
    "gn:feature_code":"PPL",
    "gn:name":"Mlyn",
    "gn:population":0,
    "gn:timezone":"Europe/Kiev",
    "iso:country":"UA",
    "name:ukr_x_preferred":[
        "Mlyn"
    ],
    "name:ukr_x_variant":[
        "\u041c\u043b\u0438\u043d"
    ],
    "wof:name":"Mlyn",
    "wof:placetype":"locality"
},
  "geometry": {"coordinates":[25.72405,51.87795],"type":"Point"}
}