{
  "type": "Feature",
  "properties": {
    "iso:country":"UA",
    "name:ukr_x_preferred":[
        "Bilorichytsya"
    ],
    "name:ukr_x_variant":[
        "\u0411\u0456\u043b\u043e\u0440\u0456\u0447\u0438\u0446\u044f"
    ],
    "name:und_x_variant":[
        "Vezbokhovka"
    ],
    "qs:a0":"\u0423\u043a\u0440\u0430\u0457\u043d\u0430",
    "qs:a1":"*\u0427\u0435\u0440\u043d\u0456\u0433\u0456\u0432\u0441\u044c\u043a\u0430",
    "qs:a1_alt":"Chernihivs'ka",
    "qs:a1r":"0",
    "qs:a2":"\u041f\u0440\u0438\u043b\u0443\u0446\u044c\u043a\u0438\u0439",
    "qs:a2_alt":"Pryluts'kyi",
    "qs:adm0":"\u0423\u043a\u0440\u0430\u0457\u043d\u0430",
    "qs:la_lc":"*",
    "qs:level":"locality",
    "qs:loc":"\u0411\u0456\u043b\u043e\u0440\u0456\u0447\u0438\u0446\u044f",
    "qs:loc_alt":"Bilorichytsia",
    "qs:pop":0,
    "qs:type":"buffered point",
    "wof:name":"\u0411\u0456\u043b\u043e\u0440\u0456\u0447\u0438\u0446\u044f",
    "wof:placetype":"locality"
},
  "geometry": {"coordinates":[32.010173,50.675754],"type":"Point"}
}