{
  "type": "Feature",
  "properties": {
    "gn:admin1_code":"27.0",
    "gn:asciiname":"Ozeryany",
    "gn:country_code":"UA",
    "gn:dem":188,
    "gn:feature_class":"P",
    "gn:feature_code":"PPL",
    "gn:name":"Ozeryany",
    "gn:population":0,
    "gn:timezone":"Europe/Kiev",
    "iso:country":"UA",
    "name:hye_x_preferred":[
        "\u0555\u0566\u0565\u0580\u0575\u0561\u0576\u056b"
    ],
    "name:rus_x_preferred":[
        "\u041e\u0437\u0435\u0440\u044f\u043d\u044b"
    ],
    "name:ukr_x_preferred":[
        "\u041e\u0437\u0435\u0440\u044f\u043d\u0438"
    ],
    "name:und_x_variant":[
        "Ozerany",
        "Ozeryane",
        "Ozeryany"
    ],
    "wof:name":"Ozeryany",
    "wof:placetype":"locality"
},
  "geometry": {"coordinates":[28.0282,51.23969],"type":"Point"}
}