{
  "type": "Feature",
  "properties": {
    "gn:admin1_code":"4.0",
    "gn:asciiname":"Baykivka",
    "gn:country_code":"UA",
    "gn:dem":135,
    "gn:feature_class":"P",
    "gn:feature_code":"PPL",
    "gn:name":"Baykivka",
    "gn:population":0,
    "gn:timezone":"Europe/Kiev",
    "iso:country":"UA",
    "name:rus_x_preferred":[
        "\u0411\u0430\u0439\u043a\u043e\u0432\u043a\u0430"
    ],
    "name:ukr_x_preferred":[
        "Baykivka"
    ],
    "name:ukr_x_variant":[
        "\u0411\u0430\u0439\u043a\u0456\u0432\u043a\u0430"
    ],
    "name:und_x_variant":[
        "Baykovka"
    ],
    "wof:name":"Baykivka",
    "wof:placetype":"locality"
},
  "geometry": {"coordinates":[33.95247,48.41307000000001],"type":"Point"}
}