{
  "type": "Feature",
  "properties": {
    "gn:admin1_code":"27.0",
    "gn:asciiname":"Zaderev'ye",
    "gn:country_code":"UA",
    "gn:dem":192,
    "gn:feature_class":"P",
    "gn:feature_code":"PPL",
    "gn:name":"Zaderev\u2019ye",
    "gn:population":0,
    "gn:timezone":"Europe/Kiev",
    "iso:country":"UA",
    "wof:name":"Zaderev'ye",
    "wof:placetype":"locality"
},
  "geometry": {"coordinates":[27.35,51.05],"type":"Point"}
}