{
  "type": "Feature",
  "properties": {
    "gn:admin1_code":"15.0",
    "gn:asciiname":"Voshchantsy",
    "gn:cc2":"UA",
    "gn:country_code":"UA",
    "gn:dem":275,
    "gn:feature_class":"P",
    "gn:feature_code":"PPL",
    "gn:name":"Voshchantsy",
    "gn:population":0,
    "gn:timezone":"Europe/Kiev",
    "iso:country":"UA",
    "name:und_x_variant":[
        "Voshan\u2019tse",
        "Voshchantsy"
    ],
    "wof:name":"Voshchantsy",
    "wof:placetype":"locality"
},
  "geometry": {"coordinates":[23.41667,49.66667],"type":"Point"}
}