{
  "type": "Feature",
  "properties": {
    "gn:admin1_code":"19.0",
    "gn:asciiname":"Maslyanka",
    "gn:country_code":"UA",
    "gn:dem":217,
    "gn:feature_class":"P",
    "gn:feature_code":"PPL",
    "gn:name":"Maslyanka",
    "gn:population":0,
    "gn:timezone":"Europe/Kiev",
    "iso:country":"UA",
    "name:ukr_x_preferred":[
        "Maslyanka"
    ],
    "name:ukr_x_variant":[
        "\u041c\u0430\u0441\u043b\u044f\u043d\u043a\u0430"
    ],
    "wof:name":"Maslyanka",
    "wof:placetype":"locality"
},
  "geometry": {"coordinates":[25.61823,50.53597],"type":"Point"}
}