{
  "type": "Feature",
  "properties": {
    "gn:admin1_code":"09",
    "gn:asciiname":"Vyshneve",
    "gn:country_code":"UA",
    "gn:dem":256,
    "gn:feature_class":"P",
    "gn:feature_code":"PPL",
    "gn:name":"Vyshneve",
    "gn:population":0,
    "gn:timezone":"Europe/Kiev",
    "iso:country":"UA",
    "name:ukr_x_preferred":[
        "Vyshneve"
    ],
    "name:ukr_x_variant":[
        "\u0412\u0438\u0448\u043d\u0435\u0432\u0435"
    ],
    "wof:name":"Vyshneve",
    "wof:placetype":"locality"
},
  "geometry": {"coordinates":[27.06066,49.97168],"type":"Point"}
}