{
  "type": "Feature",
  "properties": {
    "gn:admin1_code":"17.0",
    "gn:asciiname":"Bochmanivka",
    "gn:country_code":"UA",
    "gn:dem":237,
    "gn:feature_class":"P",
    "gn:feature_code":"PPL",
    "gn:name":"Bochmanivka",
    "gn:population":0,
    "gn:timezone":"Europe/Kiev",
    "iso:country":"UA",
    "name:ukr_x_preferred":[
        "Bochmanivka"
    ],
    "name:ukr_x_variant":[
        "\u0411\u043e\u0447\u043c\u0430\u043d\u0456\u0432\u043a\u0430"
    ],
    "name:und_x_variant":[
        "Bachmanovka",
        "Bochmanovka"
    ],
    "wof:name":"Bochmanivka",
    "wof:placetype":"locality"
},
  "geometry": {"coordinates":[29.5657,47.65691],"type":"Point"}
}