{
  "type": "Feature",
  "properties": {
    "gn:admin1_code":"5.0",
    "gn:asciiname":"Aleksandrinka",
    "gn:country_code":"UA",
    "gn:dem":141,
    "gn:feature_class":"P",
    "gn:feature_code":"PPL",
    "gn:name":"Aleksandrinka",
    "gn:population":0,
    "gn:timezone":"Europe/Kiev",
    "iso:country":"UA",
    "name:und_x_variant":[
        "Dolyn Tarama",
        "Aleksandrinka"
    ],
    "wof:name":"Aleksandrinka",
    "wof:placetype":"locality"
},
  "geometry": {"coordinates":[37.68193,47.77873],"type":"Point"}
}