{
  "type": "Feature",
  "properties": {
    "gn:admin1_code":"5.0",
    "gn:asciiname":"Stupochky",
    "gn:country_code":"UA",
    "gn:dem":186,
    "gn:feature_class":"P",
    "gn:feature_code":"PPL",
    "gn:name":"Stupochky",
    "gn:population":0,
    "gn:timezone":"Europe/Kiev",
    "iso:country":"UA",
    "name:ukr_x_preferred":[
        "Stupochky"
    ],
    "name:ukr_x_variant":[
        "\u0421\u0442\u0443\u043f\u043e\u0447\u043a\u0438"
    ],
    "wof:name":"Stupochky",
    "wof:placetype":"locality"
},
  "geometry": {"coordinates":[37.82239000000001,48.53058],"type":"Point"}
}