{
  "type": "Feature",
  "properties": {
    "gn:admin1_code":"5.0",
    "gn:asciiname":"Sketevatyy",
    "gn:country_code":"UA",
    "gn:dem":249,
    "gn:feature_class":"P",
    "gn:feature_code":"PPL",
    "gn:name":"Sketevatyy",
    "gn:population":0,
    "gn:timezone":"Europe/Kiev",
    "iso:country":"UA",
    "wof:name":"Sketevatyy",
    "wof:placetype":"locality"
},
  "geometry": {"coordinates":[38.07694,48.11639],"type":"Point"}
}