{
  "type": "Feature",
  "properties": {
    "gn:admin1_code":"7.0",
    "gn:asciiname":"Rzhavets'",
    "gn:country_code":"UA",
    "gn:dem":133,
    "gn:feature_class":"P",
    "gn:feature_code":"PPL",
    "gn:name":"Rzhavets\u2019",
    "gn:population":0,
    "gn:timezone":"Europe/Kiev",
    "iso:country":"UA",
    "name:ukr_x_preferred":[
        "Rzhavets\u2019"
    ],
    "name:ukr_x_variant":[
        "\u0420\u0436\u0430\u0432\u0435\u0446\u044c"
    ],
    "name:und_x_variant":[
        "Rizhov"
    ],
    "wof:name":"Rzhavets'",
    "wof:placetype":"locality"
},
  "geometry": {"coordinates":[36.14355,49.86303],"type":"Point"}
}