{
  "type": "Feature",
  "properties": {
    "gn:admin1_code":"2.0",
    "gn:asciiname":"Boromyky",
    "gn:country_code":"UA",
    "gn:dem":116,
    "gn:feature_class":"P",
    "gn:feature_code":"PPL",
    "gn:name":"Boromyky",
    "gn:population":0,
    "gn:timezone":"Europe/Kiev",
    "iso:country":"UA",
    "name:ukr_x_preferred":[
        "Boromyky"
    ],
    "name:ukr_x_variant":[
        "\u0411\u043e\u0440\u043e\u043c\u0438\u043a\u0438"
    ],
    "name:und_x_variant":[
        "Boromyki"
    ],
    "wof:name":"Boromyky",
    "wof:placetype":"locality"
},
  "geometry": {"coordinates":[31.60109000000001,51.53714],"type":"Point"}
}