{
  "type": "Feature",
  "properties": {
    "gn:admin1_code":"25.0",
    "gn:asciiname":"Roztots'ka Pastil'",
    "gn:country_code":"UA",
    "gn:dem":292,
    "gn:feature_class":"P",
    "gn:feature_code":"PPL",
    "gn:name":"Roztots\u2019ka Pastil\u2019",
    "gn:population":0,
    "gn:timezone":"Europe/Uzhgorod",
    "iso:country":"UA",
    "name:ukr_x_preferred":[
        "\u0420\u043e\u0437\u0442\u043e\u0446\u044c\u043a\u0430 \u041f\u0430\u0441\u0442\u0456\u043b\u044c"
    ],
    "name:und_x_variant":[
        "Roztots\u2019kaya Pastil\u2019",
        "Roztots\u2019ka Pastil\u2019",
        "Rostotskaya Pastil\u2019"
    ],
    "wof:name":"Roztots'ka Pastil'",
    "wof:placetype":"locality"
},
  "geometry": {"coordinates":[22.53142,48.87301],"type":"Point"}
}