{
  "type": "Feature",
  "properties": {
    "gn:admin1_code":"27.0",
    "gn:asciiname":"Novoselki",
    "gn:country_code":"UA",
    "gn:dem":231,
    "gn:feature_class":"P",
    "gn:feature_code":"PPL",
    "gn:name":"Novos\u00eblki",
    "gn:population":0,
    "gn:timezone":"Europe/Kiev",
    "iso:country":"UA",
    "wof:name":"Novoselki",
    "wof:placetype":"locality"
},
  "geometry": {"coordinates":[28.13333,50.08333],"type":"Point"}
}