{
  "type": "Feature",
  "properties": {
    "gn:admin1_code":"14.0",
    "gn:asciiname":"Voyevodivka",
    "gn:country_code":"UA",
    "gn:dem":54,
    "gn:feature_class":"P",
    "gn:feature_code":"PPL",
    "gn:name":"Voyevodivka",
    "gn:population":0,
    "gn:timezone":"Europe/Zaporozhye",
    "iso:country":"UA",
    "name:ukr_x_preferred":[
        "Voyevodivka"
    ],
    "name:ukr_x_variant":[
        "\u0412\u043e\u0454\u0432\u043e\u0434\u0456\u0432\u043a\u0430"
    ],
    "name:und_x_variant":[
        "Voyevodovka"
    ],
    "wof:name":"Voyevodivka",
    "wof:placetype":"locality"
},
  "geometry": {"coordinates":[38.44682,48.98031],"type":"Point"}
}