{
  "type": "Feature",
  "properties": {
    "gn:admin1_code":"17.0",
    "gn:asciiname":"Nastas'yevka",
    "gn:country_code":"UA",
    "gn:dem":44,
    "gn:feature_class":"P",
    "gn:feature_code":"PPL",
    "gn:name":"Nastas\u2019yevka",
    "gn:population":0,
    "gn:timezone":"Europe/Kiev",
    "iso:country":"UA",
    "name:und_x_variant":[
        "Anastas\u2019yevka",
        "Nastas\u2019yevka"
    ],
    "wof:name":"Nastas'yevka",
    "wof:placetype":"locality"
},
  "geometry": {"coordinates":[30.40484,47.54634],"type":"Point"}
}