{
  "type": "Feature",
  "properties": {
    "gn:admin1_code":"24.0",
    "gn:asciiname":"Pidhorodne",
    "gn:country_code":"UA",
    "gn:dem":190,
    "gn:feature_class":"P",
    "gn:feature_code":"PPL",
    "gn:name":"Pidhorodne",
    "gn:population":0,
    "gn:timezone":"Europe/Kiev",
    "iso:country":"UA",
    "name:ukr_x_preferred":[
        "Pidhorodne"
    ],
    "name:ukr_x_variant":[
        "\u041f\u0456\u0434\u0433\u043e\u0440\u043e\u0434\u043d\u0435"
    ],
    "name:und_x_variant":[
        "Podgorodno",
        "Podgorodnoye"
    ],
    "wof:name":"Pidhorodne",
    "wof:placetype":"locality"
},
  "geometry": {"coordinates":[24.18917,51.2385],"type":"Point"}
}