{
  "type": "Feature",
  "properties": {
    "gn:admin1_code":"17.0",
    "gn:asciiname":"Rostovtsevo",
    "gn:country_code":"UA",
    "gn:dem":110,
    "gn:feature_class":"P",
    "gn:feature_code":"PPL",
    "gn:name":"Rostovtsevo",
    "gn:population":0,
    "gn:timezone":"Europe/Kiev",
    "iso:country":"UA",
    "name:und_x_variant":[
        "Novos\u00eblki"
    ],
    "wof:name":"Rostovtsevo",
    "wof:placetype":"locality"
},
  "geometry": {"coordinates":[30.28333,46.91667],"type":"Point"}
}