{
  "type": "Feature",
  "properties": {
    "gn:admin1_code":"2.0",
    "gn:asciiname":"Molochky",
    "gn:country_code":"UA",
    "gn:dem":152,
    "gn:feature_class":"P",
    "gn:feature_code":"PPL",
    "gn:name":"Molochky",
    "gn:population":0,
    "gn:timezone":"Europe/Kiev",
    "iso:country":"UA",
    "name:ukr_x_preferred":[
        "Molochky"
    ],
    "name:ukr_x_variant":[
        "\u041c\u043e\u043b\u043e\u0447\u043a\u0438"
    ],
    "name:und_x_variant":[
        "Molochki"
    ],
    "wof:name":"Molochky",
    "wof:placetype":"locality"
},
  "geometry": {"coordinates":[30.90987,51.70174],"type":"Point"}
}