{
  "type": "Feature",
  "properties": {
    "gn:admin1_code":"23.0",
    "gn:asciiname":"Ordyntsi",
    "gn:country_code":"UA",
    "gn:dem":274,
    "gn:feature_class":"P",
    "gn:feature_code":"PPL",
    "gn:name":"Ordyntsi",
    "gn:population":0,
    "gn:timezone":"Europe/Kiev",
    "iso:country":"UA",
    "name:ukr_x_preferred":[
        "\u041e\u0440\u0434\u0438\u043d\u0446\u0456"
    ],
    "name:und_x_variant":[
        "Ordyntsy"
    ],
    "wof:name":"Ordyntsi",
    "wof:placetype":"locality"
},
  "geometry": {"coordinates":[29.05507,49.4351],"type":"Point"}
}