{
  "type": "Feature",
  "properties": {
    "gn:admin1_code":"5.0",
    "gn:asciiname":"Maydan",
    "gn:country_code":"UA",
    "gn:dem":80,
    "gn:feature_class":"P",
    "gn:feature_code":"PPL",
    "gn:name":"Maydan",
    "gn:population":0,
    "gn:timezone":"Europe/Kiev",
    "iso:country":"UA",
    "name:ukr_x_preferred":[
        "Maydan"
    ],
    "name:ukr_x_variant":[
        "\u041c\u0430\u0439\u0434\u0430\u043d"
    ],
    "wof:name":"Maydan",
    "wof:placetype":"locality"
},
  "geometry": {"coordinates":[37.26832,48.84501],"type":"Point"}
}