{
  "type": "Feature",
  "properties": {
    "gn:admin1_code":"21.0",
    "gn:asciiname":"Mohrytsya",
    "gn:country_code":"UA",
    "gn:dem":139,
    "gn:feature_class":"P",
    "gn:feature_code":"PPL",
    "gn:name":"Mohrytsya",
    "gn:population":0,
    "gn:timezone":"Europe/Kiev",
    "iso:country":"UA",
    "name:eng_x_preferred":[
        "Mohrytsya"
    ],
    "name:rus_x_preferred":[
        "\u041c\u043e\u0433\u0440\u0438\u0446\u0430"
    ],
    "name:ukr_x_preferred":[
        "\u041c\u043e\u0433\u0440\u0438\u0446\u044f"
    ],
    "name:und_x_variant":[
        "Mogritsa",
        "Mohrytsya"
    ],
    "wof:name":"Mohrytsya",
    "wof:placetype":"locality"
},
  "geometry": {"coordinates":[35.11312,51.02912],"type":"Point"}
}