{
  "type": "Feature",
  "properties": {
    "gn:admin1_code":"18.0",
    "gn:asciiname":"Lomaky",
    "gn:country_code":"UA",
    "gn:dem":102,
    "gn:feature_class":"P",
    "gn:feature_code":"PPL",
    "gn:name":"Lomaky",
    "gn:population":0,
    "gn:timezone":"Europe/Kiev",
    "iso:country":"UA",
    "name:ukr_x_preferred":[
        "Lomaky"
    ],
    "name:ukr_x_variant":[
        "\u041b\u043e\u043c\u0430\u043a\u0438"
    ],
    "name:und_x_variant":[
        "Lomaki"
    ],
    "wof:name":"Lomaky",
    "wof:placetype":"locality"
},
  "geometry": {"coordinates":[33.29358,50.17449000000001],"type":"Point"}
}