{
  "type": "Feature",
  "properties": {
    "gn:admin1_code":"25.0",
    "gn:asciiname":"Pidhorb",
    "gn:country_code":"UA",
    "gn:dem":110,
    "gn:feature_class":"P",
    "gn:feature_code":"PPL",
    "gn:name":"Pidhorb",
    "gn:population":0,
    "gn:timezone":"Europe/Uzhgorod",
    "iso:country":"UA",
    "name:ukr_x_preferred":[
        "Pidhorb"
    ],
    "name:ukr_x_variant":[
        "\u041f\u0456\u0434\u0433\u043e\u0440\u0431"
    ],
    "name:und_x_variant":[
        "Podgorb"
    ],
    "wof:name":"Pidhorb",
    "wof:placetype":"locality"
},
  "geometry": {"coordinates":[22.36261,48.54883],"type":"Point"}
}