{
  "type": "Feature",
  "properties": {
    "gn:admin1_code":"24.0",
    "gn:asciiname":"Strumivka",
    "gn:country_code":"UA",
    "gn:dem":224,
    "gn:feature_class":"P",
    "gn:feature_code":"PPL",
    "gn:name":"Strumivka",
    "gn:population":0,
    "gn:timezone":"Europe/Kiev",
    "iso:country":"UA",
    "name:ukr_x_preferred":[
        "Strumivka"
    ],
    "name:ukr_x_variant":[
        "\u0421\u0442\u0440\u0443\u043c\u0456\u0432\u043a\u0430"
    ],
    "name:und_x_variant":[
        "Strumovka"
    ],
    "wof:name":"Strumivka",
    "wof:placetype":"locality"
},
  "geometry": {"coordinates":[25.43058,50.73767],"type":"Point"}
}