{
  "type": "Feature",
  "properties": {
    "gn:admin1_code":"6.0",
    "gn:asciiname":"Topil's'ke",
    "gn:country_code":"UA",
    "gn:dem":373,
    "gn:feature_class":"P",
    "gn:feature_code":"PPL",
    "gn:name":"Topil\u2019s\u2019ke",
    "gn:population":0,
    "gn:timezone":"Europe/Kiev",
    "iso:country":"UA",
    "name:ukr_x_preferred":[
        "Topil\u2019s\u2019ke"
    ],
    "name:ukr_x_variant":[
        "\u0422\u043e\u043f\u0456\u043b\u044c\u0441\u044c\u043a\u0435"
    ],
    "name:und_x_variant":[
        "Topol\u2019skoye",
        "Topol\u2019sko",
        "Topol\u2019ska"
    ],
    "wof:name":"Topil's'ke",
    "wof:placetype":"locality"
},
  "geometry": {"coordinates":[24.23317,48.92534000000001],"type":"Point"}
}