{
  "type": "Feature",
  "properties": {
    "gn:admin1_code":"21.0",
    "gn:asciiname":"Sydorivka",
    "gn:country_code":"UA",
    "gn:dem":164,
    "gn:feature_class":"P",
    "gn:feature_code":"PPL",
    "gn:name":"Sydorivka",
    "gn:population":0,
    "gn:timezone":"Europe/Kiev",
    "iso:country":"UA",
    "name:ukr_x_preferred":[
        "Sydorivka"
    ],
    "name:ukr_x_variant":[
        "\u0421\u0438\u0434\u043e\u0440\u0456\u0432\u043a\u0430"
    ],
    "name:und_x_variant":[
        "Sidorovka"
    ],
    "wof:name":"Sydorivka",
    "wof:placetype":"locality"
},
  "geometry": {"coordinates":[34.41954,51.72401],"type":"Point"}
}