{
  "type": "Feature",
  "properties": {
    "gn:admin1_code":"14.0",
    "gn:asciiname":"Manuylovka",
    "gn:country_code":"UA",
    "gn:dem":240,
    "gn:feature_class":"P",
    "gn:feature_code":"PPL",
    "gn:name":"Manuylovka",
    "gn:population":0,
    "gn:timezone":"Europe/Zaporozhye",
    "iso:country":"UA",
    "wof:name":"Manuylovka",
    "wof:placetype":"locality"
},
  "geometry": {"coordinates":[38.53361,48.39778],"type":"Point"}
}