{
  "type": "Feature",
  "properties": {
    "gn:admin1_code":"4.0",
    "gn:asciiname":"Blagodatnoye",
    "gn:country_code":"UA",
    "gn:dem":103,
    "gn:feature_class":"P",
    "gn:feature_code":"PPL",
    "gn:name":"Blagodatnoye",
    "gn:population":0,
    "gn:timezone":"Europe/Kiev",
    "iso:country":"UA",
    "wof:name":"Blagodatnoye",
    "wof:placetype":"locality"
},
  "geometry": {"coordinates":[35.98333,48.56667],"type":"Point"}
}