{
  "type": "Feature",
  "properties": {
    "gn:admin1_code":"18.0",
    "gn:asciiname":"Shchorsivka",
    "gn:country_code":"UA",
    "gn:dem":156,
    "gn:feature_class":"P",
    "gn:feature_code":"PPL",
    "gn:name":"Shchorsivka",
    "gn:population":0,
    "gn:timezone":"Europe/Kiev",
    "iso:country":"UA",
    "name:ukr_x_preferred":[
        "Shchorsivka"
    ],
    "name:ukr_x_variant":[
        "\u0429\u043e\u0440\u0441\u0456\u0432\u043a\u0430"
    ],
    "wof:name":"Shchorsivka",
    "wof:placetype":"locality"
},
  "geometry": {"coordinates":[34.94602,49.82869],"type":"Point"}
}