{
  "type": "Feature",
  "properties": {
    "gn:admin1_code":"4.0",
    "gn:asciiname":"Zaporiz'ke",
    "gn:country_code":"UA",
    "gn:dem":89,
    "gn:feature_class":"P",
    "gn:feature_code":"PPL",
    "gn:name":"Zaporiz\u2019ke",
    "gn:population":0,
    "gn:timezone":"Europe/Kiev",
    "iso:country":"UA",
    "name:ukr_x_preferred":[
        "Zaporiz\u2019ke"
    ],
    "name:ukr_x_variant":[
        "\u0417\u0430\u043f\u043e\u0440\u0456\u0437\u044c\u043a\u0435"
    ],
    "name:und_x_variant":[
        "Zaporozhets"
    ],
    "wof:name":"Zaporiz'ke",
    "wof:placetype":"locality"
},
  "geometry": {"coordinates":[33.80781,47.64323],"type":"Point"}
}