{
  "type": "Feature",
  "properties": {
    "gn:admin1_code":"2.0",
    "gn:asciiname":"Karatsyubyne",
    "gn:country_code":"UA",
    "gn:dem":124,
    "gn:feature_class":"P",
    "gn:feature_code":"PPL",
    "gn:name":"Karatsyubyne",
    "gn:population":0,
    "gn:timezone":"Europe/Kiev",
    "iso:country":"UA",
    "name:ukr_x_preferred":[
        "Karatsyubyne"
    ],
    "name:ukr_x_variant":[
        "\u041a\u0430\u0440\u0430\u0446\u044e\u0431\u0438\u043d\u0435"
    ],
    "name:und_x_variant":[
        "Karatsubin",
        "Karatsyubino"
    ],
    "wof:name":"Karatsyubyne",
    "wof:placetype":"locality"
},
  "geometry": {"coordinates":[32.99669,51.37091],"type":"Point"}
}