{
  "type": "Feature",
  "properties": {
    "iso:country":"UA",
    "name:eng_x_preferred":[
        "Bolekhivtsi"
    ],
    "name:pol_x_preferred":[
        "Bolechowice"
    ],
    "name:ron_x_preferred":[
        "Bolehiv\u021bi"
    ],
    "name:rus_x_preferred":[
        "\u0411\u043e\u043b\u0435\u0445\u043e\u0432\u0446\u044b"
    ],
    "name:ukr_x_preferred":[
        "\u0411\u043e\u043b\u0435\u0445\u0456\u0432\u0446\u0456"
    ],
    "name:unk_x_variant":[
        "Bolekhivtsi"
    ],
    "name:zho_x_preferred":[
        "\u535a\u5217\u5e0c\u592b\u9f4a"
    ],
    "qs:a0":"\u0423\u043a\u0440\u0430\u0457\u043d\u0430",
    "qs:a1":"*\u041b\u044c\u0432\u0456\u0432\u0441\u044c\u043a\u0430",
    "qs:a1_alt":"L'vivs'ka",
    "qs:a1r":"0",
    "qs:a2":"\u0414\u0440\u043e\u0433\u043e\u0431\u0438\u0446\u044c\u043a\u0438\u0439",
    "qs:a2_alt":"Drohobyts'kyi",
    "qs:adm0":"\u0423\u043a\u0440\u0430\u0457\u043d\u0430",
    "qs:la_lc":"*",
    "qs:level":"locality",
    "qs:loc":"\u0411\u043e\u043b\u0435\u0445\u0456\u0432\u0446\u0456",
    "qs:loc_alt":"Bolekhivtsi",
    "qs:pop":0,
    "qs:type":"buffered point",
    "wd:wordcount":49,
    "wof:name":"\u0411\u043e\u043b\u0435\u0445\u0456\u0432\u0446\u0456",
    "wof:placetype":"locality"
},
  "geometry": {"coordinates":[23.594926,49.329035],"type":"Point"}
}