{
  "type": "Feature",
  "properties": {
    "gn:admin1_code":"24.0",
    "gn:asciiname":"Bryshche",
    "gn:country_code":"UA",
    "gn:dem":190,
    "gn:feature_class":"P",
    "gn:feature_code":"PPL",
    "gn:name":"Bryshche",
    "gn:population":0,
    "gn:timezone":"Europe/Kiev",
    "iso:country":"UA",
    "name:ukr_x_preferred":[
        "Bryshche"
    ],
    "name:ukr_x_variant":[
        "\u0411\u0440\u0438\u0449\u0435"
    ],
    "name:und_x_variant":[
        "Brishche"
    ],
    "wof:name":"Bryshche",
    "wof:placetype":"locality"
},
  "geometry": {"coordinates":[25.21858,50.84524],"type":"Point"}
}