{
  "type": "Feature",
  "properties": {
    "gn:admin1_code":"9.0",
    "gn:asciiname":"Pashuky",
    "gn:country_code":"UA",
    "gn:dem":286,
    "gn:feature_class":"P",
    "gn:feature_code":"PPL",
    "gn:name":"Pashuky",
    "gn:population":0,
    "gn:timezone":"Europe/Kiev",
    "iso:country":"UA",
    "name:ukr_x_preferred":[
        "Pashuky"
    ],
    "name:ukr_x_variant":[
        "\u041f\u0430\u0448\u0443\u043a\u0438"
    ],
    "name:und_x_variant":[
        "Pashuki"
    ],
    "wof:name":"Pashuky",
    "wof:placetype":"locality"
},
  "geometry": {"coordinates":[27.06342,50.09336],"type":"Point"}
}