{
  "type": "Feature",
  "properties": {
    "gn:admin1_code":"9.0",
    "gn:asciiname":"Lomachintsy",
    "gn:country_code":"UA",
    "gn:dem":301,
    "gn:feature_class":"P",
    "gn:feature_code":"PPL",
    "gn:name":"Lomachintsy",
    "gn:population":0,
    "gn:timezone":"Europe/Kiev",
    "iso:country":"UA",
    "wof:name":"Lomachintsy",
    "wof:placetype":"locality"
},
  "geometry": {"coordinates":[27.31277,48.96381],"type":"Point"}
}