{
  "type": "Feature",
  "properties": {
    "gn:gn_country":"UA",
    "gn:gn_fcode":"PPL",
    "gn:gn_pop":12952,
    "gn:population":12952,
    "iso:country":"UA",
    "name:eng_x_preferred":[
        "Tarashcha"
    ],
    "name:rus_x_preferred":[
        "\u0422\u0430\u0440\u0430\u0449\u0430"
    ],
    "name:ukr_x_preferred":[
        "\u0422\u0430\u0440\u0430\u0449\u0430"
    ],
    "qs_pg:aaroncc":"UA",
    "qs_pg:gn_country":"UA",
    "qs_pg:gn_fcode":"PPL",
    "qs_pg:gn_pop":12952,
    "qs_pg:name":"Tarashcha",
    "qs_pg:photos_9r":0,
    "qs_pg:photos_sr":0,
    "qs_pg:pop_sr":6,
    "qs_pg:qs_pg_placetype":"locality",
    "wof:name":"Tarashcha",
    "wof:placetype":"locality",
    "wof:population":12952
},
  "geometry": {"coordinates":[30.49259,49.55832],"type":"Point"}
}