{
  "type": "Feature",
  "properties": {
    "gn:gn_country":"UA",
    "gn:gn_fcode":"PPL",
    "gn:gn_pop":12952,
    "gn:population":12952,
    "iso:country":"UA",
    "name:bel_x_preferred":[
        "\u0422\u0430\u0440\u0430\u0448\u0447\u0430"
    ],
    "name:ceb_x_preferred":[
        "Tarashcha"
    ],
    "name:crh_x_preferred":[
        "Tara\u015f\u00e7a"
    ],
    "name:deu_x_preferred":[
        "Taraschtscha"
    ],
    "name:eng_x_preferred":[
        "Tarashcha"
    ],
    "name:fas_x_preferred":[
        "\u062a\u0627\u0631\u0627\u0634\u0686\u0627"
    ],
    "name:fin_x_preferred":[
        "Tara\u0161t\u0161a"
    ],
    "name:fra_x_preferred":[
        "Tarachtcha"
    ],
    "name:heb_x_preferred":[
        "\u05d8\u05d0\u05e8\u05d0\u05e9\u05d4"
    ],
    "name:hsb_x_preferred":[
        "Tara\u0161\u0107a"
    ],
    "name:hye_x_preferred":[
        "\u054f\u0561\u0580\u0561\u0577\u0579\u0561"
    ],
    "name:ita_x_preferred":[
        "Tara\u0161\u010da"
    ],
    "name:kat_x_preferred":[
        "\u10e2\u10d0\u10e0\u10d0\u10e8\u10e9\u10d0"
    ],
    "name:nno_x_preferred":[
        "Tarasjtsja"
    ],
    "name:pol_x_preferred":[
        "Taraszcza"
    ],
    "name:ron_x_preferred":[
        "Tara\u0219cea"
    ],
    "name:rus_x_preferred":[
        "\u0422\u0430\u0440\u0430\u0449\u0430"
    ],
    "name:sah_x_preferred":[
        "\u0422\u0430\u0440\u0430\u0449\u0430"
    ],
    "name:spa_x_preferred":[
        "Tarashcha"
    ],
    "name:ukr_x_preferred":[
        "\u0422\u0430\u0440\u0430\u0449\u0430"
    ],
    "name:vie_x_preferred":[
        "Tarascha"
    ],
    "name:zho_x_preferred":[
        "\u5854\u62c9\u590f"
    ],
    "qs_pg:aaroncc":"UA",
    "qs_pg:gn_country":"UA",
    "qs_pg:gn_fcode":"PPL",
    "qs_pg:gn_pop":12952,
    "qs_pg:name":"Tarashcha",
    "qs_pg:photos_9r":0,
    "qs_pg:photos_sr":0,
    "qs_pg:pop_sr":6,
    "qs_pg:qs_pg_placetype":"locality",
    "wof:name":"Tarashcha",
    "wof:placetype":"locality",
    "wof:population":12952
},
  "geometry": {"coordinates":[30.49259,49.55832],"type":"Point"}
}