{
  "type": "Feature",
  "properties": {
    "gn:admin1_code":"7.0",
    "gn:asciiname":"Oril's'ke",
    "gn:country_code":"UA",
    "gn:dem":116,
    "gn:feature_class":"P",
    "gn:feature_code":"PPL",
    "gn:name":"Oril\u2019s\u2019ke",
    "gn:population":0,
    "gn:timezone":"Europe/Kiev",
    "iso:country":"UA",
    "name:ukr_x_preferred":[
        "Oril\u2019s\u2019ke"
    ],
    "name:ukr_x_variant":[
        "\u041e\u0440\u0456\u043b\u044c\u0441\u044c\u043a\u0435"
    ],
    "name:und_x_variant":[
        "Voroshilova"
    ],
    "wof:name":"Oril's'ke",
    "wof:placetype":"locality"
},
  "geometry": {"coordinates":[36.235,49.09167],"type":"Point"}
}