{
  "type": "Feature",
  "properties": {
    "gn:admin1_code":"14.0",
    "gn:asciiname":"Zhovte",
    "gn:country_code":"UA",
    "gn:dem":54,
    "gn:feature_class":"P",
    "gn:feature_code":"PPL",
    "gn:name":"Zhovte",
    "gn:population":0,
    "gn:timezone":"Europe/Zaporozhye",
    "iso:country":"UA",
    "name:rus_x_preferred":[
        "Zh\u00ebltoye"
    ],
    "name:ukr_x_preferred":[
        "Zhovte"
    ],
    "name:ukr_x_variant":[
        "\u0416\u043e\u0432\u0442\u0435"
    ],
    "wof:name":"Zhovte",
    "wof:placetype":"locality"
},
  "geometry": {"coordinates":[39.11194,48.64806],"type":"Point"}
}