{
  "type": "Feature",
  "properties": {
    "gn:admin1_code":"14.0",
    "gn:asciiname":"Varvarovka",
    "gn:country_code":"UA",
    "gn:dem":84,
    "gn:feature_class":"P",
    "gn:feature_code":"PPL",
    "gn:name":"Varvarovka",
    "gn:population":0,
    "gn:timezone":"Europe/Zaporozhye",
    "iso:country":"UA",
    "name:che_x_preferred":[
        "\u0412\u0430\u0440\u0432\u0430\u0440\u043e\u0432\u043a\u0430"
    ],
    "name:rus_x_preferred":[
        "\u0412\u0430\u0440\u0432\u0430\u0440\u043e\u0432\u043a\u0430"
    ],
    "wof:name":"Varvarovka",
    "wof:placetype":"locality"
},
  "geometry": {"coordinates":[39.63972,48.26028],"type":"Point"}
}