{
  "type": "Feature",
  "properties": {
    "gn:admin1_code":"18.0",
    "gn:asciiname":"Pashchenky",
    "gn:country_code":"UA",
    "gn:dem":124,
    "gn:feature_class":"P",
    "gn:feature_code":"PPL",
    "gn:name":"Pashchenky",
    "gn:population":0,
    "gn:timezone":"Europe/Kiev",
    "iso:country":"UA",
    "name:ukr_x_preferred":[
        "Pashchenky"
    ],
    "name:ukr_x_variant":[
        "\u041f\u0430\u0449\u0435\u043d\u043a\u0438"
    ],
    "name:und_x_variant":[
        "Pashchenki"
    ],
    "wof:name":"Pashchenky",
    "wof:placetype":"locality"
},
  "geometry": {"coordinates":[34.01843,49.42019000000001],"type":"Point"}
}