{
  "type": "Feature",
  "properties": {
    "gn:population":11300,
    "iso:country":"UA",
    "name:crh_x_preferred":[
        "Mosp\u0131ne"
    ],
    "name:deu_x_preferred":[
        "Mospyne"
    ],
    "name:eng_x_preferred":[
        "Mospyne"
    ],
    "name:fas_x_preferred":[
        "\u0645\u0648\u0633\u067e\u06cc\u0646\u0647"
    ],
    "name:fra_x_preferred":[
        "Mospyne"
    ],
    "name:hsb_x_preferred":[
        "Mospyne"
    ],
    "name:hye_x_preferred":[
        "\u0544\u0578\u057d\u057a\u056b\u0576\u0578"
    ],
    "name:ita_x_preferred":[
        "Mospyne"
    ],
    "name:kat_x_preferred":[
        "\u10db\u10dd\u10e1\u10de\u10d8\u10dc\u10dd"
    ],
    "name:lav_x_preferred":[
        "Mospine"
    ],
    "name:nno_x_preferred":[
        "Mospyne"
    ],
    "name:nob_x_preferred":[
        "Mospyne"
    ],
    "name:nor_x_preferred":[
        "Mospyne"
    ],
    "name:pol_x_preferred":[
        "Mospyne"
    ],
    "name:ron_x_preferred":[
        "Mosp\u00eene"
    ],
    "name:rus_x_preferred":[
        "\u041c\u043e\u0441\u043f\u0438\u043d\u043e"
    ],
    "name:rus_x_variant":[
        "\u041c\u043e\u0441\u043f\u0438\u043d\u0435"
    ],
    "name:sco_x_preferred":[
        "Mospyne"
    ],
    "name:tat_x_preferred":[
        "\u041c\u043e\u0441\u043f\u044b\u043d\u0435"
    ],
    "name:ukr_x_preferred":[
        "\u041c\u043e\u0441\u043f\u0438\u043d\u0435"
    ],
    "name:unk_x_variant":[
        "Mospino"
    ],
    "name:vie_x_preferred":[
        "Mospyne"
    ],
    "name:zho_x_preferred":[
        "\u83ab\u65af\u76ae\u8afe"
    ],
    "qs:a0":"\u0423\u043a\u0440\u0430\u0457\u043d\u0430",
    "qs:a1":"*\u0414\u043e\u043d\u0435\u0446\u044c\u043a\u0430",
    "qs:a1_alt":"Donets'ka",
    "qs:a1r":"0",
    "qs:a2":"\u0428\u0430\u0445\u0442\u0430\u0440\u0441\u044c\u043a\u0438\u0439",
    "qs:a2_alt":"Shakhtars'kyi",
    "qs:adm0":"\u0423\u043a\u0440\u0430\u0457\u043d\u0430",
    "qs:la_lc":"*",
    "qs:level":"locality",
    "qs:loc":"\u041c\u043e\u0441\u043f\u0438\u043d\u0435",
    "qs:loc_alt":"Mospyne",
    "qs:pop":0,
    "qs:type":"buffered point",
    "wd:wordcount":85,
    "wof:name":"\u041c\u043e\u0441\u043f\u0438\u043d\u0435",
    "wof:placetype":"locality",
    "wof:population":11300
},
  "geometry": {"coordinates":[38.072737,47.871516],"type":"Point"}
}