{
  "type": "Feature",
  "properties": {
    "gn:gn_country":"UA",
    "gn:gn_fcode":"PPL",
    "gn:gn_pop":553,
    "gn:population":553,
    "iso:country":"UA",
    "name:arm_x_preferred":[
        "\u054e\u056b\u057d\u0578\u056f\u0578\u0565"
    ],
    "name:eng_x_preferred":[
        "Vysoke"
    ],
    "name:ger_x_preferred":[
        "Wyssoke"
    ],
    "name:lav_x_preferred":[
        "Visoke"
    ],
    "name:rus_x_preferred":[
        "\u0412\u0438\u0441\u043e\u043a\u0435"
    ],
    "name:ukr_x_preferred":[
        "\u0412\u0438\u0441\u043e\u043a\u0435"
    ],
    "name:unk_x_variant":[
        "Vysokoye"
    ],
    "qs_pg:aaroncc":"UA",
    "qs_pg:gn_country":"UA",
    "qs_pg:gn_fcode":"PPL",
    "qs_pg:gn_pop":553,
    "qs_pg:name":"Vysoke",
    "qs_pg:photos_9r":0,
    "qs_pg:photos_sr":0,
    "qs_pg:pop_sr":2,
    "qs_pg:qs_pg_placetype":"locality",
    "wof:name":"Vysoke",
    "wof:placetype":"locality",
    "wof:population":553
},
  "geometry": {"coordinates":[38.05804,47.94407],"type":"Point"}
}