{
  "type": "Feature",
  "properties": {
    "gn:country":"UA",
    "gn:fcode":"PPL",
    "gn:population":553,
    "iso:country":"UA",
    "name:ceb_x_preferred":[
        "Vysoke"
    ],
    "name:che_x_preferred":[
        "\u0412\u044b\u0441\u043e\u043a\u0438"
    ],
    "name:crh_x_preferred":[
        "V\u0131soke"
    ],
    "name:deu_x_preferred":[
        "Wyssoke"
    ],
    "name:eng_x_preferred":[
        "Vysoke"
    ],
    "name:fra_x_preferred":[
        "Vyssoke"
    ],
    "name:hye_x_preferred":[
        "\u054e\u056b\u057d\u0578\u056f\u0578\u0565"
    ],
    "name:lav_x_preferred":[
        "Visoke"
    ],
    "name:rus_x_preferred":[
        "\u0412\u0438\u0441\u043e\u043a\u0435"
    ],
    "name:rus_x_variant":[
        "\u0412\u044b\u0441\u043e\u043a\u043e\u0435"
    ],
    "name:ukr_x_preferred":[
        "\u0412\u0438\u0441\u043e\u043a\u0435"
    ],
    "name:und_x_variant":[
        "Vysokoye"
    ],
    "name:zho_x_preferred":[
        "\u7dad\u7d22\u514b"
    ],
    "qs_pg:aaroncc":"UA",
    "qs_pg:gn_country":"UA",
    "qs_pg:gn_fcode":"PPL",
    "qs_pg:gn_pop":553,
    "qs_pg:name":"Vysoke",
    "qs_pg:photos_9r":0,
    "qs_pg:photos_sr":0,
    "qs_pg:pop_sr":2,
    "qs_pg:qs_pg_placetype":"locality",
    "wof:name":"Vysoke",
    "wof:placetype":"locality",
    "wof:population":553
},
  "geometry": {"coordinates":[38.05804,47.94407],"type":"Point"}
}