{
  "type": "Feature",
  "properties": {
    "gn:admin1_code":"4.0",
    "gn:asciiname":"Sadovoye",
    "gn:country_code":"UA",
    "gn:dem":104,
    "gn:feature_class":"P",
    "gn:feature_code":"PPL",
    "gn:name":"Sadovoye",
    "gn:population":0,
    "gn:timezone":"Europe/Kiev",
    "iso:country":"UA",
    "name:rus_x_preferred":[
        "\u0421\u0430\u0434\u043e\u0432\u043e\u0435"
    ],
    "wof:name":"Sadovoye",
    "wof:placetype":"locality"
},
  "geometry": {"coordinates":[33.39657,47.81596],"type":"Point"}
}