{
  "type": "Feature",
  "properties": {
    "gn:admin1_code":"2.0",
    "gn:asciiname":"Pershe Travnya",
    "gn:country_code":"UA",
    "gn:dem":126,
    "gn:feature_class":"P",
    "gn:feature_code":"PPL",
    "gn:name":"Pershe Travnya",
    "gn:population":0,
    "gn:timezone":"Europe/Kiev",
    "iso:country":"UA",
    "name:ukr_x_preferred":[
        "Pershe Travnya"
    ],
    "name:ukr_x_variant":[
        "\u041f\u0435\u0440\u0448\u0435 \u0422\u0440\u0430\u0432\u043d\u044f"
    ],
    "wof:name":"Pershe Travnya",
    "wof:placetype":"locality"
},
  "geometry": {"coordinates":[32.12523,50.63947],"type":"Point"}
}