{
  "type": "Feature",
  "properties": {
    "iso:country":"UA",
    "name:che_x_preferred":[
        "\u041e\u0440\u0435\u043b\u044c\u043a\u0430"
    ],
    "name:deu_x_preferred":[
        "Orilka"
    ],
    "name:eng_x_preferred":[
        "Orel'ka"
    ],
    "name:eng_x_variant":[
        "Orilka"
    ],
    "name:lav_x_preferred":[
        "Ori\u013cka"
    ],
    "name:nan_x_preferred":[
        "Orilka"
    ],
    "name:nno_x_preferred":[
        "Orilka"
    ],
    "name:nob_x_preferred":[
        "Orilka"
    ],
    "name:ron_x_preferred":[
        "Orilka"
    ],
    "name:rus_x_preferred":[
        "\u041e\u0440\u0435\u043b\u044c\u043a\u0430"
    ],
    "name:ukr_x_preferred":[
        "Oril\u2019ka"
    ],
    "name:ukr_x_variant":[
        "\u041e\u0440\u0456\u043b\u044c\u043a\u0430"
    ],
    "name:und_x_variant":[
        "Orel\u2019ka"
    ],
    "qs:a0":"\u0423\u043a\u0440\u0430\u0457\u043d\u0430",
    "qs:a1":"*\u0425\u0430\u0440\u043a\u0456\u0432\u0441\u044c\u043a\u0430",
    "qs:a1_alt":"Kharkivs'ka",
    "qs:a1r":"0",
    "qs:a2":"\u041b\u043e\u0437\u0456\u0432\u0441\u044c\u043a\u0438\u0439",
    "qs:a2_alt":"Lozivs'kyi",
    "qs:adm0":"\u0423\u043a\u0440\u0430\u0457\u043d\u0430",
    "qs:la_lc":"*",
    "qs:level":"locality",
    "qs:loc":"\u041e\u0440\u0456\u043b\u044c\u043a\u0430",
    "qs:loc_alt":"Oril'ka",
    "qs:pop":0,
    "qs:type":"buffered point",
    "wof:name":"\u041e\u0440\u0456\u043b\u044c\u043a\u0430",
    "wof:placetype":"locality"
},
  "geometry": {"coordinates":[36.01039,48.969133],"type":"Point"}
}