{
  "type": "Feature",
  "properties": {
    "gn:admin1_code":"27.0",
    "gn:asciiname":"Rudokopy",
    "gn:country_code":"UA",
    "gn:dem":212,
    "gn:feature_class":"P",
    "gn:feature_code":"PPL",
    "gn:name":"Rudokopy",
    "gn:population":0,
    "gn:timezone":"Europe/Kiev",
    "iso:country":"UA",
    "name:ukr_x_preferred":[
        "Rudokopy"
    ],
    "name:ukr_x_variant":[
        "\u0420\u0443\u0434\u043e\u043a\u043e\u043f\u0438"
    ],
    "wof:name":"Rudokopy",
    "wof:placetype":"locality"
},
  "geometry": {"coordinates":[28.03938,50.51023],"type":"Point"}
}