{
  "type": "Feature",
  "properties": {
    "gn:admin1_code":"14.0",
    "gn:asciiname":"Popasne",
    "gn:country_code":"UA",
    "gn:dem":176,
    "gn:feature_class":"P",
    "gn:feature_code":"PPL",
    "gn:name":"Popasne",
    "gn:population":0,
    "gn:timezone":"Europe/Zaporozhye",
    "iso:country":"UA",
    "name:ukr_x_preferred":[
        "Popasne"
    ],
    "name:und_x_variant":[
        "Popasnoye",
        "Popasnyy"
    ],
    "wof:name":"Popasne",
    "wof:placetype":"locality"
},
  "geometry": {"coordinates":[38.84003,49.00332],"type":"Point"}
}