{
  "type": "Feature",
  "properties": {
    "gn:admin1_code":"5.0",
    "gn:asciiname":"Roza",
    "gn:country_code":"UA",
    "gn:dem":68,
    "gn:feature_class":"P",
    "gn:feature_code":"PPL",
    "gn:name":"Roza",
    "gn:population":0,
    "gn:timezone":"Europe/Kiev",
    "iso:country":"UA",
    "name:ukr_x_preferred":[
        "Roza"
    ],
    "name:ukr_x_variant":[
        "\u0420\u043e\u0437\u0430"
    ],
    "name:und_x_variant":[
        "Tikhiy"
    ],
    "wof:name":"Roza",
    "wof:placetype":"locality"
},
  "geometry": {"coordinates":[38.00822,47.19619],"type":"Point"}
}