{
  "type": "Feature",
  "properties": {
    "gn:admin1_code":"17.0",
    "gn:asciiname":"Zverevo",
    "gn:country_code":"UA",
    "gn:dem":25,
    "gn:feature_class":"P",
    "gn:feature_code":"PPL",
    "gn:name":"Zverevo",
    "gn:population":0,
    "gn:timezone":"Europe/Kiev",
    "iso:country":"UA",
    "name:ara_x_preferred":[
        "\u0632\u0641\u064a\u0631\u064a\u0641\u0648"
    ],
    "name:aze_x_preferred":[
        "Zverevo"
    ],
    "name:bel_x_preferred":[
        "\u0417\u0432\u0435\u0440\u0430\u0432\u0430"
    ],
    "name:bul_x_preferred":[
        "\u0417\u0432\u0435\u0440\u0435\u0432\u043e"
    ],
    "name:ceb_x_preferred":[
        "Zverevo"
    ],
    "name:che_x_preferred":[
        "\u0417\u0432\u0435\u0440\u0435\u0432\u043e"
    ],
    "name:deu_x_preferred":[
        "Swerewo"
    ],
    "name:epo_x_preferred":[
        "Zverevo"
    ],
    "name:est_x_preferred":[
        "Zverevo"
    ],
    "name:fas_x_preferred":[
        "\u0632\u0648\u0631\u0648\u0641\u0648"
    ],
    "name:fin_x_preferred":[
        "Zverevo"
    ],
    "name:fra_x_preferred":[
        "Zverevo"
    ],
    "name:hsb_x_preferred":[
        "Zwjerjewo"
    ],
    "name:ita_x_preferred":[
        "Zverevo"
    ],
    "name:kat_x_preferred":[
        "\u10d6\u10d5\u10d4\u10e0\u10d4\u10d5\u10dd"
    ],
    "name:nno_x_preferred":[
        "Zverevo"
    ],
    "name:nor_x_preferred":[
        "Zverevo"
    ],
    "name:pol_x_preferred":[
        "Zwieriewo"
    ],
    "name:rus_x_preferred":[
        "\u0417\u0432\u0435\u0440\u0435\u0432\u043e"
    ],
    "name:spa_x_preferred":[
        "Zv\u00e9revo"
    ],
    "name:srp_x_preferred":[
        "\u0417\u0432\u0435\u0440\u0435\u0432\u043e"
    ],
    "name:tat_x_preferred":[
        "\u0417\u0432\u0435\u0440\u0435\u0432\u043e"
    ],
    "name:tgk_x_preferred":[
        "\u0417\u0432\u0435\u0440\u0435\u0432\u043e"
    ],
    "name:tgl_x_preferred":[
        "Zverevo"
    ],
    "name:tur_x_preferred":[
        "Zverevo"
    ],
    "name:ukr_x_preferred":[
        "\u0417\u0432\u0454\u0440\u0435\u0432\u043e"
    ],
    "name:und_x_variant":[
        "Veselyy Kut Vtoroy",
        "Vesely Kut Vtoroy",
        "Ves\u00eblyy Kut"
    ],
    "name:vie_x_preferred":[
        "Zverevo"
    ],
    "name:war_x_preferred":[
        "Zverevo"
    ],
    "name:xal_x_preferred":[
        "\u0417\u0432\u0435\u0440\u0435\u0432\u043e \u0431\u0430\u043b\u04bb\u0441\u043d"
    ],
    "name:zho_x_preferred":[
        "\u5179\u97e6\u5217\u6c83"
    ],
    "wof:name":"Zverevo",
    "wof:placetype":"locality"
},
  "geometry": {"coordinates":[30.55,47.41667],"type":"Point"}
}