{
  "type": "Feature",
  "properties": {
    "gn:admin1_code":"17.0",
    "gn:asciiname":"Zverevo",
    "gn:country_code":"UA",
    "gn:dem":25,
    "gn:feature_class":"P",
    "gn:feature_code":"PPL",
    "gn:name":"Zverevo",
    "gn:population":0,
    "gn:timezone":"Europe/Kiev",
    "iso:country":"UA",
    "name:und_x_variant":[
        "Veselyy Kut Vtoroy",
        "Vesely Kut Vtoroy",
        "Ves\u00eblyy Kut"
    ],
    "wof:name":"Zverevo",
    "wof:placetype":"locality"
},
  "geometry": {"coordinates":[30.55,47.41667],"type":"Point"}
}