{
  "type": "Feature",
  "properties": {
    "gn:admin1_code":"11.0",
    "gn:admin2_code":"704361",
    "gn:admin3_code":"11152949",
    "gn:asciiname":"Ilyinka",
    "gn:country_code":"UA",
    "gn:dem":10,
    "gn:elevation":"9.0",
    "gn:feature_class":"P",
    "gn:feature_code":"PPLA3",
    "gn:name":"Ilyinka",
    "gn:population":1140,
    "gn:timezone":"Europe/Simferopol",
    "iso:country":"UA",
    "name:eng_x_preferred":[
        "Ilyinka"
    ],
    "name:rus_x_historical":[
        "\u041d\u043e\u0301\u0432\u044b\u0439 \u0414\u0436\u0435\u043b\u0438\u0448\u0430\u0301\u0439",
        "\u0412\u0438\u043b\u043e\u0301\u0440"
    ],
    "name:rus_x_preferred":[
        "\u0418\u043b\u044c\u0438\u043d\u043a\u0430"
    ],
    "name:rus_x_variant":[
        "\u041d\u043e\u0301\u0432\u044b\u0439 \u0414\u0436\u0435\u043b\u0438\u0448\u0430\u0301\u0439",
        "\u0412\u0438\u043b\u043e\u0301\u0440"
    ],
    "name:ukr_x_preferred":[
        "\u0406\u043b\u043b\u0456\u043d\u043a\u0430"
    ],
    "wof:name":"Ilyinka",
    "wof:placetype":"locality",
    "wof:population":1140
},
  "geometry": {"coordinates":[33.79482,45.81784],"type":"Point"}
}