{
  "type": "Feature",
  "properties": {
    "gn:admin1_code":"11.0",
    "gn:admin2_code":"700018",
    "gn:admin3_code":"11152975.0",
    "gn:asciiname":"Korennoye",
    "gn:country_code":"UA",
    "gn:dem":31,
    "gn:elevation":"34.0",
    "gn:feature_class":"P",
    "gn:feature_code":"PPL",
    "gn:name":"Korennoye",
    "gn:population":350,
    "gn:timezone":"Europe/Simferopol",
    "iso:country":"UA",
    "name:eng_x_preferred":[
        "Korennoye"
    ],
    "name:rus_x_historical":[
        "\u041d\u043e\u0301\u0432\u043e-\u0427\u0435\u043c\u0431\u0430\u0301\u0439"
    ],
    "name:rus_x_preferred":[
        "\u041a\u043e\u0440\u0435\u043d\u043d\u043e\u0435"
    ],
    "name:rus_x_variant":[
        "\u041d\u043e\u0301\u0432\u043e-\u0427\u0435\u043c\u0431\u0430\u0301\u0439"
    ],
    "name:ukr_x_preferred":[
        "\u041a\u043e\u0440\u0456\u043d\u043d\u0435"
    ],
    "wof:name":"Korennoye",
    "wof:placetype":"locality",
    "wof:population":350
},
  "geometry": {"coordinates":[34.54534,45.43972],"type":"Point"}
}