{
  "type": "Feature",
  "properties": {
    "gn:admin1_code":"27.0",
    "gn:asciiname":"Vorsivka",
    "gn:country_code":"UA",
    "gn:dem":149,
    "gn:feature_class":"P",
    "gn:feature_code":"PPL",
    "gn:name":"Vorsivka",
    "gn:population":0,
    "gn:timezone":"Europe/Kiev",
    "iso:country":"UA",
    "name:ukr_x_preferred":[
        "\u0412\u043e\u0440\u0441\u0456\u0432\u043a\u0430"
    ],
    "name:und_x_variant":[
        "Borsovka",
        "Yorsovka",
        "Vorsivka",
        "Vorsovka"
    ],
    "wof:name":"Vorsivka",
    "wof:placetype":"locality"
},
  "geometry": {"coordinates":[29.24926,50.69456],"type":"Point"}
}