{
  "type": "Feature",
  "properties": {
    "gn:admin1_code":"7.0",
    "gn:asciiname":"Ordivka",
    "gn:country_code":"UA",
    "gn:dem":151,
    "gn:feature_class":"P",
    "gn:feature_code":"PPL",
    "gn:name":"Ordivka",
    "gn:population":0,
    "gn:timezone":"Europe/Kiev",
    "iso:country":"UA",
    "name:ukr_x_preferred":[
        "\u041e\u0440\u0434\u0456\u0432\u043a\u0430"
    ],
    "name:und_x_variant":[
        "Khutor Ordivka",
        "Ordyn",
        "Ordivka",
        "Ordovka"
    ],
    "wof:name":"Ordivka",
    "wof:placetype":"locality"
},
  "geometry": {"coordinates":[35.94837000000001,49.69759000000001],"type":"Point"}
}