{
  "type": "Feature",
  "properties": {
    "gn:admin1_code":"20.0",
    "gn:admin2_code":"712927",
    "gn:admin3_code":"11153387.0",
    "gn:asciiname":"Peredovoye",
    "gn:country_code":"UA",
    "gn:dem":333,
    "gn:elevation":"332.0",
    "gn:feature_class":"P",
    "gn:feature_code":"PPL",
    "gn:name":"Peredovoye",
    "gn:population":643,
    "gn:timezone":"Europe/Simferopol",
    "iso:country":"UA",
    "name:che_x_preferred":[
        "\u041f\u0435\u0440\u0435\u0434\u043e\u0432\u0438"
    ],
    "name:eng_x_preferred":[
        "Peredovoye"
    ],
    "name:rus_x_historical":[
        "\u0423\u0440\u043a\u0443\u0441\u0442\u0430\u0301"
    ],
    "name:rus_x_preferred":[
        "\u041f\u0435\u0440\u0435\u0434\u043e\u0432\u043e\u0435"
    ],
    "name:rus_x_variant":[
        "\u0423\u0440\u043a\u0443\u0441\u0442\u0430\u0301"
    ],
    "name:tgk_x_preferred":[
        "\u041f\u0435\u0440\u0435\u0434\u043e\u0432\u043e\u0435"
    ],
    "name:ukr_x_preferred":[
        "\u041f\u0435\u0440\u0435\u0434\u043e\u0432\u0435"
    ],
    "wof:name":"Peredovoye",
    "wof:placetype":"locality",
    "wof:population":643
},
  "geometry": {"coordinates":[33.82902,44.5094],"type":"Point"}
}