{
  "type": "Feature",
  "properties": {
    "gn:population":2605,
    "iso:country":"UA",
    "name:crh_x_preferred":[
        "Korn\u0131n"
    ],
    "name:deu_x_preferred":[
        "Kornyn"
    ],
    "name:eng_x_preferred":[
        "Kornyn"
    ],
    "name:fra_x_preferred":[
        "Kornyn"
    ],
    "name:hye_x_preferred":[
        "\u053f\u0578\u0580\u0576\u056b\u0576"
    ],
    "name:nld_x_preferred":[
        "Kornyn"
    ],
    "name:pol_x_preferred":[
        "Kornyn"
    ],
    "name:ron_x_preferred":[
        "Korn\u00een"
    ],
    "name:rus_x_preferred":[
        "\u041a\u043e\u0440\u043d\u0438\u043d"
    ],
    "name:sah_x_preferred":[
        "\u041a\u043e\u0440\u043d\u0438\u043d"
    ],
    "name:ukr_x_preferred":[
        "\u041a\u043e\u0440\u043d\u0438\u043d"
    ],
    "name:unk_x_variant":[
        "Kornin"
    ],
    "name:zho_x_preferred":[
        "\u79d1\u723e\u5be7"
    ],
    "qs:a0":"\u0423\u043a\u0440\u0430\u0457\u043d\u0430",
    "qs:a1":"*\u0416\u0438\u0442\u043e\u043c\u0438\u0440\u0441\u044c\u043a\u0430",
    "qs:a1_alt":"Zhytomyrs'ka",
    "qs:a1r":"0",
    "qs:a2":"\u041f\u043e\u043f\u0456\u043b\u044c\u043d\u044f\u043d\u0441\u044c\u043a\u0438\u0439",
    "qs:a2_alt":"Popil'nians'kyi",
    "qs:adm0":"\u0423\u043a\u0440\u0430\u0457\u043d\u0430",
    "qs:la_lc":"*",
    "qs:level":"locality",
    "qs:loc":"\u041a\u043e\u0440\u043d\u0438\u043d",
    "qs:loc_alt":"Kornyn",
    "qs:pop":0,
    "qs:type":"buffered point",
    "wd:wordcount":61,
    "wof:name":"\u041a\u043e\u0440\u043d\u0438\u043d",
    "wof:placetype":"locality",
    "wof:population":2605
},
  "geometry": {"coordinates":[29.52544,50.075914],"type":"Point"}
}