{
  "type": "Feature",
  "properties": {
    "gn:admin1_code":"10.0",
    "gn:asciiname":"Fedorovka",
    "gn:country_code":"UA",
    "gn:dem":168,
    "gn:feature_class":"P",
    "gn:feature_code":"PPL",
    "gn:name":"F\u00ebdorovka",
    "gn:population":0,
    "gn:timezone":"Europe/Kiev",
    "iso:country":"UA",
    "name:eng_x_preferred":[
        "F\u00ebdorovka"
    ],
    "name:rus_x_preferred":[
        "\u0424\u0435\u0434\u043e\u0440\u043e\u0432\u043a\u0430"
    ],
    "name:und_x_variant":[
        "Fedorowka",
        "F\u00ebdorovka"
    ],
    "wof:name":"Fedorovka",
    "wof:placetype":"locality"
},
  "geometry": {"coordinates":[32.16321,48.38573],"type":"Point"}
}