{
  "type": "Feature",
  "properties": {
    "iso:country":"UA",
    "name:deu_x_preferred":[
        "Velyka Hlusha"
    ],
    "name:eng_x_preferred":[
        "Velyka Hlusha"
    ],
    "name:heb_x_preferred":[
        "\u05d2\u05dc\u05d5\u05e9\u05d4"
    ],
    "name:hye_x_preferred":[
        "\u054e\u0565\u056c\u056b\u056f\u0561\u0575\u0561 \u0533\u056c\u0578\u0582\u0577\u0561"
    ],
    "name:pol_x_preferred":[
        "Wielka G\u0142usza"
    ],
    "name:ron_x_preferred":[
        "Vel\u00eeka Hlu\u0219a"
    ],
    "name:rus_x_preferred":[
        "\u0412\u0435\u043b\u0438\u043a\u0430\u044f \u0413\u043b\u0443\u0448\u0430"
    ],
    "name:ukr_x_preferred":[
        "Velyka Hlusha"
    ],
    "name:ukr_x_variant":[
        "\u0412\u0435\u043b\u0438\u043a\u0430 \u0413\u043b\u0443\u0448\u0430"
    ],
    "name:unk_x_variant":[
        "Bol\u2019shaya Glusha"
    ],
    "name:zho_x_preferred":[
        "\u5927\u683c\u76e7\u6c99"
    ],
    "qs:a0":"\u0423\u043a\u0440\u0430\u0457\u043d\u0430",
    "qs:a1":"*\u0412\u043e\u043b\u0438\u043d\u0441\u044c\u043a\u0430",
    "qs:a1_alt":"Volyns'ka",
    "qs:a1r":"0",
    "qs:a2":"\u041b\u044e\u0431\u0435\u0448\u0456\u0432\u0441\u044c\u043a\u0438\u0439",
    "qs:a2_alt":"Liubeshivs'kyi",
    "qs:adm0":"\u0423\u043a\u0440\u0430\u0457\u043d\u0430",
    "qs:la_lc":"*",
    "qs:level":"locality",
    "qs:loc":"\u0412\u0435\u043b\u0438\u043a\u0430 \u0413\u043b\u0443\u0448\u0430",
    "qs:loc_alt":"Velyka Hlusha",
    "qs:pop":0,
    "qs:type":"buffered point",
    "wof:name":"\u0412\u0435\u043b\u0438\u043a\u0430 \u0413\u043b\u0443\u0448\u0430",
    "wof:placetype":"locality"
},
  "geometry": {"coordinates":[25.035384,51.819014],"type":"Point"}
}