{
  "type": "Feature",
  "properties": {
    "gn:admin1_code":"7.0",
    "gn:asciiname":"Volodymyrivka",
    "gn:country_code":"UA",
    "gn:dem":143,
    "gn:feature_class":"P",
    "gn:feature_code":"PPL",
    "gn:name":"Volodymyrivka",
    "gn:population":0,
    "gn:timezone":"Europe/Kiev",
    "iso:country":"UA",
    "name:spa_x_preferred":[
        "Volodymyrivka"
    ],
    "name:ukr_x_preferred":[
        "Volodymyrivka"
    ],
    "name:ukr_x_variant":[
        "\u0412\u043e\u043b\u043e\u0434\u0438\u043c\u0438\u0440\u0456\u0432\u043a\u0430"
    ],
    "name:und_x_variant":[
        "Petrovka"
    ],
    "wof:name":"Volodymyrivka",
    "wof:placetype":"locality"
},
  "geometry": {"coordinates":[37.32208,49.84114],"type":"Point"}
}