{
  "type": "Feature",
  "properties": {
    "gn:admin1_code":"7.0",
    "gn:asciiname":"Morokhovets'",
    "gn:country_code":"UA",
    "gn:dem":184,
    "gn:feature_class":"P",
    "gn:feature_code":"PPL",
    "gn:name":"Morokhovets\u2019",
    "gn:population":0,
    "gn:timezone":"Europe/Kiev",
    "iso:country":"UA",
    "name:ukr_x_preferred":[
        "\u041c\u043e\u0440\u043e\u0445\u043e\u0432\u0435\u0446\u044c"
    ],
    "name:und_x_variant":[
        "Morokhovets",
        "Morokhovets\u2019"
    ],
    "wof:name":"Morokhovets'",
    "wof:placetype":"locality"
},
  "geometry": {"coordinates":[36.46987,50.27268],"type":"Point"}
}