{
  "type": "Feature",
  "properties": {
    "gn:admin1_code":"14.0",
    "gn:asciiname":"Zymivnyky",
    "gn:country_code":"UA",
    "gn:dem":249,
    "gn:feature_class":"P",
    "gn:feature_code":"PPL",
    "gn:name":"Zymivnyky",
    "gn:population":0,
    "gn:timezone":"Europe/Zaporozhye",
    "iso:country":"UA",
    "name:ukr_x_preferred":[
        "Zymivnyky"
    ],
    "name:ukr_x_variant":[
        "\u0417\u0438\u043c\u0456\u0432\u043d\u0438\u043a\u0438"
    ],
    "name:und_x_variant":[
        "Zymovniki"
    ],
    "wof:name":"Zymivnyky",
    "wof:placetype":"locality"
},
  "geometry": {"coordinates":[39.81698,48.10033],"type":"Point"}
}