{
  "type": "Feature",
  "properties": {
    "gn:admin1_code":"9.0",
    "gn:asciiname":"Marnyanovka",
    "gn:country_code":"UA",
    "gn:dem":287,
    "gn:feature_class":"P",
    "gn:feature_code":"PPL",
    "gn:name":"Marnyanovka",
    "gn:population":0,
    "gn:timezone":"Europe/Kiev",
    "iso:country":"UA",
    "name:und_x_variant":[
        "Marjan\u00f3wka",
        "Marnyanovka",
        "Mar\u2019yanovka"
    ],
    "wof:name":"Marnyanovka",
    "wof:placetype":"locality"
},
  "geometry": {"coordinates":[26.26445,48.85882],"type":"Point"}
}