{
  "type": "Feature",
  "properties": {
    "gn:admin1_code":"27.0",
    "gn:asciiname":"Stari Novaky",
    "gn:country_code":"UA",
    "gn:dem":180,
    "gn:feature_class":"P",
    "gn:feature_code":"PPL",
    "gn:name":"Stari Novaky",
    "gn:population":0,
    "gn:timezone":"Europe/Kiev",
    "iso:country":"UA",
    "name:ukr_x_preferred":[
        "Stari Novaky"
    ],
    "name:ukr_x_variant":[
        "\u0421\u0442\u0430\u0440\u0456 \u041d\u043e\u0432\u0430\u043a\u0438"
    ],
    "name:und_x_variant":[
        "Staryye Novaki"
    ],
    "wof:name":"Stari Novaky",
    "wof:placetype":"locality"
},
  "geometry": {"coordinates":[28.23105,51.10433],"type":"Point"}
}