{
  "type": "Feature",
  "properties": {
    "gn:admin1_code":"24.0",
    "gn:asciiname":"Serkiziv",
    "gn:country_code":"UA",
    "gn:dem":200,
    "gn:feature_class":"P",
    "gn:feature_code":"PPL",
    "gn:name":"Serkiziv",
    "gn:population":0,
    "gn:timezone":"Europe/Kiev",
    "iso:country":"UA",
    "name:ukr_x_preferred":[
        "Serkiziv"
    ],
    "name:ukr_x_variant":[
        "\u0421\u0435\u0440\u043a\u0456\u0437\u0456\u0432"
    ],
    "name:und_x_variant":[
        "Serkizow",
        "Serkizuv",
        "Serkizov"
    ],
    "wof:name":"Serkiziv",
    "wof:placetype":"locality"
},
  "geometry": {"coordinates":[24.72009,50.93888],"type":"Point"}
}