{
  "type": "Feature",
  "properties": {
    "gn:admin1_code":"21.0",
    "gn:asciiname":"Zaruddya",
    "gn:country_code":"UA",
    "gn:dem":161,
    "gn:feature_class":"P",
    "gn:feature_code":"PPL",
    "gn:name":"Zaruddya",
    "gn:population":0,
    "gn:timezone":"Europe/Kiev",
    "iso:country":"UA",
    "name:rus_x_preferred":[
        "Zarud\u2019ye"
    ],
    "name:ukr_x_preferred":[
        "Zaruddya"
    ],
    "name:ukr_x_variant":[
        "\u0417\u0430\u0440\u0443\u0434\u0434\u044f"
    ],
    "wof:name":"Zaruddya",
    "wof:placetype":"locality"
},
  "geometry": {"coordinates":[33.74362,50.71169],"type":"Point"}
}