{
  "type": "Feature",
  "properties": {
    "gn:admin1_code":"4.0",
    "gn:asciiname":"Hrushivka",
    "gn:country_code":"UA",
    "gn:dem":75,
    "gn:feature_class":"P",
    "gn:feature_code":"PPL",
    "gn:name":"Hrushivka",
    "gn:population":0,
    "gn:timezone":"Europe/Kiev",
    "iso:country":"UA",
    "name:ukr_x_preferred":[
        "Hrushivka"
    ],
    "name:ukr_x_variant":[
        "\u0413\u0440\u0443\u0448\u0456\u0432\u043a\u0430"
    ],
    "name:und_x_variant":[
        "Grushevka"
    ],
    "wof:name":"Hrushivka",
    "wof:placetype":"locality"
},
  "geometry": {"coordinates":[34.58927,48.28949],"type":"Point"}
}