{
  "type": "Feature",
  "properties": {
    "iso:country":"UA",
    "name:unk_x_variant":[
        "Denekhivka"
    ],
    "qs:a0":"\u0423\u043a\u0440\u0430\u0457\u043d\u0430",
    "qs:a1":"*\u041a\u0438\u0457\u0432\u0441\u044c\u043a\u0430",
    "qs:a1_alt":"Kyivs'ka",
    "qs:a1r":"0",
    "qs:a2":"\u0422\u0435\u0442\u0456\u0457\u0432\u0441\u044c\u043a\u0438\u0439",
    "qs:a2_alt":"Tetiivs'kyi",
    "qs:adm0":"\u0423\u043a\u0440\u0430\u0457\u043d\u0430",
    "qs:la_lc":"*",
    "qs:level":"locality",
    "qs:loc":"\u0414\u0435\u043d\u0438\u0445\u0456\u0432\u043a\u0430",
    "qs:loc_alt":"Denykhivka",
    "qs:pop":0,
    "qs:type":"buffered point",
    "wof:name":"\u0414\u0435\u043d\u0438\u0445\u0456\u0432\u043a\u0430",
    "wof:placetype":"locality"
},
  "geometry": {"coordinates":[29.799129,49.296106],"type":"Point"}
}