{
  "type": "Feature",
  "properties": {
    "gn:admin1_code":"2.0",
    "gn:asciiname":"Kuz'minskiy",
    "gn:country_code":"UA",
    "gn:dem":173,
    "gn:feature_class":"P",
    "gn:feature_code":"PPL",
    "gn:name":"Kuz\u2019minskiy",
    "gn:population":0,
    "gn:timezone":"Europe/Kiev",
    "iso:country":"UA",
    "name:ukr_x_preferred":[
        "Kuz\u2019myns\u2019ke"
    ],
    "name:ukr_x_variant":[
        "Kuz\u2019minskoye"
    ],
    "name:und_x_variant":[
        "Kuz\u2019minskoye",
        "Kuz\u2019minskiy"
    ],
    "wof:name":"Kuz'minskiy",
    "wof:placetype":"locality"
},
  "geometry": {"coordinates":[33.02139,52.09219],"type":"Point"}
}