{
  "type": "Feature",
  "properties": {
    "gn:admin1_code":"23.0",
    "gn:asciiname":"Borisovka",
    "gn:country_code":"UA",
    "gn:dem":222,
    "gn:feature_class":"P",
    "gn:feature_code":"PPL",
    "gn:name":"Borisovka",
    "gn:population":0,
    "gn:timezone":"Europe/Kiev",
    "iso:country":"UA",
    "name:lav_x_preferred":[
        "Borisovka"
    ],
    "wof:name":"Borisovka",
    "wof:placetype":"locality"
},
  "geometry": {"coordinates":[29.19009,49.07001],"type":"Point"}
}