{
  "type": "Feature",
  "properties": {
    "gn:admin1_code":"2.0",
    "gn:asciiname":"Oleshnya",
    "gn:country_code":"UA",
    "gn:dem":145,
    "gn:feature_class":"P",
    "gn:feature_code":"PPL",
    "gn:name":"Oleshnya",
    "gn:population":0,
    "gn:timezone":"Europe/Kiev",
    "iso:country":"UA",
    "name:ukr_x_preferred":[
        "Oleshnya"
    ],
    "name:ukr_x_variant":[
        "\u041e\u043b\u0435\u0448\u043d\u044f"
    ],
    "wof:name":"Oleshnya",
    "wof:placetype":"locality"
},
  "geometry": {"coordinates":[32.52982,51.8596],"type":"Point"}
}