{
  "type": "Feature",
  "properties": {
    "gn:country":"UA",
    "gn:fcode":"PPL",
    "gn:population":3853,
    "iso:country":"UA",
    "name:ceb_x_preferred":[
        "Nove Davydkovo"
    ],
    "name:deu_x_preferred":[
        "Nowe Dawydkowo"
    ],
    "name:eng_x_preferred":[
        "Nove Davydkovo"
    ],
    "name:epo_x_preferred":[
        "Nove Davidkovo"
    ],
    "name:hun_x_preferred":[
        "\u00dajd\u00e1vidh\u00e1za"
    ],
    "name:hye_x_preferred":[
        "\u0546\u0578\u057e\u0578\u0565 \u0534\u0561\u057e\u056b\u0564\u056f\u0578\u057e\u0578"
    ],
    "name:nld_x_preferred":[
        "Nove Davydkovo"
    ],
    "name:pol_x_preferred":[
        "Nowe Dawydkowo"
    ],
    "name:ron_x_preferred":[
        "Nove Dav\u00eedkovo"
    ],
    "name:rue_x_preferred":[
        "\u041d\u043e\u0432\u0435 \u0414\u0430\u0432\u044b\u0434\u043a\u043e\u0432\u043e"
    ],
    "name:rus_x_preferred":[
        "\u041d\u043e\u0432\u0435 \u0414\u0430\u0432\u0438\u0434\u043a\u043e\u0432\u043e"
    ],
    "name:rus_x_variant":[
        "\u041d\u043e\u0432\u043e\u0435 \u0414\u0430\u0432\u044b\u0434\u043a\u043e\u0432\u043e"
    ],
    "name:ukr_x_preferred":[
        "\u041d\u043e\u0432\u0435 \u0414\u0430\u0432\u0438\u0434\u043a\u043e\u0432\u043e"
    ],
    "name:und_x_variant":[
        "Nove Davydkove"
    ],
    "name:zho_x_preferred":[
        "\u65b0\u9054\u7dad\u5fb7\u79d1\u6c83"
    ],
    "qs_pg:aaroncc":"UA",
    "qs_pg:gn_country":"UA",
    "qs_pg:gn_fcode":"PPL",
    "qs_pg:gn_pop":3853,
    "qs_pg:name":"Nove Davydkovo",
    "qs_pg:photos_9r":0,
    "qs_pg:photos_sr":0,
    "qs_pg:pop_sr":4,
    "qs_pg:qs_pg_placetype":"locality",
    "wof:name":"Nove Davydkovo",
    "wof:placetype":"locality",
    "wof:population":3853
},
  "geometry": {"coordinates":[22.62164,48.44133],"type":"Point"}
}