{
  "type": "Feature",
  "properties": {
    "gn:admin1_code":"24.0",
    "gn:asciiname":"Lapni",
    "gn:country_code":"UA",
    "gn:dem":161,
    "gn:feature_class":"P",
    "gn:feature_code":"PPL",
    "gn:name":"Lapni",
    "gn:population":0,
    "gn:timezone":"Europe/Kiev",
    "iso:country":"UA",
    "name:ukr_x_preferred":[
        "Lapni"
    ],
    "name:ukr_x_variant":[
        "\u041b\u0430\u043f\u043d\u0456"
    ],
    "wof:name":"Lapni",
    "wof:placetype":"locality"
},
  "geometry": {"coordinates":[24.80652000000001,51.38166],"type":"Point"}
}