{
  "type": "Feature",
  "properties": {
    "gn:admin1_code":"14.0",
    "gn:asciiname":"Yamy",
    "gn:country_code":"UA",
    "gn:dem":151,
    "gn:feature_class":"P",
    "gn:feature_code":"PPL",
    "gn:name":"Yamy",
    "gn:population":0,
    "gn:timezone":"Europe/Zaporozhye",
    "iso:country":"UA",
    "name:ind_x_preferred":[
        "Yamy"
    ],
    "name:ukr_x_preferred":[
        "\u042f\u043c\u0438"
    ],
    "name:und_x_variant":[
        "Yamnyy",
        "Yamy"
    ],
    "name:zho_x_preferred":[
        "Yamy"
    ],
    "wof:name":"Yamy",
    "wof:placetype":"locality"
},
  "geometry": {"coordinates":[38.37218,49.76156],"type":"Point"}
}