{
  "type": "Feature",
  "properties": {
    "gn:admin1_code":"15.0",
    "gn:asciiname":"Yaremkuv",
    "gn:country_code":"UA",
    "gn:dem":273,
    "gn:feature_class":"P",
    "gn:feature_code":"PPL",
    "gn:name":"Yaremkuv",
    "gn:population":0,
    "gn:timezone":"Europe/Kiev",
    "iso:country":"UA",
    "name:und_x_variant":[
        "Yaremkov",
        "Yaremkuv"
    ],
    "wof:name":"Yaremkuv",
    "wof:placetype":"locality"
},
  "geometry": {"coordinates":[23.46007,49.67586],"type":"Point"}
}