{
  "type": "Feature",
  "properties": {
    "gn:admin1_code":"5.0",
    "gn:asciiname":"Yantarne",
    "gn:country_code":"UA",
    "gn:dem":125,
    "gn:feature_class":"P",
    "gn:feature_code":"PPL",
    "gn:name":"Yantarne",
    "gn:population":0,
    "gn:timezone":"Europe/Kiev",
    "iso:country":"UA",
    "name:ukr_x_preferred":[
        "Yantarne"
    ],
    "name:ukr_x_variant":[
        "\u042f\u043d\u0442\u0430\u0440\u043d\u0435"
    ],
    "name:und_x_variant":[
        "Yantarnoye"
    ],
    "wof:name":"Yantarne",
    "wof:placetype":"locality"
},
  "geometry": {"coordinates":[37.16222,47.94049],"type":"Point"}
}