{
  "type": "Feature",
  "properties": {
    "gn:admin1_code":"17.0",
    "gn:asciiname":"Bakalovo",
    "gn:country_code":"UA",
    "gn:dem":112,
    "gn:feature_class":"P",
    "gn:feature_code":"PPL",
    "gn:name":"Bakalovo",
    "gn:population":0,
    "gn:timezone":"Europe/Kiev",
    "iso:country":"UA",
    "name:ron_x_preferred":[
        "Bakalova"
    ],
    "name:rus_x_preferred":[
        "Bakalovo"
    ],
    "wof:name":"Bakalovo",
    "wof:placetype":"locality"
},
  "geometry": {"coordinates":[30.11524,46.882],"type":"Point"}
}