{
  "type": "Feature",
  "properties": {
    "gn:admin1_code":"9.0",
    "gn:asciiname":"Lapkivtsi",
    "gn:country_code":"UA",
    "gn:dem":313,
    "gn:feature_class":"P",
    "gn:feature_code":"PPL",
    "gn:name":"Lapkivtsi",
    "gn:population":0,
    "gn:timezone":"Europe/Kiev",
    "iso:country":"UA",
    "name:und_x_variant":[
        "Lapkovtsy",
        "Lapkivtsi"
    ],
    "wof:name":"Lapkivtsi",
    "wof:placetype":"locality"
},
  "geometry": {"coordinates":[26.68727,49.44454],"type":"Point"}
}