{
  "type": "Feature",
  "properties": {
    "gn:admin1_code":"4.0",
    "gn:asciiname":"Stepnaya",
    "gn:cc2":"UA",
    "gn:country_code":"UA",
    "gn:dem":59,
    "gn:feature_class":"P",
    "gn:feature_code":"PPL",
    "gn:name":"Stepnaya",
    "gn:population":0,
    "gn:timezone":"Europe/Kiev",
    "iso:country":"UA",
    "name:und_x_variant":[
        "Sadkin",
        "Stepnaya"
    ],
    "wof:name":"Stepnaya",
    "wof:placetype":"locality"
},
  "geometry": {"coordinates":[35.16667,48.28333],"type":"Point"}
}