{
  "type": "Feature",
  "properties": {
    "gn:admin1_code":"11.0",
    "gn:admin2_code":"712585",
    "gn:admin3_code":"11152827",
    "gn:asciiname":"Russkoye",
    "gn:country_code":"UA",
    "gn:dem":337,
    "gn:elevation":"344.0",
    "gn:feature_class":"P",
    "gn:feature_code":"PPL",
    "gn:name":"Russkoye",
    "gn:population":173,
    "gn:timezone":"Europe/Simferopol",
    "iso:country":"UA",
    "name:eng_x_preferred":[
        "Russkoye"
    ],
    "name:rus_x_historical":[
        "\u0423\u0440\u0443\u0301\u0441-\u0425\u043e\u0434\u0436\u0430\u0301"
    ],
    "name:rus_x_preferred":[
        "\u0420\u0443\u0441\u0441\u043a\u043e\u0435"
    ],
    "name:rus_x_variant":[
        "\u0423\u0440\u0443\u0301\u0441-\u0425\u043e\u0434\u0436\u0430\u0301"
    ],
    "name:ukr_x_preferred":[
        "\u0420\u0443\u0441\u044c\u043a\u0435"
    ],
    "wof:name":"Russkoye",
    "wof:placetype":"locality",
    "wof:population":173
},
  "geometry": {"coordinates":[34.79111,45.02143],"type":"Point"}
}