{
  "type": "Feature",
  "properties": {
    "gn:admin1_code":"18.0",
    "gn:asciiname":"Pysarenky",
    "gn:country_code":"UA",
    "gn:dem":95,
    "gn:feature_class":"P",
    "gn:feature_code":"PPL",
    "gn:name":"Pysarenky",
    "gn:population":0,
    "gn:timezone":"Europe/Kiev",
    "iso:country":"UA",
    "name:ukr_x_preferred":[
        "Pysarenky"
    ],
    "name:ukr_x_variant":[
        "\u041f\u0438\u0441\u0430\u0440\u0435\u043d\u043a\u0438"
    ],
    "wof:name":"Pysarenky",
    "wof:placetype":"locality"
},
  "geometry": {"coordinates":[34.17366,49.65465],"type":"Point"}
}