{
  "type": "Feature",
  "properties": {
    "gn:admin1_code":"9.0",
    "gn:asciiname":"Govory",
    "gn:country_code":"UA",
    "gn:dem":259,
    "gn:feature_class":"P",
    "gn:feature_code":"PPL",
    "gn:name":"Govory",
    "gn:population":0,
    "gn:timezone":"Europe/Kiev",
    "iso:country":"UA",
    "wof:name":"Govory",
    "wof:placetype":"locality"
},
  "geometry": {"coordinates":[27.35393,48.94855],"type":"Point"}
}