{
  "type": "Feature",
  "properties": {
    "gn:admin1_code":"18.0",
    "gn:asciiname":"Knyazheva Sloboda",
    "gn:country_code":"UA",
    "gn:dem":119,
    "gn:feature_class":"P",
    "gn:feature_code":"PPL",
    "gn:name":"Knyazheva Sloboda",
    "gn:population":0,
    "gn:timezone":"Europe/Kiev",
    "iso:country":"UA",
    "name:ukr_x_preferred":[
        "Knyazheva Sloboda"
    ],
    "name:ukr_x_variant":[
        "\u041a\u043d\u044f\u0436\u0435\u0432\u0430 \u0421\u043b\u043e\u0431\u043e\u0434\u0430"
    ],
    "name:und_x_variant":[
        "Knyazheva"
    ],
    "wof:name":"Knyazheva Sloboda",
    "wof:placetype":"locality"
},
  "geometry": {"coordinates":[34.45528,50.12161],"type":"Point"}
}