{
  "type": "Feature",
  "properties": {
    "gn:admin1_code":"17.0",
    "gn:asciiname":"Luhove",
    "gn:cc2":"UA",
    "gn:country_code":"UA",
    "gn:dem":43,
    "gn:feature_class":"P",
    "gn:feature_code":"PPL",
    "gn:name":"Luhove",
    "gn:population":0,
    "gn:timezone":"Europe/Kiev",
    "iso:country":"UA",
    "name:pol_x_preferred":[
        "\u0141uhowe"
    ],
    "name:ron_x_preferred":[
        "Luhove"
    ],
    "name:rus_x_preferred":[
        "\u041b\u0443\u0433\u043e\u0432\u043e\u0435"
    ],
    "name:ukr_x_preferred":[
        "\u041b\u0443\u0433\u043e\u0432\u0435"
    ],
    "name:und_x_variant":[
        "Lugovoye"
    ],
    "name:zho_x_preferred":[
        "\u76e7\u6208\u97cb"
    ],
    "wof:name":"Luhove",
    "wof:placetype":"locality"
},
  "geometry": {"coordinates":[29.83167000000001,46.25361],"type":"Point"}
}