{
  "type": "Feature",
  "properties": {
    "iso:country":"UA",
    "name:rus_x_preferred":[
        "Malaya Ugol\u2019ka"
    ],
    "name:ukr_x_preferred":[
        "Mala Uhol\u2019ka"
    ],
    "name:ukr_x_variant":[
        "\u041c\u0430\u043b\u0430 \u0423\u0433\u043e\u043b\u044c\u043a\u0430"
    ],
    "qs:a0":"\u0423\u043a\u0440\u0430\u0457\u043d\u0430",
    "qs:a1":"*\u0417\u0430\u043a\u0430\u0440\u043f\u0430\u0442\u0441\u044c\u043a\u0430",
    "qs:a1_alt":"Zakarpats'ka",
    "qs:a1r":"0",
    "qs:a2":"\u0422\u044f\u0447\u0456\u0432\u0441\u044c\u043a\u0438\u0439",
    "qs:a2_alt":"Tiachivs'kyi",
    "qs:adm0":"\u0423\u043a\u0440\u0430\u0457\u043d\u0430",
    "qs:la_lc":"*",
    "qs:level":"locality",
    "qs:loc":"\u041c\u0430\u043b\u0430 \u0423\u0433\u043e\u043b\u044c\u043a\u0430",
    "qs:loc_alt":"Mala Uhol'ka",
    "qs:pop":0,
    "qs:type":"buffered point",
    "wof:name":"\u041c\u0430\u043b\u0430 \u0423\u0433\u043e\u043b\u044c\u043a\u0430",
    "wof:placetype":"locality"
},
  "geometry": {"coordinates":[23.637178,48.176612],"type":"Point"}
}