{
  "type": "Feature",
  "properties": {
    "gn:admin1_code":"9.0",
    "gn:asciiname":"Trebukhovka",
    "gn:country_code":"UA",
    "gn:dem":221,
    "gn:feature_class":"P",
    "gn:feature_code":"PPL",
    "gn:name":"Trebukhovka",
    "gn:population":0,
    "gn:timezone":"Europe/Kiev",
    "iso:country":"UA",
    "wof:name":"Trebukhovka",
    "wof:placetype":"locality"
},
  "geometry": {"coordinates":[26.90467,48.78118],"type":"Point"}
}