{
  "type": "Feature",
  "properties": {
    "gn:population":5464,
    "iso:country":"UA",
    "name:ara_x_preferred":[
        "\u0641\u064a\u0644\u064a\u0643\u064a \u0643\u0648\u0628\u0627\u0646\u064a\u060c \u0643\u064a\u0631\u0633\u0648\u0646\u0633\u0643\u0627"
    ],
    "name:ara_x_variant":[
        "\u0641\u064a\u0644\u064a\u0643\u064a \u0643\u0648\u0628\u0627\u0646\u064a"
    ],
    "name:ceb_x_preferred":[
        "Velyki Kopani"
    ],
    "name:deu_x_preferred":[
        "Welyki Kopani"
    ],
    "name:eng_x_preferred":[
        "Velyki Kopani"
    ],
    "name:lav_x_preferred":[
        "Veliki Kopa\u0146i"
    ],
    "name:ron_x_preferred":[
        "Vel\u00eeki Kopani"
    ],
    "name:rus_x_preferred":[
        "\u0412\u0435\u043b\u0438\u043a\u0438\u0435 \u041a\u043e\u043f\u0430\u043d\u0438"
    ],
    "name:ukr_x_preferred":[
        "Velyki Kopani"
    ],
    "name:ukr_x_variant":[
        "\u0412\u0435\u043b\u0438\u043a\u0456 \u041a\u043e\u043f\u0430\u043d\u0456"
    ],
    "name:und_x_variant":[
        "Bol\u2019shiye Kopani"
    ],
    "name:zho_x_preferred":[
        "\u5927\u79d1\u5e15\u5c3c"
    ],
    "qs:a0":"\u0423\u043a\u0440\u0430\u0457\u043d\u0430",
    "qs:a1":"*\u0425\u0435\u0440\u0441\u043e\u043d\u0441\u044c\u043a\u0430",
    "qs:a1_alt":"Khersons'ka",
    "qs:a1r":"0",
    "qs:a2":"\u0426\u044e\u0440\u0443\u043f\u0438\u043d\u0441\u044c\u043a\u0438\u0439",
    "qs:a2_alt":"Tsiurupyns'kyi",
    "qs:adm0":"\u0423\u043a\u0440\u0430\u0457\u043d\u0430",
    "qs:la_lc":"*",
    "qs:level":"locality",
    "qs:loc":"\u0412\u0435\u043b\u0438\u043a\u0456 \u041a\u043e\u043f\u0430\u043d\u0456",
    "qs:loc_alt":"Velyki Kopani",
    "qs:pop":0,
    "qs:type":"buffered point",
    "wof:name":"\u0412\u0435\u043b\u0438\u043a\u0456 \u041a\u043e\u043f\u0430\u043d\u0456",
    "wof:placetype":"locality",
    "wof:population":5464
},
  "geometry": {"coordinates":[32.959875,46.500308],"type":"Point"}
}