{
  "type": "Feature",
  "properties": {
    "gn:admin1_code":"13.0",
    "gn:asciiname":"Zrayki",
    "gn:country_code":"UA",
    "gn:dem":176,
    "gn:feature_class":"P",
    "gn:feature_code":"PPL",
    "gn:name":"Zrayki",
    "gn:population":0,
    "gn:timezone":"Europe/Kiev",
    "iso:country":"UA",
    "wof:name":"Zrayki",
    "wof:placetype":"locality"
},
  "geometry": {"coordinates":[29.82527,49.46618],"type":"Point"}
}