{
  "type": "Feature",
  "properties": {
    "iso:country":"UA",
    "name:deu_x_preferred":[
        "Tuschyliw"
    ],
    "name:eng_x_preferred":[
        "Tuzhyliv"
    ],
    "name:pol_x_preferred":[
        "Tu\u017cy\u0142\u00f3w"
    ],
    "name:ron_x_preferred":[
        "Tuj\u00eeliv"
    ],
    "name:rus_x_preferred":[
        "\u0422\u0443\u0436\u0438\u043b\u043e\u0432"
    ],
    "name:ukr_x_preferred":[
        "\u0422\u0443\u0436\u0438\u043b\u0456\u0432"
    ],
    "name:unk_x_variant":[
        "Tuzhiluv"
    ],
    "name:zho_x_preferred":[
        "\u5716\u65e5\u5229\u592b"
    ],
    "qs:a0":"\u0423\u043a\u0440\u0430\u0457\u043d\u0430",
    "qs:a1":"*\u0406\u0432\u0430\u043d\u043e-\u0424\u0440\u0430\u043d\u043a\u0456\u0432\u0441\u044c\u043a\u0430",
    "qs:a1_alt":"Ivano-Frankivs'ka",
    "qs:a1r":"0",
    "qs:a2":"\u041a\u0430\u043b\u0443\u0441\u044c\u043a\u0438\u0439",
    "qs:a2_alt":"Kalus'kyi",
    "qs:adm0":"\u0423\u043a\u0440\u0430\u0457\u043d\u0430",
    "qs:la_lc":"*",
    "qs:level":"locality",
    "qs:loc":"\u0422\u0443\u0436\u0438\u043b\u0456\u0432",
    "qs:loc_alt":"Tuzhyliv",
    "qs:pop":0,
    "qs:type":"buffered point",
    "wof:name":"\u0422\u0443\u0436\u0438\u043b\u0456\u0432",
    "wof:placetype":"locality"
},
  "geometry": {"coordinates":[24.253861,48.988305],"type":"Point"}
}