{
  "type": "Feature",
  "properties": {
    "iso:country":"UA",
    "name:eng_x_preferred":[
        "Grushkovka"
    ],
    "name:rus_x_preferred":[
        "\u0413\u0440\u0443\u0448\u043a\u043e\u0432\u043a\u0430"
    ],
    "name:ukr_x_preferred":[
        "Hrushkivka"
    ],
    "name:ukr_x_variant":[
        "\u0413\u0440\u0443\u0448\u043a\u0456\u0432\u043a\u0430"
    ],
    "name:unk_x_variant":[
        "Grushevka"
    ],
    "qs:a0":"\u0423\u043a\u0440\u0430\u0457\u043d\u0430",
    "qs:a1":"*\u0427\u0435\u0440\u043a\u0430\u0441\u044c\u043a\u0430",
    "qs:a1_alt":"Cherkas'ka",
    "qs:a1r":"0",
    "qs:a2":"\u041a\u0430\u043c'\u044f\u043d\u0441\u044c\u043a\u0438\u0439",
    "qs:a2_alt":"Kamyans'kyi",
    "qs:adm0":"\u0423\u043a\u0440\u0430\u0457\u043d\u0430",
    "qs:la_lc":"*",
    "qs:level":"locality",
    "qs:loc":"\u0413\u0440\u0443\u0448\u043a\u0456\u0432\u043a\u0430",
    "qs:loc_alt":"Hrushkivka",
    "qs:pop":0,
    "qs:type":"buffered point",
    "wof:name":"\u0413\u0440\u0443\u0448\u043a\u0456\u0432\u043a\u0430",
    "wof:placetype":"locality"
},
  "geometry": {"coordinates":[32.195266,49.085738],"type":"Point"}
}