{
  "type": "Feature",
  "properties": {
    "gn:admin1_code":"14.0",
    "gn:asciiname":"Stepanovka",
    "gn:country_code":"UA",
    "gn:dem":115,
    "gn:feature_class":"P",
    "gn:feature_code":"PPL",
    "gn:name":"Stepanovka",
    "gn:population":0,
    "gn:timezone":"Europe/Zaporozhye",
    "iso:country":"UA",
    "name:ron_x_preferred":[
        "Stepanivka"
    ],
    "name:rus_x_preferred":[
        "\u0421\u0442\u0435\u043f\u0430\u043d\u043e\u0432\u043a\u0430"
    ],
    "name:ukr_x_preferred":[
        "\u0421\u0442\u0435\u043f\u0430\u043d\u0456\u0432\u043a\u0430"
    ],
    "name:zho_x_preferred":[
        "\u65af\u6377\u5e15\u5c3c\u592b\u5361"
    ],
    "wof:name":"Stepanovka",
    "wof:placetype":"locality"
},
  "geometry": {"coordinates":[38.88583,48.42694],"type":"Point"}
}