{
  "type": "Feature",
  "properties": {
    "gn:admin1_code":"17.0",
    "gn:asciiname":"Komyshivka",
    "gn:country_code":"UA",
    "gn:dem":13,
    "gn:feature_class":"P",
    "gn:feature_code":"PPL",
    "gn:name":"Komyshivka",
    "gn:population":0,
    "gn:timezone":"Europe/Kiev",
    "iso:country":"UA",
    "name:ukr_x_preferred":[
        "Komyshivka"
    ],
    "name:ukr_x_variant":[
        "\u041a\u043e\u043c\u0438\u0448\u0456\u0432\u043a\u0430"
    ],
    "name:und_x_variant":[
        "Khadzhi-Kurda",
        "Hagi Curda",
        "Kamyshevka",
        "Kamyshovka"
    ],
    "wof:name":"Komyshivka",
    "wof:placetype":"locality"
},
  "geometry": {"coordinates":[29.12216,45.51976],"type":"Point"}
}