{
  "type": "Feature",
  "properties": {
    "gn:admin1_code":"18.0",
    "gn:asciiname":"Kurhanne",
    "gn:country_code":"UA",
    "gn:dem":121,
    "gn:feature_class":"P",
    "gn:feature_code":"PPL",
    "gn:name":"Kurhanne",
    "gn:population":0,
    "gn:timezone":"Europe/Kiev",
    "iso:country":"UA",
    "name:ukr_x_preferred":[
        "Kurhanne"
    ],
    "name:ukr_x_variant":[
        "\u041a\u0443\u0440\u0433\u0430\u043d\u043d\u0435"
    ],
    "wof:name":"Kurhanne",
    "wof:placetype":"locality"
},
  "geometry": {"coordinates":[33.08667,49.688],"type":"Point"}
}