{
  "type": "Feature",
  "properties": {
    "gn:admin1_code":"6.0",
    "gn:asciiname":"Lukvitsa",
    "gn:country_code":"UA",
    "gn:dem":378,
    "gn:feature_class":"P",
    "gn:feature_code":"PPL",
    "gn:name":"Lukvitsa",
    "gn:population":0,
    "gn:timezone":"Europe/Kiev",
    "iso:country":"UA",
    "wof:name":"Lukvitsa",
    "wof:placetype":"locality"
},
  "geometry": {"coordinates":[24.53333,48.98333],"type":"Point"}
}