{
  "type": "Feature",
  "properties": {
    "gn:admin1_code":"22.0",
    "gn:asciiname":"Lishnya",
    "gn:country_code":"UA",
    "gn:dem":247,
    "gn:feature_class":"P",
    "gn:feature_code":"PPL",
    "gn:name":"Lishnya",
    "gn:population":0,
    "gn:timezone":"Europe/Kiev",
    "iso:country":"UA",
    "wof:name":"Lishnya",
    "wof:placetype":"locality"
},
  "geometry": {"coordinates":[25.81791,50.17297],"type":"Point"}
}