{
  "type": "Feature",
  "properties": {
    "gn:admin1_code":"6.0",
    "gn:asciiname":"Khmelyuvka",
    "gn:country_code":"UA",
    "gn:dem":434,
    "gn:feature_class":"P",
    "gn:feature_code":"PPL",
    "gn:name":"Khmelyuvka",
    "gn:population":0,
    "gn:timezone":"Europe/Kiev",
    "iso:country":"UA",
    "name:und_x_variant":[
        "Khmel\u00ebvka"
    ],
    "wof:name":"Khmelyuvka",
    "wof:placetype":"locality"
},
  "geometry": {"coordinates":[24.38738,48.80801],"type":"Point"}
}