{
  "type": "Feature",
  "properties": {
    "gn:admin1_code":"21.0",
    "gn:asciiname":"Zapsillya",
    "gn:country_code":"UA",
    "gn:dem":138,
    "gn:feature_class":"P",
    "gn:feature_code":"PPL",
    "gn:name":"Zapsillya",
    "gn:population":0,
    "gn:timezone":"Europe/Kiev",
    "iso:country":"UA",
    "name:ukr_x_preferred":[
        "\u0417\u0430\u043f\u0441\u0456\u043b\u043b\u044f"
    ],
    "name:und_x_variant":[
        "Zapsel\u2019ye",
        "Zapsillya"
    ],
    "wof:name":"Zapsillya",
    "wof:placetype":"locality"
},
  "geometry": {"coordinates":[35.22109000000001,51.02555],"type":"Point"}
}