{
  "type": "Feature",
  "properties": {
    "gn:population":3363,
    "iso:country":"UA",
    "name:arm_x_preferred":[
        "\u0549\u0565\u0580\u0576\u0575\u0561\u0576\u056f\u0561"
    ],
    "name:eng_x_preferred":[
        "Chornianka"
    ],
    "name:ger_x_preferred":[
        "Tschornjanka"
    ],
    "name:lav_x_preferred":[
        "\u010cor\u0146anka"
    ],
    "name:rum_x_preferred":[
        "Ciorneanka"
    ],
    "name:rus_x_preferred":[
        "\u0427\u043e\u0440\u043d\u044f\u043d\u043a\u0430"
    ],
    "name:rus_x_variant":[
        "\u0427\u0435\u0440\u043d\u044f\u043d\u043a\u0430"
    ],
    "name:ukr_x_preferred":[
        "\u0427\u043e\u0440\u043d\u044f\u043d\u043a\u0430"
    ],
    "name:unk_x_variant":[
        "Chernen\u2019ka"
    ],
    "qs:a0":"\u0423\u043a\u0440\u0430\u0457\u043d\u0430",
    "qs:a1":"*\u0425\u0435\u0440\u0441\u043e\u043d\u0441\u044c\u043a\u0430",
    "qs:a1_alt":"Khersons'ka",
    "qs:a1r":"0",
    "qs:a2":"\u041a\u0430\u0445\u043e\u0432\u0441\u044c\u043a\u0438\u0439",
    "qs:a2_alt":"Kakhovs'kyi",
    "qs:adm0":"\u0423\u043a\u0440\u0430\u0457\u043d\u0430",
    "qs:la_lc":"*",
    "qs:level":"locality",
    "qs:loc":"\u0427\u043e\u0440\u043d\u044f\u043d\u043a\u0430",
    "qs:loc_alt":"Chornianka",
    "qs:pop":0,
    "qs:type":"buffered point",
    "wof:name":"\u0427\u043e\u0440\u043d\u044f\u043d\u043a\u0430",
    "wof:placetype":"locality",
    "wof:population":3363
},
  "geometry": {"coordinates":[33.373283,46.640419],"type":"Point"}
}