{
  "type": "Feature",
  "properties": {
    "gn:admin1_code":"15.0",
    "gn:asciiname":"Khvatuv",
    "gn:country_code":"UA",
    "gn:dem":253,
    "gn:feature_class":"P",
    "gn:feature_code":"PPL",
    "gn:name":"Khvatuv",
    "gn:population":0,
    "gn:timezone":"Europe/Kiev",
    "iso:country":"UA",
    "wof:name":"Khvatuv",
    "wof:placetype":"locality"
},
  "geometry": {"coordinates":[24.94392,49.96233],"type":"Point"}
}