{
  "type": "Feature",
  "properties": {
    "iso:country":"UA",
    "name:crh_x_preferred":[
        "Orjiv"
    ],
    "name:deu_x_preferred":[
        "Orschiw"
    ],
    "name:eng_x_preferred":[
        "Orzhiv"
    ],
    "name:fra_x_preferred":[
        "Orjiv"
    ],
    "name:jpn_x_preferred":[
        "\u30aa\u30eb\u30c4\u30a3\u30f4"
    ],
    "name:nld_x_preferred":[
        "Orzhiv"
    ],
    "name:pol_x_preferred":[
        "Orzew"
    ],
    "name:rus_x_preferred":[
        "\u041e\u0440\u0436\u0435\u0432"
    ],
    "name:ukr_x_preferred":[
        "\u041e\u0440\u0436\u0456\u0432"
    ],
    "name:zho_x_preferred":[
        "\u5967\u723e\u65e5\u592b"
    ],
    "qs:a0":"\u0423\u043a\u0440\u0430\u0457\u043d\u0430",
    "qs:a1":"*\u0420\u0456\u0432\u043d\u0435\u043d\u0441\u044c\u043a\u0430",
    "qs:a1_alt":"Rivnens'ka",
    "qs:a1r":"0",
    "qs:a2":"\u0420\u0456\u0432\u043d\u0435\u043d\u0441\u044c\u043a\u0438\u0439",
    "qs:a2_alt":"Rivnens'kyi",
    "qs:adm0":"\u0423\u043a\u0440\u0430\u0457\u043d\u0430",
    "qs:la_lc":"*",
    "qs:level":"locality",
    "qs:loc":"\u041e\u0440\u0436\u0456\u0432",
    "qs:loc_alt":"Orzhiv",
    "qs:pop":0,
    "qs:type":"buffered point",
    "wd:wordcount":153,
    "wof:name":"\u041e\u0440\u0436\u0456\u0432",
    "wof:placetype":"locality"
},
  "geometry": {"coordinates":[26.114029,50.744391],"type":"Point"}
}