{
  "type": "Feature",
  "properties": {
    "gn:admin1_code":"17.0",
    "gn:asciiname":"Miliardivka",
    "gn:country_code":"UA",
    "gn:dem":127,
    "gn:feature_class":"P",
    "gn:feature_code":"PPL",
    "gn:name":"Miliardivka",
    "gn:population":0,
    "gn:timezone":"Europe/Kiev",
    "iso:country":"UA",
    "name:ukr_x_preferred":[
        "Miliardivka"
    ],
    "name:ukr_x_variant":[
        "\u041c\u0456\u043b\u0456\u0430\u0440\u0434\u0456\u0432\u043a\u0430"
    ],
    "name:und_x_variant":[
        "Milliardivka",
        "Milliardovka"
    ],
    "wof:name":"Miliardivka",
    "wof:placetype":"locality"
},
  "geometry": {"coordinates":[30.20472,46.75245],"type":"Point"}
}