{
  "type": "Feature",
  "properties": {
    "gn:admin1_code":"14.0",
    "gn:asciiname":"Mykyshivka",
    "gn:country_code":"UA",
    "gn:dem":63,
    "gn:feature_class":"P",
    "gn:feature_code":"PPL",
    "gn:name":"Mykyshivka",
    "gn:population":0,
    "gn:timezone":"Europe/Zaporozhye",
    "iso:country":"UA",
    "name:ukr_x_preferred":[
        "Mykyshivka"
    ],
    "name:ukr_x_variant":[
        "\u041c\u0438\u043a\u0438\u0448\u0456\u0432\u043a\u0430"
    ],
    "name:und_x_variant":[
        "Nikitovka",
        "Nikishovka"
    ],
    "wof:name":"Mykyshivka",
    "wof:placetype":"locality"
},
  "geometry": {"coordinates":[39.95009,48.24088],"type":"Point"}
}