{
  "type": "Feature",
  "properties": {
    "iso:country":"UA",
    "name:ces_x_preferred":[
        "Iv\u010denko-Progress"
    ],
    "name:deu_x_preferred":[
        "Iwtschenko Progress"
    ],
    "name:fra_x_preferred":[
        "Ivtchenko-Progress ZMKB"
    ],
    "name:ind_x_preferred":[
        "Ivchenko-Progress"
    ],
    "name:jpn_x_preferred":[
        "\u30a2\u30ab\u30c7\u30df\u30fc\u4f1a\u54e1O\u30fbH\u30fb\u30a4\u30fc\u30a6\u30c1\u30a7\u30f3\u30b3\u8a18\u5ff5\u30d7\u30ed\u30d5\u30ec\u30fc\u30b9\u30fb\u30b6\u30dd\u30ea\u30fc\u30b8\u30e3\u6a5f\u68b0\u88fd\u4f5c\u8a2d\u8a08\u5c40"
    ],
    "name:pol_x_preferred":[
        "Iwczenko-Progress"
    ],
    "name:por_x_preferred":[
        "Ivchenko-Progress"
    ],
    "name:rus_x_preferred":[
        "\u0417\u041c\u041a\u0411 \u00ab\u041f\u0440\u043e\u0433\u0440\u0435\u0441\u0441\u00bb \u0438\u043c\u0435\u043d\u0438 \u0430\u043a\u0430\u0434\u0435\u043c\u0438\u043a\u0430 \u0410. \u0413. \u0418\u0432\u0447\u0435\u043d\u043a\u043e"
    ],
    "name:slv_x_preferred":[
        "Iv\u010denko-Progress"
    ],
    "name:ukr_x_preferred":[
        "\u041a\u043e\u043d\u0441\u0442\u0440\u0443\u043a\u0442\u043e\u0440\u0441\u044c\u043a\u0435 \u0431\u044e\u0440\u043e \u00ab\u041f\u0440\u043e\u0433\u0440\u0435\u0441\u00bb"
    ],
    "qs:a0":"\u0423\u043a\u0440\u0430\u0457\u043d\u0430",
    "qs:a1":"*\u0414\u043d\u0456\u043f\u0440\u043e\u043f\u0435\u0442\u0440\u043e\u0432\u0441\u044c\u043a\u0430",
    "qs:a1_alt":"Dnipropetrovs'ka",
    "qs:a1r":"0",
    "qs:a2":"\u0410\u043f\u043e\u0441\u0442\u043e\u043b\u0456\u0432\u0441\u044c\u043a\u0438\u0439",
    "qs:a2_alt":"Apostolivs'kyi",
    "qs:adm0":"\u0423\u043a\u0440\u0430\u0457\u043d\u0430",
    "qs:la_lc":"*",
    "qs:level":"locality",
    "qs:loc":"\u0417\u0430\u043f\u043e\u0440\u0456\u0437\u044c\u043a\u0435",
    "qs:loc_alt":"Zaporiz'ke",
    "qs:pop":0,
    "qs:type":"buffered point",
    "wd:wordcount":483,
    "wof:name":"\u0417\u0430\u043f\u043e\u0440\u0456\u0437\u044c\u043a\u0435",
    "wof:placetype":"locality"
},
  "geometry": {"coordinates":[33.802929,47.645748],"type":"Point"}
}