{
  "type": "Feature",
  "properties": {
    "gn:admin1_code":"9.0",
    "gn:asciiname":"Mariyanovka",
    "gn:cc2":"UA",
    "gn:country_code":"UA",
    "gn:dem":272,
    "gn:feature_class":"P",
    "gn:feature_code":"PPL",
    "gn:name":"Mariyanovka",
    "gn:population":0,
    "gn:timezone":"Europe/Kiev",
    "iso:country":"UA",
    "name:und_x_variant":[
        "Marian\u00f3wka",
        "Marianivka",
        "Mariyanovka"
    ],
    "wof:name":"Mariyanovka",
    "wof:placetype":"locality"
},
  "geometry": {"coordinates":[26.78333,48.61667],"type":"Point"}
}