{
  "type": "Feature",
  "properties": {
    "iso:country":"UA",
    "name:und_x_variant":[
        "Plotych"
    ],
    "qs:a0":"\u0423\u043a\u0440\u0430\u0457\u043d\u0430",
    "qs:a1":"*\u0422\u0435\u0440\u043d\u043e\u043f\u0456\u043b\u044c\u0441\u044c\u043a\u0430",
    "qs:a1_alt":"Ternopil's'ka",
    "qs:a1r":"0",
    "qs:a2":"\u0422\u0435\u0440\u043d\u043e\u043f\u0456\u043b\u044c\u0441\u044c\u043a\u0438\u0439",
    "qs:a2_alt":"Ternopil's'kyi",
    "qs:adm0":"\u0423\u043a\u0440\u0430\u0457\u043d\u0430",
    "qs:la_lc":"*",
    "qs:level":"locality",
    "qs:loc":"\u041f\u043b\u043e\u0442\u0438\u0447\u0430",
    "qs:loc_alt":"Plotycha",
    "qs:pop":0,
    "qs:type":"buffered point",
    "wof:name":"\u041f\u043b\u043e\u0442\u0438\u0447\u0430",
    "wof:placetype":"locality"
},
  "geometry": {"coordinates":[25.560942,49.623825],"type":"Point"}
}