{
  "type": "Feature",
  "properties": {
    "gn:admin1_code":"27",
    "gn:asciiname":"Stanislavivka",
    "gn:country_code":"UA",
    "gn:dem":236,
    "gn:feature_class":"P",
    "gn:feature_code":"PPL",
    "gn:name":"Stanislavivka",
    "gn:population":0,
    "gn:timezone":"Europe/Kiev",
    "iso:country":"UA",
    "name:ukr_x_preferred":[
        "Stanislavivka"
    ],
    "name:ukr_x_variant":[
        "\u0421\u0442\u0430\u043d\u0456\u0441\u043b\u0430\u0432\u0456\u0432\u043a\u0430"
    ],
    "wof:name":"Stanislavivka",
    "wof:placetype":"locality"
},
  "geometry": {"coordinates":[28.15521,50.17952],"type":"Point"}
}