{
  "type": "Feature",
  "properties": {
    "gn:admin1_code":"5.0",
    "gn:asciiname":"Kharkivs'ke",
    "gn:country_code":"UA",
    "gn:dem":138,
    "gn:feature_class":"P",
    "gn:feature_code":"PPL",
    "gn:name":"Kharkivs\u2019ke",
    "gn:population":0,
    "gn:timezone":"Europe/Kiev",
    "iso:country":"UA",
    "name:rus_x_preferred":[
        "Khar\u2019kovskiy"
    ],
    "name:rus_x_variant":[
        "Khar\u2019kovskoye"
    ],
    "name:ukr_x_preferred":[
        "Kharkivs\u2019ke"
    ],
    "name:ukr_x_variant":[
        "\u0425\u0430\u0440\u043a\u0456\u0432\u0441\u044c\u043a\u0435"
    ],
    "wof:name":"Kharkivs'ke",
    "wof:placetype":"locality"
},
  "geometry": {"coordinates":[38.55957,47.74542],"type":"Point"}
}