{
  "type": "Feature",
  "properties": {
    "gn:admin1_code":"4.0",
    "gn:asciiname":"Klyn",
    "gn:country_code":"UA",
    "gn:dem":156,
    "gn:feature_class":"P",
    "gn:feature_code":"PPL",
    "gn:name":"Klyn",
    "gn:population":0,
    "gn:timezone":"Europe/Kiev",
    "iso:country":"UA",
    "name:ukr_x_preferred":[
        "Klyn"
    ],
    "name:ukr_x_variant":[
        "\u041a\u043b\u0438\u043d"
    ],
    "wof:name":"Klyn",
    "wof:placetype":"locality"
},
  "geometry": {"coordinates":[33.98036,48.64604],"type":"Point"}
}