{
  "type": "Feature",
  "properties": {
    "gn:admin1_code":"27.0",
    "gn:asciiname":"Ozhhiv",
    "gn:country_code":"UA",
    "gn:dem":233,
    "gn:feature_class":"P",
    "gn:feature_code":"PPL",
    "gn:name":"Ozhhiv",
    "gn:population":0,
    "gn:timezone":"Europe/Kiev",
    "iso:country":"UA",
    "name:ukr_x_preferred":[
        "Ozhhiv"
    ],
    "name:ukr_x_variant":[
        "\u041e\u0436\u0433\u0456\u0432"
    ],
    "name:und_x_variant":[
        "Ozhgov"
    ],
    "wof:name":"Ozhhiv",
    "wof:placetype":"locality"
},
  "geometry": {"coordinates":[27.91583,50.29981],"type":"Point"}
}