{
  "type": "Feature",
  "properties": {
    "iso:country":"UA",
    "qs:a0":"\u0423\u043a\u0440\u0430\u0457\u043d\u0430",
    "qs:a1":"*\u041a\u0440\u0438\u043c",
    "qs:a1_alt":"Krym",
    "qs:a1r":"0",
    "qs:a2":"\u0421\u0430\u043a\u0441\u044c\u043a\u0438\u0439",
    "qs:a2_alt":"Saks'kyi",
    "qs:adm0":"\u0423\u043a\u0440\u0430\u0457\u043d\u0430",
    "qs:la_lc":"*",
    "qs:level":"locality",
    "qs:loc":"\u041b\u0456\u0441\u043d\u0456\u0432\u043a\u0430",
    "qs:loc_alt":"Lisnivka",
    "qs:pop":0,
    "qs:type":"buffered point",
    "wof:name":"\u041b\u0456\u0441\u043d\u0456\u0432\u043a\u0430",
    "wof:placetype":"locality"
},
  "geometry": {"coordinates":[33.625124,45.154898],"type":"Point"}
}