{
  "type": "Feature",
  "properties": {
    "gn:population":8008,
    "iso:country":"UA",
    "name:eng_x_preferred":[
        "Krasnokutsk"
    ],
    "name:rus_x_preferred":[
        "\u041a\u0440\u0430\u0441\u043d\u043e\u043a\u0443\u0442\u0441\u043a"
    ],
    "name:ukr_x_preferred":[
        "Krasnokuts\u2019k"
    ],
    "name:ukr_x_variant":[
        "\u041a\u0440\u0430\u0441\u043d\u043e\u043a\u0443\u0442\u0441\u044c\u043a"
    ],
    "qs:a0":"\u0423\u043a\u0440\u0430\u0457\u043d\u0430",
    "qs:a1":"*\u0425\u0430\u0440\u043a\u0456\u0432\u0441\u044c\u043a\u0430",
    "qs:a1_alt":"Kharkivs'ka",
    "qs:a1r":"0",
    "qs:a2":"\u041a\u0440\u0430\u0441\u043d\u043e\u043a\u0443\u0442\u0441\u044c\u043a\u0438\u0439",
    "qs:a2_alt":"Krasnokuts'kyi",
    "qs:adm0":"\u0423\u043a\u0440\u0430\u0457\u043d\u0430",
    "qs:la_lc":"*",
    "qs:level":"locality",
    "qs:loc":"\u041a\u0440\u0430\u0441\u043d\u043e\u043a\u0443\u0442\u0441\u044c\u043a",
    "qs:loc_alt":"Krasnokuts'k",
    "qs:pop":0,
    "qs:type":"buffered point",
    "wof:name":"\u041a\u0440\u0430\u0441\u043d\u043e\u043a\u0443\u0442\u0441\u044c\u043a",
    "wof:placetype":"locality",
    "wof:population":8008
},
  "geometry": {"coordinates":[35.193315,50.080667],"type":"Point"}
}