{
  "type": "Feature",
  "properties": {
    "iso:country":"UA",
    "name:eng_x_variant":[
        "Obolonskyi"
    ],
    "name:ukr_x_preferred":[
        "\u041e\u0431\u043e\u043b\u043e\u043d\u0441\u044c\u043a\u0438\u0439"
    ],
    "wof:name":"Obolon",
    "wof:placetype":"neighbourhood"
},
  "geometry": {"coordinates":[30.49593141599876,50.51064040565382],"type":"Point"}
}