{
  "type": "Feature",
  "properties": {
    "gn:admin1_code":"21.0",
    "gn:asciiname":"Petriyevskiy",
    "gn:country_code":"UA",
    "gn:dem":167,
    "gn:feature_class":"P",
    "gn:feature_code":"PPL",
    "gn:name":"Petriyevskiy",
    "gn:population":0,
    "gn:timezone":"Europe/Kiev",
    "iso:country":"UA",
    "name:und_x_variant":[
        "Bogolyubovka",
        "Petriyevskiy"
    ],
    "wof:name":"Petriyevskiy",
    "wof:placetype":"locality"
},
  "geometry": {"coordinates":[34.96667,50.41667],"type":"Point"}
}