{
  "type": "Feature",
  "properties": {
    "gn:admin1_code":"8.0",
    "gn:asciiname":"Zakharivka",
    "gn:country_code":"UA",
    "gn:dem":47,
    "gn:feature_class":"P",
    "gn:feature_code":"PPL",
    "gn:name":"Zakharivka",
    "gn:population":0,
    "gn:timezone":"Europe/Kiev",
    "iso:country":"UA",
    "name:rus_x_preferred":[
        "\u0417\u0430\u0445\u0430\u0440\u043e\u0432\u043a\u0430"
    ],
    "name:ukr_x_preferred":[
        "Zakharivka"
    ],
    "name:ukr_x_variant":[
        "\u0417\u0430\u0445\u0430\u0440\u0456\u0432\u043a\u0430"
    ],
    "name:und_x_variant":[
        "Zakharovka"
    ],
    "wof:name":"Zakharivka",
    "wof:placetype":"locality"
},
  "geometry": {"coordinates":[34.32294,46.74877],"type":"Point"}
}