{
  "type": "Feature",
  "properties": {
    "gn:admin1_code":"8.0",
    "gn:asciiname":"Zakharivka",
    "gn:country_code":"UA",
    "gn:dem":47,
    "gn:feature_class":"P",
    "gn:feature_code":"PPL",
    "gn:name":"Zakharivka",
    "gn:population":0,
    "gn:timezone":"Europe/Kiev",
    "iso:country":"UA",
    "name:bel_x_preferred":[
        "\u0417\u0430\u0445\u0430\u0440\u044b\u045e\u043a\u0430"
    ],
    "name:bul_x_preferred":[
        "\u0417\u0430\u0445\u0430\u0440\u0438\u0432\u043a\u0430"
    ],
    "name:ceb_x_preferred":[
        "Frunzivka"
    ],
    "name:crh_x_preferred":[
        "Zakharivka"
    ],
    "name:deu_x_preferred":[
        "Sachariwka"
    ],
    "name:pol_x_preferred":[
        "Zachariwka"
    ],
    "name:ron_x_preferred":[
        "Zaharivka"
    ],
    "name:rus_x_preferred":[
        "\u0417\u0430\u0445\u0430\u0440\u043e\u0432\u043a\u0430"
    ],
    "name:rus_x_variant":[
        "\u0417\u0430\u0445\u0430\u0440\u044c\u0435\u0432\u043a\u0430"
    ],
    "name:sah_x_preferred":[
        "\u0417\u0430\u0445\u0430\u0440\u044c\u0435\u0432\u043a\u0430"
    ],
    "name:spa_x_preferred":[
        "Zakharivka"
    ],
    "name:ukr_x_preferred":[
        "Zakharivka"
    ],
    "name:ukr_x_variant":[
        "\u0417\u0430\u0445\u0430\u0440\u0456\u0432\u043a\u0430"
    ],
    "name:und_x_variant":[
        "Zakharovka"
    ],
    "name:zho_x_preferred":[
        "\u5f17\u502b\u6fdf\u592b\u5361"
    ],
    "wof:name":"Zakharivka",
    "wof:placetype":"locality"
},
  "geometry": {"coordinates":[34.32294,46.74877],"type":"Point"}
}