{
  "type": "Feature",
  "properties": {
    "gn:admin1_code":"9.0",
    "gn:asciiname":"Dobrin",
    "gn:country_code":"UA",
    "gn:dem":290,
    "gn:feature_class":"P",
    "gn:feature_code":"PPL",
    "gn:name":"Dobrin",
    "gn:population":0,
    "gn:timezone":"Europe/Kiev",
    "iso:country":"UA",
    "name:ceb_x_preferred":[
        "Dobrin"
    ],
    "name:deu_x_preferred":[
        "Dobrin"
    ],
    "name:fra_x_preferred":[
        "Dobrin"
    ],
    "name:hye_x_preferred":[
        "\u0534\u0578\u0562\u0580\u056b\u0576"
    ],
    "name:nld_x_preferred":[
        "Dobrin"
    ],
    "name:ron_x_preferred":[
        "Dobrin"
    ],
    "name:rus_x_preferred":[
        "\u0414\u043e\u0431\u0440\u0438\u043d"
    ],
    "name:swe_x_preferred":[
        "Dobrin"
    ],
    "name:vie_x_preferred":[
        "Dobrin"
    ],
    "wof:name":"Dobrin",
    "wof:placetype":"locality"
},
  "geometry": {"coordinates":[26.48747,50.15025],"type":"Point"}
}