{
  "type": "Feature",
  "properties": {
    "gn:admin1_code":"9.0",
    "gn:asciiname":"Dobrin",
    "gn:country_code":"UA",
    "gn:dem":290,
    "gn:feature_class":"P",
    "gn:feature_code":"PPL",
    "gn:name":"Dobrin",
    "gn:population":0,
    "gn:timezone":"Europe/Kiev",
    "iso:country":"UA",
    "wof:name":"Dobrin",
    "wof:placetype":"locality"
},
  "geometry": {"coordinates":[26.48747,50.15025],"type":"Point"}
}