{
  "type": "Feature",
  "properties": {
    "gn:admin1_code":"14.0",
    "gn:asciiname":"Prokhladne",
    "gn:country_code":"UA",
    "gn:dem":237,
    "gn:feature_class":"P",
    "gn:feature_code":"PPL",
    "gn:name":"Prokhladne",
    "gn:population":0,
    "gn:timezone":"Europe/Zaporozhye",
    "iso:country":"UA",
    "name:ukr_x_preferred":[
        "Prokhladne"
    ],
    "name:ukr_x_variant":[
        "\u041f\u0440\u043e\u0445\u043b\u0430\u0434\u043d\u0435"
    ],
    "name:und_x_variant":[
        "Prokhladnoye"
    ],
    "wof:name":"Prokhladne",
    "wof:placetype":"locality"
},
  "geometry": {"coordinates":[39.68511,48.14437],"type":"Point"}
}