{
  "type": "Feature",
  "properties": {
    "gn:admin1_code":"13.0",
    "gn:asciiname":"Dubova",
    "gn:country_code":"UA",
    "gn:dem":147,
    "gn:feature_class":"P",
    "gn:feature_code":"PPL",
    "gn:name":"Dubova",
    "gn:population":0,
    "gn:timezone":"Europe/Kiev",
    "iso:country":"UA",
    "name:ukr_x_preferred":[
        "Dubova"
    ],
    "name:ukr_x_variant":[
        "\u0414\u0443\u0431\u043e\u0432\u0430"
    ],
    "name:und_x_variant":[
        "Oleshnya",
        "Dubovaya"
    ],
    "wof:name":"Dubova",
    "wof:placetype":"locality"
},
  "geometry": {"coordinates":[29.60451,51.1125],"type":"Point"}
}