{
  "type": "Feature",
  "properties": {
    "gn:admin1_code":"5.0",
    "gn:asciiname":"Bylbasivka",
    "gn:country_code":"UA",
    "gn:dem":80,
    "gn:feature_class":"P",
    "gn:feature_code":"PPL",
    "gn:name":"Bylbasivka",
    "gn:population":0,
    "gn:timezone":"Europe/Kiev",
    "iso:country":"UA",
    "name:ukr_x_preferred":[
        "Bylbasivka"
    ],
    "name:ukr_x_variant":[
        "\u0411\u0438\u043b\u0431\u0430\u0441\u0456\u0432\u043a\u0430"
    ],
    "name:und_x_variant":[
        "Belbasovka",
        "Bylbasovka"
    ],
    "wof:name":"Bylbasivka",
    "wof:placetype":"locality"
},
  "geometry": {"coordinates":[37.50168,48.83665],"type":"Point"}
}