{
  "type": "Feature",
  "properties": {
    "gn:admin1_code":"24.0",
    "gn:asciiname":"Krukhynychi",
    "gn:country_code":"UA",
    "gn:dem":225,
    "gn:feature_class":"P",
    "gn:feature_code":"PPL",
    "gn:name":"Krukhynychi",
    "gn:population":0,
    "gn:timezone":"Europe/Kiev",
    "iso:country":"UA",
    "name:ukr_x_preferred":[
        "Krukhynychi"
    ],
    "name:ukr_x_variant":[
        "\u041a\u0440\u0443\u0445\u0438\u043d\u0438\u0447\u0456"
    ],
    "name:und_x_variant":[
        "Krukheniche",
        "Kruchenicze",
        "Krukhinichi"
    ],
    "wof:name":"Krukhynychi",
    "wof:placetype":"locality"
},
  "geometry": {"coordinates":[24.66385,50.75635],"type":"Point"}
}