{
  "type": "Feature",
  "properties": {
    "iso:country":"UA",
    "name:deu_x_preferred":[
        "Birky"
    ],
    "name:eng_x_preferred":[
        "Borki"
    ],
    "name:hye_x_preferred":[
        "\u0532\u0578\u0580\u056f\u056b"
    ],
    "name:jpn_x_preferred":[
        "\u30dc\u30eb\u30ad"
    ],
    "name:pol_x_preferred":[
        "Borki"
    ],
    "name:rus_x_preferred":[
        "\u0411\u043e\u0440\u043a\u0438"
    ],
    "name:swe_x_preferred":[
        "Birky"
    ],
    "name:ukr_x_preferred":[
        "Birky"
    ],
    "name:ukr_x_variant":[
        "\u0411\u0456\u0440\u043a\u0438"
    ],
    "name:zho_x_preferred":[
        "\u6bd4\u723e\u57fa"
    ],
    "qs:a0":"\u0423\u043a\u0440\u0430\u0457\u043d\u0430",
    "qs:a1":"*\u0425\u0430\u0440\u043a\u0456\u0432\u0441\u044c\u043a\u0430",
    "qs:a1_alt":"Kharkivs'ka",
    "qs:a1r":"0",
    "qs:a2":"\u0417\u043c\u0456\u0457\u0432\u0441\u044c\u043a\u0438\u0439",
    "qs:a2_alt":"Zmiivs'kyi",
    "qs:adm0":"\u0423\u043a\u0440\u0430\u0457\u043d\u0430",
    "qs:la_lc":"*",
    "qs:level":"locality",
    "qs:loc":"\u0411\u0456\u0440\u043a\u0438",
    "qs:loc_alt":"Birky",
    "qs:pop":0,
    "qs:type":"buffered point",
    "wd:wordcount":98,
    "wof:name":"\u0411\u0456\u0440\u043a\u0438",
    "wof:placetype":"locality"
},
  "geometry": {"coordinates":[36.059414,49.715725],"type":"Point"}
}