{
  "type": "Feature",
  "properties": {
    "gn:admin1_code":"19.0",
    "gn:asciiname":"Sapozhyn",
    "gn:country_code":"UA",
    "gn:dem":221,
    "gn:feature_class":"P",
    "gn:feature_code":"PPL",
    "gn:name":"Sapozhyn",
    "gn:population":0,
    "gn:timezone":"Europe/Kiev",
    "iso:country":"UA",
    "name:ukr_x_preferred":[
        "Sapozhyn"
    ],
    "name:ukr_x_variant":[
        "\u0421\u0430\u043f\u043e\u0436\u0438\u043d"
    ],
    "name:und_x_variant":[
        "Sapozhin"
    ],
    "wof:name":"Sapozhyn",
    "wof:placetype":"locality"
},
  "geometry": {"coordinates":[26.88052,50.58305],"type":"Point"}
}