{
  "type": "Feature",
  "properties": {
    "gn:admin1_code":"11.0",
    "gn:admin2_code":"704383",
    "gn:admin3_code":"11152912",
    "gn:asciiname":"Yastrebovka",
    "gn:country_code":"UA",
    "gn:dem":43,
    "gn:elevation":"42.0",
    "gn:feature_class":"P",
    "gn:feature_code":"PPL",
    "gn:name":"Yastrebovka",
    "gn:population":153,
    "gn:timezone":"Europe/Simferopol",
    "iso:country":"UA",
    "name:eng_x_preferred":[
        "Yastrebovka"
    ],
    "name:rus_x_historical":[
        "\u0422\u0435\u043c\u0438\u0301\u0440"
    ],
    "name:rus_x_preferred":[
        "\u042f\u0441\u0442\u0440\u0435\u0431\u043e\u0432\u043a\u0430"
    ],
    "name:rus_x_variant":[
        "\u0422\u0435\u043c\u0438\u0301\u0440"
    ],
    "name:ukr_x_preferred":[
        "\u042f\u0441\u0442\u0440\u0443\u0431\u0456\u0432\u043a\u0430"
    ],
    "wof:name":"Yastrebovka",
    "wof:placetype":"locality",
    "wof:population":153
},
  "geometry": {"coordinates":[34.11659,45.51268],"type":"Point"}
}