{
  "type": "Feature",
  "properties": {
    "gn:admin1_code":"22.0",
    "gn:asciiname":"Sushchin",
    "gn:country_code":"UA",
    "gn:dem":283,
    "gn:feature_class":"P",
    "gn:feature_code":"PPL",
    "gn:name":"Sushchin",
    "gn:population":0,
    "gn:timezone":"Europe/Kiev",
    "iso:country":"UA",
    "name:und_x_variant":[
        "Sushchyn",
        "Sushchin"
    ],
    "wof:name":"Sushchin",
    "wof:placetype":"locality"
},
  "geometry": {"coordinates":[25.73086,49.37958],"type":"Point"}
}