{
  "type": "Feature",
  "properties": {
    "gn:admin1_code":"11.0",
    "gn:admin2_code":"710690",
    "gn:admin3_code":"11153138.0",
    "gn:asciiname":"Novoul'yanovka",
    "gn:country_code":"UA",
    "gn:dem":11,
    "gn:elevation":"7.0",
    "gn:feature_class":"P",
    "gn:feature_code":"PPL",
    "gn:name":"Novoul\u2019yanovka",
    "gn:population":239,
    "gn:timezone":"Europe/Simferopol",
    "iso:country":"UA",
    "name:eng_x_preferred":[
        "Novoul\u2019yanovka"
    ],
    "name:rus_x_preferred":[
        "\u041d\u043e\u0432\u043e\u0443\u043b\u044c\u044f\u043d\u043e\u0432\u043a\u0430"
    ],
    "name:ukr_x_preferred":[
        "\u041d\u043e\u0432\u043e\u0443\u043b\u044c\u044f\u043d\u043e\u0432\u043a\u0430"
    ],
    "wof:name":"Novoul'yanovka",
    "wof:placetype":"locality",
    "wof:population":239
},
  "geometry": {"coordinates":[32.94201,45.58031],"type":"Point"}
}