{
  "type": "Feature",
  "properties": {
    "gn:admin1_code":"21.0",
    "gn:asciiname":"Moshenka",
    "gn:country_code":"UA",
    "gn:dem":118,
    "gn:feature_class":"P",
    "gn:feature_code":"PPL",
    "gn:name":"Moshenka",
    "gn:population":0,
    "gn:timezone":"Europe/Kiev",
    "iso:country":"UA",
    "name:ukr_x_preferred":[
        "Moshenka"
    ],
    "name:ukr_x_variant":[
        "\u041c\u043e\u0448\u0435\u043d\u043a\u0430"
    ],
    "name:und_x_variant":[
        "Moshenki"
    ],
    "wof:name":"Moshenka",
    "wof:placetype":"locality"
},
  "geometry": {"coordinates":[34.9103,50.24737],"type":"Point"}
}