{
  "type": "Feature",
  "properties": {
    "gn:admin1_code":"5.0",
    "gn:asciiname":"Dersove",
    "gn:country_code":"UA",
    "gn:dem":80,
    "gn:feature_class":"P",
    "gn:feature_code":"PPL",
    "gn:name":"Dersove",
    "gn:population":0,
    "gn:timezone":"Europe/Kiev",
    "iso:country":"UA",
    "name:ukr_x_preferred":[
        "\u0414\u0435\u0440\u0441\u043e\u0432\u0435"
    ],
    "name:und_x_variant":[
        "Dertsev",
        "Dersove",
        "Dersovo"
    ],
    "wof:name":"Dersove",
    "wof:placetype":"locality"
},
  "geometry": {"coordinates":[37.99748,47.3098],"type":"Point"}
}