{
  "type": "Feature",
  "properties": {
    "gn:admin1_code":"23.0",
    "gn:asciiname":"Nove Misto",
    "gn:country_code":"UA",
    "gn:dem":266,
    "gn:feature_class":"P",
    "gn:feature_code":"PPL",
    "gn:name":"Nove Misto",
    "gn:population":0,
    "gn:timezone":"Europe/Kiev",
    "iso:country":"UA",
    "name:ukr_x_preferred":[
        "\u041d\u043e\u0432\u0435 \u041c\u0456\u0441\u0442\u043e"
    ],
    "name:und_x_variant":[
        "Novoye Mesto",
        "Nove Misto",
        "Novoye Misto"
    ],
    "wof:name":"Nove Misto",
    "wof:placetype":"locality"
},
  "geometry": {"coordinates":[28.40295,48.90155],"type":"Point"}
}