{
  "type": "Feature",
  "properties": {
    "gn:admin1_code":"18.0",
    "gn:asciiname":"Demydivka",
    "gn:country_code":"UA",
    "gn:dem":90,
    "gn:feature_class":"P",
    "gn:feature_code":"PPL",
    "gn:name":"Demydivka",
    "gn:population":0,
    "gn:timezone":"Europe/Kiev",
    "iso:country":"UA",
    "name:ara_x_preferred":[
        "\u062f\u064a\u0645\u064a\u062f\u064a\u0641\u0643\u0627"
    ],
    "name:bel_x_preferred":[
        "\u0414\u044d\u043c\u044b\u0434\u0437\u0456\u045e\u043a\u0430"
    ],
    "name:crh_x_preferred":[
        "Dem\u0131divka"
    ],
    "name:deu_x_preferred":[
        "Demydiwka"
    ],
    "name:eng_x_preferred":[
        "Demidovka"
    ],
    "name:fra_x_preferred":[
        "Demydivka"
    ],
    "name:heb_x_preferred":[
        "\u05d3\u05de\u05d9\u05d3\u05d9\u05d1\u05e7\u05d4"
    ],
    "name:pol_x_preferred":[
        "Demid\u00f3wka"
    ],
    "name:ron_x_preferred":[
        "Dem\u00eedivka"
    ],
    "name:rus_x_preferred":[
        "\u0414\u0435\u043c\u0438\u0434\u043e\u0432\u043a\u0430"
    ],
    "name:ukr_x_preferred":[
        "Demydivka"
    ],
    "name:ukr_x_variant":[
        "\u0414\u0435\u043c\u0438\u0434\u0456\u0432\u043a\u0430"
    ],
    "name:und_x_variant":[
        "Demidovka"
    ],
    "name:zho_x_preferred":[
        "\u5091\u7c73\u5b63\u592b\u5361"
    ],
    "wof:name":"Demydivka",
    "wof:placetype":"locality"
},
  "geometry": {"coordinates":[34.17945,49.56511],"type":"Point"}
}