{
  "type": "Feature",
  "properties": {
    "gn:admin1_code":"5.0",
    "gn:asciiname":"Neygeym",
    "gn:country_code":"UA",
    "gn:dem":89,
    "gn:feature_class":"P",
    "gn:feature_code":"PPL",
    "gn:name":"Neygeym",
    "gn:population":0,
    "gn:timezone":"Europe/Kiev",
    "iso:country":"UA",
    "wof:name":"Neygeym",
    "wof:placetype":"locality"
},
  "geometry": {"coordinates":[38.05,47.33333],"type":"Point"}
}