{
  "type": "Feature",
  "properties": {
    "gn:admin1_code":"17.0",
    "gn:asciiname":"Sarenkovo",
    "gn:cc2":"UA",
    "gn:country_code":"UA",
    "gn:dem":61,
    "gn:feature_class":"P",
    "gn:feature_code":"PPL",
    "gn:name":"Sarenkovo",
    "gn:population":0,
    "gn:timezone":"Europe/Kiev",
    "iso:country":"UA",
    "name:und_x_variant":[
        "Morenkovo",
        "Sarenkovo"
    ],
    "wof:name":"Sarenkovo",
    "wof:placetype":"locality"
},
  "geometry": {"coordinates":[30.91667,47.06667],"type":"Point"}
}