{
  "type": "Feature",
  "properties": {
    "gn:admin1_code":"5.0",
    "gn:asciiname":"Zuyivka",
    "gn:country_code":"UA",
    "gn:dem":124,
    "gn:feature_class":"P",
    "gn:feature_code":"PPL",
    "gn:name":"Zuyivka",
    "gn:population":0,
    "gn:timezone":"Europe/Kiev",
    "iso:country":"UA",
    "name:ukr_x_preferred":[
        "Zuyivka"
    ],
    "name:ukr_x_variant":[
        "\u0417\u0443\u0457\u0432\u043a\u0430"
    ],
    "name:und_x_variant":[
        "Zuyevka"
    ],
    "wof:name":"Zuyivka",
    "wof:placetype":"locality"
},
  "geometry": {"coordinates":[38.25001,48.06056],"type":"Point"}
}