{
  "type": "Feature",
  "properties": {
    "gn:admin1_code":"18.0",
    "gn:asciiname":"Myronivka",
    "gn:country_code":"UA",
    "gn:dem":123,
    "gn:feature_class":"P",
    "gn:feature_code":"PPL",
    "gn:name":"Myronivka",
    "gn:population":0,
    "gn:timezone":"Europe/Kiev",
    "iso:country":"UA",
    "name:bel_x_preferred":[
        "\u041c\u044b\u0440\u043e\u043d\u0456\u045e\u043a\u0430"
    ],
    "name:ceb_x_preferred":[
        "Myronivka"
    ],
    "name:ces_x_preferred":[
        "Myronivka"
    ],
    "name:crh_x_preferred":[
        "M\u0131ronivka"
    ],
    "name:deu_x_preferred":[
        "Myroniwka"
    ],
    "name:fas_x_preferred":[
        "\u0645\u06cc\u0631\u0648\u0646\u06cc\u0641\u06a9\u0627"
    ],
    "name:fin_x_preferred":[
        "Myronivka"
    ],
    "name:fra_x_preferred":[
        "Myronivka"
    ],
    "name:hsb_x_preferred":[
        "Myroniwka"
    ],
    "name:hye_x_preferred":[
        "\u0544\u056b\u0580\u0578\u0576\u0578\u057e\u056f\u0561"
    ],
    "name:ita_x_preferred":[
        "Myronivka"
    ],
    "name:kat_x_preferred":[
        "\u10db\u10d8\u10e0\u10dd\u10dc\u10dd\u10d5\u10d9\u10d0"
    ],
    "name:nno_x_preferred":[
        "Myronivka"
    ],
    "name:pol_x_preferred":[
        "Miron\u00f3wka"
    ],
    "name:ron_x_preferred":[
        "M\u00eeronivka"
    ],
    "name:rus_x_preferred":[
        "\u041c\u0438\u0440\u043e\u043d\u043e\u0432\u043a\u0430"
    ],
    "name:sah_x_preferred":[
        "\u041c\u0438\u0440\u043e\u043d\u043e\u0432\u043a\u0430"
    ],
    "name:ukr_x_preferred":[
        "Myronivka"
    ],
    "name:ukr_x_variant":[
        "\u041c\u0438\u0440\u043e\u043d\u0456\u0432\u043a\u0430"
    ],
    "name:vie_x_preferred":[
        "Myronivka"
    ],
    "name:zho_x_preferred":[
        "\u7c73\u7f85\u8afe\u592b\u5361"
    ],
    "wof:name":"Myronivka",
    "wof:placetype":"locality"
},
  "geometry": {"coordinates":[34.93919,49.49929],"type":"Point"}
}