{
  "type": "Feature",
  "properties": {
    "gn:admin1_code":"18.0",
    "gn:asciiname":"Myronivka",
    "gn:country_code":"UA",
    "gn:dem":123,
    "gn:feature_class":"P",
    "gn:feature_code":"PPL",
    "gn:name":"Myronivka",
    "gn:population":0,
    "gn:timezone":"Europe/Kiev",
    "iso:country":"UA",
    "name:ukr_x_preferred":[
        "Myronivka"
    ],
    "name:ukr_x_variant":[
        "\u041c\u0438\u0440\u043e\u043d\u0456\u0432\u043a\u0430"
    ],
    "wof:name":"Myronivka",
    "wof:placetype":"locality"
},
  "geometry": {"coordinates":[34.93919,49.49929],"type":"Point"}
}