{
  "type": "Feature",
  "properties": {
    "gn:admin1_code":"5.0",
    "gn:asciiname":"Hruz'ko-Lomivka",
    "gn:country_code":"UA",
    "gn:dem":112,
    "gn:feature_class":"P",
    "gn:feature_code":"PPL",
    "gn:name":"Hruz\u2019ko-Lomivka",
    "gn:population":0,
    "gn:timezone":"Europe/Kiev",
    "iso:country":"UA",
    "name:eng_x_preferred":[
        "Hruz'ko-Lomivka"
    ],
    "name:rus_x_preferred":[
        "\u0413\u0440\u0443\u0437\u0441\u043a\u043e-\u041b\u043e\u043c\u043e\u0432\u043a\u0430"
    ],
    "name:ukr_x_preferred":[
        "\u0413\u0440\u0443\u0437\u044c\u043a\u043e-\u041b\u043e\u043c\u0456\u0432\u043a\u0430"
    ],
    "name:und_x_variant":[
        "Kis\u00eblevka",
        "Gruzsko-Lomovskiy",
        "Gruzsko-Lomovka",
        "Hruz\u2019ko-Lomivka"
    ],
    "wof:name":"Hruz'ko-Lomivka",
    "wof:placetype":"locality"
},
  "geometry": {"coordinates":[38.10798,47.90586],"type":"Point"}
}