{
  "type": "Feature",
  "properties": {
    "gn:population":2584,
    "iso:country":"UA",
    "name:bel_x_preferred":[
        "\u041a\u043e\u0436\u0430\u043d\u043a\u0430"
    ],
    "name:bul_x_preferred":[
        "\u041a\u043e\u0436\u0430\u043d\u043a\u0430"
    ],
    "name:ceb_x_preferred":[
        "Kozhanka"
    ],
    "name:ces_x_preferred":[
        "Ko\u017eanka"
    ],
    "name:che_x_preferred":[
        "\u041a\u043e\u0436\u0430\u043d\u043a\u0430"
    ],
    "name:crh_x_preferred":[
        "Kojanka"
    ],
    "name:deu_x_preferred":[
        "Koschanka"
    ],
    "name:eng_x_preferred":[
        "Kozhanka"
    ],
    "name:fra_x_preferred":[
        "Kojanka"
    ],
    "name:mhr_x_preferred":[
        "\u041a\u043e\u0436\u0430\u043d\u043a\u0430"
    ],
    "name:pol_x_preferred":[
        "Ko\u017canka"
    ],
    "name:rus_x_preferred":[
        "\u041a\u043e\u0436\u0430\u043d\u043a\u0430"
    ],
    "name:sah_x_preferred":[
        "\u041a\u043e\u0436\u0430\u043d\u043a\u0430"
    ],
    "name:ukr_x_preferred":[
        "\u041a\u043e\u0436\u0430\u043d\u043a\u0430"
    ],
    "name:uzb_x_preferred":[
        "Kojanka"
    ],
    "name:zho_x_preferred":[
        "\u79d1\u7136\u5361"
    ],
    "qs:a0":"\u0423\u043a\u0440\u0430\u0457\u043d\u0430",
    "qs:a1":"*\u041a\u0438\u0457\u0432\u0441\u044c\u043a\u0430",
    "qs:a1_alt":"Kyivs'ka",
    "qs:a1r":"0",
    "qs:a2":"\u0424\u0430\u0441\u0442\u0456\u0432\u0441\u044c\u043a\u0438\u0439",
    "qs:a2_alt":"Fastivs'kyi",
    "qs:adm0":"\u0423\u043a\u0440\u0430\u0457\u043d\u0430",
    "qs:la_lc":"*",
    "qs:level":"locality",
    "qs:loc":"\u041a\u043e\u0436\u0430\u043d\u043a\u0430",
    "qs:loc_alt":"Kozhanka",
    "qs:pop":0,
    "qs:type":"buffered point",
    "wd:wordcount":88,
    "wof:name":"\u041a\u043e\u0436\u0430\u043d\u043a\u0430",
    "wof:placetype":"locality",
    "wof:population":2584
},
  "geometry": {"coordinates":[29.769209,49.970176],"type":"Point"}
}