{
  "type": "Feature",
  "properties": {
    "gn:admin1_code":"14.0",
    "gn:asciiname":"Kapitanove",
    "gn:country_code":"UA",
    "gn:dem":93,
    "gn:feature_class":"P",
    "gn:feature_code":"PPL",
    "gn:name":"Kapitanove",
    "gn:population":0,
    "gn:timezone":"Europe/Zaporozhye",
    "iso:country":"UA",
    "name:ukr_x_preferred":[
        "Kapitanove"
    ],
    "name:ukr_x_variant":[
        "\u041a\u0430\u043f\u0456\u0442\u0430\u043d\u043e\u0432\u0435"
    ],
    "name:und_x_variant":[
        "Kapitanovo"
    ],
    "wof:name":"Kapitanove",
    "wof:placetype":"locality"
},
  "geometry": {"coordinates":[38.76128,48.83118],"type":"Point"}
}