{
  "type": "Feature",
  "properties": {
    "iso:country":"UA",
    "name:bel_x_preferred":[
        "\u0425\u043e\u0440\u0430\u0448\u044b\u045e\u0441\u043a\u0456 \u0440\u0430\u0451\u043d"
    ],
    "name:bel_x_variant":[
        "\u0425\u043e\u0440\u0430\u0448\u0430\u045e\u0441\u043a\u0456 \u0440\u0430\u0451\u043d",
        "\u0412\u0430\u043b\u0430\u0434\u0430\u0440\u0441\u043a\u0430-\u0412\u0430\u043b\u044b\u043d\u0441\u043a\u0456 \u0440\u0430\u0451\u043d"
    ],
    "name:ceb_x_preferred":[
        "Volodarsko-Volynskiy Rayon"
    ],
    "name:deu_x_preferred":[
        "Rajon Choroschiw"
    ],
    "name:eng_x_preferred":[
        "Khoroshiv Raion"
    ],
    "name:hye_x_preferred":[
        "\u054e\u0578\u056c\u0578\u0564\u0561\u0580\u057d\u056f-\u054e\u0578\u056c\u056b\u0576\u056f\u056b\u056b \u0577\u0580\u057b\u0561\u0576"
    ],
    "name:kat_x_preferred":[
        "\u10ee\u10dd\u10e0\u10dd\u10e8\u10d4\u10d5\u10e1\u10d9\u10d8\u10e1 \u10e0\u10d0\u10d8\u10dd\u10dc\u10d8"
    ],
    "name:kat_x_variant":[
        "\u10d5\u10dd\u10da\u10dd\u10d3\u10d0\u10e0\u10e1\u10d9-\u10d5\u10dd\u10da\u10d8\u10dc\u10e1\u10d9\u10d8\u10e1 \u10e0\u10d0\u10d8\u10dd\u10dc\u10d8"
    ],
    "name:lit_x_preferred":[
        "Voluin\u0117s Volodarsko rajonas"
    ],
    "name:pol_x_preferred":[
        "Rejon horoszowski"
    ],
    "name:pol_x_variant":[
        "Rejon wo\u0142odarski"
    ],
    "name:ron_x_preferred":[
        "Raionul Volodarsk-Vol\u00eensk\u00eei"
    ],
    "name:rus_x_preferred":[
        "\u0425\u043e\u0440\u043e\u0448\u0435\u0432\u0441\u043a\u0438\u0439 \u0440\u0430\u0439\u043e\u043d"
    ],
    "name:sco_x_preferred":[
        "Khoroshiv Raion"
    ],
    "name:spa_x_preferred":[
        "Rai\u00f3n de Khoroshiv"
    ],
    "name:ukr_x_preferred":[
        "\u0425\u043e\u0440\u043e\u0448\u0456\u0432\u0441\u044c\u043a\u0438\u0439 \u0440\u0430\u0439\u043e\u043d"
    ],
    "name:ukr_x_variant":[
        "\u0412\u043e\u043b\u043e\u0434\u0430\u0440\u0441\u044c\u043a-\u0412\u043e\u043b\u0438\u043d\u0441\u044c\u043a\u0438\u0439"
    ],
    "name:und_x_variant":[
        "Goroshki"
    ],
    "name:vie_x_preferred":[
        "Volodarsk-Volynskyi"
    ],
    "name:zho_x_preferred":[
        "\u6c83\u6d1b\u9054\u723e\u897f\u514b-\u6c83\u6797\u897f\u57fa\u5340"
    ],
    "qs:a0":"\u0423\u043a\u0440\u0430\u0457\u043d\u0430",
    "qs:a1":"*\u0416\u0438\u0442\u043e\u043c\u0438\u0440\u0441\u044c\u043a\u0430",
    "qs:a1_alt":"Zhytomyrs'ka",
    "qs:a1r":"0",
    "qs:a2":"\u0412\u043e\u043b\u043e\u0434\u0430\u0440\u0441\u044c\u043a\u043e-\u0412\u043e\u043b\u0438\u043d\u0441\u044c\u043a\u0438\u0439",
    "qs:a2_alt":"Volodars'ko-Volyns'kyi",
    "qs:adm0":"\u0423\u043a\u0440\u0430\u0457\u043d\u0430",
    "qs:la_lc":"*",
    "qs:level":"locality",
    "qs:loc":"\u0412\u043e\u043b\u043e\u0434\u0430\u0440\u0441\u044c\u043a-\u0412\u043e\u043b\u0438\u043d\u0441\u044c\u043a\u0438\u0439",
    "qs:loc_alt":"Volodars'k-Volyns'kyi",
    "qs:pop":0,
    "qs:type":"buffered point",
    "wd:wordcount":115,
    "wof:name":"\u0412\u043e\u043b\u043e\u0434\u0430\u0440\u0441\u044c\u043a-\u0412\u043e\u043b\u0438\u043d\u0441\u044c\u043a\u0438\u0439",
    "wof:placetype":"locality"
},
  "geometry": {"coordinates":[28.448748,50.584144],"type":"Point"}
}