{
  "type": "Feature",
  "properties": {
    "iso:country":"UA",
    "name:che_x_preferred":[
        "\u041e\u043b\u044c\u0433\u0438\u043d\u043a\u0430"
    ],
    "name:crh_x_preferred":[
        "Olg\u0131nka"
    ],
    "name:deu_x_preferred":[
        "Olhynka"
    ],
    "name:eng_x_preferred":[
        "Ol'ginka"
    ],
    "name:eng_x_variant":[
        "Olhynka"
    ],
    "name:fra_x_preferred":[
        "Olhynka"
    ],
    "name:lav_x_preferred":[
        "O\u013chinka"
    ],
    "name:rus_x_preferred":[
        "\u041e\u043b\u044c\u0433\u0438\u043d\u043a\u0430"
    ],
    "name:spa_x_preferred":[
        "Oljinka"
    ],
    "name:ukr_x_preferred":[
        "Ol\u2019hynka"
    ],
    "name:ukr_x_variant":[
        "\u041e\u043b\u044c\u0433\u0438\u043d\u043a\u0430"
    ],
    "name:und_x_variant":[
        "Olginskoe"
    ],
    "name:zho_x_preferred":[
        "\u5967\u5229\u91d1\u5361"
    ],
    "name:zho_x_variant":[
        "\u5965\u5229\u4ea8\u5361"
    ],
    "qs:a0":"\u0423\u043a\u0440\u0430\u0457\u043d\u0430",
    "qs:a1":"*\u0414\u043e\u043d\u0435\u0446\u044c\u043a\u0430",
    "qs:a1_alt":"Donets'ka",
    "qs:a1r":"0",
    "qs:a2":"\u0412\u043e\u043b\u043d\u043e\u0432\u0430\u0445\u0441\u044c\u043a\u0438\u0439",
    "qs:a2_alt":"Volnovakhs'kyi",
    "qs:adm0":"\u0423\u043a\u0440\u0430\u0457\u043d\u0430",
    "qs:la_lc":"*",
    "qs:level":"locality",
    "qs:loc":"\u041e\u043b\u044c\u0433\u0438\u043d\u043a\u0430",
    "qs:loc_alt":"Ol'hynka",
    "qs:pop":0,
    "qs:type":"buffered point",
    "wof:name":"\u041e\u043b\u044c\u0433\u0438\u043d\u043a\u0430",
    "wof:placetype":"locality"
},
  "geometry": {"coordinates":[37.497068,47.695992],"type":"Point"}
}