{
  "type": "Feature",
  "properties": {
    "gn:admin1_code":"15.0",
    "gn:asciiname":"Kachmary",
    "gn:country_code":"UA",
    "gn:dem":225,
    "gn:feature_class":"P",
    "gn:feature_code":"PPL",
    "gn:name":"Kachmary",
    "gn:population":0,
    "gn:timezone":"Europe/Kiev",
    "iso:country":"UA",
    "name:und_x_variant":[
        "Kochman",
        "Kachmary"
    ],
    "wof:name":"Kachmary",
    "wof:placetype":"locality"
},
  "geometry": {"coordinates":[23.83362,50.11797],"type":"Point"}
}