{
  "type": "Feature",
  "properties": {
    "gn:admin1_code":"1.0",
    "gn:asciiname":"Chervonokhyzhyntsi",
    "gn:country_code":"UA",
    "gn:dem":115,
    "gn:feature_class":"P",
    "gn:feature_code":"PPL",
    "gn:name":"Chervonokhyzhyntsi",
    "gn:population":0,
    "gn:timezone":"Europe/Kiev",
    "iso:country":"UA",
    "name:ukr_x_preferred":[
        "Chervonokhyzhyntsi"
    ],
    "name:ukr_x_variant":[
        "\u0427\u0435\u0440\u0432\u043e\u043d\u043e\u0445\u0438\u0436\u0438\u043d\u0446\u0456"
    ],
    "wof:name":"Chervonokhyzhyntsi",
    "wof:placetype":"locality"
},
  "geometry": {"coordinates":[32.29239,49.55696],"type":"Point"}
}