{
  "type": "Feature",
  "properties": {
    "gn:admin1_code":"9.0",
    "gn:asciiname":"Mytkovtsy",
    "gn:country_code":"UA",
    "gn:dem":322,
    "gn:feature_class":"P",
    "gn:feature_code":"PPL",
    "gn:name":"Mytkovtsy",
    "gn:population":0,
    "gn:timezone":"Europe/Kiev",
    "iso:country":"UA",
    "wof:name":"Mytkovtsy",
    "wof:placetype":"locality"
},
  "geometry": {"coordinates":[27.32987,49.51029000000001],"type":"Point"}
}