{
  "type": "Feature",
  "properties": {
    "gn:admin1_code":"21.0",
    "gn:asciiname":"Suvorove",
    "gn:country_code":"UA",
    "gn:dem":167,
    "gn:feature_class":"P",
    "gn:feature_code":"PPL",
    "gn:name":"Suvorove",
    "gn:population":0,
    "gn:timezone":"Europe/Kiev",
    "iso:country":"UA",
    "name:eng_x_preferred":[
        "Suvorov"
    ],
    "name:rus_x_preferred":[
        "\u0421\u0443\u0432\u043e\u0440\u043e\u0432\u043e"
    ],
    "name:ukr_x_preferred":[
        "Suvorove"
    ],
    "name:ukr_x_variant":[
        "\u0421\u0443\u0432\u043e\u0440\u043e\u0432\u0435"
    ],
    "name:und_x_variant":[
        "Suvorovo"
    ],
    "wof:name":"Suvorove",
    "wof:placetype":"locality"
},
  "geometry": {"coordinates":[33.83685999999999,51.3871],"type":"Point"}
}