{
  "type": "Feature",
  "properties": {
    "gn:admin1_code":"22.0",
    "gn:asciiname":"Nesterovtsy",
    "gn:country_code":"UA",
    "gn:dem":348,
    "gn:feature_class":"P",
    "gn:feature_code":"PPL",
    "gn:name":"Nesterovtsy",
    "gn:population":0,
    "gn:timezone":"Europe/Kiev",
    "iso:country":"UA",
    "name:und_x_variant":[
        "Nesterowce",
        "Nesterovtse",
        "Nesterovtsy"
    ],
    "wof:name":"Nesterovtsy",
    "wof:placetype":"locality"
},
  "geometry": {"coordinates":[25.37723,49.69487],"type":"Point"}
}