{
  "type": "Feature",
  "properties": {
    "gn:admin1_code":"21.0",
    "gn:asciiname":"Ivolzhans'ke",
    "gn:country_code":"UA",
    "gn:dem":169,
    "gn:feature_class":"P",
    "gn:feature_code":"PPL",
    "gn:name":"Ivolzhans\u2019ke",
    "gn:population":0,
    "gn:timezone":"Europe/Kiev",
    "iso:country":"UA",
    "name:ukr_x_preferred":[
        "Ivolzhans\u2019ke"
    ],
    "name:ukr_x_variant":[
        "\u0406\u0432\u043e\u043b\u0436\u0430\u043d\u0441\u044c\u043a\u0435"
    ],
    "name:und_x_variant":[
        "Ivolzhanskoye"
    ],
    "wof:name":"Ivolzhans'ke",
    "wof:placetype":"locality"
},
  "geometry": {"coordinates":[34.87387,51.07095],"type":"Point"}
}