{
  "type": "Feature",
  "properties": {
    "iso:country":"UA",
    "name:ukr_x_preferred":[
        "\u041c\u0438\u0440\u043e\u043b\u044e\u0431\u0456\u0432\u043a\u0430"
    ],
    "name:unk_x_variant":[
        "Myrolyubivka"
    ],
    "qs:a0":"\u0423\u043a\u0440\u0430\u0457\u043d\u0430",
    "qs:a1":"*\u0412\u0456\u043d\u043d\u0438\u0446\u044c\u043a\u0430",
    "qs:a1_alt":"Vinnyts'ka",
    "qs:a1r":"0",
    "qs:a2":"\u041f\u0456\u0449\u0430\u043d\u0441\u044c\u043a\u0438\u0439",
    "qs:a2_alt":"Pischans'kyi",
    "qs:adm0":"\u0423\u043a\u0440\u0430\u0457\u043d\u0430",
    "qs:la_lc":"*",
    "qs:level":"locality",
    "qs:loc":"\u041c\u0438\u0440\u043e\u043b\u044e\u0431\u0456\u0432\u043a\u0430",
    "qs:loc_alt":"Myroliubivka",
    "qs:pop":0,
    "qs:type":"buffered point",
    "wd:wordcount":545,
    "wof:name":"\u041c\u0438\u0440\u043e\u043b\u044e\u0431\u0456\u0432\u043a\u0430",
    "wof:placetype":"locality"
},
  "geometry": {"coordinates":[28.842442,48.263111],"type":"Point"}
}