{
  "type": "Feature",
  "properties": {
    "gn:admin1_code":"7.0",
    "gn:asciiname":"Svitlychne",
    "gn:country_code":"UA",
    "gn:dem":166,
    "gn:feature_class":"P",
    "gn:feature_code":"PPL",
    "gn:name":"Svitlychne",
    "gn:population":0,
    "gn:timezone":"Europe/Kiev",
    "iso:country":"UA",
    "name:rus_x_preferred":[
        "\u0421\u0432\u0435\u0442\u043b\u0438\u0447\u043d\u043e\u0435"
    ],
    "name:ukr_x_preferred":[
        "\u0421\u0432\u0456\u0442\u043b\u0438\u0447\u043d\u0435"
    ],
    "name:und_x_variant":[
        "Svetlichnyy",
        "Svetlichnoye",
        "Svitlychne"
    ],
    "wof:name":"Svitlychne",
    "wof:placetype":"locality"
},
  "geometry": {"coordinates":[36.05367,50.32759],"type":"Point"}
}