{
  "type": "Feature",
  "properties": {
    "gn:admin1_code":"11.0",
    "gn:admin2_code":"700018",
    "gn:admin3_code":"11152982",
    "gn:asciiname":"Velikosel'ye",
    "gn:country_code":"UA",
    "gn:dem":9,
    "gn:elevation":"11.0",
    "gn:feature_class":"P",
    "gn:feature_code":"PPL",
    "gn:name":"Velikosel\u2019ye",
    "gn:population":346,
    "gn:timezone":"Europe/Simferopol",
    "iso:country":"UA",
    "name:eng_x_preferred":[
        "Velikosel\u2019ye"
    ],
    "name:rus_x_historical":[
        "\u0422\u0430\u0433\u0430\u043d\u0430\u0448\u043c\u0438\u0301\u043d",
        "\u0422\u043e\u0433\u0430\u043d\u0430\u0301\u0448-\u041c\u0438\u043d"
    ],
    "name:rus_x_preferred":[
        "\u0412\u0435\u043b\u0438\u043a\u043e\u0441\u0435\u043b\u044c\u0435"
    ],
    "name:rus_x_variant":[
        "\u0422\u0430\u0433\u0430\u043d\u0430\u0448\u043c\u0438\u0301\u043d",
        "\u0422\u043e\u0433\u0430\u043d\u0430\u0301\u0448-\u041c\u0438\u043d"
    ],
    "name:ukr_x_preferred":[
        "\u0412\u0435\u043b\u0438\u043a\u043e\u0441\u0456\u043b\u043b\u044f"
    ],
    "wof:name":"Velikosel'ye",
    "wof:placetype":"locality",
    "wof:population":346
},
  "geometry": {"coordinates":[34.74541,45.6219],"type":"Point"}
}