{
  "type": "Feature",
  "properties": {
    "gn:admin1_code":"21.0",
    "gn:asciiname":"Voznesenka",
    "gn:country_code":"UA",
    "gn:dem":162,
    "gn:feature_class":"P",
    "gn:feature_code":"PPL",
    "gn:name":"Voznesenka",
    "gn:population":0,
    "gn:timezone":"Europe/Kiev",
    "iso:country":"UA",
    "name:ukr_x_preferred":[
        "\u0412\u043e\u0437\u043d\u0435\u0441\u0435\u043d\u043a\u0430"
    ],
    "name:und_x_variant":[
        "Maloye Neplyuyevo",
        "Voznesenka"
    ],
    "wof:name":"Voznesenka",
    "wof:placetype":"locality"
},
  "geometry": {"coordinates":[33.69159000000001,51.0728],"type":"Point"}
}