{
  "type": "Feature",
  "properties": {
    "gn:admin1_code":"26.0",
    "gn:asciiname":"Stepanivka Druha",
    "gn:country_code":"UA",
    "gn:dem":20,
    "gn:feature_class":"P",
    "gn:feature_code":"PPL",
    "gn:name":"Stepanivka Druha",
    "gn:population":0,
    "gn:timezone":"Europe/Zaporozhye",
    "iso:country":"UA",
    "name:rus_x_preferred":[
        "\u0411\u043e\u0433\u0434\u0430\u043d\u043e\u0432\u043a\u0430"
    ],
    "name:ukr_x_preferred":[
        "\u0421\u0442\u0435\u043f\u0430\u043d\u0456\u0432\u043a\u0430 \u0414\u0440\u0443\u0433\u0430"
    ],
    "name:und_x_variant":[
        "Stepanovka",
        "Bogdanovka"
    ],
    "wof:name":"Stepanivka Druha",
    "wof:placetype":"locality"
},
  "geometry": {"coordinates":[35.94377,46.76641],"type":"Point"}
}