{
  "type": "Feature",
  "properties": {
    "gn:admin1_code":"14.0",
    "gn:asciiname":"Trubnyy",
    "gn:country_code":"UA",
    "gn:dem":207,
    "gn:feature_class":"P",
    "gn:feature_code":"PPL",
    "gn:name":"Trubnyy",
    "gn:population":0,
    "gn:timezone":"Europe/Zaporozhye",
    "iso:country":"UA",
    "name:ukr_x_preferred":[
        "Trubnyy"
    ],
    "name:ukr_x_variant":[
        "\u0422\u0440\u0443\u0431\u043d\u0438\u0439"
    ],
    "wof:name":"Trubnyy",
    "wof:placetype":"locality"
},
  "geometry": {"coordinates":[38.75253,48.16041],"type":"Point"}
}