{
  "type": "Feature",
  "properties": {
    "gn:admin1_code":"15.0",
    "gn:asciiname":"Tolshchev",
    "gn:country_code":"UA",
    "gn:dem":322,
    "gn:feature_class":"P",
    "gn:feature_code":"PPL",
    "gn:name":"Tolshchev",
    "gn:population":0,
    "gn:timezone":"Europe/Kiev",
    "iso:country":"UA",
    "name:und_x_variant":[
        "Tolshchuv",
        "Tolshchev"
    ],
    "wof:name":"Tolshchev",
    "wof:placetype":"locality"
},
  "geometry": {"coordinates":[24.11791,49.69478],"type":"Point"}
}