{
  "type": "Feature",
  "properties": {
    "gn:gn_country":"UA",
    "gn:gn_fcode":"PPL",
    "gn:gn_pop":0,
    "iso:country":"UA",
    "name:arm_x_preferred":[
        "\u0533\u0565\u0578\u0580\u0563\u056b\u0587\u056f\u0561"
    ],
    "name:chi_x_preferred":[
        "\u683c\u5967\u723e\u5409\u4f0a\u592b\u5361"
    ],
    "name:eng_x_preferred":[
        "Georgiyevka"
    ],
    "name:ger_x_preferred":[
        "Heorhijiwka"
    ],
    "name:lav_x_preferred":[
        "Heorhijivka"
    ],
    "name:rum_x_preferred":[
        "Heorhiivka"
    ],
    "name:rus_x_preferred":[
        "\u0413\u0435\u043e\u0440\u0433\u0438\u0435\u0432\u043a\u0430"
    ],
    "name:ukr_x_preferred":[
        "Heorhiyivka"
    ],
    "name:ukr_x_variant":[
        "\u0413\u0435\u043e\u0440\u0433\u0456\u0457\u0432\u043a\u0430"
    ],
    "name:unk_x_variant":[
        "Konoplyanka"
    ],
    "qs_pg:aaroncc":"UA",
    "qs_pg:gn_country":"UA",
    "qs_pg:gn_fcode":"PPL",
    "qs_pg:gn_pop":0,
    "qs_pg:name":"Georgiyevka",
    "qs_pg:name_adm0":"Ukraine",
    "qs_pg:name_adm1":"Luhans\u00b4ka Oblast\u00b4",
    "qs_pg:photos":26,
    "qs_pg:photos_1k":5,
    "qs_pg:photos_9k":1,
    "qs_pg:photos_9r":2,
    "qs_pg:photos_all":26,
    "qs_pg:photos_sr":2,
    "qs_pg:pop_sr":0,
    "qs_pg:qs_pg_placetype":"locality",
    "qs_pg:qs_pg_placetype_gp":"Town",
    "qs_pg:woe_adm0":23424976,
    "woe:adm0_id":23424976,
    "woe:name_adm0":"Ukraine",
    "woe:name_adm1":"Luhans\u00b4ka Oblast\u00b4",
    "woe:placetype":"Town",
    "wof:name":"Georgiyevka",
    "wof:placetype":"locality"
},
  "geometry": {"coordinates":[39.25278,48.42278],"type":"Point"}
}