{
  "type": "Feature",
  "properties": {
    "gn:admin1_code":"15.0",
    "gn:asciiname":"Chishki",
    "gn:country_code":"UA",
    "gn:dem":235,
    "gn:feature_class":"P",
    "gn:feature_code":"PPL",
    "gn:name":"Chishki",
    "gn:population":0,
    "gn:timezone":"Europe/Kiev",
    "iso:country":"UA",
    "wof:name":"Chishki",
    "wof:placetype":"locality"
},
  "geometry": {"coordinates":[24.94214,49.99243],"type":"Point"}
}