{
  "type": "Feature",
  "properties": {
    "gn:admin1_code":"21.0",
    "gn:asciiname":"Savelove",
    "gn:country_code":"UA",
    "gn:dem":171,
    "gn:feature_class":"P",
    "gn:feature_code":"PPL",
    "gn:name":"Savelove",
    "gn:population":0,
    "gn:timezone":"Europe/Kiev",
    "iso:country":"UA",
    "name:ukr_x_preferred":[
        "Savelove"
    ],
    "name:ukr_x_variant":[
        "\u0421\u0430\u0432\u0435\u043b\u043e\u0432\u0435"
    ],
    "name:und_x_variant":[
        "Savel\u2019yev"
    ],
    "wof:name":"Savelove",
    "wof:placetype":"locality"
},
  "geometry": {"coordinates":[35.11857,50.5649],"type":"Point"}
}