{
  "type": "Feature",
  "properties": {
    "gn:admin1_code":"5.0",
    "gn:asciiname":"Yunokomunarivs'k",
    "gn:country_code":"UA",
    "gn:dem":192,
    "gn:feature_class":"P",
    "gn:feature_code":"PPL",
    "gn:name":"Yunokomunarivs\u2019k",
    "gn:population":0,
    "gn:timezone":"Europe/Kiev",
    "iso:country":"UA",
    "name:ukr_x_preferred":[
        "Yunokomunarivs\u2019k"
    ],
    "name:ukr_x_variant":[
        "\u042e\u043d\u043e\u043a\u043e\u043c\u0443\u043d\u0430\u0440\u0456\u0432\u0441\u044c\u043a"
    ],
    "name:und_x_variant":[
        "Imeni Yunykh Kommunarov",
        "Yunokommunarskoye",
        "Yunykh Kommunarov",
        "Yunyy Kommunar",
        "Yunokommunarovskoye",
        "Yunokommunarovsk"
    ],
    "wof:name":"Yunokomunarivs'k",
    "wof:placetype":"locality"
},
  "geometry": {"coordinates":[38.2717,48.22225],"type":"Point"}
}