{
  "type": "Feature",
  "properties": {
    "gn:admin1_code":"15.0",
    "gn:asciiname":"Ortynychi",
    "gn:country_code":"UA",
    "gn:dem":273,
    "gn:feature_class":"P",
    "gn:feature_code":"PPL",
    "gn:name":"Ortynychi",
    "gn:population":0,
    "gn:timezone":"Europe/Kiev",
    "iso:country":"UA",
    "name:rus_x_preferred":[
        "\u041e\u0440\u0442\u044b\u043d\u0438\u0447\u0438"
    ],
    "name:ukr_x_preferred":[
        "Ortynychi"
    ],
    "name:ukr_x_variant":[
        "\u041e\u0440\u0442\u0438\u043d\u0438\u0447\u0456"
    ],
    "name:und_x_variant":[
        "Ortynichi",
        "Ortynitse"
    ],
    "wof:name":"Ortynychi",
    "wof:placetype":"locality"
},
  "geometry": {"coordinates":[23.46679,49.48289000000001],"type":"Point"}
}