{
  "type": "Feature",
  "properties": {
    "gn:admin1_code":"5.0",
    "gn:asciiname":"Bol'she-Vasyukovskiy",
    "gn:country_code":"UA",
    "gn:dem":137,
    "gn:feature_class":"P",
    "gn:feature_code":"PPL",
    "gn:name":"Bol\u2019she-Vasyukovskiy",
    "gn:population":0,
    "gn:timezone":"Europe/Kiev",
    "iso:country":"UA",
    "name:rus_x_preferred":[
        "Bol\u2019she-Vasyukovskiy"
    ],
    "wof:name":"Bol'she-Vasyukovskiy",
    "wof:placetype":"locality"
},
  "geometry": {"coordinates":[36.65,47.95],"type":"Point"}
}