{
  "type": "Feature",
  "properties": {
    "gn:admin1_code":"2.0",
    "gn:asciiname":"Pisky",
    "gn:country_code":"UA",
    "gn:dem":132,
    "gn:feature_class":"P",
    "gn:feature_code":"PPL",
    "gn:name":"Pisky",
    "gn:population":0,
    "gn:timezone":"Europe/Kiev",
    "iso:country":"UA",
    "name:ceb_x_preferred":[
        "Pisky"
    ],
    "name:deu_x_preferred":[
        "Pisky"
    ],
    "name:est_x_preferred":[
        "Pisk\u00f5"
    ],
    "name:swe_x_preferred":[
        "Pisky"
    ],
    "name:ukr_x_preferred":[
        "Pisky"
    ],
    "name:ukr_x_variant":[
        "\u041f\u0456\u0441\u043a\u0438"
    ],
    "name:und_x_variant":[
        "Peski"
    ],
    "wof:name":"Pisky",
    "wof:placetype":"locality"
},
  "geometry": {"coordinates":[32.14696,51.68005],"type":"Point"}
}