{
  "type": "Feature",
  "properties": {
    "gn:admin1_code":"4.0",
    "gn:asciiname":"Kardashi",
    "gn:country_code":"UA",
    "gn:dem":81,
    "gn:feature_class":"P",
    "gn:feature_code":"PPL",
    "gn:name":"Kardashi",
    "gn:population":0,
    "gn:timezone":"Europe/Kiev",
    "iso:country":"UA",
    "name:ukr_x_preferred":[
        "Kardashi"
    ],
    "name:ukr_x_variant":[
        "\u041a\u0430\u0440\u0434\u0430\u0448\u0456"
    ],
    "wof:name":"Kardashi",
    "wof:placetype":"locality"
},
  "geometry": {"coordinates":[36.26447,48.33057],"type":"Point"}
}