{
  "type": "Feature",
  "properties": {
    "gn:admin1_code":"18.0",
    "gn:asciiname":"Onyshchenky",
    "gn:country_code":"UA",
    "gn:dem":86,
    "gn:feature_class":"P",
    "gn:feature_code":"PPL",
    "gn:name":"Onyshchenky",
    "gn:population":0,
    "gn:timezone":"Europe/Kiev",
    "iso:country":"UA",
    "name:ukr_x_preferred":[
        "Onyshchenky"
    ],
    "name:ukr_x_variant":[
        "\u041e\u043d\u0438\u0449\u0435\u043d\u043a\u0438"
    ],
    "wof:name":"Onyshchenky",
    "wof:placetype":"locality"
},
  "geometry": {"coordinates":[33.89918,49.59204],"type":"Point"}
}