{
  "type": "Feature",
  "properties": {
    "gn:admin1_code":"2.0",
    "gn:asciiname":"Starosillya",
    "gn:country_code":"UA",
    "gn:dem":147,
    "gn:feature_class":"P",
    "gn:feature_code":"PPL",
    "gn:name":"Starosillya",
    "gn:population":0,
    "gn:timezone":"Europe/Kiev",
    "iso:country":"UA",
    "name:ukr_x_preferred":[
        "\u0421\u0442\u0430\u0440\u043e\u0441\u0456\u043b\u043b\u044f"
    ],
    "name:und_x_variant":[
        "Starosel\u2019ye"
    ],
    "wof:name":"Starosillya",
    "wof:placetype":"locality"
},
  "geometry": {"coordinates":[31.61589,52.01516],"type":"Point"}
}