{
  "type": "Feature",
  "properties": {
    "iso:country":"UA",
    "name:eng_x_preferred":[
        "Snezhkov"
    ],
    "name:rus_x_preferred":[
        "\u0421\u043d\u0435\u0436\u043a\u043e\u0432"
    ],
    "name:ukr_x_preferred":[
        "\u0421\u043d\u0456\u0436\u043a\u0456\u0432"
    ],
    "name:unk_x_variant":[
        "Ivanivka"
    ],
    "qs:a0":"\u0423\u043a\u0440\u0430\u0457\u043d\u0430",
    "qs:a1":"*\u0425\u0430\u0440\u043a\u0456\u0432\u0441\u044c\u043a\u0430",
    "qs:a1_alt":"Kharkivs'ka",
    "qs:a1r":"0",
    "qs:a2":"\u0412\u0430\u043b\u043a\u0456\u0432\u0441\u044c\u043a\u0438\u0439",
    "qs:a2_alt":"Valkivs'kyi",
    "qs:adm0":"\u0423\u043a\u0440\u0430\u0457\u043d\u0430",
    "qs:la_lc":"*",
    "qs:level":"locality",
    "qs:loc":"\u0421\u043d\u0456\u0436\u043a\u0456\u0432",
    "qs:loc_alt":"Snizhkiv",
    "qs:pop":0,
    "qs:type":"buffered point",
    "wof:name":"\u0421\u043d\u0456\u0436\u043a\u0456\u0432",
    "wof:placetype":"locality"
},
  "geometry": {"coordinates":[35.523221,49.791017],"type":"Point"}
}