{
  "type": "Feature",
  "properties": {
    "gn:admin1_code":"9.0",
    "gn:asciiname":"Ponora",
    "gn:country_code":"UA",
    "gn:dem":223,
    "gn:feature_class":"P",
    "gn:feature_code":"PPL",
    "gn:name":"Ponora",
    "gn:population":0,
    "gn:timezone":"Europe/Kiev",
    "iso:country":"UA",
    "name:ukr_x_preferred":[
        "Ponora"
    ],
    "name:ukr_x_variant":[
        "\u041f\u043e\u043d\u043e\u0440\u0430"
    ],
    "wof:name":"Ponora",
    "wof:placetype":"locality"
},
  "geometry": {"coordinates":[26.84183,50.4483],"type":"Point"}
}