{
  "type": "Feature",
  "properties": {
    "gn:admin1_code":"19.0",
    "gn:asciiname":"Horynychi",
    "gn:country_code":"UA",
    "gn:dem":140,
    "gn:feature_class":"P",
    "gn:feature_code":"PPL",
    "gn:name":"Horynychi",
    "gn:population":0,
    "gn:timezone":"Europe/Kiev",
    "iso:country":"UA",
    "name:ukr_x_preferred":[
        "Horynychi"
    ],
    "name:ukr_x_variant":[
        "\u0413\u043e\u0440\u0438\u043d\u0438\u0447\u0456"
    ],
    "name:und_x_variant":[
        "Goryniche",
        "Gorynichi"
    ],
    "wof:name":"Horynychi",
    "wof:placetype":"locality"
},
  "geometry": {"coordinates":[25.80038,51.9262],"type":"Point"}
}