{
  "type": "Feature",
  "properties": {
    "gn:admin1_code":"18.0",
    "gn:asciiname":"Malyye Krynki",
    "gn:cc2":"UA",
    "gn:country_code":"UA",
    "gn:dem":100,
    "gn:feature_class":"P",
    "gn:feature_code":"PPL",
    "gn:name":"Malyye Krynki",
    "gn:population":0,
    "gn:timezone":"Europe/Kiev",
    "iso:country":"UA",
    "name:und_x_variant":[
        "Kulyabovka",
        "Malyye Krynki"
    ],
    "wof:name":"Malyye Krynki",
    "wof:placetype":"locality"
},
  "geometry": {"coordinates":[33.46667,49.46667],"type":"Point"}
}