{
  "type": "Feature",
  "properties": {
    "gn:admin1_code":"9.0",
    "gn:asciiname":"Zastavky",
    "gn:country_code":"UA",
    "gn:dem":291,
    "gn:feature_class":"P",
    "gn:feature_code":"PPL",
    "gn:name":"Zastavky",
    "gn:population":0,
    "gn:timezone":"Europe/Kiev",
    "iso:country":"UA",
    "name:ukr_x_preferred":[
        "Zastavky"
    ],
    "name:ukr_x_variant":[
        "\u0417\u0430\u0441\u0442\u0430\u0432\u043a\u0438"
    ],
    "name:und_x_variant":[
        "Zastavki"
    ],
    "wof:name":"Zastavky",
    "wof:placetype":"locality"
},
  "geometry": {"coordinates":[26.95023,49.69776],"type":"Point"}
}