{
  "type": "Feature",
  "properties": {
    "gn:admin1_code":"25.0",
    "gn:asciiname":"Bukivts'ovo",
    "gn:country_code":"UA",
    "gn:dem":434,
    "gn:feature_class":"P",
    "gn:feature_code":"PPL",
    "gn:name":"Bukivts\u2019ovo",
    "gn:population":0,
    "gn:timezone":"Europe/Uzhgorod",
    "iso:country":"UA",
    "name:ukr_x_preferred":[
        "\u0411\u0443\u043a\u0456\u0432\u0446\u044c\u043e\u0432\u043e"
    ],
    "name:und_x_variant":[
        "Bukovtsevo",
        "Bukivtseva",
        "Bukovets",
        "Bukivtseve",
        "Bukivts\u2019ovo"
    ],
    "wof:name":"Bukivts'ovo",
    "wof:placetype":"locality"
},
  "geometry": {"coordinates":[22.67314,48.82384],"type":"Point"}
}