{
  "type": "Feature",
  "properties": {
    "gn:admin1_code":"17.0",
    "gn:asciiname":"Rozselenets'",
    "gn:country_code":"UA",
    "gn:dem":58,
    "gn:feature_class":"P",
    "gn:feature_code":"PPL",
    "gn:name":"Rozselenets\u2019",
    "gn:population":0,
    "gn:timezone":"Europe/Kiev",
    "iso:country":"UA",
    "name:ukr_x_preferred":[
        "Chervonyy Rozselenets\u2019"
    ],
    "name:ukr_x_variant":[
        "\u0427\u0435\u0440\u0432\u043e\u043d\u0438\u0439 \u0420\u043e\u0437\u0441\u0435\u043b\u0435\u043d\u0435\u0446\u044c",
        "Rozselenets\u2019",
        "\u0420\u043e\u0437\u0441\u0435\u043b\u0435\u043d\u0435\u0446\u044c"
    ],
    "name:und_x_variant":[
        "Krasny Pereselenets",
        "Krasnyy Pereselenets",
        "Chervonyy Rasselenets"
    ],
    "wof:name":"Rozselenets'",
    "wof:placetype":"locality"
},
  "geometry": {"coordinates":[30.43942,46.46314],"type":"Point"}
}