{
  "type": "Feature",
  "properties": {
    "gn:admin1_code":"11.0",
    "gn:admin2_code":"712585",
    "gn:admin3_code":"11152833.0",
    "gn:asciiname":"Mel'niki",
    "gn:country_code":"UA",
    "gn:dem":96,
    "gn:elevation":"104.0",
    "gn:feature_class":"P",
    "gn:feature_code":"PPL",
    "gn:name":"Mel\u2019niki",
    "gn:population":285,
    "gn:timezone":"Europe/Simferopol",
    "iso:country":"UA",
    "name:eng_x_preferred":[
        "Mel\u2019niki"
    ],
    "name:rus_x_historical":[
        "\u0428\u0430\u0432\u0445\u0430\u0301\u043b"
    ],
    "name:rus_x_preferred":[
        "\u041c\u0435\u043b\u044c\u043d\u0438\u043a\u0438"
    ],
    "name:rus_x_variant":[
        "\u0428\u0430\u0432\u0445\u0430\u0301\u043b"
    ],
    "name:ukr_x_preferred":[
        "\u041c\u0435\u043b\u044c\u043d\u0438\u043a\u0438"
    ],
    "wof:name":"Mel'niki",
    "wof:placetype":"locality",
    "wof:population":285
},
  "geometry": {"coordinates":[34.62307,45.19909000000001],"type":"Point"}
}