{
  "type": "Feature",
  "properties": {
    "gn:admin1_code":"21.0",
    "gn:asciiname":"Hurynivka",
    "gn:country_code":"UA",
    "gn:dem":148,
    "gn:feature_class":"P",
    "gn:feature_code":"PPL",
    "gn:name":"Hurynivka",
    "gn:population":0,
    "gn:timezone":"Europe/Kiev",
    "iso:country":"UA",
    "name:ukr_x_preferred":[
        "\u0413\u0443\u0440\u0438\u043d\u0456\u0432\u043a\u0430"
    ],
    "name:und_x_variant":[
        "Gurynevka",
        "Gurinov",
        "Gurinevka",
        "Gurinovka",
        "Hurynivka"
    ],
    "wof:name":"Hurynivka",
    "wof:placetype":"locality"
},
  "geometry": {"coordinates":[34.41718,51.15977],"type":"Point"}
}