{
  "type": "Feature",
  "properties": {
    "gn:admin1_code":"9.0",
    "gn:asciiname":"Tsvitokha",
    "gn:country_code":"UA",
    "gn:dem":223,
    "gn:feature_class":"P",
    "gn:feature_code":"PPL",
    "gn:name":"Tsvitokha",
    "gn:population":0,
    "gn:timezone":"Europe/Kiev",
    "iso:country":"UA",
    "name:ukr_x_preferred":[
        "Tsvitokha"
    ],
    "name:ukr_x_variant":[
        "\u0426\u0432\u0456\u0442\u043e\u0445\u0430"
    ],
    "name:und_x_variant":[
        "Tsvetokha"
    ],
    "wof:name":"Tsvitokha",
    "wof:placetype":"locality"
},
  "geometry": {"coordinates":[26.94379,50.24733],"type":"Point"}
}