{
  "type": "Feature",
  "properties": {
    "gn:admin1_code":"8.0",
    "gn:asciiname":"Angoli",
    "gn:country_code":"UA",
    "gn:dem":28,
    "gn:feature_class":"P",
    "gn:feature_code":"PPL",
    "gn:name":"Angoli",
    "gn:population":0,
    "gn:timezone":"Europe/Kiev",
    "iso:country":"UA",
    "name:und_x_variant":[
        "Angolivskiye",
        "Angoli"
    ],
    "wof:name":"Angoli",
    "wof:placetype":"locality"
},
  "geometry": {"coordinates":[33.65225,46.47545],"type":"Point"}
}