{
  "type": "Feature",
  "properties": {
    "gn:admin1_code":"11.0",
    "gn:admin2_code":"693803",
    "gn:admin3_code":"11152605.0",
    "gn:asciiname":"Dmitrovo",
    "gn:country_code":"UA",
    "gn:dem":268,
    "gn:elevation":"261.0",
    "gn:feature_class":"P",
    "gn:feature_code":"PPL",
    "gn:name":"Dmitrovo",
    "gn:population":265,
    "gn:timezone":"Europe/Simferopol",
    "iso:country":"UA",
    "name:eng_x_preferred":[
        "Dmitrovo"
    ],
    "name:rus_x_historical":[
        "\u041a\u0430\u043b\u043c\u0443\u0301-\u041a\u0430\u0440\u0430\u0301"
    ],
    "name:rus_x_preferred":[
        "\u0414\u043c\u0438\u0442\u0440\u043e\u0432\u043e"
    ],
    "name:rus_x_variant":[
        "\u041a\u0430\u043b\u043c\u0443\u0301-\u041a\u0430\u0440\u0430\u0301"
    ],
    "name:ukr_x_preferred":[
        "\u0414\u043c\u0438\u0442\u0440\u043e\u0432\u0435"
    ],
    "wof:name":"Dmitrovo",
    "wof:placetype":"locality",
    "wof:population":265
},
  "geometry": {"coordinates":[34.25594,45.05841],"type":"Point"}
}