{
  "type": "Feature",
  "properties": {
    "gn:admin1_code":"15.0",
    "gn:asciiname":"Komarovichi",
    "gn:country_code":"UA",
    "gn:dem":240,
    "gn:feature_class":"P",
    "gn:feature_code":"PPL",
    "gn:name":"Komarovichi",
    "gn:population":0,
    "gn:timezone":"Europe/Kiev",
    "iso:country":"UA",
    "name:und_x_variant":[
        "Romarovichi",
        "Komarovychi",
        "Komarovichi"
    ],
    "wof:name":"Komarovichi",
    "wof:placetype":"locality"
},
  "geometry": {"coordinates":[22.85171,49.62862],"type":"Point"}
}