{
  "type": "Feature",
  "properties": {
    "gn:admin1_code":"16.0",
    "gn:asciiname":"Kamennopol'",
    "gn:country_code":"UA",
    "gn:dem":101,
    "gn:feature_class":"P",
    "gn:feature_code":"PPL",
    "gn:name":"Kamennopol\u2019",
    "gn:population":0,
    "gn:timezone":"Europe/Kiev",
    "iso:country":"UA",
    "name:und_x_variant":[
        "Shteynfel\u2019d",
        "Kamennopol\u2019"
    ],
    "wof:name":"Kamennopol'",
    "wof:placetype":"locality"
},
  "geometry": {"coordinates":[31.5951,47.9622],"type":"Point"}
}