{
  "type": "Feature",
  "properties": {
    "gn:admin1_code":"5.0",
    "gn:asciiname":"Peremoha",
    "gn:country_code":"UA",
    "gn:dem":53,
    "gn:feature_class":"P",
    "gn:feature_code":"PPL",
    "gn:name":"Peremoha",
    "gn:population":0,
    "gn:timezone":"Europe/Kiev",
    "iso:country":"UA",
    "name:ukr_x_preferred":[
        "Peremoha"
    ],
    "name:ukr_x_variant":[
        "\u041f\u0435\u0440\u0435\u043c\u043e\u0433\u0430"
    ],
    "name:und_x_variant":[
        "Peremoga"
    ],
    "wof:name":"Peremoha",
    "wof:placetype":"locality"
},
  "geometry": {"coordinates":[37.40441,47.28681],"type":"Point"}
}