{
  "type": "Feature",
  "properties": {
    "gn:admin1_code":"9.0",
    "gn:asciiname":"Kolki",
    "gn:country_code":"UA",
    "gn:dem":304,
    "gn:feature_class":"P",
    "gn:feature_code":"PPL",
    "gn:name":"Kolki",
    "gn:population":0,
    "gn:timezone":"Europe/Kiev",
    "iso:country":"UA",
    "name:ceb_x_preferred":[
        "Kolki"
    ],
    "name:fra_x_preferred":[
        "Kolki"
    ],
    "name:mai_x_preferred":[
        "\u0915\u094b\u0932\u094d\u0915\u0940"
    ],
    "name:msa_x_preferred":[
        "Kolki"
    ],
    "name:nep_x_preferred":[
        "\u0915\u094b\u0932\u094d\u0915\u0940"
    ],
    "name:new_x_preferred":[
        "\u0915\u094b\u0932\u094d\u0915\u0940"
    ],
    "name:pol_x_preferred":[
        "Kolki"
    ],
    "wof:name":"Kolki",
    "wof:placetype":"locality"
},
  "geometry": {"coordinates":[26.60185,49.79257],"type":"Point"}
}