{
  "type": "Feature",
  "properties": {
    "gn:admin1_code":"5.0",
    "gn:asciiname":"Kholmyste",
    "gn:country_code":"UA",
    "gn:dem":130,
    "gn:feature_class":"P",
    "gn:feature_code":"PPL",
    "gn:name":"Kholmyste",
    "gn:population":0,
    "gn:timezone":"Europe/Kiev",
    "iso:country":"UA",
    "name:ukr_x_preferred":[
        "Kholmyste"
    ],
    "name:ukr_x_variant":[
        "\u0425\u043e\u043b\u043c\u0438\u0441\u0442\u0435"
    ],
    "wof:name":"Kholmyste",
    "wof:placetype":"locality"
},
  "geometry": {"coordinates":[38.10754,47.94062],"type":"Point"}
}