{
  "type": "Feature",
  "properties": {
    "gn:admin1_code":"14.0",
    "gn:asciiname":"Sadovo-Khrustal'nens'kyy",
    "gn:country_code":"UA",
    "gn:dem":185,
    "gn:feature_class":"P",
    "gn:feature_code":"PPL",
    "gn:name":"Sadovo-Khrustal\u2019nens\u2019kyy",
    "gn:population":0,
    "gn:timezone":"Europe/Zaporozhye",
    "iso:country":"UA",
    "name:rus_x_preferred":[
        "Sadovo-Khrustal\u2019nenskiy"
    ],
    "name:ukr_x_preferred":[
        "Sadovo-Khrustal\u2019nens\u2019kyy"
    ],
    "name:ukr_x_variant":[
        "\u0421\u0430\u0434\u043e\u0432\u043e-\u0425\u0440\u0443\u0441\u0442\u0430\u043b\u044c\u043d\u0435\u043d\u0441\u044c\u043a\u0438\u0439"
    ],
    "wof:name":"Sadovo-Khrustal'nens'kyy",
    "wof:placetype":"locality"
},
  "geometry": {"coordinates":[38.72799000000001,48.15104],"type":"Point"}
}