{
  "type": "Feature",
  "properties": {
    "gn:admin1_code":"16.0",
    "gn:asciiname":"Vossiyatskoye",
    "gn:country_code":"UA",
    "gn:dem":60,
    "gn:feature_class":"P",
    "gn:feature_code":"PPL",
    "gn:name":"Vossiyatskoye",
    "gn:population":0,
    "gn:timezone":"Europe/Kiev",
    "iso:country":"UA",
    "wof:name":"Vossiyatskoye",
    "wof:placetype":"locality"
},
  "geometry": {"coordinates":[32.11284000000001,47.66047],"type":"Point"}
}