{
  "type": "Feature",
  "properties": {
    "gn:admin1_code":"18.0",
    "gn:asciiname":"Natalenky",
    "gn:country_code":"UA",
    "gn:dem":81,
    "gn:feature_class":"P",
    "gn:feature_code":"PPL",
    "gn:name":"Natalenky",
    "gn:population":0,
    "gn:timezone":"Europe/Kiev",
    "iso:country":"UA",
    "name:ukr_x_preferred":[
        "Natalenky"
    ],
    "name:ukr_x_variant":[
        "\u041d\u0430\u0442\u0430\u043b\u0435\u043d\u043a\u0438"
    ],
    "wof:name":"Natalenky",
    "wof:placetype":"locality"
},
  "geometry": {"coordinates":[32.84375,49.59149],"type":"Point"}
}