{
  "type": "Feature",
  "properties": {
    "gn:admin1_code":"4.0",
    "gn:asciiname":"Novovitebs'ke",
    "gn:country_code":"UA",
    "gn:dem":85,
    "gn:feature_class":"P",
    "gn:feature_code":"PPL",
    "gn:name":"Novovitebs\u2019ke",
    "gn:population":0,
    "gn:timezone":"Europe/Kiev",
    "iso:country":"UA",
    "name:ukr_x_preferred":[
        "Novovitebs\u2019ke"
    ],
    "name:ukr_x_variant":[
        "\u041d\u043e\u0432\u043e\u0432\u0456\u0442\u0435\u0431\u0441\u044c\u043a\u0435"
    ],
    "name:und_x_variant":[
        "Novyy Vitebsk",
        "Novo-Vitebsk"
    ],
    "wof:name":"Novovitebs'ke",
    "wof:placetype":"locality"
},
  "geometry": {"coordinates":[33.89584,47.97344],"type":"Point"}
}