{
  "type": "Feature",
  "properties": {
    "gn:admin1_code":"5.0",
    "gn:asciiname":"Nazarivka",
    "gn:country_code":"UA",
    "gn:dem":190,
    "gn:feature_class":"P",
    "gn:feature_code":"PPL",
    "gn:name":"Nazarivka",
    "gn:population":0,
    "gn:timezone":"Europe/Kiev",
    "iso:country":"UA",
    "name:ukr_x_preferred":[
        "Nazarivka"
    ],
    "name:ukr_x_variant":[
        "\u041d\u0430\u0437\u0430\u0440\u0456\u0432\u043a\u0430"
    ],
    "name:und_x_variant":[
        "Nazarovka"
    ],
    "wof:name":"Nazarivka",
    "wof:placetype":"locality"
},
  "geometry": {"coordinates":[37.11267,47.32848],"type":"Point"}
}