{
  "type": "Feature",
  "properties": {
    "gn:admin1_code":"5.0",
    "gn:asciiname":"Chervonyy Zhovten'",
    "gn:country_code":"UA",
    "gn:dem":207,
    "gn:feature_class":"P",
    "gn:feature_code":"PPL",
    "gn:name":"Chervonyy Zhovten\u2019",
    "gn:population":0,
    "gn:timezone":"Europe/Kiev",
    "iso:country":"UA",
    "name:ukr_x_historical":[
        "Chervonyi Zhovten",
        "Chervonyy Zhovten\u2019",
        "\u0427\u0435\u0440\u0432\u043e\u043d\u0438\u0439 \u0416\u043e\u0432\u0442\u0435\u043d\u044c"
    ],
    "name:ukr_x_preferred":[
        "\u0411\u0430\u043b\u043a\u0430"
    ],
    "name:ukr_x_variant":[
        "Chervonyi Zhovten",
        "Chervonyy Zhovten\u2019",
        "\u0427\u0435\u0440\u0432\u043e\u043d\u0438\u0439 \u0416\u043e\u0432\u0442\u0435\u043d\u044c"
    ],
    "wof:name":"Chervonyy Zhovten'",
    "wof:placetype":"locality"
},
  "geometry": {"coordinates":[38.7341,47.97174],"type":"Point"}
}