{
  "type": "Feature",
  "properties": {
    "gn:admin1_code":"7.0",
    "gn:asciiname":"Koverivka",
    "gn:country_code":"UA",
    "gn:dem":188,
    "gn:feature_class":"P",
    "gn:feature_code":"PPL",
    "gn:name":"Koverivka",
    "gn:population":0,
    "gn:timezone":"Europe/Kiev",
    "iso:country":"UA",
    "name:ukr_x_preferred":[
        "Koverivka"
    ],
    "name:ukr_x_variant":[
        "\u041a\u043e\u0432\u0435\u0440\u0456\u0432\u043a\u0430"
    ],
    "wof:name":"Koverivka",
    "wof:placetype":"locality"
},
  "geometry": {"coordinates":[35.66138,49.89724],"type":"Point"}
}