{
  "type": "Feature",
  "properties": {
    "gn:admin1_code":"18.0",
    "gn:asciiname":"Teremets'ke",
    "gn:country_code":"UA",
    "gn:dem":97,
    "gn:feature_class":"P",
    "gn:feature_code":"PPL",
    "gn:name":"Teremets\u2019ke",
    "gn:population":0,
    "gn:timezone":"Europe/Kiev",
    "iso:country":"UA",
    "name:ukr_x_preferred":[
        "Teremets\u2019ke"
    ],
    "name:ukr_x_variant":[
        "\u0422\u0435\u0440\u0435\u043c\u0435\u0446\u044c\u043a\u0435"
    ],
    "wof:name":"Teremets'ke",
    "wof:placetype":"locality"
},
  "geometry": {"coordinates":[32.59696,49.84228],"type":"Point"}
}