{
  "type": "Feature",
  "properties": {
    "gn:admin1_code":"25.0",
    "gn:asciiname":"Kopynivtsi",
    "gn:country_code":"UA",
    "gn:dem":155,
    "gn:feature_class":"P",
    "gn:feature_code":"PPL",
    "gn:name":"Kopynivtsi",
    "gn:population":0,
    "gn:timezone":"Europe/Uzhgorod",
    "iso:country":"UA",
    "name:ukr_x_preferred":[
        "\u041a\u043e\u043f\u0438\u043d\u0456\u0432\u0446\u0456"
    ],
    "name:und_x_variant":[
        "Kopinovtsy",
        "Kopynovtsy"
    ],
    "wof:name":"Kopynivtsi",
    "wof:placetype":"locality"
},
  "geometry": {"coordinates":[22.63952,48.54336],"type":"Point"}
}