{
  "type": "Feature",
  "properties": {
    "iso:country":"UA",
    "name:ceb_x_preferred":[
        "Crasnencoe"
    ],
    "name:dan_x_preferred":[
        "Crasnencoe"
    ],
    "name:deu_x_preferred":[
        "Crasnencoe"
    ],
    "name:eng_x_preferred":[
        "Crasnencoe"
    ],
    "name:eus_x_preferred":[
        "Crasnencoe"
    ],
    "name:fra_x_preferred":[
        "Crasnencoe"
    ],
    "name:ita_x_preferred":[
        "Crasnencoe"
    ],
    "name:nld_x_preferred":[
        "Crasnencoe"
    ],
    "name:nno_x_preferred":[
        "Crasnencoe"
    ],
    "name:nob_x_preferred":[
        "Crasnencoe"
    ],
    "name:pol_x_preferred":[
        "\u041a\u043e\u0437\u0438\u043d"
    ],
    "name:pol_x_variant":[
        "Crasnencoe"
    ],
    "name:por_x_preferred":[
        "Crasnencoe"
    ],
    "name:ron_x_preferred":[
        "Crasnencoe"
    ],
    "name:rus_x_preferred":[
        "\u041a\u0440\u0430\u0441\u043d\u0435\u043d\u044c\u043a\u043e\u0435"
    ],
    "name:spa_x_preferred":[
        "Crasnencoe"
    ],
    "name:swe_x_preferred":[
        "Crasnencoe"
    ],
    "name:tur_x_preferred":[
        "Crasnencoe"
    ],
    "name:ukr_x_preferred":[
        "Dmytrivka"
    ],
    "name:ukr_x_variant":[
        "\u0414\u043c\u0438\u0442\u0440\u0456\u0432\u043a\u0430",
        "\u041a\u0440\u0430\u0441\u043d\u0435\u043d\u044c\u043a\u0435"
    ],
    "name:unk_x_variant":[
        "Dmitrovka"
    ],
    "qs:a0":"\u0423\u043a\u0440\u0430\u0457\u043d\u0430",
    "qs:a1":"*\u041a\u0438\u0457\u0432\u0441\u044c\u043a\u0430",
    "qs:a1_alt":"Kyivs'ka",
    "qs:a1r":"0",
    "qs:a2":"\u041a\u0438\u0454\u0432\u043e-\u0421\u0432\u044f\u0442\u043e\u0448\u0438\u043d\u0441\u044c\u043a\u0438\u0439",
    "qs:a2_alt":"Kyievo-Sviatoshyns'kyi",
    "qs:adm0":"\u0423\u043a\u0440\u0430\u0457\u043d\u0430",
    "qs:la_lc":"*",
    "qs:level":"locality",
    "qs:loc":"\u0414\u043c\u0438\u0442\u0440\u0456\u0432\u043a\u0430",
    "qs:loc_alt":"Dmytrivka",
    "qs:pop":0,
    "qs:type":"buffered point",
    "wd:wordcount":63,
    "wof:name":"\u0414\u043c\u0438\u0442\u0440\u0456\u0432\u043a\u0430",
    "wof:placetype":"locality"
},
  "geometry": {"coordinates":[30.181072,50.455583],"type":"Point"}
}