{
  "type": "Feature",
  "properties": {
    "gn:admin1_code":"15.0",
    "gn:asciiname":"Doroshuv Velikiy",
    "gn:country_code":"UA",
    "gn:dem":249,
    "gn:feature_class":"P",
    "gn:feature_code":"PPL",
    "gn:name":"Doroshuv Velikiy",
    "gn:population":0,
    "gn:timezone":"Europe/Kiev",
    "iso:country":"UA",
    "name:und_x_variant":[
        "Doroshuv Vel\u2019ke",
        "Doroshuv Velikiy"
    ],
    "wof:name":"Doroshuv Velikiy",
    "wof:placetype":"locality"
},
  "geometry": {"coordinates":[24.05676,49.95073],"type":"Point"}
}