{
  "type": "Feature",
  "properties": {
    "gn:admin1_code":"5.0",
    "gn:asciiname":"Kalynove",
    "gn:country_code":"UA",
    "gn:dem":208,
    "gn:feature_class":"P",
    "gn:feature_code":"PPL",
    "gn:name":"Kalynove",
    "gn:population":0,
    "gn:timezone":"Europe/Kiev",
    "iso:country":"UA",
    "name:crh_x_preferred":[
        "Kal\u0131nove"
    ],
    "name:deu_x_preferred":[
        "Kalynowe"
    ],
    "name:ron_x_preferred":[
        "Kal\u00eenove"
    ],
    "name:rus_x_preferred":[
        "\u041a\u0430\u043b\u0438\u043d\u043e\u0432\u043e"
    ],
    "name:ukr_x_preferred":[
        "Kalynove"
    ],
    "name:ukr_x_variant":[
        "\u041a\u0430\u043b\u0438\u043d\u043e\u0432\u0435"
    ],
    "name:zho_x_preferred":[
        "\u5361\u5229\u8afe\u97cb"
    ],
    "wof:name":"Kalynove",
    "wof:placetype":"locality"
},
  "geometry": {"coordinates":[37.44119,48.13931],"type":"Point"}
}