{
  "type": "Feature",
  "properties": {
    "gn:admin1_code":"19.0",
    "gn:asciiname":"Pidlisky",
    "gn:country_code":"UA",
    "gn:dem":243,
    "gn:feature_class":"P",
    "gn:feature_code":"PPL",
    "gn:name":"Pidlisky",
    "gn:population":0,
    "gn:timezone":"Europe/Kiev",
    "iso:country":"UA",
    "name:ukr_x_preferred":[
        "Pidlisky"
    ],
    "name:ukr_x_variant":[
        "\u041f\u0456\u0434\u043b\u0456\u0441\u043a\u0438"
    ],
    "name:und_x_variant":[
        "Podleski"
    ],
    "wof:name":"Pidlisky",
    "wof:placetype":"locality"
},
  "geometry": {"coordinates":[26.45967000000001,50.57838],"type":"Point"}
}