{
  "type": "Feature",
  "properties": {
    "iso:country":"UA",
    "name:arm_x_preferred":[
        "\u054d\u0565\u056c\u0581\u0578"
    ],
    "name:chi_x_preferred":[
        "\u897f\u5229\u91c7"
    ],
    "name:dut_x_preferred":[
        "Siltse"
    ],
    "name:eng_x_preferred":[
        "Siltse"
    ],
    "name:epo_x_preferred":[
        "Siljce"
    ],
    "name:ger_x_preferred":[
        "Silze"
    ],
    "name:hun_x_preferred":[
        "Beregkisfalud"
    ],
    "name:rum_x_preferred":[
        "Sil\u021be"
    ],
    "name:rus_x_preferred":[
        "Sel\u2019tso"
    ],
    "name:ukr_x_preferred":[
        "\u0421\u0456\u043b\u044c\u0446\u0435"
    ],
    "name:unk_x_variant":[
        "Sel\u2019tse"
    ],
    "qs:a0":"\u0423\u043a\u0440\u0430\u0457\u043d\u0430",
    "qs:a1":"*\u0417\u0430\u043a\u0430\u0440\u043f\u0430\u0442\u0441\u044c\u043a\u0430",
    "qs:a1_alt":"Zakarpats'ka",
    "qs:a1r":"0",
    "qs:a2":"\u0406\u0440\u0448\u0430\u0432\u0441\u044c\u043a\u0438\u0439",
    "qs:a2_alt":"Irshavs'kyi",
    "qs:adm0":"\u0423\u043a\u0440\u0430\u0457\u043d\u0430",
    "qs:la_lc":"*",
    "qs:level":"locality",
    "qs:loc":"\u0421\u0456\u043b\u044c\u0446\u0435",
    "qs:loc_alt":"Sil'tse",
    "qs:pop":0,
    "qs:type":"buffered point",
    "wd:wordcount":20505,
    "wof:name":"\u0421\u0456\u043b\u044c\u0446\u0435",
    "wof:placetype":"locality"
},
  "geometry": {"coordinates":[22.982035,48.287531],"type":"Point"}
}