{
  "type": "Feature",
  "properties": {
    "iso:country":"UA",
    "name:bel_x_preferred":[
        "\u0421\u0442\u044d\u043f\u0430\u043d\u044c"
    ],
    "name:cat_x_preferred":[
        "Stepan"
    ],
    "name:ceb_x_preferred":[
        "Stepan'"
    ],
    "name:ces_x_preferred":[
        "Stepa\u0148"
    ],
    "name:che_x_preferred":[
        "\u0421\u0442\u0435\u043f\u0430\u043d\u044c"
    ],
    "name:crh_x_preferred":[
        "Stepan"
    ],
    "name:deu_x_preferred":[
        "Stepan"
    ],
    "name:eng_x_preferred":[
        "Stepan"
    ],
    "name:fra_x_preferred":[
        "Stepan"
    ],
    "name:heb_x_preferred":[
        "\u05e1\u05d8\u05e4\u05d0\u05df"
    ],
    "name:jpn_x_preferred":[
        "\u30b9\u30c6\u30d1\u30cb"
    ],
    "name:lav_x_preferred":[
        "Stepa\u0146a"
    ],
    "name:mhr_x_preferred":[
        "\u0421\u0442\u0435\u043f\u0430\u043d\u044c"
    ],
    "name:nld_x_preferred":[
        "Stepan"
    ],
    "name:oci_x_preferred":[
        "Stepan"
    ],
    "name:pol_x_preferred":[
        "Stepa\u0144"
    ],
    "name:ron_x_preferred":[
        "Stepan"
    ],
    "name:rus_x_preferred":[
        "\u0421\u0442\u0435\u043f\u0430\u043d\u044c"
    ],
    "name:spa_x_preferred":[
        "Stepan"
    ],
    "name:ukr_x_preferred":[
        "\u0421\u0442\u0435\u043f\u0430\u043d\u044c"
    ],
    "name:ukr_x_variant":[
        "Stepan\u2019"
    ],
    "name:uzb_x_preferred":[
        "Stepan"
    ],
    "name:zho_x_preferred":[
        "\u65af\u6377\u5e15\u5c3c"
    ],
    "qs:a0":"\u0423\u043a\u0440\u0430\u0457\u043d\u0430",
    "qs:a1":"*\u0420\u0456\u0432\u043d\u0435\u043d\u0441\u044c\u043a\u0430",
    "qs:a1_alt":"Rivnens'ka",
    "qs:a1r":"0",
    "qs:a2":"\u0421\u0430\u0440\u043d\u0435\u043d\u0441\u044c\u043a\u0438\u0439",
    "qs:a2_alt":"Sarnens'kyi",
    "qs:adm0":"\u0423\u043a\u0440\u0430\u0457\u043d\u0430",
    "qs:la_lc":"*",
    "qs:level":"locality",
    "qs:loc":"\u0421\u0442\u0435\u043f\u0430\u043d\u044c",
    "qs:loc_alt":"Stepan",
    "qs:pop":0,
    "qs:type":"buffered point",
    "wd:wordcount":211,
    "wof:name":"\u0421\u0442\u0435\u043f\u0430\u043d\u044c",
    "wof:placetype":"locality"
},
  "geometry": {"coordinates":[26.307288,51.131301],"type":"Point"}
}