{
  "type": "Feature",
  "properties": {
    "gn:admin1_code":"27.0",
    "gn:asciiname":"Sokil'cha",
    "gn:country_code":"UA",
    "gn:dem":201,
    "gn:feature_class":"P",
    "gn:feature_code":"PPL",
    "gn:name":"Sokil\u2019cha",
    "gn:population":0,
    "gn:timezone":"Europe/Kiev",
    "iso:country":"UA",
    "name:ukr_x_preferred":[
        "Sokil\u2019cha"
    ],
    "name:ukr_x_variant":[
        "\u0421\u043e\u043a\u0456\u043b\u044c\u0447\u0430"
    ],
    "name:und_x_variant":[
        "Sokol\u2019cha"
    ],
    "wof:name":"Sokil'cha",
    "wof:placetype":"locality"
},
  "geometry": {"coordinates":[29.32446,49.98848],"type":"Point"}
}