{
  "type": "Feature",
  "properties": {
    "gn:admin1_code":"1.0",
    "gn:asciiname":"Rozsoshyntsi",
    "gn:country_code":"UA",
    "gn:dem":104,
    "gn:feature_class":"P",
    "gn:feature_code":"PPL",
    "gn:name":"Rozsoshyntsi",
    "gn:population":0,
    "gn:timezone":"Europe/Kiev",
    "iso:country":"UA",
    "name:ukr_x_preferred":[
        "Rozsoshyntsi"
    ],
    "name:ukr_x_variant":[
        "\u0420\u043e\u0437\u0441\u043e\u0448\u0438\u043d\u0446\u0456"
    ],
    "wof:name":"Rozsoshyntsi",
    "wof:placetype":"locality"
},
  "geometry": {"coordinates":[32.58552,49.14109000000001],"type":"Point"}
}