{
  "type": "Feature",
  "properties": {
    "gn:country":"UA",
    "gn:fcode":"PPL",
    "gn:population":2552,
    "iso:country":"UA",
    "name:ceb_x_preferred":[
        "Sursko-Mikhaylovka"
    ],
    "name:deu_x_preferred":[
        "Sursko-Mychajliwka"
    ],
    "name:eng_x_preferred":[
        "Sursko-Mikhaylovka"
    ],
    "name:eng_x_variant":[
        "Sursko-Mykhailivka"
    ],
    "name:lav_x_preferred":[
        "Sursko-Mihaj\u013civka"
    ],
    "name:ron_x_preferred":[
        "Sursko-M\u00eehailivka"
    ],
    "name:rus_x_preferred":[
        "\u0421\u0443\u0440\u0441\u043a\u043e-\u041c\u0438\u0445\u0430\u0439\u043b\u043e\u0432\u043a\u0430"
    ],
    "name:ukr_x_preferred":[
        "Surs\u2019ko-Mykhaylivka"
    ],
    "name:ukr_x_variant":[
        "\u0421\u0443\u0440\u0441\u044c\u043a\u043e-\u041c\u0438\u0445\u0430\u0439\u043b\u0456\u0432\u043a\u0430"
    ],
    "name:zho_x_preferred":[
        "\u8607\u723e\u897f\u79d1-\u7c73\u6d77\u5229\u592b\u5361"
    ],
    "qs_pg:aaroncc":"UA",
    "qs_pg:gn_country":"UA",
    "qs_pg:gn_fcode":"PPL",
    "qs_pg:gn_pop":2552,
    "qs_pg:name":"Sursko-Mikhaylovka",
    "qs_pg:photos_9r":0,
    "qs_pg:photos_sr":0,
    "qs_pg:pop_sr":4,
    "qs_pg:qs_pg_placetype":"locality",
    "wof:name":"Sursko-Mikhaylovka",
    "wof:placetype":"locality",
    "wof:population":2552
},
  "geometry": {"coordinates":[34.72759,48.27202],"type":"Point"}
}