{
  "type": "Feature",
  "properties": {
    "gn:admin1_code":"5.0",
    "gn:asciiname":"Khanzhenkove",
    "gn:country_code":"UA",
    "gn:dem":263,
    "gn:feature_class":"P",
    "gn:feature_code":"PPL",
    "gn:name":"Khanzhenkove",
    "gn:population":0,
    "gn:timezone":"Europe/Kiev",
    "iso:country":"UA",
    "name:ukr_x_preferred":[
        "Khanzhenkove"
    ],
    "name:ukr_x_variant":[
        "\u0425\u0430\u043d\u0436\u0435\u043d\u043a\u043e\u0432\u0435"
    ],
    "name:und_x_variant":[
        "Khanzhenskaya",
        "Khanshenkovo",
        "Khanzh\u00ebnkovo"
    ],
    "wof:name":"Khanzhenkove",
    "wof:placetype":"locality"
},
  "geometry": {"coordinates":[38.07387,48.09225],"type":"Point"}
}