{
  "type": "Feature",
  "properties": {
    "gn:admin1_code":"21.0",
    "gn:asciiname":"Proletarskoye",
    "gn:country_code":"UA",
    "gn:dem":204,
    "gn:feature_class":"P",
    "gn:feature_code":"PPL",
    "gn:name":"Proletarskoye",
    "gn:population":0,
    "gn:timezone":"Europe/Kiev",
    "iso:country":"UA",
    "name:ukr_x_preferred":[
        "Proletars\u2019ke"
    ],
    "name:ukr_x_variant":[
        "\u041f\u0440\u043e\u043b\u0435\u0442\u0430\u0440\u0441\u044c\u043a\u0435",
        "Mar\u201dyine",
        "\u041c\u0430\u0440\u2019\u0407\u043d\u0435"
    ],
    "wof:name":"Proletarskoye",
    "wof:placetype":"locality"
},
  "geometry": {"coordinates":[34.98498,51.07181],"type":"Point"}
}