{
  "type": "Feature",
  "properties": {
    "gn:admin1_code":"09",
    "gn:asciiname":"Velyki Yunachky",
    "gn:country_code":"UA",
    "gn:dem":294,
    "gn:feature_class":"P",
    "gn:feature_code":"PPL",
    "gn:name":"Velyki Yunachky",
    "gn:population":0,
    "gn:timezone":"Europe/Kiev",
    "iso:country":"UA",
    "name:ukr_x_preferred":[
        "Velyki Yunachky"
    ],
    "name:ukr_x_variant":[
        "\u0412\u0435\u043b\u0438\u043a\u0456 \u042e\u043d\u0430\u0447\u043a\u0438"
    ],
    "wof:name":"Velyki Yunachky",
    "wof:placetype":"locality"
},
  "geometry": {"coordinates":[26.97071,49.82804],"type":"Point"}
}