{
  "type": "Feature",
  "properties": {
    "gn:admin1_code":"5.0",
    "gn:asciiname":"Petrovskiy",
    "gn:country_code":"UA",
    "gn:dem":259,
    "gn:feature_class":"P",
    "gn:feature_code":"PPL",
    "gn:name":"Petrovskiy",
    "gn:population":0,
    "gn:timezone":"Europe/Kiev",
    "iso:country":"UA",
    "wof:name":"Petrovskiy",
    "wof:placetype":"locality"
},
  "geometry": {"coordinates":[38.0275,48.02444000000001],"type":"Point"}
}