{
  "type": "Feature",
  "properties": {
    "iso:country":"UA",
    "name:eng_x_preferred":[
        "Semisotka"
    ],
    "name:rus_x_preferred":[
        "\u0421\u0435\u043c\u0438\u0441\u043e\u0442\u043a\u0430"
    ],
    "name:ukr_x_preferred":[
        "\u0421\u0435\u043c\u0438\u0441\u043e\u0442\u043a\u0430"
    ],
    "qs:a0":"\u0423\u043a\u0440\u0430\u0457\u043d\u0430",
    "qs:a1":"*\u041a\u0440\u0438\u043c",
    "qs:a1_alt":"Krym",
    "qs:a1r":"0",
    "qs:a2":"\u041b\u0435\u043d\u0456\u043d\u0441\u044c\u043a\u0438\u0439",
    "qs:a2_alt":"Lenins'kyi",
    "qs:adm0":"\u0423\u043a\u0440\u0430\u0457\u043d\u0430",
    "qs:la_lc":"*",
    "qs:level":"locality",
    "qs:loc":"\u0421\u0435\u043c\u0438\u0441\u043e\u0442\u043a\u0430",
    "qs:loc_alt":"Semysotka",
    "qs:pop":0,
    "qs:type":"buffered point",
    "wof:lang":[
        "eng"
    ],
    "wof:name":"\u0421\u0435\u043c\u0438\u0441\u043e\u0442\u043a\u0430",
    "wof:placetype":"locality"
},
  "geometry": {"coordinates":[35.564354,45.24087],"type":"Point"}
}