{
  "type": "Feature",
  "properties": {
    "gn:admin1_code":"16.0",
    "gn:asciiname":"Khutor Kodry",
    "gn:country_code":"UA",
    "gn:dem":130,
    "gn:feature_class":"P",
    "gn:feature_code":"PPL",
    "gn:name":"Khutor Kodry",
    "gn:population":0,
    "gn:timezone":"Europe/Kiev",
    "iso:country":"UA",
    "wof:name":"Khutor Kodry",
    "wof:placetype":"locality"
},
  "geometry": {"coordinates":[30.45192,47.65806],"type":"Point"}
}