{
  "type": "Feature",
  "properties": {
    "gn:admin1_code":"6.0",
    "gn:asciiname":"Pererovi",
    "gn:country_code":"UA",
    "gn:dem":256,
    "gn:feature_class":"P",
    "gn:feature_code":"PPL",
    "gn:name":"Pererovi",
    "gn:population":0,
    "gn:timezone":"Europe/Kiev",
    "iso:country":"UA",
    "name:und_x_variant":[
        "Pererov",
        "Pereruv",
        "Pererovi"
    ],
    "wof:name":"Pererovi",
    "wof:placetype":"locality"
},
  "geometry": {"coordinates":[25.1336,48.50061],"type":"Point"}
}