{
  "type": "Feature",
  "properties": {
    "gn:admin1_code":"7.0",
    "gn:asciiname":"Chervonoarmiys'ke Pershe",
    "gn:country_code":"UA",
    "gn:dem":116,
    "gn:feature_class":"P",
    "gn:feature_code":"PPL",
    "gn:name":"Chervonoarmiys\u2019ke Pershe",
    "gn:population":0,
    "gn:timezone":"Europe/Kiev",
    "iso:country":"UA",
    "name:ukr_x_preferred":[
        "Chervonoarmiys\u2019ke Pershe"
    ],
    "name:ukr_x_variant":[
        "\u0427\u0435\u0440\u0432\u043e\u043d\u043e\u0430\u0440\u043c\u0456\u0439\u0441\u044c\u043a\u0435 \u041f\u0435\u0440\u0448\u0435"
    ],
    "name:und_x_variant":[
        "Krasnoarmeyskoye",
        "Pervo-Krasnoarmeyskoye",
        "Pervoye Krasnoarmeyskoye",
        "Chervonoarmeyskoye Pervoye"
    ],
    "wof:name":"Chervonoarmiys'ke Pershe",
    "wof:placetype":"locality"
},
  "geometry": {"coordinates":[36.89788,50.21579000000001],"type":"Point"}
}