{
  "type": "Feature",
  "properties": {
    "gn:admin1_code":"8.0",
    "gn:asciiname":"Novoyefremivka",
    "gn:country_code":"UA",
    "gn:dem":27,
    "gn:feature_class":"P",
    "gn:feature_code":"PPL",
    "gn:name":"Novoyefremivka",
    "gn:population":0,
    "gn:timezone":"Europe/Kiev",
    "iso:country":"UA",
    "name:rus_x_preferred":[
        "\u041d\u043e\u0432\u043e\u0435\u0444\u0440\u0435\u043c\u043e\u0432\u043a\u0430"
    ],
    "name:ukr_x_preferred":[
        "Novoyefremivka"
    ],
    "name:ukr_x_variant":[
        "\u041d\u043e\u0432\u043e\u0454\u0444\u0440\u0435\u043c\u0456\u0432\u043a\u0430"
    ],
    "name:und_x_variant":[
        "Novoyefremovka"
    ],
    "wof:name":"Novoyefremivka",
    "wof:placetype":"locality"
},
  "geometry": {"coordinates":[34.93821,46.47951],"type":"Point"}
}