{
  "type": "Feature",
  "properties": {
    "gn:admin1_code":"2.0",
    "gn:asciiname":"Mashevo",
    "gn:country_code":"UA",
    "gn:dem":159,
    "gn:feature_class":"P",
    "gn:feature_code":"PPL",
    "gn:name":"Mashevo",
    "gn:population":0,
    "gn:timezone":"Europe/Kiev",
    "iso:country":"UA",
    "name:eng_x_preferred":[
        "Mashevo"
    ],
    "name:rus_x_preferred":[
        "\u041c\u0430\u0448\u0435\u0432\u043e"
    ],
    "name:ukr_x_preferred":[
        "Masheve"
    ],
    "name:ukr_x_variant":[
        "\u041c\u0430\u0448\u0435\u0432\u0435",
        "Mashevskaya"
    ],
    "name:und_x_variant":[
        "Mashevskaya",
        "Mashevo"
    ],
    "wof:name":"Mashevo",
    "wof:placetype":"locality"
},
  "geometry": {"coordinates":[32.79984,52.08645],"type":"Point"}
}