{
  "type": "Feature",
  "properties": {
    "gn:admin1_code":"1.0",
    "gn:asciiname":"Belozer'ye",
    "gn:country_code":"UA",
    "gn:dem":96,
    "gn:feature_class":"P",
    "gn:feature_code":"PPL",
    "gn:name":"Beloz\u00ebr\u2019ye",
    "gn:population":0,
    "gn:timezone":"Europe/Kiev",
    "iso:country":"UA",
    "name:eng_x_preferred":[
        "Beloz\u00ebr'ye"
    ],
    "name:rus_x_preferred":[
        "\u0411\u0435\u043b\u043e\u0437\u043e\u0440\u044c\u0435"
    ],
    "name:und_x_variant":[
        "Beloz\u00ebr\u2019ye"
    ],
    "wof:name":"Belozer'ye",
    "wof:placetype":"locality"
},
  "geometry": {"coordinates":[31.89355,49.30105],"type":"Point"}
}