{
  "type": "Feature",
  "properties": {
    "gn:admin1_code":"15.0",
    "gn:asciiname":"Zabrod",
    "gn:country_code":"UA",
    "gn:dem":213,
    "gn:feature_class":"P",
    "gn:feature_code":"PPL",
    "gn:name":"Zabrod",
    "gn:population":0,
    "gn:timezone":"Europe/Kiev",
    "iso:country":"UA",
    "name:und_x_variant":[
        "Zabrod\u2019ye",
        "Zabrod"
    ],
    "wof:name":"Zabrod",
    "wof:placetype":"locality"
},
  "geometry": {"coordinates":[23.96336,50.19869],"type":"Point"}
}