{
  "type": "Feature",
  "properties": {
    "gn:admin1_code":"16.0",
    "gn:asciiname":"Dmitrovka",
    "gn:country_code":"UA",
    "gn:dem":95,
    "gn:feature_class":"P",
    "gn:feature_code":"PPL",
    "gn:name":"Dmitrovka",
    "gn:population":0,
    "gn:timezone":"Europe/Kiev",
    "iso:country":"UA",
    "wof:name":"Dmitrovka",
    "wof:placetype":"locality"
},
  "geometry": {"coordinates":[32.48333,47.75],"type":"Point"}
}