{
  "type": "Feature",
  "properties": {
    "gn:population":1891,
    "iso:country":"UA",
    "name:ara_x_preferred":[
        "\u0647\u0648\u0644\u0648\u0641\u064a\u0646\u064a"
    ],
    "name:bel_x_preferred":[
        "\u0413\u0430\u043b\u0430\u0432\u044b\u043d\u044d"
    ],
    "name:ceb_x_preferred":[
        "Holovyne"
    ],
    "name:ces_x_preferred":[
        "Holovyne"
    ],
    "name:crh_x_preferred":[
        "Golov\u0131ne"
    ],
    "name:deu_x_preferred":[
        "Holowyne"
    ],
    "name:eng_x_preferred":[
        "Holovyne"
    ],
    "name:fra_x_preferred":[
        "Holovyne"
    ],
    "name:hye_x_preferred":[
        "\u0533\u0578\u056c\u0578\u057e\u056b\u0576\u0578"
    ],
    "name:nld_x_preferred":[
        "Holovyne"
    ],
    "name:pol_x_preferred":[
        "Ho\u0142owyne"
    ],
    "name:pol_x_variant":[
        "Ho\u0142owin"
    ],
    "name:ron_x_preferred":[
        "Holov\u00eene"
    ],
    "name:rus_x_preferred":[
        "\u0413\u043e\u043b\u043e\u0432\u0438\u043d\u043e"
    ],
    "name:rus_x_variant":[
        "\u0413\u043e\u043b\u043e\u0432\u0438\u043d\u0435"
    ],
    "name:sah_x_preferred":[
        "\u0413\u043e\u043b\u043e\u0432\u0438\u043d\u043e"
    ],
    "name:ukr_x_preferred":[
        "\u0413\u043e\u043b\u043e\u0432\u0438\u043d\u0435"
    ],
    "name:und_x_variant":[
        "Golovino"
    ],
    "name:zho_x_preferred":[
        "\u6208\u6d1b\u7dad\u6d85"
    ],
    "qs:a0":"\u0423\u043a\u0440\u0430\u0457\u043d\u0430",
    "qs:a1":"*\u0416\u0438\u0442\u043e\u043c\u0438\u0440\u0441\u044c\u043a\u0430",
    "qs:a1_alt":"Zhytomyrs'ka",
    "qs:a1r":"0",
    "qs:a2":"\u0427\u0435\u0440\u043d\u044f\u0445\u0456\u0432\u0441\u044c\u043a\u0438\u0439",
    "qs:a2_alt":"Cherniakhivs'kyi",
    "qs:adm0":"\u0423\u043a\u0440\u0430\u0457\u043d\u0430",
    "qs:la_lc":"*",
    "qs:level":"locality",
    "qs:loc":"\u0413\u043e\u043b\u043e\u0432\u0438\u043d\u0435",
    "qs:loc_alt":"Holovyne",
    "qs:pop":0,
    "qs:type":"buffered point",
    "wd:wordcount":61,
    "wof:name":"\u0413\u043e\u043b\u043e\u0432\u0438\u043d\u0435",
    "wof:placetype":"locality",
    "wof:population":1891
},
  "geometry": {"coordinates":[28.830273,50.474876],"type":"Point"}
}