{
  "type": "Feature",
  "properties": {
    "gn:admin1_code":"15.0",
    "gn:asciiname":"Uhryniv",
    "gn:country_code":"UA",
    "gn:dem":191,
    "gn:feature_class":"P",
    "gn:feature_code":"PPL",
    "gn:name":"Uhryniv",
    "gn:population":0,
    "gn:timezone":"Europe/Kiev",
    "iso:country":"UA",
    "name:ukr_x_preferred":[
        "Uhryniv"
    ],
    "name:ukr_x_variant":[
        "\u0423\u0433\u0440\u0438\u043d\u0456\u0432"
    ],
    "name:und_x_variant":[
        "Uhryn\u00f3w",
        "Dubravka",
        "Ugrynuv",
        "Dubrovka"
    ],
    "wof:name":"Uhryniv",
    "wof:placetype":"locality"
},
  "geometry": {"coordinates":[24.11148,50.57582],"type":"Point"}
}