{
  "type": "Feature",
  "properties": {
    "gn:admin1_code":"23.0",
    "gn:asciiname":"Stupnyk",
    "gn:country_code":"UA",
    "gn:dem":272,
    "gn:feature_class":"P",
    "gn:feature_code":"PPL",
    "gn:name":"Stupnyk",
    "gn:population":0,
    "gn:timezone":"Europe/Kiev",
    "iso:country":"UA",
    "name:ukr_x_preferred":[
        "Stupnyk"
    ],
    "name:ukr_x_variant":[
        "\u0421\u0442\u0443\u043f\u043d\u0438\u043a"
    ],
    "name:und_x_variant":[
        "Stupnik"
    ],
    "wof:name":"Stupnyk",
    "wof:placetype":"locality"
},
  "geometry": {"coordinates":[28.28829,49.74412],"type":"Point"}
}