{
  "type": "Feature",
  "properties": {
    "iso:country":"UA",
    "name:che_x_preferred":[
        "\u041d\u0435\u0449\u0435\u0440\u0435\u0442\u043e\u0432\u043e"
    ],
    "name:deu_x_preferred":[
        "Neschtscheretowe"
    ],
    "name:eng_x_preferred":[
        "Neshcheretovo"
    ],
    "name:eng_x_variant":[
        "Nescheretove",
        "Neshcheretove"
    ],
    "name:fin_x_preferred":[
        "N\u0435\u0161t\u0161\u0435r\u0435t\u043ev\u0435"
    ],
    "name:lav_x_preferred":[
        "Ne\u0161\u010deretove"
    ],
    "name:nan_x_preferred":[
        "Neshcheretove"
    ],
    "name:nno_x_preferred":[
        "Nesjtsjeretove"
    ],
    "name:nob_x_preferred":[
        "Nesjtsjeretove"
    ],
    "name:pol_x_preferred":[
        "Neszczeretowe"
    ],
    "name:ron_x_preferred":[
        "Ne\u0219ceretove"
    ],
    "name:rus_x_preferred":[
        "\u041d\u0435\u0449\u0435\u0440\u0435\u0442\u043e\u0432\u043e"
    ],
    "name:ukr_x_preferred":[
        "Neshcheretove"
    ],
    "name:ukr_x_variant":[
        "\u041d\u0435\u0449\u0435\u0440\u0435\u0442\u043e\u0432\u0435"
    ],
    "name:und_x_variant":[
        "Neshcheretovka"
    ],
    "name:zho_x_preferred":[
        "\u6d85\u8b1d\u5217\u6258\u97cb"
    ],
    "qs:a0":"\u0423\u043a\u0440\u0430\u0457\u043d\u0430",
    "qs:a1":"*\u041b\u0443\u0433\u0430\u043d\u0441\u044c\u043a\u0430",
    "qs:a1_alt":"Luhans'ka",
    "qs:a1r":"0",
    "qs:a2":"\u0411\u0456\u043b\u043e\u043a\u0443\u0440\u0430\u043a\u0438\u043d\u0441\u044c\u043a\u0438\u0439",
    "qs:a2_alt":"Bilokurakyns'kyi",
    "qs:adm0":"\u0423\u043a\u0440\u0430\u0457\u043d\u0430",
    "qs:la_lc":"*",
    "qs:level":"locality",
    "qs:loc":"\u041d\u0435\u0449\u0435\u0440\u0435\u0442\u043e\u0432\u0435",
    "qs:loc_alt":"Nescheretove",
    "qs:pop":0,
    "qs:type":"buffered point",
    "wof:name":"\u041d\u0435\u0449\u0435\u0440\u0435\u0442\u043e\u0432\u0435",
    "wof:placetype":"locality"
},
  "geometry": {"coordinates":[38.811425,49.372122],"type":"Point"}
}