{
  "type": "Feature",
  "properties": {
    "gn:admin1_code":"4.0",
    "gn:asciiname":"Semenivka",
    "gn:country_code":"UA",
    "gn:dem":73,
    "gn:feature_class":"P",
    "gn:feature_code":"PPL",
    "gn:name":"Semenivka",
    "gn:population":0,
    "gn:timezone":"Europe/Kiev",
    "iso:country":"UA",
    "name:aze_x_preferred":[
        "Semyonovka"
    ],
    "name:bel_x_preferred":[
        "\u0421\u044f\u043c\u0451\u043d\u0430\u045e\u043a\u0430"
    ],
    "name:ceb_x_preferred":[
        "Semenivka"
    ],
    "name:ces_x_preferred":[
        "Semenivka"
    ],
    "name:deu_x_preferred":[
        "Semeniwka"
    ],
    "name:ita_x_preferred":[
        "Semenivka"
    ],
    "name:mhr_x_preferred":[
        "\u0421\u0435\u043c\u043e\u043d\u0441\u043e\u043b\u0430"
    ],
    "name:pol_x_preferred":[
        "Semeniwka"
    ],
    "name:rus_x_preferred":[
        "\u0421\u0435\u043c\u0451\u043d\u043e\u0432\u043a\u0430"
    ],
    "name:spa_x_preferred":[
        "Semenivka"
    ],
    "name:tat_x_preferred":[
        "\u0421\u0435\u043c\u0435\u043d\u043e\u0432\u043a\u0430"
    ],
    "name:ukr_x_preferred":[
        "Semenivka"
    ],
    "name:ukr_x_variant":[
        "\u0421\u0435\u043c\u0435\u043d\u0456\u0432\u043a\u0430"
    ],
    "name:vie_x_preferred":[
        "Semenivka"
    ],
    "wof:name":"Semenivka",
    "wof:placetype":"locality"
},
  "geometry": {"coordinates":[34.62069,49.02872],"type":"Point"}
}