{
  "type": "Feature",
  "properties": {
    "gn:admin1_code":"2.0",
    "gn:asciiname":"Pushkari",
    "gn:country_code":"UA",
    "gn:dem":113,
    "gn:feature_class":"P",
    "gn:feature_code":"PPL",
    "gn:name":"Pushkari",
    "gn:population":0,
    "gn:timezone":"Europe/Kiev",
    "iso:country":"UA",
    "name:ukr_x_preferred":[
        "Pushkari"
    ],
    "name:ukr_x_variant":[
        "\u041f\u0443\u0448\u043a\u0430\u0440\u0456"
    ],
    "wof:name":"Pushkari",
    "wof:placetype":"locality"
},
  "geometry": {"coordinates":[31.04805,50.93272],"type":"Point"}
}