{
  "type": "Feature",
  "properties": {
    "gn:admin1_code":"19.0",
    "gn:asciiname":"Novorichytsya",
    "gn:country_code":"UA",
    "gn:dem":145,
    "gn:feature_class":"P",
    "gn:feature_code":"PPL",
    "gn:name":"Novorichytsya",
    "gn:population":0,
    "gn:timezone":"Europe/Kiev",
    "iso:country":"UA",
    "name:ukr_x_preferred":[
        "Novorichytsya"
    ],
    "name:ukr_x_variant":[
        "\u041d\u043e\u0432\u043e\u0440\u0456\u0447\u0438\u0446\u044f"
    ],
    "name:und_x_variant":[
        "Vul\u2019ka Zhechiska",
        "Novorechitsa"
    ],
    "wof:name":"Novorichytsya",
    "wof:placetype":"locality"
},
  "geometry": {"coordinates":[25.93333,51.76667],"type":"Point"}
}