{
  "type": "Feature",
  "properties": {
    "gn:admin1_code":"6.0",
    "gn:asciiname":"Koloniya Troyan",
    "gn:cc2":"UA",
    "gn:country_code":"UA",
    "gn:dem":278,
    "gn:feature_class":"P",
    "gn:feature_code":"PPL",
    "gn:name":"Koloniya Troyan",
    "gn:population":0,
    "gn:timezone":"Europe/Kiev",
    "iso:country":"UA",
    "name:und_x_variant":[
        "Troyan",
        "Koloniya Troyan"
    ],
    "wof:name":"Koloniya Troyan",
    "wof:placetype":"locality"
},
  "geometry": {"coordinates":[25.08333,48.78333],"type":"Point"}
}