{
  "type": "Feature",
  "properties": {
    "gn:admin1_code":"11.0",
    "gn:admin2_code":"704361",
    "gn:admin3_code":"11152956",
    "gn:asciiname":"Risovoye",
    "gn:country_code":"UA",
    "gn:dem":5,
    "gn:elevation":"5.0",
    "gn:feature_class":"P",
    "gn:feature_code":"PPL",
    "gn:name":"Risovoye",
    "gn:population":528,
    "gn:timezone":"Europe/Simferopol",
    "iso:country":"UA",
    "name:eng_x_preferred":[
        "Risovoye"
    ],
    "name:rus_x_preferred":[
        "\u0420\u0438\u0441\u043e\u0432\u043e\u0435"
    ],
    "name:ukr_x_preferred":[
        "\u0420\u0438\u0441\u043e\u0432\u0435"
    ],
    "wof:name":"Risovoye",
    "wof:placetype":"locality",
    "wof:population":528
},
  "geometry": {"coordinates":[33.69284,46.02716],"type":"Point"}
}