{
  "type": "Feature",
  "properties": {
    "gn:admin1_code":"21.0",
    "gn:asciiname":"Bolotivka",
    "gn:country_code":"UA",
    "gn:dem":163,
    "gn:feature_class":"P",
    "gn:feature_code":"PPL",
    "gn:name":"Bolotivka",
    "gn:population":0,
    "gn:timezone":"Europe/Kiev",
    "iso:country":"UA",
    "name:ukr_x_preferred":[
        "Bolotivka"
    ],
    "name:ukr_x_variant":[
        "\u0411\u043e\u043b\u043e\u0442\u0456\u0432\u043a\u0430"
    ],
    "name:und_x_variant":[
        "Bolotovka"
    ],
    "wof:name":"Bolotivka",
    "wof:placetype":"locality"
},
  "geometry": {"coordinates":[33.73047,51.04775],"type":"Point"}
}