{
  "type": "Feature",
  "properties": {
    "gn:admin1_code":"11.0",
    "gn:admin2_code":"712585",
    "gn:admin3_code":"11152829.0",
    "gn:asciiname":"Mironovka",
    "gn:country_code":"UA",
    "gn:dem":188,
    "gn:elevation":"189.0",
    "gn:feature_class":"P",
    "gn:feature_code":"PPL",
    "gn:name":"Mironovka",
    "gn:population":245,
    "gn:timezone":"Europe/Simferopol",
    "iso:country":"UA",
    "name:eng_x_preferred":[
        "Mironovka"
    ],
    "name:rus_x_historical":[
        "\u041a\u0430\u0440\u0430\u0431\u0430\u0301\u0439"
    ],
    "name:rus_x_preferred":[
        "\u041c\u0438\u0440\u043e\u043d\u043e\u0432\u043a\u0430"
    ],
    "name:rus_x_variant":[
        "\u041a\u0430\u0440\u0430\u0431\u0430\u0301\u0439"
    ],
    "name:ukr_x_preferred":[
        "\u041c\u0438\u0440\u043e\u043d\u0456\u0432\u043a\u0430"
    ],
    "wof:name":"Mironovka",
    "wof:placetype":"locality",
    "wof:population":245
},
  "geometry": {"coordinates":[34.57017,45.13427],"type":"Point"}
}