{
  "type": "Feature",
  "properties": {
    "gn:admin1_code":"6.0",
    "gn:asciiname":"Osmoloda",
    "gn:country_code":"UA",
    "gn:dem":711,
    "gn:elevation":"730.0",
    "gn:feature_class":"P",
    "gn:feature_code":"PPL",
    "gn:name":"Osmoloda",
    "gn:population":0,
    "gn:timezone":"Europe/Kiev",
    "iso:country":"UA",
    "name:rus_x_preferred":[
        "\u041e\u0441\u043c\u043e\u043b\u043e\u0434\u0430"
    ],
    "name:ukr_x_preferred":[
        "Osmoloda"
    ],
    "name:ukr_x_variant":[
        "\u041e\u0441\u043c\u043e\u043b\u043e\u0434\u0430"
    ],
    "wof:name":"Osmoloda",
    "wof:placetype":"locality"
},
  "geometry": {"coordinates":[24.0202,48.65138],"type":"Point"}
}