{
  "type": "Feature",
  "properties": {
    "gn:admin1_code":"19.0",
    "gn:asciiname":"Chudvy",
    "gn:country_code":"UA",
    "gn:dem":168,
    "gn:feature_class":"P",
    "gn:feature_code":"PPL",
    "gn:name":"Chudvy",
    "gn:population":0,
    "gn:timezone":"Europe/Kiev",
    "iso:country":"UA",
    "name:ukr_x_preferred":[
        "Chudvy"
    ],
    "name:ukr_x_variant":[
        "\u0427\u0443\u0434\u0432\u0438"
    ],
    "wof:name":"Chudvy",
    "wof:placetype":"locality"
},
  "geometry": {"coordinates":[26.15397,50.87515],"type":"Point"}
}