{
  "type": "Feature",
  "properties": {
    "gn:admin1_code":"25.0",
    "gn:asciiname":"Tysauyfalu",
    "gn:country_code":"UA",
    "gn:dem":102,
    "gn:feature_class":"P",
    "gn:feature_code":"PPL",
    "gn:name":"Tysauyfalu",
    "gn:population":0,
    "gn:timezone":"Europe/Uzhgorod",
    "iso:country":"UA",
    "name:ukr_x_preferred":[
        "Tysauyfalu"
    ],
    "name:ukr_x_variant":[
        "\u0422\u0438\u0441\u0430\u0443\u0439\u0444\u0430\u043b\u0443"
    ],
    "wof:name":"Tysauyfalu",
    "wof:placetype":"locality"
},
  "geometry": {"coordinates":[22.27711,48.41075],"type":"Point"}
}