{
  "type": "Feature",
  "properties": {
    "gn:admin1_code":"27.0",
    "gn:asciiname":"Vyhoda",
    "gn:country_code":"UA",
    "gn:dem":231,
    "gn:feature_class":"P",
    "gn:feature_code":"PPL",
    "gn:name":"Vyhoda",
    "gn:population":0,
    "gn:timezone":"Europe/Kiev",
    "iso:country":"UA",
    "name:ukr_x_preferred":[
        "Vyhoda"
    ],
    "name:ukr_x_variant":[
        "\u0412\u0438\u0433\u043e\u0434\u0430"
    ],
    "name:und_x_variant":[
        "Vygoda"
    ],
    "wof:name":"Vyhoda",
    "wof:placetype":"locality"
},
  "geometry": {"coordinates":[28.52138,50.33561],"type":"Point"}
}