{
  "type": "Feature",
  "properties": {
    "gn:admin1_code":"24.0",
    "gn:asciiname":"Horishnye",
    "gn:country_code":"UA",
    "gn:dem":216,
    "gn:feature_class":"P",
    "gn:feature_code":"PPL",
    "gn:name":"Horishnye",
    "gn:population":0,
    "gn:timezone":"Europe/Kiev",
    "iso:country":"UA",
    "name:ukr_x_preferred":[
        "Horishnye"
    ],
    "name:ukr_x_variant":[
        "\u0413\u043e\u0440\u0456\u0448\u043d\u0454"
    ],
    "name:und_x_variant":[
        "Dol\u2019ny",
        "Golyatyn Dol\u2019ny",
        "Gorishniy Golyatyn",
        "Gorishne",
        "Gorishneye"
    ],
    "wof:name":"Horishnye",
    "wof:placetype":"locality"
},
  "geometry": {"coordinates":[25.05027,50.4618],"type":"Point"}
}