{
  "type": "Feature",
  "properties": {
    "gn:admin1_code":"17.0",
    "gn:asciiname":"Shimkovo",
    "gn:country_code":"UA",
    "gn:dem":81,
    "gn:feature_class":"P",
    "gn:feature_code":"PPL",
    "gn:name":"Shimkovo",
    "gn:population":0,
    "gn:timezone":"Europe/Kiev",
    "iso:country":"UA",
    "name:und_x_variant":[
        "Zhurovka",
        "Shnikovo",
        "Shimkovo"
    ],
    "wof:name":"Shimkovo",
    "wof:placetype":"locality"
},
  "geometry": {"coordinates":[30.07606,47.59081],"type":"Point"}
}