{
  "type": "Feature",
  "properties": {
    "iso:country":"UA",
    "name:und_x_variant":[
        "Babino"
    ],
    "qs:a0":"\u0423\u043a\u0440\u0430\u0457\u043d\u0430",
    "qs:a1":"*\u0427\u0435\u0440\u043d\u0456\u0432\u0435\u0446\u044c\u043a\u0430",
    "qs:a1_alt":"Chernivets'ka",
    "qs:a1r":"0",
    "qs:a2":"\u041a\u0435\u043b\u044c\u043c\u0435\u043d\u0435\u0446\u044c\u043a\u0438\u0439",
    "qs:a2_alt":"Kel'menets'kyi",
    "qs:adm0":"\u0423\u043a\u0440\u0430\u0457\u043d\u0430",
    "qs:la_lc":"*",
    "qs:level":"locality",
    "qs:loc":"\u0411\u0430\u0431\u0438\u043d",
    "qs:loc_alt":"Babyn",
    "qs:pop":0,
    "qs:type":"buffered point",
    "wd:wordcount":3917,
    "wof:name":"\u0411\u0430\u0431\u0438\u043d",
    "wof:placetype":"locality"
},
  "geometry": {"coordinates":[26.84541,48.51802],"type":"Point"}
}