{
  "type": "Feature",
  "properties": {
    "gn:admin1_code":"5.0",
    "gn:asciiname":"Bur'yanovka",
    "gn:country_code":"UA",
    "gn:dem":172,
    "gn:feature_class":"P",
    "gn:feature_code":"PPL",
    "gn:name":"Bur\u2019yanovka",
    "gn:population":0,
    "gn:timezone":"Europe/Kiev",
    "iso:country":"UA",
    "name:rus_x_preferred":[
        "Bur\u2019yanovka"
    ],
    "wof:name":"Bur'yanovka",
    "wof:placetype":"locality"
},
  "geometry": {"coordinates":[37.61667,48.08333],"type":"Point"}
}