{
  "type": "Feature",
  "properties": {
    "gn:admin1_code":"9.0",
    "gn:asciiname":"Zarud'ye",
    "gn:country_code":"UA",
    "gn:dem":284,
    "gn:feature_class":"P",
    "gn:feature_code":"PPL",
    "gn:name":"Zarud\u2019ye",
    "gn:population":0,
    "gn:timezone":"Europe/Kiev",
    "iso:country":"UA",
    "wof:name":"Zarud'ye",
    "wof:placetype":"locality"
},
  "geometry": {"coordinates":[27.01729000000001,49.5563],"type":"Point"}
}