{
  "type": "Feature",
  "properties": {
    "gn:admin1_code":"2.0",
    "gn:asciiname":"Volynka",
    "gn:country_code":"UA",
    "gn:dem":134,
    "gn:feature_class":"P",
    "gn:feature_code":"PPL",
    "gn:name":"Volynka",
    "gn:population":0,
    "gn:timezone":"Europe/Kiev",
    "iso:country":"UA",
    "name:crh_x_preferred":[
        "Tulup zurna"
    ],
    "name:eng_x_preferred":[
        "Volynka"
    ],
    "name:rus_x_preferred":[
        "\u0412\u043e\u043b\u044b\u043d\u043a\u0430"
    ],
    "name:ukr_x_preferred":[
        "\u0412\u043e\u043b\u0438\u043d\u043a\u0430"
    ],
    "name:und_x_variant":[
        "Volynskoye",
        "Volynka"
    ],
    "wof:name":"Volynka",
    "wof:placetype":"locality"
},
  "geometry": {"coordinates":[32.46553,51.62708],"type":"Point"}
}