{
  "type": "Feature",
  "properties": {
    "gn:admin1_code":"18.0",
    "gn:asciiname":"Iskrivka",
    "gn:country_code":"UA",
    "gn:dem":173,
    "gn:feature_class":"P",
    "gn:feature_code":"PPL",
    "gn:name":"Iskrivka",
    "gn:population":0,
    "gn:timezone":"Europe/Kiev",
    "iso:country":"UA",
    "name:eng_x_preferred":[
        "Iskrovka"
    ],
    "name:rus_x_preferred":[
        "\u0418\u0441\u043a\u0440\u043e\u0432\u043a\u0430"
    ],
    "name:ukr_x_preferred":[
        "Iskrivka"
    ],
    "name:ukr_x_variant":[
        "\u0406\u0441\u043a\u0440\u0456\u0432\u043a\u0430"
    ],
    "name:und_x_variant":[
        "Iskrovka"
    ],
    "wof:name":"Iskrivka",
    "wof:placetype":"locality"
},
  "geometry": {"coordinates":[35.17042,49.82473],"type":"Point"}
}