{
  "type": "Feature",
  "properties": {
    "gn:admin1_code":"18.0",
    "gn:asciiname":"Mykhaylyky",
    "gn:country_code":"UA",
    "gn:dem":130,
    "gn:feature_class":"P",
    "gn:feature_code":"PPL",
    "gn:name":"Mykhaylyky",
    "gn:population":0,
    "gn:timezone":"Europe/Kiev",
    "iso:country":"UA",
    "name:ukr_x_preferred":[
        "Mykhaylyky"
    ],
    "name:ukr_x_variant":[
        "\u041c\u0438\u0445\u0430\u0439\u043b\u0438\u043a\u0438"
    ],
    "wof:name":"Mykhaylyky",
    "wof:placetype":"locality"
},
  "geometry": {"coordinates":[34.31180999999999,49.50025],"type":"Point"}
}