{
  "type": "Feature",
  "properties": {
    "gn:admin1_code":"24.0",
    "gn:asciiname":"Shel'viv",
    "gn:country_code":"UA",
    "gn:dem":219,
    "gn:feature_class":"P",
    "gn:feature_code":"PPL",
    "gn:name":"Shel\u2019viv",
    "gn:population":0,
    "gn:timezone":"Europe/Kiev",
    "iso:country":"UA",
    "name:ukr_x_preferred":[
        "Shel\u2019viv"
    ],
    "name:ukr_x_variant":[
        "\u0428\u0435\u043b\u044c\u0432\u0456\u0432"
    ],
    "name:und_x_variant":[
        "Szelw\u00f3w",
        "Shel\u2019vuv",
        "Shel\u2019vov"
    ],
    "wof:name":"Shel'viv",
    "wof:placetype":"locality"
},
  "geometry": {"coordinates":[24.78066,50.72143],"type":"Point"}
}