{
  "type": "Feature",
  "properties": {
    "gn:admin1_code":"10.0",
    "gn:asciiname":"Dolyna",
    "gn:country_code":"UA",
    "gn:dem":168,
    "gn:feature_class":"P",
    "gn:feature_code":"PPL",
    "gn:name":"Dolyna",
    "gn:population":0,
    "gn:timezone":"Europe/Kiev",
    "iso:country":"UA",
    "name:ukr_x_preferred":[
        "Dolyna"
    ],
    "name:ukr_x_variant":[
        "\u0414\u043e\u043b\u0438\u043d\u0430"
    ],
    "wof:name":"Dolyna",
    "wof:placetype":"locality"
},
  "geometry": {"coordinates":[32.75355,48.73799],"type":"Point"}
}