{
  "type": "Feature",
  "properties": {
    "gn:admin1_code":"10.0",
    "gn:asciiname":"Dolyna",
    "gn:country_code":"UA",
    "gn:dem":168,
    "gn:feature_class":"P",
    "gn:feature_code":"PPL",
    "gn:name":"Dolyna",
    "gn:population":0,
    "gn:timezone":"Europe/Kiev",
    "iso:country":"UA",
    "name:ara_x_preferred":[
        "\u062f\u0648\u0644\u064a\u0646\u0627"
    ],
    "name:azb_x_preferred":[
        "\u062f\u0648\u0644\u06cc\u0646\u0627"
    ],
    "name:bel_x_preferred":[
        "\u0414\u0430\u043b\u044b\u043d\u0430"
    ],
    "name:ceb_x_preferred":[
        "Dolyna"
    ],
    "name:ces_x_preferred":[
        "Dolyna"
    ],
    "name:crh_x_preferred":[
        "Dol\u0131na"
    ],
    "name:deu_x_preferred":[
        "Dolyna"
    ],
    "name:fas_x_preferred":[
        "\u062f\u0648\u0644\u06cc\u0646\u0627"
    ],
    "name:fra_x_preferred":[
        "Dolyna"
    ],
    "name:glg_x_preferred":[
        "Dolyna"
    ],
    "name:heb_x_preferred":[
        "\u05d3\u05d5\u05dc\u05d9\u05e0\u05d4"
    ],
    "name:hsb_x_preferred":[
        "Dolyna"
    ],
    "name:hye_x_preferred":[
        "\u0534\u0578\u056c\u056b\u0576\u0561"
    ],
    "name:ita_x_preferred":[
        "Dolyna"
    ],
    "name:kat_x_preferred":[
        "\u10d3\u10dd\u10da\u10d8\u10dc\u10d0"
    ],
    "name:kor_x_preferred":[
        "\ub3cc\ub9ac\ub098"
    ],
    "name:lav_x_preferred":[
        "Dolina"
    ],
    "name:lit_x_preferred":[
        "Dolyna"
    ],
    "name:nld_x_preferred":[
        "Dolyna"
    ],
    "name:nno_x_preferred":[
        "Dolyna"
    ],
    "name:nor_x_preferred":[
        "Dolyna"
    ],
    "name:pol_x_preferred":[
        "Dolina"
    ],
    "name:ron_x_preferred":[
        "Dol\u00eena"
    ],
    "name:rus_x_preferred":[
        "\u0414\u043e\u043b\u0438\u043d\u0430"
    ],
    "name:srp_x_preferred":[
        "\u0414\u043e\u043b\u0438\u043d\u0430"
    ],
    "name:ukr_x_preferred":[
        "Dolyna"
    ],
    "name:ukr_x_variant":[
        "\u0414\u043e\u043b\u0438\u043d\u0430"
    ],
    "name:vie_x_preferred":[
        "Dolyna"
    ],
    "name:yid_x_preferred":[
        "\u05d3\u05d0\u05dc\u05d9\u05e0\u05e2"
    ],
    "name:zho_x_preferred":[
        "\u591a\u5229\u7d0d"
    ],
    "wof:name":"Dolyna",
    "wof:placetype":"locality"
},
  "geometry": {"coordinates":[32.75355,48.73799],"type":"Point"}
}