{
  "type": "Feature",
  "properties": {
    "gn:admin1_code":"27.0",
    "gn:asciiname":"Kryvotyn",
    "gn:country_code":"UA",
    "gn:dem":214,
    "gn:feature_class":"P",
    "gn:feature_code":"PPL",
    "gn:name":"Kryvotyn",
    "gn:population":0,
    "gn:timezone":"Europe/Kiev",
    "iso:country":"UA",
    "name:ukr_x_preferred":[
        "Kryvotyn"
    ],
    "name:ukr_x_variant":[
        "\u041a\u0440\u0438\u0432\u043e\u0442\u0438\u043d"
    ],
    "name:und_x_variant":[
        "Krivotin"
    ],
    "wof:name":"Kryvotyn",
    "wof:placetype":"locality"
},
  "geometry": {"coordinates":[28.07919,50.94573],"type":"Point"}
}