{
  "type": "Feature",
  "properties": {
    "gn:admin1_code":"6.0",
    "gn:asciiname":"Bukuvna",
    "gn:country_code":"UA",
    "gn:dem":321,
    "gn:feature_class":"P",
    "gn:feature_code":"PPL",
    "gn:name":"Bukuvna",
    "gn:population":0,
    "gn:timezone":"Europe/Kiev",
    "iso:country":"UA",
    "name:und_x_variant":[
        "Bukovna",
        "Bukuvna"
    ],
    "wof:name":"Bukuvna",
    "wof:placetype":"locality"
},
  "geometry": {"coordinates":[24.96774,48.9684],"type":"Point"}
}