{
  "type": "Feature",
  "properties": {
    "gn:admin1_code":"15.0",
    "gn:asciiname":"Kulparkiv",
    "gn:country_code":"UA",
    "gn:dem":337,
    "gn:elevation":"330.0",
    "gn:feature_class":"P",
    "gn:feature_code":"PPL",
    "gn:name":"Kulparkiv",
    "gn:population":0,
    "gn:timezone":"Europe/Kiev",
    "iso:country":"UA",
    "name:pol_x_preferred":[
        "Kulparkow"
    ],
    "name:rus_x_preferred":[
        "\u041a\u0443\u043b\u044c\u043f\u0430\u0440\u043a\u043e\u0432"
    ],
    "name:ukr_x_preferred":[
        "\u041a\u0443\u043b\u044c\u043f\u0430\u0440\u043a\u0456\u0432"
    ],
    "wof:name":"Kulparkiv",
    "wof:placetype":"locality"
},
  "geometry": {"coordinates":[23.99041,49.81577],"type":"Point"}
}