{
  "type": "Feature",
  "properties": {
    "gn:admin1_code":"26.0",
    "gn:asciiname":"Novoselivka",
    "gn:country_code":"UA",
    "gn:dem":75,
    "gn:feature_class":"P",
    "gn:feature_code":"PPL",
    "gn:name":"Novoselivka",
    "gn:population":0,
    "gn:timezone":"Europe/Zaporozhye",
    "iso:country":"UA",
    "name:ukr_x_preferred":[
        "Novoselivka"
    ],
    "name:ukr_x_variant":[
        "\u041d\u043e\u0432\u043e\u0441\u0435\u043b\u0456\u0432\u043a\u0430"
    ],
    "name:und_x_variant":[
        "Novoselitsa",
        "Novaya Sel\u2019yevka",
        "Novoselitsa Vtoraya",
        "Novos\u00eblovka"
    ],
    "wof:name":"Novoselivka",
    "wof:placetype":"locality"
},
  "geometry": {"coordinates":[36.00139,47.61719],"type":"Point"}
}