{
  "type": "Feature",
  "properties": {
    "gn:admin1_code":"5.0",
    "gn:asciiname":"Hirnyk",
    "gn:country_code":"UA",
    "gn:dem":201,
    "gn:feature_class":"P",
    "gn:feature_code":"PPL",
    "gn:name":"Hirnyk",
    "gn:population":0,
    "gn:timezone":"Europe/Kiev",
    "iso:country":"UA",
    "name:ces_x_preferred":[
        "Hirnyk"
    ],
    "name:crh_x_preferred":[
        "Girn\u0131k"
    ],
    "name:deu_x_preferred":[
        "Hirnyk"
    ],
    "name:eng_x_preferred":[
        "Gornyak"
    ],
    "name:fas_x_preferred":[
        "\u0647\u06cc\u0631\u0646\u06cc\u06a9"
    ],
    "name:fra_x_preferred":[
        "Hirnyk"
    ],
    "name:hsb_x_preferred":[
        "Hirnyk"
    ],
    "name:hye_x_preferred":[
        "\u0533\u0578\u0580\u0576\u0575\u0561\u056f"
    ],
    "name:ita_x_preferred":[
        "Hirnyk"
    ],
    "name:kat_x_preferred":[
        "\u10d2\u10dd\u10e0\u10dc\u10d8\u10d0\u10d9\u10d8"
    ],
    "name:lav_x_preferred":[
        "Hirnika"
    ],
    "name:lit_x_preferred":[
        "Hirnykas"
    ],
    "name:nno_x_preferred":[
        "Hirnyk"
    ],
    "name:nor_x_preferred":[
        "Hirnyk"
    ],
    "name:pol_x_preferred":[
        "Hirnyk"
    ],
    "name:ron_x_preferred":[
        "Hirn\u00eek"
    ],
    "name:rus_x_preferred":[
        "\u0413\u043e\u0440\u043d\u044f\u043a"
    ],
    "name:ukr_x_preferred":[
        "Hirnyk"
    ],
    "name:ukr_x_variant":[
        "\u0413\u0456\u0440\u043d\u0438\u043a"
    ],
    "name:und_x_variant":[
        "Sotsgorodok",
        "Gornyak"
    ],
    "name:zho_x_preferred":[
        "\u6208\u723e\u5c3c\u4e9e\u514b"
    ],
    "wof:name":"Hirnyk",
    "wof:placetype":"locality"
},
  "geometry": {"coordinates":[37.37309000000001,48.0557],"type":"Point"}
}