{
  "type": "Feature",
  "properties": {
    "gn:admin1_code":"14.0",
    "gn:asciiname":"Makiyivka",
    "gn:country_code":"UA",
    "gn:dem":80,
    "gn:feature_class":"P",
    "gn:feature_code":"PPL",
    "gn:name":"Makiyivka",
    "gn:population":0,
    "gn:timezone":"Europe/Zaporozhye",
    "iso:country":"UA",
    "name:eng_x_preferred":[
        "Makiyivka"
    ],
    "name:rus_x_preferred":[
        "\u041c\u0430\u043a\u0435\u0435\u0432\u043a\u0430"
    ],
    "name:ukr_x_preferred":[
        "Makiyivka"
    ],
    "name:und_x_variant":[
        "Makeyevka"
    ],
    "wof:name":"Makiyivka",
    "wof:placetype":"locality"
},
  "geometry": {"coordinates":[37.98363,49.2278],"type":"Point"}
}