{
  "type": "Feature",
  "properties": {
    "gn:admin1_code":"17.0",
    "gn:asciiname":"Vasylivka",
    "gn:cc2":"UA",
    "gn:country_code":"UA",
    "gn:dem":59,
    "gn:feature_class":"P",
    "gn:feature_code":"PPL",
    "gn:name":"Vasylivka",
    "gn:population":0,
    "gn:timezone":"Europe/Kiev",
    "iso:country":"UA",
    "name:und_x_variant":[
        "Vasil'yevka"
    ],
    "wof:name":"Vasylivka",
    "wof:placetype":"locality"
},
  "geometry": {"coordinates":[29.18944,47.47111],"type":"Point"}
}