{
  "type": "Feature",
  "properties": {
    "gn:admin1_code":"27.0",
    "gn:asciiname":"Radets'ka Bolyarka",
    "gn:country_code":"UA",
    "gn:dem":229,
    "gn:feature_class":"P",
    "gn:feature_code":"PPL",
    "gn:name":"Radets\u2019ka Bolyarka",
    "gn:population":0,
    "gn:timezone":"Europe/Kiev",
    "iso:country":"UA",
    "name:ukr_x_preferred":[
        "Radets\u2019ka Bolyarka"
    ],
    "name:ukr_x_variant":[
        "\u0420\u0430\u0434\u0435\u0446\u044c\u043a\u0430 \u0411\u043e\u043b\u044f\u0440\u043a\u0430"
    ],
    "name:und_x_variant":[
        "Radetskaya Bolyarka"
    ],
    "wof:name":"Radets'ka Bolyarka",
    "wof:placetype":"locality"
},
  "geometry": {"coordinates":[28.24969,50.59097],"type":"Point"}
}