{
  "type": "Feature",
  "properties": {
    "gn:admin1_code":"11.0",
    "gn:admin2_code":"703233",
    "gn:admin3_code":"11129210.0",
    "gn:asciiname":"Ptashkino",
    "gn:country_code":"UA",
    "gn:dem":49,
    "gn:feature_class":"P",
    "gn:feature_code":"PPL",
    "gn:name":"Ptashkino",
    "gn:population":23,
    "gn:timezone":"Europe/Simferopol",
    "iso:country":"UA",
    "name:eng_x_preferred":[
        "Ptashkino"
    ],
    "name:rus_x_historical":[
        "\u0414\u0436\u0435\u043b\u044c\u043a\u0435\u0434\u0436\u0438\u0301-\u042d\u043b\u0438\u0301"
    ],
    "name:rus_x_preferred":[
        "\u041f\u0442\u0430\u0448\u043a\u0438\u043d\u043e"
    ],
    "name:rus_x_variant":[
        "\u0414\u0436\u0435\u043b\u044c\u043a\u0435\u0434\u0436\u0438\u0301-\u042d\u043b\u0438\u0301"
    ],
    "name:ukr_x_preferred":[
        "\u041f\u0442\u0430\u0448\u0438\u043d\u0435"
    ],
    "wof:name":"Ptashkino",
    "wof:placetype":"locality",
    "wof:population":23
},
  "geometry": {"coordinates":[36.18676,45.16458],"type":"Point"}
}