{
  "type": "Feature",
  "properties": {
    "gn:admin1_code":"15.0",
    "gn:asciiname":"Staryava",
    "gn:country_code":"UA",
    "gn:dem":367,
    "gn:feature_class":"P",
    "gn:feature_code":"PPL",
    "gn:name":"Staryava",
    "gn:population":0,
    "gn:timezone":"Europe/Kiev",
    "iso:country":"UA",
    "name:ukr_x_preferred":[
        "Staryava"
    ],
    "name:ukr_x_variant":[
        "\u0421\u0442\u0430\u0440\u044f\u0432\u0430"
    ],
    "name:und_x_variant":[
        "Starzawa",
        "Stazhava",
        "Starzhava"
    ],
    "wof:name":"Staryava",
    "wof:placetype":"locality"
},
  "geometry": {"coordinates":[22.76114,49.50469],"type":"Point"}
}