{
  "type": "Feature",
  "properties": {
    "gn:admin1_code":"27",
    "gn:asciiname":"Komarovka",
    "gn:country_code":"UA",
    "gn:dem":218,
    "gn:feature_class":"P",
    "gn:feature_code":"PPL",
    "gn:name":"Komarovka",
    "gn:population":0,
    "gn:timezone":"Europe/Kiev",
    "iso:country":"UA",
    "name:che_x_preferred":[
        "\u041a\u043e\u043c\u0430\u0440\u043e\u0432\u043a\u0430"
    ],
    "name:rus_x_preferred":[
        "\u041a\u043e\u043c\u0430\u0440\u043e\u0432\u043a\u0430"
    ],
    "name:tgk_x_preferred":[
        "\u041a\u043e\u043c\u0430\u0440\u043e\u0432\u043a\u0430"
    ],
    "name:ukr_x_preferred":[
        "\u041a\u043e\u043c\u0430\u0440\u0456\u0432\u043a\u0430"
    ],
    "wof:name":"Komarovka",
    "wof:placetype":"locality"
},
  "geometry": {"coordinates":[28.64479,50.54785],"type":"Point"}
}