{
  "type": "Feature",
  "properties": {
    "gn:admin1_code":"21.0",
    "gn:asciiname":"Svirzh",
    "gn:country_code":"UA",
    "gn:dem":135,
    "gn:feature_class":"P",
    "gn:feature_code":"PPL",
    "gn:name":"Svirzh",
    "gn:population":0,
    "gn:timezone":"Europe/Kiev",
    "iso:country":"UA",
    "name:ukr_x_preferred":[
        "Svirzh"
    ],
    "name:ukr_x_variant":[
        "\u0421\u0432\u0456\u0440\u0436"
    ],
    "wof:name":"Svirzh",
    "wof:placetype":"locality"
},
  "geometry": {"coordinates":[33.40831,52.00999],"type":"Point"}
}