{
  "type": "Feature",
  "properties": {
    "gn:admin1_code":"25.0",
    "gn:asciiname":"Karachyn",
    "gn:country_code":"UA",
    "gn:dem":118,
    "gn:feature_class":"P",
    "gn:feature_code":"PPL",
    "gn:name":"Karachyn",
    "gn:population":0,
    "gn:timezone":"Europe/Uzhgorod",
    "iso:country":"UA",
    "name:ukr_x_preferred":[
        "Karachyn"
    ],
    "name:ukr_x_variant":[
        "\u041a\u0430\u0440\u0430\u0447\u0438\u043d"
    ],
    "name:und_x_variant":[
        "Karachin"
    ],
    "wof:name":"Karachyn",
    "wof:placetype":"locality"
},
  "geometry": {"coordinates":[22.8728,48.13065],"type":"Point"}
}