{
  "type": "Feature",
  "properties": {
    "gn:admin1_code":"17.0",
    "gn:asciiname":"Divots'ke",
    "gn:country_code":"UA",
    "gn:dem":183,
    "gn:feature_class":"P",
    "gn:feature_code":"PPL",
    "gn:name":"Divots\u2019ke",
    "gn:population":0,
    "gn:timezone":"Europe/Kiev",
    "iso:country":"UA",
    "name:ukr_x_preferred":[
        "Divots\u2019ke"
    ],
    "name:ukr_x_variant":[
        "\u0414\u0456\u0432\u043e\u0446\u044c\u043a\u0435"
    ],
    "name:und_x_variant":[
        "Khutor Devitskiy",
        "Devitskiy",
        "Devotskoye"
    ],
    "wof:name":"Divots'ke",
    "wof:placetype":"locality"
},
  "geometry": {"coordinates":[29.69779,47.08794],"type":"Point"}
}