{
  "type": "Feature",
  "properties": {
    "iso:country":"UA",
    "name:azb_x_preferred":[
        "\u0633\u0648\u06a9\u0648\u0644\u06cc\u0646"
    ],
    "name:bel_x_preferred":[
        "\u0421\u0430\u043a\u0430\u043b\u044b\u043d\u044d"
    ],
    "name:cat_x_preferred":[
        "Sokol\u00ednoie"
    ],
    "name:crh_x_preferred":[
        "K\u00f6kk\u00f6z"
    ],
    "name:deu_x_preferred":[
        "Sokolinoje"
    ],
    "name:eng_x_preferred":[
        "Sokolinoye"
    ],
    "name:eng_x_variant":[
        "Sokolyne"
    ],
    "name:fas_x_preferred":[
        "\u0633\u0648\u06a9\u0648\u0644\u06cc\u0646\u0647"
    ],
    "name:hye_x_preferred":[
        "\u054d\u0578\u056f\u0578\u056c\u056b\u0576\u0578\u0565"
    ],
    "name:nld_x_preferred":[
        "Sokolinoe"
    ],
    "name:nno_x_preferred":[
        "Sokolinoje"
    ],
    "name:nob_x_preferred":[
        "Sokolinoje"
    ],
    "name:ron_x_preferred":[
        "Sokol\u00eene"
    ],
    "name:rus_x_historical":[
        "\u041a\u043e\u043a\u043a\u043e\u0301\u0437\u044b"
    ],
    "name:rus_x_preferred":[
        "\u0421\u043e\u043a\u043e\u043b\u0438\u043d\u043e\u0435"
    ],
    "name:sqi_x_preferred":[
        "Sokolinoe"
    ],
    "name:ukr_x_preferred":[
        "\u0421\u043e\u043a\u043e\u043b\u0438\u043d\u0435"
    ],
    "qs:a0":"\u0423\u043a\u0440\u0430\u0457\u043d\u0430",
    "qs:a1":"*\u041a\u0440\u0438\u043c",
    "qs:a1_alt":"Krym",
    "qs:a1r":"0",
    "qs:a2":"\u0411\u0430\u0445\u0447\u0438\u0441\u0430\u0440\u0430\u0439\u0441\u044c\u043a\u0438\u0439",
    "qs:a2_alt":"Bakhchysarais'kyi",
    "qs:adm0":"\u0423\u043a\u0440\u0430\u0457\u043d\u0430",
    "qs:la_lc":"*",
    "qs:level":"locality",
    "qs:loc":"\u0421\u043e\u043a\u043e\u043b\u0438\u043d\u0435",
    "qs:loc_alt":"Sokolyne",
    "qs:pop":0,
    "qs:type":"buffered point",
    "wd:wordcount":128,
    "wof:name":"\u0421\u043e\u043a\u043e\u043b\u0438\u043d\u0435",
    "wof:placetype":"locality"
},
  "geometry": {"coordinates":[33.954649,44.550484],"type":"Point"}
}