{
  "type": "Feature",
  "properties": {
    "iso:country":"UA",
    "qs:a0":"\u0423\u043a\u0440\u0430\u0457\u043d\u0430",
    "qs:a1":"*\u0416\u0438\u0442\u043e\u043c\u0438\u0440\u0441\u044c\u043a\u0430",
    "qs:a1_alt":"Zhytomyrs'ka",
    "qs:a1r":"0",
    "qs:a2":"\u0420\u0443\u0436\u0438\u043d\u0441\u044c\u043a\u0438\u0439",
    "qs:a2_alt":"Ruzhyns'kyi",
    "qs:adm0":"\u0423\u043a\u0440\u0430\u0457\u043d\u0430",
    "qs:la_lc":"*",
    "qs:level":"locality",
    "qs:loc":"\u0417\u0430\u0440\u0456\u0447\u0447\u044f",
    "qs:loc_alt":"Zarichchia",
    "qs:pop":0,
    "qs:type":"buffered point",
    "wd:wordcount":102,
    "wof:name":"\u0417\u0430\u0440\u0456\u0447\u0447\u044f",
    "wof:placetype":"locality"
},
  "geometry": {"coordinates":[29.240865,49.708965],"type":"Point"}
}