{
  "type": "Feature",
  "properties": {
    "gn:admin1_code":"13.0",
    "gn:asciiname":"Sloboda-Kukhars'ka",
    "gn:country_code":"UA",
    "gn:dem":152,
    "gn:feature_class":"P",
    "gn:feature_code":"PPL",
    "gn:name":"Sloboda-Kukhars\u2019ka",
    "gn:population":0,
    "gn:timezone":"Europe/Kiev",
    "iso:country":"UA",
    "name:ukr_x_preferred":[
        "Sloboda-Kukhars\u2019ka"
    ],
    "name:ukr_x_variant":[
        "\u0421\u043b\u043e\u0431\u043e\u0434\u0430-\u041a\u0443\u0445\u0430\u0440\u0441\u044c\u043a\u0430"
    ],
    "name:und_x_variant":[
        "Sloboda Kukasskaya",
        "Kukharskaya",
        "Sloboda-Kukharskaya"
    ],
    "wof:name":"Sloboda-Kukhars'ka",
    "wof:placetype":"locality"
},
  "geometry": {"coordinates":[29.54502,50.8406],"type":"Point"}
}