{
  "type": "Feature",
  "properties": {
    "gn:admin1_code":"18.0",
    "gn:asciiname":"Nahirne",
    "gn:country_code":"UA",
    "gn:dem":123,
    "gn:feature_class":"P",
    "gn:feature_code":"PPL",
    "gn:name":"Nahirne",
    "gn:population":0,
    "gn:timezone":"Europe/Kiev",
    "iso:country":"UA",
    "name:ukr_x_preferred":[
        "Nahirne"
    ],
    "name:ukr_x_variant":[
        "\u041d\u0430\u0433\u0456\u0440\u043d\u0435"
    ],
    "wof:name":"Nahirne",
    "wof:placetype":"locality"
},
  "geometry": {"coordinates":[34.01872,49.45469],"type":"Point"}
}