{
  "type": "Feature",
  "properties": {
    "gn:admin1_code":"15.0",
    "gn:asciiname":"Sebechiv",
    "gn:country_code":"UA",
    "gn:dem":221,
    "gn:feature_class":"P",
    "gn:feature_code":"PPL",
    "gn:name":"Sebechiv",
    "gn:population":0,
    "gn:timezone":"Europe/Kiev",
    "iso:country":"UA",
    "name:ukr_x_preferred":[
        "Sebechiv"
    ],
    "name:ukr_x_variant":[
        "\u0421\u0435\u0431\u0435\u0447\u0456\u0432"
    ],
    "name:und_x_variant":[
        "Siebiecz\u00f3w",
        "Sebechuv",
        "Krasnosel\u2019ye"
    ],
    "wof:name":"Sebechiv",
    "wof:placetype":"locality"
},
  "geometry": {"coordinates":[24.12691,50.44411],"type":"Point"}
}