{
  "type": "Feature",
  "properties": {
    "gn:admin1_code":"23.0",
    "gn:asciiname":"Vyhnanka",
    "gn:country_code":"UA",
    "gn:dem":212,
    "gn:feature_class":"P",
    "gn:feature_code":"PPL",
    "gn:name":"Vyhnanka",
    "gn:population":0,
    "gn:timezone":"Europe/Kiev",
    "iso:country":"UA",
    "name:ukr_x_preferred":[
        "Vyhnanka"
    ],
    "name:und_x_variant":[
        "\u0412\u0438\u0433\u043d\u0430\u043d\u043a\u0430",
        "Vygnanka"
    ],
    "wof:name":"Vyhnanka",
    "wof:placetype":"locality"
},
  "geometry": {"coordinates":[28.81562000000001,48.86132],"type":"Point"}
}