{
  "type": "Feature",
  "properties": {
    "gn:admin1_code":"21.0",
    "gn:asciiname":"Roman'kove",
    "gn:country_code":"UA",
    "gn:dem":186,
    "gn:feature_class":"P",
    "gn:feature_code":"PPL",
    "gn:name":"Roman\u2019kove",
    "gn:population":0,
    "gn:timezone":"Europe/Kiev",
    "iso:country":"UA",
    "name:rus_x_preferred":[
        "Roman\u2019kovo"
    ],
    "name:ukr_x_preferred":[
        "Roman\u2019kove"
    ],
    "name:ukr_x_variant":[
        "\u0420\u043e\u043c\u0430\u043d\u044c\u043a\u043e\u0432\u0435"
    ],
    "name:und_x_variant":[
        "Roman\u2019kov"
    ],
    "wof:name":"Roman'kove",
    "wof:placetype":"locality"
},
  "geometry": {"coordinates":[33.86158,52.05411],"type":"Point"}
}