{
  "type": "Feature",
  "properties": {
    "gn:admin1_code":"18.0",
    "gn:asciiname":"Brovarky",
    "gn:country_code":"UA",
    "gn:dem":135,
    "gn:feature_class":"P",
    "gn:feature_code":"PPL",
    "gn:name":"Brovarky",
    "gn:population":0,
    "gn:timezone":"Europe/Kiev",
    "iso:country":"UA",
    "name:ukr_x_preferred":[
        "Brovarky"
    ],
    "name:ukr_x_variant":[
        "\u0411\u0440\u043e\u0432\u0430\u0440\u043a\u0438"
    ],
    "wof:name":"Brovarky",
    "wof:placetype":"locality"
},
  "geometry": {"coordinates":[33.32599,50.10046],"type":"Point"}
}