{
  "type": "Feature",
  "properties": {
    "gn:admin1_code":"8.0",
    "gn:asciiname":"Bilotserkivka",
    "gn:country_code":"UA",
    "gn:dem":26,
    "gn:feature_class":"P",
    "gn:feature_code":"PPL",
    "gn:name":"Bilotserkivka",
    "gn:population":0,
    "gn:timezone":"Europe/Kiev",
    "iso:country":"UA",
    "name:rus_x_preferred":[
        "\u0411\u0435\u043b\u043e\u0446\u0435\u0440\u043a\u043e\u0432\u043a\u0430"
    ],
    "name:ukr_x_preferred":[
        "\u0411\u0456\u043b\u043e\u0446\u0435\u0440\u043a\u0456\u0432\u043a\u0430"
    ],
    "name:und_x_variant":[
        "Belozerkowka",
        "Belotserkovka",
        "Bilotserkivka"
    ],
    "wof:name":"Bilotserkivka",
    "wof:placetype":"locality"
},
  "geometry": {"coordinates":[33.30078,46.4633],"type":"Point"}
}