{
  "type": "Feature",
  "properties": {
    "iso:country":"UA",
    "name:rus_x_preferred":[
        "\u0411\u043e\u043b\u044c\u0448\u0438\u0435 \u041f\u0440\u043e\u0445\u043e\u0434\u044b"
    ],
    "name:ukr_x_preferred":[
        "\u0412\u0435\u043b\u0438\u043a\u0456 \u041f\u0440\u043e\u0445\u043e\u0434\u0438"
    ],
    "name:und_x_variant":[
        "Velikiye Prokhody"
    ],
    "qs:a0":"\u0423\u043a\u0440\u0430\u0457\u043d\u0430",
    "qs:a1":"*\u0425\u0430\u0440\u043a\u0456\u0432\u0441\u044c\u043a\u0430",
    "qs:a1_alt":"Kharkivs'ka",
    "qs:a1r":"0",
    "qs:a2":"\u0414\u0435\u0440\u0433\u0430\u0447\u0456\u0432\u0441\u044c\u043a\u0438\u0439",
    "qs:a2_alt":"Derhachivs'kyi",
    "qs:adm0":"\u0423\u043a\u0440\u0430\u0457\u043d\u0430",
    "qs:la_lc":"*",
    "qs:level":"locality",
    "qs:loc":"\u0412\u0435\u043b\u0438\u043a\u0456 \u041f\u0440\u043e\u0445\u043e\u0434\u0438",
    "qs:loc_alt":"Velyki Prokhody",
    "qs:pop":0,
    "qs:type":"buffered point",
    "wof:name":"\u0412\u0435\u043b\u0438\u043a\u0456 \u041f\u0440\u043e\u0445\u043e\u0434\u0438",
    "wof:placetype":"locality"
},
  "geometry": {"coordinates":[36.335709,50.203583],"type":"Point"}
}