{
  "type": "Feature",
  "properties": {
    "gn:admin1_code":"4.0",
    "gn:asciiname":"Krasnyy Pid",
    "gn:country_code":"UA",
    "gn:dem":99,
    "gn:feature_class":"P",
    "gn:feature_code":"PPL",
    "gn:name":"Krasnyy Pid",
    "gn:population":0,
    "gn:timezone":"Europe/Kiev",
    "iso:country":"UA",
    "name:ukr_x_preferred":[
        "Krasnyy Pid"
    ],
    "name:ukr_x_variant":[
        "\u041a\u0440\u0430\u0441\u043d\u0438\u0439 \u041f\u0456\u0434"
    ],
    "name:und_x_variant":[
        "Krasny Pod",
        "Krasnyy Pod"
    ],
    "wof:name":"Krasnyy Pid",
    "wof:placetype":"locality"
},
  "geometry": {"coordinates":[33.45427,47.75861],"type":"Point"}
}