{
  "type": "Feature",
  "properties": {
    "gn:admin1_code":"9.0",
    "gn:asciiname":"Dosin",
    "gn:country_code":"UA",
    "gn:dem":215,
    "gn:feature_class":"P",
    "gn:feature_code":"PPL",
    "gn:name":"Dosin",
    "gn:population":0,
    "gn:timezone":"Europe/Kiev",
    "iso:country":"UA",
    "name:ukr_x_preferred":[
        "Dosin"
    ],
    "name:ukr_x_variant":[
        "\u0414\u043e\u0441\u0456\u043d"
    ],
    "wof:name":"Dosin",
    "wof:placetype":"locality"
},
  "geometry": {"coordinates":[26.93511,50.42187],"type":"Point"}
}