{
  "type": "Feature",
  "properties": {
    "gn:admin1_code":"18.0",
    "gn:asciiname":"Datsiyi",
    "gn:country_code":"UA",
    "gn:dem":88,
    "gn:feature_class":"P",
    "gn:feature_code":"PPL",
    "gn:name":"Datsiyi",
    "gn:population":0,
    "gn:timezone":"Europe/Kiev",
    "iso:country":"UA",
    "name:ukr_x_preferred":[
        "Datsiyi"
    ],
    "name:ukr_x_variant":[
        "\u0414\u0430\u0446\u0456\u0457"
    ],
    "wof:name":"Datsiyi",
    "wof:placetype":"locality"
},
  "geometry": {"coordinates":[32.99473,49.82607],"type":"Point"}
}