{
  "type": "Feature",
  "properties": {
    "gn:admin1_code":"22.0",
    "gn:asciiname":"Romanovka",
    "gn:country_code":"UA",
    "gn:dem":314,
    "gn:feature_class":"P",
    "gn:feature_code":"PPL",
    "gn:name":"Romanovka",
    "gn:population":0,
    "gn:timezone":"Europe/Kiev",
    "iso:country":"UA",
    "name:und_x_variant":[
        "Romanivka",
        "Romanovka"
    ],
    "wof:name":"Romanovka",
    "wof:placetype":"locality"
},
  "geometry": {"coordinates":[25.5803,49.21367],"type":"Point"}
}