{
  "type": "Feature",
  "properties": {
    "gn:admin1_code":"2.0",
    "gn:asciiname":"Shyshkivka",
    "gn:country_code":"UA",
    "gn:dem":133,
    "gn:feature_class":"P",
    "gn:feature_code":"PPL",
    "gn:name":"Shyshkivka",
    "gn:population":0,
    "gn:timezone":"Europe/Kiev",
    "iso:country":"UA",
    "name:eng_x_preferred":[
        "Shishkovka"
    ],
    "name:rus_x_preferred":[
        "\u0428\u0438\u0448\u043a\u043e\u0432\u043a\u0430"
    ],
    "name:ukr_x_preferred":[
        "Shyshkivka"
    ],
    "name:ukr_x_variant":[
        "\u0428\u0438\u0448\u043a\u0456\u0432\u043a\u0430"
    ],
    "name:und_x_variant":[
        "Shishkovka"
    ],
    "wof:name":"Shyshkivka",
    "wof:placetype":"locality"
},
  "geometry": {"coordinates":[32.28913,52.022],"type":"Point"}
}