{
  "type": "Feature",
  "properties": {
    "gn:admin1_code":"19.0",
    "gn:asciiname":"Yablunne",
    "gn:country_code":"UA",
    "gn:dem":182,
    "gn:feature_class":"P",
    "gn:feature_code":"PPL",
    "gn:name":"Yablunne",
    "gn:population":0,
    "gn:timezone":"Europe/Kiev",
    "iso:country":"UA",
    "name:ukr_x_preferred":[
        "Yablunne"
    ],
    "name:ukr_x_variant":[
        "\u042f\u0431\u043b\u0443\u043d\u043d\u0435"
    ],
    "name:und_x_variant":[
        "Yablonne",
        "Yablonnoye"
    ],
    "wof:name":"Yablunne",
    "wof:placetype":"locality"
},
  "geometry": {"coordinates":[26.63387,50.95538],"type":"Point"}
}