{
  "type": "Feature",
  "properties": {
    "iso:country":"UA",
    "name:crh_x_preferred":[
        "Krakovets"
    ],
    "name:deu_x_preferred":[
        "Krakowez"
    ],
    "name:eng_x_preferred":[
        "Krakovets"
    ],
    "name:pol_x_preferred":[
        "Krakowiec"
    ],
    "name:ron_x_preferred":[
        "Krakove\u021b"
    ],
    "name:rus_x_preferred":[
        "\u041a\u0440\u0430\u043a\u043e\u0432\u0435\u0446"
    ],
    "name:ukr_x_preferred":[
        "\u041a\u0440\u0430\u043a\u043e\u0432\u0435\u0446\u044c"
    ],
    "name:unk_x_variant":[
        "Krakowiec"
    ],
    "name:zho_x_preferred":[
        "\u514b\u62c9\u79d1\u97cb\u9f4a"
    ],
    "qs:a0":"\u0423\u043a\u0440\u0430\u0457\u043d\u0430",
    "qs:a1":"*\u041b\u044c\u0432\u0456\u0432\u0441\u044c\u043a\u0430",
    "qs:a1_alt":"L'vivs'ka",
    "qs:a1r":"0",
    "qs:a2":"\u042f\u0432\u043e\u0440\u0456\u0432\u0441\u044c\u043a\u0438\u0439",
    "qs:a2_alt":"Yavorivs'kyi",
    "qs:adm0":"\u0423\u043a\u0440\u0430\u0457\u043d\u0430",
    "qs:la_lc":"*",
    "qs:level":"locality",
    "qs:loc":"\u041a\u0440\u0430\u043a\u043e\u0432\u0435\u0446\u044c",
    "qs:loc_alt":"Krakovets",
    "qs:pop":0,
    "qs:type":"buffered point",
    "wd:wordcount":109,
    "wof:name":"\u041a\u0440\u0430\u043a\u043e\u0432\u0435\u0446\u044c",
    "wof:placetype":"locality"
},
  "geometry": {"coordinates":[23.161028,49.961508],"type":"Point"}
}