{
  "type": "Feature",
  "properties": {
    "gn:admin1_code":"13.0",
    "gn:asciiname":"Petropavlivs'ke",
    "gn:country_code":"UA",
    "gn:dem":123,
    "gn:feature_class":"P",
    "gn:feature_code":"PPL",
    "gn:name":"Petropavlivs\u2019ke",
    "gn:population":0,
    "gn:timezone":"Europe/Kiev",
    "iso:country":"UA",
    "name:ukr_x_preferred":[
        "Petrovs\u2019ke"
    ],
    "name:ukr_x_variant":[
        "\u041f\u0435\u0442\u0440\u043e\u0432\u0441\u044c\u043a\u0435",
        "Petropavlivs\u2019ke",
        "\u041f\u0435\u0442\u0440\u043e\u043f\u0430\u0432\u043b\u0456\u0432\u0441\u044c\u043a\u0435"
    ],
    "name:und_x_variant":[
        "Khutor-Petrovskiy"
    ],
    "wof:name":"Petropavlivs'ke",
    "wof:placetype":"locality"
},
  "geometry": {"coordinates":[30.82864,50.32593],"type":"Point"}
}