{
  "type": "Feature",
  "properties": {
    "gn:admin1_code":"26.0",
    "gn:asciiname":"Sakhno",
    "gn:country_code":"UA",
    "gn:dem":102,
    "gn:feature_class":"P",
    "gn:feature_code":"PPL",
    "gn:name":"Sakhno",
    "gn:population":0,
    "gn:timezone":"Europe/Zaporozhye",
    "iso:country":"UA",
    "name:ukr_x_preferred":[
        "Sakhno"
    ],
    "wof:name":"Sakhno",
    "wof:placetype":"locality"
},
  "geometry": {"coordinates":[36.46848,47.10305],"type":"Point"}
}