{
  "type": "Feature",
  "properties": {
    "gn:admin1_code":"15.0",
    "gn:asciiname":"Rusilov",
    "gn:country_code":"UA",
    "gn:dem":237,
    "gn:feature_class":"P",
    "gn:feature_code":"PPL",
    "gn:name":"Rusilov",
    "gn:population":0,
    "gn:timezone":"Europe/Kiev",
    "iso:country":"UA",
    "name:und_x_variant":[
        "Rusilow",
        "Rusiluv",
        "Rusilov"
    ],
    "wof:name":"Rusilov",
    "wof:placetype":"locality"
},
  "geometry": {"coordinates":[24.58903,49.88],"type":"Point"}
}