{
  "type": "Feature",
  "properties": {
    "gn:admin1_code":"19.0",
    "gn:asciiname":"Malyy Zholuds'k",
    "gn:country_code":"UA",
    "gn:dem":167,
    "gn:feature_class":"P",
    "gn:feature_code":"PPL",
    "gn:name":"Malyy Zholuds\u2019k",
    "gn:population":0,
    "gn:timezone":"Europe/Kiev",
    "iso:country":"UA",
    "name:ukr_x_preferred":[
        "Malyy Zholuds\u2019k"
    ],
    "name:ukr_x_variant":[
        "\u041c\u0430\u043b\u0438\u0439 \u0416\u043e\u043b\u0443\u0434\u0441\u044c\u043a"
    ],
    "name:und_x_variant":[
        "Malyy Zholudsk",
        "Maly Zholudsk",
        "Malyy Zh\u00eblutsk"
    ],
    "wof:name":"Malyy Zholuds'k",
    "wof:placetype":"locality"
},
  "geometry": {"coordinates":[26.10074,51.30492],"type":"Point"}
}