{
  "type": "Feature",
  "properties": {
    "gn:admin1_code":"26.0",
    "gn:asciiname":"Trudove",
    "gn:country_code":"UA",
    "gn:dem":68,
    "gn:feature_class":"P",
    "gn:feature_code":"PPL",
    "gn:name":"Trudove",
    "gn:population":0,
    "gn:timezone":"Europe/Zaporozhye",
    "iso:country":"UA",
    "name:ukr_x_preferred":[
        "Trudove"
    ],
    "name:ukr_x_variant":[
        "\u0422\u0440\u0443\u0434\u043e\u0432\u0435"
    ],
    "name:und_x_variant":[
        "Kaykulak"
    ],
    "wof:name":"Trudove",
    "wof:placetype":"locality"
},
  "geometry": {"coordinates":[35.94848,47.2577],"type":"Point"}
}