{
  "type": "Feature",
  "properties": {
    "gn:admin1_code":"15",
    "gn:asciiname":"Komariv",
    "gn:country_code":"UA",
    "gn:dem":309,
    "gn:feature_class":"P",
    "gn:feature_code":"PPL",
    "gn:name":"Komariv",
    "gn:population":0,
    "gn:timezone":"Europe/Kiev",
    "iso:country":"UA",
    "name:rus_x_preferred":[
        "\u041a\u043e\u043c\u0430\u0440\u043e\u0432"
    ],
    "name:ukr_x_preferred":[
        "Komariv"
    ],
    "name:ukr_x_variant":[
        "\u041a\u043e\u043c\u0430\u0440\u0456\u0432"
    ],
    "name:und_x_variant":[
        "Komarov"
    ],
    "wof:name":"Komariv",
    "wof:placetype":"locality"
},
  "geometry": {"coordinates":[23.94968,49.27322],"type":"Point"}
}