{
  "type": "Feature",
  "properties": {
    "gn:admin1_code":"22.0",
    "gn:asciiname":"Mlynki",
    "gn:country_code":"UA",
    "gn:dem":289,
    "gn:feature_class":"P",
    "gn:feature_code":"PPL",
    "gn:name":"Mlynki",
    "gn:population":0,
    "gn:timezone":"Europe/Kiev",
    "iso:country":"UA",
    "name:und_x_variant":[
        "Mlinki",
        "Mlynki"
    ],
    "wof:name":"Mlynki",
    "wof:placetype":"locality"
},
  "geometry": {"coordinates":[25.26417,48.93172],"type":"Point"}
}