{
  "type": "Feature",
  "properties": {
    "gn:admin1_code":"23.0",
    "gn:asciiname":"Khutora",
    "gn:country_code":"UA",
    "gn:dem":294,
    "gn:feature_class":"P",
    "gn:feature_code":"PPL",
    "gn:name":"Khutora",
    "gn:population":0,
    "gn:timezone":"Europe/Kiev",
    "iso:country":"UA",
    "name:und_x_variant":[
        "Bol\u2019shiye Khutora"
    ],
    "wof:name":"Khutora",
    "wof:placetype":"locality"
},
  "geometry": {"coordinates":[28.58448,49.20162],"type":"Point"}
}