{
  "type": "Feature",
  "properties": {
    "iso:country":"UA",
    "name:deu_x_preferred":[
        "Iwano-Hanniwka"
    ],
    "name:eng_x_preferred":[
        "Hannivka"
    ],
    "name:eng_x_variant":[
        "Ivano-Hannivka"
    ],
    "name:lav_x_preferred":[
        "Ivano-Ha\u0146\u0146ivka"
    ],
    "name:nld_x_preferred":[
        "Ivano-Hannivka"
    ],
    "name:rus_x_preferred":[
        "\u0410\u043d\u043d\u043e\u0432\u043a\u0430"
    ],
    "name:rus_x_variant":[
        "\u0418\u0432\u0430\u043d\u043e-\u0410\u043d\u043d\u043e\u0432\u043a\u0430"
    ],
    "name:ukr_x_preferred":[
        "\u0413\u0430\u043d\u043d\u0456\u0432\u043a\u0430"
    ],
    "name:ukr_x_variant":[
        "\u0406\u0432\u0430\u043d\u043e-\u0413\u0430\u043d\u043d\u0456\u0432\u043a\u0430"
    ],
    "name:und_x_variant":[
        "Annovka"
    ],
    "name:zho_x_preferred":[
        "\u4f0a\u74e6\u8afe-\u7518\u5c3c\u592b\u5361"
    ],
    "qs:a0":"\u0423\u043a\u0440\u0430\u0457\u043d\u0430",
    "qs:a1":"*\u041a\u0456\u0440\u043e\u0432\u043e\u0433\u0440\u0430\u0434\u0441\u044c\u043a\u0430",
    "qs:a1_alt":"Kirovohrads'ka",
    "qs:a1r":"0",
    "qs:a2":"\u041f\u0435\u0442\u0440\u0456\u0432\u0441\u044c\u043a\u0438\u0439",
    "qs:a2_alt":"Petrivs'kyi",
    "qs:adm0":"\u0423\u043a\u0440\u0430\u0457\u043d\u0430",
    "qs:la_lc":"*",
    "qs:level":"locality",
    "qs:loc":"\u0413\u0430\u043d\u043d\u0456\u0432\u043a\u0430",
    "qs:loc_alt":"Hannivka",
    "qs:pop":0,
    "qs:type":"buffered point",
    "wd:wordcount":78,
    "wof:name":"\u0413\u0430\u043d\u043d\u0456\u0432\u043a\u0430",
    "wof:placetype":"locality"
},
  "geometry": {"coordinates":[33.45308,48.241454],"type":"Point"}
}