{
  "type": "Feature",
  "properties": {
    "gn:admin1_code":"25.0",
    "gn:asciiname":"Chabanivka",
    "gn:country_code":"UA",
    "gn:dem":111,
    "gn:feature_class":"P",
    "gn:feature_code":"PPL",
    "gn:name":"Chabanivka",
    "gn:population":0,
    "gn:timezone":"Europe/Uzhgorod",
    "iso:country":"UA",
    "name:ukr_x_preferred":[
        "Chabanivka"
    ],
    "name:ukr_x_variant":[
        "\u0427\u0430\u0431\u0430\u043d\u0456\u0432\u043a\u0430"
    ],
    "name:und_x_variant":[
        "Chabanovka"
    ],
    "wof:name":"Chabanivka",
    "wof:placetype":"locality"
},
  "geometry": {"coordinates":[22.54601,48.48941],"type":"Point"}
}