{
  "type": "Feature",
  "properties": {
    "gn:admin1_code":"25.0",
    "gn:asciiname":"Chabanivka",
    "gn:country_code":"UA",
    "gn:dem":111,
    "gn:feature_class":"P",
    "gn:feature_code":"PPL",
    "gn:name":"Chabanivka",
    "gn:population":0,
    "gn:timezone":"Europe/Uzhgorod",
    "iso:country":"UA",
    "name:bel_x_preferred":[
        "\u0427\u0430\u0431\u0430\u043d\u0456\u045e\u043a\u0430"
    ],
    "name:che_x_preferred":[
        "\u0427\u0430\u0431\u0430\u043d\u043e\u0432\u043a\u0430"
    ],
    "name:epo_x_preferred":[
        "\u0108abanivka"
    ],
    "name:hun_x_preferred":[
        "Bacs\u00f3"
    ],
    "name:hye_x_preferred":[
        "\u0549\u0561\u0562\u0561\u0576\u0578\u057e\u056f\u0561"
    ],
    "name:pol_x_preferred":[
        "Czabaniwka"
    ],
    "name:ron_x_preferred":[
        "Ceabanivka"
    ],
    "name:rus_x_preferred":[
        "\u0427\u0430\u0431\u0430\u043d\u043e\u0432\u043a\u0430"
    ],
    "name:ukr_x_preferred":[
        "Chabanivka"
    ],
    "name:ukr_x_variant":[
        "\u0427\u0430\u0431\u0430\u043d\u0456\u0432\u043a\u0430"
    ],
    "name:und_x_variant":[
        "Chabanovka"
    ],
    "name:zho_x_preferred":[
        "\u6070\u5df4\u5c3c\u592b\u5361"
    ],
    "wof:name":"Chabanivka",
    "wof:placetype":"locality"
},
  "geometry": {"coordinates":[22.54601,48.48941],"type":"Point"}
}