{
  "type": "Feature",
  "properties": {
    "gn:admin1_code":"13.0",
    "gn:asciiname":"Malyy Karatul'",
    "gn:country_code":"UA",
    "gn:dem":99,
    "gn:feature_class":"P",
    "gn:feature_code":"PPL",
    "gn:name":"Malyy Karatul\u2019",
    "gn:population":0,
    "gn:timezone":"Europe/Kiev",
    "iso:country":"UA",
    "name:und_x_variant":[
        "Maly Karatul",
        "Malyy Karatul\u2019"
    ],
    "wof:name":"Malyy Karatul'",
    "wof:placetype":"locality"
},
  "geometry": {"coordinates":[31.56603,50.04547],"type":"Point"}
}