{
  "type": "Feature",
  "properties": {
    "gn:admin1_code":"7.0",
    "gn:asciiname":"Klyuchkin",
    "gn:country_code":"UA",
    "gn:dem":161,
    "gn:feature_class":"P",
    "gn:feature_code":"PPL",
    "gn:name":"Klyuchkin",
    "gn:population":0,
    "gn:timezone":"Europe/Kiev",
    "iso:country":"UA",
    "name:und_x_variant":[
        "Klyuchki",
        "Klyuchkin"
    ],
    "wof:name":"Klyuchkin",
    "wof:placetype":"locality"
},
  "geometry": {"coordinates":[36.47813,50.06625],"type":"Point"}
}