{
  "type": "Feature",
  "properties": {
    "gn:admin1_code":"13.0",
    "gn:asciiname":"Lisove",
    "gn:country_code":"UA",
    "gn:dem":156,
    "gn:feature_class":"P",
    "gn:feature_code":"PPL",
    "gn:name":"Lisove",
    "gn:population":0,
    "gn:timezone":"Europe/Kiev",
    "iso:country":"UA",
    "name:bel_x_preferred":[
        "\u041b\u0456\u0441\u0430\u0432\u044d"
    ],
    "name:deu_x_preferred":[
        "Lissowe"
    ],
    "name:rus_x_preferred":[
        "\u041b\u0435\u0441\u043e\u0432\u043e\u0435"
    ],
    "name:ukr_x_preferred":[
        "Chapayeve"
    ],
    "name:ukr_x_variant":[
        "\u0427\u0430\u043f\u0430\u0454\u0432\u0435",
        "Lisove",
        "\u041b\u0456\u0441\u043e\u0432\u0435"
    ],
    "name:und_x_variant":[
        "Chapayevo"
    ],
    "wof:name":"Lisove",
    "wof:placetype":"locality"
},
  "geometry": {"coordinates":[29.64401,51.04008],"type":"Point"}
}