{
  "type": "Feature",
  "properties": {
    "gn:admin1_code":"15.0",
    "gn:asciiname":"Baryliv",
    "gn:country_code":"UA",
    "gn:dem":203,
    "gn:feature_class":"P",
    "gn:feature_code":"PPL",
    "gn:name":"Baryliv",
    "gn:population":0,
    "gn:timezone":"Europe/Kiev",
    "iso:country":"UA",
    "name:pol_x_preferred":[
        "Bary\u0142\u00f3w"
    ],
    "name:ron_x_preferred":[
        "Bar\u00eeliv"
    ],
    "name:rus_x_preferred":[
        "\u0411\u0430\u0440\u0438\u043b\u043e\u0432"
    ],
    "name:ukr_x_preferred":[
        "\u0411\u0430\u0440\u0438\u043b\u0456\u0432"
    ],
    "name:und_x_variant":[
        "Baryluv",
        "Barylov",
        "Barilov"
    ],
    "name:zho_x_preferred":[
        "\u5df4\u91cc\u5229\u592b"
    ],
    "wof:name":"Baryliv",
    "wof:placetype":"locality"
},
  "geometry": {"coordinates":[24.86756,50.34577],"type":"Point"}
}