{
  "type": "Feature",
  "properties": {
    "gn:admin1_code":"2.0",
    "gn:asciiname":"Naumivs'ke",
    "gn:country_code":"UA",
    "gn:dem":125,
    "gn:feature_class":"P",
    "gn:feature_code":"PPL",
    "gn:name":"Naumivs\u2019ke",
    "gn:population":0,
    "gn:timezone":"Europe/Kiev",
    "iso:country":"UA",
    "name:ukr_x_preferred":[
        "Naumivs\u2019ke"
    ],
    "name:ukr_x_variant":[
        "\u041d\u0430\u0443\u043c\u0456\u0432\u0441\u044c\u043a\u0435"
    ],
    "name:und_x_variant":[
        "Naumovskiy",
        "Khutor Naumovskiy",
        "Naumovskov"
    ],
    "wof:name":"Naumivs'ke",
    "wof:placetype":"locality"
},
  "geometry": {"coordinates":[31.99155,51.00918],"type":"Point"}
}