{
  "type": "Feature",
  "properties": {
    "gn:admin1_code":"21.0",
    "gn:asciiname":"Kaliyivka",
    "gn:country_code":"UA",
    "gn:dem":156,
    "gn:feature_class":"P",
    "gn:feature_code":"PPL",
    "gn:name":"Kaliyivka",
    "gn:population":0,
    "gn:timezone":"Europe/Kiev",
    "iso:country":"UA",
    "name:ukr_x_preferred":[
        "\u041a\u0430\u043b\u0456\u0457\u0432\u043a\u0430"
    ],
    "name:ukr_x_variant":[
        "Koleyevka",
        "Kaliyevka",
        "Kaleyevka"
    ],
    "name:und_x_variant":[
        "Kaliyivka"
    ],
    "wof:name":"Kaliyivka",
    "wof:placetype":"locality"
},
  "geometry": {"coordinates":[33.5444,52.06291],"type":"Point"}
}