{
  "type": "Feature",
  "properties": {
    "gn:admin1_code":"7.0",
    "gn:asciiname":"Zahryzove",
    "gn:country_code":"UA",
    "gn:dem":83,
    "gn:feature_class":"P",
    "gn:feature_code":"PPL",
    "gn:name":"Zahryzove",
    "gn:population":0,
    "gn:timezone":"Europe/Kiev",
    "iso:country":"UA",
    "name:eng_x_preferred":[
        "Zagryzovo"
    ],
    "name:rus_x_preferred":[
        "\u0417\u0430\u0433\u0440\u044b\u0437\u043e\u0432\u043e"
    ],
    "name:ukr_x_preferred":[
        "Zahryzove"
    ],
    "name:und_x_variant":[
        "Zagryzova",
        "Zagrizovo",
        "Zagryzovo"
    ],
    "wof:name":"Zahryzove",
    "wof:placetype":"locality"
},
  "geometry": {"coordinates":[37.72389,49.50833],"type":"Point"}
}