{
  "type": "Feature",
  "properties": {
    "gn:admin1_code":"24.0",
    "gn:asciiname":"Hodovychi",
    "gn:country_code":"UA",
    "gn:dem":199,
    "gn:feature_class":"P",
    "gn:feature_code":"PPL",
    "gn:name":"Hodovychi",
    "gn:population":0,
    "gn:timezone":"Europe/Kiev",
    "iso:country":"UA",
    "name:ukr_x_preferred":[
        "Hodovychi"
    ],
    "name:ukr_x_variant":[
        "\u0413\u043e\u0434\u043e\u0432\u0438\u0447\u0456"
    ],
    "name:und_x_variant":[
        "Godoviche",
        "Godovichi"
    ],
    "wof:name":"Hodovychi",
    "wof:placetype":"locality"
},
  "geometry": {"coordinates":[24.4256,51.20741],"type":"Point"}
}