{
  "type": "Feature",
  "properties": {
    "iso:country":"UA",
    "qs:a0":"\u0423\u043a\u0440\u0430\u0457\u043d\u0430",
    "qs:a1":"*\u041c\u0438\u043a\u043e\u043b\u0430\u0457\u0432\u0441\u044c\u043a\u0430",
    "qs:a1_alt":"Mykolaivs'ka",
    "qs:a1r":"0",
    "qs:a2":"\u0411\u0435\u0440\u0435\u0437\u043d\u0435\u0433\u0443\u0432\u0430\u0442\u0441\u044c\u043a\u0438\u0439",
    "qs:a2_alt":"Bereznehuvats'kyi",
    "qs:adm0":"\u0423\u043a\u0440\u0430\u0457\u043d\u0430",
    "qs:la_lc":"*",
    "qs:level":"locality",
    "qs:loc":"\u041c\u0430\u043b\u0456\u0457\u0432\u043a\u0430",
    "qs:loc_alt":"Maliivka",
    "qs:pop":0,
    "qs:type":"buffered point",
    "wof:name":"\u041c\u0430\u043b\u0456\u0457\u0432\u043a\u0430",
    "wof:placetype":"locality"
},
  "geometry": {"coordinates":[32.725345,47.481652],"type":"Point"}
}