{
  "type": "Feature",
  "properties": {
    "gn:admin1_code":"26.0",
    "gn:asciiname":"Radisne",
    "gn:country_code":"UA",
    "gn:dem":82,
    "gn:feature_class":"P",
    "gn:feature_code":"PPL",
    "gn:name":"Radisne",
    "gn:population":0,
    "gn:timezone":"Europe/Zaporozhye",
    "iso:country":"UA",
    "name:ukr_x_preferred":[
        "Radisne"
    ],
    "name:ukr_x_variant":[
        "\u0420\u0430\u0434\u0456\u0441\u043d\u0435"
    ],
    "name:und_x_variant":[
        "Radostny",
        "Radostnyy",
        "Radostnoye"
    ],
    "wof:name":"Radisne",
    "wof:placetype":"locality"
},
  "geometry": {"coordinates":[35.40094000000001,47.18316],"type":"Point"}
}