{
  "type": "Feature",
  "properties": {
    "iso:country":"UA",
    "name:eng_x_preferred":[
        "Pancheve"
    ],
    "name:rus_x_preferred":[
        "\u041f\u0430\u043d\u0447\u0435\u0432\u043e"
    ],
    "name:unk_x_variant":[
        "Panchevo"
    ],
    "qs:a0":"\u0423\u043a\u0440\u0430\u0457\u043d\u0430",
    "qs:a1":"*\u041a\u0456\u0440\u043e\u0432\u043e\u0433\u0440\u0430\u0434\u0441\u044c\u043a\u0430",
    "qs:a1_alt":"Kirovohrads'ka",
    "qs:a1r":"0",
    "qs:a2":"\u041d\u043e\u0432\u043e\u043c\u0438\u0440\u0433\u043e\u0440\u043e\u0434\u0441\u044c\u043a\u0438\u0439",
    "qs:a2_alt":"Novomyrhorods'kyi",
    "qs:adm0":"\u0423\u043a\u0440\u0430\u0457\u043d\u0430",
    "qs:la_lc":"*",
    "qs:level":"locality",
    "qs:loc":"\u041f\u0430\u043d\u0447\u0435\u0432\u0435",
    "qs:loc_alt":"Pancheve",
    "qs:pop":0,
    "qs:type":"buffered point",
    "wof:name":"\u041f\u0430\u043d\u0447\u0435\u0432\u0435",
    "wof:placetype":"locality"
},
  "geometry": {"coordinates":[31.847053,48.735432],"type":"Point"}
}