{
  "type": "Feature",
  "properties": {
    "gn:admin1_code":"6.0",
    "gn:asciiname":"Semakovtsy",
    "gn:country_code":"UA",
    "gn:dem":243,
    "gn:feature_class":"P",
    "gn:feature_code":"PPL",
    "gn:name":"Semakovtsy",
    "gn:population":0,
    "gn:timezone":"Europe/Kiev",
    "iso:country":"UA",
    "name:und_x_variant":[
        "Semakovtse nad Prutem",
        "Semakovtsy"
    ],
    "wof:name":"Semakovtsy",
    "wof:placetype":"locality"
},
  "geometry": {"coordinates":[25.21276,48.48345],"type":"Point"}
}