{
  "type": "Feature",
  "properties": {
    "gn:admin1_code":"24.0",
    "gn:asciiname":"Oleksandriya",
    "gn:country_code":"UA",
    "gn:dem":167,
    "gn:feature_class":"P",
    "gn:feature_code":"PPL",
    "gn:name":"Oleksandriya",
    "gn:population":0,
    "gn:timezone":"Europe/Kiev",
    "iso:country":"UA",
    "name:ukr_x_preferred":[
        "Oleksandriya"
    ],
    "name:ukr_x_variant":[
        "\u041e\u043b\u0435\u043a\u0441\u0430\u043d\u0434\u0440\u0456\u044f"
    ],
    "name:und_x_variant":[
        "Aleksandrija",
        "Aleksandria",
        "Aleksandriya"
    ],
    "wof:name":"Oleksandriya",
    "wof:placetype":"locality"
},
  "geometry": {"coordinates":[24.8502,51.50482],"type":"Point"}
}