{
  "type": "Feature",
  "properties": {
    "gn:admin1_code":"17.0",
    "gn:asciiname":"Dobrozhanove",
    "gn:country_code":"UA",
    "gn:dem":48,
    "gn:feature_class":"P",
    "gn:feature_code":"PPL",
    "gn:name":"Dobrozhanove",
    "gn:population":0,
    "gn:timezone":"Europe/Kiev",
    "iso:country":"UA",
    "name:ukr_x_preferred":[
        "Dobrozhanove"
    ],
    "name:ukr_x_variant":[
        "\u0414\u043e\u0431\u0440\u043e\u0436\u0430\u043d\u043e\u0432\u0435"
    ],
    "name:und_x_variant":[
        "Dobrozhanovo"
    ],
    "wof:name":"Dobrozhanove",
    "wof:placetype":"locality"
},
  "geometry": {"coordinates":[30.335,46.53775],"type":"Point"}
}