{
  "type": "Feature",
  "properties": {
    "gn:admin1_code":"18.0",
    "gn:asciiname":"Mala Pobyvanka",
    "gn:country_code":"UA",
    "gn:dem":159,
    "gn:feature_class":"P",
    "gn:feature_code":"PPL",
    "gn:name":"Mala Pobyvanka",
    "gn:population":0,
    "gn:timezone":"Europe/Kiev",
    "iso:country":"UA",
    "name:ukr_x_preferred":[
        "Mala Pobyvanka"
    ],
    "name:ukr_x_variant":[
        "\u041c\u0430\u043b\u0430 \u041f\u043e\u0431\u0438\u0432\u0430\u043d\u043a\u0430"
    ],
    "wof:name":"Mala Pobyvanka",
    "wof:placetype":"locality"
},
  "geometry": {"coordinates":[33.8537,50.46224],"type":"Point"}
}