{
  "type": "Feature",
  "properties": {
    "gn:admin1_code":"1.0",
    "gn:asciiname":"Bosovka",
    "gn:country_code":"UA",
    "gn:dem":198,
    "gn:feature_class":"P",
    "gn:feature_code":"PPL",
    "gn:name":"Bosovka",
    "gn:population":0,
    "gn:timezone":"Europe/Kiev",
    "iso:country":"UA",
    "name:eng_x_preferred":[
        "Bosovka"
    ],
    "name:rus_x_preferred":[
        "\u0411\u043e\u0441\u043e\u0432\u043a\u0430"
    ],
    "wof:name":"Bosovka",
    "wof:placetype":"locality"
},
  "geometry": {"coordinates":[30.62926,49.23301],"type":"Point"}
}