{
  "type": "Feature",
  "properties": {
    "gn:admin1_code":"6.0",
    "gn:asciiname":"Kalinovka",
    "gn:country_code":"UA",
    "gn:dem":268,
    "gn:feature_class":"P",
    "gn:feature_code":"PPL",
    "gn:name":"Kalinovka",
    "gn:population":0,
    "gn:timezone":"Europe/Kiev",
    "iso:country":"UA",
    "name:bel_x_preferred":[
        "\u041a\u0430\u043b\u0456\u043d\u0430\u045e\u043a\u0430"
    ],
    "name:ceb_x_preferred":[
        "Kalinovka"
    ],
    "name:fra_x_preferred":[
        "Kalinovka"
    ],
    "name:kaz_x_preferred":[
        "\u041a\u0430\u043b\u0438\u043d\u043e\u0432\u043a\u0430"
    ],
    "name:lit_x_preferred":[
        "Kalinovka"
    ],
    "name:rus_x_preferred":[
        "\u041a\u0430\u043b\u0438\u043d\u043e\u0432\u043a\u0430"
    ],
    "name:sco_x_preferred":[
        "Kalinovka"
    ],
    "name:spa_x_preferred":[
        "Kalinovka"
    ],
    "name:swe_x_preferred":[
        "Kalinovka"
    ],
    "name:ukr_x_preferred":[
        "\u041a\u0430\u043b\u0438\u043d\u043e\u0432\u043a\u0430"
    ],
    "name:und_x_variant":[
        "Danil\u2019che",
        "Kalynivka",
        "Zhovchiv"
    ],
    "wof:name":"Kalinovka",
    "wof:placetype":"locality"
},
  "geometry": {"coordinates":[24.71913,49.36029],"type":"Point"}
}