{
  "type": "Feature",
  "properties": {
    "iso:country":"UA",
    "name:rus_x_preferred":[
        "\u0421\u0430\u043c\u0433\u043e\u0440\u043e\u0434\u043e\u043a"
    ],
    "name:ukr_x_preferred":[
        "\u0421\u0430\u043c\u0433\u043e\u0440\u043e\u0434\u043e\u043a"
    ],
    "name:und_x_variant":[
        "Samgorodok"
    ],
    "qs:a0":"\u0423\u043a\u0440\u0430\u0457\u043d\u0430",
    "qs:a1":"*\u0412\u0456\u043d\u043d\u0438\u0446\u044c\u043a\u0430",
    "qs:a1_alt":"Vinnyts'ka",
    "qs:a1r":"0",
    "qs:a2":"\u041a\u043e\u0437\u044f\u0442\u0438\u043d\u0441\u044c\u043a\u0438\u0439",
    "qs:a2_alt":"Koziatyns'kyi",
    "qs:adm0":"\u0423\u043a\u0440\u0430\u0457\u043d\u0430",
    "qs:la_lc":"*",
    "qs:level":"locality",
    "qs:loc":"\u0421\u0430\u043c\u0433\u043e\u0440\u043e\u0434\u043e\u043a",
    "qs:loc_alt":"Samhorodok",
    "qs:pop":0,
    "qs:type":"buffered point",
    "wof:name":"\u0421\u0430\u043c\u0433\u043e\u0440\u043e\u0434\u043e\u043a",
    "wof:placetype":"locality"
},
  "geometry": {"coordinates":[28.841252,49.531718],"type":"Point"}
}