{
  "type": "Feature",
  "properties": {
    "gn:admin1_code":"10.0",
    "gn:asciiname":"Neglyadovka",
    "gn:country_code":"UA",
    "gn:dem":92,
    "gn:feature_class":"P",
    "gn:feature_code":"PPL",
    "gn:name":"Neglyadovka",
    "gn:population":0,
    "gn:timezone":"Europe/Kiev",
    "iso:country":"UA",
    "name:und_x_variant":[
        "Naglyadovka",
        "Neglyadovka"
    ],
    "wof:name":"Neglyadovka",
    "wof:placetype":"locality"
},
  "geometry": {"coordinates":[32.42168,48.1766],"type":"Point"}
}