{
  "type": "Feature",
  "properties": {
    "gn:admin1_code":"5.0",
    "gn:asciiname":"Gorbakonovka",
    "gn:cc2":"UA",
    "gn:country_code":"UA",
    "gn:dem":156,
    "gn:feature_class":"P",
    "gn:feature_code":"PPL",
    "gn:name":"Gorbakonovka",
    "gn:population":0,
    "gn:timezone":"Europe/Kiev",
    "iso:country":"UA",
    "name:und_x_variant":[
        "Gorbakonevka",
        "Gorbakonovka"
    ],
    "wof:name":"Gorbakonovka",
    "wof:placetype":"locality"
},
  "geometry": {"coordinates":[37.85,48.71667],"type":"Point"}
}