{
  "type": "Feature",
  "properties": {
    "gn:admin1_code":"2.0",
    "gn:asciiname":"Bykhal'tsokhivka",
    "gn:country_code":"UA",
    "gn:dem":142,
    "gn:feature_class":"P",
    "gn:feature_code":"PPL",
    "gn:name":"Bykhal\u2019tsokhivka",
    "gn:population":0,
    "gn:timezone":"Europe/Kiev",
    "iso:country":"UA",
    "name:rus_x_preferred":[
        "Bikhal\u2019tsokhovka"
    ],
    "name:ukr_x_preferred":[
        "Bykhal\u2019tsokhivka"
    ],
    "name:ukr_x_variant":[
        "\u0411\u0438\u0445\u0430\u043b\u044c\u0446\u043e\u0445\u0456\u0432\u043a\u0430"
    ],
    "name:und_x_variant":[
        "Bikhol\u2019tsokhovtsy"
    ],
    "wof:name":"Bykhal'tsokhivka",
    "wof:placetype":"locality"
},
  "geometry": {"coordinates":[31.02063,51.70061],"type":"Point"}
}