{
  "type": "Feature",
  "properties": {
    "gn:admin1_code":"21.0",
    "gn:asciiname":"Lyashky",
    "gn:country_code":"UA",
    "gn:dem":173,
    "gn:feature_class":"P",
    "gn:feature_code":"PPL",
    "gn:name":"Lyashky",
    "gn:population":0,
    "gn:timezone":"Europe/Kiev",
    "iso:country":"UA",
    "name:ukr_x_preferred":[
        "Lyashky"
    ],
    "name:ukr_x_variant":[
        "\u041b\u044f\u0448\u043a\u0438"
    ],
    "name:und_x_variant":[
        "Pushkar\u2019"
    ],
    "wof:name":"Lyashky",
    "wof:placetype":"locality"
},
  "geometry": {"coordinates":[34.59778,50.51528],"type":"Point"}
}