{
  "type": "Feature",
  "properties": {
    "gn:admin1_code":"15.0",
    "gn:asciiname":"Staviska",
    "gn:cc2":"UA",
    "gn:country_code":"UA",
    "gn:dem":194,
    "gn:feature_class":"P",
    "gn:feature_code":"PPL",
    "gn:name":"Staviska",
    "gn:population":0,
    "gn:timezone":"Europe/Kiev",
    "iso:country":"UA",
    "name:und_x_variant":[
        "Stavisko",
        "Staviska"
    ],
    "wof:name":"Staviska",
    "wof:placetype":"locality"
},
  "geometry": {"coordinates":[23.03333,49.85],"type":"Point"}
}