{
  "type": "Feature",
  "properties": {
    "gn:admin1_code":"27.0",
    "gn:asciiname":"Buryaky",
    "gn:country_code":"UA",
    "gn:dem":290,
    "gn:feature_class":"P",
    "gn:feature_code":"PPL",
    "gn:name":"Buryaky",
    "gn:population":0,
    "gn:timezone":"Europe/Kiev",
    "iso:country":"UA",
    "name:ukr_x_preferred":[
        "Buryaky"
    ],
    "name:ukr_x_variant":[
        "\u0411\u0443\u0440\u044f\u043a\u0438"
    ],
    "name:und_x_variant":[
        "Buraki",
        "Buryaki"
    ],
    "wof:name":"Buryaky",
    "wof:placetype":"locality"
},
  "geometry": {"coordinates":[28.28469,49.81777],"type":"Point"}
}