{
  "type": "Feature",
  "properties": {
    "gn:admin1_code":"4.0",
    "gn:asciiname":"Novokhoroshevs'ke",
    "gn:country_code":"UA",
    "gn:dem":95,
    "gn:feature_class":"P",
    "gn:feature_code":"PPL",
    "gn:name":"Novokhoroshevs\u2019ke",
    "gn:population":0,
    "gn:timezone":"Europe/Kiev",
    "iso:country":"UA",
    "name:ukr_x_preferred":[
        "Novokhoroshevs\u2019ke"
    ],
    "name:ukr_x_variant":[
        "\u041d\u043e\u0432\u043e\u0445\u043e\u0440\u043e\u0448\u0435\u0432\u0441\u044c\u043a\u0435"
    ],
    "wof:name":"Novokhoroshevs'ke",
    "wof:placetype":"locality"
},
  "geometry": {"coordinates":[36.61365,48.50835],"type":"Point"}
}