{
  "type": "Feature",
  "properties": {
    "gn:admin1_code":"10.0",
    "gn:asciiname":"Rystichevo",
    "gn:country_code":"UA",
    "gn:dem":94,
    "gn:feature_class":"P",
    "gn:feature_code":"PPL",
    "gn:name":"Rystichevo",
    "gn:population":0,
    "gn:timezone":"Europe/Kiev",
    "iso:country":"UA",
    "wof:name":"Rystichevo",
    "wof:placetype":"locality"
},
  "geometry": {"coordinates":[32.01667,47.81667],"type":"Point"}
}