{
  "type": "Feature",
  "properties": {
    "iso:country":"UA",
    "name:eng_x_preferred":[
        "Orlovets'"
    ],
    "name:rus_x_preferred":[
        "\u041e\u0440\u043b\u043e\u0432\u0435\u0446"
    ],
    "name:und_x_variant":[
        "Orlovets\u2019"
    ],
    "qs:a0":"\u0423\u043a\u0440\u0430\u0457\u043d\u0430",
    "qs:a1":"*\u0427\u0435\u0440\u043a\u0430\u0441\u044c\u043a\u0430",
    "qs:a1_alt":"Cherkas'ka",
    "qs:a1r":"0",
    "qs:a2":"\u0413\u043e\u0440\u043e\u0434\u0438\u0449\u0435\u043d\u0441\u044c\u043a\u0438\u0439",
    "qs:a2_alt":"Horodyschens'kyi",
    "qs:adm0":"\u0423\u043a\u0440\u0430\u0457\u043d\u0430",
    "qs:la_lc":"*",
    "qs:level":"locality",
    "qs:loc":"\u041e\u0440\u043b\u043e\u0432\u0435\u0446\u044c",
    "qs:loc_alt":"Orlovets",
    "qs:pop":0,
    "qs:type":"buffered point",
    "wof:name":"\u041e\u0440\u043b\u043e\u0432\u0435\u0446\u044c",
    "wof:placetype":"locality"
},
  "geometry": {"coordinates":[31.617041,49.235872],"type":"Point"}
}