{
  "type": "Feature",
  "properties": {
    "gn:gn_country":"UA",
    "gn:gn_fcode":"PPL",
    "gn:gn_pop":3859,
    "gn:population":3859,
    "iso:country":"UA",
    "name:eng_x_preferred":[
        "Adzhamka"
    ],
    "name:rus_x_preferred":[
        "\u0410\u0434\u0436\u0430\u043c\u043a\u0430"
    ],
    "name:ukr_x_preferred":[
        "\u0410\u0434\u0436\u0430\u043c\u043a\u0430"
    ],
    "qs_pg:aaroncc":"UA",
    "qs_pg:gn_country":"UA",
    "qs_pg:gn_fcode":"PPL",
    "qs_pg:gn_pop":3859,
    "qs_pg:name":"Adzhamka",
    "qs_pg:name_adm0":"Ukraine",
    "qs_pg:name_adm1":"Kirovohrads\u00b4ka Oblast\u00b4",
    "qs_pg:photos_9r":0,
    "qs_pg:photos_sr":0,
    "qs_pg:pop_sr":4,
    "qs_pg:qs_pg_placetype":"locality",
    "qs_pg:qs_pg_placetype_gp":"Town",
    "qs_pg:woe_adm0":23424976,
    "woe:adm0_id":23424976,
    "woe:name_adm0":"Ukraine",
    "woe:name_adm1":"Kirovohrads\u00b4ka Oblast\u00b4",
    "woe:placetype":"Town",
    "wof:name":"Adzhamka",
    "wof:placetype":"locality",
    "wof:population":3859
},
  "geometry": {"coordinates":[32.53542,48.54244],"type":"Point"}
}