{
  "type": "Feature",
  "properties": {
    "gn:admin1_code":"7.0",
    "gn:asciiname":"Husyna Polyana",
    "gn:country_code":"UA",
    "gn:dem":98,
    "gn:feature_class":"P",
    "gn:feature_code":"PPL",
    "gn:name":"Husyna Polyana",
    "gn:population":0,
    "gn:timezone":"Europe/Kiev",
    "iso:country":"UA",
    "name:ukr_x_preferred":[
        "Husyna Polyana"
    ],
    "name:ukr_x_variant":[
        "\u0413\u0443\u0441\u0438\u043d\u0430 \u041f\u043e\u043b\u044f\u043d\u0430"
    ],
    "name:und_x_variant":[
        "Gusinaya Polyana"
    ],
    "wof:name":"Husyna Polyana",
    "wof:placetype":"locality"
},
  "geometry": {"coordinates":[36.28942,49.82148],"type":"Point"}
}