{
  "type": "Feature",
  "properties": {
    "gn:admin1_code":"4.0",
    "gn:asciiname":"Novohnide",
    "gn:country_code":"UA",
    "gn:dem":156,
    "gn:feature_class":"P",
    "gn:feature_code":"PPL",
    "gn:name":"Novohnide",
    "gn:population":0,
    "gn:timezone":"Europe/Kiev",
    "iso:country":"UA",
    "name:ukr_x_preferred":[
        "Novohnide"
    ],
    "name:ukr_x_variant":[
        "\u041d\u043e\u0432\u043e\u0433\u043d\u0456\u0434\u0435"
    ],
    "name:und_x_variant":[
        "Novognedoye"
    ],
    "wof:name":"Novohnide",
    "wof:placetype":"locality"
},
  "geometry": {"coordinates":[35.48787,48.30722],"type":"Point"}
}