{
  "type": "Feature",
  "properties": {
    "gn:admin1_code":"7.0",
    "gn:asciiname":"Zhovtneve Druhe",
    "gn:country_code":"UA",
    "gn:dem":125,
    "gn:feature_class":"P",
    "gn:feature_code":"PPL",
    "gn:name":"Zhovtneve Druhe",
    "gn:population":0,
    "gn:timezone":"Europe/Kiev",
    "iso:country":"UA",
    "name:rus_x_preferred":[
        "\u0416\u043e\u0432\u0442\u043d\u0435\u0432\u043e\u0435 \u0412\u0442\u043e\u0440\u043e\u0435"
    ],
    "name:ukr_x_preferred":[
        "Zhovtneve Druhe"
    ],
    "name:ukr_x_variant":[
        "\u0416\u043e\u0432\u0442\u043d\u0435\u0432\u0435 \u0414\u0440\u0443\u0433\u0435"
    ],
    "name:und_x_variant":[
        "Oktyabr\u2019skoye Vtoroye",
        "Nikolayevka",
        "Oktyabr\u2019skoye",
        "Zhovtneve Druge",
        "Zhovtnevoye Vtoroye"
    ],
    "wof:name":"Zhovtneve Druhe",
    "wof:placetype":"locality"
},
  "geometry": {"coordinates":[37.33173,50.37517],"type":"Point"}
}