{
  "type": "Feature",
  "properties": {
    "gn:admin1_code":"23.0",
    "gn:asciiname":"Skalopil'",
    "gn:country_code":"UA",
    "gn:dem":187,
    "gn:feature_class":"P",
    "gn:feature_code":"PPL",
    "gn:name":"Skalopil\u2019",
    "gn:population":0,
    "gn:timezone":"Europe/Kiev",
    "iso:country":"UA",
    "name:rus_x_preferred":[
        "Skalopol\u2019"
    ],
    "name:ukr_x_preferred":[
        "\u0421\u043a\u0430\u043b\u043e\u043f\u0456\u043b\u044c"
    ],
    "name:und_x_variant":[
        "Skalopil\u2019"
    ],
    "wof:name":"Skalopil'",
    "wof:placetype":"locality"
},
  "geometry": {"coordinates":[28.059,48.49399],"type":"Point"}
}