{
  "type": "Feature",
  "properties": {
    "gn:country":"UA",
    "gn:fcode":"PPL",
    "gn:population":6404,
    "iso:country":"UA",
    "name:ceb_x_preferred":[
        "Kehychivka"
    ],
    "name:crh_x_preferred":[
        "Keg\u0131\u00e7ivka"
    ],
    "name:deu_x_preferred":[
        "Kehytschiwka"
    ],
    "name:eng_x_preferred":[
        "Kehychivka"
    ],
    "name:hye_x_preferred":[
        "\u053f\u0565\u0563\u056b\u0579\u0575\u0578\u057e\u056f\u0561"
    ],
    "name:pol_x_preferred":[
        "Kehycziwka"
    ],
    "name:rus_x_preferred":[
        "\u041a\u0435\u0433\u0438\u0447\u0435\u0432\u043a\u0430"
    ],
    "name:rus_x_variant":[
        "\u041a\u0435\u0433\u0438\u0447\u0456\u0432\u043a\u0430",
        "\u041a\u0435\u0433\u0438\u0447\u0451\u0432\u043a\u0430"
    ],
    "name:ukr_x_preferred":[
        "\u041a\u0435\u0433\u0438\u0447\u0456\u0432\u043a\u0430"
    ],
    "name:und_x_variant":[
        "Kegich\u00ebvka"
    ],
    "name:zho_x_preferred":[
        "\u514b\u5409\u5947\u592b\u5361"
    ],
    "qs_pg:aaroncc":"UA",
    "qs_pg:gn_country":"UA",
    "qs_pg:gn_fcode":"PPL",
    "qs_pg:gn_pop":6404,
    "qs_pg:name":"Kehychivka",
    "qs_pg:photos_9r":0,
    "qs_pg:photos_sr":0,
    "qs_pg:pop_sr":5,
    "qs_pg:qs_pg_placetype":"locality",
    "wof:name":"Kehychivka",
    "wof:placetype":"locality",
    "wof:population":6404
},
  "geometry": {"coordinates":[35.76153,49.28656],"type":"Point"}
}