{
  "type": "Feature",
  "properties": {
    "gn:gn_country":"UA",
    "gn:gn_fcode":"PPL",
    "gn:gn_pop":4251,
    "gn:population":4251,
    "iso:country":"UA",
    "name:rus_x_preferred":[
        "\u041c\u0443\u0440\u043e\u0432\u0430\u043d\u0435"
    ],
    "name:rus_x_variant":[
        "\u041c\u0443\u0440\u043e\u0432\u0430\u043d\u043e\u0435"
    ],
    "name:ukr_x_preferred":[
        "\u041c\u0443\u0440\u043e\u0432\u0430\u043d\u0435"
    ],
    "name:unk_x_variant":[
        "Laszki Murowane"
    ],
    "qs_pg:aaroncc":"UA",
    "qs_pg:gn_country":"UA",
    "qs_pg:gn_fcode":"PPL",
    "qs_pg:gn_pop":4251,
    "qs_pg:name":"Murovanoye",
    "qs_pg:photos_9r":0,
    "qs_pg:photos_sr":0,
    "qs_pg:pop_sr":4,
    "qs_pg:qs_pg_placetype":"locality",
    "wof:name":"Murovanoye",
    "wof:placetype":"locality",
    "wof:population":4251
},
  "geometry": {"coordinates":[22.9367,49.52143],"type":"Point"}
}