{
  "type": "Feature",
  "properties": {
    "gn:admin1_code":"19.0",
    "gn:asciiname":"Oleksandrove",
    "gn:country_code":"UA",
    "gn:dem":143,
    "gn:feature_class":"P",
    "gn:feature_code":"PPL",
    "gn:name":"Oleksandrove",
    "gn:population":0,
    "gn:timezone":"Europe/Kiev",
    "iso:country":"UA",
    "name:ukr_x_preferred":[
        "Oleksandrove"
    ],
    "name:ukr_x_variant":[
        "\u041e\u043b\u0435\u043a\u0441\u0430\u043d\u0434\u0440\u043e\u0432\u0435"
    ],
    "name:und_x_variant":[
        "Koloniya Nove Aleksandrovske",
        "Aleksandrovo"
    ],
    "wof:name":"Oleksandrove",
    "wof:placetype":"locality"
},
  "geometry": {"coordinates":[26.2606,51.78407],"type":"Point"}
}