{
  "type": "Feature",
  "properties": {
    "iso:country":"UA",
    "name:arz_x_preferred":[
        "\u0646\u0647\u0631 \u0633\u0645\u0648\u062a\u0631\u064a\u062a\u0634"
    ],
    "name:ast_x_preferred":[
        "R\u00edu Smotrych"
    ],
    "name:avk_x_preferred":[
        "Smotritc"
    ],
    "name:bak_x_preferred":[
        "\u0421\u043c\u043e\u0442\u0440\u0438\u0447"
    ],
    "name:ceb_x_preferred":[
        "Smotrich"
    ],
    "name:ces_x_preferred":[
        "Smotry\u010d"
    ],
    "name:cym_x_preferred":[
        "Afon Smotrych"
    ],
    "name:dan_x_preferred":[
        "Smotrytj"
    ],
    "name:deu_x_preferred":[
        "Smotrytsch"
    ],
    "name:ell_x_preferred":[
        "\u03a3\u03bc\u03cc\u03c4\u03c1\u03b9\u03c4\u03c2"
    ],
    "name:eng_x_preferred":[
        "Smotrych River"
    ],
    "name:epo_x_preferred":[
        "Smotri\u0109"
    ],
    "name:fin_x_preferred":[
        "Smotryt\u0161"
    ],
    "name:fra_x_preferred":[
        "Smotrytch"
    ],
    "name:gle_x_preferred":[
        "Abhainn Smotrych"
    ],
    "name:heb_x_preferred":[
        "\u05e1\u05de\u05d5\u05d8\u05e8\u05d9\u05e5'"
    ],
    "name:hrv_x_preferred":[
        "Smotri\u010d"
    ],
    "name:hun_x_preferred":[
        "Szmotrics"
    ],
    "name:ita_x_preferred":[
        "Smotry\u010d"
    ],
    "name:jpn_x_preferred":[
        "\u30b9\u30e2\u30c8\u30eb\u30a3\u30c1\u5ddd"
    ],
    "name:lit_x_preferred":[
        "Smotry\u010dius"
    ],
    "name:lld_x_preferred":[
        "Smotrych"
    ],
    "name:nld_x_preferred":[
        "Smotrych River"
    ],
    "name:nno_x_preferred":[
        "Smotrytsj"
    ],
    "name:nob_x_preferred":[
        "Smotrytsj"
    ],
    "name:pol_x_preferred":[
        "Smotrycz"
    ],
    "name:rus_x_preferred":[
        "\u0421\u043c\u043e\u0442\u0440\u0438\u0447"
    ],
    "name:ukr_x_preferred":[
        "\u0421\u043c\u043e\u0442\u0440\u0438\u0447"
    ],
    "name:zho_x_preferred":[
        "\u65af\u83ab\u7279\u91cc\u5947\u6cb3"
    ],
    "qs:a0":"\u0423\u043a\u0440\u0430\u0457\u043d\u0430",
    "qs:a1":"*\u0425\u043c\u0435\u043b\u044c\u043d\u0438\u0446\u044c\u043a\u0430",
    "qs:a1_alt":"Khmel'nyts'ka",
    "qs:a1r":"0",
    "qs:a2":"\u041a\u0430\u043c'\u044f\u043d\u0435\u0446\u044c-\u041f\u043e\u0434\u0456\u043b\u044c\u0441\u044c\u043a\u0438\u0439",
    "qs:a2_alt":"Kamyanets'-Podil's'kyi",
    "qs:adm0":"\u0423\u043a\u0440\u0430\u0457\u043d\u0430",
    "qs:la_lc":"*",
    "qs:level":"locality",
    "qs:loc":"\u0421\u043c\u043e\u0442\u0440\u0438\u0447",
    "qs:loc_alt":"Smotrych",
    "qs:pop":0,
    "qs:type":"buffered point",
    "wd:wordcount":89,
    "wof:name":"\u0421\u043c\u043e\u0442\u0440\u0438\u0447",
    "wof:placetype":"locality"
},
  "geometry": {"coordinates":[26.574714,48.654881],"type":"Point"}
}