{
  "type": "Feature",
  "properties": {
    "gn:admin1_code":"23.0",
    "gn:asciiname":"Bortnyky",
    "gn:country_code":"UA",
    "gn:dem":218,
    "gn:feature_class":"P",
    "gn:feature_code":"PPL",
    "gn:name":"Bortnyky",
    "gn:population":0,
    "gn:timezone":"Europe/Kiev",
    "iso:country":"UA",
    "name:ukr_x_preferred":[
        "Bortnyky"
    ],
    "name:und_x_variant":[
        "\u0411\u043e\u0440\u0442\u043d\u0438\u043a\u0438",
        "Bortniki"
    ],
    "wof:name":"Bortnyky",
    "wof:placetype":"locality"
},
  "geometry": {"coordinates":[28.7906,48.79337],"type":"Point"}
}