{
  "type": "Feature",
  "properties": {
    "gn:admin1_code":"18.0",
    "gn:asciiname":"Melyushky",
    "gn:country_code":"UA",
    "gn:dem":107,
    "gn:feature_class":"P",
    "gn:feature_code":"PPL",
    "gn:name":"Melyushky",
    "gn:population":0,
    "gn:timezone":"Europe/Kiev",
    "iso:country":"UA",
    "name:ukr_x_preferred":[
        "Melyushky"
    ],
    "name:ukr_x_variant":[
        "\u041c\u0435\u043b\u044e\u0448\u043a\u0438"
    ],
    "wof:name":"Melyushky",
    "wof:placetype":"locality"
},
  "geometry": {"coordinates":[33.4796,49.83881],"type":"Point"}
}