{
  "type": "Feature",
  "properties": {
    "gn:admin1_code":"6.0",
    "gn:asciiname":"Holoshyna",
    "gn:cc2":"UA",
    "gn:country_code":"UA",
    "gn:dem":739,
    "gn:feature_class":"P",
    "gn:feature_code":"PPL",
    "gn:name":"Holoshyna",
    "gn:population":0,
    "gn:timezone":"Europe/Kiev",
    "iso:country":"UA",
    "name:ukr_x_preferred":[
        "Holoshyna"
    ],
    "name:ukr_x_variant":[
        "\u0413\u043e\u043b\u043e\u0448\u0438\u043d\u0430"
    ],
    "name:und_x_variant":[
        "Goloshina"
    ],
    "wof:name":"Holoshyna",
    "wof:placetype":"locality"
},
  "geometry": {"coordinates":[24.93528,47.93278],"type":"Point"}
}