{
  "type": "Feature",
  "properties": {
    "gn:admin1_code":"4.0",
    "gn:asciiname":"Harasymivka",
    "gn:country_code":"UA",
    "gn:dem":83,
    "gn:feature_class":"P",
    "gn:feature_code":"PPL",
    "gn:name":"Harasymivka",
    "gn:population":0,
    "gn:timezone":"Europe/Kiev",
    "iso:country":"UA",
    "name:ukr_x_preferred":[
        "Harasymivka"
    ],
    "name:ukr_x_variant":[
        "\u0413\u0430\u0440\u0430\u0441\u0438\u043c\u0456\u0432\u043a\u0430"
    ],
    "name:und_x_variant":[
        "Gerasimovskiy"
    ],
    "wof:name":"Harasymivka",
    "wof:placetype":"locality"
},
  "geometry": {"coordinates":[36.16667,47.88333],"type":"Point"}
}