{
  "type": "Feature",
  "properties": {
    "iso:country":"UA",
    "name:bel_x_preferred":[
        "\u0423\u043a\u0440\u0430\u0456\u043d\u0441\u043a"
    ],
    "name:ces_x_preferred":[
        "Ukrajinsk"
    ],
    "name:crh_x_preferred":[
        "Ukrayinsk"
    ],
    "name:deu_x_preferred":[
        "Ukrajinsk"
    ],
    "name:eng_x_preferred":[
        "Ukrainsk"
    ],
    "name:fas_x_preferred":[
        "\u0627\u0648\u06a9\u0631\u0627\u0626\u06cc\u0646\u0633\u06a9"
    ],
    "name:fra_x_preferred":[
        "Oukra\u00efnsk"
    ],
    "name:hsb_x_preferred":[
        "Ukrajinsk"
    ],
    "name:hye_x_preferred":[
        "\u0548\u0582\u056f\u0580\u0561\u056b\u0576\u057d\u056f"
    ],
    "name:ita_x_preferred":[
        "Ukra\u00efns'k"
    ],
    "name:kat_x_preferred":[
        "\u10e3\u10d9\u10e0\u10d0\u10d8\u10dc\u10e1\u10d9\u10d8"
    ],
    "name:lav_x_preferred":[
        "Ukrajinska"
    ],
    "name:nno_x_preferred":[
        "Ukrajinsk"
    ],
    "name:nob_x_preferred":[
        "Ukrajinsk"
    ],
    "name:nor_x_preferred":[
        "Ukrajinsk"
    ],
    "name:pol_x_preferred":[
        "Ukrajin\u015bk"
    ],
    "name:pol_x_variant":[
        "Ukrai\u0144sk"
    ],
    "name:ron_x_preferred":[
        "Ukraiinsk"
    ],
    "name:ron_x_variant":[
        "Ukrainsk"
    ],
    "name:rus_x_preferred":[
        "\u0423\u043a\u0440\u0430\u0438\u043d\u0441\u043a"
    ],
    "name:sco_x_preferred":[
        "Ukrainsk"
    ],
    "name:tat_x_preferred":[
        "\u0423\u043a\u0440\u0430\u0438\u043d\u0441\u043a"
    ],
    "name:ukr_x_preferred":[
        "\u0423\u043a\u0440\u0430\u0457\u043d\u0441\u044c\u043a"
    ],
    "name:ukr_x_variant":[
        "Ukrayins\u2019k"
    ],
    "name:und_x_variant":[
        "Koloniya Lisovka"
    ],
    "name:vie_x_preferred":[
        "Ukrainsk"
    ],
    "name:zho_x_preferred":[
        "\u70cf\u514b\u62c9\u56e0\u897f\u514b"
    ],
    "qs:a0":"\u0423\u043a\u0440\u0430\u0457\u043d\u0430",
    "qs:a1":"*\u0414\u043e\u043d\u0435\u0446\u044c\u043a\u0430",
    "qs:a1_alt":"Donets'ka",
    "qs:a1r":"0",
    "qs:a2":"\u041a\u0440\u0430\u0441\u043d\u043e\u0430\u0440\u043c\u0456\u0439\u0441\u044c\u043a\u0438\u0439",
    "qs:a2_alt":"Krasnoarmiis'kyi",
    "qs:adm0":"\u0423\u043a\u0440\u0430\u0457\u043d\u0430",
    "qs:la_lc":"*",
    "qs:level":"locality",
    "qs:loc":"\u0423\u043a\u0440\u0430\u0457\u043d\u0441\u044c\u043a",
    "qs:loc_alt":"Ukrains'k",
    "qs:pop":0,
    "qs:type":"buffered point",
    "wd:wordcount":56,
    "wof:name":"\u0423\u043a\u0440\u0430\u0457\u043d\u0441\u044c\u043a",
    "wof:placetype":"locality"
},
  "geometry": {"coordinates":[37.357231,48.094473],"type":"Point"}
}