{
  "type": "Feature",
  "properties": {
    "gn:admin1_code":"11.0",
    "gn:admin2_code":"704383",
    "gn:admin3_code":"11152926.0",
    "gn:asciiname":"Pyatikhatka",
    "gn:country_code":"UA",
    "gn:dem":61,
    "gn:elevation":"61.0",
    "gn:feature_class":"P",
    "gn:feature_code":"PPLA3",
    "gn:name":"Pyatikhatka",
    "gn:population":2375,
    "gn:timezone":"Europe/Simferopol",
    "iso:country":"UA",
    "name:eng_x_preferred":[
        "Pyatikhatka"
    ],
    "name:rus_x_historical":[
        "\u0411\u0435\u0448\u0443\u0301\u0439-\u042d\u043b\u0438\u0301"
    ],
    "name:rus_x_preferred":[
        "\u041f\u044f\u0442\u0438\u0445\u0430\u0442\u043a\u0430"
    ],
    "name:rus_x_variant":[
        "\u0411\u0435\u0448\u0443\u0301\u0439-\u042d\u043b\u0438\u0301"
    ],
    "name:ukr_x_preferred":[
        "\u041f\u2019\u044f\u0442\u0438\u0445\u0430\u0442\u043a\u0430"
    ],
    "wof:name":"Pyatikhatka",
    "wof:placetype":"locality",
    "wof:population":2375
},
  "geometry": {"coordinates":[34.25516,45.32347],"type":"Point"}
}