{
  "type": "Feature",
  "properties": {
    "iso:country":"UA",
    "name:bel_x_preferred":[
        "\u0412\u044b\u0433\u0430\u0434\u0430"
    ],
    "name:che_x_preferred":[
        "\u0412\u044b\u0433\u043e\u0434\u0430"
    ],
    "name:crh_x_preferred":[
        "V\u0131goda"
    ],
    "name:deu_x_preferred":[
        "Wyhoda"
    ],
    "name:eng_x_preferred":[
        "Vyhoda"
    ],
    "name:fin_x_preferred":[
        "Vyh\u043ed\u0430"
    ],
    "name:lav_x_preferred":[
        "Vihoda"
    ],
    "name:nan_x_preferred":[
        "Vyhoda"
    ],
    "name:nno_x_preferred":[
        "Vyhoda"
    ],
    "name:nob_x_preferred":[
        "Vyhoda"
    ],
    "name:pol_x_preferred":[
        "Wyhoda"
    ],
    "name:ron_x_preferred":[
        "V\u00eehoda"
    ],
    "name:rus_x_preferred":[
        "\u0412\u044b\u0433\u043e\u0434\u0430"
    ],
    "name:spa_x_preferred":[
        "Vyhoda"
    ],
    "name:ukr_x_preferred":[
        "Vyhoda"
    ],
    "name:ukr_x_variant":[
        "\u0412\u0438\u0433\u043e\u0434\u0430"
    ],
    "name:und_x_variant":[
        "Vygoda"
    ],
    "name:zho_x_preferred":[
        "\u7dad\u6208\u9054"
    ],
    "qs:a0":"\u0423\u043a\u0440\u0430\u0457\u043d\u0430",
    "qs:a1":"*\u041e\u0434\u0435\u0441\u044c\u043a\u0430",
    "qs:a1_alt":"Odes'ka",
    "qs:a1r":"0",
    "qs:a2":"\u0411\u0456\u043b\u044f\u0457\u0432\u0441\u044c\u043a\u0438\u0439",
    "qs:a2_alt":"Biliaivs'kyi",
    "qs:adm0":"\u0423\u043a\u0440\u0430\u0457\u043d\u0430",
    "qs:la_lc":"*",
    "qs:level":"locality",
    "qs:loc":"\u0412\u0438\u0433\u043e\u0434\u0430",
    "qs:loc_alt":"Vyhoda",
    "qs:pop":0,
    "qs:type":"buffered point",
    "wof:name":"\u0412\u0438\u0433\u043e\u0434\u0430",
    "wof:placetype":"locality"
},
  "geometry": {"coordinates":[30.395243,46.612209],"type":"Point"}
}