{
  "type": "Feature",
  "properties": {
    "gn:admin1_code":"1.0",
    "gn:asciiname":"Okhmatov",
    "gn:country_code":"UA",
    "gn:dem":186,
    "gn:feature_class":"P",
    "gn:feature_code":"PPL",
    "gn:name":"Okhmatov",
    "gn:population":0,
    "gn:timezone":"Europe/Kiev",
    "iso:country":"UA",
    "name:eng_x_preferred":[
        "Okhmatov"
    ],
    "name:rus_x_preferred":[
        "\u041e\u0445\u043c\u0430\u0442\u043e\u0432"
    ],
    "name:und_x_variant":[
        "Okhamtov",
        "Okhmatovo"
    ],
    "wof:name":"Okhmatov",
    "wof:placetype":"locality"
},
  "geometry": {"coordinates":[30.22133,49.16986],"type":"Point"}
}