{
  "type": "Feature",
  "properties": {
    "gn:admin1_code":"24.0",
    "gn:asciiname":"Brany",
    "gn:country_code":"UA",
    "gn:dem":211,
    "gn:feature_class":"P",
    "gn:feature_code":"PPL",
    "gn:name":"Brany",
    "gn:population":0,
    "gn:timezone":"Europe/Kiev",
    "iso:country":"UA",
    "name:ukr_x_preferred":[
        "Brany"
    ],
    "name:ukr_x_variant":[
        "\u0411\u0440\u0430\u043d\u0438"
    ],
    "wof:name":"Brany",
    "wof:placetype":"locality"
},
  "geometry": {"coordinates":[24.74718,50.4102],"type":"Point"}
}