{
  "type": "Feature",
  "properties": {
    "gn:admin1_code":"4.0",
    "gn:asciiname":"Malozakharyne",
    "gn:country_code":"UA",
    "gn:dem":115,
    "gn:feature_class":"P",
    "gn:feature_code":"PPL",
    "gn:name":"Malozakharyne",
    "gn:population":0,
    "gn:timezone":"Europe/Kiev",
    "iso:country":"UA",
    "name:ukr_x_preferred":[
        "Malozakharyne"
    ],
    "name:ukr_x_variant":[
        "\u041c\u0430\u043b\u043e\u0437\u0430\u0445\u0430\u0440\u0438\u043d\u0435"
    ],
    "name:und_x_variant":[
        "Aleksandrovka",
        "Malo-Zakharino"
    ],
    "wof:name":"Malozakharyne",
    "wof:placetype":"locality"
},
  "geometry": {"coordinates":[34.82015,48.06169000000001],"type":"Point"}
}