{
  "type": "Feature",
  "properties": {
    "gn:admin1_code":"24.0",
    "gn:asciiname":"Stavyshche",
    "gn:country_code":"UA",
    "gn:dem":158,
    "gn:feature_class":"P",
    "gn:feature_code":"PPL",
    "gn:name":"Stavyshche",
    "gn:population":0,
    "gn:timezone":"Europe/Kiev",
    "iso:country":"UA",
    "name:bel_x_preferred":[
        "\u0421\u0442\u0430\u0432\u044b\u0448\u0447\u044d"
    ],
    "name:ceb_x_preferred":[
        "Stavyshche"
    ],
    "name:crh_x_preferred":[
        "Stav\u0131\u015f\u00e7e"
    ],
    "name:deu_x_preferred":[
        "Stawyschtsche"
    ],
    "name:pol_x_preferred":[
        "Stawyszcze"
    ],
    "name:ron_x_preferred":[
        "Stav\u00ee\u0219ce"
    ],
    "name:rus_x_preferred":[
        "\u0421\u0442\u0430\u0432\u0438\u0449\u0435"
    ],
    "name:sah_x_preferred":[
        "\u0421\u0442\u0430\u0432\u0438\u0449\u0435"
    ],
    "name:ukr_x_preferred":[
        "Stavyshche"
    ],
    "name:ukr_x_variant":[
        "\u0421\u0442\u0430\u0432\u0438\u0449\u0435"
    ],
    "name:und_x_variant":[
        "Stavishche"
    ],
    "name:zho_x_preferred":[
        "\u65af\u5854\u7dad\u8b1d"
    ],
    "wof:name":"Stavyshche",
    "wof:placetype":"locality"
},
  "geometry": {"coordinates":[24.77656,51.51965],"type":"Point"}
}