{
  "type": "Feature",
  "properties": {
    "gn:admin1_code":"24.0",
    "gn:asciiname":"Stavyshche",
    "gn:country_code":"UA",
    "gn:dem":158,
    "gn:feature_class":"P",
    "gn:feature_code":"PPL",
    "gn:name":"Stavyshche",
    "gn:population":0,
    "gn:timezone":"Europe/Kiev",
    "iso:country":"UA",
    "name:ukr_x_preferred":[
        "Stavyshche"
    ],
    "name:ukr_x_variant":[
        "\u0421\u0442\u0430\u0432\u0438\u0449\u0435"
    ],
    "name:und_x_variant":[
        "Stavishche"
    ],
    "wof:name":"Stavyshche",
    "wof:placetype":"locality"
},
  "geometry": {"coordinates":[24.77656,51.51965],"type":"Point"}
}