{
  "type": "Feature",
  "properties": {
    "gn:admin1_code":"17.0",
    "gn:asciiname":"Abrykosove",
    "gn:country_code":"UA",
    "gn:dem":42,
    "gn:feature_class":"P",
    "gn:feature_code":"PPL",
    "gn:name":"Abrykosove",
    "gn:population":0,
    "gn:timezone":"Europe/Kiev",
    "iso:country":"UA",
    "name:ukr_x_preferred":[
        "Abrykosove"
    ],
    "name:ukr_x_variant":[
        "\u0410\u0431\u0440\u0438\u043a\u043e\u0441\u043e\u0432\u0435"
    ],
    "name:und_x_variant":[
        "Abrikosovoye"
    ],
    "wof:name":"Abrykosove",
    "wof:placetype":"locality"
},
  "geometry": {"coordinates":[30.29347000000001,46.11577],"type":"Point"}
}