{
  "type": "Feature",
  "properties": {
    "gn:admin1_code":"21.0",
    "gn:asciiname":"Stolyarove",
    "gn:country_code":"UA",
    "gn:dem":164,
    "gn:feature_class":"P",
    "gn:feature_code":"PPL",
    "gn:name":"Stolyarove",
    "gn:population":0,
    "gn:timezone":"Europe/Kiev",
    "iso:country":"UA",
    "name:ukr_x_preferred":[
        "Stolyarove"
    ],
    "name:ukr_x_variant":[
        "\u0421\u0442\u043e\u043b\u044f\u0440\u043e\u0432\u0435"
    ],
    "name:und_x_variant":[
        "Stolyarovo"
    ],
    "wof:name":"Stolyarove",
    "wof:placetype":"locality"
},
  "geometry": {"coordinates":[33.75872,50.65502],"type":"Point"}
}