{
  "type": "Feature",
  "properties": {
    "gn:admin1_code":"16.0",
    "gn:asciiname":"Grebeniki",
    "gn:country_code":"UA",
    "gn:dem":82,
    "gn:feature_class":"P",
    "gn:feature_code":"PPL",
    "gn:name":"Grebeniki",
    "gn:population":0,
    "gn:timezone":"Europe/Kiev",
    "iso:country":"UA",
    "wof:name":"Grebeniki",
    "wof:placetype":"locality"
},
  "geometry": {"coordinates":[31.94427,47.46119],"type":"Point"}
}