{
  "type": "Feature",
  "properties": {
    "gn:admin1_code":"2.0",
    "gn:asciiname":"Peschanka",
    "gn:country_code":"UA",
    "gn:dem":141,
    "gn:feature_class":"P",
    "gn:feature_code":"PPL",
    "gn:name":"Peschanka",
    "gn:population":0,
    "gn:timezone":"Europe/Kiev",
    "iso:country":"UA",
    "name:ukr_x_preferred":[
        "Peschanka"
    ],
    "wof:name":"Peschanka",
    "wof:placetype":"locality"
},
  "geometry": {"coordinates":[32.62194,52.16806],"type":"Point"}
}