{
  "type": "Feature",
  "properties": {
    "gn:admin1_code":"7.0",
    "gn:asciiname":"Krutoyarka",
    "gn:country_code":"UA",
    "gn:dem":172,
    "gn:feature_class":"P",
    "gn:feature_code":"PPL",
    "gn:name":"Krutoyarka",
    "gn:population":0,
    "gn:timezone":"Europe/Kiev",
    "iso:country":"UA",
    "name:ukr_x_preferred":[
        "\u041a\u0440\u0443\u0442\u043e\u044f\u0440\u043a\u0430"
    ],
    "name:und_x_variant":[
        "Krutoyarovka",
        "Krutoyarka"
    ],
    "wof:name":"Krutoyarka",
    "wof:placetype":"locality"
},
  "geometry": {"coordinates":[36.58486,49.28967],"type":"Point"}
}