{
  "type": "Feature",
  "properties": {
    "gn:admin1_code":"4.0",
    "gn:asciiname":"Chystopil'",
    "gn:country_code":"UA",
    "gn:dem":125,
    "gn:feature_class":"P",
    "gn:feature_code":"PPL",
    "gn:name":"Chystopil\u2019",
    "gn:population":0,
    "gn:timezone":"Europe/Kiev",
    "iso:country":"UA",
    "name:rus_x_preferred":[
        "Chistopol\u2019"
    ],
    "name:rus_x_variant":[
        "\u0427\u0438\u0441\u0442\u043e\u043f\u043e\u043b\u044c"
    ],
    "name:ukr_x_preferred":[
        "Chystopil\u2019"
    ],
    "name:ukr_x_variant":[
        "\u0427\u0438\u0441\u0442\u043e\u043f\u0456\u043b\u044c"
    ],
    "wof:name":"Chystopil'",
    "wof:placetype":"locality"
},
  "geometry": {"coordinates":[33.72175,48.49984],"type":"Point"}
}