{
  "type": "Feature",
  "properties": {
    "gn:admin1_code":"18.0",
    "gn:asciiname":"Nyzhni Vil'shany",
    "gn:country_code":"UA",
    "gn:dem":112,
    "gn:feature_class":"P",
    "gn:feature_code":"PPL",
    "gn:name":"Nyzhni Vil\u2019shany",
    "gn:population":0,
    "gn:timezone":"Europe/Kiev",
    "iso:country":"UA",
    "name:ukr_x_preferred":[
        "Nyzhni Vil\u2019shany"
    ],
    "name:ukr_x_variant":[
        "\u041d\u0438\u0436\u043d\u0456 \u0412\u0456\u043b\u044c\u0448\u0430\u043d\u0438"
    ],
    "wof:name":"Nyzhni Vil'shany",
    "wof:placetype":"locality"
},
  "geometry": {"coordinates":[34.49503,49.4733],"type":"Point"}
}