{
  "type": "Feature",
  "properties": {
    "gn:admin1_code":"7.0",
    "gn:asciiname":"Veselyy Poselok",
    "gn:country_code":"UA",
    "gn:dem":112,
    "gn:feature_class":"P",
    "gn:feature_code":"PPL",
    "gn:name":"Veselyy Poselok",
    "gn:population":0,
    "gn:timezone":"Europe/Kiev",
    "iso:country":"UA",
    "wof:name":"Veselyy Poselok",
    "wof:placetype":"locality"
},
  "geometry": {"coordinates":[36.48583,49.90333],"type":"Point"}
}