{
  "type": "Feature",
  "properties": {
    "iso:country":"UA",
    "name:ukr_x_preferred":[
        "\u041f\u0430\u0432\u043b\u0456\u0432\u043a\u0430"
    ],
    "name:und_x_variant":[
        "Pavlivka"
    ],
    "qs:a0":"\u0423\u043a\u0440\u0430\u0457\u043d\u0430",
    "qs:a1":"*\u0425\u0430\u0440\u043a\u0456\u0432\u0441\u044c\u043a\u0430",
    "qs:a1_alt":"Kharkivs'ka",
    "qs:a1r":"0",
    "qs:a2":"\u0411\u043e\u0433\u043e\u0434\u0443\u0445\u0456\u0432\u0441\u044c\u043a\u0438\u0439",
    "qs:a2_alt":"Bohodukhivs'kyi",
    "qs:adm0":"\u0423\u043a\u0440\u0430\u0457\u043d\u0430",
    "qs:la_lc":"*",
    "qs:level":"locality",
    "qs:loc":"\u041f\u0430\u0432\u043b\u0456\u0432\u043a\u0430",
    "qs:loc_alt":"Pavlivka",
    "qs:pop":0,
    "qs:type":"buffered point",
    "wd:wordcount":193,
    "wof:name":"\u041f\u0430\u0432\u043b\u0456\u0432\u043a\u0430",
    "wof:placetype":"locality"
},
  "geometry": {"coordinates":[35.449554,50.155082],"type":"Point"}
}