{
  "type": "Feature",
  "properties": {
    "gn:admin1_code":"27.0",
    "gn:asciiname":"Zelena Polyana",
    "gn:country_code":"UA",
    "gn:dem":229,
    "gn:feature_class":"P",
    "gn:feature_code":"PPL",
    "gn:name":"Zelena Polyana",
    "gn:population":0,
    "gn:timezone":"Europe/Kiev",
    "iso:country":"UA",
    "name:rus_x_preferred":[
        "Zel\u00ebnaya Polyana"
    ],
    "name:ukr_x_preferred":[
        "Zelena Polyana"
    ],
    "name:ukr_x_variant":[
        "\u0417\u0435\u043b\u0435\u043d\u0430 \u041f\u043e\u043b\u044f\u043d\u0430"
    ],
    "name:und_x_variant":[
        "Kutuzovka",
        "Koloniya Grital\u2019"
    ],
    "wof:name":"Zelena Polyana",
    "wof:placetype":"locality"
},
  "geometry": {"coordinates":[28.1623,50.59444000000001],"type":"Point"}
}