{
  "type": "Feature",
  "properties": {
    "gn:admin1_code":"7.0",
    "gn:asciiname":"Harbuzy",
    "gn:country_code":"UA",
    "gn:dem":183,
    "gn:feature_class":"P",
    "gn:feature_code":"PPL",
    "gn:name":"Harbuzy",
    "gn:population":0,
    "gn:timezone":"Europe/Kiev",
    "iso:country":"UA",
    "name:ukr_x_preferred":[
        "Harbuzy"
    ],
    "name:ukr_x_variant":[
        "\u0413\u0430\u0440\u0431\u0443\u0437\u0438"
    ],
    "name:und_x_variant":[
        "Khutor Garbuzy",
        "Garbuzy"
    ],
    "wof:name":"Harbuzy",
    "wof:placetype":"locality"
},
  "geometry": {"coordinates":[35.54938,50.29495],"type":"Point"}
}