{
  "type": "Feature",
  "properties": {
    "iso:country":"UA",
    "name:eng_x_preferred":[
        "Darakhiv"
    ],
    "name:pol_x_preferred":[
        "Darach\u00f3w"
    ],
    "name:rum_x_preferred":[
        "Darahiv"
    ],
    "name:rus_x_preferred":[
        "\u0414\u0430\u0440\u0430\u0445\u043e\u0432"
    ],
    "name:ukr_x_preferred":[
        "\u0414\u0430\u0440\u0430\u0445\u0456\u0432"
    ],
    "name:unk_x_variant":[
        "Dorokhov"
    ],
    "qs:a0":"\u0423\u043a\u0440\u0430\u0457\u043d\u0430",
    "qs:a1":"*\u0422\u0435\u0440\u043d\u043e\u043f\u0456\u043b\u044c\u0441\u044c\u043a\u0430",
    "qs:a1_alt":"Ternopil's'ka",
    "qs:a1r":"0",
    "qs:a2":"\u0422\u0435\u0440\u0435\u0431\u043e\u0432\u043b\u044f\u043d\u0441\u044c\u043a\u0438\u0439",
    "qs:a2_alt":"Terebovlians'kyi",
    "qs:adm0":"\u0423\u043a\u0440\u0430\u0457\u043d\u0430",
    "qs:la_lc":"*",
    "qs:level":"locality",
    "qs:loc":"\u0414\u0430\u0440\u0430\u0445\u0456\u0432",
    "qs:loc_alt":"Darakhiv",
    "qs:pop":0,
    "qs:type":"buffered point",
    "wof:name":"\u0414\u0430\u0440\u0430\u0445\u0456\u0432",
    "wof:placetype":"locality"
},
  "geometry": {"coordinates":[25.537103,49.291103],"type":"Point"}
}