{
  "type": "Feature",
  "properties": {
    "gn:admin1_code":"13.0",
    "gn:asciiname":"Kvitneve",
    "gn:country_code":"UA",
    "gn:dem":120,
    "gn:feature_class":"P",
    "gn:feature_code":"PPL",
    "gn:name":"Kvitneve",
    "gn:population":0,
    "gn:timezone":"Europe/Kiev",
    "iso:country":"UA",
    "name:ukr_x_preferred":[
        "Dymytrove"
    ],
    "name:ukr_x_variant":[
        "\u0414\u0438\u043c\u0438\u0442\u0440\u043e\u0432\u0435",
        "Kvitneve",
        "\u041a\u0432\u0456\u0442\u043d\u0435\u0432\u0435"
    ],
    "wof:name":"Kvitneve",
    "wof:placetype":"locality"
},
  "geometry": {"coordinates":[30.85257,50.53018],"type":"Point"}
}