{
  "type": "Feature",
  "properties": {
    "iso:country":"UA",
    "name:bel_x_preferred":[
        "\u0420\u044d\u0441\u043f\u0443\u0431\u043b\u0456\u043a\u0430\u043d\u0441\u043a\u0430\u044f \u043f\u043b\u0430\u0442\u0444\u043e\u0440\u043c\u0430"
    ],
    "name:cat_x_preferred":[
        "Partit Republic\u00e0 Ucra\u00efn\u00e8s \"Assemblea\""
    ],
    "name:deu_x_preferred":[
        "Ukrainische Republikanische Partei"
    ],
    "name:jpn_x_preferred":[
        "\u30a6\u30af\u30e9\u30a4\u30ca\u30d7\u30e9\u30c3\u30c8\u30d5\u30a9\u30fc\u30e0\u300c\u30bd\u30dc\u30eb\u300d"
    ],
    "name:pol_x_preferred":[
        "Ukrai\u0144ska Platforma \u201eZjednoczenie\u201d"
    ],
    "name:rus_x_preferred":[
        "\u0423\u043a\u0440\u0430\u0438\u043d\u0441\u043a\u0430\u044f \u043f\u043b\u0430\u0442\u0444\u043e\u0440\u043c\u0430 \u00ab\u0421\u043e\u0431\u043e\u0440\u00bb"
    ],
    "name:rus_x_variant":[
        "\u0420\u0435\u0441\u043f\u0443\u0431\u043b\u0438\u043a\u0430\u043d\u0441\u043a\u0430\u044f \u043f\u043b\u0430\u0442\u0444\u043e\u0440\u043c\u0430"
    ],
    "name:swe_x_preferred":[
        "Ukrainska republikanska partiet \"Samling\""
    ],
    "name:ukr_x_preferred":[
        "\u0420\u0435\u0441\u043f\u0443\u0431\u043b\u0456\u043a\u0430\u043d\u0441\u044c\u043a\u0430 \u043f\u043b\u0430\u0442\u0444\u043e\u0440\u043c\u0430"
    ],
    "name:ukr_x_variant":[
        "\u041a\u043e\u0440\u0438\u0441\u0442\u044c"
    ],
    "name:und_x_variant":[
        "Kozhists\u2019"
    ],
    "qs:a0":"\u0423\u043a\u0440\u0430\u0457\u043d\u0430",
    "qs:a1":"*\u0420\u0456\u0432\u043d\u0435\u043d\u0441\u044c\u043a\u0430",
    "qs:a1_alt":"Rivnens'ka",
    "qs:a1r":"0",
    "qs:a2":"\u041a\u043e\u0440\u0435\u0446\u044c\u043a\u0438\u0439",
    "qs:a2_alt":"Korets'kyi",
    "qs:adm0":"\u0423\u043a\u0440\u0430\u0457\u043d\u0430",
    "qs:la_lc":"*",
    "qs:level":"locality",
    "qs:loc":"\u041a\u043e\u0440\u0438\u0441\u0442\u044c",
    "qs:loc_alt":"Koryst",
    "qs:pop":0,
    "qs:type":"buffered point",
    "wd:wordcount":375,
    "wof:name":"\u041a\u043e\u0440\u0438\u0441\u0442\u044c",
    "wof:placetype":"locality"
},
  "geometry": {"coordinates":[27.027622,50.602594],"type":"Point"}
}