{
  "type": "Feature",
  "properties": {
    "gn:admin1_code":"27.0",
    "gn:asciiname":"Al'binivka",
    "gn:country_code":"UA",
    "gn:dem":190,
    "gn:feature_class":"P",
    "gn:feature_code":"PPL",
    "gn:name":"Al\u2019binivka",
    "gn:population":0,
    "gn:timezone":"Europe/Kiev",
    "iso:country":"UA",
    "name:und_x_variant":[
        "Al\u2019binovka",
        "Al\u2019binivka"
    ],
    "wof:name":"Al'binivka",
    "wof:placetype":"locality"
},
  "geometry": {"coordinates":[28.58333,50.23333],"type":"Point"}
}