{
  "type": "Feature",
  "properties": {
    "gn:admin1_code":"22.0",
    "gn:asciiname":"Bashkovtsy",
    "gn:country_code":"UA",
    "gn:dem":355,
    "gn:feature_class":"P",
    "gn:feature_code":"PPL",
    "gn:name":"Bashkovtsy",
    "gn:population":0,
    "gn:timezone":"Europe/Kiev",
    "iso:country":"UA",
    "name:und_x_variant":[
        "Bashkovtse",
        "Bashkovtsy"
    ],
    "wof:name":"Bashkovtsy",
    "wof:placetype":"locality"
},
  "geometry": {"coordinates":[25.87283,50.13101],"type":"Point"}
}