{
  "type": "Feature",
  "properties": {
    "gn:admin1_code":"2.0",
    "gn:asciiname":"Chudivka",
    "gn:country_code":"UA",
    "gn:dem":135,
    "gn:feature_class":"P",
    "gn:feature_code":"PPL",
    "gn:name":"Chudivka",
    "gn:population":0,
    "gn:timezone":"Europe/Kiev",
    "iso:country":"UA",
    "name:ukr_x_preferred":[
        "Chudivka"
    ],
    "name:ukr_x_variant":[
        "\u0427\u0443\u0434\u0456\u0432\u043a\u0430"
    ],
    "name:und_x_variant":[
        "Chudovka"
    ],
    "wof:name":"Chudivka",
    "wof:placetype":"locality"
},
  "geometry": {"coordinates":[30.99715,51.8763],"type":"Point"}
}