{
  "type": "Feature",
  "properties": {
    "gn:admin1_code":"17.0",
    "gn:asciiname":"Svitlohirs'ke",
    "gn:country_code":"UA",
    "gn:dem":87,
    "gn:feature_class":"P",
    "gn:feature_code":"PPL",
    "gn:name":"Svitlohirs\u2019ke",
    "gn:population":0,
    "gn:timezone":"Europe/Kiev",
    "iso:country":"UA",
    "name:ukr_x_preferred":[
        "Svitlohirs\u2019ke"
    ],
    "name:ukr_x_variant":[
        "\u0421\u0432\u0456\u0442\u043b\u043e\u0433\u0456\u0440\u0441\u044c\u043a\u0435"
    ],
    "name:und_x_variant":[
        "Svetlogorokoye"
    ],
    "wof:name":"Svitlohirs'ke",
    "wof:placetype":"locality"
},
  "geometry": {"coordinates":[30.36687,46.73264],"type":"Point"}
}