{
  "type": "Feature",
  "properties": {
    "gn:admin1_code":"11.0",
    "gn:admin2_code":"692311",
    "gn:asciiname":"Mindal'noye",
    "gn:country_code":"UA",
    "gn:dem":79,
    "gn:elevation":"134.0",
    "gn:feature_class":"P",
    "gn:feature_code":"PPL",
    "gn:name":"Mindal\u2019noye",
    "gn:population":143,
    "gn:timezone":"Europe/Simferopol",
    "iso:country":"UA",
    "name:eng_x_preferred":[
        "Mindal\u2019noye"
    ],
    "name:rus_x_historical":[
        "\u0410\u0440\u043a\u0430\u0301-\u0414\u0435\u0440\u0435\u0441\u0438\u0301"
    ],
    "name:rus_x_preferred":[
        "\u041c\u0438\u043d\u0434\u0430\u043b\u044c\u043d\u043e\u0435"
    ],
    "name:rus_x_variant":[
        "\u0410\u0440\u043a\u0430\u0301-\u0414\u0435\u0440\u0435\u0441\u0438\u0301"
    ],
    "name:ukr_x_preferred":[
        "\u041c\u0438\u043d\u0434\u0430\u043b\u044c\u043d\u0435"
    ],
    "wof:name":"Mindal'noye",
    "wof:placetype":"locality",
    "wof:population":143
},
  "geometry": {"coordinates":[35.04374,44.84874],"type":"Point"}
}