{
  "type": "Feature",
  "properties": {
    "gn:admin1_code":"9.0",
    "gn:asciiname":"Velikozales'ye",
    "gn:country_code":"UA",
    "gn:dem":194,
    "gn:feature_class":"P",
    "gn:feature_code":"PPL",
    "gn:name":"Velikozales\u2019ye",
    "gn:population":0,
    "gn:timezone":"Europe/Kiev",
    "iso:country":"UA",
    "name:und_x_variant":[
        "Bol\u2019shiye Armyane",
        "Armiani",
        "Velikozales\u2019ye"
    ],
    "wof:name":"Velikozales'ye",
    "wof:placetype":"locality"
},
  "geometry": {"coordinates":[26.54538,48.78643],"type":"Point"}
}