{
  "type": "Feature",
  "properties": {
    "gn:admin1_code":"21.0",
    "gn:asciiname":"Suprunivka",
    "gn:country_code":"UA",
    "gn:dem":177,
    "gn:feature_class":"P",
    "gn:feature_code":"PPL",
    "gn:name":"Suprunivka",
    "gn:population":0,
    "gn:timezone":"Europe/Kiev",
    "iso:country":"UA",
    "name:ukr_x_preferred":[
        "Suprunivka"
    ],
    "name:ukr_x_variant":[
        "\u0421\u0443\u043f\u0440\u0443\u043d\u0456\u0432\u043a\u0430"
    ],
    "name:und_x_variant":[
        "Suprunovka"
    ],
    "wof:name":"Suprunivka",
    "wof:placetype":"locality"
},
  "geometry": {"coordinates":[34.12566,51.00813],"type":"Point"}
}