{
  "type": "Feature",
  "properties": {
    "gn:admin1_code":"27.0",
    "gn:asciiname":"Nerazh",
    "gn:country_code":"UA",
    "gn:dem":202,
    "gn:feature_class":"P",
    "gn:feature_code":"PPL",
    "gn:name":"Nerazh",
    "gn:population":0,
    "gn:timezone":"Europe/Kiev",
    "iso:country":"UA",
    "name:ukr_x_preferred":[
        "Nerazh"
    ],
    "name:ukr_x_variant":[
        "\u041d\u0435\u0440\u0430\u0436"
    ],
    "wof:name":"Nerazh",
    "wof:placetype":"locality"
},
  "geometry": {"coordinates":[28.88718,50.6041],"type":"Point"}
}