{
  "type": "Feature",
  "properties": {
    "gn:admin1_code":"24.0",
    "gn:asciiname":"Stavok",
    "gn:country_code":"UA",
    "gn:dem":187,
    "gn:feature_class":"P",
    "gn:feature_code":"PPL",
    "gn:name":"Stavok",
    "gn:population":0,
    "gn:timezone":"Europe/Kiev",
    "iso:country":"UA",
    "name:ukr_x_preferred":[
        "Stavok"
    ],
    "name:ukr_x_variant":[
        "\u0421\u0442\u0430\u0432\u043e\u043a"
    ],
    "name:und_x_variant":[
        "Stavek"
    ],
    "wof:name":"Stavok",
    "wof:placetype":"locality"
},
  "geometry": {"coordinates":[24.4839,51.11375],"type":"Point"}
}