{
  "type": "Feature",
  "properties": {
    "gn:admin1_code":"11.0",
    "gn:admin2_code":"8449688",
    "gn:asciiname":"Zelenogor'e",
    "gn:country_code":"UA",
    "gn:dem":254,
    "gn:elevation":"260.0",
    "gn:feature_class":"P",
    "gn:feature_code":"PPL",
    "gn:name":"Zelenogor'e",
    "gn:population":231,
    "gn:timezone":"Europe/Simferopol",
    "iso:country":"UA",
    "name:eng_x_historical":[
        "Arpat"
    ],
    "name:eng_x_preferred":[
        "Arpat"
    ],
    "name:eng_x_variant":[
        "Zelenogor\u2019e"
    ],
    "name:rus_x_historical":[
        "\u0410\u0440\u043f\u0430\u0442"
    ],
    "name:rus_x_preferred":[
        "\u0417\u0435\u043b\u0435\u043d\u043e\u0433\u043e\u0440\u044c\u0435"
    ],
    "name:rus_x_variant":[
        "\u0410\u0440\u043f\u0430\u0442"
    ],
    "name:ukr_x_preferred":[
        "\u0417\u0435\u043b\u0435\u043d\u043e\u0433\u0456\u0440\u2019\u044f"
    ],
    "wof:name":"Zelenogor'e",
    "wof:placetype":"locality",
    "wof:population":231
},
  "geometry": {"coordinates":[34.72149,44.86978],"type":"Point"}
}