{
  "type": "Feature",
  "properties": {
    "gn:admin1_code":"27.0",
    "gn:asciiname":"Osychky",
    "gn:country_code":"UA",
    "gn:dem":187,
    "gn:feature_class":"P",
    "gn:feature_code":"PPL",
    "gn:name":"Osychky",
    "gn:population":0,
    "gn:timezone":"Europe/Kiev",
    "iso:country":"UA",
    "name:ukr_x_preferred":[
        "Osychky"
    ],
    "name:ukr_x_variant":[
        "\u041e\u0441\u0438\u0447\u043a\u0438"
    ],
    "name:und_x_variant":[
        "Osichki"
    ],
    "wof:name":"Osychky",
    "wof:placetype":"locality"
},
  "geometry": {"coordinates":[29.12147,50.57128],"type":"Point"}
}