{
  "type": "Feature",
  "properties": {
    "gn:admin1_code":"8.0",
    "gn:asciiname":"Stara Mayachka",
    "gn:country_code":"UA",
    "gn:dem":11,
    "gn:feature_class":"P",
    "gn:feature_code":"PPL",
    "gn:name":"Stara Mayachka",
    "gn:population":0,
    "gn:timezone":"Europe/Kiev",
    "iso:country":"UA",
    "name:rus_x_preferred":[
        "\u0421\u0442\u0430\u0440\u0430\u044f \u041c\u0430\u044f\u0447\u043a\u0430"
    ],
    "name:ukr_x_preferred":[
        "\u0421\u0442\u0430\u0440\u0430 \u041c\u0430\u044f\u0447\u043a\u0430"
    ],
    "name:und_x_variant":[
        "Malaja Majatschka",
        "Staraya Mayachka",
        "Malaya Mayachka",
        "Stara Mayachka"
    ],
    "wof:name":"Stara Mayachka",
    "wof:placetype":"locality"
},
  "geometry": {"coordinates":[33.18089000000001,46.5104],"type":"Point"}
}