{
  "type": "Feature",
  "properties": {
    "gn:admin1_code":"6.0",
    "gn:asciiname":"Lypa",
    "gn:country_code":"UA",
    "gn:dem":624,
    "gn:feature_class":"P",
    "gn:feature_code":"PPL",
    "gn:name":"Lypa",
    "gn:population":0,
    "gn:timezone":"Europe/Kiev",
    "iso:country":"UA",
    "name:deu_x_preferred":[
        "Lypa"
    ],
    "name:ukr_x_preferred":[
        "Lypa"
    ],
    "name:ukr_x_variant":[
        "\u041b\u0443\u043f\u0430"
    ],
    "name:und_x_variant":[
        "Lipa"
    ],
    "wof:name":"Lypa",
    "wof:placetype":"locality"
},
  "geometry": {"coordinates":[23.71648,48.94618],"type":"Point"}
}