{
  "type": "Feature",
  "properties": {
    "gn:country":"UA",
    "gn:fcode":"PPL",
    "gn:population":1826,
    "iso:country":"UA",
    "name:eng_x_preferred":[
        "Tukhlya"
    ],
    "name:rus_x_preferred":[
        "\u0422\u0443\u0445\u043b\u044f"
    ],
    "name:ukr_x_preferred":[
        "\u0422\u0443\u0445\u043b\u044f"
    ],
    "name:und_x_variant":[
        "Tuchla"
    ],
    "qs_pg:aaroncc":"UA",
    "qs_pg:gn_country":"UA",
    "qs_pg:gn_fcode":"PPL",
    "qs_pg:gn_pop":1826,
    "qs_pg:name":"Tukhlya",
    "qs_pg:photos_9r":0,
    "qs_pg:photos_sr":0,
    "qs_pg:pop_sr":3,
    "qs_pg:qs_pg_placetype":"locality",
    "wof:name":"Tukhlya",
    "wof:placetype":"locality",
    "wof:population":1826
},
  "geometry": {"coordinates":[23.47303,48.91218],"type":"Point"}
}