{
  "type": "Feature",
  "properties": {
    "gn:admin1_code":"5.0",
    "gn:asciiname":"Serednye",
    "gn:country_code":"UA",
    "gn:dem":95,
    "gn:feature_class":"P",
    "gn:feature_code":"PPL",
    "gn:name":"Serednye",
    "gn:population":0,
    "gn:timezone":"Europe/Kiev",
    "iso:country":"UA",
    "name:ukr_x_preferred":[
        "Serednye"
    ],
    "name:und_x_variant":[
        "Sredniy"
    ],
    "wof:name":"Serednye",
    "wof:placetype":"locality"
},
  "geometry": {"coordinates":[37.70826,49.12363],"type":"Point"}
}