{
  "type": "Feature",
  "properties": {
    "iso:country":"UA",
    "name:pol_x_preferred":[
        "Kutyszcze"
    ],
    "name:ron_x_preferred":[
        "Kut\u00ee\u0219ce"
    ],
    "name:rus_x_preferred":[
        "\u041a\u0443\u0442\u0438\u0449\u0435"
    ],
    "name:ukr_x_preferred":[
        "\u041a\u0443\u0442\u0438\u0449\u0435"
    ],
    "name:unk_x_variant":[
        "Kutyska"
    ],
    "name:zho_x_preferred":[
        "\u5eab\u5b63\u8b1d"
    ],
    "qs:a0":"\u0423\u043a\u0440\u0430\u0457\u043d\u0430",
    "qs:a1":"*\u0406\u0432\u0430\u043d\u043e-\u0424\u0440\u0430\u043d\u043a\u0456\u0432\u0441\u044c\u043a\u0430",
    "qs:a1_alt":"Ivano-Frankivs'ka",
    "qs:a1r":"0",
    "qs:a2":"\u0422\u043b\u0443\u043c\u0430\u0446\u044c\u043a\u0438\u0439",
    "qs:a2_alt":"Tlumats'kyi",
    "qs:adm0":"\u0423\u043a\u0440\u0430\u0457\u043d\u0430",
    "qs:la_lc":"*",
    "qs:level":"locality",
    "qs:loc":"\u041a\u0443\u0442\u0438\u0449\u0435",
    "qs:loc_alt":"Kutysche",
    "qs:pop":0,
    "qs:type":"buffered point",
    "wd:wordcount":49,
    "wof:name":"\u041a\u0443\u0442\u0438\u0449\u0435",
    "wof:placetype":"locality"
},
  "geometry": {"coordinates":[25.108918,48.904937],"type":"Point"}
}