{
  "type": "Feature",
  "properties": {
    "gn:admin1_code":"14.0",
    "gn:asciiname":"Hannivka",
    "gn:country_code":"UA",
    "gn:dem":62,
    "gn:feature_class":"P",
    "gn:feature_code":"PPL",
    "gn:name":"Hannivka",
    "gn:population":0,
    "gn:timezone":"Europe/Zaporozhye",
    "iso:country":"UA",
    "name:ukr_x_preferred":[
        "Hannivka"
    ],
    "wof:name":"Hannivka",
    "wof:placetype":"locality"
},
  "geometry": {"coordinates":[38.82854,49.36056],"type":"Point"}
}