{
  "type": "Feature",
  "properties": {
    "gn:admin1_code":"25.0",
    "gn:asciiname":"Kholmovets'",
    "gn:country_code":"UA",
    "gn:dem":126,
    "gn:feature_class":"P",
    "gn:feature_code":"PPL",
    "gn:name":"Kholmovets\u2019",
    "gn:population":0,
    "gn:timezone":"Europe/Uzhgorod",
    "iso:country":"UA",
    "name:ukr_x_preferred":[
        "Kholmovets\u2019"
    ],
    "name:ukr_x_variant":[
        "\u0425\u043e\u043b\u043c\u043e\u0432\u0435\u0446\u044c"
    ],
    "name:und_x_variant":[
        "Kholmovets"
    ],
    "wof:name":"Kholmovets'",
    "wof:placetype":"locality"
},
  "geometry": {"coordinates":[23.08664,48.05799],"type":"Point"}
}