{
  "type": "Feature",
  "properties": {
    "gn:admin1_code":"8.0",
    "gn:asciiname":"Rozhnovka",
    "gn:country_code":"UA",
    "gn:dem":31,
    "gn:feature_class":"P",
    "gn:feature_code":"PPL",
    "gn:name":"Rozhnovka",
    "gn:population":0,
    "gn:timezone":"Europe/Kiev",
    "iso:country":"UA",
    "wof:name":"Rozhnovka",
    "wof:placetype":"locality"
},
  "geometry": {"coordinates":[32.61667,46.71667],"type":"Point"}
}