{
  "type": "Feature",
  "properties": {
    "iso:country":"UA",
    "qs:a0":"\u0423\u043a\u0440\u0430\u0457\u043d\u0430",
    "qs:a1":"*\u041c\u0438\u043a\u043e\u043b\u0430\u0457\u0432\u0441\u044c\u043a\u0430",
    "qs:a1_alt":"Mykolaivs'ka",
    "qs:a1r":"0",
    "qs:a2":"\u0410\u0440\u0431\u0443\u0437\u0438\u043d\u0441\u044c\u043a\u0438\u0439",
    "qs:a2_alt":"Arbuzyns'kyi",
    "qs:adm0":"\u0423\u043a\u0440\u0430\u0457\u043d\u0430",
    "qs:la_lc":"*",
    "qs:level":"locality",
    "qs:loc":"\u0410\u0433\u0440\u043e\u043d\u043e\u043c\u0456\u044f",
    "qs:loc_alt":"Ahronomiia",
    "qs:pop":0,
    "qs:type":"buffered point",
    "wof:name":"\u0410\u0433\u0440\u043e\u043d\u043e\u043c\u0456\u044f",
    "wof:placetype":"locality"
},
  "geometry": {"coordinates":[31.309942,47.766916],"type":"Point"}
}