{
  "type": "Feature",
  "properties": {
    "gn:admin1_code":"14.0",
    "gn:asciiname":"Kovalivka",
    "gn:country_code":"UA",
    "gn:dem":96,
    "gn:feature_class":"P",
    "gn:feature_code":"PPL",
    "gn:name":"Kovalivka",
    "gn:population":0,
    "gn:timezone":"Europe/Zaporozhye",
    "iso:country":"UA",
    "name:ukr_x_preferred":[
        "Kovalivka"
    ],
    "name:und_x_variant":[
        "Kovalevka"
    ],
    "wof:name":"Kovalivka",
    "wof:placetype":"locality"
},
  "geometry": {"coordinates":[38.00968,49.3362],"type":"Point"}
}