{
  "type": "Feature",
  "properties": {
    "gn:admin1_code":"3.0",
    "gn:asciiname":"Vashkovtsy",
    "gn:country_code":"UA",
    "gn:dem":257,
    "gn:feature_class":"P",
    "gn:feature_code":"PPL",
    "gn:name":"Vashkovtsy",
    "gn:population":0,
    "gn:timezone":"Europe/Kiev",
    "iso:country":"UA",
    "name:und_x_variant":[
        "Vaskauts\u2019",
        "Vas\u2019kovtsy",
        "V\u0103sc\u0103u\u0163i",
        "Vashkovtsy"
    ],
    "wof:name":"Vashkovtsy",
    "wof:placetype":"locality"
},
  "geometry": {"coordinates":[27.13221,48.4094],"type":"Point"}
}