{
  "type": "Feature",
  "properties": {
    "gn:admin1_code":"19.0",
    "gn:asciiname":"Hrushvytsya Persha",
    "gn:country_code":"UA",
    "gn:dem":212,
    "gn:feature_class":"P",
    "gn:feature_code":"PPL",
    "gn:name":"Hrushvytsya Persha",
    "gn:population":0,
    "gn:timezone":"Europe/Kiev",
    "iso:country":"UA",
    "name:ukr_x_preferred":[
        "Hrushvytsya Persha"
    ],
    "name:ukr_x_variant":[
        "\u0413\u0440\u0443\u0448\u0432\u0438\u0446\u044f \u041f\u0435\u0440\u0448\u0430"
    ],
    "name:und_x_variant":[
        "Khrushevitsi",
        "Grushevitsa",
        "Khrushvitsa",
        "Hruszwica",
        "Grushvitsi",
        "Grushvitsa",
        "Grushvitsy Pervyye",
        "Grushvitsa Pervaya"
    ],
    "wof:name":"Hrushvytsya Persha",
    "wof:placetype":"locality"
},
  "geometry": {"coordinates":[26.02789,50.5493],"type":"Point"}
}