{
  "type": "Feature",
  "properties": {
    "gn:admin1_code":"2.0",
    "gn:asciiname":"Smosh",
    "gn:country_code":"UA",
    "gn:dem":112,
    "gn:feature_class":"P",
    "gn:feature_code":"PPL",
    "gn:name":"Smosh",
    "gn:population":0,
    "gn:timezone":"Europe/Kiev",
    "iso:country":"UA",
    "name:ara_x_preferred":[
        "\u0633\u0645\u0648\u0634"
    ],
    "name:bul_x_preferred":[
        "\u0421\u043c\u043e\u0448"
    ],
    "name:dan_x_preferred":[
        "Smosh"
    ],
    "name:deu_x_preferred":[
        "Smosh"
    ],
    "name:est_x_preferred":[
        "Smosh"
    ],
    "name:fas_x_preferred":[
        "\u0627\u0633\u0645\u0627\u0634"
    ],
    "name:fin_x_preferred":[
        "Smosh"
    ],
    "name:fra_x_preferred":[
        "Smosh"
    ],
    "name:glg_x_preferred":[
        "Smosh"
    ],
    "name:heb_x_preferred":[
        "\u05e1\u05de\u05d5\u05e9"
    ],
    "name:hun_x_preferred":[
        "Smosh"
    ],
    "name:ido_x_preferred":[
        "Smosh"
    ],
    "name:ind_x_preferred":[
        "Smosh"
    ],
    "name:ita_x_preferred":[
        "Smosh"
    ],
    "name:jpn_x_preferred":[
        "\u30b9\u30e2\u30c3\u30b7\u30e5"
    ],
    "name:kor_x_preferred":[
        "\uc2a4\ubaa8\uc26c"
    ],
    "name:lat_x_preferred":[
        "Smosh"
    ],
    "name:msa_x_preferred":[
        "Smosh"
    ],
    "name:nor_x_preferred":[
        "Smosh"
    ],
    "name:oci_x_preferred":[
        "Smosh"
    ],
    "name:pol_x_preferred":[
        "Smosh"
    ],
    "name:por_x_preferred":[
        "Smosh"
    ],
    "name:rus_x_preferred":[
        "Smosh"
    ],
    "name:swa_x_preferred":[
        "Smosh"
    ],
    "name:swe_x_preferred":[
        "Smosh"
    ],
    "name:tgl_x_preferred":[
        "Smosh"
    ],
    "name:tur_x_preferred":[
        "Smosh"
    ],
    "name:ukr_x_preferred":[
        "Smosh"
    ],
    "name:ukr_x_variant":[
        "\u0421\u043c\u043e\u0448"
    ],
    "name:vie_x_preferred":[
        "Smosh"
    ],
    "name:zho_x_preferred":[
        "Smosh"
    ],
    "wof:name":"Smosh",
    "wof:placetype":"locality"
},
  "geometry": {"coordinates":[32.54435,50.67357],"type":"Point"}
}