{
  "type": "Feature",
  "properties": {
    "gn:admin1_code":"2.0",
    "gn:asciiname":"Smosh",
    "gn:country_code":"UA",
    "gn:dem":112,
    "gn:feature_class":"P",
    "gn:feature_code":"PPL",
    "gn:name":"Smosh",
    "gn:population":0,
    "gn:timezone":"Europe/Kiev",
    "iso:country":"UA",
    "name:ukr_x_preferred":[
        "Smosh"
    ],
    "name:ukr_x_variant":[
        "\u0421\u043c\u043e\u0448"
    ],
    "wof:name":"Smosh",
    "wof:placetype":"locality"
},
  "geometry": {"coordinates":[32.54435,50.67357],"type":"Point"}
}