{
  "type": "Feature",
  "properties": {
    "gn:admin1_code":"14.0",
    "gn:asciiname":"Kruta Hora",
    "gn:country_code":"UA",
    "gn:dem":46,
    "gn:feature_class":"P",
    "gn:feature_code":"PPL",
    "gn:name":"Kruta Hora",
    "gn:population":0,
    "gn:timezone":"Europe/Zaporozhye",
    "iso:country":"UA",
    "name:ukr_x_preferred":[
        "Kruta Hora"
    ],
    "name:ukr_x_variant":[
        "\u041a\u0440\u0443\u0442\u0430 \u0413\u043e\u0440\u0430"
    ],
    "name:und_x_variant":[
        "Krutogorovka",
        "Krutaya Gora"
    ],
    "wof:name":"Kruta Hora",
    "wof:placetype":"locality"
},
  "geometry": {"coordinates":[39.14413,48.66426],"type":"Point"}
}