{
  "type": "Feature",
  "properties": {
    "gn:population":2965,
    "iso:country":"UA",
    "name:ceb_x_preferred":[
        "Chornoliztsi"
    ],
    "name:deu_x_preferred":[
        "Tschornoliszi"
    ],
    "name:eng_x_preferred":[
        "Chornoliztsi"
    ],
    "name:pol_x_preferred":[
        "Czarno\u0142o\u015bce"
    ],
    "name:ron_x_preferred":[
        "Ciornoliz\u021bi"
    ],
    "name:rus_x_preferred":[
        "\u0427\u043e\u0440\u043d\u043e\u043b\u0456\u0437\u0446\u0456"
    ],
    "name:rus_x_variant":[
        "\u0427\u0435\u0440\u043d\u043e\u043b\u043e\u0437\u0446\u044b"
    ],
    "name:ukr_x_preferred":[
        "\u0427\u043e\u0440\u043d\u043e\u043b\u0456\u0437\u0446\u0456"
    ],
    "name:und_x_variant":[
        "Charnolozhtsy"
    ],
    "name:zho_x_preferred":[
        "\u55ac\u723e\u8afe\u5229\u8332\u9f4a"
    ],
    "qs:a0":"\u0423\u043a\u0440\u0430\u0457\u043d\u0430",
    "qs:a1":"*\u0406\u0432\u0430\u043d\u043e-\u0424\u0440\u0430\u043d\u043a\u0456\u0432\u0441\u044c\u043a\u0430",
    "qs:a1_alt":"Ivano-Frankivs'ka",
    "qs:a1r":"0",
    "qs:a2":"\u0422\u0438\u0441\u043c\u0435\u043d\u0438\u0446\u044c\u043a\u0438\u0439",
    "qs:a2_alt":"Tysmenyts'kyi",
    "qs:adm0":"\u0423\u043a\u0440\u0430\u0457\u043d\u0430",
    "qs:la_lc":"*",
    "qs:level":"locality",
    "qs:loc":"\u0427\u043e\u0440\u043d\u043e\u043b\u0456\u0437\u0446\u0456",
    "qs:loc_alt":"Chornoliztsi",
    "qs:pop":0,
    "qs:type":"buffered point",
    "wof:name":"\u0427\u043e\u0440\u043d\u043e\u043b\u0456\u0437\u0446\u0456",
    "wof:placetype":"locality",
    "wof:population":2965
},
  "geometry": {"coordinates":[24.893524,48.822409],"type":"Point"}
}