{
  "type": "Feature",
  "properties": {
    "gn:admin1_code":"21.0",
    "gn:asciiname":"Zatsarne",
    "gn:country_code":"UA",
    "gn:dem":154,
    "gn:feature_class":"P",
    "gn:feature_code":"PPL",
    "gn:name":"Zatsarne",
    "gn:population":0,
    "gn:timezone":"Europe/Kiev",
    "iso:country":"UA",
    "name:ukr_x_preferred":[
        "Zatsarne"
    ],
    "name:ukr_x_variant":[
        "\u0417\u0430\u0446\u0430\u0440\u043d\u0435"
    ],
    "name:und_x_variant":[
        "Zatsarnyy",
        "Zatsarnoye"
    ],
    "wof:name":"Zatsarne",
    "wof:placetype":"locality"
},
  "geometry": {"coordinates":[35.00888,50.90393],"type":"Point"}
}