{
  "type": "Feature",
  "properties": {
    "gn:admin1_code":"10.0",
    "gn:asciiname":"Troyanka",
    "gn:country_code":"UA",
    "gn:dem":141,
    "gn:feature_class":"P",
    "gn:feature_code":"PPL",
    "gn:name":"Troyanka",
    "gn:population":0,
    "gn:timezone":"Europe/Kiev",
    "iso:country":"UA",
    "name:ukr_x_preferred":[
        "Troyanka"
    ],
    "name:ukr_x_variant":[
        "\u0422\u0440\u043e\u044f\u043d\u043a\u0430"
    ],
    "wof:name":"Troyanka",
    "wof:placetype":"locality"
},
  "geometry": {"coordinates":[32.77435,48.65215],"type":"Point"}
}