{
  "type": "Feature",
  "properties": {
    "gn:admin1_code":"18.0",
    "gn:asciiname":"Velykyy Trostyanets'",
    "gn:country_code":"UA",
    "gn:dem":151,
    "gn:feature_class":"P",
    "gn:feature_code":"PPL",
    "gn:name":"Velykyy Trostyanets\u2019",
    "gn:population":0,
    "gn:timezone":"Europe/Kiev",
    "iso:country":"UA",
    "name:ukr_x_preferred":[
        "Velykyy Trostyanets\u2019"
    ],
    "name:ukr_x_variant":[
        "\u0412\u0435\u043b\u0438\u043a\u0438\u0439 \u0422\u0440\u043e\u0441\u0442\u044f\u043d\u0435\u0446\u044c"
    ],
    "name:und_x_variant":[
        "Trostyanets",
        "Velikiy Trostyanets"
    ],
    "wof:name":"Velykyy Trostyanets'",
    "wof:placetype":"locality"
},
  "geometry": {"coordinates":[34.53665,49.4971],"type":"Point"}
}