{
  "type": "Feature",
  "properties": {
    "gn:admin1_code":"19.0",
    "gn:asciiname":"Kolets",
    "gn:country_code":"UA",
    "gn:dem":151,
    "gn:feature_class":"P",
    "gn:feature_code":"PPL",
    "gn:name":"Kolets",
    "gn:population":0,
    "gn:timezone":"Europe/Kiev",
    "iso:country":"UA",
    "name:bul_x_preferred":[
        "\u041a\u043e\u043b\u0435\u0446"
    ],
    "name:ceb_x_preferred":[
        "Kolec"
    ],
    "name:kaz_x_preferred":[
        "\u041a\u043e\u043b\u0435\u0446"
    ],
    "name:pol_x_preferred":[
        "Kolec"
    ],
    "name:ron_x_preferred":[
        "Kole\u021b"
    ],
    "name:rus_x_preferred":[
        "\u041a\u043e\u043b\u0435\u0446"
    ],
    "name:swe_x_preferred":[
        "Kolets"
    ],
    "name:ukr_x_preferred":[
        "\u041a\u043e\u043b\u0435\u0446\u044c"
    ],
    "wof:name":"Kolets",
    "wof:placetype":"locality"
},
  "geometry": {"coordinates":[26.51667,51.31667],"type":"Point"}
}