{
  "type": "Feature",
  "properties": {
    "gn:admin1_code":"7.0",
    "gn:asciiname":"Zheleznyy",
    "gn:country_code":"UA",
    "gn:dem":139,
    "gn:feature_class":"P",
    "gn:feature_code":"PPL",
    "gn:name":"Zheleznyy",
    "gn:population":0,
    "gn:timezone":"Europe/Kiev",
    "iso:country":"UA",
    "wof:name":"Zheleznyy",
    "wof:placetype":"locality"
},
  "geometry": {"coordinates":[37.40028,49.43],"type":"Point"}
}