{
  "type": "Feature",
  "properties": {
    "gn:admin1_code":"11.0",
    "gn:admin2_code":"703233",
    "gn:admin3_code":"11128516.0",
    "gn:asciiname":"Korolyovo",
    "gn:country_code":"UA",
    "gn:dem":35,
    "gn:feature_class":"P",
    "gn:feature_code":"PPL",
    "gn:name":"Korolyovo",
    "gn:population":104,
    "gn:timezone":"Europe/Simferopol",
    "iso:country":"UA",
    "name:aze_x_preferred":[
        "Korolyov"
    ],
    "name:bak_x_preferred":[
        "\u041a\u043e\u0440\u043e\u043b\u0435\u0432"
    ],
    "name:eng_x_preferred":[
        "Korolyovo"
    ],
    "name:hye_x_preferred":[
        "\u053f\u0578\u0580\u0578\u056c\u0587\u0578"
    ],
    "name:kat_x_preferred":[
        "\u10d9\u10dd\u10e0\u10dd\u10da\u10d4\u10d5\u10dd"
    ],
    "name:kaz_x_preferred":[
        "\u041a\u043e\u0440\u043e\u043b"
    ],
    "name:kir_x_preferred":[
        "\u041a\u043e\u0440\u043e\u043b"
    ],
    "name:rus_x_historical":[
        "\u041a\u043e\u0434\u0436\u0430\u043b\u0430\u0301\u0440"
    ],
    "name:rus_x_preferred":[
        "\u041a\u043e\u0440\u043e\u043b\u0451\u0432\u043e"
    ],
    "name:rus_x_variant":[
        "\u041a\u043e\u0434\u0436\u0430\u043b\u0430\u0301\u0440"
    ],
    "name:tat_x_preferred":[
        "\u041a\u043e\u0440\u043e\u043b\u0435\u0432\u043e"
    ],
    "name:ukr_x_preferred":[
        "\u041a\u043e\u0440\u043e\u043b\u044c\u043e\u0432\u0435"
    ],
    "wof:name":"Korolyovo",
    "wof:placetype":"locality",
    "wof:population":104
},
  "geometry": {"coordinates":[35.78425,45.27235],"type":"Point"}
}