{
  "type": "Feature",
  "properties": {
    "gn:admin1_code":"09",
    "gn:asciiname":"Krasnosilka",
    "gn:country_code":"UA",
    "gn:dem":264,
    "gn:feature_class":"P",
    "gn:feature_code":"PPL",
    "gn:name":"Krasnosilka",
    "gn:population":0,
    "gn:timezone":"Europe/Kiev",
    "iso:country":"UA",
    "name:ukr_x_preferred":[
        "Krasnosilka"
    ],
    "name:ukr_x_variant":[
        "\u041a\u0440\u0430\u0441\u043d\u043e\u0441\u0456\u043b\u043a\u0430"
    ],
    "wof:name":"Krasnosilka",
    "wof:placetype":"locality"
},
  "geometry": {"coordinates":[27.08921,50.15474],"type":"Point"}
}