{
  "type": "Feature",
  "properties": {
    "gn:admin1_code":"15.0",
    "gn:asciiname":"Polyany",
    "gn:country_code":"UA",
    "gn:dem":379,
    "gn:feature_class":"P",
    "gn:feature_code":"PPL",
    "gn:name":"Polyany",
    "gn:population":0,
    "gn:timezone":"Europe/Kiev",
    "iso:country":"UA",
    "name:bel_x_preferred":[
        "\u041f\u0430\u043b\u044f\u043d\u044b"
    ],
    "name:rus_x_preferred":[
        "\u041f\u043e\u043b\u044f\u043d\u044b"
    ],
    "name:ukr_x_preferred":[
        "\u041f\u043e\u043b\u044f\u043d\u0438"
    ],
    "name:und_x_variant":[
        "Rykuv",
        "Polyany"
    ],
    "wof:name":"Polyany",
    "wof:placetype":"locality"
},
  "geometry": {"coordinates":[24.98696,49.74261],"type":"Point"}
}