{
  "type": "Feature",
  "properties": {
    "gn:admin1_code":"15.0",
    "gn:asciiname":"Ushnya",
    "gn:country_code":"UA",
    "gn:dem":260,
    "gn:feature_class":"P",
    "gn:feature_code":"PPL",
    "gn:name":"Ushnya",
    "gn:population":0,
    "gn:timezone":"Europe/Kiev",
    "iso:country":"UA",
    "wof:name":"Ushnya",
    "wof:placetype":"locality"
},
  "geometry": {"coordinates":[24.91554,49.89093],"type":"Point"}
}