{
  "type": "Feature",
  "properties": {
    "gn:admin1_code":"9.0",
    "gn:asciiname":"Zhenishkovtsy",
    "gn:country_code":"UA",
    "gn:dem":338,
    "gn:feature_class":"P",
    "gn:feature_code":"PPL",
    "gn:name":"Zhenishkovtsy",
    "gn:population":0,
    "gn:timezone":"Europe/Kiev",
    "iso:country":"UA",
    "wof:name":"Zhenishkovtsy",
    "wof:placetype":"locality"
},
  "geometry": {"coordinates":[27.38974,49.10285],"type":"Point"}
}