{
  "type": "Feature",
  "properties": {
    "gn:admin1_code":"14.0",
    "gn:asciiname":"Valuys'ke",
    "gn:country_code":"UA",
    "gn:dem":57,
    "gn:feature_class":"P",
    "gn:feature_code":"PPL",
    "gn:name":"Valuys\u2019ke",
    "gn:population":0,
    "gn:timezone":"Europe/Zaporozhye",
    "iso:country":"UA",
    "name:eng_x_preferred":[
        "Valuyskoye"
    ],
    "name:rus_x_preferred":[
        "\u0412\u0430\u043b\u0443\u0439\u0441\u043a\u043e\u0435"
    ],
    "name:ukr_x_preferred":[
        "Valuys\u2019ke"
    ],
    "name:ukr_x_variant":[
        "\u0412\u0430\u043b\u0443\u0439\u0441\u044c\u043a\u0435"
    ],
    "name:und_x_variant":[
        "Valuyskiy",
        "Valuysk"
    ],
    "wof:name":"Valuys'ke",
    "wof:placetype":"locality"
},
  "geometry": {"coordinates":[39.53681,48.6747],"type":"Point"}
}