{
  "type": "Feature",
  "properties": {
    "gn:admin1_code":"15.0",
    "gn:asciiname":"Fusiv",
    "gn:country_code":"UA",
    "gn:dem":230,
    "gn:feature_class":"P",
    "gn:feature_code":"PPL",
    "gn:name":"Fusiv",
    "gn:population":0,
    "gn:timezone":"Europe/Kiev",
    "iso:country":"UA",
    "name:ukr_x_preferred":[
        "\u0424\u0443\u0441\u0456\u0432"
    ],
    "name:und_x_variant":[
        "Fusov"
    ],
    "wof:name":"Fusiv",
    "wof:placetype":"locality"
},
  "geometry": {"coordinates":[24.54369,50.42844],"type":"Point"}
}