{
  "type": "Feature",
  "properties": {
    "gn:admin1_code":"26.0",
    "gn:asciiname":"Rays'ke",
    "gn:country_code":"UA",
    "gn:dem":124,
    "gn:feature_class":"P",
    "gn:feature_code":"PPL",
    "gn:name":"Rays\u2019ke",
    "gn:population":0,
    "gn:timezone":"Europe/Zaporozhye",
    "iso:country":"UA",
    "name:ukr_x_preferred":[
        "Rays\u2019ke"
    ],
    "name:ukr_x_variant":[
        "\u0420\u0430\u0439\u0441\u044c\u043a\u0435"
    ],
    "name:und_x_variant":[
        "Udachny",
        "Udachnyy",
        "Rayskoye",
        "Rayskiy",
        "Ratskiy"
    ],
    "wof:name":"Rays'ke",
    "wof:placetype":"locality"
},
  "geometry": {"coordinates":[35.63644,47.86938],"type":"Point"}
}