{
  "type": "Feature",
  "properties": {
    "gn:admin1_code":"21.0",
    "gn:asciiname":"Kononenkove",
    "gn:country_code":"UA",
    "gn:dem":159,
    "gn:feature_class":"P",
    "gn:feature_code":"PPL",
    "gn:name":"Kononenkove",
    "gn:population":0,
    "gn:timezone":"Europe/Kiev",
    "iso:country":"UA",
    "name:ukr_x_preferred":[
        "Kononenkove"
    ],
    "name:ukr_x_variant":[
        "\u041a\u043e\u043d\u043e\u043d\u0435\u043d\u043a\u043e\u0432\u0435"
    ],
    "name:und_x_variant":[
        "Kononenkovo"
    ],
    "wof:name":"Kononenkove",
    "wof:placetype":"locality"
},
  "geometry": {"coordinates":[33.53805,50.80683],"type":"Point"}
}