{
  "type": "Feature",
  "properties": {
    "gn:admin1_code":"23.0",
    "gn:asciiname":"Bakhtyn",
    "gn:country_code":"UA",
    "gn:dem":270,
    "gn:feature_class":"P",
    "gn:feature_code":"PPL",
    "gn:name":"Bakhtyn",
    "gn:population":0,
    "gn:timezone":"Europe/Kiev",
    "iso:country":"UA",
    "name:und_x_variant":[
        "Bakhtin",
        "Bakhtyn"
    ],
    "wof:name":"Bakhtyn",
    "wof:placetype":"locality"
},
  "geometry": {"coordinates":[27.48592,48.81267],"type":"Point"}
}