{
  "type": "Feature",
  "properties": {
    "gn:admin1_code":"18.0",
    "gn:asciiname":"Hovtvyanchyk",
    "gn:country_code":"UA",
    "gn:dem":144,
    "gn:feature_class":"P",
    "gn:feature_code":"PPL",
    "gn:name":"Hovtvyanchyk",
    "gn:population":0,
    "gn:timezone":"Europe/Kiev",
    "iso:country":"UA",
    "name:ukr_x_preferred":[
        "Hovtvyanchyk"
    ],
    "name:ukr_x_variant":[
        "\u0413\u043e\u0432\u0442\u0432\u044f\u043d\u0447\u0438\u043a"
    ],
    "wof:name":"Hovtvyanchyk",
    "wof:placetype":"locality"
},
  "geometry": {"coordinates":[34.46818,49.57029],"type":"Point"}
}