{
  "type": "Feature",
  "properties": {
    "gn:admin1_code":"2.0",
    "gn:asciiname":"Yasne",
    "gn:country_code":"UA",
    "gn:dem":169,
    "gn:feature_class":"P",
    "gn:feature_code":"PPL",
    "gn:name":"Yasne",
    "gn:population":0,
    "gn:timezone":"Europe/Kiev",
    "iso:country":"UA",
    "name:ukr_x_preferred":[
        "Yasne"
    ],
    "name:ukr_x_variant":[
        "\u042f\u0441\u043d\u0435",
        "Uzruy",
        "Uzrui"
    ],
    "name:und_x_variant":[
        "Uzrui",
        "Uzruy"
    ],
    "wof:name":"Yasne",
    "wof:placetype":"locality"
},
  "geometry": {"coordinates":[32.99389,52.1225],"type":"Point"}
}