{
  "type": "Feature",
  "properties": {
    "gn:admin1_code":"4.0",
    "gn:asciiname":"Dachne",
    "gn:country_code":"UA",
    "gn:dem":170,
    "gn:feature_class":"P",
    "gn:feature_code":"PPL",
    "gn:name":"Dachne",
    "gn:population":0,
    "gn:timezone":"Europe/Kiev",
    "iso:country":"UA",
    "name:deu_x_preferred":[
        "Datschnoje"
    ],
    "name:hye_x_preferred":[
        "\u0534\u0561\u0579\u0576\u0578\u0565"
    ],
    "name:rus_x_preferred":[
        "\u0414\u0430\u0447\u043d\u043e\u0435"
    ],
    "name:ukr_x_preferred":[
        "Dachne"
    ],
    "name:ukr_x_variant":[
        "\u0414\u0430\u0447\u043d\u0435"
    ],
    "name:und_x_variant":[
        "Dachnyy"
    ],
    "wof:name":"Dachne",
    "wof:placetype":"locality"
},
  "geometry": {"coordinates":[36.56667,48.21667],"type":"Point"}
}