{
  "type": "Feature",
  "properties": {
    "gn:admin1_code":"15.0",
    "gn:asciiname":"Stshalki",
    "gn:country_code":"UA",
    "gn:dem":308,
    "gn:feature_class":"P",
    "gn:feature_code":"PPL",
    "gn:name":"Stshalki",
    "gn:population":0,
    "gn:timezone":"Europe/Kiev",
    "iso:country":"UA",
    "wof:name":"Stshalki",
    "wof:placetype":"locality"
},
  "geometry": {"coordinates":[24.3151,49.63845],"type":"Point"}
}