{
  "type": "Feature",
  "properties": {
    "gn:admin1_code":"15.0",
    "gn:asciiname":"Stodilka",
    "gn:country_code":"UA",
    "gn:dem":574,
    "gn:feature_class":"P",
    "gn:feature_code":"PPL",
    "gn:name":"Stodilka",
    "gn:population":0,
    "gn:timezone":"Europe/Kiev",
    "iso:country":"UA",
    "name:ukr_x_preferred":[
        "Stodilka"
    ],
    "name:ukr_x_variant":[
        "\u0421\u0442\u043e\u0434\u0456\u043b\u043a\u0430"
    ],
    "name:und_x_variant":[
        "Studnevka",
        "Studnivka",
        "Stodolka"
    ],
    "wof:name":"Stodilka",
    "wof:placetype":"locality"
},
  "geometry": {"coordinates":[23.08124,49.18977],"type":"Point"}
}