{
  "type": "Feature",
  "properties": {
    "gn:admin1_code":"23.0",
    "gn:asciiname":"D'yakovka",
    "gn:country_code":"UA",
    "gn:dem":188,
    "gn:feature_class":"P",
    "gn:feature_code":"PPL",
    "gn:name":"D\u2019yakovka",
    "gn:population":0,
    "gn:timezone":"Europe/Kiev",
    "iso:country":"UA",
    "name:und_x_variant":[
        "D\u2019yakivka",
        "D\u2019yakovka"
    ],
    "wof:name":"D'yakovka",
    "wof:placetype":"locality"
},
  "geometry": {"coordinates":[29.925,48.47641],"type":"Point"}
}