{
  "type": "Feature",
  "properties": {
    "iso:country":"UA",
    "name:eng_x_preferred":[
        "Novodmytrivka"
    ],
    "name:ger_x_preferred":[
        "Nowodmytriwka"
    ],
    "name:lav_x_preferred":[
        "Novodmitrivka"
    ],
    "name:rum_x_preferred":[
        "Novodm\u00eetrivka"
    ],
    "name:rus_x_preferred":[
        "\u041d\u043e\u0432\u043e\u0434\u043c\u0438\u0442\u0440\u043e\u0432\u043a\u0430"
    ],
    "name:ukr_x_preferred":[
        "\u041d\u043e\u0432\u043e\u0434\u043c\u0438\u0442\u0440\u0456\u0432\u043a\u0430"
    ],
    "name:unk_x_variant":[
        "Novodmitrovka"
    ],
    "qs:a0":"\u0423\u043a\u0440\u0430\u0457\u043d\u0430",
    "qs:a1":"*\u0425\u0435\u0440\u0441\u043e\u043d\u0441\u044c\u043a\u0430",
    "qs:a1_alt":"Khersons'ka",
    "qs:a1r":"0",
    "qs:a2":"\u0413\u0435\u043d\u0456\u0447\u0435\u0441\u044c\u043a\u0438\u0439",
    "qs:a2_alt":"Heniches'kyi",
    "qs:adm0":"\u0423\u043a\u0440\u0430\u0457\u043d\u0430",
    "qs:la_lc":"*",
    "qs:level":"locality",
    "qs:loc":"\u041d\u043e\u0432\u043e\u0434\u043c\u0438\u0442\u0440\u0456\u0432\u043a\u0430",
    "qs:loc_alt":"Novodmytrivka",
    "qs:pop":0,
    "qs:type":"buffered point",
    "wof:name":"\u041d\u043e\u0432\u043e\u0434\u043c\u0438\u0442\u0440\u0456\u0432\u043a\u0430",
    "wof:placetype":"locality"
},
  "geometry": {"coordinates":[34.515016,46.202322],"type":"Point"}
}