{
  "type": "Feature",
  "properties": {
    "gn:admin1_code":"7.0",
    "gn:asciiname":"Rizdvyanka",
    "gn:country_code":"UA",
    "gn:dem":89,
    "gn:feature_class":"P",
    "gn:feature_code":"PPL",
    "gn:name":"Rizdvyanka",
    "gn:population":0,
    "gn:timezone":"Europe/Kiev",
    "iso:country":"UA",
    "name:ukr_x_preferred":[
        "\u0420\u0456\u0437\u0434\u0432\u044f\u043d\u043a\u0430"
    ],
    "name:und_x_variant":[
        "Rozhdestvenka",
        "Rozhdestvenskoye",
        "Rizdvyanka"
    ],
    "wof:name":"Rizdvyanka",
    "wof:placetype":"locality"
},
  "geometry": {"coordinates":[36.51666,49.06955],"type":"Point"}
}