{
  "type": "Feature",
  "properties": {
    "iso:country":"UA",
    "name:deu_x_preferred":[
        "Baltasariwka"
    ],
    "name:eng_x_preferred":[
        "Baltazarivka"
    ],
    "name:lav_x_preferred":[
        "Baltazarivka"
    ],
    "name:ron_x_preferred":[
        "Baltazarivka"
    ],
    "name:rus_x_preferred":[
        "\u0411\u0430\u043b\u0442\u0430\u0437\u0430\u0440\u043e\u0432\u043a\u0430"
    ],
    "name:ukr_x_preferred":[
        "\u0411\u0430\u043b\u0442\u0430\u0437\u0430\u0440\u0456\u0432\u043a\u0430"
    ],
    "name:und_x_variant":[
        "Karla Marksa"
    ],
    "name:zho_x_preferred":[
        "\u5df4\u723e\u5854\u624e\u91cc\u592b\u5361"
    ],
    "qs:a0":"\u0423\u043a\u0440\u0430\u0457\u043d\u0430",
    "qs:a1":"*\u0425\u0435\u0440\u0441\u043e\u043d\u0441\u044c\u043a\u0430",
    "qs:a1_alt":"Khersons'ka",
    "qs:a1r":"0",
    "qs:a2":"\u0427\u0430\u043f\u043b\u0438\u043d\u0441\u044c\u043a\u0438\u0439",
    "qs:a2_alt":"Chaplyns'kyi",
    "qs:adm0":"\u0423\u043a\u0440\u0430\u0457\u043d\u0430",
    "qs:la_lc":"*",
    "qs:level":"locality",
    "qs:loc":"\u0411\u0430\u043b\u0442\u0430\u0437\u0430\u0440\u0456\u0432\u043a\u0430",
    "qs:loc_alt":"Baltazarivka",
    "qs:pop":0,
    "qs:type":"buffered point",
    "wof:name":"\u0411\u0430\u043b\u0442\u0430\u0437\u0430\u0440\u0456\u0432\u043a\u0430",
    "wof:placetype":"locality"
},
  "geometry": {"coordinates":[33.407503,46.412376],"type":"Point"}
}