{
  "type": "Feature",
  "properties": {
    "gn:population":10393,
    "iso:country":"UA",
    "name:ara_x_preferred":[
        "\u0632\u064a\u0646\u0643\u064a\u0641"
    ],
    "name:bel_x_preferred":[
        "\u0417\u0456\u043d\u044c\u043a\u0456\u045e"
    ],
    "name:bel_x_variant":[
        "\u0417\u0435\u043d\u044c\u043a\u0430\u045e"
    ],
    "name:ceb_x_preferred":[
        "Zin'kiv"
    ],
    "name:ces_x_preferred":[
        "Zi\u0148kiv"
    ],
    "name:crh_x_preferred":[
        "Zinkiv"
    ],
    "name:deu_x_preferred":[
        "Sinkiw"
    ],
    "name:eng_x_preferred":[
        "Zin'kiv"
    ],
    "name:eng_x_variant":[
        "Zinkiv"
    ],
    "name:epo_x_preferred":[
        "Zinkiv"
    ],
    "name:est_x_preferred":[
        "Zinkiv"
    ],
    "name:fas_x_preferred":[
        "\u0632\u06cc\u0646\u06a9\u06cc\u0641"
    ],
    "name:fra_x_preferred":[
        "Zinkiv"
    ],
    "name:hsb_x_preferred":[
        "Zi\u0144kiw"
    ],
    "name:hye_x_preferred":[
        "\u0536\u0565\u0576\u056f\u0578\u057e"
    ],
    "name:ind_x_preferred":[
        "Zinkiv"
    ],
    "name:ita_x_preferred":[
        "Zin'kiv"
    ],
    "name:jpn_x_preferred":[
        "\u30b8\u30cb\u30ad\u30a6"
    ],
    "name:kat_x_preferred":[
        "\u10d6\u10d4\u10dc\u10d9\u10dd\u10d5\u10d8"
    ],
    "name:lav_x_preferred":[
        "Zi\u0146kiva"
    ],
    "name:nld_x_preferred":[
        "Zinkiv"
    ],
    "name:nno_x_preferred":[
        "Zinkiv"
    ],
    "name:pol_x_preferred":[
        "Zink\u00f3w"
    ],
    "name:por_x_preferred":[
        "Zinkiv"
    ],
    "name:ron_x_preferred":[
        "Zinkiv"
    ],
    "name:rus_x_preferred":[
        "\u0417\u0435\u043d\u044c\u043a\u043e\u0432"
    ],
    "name:sah_x_preferred":[
        "\u0417\u0438\u043d\u044c\u043a\u0438\u0432"
    ],
    "name:tat_x_preferred":[
        "\u0417\u0438\u043d\u043a\u0438\u0432"
    ],
    "name:ukr_x_preferred":[
        "\u0417\u0456\u043d\u044c\u043a\u0456\u0432"
    ],
    "name:und_x_variant":[
        "Zen\u2019kov"
    ],
    "name:vie_x_preferred":[
        "Zinkiv"
    ],
    "name:zho_x_preferred":[
        "\u6d25\u79d1\u592b"
    ],
    "qs:a0":"\u0423\u043a\u0440\u0430\u0457\u043d\u0430",
    "qs:a1":"*\u041f\u043e\u043b\u0442\u0430\u0432\u0441\u044c\u043a\u0430",
    "qs:a1_alt":"Poltavs'ka",
    "qs:a1r":"0",
    "qs:a2":"\u0417\u0456\u043d\u044c\u043a\u0456\u0432\u0441\u044c\u043a\u0438\u0439",
    "qs:a2_alt":"Zin'kivs'kyi",
    "qs:adm0":"\u0423\u043a\u0440\u0430\u0457\u043d\u0430",
    "qs:la_lc":"*",
    "qs:level":"locality",
    "qs:loc":"\u0417\u0456\u043d\u044c\u043a\u0456\u0432",
    "qs:loc_alt":"Zin'kiv",
    "qs:pop":0,
    "qs:type":"buffered point",
    "wd:wordcount":49,
    "wof:name":"\u0417\u0456\u043d\u044c\u043a\u0456\u0432",
    "wof:placetype":"locality",
    "wof:population":10393
},
  "geometry": {"coordinates":[34.366161,50.204487],"type":"Point"}
}