{
  "type": "Feature",
  "properties": {
    "gn:admin1_code":"24.0",
    "gn:asciiname":"Novouhruz'ke",
    "gn:country_code":"UA",
    "gn:dem":169,
    "gn:feature_class":"P",
    "gn:feature_code":"PPL",
    "gn:name":"Novouhruz\u2019ke",
    "gn:population":0,
    "gn:timezone":"Europe/Kiev",
    "iso:country":"UA",
    "name:ukr_x_preferred":[
        "Novouhruz\u2019ke"
    ],
    "name:ukr_x_variant":[
        "\u041d\u043e\u0432\u043e\u0443\u0433\u0440\u0443\u0437\u044c\u043a\u0435"
    ],
    "name:und_x_variant":[
        "Novougruzskoye"
    ],
    "wof:name":"Novouhruz'ke",
    "wof:placetype":"locality"
},
  "geometry": {"coordinates":[23.67329,51.32045],"type":"Point"}
}