{
  "type": "Feature",
  "properties": {
    "gn:admin1_code":"2.0",
    "gn:asciiname":"Dihtyarivka",
    "gn:country_code":"UA",
    "gn:dem":128,
    "gn:feature_class":"P",
    "gn:feature_code":"PPL",
    "gn:name":"Dihtyarivka",
    "gn:population":0,
    "gn:timezone":"Europe/Kiev",
    "iso:country":"UA",
    "name:eng_x_preferred":[
        "Degtyar\u00ebvka"
    ],
    "name:rus_x_preferred":[
        "\u0414\u0435\u0433\u0442\u044f\u0440\u0435\u0432\u043a\u0430"
    ],
    "name:ukr_x_preferred":[
        "Dihtyarivka"
    ],
    "name:ukr_x_variant":[
        "\u0414\u0456\u0433\u0442\u044f\u0440\u0456\u0432\u043a\u0430"
    ],
    "wof:name":"Dihtyarivka",
    "wof:placetype":"locality"
},
  "geometry": {"coordinates":[33.14145,51.92101],"type":"Point"}
}