{
  "type": "Feature",
  "properties": {
    "gn:admin1_code":"2.0",
    "gn:asciiname":"Halkiv",
    "gn:country_code":"UA",
    "gn:dem":160,
    "gn:feature_class":"P",
    "gn:feature_code":"PPL",
    "gn:name":"Halkiv",
    "gn:population":0,
    "gn:timezone":"Europe/Kiev",
    "iso:country":"UA",
    "name:ukr_x_preferred":[
        "Halkiv"
    ],
    "name:ukr_x_variant":[
        "\u0413\u0430\u043b\u043a\u0456\u0432"
    ],
    "name:und_x_variant":[
        "Galkov",
        "Galkovo"
    ],
    "wof:name":"Halkiv",
    "wof:placetype":"locality"
},
  "geometry": {"coordinates":[30.79917,51.69235],"type":"Point"}
}