{
  "type": "Feature",
  "properties": {
    "gn:admin1_code":"15.0",
    "gn:asciiname":"Ushkovichi",
    "gn:country_code":"UA",
    "gn:dem":280,
    "gn:feature_class":"P",
    "gn:feature_code":"PPL",
    "gn:name":"Ushkovichi",
    "gn:population":0,
    "gn:timezone":"Europe/Kiev",
    "iso:country":"UA",
    "name:und_x_variant":[
        "Ushkovitse",
        "Ushkovychi",
        "Ushkovichi"
    ],
    "wof:name":"Ushkovichi",
    "wof:placetype":"locality"
},
  "geometry": {"coordinates":[24.54422000000001,49.6426],"type":"Point"}
}