{
  "type": "Feature",
  "properties": {
    "gn:admin1_code":"14.0",
    "gn:asciiname":"Porichchya",
    "gn:country_code":"UA",
    "gn:dem":61,
    "gn:feature_class":"P",
    "gn:feature_code":"PPL",
    "gn:name":"Porichchya",
    "gn:population":0,
    "gn:timezone":"Europe/Zaporozhye",
    "iso:country":"UA",
    "name:rus_x_preferred":[
        "Porech\u2019ye"
    ],
    "name:ukr_x_preferred":[
        "Porichchya"
    ],
    "name:ukr_x_variant":[
        "\u041f\u043e\u0440\u0456\u0447\u0447\u044f"
    ],
    "wof:name":"Porichchya",
    "wof:placetype":"locality"
},
  "geometry": {"coordinates":[39.78973,48.26588],"type":"Point"}
}