{
  "type": "Feature",
  "properties": {
    "gn:admin1_code":"2.0",
    "gn:asciiname":"Vyly",
    "gn:country_code":"UA",
    "gn:dem":134,
    "gn:feature_class":"P",
    "gn:feature_code":"PPL",
    "gn:name":"Vyly",
    "gn:population":0,
    "gn:timezone":"Europe/Kiev",
    "iso:country":"UA",
    "name:ukr_x_preferred":[
        "Vyly"
    ],
    "name:ukr_x_variant":[
        "\u0412\u0438\u043b\u0438"
    ],
    "name:und_x_variant":[
        "Vily"
    ],
    "wof:name":"Vyly",
    "wof:placetype":"locality"
},
  "geometry": {"coordinates":[31.72889,50.75841],"type":"Point"}
}