{
  "type": "Feature",
  "properties": {
    "gn:admin1_code":"7.0",
    "gn:asciiname":"Lenins'ke",
    "gn:country_code":"UA",
    "gn:dem":143,
    "gn:feature_class":"P",
    "gn:feature_code":"PPL",
    "gn:name":"Lenins\u2019ke",
    "gn:population":0,
    "gn:timezone":"Europe/Kiev",
    "iso:country":"UA",
    "name:rus_x_preferred":[
        "Ul\u2019yanovka"
    ],
    "name:rus_x_variant":[
        "\u041b\u0435\u043d\u0438\u043d\u0441\u043a\u043e\u0435"
    ],
    "name:ukr_x_preferred":[
        "Lenins\u2019ke"
    ],
    "name:ukr_x_variant":[
        "\u041b\u0435\u043d\u0456\u043d\u0441\u044c\u043a\u0435"
    ],
    "name:und_x_variant":[
        "Leninskoye"
    ],
    "wof:name":"Lenins'ke",
    "wof:placetype":"locality"
},
  "geometry": {"coordinates":[36.01701,49.12585],"type":"Point"}
}