{
  "type": "Feature",
  "properties": {
    "iso:country":"UA",
    "name:che_x_preferred":[
        "\u0421\u0442\u0440\u0443\u043c\u043e\u043a"
    ],
    "name:crh_x_preferred":[
        "Strumok"
    ],
    "name:deu_x_preferred":[
        "Strumok"
    ],
    "name:eng_x_preferred":[
        "Strumok"
    ],
    "name:fin_x_preferred":[
        "Strum\u043ek"
    ],
    "name:lav_x_preferred":[
        "Strumoka"
    ],
    "name:nan_x_preferred":[
        "Strumok"
    ],
    "name:nno_x_preferred":[
        "Strumok"
    ],
    "name:nob_x_preferred":[
        "Strumok"
    ],
    "name:ron_x_preferred":[
        "Ci\u0219mele"
    ],
    "name:rus_x_preferred":[
        "\u0421\u0442\u0440\u0443\u043c\u043e\u043a"
    ],
    "name:spa_x_preferred":[
        "Strymok"
    ],
    "name:ukr_x_preferred":[
        "\u0421\u0442\u0440\u0443\u043c\u043e\u043a"
    ],
    "name:und_x_variant":[
        "Chishmele"
    ],
    "name:zho_x_preferred":[
        "\u65af\u7279\u9b6f\u83ab\u514b"
    ],
    "qs:a0":"\u0423\u043a\u0440\u0430\u0457\u043d\u0430",
    "qs:a1":"*\u041e\u0434\u0435\u0441\u044c\u043a\u0430",
    "qs:a1_alt":"Odes'ka",
    "qs:a1r":"0",
    "qs:a2":"\u0422\u0430\u0442\u0430\u0440\u0431\u0443\u043d\u0430\u0440\u0441\u044c\u043a\u0438\u0439",
    "qs:a2_alt":"Tatarbunars'kyi",
    "qs:adm0":"\u0423\u043a\u0440\u0430\u0457\u043d\u0430",
    "qs:la_lc":"*",
    "qs:level":"locality",
    "qs:loc":"\u0421\u0442\u0440\u0443\u043c\u043e\u043a",
    "qs:loc_alt":"Strumok",
    "qs:pop":0,
    "qs:type":"buffered point",
    "wof:name":"\u0421\u0442\u0440\u0443\u043c\u043e\u043a",
    "wof:placetype":"locality"
},
  "geometry": {"coordinates":[29.433956,45.719314],"type":"Point"}
}