{
  "type": "Feature",
  "properties": {
    "gn:admin1_code":"2.0",
    "gn:asciiname":"Sutoky",
    "gn:country_code":"UA",
    "gn:dem":129,
    "gn:feature_class":"P",
    "gn:feature_code":"PPL",
    "gn:name":"Sutoky",
    "gn:population":0,
    "gn:timezone":"Europe/Kiev",
    "iso:country":"UA",
    "name:ukr_x_preferred":[
        "Sutoky"
    ],
    "name:ukr_x_variant":[
        "\u0421\u0443\u0442\u043e\u043a\u0438"
    ],
    "name:und_x_variant":[
        "Sutoki"
    ],
    "wof:name":"Sutoky",
    "wof:placetype":"locality"
},
  "geometry": {"coordinates":[31.75045,52.00678],"type":"Point"}
}