{
  "type": "Feature",
  "properties": {
    "gn:admin1_code":"4.0",
    "gn:asciiname":"Petro-Svystunove",
    "gn:country_code":"UA",
    "gn:dem":59,
    "gn:feature_class":"P",
    "gn:feature_code":"PPL",
    "gn:name":"Petro-Svystunove",
    "gn:population":0,
    "gn:timezone":"Europe/Zaporozhye",
    "iso:country":"UA",
    "name:ukr_x_preferred":[
        "\u041f\u0435\u0442\u0440\u043e-\u0421\u0432\u0438\u0441\u0442\u0443\u043d\u043e\u0432\u0435"
    ],
    "name:und_x_variant":[
        "Petro-Svistunovo"
    ],
    "wof:name":"Petro-Svystunove",
    "wof:placetype":"locality"
},
  "geometry": {"coordinates":[35.18466,48.113],"type":"Point"}
}