{
  "type": "Feature",
  "properties": {
    "gn:admin1_code":"15.0",
    "gn:asciiname":"Bzhukhovitse",
    "gn:country_code":"UA",
    "gn:dem":258,
    "gn:feature_class":"P",
    "gn:feature_code":"PPL",
    "gn:name":"Bzhukhovitse",
    "gn:population":0,
    "gn:timezone":"Europe/Kiev",
    "iso:country":"UA",
    "wof:name":"Bzhukhovitse",
    "wof:placetype":"locality"
},
  "geometry": {"coordinates":[24.58333,49.58333],"type":"Point"}
}