{
  "type": "Feature",
  "properties": {
    "gn:admin1_code":"17.0",
    "gn:asciiname":"Poznanka-Persha",
    "gn:country_code":"UA",
    "gn:dem":104,
    "gn:feature_class":"P",
    "gn:feature_code":"PPL",
    "gn:name":"Poznanka-Persha",
    "gn:population":0,
    "gn:timezone":"Europe/Kiev",
    "iso:country":"UA",
    "name:ukr_x_preferred":[
        "Poznanka-Persha"
    ],
    "name:ukr_x_variant":[
        "\u041f\u043e\u0437\u043d\u0430\u043d\u043a\u0430 \u041f\u0435\u0440\u0448\u0430"
    ],
    "name:und_x_variant":[
        "Stalino",
        "Poznanna Pervaya",
        "Stalino Poznanka",
        "Poznanka Pervaya",
        "Poznanka"
    ],
    "wof:name":"Poznanka-Persha",
    "wof:placetype":"locality"
},
  "geometry": {"coordinates":[29.93716,47.92518],"type":"Point"}
}