{
  "type": "Feature",
  "properties": {
    "iso:country":"UA",
    "name:aze_x_preferred":[
        "\u0130zba"
    ],
    "name:bak_x_preferred":[
        "\u0423\u0440\u044b\u04ab \u04e9\u0439\u04e9"
    ],
    "name:bul_x_preferred":[
        "\u0420\u0443\u0441\u043a\u0430 \u043a\u044a\u0449\u0430"
    ],
    "name:cat_x_preferred":[
        "Isba"
    ],
    "name:cat_x_variant":[
        "isba"
    ],
    "name:chv_x_preferred":[
        "\u041f\u04f3\u0440\u0442"
    ],
    "name:deu_x_preferred":[
        "Izba"
    ],
    "name:ell_x_preferred":[
        "\u0399\u03b6\u03bc\u03c0\u03ac"
    ],
    "name:eng_x_preferred":[
        "Mazanka"
    ],
    "name:eng_x_variant":[
        "izba"
    ],
    "name:fra_x_preferred":[
        "Isba"
    ],
    "name:fra_x_variant":[
        "isba"
    ],
    "name:hye_x_preferred":[
        "\u056d\u0580\u0573\u056b\u0569"
    ],
    "name:ind_x_preferred":[
        "Rumah Izba"
    ],
    "name:ita_x_preferred":[
        "Isba"
    ],
    "name:ita_x_variant":[
        "isba"
    ],
    "name:jpn_x_preferred":[
        "\u6728\u9020\u306e\u6c11\u5bb6"
    ],
    "name:nld_x_preferred":[
        "Izba"
    ],
    "name:nld_x_variant":[
        "izba"
    ],
    "name:nno_x_preferred":[
        "rom"
    ],
    "name:pol_x_preferred":[
        "Izba"
    ],
    "name:pol_x_variant":[
        "izba"
    ],
    "name:por_x_preferred":[
        "Isb\u00e1"
    ],
    "name:por_x_variant":[
        "isb\u00e1"
    ],
    "name:rus_x_preferred":[
        "\u0418\u0437\u0431\u0430"
    ],
    "name:rus_x_variant":[
        "\u041c\u0430\u0437\u0430\u043d\u043a\u0430",
        "\u0438\u0437\u0431\u0430"
    ],
    "name:slk_x_preferred":[
        "Izba"
    ],
    "name:spa_x_preferred":[
        "Isba"
    ],
    "name:tat_x_preferred":[
        "\u042b\u0437\u0431\u0430"
    ],
    "name:tur_x_preferred":[
        "Izba"
    ],
    "name:ukr_x_preferred":[
        "\u041c\u0430\u0437\u0430\u043d\u043a\u0430"
    ],
    "name:ukr_x_variant":[
        "\u0406\u0437\u0431\u0430"
    ],
    "name:vie_x_preferred":[
        "Nh\u00e0 g\u1ed7 Nga"
    ],
    "qs:a0":"\u0423\u043a\u0440\u0430\u0457\u043d\u0430",
    "qs:a1":"*\u041a\u0440\u0438\u043c",
    "qs:a1_alt":"Krym",
    "qs:a1r":"0",
    "qs:a2":"\u0421\u0456\u043c\u0444\u0435\u0440\u043e\u043f\u043e\u043b\u044c\u0441\u044c\u043a\u0438\u0439",
    "qs:a2_alt":"Simferopol's'kyi",
    "qs:adm0":"\u0423\u043a\u0440\u0430\u0457\u043d\u0430",
    "qs:la_lc":"*",
    "qs:level":"locality",
    "qs:loc":"\u041c\u0430\u0437\u0430\u043d\u043a\u0430",
    "qs:loc_alt":"Mazanka",
    "qs:pop":0,
    "qs:type":"buffered point",
    "wd:wordcount":482,
    "wof:name":"\u041c\u0430\u0437\u0430\u043d\u043a\u0430",
    "wof:placetype":"locality"
},
  "geometry": {"coordinates":[34.255503,45.004226],"type":"Point"}
}