{
  "type": "Feature",
  "properties": {
    "gn:admin1_code":"21.0",
    "gn:asciiname":"Varvarovka",
    "gn:country_code":"UA",
    "gn:dem":154,
    "gn:feature_class":"P",
    "gn:feature_code":"PPL",
    "gn:name":"Varvarovka",
    "gn:population":0,
    "gn:timezone":"Europe/Kiev",
    "iso:country":"UA",
    "name:che_x_preferred":[
        "\u0412\u0430\u0440\u0432\u0430\u0440\u043e\u0432\u043a\u0430"
    ],
    "name:rus_x_preferred":[
        "\u0412\u0430\u0440\u0432\u0430\u0440\u043e\u0432\u043a\u0430"
    ],
    "wof:name":"Varvarovka",
    "wof:placetype":"locality"
},
  "geometry": {"coordinates":[35.48333,50.31667],"type":"Point"}
}