{
  "type": "Feature",
  "properties": {
    "iso:country":"UA",
    "qs:a0":"\u0423\u043a\u0440\u0430\u0457\u043d\u0430",
    "qs:a1":"*\u0425\u0435\u0440\u0441\u043e\u043d\u0441\u044c\u043a\u0430",
    "qs:a1_alt":"Khersons'ka",
    "qs:a1r":"0",
    "qs:a2":"\u0412\u0435\u043b\u0438\u043a\u043e\u043e\u043b\u0435\u043a\u0441\u0430\u043d\u0434\u0440\u0456\u0432\u0441\u044c\u043a\u0438\u0439",
    "qs:a2_alt":"Velykooleksandrivs'kyi",
    "qs:adm0":"\u0423\u043a\u0440\u0430\u0457\u043d\u0430",
    "qs:la_lc":"*",
    "qs:level":"locality",
    "qs:loc":"\u0411\u043e\u0440\u043e\u0437\u0435\u043d\u0441\u044c\u043a\u0435",
    "qs:loc_alt":"Borozens'ke",
    "qs:pop":0,
    "qs:type":"buffered point",
    "wof:name":"\u0411\u043e\u0440\u043e\u0437\u0435\u043d\u0441\u044c\u043a\u0435",
    "wof:placetype":"locality"
},
  "geometry": {"coordinates":[33.421513,47.173306],"type":"Point"}
}