{
  "type": "Feature",
  "properties": {
    "gn:admin1_code":"17.0",
    "gn:asciiname":"Prokhorovo",
    "gn:country_code":"UA",
    "gn:dem":21,
    "gn:feature_class":"P",
    "gn:feature_code":"PPL",
    "gn:name":"Prokhorovo",
    "gn:population":0,
    "gn:timezone":"Europe/Kiev",
    "iso:country":"UA",
    "wof:name":"Prokhorovo",
    "wof:placetype":"locality"
},
  "geometry": {"coordinates":[30.46722,47.00484],"type":"Point"}
}