{
  "type": "Feature",
  "properties": {
    "gn:admin1_code":"7.0",
    "gn:asciiname":"Pershotravneve",
    "gn:country_code":"UA",
    "gn:dem":172,
    "gn:feature_class":"P",
    "gn:feature_code":"PPL",
    "gn:name":"Pershotravneve",
    "gn:population":0,
    "gn:timezone":"Europe/Kiev",
    "iso:country":"UA",
    "name:ukr_x_preferred":[
        "Pershotravneve"
    ],
    "name:ukr_x_variant":[
        "\u041f\u0435\u0440\u0448\u043e\u0442\u0440\u0430\u0432\u043d\u0435\u0432\u0435"
    ],
    "name:und_x_variant":[
        "Manuylovka",
        "Getmanovka",
        "Pervaya Lipovka"
    ],
    "wof:name":"Pershotravneve",
    "wof:placetype":"locality"
},
  "geometry": {"coordinates":[37.91333,49.74063],"type":"Point"}
}