{
  "type": "Feature",
  "properties": {
    "gn:admin1_code":"18.0",
    "gn:asciiname":"Haymarivka",
    "gn:country_code":"UA",
    "gn:dem":72,
    "gn:feature_class":"P",
    "gn:feature_code":"PPL",
    "gn:name":"Haymarivka",
    "gn:population":0,
    "gn:timezone":"Europe/Kiev",
    "iso:country":"UA",
    "name:ukr_x_preferred":[
        "Haymarivka"
    ],
    "name:ukr_x_variant":[
        "\u0413\u0430\u0439\u043c\u0430\u0440\u0456\u0432\u043a\u0430"
    ],
    "wof:name":"Haymarivka",
    "wof:placetype":"locality"
},
  "geometry": {"coordinates":[34.23573,49.0291],"type":"Point"}
}