{
  "type": "Feature",
  "properties": {
    "gn:admin1_code":"27.0",
    "gn:asciiname":"Zbran'kivtsi",
    "gn:country_code":"UA",
    "gn:dem":142,
    "gn:feature_class":"P",
    "gn:feature_code":"PPL",
    "gn:name":"Zbran\u2019kivtsi",
    "gn:population":0,
    "gn:timezone":"Europe/Kiev",
    "iso:country":"UA",
    "name:rus_x_preferred":[
        "Zbran\u2019kovtsy"
    ],
    "name:ukr_x_preferred":[
        "Zbran\u2019kivtsi"
    ],
    "name:ukr_x_variant":[
        "\u0417\u0431\u0440\u0430\u043d\u044c\u043a\u0456\u0432\u0446\u0456"
    ],
    "wof:name":"Zbran'kivtsi",
    "wof:placetype":"locality"
},
  "geometry": {"coordinates":[29.04219,51.35777],"type":"Point"}
}