{
  "type": "Feature",
  "properties": {
    "gn:admin1_code":"10.0",
    "gn:asciiname":"Sverdlykove",
    "gn:country_code":"UA",
    "gn:dem":126,
    "gn:feature_class":"P",
    "gn:feature_code":"PPL",
    "gn:name":"Sverdlykove",
    "gn:population":0,
    "gn:timezone":"Europe/Kiev",
    "iso:country":"UA",
    "name:ukr_x_preferred":[
        "\u0421\u0432\u0435\u0440\u0434\u043b\u0438\u043a\u043e\u0432\u0435"
    ],
    "name:und_x_variant":[
        "Sverdlikovo"
    ],
    "wof:name":"Sverdlykove",
    "wof:placetype":"locality"
},
  "geometry": {"coordinates":[30.77635,48.71357],"type":"Point"}
}