{
  "type": "Feature",
  "properties": {
    "gn:admin1_code":"17.0",
    "gn:asciiname":"Sahaydak",
    "gn:country_code":"UA",
    "gn:dem":130,
    "gn:feature_class":"P",
    "gn:feature_code":"PPL",
    "gn:name":"Sahaydak",
    "gn:population":0,
    "gn:timezone":"Europe/Kiev",
    "iso:country":"UA",
    "name:ukr_x_preferred":[
        "Sahaydak"
    ],
    "name:und_x_variant":[
        "Sagaydak"
    ],
    "wof:name":"Sahaydak",
    "wof:placetype":"locality"
},
  "geometry": {"coordinates":[29.27657,47.62754],"type":"Point"}
}