{
  "type": "Feature",
  "properties": {
    "gn:admin1_code":"7.0",
    "gn:asciiname":"Zaliznychne",
    "gn:country_code":"UA",
    "gn:dem":148,
    "gn:feature_class":"P",
    "gn:feature_code":"PPL",
    "gn:name":"Zaliznychne",
    "gn:population":0,
    "gn:timezone":"Europe/Kiev",
    "iso:country":"UA",
    "name:ukr_x_preferred":[
        "Zaliznychne"
    ],
    "name:ukr_x_variant":[
        "\u0417\u0430\u043b\u0456\u0437\u043d\u0438\u0447\u043d\u0435"
    ],
    "wof:name":"Zaliznychne",
    "wof:placetype":"locality"
},
  "geometry": {"coordinates":[36.86634,49.72733],"type":"Point"}
}