{
  "type": "Feature",
  "properties": {
    "gn:admin1_code":"7.0",
    "gn:asciiname":"Zaliznychne",
    "gn:country_code":"UA",
    "gn:dem":148,
    "gn:feature_class":"P",
    "gn:feature_code":"PPL",
    "gn:name":"Zaliznychne",
    "gn:population":0,
    "gn:timezone":"Europe/Kiev",
    "iso:country":"UA",
    "name:bul_x_preferred":[
        "\u0417\u0430\u043b\u0438\u0437\u043d\u0438\u0447\u043d\u0435"
    ],
    "name:ceb_x_preferred":[
        "Zaliznychne"
    ],
    "name:crh_x_preferred":[
        "Zalizn\u0131\u00e7ne"
    ],
    "name:deu_x_preferred":[
        "Salisnytschne"
    ],
    "name:hye_x_preferred":[
        "\u0536\u0561\u056c\u056b\u0566\u0576\u056b\u0579\u0576\u0578\u0565"
    ],
    "name:pol_x_preferred":[
        "Zaliznyczne"
    ],
    "name:ron_x_preferred":[
        "Zalizn\u00eecine"
    ],
    "name:rus_x_preferred":[
        "\u0417\u0430\u043b\u0438\u0437\u043d\u0438\u0447\u043d\u043e\u0435"
    ],
    "name:ukr_x_preferred":[
        "Zaliznychne"
    ],
    "name:ukr_x_variant":[
        "\u0417\u0430\u043b\u0456\u0437\u043d\u0438\u0447\u043d\u0435"
    ],
    "name:zho_x_preferred":[
        "\u624e\u5229\u8332\u5c3c\u5947\u6d85"
    ],
    "wof:name":"Zaliznychne",
    "wof:placetype":"locality"
},
  "geometry": {"coordinates":[36.86634,49.72733],"type":"Point"}
}