{
  "type": "Feature",
  "properties": {
    "gn:admin1_code":"27.0",
    "gn:asciiname":"Druzhba",
    "gn:country_code":"UA",
    "gn:dem":213,
    "gn:feature_class":"P",
    "gn:feature_code":"PPL",
    "gn:name":"Druzhba",
    "gn:population":531,
    "gn:timezone":"Europe/Kiev",
    "iso:country":"UA",
    "name:ara_x_preferred":[
        "\u062f\u0631\u0648\u0632\u0647\u0628\u0627"
    ],
    "name:bel_x_preferred":[
        "\u0414\u0440\u0443\u0436\u0431\u0430"
    ],
    "name:ceb_x_preferred":[
        "Druzhba"
    ],
    "name:crh_x_preferred":[
        "Drujba"
    ],
    "name:deu_x_preferred":[
        "Druschba"
    ],
    "name:pol_x_preferred":[
        "Dru\u017cba"
    ],
    "name:ron_x_preferred":[
        "Drujba"
    ],
    "name:rus_x_preferred":[
        "\u0414\u0440\u0443\u0436\u0431\u0430"
    ],
    "name:sah_x_preferred":[
        "\u0414\u0440\u0443\u0436\u0431\u0430"
    ],
    "name:ukr_x_preferred":[
        "Druzhba"
    ],
    "name:ukr_x_variant":[
        "\u0414\u0440\u0443\u0436\u0431\u0430"
    ],
    "name:zho_x_preferred":[
        "\u5fb7\u9b6f\u65e5\u5df4"
    ],
    "wof:name":"Druzhba",
    "wof:placetype":"locality",
    "wof:population":531
},
  "geometry": {"coordinates":[27.97403,51.18768],"type":"Point"}
}