{
  "type": "Feature",
  "properties": {
    "gn:admin1_code":"15.0",
    "gn:asciiname":"Syn'kovychi",
    "gn:country_code":"UA",
    "gn:dem":224,
    "gn:feature_class":"P",
    "gn:feature_code":"PPL",
    "gn:name":"Syn\u2019kovychi",
    "gn:population":0,
    "gn:timezone":"Europe/Kiev",
    "iso:country":"UA",
    "name:rus_x_preferred":[
        "Sin\u2019kovichi"
    ],
    "name:ukr_x_preferred":[
        "Syn\u2019kovychi"
    ],
    "name:ukr_x_variant":[
        "\u0421\u0438\u043d\u044c\u043a\u043e\u0432\u0438\u0447\u0456"
    ],
    "name:und_x_variant":[
        "Se\u0144kowice",
        "Sen\u2019kovitse"
    ],
    "wof:name":"Syn'kovychi",
    "wof:placetype":"locality"
},
  "geometry": {"coordinates":[23.70976,50.24573],"type":"Point"}
}