{
  "type": "Feature",
  "properties": {
    "gn:admin1_code":"21.0",
    "gn:asciiname":"Zahirs'ke",
    "gn:country_code":"UA",
    "gn:dem":173,
    "gn:feature_class":"P",
    "gn:feature_code":"PPL",
    "gn:name":"Zahirs\u2019ke",
    "gn:population":0,
    "gn:timezone":"Europe/Kiev",
    "iso:country":"UA",
    "name:ukr_x_preferred":[
        "Zahirs\u2019ke"
    ],
    "name:ukr_x_variant":[
        "\u0417\u0430\u0433\u0456\u0440\u0441\u044c\u043a\u0435"
    ],
    "name:und_x_variant":[
        "Mikhaylovskiy",
        "Zagorskoye"
    ],
    "wof:name":"Zahirs'ke",
    "wof:placetype":"locality"
},
  "geometry": {"coordinates":[34.72902,50.9644],"type":"Point"}
}