{
  "type": "Feature",
  "properties": {
    "iso:country":"UA",
    "qs:a0":"\u0423\u043a\u0440\u0430\u0457\u043d\u0430",
    "qs:a1":"*\u041f\u043e\u043b\u0442\u0430\u0432\u0441\u044c\u043a\u0430",
    "qs:a1_alt":"Poltavs'ka",
    "qs:a1r":"0",
    "qs:a2":"\u0413\u043b\u043e\u0431\u0438\u043d\u0441\u044c\u043a\u0438\u0439",
    "qs:a2_alt":"Hlobyns'kyi",
    "qs:adm0":"\u0423\u043a\u0440\u0430\u0457\u043d\u0430",
    "qs:la_lc":"*",
    "qs:level":"locality",
    "qs:loc":"\u041f\u0443\u0441\u0442\u043e\u0432\u0456\u0439\u0442\u043e\u0432\u0435",
    "qs:loc_alt":"Pustoviitove",
    "qs:pop":0,
    "qs:type":"buffered point",
    "wof:name":"\u041f\u0443\u0441\u0442\u043e\u0432\u0456\u0439\u0442\u043e\u0432\u0435",
    "wof:placetype":"locality"
},
  "geometry": {"coordinates":[33.384097,49.326351],"type":"Point"}
}