{
  "type": "Feature",
  "properties": {
    "gn:admin1_code":"21.0",
    "gn:asciiname":"Sakunykha",
    "gn:country_code":"UA",
    "gn:dem":169,
    "gn:feature_class":"P",
    "gn:feature_code":"PPL",
    "gn:name":"Sakunykha",
    "gn:population":0,
    "gn:timezone":"Europe/Kiev",
    "iso:country":"UA",
    "name:eng_x_preferred":[
        "Sakunikha"
    ],
    "name:rus_x_preferred":[
        "\u0421\u0430\u043a\u0443\u043d\u0438\u0445\u0430"
    ],
    "name:ukr_x_preferred":[
        "Sakunykha"
    ],
    "name:ukr_x_variant":[
        "\u0421\u0430\u043a\u0443\u043d\u0438\u0445\u0430"
    ],
    "name:und_x_variant":[
        "Sakunovo"
    ],
    "wof:name":"Sakunykha",
    "wof:placetype":"locality"
},
  "geometry": {"coordinates":[33.87607,50.76651],"type":"Point"}
}