{
  "type": "Feature",
  "properties": {
    "gn:admin1_code":"7.0",
    "gn:asciiname":"Andriyivka",
    "gn:country_code":"UA",
    "gn:dem":83,
    "gn:feature_class":"P",
    "gn:feature_code":"PPL",
    "gn:name":"Andriyivka",
    "gn:population":0,
    "gn:timezone":"Europe/Kiev",
    "iso:country":"UA",
    "name:eng_x_preferred":[
        "Andreyevka"
    ],
    "name:rus_x_preferred":[
        "\u0410\u043d\u0434\u0440\u0435\u0435\u0432\u043a\u0430"
    ],
    "name:ukr_x_preferred":[
        "Andriyivka"
    ],
    "name:ukr_x_variant":[
        "\u0410\u043d\u0434\u0440\u0456\u0457\u0432\u043a\u0430"
    ],
    "name:und_x_variant":[
        "Andreyevka"
    ],
    "wof:name":"Andriyivka",
    "wof:placetype":"locality"
},
  "geometry": {"coordinates":[36.61959,49.53601],"type":"Point"}
}