{
  "type": "Feature",
  "properties": {
    "gn:admin1_code":"17.0",
    "gn:asciiname":"Demidovka",
    "gn:country_code":"UA",
    "gn:dem":40,
    "gn:feature_class":"P",
    "gn:feature_code":"PPL",
    "gn:name":"Demidovka",
    "gn:population":0,
    "gn:timezone":"Europe/Kiev",
    "iso:country":"UA",
    "name:und_x_variant":[
        "Davideni",
        "Demidovka",
        "Daviden\u2019"
    ],
    "wof:name":"Demidovka",
    "wof:placetype":"locality"
},
  "geometry": {"coordinates":[30.11667000000001,46.05],"type":"Point"}
}