{
  "type": "Feature",
  "properties": {
    "gn:admin1_code":"4.0",
    "gn:asciiname":"Nikolayevka",
    "gn:country_code":"UA",
    "gn:dem":79,
    "gn:feature_class":"P",
    "gn:feature_code":"PPL",
    "gn:name":"Nikolayevka",
    "gn:population":0,
    "gn:timezone":"Europe/Kiev",
    "iso:country":"UA",
    "name:eng_x_preferred":[
        "Nikolayevka"
    ],
    "name:rus_x_preferred":[
        "\u041d\u0438\u043a\u043e\u043b\u0430\u0435\u0432\u043a\u0430"
    ],
    "wof:name":"Nikolayevka",
    "wof:placetype":"locality"
},
  "geometry": {"coordinates":[36.30252,48.38401],"type":"Point"}
}