{
  "type": "Feature",
  "properties": {
    "gn:admin1_code":"26.0",
    "gn:asciiname":"Krutyy Yar",
    "gn:country_code":"UA",
    "gn:dem":142,
    "gn:feature_class":"P",
    "gn:feature_code":"PPL",
    "gn:name":"Krutyy Yar",
    "gn:population":0,
    "gn:timezone":"Europe/Zaporozhye",
    "iso:country":"UA",
    "name:ukr_x_preferred":[
        "Krutyy Yar"
    ],
    "name:ukr_x_variant":[
        "\u041a\u0440\u0443\u0442\u0438\u0439 \u042f\u0440"
    ],
    "name:und_x_variant":[
        "Krutoy Yar"
    ],
    "wof:name":"Krutyy Yar",
    "wof:placetype":"locality"
},
  "geometry": {"coordinates":[35.70083,48.06015],"type":"Point"}
}