{
  "type": "Feature",
  "properties": {
    "gn:admin1_code":"1.0",
    "gn:asciiname":"Shcherbynivka",
    "gn:country_code":"UA",
    "gn:dem":119,
    "gn:feature_class":"P",
    "gn:feature_code":"PPL",
    "gn:name":"Shcherbynivka",
    "gn:population":0,
    "gn:timezone":"Europe/Kiev",
    "iso:country":"UA",
    "name:ukr_x_preferred":[
        "Shcherbynivka"
    ],
    "name:ukr_x_variant":[
        "\u0429\u0435\u0440\u0431\u0438\u043d\u0456\u0432\u043a\u0430"
    ],
    "wof:name":"Shcherbynivka",
    "wof:placetype":"locality"
},
  "geometry": {"coordinates":[32.20064,49.67286],"type":"Point"}
}