{
  "type": "Feature",
  "properties": {
    "iso:country":"UA",
    "name:eng_x_preferred":[
        "Muzhiievo"
    ],
    "name:epo_x_preferred":[
        "Mu\u0135ijevo"
    ],
    "name:hun_x_preferred":[
        "Nagymuzsaly"
    ],
    "name:hun_x_variant":[
        "Nagy-Muzsaly"
    ],
    "name:hye_x_preferred":[
        "\u0544\u0578\u0582\u056a\u056b\u0587\u0578"
    ],
    "name:nld_x_preferred":[
        "Mu\u017cijewo"
    ],
    "name:pol_x_preferred":[
        "Mu\u017cijewo"
    ],
    "name:ron_x_preferred":[
        "Mujievo"
    ],
    "name:rus_x_preferred":[
        "\u041c\u0443\u0436\u0438\u0435\u0432\u043e"
    ],
    "name:ukr_x_preferred":[
        "\u041c\u0443\u0436\u0456\u0454\u0432\u043e"
    ],
    "name:und_x_variant":[
        "Velikoye Muzhiyovo"
    ],
    "name:zho_x_preferred":[
        "\u7a46\u65e5\u57c3\u6c83"
    ],
    "qs:a0":"\u0423\u043a\u0440\u0430\u0457\u043d\u0430",
    "qs:a1":"*\u0417\u0430\u043a\u0430\u0440\u043f\u0430\u0442\u0441\u044c\u043a\u0430",
    "qs:a1_alt":"Zakarpats'ka",
    "qs:a1r":"0",
    "qs:a2":"\u0411\u0435\u0440\u0435\u0433\u0456\u0432\u0441\u044c\u043a\u0438\u0439",
    "qs:a2_alt":"Berehivs'kyi",
    "qs:adm0":"\u0423\u043a\u0440\u0430\u0457\u043d\u0430",
    "qs:la_lc":"*",
    "qs:level":"locality",
    "qs:loc":"\u041c\u0443\u0436\u0456\u0454\u0432\u043e",
    "qs:loc_alt":"Muzhiievo",
    "qs:pop":0,
    "qs:type":"buffered point",
    "wof:name":"\u041c\u0443\u0436\u0456\u0454\u0432\u043e",
    "wof:placetype":"locality"
},
  "geometry": {"coordinates":[22.711096,48.178164],"type":"Point"}
}