{
  "type": "Feature",
  "properties": {
    "iso:country":"UA",
    "name:bel_x_preferred":[
        "\u0416\u0430\u043c\u0447\u0443\u0436\u044b\u043d\u0430"
    ],
    "name:eng_x_preferred":[
        "Zhemchuzhina"
    ],
    "name:eng_x_variant":[
        "La Perle"
    ],
    "name:fra_x_preferred":[
        "La Perle"
    ],
    "name:ita_x_preferred":[
        "La Perle"
    ],
    "name:rus_x_historical":[
        "\u0427\u043e\u0442\u044b\u0301"
    ],
    "name:rus_x_preferred":[
        "\u0427\u043e\u0442\u044b\u0301"
    ],
    "name:rus_x_variant":[
        "\u0416\u0435\u043c\u0447\u0443\u0436\u0438\u043d\u0430"
    ],
    "name:ukr_x_preferred":[
        "\u0416\u0435\u043c\u0447\u0443\u0436\u0438\u043d\u0430"
    ],
    "qs:a0":"\u0423\u043a\u0440\u0430\u0457\u043d\u0430",
    "qs:a1":"*\u041a\u0440\u0438\u043c",
    "qs:a1_alt":"Krym",
    "qs:a1r":"0",
    "qs:a2":"\u041d\u0438\u0436\u043d\u044c\u043e\u0433\u0456\u0440\u0441\u044c\u043a\u0438\u0439",
    "qs:a2_alt":"Nyzhn'ohirs'kyi",
    "qs:adm0":"\u0423\u043a\u0440\u0430\u0457\u043d\u0430",
    "qs:la_lc":"*",
    "qs:level":"locality",
    "qs:loc":"\u0416\u0435\u043c\u0447\u0443\u0436\u0438\u043d\u0430",
    "qs:loc_alt":"Zhemchuzhyna",
    "qs:pop":0,
    "qs:type":"buffered point",
    "wd:wordcount":1155,
    "wof:name":"\u0416\u0435\u043c\u0447\u0443\u0436\u0438\u043d\u0430",
    "wof:placetype":"locality"
},
  "geometry": {"coordinates":[34.65809,45.274689],"type":"Point"}
}