{
  "type": "Feature",
  "properties": {
    "gn:admin1_code":"22.0",
    "gn:asciiname":"Molchanovka",
    "gn:country_code":"UA",
    "gn:dem":352,
    "gn:feature_class":"P",
    "gn:feature_code":"PPL",
    "gn:name":"Molchanovka",
    "gn:population":0,
    "gn:timezone":"Europe/Kiev",
    "iso:country":"UA",
    "name:und_x_variant":[
        "Molchanuvka",
        "Molchanovka"
    ],
    "wof:name":"Molchanovka",
    "wof:placetype":"locality"
},
  "geometry": {"coordinates":[26.0323,49.52295],"type":"Point"}
}