{
  "type": "Feature",
  "properties": {
    "gn:admin1_code":"26.0",
    "gn:asciiname":"Velykodubove",
    "gn:country_code":"UA",
    "gn:dem":96,
    "gn:feature_class":"P",
    "gn:feature_code":"PPL",
    "gn:name":"Velykodubove",
    "gn:population":0,
    "gn:timezone":"Europe/Zaporozhye",
    "iso:country":"UA",
    "name:ukr_x_preferred":[
        "Velykodubove"
    ],
    "name:ukr_x_variant":[
        "\u0412\u0435\u043b\u0438\u043a\u043e\u0434\u0443\u0431\u043e\u0432\u0435"
    ],
    "name:und_x_variant":[
        "Velikodubovoye"
    ],
    "wof:name":"Velykodubove",
    "wof:placetype":"locality"
},
  "geometry": {"coordinates":[35.26495999999999,48.09334000000001],"type":"Point"}
}