{
  "type": "Feature",
  "properties": {
    "gn:admin1_code":"19.0",
    "gn:asciiname":"Obirky",
    "gn:country_code":"UA",
    "gn:dem":145,
    "gn:feature_class":"P",
    "gn:feature_code":"PPL",
    "gn:name":"Obirky",
    "gn:population":0,
    "gn:timezone":"Europe/Kiev",
    "iso:country":"UA",
    "name:ukr_x_preferred":[
        "Obirky"
    ],
    "name:ukr_x_variant":[
        "\u041e\u0431\u0456\u0440\u043a\u0438"
    ],
    "name:und_x_variant":[
        "Obirki"
    ],
    "wof:name":"Obirky",
    "wof:placetype":"locality"
},
  "geometry": {"coordinates":[26.66461,51.35561],"type":"Point"}
}