{
  "type": "Feature",
  "properties": {
    "gn:admin1_code":"21.0",
    "gn:asciiname":"Velyki Budky",
    "gn:country_code":"UA",
    "gn:dem":122,
    "gn:feature_class":"P",
    "gn:feature_code":"PPL",
    "gn:name":"Velyki Budky",
    "gn:population":0,
    "gn:timezone":"Europe/Kiev",
    "iso:country":"UA",
    "name:ukr_x_preferred":[
        "Velyki Budky"
    ],
    "name:ukr_x_variant":[
        "\u0412\u0435\u043b\u0438\u043a\u0456 \u0411\u0443\u0434\u043a\u0438"
    ],
    "name:und_x_variant":[
        "Velikiye Budki"
    ],
    "wof:name":"Velyki Budky",
    "wof:placetype":"locality"
},
  "geometry": {"coordinates":[33.60051,50.80786],"type":"Point"}
}