{
  "type": "Feature",
  "properties": {
    "gn:admin1_code":"27.0",
    "gn:asciiname":"Hlukhova",
    "gn:country_code":"UA",
    "gn:dem":178,
    "gn:feature_class":"P",
    "gn:feature_code":"PPL",
    "gn:name":"Hlukhova",
    "gn:population":0,
    "gn:timezone":"Europe/Kiev",
    "iso:country":"UA",
    "name:ukr_x_preferred":[
        "Hlukhova"
    ],
    "name:ukr_x_variant":[
        "\u0413\u043b\u0443\u0445\u043e\u0432\u0430"
    ],
    "name:und_x_variant":[
        "Glukhova"
    ],
    "wof:name":"Hlukhova",
    "wof:placetype":"locality"
},
  "geometry": {"coordinates":[28.39195,51.05501],"type":"Point"}
}