{
  "type": "Feature",
  "properties": {
    "gn:admin1_code":"4.0",
    "gn:asciiname":"Vozvratne",
    "gn:country_code":"UA",
    "gn:dem":87,
    "gn:feature_class":"P",
    "gn:feature_code":"PPL",
    "gn:name":"Vozvratne",
    "gn:population":0,
    "gn:timezone":"Europe/Kiev",
    "iso:country":"UA",
    "name:ukr_x_preferred":[
        "Vozvratne"
    ],
    "name:ukr_x_variant":[
        "\u0412\u043e\u0437\u0432\u0440\u0430\u0442\u043d\u0435"
    ],
    "name:und_x_variant":[
        "Vozvratnoye"
    ],
    "wof:name":"Vozvratne",
    "wof:placetype":"locality"
},
  "geometry": {"coordinates":[35.75767000000001,48.28489],"type":"Point"}
}