{
  "type": "Feature",
  "properties": {
    "gn:population":6369,
    "iso:country":"UA",
    "name:ara_x_preferred":[
        "\u0632\u0647\u0648\u0631\u064a\u0641\u0643\u0627"
    ],
    "name:bel_x_variant":[
        "\u0417\u0433\u0443\u0440\u0430\u045e\u043a\u0430"
    ],
    "name:chi_x_preferred":[
        "\u8332\u53e4\u91cc\u592b\u5361"
    ],
    "name:crh_x_preferred":[
        "Zgurivka"
    ],
    "name:deu_x_preferred":[
        "Shuriwka"
    ],
    "name:eng_x_preferred":[
        "Zhurivka"
    ],
    "name:ger_x_preferred":[
        "Shuriwka"
    ],
    "name:pol_x_preferred":[
        "Zhuriwka"
    ],
    "name:ron_x_preferred":[
        "Zhurivka"
    ],
    "name:rum_x_preferred":[
        "Zhurivka"
    ],
    "name:rus_x_preferred":[
        "\u0417\u0433\u0443\u0440\u043e\u0432\u043a\u0430"
    ],
    "name:rus_x_variant":[
        "\u0417\u0433\u0443\u0440\u0456\u0432\u043a\u0430"
    ],
    "name:sah_x_preferred":[
        "\u0417\u0433\u0443\u0440\u043e\u0432\u043a\u0430"
    ],
    "name:sco_x_preferred":[
        "Zghurivka"
    ],
    "name:ukr_x_preferred":[
        "\u0417\u0433\u0443\u0440\u0456\u0432\u043a\u0430"
    ],
    "name:ukr_x_variant":[
        "Z\u00b7hurivka"
    ],
    "name:unk_x_variant":[
        "Zgurovka"
    ],
    "name:zho_x_preferred":[
        "\u8332\u53e4\u91cc\u592b\u5361"
    ],
    "qs:a0":"\u0423\u043a\u0440\u0430\u0457\u043d\u0430",
    "qs:a1":"*\u041a\u0438\u0457\u0432\u0441\u044c\u043a\u0430",
    "qs:a1_alt":"Kyivs'ka",
    "qs:a1r":"0",
    "qs:a2":"\u0417\u0433\u0443\u0440\u0456\u0432\u0441\u044c\u043a\u0438\u0439",
    "qs:a2_alt":"Zghurivs'kyi",
    "qs:adm0":"\u0423\u043a\u0440\u0430\u0457\u043d\u0430",
    "qs:la_lc":"*",
    "qs:level":"locality",
    "qs:loc":"\u0417\u0433\u0443\u0440\u0456\u0432\u043a\u0430",
    "qs:loc_alt":"Zghurivka",
    "qs:pop":0,
    "qs:type":"buffered point",
    "wd:wordcount":73,
    "wof:name":"\u0417\u0433\u0443\u0440\u0456\u0432\u043a\u0430",
    "wof:placetype":"locality",
    "wof:population":6369
},
  "geometry": {"coordinates":[31.771742,50.491966],"type":"Point"}
}