{
  "type": "Feature",
  "properties": {
    "gn:admin1_code":"5.0",
    "gn:asciiname":"Kyselivka",
    "gn:country_code":"UA",
    "gn:dem":109,
    "gn:feature_class":"P",
    "gn:feature_code":"PPL",
    "gn:name":"Kyselivka",
    "gn:population":0,
    "gn:timezone":"Europe/Kiev",
    "iso:country":"UA",
    "name:rus_x_preferred":[
        "Kisel\u00ebvka"
    ],
    "name:ukr_x_preferred":[
        "Kyselivka"
    ],
    "name:ukr_x_variant":[
        "\u041a\u0438\u0441\u0435\u043b\u0456\u0432\u043a\u0430"
    ],
    "wof:name":"Kyselivka",
    "wof:placetype":"locality"
},
  "geometry": {"coordinates":[38.46009,47.75145],"type":"Point"}
}