{
  "type": "Feature",
  "properties": {
    "iso:country":"UA",
    "qs:a0":"\u0423\u043a\u0440\u0430\u0457\u043d\u0430",
    "qs:a1":"*\u041b\u044c\u0432\u0456\u0432\u0441\u044c\u043a\u0430",
    "qs:a1_alt":"L'vivs'ka",
    "qs:a1r":"0",
    "qs:a2":"\u0421\u0442\u0440\u0438\u0439\u0441\u044c\u043a\u0438\u0439",
    "qs:a2_alt":"Stryis'kyi",
    "qs:adm0":"\u0423\u043a\u0440\u0430\u0457\u043d\u0430",
    "qs:la_lc":"*",
    "qs:level":"locality",
    "qs:loc":"\u0414\u0430\u0448\u0430\u0432\u0430",
    "qs:loc_alt":"Dashava",
    "qs:pop":0,
    "qs:type":"buffered point",
    "wof:name":"\u0414\u0430\u0448\u0430\u0432\u0430",
    "wof:placetype":"locality"
},
  "geometry": {"coordinates":[24.001713,49.260045],"type":"Point"}
}