{
  "type": "Feature",
  "properties": {
    "gn:admin1_code":"18.0",
    "gn:asciiname":"Dudnykove",
    "gn:country_code":"UA",
    "gn:dem":89,
    "gn:feature_class":"P",
    "gn:feature_code":"PPL",
    "gn:name":"Dudnykove",
    "gn:population":0,
    "gn:timezone":"Europe/Kiev",
    "iso:country":"UA",
    "name:ukr_x_preferred":[
        "Dudnykove"
    ],
    "name:ukr_x_variant":[
        "\u0414\u0443\u0434\u043d\u0438\u043a\u043e\u0432\u0435"
    ],
    "wof:name":"Dudnykove",
    "wof:placetype":"locality"
},
  "geometry": {"coordinates":[34.81133,49.62103],"type":"Point"}
}