{
  "type": "Feature",
  "properties": {
    "gn:admin1_code":"24.0",
    "gn:asciiname":"Kupychiv",
    "gn:country_code":"UA",
    "gn:dem":200,
    "gn:feature_class":"P",
    "gn:feature_code":"PPL",
    "gn:name":"Kupychiv",
    "gn:population":0,
    "gn:timezone":"Europe/Kiev",
    "iso:country":"UA",
    "name:bel_x_preferred":[
        "\u041a\u0443\u043f\u044b\u0447\u044b\u045e"
    ],
    "name:deu_x_preferred":[
        "Kupytschiw"
    ],
    "name:hye_x_preferred":[
        "\u053f\u0578\u0582\u057a\u056b\u0579\u0587"
    ],
    "name:pol_x_preferred":[
        "Kupicz\u00f3w"
    ],
    "name:ron_x_preferred":[
        "Kup\u00eeciv"
    ],
    "name:rus_x_preferred":[
        "\u041a\u0443\u043f\u0438\u0447\u0435\u0432"
    ],
    "name:ukr_x_preferred":[
        "Kupychiv"
    ],
    "name:ukr_x_variant":[
        "\u041a\u0443\u043f\u0438\u0447\u0456\u0432"
    ],
    "name:und_x_variant":[
        "Kupichuv",
        "Kupichov",
        "Kupichev"
    ],
    "name:zho_x_preferred":[
        "\u5eab\u76ae\u5947\u592b"
    ],
    "wof:name":"Kupychiv",
    "wof:placetype":"locality"
},
  "geometry": {"coordinates":[24.71564,50.99426],"type":"Point"}
}