{
  "type": "Feature",
  "properties": {
    "iso:country":"UA",
    "name:cat_x_preferred":[
        "Kuqa"
    ],
    "name:deu_x_preferred":[
        "Kuqa"
    ],
    "name:fra_x_preferred":[
        "Kucha"
    ],
    "name:jpn_x_preferred":[
        "\u30af\u30c1\u30e3\u770c"
    ],
    "name:kir_x_preferred":[
        "\u041a\u0443\u0447\u0430 \u0448\u0430\u0430\u0440\u044b"
    ],
    "name:kor_x_preferred":[
        "\ucfe0\ucc98 \ud604"
    ],
    "name:nor_x_preferred":[
        "Kucha"
    ],
    "name:rus_x_preferred":[
        "\u041a\u0443\u0447\u0430"
    ],
    "name:swe_x_preferred":[
        "Kuchar"
    ],
    "name:tur_x_preferred":[
        "Ku\u00e7ar \u0130l\u00e7esi"
    ],
    "name:uig_x_preferred":[
        "\u0643\u06c7\u0686\u0627\u0631 \u0646\u0627\u06be\u0649\u064a\u0649\u0633\u0649"
    ],
    "name:urd_x_preferred":[
        "\u06a9\u0648\u0686\u0627 \u06a9\u0627\u0624\u0646\u0679\u06cc"
    ],
    "name:uzb_x_preferred":[
        "Kuchar"
    ],
    "name:vie_x_preferred":[
        "Kuchar"
    ],
    "name:zho_x_preferred":[
        "\u5e93\u8f66\u53bf"
    ],
    "qs:a0":"\u0423\u043a\u0440\u0430\u0457\u043d\u0430",
    "qs:a1":"*\u0425\u043c\u0435\u043b\u044c\u043d\u0438\u0446\u044c\u043a\u0430",
    "qs:a1_alt":"Khmel'nyts'ka",
    "qs:a1r":"0",
    "qs:a2":"\u041d\u043e\u0432\u043e\u0443\u0448\u0438\u0446\u044c\u043a\u0438\u0439",
    "qs:a2_alt":"Novoushyts'kyi",
    "qs:adm0":"\u0423\u043a\u0440\u0430\u0457\u043d\u0430",
    "qs:la_lc":"*",
    "qs:level":"locality",
    "qs:loc":"\u041a\u0443\u0447\u0430",
    "qs:loc_alt":"Kucha",
    "qs:pop":0,
    "qs:type":"buffered point",
    "wd:wordcount":339,
    "wof:name":"\u041a\u0443\u0447\u0430",
    "wof:placetype":"locality"
},
  "geometry": {"coordinates":[27.263657,48.76788],"type":"Point"}
}