{
  "type": "Feature",
  "properties": {
    "gn:admin1_code":"15.0",
    "gn:asciiname":"Mosty",
    "gn:country_code":"UA",
    "gn:dem":260,
    "gn:feature_class":"P",
    "gn:feature_code":"PPL",
    "gn:name":"Mosty",
    "gn:population":0,
    "gn:timezone":"Europe/Kiev",
    "iso:country":"UA",
    "name:ukr_x_preferred":[
        "Mosty"
    ],
    "name:ukr_x_variant":[
        "\u041c\u043e\u0441\u0442\u0438"
    ],
    "wof:name":"Mosty",
    "wof:placetype":"locality"
},
  "geometry": {"coordinates":[23.65367,49.54052],"type":"Point"}
}