{
  "type": "Feature",
  "properties": {
    "gn:admin1_code":"17.0",
    "gn:asciiname":"Markivka",
    "gn:country_code":"UA",
    "gn:dem":29,
    "gn:feature_class":"P",
    "gn:feature_code":"PPL",
    "gn:name":"Markivka",
    "gn:population":0,
    "gn:timezone":"Europe/Kiev",
    "iso:country":"UA",
    "name:ukr_x_preferred":[
        "Markivka"
    ],
    "name:ukr_x_variant":[
        "\u041c\u0430\u0440\u043a\u0456\u0432\u043a\u0430"
    ],
    "name:und_x_variant":[
        "Naksiya",
        "Markovka"
    ],
    "wof:name":"Markivka",
    "wof:placetype":"locality"
},
  "geometry": {"coordinates":[29.94974,46.92876],"type":"Point"}
}