{
  "type": "Feature",
  "properties": {
    "gn:admin1_code":"3.0",
    "gn:asciiname":"Mosoreni",
    "gn:country_code":"UA",
    "gn:dem":142,
    "gn:feature_class":"P",
    "gn:feature_code":"PPL",
    "gn:name":"Mosoreni",
    "gn:population":0,
    "gn:timezone":"Europe/Kiev",
    "iso:country":"UA",
    "name:und_x_variant":[
        "Mosoruvka",
        "Mosoreni"
    ],
    "wof:name":"Mosoreni",
    "wof:placetype":"locality"
},
  "geometry": {"coordinates":[26.03637,48.62878],"type":"Point"}
}