{
  "type": "Feature",
  "properties": {
    "gn:admin1_code":"23.0",
    "gn:asciiname":"Sadkivtsi",
    "gn:country_code":"UA",
    "gn:dem":240,
    "gn:feature_class":"P",
    "gn:feature_code":"PPL",
    "gn:name":"Sadkivtsi",
    "gn:population":0,
    "gn:timezone":"Europe/Kiev",
    "iso:country":"UA",
    "name:ukr_x_preferred":[
        "\u0421\u0430\u0434\u043a\u0456\u0432\u0446\u0456"
    ],
    "name:und_x_variant":[
        "Sadkovtsy"
    ],
    "wof:name":"Sadkivtsi",
    "wof:placetype":"locality"
},
  "geometry": {"coordinates":[28.23264,48.62963],"type":"Point"}
}