{
  "type": "Feature",
  "properties": {
    "gn:admin1_code":"27.0",
    "gn:asciiname":"Hlezne",
    "gn:country_code":"UA",
    "gn:dem":231,
    "gn:feature_class":"P",
    "gn:feature_code":"PPL",
    "gn:name":"Hlezne",
    "gn:population":0,
    "gn:timezone":"Europe/Kiev",
    "iso:country":"UA",
    "name:ukr_x_preferred":[
        "Hlezne"
    ],
    "name:ukr_x_variant":[
        "\u0413\u043b\u0435\u0437\u043d\u0435"
    ],
    "name:und_x_variant":[
        "Glezno"
    ],
    "wof:name":"Hlezne",
    "wof:placetype":"locality"
},
  "geometry": {"coordinates":[27.7079,49.97874],"type":"Point"}
}