{
  "type": "Feature",
  "properties": {
    "gn:admin1_code":"27.0",
    "gn:asciiname":"Velyki Korovyntsi",
    "gn:country_code":"UA",
    "gn:dem":261,
    "gn:feature_class":"P",
    "gn:feature_code":"PPL",
    "gn:name":"Velyki Korovyntsi",
    "gn:population":0,
    "gn:timezone":"Europe/Kiev",
    "iso:country":"UA",
    "name:ukr_x_preferred":[
        "Velyki Korovyntsi"
    ],
    "name:ukr_x_variant":[
        "\u0412\u0435\u043b\u0438\u043a\u0456 \u041a\u043e\u0440\u043e\u0432\u0438\u043d\u0446\u0456"
    ],
    "name:und_x_variant":[
        "Bol\u2019shiye Korovintsy",
        "Velikiye Korovintsy"
    ],
    "wof:name":"Velyki Korovyntsi",
    "wof:placetype":"locality"
},
  "geometry": {"coordinates":[28.29531,49.98197],"type":"Point"}
}