{
  "type": "Feature",
  "properties": {
    "gn:admin1_code":"27.0",
    "gn:asciiname":"Velyki Korovyntsi",
    "gn:country_code":"UA",
    "gn:dem":261,
    "gn:feature_class":"P",
    "gn:feature_code":"PPL",
    "gn:name":"Velyki Korovyntsi",
    "gn:population":0,
    "gn:timezone":"Europe/Kiev",
    "iso:country":"UA",
    "name:ara_x_preferred":[
        "\u0641\u064a\u0644\u064a\u0643\u064a \u0643\u0648\u0631\u0648\u0641\u064a\u0646\u062a\u0633\u064a"
    ],
    "name:crh_x_preferred":[
        "Vel\u0131ki Korov\u0131ntsi"
    ],
    "name:deu_x_preferred":[
        "Welyki Korowynzi"
    ],
    "name:fra_x_preferred":[
        "Velyki Korovyntsi"
    ],
    "name:hye_x_preferred":[
        "\u054e\u0565\u056c\u056b\u056f\u056b\u0565 \u053f\u0578\u0580\u0578\u057e\u056b\u0576\u0581\u056b"
    ],
    "name:pol_x_preferred":[
        "We\u0142yki Korowynci"
    ],
    "name:ron_x_preferred":[
        "Vel\u00eeki Korov\u00een\u021bi"
    ],
    "name:rus_x_preferred":[
        "\u0412\u0435\u043b\u0438\u043a\u0438\u0435 \u041a\u043e\u0440\u043e\u0432\u0438\u043d\u0446\u044b"
    ],
    "name:sah_x_preferred":[
        "\u0412\u0435\u043b\u0438\u043a\u0438\u0435 \u041a\u043e\u0440\u043e\u0432\u0438\u043d\u0446\u044b"
    ],
    "name:ukr_x_preferred":[
        "Velyki Korovyntsi"
    ],
    "name:ukr_x_variant":[
        "\u0412\u0435\u043b\u0438\u043a\u0456 \u041a\u043e\u0440\u043e\u0432\u0438\u043d\u0446\u0456"
    ],
    "name:und_x_variant":[
        "Bol\u2019shiye Korovintsy",
        "Velikiye Korovintsy"
    ],
    "name:zho_x_preferred":[
        "\u5927\u79d1\u7f85\u6eab\u9f4a"
    ],
    "wof:name":"Velyki Korovyntsi",
    "wof:placetype":"locality"
},
  "geometry": {"coordinates":[28.29531,49.98197],"type":"Point"}
}