{
  "type": "Feature",
  "properties": {
    "gn:admin1_code":"23.0",
    "gn:asciiname":"Makhnivka",
    "gn:country_code":"UA",
    "gn:dem":290,
    "gn:feature_class":"P",
    "gn:feature_code":"PPL",
    "gn:name":"Makhnivka",
    "gn:population":0,
    "gn:timezone":"Europe/Kiev",
    "iso:country":"UA",
    "name:ukr_x_preferred":[
        "\u041c\u0430\u0445\u043d\u0456\u0432\u043a\u0430"
    ],
    "name:ukr_x_variant":[
        "Krasne",
        "\u041a\u0440\u0430\u0441\u043d\u0435"
    ],
    "name:und_x_variant":[
        "Krasnoye"
    ],
    "wof:name":"Makhnivka",
    "wof:placetype":"locality"
},
  "geometry": {"coordinates":[28.15339,49.19114],"type":"Point"}
}