{
  "type": "Feature",
  "properties": {
    "gn:admin1_code":"24.0",
    "gn:asciiname":"Ezyurko",
    "gn:country_code":"UA",
    "gn:dem":158,
    "gn:feature_class":"P",
    "gn:feature_code":"PPL",
    "gn:name":"Ezyurko",
    "gn:population":0,
    "gn:timezone":"Europe/Kiev",
    "iso:country":"UA",
    "wof:name":"Ezyurko",
    "wof:placetype":"locality"
},
  "geometry": {"coordinates":[25.03333,51.63333],"type":"Point"}
}