{
  "type": "Feature",
  "properties": {
    "gn:admin1_code":"19.0",
    "gn:asciiname":"Urichchya",
    "gn:country_code":"UA",
    "gn:dem":153,
    "gn:feature_class":"P",
    "gn:feature_code":"PPL",
    "gn:name":"Urichchya",
    "gn:population":0,
    "gn:timezone":"Europe/Kiev",
    "iso:country":"UA",
    "name:rus_x_preferred":[
        "Urech\u2019ye"
    ],
    "name:ukr_x_preferred":[
        "Urichchya"
    ],
    "name:ukr_x_variant":[
        "\u0423\u0440\u0456\u0447\u0447\u044f"
    ],
    "wof:name":"Urichchya",
    "wof:placetype":"locality"
},
  "geometry": {"coordinates":[25.91759,51.58083],"type":"Point"}
}