{
  "type": "Feature",
  "properties": {
    "gn:admin1_code":"27.0",
    "gn:asciiname":"Serninki",
    "gn:country_code":"UA",
    "gn:dem":154,
    "gn:feature_class":"P",
    "gn:feature_code":"PPL",
    "gn:name":"Serninki",
    "gn:population":0,
    "gn:timezone":"Europe/Kiev",
    "iso:country":"UA",
    "wof:name":"Serninki",
    "wof:placetype":"locality"
},
  "geometry": {"coordinates":[28.83333,51.25],"type":"Point"}
}