{
  "type": "Feature",
  "properties": {
    "gn:admin1_code":"15.0",
    "gn:asciiname":"Babichi",
    "gn:country_code":"UA",
    "gn:dem":215,
    "gn:feature_class":"P",
    "gn:feature_code":"PPL",
    "gn:name":"Babichi",
    "gn:population":0,
    "gn:timezone":"Europe/Kiev",
    "iso:country":"UA",
    "name:und_x_variant":[
        "Babicze",
        "Babiche",
        "Babichi"
    ],
    "wof:name":"Babichi",
    "wof:placetype":"locality"
},
  "geometry": {"coordinates":[24.51531,50.2085],"type":"Point"}
}