{
  "type": "Feature",
  "properties": {
    "gn:population":4090,
    "iso:country":"UA",
    "name:ara_x_preferred":[
        "\u0628\u064a\u0631\u064a\u0632\u0627\u0646\u0643\u0627"
    ],
    "name:bel_x_variant":[
        "\u0411\u0435\u0440\u0430\u0437\u0430\u043d\u043a\u0430"
    ],
    "name:bul_x_preferred":[
        "\u0411\u0435\u0440\u0435\u0437\u0430\u043d\u043a\u0430"
    ],
    "name:ceb_x_preferred":[
        "Berezanka"
    ],
    "name:crh_x_preferred":[
        "Berezanka"
    ],
    "name:deu_x_preferred":[
        "Beresanka"
    ],
    "name:eng_x_preferred":[
        "Berezanka"
    ],
    "name:hye_x_preferred":[
        "\u0532\u0565\u0580\u0565\u0566\u0561\u0576\u056f\u0561"
    ],
    "name:lav_x_preferred":[
        "Berezanka"
    ],
    "name:pol_x_preferred":[
        "Berezanka"
    ],
    "name:ron_x_preferred":[
        "Berezanka"
    ],
    "name:rus_x_preferred":[
        "\u0411\u0435\u0440\u0435\u0437\u0430\u043d\u043a\u0430"
    ],
    "name:ukr_x_preferred":[
        "\u0411\u0435\u0440\u0435\u0437\u0430\u043d\u043a\u0430"
    ],
    "name:und_x_variant":[
        "Tiligulo-Berezannya"
    ],
    "name:zho_x_preferred":[
        "\u5225\u5217\u8d0a\u5361"
    ],
    "qs:a0":"\u0423\u043a\u0440\u0430\u0457\u043d\u0430",
    "qs:a1":"*\u041c\u0438\u043a\u043e\u043b\u0430\u0457\u0432\u0441\u044c\u043a\u0430",
    "qs:a1_alt":"Mykolaivs'ka",
    "qs:a1r":"0",
    "qs:a2":"\u0411\u0435\u0440\u0435\u0437\u0430\u043d\u0441\u044c\u043a\u0438\u0439",
    "qs:a2_alt":"Berezans'kyi",
    "qs:adm0":"\u0423\u043a\u0440\u0430\u0457\u043d\u0430",
    "qs:la_lc":"*",
    "qs:level":"locality",
    "qs:loc":"\u0411\u0435\u0440\u0435\u0437\u0430\u043d\u043a\u0430",
    "qs:loc_alt":"Berezanka",
    "qs:pop":0,
    "qs:type":"buffered point",
    "wd:wordcount":392,
    "wof:name":"\u0411\u0435\u0440\u0435\u0437\u0430\u043d\u043a\u0430",
    "wof:placetype":"locality",
    "wof:population":4090
},
  "geometry": {"coordinates":[31.385643,46.855228],"type":"Point"}
}