{
  "type": "Feature",
  "properties": {
    "gn:admin1_code":"09",
    "gn:asciiname":"Krynytsya",
    "gn:country_code":"UA",
    "gn:dem":286,
    "gn:feature_class":"P",
    "gn:feature_code":"PPL",
    "gn:name":"Krynytsya",
    "gn:population":0,
    "gn:timezone":"Europe/Kiev",
    "iso:country":"UA",
    "name:ukr_x_preferred":[
        "Krynytsya"
    ],
    "name:ukr_x_variant":[
        "\u041a\u0440\u0438\u043d\u0438\u0446\u044f"
    ],
    "wof:name":"Krynytsya",
    "wof:placetype":"locality"
},
  "geometry": {"coordinates":[27.08936,49.90093],"type":"Point"}
}