{
  "type": "Feature",
  "properties": {
    "gn:admin1_code":"7.0",
    "gn:asciiname":"Krasnyy Oktyabr'",
    "gn:country_code":"UA",
    "gn:dem":121,
    "gn:feature_class":"P",
    "gn:feature_code":"PPL",
    "gn:name":"Krasnyy Oktyabr\u2019",
    "gn:population":0,
    "gn:timezone":"Europe/Kiev",
    "iso:country":"UA",
    "wof:name":"Krasnyy Oktyabr'",
    "wof:placetype":"locality"
},
  "geometry": {"coordinates":[37.25861,49.40806],"type":"Point"}
}