{
  "type": "Feature",
  "properties": {
    "gn:admin1_code":"23.0",
    "gn:asciiname":"Kordyshevka",
    "gn:country_code":"UA",
    "gn:dem":301,
    "gn:feature_class":"P",
    "gn:feature_code":"PPL",
    "gn:name":"Kordyshevka",
    "gn:population":0,
    "gn:timezone":"Europe/Kiev",
    "iso:country":"UA",
    "wof:name":"Kordyshevka",
    "wof:placetype":"locality"
},
  "geometry": {"coordinates":[28.75477,49.08966],"type":"Point"}
}