{
  "type": "Feature",
  "properties": {
    "gn:admin1_code":"14.0",
    "gn:asciiname":"Synets'kyy",
    "gn:country_code":"UA",
    "gn:dem":51,
    "gn:feature_class":"P",
    "gn:feature_code":"PPL",
    "gn:name":"Synets\u2019kyy",
    "gn:population":0,
    "gn:timezone":"Europe/Zaporozhye",
    "iso:country":"UA",
    "name:ukr_x_preferred":[
        "Synets\u2019kyy"
    ],
    "name:ukr_x_variant":[
        "\u0421\u0438\u043d\u0435\u0446\u044c\u043a\u0438\u0439"
    ],
    "name:und_x_variant":[
        "Sinetskiy"
    ],
    "wof:name":"Synets'kyy",
    "wof:placetype":"locality"
},
  "geometry": {"coordinates":[38.4119,48.94711],"type":"Point"}
}