{
  "type": "Feature",
  "properties": {
    "gn:admin1_code":"4.0",
    "gn:asciiname":"Korolivka",
    "gn:country_code":"UA",
    "gn:dem":116,
    "gn:feature_class":"P",
    "gn:feature_code":"PPL",
    "gn:name":"Korolivka",
    "gn:population":0,
    "gn:timezone":"Europe/Kiev",
    "iso:country":"UA",
    "name:rus_x_preferred":[
        "Korol\u00ebvka"
    ],
    "name:ukr_x_preferred":[
        "Korolivka"
    ],
    "name:ukr_x_variant":[
        "\u041a\u043e\u0440\u043e\u043b\u0456\u0432\u043a\u0430"
    ],
    "wof:name":"Korolivka",
    "wof:placetype":"locality"
},
  "geometry": {"coordinates":[35.12786,48.84444000000001],"type":"Point"}
}