{
  "type": "Feature",
  "properties": {
    "gn:admin1_code":"1.0",
    "gn:asciiname":"Skelivka",
    "gn:country_code":"UA",
    "gn:dem":161,
    "gn:feature_class":"P",
    "gn:feature_code":"PPL",
    "gn:name":"Skelivka",
    "gn:population":0,
    "gn:timezone":"Europe/Kiev",
    "iso:country":"UA",
    "name:ukr_x_preferred":[
        "Skelivka"
    ],
    "name:ukr_x_variant":[
        "\u0421\u043a\u0435\u043b\u0456\u0432\u043a\u0430"
    ],
    "wof:name":"Skelivka",
    "wof:placetype":"locality"
},
  "geometry": {"coordinates":[32.31454,49.08817],"type":"Point"}
}