{
  "type": "Feature",
  "properties": {
    "gn:admin1_code":"1.0",
    "gn:asciiname":"Skelivka",
    "gn:country_code":"UA",
    "gn:dem":161,
    "gn:feature_class":"P",
    "gn:feature_code":"PPL",
    "gn:name":"Skelivka",
    "gn:population":0,
    "gn:timezone":"Europe/Kiev",
    "iso:country":"UA",
    "name:ceb_x_preferred":[
        "Skelivka"
    ],
    "name:deu_x_preferred":[
        "Skeliwka"
    ],
    "name:heb_x_preferred":[
        "\u05e4\u05dc\u05e9\u05d8\u05d9\u05df"
    ],
    "name:pol_x_preferred":[
        "Skeliwka"
    ],
    "name:ron_x_preferred":[
        "Skelivka"
    ],
    "name:rus_x_preferred":[
        "\u0421\u043a\u0435\u043b\u0435\u0432\u043a\u0430"
    ],
    "name:ukr_x_preferred":[
        "Skelivka"
    ],
    "name:ukr_x_variant":[
        "\u0421\u043a\u0435\u043b\u0456\u0432\u043a\u0430"
    ],
    "name:zho_x_preferred":[
        "\u65af\u514b\u5229\u592b\u5361"
    ],
    "wof:name":"Skelivka",
    "wof:placetype":"locality"
},
  "geometry": {"coordinates":[32.31454,49.08817],"type":"Point"}
}