{
  "type": "Feature",
  "properties": {
    "gn:admin1_code":"14.0",
    "gn:asciiname":"Koshelivka",
    "gn:country_code":"UA",
    "gn:dem":152,
    "gn:feature_class":"P",
    "gn:feature_code":"PPL",
    "gn:name":"Koshelivka",
    "gn:population":0,
    "gn:timezone":"Europe/Zaporozhye",
    "iso:country":"UA",
    "name:rus_x_preferred":[
        "Koshel\u00ebvka"
    ],
    "name:ukr_x_preferred":[
        "Koshelivka"
    ],
    "name:ukr_x_variant":[
        "\u041a\u043e\u0448\u0435\u043b\u0456\u0432\u043a\u0430"
    ],
    "wof:name":"Koshelivka",
    "wof:placetype":"locality"
},
  "geometry": {"coordinates":[38.04783,49.76094000000001],"type":"Point"}
}