{
  "type": "Feature",
  "properties": {
    "gn:admin1_code":"26.0",
    "gn:asciiname":"Prudentove",
    "gn:country_code":"UA",
    "gn:dem":31,
    "gn:feature_class":"P",
    "gn:feature_code":"PPL",
    "gn:name":"Prudentove",
    "gn:population":0,
    "gn:timezone":"Europe/Zaporozhye",
    "iso:country":"UA",
    "name:ukr_x_preferred":[
        "\u041f\u0440\u0443\u0434\u0435\u043d\u0442\u043e\u0432\u0435"
    ],
    "wof:name":"Prudentove",
    "wof:placetype":"locality"
},
  "geometry": {"coordinates":[35.9813,46.80206],"type":"Point"}
}