{
  "type": "Feature",
  "properties": {
    "gn:admin1_code":"9.0",
    "gn:asciiname":"Zagontsy",
    "gn:country_code":"UA",
    "gn:dem":331,
    "gn:feature_class":"P",
    "gn:feature_code":"PPL",
    "gn:name":"Zagontsy",
    "gn:population":0,
    "gn:timezone":"Europe/Kiev",
    "iso:country":"UA",
    "name:und_x_variant":[
        "Zagintsy",
        "Zagontsy"
    ],
    "wof:name":"Zagontsy",
    "wof:placetype":"locality"
},
  "geometry": {"coordinates":[27.16113,49.21133],"type":"Point"}
}