{
  "type": "Feature",
  "properties": {
    "gn:admin1_code":"5.0",
    "gn:admin2_code":"689196",
    "gn:asciiname":"Kalynove",
    "gn:country_code":"UA",
    "gn:dem":155,
    "gn:elevation":"161.0",
    "gn:feature_class":"P",
    "gn:feature_code":"PPL",
    "gn:name":"Kalynove",
    "gn:population":577,
    "gn:timezone":"Europe/Kiev",
    "iso:country":"UA",
    "name:deu_x_preferred":[
        "Kalynowe"
    ],
    "name:hye_x_preferred":[
        "\u053f\u0561\u056c\u0575\u0576\u0578\u057e\u0565"
    ],
    "name:hye_x_variant":[
        "\u053f\u0561\u056c\u056b\u0576\u056b\u0576\u0578",
        "\u053f\u0561\u056c\u056b\u0576\u0578\u057e\u0578"
    ],
    "name:kat_x_preferred":[
        "\u10d9\u10d0\u10da\u10d8\u10dc\u10dd\u10d5\u10d4"
    ],
    "name:kat_x_variant":[
        "\u10d9\u10d0\u10da\u10d8\u10dc\u10dd\u10d5\u10dd"
    ],
    "name:ron_x_preferred":[
        "Kal\u00eenove"
    ],
    "name:rus_x_historical":[
        "Kalinino",
        "\u041a\u0430\u043b\u0438\u043d\u0438\u043d\u043e"
    ],
    "name:rus_x_preferred":[
        "Kalinino"
    ],
    "name:rus_x_variant":[
        "\u041a\u0430\u043b\u0438\u043d\u0438\u043d\u043e",
        "\u041a\u0430\u043b\u0438\u043d\u043e\u0432\u043e"
    ],
    "name:ukr_x_historical":[
        "Kalinine",
        "\u041a\u0430\u043b\u0456\u043d\u0456\u043d\u0435"
    ],
    "name:ukr_x_preferred":[
        "Kalinine"
    ],
    "name:ukr_x_variant":[
        "\u041a\u0430\u043b\u0456\u043d\u0456\u043d\u0435"
    ],
    "name:zho_x_preferred":[
        "\u5361\u5229\u8afe\u97cb"
    ],
    "wof:name":"Kalynove",
    "wof:placetype":"locality",
    "wof:population":577
},
  "geometry": {"coordinates":[37.46403,47.4571],"type":"Point"}
}