{
  "type": "Feature",
  "properties": {
    "gn:admin1_code":"6.0",
    "gn:asciiname":"Oleyeva-Kornev",
    "gn:country_code":"UA",
    "gn:dem":302,
    "gn:feature_class":"P",
    "gn:feature_code":"PPL",
    "gn:name":"Oleyeva-Kornev",
    "gn:population":0,
    "gn:timezone":"Europe/Kiev",
    "iso:country":"UA",
    "name:und_x_variant":[
        "Oleyy\u00ebva Kornyuv",
        "Oley\u00ebva Kornyuv"
    ],
    "wof:name":"Oleyeva-Kornev",
    "wof:placetype":"locality"
},
  "geometry": {"coordinates":[25.37874,48.74461],"type":"Point"}
}