{
  "type": "Feature",
  "properties": {
    "gn:admin1_code":"26.0",
    "gn:asciiname":"Chkalove",
    "gn:country_code":"UA",
    "gn:dem":16,
    "gn:feature_class":"P",
    "gn:feature_code":"PPL",
    "gn:name":"Chkalove",
    "gn:population":0,
    "gn:timezone":"Europe/Zaporozhye",
    "iso:country":"UA",
    "name:ukr_x_preferred":[
        "Chkalove"
    ],
    "name:ukr_x_variant":[
        "\u0427\u043a\u0430\u043b\u043e\u0432\u0435"
    ],
    "name:und_x_variant":[
        "Troitskoye",
        "Chkalovo"
    ],
    "wof:name":"Chkalove",
    "wof:placetype":"locality"
},
  "geometry": {"coordinates":[35.64554000000001,46.55081],"type":"Point"}
}