{
  "type": "Feature",
  "properties": {
    "gn:admin1_code":"21.0",
    "gn:asciiname":"Chervone",
    "gn:country_code":"UA",
    "gn:dem":157,
    "gn:feature_class":"P",
    "gn:feature_code":"PPL",
    "gn:name":"Chervone",
    "gn:population":0,
    "gn:timezone":"Europe/Kiev",
    "iso:country":"UA",
    "name:ukr_x_preferred":[
        "Chervone"
    ],
    "name:ukr_x_variant":[
        "\u0427\u0435\u0440\u0432\u043e\u043d\u0435"
    ],
    "name:und_x_variant":[
        "Chervonoye"
    ],
    "wof:name":"Chervone",
    "wof:placetype":"locality"
},
  "geometry": {"coordinates":[33.56942,50.86738],"type":"Point"}
}