{
  "type": "Feature",
  "properties": {
    "gn:admin1_code":"11.0",
    "gn:admin2_code":"693803",
    "gn:admin3_code":"11152605.0",
    "gn:asciiname":"Nizhnekurgannoye",
    "gn:country_code":"UA",
    "gn:dem":182,
    "gn:elevation":"179.0",
    "gn:feature_class":"P",
    "gn:feature_code":"PPL",
    "gn:name":"Nizhnekurgannoye",
    "gn:population":74,
    "gn:timezone":"Europe/Simferopol",
    "iso:country":"UA",
    "name:eng_x_preferred":[
        "Nizhnekurgannoye"
    ],
    "name:rus_x_historical":[
        "\u041d\u0438\u0301\u0436\u043d\u044f\u044f \u0410\u0441\u043c\u0430\u0301"
    ],
    "name:rus_x_preferred":[
        "\u041d\u0438\u0436\u043d\u0435\u043a\u0443\u0440\u0433\u0430\u043d\u043d\u043e\u0435"
    ],
    "name:rus_x_variant":[
        "\u041d\u0438\u0301\u0436\u043d\u044f\u044f \u0410\u0441\u043c\u0430\u0301"
    ],
    "name:ukr_x_preferred":[
        "\u041d\u0438\u0436\u043d\u044c\u043e\u043a\u0443\u0440\u0433\u0430\u043d\u043d\u0435"
    ],
    "wof:name":"Nizhnekurgannoye",
    "wof:placetype":"locality",
    "wof:population":74
},
  "geometry": {"coordinates":[34.23488,45.11431],"type":"Point"}
}