{
  "type": "Feature",
  "properties": {
    "gn:admin1_code":"27.0",
    "gn:asciiname":"Bahate",
    "gn:country_code":"UA",
    "gn:dem":221,
    "gn:feature_class":"P",
    "gn:feature_code":"PPL",
    "gn:name":"Bahate",
    "gn:population":0,
    "gn:timezone":"Europe/Kiev",
    "iso:country":"UA",
    "name:ukr_x_preferred":[
        "Bahate"
    ],
    "name:ukr_x_variant":[
        "\u0411\u0430\u0433\u0430\u0442\u0435"
    ],
    "name:und_x_variant":[
        "Bogatoye"
    ],
    "wof:name":"Bahate",
    "wof:placetype":"locality"
},
  "geometry": {"coordinates":[27.39381,50.58953],"type":"Point"}
}