{
  "type": "Feature",
  "properties": {
    "gn:admin1_code":"3.0",
    "gn:asciiname":"Chereshnov",
    "gn:country_code":"UA",
    "gn:dem":811,
    "gn:feature_class":"P",
    "gn:feature_code":"PPL",
    "gn:name":"Chereshnov",
    "gn:population":0,
    "gn:timezone":"Europe/Kiev",
    "iso:country":"UA",
    "wof:name":"Chereshnov",
    "wof:placetype":"locality"
},
  "geometry": {"coordinates":[25.16667,48.15],"type":"Point"}
}