{
  "type": "Feature",
  "properties": {
    "gn:admin1_code":"7.0",
    "gn:asciiname":"Kustorivka",
    "gn:country_code":"UA",
    "gn:dem":164,
    "gn:feature_class":"P",
    "gn:feature_code":"PPL",
    "gn:name":"Kustorivka",
    "gn:population":0,
    "gn:timezone":"Europe/Kiev",
    "iso:country":"UA",
    "name:ukr_x_preferred":[
        "Kustorivka"
    ],
    "name:ukr_x_variant":[
        "\u041a\u0443\u0441\u0442\u043e\u0440\u0456\u0432\u043a\u0430"
    ],
    "wof:name":"Kustorivka",
    "wof:placetype":"locality"
},
  "geometry": {"coordinates":[35.2754,49.98424],"type":"Point"}
}