{
  "type": "Feature",
  "properties": {
    "gn:admin1_code":"21.0",
    "gn:asciiname":"Sholud'ky",
    "gn:country_code":"UA",
    "gn:dem":187,
    "gn:feature_class":"P",
    "gn:feature_code":"PPL",
    "gn:name":"Sholud\u2019ky",
    "gn:population":0,
    "gn:timezone":"Europe/Kiev",
    "iso:country":"UA",
    "name:ukr_x_preferred":[
        "Sholud\u2019ky"
    ],
    "name:ukr_x_variant":[
        "\u0428\u043e\u043b\u0443\u0434\u044c\u043a\u0438"
    ],
    "name:und_x_variant":[
        "Sholud\u2019kl"
    ],
    "wof:name":"Sholud'ky",
    "wof:placetype":"locality"
},
  "geometry": {"coordinates":[34.57195,50.25548],"type":"Point"}
}