{
  "type": "Feature",
  "properties": {
    "gn:admin1_code":"18.0",
    "gn:asciiname":"Pelenkivshchyna",
    "gn:country_code":"UA",
    "gn:dem":104,
    "gn:feature_class":"P",
    "gn:feature_code":"PPL",
    "gn:name":"Pelenkivshchyna",
    "gn:population":0,
    "gn:timezone":"Europe/Kiev",
    "iso:country":"UA",
    "name:ukr_x_preferred":[
        "Pelenkivshchyna"
    ],
    "name:ukr_x_variant":[
        "\u041f\u0435\u043b\u0435\u043d\u043a\u0456\u0432\u0449\u0438\u043d\u0430"
    ],
    "wof:name":"Pelenkivshchyna",
    "wof:placetype":"locality"
},
  "geometry": {"coordinates":[34.33985999999999,50.18955],"type":"Point"}
}