{
  "type": "Feature",
  "properties": {
    "gn:admin1_code":"5.0",
    "gn:asciiname":"Hrushivs'ke",
    "gn:country_code":"UA",
    "gn:dem":94,
    "gn:feature_class":"P",
    "gn:feature_code":"PPL",
    "gn:name":"Hrushivs\u2019ke",
    "gn:population":0,
    "gn:timezone":"Europe/Kiev",
    "iso:country":"UA",
    "name:ukr_x_preferred":[
        "Hrushivs\u2019ke"
    ],
    "name:ukr_x_variant":[
        "\u0413\u0440\u0443\u0448\u0456\u0432\u0441\u044c\u043a\u0435"
    ],
    "name:und_x_variant":[
        "Grushevskoye"
    ],
    "wof:name":"Hrushivs'ke",
    "wof:placetype":"locality"
},
  "geometry": {"coordinates":[36.71122,48.0463],"type":"Point"}
}