{
  "type": "Feature",
  "properties": {
    "gn:admin1_code":"18.0",
    "gn:asciiname":"Kuz'menky",
    "gn:country_code":"UA",
    "gn:dem":67,
    "gn:feature_class":"P",
    "gn:feature_code":"PPL",
    "gn:name":"Kuz\u2019menky",
    "gn:population":0,
    "gn:timezone":"Europe/Kiev",
    "iso:country":"UA",
    "name:ukr_x_preferred":[
        "Kuz\u2019menky"
    ],
    "name:ukr_x_variant":[
        "\u041a\u0443\u0437\u044c\u043c\u0435\u043d\u043a\u0438"
    ],
    "wof:name":"Kuz'menky",
    "wof:placetype":"locality"
},
  "geometry": {"coordinates":[33.61775,49.15059],"type":"Point"}
}