{
  "type": "Feature",
  "properties": {
    "gn:population":4186,
    "iso:country":"UA",
    "name:eng_x_preferred":[
        "Obroshyne"
    ],
    "name:pol_x_preferred":[
        "Obroszyn"
    ],
    "name:ron_x_preferred":[
        "Obro\u0219\u00eene"
    ],
    "name:rus_x_preferred":[
        "\u041e\u0431\u0440\u043e\u0448\u0438\u043d\u043e"
    ],
    "name:rus_x_variant":[
        "\u041e\u0431\u0440\u043e\u0448\u0438\u043d"
    ],
    "name:ukr_x_preferred":[
        "\u041e\u0431\u0440\u043e\u0448\u0438\u043d\u0435"
    ],
    "name:unk_x_variant":[
        "Obroshin"
    ],
    "name:zho_x_preferred":[
        "\u5967\u5e03\u7f85\u4ec0\u6d85"
    ],
    "qs:a0":"\u0423\u043a\u0440\u0430\u0457\u043d\u0430",
    "qs:a1":"*\u041b\u044c\u0432\u0456\u0432\u0441\u044c\u043a\u0430",
    "qs:a1_alt":"L'vivs'ka",
    "qs:a1r":"0",
    "qs:a2":"\u041f\u0443\u0441\u0442\u043e\u043c\u0438\u0442\u0456\u0432\u0441\u044c\u043a\u0438\u0439",
    "qs:a2_alt":"Pustomytivs'kyi",
    "qs:adm0":"\u0423\u043a\u0440\u0430\u0457\u043d\u0430",
    "qs:la_lc":"*",
    "qs:level":"locality",
    "qs:loc":"\u041e\u0431\u0440\u043e\u0448\u0438\u043d\u0435",
    "qs:loc_alt":"Obroshyne",
    "qs:pop":0,
    "qs:type":"buffered point",
    "wd:wordcount":310,
    "wof:name":"\u041e\u0431\u0440\u043e\u0448\u0438\u043d\u0435",
    "wof:placetype":"locality",
    "wof:population":4186
},
  "geometry": {"coordinates":[23.874224,49.778555],"type":"Point"}
}