{
  "type": "Feature",
  "properties": {
    "gn:admin1_code":"7.0",
    "gn:asciiname":"Shyrokyy Yar",
    "gn:country_code":"UA",
    "gn:dem":180,
    "gn:feature_class":"P",
    "gn:feature_code":"PPL",
    "gn:name":"Shyrokyy Yar",
    "gn:population":0,
    "gn:timezone":"Europe/Kiev",
    "iso:country":"UA",
    "name:ukr_x_preferred":[
        "Shyrokyy Yar"
    ],
    "name:ukr_x_variant":[
        "\u0428\u0438\u0440\u043e\u043a\u0438\u0439 \u042f\u0440"
    ],
    "wof:name":"Shyrokyy Yar",
    "wof:placetype":"locality"
},
  "geometry": {"coordinates":[35.84900000000001,50.3486],"type":"Point"}
}