{
  "type": "Feature",
  "properties": {
    "gn:admin1_code":"9.0",
    "gn:asciiname":"Ustyanivka",
    "gn:country_code":"UA",
    "gn:dem":287,
    "gn:feature_class":"P",
    "gn:feature_code":"PPL",
    "gn:name":"Ustyanivka",
    "gn:population":0,
    "gn:timezone":"Europe/Kiev",
    "iso:country":"UA",
    "name:ukr_x_preferred":[
        "Ustyanivka"
    ],
    "name:ukr_x_variant":[
        "\u0423\u0441\u0442\u044f\u043d\u0456\u0432\u043a\u0430"
    ],
    "name:und_x_variant":[
        "Ust\u2019yanovka"
    ],
    "wof:name":"Ustyanivka",
    "wof:placetype":"locality"
},
  "geometry": {"coordinates":[27.21547,50.03829],"type":"Point"}
}