{
  "type": "Feature",
  "properties": {
    "iso:country":"UA",
    "name:pol_x_preferred":[
        "Wierzchownia"
    ],
    "qs:a0":"\u0423\u043a\u0440\u0430\u0457\u043d\u0430",
    "qs:a1":"*\u0416\u0438\u0442\u043e\u043c\u0438\u0440\u0441\u044c\u043a\u0430",
    "qs:a1_alt":"Zhytomyrs'ka",
    "qs:a1r":"0",
    "qs:a2":"\u0420\u0443\u0436\u0438\u043d\u0441\u044c\u043a\u0438\u0439",
    "qs:a2_alt":"Ruzhyns'kyi",
    "qs:adm0":"\u0423\u043a\u0440\u0430\u0457\u043d\u0430",
    "qs:la_lc":"*",
    "qs:level":"locality",
    "qs:loc":"\u0412\u0435\u0440\u0445\u0456\u0432\u043d\u044f",
    "qs:loc_alt":"Verkhivnia",
    "qs:pop":0,
    "qs:type":"buffered point",
    "wd:wordcount":41,
    "wof:name":"\u0412\u0435\u0440\u0445\u0456\u0432\u043d\u044f",
    "wof:placetype":"locality"
},
  "geometry": {"coordinates":[29.325346,49.79987],"type":"Point"}
}