{
  "type": "Feature",
  "properties": {
    "gn:admin1_code":"15.0",
    "gn:asciiname":"Slyvnytsya",
    "gn:country_code":"UA",
    "gn:dem":451,
    "gn:feature_class":"P",
    "gn:feature_code":"PPL",
    "gn:name":"Slyvnytsya",
    "gn:population":0,
    "gn:timezone":"Europe/Kiev",
    "iso:country":"UA",
    "name:rus_x_preferred":[
        "\u0421\u043b\u0438\u0432\u043d\u0438\u0446\u0430"
    ],
    "name:ukr_x_preferred":[
        "Slyvnytsya"
    ],
    "name:ukr_x_variant":[
        "\u0421\u043b\u0438\u0432\u043d\u0438\u0446\u044f"
    ],
    "name:und_x_variant":[
        "Slivnitsa"
    ],
    "wof:name":"Slyvnytsya",
    "wof:placetype":"locality"
},
  "geometry": {"coordinates":[22.86848,49.50771],"type":"Point"}
}