{
  "type": "Feature",
  "properties": {
    "gn:admin1_code":"10.0",
    "gn:asciiname":"Ruzhycheve",
    "gn:country_code":"UA",
    "gn:dem":150,
    "gn:feature_class":"P",
    "gn:feature_code":"PPL",
    "gn:name":"Ruzhycheve",
    "gn:population":0,
    "gn:timezone":"Europe/Kiev",
    "iso:country":"UA",
    "name:ukr_x_preferred":[
        "Ruzhycheve"
    ],
    "name:ukr_x_variant":[
        "\u0420\u0443\u0436\u0438\u0447\u0435\u0432\u0435"
    ],
    "name:und_x_variant":[
        "Ruzhichevka"
    ],
    "wof:name":"Ruzhycheve",
    "wof:placetype":"locality"
},
  "geometry": {"coordinates":[32.55461,48.95567],"type":"Point"}
}