{
  "type": "Feature",
  "properties": {
    "gn:admin1_code":"15.0",
    "gn:asciiname":"Kyyivets'",
    "gn:country_code":"UA",
    "gn:dem":255,
    "gn:feature_class":"P",
    "gn:feature_code":"PPL",
    "gn:name":"Kyyivets\u2019",
    "gn:population":0,
    "gn:timezone":"Europe/Kiev",
    "iso:country":"UA",
    "name:rus_x_preferred":[
        "\u041a\u0438\u0435\u0432\u0435\u0446"
    ],
    "name:ukr_x_preferred":[
        "Kyyivets\u2019"
    ],
    "name:ukr_x_variant":[
        "\u041a\u0438\u0457\u0432\u0435\u0446\u044c"
    ],
    "name:und_x_variant":[
        "Kiy\u00ebvets",
        "Kiyevets"
    ],
    "wof:name":"Kyyivets'",
    "wof:placetype":"locality"
},
  "geometry": {"coordinates":[24.02918,49.43371],"type":"Point"}
}