{
  "type": "Feature",
  "properties": {
    "gn:admin1_code":"7.0",
    "gn:asciiname":"Pokalyane",
    "gn:country_code":"UA",
    "gn:dem":110,
    "gn:feature_class":"P",
    "gn:feature_code":"PPL",
    "gn:name":"Pokalyane",
    "gn:population":0,
    "gn:timezone":"Europe/Kiev",
    "iso:country":"UA",
    "name:rus_x_preferred":[
        "\u041f\u043e\u043a\u0430\u043b\u044f\u043d\u043e\u0435"
    ],
    "name:ukr_x_preferred":[
        "Pokalyane"
    ],
    "name:ukr_x_variant":[
        "\u041f\u043e\u043a\u0430\u043b\u044f\u043d\u0435"
    ],
    "name:und_x_variant":[
        "Pokalyanoye"
    ],
    "wof:name":"Pokalyane",
    "wof:placetype":"locality"
},
  "geometry": {"coordinates":[37.0721,50.2983],"type":"Point"}
}