{
  "type": "Feature",
  "properties": {
    "gn:admin1_code":"7.0",
    "gn:asciiname":"Bubnove-Pershe",
    "gn:country_code":"UA",
    "gn:dem":166,
    "gn:feature_class":"P",
    "gn:feature_code":"PPL",
    "gn:name":"Bubnove-Pershe",
    "gn:population":0,
    "gn:timezone":"Europe/Kiev",
    "iso:country":"UA",
    "name:ukr_x_preferred":[
        "Bubnove-Pershe"
    ],
    "name:ukr_x_variant":[
        "\u0411\u0443\u0431\u043d\u043e\u0432\u0435-\u041f\u0435\u0440\u0448\u0435"
    ],
    "name:und_x_variant":[
        "Bubnovo-Pervoye"
    ],
    "wof:name":"Bubnove-Pershe",
    "wof:placetype":"locality"
},
  "geometry": {"coordinates":[36.21829,48.739],"type":"Point"}
}