{
  "type": "Feature",
  "properties": {
    "gn:admin1_code":"23.0",
    "gn:asciiname":"Medovka",
    "gn:country_code":"UA",
    "gn:dem":229,
    "gn:feature_class":"P",
    "gn:feature_code":"PPL",
    "gn:name":"Medovka",
    "gn:population":0,
    "gn:timezone":"Europe/Kiev",
    "iso:country":"UA",
    "wof:name":"Medovka",
    "wof:placetype":"locality"
},
  "geometry": {"coordinates":[29.33883,49.2613],"type":"Point"}
}