{
  "type": "Feature",
  "properties": {
    "gn:admin1_code":"23.0",
    "gn:asciiname":"Medovka",
    "gn:country_code":"UA",
    "gn:dem":229,
    "gn:feature_class":"P",
    "gn:feature_code":"PPL",
    "gn:name":"Medovka",
    "gn:population":0,
    "gn:timezone":"Europe/Kiev",
    "iso:country":"UA",
    "name:aze_x_preferred":[
        "Medovka"
    ],
    "name:fas_x_preferred":[
        "\u0645\u062f\u0648\u0641\u06a9\u0627"
    ],
    "name:fra_x_preferred":[
        "Medovka"
    ],
    "name:hye_x_preferred":[
        "\u0544\u0565\u0564\u0578\u057e\u056f\u0561"
    ],
    "name:ita_x_preferred":[
        "Medovka"
    ],
    "name:kat_x_preferred":[
        "\u10db\u10d4\u10d3\u10dd\u10d5\u10d9\u10d0"
    ],
    "name:msa_x_preferred":[
        "Medovka"
    ],
    "name:spa_x_preferred":[
        "Medovka"
    ],
    "name:vie_x_preferred":[
        "Medovka"
    ],
    "wof:name":"Medovka",
    "wof:placetype":"locality"
},
  "geometry": {"coordinates":[29.33883,49.2613],"type":"Point"}
}