{
  "type": "Feature",
  "properties": {
    "gn:admin1_code":"6.0",
    "gn:asciiname":"Stav",
    "gn:country_code":"UA",
    "gn:dem":276,
    "gn:feature_class":"P",
    "gn:feature_code":"PPL",
    "gn:name":"Stav",
    "gn:population":0,
    "gn:timezone":"Europe/Kiev",
    "iso:country":"UA",
    "name:ceb_x_preferred":[
        "Stav"
    ],
    "name:ces_x_preferred":[
        "Stav"
    ],
    "name:deu_x_preferred":[
        "Stav"
    ],
    "name:slk_x_preferred":[
        "Stav"
    ],
    "name:srp_x_preferred":[
        "\u0421\u0442\u0430\u0432"
    ],
    "name:swe_x_preferred":[
        "Stav"
    ],
    "wof:name":"Stav",
    "wof:placetype":"locality"
},
  "geometry": {"coordinates":[24.81667,48.78333],"type":"Point"}
}