{
  "type": "Feature",
  "properties": {
    "gn:admin1_code":"2.0",
    "gn:asciiname":"Lubenets'",
    "gn:country_code":"UA",
    "gn:dem":144,
    "gn:feature_class":"P",
    "gn:feature_code":"PPL",
    "gn:name":"Lubenets\u2019",
    "gn:population":0,
    "gn:timezone":"Europe/Kiev",
    "iso:country":"UA",
    "name:ukr_x_preferred":[
        "Lubenets\u2019"
    ],
    "name:ukr_x_variant":[
        "\u041b\u0443\u0431\u0435\u043d\u0435\u0446\u044c"
    ],
    "name:und_x_variant":[
        "Lubenets"
    ],
    "wof:name":"Lubenets'",
    "wof:placetype":"locality"
},
  "geometry": {"coordinates":[32.35969,51.75022],"type":"Point"}
}