{
  "type": "Feature",
  "properties": {
    "gn:admin1_code":"24.0",
    "gn:asciiname":"Novyy Dvir",
    "gn:country_code":"UA",
    "gn:dem":193,
    "gn:feature_class":"P",
    "gn:feature_code":"PPL",
    "gn:name":"Novyy Dvir",
    "gn:population":0,
    "gn:timezone":"Europe/Kiev",
    "iso:country":"UA",
    "name:ukr_x_preferred":[
        "Novyy Dvir"
    ],
    "name:ukr_x_variant":[
        "\u041d\u043e\u0432\u0438\u0439 \u0414\u0432\u0456\u0440"
    ],
    "name:und_x_variant":[
        "Nowy Dw\u00f3r",
        "Novy Dvur",
        "Novyy Dvor"
    ],
    "wof:name":"Novyy Dvir",
    "wof:placetype":"locality"
},
  "geometry": {"coordinates":[24.79708,50.96765],"type":"Point"}
}