{
  "type": "Feature",
  "properties": {
    "gn:admin1_code":"6.0",
    "gn:asciiname":"Probabnyy",
    "gn:country_code":"UA",
    "gn:dem":256,
    "gn:feature_class":"P",
    "gn:feature_code":"PPL",
    "gn:name":"Probabnyy",
    "gn:population":0,
    "gn:timezone":"Europe/Kiev",
    "iso:country":"UA",
    "name:und_x_variant":[
        "Pol\u2019sha",
        "Probabin",
        "Probabnyy"
    ],
    "wof:name":"Probabnyy",
    "wof:placetype":"locality"
},
  "geometry": {"coordinates":[25.5857,48.66481],"type":"Point"}
}