{
  "type": "Feature",
  "properties": {
    "gn:admin1_code":"21.0",
    "gn:asciiname":"Hostrobury",
    "gn:country_code":"UA",
    "gn:dem":195,
    "gn:feature_class":"P",
    "gn:feature_code":"PPL",
    "gn:name":"Hostrobury",
    "gn:population":0,
    "gn:timezone":"Europe/Kiev",
    "iso:country":"UA",
    "name:ukr_x_preferred":[
        "Hostrobury"
    ],
    "name:ukr_x_variant":[
        "\u0413\u043e\u0441\u0442\u0440\u043e\u0431\u0443\u0440\u0438"
    ],
    "wof:name":"Hostrobury",
    "wof:placetype":"locality"
},
  "geometry": {"coordinates":[34.5105,50.76352],"type":"Point"}
}