{
  "type": "Feature",
  "properties": {
    "gn:population":3170,
    "iso:country":"UA",
    "name:ceb_x_preferred":[
        "Dmytrivka"
    ],
    "name:deu_x_preferred":[
        "Dmytriwka"
    ],
    "name:eng_x_preferred":[
        "Dmytrivka"
    ],
    "name:hye_x_preferred":[
        "\u0534\u0574\u056b\u057f\u0580\u0578\u057e\u056f\u0561"
    ],
    "name:lav_x_preferred":[
        "Dmitrivka"
    ],
    "name:rus_x_preferred":[
        "\u0414\u043c\u0438\u0442\u0440\u043e\u0432\u043a\u0430"
    ],
    "name:ukr_x_preferred":[
        "\u0414\u043c\u0438\u0442\u0440\u0456\u0432\u043a\u0430"
    ],
    "name:und_x_variant":[
        "Dmitrievka"
    ],
    "qs:a0":"\u0423\u043a\u0440\u0430\u0457\u043d\u0430",
    "qs:a1":"*\u0414\u043e\u043d\u0435\u0446\u044c\u043a\u0430",
    "qs:a1_alt":"Donets'ka",
    "qs:a1r":"0",
    "qs:a2":"\u0428\u0430\u0445\u0442\u0430\u0440\u0441\u044c\u043a\u0438\u0439",
    "qs:a2_alt":"Shakhtars'kyi",
    "qs:adm0":"\u0423\u043a\u0440\u0430\u0457\u043d\u0430",
    "qs:la_lc":"*",
    "qs:level":"locality",
    "qs:loc":"\u0414\u043c\u0438\u0442\u0440\u0456\u0432\u043a\u0430",
    "qs:loc_alt":"Dmytrivka",
    "qs:pop":0,
    "qs:type":"buffered point",
    "wd:wordcount":63,
    "wof:name":"\u0414\u043c\u0438\u0442\u0440\u0456\u0432\u043a\u0430",
    "wof:placetype":"locality",
    "wof:population":3170
},
  "geometry": {"coordinates":[38.934621,47.93532],"type":"Point"}
}