{
  "type": "Feature",
  "properties": {
    "gn:admin1_code":"18.0",
    "gn:asciiname":"Nova Mykhaylivka",
    "gn:country_code":"UA",
    "gn:dem":100,
    "gn:feature_class":"P",
    "gn:feature_code":"PPL",
    "gn:name":"Nova Mykhaylivka",
    "gn:population":0,
    "gn:timezone":"Europe/Kiev",
    "iso:country":"UA",
    "name:ukr_x_preferred":[
        "Nova Mykhaylivka"
    ],
    "name:ukr_x_variant":[
        "\u041d\u043e\u0432\u0430 \u041c\u0438\u0445\u0430\u0439\u043b\u0456\u0432\u043a\u0430"
    ],
    "wof:name":"Nova Mykhaylivka",
    "wof:placetype":"locality"
},
  "geometry": {"coordinates":[34.10548,49.73514],"type":"Point"}
}