{
  "type": "Feature",
  "properties": {
    "gn:gn_country":"UA",
    "gn:gn_fcode":"PPL",
    "gn:gn_pop":3068,
    "gn:population":3068,
    "iso:country":"UA",
    "name:ceb_x_preferred":[
        "Lysychovo"
    ],
    "name:eng_x_preferred":[
        "Lisichovo"
    ],
    "name:epo_x_preferred":[
        "Lisi\u0109ovo"
    ],
    "name:hun_x_preferred":[
        "R\u00f3kamez\u0151"
    ],
    "name:hye_x_preferred":[
        "\u053c\u056b\u057d\u056b\u0579\u0578\u057e\u0578"
    ],
    "name:nld_x_preferred":[
        "R\u00f3kamez\u0151"
    ],
    "name:ron_x_preferred":[
        "L\u00ees\u00eeciovo"
    ],
    "name:rus_x_preferred":[
        "\u041b\u0438\u0441\u0438\u0447\u043e\u0432\u043e"
    ],
    "name:ukr_x_preferred":[
        "\u041b\u0438\u0441\u0438\u0447\u043e\u0432\u043e"
    ],
    "name:unk_x_variant":[
        "Lisichevo"
    ],
    "name:zho_x_preferred":[
        "\u5229\u897f\u55ac\u6c83"
    ],
    "qs_pg:aaroncc":"UA",
    "qs_pg:gn_country":"UA",
    "qs_pg:gn_fcode":"PPL",
    "qs_pg:gn_pop":3068,
    "qs_pg:name":"Lysychovo",
    "qs_pg:photos_9r":0,
    "qs_pg:photos_sr":0,
    "qs_pg:pop_sr":4,
    "qs_pg:qs_pg_placetype":"locality",
    "wof:name":"Lysychovo",
    "wof:placetype":"locality",
    "wof:population":3068
},
  "geometry": {"coordinates":[23.28992,48.49677],"type":"Point"}
}