{
  "type": "Feature",
  "properties": {
    "gn:admin1_code":"4.0",
    "gn:asciiname":"Kruten'ke",
    "gn:country_code":"UA",
    "gn:dem":138,
    "gn:feature_class":"P",
    "gn:feature_code":"PPL",
    "gn:name":"Kruten\u2019ke",
    "gn:population":0,
    "gn:timezone":"Europe/Kiev",
    "iso:country":"UA",
    "name:rus_x_preferred":[
        "Kruten\u2019koye"
    ],
    "name:ukr_x_preferred":[
        "Kruten\u2019ke"
    ],
    "name:ukr_x_variant":[
        "\u041a\u0440\u0443\u0442\u0435\u043d\u044c\u043a\u0435"
    ],
    "wof:name":"Kruten'ke",
    "wof:placetype":"locality"
},
  "geometry": {"coordinates":[36.34616,48.16292],"type":"Point"}
}