{
  "type": "Feature",
  "properties": {
    "gn:admin1_code":"24.0",
    "gn:asciiname":"Shepel'",
    "gn:country_code":"UA",
    "gn:dem":197,
    "gn:feature_class":"P",
    "gn:feature_code":"PPL",
    "gn:name":"Shepel\u2019",
    "gn:population":0,
    "gn:timezone":"Europe/Kiev",
    "iso:country":"UA",
    "name:ukr_x_preferred":[
        "Shepel\u2019"
    ],
    "name:ukr_x_variant":[
        "\u0428\u0435\u043f\u0435\u043b\u044c"
    ],
    "wof:name":"Shepel'",
    "wof:placetype":"locality"
},
  "geometry": {"coordinates":[25.11437,50.78875],"type":"Point"}
}