{
  "type": "Feature",
  "properties": {
    "gn:admin1_code":"15.0",
    "gn:asciiname":"Chornyy Ostriv",
    "gn:country_code":"UA",
    "gn:dem":271,
    "gn:feature_class":"P",
    "gn:feature_code":"PPL",
    "gn:name":"Chornyy Ostriv",
    "gn:population":0,
    "gn:timezone":"Europe/Kiev",
    "iso:country":"UA",
    "name:rus_x_preferred":[
        "Ch\u00ebrnyy Ostrov"
    ],
    "name:rus_x_variant":[
        "\u0427\u0451\u0440\u043d\u044b\u0439 \u041e\u0441\u0442\u0440\u043e\u0432"
    ],
    "name:ukr_x_preferred":[
        "Chornyy Ostriv"
    ],
    "name:ukr_x_variant":[
        "\u0427\u043e\u0440\u043d\u0438\u0439 \u041e\u0441\u0442\u0440\u0456\u0432"
    ],
    "name:und_x_variant":[
        "Ostruv"
    ],
    "wof:name":"Chornyy Ostriv",
    "wof:placetype":"locality"
},
  "geometry": {"coordinates":[24.26667,49.46667],"type":"Point"}
}