{
  "type": "Feature",
  "properties": {
    "gn:population":2800,
    "iso:country":"UA",
    "name:crh_x_preferred":[
        "Sm\u0131ga"
    ],
    "name:deu_x_preferred":[
        "Smyha"
    ],
    "name:fra_x_preferred":[
        "Orjiv"
    ],
    "name:pol_x_preferred":[
        "Orzew"
    ],
    "name:ron_x_preferred":[
        "Sm\u00eeha"
    ],
    "name:rus_x_preferred":[
        "\u041e\u0440\u0436\u0435\u0432"
    ],
    "name:rus_x_variant":[
        "\u0421\u043c\u044b\u0433\u0430"
    ],
    "name:ukr_x_preferred":[
        "\u0421\u043c\u0438\u0433\u0430"
    ],
    "name:unk_x_variant":[
        "Smyga"
    ],
    "name:zho_x_preferred":[
        "\u65af\u7c73\u52a0"
    ],
    "qs:a0":"\u0423\u043a\u0440\u0430\u0457\u043d\u0430",
    "qs:a1":"*\u0420\u0456\u0432\u043d\u0435\u043d\u0441\u044c\u043a\u0430",
    "qs:a1_alt":"Rivnens'ka",
    "qs:a1r":"0",
    "qs:a2":"\u0414\u0443\u0431\u0435\u043d\u0441\u044c\u043a\u0438\u0439",
    "qs:a2_alt":"Dubens'kyi",
    "qs:adm0":"\u0423\u043a\u0440\u0430\u0457\u043d\u0430",
    "qs:la_lc":"*",
    "qs:level":"locality",
    "qs:loc":"\u0421\u043c\u0438\u0433\u0430",
    "qs:loc_alt":"Smyha",
    "qs:pop":0,
    "qs:type":"buffered point",
    "wd:wordcount":99,
    "wof:name":"\u0421\u043c\u0438\u0433\u0430",
    "wof:placetype":"locality",
    "wof:population":2800
},
  "geometry": {"coordinates":[25.769288,50.2343],"type":"Point"}
}