{
  "type": "Feature",
  "properties": {
    "gn:admin1_code":"18.0",
    "gn:asciiname":"Toybik",
    "gn:country_code":"UA",
    "gn:dem":94,
    "gn:feature_class":"P",
    "gn:feature_code":"PPL",
    "gn:name":"Toybik",
    "gn:population":0,
    "gn:timezone":"Europe/Kiev",
    "iso:country":"UA",
    "name:ukr_x_preferred":[
        "Toybik"
    ],
    "name:ukr_x_variant":[
        "\u0422\u043e\u0439\u0431\u0456\u043a"
    ],
    "wof:name":"Toybik",
    "wof:placetype":"locality"
},
  "geometry": {"coordinates":[34.94873,49.65661],"type":"Point"}
}