{
  "type": "Feature",
  "properties": {
    "gn:admin1_code":"13.0",
    "gn:asciiname":"Pivni",
    "gn:country_code":"UA",
    "gn:dem":193,
    "gn:feature_class":"P",
    "gn:feature_code":"PPL",
    "gn:name":"Pivni",
    "gn:population":0,
    "gn:timezone":"Europe/Kiev",
    "iso:country":"UA",
    "name:ukr_x_preferred":[
        "Pivni"
    ],
    "name:ukr_x_variant":[
        "\u041f\u0456\u0432\u043d\u0456"
    ],
    "wof:name":"Pivni",
    "wof:placetype":"locality"
},
  "geometry": {"coordinates":[29.72754,50.00841],"type":"Point"}
}