{
  "type": "Feature",
  "properties": {
    "gn:admin1_code":"24.0",
    "gn:asciiname":"Horodne",
    "gn:country_code":"UA",
    "gn:dem":192,
    "gn:feature_class":"P",
    "gn:feature_code":"PPL",
    "gn:name":"Horodne",
    "gn:population":0,
    "gn:timezone":"Europe/Kiev",
    "iso:country":"UA",
    "name:ukr_x_preferred":[
        "Horodne"
    ],
    "name:ukr_x_variant":[
        "\u0413\u043e\u0440\u043e\u0434\u043d\u0435"
    ],
    "name:und_x_variant":[
        "Horodno",
        "Gorodno",
        "Gorodneye"
    ],
    "wof:name":"Horodne",
    "wof:placetype":"locality"
},
  "geometry": {"coordinates":[24.12683,51.27198],"type":"Point"}
}