{
  "type": "Feature",
  "properties": {
    "gn:admin1_code":"9.0",
    "gn:asciiname":"Chekhi",
    "gn:country_code":"UA",
    "gn:dem":280,
    "gn:feature_class":"P",
    "gn:feature_code":"PPL",
    "gn:name":"Chekhi",
    "gn:population":0,
    "gn:timezone":"Europe/Kiev",
    "iso:country":"UA",
    "wof:name":"Chekhi",
    "wof:placetype":"locality"
},
  "geometry": {"coordinates":[27.65792,49.54844],"type":"Point"}
}