{
  "type": "Feature",
  "properties": {
    "gn:admin1_code":"16.0",
    "gn:asciiname":"Zelenyye Koshary",
    "gn:country_code":"UA",
    "gn:dem":141,
    "gn:feature_class":"P",
    "gn:feature_code":"PPL",
    "gn:name":"Zel\u00ebnyye Koshary",
    "gn:population":0,
    "gn:timezone":"Europe/Kiev",
    "iso:country":"UA",
    "wof:name":"Zelenyye Koshary",
    "wof:placetype":"locality"
},
  "geometry": {"coordinates":[30.84018,47.88146],"type":"Point"}
}