{
  "type": "Feature",
  "properties": {
    "gn:admin1_code":"17.0",
    "gn:asciiname":"Ponyatovka",
    "gn:country_code":"UA",
    "gn:dem":112,
    "gn:feature_class":"P",
    "gn:feature_code":"PPL",
    "gn:name":"Ponyatovka",
    "gn:population":0,
    "gn:timezone":"Europe/Kiev",
    "iso:country":"UA",
    "name:und_x_variant":[
        "Ponyativka",
        "Ponyatovka"
    ],
    "wof:name":"Ponyatovka",
    "wof:placetype":"locality"
},
  "geometry": {"coordinates":[30.16592,46.90332],"type":"Point"}
}