{
  "type": "Feature",
  "properties": {
    "gn:admin1_code":"06",
    "gn:asciiname":"Pidberezhzhya",
    "gn:country_code":"UA",
    "gn:dem":358,
    "gn:feature_class":"P",
    "gn:feature_code":"PPL",
    "gn:name":"Pidberezhzhya",
    "gn:population":0,
    "gn:timezone":"Europe/Kiev",
    "iso:country":"UA",
    "name:rus_x_preferred":[
        "Podberezh\u2019ye"
    ],
    "name:rus_x_variant":[
        "\u041f\u043e\u0434\u0431\u0435\u0440\u0435\u0436\u044c\u0435"
    ],
    "name:ukr_x_preferred":[
        "Pidberezhzhya"
    ],
    "name:ukr_x_variant":[
        "\u041f\u0456\u0434\u0431\u0435\u0440\u0435\u0436\u0436\u044f"
    ],
    "wof:name":"Pidberezhzhya",
    "wof:placetype":"locality"
},
  "geometry": {"coordinates":[23.91343,49.05566],"type":"Point"}
}