{
  "type": "Feature",
  "properties": {
    "gn:admin1_code":"18.0",
    "gn:asciiname":"Chykalivka",
    "gn:country_code":"UA",
    "gn:dem":67,
    "gn:feature_class":"P",
    "gn:feature_code":"PPL",
    "gn:name":"Chykalivka",
    "gn:population":0,
    "gn:timezone":"Europe/Kiev",
    "iso:country":"UA",
    "name:ukr_x_preferred":[
        "Chykalivka"
    ],
    "name:ukr_x_variant":[
        "\u0427\u0438\u043a\u0430\u043b\u0456\u0432\u043a\u0430"
    ],
    "name:und_x_variant":[
        "Chikalovka"
    ],
    "wof:name":"Chykalivka",
    "wof:placetype":"locality"
},
  "geometry": {"coordinates":[33.59653,48.98653],"type":"Point"}
}