{
  "type": "Feature",
  "properties": {
    "iso:country":"UA",
    "name:eng_x_preferred":[
        "Turyatka"
    ],
    "name:ron_x_preferred":[
        "Comuna Tureatca"
    ],
    "name:ukr_x_preferred":[
        "\u0422\u0443\u0440\u044f\u0442\u0441\u044c\u043a\u0430 \u0441\u0456\u043b\u044c\u0441\u044c\u043a\u0430 \u0440\u0430\u0434\u0430"
    ],
    "qs:a0":"\u0423\u043a\u0440\u0430\u0457\u043d\u0430",
    "qs:a1":"*\u0427\u0435\u0440\u043d\u0456\u0432\u0435\u0446\u044c\u043a\u0430",
    "qs:a1_alt":"Chernivets'ka",
    "qs:a1r":"0",
    "qs:a2":"\u0413\u043b\u0438\u0431\u043e\u0446\u044c\u043a\u0438\u0439",
    "qs:a2_alt":"Hlybots'kyi",
    "qs:adm0":"\u0423\u043a\u0440\u0430\u0457\u043d\u0430",
    "qs:la_lc":"*",
    "qs:level":"locality",
    "qs:loc":"\u0422\u0443\u0440\u044f\u0442\u043a\u0430",
    "qs:loc_alt":"Turiatka",
    "qs:pop":0,
    "qs:type":"buffered point",
    "wd:wordcount":43,
    "wof:name":"\u0422\u0443\u0440\u044f\u0442\u043a\u0430",
    "wof:placetype":"locality"
},
  "geometry": {"coordinates":[26.14109,48.044042],"type":"Point"}
}