{
  "type": "Feature",
  "properties": {
    "gn:admin1_code":"16.0",
    "gn:asciiname":"Nadezhdovka",
    "gn:country_code":"UA",
    "gn:dem":52,
    "gn:feature_class":"P",
    "gn:feature_code":"PPL",
    "gn:name":"Nadezhdovka",
    "gn:population":0,
    "gn:timezone":"Europe/Kiev",
    "iso:country":"UA",
    "wof:name":"Nadezhdovka",
    "wof:placetype":"locality"
},
  "geometry": {"coordinates":[32.08333,47.21667],"type":"Point"}
}