{
  "type": "Feature",
  "properties": {
    "iso:country":"UA",
    "name:eng_x_preferred":[
        "Podlipnoye"
    ],
    "name:hye_x_preferred":[
        "\u054a\u0578\u0564\u056c\u056b\u057a\u0576\u0578\u0565"
    ],
    "name:nld_x_preferred":[
        "Pidlypne"
    ],
    "name:pol_x_preferred":[
        "Pidlypne"
    ],
    "name:ron_x_preferred":[
        "Pidl\u00eepne"
    ],
    "name:rus_x_preferred":[
        "\u041f\u043e\u0434\u043b\u0438\u043f\u043d\u043e\u0435"
    ],
    "name:ukr_x_preferred":[
        "Pidlypne"
    ],
    "name:ukr_x_variant":[
        "\u041f\u0456\u0434\u043b\u0438\u043f\u043d\u0435"
    ],
    "name:unk_x_variant":[
        "Podlipnoye"
    ],
    "qs:a0":"\u0423\u043a\u0440\u0430\u0457\u043d\u0430",
    "qs:a1":"*\u0421\u0443\u043c\u0441\u044c\u043a\u0430",
    "qs:a1_alt":"Sums'ka",
    "qs:a1r":"0",
    "qs:a2":"\u041a\u043e\u043d\u043e\u0442\u043e\u043f\u0441\u044c\u043a\u0438\u0439",
    "qs:a2_alt":"Konotops'kyi",
    "qs:adm0":"\u0423\u043a\u0440\u0430\u0457\u043d\u0430",
    "qs:la_lc":"*",
    "qs:level":"locality",
    "qs:loc":"\u041f\u0456\u0434\u043b\u0438\u043f\u043d\u0435",
    "qs:loc_alt":"Pidlypne",
    "qs:pop":0,
    "qs:type":"buffered point",
    "wof:name":"\u041f\u0456\u0434\u043b\u0438\u043f\u043d\u0435",
    "wof:placetype":"locality"
},
  "geometry": {"coordinates":[33.206677,51.195142],"type":"Point"}
}