{
  "type": "Feature",
  "properties": {
    "gn:gn_country":"UA",
    "gn:gn_fcode":"PPL",
    "gn:gn_pop":10988,
    "gn:population":10988,
    "iso:country":"UA",
    "name:rus_x_preferred":[
        "\u0412\u0438\u0441\u043e\u043a\u0438\u0439"
    ],
    "name:ukr_x_preferred":[
        "\u0412\u0438\u0441\u043e\u043a\u0438\u0439"
    ],
    "name:unk_x_variant":[
        "Vysokiy"
    ],
    "qs_pg:aaroncc":"UA",
    "qs_pg:gn_country":"UA",
    "qs_pg:gn_fcode":"PPL",
    "qs_pg:gn_pop":10988,
    "qs_pg:name":"Vysokyy",
    "qs_pg:photos_9r":0,
    "qs_pg:photos_sr":0,
    "qs_pg:pop_sr":6,
    "qs_pg:qs_pg_placetype":"locality",
    "wof:name":"Vysokyy",
    "wof:placetype":"locality",
    "wof:population":10988
},
  "geometry": {"coordinates":[36.1321,49.8892],"type":"Point"}
}