{
  "type": "Feature",
  "properties": {
    "gn:admin1_code":"13",
    "gn:asciiname":"Chornibyl-2",
    "gn:country_code":"UA",
    "gn:dem":132,
    "gn:feature_class":"P",
    "gn:feature_code":"PPL",
    "gn:name":"Chornibyl-2",
    "gn:population":1,
    "gn:timezone":"Europe/Kiev",
    "iso:country":"UA",
    "name:eng_x_preferred":[
        "Chornobyl-2"
    ],
    "name:rus_x_preferred":[
        "\u0427\u0435\u0440\u043d\u043e\u0431\u044b\u043b\u044c-2"
    ],
    "name:ukr_x_preferred":[
        "\u0427\u043e\u0440\u043d\u043e\u0431\u0438\u043b\u044c-2"
    ],
    "wof:name":"Chornibyl-2",
    "wof:placetype":"locality",
    "wof:population":1
},
  "geometry": {"coordinates":[30.06782,51.30392],"type":"Point"}
}