{
  "type": "Feature",
  "properties": {
    "gn:admin1_code":"2.0",
    "gn:asciiname":"Zan'ky",
    "gn:country_code":"UA",
    "gn:dem":126,
    "gn:feature_class":"P",
    "gn:feature_code":"PPL",
    "gn:name":"Zan\u2019ky",
    "gn:population":0,
    "gn:timezone":"Europe/Kiev",
    "iso:country":"UA",
    "name:rus_x_preferred":[
        "Zan\u2019ki"
    ],
    "name:ukr_x_preferred":[
        "Zan\u2019ky"
    ],
    "name:ukr_x_variant":[
        "\u0417\u0430\u043d\u044c\u043a\u0438"
    ],
    "wof:name":"Zan'ky",
    "wof:placetype":"locality"
},
  "geometry": {"coordinates":[31.9791,51.19703],"type":"Point"}
}