{
  "type": "Feature",
  "properties": {
    "gn:admin1_code":"19.0",
    "gn:asciiname":"Dovhalivka",
    "gn:country_code":"UA",
    "gn:dem":205,
    "gn:feature_class":"P",
    "gn:feature_code":"PPL",
    "gn:name":"Dovhalivka",
    "gn:population":0,
    "gn:timezone":"Europe/Kiev",
    "iso:country":"UA",
    "name:ukr_x_preferred":[
        "Dovhalivka"
    ],
    "name:ukr_x_variant":[
        "\u0414\u043e\u0432\u0433\u0430\u043b\u0456\u0432\u043a\u0430"
    ],
    "name:und_x_variant":[
        "Dovgalevka"
    ],
    "wof:name":"Dovhalivka",
    "wof:placetype":"locality"
},
  "geometry": {"coordinates":[25.364,50.28868],"type":"Point"}
}