{
  "type": "Feature",
  "properties": {
    "gn:admin1_code":"21.0",
    "gn:asciiname":"Mel'nyky",
    "gn:country_code":"UA",
    "gn:dem":109,
    "gn:feature_class":"P",
    "gn:feature_code":"PPL",
    "gn:name":"Mel\u2019nyky",
    "gn:population":0,
    "gn:timezone":"Europe/Kiev",
    "iso:country":"UA",
    "name:rus_x_preferred":[
        "Mel\u2019niki"
    ],
    "name:ukr_x_preferred":[
        "Mel\u2019nyky"
    ],
    "name:ukr_x_variant":[
        "\u041c\u0435\u043b\u044c\u043d\u0438\u043a\u0438"
    ],
    "wof:name":"Mel'nyky",
    "wof:placetype":"locality"
},
  "geometry": {"coordinates":[33.3608,50.5847],"type":"Point"}
}