{
  "type": "Feature",
  "properties": {
    "gn:admin1_code":"23.0",
    "gn:asciiname":"Dubynky",
    "gn:country_code":"UA",
    "gn:dem":261,
    "gn:feature_class":"P",
    "gn:feature_code":"PPL",
    "gn:name":"Dubynky",
    "gn:population":0,
    "gn:timezone":"Europe/Kiev",
    "iso:country":"UA",
    "name:ukr_x_preferred":[
        "Dubynky"
    ],
    "name:und_x_variant":[
        "\u0414\u0443\u0431\u0438\u043d\u043a\u0438",
        "Dubinki"
    ],
    "wof:name":"Dubynky",
    "wof:placetype":"locality"
},
  "geometry": {"coordinates":[28.17164,48.67919000000001],"type":"Point"}
}