{
  "type": "Feature",
  "properties": {
    "gn:admin1_code":"7.0",
    "gn:asciiname":"Sontsedarivka",
    "gn:country_code":"UA",
    "gn:dem":172,
    "gn:feature_class":"P",
    "gn:feature_code":"PPL",
    "gn:name":"Sontsedarivka",
    "gn:population":0,
    "gn:timezone":"Europe/Kiev",
    "iso:country":"UA",
    "name:ukr_x_preferred":[
        "Sontsedarivka"
    ],
    "name:ukr_x_variant":[
        "\u0421\u043e\u043d\u0446\u0435\u0434\u0430\u0440\u0456\u0432\u043a\u0430"
    ],
    "wof:name":"Sontsedarivka",
    "wof:placetype":"locality"
},
  "geometry": {"coordinates":[35.35542,49.94531],"type":"Point"}
}