{
  "type": "Feature",
  "properties": {
    "gn:admin1_code":"16.0",
    "gn:asciiname":"Novovladimirovka",
    "gn:country_code":"UA",
    "gn:dem":71,
    "gn:feature_class":"P",
    "gn:feature_code":"PPL",
    "gn:name":"Novovladimirovka",
    "gn:population":0,
    "gn:timezone":"Europe/Kiev",
    "iso:country":"UA",
    "wof:name":"Novovladimirovka",
    "wof:placetype":"locality"
},
  "geometry": {"coordinates":[32.73177,47.44378],"type":"Point"}
}