{
  "type": "Feature",
  "properties": {
    "gn:admin1_code":"11.0",
    "gn:admin2_code":"709333",
    "gn:admin3_code":"11152861.0",
    "gn:asciiname":"Aprelevka",
    "gn:country_code":"UA",
    "gn:dem":12,
    "gn:elevation":"12.0",
    "gn:feature_class":"P",
    "gn:feature_code":"PPL",
    "gn:name":"Aprelevka",
    "gn:population":281,
    "gn:timezone":"Europe/Simferopol",
    "iso:country":"UA",
    "name:eng_x_preferred":[
        "Aprelevka"
    ],
    "name:rus_x_preferred":[
        "\u0410\u043f\u0440\u0435\u043b\u0435\u0432\u043a\u0430"
    ],
    "name:ukr_x_preferred":[
        "\u0410\u043f\u0440\u0435\u043b\u0456\u0432\u043a\u0430"
    ],
    "wof:name":"Aprelevka",
    "wof:placetype":"locality",
    "wof:population":281
},
  "geometry": {"coordinates":[34.74008,45.68839000000001],"type":"Point"}
}