{
  "type": "Feature",
  "properties": {
    "gn:admin1_code":"27.0",
    "gn:asciiname":"Budo-Litky",
    "gn:country_code":"UA",
    "gn:dem":197,
    "gn:feature_class":"P",
    "gn:feature_code":"PPL",
    "gn:name":"Budo-Litky",
    "gn:population":0,
    "gn:timezone":"Europe/Kiev",
    "iso:country":"UA",
    "name:ukr_x_preferred":[
        "Budo-Litky"
    ],
    "name:ukr_x_variant":[
        "\u0411\u0443\u0434\u043e-\u041b\u0456\u0442\u043a\u0438"
    ],
    "name:und_x_variant":[
        "Buda Litkovskaya",
        "Budo-Litki"
    ],
    "wof:name":"Budo-Litky",
    "wof:placetype":"locality"
},
  "geometry": {"coordinates":[28.34427,50.97812],"type":"Point"}
}