{
  "type": "Feature",
  "properties": {
    "gn:admin1_code":"21.0",
    "gn:asciiname":"Zhily",
    "gn:country_code":"UA",
    "gn:dem":117,
    "gn:feature_class":"P",
    "gn:feature_code":"PPL",
    "gn:name":"Zhily",
    "gn:population":0,
    "gn:timezone":"Europe/Kiev",
    "iso:country":"UA",
    "wof:name":"Zhily",
    "wof:placetype":"locality"
},
  "geometry": {"coordinates":[35.04167,50.32583],"type":"Point"}
}