{
  "type": "Feature",
  "properties": {
    "gn:admin1_code":"4.0",
    "gn:asciiname":"Hrushuvato-Krynychne",
    "gn:country_code":"UA",
    "gn:dem":77,
    "gn:feature_class":"P",
    "gn:feature_code":"PPL",
    "gn:name":"Hrushuvato-Krynychne",
    "gn:population":0,
    "gn:timezone":"Europe/Kiev",
    "iso:country":"UA",
    "name:ukr_x_preferred":[
        "Hrushuvato-Krynychne"
    ],
    "name:ukr_x_variant":[
        "\u0413\u0440\u0443\u0448\u0443\u0432\u0430\u0442\u043e-\u041a\u0440\u0438\u043d\u0438\u0447\u043d\u0435"
    ],
    "name:und_x_variant":[
        "Grushevato-Krinichnoye"
    ],
    "wof:name":"Hrushuvato-Krynychne",
    "wof:placetype":"locality"
},
  "geometry": {"coordinates":[35.24157,48.25707],"type":"Point"}
}