{
  "type": "Feature",
  "properties": {
    "gn:admin1_code":"21.0",
    "gn:asciiname":"Sakhans'ke",
    "gn:country_code":"UA",
    "gn:dem":161,
    "gn:feature_class":"P",
    "gn:feature_code":"PPL",
    "gn:name":"Sakhans\u2019ke",
    "gn:population":0,
    "gn:timezone":"Europe/Kiev",
    "iso:country":"UA",
    "name:ukr_x_preferred":[
        "Sakhans\u2019ke"
    ],
    "name:ukr_x_variant":[
        "\u0421\u0430\u0445\u0430\u043d\u0441\u044c\u043a\u0435"
    ],
    "name:und_x_variant":[
        "Sakhanskoye"
    ],
    "wof:name":"Sakhans'ke",
    "wof:placetype":"locality"
},
  "geometry": {"coordinates":[33.62739000000001,50.58388],"type":"Point"}
}