{
  "type": "Feature",
  "properties": {
    "gn:admin1_code":"15.0",
    "gn:asciiname":"Khodovitsa",
    "gn:country_code":"UA",
    "gn:dem":291,
    "gn:feature_class":"P",
    "gn:feature_code":"PPL",
    "gn:name":"Khodovitsa",
    "gn:population":0,
    "gn:timezone":"Europe/Kiev",
    "iso:country":"UA",
    "wof:name":"Khodovitsa",
    "wof:placetype":"locality"
},
  "geometry": {"coordinates":[23.91667,49.76667],"type":"Point"}
}