{
  "type": "Feature",
  "properties": {
    "gn:admin1_code":"5.0",
    "gn:asciiname":"Sontseve",
    "gn:country_code":"UA",
    "gn:dem":133,
    "gn:feature_class":"P",
    "gn:feature_code":"PPL",
    "gn:name":"Sontseve",
    "gn:population":0,
    "gn:timezone":"Europe/Kiev",
    "iso:country":"UA",
    "name:ukr_x_preferred":[
        "\u0421\u043e\u043d\u0446\u0435\u0432\u0435"
    ],
    "name:und_x_variant":[
        "Staroye Solntsevo",
        "Solntsevo",
        "Sontseve"
    ],
    "wof:name":"Sontseve",
    "wof:placetype":"locality"
},
  "geometry": {"coordinates":[38.03153,47.53982],"type":"Point"}
}