{
  "type": "Feature",
  "properties": {
    "gn:admin1_code":"15",
    "gn:asciiname":"Banya Lysovyts'ka",
    "gn:country_code":"UA",
    "gn:dem":356,
    "gn:feature_class":"P",
    "gn:feature_code":"PPL",
    "gn:name":"Banya Lysovyts\u2019ka",
    "gn:population":0,
    "gn:timezone":"Europe/Kiev",
    "iso:country":"UA",
    "name:rus_x_preferred":[
        "\u0411\u0430\u043d\u044f"
    ],
    "name:ukr_x_preferred":[
        "Banya Lysovyts\u2019ka"
    ],
    "name:ukr_x_variant":[
        "\u0411\u0430\u043d\u044f \u041b\u0438\u0441\u043e\u0432\u0438\u0446\u044c\u043a\u0430"
    ],
    "name:und_x_variant":[
        "Banya"
    ],
    "wof:name":"Banya Lysovyts'ka",
    "wof:placetype":"locality"
},
  "geometry": {"coordinates":[23.88332,49.13128],"type":"Point"}
}