{
  "type": "Feature",
  "properties": {
    "gn:admin1_code":"24.0",
    "gn:asciiname":"Kopyllya",
    "gn:country_code":"UA",
    "gn:dem":173,
    "gn:feature_class":"P",
    "gn:feature_code":"PPL",
    "gn:name":"Kopyllya",
    "gn:population":0,
    "gn:timezone":"Europe/Kiev",
    "iso:country":"UA",
    "name:ukr_x_preferred":[
        "Kopyllya"
    ],
    "name:ukr_x_variant":[
        "\u041a\u043e\u043f\u0438\u043b\u043b\u044f"
    ],
    "name:und_x_variant":[
        "Kopyle",
        "Kopyl\u2019ye"
    ],
    "wof:name":"Kopyllya",
    "wof:placetype":"locality"
},
  "geometry": {"coordinates":[25.59564,51.11306],"type":"Point"}
}