{
  "type": "Feature",
  "properties": {
    "gn:admin1_code":"9.0",
    "gn:asciiname":"Zhemelintsy",
    "gn:country_code":"UA",
    "gn:dem":244,
    "gn:feature_class":"P",
    "gn:feature_code":"PPL",
    "gn:name":"Zhemelintsy",
    "gn:population":0,
    "gn:timezone":"Europe/Kiev",
    "iso:country":"UA",
    "wof:name":"Zhemelintsy",
    "wof:placetype":"locality"
},
  "geometry": {"coordinates":[26.41226,49.97864000000001],"type":"Point"}
}