{
  "type": "Feature",
  "properties": {
    "gn:admin1_code":"2.0",
    "gn:asciiname":"Bezborod'kiv",
    "gn:country_code":"UA",
    "gn:dem":131,
    "gn:feature_class":"P",
    "gn:feature_code":"PPL",
    "gn:name":"Bezborod\u2019kiv",
    "gn:population":0,
    "gn:timezone":"Europe/Kiev",
    "iso:country":"UA",
    "name:rus_x_preferred":[
        "Bezborod\u2019kov"
    ],
    "name:ukr_x_preferred":[
        "Bezborod\u2019kiv"
    ],
    "name:ukr_x_variant":[
        "\u0411\u0435\u0437\u0431\u043e\u0440\u043e\u0434\u044c\u043a\u0456\u0432"
    ],
    "wof:name":"Bezborod'kiv",
    "wof:placetype":"locality"
},
  "geometry": {"coordinates":[32.24378,50.93029],"type":"Point"}
}