{
  "type": "Feature",
  "properties": {
    "gn:admin1_code":"27.0",
    "gn:asciiname":"Pishchiv",
    "gn:country_code":"UA",
    "gn:dem":208,
    "gn:feature_class":"P",
    "gn:feature_code":"PPL",
    "gn:name":"Pishchiv",
    "gn:population":0,
    "gn:timezone":"Europe/Kiev",
    "iso:country":"UA",
    "name:ukr_x_preferred":[
        "Pishchiv"
    ],
    "name:ukr_x_variant":[
        "\u041f\u0456\u0449\u0456\u0432"
    ],
    "name:und_x_variant":[
        "Pishchevo",
        "Pishchev"
    ],
    "wof:name":"Pishchiv",
    "wof:placetype":"locality"
},
  "geometry": {"coordinates":[27.31704,50.6065],"type":"Point"}
}