{
  "type": "Feature",
  "properties": {
    "gn:admin1_code":"21.0",
    "gn:asciiname":"Vyntorivka",
    "gn:country_code":"UA",
    "gn:dem":170,
    "gn:feature_class":"P",
    "gn:feature_code":"PPL",
    "gn:name":"Vyntorivka",
    "gn:population":0,
    "gn:timezone":"Europe/Kiev",
    "iso:country":"UA",
    "name:ukr_x_preferred":[
        "Vyntorivka"
    ],
    "name:ukr_x_variant":[
        "\u0412\u0438\u043d\u0442\u043e\u0440\u0456\u0432\u043a\u0430"
    ],
    "wof:name":"Vyntorivka",
    "wof:placetype":"locality"
},
  "geometry": {"coordinates":[33.9533,52.23985],"type":"Point"}
}