{
  "type": "Feature",
  "properties": {
    "gn:admin1_code":"7.0",
    "gn:asciiname":"Novo-Ivanovka",
    "gn:cc2":"UA",
    "gn:country_code":"UA",
    "gn:dem":125,
    "gn:feature_class":"P",
    "gn:feature_code":"PPL",
    "gn:name":"Novo-Ivanovka",
    "gn:population":0,
    "gn:timezone":"Europe/Kiev",
    "iso:country":"UA",
    "name:und_x_variant":[
        "Novaya Ivanovka",
        "Novo-Ivanovka"
    ],
    "wof:name":"Novo-Ivanovka",
    "wof:placetype":"locality"
},
  "geometry": {"coordinates":[35.33333,49.86667],"type":"Point"}
}