{
  "type": "Feature",
  "properties": {
    "gn:admin1_code":"16.0",
    "gn:asciiname":"Otradnoye",
    "gn:country_code":"UA",
    "gn:dem":103,
    "gn:feature_class":"P",
    "gn:feature_code":"PPL",
    "gn:name":"Otradnoye",
    "gn:population":0,
    "gn:timezone":"Europe/Kiev",
    "iso:country":"UA",
    "wof:name":"Otradnoye",
    "wof:placetype":"locality"
},
  "geometry": {"coordinates":[31.03333,48.06667],"type":"Point"}
}