{
  "type": "Feature",
  "properties": {
    "gn:admin1_code":"11.0",
    "gn:admin2_code":"695741",
    "gn:admin3_code":"11153038.0",
    "gn:asciiname":"Bakhchevka",
    "gn:country_code":"UA",
    "gn:dem":78,
    "gn:elevation":"76.0",
    "gn:feature_class":"P",
    "gn:feature_code":"PPL",
    "gn:name":"Bakhchevka",
    "gn:population":46,
    "gn:timezone":"Europe/Simferopol",
    "iso:country":"UA",
    "name:eng_x_preferred":[
        "Bakhchevka"
    ],
    "name:rus_x_historical":[
        "\u0410\u043a-\u0421\u0430\u043a\u0430\u0301\u043b-\u041c\u0435\u0440\u043a\u0438\u0301\u0442"
    ],
    "name:rus_x_preferred":[
        "\u0411\u0430\u0445\u0447\u0451\u0432\u043a\u0430"
    ],
    "name:rus_x_variant":[
        "\u0410\u043a-\u0421\u0430\u043a\u0430\u0301\u043b-\u041c\u0435\u0440\u043a\u0438\u0301\u0442"
    ],
    "name:ukr_x_preferred":[
        "\u0411\u0430\u0445\u0447\u0456\u0432\u043a\u0430"
    ],
    "wof:name":"Bakhchevka",
    "wof:placetype":"locality",
    "wof:population":46
},
  "geometry": {"coordinates":[33.41996,45.61293],"type":"Point"}
}