{
  "type": "Feature",
  "properties": {
    "gn:admin1_code":"13.0",
    "gn:asciiname":"Sosnivka",
    "gn:country_code":"UA",
    "gn:dem":132,
    "gn:feature_class":"P",
    "gn:feature_code":"PPL",
    "gn:name":"Sosnivka",
    "gn:population":0,
    "gn:timezone":"Europe/Kiev",
    "iso:country":"UA",
    "name:ukr_x_preferred":[
        "Sosnivka"
    ],
    "name:ukr_x_variant":[
        "\u0421\u043e\u0441\u043d\u0456\u0432\u043a\u0430"
    ],
    "name:und_x_variant":[
        "Sosnovka"
    ],
    "wof:name":"Sosnivka",
    "wof:placetype":"locality"
},
  "geometry": {"coordinates":[30.04108,50.79405],"type":"Point"}
}