{
  "type": "Feature",
  "properties": {
    "gn:admin1_code":"13.0",
    "gn:asciiname":"Sosnivka",
    "gn:country_code":"UA",
    "gn:dem":132,
    "gn:feature_class":"P",
    "gn:feature_code":"PPL",
    "gn:name":"Sosnivka",
    "gn:population":0,
    "gn:timezone":"Europe/Kiev",
    "iso:country":"UA",
    "name:bel_x_preferred":[
        "\u0421\u0430\u0441\u043d\u0456\u045e\u043a\u0430"
    ],
    "name:crh_x_preferred":[
        "Sosnivka"
    ],
    "name:deu_x_preferred":[
        "Sosniwka"
    ],
    "name:fas_x_preferred":[
        "\u0633\u0648\u0633\u0646\u0648\u0641\u06a9\u0627"
    ],
    "name:fra_x_preferred":[
        "Sosnivka"
    ],
    "name:hsb_x_preferred":[
        "Sosniwka"
    ],
    "name:hye_x_preferred":[
        "\u054d\u0578\u057d\u0576\u0578\u057e\u056f\u0561"
    ],
    "name:ita_x_preferred":[
        "Sosnivka"
    ],
    "name:kat_x_preferred":[
        "\u10e1\u10dd\u10e1\u10dc\u10dd\u10d5\u10d9\u10d0"
    ],
    "name:lav_x_preferred":[
        "Sos\u0146ivka"
    ],
    "name:nno_x_preferred":[
        "Sosnivka"
    ],
    "name:nor_x_preferred":[
        "Sosnivka"
    ],
    "name:pol_x_preferred":[
        "Sosn\u00f3wka"
    ],
    "name:ron_x_preferred":[
        "Sosnivka"
    ],
    "name:rus_x_preferred":[
        "\u0421\u043e\u0441\u043d\u043e\u0432\u043a\u0430"
    ],
    "name:ukr_x_preferred":[
        "Sosnivka"
    ],
    "name:ukr_x_variant":[
        "\u0421\u043e\u0441\u043d\u0456\u0432\u043a\u0430"
    ],
    "name:und_x_variant":[
        "Sosnovka"
    ],
    "name:vie_x_preferred":[
        "Sosnivka"
    ],
    "name:zho_x_preferred":[
        "\u7d22\u65af\u5c3c\u592b\u5361"
    ],
    "wof:name":"Sosnivka",
    "wof:placetype":"locality"
},
  "geometry": {"coordinates":[30.04108,50.79405],"type":"Point"}
}