{
  "type": "Feature",
  "properties": {
    "gn:admin1_code":"14.0",
    "gn:asciiname":"Kuplyuvate",
    "gn:country_code":"UA",
    "gn:dem":164,
    "gn:feature_class":"P",
    "gn:feature_code":"PPL",
    "gn:name":"Kuplyuvate",
    "gn:population":0,
    "gn:timezone":"Europe/Zaporozhye",
    "iso:country":"UA",
    "name:ukr_x_preferred":[
        "Kuplyuvate"
    ],
    "name:ukr_x_variant":[
        "\u041a\u0443\u043f\u043b\u044e\u0432\u0430\u0442\u0435"
    ],
    "wof:name":"Kuplyuvate",
    "wof:placetype":"locality"
},
  "geometry": {"coordinates":[38.77343,49.72587],"type":"Point"}
}