{
  "type": "Feature",
  "properties": {
    "gn:country":"UA",
    "gn:fcode":"PPL",
    "gn:population":6109,
    "iso:country":"UA",
    "name:bel_x_preferred":[
        "\u041f\u0430\u043f\u0456\u043b\u044c\u043d\u044f"
    ],
    "name:ceb_x_preferred":[
        "Popil'nya"
    ],
    "name:crh_x_preferred":[
        "Popiln\u00e2"
    ],
    "name:deu_x_preferred":[
        "Popilnja"
    ],
    "name:eng_x_preferred":[
        "Popilnia"
    ],
    "name:fra_x_preferred":[
        "Popilnia"
    ],
    "name:pol_x_preferred":[
        "Popielnia"
    ],
    "name:pol_x_variant":[
        "Tel\u2019manove"
    ],
    "name:rus_x_preferred":[
        "\u041f\u043e\u043f\u0435\u043b\u044c\u043d\u044f"
    ],
    "name:sah_x_preferred":[
        "\u041f\u043e\u043f\u0435\u043b\u044c\u043d\u044f"
    ],
    "name:sco_x_preferred":[
        "Popilnia"
    ],
    "name:ukr_x_preferred":[
        "\u041f\u043e\u043f\u0456\u043b\u044c\u043d\u044f"
    ],
    "name:und_x_variant":[
        "Poelnja"
    ],
    "name:zho_x_preferred":[
        "\u6ce2\u76ae\u5229\u5c3c\u4e9e"
    ],
    "qs_pg:aaroncc":"UA",
    "qs_pg:gn_country":"UA",
    "qs_pg:gn_fcode":"PPL",
    "qs_pg:gn_pop":6109,
    "qs_pg:name":"Popil'nya",
    "qs_pg:photos_9r":0,
    "qs_pg:photos_sr":0,
    "qs_pg:pop_sr":5,
    "qs_pg:qs_pg_placetype":"locality",
    "wof:name":"Popil'nya",
    "wof:placetype":"locality",
    "wof:population":6109
},
  "geometry": {"coordinates":[29.44353,49.96652],"type":"Point"}
}