{
  "type": "Feature",
  "properties": {
    "iso:country":"UA",
    "name:deu_x_preferred":[
        "Staryj Misun"
    ],
    "name:eng_x_preferred":[
        "Staryi Mizun"
    ],
    "name:pol_x_preferred":[
        "Mizu\u0144 Stary"
    ],
    "name:ron_x_preferred":[
        "Star\u00eei Mizun"
    ],
    "name:rus_x_preferred":[
        "\u0421\u0442\u0430\u0440\u044b\u0439 \u041c\u0438\u0437\u0443\u043d\u044c"
    ],
    "name:ukr_x_preferred":[
        "Staryy Mizun\u2019"
    ],
    "name:ukr_x_variant":[
        "\u0421\u0442\u0430\u0440\u0438\u0439 \u041c\u0456\u0437\u0443\u043d\u044c"
    ],
    "name:zho_x_preferred":[
        "\u820a\u7c73\u5c0a"
    ],
    "qs:a0":"\u0423\u043a\u0440\u0430\u0457\u043d\u0430",
    "qs:a1":"*\u0406\u0432\u0430\u043d\u043e-\u0424\u0440\u0430\u043d\u043a\u0456\u0432\u0441\u044c\u043a\u0430",
    "qs:a1_alt":"Ivano-Frankivs'ka",
    "qs:a1r":"0",
    "qs:a2":"\u0414\u043e\u043b\u0438\u043d\u0441\u044c\u043a\u0438\u0439",
    "qs:a2_alt":"Dolyns'kyi",
    "qs:adm0":"\u0423\u043a\u0440\u0430\u0457\u043d\u0430",
    "qs:la_lc":"*",
    "qs:level":"locality",
    "qs:loc":"\u0421\u0442\u0430\u0440\u0438\u0439 \u041c\u0456\u0437\u0443\u043d\u044c",
    "qs:loc_alt":"Staryi Mizun",
    "qs:pop":0,
    "qs:type":"buffered point",
    "wof:name":"\u0421\u0442\u0430\u0440\u0438\u0439 \u041c\u0456\u0437\u0443\u043d\u044c",
    "wof:placetype":"locality"
},
  "geometry": {"coordinates":[23.883797,48.92756],"type":"Point"}
}