{
  "type": "Feature",
  "properties": {
    "gn:admin1_code":"23.0",
    "gn:asciiname":"Kustovets'ke",
    "gn:country_code":"UA",
    "gn:dem":293,
    "gn:feature_class":"P",
    "gn:feature_code":"PPL",
    "gn:name":"Kustovets\u2019ke",
    "gn:population":0,
    "gn:timezone":"Europe/Kiev",
    "iso:country":"UA",
    "name:ukr_x_preferred":[
        "Kustovets\u2019ke"
    ],
    "name:ukr_x_variant":[
        "\u041a\u0443\u0441\u0442\u043e\u0432\u0435\u0446\u044c\u043a\u0435"
    ],
    "name:und_x_variant":[
        "Kustovetska"
    ],
    "wof:name":"Kustovets'ke",
    "wof:placetype":"locality"
},
  "geometry": {"coordinates":[28.3784,49.68212],"type":"Point"}
}