{
  "type": "Feature",
  "properties": {
    "iso:country":"UA",
    "name:cat_x_preferred":[
        "M\u00edlove"
    ],
    "name:che_x_preferred":[
        "\u041c\u0438\u043b\u043e\u0432\u0438"
    ],
    "name:deu_x_preferred":[
        "Mylowe"
    ],
    "name:eng_x_preferred":[
        "Mylove"
    ],
    "name:fin_x_preferred":[
        "Myl\u043ev\u0435"
    ],
    "name:fra_x_preferred":[
        "Mylove"
    ],
    "name:jpn_x_preferred":[
        "\u30e0\u30a3\u30ed\u30f4\u30a7"
    ],
    "name:kat_x_preferred":[
        "\u10db\u10d8\u10da\u10dd\u10d5\u10d4"
    ],
    "name:lav_x_preferred":[
        "Milove"
    ],
    "name:nan_x_preferred":[
        "Mylove"
    ],
    "name:nno_x_preferred":[
        "Mylove"
    ],
    "name:nob_x_preferred":[
        "Mylove"
    ],
    "name:ron_x_preferred":[
        "M\u00eelove"
    ],
    "name:rus_x_preferred":[
        "\u041c\u044b\u043b\u043e\u0432\u043e\u0435"
    ],
    "name:swe_x_preferred":[
        "Mylove"
    ],
    "name:ukr_x_preferred":[
        "\u041c\u0438\u043b\u043e\u0432\u0435"
    ],
    "name:und_x_variant":[
        "Milovoye"
    ],
    "name:zho_x_preferred":[
        "\u7c73\u6d1b\u97cb"
    ],
    "qs:a0":"\u0423\u043a\u0440\u0430\u0457\u043d\u0430",
    "qs:a1":"*\u0425\u0435\u0440\u0441\u043e\u043d\u0441\u044c\u043a\u0430",
    "qs:a1_alt":"Khersons'ka",
    "qs:a1r":"0",
    "qs:a2":"\u0411\u0435\u0440\u0438\u0441\u043b\u0430\u0432\u0441\u044c\u043a\u0438\u0439",
    "qs:a2_alt":"Beryslavs'kyi",
    "qs:adm0":"\u0423\u043a\u0440\u0430\u0457\u043d\u0430",
    "qs:la_lc":"*",
    "qs:level":"locality",
    "qs:loc":"\u041c\u0438\u043b\u043e\u0432\u0435",
    "qs:loc_alt":"Mylove",
    "qs:pop":0,
    "qs:type":"buffered point",
    "wof:name":"\u041c\u0438\u043b\u043e\u0432\u0435",
    "wof:placetype":"locality"
},
  "geometry": {"coordinates":[33.628821,47.068662],"type":"Point"}
}