{
  "type": "Feature",
  "properties": {
    "gn:admin1_code":"25.0",
    "gn:asciiname":"Stebnyy",
    "gn:country_code":"UA",
    "gn:dem":808,
    "gn:feature_class":"P",
    "gn:feature_code":"PPL",
    "gn:name":"Stebnyy",
    "gn:population":0,
    "gn:timezone":"Europe/Uzhgorod",
    "iso:country":"UA",
    "name:ukr_x_preferred":[
        "Stebnyy"
    ],
    "name:ukr_x_variant":[
        "\u0421\u0442\u0435\u0431\u043d\u0438\u0439"
    ],
    "wof:name":"Stebnyy",
    "wof:placetype":"locality"
},
  "geometry": {"coordinates":[24.3665,48.30753],"type":"Point"}
}