{
  "type": "Feature",
  "properties": {
    "gn:admin1_code":"27.0",
    "gn:asciiname":"Ivankiv",
    "gn:country_code":"UA",
    "gn:dem":209,
    "gn:feature_class":"P",
    "gn:feature_code":"PPL",
    "gn:name":"Ivankiv",
    "gn:population":0,
    "gn:timezone":"Europe/Kiev",
    "iso:country":"UA",
    "name:bel_x_preferred":[
        "\u0406\u0432\u0430\u043d\u043a\u0456\u045e"
    ],
    "name:ceb_x_preferred":[
        "Ivankiv"
    ],
    "name:crh_x_preferred":[
        "\u0130vankiv"
    ],
    "name:deu_x_preferred":[
        "Iwankiw"
    ],
    "name:fin_x_preferred":[
        "Ivankiv"
    ],
    "name:hye_x_preferred":[
        "\u053b\u057e\u0561\u0576\u056f\u0578\u057e"
    ],
    "name:ita_x_preferred":[
        "Ivankiv"
    ],
    "name:lit_x_preferred":[
        "Ivankovas"
    ],
    "name:pol_x_preferred":[
        "Iwank\u00f3w"
    ],
    "name:ron_x_preferred":[
        "Ivankiv"
    ],
    "name:rus_x_preferred":[
        "\u0418\u0432\u0430\u043d\u043a\u043e\u0432"
    ],
    "name:sah_x_preferred":[
        "\u0418\u0432\u0430\u043d\u043a\u043e\u0432"
    ],
    "name:spa_x_preferred":[
        "Ivankiv"
    ],
    "name:ukr_x_preferred":[
        "Ivankiv"
    ],
    "name:ukr_x_variant":[
        "\u0406\u0432\u0430\u043d\u043a\u0456\u0432"
    ],
    "name:und_x_variant":[
        "Ivankovo",
        "Ivankov"
    ],
    "name:zho_x_preferred":[
        "\u4f0a\u842c\u57fa\u592b"
    ],
    "wof:name":"Ivankiv",
    "wof:placetype":"locality"
},
  "geometry": {"coordinates":[28.87741,50.13963],"type":"Point"}
}