{
  "type": "Feature",
  "properties": {
    "gn:admin1_code":"27.0",
    "gn:asciiname":"Ivankiv",
    "gn:country_code":"UA",
    "gn:dem":209,
    "gn:feature_class":"P",
    "gn:feature_code":"PPL",
    "gn:name":"Ivankiv",
    "gn:population":0,
    "gn:timezone":"Europe/Kiev",
    "iso:country":"UA",
    "name:ukr_x_preferred":[
        "Ivankiv"
    ],
    "name:ukr_x_variant":[
        "\u0406\u0432\u0430\u043d\u043a\u0456\u0432"
    ],
    "name:und_x_variant":[
        "Ivankovo",
        "Ivankov"
    ],
    "wof:name":"Ivankiv",
    "wof:placetype":"locality"
},
  "geometry": {"coordinates":[28.87741,50.13963],"type":"Point"}
}