{
  "type": "Feature",
  "properties": {
    "gn:admin1_code":"4.0",
    "gn:asciiname":"Pylypivka",
    "gn:country_code":"UA",
    "gn:dem":69,
    "gn:feature_class":"P",
    "gn:feature_code":"PPL",
    "gn:name":"Pylypivka",
    "gn:population":0,
    "gn:timezone":"Europe/Kiev",
    "iso:country":"UA",
    "name:ukr_x_preferred":[
        "Pylypivka"
    ],
    "name:ukr_x_variant":[
        "\u041f\u0438\u043b\u0438\u043f\u0456\u0432\u043a\u0430"
    ],
    "wof:name":"Pylypivka",
    "wof:placetype":"locality"
},
  "geometry": {"coordinates":[34.58573,48.90901],"type":"Point"}
}