{
  "type": "Feature",
  "properties": {
    "iso:country":"UA",
    "name:arm_x_preferred":[
        "\u053c\u0578\u0566\u0575\u0561\u0576\u057d\u056f\u056b"
    ],
    "name:dut_x_preferred":[
        "Cserj\u00e9s"
    ],
    "name:eng_x_preferred":[
        "Lozians'kii"
    ],
    "name:epo_x_preferred":[
        "Lozjanskij"
    ],
    "name:hun_x_preferred":[
        "Cserj\u00e9s"
    ],
    "name:rum_x_preferred":[
        "Lozeansk\u00eei"
    ],
    "name:rus_x_preferred":[
        "\u041b\u043e\u0437\u044f\u043d\u0441\u043a\u0438\u0439"
    ],
    "name:ukr_x_preferred":[
        "\u041b\u043e\u0437\u044f\u043d\u0441\u044c\u043a\u0438\u0439"
    ],
    "name:unk_x_variant":[
        "Lozanskoye"
    ],
    "qs:a0":"\u0423\u043a\u0440\u0430\u0457\u043d\u0430",
    "qs:a1":"*\u0417\u0430\u043a\u0430\u0440\u043f\u0430\u0442\u0441\u044c\u043a\u0430",
    "qs:a1_alt":"Zakarpats'ka",
    "qs:a1r":"0",
    "qs:a2":"\u041c\u0456\u0436\u0433\u0456\u0440\u0441\u044c\u043a\u0438\u0439",
    "qs:a2_alt":"Mizhhirs'kyi",
    "qs:adm0":"\u0423\u043a\u0440\u0430\u0457\u043d\u0430",
    "qs:la_lc":"*",
    "qs:level":"locality",
    "qs:loc":"\u041b\u043e\u0437\u044f\u043d\u0441\u044c\u043a\u0438\u0439",
    "qs:loc_alt":"Lozians'kyi",
    "qs:pop":0,
    "qs:type":"buffered point",
    "wof:name":"\u041b\u043e\u0437\u044f\u043d\u0441\u044c\u043a\u0438\u0439",
    "wof:placetype":"locality"
},
  "geometry": {"coordinates":[23.477216,48.542112],"type":"Point"}
}