{
  "type": "Feature",
  "properties": {
    "gn:admin1_code":"7.0",
    "gn:asciiname":"Pershotravneve",
    "gn:country_code":"UA",
    "gn:dem":188,
    "gn:feature_class":"P",
    "gn:feature_code":"PPL",
    "gn:name":"Pershotravneve",
    "gn:population":0,
    "gn:timezone":"Europe/Kiev",
    "iso:country":"UA",
    "name:ukr_x_preferred":[
        "Pershotravneve"
    ],
    "name:und_x_variant":[
        "Kolonia Khutir Stepy",
        "Pershotravnevoye"
    ],
    "wof:name":"Pershotravneve",
    "wof:placetype":"locality"
},
  "geometry": {"coordinates":[37.85,49.38333],"type":"Point"}
}