{
  "type": "Feature",
  "properties": {
    "gn:admin1_code":"18.0",
    "gn:asciiname":"Birky",
    "gn:country_code":"UA",
    "gn:dem":82,
    "gn:feature_class":"P",
    "gn:feature_code":"PPL",
    "gn:name":"Birky",
    "gn:population":0,
    "gn:timezone":"Europe/Kiev",
    "iso:country":"UA",
    "name:ukr_x_preferred":[
        "Birky"
    ],
    "name:ukr_x_variant":[
        "\u0411\u0456\u0440\u043a\u0438"
    ],
    "name:und_x_variant":[
        "Borki",
        "Birki"
    ],
    "wof:name":"Birky",
    "wof:placetype":"locality"
},
  "geometry": {"coordinates":[33.80877,49.63979000000001],"type":"Point"}
}