{
  "type": "Feature",
  "properties": {
    "gn:admin1_code":"26.0",
    "gn:asciiname":"Danylo-Ivanivka",
    "gn:country_code":"UA",
    "gn:dem":14,
    "gn:feature_class":"P",
    "gn:feature_code":"PPL",
    "gn:name":"Danylo-Ivanivka",
    "gn:population":0,
    "gn:timezone":"Europe/Zaporozhye",
    "iso:country":"UA",
    "name:ukr_x_preferred":[
        "\u0414\u0430\u043d\u0438\u043b\u043e-\u0406\u0432\u0430\u043d\u0456\u0432\u043a\u0430"
    ],
    "name:und_x_variant":[
        "Danilo-Ivanovka",
        "Danylo-Ivanivka"
    ],
    "wof:name":"Danylo-Ivanivka",
    "wof:placetype":"locality"
},
  "geometry": {"coordinates":[35.28035999999999,46.75134],"type":"Point"}
}