{
  "type": "Feature",
  "properties": {
    "gn:admin1_code":"7.0",
    "gn:asciiname":"Dovhen'ke",
    "gn:country_code":"UA",
    "gn:dem":207,
    "gn:feature_class":"P",
    "gn:feature_code":"PPL",
    "gn:name":"Dovhen\u2019ke",
    "gn:population":0,
    "gn:timezone":"Europe/Kiev",
    "iso:country":"UA",
    "name:eng_x_preferred":[
        "Dolgen'koye"
    ],
    "name:rus_x_preferred":[
        "\u0414\u043e\u043b\u0433\u0435\u043d\u044c\u043a\u043e\u0435"
    ],
    "name:ukr_x_preferred":[
        "Dovhen\u2019ke"
    ],
    "name:und_x_variant":[
        "Dolgen\u2019kaya",
        "Dolgen\u2019koye"
    ],
    "wof:name":"Dovhen'ke",
    "wof:placetype":"locality"
},
  "geometry": {"coordinates":[37.32499,49.0157],"type":"Point"}
}