{
  "type": "Feature",
  "properties": {
    "gn:admin1_code":"14.0",
    "gn:asciiname":"Verkhn'oderevechka",
    "gn:country_code":"UA",
    "gn:dem":149,
    "gn:feature_class":"P",
    "gn:feature_code":"PPL",
    "gn:name":"Verkhn\u2019oderevechka",
    "gn:population":0,
    "gn:timezone":"Europe/Zaporozhye",
    "iso:country":"UA",
    "name:ukr_x_preferred":[
        "Verkhn\u2019oderevechka"
    ],
    "name:ukr_x_variant":[
        "\u0412\u0435\u0440\u0445\u043d\u044c\u043e\u0434\u0435\u0440\u0435\u0432\u0435\u0447\u043a\u0430"
    ],
    "name:und_x_variant":[
        "Khutor Verkhnyaya Derevechka",
        "Verkhnyaya Derevechka",
        "Verkhnederevechka"
    ],
    "wof:name":"Verkhn'oderevechka",
    "wof:placetype":"locality"
},
  "geometry": {"coordinates":[39.72426,48.19868],"type":"Point"}
}