{
  "type": "Feature",
  "properties": {
    "gn:admin1_code":"27.0",
    "gn:asciiname":"Orzhiv",
    "gn:country_code":"UA",
    "gn:dem":134,
    "gn:feature_class":"P",
    "gn:feature_code":"PPL",
    "gn:name":"Orzhiv",
    "gn:population":0,
    "gn:timezone":"Europe/Kiev",
    "iso:country":"UA",
    "name:bel_x_preferred":[
        "\u041e\u0440\u0436\u044b\u045e"
    ],
    "name:crh_x_preferred":[
        "Orjiv"
    ],
    "name:deu_x_preferred":[
        "Orschiw"
    ],
    "name:fra_x_preferred":[
        "Orjiv"
    ],
    "name:pol_x_preferred":[
        "Orzew"
    ],
    "name:rus_x_preferred":[
        "\u041e\u0440\u0436\u0435\u0432"
    ],
    "name:ukr_x_preferred":[
        "Orzhiv"
    ],
    "name:ukr_x_variant":[
        "\u041e\u0440\u0436\u0456\u0432"
    ],
    "name:zho_x_preferred":[
        "\u5967\u723e\u65e5\u592b"
    ],
    "wof:name":"Orzhiv",
    "wof:placetype":"locality"
},
  "geometry": {"coordinates":[28.99277,51.28393],"type":"Point"}
}