{
  "type": "Feature",
  "properties": {
    "gn:admin1_code":"27.0",
    "gn:asciiname":"Orzhiv",
    "gn:country_code":"UA",
    "gn:dem":134,
    "gn:feature_class":"P",
    "gn:feature_code":"PPL",
    "gn:name":"Orzhiv",
    "gn:population":0,
    "gn:timezone":"Europe/Kiev",
    "iso:country":"UA",
    "name:ukr_x_preferred":[
        "Orzhiv"
    ],
    "name:ukr_x_variant":[
        "\u041e\u0440\u0436\u0456\u0432"
    ],
    "wof:name":"Orzhiv",
    "wof:placetype":"locality"
},
  "geometry": {"coordinates":[28.99277,51.28393],"type":"Point"}
}