{
  "type": "Feature",
  "properties": {
    "gn:admin1_code":"8.0",
    "gn:asciiname":"Krasnaya Stantsiya",
    "gn:country_code":"UA",
    "gn:dem":47,
    "gn:feature_class":"P",
    "gn:feature_code":"PPL",
    "gn:name":"Krasnaya Stantsiya",
    "gn:population":0,
    "gn:timezone":"Europe/Kiev",
    "iso:country":"UA",
    "wof:name":"Krasnaya Stantsiya",
    "wof:placetype":"locality"
},
  "geometry": {"coordinates":[33.78333,46.76667],"type":"Point"}
}