{
  "type": "Feature",
  "properties": {
    "iso:country":"UA",
    "name:bel_x_preferred":[
        "\u0428\u0430\u0431\u0430\u043b\u044b\u043d\u0456\u045e"
    ],
    "name:eng_x_preferred":[
        "Shabalinov"
    ],
    "name:eng_x_variant":[
        "Shabalyniv"
    ],
    "name:ron_x_preferred":[
        "\u0218abal\u00eeniv"
    ],
    "name:rus_x_preferred":[
        "\u0428\u0430\u0431\u0430\u043b\u0438\u043d\u043e\u0432"
    ],
    "name:ukr_x_preferred":[
        "\u0428\u0430\u0431\u0430\u043b\u0438\u043d\u0456\u0432"
    ],
    "name:ukr_x_variant":[
        "Shabalyniv"
    ],
    "name:und_x_variant":[
        "Shabelinovo"
    ],
    "name:zho_x_preferred":[
        "\u6c99\u5df4\u5229\u5c3c\u592b"
    ],
    "qs:a0":"\u0423\u043a\u0440\u0430\u0457\u043d\u0430",
    "qs:a1":"*\u0427\u0435\u0440\u043d\u0456\u0433\u0456\u0432\u0441\u044c\u043a\u0430",
    "qs:a1_alt":"Chernihivs'ka",
    "qs:a1r":"0",
    "qs:a2":"\u041a\u043e\u0440\u043e\u043f\u0441\u044c\u043a\u0438\u0439",
    "qs:a2_alt":"Korops'kyi",
    "qs:adm0":"\u0423\u043a\u0440\u0430\u0457\u043d\u0430",
    "qs:la_lc":"*",
    "qs:level":"locality",
    "qs:loc":"\u0428\u0430\u0431\u0430\u043b\u0438\u043d\u0456\u0432",
    "qs:loc_alt":"Shabalyniv",
    "qs:pop":0,
    "qs:type":"buffered point",
    "wd:wordcount":195,
    "wof:name":"\u0428\u0430\u0431\u0430\u043b\u0438\u043d\u0456\u0432",
    "wof:placetype":"locality"
},
  "geometry": {"coordinates":[32.711144,51.520351],"type":"Point"}
}