{
  "type": "Feature",
  "properties": {
    "gn:admin1_code":"17.0",
    "gn:asciiname":"Stepanovka",
    "gn:cc2":"UA",
    "gn:country_code":"UA",
    "gn:dem":117,
    "gn:feature_class":"P",
    "gn:feature_code":"PPL",
    "gn:name":"Stepanovka",
    "gn:population":0,
    "gn:timezone":"Europe/Kiev",
    "iso:country":"UA",
    "name:und_x_variant":[
        "Yastremskaya",
        "Stepanovka"
    ],
    "wof:name":"Stepanovka",
    "wof:placetype":"locality"
},
  "geometry": {"coordinates":[30.56667,47.15],"type":"Point"}
}