{
  "type": "Feature",
  "properties": {
    "gn:admin1_code":"21.0",
    "gn:asciiname":"Sagaydachnyy",
    "gn:country_code":"UA",
    "gn:dem":185,
    "gn:feature_class":"P",
    "gn:feature_code":"PPL",
    "gn:name":"Sagaydachnyy",
    "gn:population":0,
    "gn:timezone":"Europe/Kiev",
    "iso:country":"UA",
    "wof:name":"Sagaydachnyy",
    "wof:placetype":"locality"
},
  "geometry": {"coordinates":[34.11944,51.90611],"type":"Point"}
}