{
  "type": "Feature",
  "properties": {
    "gn:admin1_code":"27.0",
    "gn:asciiname":"Kosyak",
    "gn:country_code":"UA",
    "gn:dem":204,
    "gn:feature_class":"P",
    "gn:feature_code":"PPL",
    "gn:name":"Kosyak",
    "gn:population":0,
    "gn:timezone":"Europe/Kiev",
    "iso:country":"UA",
    "name:ukr_x_preferred":[
        "Kosyak"
    ],
    "name:ukr_x_variant":[
        "\u041a\u043e\u0441\u044f\u043a"
    ],
    "wof:name":"Kosyak",
    "wof:placetype":"locality"
},
  "geometry": {"coordinates":[28.02363,50.95361],"type":"Point"}
}