{
  "type": "Feature",
  "properties": {
    "gn:admin1_code":"7.0",
    "gn:asciiname":"Ukrainka",
    "gn:country_code":"UA",
    "gn:dem":140,
    "gn:feature_class":"P",
    "gn:feature_code":"PPL",
    "gn:name":"Ukrainka",
    "gn:population":0,
    "gn:timezone":"Europe/Kiev",
    "iso:country":"UA",
    "wof:name":"Ukrainka",
    "wof:placetype":"locality"
},
  "geometry": {"coordinates":[36.43187,49.13678],"type":"Point"}
}