{
  "type": "Feature",
  "properties": {
    "gn:admin1_code":"7.0",
    "gn:asciiname":"Ukrainka",
    "gn:country_code":"UA",
    "gn:dem":140,
    "gn:feature_class":"P",
    "gn:feature_code":"PPL",
    "gn:name":"Ukrainka",
    "gn:population":0,
    "gn:timezone":"Europe/Kiev",
    "iso:country":"UA",
    "name:ceb_x_preferred":[
        "\u0423\u043a\u0440\u0430\u0438\u043d\u043a\u0430"
    ],
    "name:ces_x_preferred":[
        "Ukrajinka"
    ],
    "name:deu_x_preferred":[
        "Ukrajinka"
    ],
    "name:jpn_x_preferred":[
        "\u30a6\u30af\u30e9\u30a4\u30f3\u30ab"
    ],
    "name:kaz_x_preferred":[
        "\u0423\u043a\u0440\u0430\u0438\u043d\u043a\u0430"
    ],
    "name:pol_x_preferred":[
        "Ukrainka"
    ],
    "name:rus_x_preferred":[
        "\u0423\u043a\u0440\u0430\u0438\u043d\u043a\u0430"
    ],
    "name:ukr_x_preferred":[
        "\u0423\u043a\u0440\u0430\u0457\u043d\u043a\u0430"
    ],
    "name:zho_x_preferred":[
        "\u70cf\u514b\u862d\u5361"
    ],
    "wof:name":"Ukrainka",
    "wof:placetype":"locality"
},
  "geometry": {"coordinates":[36.43187,49.13678],"type":"Point"}
}