{
  "type": "Feature",
  "properties": {
    "iso:country":"UA",
    "name:ukr_x_preferred":[
        "Dovhoshyyi"
    ],
    "name:ukr_x_variant":[
        "\u0414\u043e\u0432\u0433\u043e\u0448\u0438\u0457"
    ],
    "name:und_x_variant":[
        "Dolkhoshiye"
    ],
    "qs:a0":"\u0423\u043a\u0440\u0430\u0457\u043d\u0430",
    "qs:a1":"*\u0420\u0456\u0432\u043d\u0435\u043d\u0441\u044c\u043a\u0430",
    "qs:a1_alt":"Rivnens'ka",
    "qs:a1r":"0",
    "qs:a2":"\u041c\u043b\u0438\u043d\u0456\u0432\u0441\u044c\u043a\u0438\u0439",
    "qs:a2_alt":"Mlynivs'kyi",
    "qs:adm0":"\u0423\u043a\u0440\u0430\u0457\u043d\u0430",
    "qs:la_lc":"*",
    "qs:level":"locality",
    "qs:loc":"\u0414\u043e\u0432\u0433\u043e\u0448\u0438\u0457",
    "qs:loc_alt":"Dovhoshyi",
    "qs:pop":0,
    "qs:type":"buffered point",
    "wof:name":"\u0414\u043e\u0432\u0433\u043e\u0448\u0438\u0457",
    "wof:placetype":"locality"
},
  "geometry": {"coordinates":[25.761546,50.608168],"type":"Point"}
}