{
  "type": "Feature",
  "properties": {
    "gn:admin1_code":"23.0",
    "gn:asciiname":"Belyy Rukav",
    "gn:country_code":"UA",
    "gn:dem":271,
    "gn:feature_class":"P",
    "gn:feature_code":"PPL",
    "gn:name":"Belyy Rukav",
    "gn:population":0,
    "gn:timezone":"Europe/Kiev",
    "iso:country":"UA",
    "name:und_x_variant":[
        "Bely Rukav",
        "Belyy Rukav"
    ],
    "wof:name":"Belyy Rukav",
    "wof:placetype":"locality"
},
  "geometry": {"coordinates":[28.1021,49.60706],"type":"Point"}
}