{
  "type": "Feature",
  "properties": {
    "gn:admin1_code":"26.0",
    "gn:asciiname":"Zelenchuk",
    "gn:country_code":"UA",
    "gn:dem":58,
    "gn:feature_class":"P",
    "gn:feature_code":"PPL",
    "gn:name":"Zelenchuk",
    "gn:population":0,
    "gn:timezone":"Europe/Zaporozhye",
    "iso:country":"UA",
    "name:ukr_x_preferred":[
        "Zelenchuk"
    ],
    "name:ukr_x_variant":[
        "\u0417\u0435\u043b\u0435\u043d\u0447\u0443\u043a"
    ],
    "wof:name":"Zelenchuk",
    "wof:placetype":"locality"
},
  "geometry": {"coordinates":[35.10725,46.90209],"type":"Point"}
}