{
  "type": "Feature",
  "properties": {
    "gn:admin1_code":"21.0",
    "gn:asciiname":"Snizhky",
    "gn:country_code":"UA",
    "gn:dem":172,
    "gn:feature_class":"P",
    "gn:feature_code":"PPL",
    "gn:name":"Snizhky",
    "gn:population":0,
    "gn:timezone":"Europe/Kiev",
    "iso:country":"UA",
    "name:ukr_x_preferred":[
        "Snizhky"
    ],
    "name:ukr_x_variant":[
        "\u0421\u043d\u0456\u0436\u043a\u0438"
    ],
    "name:und_x_variant":[
        "Snezhki",
        "Velikiye Snezhki"
    ],
    "wof:name":"Snizhky",
    "wof:placetype":"locality"
},
  "geometry": {"coordinates":[33.67699,51.02434],"type":"Point"}
}