{
  "type": "Feature",
  "properties": {
    "gn:admin1_code":"19.0",
    "gn:asciiname":"Mykulyn",
    "gn:country_code":"UA",
    "gn:dem":190,
    "gn:feature_class":"P",
    "gn:feature_code":"PPL",
    "gn:name":"Mykulyn",
    "gn:population":0,
    "gn:timezone":"Europe/Kiev",
    "iso:country":"UA",
    "name:ukr_x_preferred":[
        "Mykulyn"
    ],
    "name:ukr_x_variant":[
        "\u041c\u0438\u043a\u0443\u043b\u0438\u043d"
    ],
    "name:und_x_variant":[
        "Mikulin"
    ],
    "wof:name":"Mykulyn",
    "wof:placetype":"locality"
},
  "geometry": {"coordinates":[26.5232,50.66706],"type":"Point"}
}