{
  "type": "Feature",
  "properties": {
    "gn:admin1_code":"22.0",
    "gn:asciiname":"Kotsyubinchiki",
    "gn:country_code":"UA",
    "gn:dem":277,
    "gn:feature_class":"P",
    "gn:feature_code":"PPL",
    "gn:name":"Kotsyubinchiki",
    "gn:population":0,
    "gn:timezone":"Europe/Kiev",
    "iso:country":"UA",
    "name:und_x_variant":[
        "Kociubi\u0144czyki",
        "Kotsiubinchiki",
        "Kotsyubin\u2019chyki",
        "Kotsyubinchiki"
    ],
    "wof:name":"Kotsyubinchiki",
    "wof:placetype":"locality"
},
  "geometry": {"coordinates":[26.15961,48.95901],"type":"Point"}
}