{
  "type": "Feature",
  "properties": {
    "iso:country":"UA",
    "name:cat_x_preferred":[
        "BK Spartak Sant Petersburg"
    ],
    "name:che_x_preferred":[
        "\u0421\u043f\u0430\u0440\u0442\u0430\u043a"
    ],
    "name:deu_x_preferred":[
        "BK Spartak Sankt Petersburg"
    ],
    "name:deu_x_variant":[
        "Spartak"
    ],
    "name:eng_x_preferred":[
        "Spartak"
    ],
    "name:est_x_preferred":[
        "Spartak"
    ],
    "name:fin_x_preferred":[
        "BK Spartak Pietari"
    ],
    "name:fin_x_variant":[
        "Sp\u0430rt\u0430k"
    ],
    "name:fra_x_preferred":[
        "Spartak Saint-P\u00e9tersbourg"
    ],
    "name:heb_x_preferred":[
        "\u05e1\u05e4\u05e8\u05d8\u05e7 \u05e1\u05e0\u05e7\u05d8 \u05e4\u05d8\u05e8\u05d1\u05d5\u05e8\u05d2"
    ],
    "name:hrv_x_preferred":[
        "Spartak Sankt Peterburg"
    ],
    "name:hye_x_preferred":[
        "\u054d\u057a\u0561\u0580\u057f\u0561\u056f"
    ],
    "name:ita_x_preferred":[
        "Basketbol'nyj klub Spartak Sankt-Peterburg"
    ],
    "name:jpn_x_preferred":[
        "\u30b9\u30d1\u30eb\u30bf\u30af"
    ],
    "name:lav_x_preferred":[
        "Spartaka"
    ],
    "name:nan_x_preferred":[
        "Spartak"
    ],
    "name:nld_x_preferred":[
        "BK Spartak Sint-Petersburg"
    ],
    "name:nno_x_preferred":[
        "Spartak"
    ],
    "name:nob_x_preferred":[
        "Spartak"
    ],
    "name:pol_x_preferred":[
        "Spartak Petersburg"
    ],
    "name:rus_x_preferred":[
        "\u0421\u043f\u0430\u0440\u0442\u0430\u043a"
    ],
    "name:spa_x_preferred":[
        "BC Spartak de San Petersburgo"
    ],
    "name:srp_x_preferred":[
        "\u041a\u041a \u0421\u043f\u0430\u0440\u0442\u0430\u043a \u0421\u0430\u043d\u043a\u0442 \u041f\u0435\u0442\u0435\u0440\u0431\u0443\u0440\u0433"
    ],
    "name:tur_x_preferred":[
        "BK Spartak St. Petersburg"
    ],
    "name:ukr_x_preferred":[
        "\u0421\u043f\u0430\u0440\u0442\u0430\u043a"
    ],
    "name:zho_x_preferred":[
        "\u65af\u5e15\u723e\u5854\u514b"
    ],
    "qs:a0":"\u0423\u043a\u0440\u0430\u0457\u043d\u0430",
    "qs:a1":"*\u0414\u043e\u043d\u0435\u0446\u044c\u043a\u0430",
    "qs:a1_alt":"Donets'ka",
    "qs:a1r":"0",
    "qs:a2":"\u042f\u0441\u0438\u043d\u0443\u0432\u0430\u0442\u0441\u044c\u043a\u0438\u0439",
    "qs:a2_alt":"Yasynuvats'kyi",
    "qs:adm0":"\u0423\u043a\u0440\u0430\u0457\u043d\u0430",
    "qs:la_lc":"*",
    "qs:level":"locality",
    "qs:loc":"\u0421\u043f\u0430\u0440\u0442\u0430\u043a",
    "qs:loc_alt":"Spartak",
    "qs:pop":0,
    "qs:type":"buffered point",
    "wd:wordcount":152,
    "wof:name":"\u0421\u043f\u0430\u0440\u0442\u0430\u043a",
    "wof:placetype":"locality"
},
  "geometry": {"coordinates":[37.767341,48.08293],"type":"Point"}
}