{
  "type": "Feature",
  "properties": {
    "gn:admin1_code":"17.0",
    "gn:asciiname":"Hvozdavka Druha",
    "gn:country_code":"UA",
    "gn:dem":101,
    "gn:feature_class":"P",
    "gn:feature_code":"PPL",
    "gn:name":"Hvozdavka Druha",
    "gn:population":0,
    "gn:timezone":"Europe/Kiev",
    "iso:country":"UA",
    "name:ukr_x_preferred":[
        "Hvozdavka Druha"
    ],
    "name:ukr_x_variant":[
        "\u0413\u0432\u043e\u0437\u0434\u0430\u0432\u043a\u0430 \u0414\u0440\u0443\u0433\u0430"
    ],
    "name:und_x_variant":[
        "Gvozdavka",
        "Gvozdovka",
        "Gvozdavka Vtoraya",
        "Gvozdovka Vtoraya"
    ],
    "wof:name":"Hvozdavka Druha",
    "wof:placetype":"locality"
},
  "geometry": {"coordinates":[30.08049,47.88705],"type":"Point"}
}