{
  "type": "Feature",
  "properties": {
    "gn:admin1_code":"24.0",
    "gn:asciiname":"Borovne",
    "gn:country_code":"UA",
    "gn:dem":159,
    "gn:feature_class":"P",
    "gn:feature_code":"PPL",
    "gn:name":"Borovne",
    "gn:population":0,
    "gn:timezone":"Europe/Kiev",
    "iso:country":"UA",
    "name:ukr_x_preferred":[
        "Borovne"
    ],
    "name:ukr_x_variant":[
        "\u0411\u043e\u0440\u043e\u0432\u043d\u0435"
    ],
    "name:und_x_variant":[
        "Borowno",
        "Borovno"
    ],
    "wof:name":"Borovne",
    "wof:placetype":"locality"
},
  "geometry": {"coordinates":[25.29251,51.51629000000001],"type":"Point"}
}