{
  "type": "Feature",
  "properties": {
    "iso:country":"UA",
    "qs:a0":"\u0423\u043a\u0440\u0430\u0457\u043d\u0430",
    "qs:a1":"*\u041b\u0443\u0433\u0430\u043d\u0441\u044c\u043a\u0430",
    "qs:a1_alt":"Luhans'ka",
    "qs:a1r":"0",
    "qs:a2":"\u0421\u0432\u0435\u0440\u0434\u043b\u043e\u0432\u0441\u044c\u043a\u0438\u0439",
    "qs:a2_alt":"Sverdlovs'kyi",
    "qs:adm0":"\u0423\u043a\u0440\u0430\u0457\u043d\u0430",
    "qs:la_lc":"*",
    "qs:level":"locality",
    "qs:loc":"\u041d\u043e\u0432\u043e\u0434\u0430\u0440'\u0457\u0432\u043a\u0430",
    "qs:loc_alt":"Novodarivka",
    "qs:pop":0,
    "qs:type":"buffered point",
    "wof:name":"\u041d\u043e\u0432\u043e\u0434\u0430\u0440'\u0457\u0432\u043a\u0430",
    "wof:placetype":"locality"
},
  "geometry": {"coordinates":[39.479581,48.079985],"type":"Point"}
}