{
  "type": "Feature",
  "properties": {
    "gn:admin1_code":"2.0",
    "gn:asciiname":"Polissya",
    "gn:country_code":"UA",
    "gn:dem":156,
    "gn:feature_class":"P",
    "gn:feature_code":"PPL",
    "gn:name":"Polissya",
    "gn:population":0,
    "gn:timezone":"Europe/Kiev",
    "iso:country":"UA",
    "name:rus_x_preferred":[
        "Poles\u2019ye"
    ],
    "name:ukr_x_preferred":[
        "Polissya"
    ],
    "name:ukr_x_variant":[
        "\u041f\u043e\u043b\u0456\u0441\u0441\u044f"
    ],
    "name:und_x_variant":[
        "Zhabchichi"
    ],
    "wof:name":"Polissya",
    "wof:placetype":"locality"
},
  "geometry": {"coordinates":[31.72256,51.96699],"type":"Point"}
}