{
  "type": "Feature",
  "properties": {
    "gn:admin1_code":"15.0",
    "gn:asciiname":"Khashchovania",
    "gn:country_code":"UA",
    "gn:dem":739,
    "gn:feature_class":"P",
    "gn:feature_code":"PPL",
    "gn:name":"Khashchovania",
    "gn:population":0,
    "gn:timezone":"Europe/Kiev",
    "iso:country":"UA",
    "name:ukr_x_preferred":[
        "Khashchovanya"
    ],
    "name:ukr_x_variant":[
        "\u0425\u0430\u0449\u043e\u0432\u0430\u043d\u044f"
    ],
    "name:und_x_variant":[
        "Khashchovane",
        "Khashchovanoye"
    ],
    "wof:name":"Khashchovania",
    "wof:placetype":"locality"
},
  "geometry": {"coordinates":[23.39667,48.75645],"type":"Point"}
}