{
  "type": "Feature",
  "properties": {
    "gn:admin1_code":"24.0",
    "gn:asciiname":"Rokytnytsya",
    "gn:country_code":"UA",
    "gn:dem":179,
    "gn:feature_class":"P",
    "gn:feature_code":"PPL",
    "gn:name":"Rokytnytsya",
    "gn:population":0,
    "gn:timezone":"Europe/Kiev",
    "iso:country":"UA",
    "name:ukr_x_preferred":[
        "Rokytnytsya"
    ],
    "name:ukr_x_variant":[
        "\u0420\u043e\u043a\u0438\u0442\u043d\u0438\u0446\u044f"
    ],
    "name:und_x_variant":[
        "Rokitnitsa",
        "Rakitnitsa"
    ],
    "wof:name":"Rokytnytsya",
    "wof:placetype":"locality"
},
  "geometry": {"coordinates":[24.77742000000001,51.10112],"type":"Point"}
}