{
  "type": "Feature",
  "properties": {
    "gn:admin1_code":"2.0",
    "gn:asciiname":"Mala Doch",
    "gn:country_code":"UA",
    "gn:dem":136,
    "gn:feature_class":"P",
    "gn:feature_code":"PPL",
    "gn:name":"Mala Doch",
    "gn:population":0,
    "gn:timezone":"Europe/Kiev",
    "iso:country":"UA",
    "name:rus_x_preferred":[
        "Malaya Doch\u2019"
    ],
    "name:ukr_x_preferred":[
        "Mala Doch"
    ],
    "name:ukr_x_variant":[
        "\u041c\u0430\u043b\u0430 \u0414\u043e\u0447"
    ],
    "name:und_x_variant":[
        "Khutor Malaya Doch\u2019"
    ],
    "wof:name":"Mala Doch",
    "wof:placetype":"locality"
},
  "geometry": {"coordinates":[32.7045,51.30172],"type":"Point"}
}