{
  "type": "Feature",
  "properties": {
    "gn:admin1_code":"17.0",
    "gn:asciiname":"Staraya Yefrosinovka",
    "gn:country_code":"UA",
    "gn:dem":203,
    "gn:feature_class":"P",
    "gn:feature_code":"PPL",
    "gn:name":"Staraya Yefrosinovka",
    "gn:population":0,
    "gn:timezone":"Europe/Kiev",
    "iso:country":"UA",
    "wof:name":"Staraya Yefrosinovka",
    "wof:placetype":"locality"
},
  "geometry": {"coordinates":[29.7825,47.66833],"type":"Point"}
}