{
  "type": "Feature",
  "properties": {
    "gn:admin1_code":"14.0",
    "gn:asciiname":"Sychans'ke",
    "gn:country_code":"UA",
    "gn:dem":196,
    "gn:feature_class":"P",
    "gn:feature_code":"PPL",
    "gn:name":"Sychans\u2019ke",
    "gn:population":0,
    "gn:timezone":"Europe/Zaporozhye",
    "iso:country":"UA",
    "name:ukr_x_preferred":[
        "Sychans\u2019ke"
    ],
    "name:ukr_x_variant":[
        "\u0421\u0438\u0447\u0430\u043d\u0441\u044c\u043a\u0435"
    ],
    "wof:name":"Sychans'ke",
    "wof:placetype":"locality"
},
  "geometry": {"coordinates":[39.39807,49.43632],"type":"Point"}
}