{
  "type": "Feature",
  "properties": {
    "gn:admin1_code":"7.0",
    "gn:asciiname":"Bondarivka",
    "gn:country_code":"UA",
    "gn:dem":146,
    "gn:feature_class":"P",
    "gn:feature_code":"PPL",
    "gn:name":"Bondarivka",
    "gn:population":0,
    "gn:timezone":"Europe/Kiev",
    "iso:country":"UA",
    "name:rus_x_preferred":[
        "\u0411\u043e\u043d\u0434\u0430\u0440\u0435\u0432\u043a\u0430"
    ],
    "name:ukr_x_preferred":[
        "Bondarivka"
    ],
    "name:ukr_x_variant":[
        "\u0411\u043e\u043d\u0434\u0430\u0440\u0456\u0432\u043a\u0430"
    ],
    "name:und_x_variant":[
        "Chervonyy Step",
        "Bondaryevka"
    ],
    "wof:name":"Bondarivka",
    "wof:placetype":"locality"
},
  "geometry": {"coordinates":[36.07444,49.07444],"type":"Point"}
}