{
  "type": "Feature",
  "properties": {
    "gn:admin1_code":"27.0",
    "gn:asciiname":"Zakusilovka",
    "gn:country_code":"UA",
    "gn:dem":223,
    "gn:feature_class":"P",
    "gn:feature_code":"PPL",
    "gn:name":"Zakusilovka",
    "gn:population":0,
    "gn:timezone":"Europe/Kiev",
    "iso:country":"UA",
    "wof:name":"Zakusilovka",
    "wof:placetype":"locality"
},
  "geometry": {"coordinates":[28.68333,50.08333],"type":"Point"}
}