{
  "type": "Feature",
  "properties": {
    "gn:population":2896,
    "iso:country":"UA",
    "name:ast_x_preferred":[
        "Olga Markova"
    ],
    "name:deu_x_preferred":[
        "Olga Dmitrijewna Markowa"
    ],
    "name:eng_x_preferred":[
        "Olga Markova"
    ],
    "name:fra_x_preferred":[
        "Olga Markova"
    ],
    "name:jpn_x_preferred":[
        "\u30aa\u30eb\u30ac\u30fb\u30de\u30eb\u30b3\u30ef"
    ],
    "name:nld_x_preferred":[
        "Olga Markova"
    ],
    "name:nno_x_preferred":[
        "Olga Markova"
    ],
    "name:nob_x_preferred":[
        "Olga Markova"
    ],
    "name:rus_x_preferred":[
        "\u041c\u0430\u0440\u043a\u043e\u0432\u0430"
    ],
    "name:spa_x_preferred":[
        "Olga Markova"
    ],
    "name:ukr_x_preferred":[
        "\u041c\u0430\u0440\u043a\u043e\u0432\u0430"
    ],
    "name:und_x_variant":[
        "Markova"
    ],
    "qs:a0":"\u0423\u043a\u0440\u0430\u0457\u043d\u0430",
    "qs:a1":"*\u0406\u0432\u0430\u043d\u043e-\u0424\u0440\u0430\u043d\u043a\u0456\u0432\u0441\u044c\u043a\u0430",
    "qs:a1_alt":"Ivano-Frankivs'ka",
    "qs:a1r":"0",
    "qs:a2":"\u0411\u043e\u0433\u043e\u0440\u043e\u0434\u0447\u0430\u043d\u0441\u044c\u043a\u0438\u0439",
    "qs:a2_alt":"Bohorodchans'kyi",
    "qs:adm0":"\u0423\u043a\u0440\u0430\u0457\u043d\u0430",
    "qs:la_lc":"*",
    "qs:level":"locality",
    "qs:loc":"\u041c\u0430\u0440\u043a\u043e\u0432\u0430",
    "qs:loc_alt":"Markova",
    "qs:pop":0,
    "qs:type":"buffered point",
    "wd:wordcount":194,
    "wof:name":"\u041c\u0430\u0440\u043a\u043e\u0432\u0430",
    "wof:placetype":"locality",
    "wof:population":2896
},
  "geometry": {"coordinates":[24.420984,48.684477],"type":"Point"}
}