{
  "type": "Feature",
  "properties": {
    "gn:admin1_code":"2.0",
    "gn:asciiname":"Zaytsi",
    "gn:country_code":"UA",
    "gn:dem":136,
    "gn:feature_class":"P",
    "gn:feature_code":"PPL",
    "gn:name":"Zaytsi",
    "gn:population":0,
    "gn:timezone":"Europe/Kiev",
    "iso:country":"UA",
    "name:ukr_x_preferred":[
        "Zaytsi"
    ],
    "name:ukr_x_variant":[
        "\u0417\u0430\u0439\u0446\u0456"
    ],
    "name:und_x_variant":[
        "Zaytsy"
    ],
    "wof:name":"Zaytsi",
    "wof:placetype":"locality"
},
  "geometry": {"coordinates":[31.1217,51.46982],"type":"Point"}
}