{
  "type": "Feature",
  "properties": {
    "gn:admin1_code":"22.0",
    "gn:asciiname":"Klimkovtse",
    "gn:country_code":"UA",
    "gn:dem":309,
    "gn:feature_class":"P",
    "gn:feature_code":"PPL",
    "gn:name":"Klimkovtse",
    "gn:population":0,
    "gn:timezone":"Europe/Kiev",
    "iso:country":"UA",
    "wof:name":"Klimkovtse",
    "wof:placetype":"locality"
},
  "geometry": {"coordinates":[26.09935,49.60607],"type":"Point"}
}