{
  "type": "Feature",
  "properties": {
    "iso:country":"UA",
    "name:eng_x_preferred":[
        "Barakhty"
    ],
    "name:rus_x_preferred":[
        "\u0411\u0430\u0440\u0430\u0445\u0442\u044b"
    ],
    "name:unk_x_variant":[
        "Barakhty"
    ],
    "qs:a0":"\u0423\u043a\u0440\u0430\u0457\u043d\u0430",
    "qs:a1":"*\u041a\u0438\u0457\u0432\u0441\u044c\u043a\u0430",
    "qs:a1_alt":"Kyivs'ka",
    "qs:a1r":"0",
    "qs:a2":"\u0412\u0430\u0441\u0438\u043b\u044c\u043a\u0456\u0432\u0441\u044c\u043a\u0438\u0439",
    "qs:a2_alt":"Vasyl'kivs'kyi",
    "qs:adm0":"\u0423\u043a\u0440\u0430\u0457\u043d\u0430",
    "qs:la_lc":"*",
    "qs:level":"locality",
    "qs:loc":"\u0411\u0430\u0440\u0430\u0445\u0442\u0438",
    "qs:loc_alt":"Barakhty",
    "qs:pop":0,
    "qs:type":"buffered point",
    "wof:name":"\u0411\u0430\u0440\u0430\u0445\u0442\u0438",
    "wof:placetype":"locality"
},
  "geometry": {"coordinates":[30.357303,50.121333],"type":"Point"}
}