{
  "type": "Feature",
  "properties": {
    "gn:admin1_code":"18.0",
    "gn:asciiname":"Prosyanykivka",
    "gn:country_code":"UA",
    "gn:dem":94,
    "gn:feature_class":"P",
    "gn:feature_code":"PPL",
    "gn:name":"Prosyanykivka",
    "gn:population":0,
    "gn:timezone":"Europe/Kiev",
    "iso:country":"UA",
    "name:ukr_x_preferred":[
        "Prosyanykivka"
    ],
    "name:ukr_x_variant":[
        "\u041f\u0440\u043e\u0441\u044f\u043d\u0438\u043a\u0456\u0432\u043a\u0430"
    ],
    "name:und_x_variant":[
        "Prosyanikovka"
    ],
    "wof:name":"Prosyanykivka",
    "wof:placetype":"locality"
},
  "geometry": {"coordinates":[34.00814,48.95157],"type":"Point"}
}