{
  "type": "Feature",
  "properties": {
    "gn:admin1_code":"26.0",
    "gn:asciiname":"Krasnoyarskoye",
    "gn:country_code":"UA",
    "gn:dem":76,
    "gn:feature_class":"P",
    "gn:feature_code":"PPL",
    "gn:name":"Krasnoyarskoye",
    "gn:population":0,
    "gn:timezone":"Europe/Zaporozhye",
    "iso:country":"UA",
    "wof:name":"Krasnoyarskoye",
    "wof:placetype":"locality"
},
  "geometry": {"coordinates":[34.67499,47.1142],"type":"Point"}
}