{
  "type": "Feature",
  "properties": {
    "gn:admin1_code":"17.0",
    "gn:asciiname":"Novoukrayinka",
    "gn:country_code":"UA",
    "gn:dem":33,
    "gn:feature_class":"P",
    "gn:feature_code":"PPL",
    "gn:name":"Novoukrayinka",
    "gn:population":0,
    "gn:timezone":"Europe/Kiev",
    "iso:country":"UA",
    "name:ukr_x_preferred":[
        "Novoukrayinka"
    ],
    "name:ukr_x_variant":[
        "\u041d\u043e\u0432\u043e\u0443\u043a\u0440\u0430\u0457\u043d\u043a\u0430"
    ],
    "name:und_x_variant":[
        "Budenivka",
        "Budenovka",
        "Bud\u00ebnnovka",
        "Novoukrainka"
    ],
    "wof:name":"Novoukrayinka",
    "wof:placetype":"locality"
},
  "geometry": {"coordinates":[30.28915,46.81472],"type":"Point"}
}