{
  "type": "Feature",
  "properties": {
    "gn:admin1_code":"22.0",
    "gn:asciiname":"Bogdanovka",
    "gn:country_code":"UA",
    "gn:dem":146,
    "gn:feature_class":"P",
    "gn:feature_code":"PPL",
    "gn:name":"Bogdanovka",
    "gn:population":0,
    "gn:timezone":"Europe/Kiev",
    "iso:country":"UA",
    "name:und_x_variant":[
        "Sinyuv",
        "Sin\u2019kov",
        "Bogdanovka"
    ],
    "wof:name":"Bogdanovka",
    "wof:placetype":"locality"
},
  "geometry": {"coordinates":[25.95586,48.61537],"type":"Point"}
}