{
  "type": "Feature",
  "properties": {
    "gn:admin1_code":"2.0",
    "gn:asciiname":"Kirove",
    "gn:country_code":"UA",
    "gn:dem":196,
    "gn:feature_class":"P",
    "gn:feature_code":"PPL",
    "gn:name":"Kirove",
    "gn:population":0,
    "gn:timezone":"Europe/Kiev",
    "iso:country":"UA",
    "name:eng_x_preferred":[
        "Kirovo"
    ],
    "name:rus_x_preferred":[
        "\u041a\u0438\u0440\u043e\u0432\u043e"
    ],
    "name:ukr_x_preferred":[
        "Kirove"
    ],
    "name:ukr_x_variant":[
        "\u041a\u0456\u0440\u043e\u0432\u0435"
    ],
    "name:und_x_variant":[
        "Kirovo"
    ],
    "wof:name":"Kirove",
    "wof:placetype":"locality"
},
  "geometry": {"coordinates":[33.10796,51.9778],"type":"Point"}
}