{
  "type": "Feature",
  "properties": {
    "gn:admin1_code":"27.0",
    "gn:asciiname":"Olenychi",
    "gn:country_code":"UA",
    "gn:dem":213,
    "gn:feature_class":"P",
    "gn:feature_code":"PPL",
    "gn:name":"Olenychi",
    "gn:population":0,
    "gn:timezone":"Europe/Kiev",
    "iso:country":"UA",
    "name:ukr_x_preferred":[
        "Olenychi"
    ],
    "name:ukr_x_variant":[
        "\u041e\u043b\u0435\u043d\u0438\u0447\u0456"
    ],
    "name:und_x_variant":[
        "Olenichi"
    ],
    "wof:name":"Olenychi",
    "wof:placetype":"locality"
},
  "geometry": {"coordinates":[28.52257,51.35888],"type":"Point"}
}