{
  "type": "Feature",
  "properties": {
    "iso:country":"UA",
    "name:eng_x_preferred":[
        "Kalinino"
    ],
    "name:rus_x_historical":[
        "\u041d\u0430\u0439\u043b\u0435\u0301\u0442\u0435\u043d",
        "\u041a\u0430\u043b\u0438\u043d\u0438\u043d\u0434\u043e\u0301\u0440\u0444",
        "\u041e\u0440\u043c\u0430\u0301\u043d-\u0410\u0434\u0436\u0438\u0301"
    ],
    "name:rus_x_preferred":[
        "\u041d\u0430\u0439\u043b\u0435\u0301\u0442\u0435\u043d"
    ],
    "name:rus_x_variant":[
        "\u041a\u0430\u043b\u0438\u043d\u0438\u043d\u0434\u043e\u0301\u0440\u0444",
        "\u041a\u0430\u043b\u0438\u043d\u0438\u043d\u043e",
        "\u041e\u0440\u043c\u0430\u0301\u043d-\u0410\u0434\u0436\u0438\u0301"
    ],
    "name:ukr_x_preferred":[
        "\u041a\u0430\u043b\u0456\u043d\u0456\u043d\u0435"
    ],
    "qs:a0":"\u0423\u043a\u0440\u0430\u0457\u043d\u0430",
    "qs:a1":"*\u041a\u0440\u0438\u043c",
    "qs:a1_alt":"Krym",
    "qs:a1r":"0",
    "qs:a2":"\u041f\u0435\u0440\u0432\u043e\u043c\u0430\u0439\u0441\u044c\u043a\u0438\u0439",
    "qs:a2_alt":"Pervomais'kyi",
    "qs:adm0":"\u0423\u043a\u0440\u0430\u0457\u043d\u0430",
    "qs:la_lc":"*",
    "qs:level":"locality",
    "qs:loc":"\u041a\u0430\u043b\u0456\u043d\u0456\u043d\u0435",
    "qs:loc_alt":"Kalinine",
    "qs:pop":0,
    "qs:type":"buffered point",
    "wof:name":"\u041a\u0430\u043b\u0456\u043d\u0456\u043d\u0435",
    "wof:placetype":"locality"
},
  "geometry": {"coordinates":[33.778291,45.746546],"type":"Point"}
}