{
  "type": "Feature",
  "properties": {
    "gn:admin1_code":"9.0",
    "gn:asciiname":"Noryl",
    "gn:country_code":"UA",
    "gn:dem":239,
    "gn:feature_class":"P",
    "gn:feature_code":"PPL",
    "gn:name":"Noryl",
    "gn:population":0,
    "gn:timezone":"Europe/Kiev",
    "iso:country":"UA",
    "name:fra_x_preferred":[
        "Noryl"
    ],
    "wof:name":"Noryl",
    "wof:placetype":"locality"
},
  "geometry": {"coordinates":[26.23333,49.95],"type":"Point"}
}