{
  "type": "Feature",
  "properties": {
    "gn:admin1_code":"9.0",
    "gn:asciiname":"Zamlynovka",
    "gn:country_code":"UA",
    "gn:dem":253,
    "gn:feature_class":"P",
    "gn:feature_code":"PPL",
    "gn:name":"Zamlynovka",
    "gn:population":0,
    "gn:timezone":"Europe/Kiev",
    "iso:country":"UA",
    "wof:name":"Zamlynovka",
    "wof:placetype":"locality"
},
  "geometry": {"coordinates":[26.91667,48.81667],"type":"Point"}
}