{
  "type": "Feature",
  "properties": {
    "gn:admin1_code":"7.0",
    "gn:asciiname":"Boyni",
    "gn:country_code":"UA",
    "gn:dem":86,
    "gn:feature_class":"P",
    "gn:feature_code":"PPL",
    "gn:name":"Boyni",
    "gn:population":0,
    "gn:timezone":"Europe/Kiev",
    "iso:country":"UA",
    "name:ukr_x_preferred":[
        "Boyni"
    ],
    "name:und_x_variant":[
        "Borovskoy",
        "Oskol"
    ],
    "wof:name":"Boyni",
    "wof:placetype":"locality"
},
  "geometry": {"coordinates":[37.59528,49.38528],"type":"Point"}
}