{
  "type": "Feature",
  "properties": {
    "iso:country":"UA",
    "name:eng_x_preferred":[
        "Khalyavin"
    ],
    "name:jpn_x_preferred":[
        "\u30ad\u30ea\u30eb\u30fb\u30cf\u30ea\u30e3\u30f4\u30a3\u30f3"
    ],
    "name:rus_x_preferred":[
        "\u0425\u0430\u043b\u044f\u0432\u0438\u043d"
    ],
    "name:tur_x_preferred":[
        "Kirill Halyavin"
    ],
    "name:ukr_x_preferred":[
        "Khalyavyn"
    ],
    "name:ukr_x_variant":[
        "\u0425\u0430\u043b\u044f\u0432\u0438\u043d"
    ],
    "name:unk_x_variant":[
        "Khalyvin"
    ],
    "qs:a0":"\u0423\u043a\u0440\u0430\u0457\u043d\u0430",
    "qs:a1":"*\u0427\u0435\u0440\u043d\u0456\u0433\u0456\u0432\u0441\u044c\u043a\u0430",
    "qs:a1_alt":"Chernihivs'ka",
    "qs:a1r":"0",
    "qs:a2":"\u0427\u0435\u0440\u043d\u0456\u0433\u0456\u0432\u0441\u044c\u043a\u0438\u0439",
    "qs:a2_alt":"Chernihivs'kyi",
    "qs:adm0":"\u0423\u043a\u0440\u0430\u0457\u043d\u0430",
    "qs:la_lc":"*",
    "qs:level":"locality",
    "qs:loc":"\u0425\u0430\u043b\u044f\u0432\u0438\u043d",
    "qs:loc_alt":"Khaliavyn",
    "qs:pop":0,
    "qs:type":"buffered point",
    "wd:wordcount":858,
    "wof:name":"\u0425\u0430\u043b\u044f\u0432\u0438\u043d",
    "wof:placetype":"locality"
},
  "geometry": {"coordinates":[31.286786,51.590118],"type":"Point"}
}