{
  "type": "Feature",
  "properties": {
    "gn:admin1_code":"25.0",
    "gn:asciiname":"Pryhid'",
    "gn:country_code":"UA",
    "gn:dem":471,
    "gn:feature_class":"P",
    "gn:feature_code":"PPL",
    "gn:name":"Pryhid\u2019",
    "gn:population":0,
    "gn:timezone":"Europe/Uzhgorod",
    "iso:country":"UA",
    "name:ukr_x_preferred":[
        "Pryhid\u2019"
    ],
    "name:ukr_x_variant":[
        "\u041f\u0440\u0438\u0433\u0456\u0434\u044c"
    ],
    "name:und_x_variant":[
        "Prigod"
    ],
    "wof:name":"Pryhid'",
    "wof:placetype":"locality"
},
  "geometry": {"coordinates":[23.73823,48.26234],"type":"Point"}
}