{
  "type": "Feature",
  "properties": {
    "gn:admin1_code":"18.0",
    "gn:asciiname":"Zhorzhivka",
    "gn:country_code":"UA",
    "gn:dem":146,
    "gn:feature_class":"P",
    "gn:feature_code":"PPL",
    "gn:name":"Zhorzhivka",
    "gn:population":0,
    "gn:timezone":"Europe/Kiev",
    "iso:country":"UA",
    "name:ukr_x_preferred":[
        "Zhorzhivka"
    ],
    "name:ukr_x_variant":[
        "\u0416\u043e\u0440\u0436\u0456\u0432\u043a\u0430"
    ],
    "name:und_x_variant":[
        "Zhorzhevka"
    ],
    "wof:name":"Zhorzhivka",
    "wof:placetype":"locality"
},
  "geometry": {"coordinates":[34.21724,49.93292],"type":"Point"}
}