{
  "type": "Feature",
  "properties": {
    "iso:country":"UA",
    "qs:a0":"\u0423\u043a\u0440\u0430\u0457\u043d\u0430",
    "qs:a1":"*\u041e\u0434\u0435\u0441\u044c\u043a\u0430",
    "qs:a1_alt":"Odes'ka",
    "qs:a1r":"0",
    "qs:a2":"\u0411\u0456\u043b\u044f\u0457\u0432\u0441\u044c\u043a\u0438\u0439",
    "qs:a2_alt":"Biliaivs'kyi",
    "qs:adm0":"\u0423\u043a\u0440\u0430\u0457\u043d\u0430",
    "qs:la_lc":"*",
    "qs:level":"locality",
    "qs:loc":"\u041d\u0435\u0440\u0443\u0431\u0430\u0439\u0441\u044c\u043a\u0435",
    "qs:loc_alt":"Nerubais'ke",
    "qs:pop":0,
    "qs:type":"buffered point",
    "wof:name":"\u041d\u0435\u0440\u0443\u0431\u0430\u0439\u0441\u044c\u043a\u0435",
    "wof:placetype":"locality"
},
  "geometry": {"coordinates":[30.619359,46.540875],"type":"Point"}
}