{
  "type": "Feature",
  "properties": {
    "gn:admin1_code":"27.0",
    "gn:asciiname":"Mala Derevychka",
    "gn:country_code":"UA",
    "gn:dem":231,
    "gn:feature_class":"P",
    "gn:feature_code":"PPL",
    "gn:name":"Mala Derevychka",
    "gn:population":0,
    "gn:timezone":"Europe/Kiev",
    "iso:country":"UA",
    "name:ukr_x_preferred":[
        "Mala Derevychka"
    ],
    "name:ukr_x_variant":[
        "\u041c\u0430\u043b\u0430 \u0414\u0435\u0440\u0435\u0432\u0438\u0447\u043a\u0430"
    ],
    "name:und_x_variant":[
        "Malyye Derevichki"
    ],
    "wof:name":"Mala Derevychka",
    "wof:placetype":"locality"
},
  "geometry": {"coordinates":[27.71677,49.99603],"type":"Point"}
}