{
  "type": "Feature",
  "properties": {
    "gn:admin1_code":"19.0",
    "gn:asciiname":"Stakhuvka",
    "gn:country_code":"UA",
    "gn:dem":160,
    "gn:feature_class":"P",
    "gn:feature_code":"PPL",
    "gn:name":"Stakhuvka",
    "gn:population":0,
    "gn:timezone":"Europe/Kiev",
    "iso:country":"UA",
    "wof:name":"Stakhuvka",
    "wof:placetype":"locality"
},
  "geometry": {"coordinates":[26.26667,51.46667],"type":"Point"}
}