{
  "type": "Feature",
  "properties": {
    "gn:admin1_code":"14.0",
    "gn:asciiname":"Verhulivka",
    "gn:country_code":"UA",
    "gn:dem":310,
    "gn:feature_class":"P",
    "gn:feature_code":"PPL",
    "gn:name":"Verhulivka",
    "gn:population":0,
    "gn:timezone":"Europe/Zaporozhye",
    "iso:country":"UA",
    "name:ukr_x_preferred":[
        "Verhulivka"
    ],
    "name:ukr_x_variant":[
        "\u0412\u0435\u0440\u0433\u0443\u043b\u0456\u0432\u043a\u0430"
    ],
    "name:und_x_variant":[
        "Vergel\u00ebvka",
        "Vergul\u00ebvka"
    ],
    "wof:name":"Verhulivka",
    "wof:placetype":"locality"
},
  "geometry": {"coordinates":[38.49203,48.39559000000001],"type":"Point"}
}