{
  "type": "Feature",
  "properties": {
    "gn:admin1_code":"9.0",
    "gn:asciiname":"Missiorovka",
    "gn:country_code":"UA",
    "gn:dem":281,
    "gn:feature_class":"P",
    "gn:feature_code":"PPL",
    "gn:name":"Missiorovka",
    "gn:population":0,
    "gn:timezone":"Europe/Kiev",
    "iso:country":"UA",
    "name:und_x_variant":[
        "Missiorivka",
        "Missiorovka"
    ],
    "wof:name":"Missiorovka",
    "wof:placetype":"locality"
},
  "geometry": {"coordinates":[27.58863,49.6419],"type":"Point"}
}