{
  "type": "Feature",
  "properties": {
    "gn:admin1_code":"11.0",
    "gn:admin2_code":"693803",
    "gn:admin3_code":"11152619.0",
    "gn:asciiname":"Shafrannoye",
    "gn:country_code":"UA",
    "gn:dem":119,
    "gn:elevation":"119.0",
    "gn:feature_class":"P",
    "gn:feature_code":"PPL",
    "gn:name":"Shafrannoye",
    "gn:population":244,
    "gn:timezone":"Europe/Simferopol",
    "iso:country":"UA",
    "name:eng_x_preferred":[
        "Shafrannoye"
    ],
    "name:eng_x_variant":[
        "Shafranne"
    ],
    "name:fra_x_preferred":[
        "Chafranne"
    ],
    "name:hye_x_preferred":[
        "\u0547\u0561\u0586\u0580\u0561\u0576\u0578\u0565"
    ],
    "name:ron_x_preferred":[
        "\u0218afranne"
    ],
    "name:rus_x_historical":[
        "\u0428\u0438\u0440\u043e\u0301\u043a\u043e\u0435",
        "\u041a\u0430\u0440\u0442\u043c\u044b\u0448\u0438\u0301\u043a \u041d\u0435\u043c\u0435\u0301\u0446\u043a\u0438\u0439"
    ],
    "name:rus_x_preferred":[
        "\u0428\u0430\u0444\u0440\u0430\u043d\u043d\u043e\u0435"
    ],
    "name:rus_x_variant":[
        "\u0428\u0438\u0440\u043e\u0301\u043a\u043e\u0435",
        "\u041a\u0430\u0440\u0442\u043c\u044b\u0448\u0438\u0301\u043a \u041d\u0435\u043c\u0435\u0301\u0446\u043a\u0438\u0439"
    ],
    "name:ukr_x_preferred":[
        "\u0428\u0430\u0444\u0440\u0430\u043d\u043d\u0435"
    ],
    "wof:name":"Shafrannoye",
    "wof:placetype":"locality",
    "wof:population":244
},
  "geometry": {"coordinates":[33.91567,45.11478],"type":"Point"}
}