{
  "type": "Feature",
  "properties": {
    "gn:admin1_code":"21.0",
    "gn:asciiname":"Stinka",
    "gn:country_code":"UA",
    "gn:dem":148,
    "gn:feature_class":"P",
    "gn:feature_code":"PPL",
    "gn:name":"Stinka",
    "gn:population":0,
    "gn:timezone":"Europe/Kiev",
    "iso:country":"UA",
    "name:ukr_x_preferred":[
        "Stinka"
    ],
    "name:ukr_x_variant":[
        "\u0421\u0442\u0456\u043d\u043a\u0430"
    ],
    "wof:name":"Stinka",
    "wof:placetype":"locality"
},
  "geometry": {"coordinates":[35.02553,50.82749],"type":"Point"}
}