{
  "type": "Feature",
  "properties": {
    "gn:admin1_code":"17.0",
    "gn:asciiname":"Novopavlivka",
    "gn:country_code":"UA",
    "gn:dem":127,
    "gn:feature_class":"P",
    "gn:feature_code":"PPL",
    "gn:name":"Novopavlivka",
    "gn:population":0,
    "gn:timezone":"Europe/Kiev",
    "iso:country":"UA",
    "name:ukr_x_preferred":[
        "Novopavlivka"
    ],
    "name:und_x_variant":[
        "Novopavlovka"
    ],
    "wof:name":"Novopavlivka",
    "wof:placetype":"locality"
},
  "geometry": {"coordinates":[29.962,47.1553],"type":"Point"}
}