{
  "type": "Feature",
  "properties": {
    "gn:admin1_code":"6.0",
    "gn:asciiname":"Ol'shanitsa",
    "gn:country_code":"UA",
    "gn:dem":288,
    "gn:feature_class":"P",
    "gn:feature_code":"PPL",
    "gn:name":"Ol\u2019shanitsa",
    "gn:population":0,
    "gn:timezone":"Europe/Kiev",
    "iso:country":"UA",
    "wof:name":"Ol'shanitsa",
    "wof:placetype":"locality"
},
  "geometry": {"coordinates":[24.86967000000001,48.95063],"type":"Point"}
}