{
  "type": "Feature",
  "properties": {
    "gn:admin1_code":"13.0",
    "gn:asciiname":"Vinnitskiye Stavy",
    "gn:country_code":"UA",
    "gn:dem":181,
    "gn:feature_class":"P",
    "gn:feature_code":"PPL",
    "gn:name":"Vinnitskiye Stavy",
    "gn:population":0,
    "gn:timezone":"Europe/Kiev",
    "iso:country":"UA",
    "name:und_x_variant":[
        "Vinitskiye Stavy",
        "Vinnitskiye Stavy"
    ],
    "wof:name":"Vinnitskiye Stavy",
    "wof:placetype":"locality"
},
  "geometry": {"coordinates":[30.12168,50.01011],"type":"Point"}
}