{
  "type": "Feature",
  "properties": {
    "gn:admin1_code":"6.0",
    "gn:asciiname":"Skopuvka",
    "gn:country_code":"UA",
    "gn:dem":347,
    "gn:feature_class":"P",
    "gn:feature_code":"PPL",
    "gn:name":"Skopuvka",
    "gn:population":0,
    "gn:timezone":"Europe/Kiev",
    "iso:country":"UA",
    "name:und_x_variant":[
        "Skopovka",
        "Skopuvka"
    ],
    "wof:name":"Skopuvka",
    "wof:placetype":"locality"
},
  "geometry": {"coordinates":[24.8902,48.68047],"type":"Point"}
}