{
  "type": "Feature",
  "properties": {
    "iso:country":"UA",
    "name:epo_x_preferred":[
        "Urycz"
    ],
    "name:nld_x_preferred":[
        "Urycz"
    ],
    "name:pol_x_preferred":[
        "Urycz"
    ],
    "name:ron_x_preferred":[
        "Ur\u00eeci"
    ],
    "name:rus_x_preferred":[
        "\u0423\u0440\u044b\u0447"
    ],
    "name:ukr_x_preferred":[
        "\u0423\u0440\u0438\u0447"
    ],
    "qs:a0":"\u0423\u043a\u0440\u0430\u0457\u043d\u0430",
    "qs:a1":"*\u0406\u0432\u0430\u043d\u043e-\u0424\u0440\u0430\u043d\u043a\u0456\u0432\u0441\u044c\u043a\u0430",
    "qs:a1_alt":"Ivano-Frankivs'ka",
    "qs:a1r":"0",
    "qs:a2":"\u0413\u0430\u043b\u0438\u0446\u044c\u043a\u0438\u0439",
    "qs:a2_alt":"Halyts'kyi",
    "qs:adm0":"\u0423\u043a\u0440\u0430\u0457\u043d\u0430",
    "qs:la_lc":"*",
    "qs:level":"locality",
    "qs:loc":"\u0422\u0443\u0441\u0442\u0430\u043d\u044c",
    "qs:loc_alt":"Tustan",
    "qs:pop":0,
    "qs:type":"buffered point",
    "wd:wordcount":234,
    "wof:name":"\u0422\u0443\u0441\u0442\u0430\u043d\u044c",
    "wof:placetype":"locality"
},
  "geometry": {"coordinates":[24.767906,49.126893],"type":"Point"}
}