{
  "type": "Feature",
  "properties": {
    "iso:country":"UA",
    "name:jpn_x_preferred":[
        "\u30a6\u30af\u30e9\u30a4\u30ca\u5efa\u7bc9\u6c11\u4fd7\u535a\u7269\u9928"
    ],
    "name:spa_x_preferred":[
        "Pyrohiv"
    ],
    "name:ukr_x_preferred":[
        "\u041f\u0438\u0440\u043e\u0433\u0456\u0432"
    ],
    "wof:name":"Pyrohiv",
    "wof:placetype":"neighbourhood"
},
  "geometry": {"coordinates":[30.52130870232694,50.34624272787909],"type":"Point"}
}