{
  "type": "Feature",
  "properties": {
    "iso:country":"UA",
    "name:ukr_x_preferred":[
        "\u041f\u0438\u0440\u043e\u0433\u0456\u0432"
    ],
    "wof:name":"Pyrohiv",
    "wof:placetype":"neighbourhood"
},
  "geometry": {"coordinates":[30.52130870232694,50.34624272787909],"type":"Point"}
}