{
  "type": "Feature",
  "properties": {
    "gn:admin1_code":"14.0",
    "gn:asciiname":"Chervona Dibrova",
    "gn:country_code":"UA",
    "gn:dem":94,
    "gn:feature_class":"P",
    "gn:feature_code":"PPL",
    "gn:name":"Chervona Dibrova",
    "gn:population":0,
    "gn:timezone":"Europe/Zaporozhye",
    "iso:country":"UA",
    "name:ukr_x_preferred":[
        "Chervona Dibrova"
    ],
    "name:ukr_x_variant":[
        "\u0427\u0435\u0440\u0432\u043e\u043d\u0430 \u0414\u0456\u0431\u0440\u043e\u0432\u0430"
    ],
    "name:und_x_variant":[
        "Novo-Dubrovskiy",
        "Chervonnaya Dubrava"
    ],
    "wof:name":"Chervona Dibrova",
    "wof:placetype":"locality"
},
  "geometry": {"coordinates":[38.10844,48.99702],"type":"Point"}
}