{
  "type": "Feature",
  "properties": {
    "gn:admin1_code":"17.0",
    "gn:asciiname":"Pavlynka",
    "gn:country_code":"UA",
    "gn:dem":64,
    "gn:feature_class":"P",
    "gn:feature_code":"PPL",
    "gn:name":"Pavlynka",
    "gn:population":0,
    "gn:timezone":"Europe/Kiev",
    "iso:country":"UA",
    "name:ukr_x_preferred":[
        "Pavlynka"
    ],
    "name:ukr_x_variant":[
        "\u041f\u0430\u0432\u043b\u0438\u043d\u043a\u0430"
    ],
    "name:und_x_variant":[
        "Pavlinka"
    ],
    "wof:name":"Pavlynka",
    "wof:placetype":"locality"
},
  "geometry": {"coordinates":[30.67608,46.81521],"type":"Point"}
}