{
  "type": "Feature",
  "properties": {
    "gn:admin1_code":"6.0",
    "gn:asciiname":"Kopan'",
    "gn:country_code":"UA",
    "gn:dem":437,
    "gn:feature_class":"P",
    "gn:feature_code":"PPL",
    "gn:name":"Kopan\u2019",
    "gn:population":0,
    "gn:timezone":"Europe/Kiev",
    "iso:country":"UA",
    "wof:name":"Kopan'",
    "wof:placetype":"locality"
},
  "geometry": {"coordinates":[24.11667000000001,48.98333],"type":"Point"}
}