{
  "type": "Feature",
  "properties": {
    "gn:admin1_code":"22.0",
    "gn:asciiname":"Ugrin'kovtsy",
    "gn:country_code":"UA",
    "gn:dem":232,
    "gn:feature_class":"P",
    "gn:feature_code":"PPL",
    "gn:name":"Ugrin\u2019kovtsy",
    "gn:population":0,
    "gn:timezone":"Europe/Kiev",
    "iso:country":"UA",
    "name:und_x_variant":[
        "Ugryn\u2019kovtse",
        "Ugrin\u2019kovtsy"
    ],
    "wof:name":"Ugrin'kovtsy",
    "wof:placetype":"locality"
},
  "geometry": {"coordinates":[25.75912000000001,48.74263],"type":"Point"}
}