{
  "type": "Feature",
  "properties": {
    "gn:admin1_code":"4.0",
    "gn:asciiname":"Chervonyy Lyman",
    "gn:country_code":"UA",
    "gn:dem":83,
    "gn:feature_class":"P",
    "gn:feature_code":"PPL",
    "gn:name":"Chervonyy Lyman",
    "gn:population":0,
    "gn:timezone":"Europe/Kiev",
    "iso:country":"UA",
    "name:ukr_x_preferred":[
        "Chervonyy Lyman"
    ],
    "name:ukr_x_variant":[
        "\u0427\u0435\u0440\u0432\u043e\u043d\u0438\u0439 \u041b\u0438\u043c\u0430\u043d"
    ],
    "name:und_x_variant":[
        "Krasny Liman",
        "Krasnyy Liman",
        "Chervonyy Liman"
    ],
    "wof:name":"Chervonyy Lyman",
    "wof:placetype":"locality"
},
  "geometry": {"coordinates":[36.28339,47.97412],"type":"Point"}
}