{
  "type": "Feature",
  "properties": {
    "iso:country":"UA",
    "name:und_x_variant":[
        "Holhocha"
    ],
    "qs:a0":"\u0423\u043a\u0440\u0430\u0457\u043d\u0430",
    "qs:a1":"*\u0422\u0435\u0440\u043d\u043e\u043f\u0456\u043b\u044c\u0441\u044c\u043a\u0430",
    "qs:a1_alt":"Ternopil's'ka",
    "qs:a1r":"0",
    "qs:a2":"\u041f\u0456\u0434\u0433\u0430\u0454\u0446\u044c\u043a\u0438\u0439",
    "qs:a2_alt":"Pidhaiets'kyi",
    "qs:adm0":"\u0423\u043a\u0440\u0430\u0457\u043d\u0430",
    "qs:la_lc":"*",
    "qs:level":"locality",
    "qs:loc":"\u0413\u043e\u043b\u0433\u043e\u0447\u0430",
    "qs:loc_alt":"Holhocha",
    "qs:pop":0,
    "qs:type":"buffered point",
    "wof:name":"\u0413\u043e\u043b\u0433\u043e\u0447\u0430",
    "wof:placetype":"locality"
},
  "geometry": {"coordinates":[25.155299,49.19162],"type":"Point"}
}