{
  "type": "Feature",
  "properties": {
    "gn:admin1_code":"8.0",
    "gn:asciiname":"Lyubymo-Pavlivka",
    "gn:country_code":"UA",
    "gn:dem":40,
    "gn:feature_class":"P",
    "gn:feature_code":"PPL",
    "gn:name":"Lyubymo-Pavlivka",
    "gn:population":0,
    "gn:timezone":"Europe/Kiev",
    "iso:country":"UA",
    "name:rus_x_preferred":[
        "\u041b\u044e\u0431\u0438\u043c\u043e-\u041f\u0430\u0432\u043b\u043e\u0432\u043a\u0430"
    ],
    "name:ukr_x_preferred":[
        "\u041b\u044e\u0431\u0438\u043c\u043e-\u041f\u0430\u0432\u043b\u0456\u0432\u043a\u0430"
    ],
    "name:und_x_variant":[
        "Lyubimo-Pavlovka",
        "Lyubymo-Pavlivka"
    ],
    "wof:name":"Lyubymo-Pavlivka",
    "wof:placetype":"locality"
},
  "geometry": {"coordinates":[33.6806,46.58671],"type":"Point"}
}