{
  "type": "Feature",
  "properties": {
    "gn:admin1_code":"24.0",
    "gn:asciiname":"Natalyn",
    "gn:country_code":"UA",
    "gn:dem":245,
    "gn:feature_class":"P",
    "gn:feature_code":"PPL",
    "gn:name":"Natalyn",
    "gn:population":0,
    "gn:timezone":"Europe/Kiev",
    "iso:country":"UA",
    "name:ukr_x_preferred":[
        "Natalyn"
    ],
    "name:ukr_x_variant":[
        "\u041d\u0430\u0442\u0430\u043b\u0438\u043d"
    ],
    "name:und_x_variant":[
        "Natalin"
    ],
    "wof:name":"Natalyn",
    "wof:placetype":"locality"
},
  "geometry": {"coordinates":[25.0698,50.48925],"type":"Point"}
}