{
  "type": "Feature",
  "properties": {
    "gn:admin1_code":"9.0",
    "gn:asciiname":"Volitsa Polevaya",
    "gn:country_code":"UA",
    "gn:dem":297,
    "gn:feature_class":"P",
    "gn:feature_code":"PPL",
    "gn:name":"Volitsa Polevaya",
    "gn:population":0,
    "gn:timezone":"Europe/Kiev",
    "iso:country":"UA",
    "name:und_x_variant":[
        "Volitsa",
        "Volitsa Polevaya"
    ],
    "wof:name":"Volitsa Polevaya",
    "wof:placetype":"locality"
},
  "geometry": {"coordinates":[26.61271,49.82614],"type":"Point"}
}