{
  "type": "Feature",
  "properties": {
    "iso:country":"UA",
    "qs:a0":"\u0423\u043a\u0440\u0430\u0457\u043d\u0430",
    "qs:a1":"*\u041c\u0438\u043a\u043e\u043b\u0430\u0457\u0432\u0441\u044c\u043a\u0430",
    "qs:a1_alt":"Mykolaivs'ka",
    "qs:a1r":"0",
    "qs:a2":"\u041a\u0440\u0438\u0432\u043e\u043e\u0437\u0435\u0440\u0441\u044c\u043a\u0438\u0439",
    "qs:a2_alt":"Kryvoozers'kyi",
    "qs:adm0":"\u0423\u043a\u0440\u0430\u0457\u043d\u0430",
    "qs:la_lc":"*",
    "qs:level":"locality",
    "qs:loc":"\u041b\u0443\u043a\u0430\u043d\u0456\u0432\u043a\u0430",
    "qs:loc_alt":"Lukanivka",
    "qs:pop":0,
    "qs:type":"buffered point",
    "wof:name":"\u041b\u0443\u043a\u0430\u043d\u0456\u0432\u043a\u0430",
    "wof:placetype":"locality"
},
  "geometry": {"coordinates":[30.47568,47.918152],"type":"Point"}
}