{
  "type": "Feature",
  "properties": {
    "gn:admin1_code":"8.0",
    "gn:asciiname":"Chumpod",
    "gn:country_code":"UA",
    "gn:dem":71,
    "gn:feature_class":"P",
    "gn:feature_code":"PPL",
    "gn:name":"Chumpod",
    "gn:population":0,
    "gn:timezone":"Europe/Kiev",
    "iso:country":"UA",
    "wof:name":"Chumpod",
    "wof:placetype":"locality"
},
  "geometry": {"coordinates":[34.28333,47.05],"type":"Point"}
}