{
  "type": "Feature",
  "properties": {
    "gn:admin1_code":"10.0",
    "gn:asciiname":"Batyzman",
    "gn:country_code":"UA",
    "gn:dem":167,
    "gn:feature_class":"P",
    "gn:feature_code":"PPL",
    "gn:name":"Batyzman",
    "gn:population":0,
    "gn:timezone":"Europe/Kiev",
    "iso:country":"UA",
    "name:eng_x_preferred":[
        "Sukhodol'skoye"
    ],
    "name:rus_x_preferred":[
        "\u0421\u0443\u0445\u043e\u0434\u043e\u043b\u044c\u0441\u043a\u043e\u0435"
    ],
    "name:und_x_variant":[
        "Sukhodol\u2019skoye"
    ],
    "wof:name":"Batyzman",
    "wof:placetype":"locality"
},
  "geometry": {"coordinates":[32.70694,48.23845],"type":"Point"}
}