{
  "type": "Feature",
  "properties": {
    "gn:admin1_code":"7.0",
    "gn:asciiname":"Lypchanivka",
    "gn:country_code":"UA",
    "gn:dem":88,
    "gn:feature_class":"P",
    "gn:feature_code":"PPL",
    "gn:name":"Lypchanivka",
    "gn:population":0,
    "gn:timezone":"Europe/Kiev",
    "iso:country":"UA",
    "name:ukr_x_preferred":[
        "Lypchanivka"
    ],
    "name:und_x_variant":[
        "Lipchanovka"
    ],
    "wof:name":"Lypchanivka",
    "wof:placetype":"locality"
},
  "geometry": {"coordinates":[37.31756,49.32668],"type":"Point"}
}