{
  "type": "Feature",
  "properties": {
    "gn:admin1_code":"27.0",
    "gn:asciiname":"Svydya",
    "gn:country_code":"UA",
    "gn:dem":206,
    "gn:feature_class":"P",
    "gn:feature_code":"PPL",
    "gn:name":"Svydya",
    "gn:population":0,
    "gn:timezone":"Europe/Kiev",
    "iso:country":"UA",
    "name:ukr_x_preferred":[
        "Svydya"
    ],
    "name:ukr_x_variant":[
        "\u0421\u0432\u0438\u0434\u044f"
    ],
    "name:und_x_variant":[
        "Svida",
        "Svidya"
    ],
    "wof:name":"Svydya",
    "wof:placetype":"locality"
},
  "geometry": {"coordinates":[28.85376,50.53179],"type":"Point"}
}