{
  "type": "Feature",
  "properties": {
    "iso:country":"UA",
    "name:unk_x_variant":[
        "Yampil\u2019"
    ],
    "qs:a0":"\u0423\u043a\u0440\u0430\u0457\u043d\u0430",
    "qs:a1":"*\u041b\u044c\u0432\u0456\u0432\u0441\u044c\u043a\u0430",
    "qs:a1_alt":"L'vivs'ka",
    "qs:a1r":"0",
    "qs:a2":"\u041f\u0443\u0441\u0442\u043e\u043c\u0438\u0442\u0456\u0432\u0441\u044c\u043a\u0438\u0439",
    "qs:a2_alt":"Pustomytivs'kyi",
    "qs:adm0":"\u0423\u043a\u0440\u0430\u0457\u043d\u0430",
    "qs:la_lc":"*",
    "qs:level":"locality",
    "qs:loc":"\u042f\u043c\u043f\u0456\u043b\u044c",
    "qs:loc_alt":"Yampil",
    "qs:pop":0,
    "qs:type":"buffered point",
    "wd:wordcount":109,
    "wof:name":"\u042f\u043c\u043f\u0456\u043b\u044c",
    "wof:placetype":"locality"
},
  "geometry": {"coordinates":[24.183967,49.872559],"type":"Point"}
}