{
  "type": "Feature",
  "properties": {
    "gn:admin1_code":"7.0",
    "gn:asciiname":"Timchenko",
    "gn:country_code":"UA",
    "gn:dem":175,
    "gn:feature_class":"P",
    "gn:feature_code":"PPL",
    "gn:name":"Timchenko",
    "gn:population":0,
    "gn:timezone":"Europe/Kiev",
    "iso:country":"UA",
    "wof:name":"Timchenko",
    "wof:placetype":"locality"
},
  "geometry": {"coordinates":[36.13333,49.35],"type":"Point"}
}