{
  "type": "Feature",
  "properties": {
    "gn:admin1_code":"23.0",
    "gn:asciiname":"Hlukhivtsi",
    "gn:country_code":"UA",
    "gn:dem":283,
    "gn:feature_class":"P",
    "gn:feature_code":"PPL",
    "gn:name":"Hlukhivtsi",
    "gn:population":0,
    "gn:timezone":"Europe/Kiev",
    "iso:country":"UA",
    "name:ukr_x_preferred":[
        "Hlukhivtsi"
    ],
    "name:ukr_x_variant":[
        "\u0413\u043b\u0443\u0445\u0456\u0432\u0446\u0456"
    ],
    "name:und_x_variant":[
        "Glukhovtsy"
    ],
    "wof:name":"Hlukhivtsi",
    "wof:placetype":"locality"
},
  "geometry": {"coordinates":[28.7334,49.77037],"type":"Point"}
}