{
  "type": "Feature",
  "properties": {
    "gn:admin1_code":"27.0",
    "gn:asciiname":"Marki",
    "gn:country_code":"UA",
    "gn:dem":172,
    "gn:feature_class":"P",
    "gn:feature_code":"PPL",
    "gn:name":"Marki",
    "gn:population":0,
    "gn:timezone":"Europe/Kiev",
    "iso:country":"UA",
    "name:bul_x_preferred":[
        "\u041c\u0430\u0440\u043a\u0438"
    ],
    "name:dan_x_preferred":[
        "Marki"
    ],
    "name:deu_x_preferred":[
        "Marki"
    ],
    "name:epo_x_preferred":[
        "Marki"
    ],
    "name:est_x_preferred":[
        "Marki"
    ],
    "name:eus_x_preferred":[
        "Marki"
    ],
    "name:fra_x_preferred":[
        "Marki"
    ],
    "name:ita_x_preferred":[
        "Marki"
    ],
    "name:jav_x_preferred":[
        "Marki"
    ],
    "name:kor_x_preferred":[
        "\ub9c8\ub974\ud0a4"
    ],
    "name:lav_x_preferred":[
        "Marki"
    ],
    "name:lit_x_preferred":[
        "Markos"
    ],
    "name:msa_x_preferred":[
        "Marki"
    ],
    "name:nld_x_preferred":[
        "Marki"
    ],
    "name:pol_x_preferred":[
        "Marki"
    ],
    "name:por_x_preferred":[
        "Marki"
    ],
    "name:ron_x_preferred":[
        "Marki"
    ],
    "name:rus_x_preferred":[
        "\u041c\u0430\u0440\u043a\u0438"
    ],
    "name:slk_x_preferred":[
        "Marki"
    ],
    "name:srp_x_preferred":[
        "\u041c\u0430\u0440\u043a\u0438"
    ],
    "name:szl_x_preferred":[
        "Marki"
    ],
    "name:ukr_x_preferred":[
        "\u041c\u0430\u0440\u043a\u0456"
    ],
    "name:vie_x_preferred":[
        "Marki"
    ],
    "name:war_x_preferred":[
        "Marki"
    ],
    "name:zho_x_preferred":[
        "\u99ac\u723e\u57fa"
    ],
    "wof:name":"Marki",
    "wof:placetype":"locality"
},
  "geometry": {"coordinates":[29.01599,51.42967],"type":"Point"}
}