{
  "type": "Feature",
  "properties": {
    "gn:country":"UA",
    "gn:fcode":"PPL",
    "gn:population":0,
    "iso:country":"UA",
    "name:deu_x_preferred":[
        "Makedoniwka"
    ],
    "name:eng_x_preferred":[
        "Makedonivka"
    ],
    "name:lav_x_preferred":[
        "Makedo\u0146ivka"
    ],
    "name:mkd_x_preferred":[
        "\u041c\u0430\u043a\u0435\u0434\u043e\u043d\u043e\u0432\u043a\u0430"
    ],
    "name:nld_x_preferred":[
        "Makedonivka"
    ],
    "name:ron_x_preferred":[
        "Makedonivka"
    ],
    "name:rus_x_preferred":[
        "\u041c\u0430\u043a\u0435\u0434\u043e\u043d\u043e\u0432\u043a\u0430"
    ],
    "name:ukr_x_preferred":[
        "Makedonivka"
    ],
    "name:ukr_x_variant":[
        "\u041c\u0430\u043a\u0435\u0434\u043e\u043d\u0456\u0432\u043a\u0430"
    ],
    "name:zho_x_preferred":[
        "\u99ac\u514b\u591a\u5c3c\u592b\u5361"
    ],
    "qs_pg:aaroncc":"UA",
    "qs_pg:gn_country":"UA",
    "qs_pg:gn_fcode":"PPL",
    "qs_pg:gn_pop":0,
    "qs_pg:name":"Makedonovka",
    "qs_pg:name_adm0":"Ukraine",
    "qs_pg:name_adm1":"Luhans\u00b4ka Oblast\u00b4",
    "qs_pg:photos":16,
    "qs_pg:photos_1k":3,
    "qs_pg:photos_9k":1,
    "qs_pg:photos_9r":1,
    "qs_pg:photos_all":16,
    "qs_pg:photos_sr":1,
    "qs_pg:pop_sr":0,
    "qs_pg:qs_pg_placetype":"locality",
    "qs_pg:qs_pg_placetype_gp":"Town",
    "qs_pg:woe_adm0":23424976,
    "woe:adm0_id":23424976,
    "woe:name_adm0":"Ukraine",
    "woe:name_adm1":"Luhans\u00b4ka Oblast\u00b4",
    "woe:placetype":"Town",
    "wof:name":"Makedonovka",
    "wof:placetype":"locality"
},
  "geometry": {"coordinates":[39.29426,48.23538],"type":"Point"}
}