{
  "type": "Feature",
  "properties": {
    "gn:admin1_code":"15.0",
    "gn:asciiname":"Lagodov",
    "gn:country_code":"UA",
    "gn:dem":352,
    "gn:elevation":"380.0",
    "gn:feature_class":"P",
    "gn:feature_code":"PPL",
    "gn:name":"Lagodov",
    "gn:population":0,
    "gn:timezone":"Europe/Kiev",
    "iso:country":"UA",
    "name:und_x_variant":[
        "Lagodiv",
        "Lagodov"
    ],
    "wof:name":"Lagodov",
    "wof:placetype":"locality"
},
  "geometry": {"coordinates":[24.50269,49.72431],"type":"Point"}
}