{
  "type": "Feature",
  "properties": {
    "gn:admin1_code":"7.0",
    "gn:asciiname":"Lebedivka",
    "gn:country_code":"UA",
    "gn:dem":150,
    "gn:feature_class":"P",
    "gn:feature_code":"PPL",
    "gn:name":"Lebedivka",
    "gn:population":0,
    "gn:timezone":"Europe/Kiev",
    "iso:country":"UA",
    "name:rus_x_preferred":[
        "\u041b\u0435\u0431\u0435\u0434\u0435\u0432\u043a\u0430"
    ],
    "name:ukr_x_preferred":[
        "Lebedivka"
    ],
    "name:ukr_x_variant":[
        "\u041b\u0435\u0431\u0435\u0434\u0456\u0432\u043a\u0430"
    ],
    "name:und_x_variant":[
        "Lebedovka",
        "Lebedevka"
    ],
    "wof:name":"Lebedivka",
    "wof:placetype":"locality"
},
  "geometry": {"coordinates":[35.95863,49.16275],"type":"Point"}
}