{
  "type": "Feature",
  "properties": {
    "gn:admin1_code":"7.0",
    "gn:asciiname":"Baba",
    "gn:country_code":"UA",
    "gn:dem":149,
    "gn:feature_class":"P",
    "gn:feature_code":"PPL",
    "gn:name":"Baba",
    "gn:population":0,
    "gn:timezone":"Europe/Kiev",
    "iso:country":"UA",
    "wof:name":"Baba",
    "wof:placetype":"locality"
},
  "geometry": {"coordinates":[37.17111,49.70694],"type":"Point"}
}