{
  "type": "Feature",
  "properties": {
    "gn:admin1_code":"7.0",
    "gn:asciiname":"Baba",
    "gn:country_code":"UA",
    "gn:dem":149,
    "gn:feature_class":"P",
    "gn:feature_code":"PPL",
    "gn:name":"Baba",
    "gn:population":0,
    "gn:timezone":"Europe/Kiev",
    "iso:country":"UA",
    "name:ara_x_preferred":[
        "\u0628\u0627\u0628\u0627"
    ],
    "name:aze_x_preferred":[
        "Baba"
    ],
    "name:bul_x_preferred":[
        "\u0411\u0430\u0431\u0430"
    ],
    "name:cat_x_preferred":[
        "Baba"
    ],
    "name:ceb_x_preferred":[
        "Baba"
    ],
    "name:ces_x_preferred":[
        "Baba"
    ],
    "name:deu_x_preferred":[
        "Baba"
    ],
    "name:epo_x_preferred":[
        "Baba"
    ],
    "name:fin_x_preferred":[
        "Baba"
    ],
    "name:fra_x_preferred":[
        "Baba"
    ],
    "name:heb_x_preferred":[
        "\u05d1\u05d1\u05d0"
    ],
    "name:hin_x_preferred":[
        "\u092c\u093e\u092c\u093e"
    ],
    "name:hrv_x_preferred":[
        "Baba"
    ],
    "name:hun_x_preferred":[
        "Baba"
    ],
    "name:hye_x_preferred":[
        "\u0532\u0561\u0562\u0561"
    ],
    "name:ita_x_preferred":[
        "Baba"
    ],
    "name:kaz_x_preferred":[
        "\u0411\u0430\u0431\u0430"
    ],
    "name:nld_x_preferred":[
        "Baba"
    ],
    "name:nno_x_preferred":[
        "Baba"
    ],
    "name:pol_x_preferred":[
        "Baba"
    ],
    "name:por_x_preferred":[
        "Baba"
    ],
    "name:ron_x_preferred":[
        "Baba"
    ],
    "name:rus_x_preferred":[
        "\u0411\u0430\u0431\u0430"
    ],
    "name:slk_x_preferred":[
        "Baba"
    ],
    "name:slv_x_preferred":[
        "Baba"
    ],
    "name:spa_x_preferred":[
        "Baba"
    ],
    "name:srp_x_preferred":[
        "\u0411\u0430\u0431\u0430"
    ],
    "name:swe_x_preferred":[
        "Baba"
    ],
    "name:tgl_x_preferred":[
        "Baba"
    ],
    "name:tur_x_preferred":[
        "Baba"
    ],
    "name:ukr_x_preferred":[
        "\u0411\u0430\u0431\u0430"
    ],
    "name:urd_x_preferred":[
        "\u0628\u0627\u0628\u0627"
    ],
    "wof:name":"Baba",
    "wof:placetype":"locality"
},
  "geometry": {"coordinates":[37.17111,49.70694],"type":"Point"}
}