{
  "type": "Feature",
  "properties": {
    "gn:admin1_code":"5.0",
    "gn:asciiname":"Novoyelanchyk",
    "gn:country_code":"UA",
    "gn:dem":125,
    "gn:feature_class":"P",
    "gn:feature_code":"PPL",
    "gn:name":"Novoyelanchyk",
    "gn:population":0,
    "gn:timezone":"Europe/Kiev",
    "iso:country":"UA",
    "name:ukr_x_preferred":[
        "Novoyelanchyk"
    ],
    "name:ukr_x_variant":[
        "\u041d\u043e\u0432\u043e\u0454\u043b\u0430\u043d\u0447\u0438\u043a"
    ],
    "name:und_x_variant":[
        "Novoyelanchik"
    ],
    "wof:name":"Novoyelanchyk",
    "wof:placetype":"locality"
},
  "geometry": {"coordinates":[38.43221,47.77972000000001],"type":"Point"}
}