{
  "type": "Feature",
  "properties": {
    "gn:admin1_code":"27.0",
    "gn:asciiname":"Khomivka",
    "gn:country_code":"UA",
    "gn:dem":144,
    "gn:feature_class":"P",
    "gn:feature_code":"PPL",
    "gn:name":"Khomivka",
    "gn:population":0,
    "gn:timezone":"Europe/Kiev",
    "iso:country":"UA",
    "name:ukr_x_preferred":[
        "Khomivka"
    ],
    "name:ukr_x_variant":[
        "\u0425\u043e\u043c\u0456\u0432\u043a\u0430"
    ],
    "name:und_x_variant":[
        "Khomovka"
    ],
    "wof:name":"Khomivka",
    "wof:placetype":"locality"
},
  "geometry": {"coordinates":[29.45311,50.54847],"type":"Point"}
}