{
  "type": "Feature",
  "properties": {
    "iso:country":"UA",
    "name:ukr_x_preferred":[
        "Rakhynya"
    ],
    "name:ukr_x_variant":[
        "\u0420\u0430\u0445\u0438\u043d\u044f"
    ],
    "name:unk_x_variant":[
        "Rakhin\u2019"
    ],
    "qs:a0":"\u0423\u043a\u0440\u0430\u0457\u043d\u0430",
    "qs:a1":"*\u0406\u0432\u0430\u043d\u043e-\u0424\u0440\u0430\u043d\u043a\u0456\u0432\u0441\u044c\u043a\u0430",
    "qs:a1_alt":"Ivano-Frankivs'ka",
    "qs:a1r":"0",
    "qs:a2":"\u0414\u043e\u043b\u0438\u043d\u0441\u044c\u043a\u0438\u0439",
    "qs:a2_alt":"Dolyns'kyi",
    "qs:adm0":"\u0423\u043a\u0440\u0430\u0457\u043d\u0430",
    "qs:la_lc":"*",
    "qs:level":"locality",
    "qs:loc":"\u0420\u0430\u0445\u0438\u043d\u044f",
    "qs:loc_alt":"Rakhynia",
    "qs:pop":0,
    "qs:type":"buffered point",
    "wof:name":"\u0420\u0430\u0445\u0438\u043d\u044f",
    "wof:placetype":"locality"
},
  "geometry": {"coordinates":[24.043797,48.993546],"type":"Point"}
}