{
  "type": "Feature",
  "properties": {
    "iso:country":"UA",
    "qs:a0":"\u0423\u043a\u0440\u0430\u0457\u043d\u0430",
    "qs:a1":"*\u041e\u0434\u0435\u0441\u044c\u043a\u0430",
    "qs:a1_alt":"Odes'ka",
    "qs:a1r":"0",
    "qs:a2":"\u0406\u0437\u043c\u0430\u0457\u043b\u044c\u0441\u044c\u043a\u0438\u0439",
    "qs:a2_alt":"Izmail's'kyi",
    "qs:adm0":"\u0423\u043a\u0440\u0430\u0457\u043d\u0430",
    "qs:la_lc":"*",
    "qs:level":"locality",
    "qs:loc":"\u041f\u0435\u0440\u0448\u043e\u0442\u0440\u0430\u0432\u043d\u0435\u0432\u0435",
    "qs:loc_alt":"Pershotravneve",
    "qs:pop":0,
    "qs:type":"buffered point",
    "wd:wordcount":61,
    "wof:name":"\u041f\u0435\u0440\u0448\u043e\u0442\u0440\u0430\u0432\u043d\u0435\u0432\u0435",
    "wof:placetype":"locality"
},
  "geometry": {"coordinates":[29.047873,45.496225],"type":"Point"}
}