{
  "type": "Feature",
  "properties": {
    "gn:admin1_code":"16.0",
    "gn:asciiname":"Anatol'yevka",
    "gn:country_code":"UA",
    "gn:dem":115,
    "gn:feature_class":"P",
    "gn:feature_code":"PPL",
    "gn:name":"Anatol\u2019yevka",
    "gn:population":0,
    "gn:timezone":"Europe/Kiev",
    "iso:country":"UA",
    "name:und_x_variant":[
        "Khutor Anatol\u2019yevka",
        "Anatol\u2019yevka"
    ],
    "wof:name":"Anatol'yevka",
    "wof:placetype":"locality"
},
  "geometry": {"coordinates":[30.93333,47.55],"type":"Point"}
}