{
  "type": "Feature",
  "properties": {
    "iso:country":"UA",
    "name:und_x_variant":[
        "Borshchiv"
    ],
    "qs:a0":"\u0423\u043a\u0440\u0430\u0457\u043d\u0430",
    "qs:a1":"*\u041b\u044c\u0432\u0456\u0432\u0441\u044c\u043a\u0430",
    "qs:a1_alt":"L'vivs'ka",
    "qs:a1r":"0",
    "qs:a2":"\u041f\u0435\u0440\u0435\u043c\u0438\u0448\u043b\u044f\u043d\u0441\u044c\u043a\u0438\u0439",
    "qs:a2_alt":"Peremyshlians'kyi",
    "qs:adm0":"\u0423\u043a\u0440\u0430\u0457\u043d\u0430",
    "qs:la_lc":"*",
    "qs:level":"locality",
    "qs:loc":"\u0411\u043e\u0440\u0449\u0456\u0432",
    "qs:loc_alt":"Borschiv",
    "qs:pop":0,
    "qs:type":"buffered point",
    "wd:wordcount":528,
    "wof:name":"\u0411\u043e\u0440\u0449\u0456\u0432",
    "wof:placetype":"locality"
},
  "geometry": {"coordinates":[24.590586,49.66056],"type":"Point"}
}