{
  "type": "Feature",
  "properties": {
    "iso:country":"UA",
    "name:eng_x_preferred":[
        "Vinogradovo"
    ],
    "name:rus_x_historical":[
        "\u0411\u043e\u0437-\u041e\u0433\u043b\u0443\u0301-\u041c\u043e\u043d\u0442\u0430\u043d\u0430\u0301\u0439"
    ],
    "name:rus_x_preferred":[
        "\u0412\u0438\u043d\u043e\u0433\u0440\u0430\u0434\u043e\u0432\u043e"
    ],
    "name:rus_x_variant":[
        "\u0411\u043e\u0437-\u041e\u0433\u043b\u0443\u0301-\u041c\u043e\u043d\u0442\u0430\u043d\u0430\u0301\u0439"
    ],
    "name:ukr_x_preferred":[
        "\u0412\u0438\u043d\u043e\u0433\u0440\u0430\u0434\u043e\u0432\u0435"
    ],
    "qs:a0":"\u0423\u043a\u0440\u0430\u0457\u043d\u0430",
    "qs:a1":"*\u041a\u0440\u0438\u043c",
    "qs:a1_alt":"Krym",
    "qs:a1r":"0",
    "qs:a2":"\u0421\u0430\u043a\u0441\u044c\u043a\u0438\u0439",
    "qs:a2_alt":"Saks'kyi",
    "qs:adm0":"\u0423\u043a\u0440\u0430\u0457\u043d\u0430",
    "qs:la_lc":"*",
    "qs:level":"locality",
    "qs:loc":"\u0412\u0438\u043d\u043e\u0433\u0440\u0430\u0434\u043e\u0432\u0435",
    "qs:loc_alt":"Vynohradove",
    "qs:pop":0,
    "qs:type":"buffered point",
    "wof:name":"\u0412\u0438\u043d\u043e\u0433\u0440\u0430\u0434\u043e\u0432\u0435",
    "wof:placetype":"locality"
},
  "geometry": {"coordinates":[33.644715,45.394079],"type":"Point"}
}