{
  "type": "Feature",
  "properties": {
    "gn:admin1_code":"14.0",
    "gn:asciiname":"Yurkivka",
    "gn:country_code":"UA",
    "gn:dem":168,
    "gn:feature_class":"P",
    "gn:feature_code":"PPL",
    "gn:name":"Yurkivka",
    "gn:population":0,
    "gn:timezone":"Europe/Zaporozhye",
    "iso:country":"UA",
    "name:und_x_variant":[
        "Yurkovka"
    ],
    "wof:name":"Yurkivka",
    "wof:placetype":"locality"
},
  "geometry": {"coordinates":[38.15,49.83333],"type":"Point"}
}