{
  "type": "Feature",
  "properties": {
    "gn:admin1_code":"17.0",
    "gn:asciiname":"Katlabug",
    "gn:country_code":"UA",
    "gn:dem":13,
    "gn:feature_class":"P",
    "gn:feature_code":"PPL",
    "gn:name":"Katlabug",
    "gn:population":0,
    "gn:timezone":"Europe/Kiev",
    "iso:country":"UA",
    "name:und_x_variant":[
        "Catlapuh",
        "Katlabug",
        "Oz\u00ebrnoye"
    ],
    "wof:name":"Katlabug",
    "wof:placetype":"locality"
},
  "geometry": {"coordinates":[29.96667,45.81667],"type":"Point"}
}