{
  "type": "Feature",
  "properties": {
    "gn:admin1_code":"7.0",
    "gn:asciiname":"Dmytrivka",
    "gn:country_code":"UA",
    "gn:dem":80,
    "gn:feature_class":"P",
    "gn:feature_code":"PPL",
    "gn:name":"Dmytrivka",
    "gn:population":0,
    "gn:timezone":"Europe/Kiev",
    "iso:country":"UA",
    "name:ceb_x_preferred":[
        "Dmytrivka"
    ],
    "name:deu_x_preferred":[
        "Dmytriwka"
    ],
    "name:est_x_preferred":[
        "Dm\u00f5trivka"
    ],
    "name:hye_x_preferred":[
        "\u0534\u0574\u056b\u057f\u0580\u0578\u057e\u056f\u0561"
    ],
    "name:rus_x_preferred":[
        "\u0414\u043c\u0438\u0442\u0440\u043e\u0432\u043a\u0430"
    ],
    "name:spa_x_preferred":[
        "Dmytrivka"
    ],
    "name:ukr_x_preferred":[
        "\u0414\u043c\u0438\u0442\u0440\u0456\u0432\u043a\u0430"
    ],
    "name:und_x_variant":[
        "Dmitriyevka",
        "Dmitrovka"
    ],
    "wof:name":"Dmytrivka",
    "wof:placetype":"locality"
},
  "geometry": {"coordinates":[36.67334,49.14219],"type":"Point"}
}