{
  "type": "Feature",
  "properties": {
    "iso:country":"UA",
    "name:bel_x_variant":[
        "\u0406\u043d\u0433\u0443\u043b\u0435\u0446"
    ],
    "name:bul_x_preferred":[
        "\u0418\u043d\u0433\u0443\u043b\u0435\u0446"
    ],
    "name:cat_x_preferred":[
        "Inhulets"
    ],
    "name:ces_x_preferred":[
        "Inhulec"
    ],
    "name:dan_x_preferred":[
        "Inhulets"
    ],
    "name:deu_x_preferred":[
        "Inhulez"
    ],
    "name:eng_x_preferred":[
        "Inhulets"
    ],
    "name:fas_x_preferred":[
        "\u0631\u0648\u062f\u062e\u0627\u0646\u0647 \u0627\u06cc\u0646\u06af\u0648\u0644\u062a"
    ],
    "name:fra_x_preferred":[
        "Inhoulets"
    ],
    "name:hrv_x_preferred":[
        "Ingulec"
    ],
    "name:ita_x_preferred":[
        "Inhulec'"
    ],
    "name:lav_x_preferred":[
        "Inhuleca"
    ],
    "name:lit_x_preferred":[
        "Inhulecas"
    ],
    "name:nno_x_preferred":[
        "Inhulets"
    ],
    "name:nor_x_preferred":[
        "Inhulets"
    ],
    "name:pol_x_preferred":[
        "Ingulec"
    ],
    "name:ron_x_preferred":[
        "Inhule\u021b"
    ],
    "name:rus_x_preferred":[
        "\u0418\u043d\u0433\u0443\u043b\u0435\u0446"
    ],
    "name:spa_x_preferred":[
        "R\u00edo Inhulets"
    ],
    "name:swe_x_preferred":[
        "Inhulets"
    ],
    "name:tgk_x_preferred":[
        "\u0418\u043d\u0433\u0443\u043b\u0435\u0442\u0441"
    ],
    "name:ukr_x_preferred":[
        "\u0406\u043d\u0433\u0443\u043b\u0435\u0446\u044c"
    ],
    "name:ukr_x_variant":[
        "Inhulets\u2019"
    ],
    "name:und_x_variant":[
        "Ingulets"
    ],
    "name:zho_x_preferred":[
        "\u56e0\u53e4\u5217\u8328\u6cb3"
    ],
    "name:zho_x_variant":[
        "\u56e0\u53e4\u5217\u9f4a"
    ],
    "qs:a0":"\u0423\u043a\u0440\u0430\u0457\u043d\u0430",
    "qs:a1":"*\u0425\u0435\u0440\u0441\u043e\u043d\u0441\u044c\u043a\u0430",
    "qs:a1_alt":"Khersons'ka",
    "qs:a1r":"0",
    "qs:a2":"\u0411\u0456\u043b\u043e\u0437\u0435\u0440\u0441\u044c\u043a\u0438\u0439",
    "qs:a2_alt":"Bilozers'kyi",
    "qs:adm0":"\u0423\u043a\u0440\u0430\u0457\u043d\u0430",
    "qs:la_lc":"*",
    "qs:level":"locality",
    "qs:loc":"\u0406\u043d\u0433\u0443\u043b\u0435\u0446\u044c",
    "qs:loc_alt":"Inhulets",
    "qs:pop":0,
    "qs:type":"buffered point",
    "wd:wordcount":199,
    "wof:name":"\u0406\u043d\u0433\u0443\u043b\u0435\u0446\u044c",
    "wof:placetype":"locality"
},
  "geometry": {"coordinates":[32.830058,46.800466],"type":"Point"}
}