{
  "type": "Feature",
  "properties": {
    "gn:admin1_code":"9.0",
    "gn:asciiname":"Stepok",
    "gn:country_code":"UA",
    "gn:dem":280,
    "gn:feature_class":"P",
    "gn:feature_code":"PPL",
    "gn:name":"Stepok",
    "gn:population":0,
    "gn:timezone":"Europe/Kiev",
    "iso:country":"UA",
    "name:ukr_x_preferred":[
        "Stepok"
    ],
    "name:ukr_x_variant":[
        "\u0421\u0442\u0435\u043f\u043e\u043a"
    ],
    "wof:name":"Stepok",
    "wof:placetype":"locality"
},
  "geometry": {"coordinates":[27.37951,49.73533],"type":"Point"}
}