{
  "type": "Feature",
  "properties": {
    "gn:admin1_code":"7.0",
    "gn:asciiname":"Karayichne",
    "gn:country_code":"UA",
    "gn:dem":119,
    "gn:feature_class":"P",
    "gn:feature_code":"PPL",
    "gn:name":"Karayichne",
    "gn:population":0,
    "gn:timezone":"Europe/Kiev",
    "iso:country":"UA",
    "name:rus_x_preferred":[
        "\u041a\u0430\u0440\u0430\u0438\u0447\u043d\u043e\u0435"
    ],
    "name:ukr_x_preferred":[
        "Karayichne"
    ],
    "name:ukr_x_variant":[
        "\u041a\u0430\u0440\u0430\u0457\u0447\u043d\u0435"
    ],
    "name:und_x_variant":[
        "Karaichnoye"
    ],
    "wof:name":"Karayichne",
    "wof:placetype":"locality"
},
  "geometry": {"coordinates":[37.12544000000001,50.30454],"type":"Point"}
}