{
  "type": "Feature",
  "properties": {
    "gn:admin1_code":"7.0",
    "gn:asciiname":"Oliynyky",
    "gn:country_code":"UA",
    "gn:dem":116,
    "gn:feature_class":"P",
    "gn:feature_code":"PPL",
    "gn:name":"Oliynyky",
    "gn:population":0,
    "gn:timezone":"Europe/Kiev",
    "iso:country":"UA",
    "name:rus_x_preferred":[
        "\u041e\u043b\u0435\u0439\u043d\u0438\u043a\u0438"
    ],
    "name:ukr_x_preferred":[
        "Oliynyky"
    ],
    "name:ukr_x_variant":[
        "\u041e\u043b\u0456\u0439\u043d\u0438\u043a\u0438"
    ],
    "name:und_x_variant":[
        "Oleyniki"
    ],
    "wof:name":"Oliynyky",
    "wof:placetype":"locality"
},
  "geometry": {"coordinates":[36.06792,49.22556],"type":"Point"}
}