{
  "type": "Feature",
  "properties": {
    "iso:country":"UA",
    "name:eng_x_preferred":[
        "Vasil'yevka"
    ],
    "name:rus_x_preferred":[
        "\u0412\u0430\u0441\u0438\u043b\u0435\u0432\u043a\u0430"
    ],
    "name:ukr_x_preferred":[
        "Vasylivka"
    ],
    "name:ukr_x_variant":[
        "\u0412\u0430\u0441\u0438\u043b\u0456\u0432\u043a\u0430"
    ],
    "name:unk_x_variant":[
        "Vasilevka"
    ],
    "qs:a0":"\u0423\u043a\u0440\u0430\u0457\u043d\u0430",
    "qs:a1":"*\u0421\u0443\u043c\u0441\u044c\u043a\u0430",
    "qs:a1_alt":"Sums'ka",
    "qs:a1r":"0",
    "qs:a2":"\u041b\u0435\u0431\u0435\u0434\u0438\u043d\u0441\u044c\u043a\u0438\u0439",
    "qs:a2_alt":"Lebedyns'kyi",
    "qs:adm0":"\u0423\u043a\u0440\u0430\u0457\u043d\u0430",
    "qs:la_lc":"*",
    "qs:level":"locality",
    "qs:loc":"\u0412\u0430\u0441\u0438\u043b\u0456\u0432\u043a\u0430",
    "qs:loc_alt":"Vasylivka",
    "qs:pop":0,
    "qs:type":"buffered point",
    "wd:wordcount":146,
    "wof:name":"\u0412\u0430\u0441\u0438\u043b\u0456\u0432\u043a\u0430",
    "wof:placetype":"locality"
},
  "geometry": {"coordinates":[34.188886,50.652693],"type":"Point"}
}