{
  "type": "Feature",
  "properties": {
    "gn:admin1_code":"5.0",
    "gn:asciiname":"Orlyns'ke",
    "gn:country_code":"UA",
    "gn:dem":129,
    "gn:feature_class":"P",
    "gn:feature_code":"PPL",
    "gn:name":"Orlyns\u2019ke",
    "gn:population":0,
    "gn:timezone":"Europe/Kiev",
    "iso:country":"UA",
    "name:ukr_x_preferred":[
        "Orlyns\u2019ke"
    ],
    "name:ukr_x_variant":[
        "\u041e\u0440\u043b\u0438\u043d\u0441\u044c\u043a\u0435"
    ],
    "name:und_x_variant":[
        "Orlinskaya"
    ],
    "wof:name":"Orlyns'ke",
    "wof:placetype":"locality"
},
  "geometry": {"coordinates":[36.76606,47.65342],"type":"Point"}
}