{
  "type": "Feature",
  "properties": {
    "gn:admin1_code":"9.0",
    "gn:asciiname":"Velikiy Aleksandrov",
    "gn:country_code":"UA",
    "gn:dem":267,
    "gn:feature_class":"P",
    "gn:feature_code":"PPL",
    "gn:name":"Velikiy Aleksandrov",
    "gn:population":0,
    "gn:timezone":"Europe/Kiev",
    "iso:country":"UA",
    "name:und_x_variant":[
        "Bol\u2019shoy Aleksandrov",
        "Velikiy Aleksandrov"
    ],
    "wof:name":"Velikiy Aleksandrov",
    "wof:placetype":"locality"
},
  "geometry": {"coordinates":[27.13278,48.99486],"type":"Point"}
}