{
  "type": "Feature",
  "properties": {
    "iso:country":"UA",
    "name:ukr_x_preferred":[
        "Nyzhnya Apsha"
    ],
    "name:ukr_x_variant":[
        "\u041d\u0438\u0436\u043d\u044f \u0410\u043f\u0448\u0430"
    ],
    "name:unk_x_variant":[
        "Dibrovo"
    ],
    "qs:a0":"\u0423\u043a\u0440\u0430\u0457\u043d\u0430",
    "qs:a1":"*\u0417\u0430\u043a\u0430\u0440\u043f\u0430\u0442\u0441\u044c\u043a\u0430",
    "qs:a1_alt":"Zakarpats'ka",
    "qs:a1r":"0",
    "qs:a2":"\u0422\u044f\u0447\u0456\u0432\u0441\u044c\u043a\u0438\u0439",
    "qs:a2_alt":"Tiachivs'kyi",
    "qs:adm0":"\u0423\u043a\u0440\u0430\u0457\u043d\u0430",
    "qs:la_lc":"*",
    "qs:level":"locality",
    "qs:loc":"\u0414\u0456\u0431\u0440\u043e\u0432\u0430",
    "qs:loc_alt":"Dibrova",
    "qs:pop":0,
    "qs:type":"buffered point",
    "wd:wordcount":104,
    "wof:name":"\u0414\u0456\u0431\u0440\u043e\u0432\u0430",
    "wof:placetype":"locality"
},
  "geometry": {"coordinates":[23.855598,47.996216],"type":"Point"}
}