{
  "type": "Feature",
  "properties": {
    "gn:admin1_code":"27.0",
    "gn:asciiname":"Verlok",
    "gn:country_code":"UA",
    "gn:dem":171,
    "gn:feature_class":"P",
    "gn:feature_code":"PPL",
    "gn:name":"Verlok",
    "gn:population":0,
    "gn:timezone":"Europe/Kiev",
    "iso:country":"UA",
    "name:ukr_x_preferred":[
        "Verlok"
    ],
    "name:ukr_x_variant":[
        "\u0412\u0435\u0440\u043b\u043e\u043a"
    ],
    "name:und_x_variant":[
        "Verlook"
    ],
    "wof:name":"Verlok",
    "wof:placetype":"locality"
},
  "geometry": {"coordinates":[29.1683,50.49569],"type":"Point"}
}