{
  "type": "Feature",
  "properties": {
    "gn:admin1_code":"7.0",
    "gn:asciiname":"Frunze",
    "gn:country_code":"UA",
    "gn:dem":154,
    "gn:feature_class":"P",
    "gn:feature_code":"PPL",
    "gn:name":"Frunze",
    "gn:population":0,
    "gn:timezone":"Europe/Kiev",
    "iso:country":"UA",
    "name:ukr_x_preferred":[
        "\u0424\u0440\u0443\u043d\u0437\u0435"
    ],
    "wof:name":"Frunze",
    "wof:placetype":"locality"
},
  "geometry": {"coordinates":[36.44573,50.0185],"type":"Point"}
}