{
  "type": "Feature",
  "properties": {
    "gn:admin1_code":"17.0",
    "gn:asciiname":"Yasnopillya",
    "gn:country_code":"UA",
    "gn:dem":102,
    "gn:elevation":"97.0",
    "gn:feature_class":"P",
    "gn:feature_code":"PPL",
    "gn:name":"Yasnopillya",
    "gn:population":333,
    "gn:timezone":"Europe/Kiev",
    "iso:country":"UA",
    "name:deu_x_historical":[
        "Jasnopolje",
        "Lichtenfeld"
    ],
    "name:deu_x_preferred":[
        "Jasnopillja"
    ],
    "name:deu_x_variant":[
        "Jassnopillja",
        "Jasnopolje",
        "Lichtenfeld"
    ],
    "name:rus_x_preferred":[
        "Yasnopol\u2019ye"
    ],
    "name:rus_x_variant":[
        "\u042f\u0441\u043d\u043e\u043f\u043e\u043b\u044c\u0435"
    ],
    "name:spa_x_preferred":[
        "Yasnopillya"
    ],
    "name:ukr_x_preferred":[
        "\u042f\u0441\u043d\u043e\u043f\u0456\u043b\u043b\u044f"
    ],
    "name:ukr_x_variant":[
        "Yasnopill'ya"
    ],
    "name:und_x_variant":[
        "Likhtenfel\u2019d",
        "Yasnopillia"
    ],
    "wof:name":"Yasnopillya",
    "wof:placetype":"locality",
    "wof:population":333
},
  "geometry": {"coordinates":[30.81622,47.35563],"type":"Point"}
}