{
  "type": "Feature",
  "properties": {
    "gn:admin1_code":"5.0",
    "gn:asciiname":"Pyatipol'ye",
    "gn:country_code":"UA",
    "gn:dem":230,
    "gn:feature_class":"P",
    "gn:feature_code":"PPL",
    "gn:name":"Pyatipol\u2019ye",
    "gn:population":0,
    "gn:timezone":"Europe/Kiev",
    "iso:country":"UA",
    "wof:name":"Pyatipol'ye",
    "wof:placetype":"locality"
},
  "geometry": {"coordinates":[38.095,48.01861],"type":"Point"}
}