{
  "type": "Feature",
  "properties": {
    "gn:admin1_code":"9.0",
    "gn:asciiname":"Zaglosna",
    "gn:country_code":"UA",
    "gn:dem":228,
    "gn:feature_class":"P",
    "gn:feature_code":"PPL",
    "gn:name":"Zaglosna",
    "gn:population":0,
    "gn:timezone":"Europe/Kiev",
    "iso:country":"UA",
    "wof:name":"Zaglosna",
    "wof:placetype":"locality"
},
  "geometry": {"coordinates":[27.05342000000001,48.81346],"type":"Point"}
}