{
  "type": "Feature",
  "properties": {
    "gn:admin1_code":"5.0",
    "gn:admin2_code":"704417",
    "gn:asciiname":"Fedorivka",
    "gn:country_code":"UA",
    "gn:dem":132,
    "gn:feature_class":"P",
    "gn:feature_code":"PPL",
    "gn:name":"Fedorivka",
    "gn:population":0,
    "gn:timezone":"Europe/Kiev",
    "iso:country":"UA",
    "name:ara_x_preferred":[
        "\u0641\u064a\u062f\u0648\u0631\u0625\u064a\u0641\u0643\u0627"
    ],
    "name:ell_x_preferred":[
        "\u03a6\u03b5\u03bd\u03c4\u03bf\u03c1\u03b9\u03b2\u03ba\u03b1"
    ],
    "name:eng_x_preferred":[
        "Fedorivka"
    ],
    "name:heb_x_preferred":[
        "\u05e4\u05b6\u05d3\u05d5\u05b9\u05e8\u05b4\u05d9\u05d1\u05b0\u05e7\u05b8\u05d4"
    ],
    "name:hye_x_colloquial":[
        "\u0556\u0565\u0564\u0578\u057c\u0578\u057e\u056f\u0561"
    ],
    "name:hye_x_preferred":[
        "\u0556\u0565\u0564\u0578\u0580\u056b\u057e\u056f\u0561"
    ],
    "name:hye_x_variant":[
        "\u053c\u0578\u0582\u0576\u0561\u0579\u0561\u0580\u057d\u056f\u0578\u0565",
        "\u0556\u0565\u0564\u0578\u057c\u0578\u057e\u056f\u0561"
    ],
    "name:jpn_x_preferred":[
        "\u30d5\u30a7\u30c9\u30ea\u30f4\u30ab"
    ],
    "name:rus_x_historical":[
        "Lunacharskoye",
        "\u041b\u0443\u043d\u0430\u0447\u0430\u0440\u0441\u043a\u043e\u0435"
    ],
    "name:rus_x_preferred":[
        "Lunacharskoye"
    ],
    "name:rus_x_variant":[
        "\u041b\u0443\u043d\u0430\u0447\u0430\u0440\u0441\u043a\u043e\u0435"
    ],
    "name:ukr_x_historical":[
        "Lunachars\u2019ke",
        "\u041b\u0443\u043d\u0430\u0447\u0430\u0440\u0441\u044c\u043a\u0435"
    ],
    "name:ukr_x_preferred":[
        "Lunachars\u2019ke"
    ],
    "name:ukr_x_variant":[
        "\u041b\u0443\u043d\u0430\u0447\u0430\u0440\u0441\u044c\u043a\u0435"
    ],
    "name:und_x_variant":[
        "Fedoriwka"
    ],
    "name:yid_x_preferred":[
        "\u05e4\u05bf\u05e2\u05d3\u05d0\u05b8\u05e8\u05d9\u05d5\u05d5\u05e7\u05d0\u05b7"
    ],
    "wof:name":"Fedorivka",
    "wof:placetype":"locality"
},
  "geometry": {"coordinates":[37.28446,48.37973],"type":"Point"}
}