{
  "type": "Feature",
  "properties": {
    "gn:admin1_code":"26.0",
    "gn:asciiname":"Berestove",
    "gn:country_code":"UA",
    "gn:dem":138,
    "gn:feature_class":"P",
    "gn:feature_code":"PPL",
    "gn:name":"Berestove",
    "gn:population":0,
    "gn:timezone":"Europe/Zaporozhye",
    "iso:country":"UA",
    "name:jpn_x_preferred":[
        "\u30d9\u30ec\u30b9\u30c8\u30f4\u30a7"
    ],
    "name:rus_x_preferred":[
        "\u0411\u0435\u0440\u0435\u0441\u0442\u043e\u0432\u043e"
    ],
    "name:ukr_x_preferred":[
        "Berestove"
    ],
    "name:ukr_x_variant":[
        "\u0411\u0435\u0440\u0435\u0441\u0442\u043e\u0432\u0435"
    ],
    "name:und_x_variant":[
        "Berestovoye"
    ],
    "wof:name":"Berestove",
    "wof:placetype":"locality"
},
  "geometry": {"coordinates":[35.88523,48.06595],"type":"Point"}
}