{
  "type": "Feature",
  "properties": {
    "gn:admin1_code":"13.0",
    "gn:asciiname":"Koblyts'kyy Lis",
    "gn:country_code":"UA",
    "gn:dem":138,
    "gn:feature_class":"P",
    "gn:feature_code":"PPL",
    "gn:name":"Koblyts\u2019kyy Lis",
    "gn:population":0,
    "gn:timezone":"Europe/Kiev",
    "iso:country":"UA",
    "name:ukr_x_preferred":[
        "Koblyts\u2019kyy Lis"
    ],
    "name:ukr_x_variant":[
        "\u041a\u043e\u0431\u043b\u0438\u0446\u044c\u043a\u0438\u0439 \u041b\u0456\u0441"
    ],
    "name:und_x_variant":[
        "Koblitskiy Les"
    ],
    "wof:name":"Koblyts'kyy Lis",
    "wof:placetype":"locality"
},
  "geometry": {"coordinates":[29.91394,50.76966],"type":"Point"}
}