{
  "type": "Feature",
  "properties": {
    "gn:admin1_code":"18.0",
    "gn:asciiname":"Zahrebellya",
    "gn:country_code":"UA",
    "gn:dem":99,
    "gn:feature_class":"P",
    "gn:feature_code":"PPL",
    "gn:name":"Zahrebellya",
    "gn:population":0,
    "gn:timezone":"Europe/Kiev",
    "iso:country":"UA",
    "name:ukr_x_preferred":[
        "Zahrebellya"
    ],
    "name:ukr_x_variant":[
        "\u0417\u0430\u0433\u0440\u0435\u0431\u0435\u043b\u043b\u044f"
    ],
    "wof:name":"Zahrebellya",
    "wof:placetype":"locality"
},
  "geometry": {"coordinates":[33.07008,50.19708],"type":"Point"}
}