{
  "type": "Feature",
  "properties": {
    "gn:admin1_code":"27",
    "gn:asciiname":"Lisove",
    "gn:country_code":"UA",
    "gn:dem":274,
    "gn:feature_class":"P",
    "gn:feature_code":"PPL",
    "gn:name":"Lisove",
    "gn:population":0,
    "gn:timezone":"Europe/Kiev",
    "iso:country":"UA",
    "name:bel_x_preferred":[
        "\u041b\u0456\u0441\u0430\u0432\u044d"
    ],
    "name:deu_x_preferred":[
        "Lissowe"
    ],
    "name:rus_x_preferred":[
        "\u041b\u0435\u0441\u043e\u0432\u043e\u0435"
    ],
    "name:ukr_x_preferred":[
        "Chervona Zirka"
    ],
    "name:ukr_x_variant":[
        "\u0427\u0435\u0440\u0432\u043e\u043d\u0430 \u0417\u0456\u0440\u043a\u0430",
        "Lisove",
        "\u041b\u0456\u0441\u043e\u0432\u0435"
    ],
    "wof:name":"Lisove",
    "wof:placetype":"locality"
},
  "geometry": {"coordinates":[28.42225,49.86974],"type":"Point"}
}