{
  "type": "Feature",
  "properties": {
    "gn:admin1_code":"1.0",
    "gn:asciiname":"Buzukiv",
    "gn:country_code":"UA",
    "gn:dem":97,
    "gn:feature_class":"P",
    "gn:feature_code":"PPL",
    "gn:name":"Buzukiv",
    "gn:population":0,
    "gn:timezone":"Europe/Kiev",
    "iso:country":"UA",
    "name:ukr_x_preferred":[
        "Buzukiv"
    ],
    "name:ukr_x_variant":[
        "\u0411\u0443\u0437\u0443\u043a\u0456\u0432"
    ],
    "wof:name":"Buzukiv",
    "wof:placetype":"locality"
},
  "geometry": {"coordinates":[32.02066,49.31262],"type":"Point"}
}