{
  "type": "Feature",
  "properties": {
    "iso:country":"UA",
    "name:bel_x_preferred":[
        "\u0427\u0430\u043c\u044f\u0440\u044b\u045e\u0446\u044b"
    ],
    "name:bul_x_preferred":[
        "\u0427\u0435\u043c\u0435\u0440\u043e\u0432\u0446\u0438"
    ],
    "name:ces_x_preferred":[
        "Dunajivci"
    ],
    "name:che_x_preferred":[
        "\u0427\u0435\u043c\u0435\u0440\u043e\u0432\u0446\u044b"
    ],
    "name:crh_x_preferred":[
        "\u00c7emerivtsi"
    ],
    "name:deu_x_preferred":[
        "Tschemeriwzi"
    ],
    "name:eng_x_preferred":[
        "Chemerivtsi"
    ],
    "name:fra_x_preferred":[
        "Tchemerivtsi"
    ],
    "name:lit_x_preferred":[
        "\u010cemerivciai"
    ],
    "name:mhr_x_preferred":[
        "\u0427\u0435\u043c\u0435\u0440\u043e\u0432\u0446\u044b"
    ],
    "name:pol_x_preferred":[
        "Czemerowce"
    ],
    "name:ron_x_preferred":[
        "Cemeriv\u021bi"
    ],
    "name:rus_x_preferred":[
        "\u0427\u0435\u043c\u0435\u0440\u043e\u0432\u0446\u044b"
    ],
    "name:rus_x_variant":[
        "\u0427\u0435\u043c\u0435\u0440\u0456\u0432\u0446\u0456"
    ],
    "name:sco_x_preferred":[
        "Chemerivtsi"
    ],
    "name:ukr_x_preferred":[
        "\u0427\u0435\u043c\u0435\u0440\u0456\u0432\u0446\u0456"
    ],
    "name:und_x_variant":[
        "Chemirovtsy"
    ],
    "name:uzb_x_preferred":[
        "Chemerivtsi"
    ],
    "name:zho_x_preferred":[
        "\u5207\u6885\u91cc\u592b\u9f4a"
    ],
    "qs:a0":"\u0423\u043a\u0440\u0430\u0457\u043d\u0430",
    "qs:a1":"*\u0425\u043c\u0435\u043b\u044c\u043d\u0438\u0446\u044c\u043a\u0430",
    "qs:a1_alt":"Khmel'nyts'ka",
    "qs:a1r":"0",
    "qs:a2":"\u0427\u0435\u043c\u0435\u0440\u043e\u0432\u0435\u0446\u044c\u043a\u0438\u0439",
    "qs:a2_alt":"Chemerovets'kyi",
    "qs:adm0":"\u0423\u043a\u0440\u0430\u0457\u043d\u0430",
    "qs:la_lc":"*",
    "qs:level":"locality",
    "qs:loc":"\u0427\u0435\u043c\u0435\u0440\u0456\u0432\u0446\u0456",
    "qs:loc_alt":"Chemerivtsi",
    "qs:pop":0,
    "qs:type":"buffered point",
    "wd:wordcount":185,
    "wof:name":"\u0427\u0435\u043c\u0435\u0440\u0456\u0432\u0446\u0456",
    "wof:placetype":"locality"
},
  "geometry": {"coordinates":[26.361435,49.014846],"type":"Point"}
}