{
  "type": "Feature",
  "properties": {
    "gn:admin1_code":"26.0",
    "gn:asciiname":"Kozoluhivka",
    "gn:country_code":"UA",
    "gn:dem":46,
    "gn:feature_class":"P",
    "gn:feature_code":"PPL",
    "gn:name":"Kozoluhivka",
    "gn:population":0,
    "gn:timezone":"Europe/Zaporozhye",
    "iso:country":"UA",
    "name:ukr_x_preferred":[
        "Kozoluhivka"
    ],
    "name:ukr_x_variant":[
        "\u041a\u043e\u0437\u043e\u043b\u0443\u0433\u0456\u0432\u043a\u0430"
    ],
    "name:und_x_variant":[
        "Rikhenau",
        "Kozolugovka"
    ],
    "wof:name":"Kozoluhivka",
    "wof:placetype":"locality"
},
  "geometry": {"coordinates":[35.798,47.11],"type":"Point"}
}