{
  "type": "Feature",
  "properties": {
    "gn:admin1_code":"7.0",
    "gn:asciiname":"Volodarivka",
    "gn:country_code":"UA",
    "gn:dem":194,
    "gn:feature_class":"P",
    "gn:feature_code":"PPL",
    "gn:name":"Volodarivka",
    "gn:population":0,
    "gn:timezone":"Europe/Kiev",
    "iso:country":"UA",
    "name:ukr_x_preferred":[
        "Volodarivka"
    ],
    "name:ukr_x_variant":[
        "\u0412\u043e\u043b\u043e\u0434\u0430\u0440\u0456\u0432\u043a\u0430"
    ],
    "wof:name":"Volodarivka",
    "wof:placetype":"locality"
},
  "geometry": {"coordinates":[35.76011,50.13896],"type":"Point"}
}