{
  "type": "Feature",
  "properties": {
    "gn:admin1_code":"7.0",
    "gn:asciiname":"Pristin",
    "gn:country_code":"UA",
    "gn:dem":122,
    "gn:feature_class":"P",
    "gn:feature_code":"PPL",
    "gn:name":"Pristin",
    "gn:population":0,
    "gn:timezone":"Europe/Kiev",
    "iso:country":"UA",
    "name:ara_x_preferred":[
        "\u0628\u0631\u0633\u062a\u0646"
    ],
    "name:azb_x_preferred":[
        "\u0628\u0631\u0633\u062a\u0646"
    ],
    "name:deu_x_preferred":[
        "Pristin"
    ],
    "name:fin_x_preferred":[
        "Pristin"
    ],
    "name:fra_x_preferred":[
        "Pristin"
    ],
    "name:hye_x_preferred":[
        "Pristin"
    ],
    "name:ind_x_preferred":[
        "Pristin"
    ],
    "name:ita_x_preferred":[
        "Pristin"
    ],
    "name:kor_x_preferred":[
        "\ud504\ub9ac\uc2a4\ud2f4"
    ],
    "name:mon_x_preferred":[
        "Pristin"
    ],
    "name:msa_x_preferred":[
        "Pristin"
    ],
    "name:pol_x_preferred":[
        "Pristin"
    ],
    "name:por_x_preferred":[
        "Pristin"
    ],
    "name:rus_x_preferred":[
        "Pristin"
    ],
    "name:spa_x_preferred":[
        "Pristin"
    ],
    "name:swe_x_preferred":[
        "Pristin"
    ],
    "name:tha_x_preferred":[
        "\u0e1e\u0e23\u0e34\u0e2a\u0e17\u0e34\u0e19"
    ],
    "name:tur_x_preferred":[
        "Pristin"
    ],
    "name:vie_x_preferred":[
        "Pristin"
    ],
    "wof:name":"Pristin",
    "wof:placetype":"locality"
},
  "geometry": {"coordinates":[37.4844,49.24925],"type":"Point"}
}