{
  "type": "Feature",
  "properties": {
    "gn:admin1_code":"6.0",
    "gn:asciiname":"Donbrova",
    "gn:country_code":"UA",
    "gn:dem":222,
    "gn:feature_class":"P",
    "gn:feature_code":"PPL",
    "gn:name":"Donbrova",
    "gn:population":0,
    "gn:timezone":"Europe/Kiev",
    "iso:country":"UA",
    "name:und_x_variant":[
        "Dubrova",
        "Donbrova"
    ],
    "wof:name":"Donbrova",
    "wof:placetype":"locality"
},
  "geometry": {"coordinates":[25.09621,48.97158],"type":"Point"}
}