{
  "type": "Feature",
  "properties": {
    "gn:admin1_code":"17.0",
    "gn:asciiname":"Novoyelizavetovka",
    "gn:country_code":"UA",
    "gn:dem":34,
    "gn:feature_class":"P",
    "gn:feature_code":"PPL",
    "gn:name":"Novoyelizavetovka",
    "gn:population":0,
    "gn:timezone":"Europe/Kiev",
    "iso:country":"UA",
    "name:und_x_variant":[
        "Polustal\u2019",
        "Novaya Yelizavetovka",
        "Novoyelizavetovka"
    ],
    "wof:name":"Novoyelizavetovka",
    "wof:placetype":"locality"
},
  "geometry": {"coordinates":[30.39987,47.1538],"type":"Point"}
}