{
  "type": "Feature",
  "properties": {
    "gn:admin1_code":"4.0",
    "gn:asciiname":"Putylivka",
    "gn:country_code":"UA",
    "gn:dem":60,
    "gn:feature_class":"P",
    "gn:feature_code":"PPL",
    "gn:name":"Putylivka",
    "gn:population":0,
    "gn:timezone":"Europe/Kiev",
    "iso:country":"UA",
    "name:rus_x_preferred":[
        "\u041f\u0443\u0442\u0438\u043b\u043e\u0432\u043a\u0430"
    ],
    "name:ukr_x_preferred":[
        "Putylivka"
    ],
    "name:ukr_x_variant":[
        "\u041f\u0443\u0442\u0438\u043b\u0456\u0432\u043a\u0430"
    ],
    "name:und_x_variant":[
        "Otruba",
        "Putilino Boginovka",
        "Putilovka"
    ],
    "wof:name":"Putylivka",
    "wof:placetype":"locality"
},
  "geometry": {"coordinates":[34.20776,47.8062],"type":"Point"}
}