{
  "type": "Feature",
  "properties": {
    "gn:admin1_code":"26.0",
    "gn:asciiname":"Chervonyy",
    "gn:cc2":"UA",
    "gn:country_code":"UA",
    "gn:dem":137,
    "gn:feature_class":"P",
    "gn:feature_code":"PPL",
    "gn:name":"Chervonyy",
    "gn:population":0,
    "gn:timezone":"Europe/Zaporozhye",
    "iso:country":"UA",
    "name:und_x_variant":[
        "Chervonnyy",
        "Chervony",
        "Chervonyy"
    ],
    "wof:name":"Chervonyy",
    "wof:placetype":"locality"
},
  "geometry": {"coordinates":[36.05,47.98333],"type":"Point"}
}