{
  "type": "Feature",
  "properties": {
    "iso:country":"UA",
    "name:eng_x_preferred":[
        "Pushkino"
    ],
    "name:rus_x_historical":[
        "\u042d\u0441\u0435\u043d-\u042d\u043a\u0438\u0301"
    ],
    "name:rus_x_preferred":[
        "\u042d\u0441\u0435\u043d-\u042d\u043a\u0438\u0301"
    ],
    "name:rus_x_variant":[
        "\u041f\u0443\u0448\u043a\u0438\u043d\u043e"
    ],
    "name:ukr_x_preferred":[
        "\u041f\u0443\u0448\u043a\u0456\u043d\u0435"
    ],
    "qs:a0":"\u0423\u043a\u0440\u0430\u0457\u043d\u0430",
    "qs:a1":"*\u041a\u0440\u0438\u043c",
    "qs:a1_alt":"Krym",
    "qs:a1r":"0",
    "qs:a2":"\u0421\u043e\u0432\u0454\u0442\u0441\u044c\u043a\u0438\u0439",
    "qs:a2_alt":"Soviets'kyi",
    "qs:adm0":"\u0423\u043a\u0440\u0430\u0457\u043d\u0430",
    "qs:la_lc":"*",
    "qs:level":"locality",
    "qs:loc":"\u041f\u0443\u0448\u043a\u0456\u043d\u0435",
    "qs:loc_alt":"Pushkine",
    "qs:pop":0,
    "qs:type":"buffered point",
    "wof:name":"\u041f\u0443\u0448\u043a\u0456\u043d\u0435",
    "wof:placetype":"locality"
},
  "geometry": {"coordinates":[34.977182,45.200138],"type":"Point"}
}