{
  "type": "Feature",
  "properties": {
    "gn:admin1_code":"11.0",
    "gn:admin2_code":"712585",
    "gn:admin3_code":"11152826.0",
    "gn:asciiname":"Krasnogorskoye",
    "gn:country_code":"UA",
    "gn:dem":397,
    "gn:elevation":"404.0",
    "gn:feature_class":"P",
    "gn:feature_code":"PPL",
    "gn:name":"Krasnogorskoye",
    "gn:population":211,
    "gn:timezone":"Europe/Simferopol",
    "iso:country":"UA",
    "name:eng_x_preferred":[
        "Krasnogorskoye"
    ],
    "name:rus_x_historical":[
        "\u041d\u0435\u0439\u0437\u0430\u0301\u0446"
    ],
    "name:rus_x_preferred":[
        "\u041a\u0440\u0430\u0441\u043d\u043e\u0433\u043e\u0440\u0441\u043a\u043e\u0435"
    ],
    "name:rus_x_variant":[
        "\u041d\u0435\u0439\u0437\u0430\u0301\u0446"
    ],
    "name:ukr_x_preferred":[
        "\u041a\u0440\u0430\u0441\u043d\u043e\u0433\u0456\u0440\u0441\u044c\u043a\u0435"
    ],
    "wof:name":"Krasnogorskoye",
    "wof:placetype":"locality",
    "wof:population":211
},
  "geometry": {"coordinates":[34.34739,45.0044],"type":"Point"}
}