{
  "type": "Feature",
  "properties": {
    "iso:country":"UA",
    "name:eng_x_preferred":[
        "Nyzhni Torhai"
    ],
    "name:ger_x_preferred":[
        "Nyschni Torhaji"
    ],
    "name:lav_x_preferred":[
        "Ni\u017e\u0146i Torhaji"
    ],
    "name:rum_x_preferred":[
        "N\u00eejni Torhaii"
    ],
    "name:rus_x_preferred":[
        "\u041d\u0438\u0436\u043d\u0438\u0435 \u0422\u043e\u0440\u0433\u0430\u0438"
    ],
    "name:ukr_x_preferred":[
        "\u041d\u0438\u0436\u043d\u0456 \u0422\u043e\u0440\u0433\u0430\u0457"
    ],
    "name:unk_x_variant":[
        "Nizhnyaya Torgayevka"
    ],
    "qs:a0":"\u0423\u043a\u0440\u0430\u0457\u043d\u0430",
    "qs:a1":"*\u0425\u0435\u0440\u0441\u043e\u043d\u0441\u044c\u043a\u0430",
    "qs:a1_alt":"Khersons'ka",
    "qs:a1r":"0",
    "qs:a2":"\u041d\u0438\u0436\u043d\u044c\u043e\u0441\u0456\u0440\u043e\u0433\u043e\u0437\u044c\u043a\u0438\u0439",
    "qs:a2_alt":"Nyzhn'osirohoz'kyi",
    "qs:adm0":"\u0423\u043a\u0440\u0430\u0457\u043d\u0430",
    "qs:la_lc":"*",
    "qs:level":"locality",
    "qs:loc":"\u041d\u0438\u0436\u043d\u0456 \u0422\u043e\u0440\u0433\u0430\u0457",
    "qs:loc_alt":"Nyzhni Torhai",
    "qs:pop":0,
    "qs:type":"buffered point",
    "wof:name":"\u041d\u0438\u0436\u043d\u0456 \u0422\u043e\u0440\u0433\u0430\u0457",
    "wof:placetype":"locality"
},
  "geometry": {"coordinates":[34.258124,46.783094],"type":"Point"}
}