{
  "type": "Feature",
  "properties": {
    "gn:admin1_code":"4.0",
    "gn:asciiname":"Starokasyanivs'ke",
    "gn:country_code":"UA",
    "gn:dem":109,
    "gn:feature_class":"P",
    "gn:feature_code":"PPL",
    "gn:name":"Starokasyanivs\u2019ke",
    "gn:population":0,
    "gn:timezone":"Europe/Kiev",
    "iso:country":"UA",
    "name:rus_x_preferred":[
        "Starokas\u2019yanovka"
    ],
    "name:ukr_x_preferred":[
        "Starokasyanivs\u2019ke"
    ],
    "name:ukr_x_variant":[
        "\u0421\u0442\u0430\u0440\u043e\u043a\u0430\u0441\u044f\u043d\u0456\u0432\u0441\u044c\u043a\u0435"
    ],
    "wof:name":"Starokasyanivs'ke",
    "wof:placetype":"locality"
},
  "geometry": {"coordinates":[36.13101,47.96454],"type":"Point"}
}