{
  "type": "Feature",
  "properties": {
    "gn:admin1_code":"15.0",
    "gn:asciiname":"Zavady",
    "gn:country_code":"UA",
    "gn:dem":227,
    "gn:feature_class":"P",
    "gn:feature_code":"PPL",
    "gn:name":"Zavady",
    "gn:population":0,
    "gn:timezone":"Europe/Kiev",
    "iso:country":"UA",
    "name:und_x_variant":[
        "Lavady",
        "Zavady"
    ],
    "wof:name":"Zavady",
    "wof:placetype":"locality"
},
  "geometry": {"coordinates":[23.90019,50.08054],"type":"Point"}
}