{
  "type": "Feature",
  "properties": {
    "gn:admin1_code":"5.0",
    "gn:asciiname":"Taramchuk",
    "gn:country_code":"UA",
    "gn:dem":193,
    "gn:feature_class":"P",
    "gn:feature_code":"PPL",
    "gn:name":"Taramchuk",
    "gn:population":0,
    "gn:timezone":"Europe/Kiev",
    "iso:country":"UA",
    "name:hye_x_preferred":[
        "\u054f\u0561\u0580\u0561\u0574\u0579\u0578\u0582\u056f"
    ],
    "name:rus_x_preferred":[
        "\u0422\u0430\u0440\u0430\u043c\u0447\u0443\u043a"
    ],
    "name:ukr_x_preferred":[
        "Taramchuk"
    ],
    "name:ukr_x_variant":[
        "\u0422\u0430\u0440\u0430\u043c\u0447\u0443\u043a"
    ],
    "wof:name":"Taramchuk",
    "wof:placetype":"locality"
},
  "geometry": {"coordinates":[37.57695,47.80513],"type":"Point"}
}