{
  "type": "Feature",
  "properties": {
    "gn:admin1_code":"14.0",
    "gn:asciiname":"Kolyadivka",
    "gn:country_code":"UA",
    "gn:dem":70,
    "gn:feature_class":"P",
    "gn:feature_code":"PPL",
    "gn:name":"Kolyadivka",
    "gn:population":0,
    "gn:timezone":"Europe/Zaporozhye",
    "iso:country":"UA",
    "name:eng_x_preferred":[
        "Kolyadovka"
    ],
    "name:rus_x_preferred":[
        "\u041a\u043e\u043b\u044f\u0434\u043e\u0432\u043a\u0430"
    ],
    "name:ukr_x_preferred":[
        "Kolyadivka"
    ],
    "name:ukr_x_variant":[
        "\u041a\u043e\u043b\u044f\u0434\u0456\u0432\u043a\u0430"
    ],
    "wof:name":"Kolyadivka",
    "wof:placetype":"locality"
},
  "geometry": {"coordinates":[39.20103,49.08456],"type":"Point"}
}