{
  "type": "Feature",
  "properties": {
    "gn:admin1_code":"26.0",
    "gn:asciiname":"Ivano-Hannivka",
    "gn:country_code":"UA",
    "gn:dem":65,
    "gn:feature_class":"P",
    "gn:feature_code":"PPL",
    "gn:name":"Ivano-Hannivka",
    "gn:population":0,
    "gn:timezone":"Europe/Zaporozhye",
    "iso:country":"UA",
    "name:rus_x_preferred":[
        "\u0418\u0432\u0430\u043d\u043e-\u0410\u043d\u043d\u043e\u0432\u043a\u0430"
    ],
    "name:ukr_x_preferred":[
        "Ivano-Hannivka"
    ],
    "name:ukr_x_variant":[
        "\u0406\u0432\u0430\u043d\u043e-\u0413\u0430\u043d\u043d\u0456\u0432\u043a\u0430"
    ],
    "name:und_x_variant":[
        "Ivano-Gannovka",
        "Ivano-Annovka"
    ],
    "name:zho_x_preferred":[
        "\u4f0a\u74e6\u8afe-\u7518\u5c3c\u592b\u5361"
    ],
    "wof:name":"Ivano-Hannivka",
    "wof:placetype":"locality"
},
  "geometry": {"coordinates":[35.37055,47.84903],"type":"Point"}
}