{
  "type": "Feature",
  "properties": {
    "gn:admin1_code":"16.0",
    "gn:asciiname":"Kuznetsovo",
    "gn:country_code":"UA",
    "gn:dem":51,
    "gn:feature_class":"P",
    "gn:feature_code":"PPL",
    "gn:name":"Kuznetsovo",
    "gn:population":0,
    "gn:timezone":"Europe/Kiev",
    "iso:country":"UA",
    "name:und_x_variant":[
        "Bakshala",
        "Kuznetsova",
        "Kuznetsovo"
    ],
    "wof:name":"Kuznetsovo",
    "wof:placetype":"locality"
},
  "geometry": {"coordinates":[30.96577000000001,47.75265],"type":"Point"}
}