{
  "type": "Feature",
  "properties": {
    "gn:admin1_code":"5.0",
    "gn:admin2_code":"709904",
    "gn:asciiname":"Vesna",
    "gn:country_code":"UA",
    "gn:dem":147,
    "gn:feature_class":"P",
    "gn:feature_code":"PPL",
    "gn:name":"Vesna",
    "gn:population":0,
    "gn:timezone":"Europe/Kiev",
    "iso:country":"UA",
    "name:ces_x_preferred":[
        "Vesna"
    ],
    "name:epo_x_preferred":[
        "Printempo"
    ],
    "name:fra_x_historical":[
        "Ourytske",
        "Ouritskoye",
        "Ouritskoy\u00e8",
        "Ourytsk\u00e8"
    ],
    "name:fra_x_preferred":[
        "Ourytske"
    ],
    "name:fra_x_variant":[
        "Ouritskoye",
        "Ouritskoy\u00e8",
        "Ourytsk\u00e8",
        "Vesna"
    ],
    "name:hrv_x_preferred":[
        "Vesna"
    ],
    "name:hye_x_historical":[
        "\u0548\u0582\u0580\u056b\u0581\u056f\u0578\u0565"
    ],
    "name:hye_x_preferred":[
        "\u0548\u0582\u0580\u056b\u0581\u056f\u0578\u0565"
    ],
    "name:hye_x_variant":[
        "\u054e\u0565\u057d\u0576\u0561",
        "\u054e\u0567\u057d\u0576\u0561"
    ],
    "name:ita_x_preferred":[
        "Vesna"
    ],
    "name:mkd_x_preferred":[
        "\u0412\u0435\u0441\u043d\u0430"
    ],
    "name:rus_x_historical":[
        "Uritskoye"
    ],
    "name:rus_x_preferred":[
        "Uritskoye"
    ],
    "name:rus_x_variant":[
        "\u0412\u0435\u0441\u043d\u0430"
    ],
    "name:slk_x_preferred":[
        "Vesna"
    ],
    "name:srp_x_preferred":[
        "\u0412\u0435\u0441\u043d\u0430"
    ],
    "name:ukr_x_historical":[
        "\u0445\u0443\u0442\u0456\u0440 \u041d\u043e\u0432\u043e\u043e\u043b\u0435\u043a\u0441\u0430\u043d\u0434\u0440\u0456\u0432\u043a\u0430"
    ],
    "name:ukr_x_preferred":[
        "\u0412\u0435\u0441\u043d\u0430"
    ],
    "name:ukr_x_variant":[
        "\u0445\u0443\u0442\u0456\u0440 \u041d\u043e\u0432\u043e\u043e\u043b\u0435\u043a\u0441\u0430\u043d\u0434\u0440\u0456\u0432\u043a\u0430"
    ],
    "name:und_x_variant":[
        "Wesna",
        "Wessna",
        "Urytske",
        "Uritzkoje"
    ],
    "wof:name":"Vesna",
    "wof:placetype":"locality"
},
  "geometry": {"coordinates":[37.07491,48.58671],"type":"Point"}
}