{
  "type": "Feature",
  "properties": {
    "gn:admin1_code":"18.0",
    "gn:asciiname":"Pologi",
    "gn:country_code":"UA",
    "gn:dem":65,
    "gn:feature_class":"P",
    "gn:feature_code":"PPL",
    "gn:name":"Pologi",
    "gn:population":0,
    "gn:timezone":"Europe/Kiev",
    "iso:country":"UA",
    "wof:name":"Pologi",
    "wof:placetype":"locality"
},
  "geometry": {"coordinates":[34.11667,48.93333],"type":"Point"}
}