{
  "type": "Feature",
  "properties": {
    "iso:country":"UA",
    "name:arm_x_preferred":[
        "\u054c\u0578\u057d\u0578\u0577\u056f\u0561"
    ],
    "name:chi_x_preferred":[
        "\u7f85\u897f\u4ec0\u5361"
    ],
    "name:dut_x_preferred":[
        "Rosischka"
    ],
    "name:eng_x_preferred":[
        "Rosishka"
    ],
    "name:epo_x_preferred":[
        "Rosi\u015dka"
    ],
    "name:ger_x_preferred":[
        "Rosischka"
    ],
    "name:hun_x_preferred":[
        "R\u00e1sz\u00f3cska"
    ],
    "name:rum_x_preferred":[
        "T\u0103ietura"
    ],
    "name:rus_x_preferred":[
        "\u0420\u043e\u0441\u043e\u0448\u043a\u0430"
    ],
    "name:ukr_x_preferred":[
        "Rosishka"
    ],
    "name:ukr_x_variant":[
        "\u0420\u043e\u0441\u0456\u0448\u043a\u0430"
    ],
    "name:unk_x_variant":[
        "Rososhka"
    ],
    "qs:a0":"\u0423\u043a\u0440\u0430\u0457\u043d\u0430",
    "qs:a1":"*\u0417\u0430\u043a\u0430\u0440\u043f\u0430\u0442\u0441\u044c\u043a\u0430",
    "qs:a1_alt":"Zakarpats'ka",
    "qs:a1r":"0",
    "qs:a2":"\u0420\u0430\u0445\u0456\u0432\u0441\u044c\u043a\u0438\u0439",
    "qs:a2_alt":"Rakhivs'kyi",
    "qs:adm0":"\u0423\u043a\u0440\u0430\u0457\u043d\u0430",
    "qs:la_lc":"*",
    "qs:level":"locality",
    "qs:loc":"\u0420\u043e\u0441\u0456\u0448\u043a\u0430",
    "qs:loc_alt":"Rosishka",
    "qs:pop":0,
    "qs:type":"buffered point",
    "wof:name":"\u0420\u043e\u0441\u0456\u0448\u043a\u0430",
    "wof:placetype":"locality"
},
  "geometry": {"coordinates":[24.076088,47.977568],"type":"Point"}
}