{
  "type": "Feature",
  "properties": {
    "gn:admin1_code":"9.0",
    "gn:asciiname":"Berezhanka",
    "gn:country_code":"UA",
    "gn:dem":295,
    "gn:feature_class":"P",
    "gn:feature_code":"PPL",
    "gn:name":"Berezhanka",
    "gn:population":0,
    "gn:timezone":"Europe/Kiev",
    "iso:country":"UA",
    "name:und_x_variant":[
        "Voytovtsy",
        "Berezhanka"
    ],
    "wof:name":"Berezhanka",
    "wof:placetype":"locality"
},
  "geometry": {"coordinates":[26.77286,49.46706],"type":"Point"}
}