{
  "type": "Feature",
  "properties": {
    "iso:country":"UA",
    "name:crh_x_preferred":[
        "Uda\u00e7ne"
    ],
    "name:deu_x_preferred":[
        "Udatschne"
    ],
    "name:eng_x_preferred":[
        "Udachnoye"
    ],
    "name:eng_x_variant":[
        "Udachne"
    ],
    "name:lav_x_preferred":[
        "Uda\u010dne"
    ],
    "name:rus_x_preferred":[
        "\u0423\u0434\u0430\u0447\u043d\u043e\u0435"
    ],
    "name:ukr_x_preferred":[
        "Udachne"
    ],
    "name:ukr_x_variant":[
        "\u0423\u0434\u0430\u0447\u043d\u0435"
    ],
    "name:unk_x_variant":[
        "Udachnaya"
    ],
    "name:zho_x_preferred":[
        "\u70cf\u9054\u5947\u6d85"
    ],
    "qs:a0":"\u0423\u043a\u0440\u0430\u0457\u043d\u0430",
    "qs:a1":"*\u0414\u043e\u043d\u0435\u0446\u044c\u043a\u0430",
    "qs:a1_alt":"Donets'ka",
    "qs:a1r":"0",
    "qs:a2":"\u041a\u0440\u0430\u0441\u043d\u043e\u0430\u0440\u043c\u0456\u0439\u0441\u044c\u043a\u0438\u0439",
    "qs:a2_alt":"Krasnoarmiis'kyi",
    "qs:adm0":"\u0423\u043a\u0440\u0430\u0457\u043d\u0430",
    "qs:la_lc":"*",
    "qs:level":"locality",
    "qs:loc":"\u0423\u0434\u0430\u0447\u043d\u0435",
    "qs:loc_alt":"Udachne",
    "qs:pop":0,
    "qs:type":"buffered point",
    "wof:name":"\u0423\u0434\u0430\u0447\u043d\u0435",
    "wof:placetype":"locality"
},
  "geometry": {"coordinates":[36.996909,48.235716],"type":"Point"}
}