{
  "type": "Feature",
  "properties": {
    "gn:admin1_code":"8.0",
    "gn:asciiname":"Zeleny Pod",
    "gn:country_code":"UA",
    "gn:dem":35,
    "gn:feature_class":"P",
    "gn:feature_code":"PPL",
    "gn:name":"Zeleny Pod",
    "gn:population":0,
    "gn:timezone":"Europe/Kiev",
    "iso:country":"UA",
    "name:und_x_variant":[
        "Zel\u00ebnyy Pod"
    ],
    "wof:name":"Zeleny Pod",
    "wof:placetype":"locality"
},
  "geometry": {"coordinates":[33.7091,46.6873],"type":"Point"}
}