{
  "type": "Feature",
  "properties": {
    "gn:admin1_code":"14.0",
    "gn:asciiname":"Kreydyane",
    "gn:country_code":"UA",
    "gn:dem":119,
    "gn:feature_class":"P",
    "gn:feature_code":"PPL",
    "gn:name":"Kreydyane",
    "gn:population":0,
    "gn:timezone":"Europe/Zaporozhye",
    "iso:country":"UA",
    "name:ukr_x_preferred":[
        "Kreydyane"
    ],
    "name:ukr_x_variant":[
        "\u041a\u0440\u0435\u0439\u0434\u044f\u043d\u0435"
    ],
    "name:und_x_variant":[
        "Kreydyanoye"
    ],
    "wof:name":"Kreydyane",
    "wof:placetype":"locality"
},
  "geometry": {"coordinates":[39.66246,49.29957],"type":"Point"}
}