{
  "type": "Feature",
  "properties": {
    "gn:admin1_code":"7.0",
    "gn:asciiname":"Vil'khuvatka",
    "gn:country_code":"UA",
    "gn:dem":104,
    "gn:feature_class":"P",
    "gn:feature_code":"PPL",
    "gn:name":"Vil\u2019khuvatka",
    "gn:population":0,
    "gn:timezone":"Europe/Kiev",
    "iso:country":"UA",
    "name:ukr_x_preferred":[
        "Vil\u2019khuvatka"
    ],
    "name:ukr_x_variant":[
        "\u0412\u0456\u043b\u044c\u0445\u0443\u0432\u0430\u0442\u043a\u0430"
    ],
    "name:und_x_variant":[
        "Karlovka"
    ],
    "wof:name":"Vil'khuvatka",
    "wof:placetype":"locality"
},
  "geometry": {"coordinates":[35.93333,49.76667],"type":"Point"}
}