{
  "type": "Feature",
  "properties": {
    "gn:admin1_code":"21.0",
    "gn:asciiname":"Pisky",
    "gn:country_code":"UA",
    "gn:dem":117,
    "gn:feature_class":"P",
    "gn:feature_code":"PPL",
    "gn:name":"Pisky",
    "gn:population":0,
    "gn:timezone":"Europe/Kiev",
    "iso:country":"UA",
    "name:ukr_x_preferred":[
        "Pisky"
    ],
    "name:ukr_x_variant":[
        "\u041f\u0456\u0441\u043a\u0438"
    ],
    "name:und_x_variant":[
        "Peski"
    ],
    "wof:name":"Pisky",
    "wof:placetype":"locality"
},
  "geometry": {"coordinates":[33.4698,50.68956],"type":"Point"}
}