{
  "type": "Feature",
  "properties": {
    "gn:admin1_code":"27.0",
    "gn:asciiname":"Novi Ozeryany",
    "gn:country_code":"UA",
    "gn:dem":184,
    "gn:feature_class":"P",
    "gn:feature_code":"PPL",
    "gn:name":"Novi Ozeryany",
    "gn:population":0,
    "gn:timezone":"Europe/Kiev",
    "iso:country":"UA",
    "name:ukr_x_preferred":[
        "Novi Ozeryany"
    ],
    "name:ukr_x_variant":[
        "\u041d\u043e\u0432\u0456 \u041e\u0437\u0435\u0440\u044f\u043d\u0438"
    ],
    "name:und_x_variant":[
        "Ozeryany",
        "Novyye Ozeryany"
    ],
    "wof:name":"Novi Ozeryany",
    "wof:placetype":"locality"
},
  "geometry": {"coordinates":[29.41667,50.31667],"type":"Point"}
}