{
  "type": "Feature",
  "properties": {
    "gn:admin1_code":"21.0",
    "gn:asciiname":"Hodunivka",
    "gn:country_code":"UA",
    "gn:dem":168,
    "gn:feature_class":"P",
    "gn:feature_code":"PPL",
    "gn:name":"Hodunivka",
    "gn:population":0,
    "gn:timezone":"Europe/Kiev",
    "iso:country":"UA",
    "name:ukr_x_preferred":[
        "Hodunivka"
    ],
    "name:ukr_x_variant":[
        "\u0413\u043e\u0434\u0443\u043d\u0456\u0432\u043a\u0430"
    ],
    "name:und_x_variant":[
        "Godunovka"
    ],
    "wof:name":"Hodunivka",
    "wof:placetype":"locality"
},
  "geometry": {"coordinates":[33.95034,51.74092],"type":"Point"}
}