{
  "type": "Feature",
  "properties": {
    "gn:admin1_code":"13.0",
    "gn:asciiname":"Mikhaylovka",
    "gn:country_code":"UA",
    "gn:dem":242,
    "gn:feature_class":"P",
    "gn:feature_code":"PPL",
    "gn:name":"Mikhaylovka",
    "gn:population":0,
    "gn:timezone":"Europe/Kiev",
    "iso:country":"UA",
    "wof:name":"Mikhaylovka",
    "wof:placetype":"locality"
},
  "geometry": {"coordinates":[29.55275,49.36984],"type":"Point"}
}