{
  "type": "Feature",
  "properties": {
    "gn:admin1_code":"23.0",
    "gn:asciiname":"Lavrivka",
    "gn:country_code":"UA",
    "gn:dem":246,
    "gn:feature_class":"P",
    "gn:feature_code":"PPL",
    "gn:name":"Lavrivka",
    "gn:population":0,
    "gn:timezone":"Europe/Kiev",
    "iso:country":"UA",
    "wof:name":"Lavrivka",
    "wof:placetype":"locality"
},
  "geometry": {"coordinates":[28.47122,49.3427],"type":"Point"}
}