{
  "type": "Feature",
  "properties": {
    "gn:admin1_code":"21.0",
    "gn:asciiname":"Demchenkove",
    "gn:country_code":"UA",
    "gn:dem":180,
    "gn:feature_class":"P",
    "gn:feature_code":"PPL",
    "gn:name":"Demchenkove",
    "gn:population":0,
    "gn:timezone":"Europe/Kiev",
    "iso:country":"UA",
    "name:ukr_x_preferred":[
        "Demchenkove"
    ],
    "name:ukr_x_variant":[
        "\u0414\u0435\u043c\u0447\u0435\u043d\u043a\u043e\u0432\u0435",
        "Strizhevskiy"
    ],
    "wof:name":"Demchenkove",
    "wof:placetype":"locality"
},
  "geometry": {"coordinates":[33.95475,52.14474000000001],"type":"Point"}
}