{
  "type": "Feature",
  "properties": {
    "gn:admin1_code":"5.0",
    "gn:asciiname":"Novo-Pavlovka",
    "gn:country_code":"UA",
    "gn:dem":182,
    "gn:feature_class":"P",
    "gn:feature_code":"PPL",
    "gn:name":"Novo-Pavlovka",
    "gn:population":0,
    "gn:timezone":"Europe/Kiev",
    "iso:country":"UA",
    "wof:name":"Novo-Pavlovka",
    "wof:placetype":"locality"
},
  "geometry": {"coordinates":[37.03852,48.58047],"type":"Point"}
}