{
  "type": "Feature",
  "properties": {
    "gn:admin1_code":"26.0",
    "gn:asciiname":"Serhiyivka",
    "gn:country_code":"UA",
    "gn:dem":105,
    "gn:feature_class":"P",
    "gn:feature_code":"PPL",
    "gn:name":"Serhiyivka",
    "gn:population":0,
    "gn:timezone":"Europe/Zaporozhye",
    "iso:country":"UA",
    "name:ukr_x_preferred":[
        "Serhiyivka"
    ],
    "name:ukr_x_variant":[
        "\u0421\u0435\u0440\u0433\u0456\u0457\u0432\u043a\u0430"
    ],
    "name:und_x_variant":[
        "Sergoyevka"
    ],
    "wof:name":"Serhiyivka",
    "wof:placetype":"locality"
},
  "geometry": {"coordinates":[35.2208,47.9819],"type":"Point"}
}