{
  "type": "Feature",
  "properties": {
    "iso:country":"UA",
    "name:deu_x_preferred":[
        "Kurin"
    ],
    "name:eng_x_preferred":[
        "Kuren'"
    ],
    "name:eng_x_variant":[
        "Kurin"
    ],
    "name:nld_x_preferred":[
        "Kurin"
    ],
    "name:pol_x_preferred":[
        "Kure\u0144"
    ],
    "name:rus_x_preferred":[
        "\u041a\u0443\u0440\u0435\u043d\u044c"
    ],
    "name:ukr_x_preferred":[
        "\u041a\u0443\u0440\u0456\u043d\u044c"
    ],
    "name:ukr_x_variant":[
        "Kurin\u2019"
    ],
    "name:und_x_variant":[
        "Kuren\u2019"
    ],
    "qs:a0":"\u0423\u043a\u0440\u0430\u0457\u043d\u0430",
    "qs:a1":"*\u0427\u0435\u0440\u043d\u0456\u0433\u0456\u0432\u0441\u044c\u043a\u0430",
    "qs:a1_alt":"Chernihivs'ka",
    "qs:a1r":"0",
    "qs:a2":"\u0411\u0430\u0445\u043c\u0430\u0446\u044c\u043a\u0438\u0439",
    "qs:a2_alt":"Bakhmats'kyi",
    "qs:adm0":"\u0423\u043a\u0440\u0430\u0457\u043d\u0430",
    "qs:la_lc":"*",
    "qs:level":"locality",
    "qs:loc":"\u041a\u0443\u0440\u0456\u043d\u044c",
    "qs:loc_alt":"Kurin",
    "qs:pop":0,
    "qs:type":"buffered point",
    "wd:wordcount":185,
    "wof:name":"\u041a\u0443\u0440\u0456\u043d\u044c",
    "wof:placetype":"locality"
},
  "geometry": {"coordinates":[32.821875,51.092768],"type":"Point"}
}