{
  "type": "Feature",
  "properties": {
    "gn:admin1_code":"7.0",
    "gn:asciiname":"Zavody Vtoryye",
    "gn:country_code":"UA",
    "gn:dem":108,
    "gn:feature_class":"P",
    "gn:feature_code":"PPL",
    "gn:name":"Zavody Vtoryye",
    "gn:population":0,
    "gn:timezone":"Europe/Kiev",
    "iso:country":"UA",
    "wof:name":"Zavody Vtoryye",
    "wof:placetype":"locality"
},
  "geometry": {"coordinates":[36.96389,50.28667],"type":"Point"}
}