{
  "type": "Feature",
  "properties": {
    "gn:country":"UA",
    "gn:fcode":"PPL",
    "gn:population":1529,
    "iso:country":"UA",
    "name:bul_x_preferred":[
        "\u0416\u0432\u0430\u043d\u0435\u0446"
    ],
    "name:ceb_x_preferred":[
        "Zhvanets"
    ],
    "name:che_x_preferred":[
        "\u0416\u0432\u0430\u043d\u0435\u0446"
    ],
    "name:deu_x_preferred":[
        "Schwanez"
    ],
    "name:ell_x_preferred":[
        "\u0396\u03b2\u03ac\u03bd\u03b5\u03c4\u03c2"
    ],
    "name:eng_x_preferred":[
        "Zhvanets"
    ],
    "name:est_x_preferred":[
        "\u017dvanets"
    ],
    "name:fin_x_preferred":[
        "\u017dv\u0430n\u0435ts"
    ],
    "name:hye_x_preferred":[
        "\u053a\u057e\u0561\u0576\u0565\u0581"
    ],
    "name:nan_x_preferred":[
        "Zhvanets"
    ],
    "name:nno_x_preferred":[
        "Zjvanets"
    ],
    "name:nob_x_preferred":[
        "Zjvanets"
    ],
    "name:pol_x_preferred":[
        "\u017bwaniec"
    ],
    "name:ron_x_preferred":[
        "Jvane\u021b"
    ],
    "name:rus_x_preferred":[
        "\u0416\u0432\u0430\u043d\u0435\u0446"
    ],
    "name:ukr_x_preferred":[
        "\u0416\u0432\u0430\u043d\u0435\u0446\u044c"
    ],
    "name:und_x_variant":[
        "Zhvaned"
    ],
    "name:zho_x_preferred":[
        "\u65e5\u74e6\u6d85\u9f4a"
    ],
    "qs_pg:aaroncc":"UA",
    "qs_pg:gn_country":"UA",
    "qs_pg:gn_fcode":"PPL",
    "qs_pg:gn_pop":1529,
    "qs_pg:name":"Zhvanets",
    "qs_pg:photos_9r":0,
    "qs_pg:photos_sr":0,
    "qs_pg:pop_sr":3,
    "qs_pg:qs_pg_placetype":"locality",
    "wof:name":"Zhvanets",
    "wof:placetype":"locality",
    "wof:population":1529
},
  "geometry": {"coordinates":[26.48744,48.54968],"type":"Point"}
}