{
  "type": "Feature",
  "properties": {
    "gn:gn_country":"UA",
    "gn:gn_fcode":"PPL",
    "gn:gn_pop":1529,
    "gn:population":1529,
    "iso:country":"UA",
    "name:arm_x_preferred":[
        "\u053a\u057e\u0561\u0576\u0565\u0581"
    ],
    "name:chi_x_preferred":[
        "\u65e5\u74e6\u6d85\u9f4a"
    ],
    "name:eng_x_preferred":[
        "Zhvanets"
    ],
    "name:est_x_preferred":[
        "\u017dvanets"
    ],
    "name:ger_x_preferred":[
        "Schwanez"
    ],
    "name:pol_x_preferred":[
        "\u017bwaniec"
    ],
    "name:rum_x_preferred":[
        "Jvane\u021b"
    ],
    "name:rus_x_preferred":[
        "\u0416\u0432\u0430\u043d\u0435\u0446"
    ],
    "name:ukr_x_preferred":[
        "\u0416\u0432\u0430\u043d\u0435\u0446\u044c"
    ],
    "name:unk_x_variant":[
        "Zhvaned"
    ],
    "qs_pg:aaroncc":"UA",
    "qs_pg:gn_country":"UA",
    "qs_pg:gn_fcode":"PPL",
    "qs_pg:gn_pop":1529,
    "qs_pg:name":"Zhvanets",
    "qs_pg:photos_9r":0,
    "qs_pg:photos_sr":0,
    "qs_pg:pop_sr":3,
    "qs_pg:qs_pg_placetype":"locality",
    "wof:name":"Zhvanets",
    "wof:placetype":"locality",
    "wof:population":1529
},
  "geometry": {"coordinates":[26.48744,48.54968],"type":"Point"}
}