{
  "type": "Feature",
  "properties": {
    "gn:admin1_code":"21.0",
    "gn:asciiname":"Huta",
    "gn:country_code":"UA",
    "gn:dem":170,
    "gn:feature_class":"P",
    "gn:feature_code":"PPL",
    "gn:name":"Huta",
    "gn:population":0,
    "gn:timezone":"Europe/Kiev",
    "iso:country":"UA",
    "name:ukr_x_preferred":[
        "Huta"
    ],
    "name:ukr_x_variant":[
        "\u0413\u0443\u0442\u0430"
    ],
    "name:und_x_variant":[
        "Guta",
        "Gutka"
    ],
    "wof:name":"Huta",
    "wof:placetype":"locality"
},
  "geometry": {"coordinates":[33.6286,51.74301],"type":"Point"}
}