{
  "type": "Feature",
  "properties": {
    "iso:country":"UA",
    "name:ukr_x_preferred":[
        "Bochanytsya"
    ],
    "name:ukr_x_variant":[
        "\u0411\u043e\u0447\u0430\u043d\u0438\u0446\u044f"
    ],
    "name:unk_x_variant":[
        "Bochanitsa"
    ],
    "qs:a0":"\u0423\u043a\u0440\u0430\u0457\u043d\u0430",
    "qs:a1":"*\u0420\u0456\u0432\u043d\u0435\u043d\u0441\u044c\u043a\u0430",
    "qs:a1_alt":"Rivnens'ka",
    "qs:a1r":"0",
    "qs:a2":"\u0413\u043e\u0449\u0430\u043d\u0441\u044c\u043a\u0438\u0439",
    "qs:a2_alt":"Hoschans'kyi",
    "qs:adm0":"\u0423\u043a\u0440\u0430\u0457\u043d\u0430",
    "qs:la_lc":"*",
    "qs:level":"locality",
    "qs:loc":"\u0411\u043e\u0447\u0430\u043d\u0438\u0446\u044f",
    "qs:loc_alt":"Bochanytsia",
    "qs:pop":0,
    "qs:type":"buffered point",
    "wof:name":"\u0411\u043e\u0447\u0430\u043d\u0438\u0446\u044f",
    "wof:placetype":"locality"
},
  "geometry": {"coordinates":[26.695163,50.527],"type":"Point"}
}