{
  "type": "Feature",
  "properties": {
    "gn:admin1_code":"21.0",
    "gn:asciiname":"Khyl'chychi",
    "gn:country_code":"UA",
    "gn:dem":137,
    "gn:feature_class":"P",
    "gn:feature_code":"PPL",
    "gn:name":"Khyl\u2019chychi",
    "gn:population":0,
    "gn:timezone":"Europe/Kiev",
    "iso:country":"UA",
    "name:ukr_x_preferred":[
        "\u0425\u0438\u043b\u044c\u0447\u0438\u0447\u0456"
    ],
    "name:ukr_x_variant":[
        "Khil\u2019chitsy",
        "Khil\u2019chichi"
    ],
    "name:und_x_variant":[
        "Khyl\u2019chychi"
    ],
    "wof:name":"Khyl'chychi",
    "wof:placetype":"locality"
},
  "geometry": {"coordinates":[33.47462,52.15589],"type":"Point"}
}