{
  "type": "Feature",
  "properties": {
    "gn:admin1_code":"24.0",
    "gn:asciiname":"Nova Vyzhva",
    "gn:country_code":"UA",
    "gn:dem":166,
    "gn:feature_class":"P",
    "gn:feature_code":"PPL",
    "gn:name":"Nova Vyzhva",
    "gn:population":0,
    "gn:timezone":"Europe/Kiev",
    "iso:country":"UA",
    "name:ukr_x_preferred":[
        "Nova Vyzhva"
    ],
    "name:ukr_x_variant":[
        "\u041d\u043e\u0432\u0430 \u0412\u0438\u0436\u0432\u0430"
    ],
    "name:und_x_variant":[
        "Novaya Vyzhva"
    ],
    "wof:name":"Nova Vyzhva",
    "wof:placetype":"locality"
},
  "geometry": {"coordinates":[24.42394,51.39621],"type":"Point"}
}