{
  "type": "Feature",
  "properties": {
    "gn:admin1_code":"24.0",
    "gn:asciiname":"Lishnya",
    "gn:cc2":"UA",
    "gn:country_code":"UA",
    "gn:dem":203,
    "gn:feature_class":"P",
    "gn:feature_code":"PPL",
    "gn:name":"Lishnya",
    "gn:population":0,
    "gn:timezone":"Europe/Kiev",
    "iso:country":"UA",
    "name:und_x_variant":[
        "Lisznia",
        "Lishnya"
    ],
    "wof:name":"Lishnya",
    "wof:placetype":"locality"
},
  "geometry": {"coordinates":[24.18333,50.68333],"type":"Point"}
}