{
  "type": "Feature",
  "properties": {
    "gn:admin1_code":"18.0",
    "gn:asciiname":"Salymivshchyna",
    "gn:country_code":"UA",
    "gn:dem":140,
    "gn:feature_class":"P",
    "gn:feature_code":"PPL",
    "gn:name":"Salymivshchyna",
    "gn:population":0,
    "gn:timezone":"Europe/Kiev",
    "iso:country":"UA",
    "name:ukr_x_preferred":[
        "Salymivshchyna"
    ],
    "name:ukr_x_variant":[
        "\u0421\u0430\u043b\u0438\u043c\u0456\u0432\u0449\u0438\u043d\u0430"
    ],
    "wof:name":"Salymivshchyna",
    "wof:placetype":"locality"
},
  "geometry": {"coordinates":[34.03078,49.72386],"type":"Point"}
}