{
  "type": "Feature",
  "properties": {
    "gn:admin1_code":"11.0",
    "gn:admin2_code":"693803",
    "gn:admin3_code":"11152619.0",
    "gn:asciiname":"Kurgannoye",
    "gn:country_code":"UA",
    "gn:dem":159,
    "gn:elevation":"156.0",
    "gn:feature_class":"P",
    "gn:feature_code":"PPL",
    "gn:name":"Kurgannoye",
    "gn:population":651,
    "gn:timezone":"Europe/Simferopol",
    "iso:country":"UA",
    "name:eng_x_preferred":[
        "Kurgannoye"
    ],
    "name:rus_x_historical":[
        "\u0423\u043b\u0443\u0301-\u0427\u043e\u043a\u0440\u0430\u0301\u043a"
    ],
    "name:rus_x_preferred":[
        "\u041a\u0443\u0440\u0433\u0430\u043d\u043d\u043e\u0435"
    ],
    "name:rus_x_variant":[
        "\u0423\u043b\u0443\u0301-\u0427\u043e\u043a\u0440\u0430\u0301\u043a"
    ],
    "name:ukr_x_preferred":[
        "\u041a\u0443\u0440\u0433\u0430\u043d\u043d\u0435"
    ],
    "wof:name":"Kurgannoye",
    "wof:placetype":"locality",
    "wof:population":651
},
  "geometry": {"coordinates":[33.93912,45.06893],"type":"Point"}
}