{
  "type": "Feature",
  "properties": {
    "iso:country":"UA",
    "name:ces_x_preferred":[
        "Jelena R\u017eevskaja"
    ],
    "name:eng_x_preferred":[
        "Nekrasovo"
    ],
    "name:eng_x_variant":[
        "Elena Rzhevskaya"
    ],
    "name:fra_x_preferred":[
        "Elena Rzhevskaya"
    ],
    "name:pol_x_preferred":[
        "Helena R\u017cewska"
    ],
    "name:rus_x_historical":[
        "\u0411\u043e\u043b\u044c\u0448\u0435\u0432\u0438\u043a"
    ],
    "name:rus_x_preferred":[
        "\u0420\u0436\u0435\u0432\u0441\u043a\u0430\u044f"
    ],
    "name:rus_x_variant":[
        "\u041d\u0435\u043a\u0440\u0430\u0441\u043e\u0432\u043e",
        "\u0411\u043e\u043b\u044c\u0448\u0435\u0432\u0438\u043a"
    ],
    "name:spa_x_preferred":[
        "Elena Rzhevskaya"
    ],
    "name:tur_x_preferred":[
        "Elena Rzhevskaya"
    ],
    "name:ukr_x_preferred":[
        "\u041d\u0435\u043a\u0440\u0430\u0441\u043e\u0432\u0435"
    ],
    "qs:a0":"\u0423\u043a\u0440\u0430\u0457\u043d\u0430",
    "qs:a1":"*\u041a\u0440\u0438\u043c",
    "qs:a1_alt":"Krym",
    "qs:a1r":"0",
    "qs:a2":"\u041a\u0440\u0430\u0441\u043d\u043e\u0433\u0432\u0430\u0440\u0434\u0456\u0439\u0441\u044c\u043a\u0438\u0439",
    "qs:a2_alt":"Krasnohvardiis'kyi",
    "qs:adm0":"\u0423\u043a\u0440\u0430\u0457\u043d\u0430",
    "qs:la_lc":"*",
    "qs:level":"locality",
    "qs:loc":"\u041d\u0435\u043a\u0440\u0430\u0441\u043e\u0432\u0435",
    "qs:loc_alt":"Nekrasove",
    "qs:pop":0,
    "qs:type":"buffered point",
    "wd:wordcount":1652,
    "wof:name":"\u041d\u0435\u043a\u0440\u0430\u0441\u043e\u0432\u0435",
    "wof:placetype":"locality"
},
  "geometry": {"coordinates":[34.284203,45.417453],"type":"Point"}
}