{
  "type": "Feature",
  "properties": {
    "gn:admin1_code":"7.0",
    "gn:asciiname":"Oleksiyivka",
    "gn:country_code":"UA",
    "gn:dem":103,
    "gn:feature_class":"P",
    "gn:feature_code":"PPL",
    "gn:name":"Oleksiyivka",
    "gn:population":0,
    "gn:timezone":"Europe/Kiev",
    "iso:country":"UA",
    "name:rus_x_preferred":[
        "\u0410\u043b\u043a\u0441\u0435\u0435\u0432\u043a\u0430"
    ],
    "name:ukr_x_preferred":[
        "Oleksiyivka"
    ],
    "name:ukr_x_variant":[
        "\u041e\u043b\u0435\u043a\u0441\u0456\u0457\u0432\u043a\u0430"
    ],
    "name:und_x_variant":[
        "Alekseyevka"
    ],
    "wof:name":"Oleksiyivka",
    "wof:placetype":"locality"
},
  "geometry": {"coordinates":[36.03861,49.09263],"type":"Point"}
}