{
  "type": "Feature",
  "properties": {
    "gn:admin1_code":"18.0",
    "gn:asciiname":"Pysarivka",
    "gn:country_code":"UA",
    "gn:dem":150,
    "gn:feature_class":"P",
    "gn:feature_code":"PPL",
    "gn:name":"Pysarivka",
    "gn:population":0,
    "gn:timezone":"Europe/Kiev",
    "iso:country":"UA",
    "name:ukr_x_preferred":[
        "Pysarivka"
    ],
    "name:ukr_x_variant":[
        "\u041f\u0438\u0441\u0430\u0440\u0456\u0432\u043a\u0430"
    ],
    "wof:name":"Pysarivka",
    "wof:placetype":"locality"
},
  "geometry": {"coordinates":[33.53692,50.15863],"type":"Point"}
}