{
  "type": "Feature",
  "properties": {
    "gn:admin1_code":"15.0",
    "gn:asciiname":"Zasadky",
    "gn:country_code":"UA",
    "gn:dem":336,
    "gn:feature_class":"P",
    "gn:feature_code":"PPL",
    "gn:name":"Zasadky",
    "gn:population":0,
    "gn:timezone":"Europe/Kiev",
    "iso:country":"UA",
    "name:ukr_x_preferred":[
        "Zasadky"
    ],
    "name:ukr_x_variant":[
        "\u0417\u0430\u0441\u0430\u0434\u043a\u0438"
    ],
    "name:und_x_variant":[
        "Zasadki"
    ],
    "wof:name":"Zasadky",
    "wof:placetype":"locality"
},
  "geometry": {"coordinates":[22.97437,49.51579],"type":"Point"}
}