{
  "type": "Feature",
  "properties": {
    "iso:country":"UA",
    "name:che_x_preferred":[
        "\u0422\u0435\u043a\u0443\u0447\u0430"
    ],
    "name:eng_x_preferred":[
        "Tekuche"
    ],
    "name:eng_x_variant":[
        "Tekucha"
    ],
    "name:fin_x_preferred":[
        "T\u0435kut\u0161\u0430"
    ],
    "name:hun_x_preferred":[
        "Tekucse"
    ],
    "name:lav_x_preferred":[
        "Teku\u010de"
    ],
    "name:nno_x_preferred":[
        "Tekutsja"
    ],
    "name:nob_x_preferred":[
        "Tekutsja"
    ],
    "name:pol_x_preferred":[
        "Tekucza"
    ],
    "name:ron_x_preferred":[
        "Tekuce"
    ],
    "name:rus_x_preferred":[
        "\u0422\u0435\u043a\u0443\u0447\u0435\u0435"
    ],
    "name:ukr_x_preferred":[
        "Tekuche"
    ],
    "name:ukr_x_variant":[
        "\u0422\u0435\u043a\u0443\u0447\u0435",
        "\u0422\u0435\u043a\u0443\u0447\u0430"
    ],
    "name:und_x_variant":[
        "Tekuchaya"
    ],
    "name:zho_x_preferred":[
        "\u6377\u5eab\u5207"
    ],
    "qs:a0":"\u0423\u043a\u0440\u0430\u0457\u043d\u0430",
    "qs:a1":"*\u0406\u0432\u0430\u043d\u043e-\u0424\u0440\u0430\u043d\u043a\u0456\u0432\u0441\u044c\u043a\u0430",
    "qs:a1_alt":"Ivano-Frankivs'ka",
    "qs:a1r":"0",
    "qs:a2":"\u041a\u043e\u0441\u0456\u0432\u0441\u044c\u043a\u0438\u0439",
    "qs:a2_alt":"Kosivs'kyi",
    "qs:adm0":"\u0423\u043a\u0440\u0430\u0457\u043d\u0430",
    "qs:la_lc":"*",
    "qs:level":"locality",
    "qs:loc":"\u0422\u0435\u043a\u0443\u0447\u0435",
    "qs:loc_alt":"Tekuche",
    "qs:pop":0,
    "qs:type":"buffered point",
    "wof:name":"\u0422\u0435\u043a\u0443\u0447\u0435",
    "wof:placetype":"locality"
},
  "geometry": {"coordinates":[24.795741,48.393345],"type":"Point"}
}