{
  "type": "Feature",
  "properties": {
    "gn:admin1_code":"14.0",
    "gn:asciiname":"Shovkova Protoka",
    "gn:country_code":"UA",
    "gn:dem":177,
    "gn:feature_class":"P",
    "gn:feature_code":"PPL",
    "gn:name":"Shovkova Protoka",
    "gn:population":0,
    "gn:timezone":"Europe/Zaporozhye",
    "iso:country":"UA",
    "name:ukr_x_preferred":[
        "Shovkova Protoka"
    ],
    "name:ukr_x_variant":[
        "\u0428\u043e\u0432\u043a\u043e\u0432\u0430 \u041f\u0440\u043e\u0442\u043e\u043a\u0430"
    ],
    "name:und_x_variant":[
        "Golubovka",
        "Sholkovyy Protok",
        "Sh\u00eblkovyy Protok",
        "Shelkovaya Protoka"
    ],
    "wof:name":"Shovkova Protoka",
    "wof:placetype":"locality"
},
  "geometry": {"coordinates":[39.25478,48.30518],"type":"Point"}
}