{
  "type": "Feature",
  "properties": {
    "iso:country":"UA",
    "name:cat_x_preferred":[
        "Berestov\u00e8"
    ],
    "name:che_x_preferred":[
        "\u0411\u0435\u0440\u0435\u0441\u0442\u043e\u0432\u0438"
    ],
    "name:deu_x_preferred":[
        "Berestowe"
    ],
    "name:eng_x_preferred":[
        "Berestovoye"
    ],
    "name:eng_x_variant":[
        "Berestove"
    ],
    "name:fin_x_preferred":[
        "B\u0435r\u0435st\u043ev\u0435"
    ],
    "name:lav_x_preferred":[
        "Berestove"
    ],
    "name:nan_x_preferred":[
        "Berestove"
    ],
    "name:nno_x_preferred":[
        "Berestove"
    ],
    "name:nob_x_preferred":[
        "Berestove"
    ],
    "name:ron_x_preferred":[
        "Berestove"
    ],
    "name:rus_x_preferred":[
        "\u0411\u0435\u0440\u0435\u0441\u0442\u043e\u0432\u043e\u0435"
    ],
    "name:ukr_x_preferred":[
        "Berestove"
    ],
    "name:ukr_x_variant":[
        "\u0411\u0435\u0440\u0435\u0441\u0442\u043e\u0432\u0435"
    ],
    "name:zho_x_preferred":[
        "\u5225\u5217\u65af\u6258\u97cb"
    ],
    "qs:a0":"\u0423\u043a\u0440\u0430\u0457\u043d\u0430",
    "qs:a1":"*\u0417\u0430\u043f\u043e\u0440\u0456\u0437\u044c\u043a\u0430",
    "qs:a1_alt":"Zaporiz'ka",
    "qs:a1r":"0",
    "qs:a2":"\u0411\u0435\u0440\u0434\u044f\u043d\u0441\u044c\u043a\u0438\u0439",
    "qs:a2_alt":"Berdians'kyi",
    "qs:adm0":"\u0423\u043a\u0440\u0430\u0457\u043d\u0430",
    "qs:la_lc":"*",
    "qs:level":"locality",
    "qs:loc":"\u0411\u0435\u0440\u0435\u0441\u0442\u043e\u0432\u0435",
    "qs:loc_alt":"Berestove",
    "qs:pop":0,
    "qs:type":"buffered point",
    "wd:wordcount":897,
    "wof:name":"\u0411\u0435\u0440\u0435\u0441\u0442\u043e\u0432\u0435",
    "wof:placetype":"locality"
},
  "geometry": {"coordinates":[36.802624,47.139386],"type":"Point"}
}