{
  "type": "Feature",
  "properties": {
    "gn:admin1_code":"18.0",
    "gn:asciiname":"Valok",
    "gn:country_code":"UA",
    "gn:dem":145,
    "gn:feature_class":"P",
    "gn:feature_code":"PPL",
    "gn:name":"Valok",
    "gn:population":0,
    "gn:timezone":"Europe/Kiev",
    "iso:country":"UA",
    "name:ukr_x_preferred":[
        "Valok"
    ],
    "name:ukr_x_variant":[
        "\u0412\u0430\u043b\u043e\u043a"
    ],
    "name:und_x_variant":[
        "Volok"
    ],
    "wof:name":"Valok",
    "wof:placetype":"locality"
},
  "geometry": {"coordinates":[34.26806,49.70854],"type":"Point"}
}