{
  "type": "Feature",
  "properties": {
    "gn:admin1_code":"7.0",
    "gn:asciiname":"Vesele",
    "gn:country_code":"UA",
    "gn:dem":86,
    "gn:feature_class":"P",
    "gn:feature_code":"PPL",
    "gn:name":"Vesele",
    "gn:population":0,
    "gn:timezone":"Europe/Kiev",
    "iso:country":"UA",
    "name:bel_x_preferred":[
        "\u0412\u044f\u0441\u0451\u043b\u0430\u0435"
    ],
    "name:ceb_x_preferred":[
        "Vesele"
    ],
    "name:deu_x_preferred":[
        "Wessele"
    ],
    "name:hye_x_preferred":[
        "\u054e\u0565\u057d\u0575\u0578\u056c\u0578\u0565"
    ],
    "name:kaz_x_preferred":[
        "\u0412\u0435\u0441\u0435\u043b\u043e\u0435"
    ],
    "name:ron_x_preferred":[
        "Vesele"
    ],
    "name:rus_x_preferred":[
        "Ves\u00eblyy"
    ],
    "name:rus_x_variant":[
        "\u0412\u0435\u0441\u0451\u043b\u043e\u0435"
    ],
    "name:spa_x_preferred":[
        "Vesele"
    ],
    "name:swe_x_preferred":[
        "Vesele"
    ],
    "name:ukr_x_preferred":[
        "Vesele"
    ],
    "name:ukr_x_variant":[
        "\u0412\u0435\u0441\u0435\u043b\u0435"
    ],
    "name:und_x_variant":[
        "Veseloye"
    ],
    "wof:name":"Vesele",
    "wof:placetype":"locality"
},
  "geometry": {"coordinates":[36.59852,48.62114],"type":"Point"}
}