{
  "type": "Feature",
  "properties": {
    "iso:country":"UA",
    "name:und_x_variant":[
        "Poyyana"
    ],
    "qs:a0":"\u0423\u043a\u0440\u0430\u0457\u043d\u0430",
    "qs:a1":"*\u0427\u0435\u0440\u043d\u0456\u0432\u0435\u0446\u044c\u043a\u0430",
    "qs:a1_alt":"Chernivets'ka",
    "qs:a1r":"0",
    "qs:a2":"\u0425\u043e\u0442\u0438\u043d\u0441\u044c\u043a\u0438\u0439",
    "qs:a2_alt":"Khotyns'kyi",
    "qs:adm0":"\u0423\u043a\u0440\u0430\u0457\u043d\u0430",
    "qs:la_lc":"*",
    "qs:level":"locality",
    "qs:loc":"\u041f\u043e\u043b\u044f\u043d\u0430",
    "qs:loc_alt":"Poliana",
    "qs:pop":0,
    "qs:type":"buffered point",
    "wof:name":"\u041f\u043e\u043b\u044f\u043d\u0430",
    "wof:placetype":"locality"
},
  "geometry": {"coordinates":[26.235312,48.494421],"type":"Point"}
}