{
  "type": "Feature",
  "properties": {
    "gn:admin1_code":"5.0",
    "gn:asciiname":"Bohorodychne",
    "gn:country_code":"UA",
    "gn:dem":70,
    "gn:feature_class":"P",
    "gn:feature_code":"PPL",
    "gn:name":"Bohorodychne",
    "gn:population":0,
    "gn:timezone":"Europe/Kiev",
    "iso:country":"UA",
    "name:ukr_x_preferred":[
        "Bohorodychne"
    ],
    "name:und_x_variant":[
        "Bogorodichnoye"
    ],
    "wof:name":"Bohorodychne",
    "wof:placetype":"locality"
},
  "geometry": {"coordinates":[37.51079,49.01919],"type":"Point"}
}