{
  "type": "Feature",
  "properties": {
    "gn:admin1_code":"15.0",
    "gn:asciiname":"Novyy Vitkov",
    "gn:country_code":"UA",
    "gn:dem":217,
    "gn:feature_class":"P",
    "gn:feature_code":"PPL",
    "gn:name":"Novyy Vitkov",
    "gn:population":0,
    "gn:timezone":"Europe/Kiev",
    "iso:country":"UA",
    "name:und_x_variant":[
        "Vitkov",
        "Witk\u00f3w Nowy",
        "Vitkuv Novy",
        "Vitkov Novy",
        "Novyy Vitkov"
    ],
    "wof:name":"Novyy Vitkov",
    "wof:placetype":"locality"
},
  "geometry": {"coordinates":[24.48614,50.31265],"type":"Point"}
}