{
  "type": "Feature",
  "properties": {
    "gn:admin1_code":"26.0",
    "gn:asciiname":"Verkhn'odrahuns'ke",
    "gn:country_code":"UA",
    "gn:dem":254,
    "gn:feature_class":"P",
    "gn:feature_code":"PPL",
    "gn:name":"Verkhn\u2019odrahuns\u2019ke",
    "gn:population":0,
    "gn:timezone":"Europe/Zaporozhye",
    "iso:country":"UA",
    "name:ukr_x_preferred":[
        "Verkhn\u2019odrahuns\u2019ke"
    ],
    "name:ukr_x_variant":[
        "\u0412\u0435\u0440\u0445\u043d\u044c\u043e\u0434\u0440\u0430\u0433\u0443\u043d\u0441\u044c\u043a\u0435"
    ],
    "name:und_x_variant":[
        "Ruga"
    ],
    "wof:name":"Verkhn'odrahuns'ke",
    "wof:placetype":"locality"
},
  "geometry": {"coordinates":[36.45,47.28333],"type":"Point"}
}