{
  "type": "Feature",
  "properties": {
    "gn:admin1_code":"15.0",
    "gn:asciiname":"Gorodishche",
    "gn:cc2":"UA",
    "gn:country_code":"UA",
    "gn:dem":275,
    "gn:feature_class":"P",
    "gn:feature_code":"PPL",
    "gn:name":"Gorodishche",
    "gn:population":0,
    "gn:timezone":"Europe/Kiev",
    "iso:country":"UA",
    "name:ceb_x_preferred":[
        "Gorodishche"
    ],
    "name:tgl_x_preferred":[
        "Gorodishche"
    ],
    "name:und_x_variant":[
        "Gorodyshche-Tsetnarske",
        "Gorodishche"
    ],
    "name:zho_x_preferred":[
        "\u6208\u7f85\u5b63\u8b1d"
    ],
    "wof:name":"Gorodishche",
    "wof:placetype":"locality"
},
  "geometry": {"coordinates":[24.31667,49.45],"type":"Point"}
}