{
  "type": "Feature",
  "properties": {
    "gn:admin1_code":"1.0",
    "gn:asciiname":"Khrushchivka",
    "gn:country_code":"UA",
    "gn:dem":109,
    "gn:feature_class":"P",
    "gn:feature_code":"PPL",
    "gn:name":"Khrushchivka",
    "gn:population":0,
    "gn:timezone":"Europe/Kiev",
    "iso:country":"UA",
    "name:ukr_x_preferred":[
        "Khrushchivka"
    ],
    "name:ukr_x_variant":[
        "\u0425\u0440\u0443\u0449\u0456\u0432\u043a\u0430"
    ],
    "wof:name":"Khrushchivka",
    "wof:placetype":"locality"
},
  "geometry": {"coordinates":[32.23860999999999,49.76566],"type":"Point"}
}