{
  "type": "Feature",
  "properties": {
    "gn:admin1_code":"2.0",
    "gn:asciiname":"Man'ky",
    "gn:country_code":"UA",
    "gn:dem":153,
    "gn:feature_class":"P",
    "gn:feature_code":"PPL",
    "gn:name":"Man\u2019ky",
    "gn:population":0,
    "gn:timezone":"Europe/Kiev",
    "iso:country":"UA",
    "name:rus_x_preferred":[
        "Man\u2019ki"
    ],
    "name:ukr_x_preferred":[
        "Man\u2019ky"
    ],
    "name:ukr_x_variant":[
        "\u041c\u0430\u043d\u044c\u043a\u0438"
    ],
    "wof:name":"Man'ky",
    "wof:placetype":"locality"
},
  "geometry": {"coordinates":[30.74098,51.71997],"type":"Point"}
}