{
  "type": "Feature",
  "properties": {
    "gn:admin1_code":"9.0",
    "gn:asciiname":"Malaya Radogoshch'",
    "gn:country_code":"UA",
    "gn:dem":219,
    "gn:feature_class":"P",
    "gn:feature_code":"PPL",
    "gn:name":"Malaya Radogoshch\u2019",
    "gn:population":0,
    "gn:timezone":"Europe/Kiev",
    "iso:country":"UA",
    "name:und_x_variant":[
        "Maly Radogoshch\u2019",
        "Malaya Radogoshch\u2019"
    ],
    "wof:name":"Malaya Radogoshch'",
    "wof:placetype":"locality"
},
  "geometry": {"coordinates":[26.43776,50.19638],"type":"Point"}
}