{
  "type": "Feature",
  "properties": {
    "gn:admin1_code":"27.0",
    "gn:asciiname":"Tyutyunnyky",
    "gn:country_code":"UA",
    "gn:dem":269,
    "gn:feature_class":"P",
    "gn:feature_code":"PPL",
    "gn:name":"Tyutyunnyky",
    "gn:population":0,
    "gn:timezone":"Europe/Kiev",
    "iso:country":"UA",
    "name:ukr_x_preferred":[
        "Tyutyunnyky"
    ],
    "name:ukr_x_variant":[
        "\u0422\u044e\u0442\u044e\u043d\u043d\u0438\u043a\u0438"
    ],
    "name:und_x_variant":[
        "Tyutyuniki"
    ],
    "wof:name":"Tyutyunnyky",
    "wof:placetype":"locality"
},
  "geometry": {"coordinates":[28.23366,50.02929],"type":"Point"}
}