{
  "type": "Feature",
  "properties": {
    "gn:admin1_code":"5.0",
    "gn:asciiname":"Yurkivka",
    "gn:country_code":"UA",
    "gn:dem":211,
    "gn:feature_class":"P",
    "gn:feature_code":"PPL",
    "gn:name":"Yurkivka",
    "gn:population":0,
    "gn:timezone":"Europe/Kiev",
    "iso:country":"UA",
    "name:ukr_x_preferred":[
        "Yurkivka"
    ],
    "name:ukr_x_variant":[
        "\u042e\u0440\u043a\u0456\u0432\u043a\u0430"
    ],
    "name:und_x_variant":[
        "Yurkovka"
    ],
    "wof:name":"Yurkivka",
    "wof:placetype":"locality"
},
  "geometry": {"coordinates":[37.80132,48.77629],"type":"Point"}
}