{
  "type": "Feature",
  "properties": {
    "gn:admin1_code":"11.0",
    "gn:admin2_code":"704361",
    "gn:admin3_code":"11152951",
    "gn:asciiname":"Smushkino",
    "gn:country_code":"UA",
    "gn:dem":2,
    "gn:elevation":"4.0",
    "gn:feature_class":"P",
    "gn:feature_code":"PPL",
    "gn:name":"Smushkino",
    "gn:population":17,
    "gn:timezone":"Europe/Simferopol",
    "iso:country":"UA",
    "name:eng_x_preferred":[
        "Smushkino"
    ],
    "name:rus_x_historical":[
        "\u0423\u0440\u0436\u0438\u043d\u043e"
    ],
    "name:rus_x_preferred":[
        "\u0421\u043c\u0443\u0448\u043a\u0438\u043d\u043e"
    ],
    "name:rus_x_variant":[
        "\u0423\u0440\u0436\u0438\u043d\u043e"
    ],
    "name:ukr_x_preferred":[
        "\u0421\u043c\u0443\u0448\u043a\u0438\u043d\u0435"
    ],
    "wof:name":"Smushkino",
    "wof:placetype":"locality",
    "wof:population":17
},
  "geometry": {"coordinates":[33.93813,46.01473],"type":"Point"}
}