{
  "type": "Feature",
  "properties": {
    "gn:admin1_code":"5.0",
    "gn:asciiname":"Vozdvyzhenka",
    "gn:country_code":"UA",
    "gn:dem":183,
    "gn:feature_class":"P",
    "gn:feature_code":"PPL",
    "gn:name":"Vozdvyzhenka",
    "gn:population":0,
    "gn:timezone":"Europe/Kiev",
    "iso:country":"UA",
    "name:ukr_x_preferred":[
        "Vozdvyzhenka"
    ],
    "name:ukr_x_variant":[
        "\u0412\u043e\u0437\u0434\u0432\u0438\u0436\u0435\u043d\u043a\u0430"
    ],
    "name:und_x_variant":[
        "Vozdvizhenka"
    ],
    "wof:name":"Vozdvyzhenka",
    "wof:placetype":"locality"
},
  "geometry": {"coordinates":[37.51503,48.30365],"type":"Point"}
}