{
  "type": "Feature",
  "properties": {
    "gn:admin1_code":"26.0",
    "gn:asciiname":"Druzhelyubivka",
    "gn:country_code":"UA",
    "gn:dem":118,
    "gn:feature_class":"P",
    "gn:feature_code":"PPL",
    "gn:name":"Druzhelyubivka",
    "gn:population":0,
    "gn:timezone":"Europe/Zaporozhye",
    "iso:country":"UA",
    "name:ukr_x_preferred":[
        "Druzhelyubivka"
    ],
    "name:ukr_x_variant":[
        "\u0414\u0440\u0443\u0436\u0435\u043b\u044e\u0431\u0456\u0432\u043a\u0430"
    ],
    "name:und_x_variant":[
        "Druzhelyubovka"
    ],
    "wof:name":"Druzhelyubivka",
    "wof:placetype":"locality"
},
  "geometry": {"coordinates":[35.37589000000001,47.89239],"type":"Point"}
}