{
  "type": "Feature",
  "properties": {
    "iso:country":"UA",
    "name:deu_x_preferred":[
        "Wynohradar"
    ],
    "name:eng_x_preferred":[
        "Vynohradar"
    ],
    "name:lav_x_preferred":[
        "Vinohradara"
    ],
    "name:ron_x_preferred":[
        "V\u00eenohradar"
    ],
    "name:rus_x_preferred":[
        "\u0412\u0438\u043d\u043e\u0433\u0440\u0430\u0434\u0430\u0440\u044c"
    ],
    "name:ukr_x_preferred":[
        "\u0412\u0438\u043d\u043e\u0433\u0440\u0430\u0434\u0430\u0440"
    ],
    "name:zho_x_preferred":[
        "\u7dad\u8afe\u683c\u62c9\u9054\u723e"
    ],
    "qs:a0":"\u0423\u043a\u0440\u0430\u0457\u043d\u0430",
    "qs:a1":"*\u041e\u0434\u0435\u0441\u044c\u043a\u0430",
    "qs:a1_alt":"Odes'ka",
    "qs:a1r":"0",
    "qs:a2":"\u0420\u043e\u0437\u0434\u0456\u043b\u044c\u043d\u044f\u043d\u0441\u044c\u043a\u0438\u0439",
    "qs:a2_alt":"Rozdil'nians'kyi",
    "qs:adm0":"\u0423\u043a\u0440\u0430\u0457\u043d\u0430",
    "qs:la_lc":"*",
    "qs:level":"locality",
    "qs:loc":"\u0412\u0438\u043d\u043e\u0433\u0440\u0430\u0434\u0430\u0440",
    "qs:loc_alt":"Vynohradar",
    "qs:pop":0,
    "qs:type":"buffered point",
    "wd:wordcount":98,
    "wof:name":"\u0412\u0438\u043d\u043e\u0433\u0440\u0430\u0434\u0430\u0440",
    "wof:placetype":"locality"
},
  "geometry": {"coordinates":[30.352276,46.665851],"type":"Point"}
}