{
  "type": "Feature",
  "properties": {
    "gn:admin1_code":"7.0",
    "gn:asciiname":"Karabushchyne",
    "gn:country_code":"UA",
    "gn:dem":135,
    "gn:feature_class":"P",
    "gn:feature_code":"PPL",
    "gn:name":"Karabushchyne",
    "gn:population":0,
    "gn:timezone":"Europe/Kiev",
    "iso:country":"UA",
    "name:rus_x_preferred":[
        "\u041a\u0430\u0440\u0430\u0431\u0443\u0449\u0438\u043d\u043e"
    ],
    "name:ukr_x_preferred":[
        "Karabushchyne"
    ],
    "name:ukr_x_variant":[
        "\u041a\u0430\u0440\u0430\u0431\u0443\u0449\u0438\u043d\u0435"
    ],
    "name:und_x_variant":[
        "Karabushchino"
    ],
    "wof:name":"Karabushchyne",
    "wof:placetype":"locality"
},
  "geometry": {"coordinates":[35.72005,49.20026],"type":"Point"}
}