{
  "type": "Feature",
  "properties": {
    "iso:country":"UA",
    "name:ukr_x_preferred":[
        "Bilashiv"
    ],
    "name:ukr_x_variant":[
        "\u0411\u0456\u043b\u0430\u0448\u0456\u0432"
    ],
    "name:unk_x_variant":[
        "Byalashuv"
    ],
    "qs:a0":"\u0423\u043a\u0440\u0430\u0457\u043d\u0430",
    "qs:a1":"*\u0420\u0456\u0432\u043d\u0435\u043d\u0441\u044c\u043a\u0430",
    "qs:a1_alt":"Rivnens'ka",
    "qs:a1r":"0",
    "qs:a2":"\u0417\u0434\u043e\u043b\u0431\u0443\u043d\u0456\u0432\u0441\u044c\u043a\u0438\u0439",
    "qs:a2_alt":"Zdolbunivs'kyi",
    "qs:adm0":"\u0423\u043a\u0440\u0430\u0457\u043d\u0430",
    "qs:la_lc":"*",
    "qs:level":"locality",
    "qs:loc":"\u0411\u0456\u043b\u0430\u0448\u0456\u0432",
    "qs:loc_alt":"Bilashiv",
    "qs:pop":0,
    "qs:type":"buffered point",
    "wof:name":"\u0411\u0456\u043b\u0430\u0448\u0456\u0432",
    "wof:placetype":"locality"
},
  "geometry": {"coordinates":[26.092234,50.374305],"type":"Point"}
}