{
  "type": "Feature",
  "properties": {
    "gn:admin1_code":"11.0",
    "gn:admin2_code":"692311",
    "gn:asciiname":"Mezhdurech'e",
    "gn:country_code":"UA",
    "gn:dem":187,
    "gn:elevation":"198.0",
    "gn:feature_class":"P",
    "gn:feature_code":"PPL",
    "gn:name":"Mezhdurech'e",
    "gn:population":519,
    "gn:timezone":"Europe/Simferopol",
    "iso:country":"UA",
    "name:crh_x_historical":[
        "Aj Serez"
    ],
    "name:crh_x_preferred":[
        "Aj Serez"
    ],
    "name:eng_x_preferred":[
        "Mezhdurech\u2019e"
    ],
    "name:rus_x_historical":[
        "\u0410\u0439-\u0421\u0435\u0440\u0435\u0301\u0437"
    ],
    "name:rus_x_preferred":[
        "\u041c\u0435\u0436\u0434\u0443\u0440\u0435\u0447\u044c\u0435"
    ],
    "name:rus_x_variant":[
        "\u0410\u0439-\u0421\u0435\u0440\u0435\u0301\u0437"
    ],
    "name:ukr_x_preferred":[
        "\u041c\u0456\u0436\u0440\u0456\u0447\u0447\u044f"
    ],
    "wof:name":"Mezhdurech'e",
    "wof:placetype":"locality",
    "wof:population":519
},
  "geometry": {"coordinates":[34.84808,44.87654000000001],"type":"Point"}
}