{
  "type": "Feature",
  "properties": {
    "gn:admin1_code":"4.0",
    "gn:asciiname":"Kolono-Mykolayivka",
    "gn:country_code":"UA",
    "gn:dem":126,
    "gn:feature_class":"P",
    "gn:feature_code":"PPL",
    "gn:name":"Kolono-Mykolayivka",
    "gn:population":0,
    "gn:timezone":"Europe/Kiev",
    "iso:country":"UA",
    "name:ukr_x_preferred":[
        "Kolono-Mykolayivka"
    ],
    "name:ukr_x_variant":[
        "\u041a\u043e\u043b\u043e\u043d\u043e-\u041c\u0438\u043a\u043e\u043b\u0430\u0457\u0432\u043a\u0430"
    ],
    "name:und_x_variant":[
        "Kolono-Nikolayevka"
    ],
    "wof:name":"Kolono-Mykolayivka",
    "wof:placetype":"locality"
},
  "geometry": {"coordinates":[35.89817,48.28185],"type":"Point"}
}