{
  "type": "Feature",
  "properties": {
    "gn:admin1_code":"2.0",
    "gn:asciiname":"Borki",
    "gn:country_code":"UA",
    "gn:dem":111,
    "gn:feature_class":"P",
    "gn:feature_code":"PPL",
    "gn:name":"Borki",
    "gn:population":0,
    "gn:timezone":"Europe/Kiev",
    "iso:country":"UA",
    "name:bel_x_preferred":[
        "\u0411\u043e\u0440\u043a\u0456"
    ],
    "name:bos_x_preferred":[
        "Borki"
    ],
    "name:ceb_x_preferred":[
        "Borki"
    ],
    "name:crh_x_preferred":[
        "Birk\u0131"
    ],
    "name:deu_x_preferred":[
        "Borki"
    ],
    "name:fra_x_preferred":[
        "Borki"
    ],
    "name:hye_x_preferred":[
        "\u0532\u0578\u0580\u056f\u056b"
    ],
    "name:lit_x_preferred":[
        "Borkai"
    ],
    "name:nld_x_preferred":[
        "Borki"
    ],
    "name:pol_x_preferred":[
        "Borki"
    ],
    "name:rus_x_preferred":[
        "\u0411\u043e\u0440\u043a\u0438"
    ],
    "name:ukr_x_preferred":[
        "\u0411\u043e\u0440\u043a\u0438"
    ],
    "wof:name":"Borki",
    "wof:placetype":"locality"
},
  "geometry": {"coordinates":[31.56667,51.56667],"type":"Point"}
}