{
  "type": "Feature",
  "properties": {
    "gn:admin1_code":"19.0",
    "gn:asciiname":"Nyvets'k",
    "gn:country_code":"UA",
    "gn:dem":155,
    "gn:feature_class":"P",
    "gn:feature_code":"PPL",
    "gn:name":"Nyvets\u2019k",
    "gn:population":0,
    "gn:timezone":"Europe/Kiev",
    "iso:country":"UA",
    "name:ukr_x_preferred":[
        "Nyvets\u2019k"
    ],
    "name:ukr_x_variant":[
        "\u041d\u0438\u0432\u0435\u0446\u044c\u043a"
    ],
    "name:und_x_variant":[
        "Niweck",
        "Nivetsk"
    ],
    "wof:name":"Nyvets'k",
    "wof:placetype":"locality"
},
  "geometry": {"coordinates":[26.43867,51.51393],"type":"Point"}
}