{
  "type": "Feature",
  "properties": {
    "gn:admin1_code":"16.0",
    "gn:asciiname":"Viktorovka",
    "gn:country_code":"UA",
    "gn:dem":84,
    "gn:feature_class":"P",
    "gn:feature_code":"PPL",
    "gn:name":"Viktorovka",
    "gn:population":0,
    "gn:timezone":"Europe/Kiev",
    "iso:country":"UA",
    "name:und_x_variant":[
        "Moiseyevka",
        "Viktorovka"
    ],
    "wof:name":"Viktorovka",
    "wof:placetype":"locality"
},
  "geometry": {"coordinates":[31.56801,47.82437],"type":"Point"}
}