{
  "type": "Feature",
  "properties": {
    "gn:admin1_code":"14.0",
    "gn:asciiname":"Finogeyeva",
    "gn:country_code":"UA",
    "gn:dem":296,
    "gn:feature_class":"P",
    "gn:feature_code":"PPL",
    "gn:name":"Finogeyeva",
    "gn:population":0,
    "gn:timezone":"Europe/Zaporozhye",
    "iso:country":"UA",
    "wof:name":"Finogeyeva",
    "wof:placetype":"locality"
},
  "geometry": {"coordinates":[39.18,48.23889000000001],"type":"Point"}
}