{
  "type": "Feature",
  "properties": {
    "iso:country":"UA",
    "name:bel_x_preferred":[
        "\u041a\u0430\u0440\u044b\u045e"
    ],
    "name:che_x_preferred":[
        "\u041a\u0430\u0440\u043e\u0432"
    ],
    "name:eng_x_preferred":[
        "Kariv"
    ],
    "name:fin_x_preferred":[
        "K\u0430r\u0456v"
    ],
    "name:hye_x_preferred":[
        "\u053f\u0561\u0580\u0578\u057e"
    ],
    "name:nan_x_preferred":[
        "Kariv"
    ],
    "name:nno_x_preferred":[
        "Kariv"
    ],
    "name:nob_x_preferred":[
        "Kariv"
    ],
    "name:pol_x_preferred":[
        "Kar\u00f3w"
    ],
    "name:ron_x_preferred":[
        "Kariv"
    ],
    "name:rus_x_preferred":[
        "\u041a\u0430\u0440\u043e\u0432"
    ],
    "name:ukr_x_preferred":[
        "\u041a\u0430\u0440\u0456\u0432"
    ],
    "name:uzb_x_preferred":[
        "Kariv"
    ],
    "name:zho_x_preferred":[
        "\u5361\u91cc\u592b"
    ],
    "qs:a0":"\u0423\u043a\u0440\u0430\u0457\u043d\u0430",
    "qs:a1":"*\u041b\u044c\u0432\u0456\u0432\u0441\u044c\u043a\u0430",
    "qs:a1_alt":"L'vivs'ka",
    "qs:a1r":"0",
    "qs:a2":"\u0421\u043e\u043a\u0430\u043b\u044c\u0441\u044c\u043a\u0438\u0439",
    "qs:a2_alt":"Sokal's'kyi",
    "qs:adm0":"\u0423\u043a\u0440\u0430\u0457\u043d\u0430",
    "qs:la_lc":"*",
    "qs:level":"locality",
    "qs:loc":"\u041a\u0430\u0440\u0456\u0432",
    "qs:loc_alt":"Kariv",
    "qs:pop":0,
    "qs:type":"buffered point",
    "wof:name":"\u041a\u0430\u0440\u0456\u0432",
    "wof:placetype":"locality"
},
  "geometry": {"coordinates":[23.788119,50.345642],"type":"Point"}
}