{
  "type": "Feature",
  "properties": {
    "gn:admin1_code":"3.0",
    "gn:asciiname":"Glinitsa",
    "gn:country_code":"UA",
    "gn:dem":186,
    "gn:feature_class":"P",
    "gn:feature_code":"PPL",
    "gn:name":"Glinitsa",
    "gn:population":0,
    "gn:timezone":"Europe/Kiev",
    "iso:country":"UA",
    "name:und_x_variant":[
        "Khlinitsa",
        "Gnilitsa",
        "Hlini\u0163a",
        "Glintsa",
        "Glinitsa"
    ],
    "wof:name":"Glinitsa",
    "wof:placetype":"locality"
},
  "geometry": {"coordinates":[25.70507000000001,48.33406],"type":"Point"}
}