{
  "type": "Feature",
  "properties": {
    "gn:admin1_code":"18.0",
    "gn:asciiname":"Arkhypivka",
    "gn:country_code":"UA",
    "gn:dem":159,
    "gn:feature_class":"P",
    "gn:feature_code":"PPL",
    "gn:name":"Arkhypivka",
    "gn:population":0,
    "gn:timezone":"Europe/Kiev",
    "iso:country":"UA",
    "name:ukr_x_preferred":[
        "Arkhypivka"
    ],
    "name:ukr_x_variant":[
        "\u0410\u0440\u0445\u0438\u043f\u0456\u0432\u043a\u0430"
    ],
    "name:und_x_variant":[
        "Arkhipovka"
    ],
    "wof:name":"Arkhypivka",
    "wof:placetype":"locality"
},
  "geometry": {"coordinates":[33.13137,50.29208],"type":"Point"}
}