{
  "type": "Feature",
  "properties": {
    "iso:country":"UA",
    "name:eng_x_preferred":[
        "Rus'ke Pole"
    ],
    "name:epo_x_preferred":[
        "Ruske Pole"
    ],
    "name:heb_x_preferred":[
        "\u05e8\u05d5\u05e1\u05e7\u05d4 \u05e4\u05d5\u05dc\u05d4"
    ],
    "name:hun_x_preferred":[
        "\u00darmez\u0151"
    ],
    "name:hye_x_preferred":[
        "\u054c\u0578\u0582\u057d\u056f\u0578\u0565 \u054a\u0578\u056c\u0565"
    ],
    "name:nld_x_preferred":[
        "\u00darmez\u0151"
    ],
    "name:ron_x_preferred":[
        "Ruske Pole"
    ],
    "name:rus_x_preferred":[
        "\u0420\u0443\u0441\u0441\u043a\u043e\u0435 \u041f\u043e\u043b\u0435"
    ],
    "name:ukr_x_preferred":[
        "Rus\u2019ke Pole"
    ],
    "name:ukr_x_variant":[
        "\u0420\u0443\u0441\u044c\u043a\u0435 \u041f\u043e\u043b\u0435"
    ],
    "name:und_x_variant":[
        "Velikoye Urmez\u00ebvo"
    ],
    "name:zho_x_preferred":[
        "\u9b6f\u897f\u514b\u6ce2\u5217"
    ],
    "qs:a0":"\u0423\u043a\u0440\u0430\u0457\u043d\u0430",
    "qs:a1":"*\u0417\u0430\u043a\u0430\u0440\u043f\u0430\u0442\u0441\u044c\u043a\u0430",
    "qs:a1_alt":"Zakarpats'ka",
    "qs:a1r":"0",
    "qs:a2":"\u0422\u044f\u0447\u0456\u0432\u0441\u044c\u043a\u0438\u0439",
    "qs:a2_alt":"Tiachivs'kyi",
    "qs:adm0":"\u0423\u043a\u0440\u0430\u0457\u043d\u0430",
    "qs:la_lc":"*",
    "qs:level":"locality",
    "qs:loc":"\u0420\u0443\u0441\u044c\u043a\u0435 \u041f\u043e\u043b\u0435",
    "qs:loc_alt":"Rus'ke Pole",
    "qs:pop":0,
    "qs:type":"buffered point",
    "wd:wordcount":20505,
    "wof:name":"\u0420\u0443\u0441\u044c\u043a\u0435 \u041f\u043e\u043b\u0435",
    "wof:placetype":"locality"
},
  "geometry": {"coordinates":[23.526015,48.054657],"type":"Point"}
}