{
  "type": "Feature",
  "properties": {
    "gn:admin1_code":"4.0",
    "gn:asciiname":"Zhovtneve",
    "gn:country_code":"UA",
    "gn:dem":135,
    "gn:feature_class":"P",
    "gn:feature_code":"PPL",
    "gn:name":"Zhovtneve",
    "gn:population":0,
    "gn:timezone":"Europe/Kiev",
    "iso:country":"UA",
    "name:ceb_x_preferred":[
        "Zhovtneve"
    ],
    "name:deu_x_preferred":[
        "Schowtnewe"
    ],
    "name:rus_x_preferred":[
        "\u0416\u043e\u0432\u0442\u043d\u0435\u0432\u043e\u0435"
    ],
    "name:spa_x_preferred":[
        "Zhovtneve"
    ],
    "name:ukr_x_preferred":[
        "Zhovtneve"
    ],
    "name:ukr_x_variant":[
        "\u0416\u043e\u0432\u0442\u043d\u0435\u0432\u0435"
    ],
    "wof:name":"Zhovtneve",
    "wof:placetype":"locality"
},
  "geometry": {"coordinates":[34.14743,48.38067],"type":"Point"}
}