{
  "type": "Feature",
  "properties": {
    "gn:admin1_code":"27.0",
    "gn:asciiname":"Yurkovshchina",
    "gn:country_code":"UA",
    "gn:dem":212,
    "gn:feature_class":"P",
    "gn:feature_code":"PPL",
    "gn:name":"Yurkovshchina",
    "gn:population":0,
    "gn:timezone":"Europe/Kiev",
    "iso:country":"UA",
    "wof:name":"Yurkovshchina",
    "wof:placetype":"locality"
},
  "geometry": {"coordinates":[27.48333,50.55],"type":"Point"}
}