{
  "type": "Feature",
  "properties": {
    "gn:admin1_code":"6.0",
    "gn:asciiname":"Chepelitsy",
    "gn:cc2":"UA",
    "gn:country_code":"UA",
    "gn:dem":310,
    "gn:feature_class":"P",
    "gn:feature_code":"PPL",
    "gn:name":"Chepelitsy",
    "gn:population":0,
    "gn:timezone":"Europe/Kiev",
    "iso:country":"UA",
    "name:und_x_variant":[
        "Chepelitskaya",
        "Chepelitska",
        "Chepelitsy"
    ],
    "wof:name":"Chepelitsy",
    "wof:placetype":"locality"
},
  "geometry": {"coordinates":[25.03333,48.66667],"type":"Point"}
}