{
  "type": "Feature",
  "properties": {
    "gn:admin1_code":"17.0",
    "gn:asciiname":"Sukhe",
    "gn:country_code":"UA",
    "gn:dem":150,
    "gn:feature_class":"P",
    "gn:feature_code":"PPL",
    "gn:name":"Sukhe",
    "gn:population":0,
    "gn:timezone":"Europe/Kiev",
    "iso:country":"UA",
    "name:ukr_x_preferred":[
        "Sukhe"
    ],
    "name:ukr_x_variant":[
        "\u0421\u0443\u0445\u0435"
    ],
    "name:und_x_variant":[
        "Sukhiy Khutor"
    ],
    "wof:name":"Sukhe",
    "wof:placetype":"locality"
},
  "geometry": {"coordinates":[30.09698,46.96848],"type":"Point"}
}