{
  "type": "Feature",
  "properties": {
    "gn:country":"UA",
    "gn:fcode":"PPL",
    "gn:population":3457,
    "iso:country":"UA",
    "name:bel_x_preferred":[
        "\u041c\u044b\u043a\u0443\u043b\u044b\u043d\u0446\u0456"
    ],
    "name:ceb_x_preferred":[
        "Mikulintsy"
    ],
    "name:ces_x_preferred":[
        "Mykulynci"
    ],
    "name:che_x_preferred":[
        "\u041c\u0438\u043a\u0443\u043b\u0438\u043d\u0446\u044b"
    ],
    "name:crh_x_preferred":[
        "M\u0131kul\u0131ntsi"
    ],
    "name:deu_x_preferred":[
        "Mykulynzi"
    ],
    "name:ell_x_preferred":[
        "\u039c\u03b9\u03ba\u03bf\u03cd\u03bb\u03b9\u03bd\u03c4\u03c3\u03b9"
    ],
    "name:eng_x_preferred":[
        "Mikulintsy"
    ],
    "name:eng_x_variant":[
        "Mykulyntsi"
    ],
    "name:fra_x_preferred":[
        "Mykoulyntsi"
    ],
    "name:heb_x_preferred":[
        "\u05de\u05d9\u05e7\u05d5\u05dc\u05d9\u05e0\u05e6\u05d4"
    ],
    "name:hye_x_preferred":[
        "\u0544\u056b\u056f\u0578\u0582\u056c\u056b\u0576\u0581\u056b"
    ],
    "name:nld_x_preferred":[
        "Mykulyntsi"
    ],
    "name:nob_x_preferred":[
        "Mykulyntsi"
    ],
    "name:pol_x_preferred":[
        "Mikuli\u0144ce"
    ],
    "name:rus_x_preferred":[
        "\u041c\u0438\u043a\u0443\u043b\u0438\u043d\u0446\u044b"
    ],
    "name:spa_x_preferred":[
        "Myk\u00falyntsi"
    ],
    "name:szl_x_preferred":[
        "Myku\u0142ynci"
    ],
    "name:ukr_x_preferred":[
        "\u041c\u0438\u043a\u0443\u043b\u0438\u043d\u0446\u0456"
    ],
    "name:und_x_variant":[
        "Mikuliczyn"
    ],
    "name:uzb_x_preferred":[
        "Mykulyntsi"
    ],
    "name:zho_x_preferred":[
        "\u7c73\u5eab\u6797\u9f4a"
    ],
    "qs_pg:aaroncc":"UA",
    "qs_pg:gn_country":"UA",
    "qs_pg:gn_fcode":"PPL",
    "qs_pg:gn_pop":3457,
    "qs_pg:name":"Mikulintsy",
    "qs_pg:photos_9r":0,
    "qs_pg:photos_sr":0,
    "qs_pg:pop_sr":4,
    "qs_pg:qs_pg_placetype":"locality",
    "wof:name":"Mikulintsy",
    "wof:placetype":"locality",
    "wof:population":3457
},
  "geometry": {"coordinates":[25.60518,49.396],"type":"Point"}
}