{
  "type": "Feature",
  "properties": {
    "gn:gn_country":"UA",
    "gn:gn_fcode":"PPL",
    "gn:gn_pop":3457,
    "gn:population":3457,
    "iso:country":"UA",
    "name:deu_x_preferred":[
        "Mykulynzi"
    ],
    "name:eng_x_preferred":[
        "Mikulintsy"
    ],
    "name:fra_x_preferred":[
        "Mykoulyntsi"
    ],
    "name:hye_x_preferred":[
        "\u0544\u056b\u056f\u0578\u0582\u056c\u056b\u0576\u0581\u056b"
    ],
    "name:nld_x_preferred":[
        "Mykulyntsi"
    ],
    "name:pol_x_preferred":[
        "Mikuli\u0144ce"
    ],
    "name:rus_x_preferred":[
        "\u041c\u0438\u043a\u0443\u043b\u0438\u043d\u0446\u044b"
    ],
    "name:ukr_x_preferred":[
        "\u041c\u0438\u043a\u0443\u043b\u0438\u043d\u0446\u0456"
    ],
    "name:unk_x_variant":[
        "Mikuliczyn"
    ],
    "name:zho_x_preferred":[
        "\u7c73\u5eab\u6797\u9f4a"
    ],
    "qs_pg:aaroncc":"UA",
    "qs_pg:gn_country":"UA",
    "qs_pg:gn_fcode":"PPL",
    "qs_pg:gn_pop":3457,
    "qs_pg:name":"Mikulintsy",
    "qs_pg:photos_9r":0,
    "qs_pg:photos_sr":0,
    "qs_pg:pop_sr":4,
    "qs_pg:qs_pg_placetype":"locality",
    "wof:name":"Mikulintsy",
    "wof:placetype":"locality",
    "wof:population":3457
},
  "geometry": {"coordinates":[25.60518,49.396],"type":"Point"}
}