{
  "type": "Feature",
  "properties": {
    "gn:admin1_code":"27",
    "gn:asciiname":"Novoivnyts'ke",
    "gn:country_code":"UA",
    "gn:dem":218,
    "gn:feature_class":"P",
    "gn:feature_code":"PPL",
    "gn:name":"Novoivnyts\u2019ke",
    "gn:population":0,
    "gn:timezone":"Europe/Kiev",
    "iso:country":"UA",
    "name:ukr_x_preferred":[
        "Novoivnyts\u2019ke"
    ],
    "name:ukr_x_variant":[
        "\u041d\u043e\u0432\u043e\u0456\u0432\u043d\u0438\u0446\u044c\u043a\u0435"
    ],
    "wof:name":"Novoivnyts'ke",
    "wof:placetype":"locality"
},
  "geometry": {"coordinates":[29.08146,50.14275],"type":"Point"}
}