{
  "type": "Feature",
  "properties": {
    "iso:country":"UA",
    "name:eng_x_preferred":[
        "Nedra"
    ],
    "name:rus_x_preferred":[
        "\u041d\u0435\u0434\u0440\u0430"
    ],
    "name:rus_x_variant":[
        "\u0418\u0437\u0434\u0430\u0442\u0435\u043b\u044c\u0441\u0442\u0432\u0430 \u0421\u0421\u0421\u0420"
    ],
    "name:ukr_x_preferred":[
        "\u041d\u0435\u0434\u0440\u0430"
    ],
    "name:zho_x_preferred":[
        "\u8607\u806f\u5927\u767e\u79d1\u5168\u4e66\u51fa\u7248\u793e"
    ],
    "qs:a0":"\u0423\u043a\u0440\u0430\u0457\u043d\u0430",
    "qs:a1":"*\u041a\u0438\u0457\u0432\u0441\u044c\u043a\u0430",
    "qs:a1_alt":"Kyivs'ka",
    "qs:a1r":"0",
    "qs:a2":"\u0411\u0430\u0440\u0438\u0448\u0456\u0432\u0441\u044c\u043a\u0438\u0439",
    "qs:a2_alt":"Baryshivs'kyi",
    "qs:adm0":"\u0423\u043a\u0440\u0430\u0457\u043d\u0430",
    "qs:la_lc":"*",
    "qs:level":"locality",
    "qs:loc":"\u041d\u0435\u0434\u0440\u0430",
    "qs:loc_alt":"Nedra",
    "qs:pop":0,
    "qs:type":"buffered point",
    "wd:wordcount":398,
    "wof:name":"\u041d\u0435\u0434\u0440\u0430",
    "wof:placetype":"locality"
},
  "geometry": {"coordinates":[31.507799,50.367449],"type":"Point"}
}