{
  "type": "Feature",
  "properties": {
    "gn:admin1_code":"23.0",
    "gn:asciiname":"Osichna",
    "gn:country_code":"UA",
    "gn:dem":217,
    "gn:feature_class":"P",
    "gn:feature_code":"PPL",
    "gn:name":"Osichna",
    "gn:population":0,
    "gn:timezone":"Europe/Kiev",
    "iso:country":"UA",
    "wof:name":"Osichna",
    "wof:placetype":"locality"
},
  "geometry": {"coordinates":[29.62923,49.22183],"type":"Point"}
}