{
  "type": "Feature",
  "properties": {
    "gn:admin1_code":"4.0",
    "gn:asciiname":"Yuzhne",
    "gn:country_code":"UA",
    "gn:dem":113,
    "gn:feature_class":"P",
    "gn:feature_code":"PPL",
    "gn:name":"Yuzhne",
    "gn:population":0,
    "gn:timezone":"Europe/Kiev",
    "iso:country":"UA",
    "name:rus_x_preferred":[
        "\u042e\u0436\u043d\u043e\u0435"
    ],
    "name:ukr_x_preferred":[
        "Yuzhne"
    ],
    "name:ukr_x_variant":[
        "\u042e\u0436\u043d\u0435"
    ],
    "name:und_x_variant":[
        "Yuzhnoye"
    ],
    "wof:name":"Yuzhne",
    "wof:placetype":"locality"
},
  "geometry": {"coordinates":[33.85211,48.2214],"type":"Point"}
}