{
  "type": "Feature",
  "properties": {
    "gn:admin1_code":"4.0",
    "gn:asciiname":"Yuzhne",
    "gn:country_code":"UA",
    "gn:dem":113,
    "gn:feature_class":"P",
    "gn:feature_code":"PPL",
    "gn:name":"Yuzhne",
    "gn:population":0,
    "gn:timezone":"Europe/Kiev",
    "iso:country":"UA",
    "name:azb_x_preferred":[
        "\u06cc\u0648\u0698\u0646\u0647"
    ],
    "name:bel_x_preferred":[
        "\u042e\u0436\u043d\u044d"
    ],
    "name:bul_x_preferred":[
        "\u042e\u0436\u043d\u0435"
    ],
    "name:ceb_x_preferred":[
        "Yuzhne"
    ],
    "name:ces_x_preferred":[
        "Ju\u017ene"
    ],
    "name:crh_x_preferred":[
        "Yujne"
    ],
    "name:deu_x_preferred":[
        "Juschne"
    ],
    "name:fas_x_preferred":[
        "\u06cc\u0648\u0698\u0646\u0647"
    ],
    "name:fin_x_preferred":[
        "Ju\u017ene"
    ],
    "name:fra_x_preferred":[
        "Youjne"
    ],
    "name:heb_x_preferred":[
        "\u05d9\u05d5\u05d6'\u05e0\u05d9"
    ],
    "name:hsb_x_preferred":[
        "Ju\u017ene"
    ],
    "name:hye_x_preferred":[
        "\u0545\u0578\u0582\u056a\u0576\u056b\u0575"
    ],
    "name:ita_x_preferred":[
        "Ju\u017ene"
    ],
    "name:kat_x_preferred":[
        "\u10d8\u10e3\u10df\u10dc\u10d8"
    ],
    "name:lav_x_preferred":[
        "Ju\u017ene"
    ],
    "name:nno_x_preferred":[
        "Juzjne"
    ],
    "name:nor_x_preferred":[
        "Juzjne"
    ],
    "name:pol_x_preferred":[
        "Ju\u017cne"
    ],
    "name:ron_x_preferred":[
        "Iujne"
    ],
    "name:rus_x_preferred":[
        "\u042e\u0436\u043d\u043e\u0435"
    ],
    "name:sah_x_preferred":[
        "\u042e\u0436\u043d\u0435"
    ],
    "name:srp_x_preferred":[
        "\u0408\u0443\u0436\u043d\u0435"
    ],
    "name:swe_x_preferred":[
        "Juzjne"
    ],
    "name:tat_x_preferred":[
        "\u042e\u0436\u043d\u043e\u0435"
    ],
    "name:ukr_x_preferred":[
        "Yuzhne"
    ],
    "name:ukr_x_variant":[
        "\u042e\u0436\u043d\u0435"
    ],
    "name:und_x_variant":[
        "Yuzhnoye"
    ],
    "name:vie_x_preferred":[
        "Yuzhne"
    ],
    "name:zho_x_preferred":[
        "\u5c24\u65e5\u5167"
    ],
    "wof:name":"Yuzhne",
    "wof:placetype":"locality"
},
  "geometry": {"coordinates":[33.85211,48.2214],"type":"Point"}
}