{
  "type": "Feature",
  "properties": {
    "iso:country":"UA",
    "name:arm_x_preferred":[
        "\u0545\u0561\u0580\u0578\u057e\u0561\u0575\u0561"
    ],
    "name:chi_x_preferred":[
        "\u4e9e\u7f85\u74e6"
    ],
    "name:eng_x_preferred":[
        "Yarovaya"
    ],
    "name:ger_x_preferred":[
        "Jarowa"
    ],
    "name:lav_x_preferred":[
        "Jarova"
    ],
    "name:rus_x_preferred":[
        "\u042f\u0440\u043e\u0432\u0430\u044f"
    ],
    "name:ukr_x_preferred":[
        "Yarova"
    ],
    "name:unk_x_variant":[
        "Yarovaya"
    ],
    "qs:a0":"\u0423\u043a\u0440\u0430\u0457\u043d\u0430",
    "qs:a1":"*\u0414\u043e\u043d\u0435\u0446\u044c\u043a\u0430",
    "qs:a1_alt":"Donets'ka",
    "qs:a1r":"0",
    "qs:a2":"\u041a\u0440\u0430\u0441\u043d\u043e\u043b\u0438\u043c\u0430\u043d\u0441\u044c\u043a\u0438\u0439",
    "qs:a2_alt":"Krasnolymans'kyi",
    "qs:adm0":"\u0423\u043a\u0440\u0430\u0457\u043d\u0430",
    "qs:la_lc":"*",
    "qs:level":"locality",
    "qs:loc":"\u042f\u0440\u043e\u0432\u0430",
    "qs:loc_alt":"Yarova",
    "qs:pop":0,
    "qs:type":"buffered point",
    "wof:name":"\u042f\u0440\u043e\u0432\u0430",
    "wof:placetype":"locality"
},
  "geometry": {"coordinates":[37.645314,49.052472],"type":"Point"}
}