{
  "type": "Feature",
  "properties": {
    "iso:country":"UA",
    "name:deu_x_preferred":[
        "Iwanopillja"
    ],
    "name:eng_x_preferred":[
        "Ivanopillia"
    ],
    "name:hye_x_preferred":[
        "\u053b\u057e\u0561\u0576\u0578\u057a\u0578\u056c\u056b\u0565"
    ],
    "name:lav_x_preferred":[
        "Ivanopi\u013c\u013ca"
    ],
    "name:rus_x_preferred":[
        "\u0418\u0432\u0430\u043d\u043e\u043f\u043e\u043b\u044c\u0435"
    ],
    "name:ukr_x_preferred":[
        "\u0406\u0432\u0430\u043d\u043e\u043f\u0456\u043b\u043b\u044f"
    ],
    "name:und_x_variant":[
        "Ivanopillya"
    ],
    "qs:a0":"\u0423\u043a\u0440\u0430\u0457\u043d\u0430",
    "qs:a1":"*\u0414\u043e\u043d\u0435\u0446\u044c\u043a\u0430",
    "qs:a1_alt":"Donets'ka",
    "qs:a1r":"0",
    "qs:a2":"\u041a\u043e\u0441\u0442\u044f\u043d\u0442\u0438\u043d\u0456\u0432\u0441\u044c\u043a\u0438\u0439",
    "qs:a2_alt":"Kostiantynivs'kyi",
    "qs:adm0":"\u0423\u043a\u0440\u0430\u0457\u043d\u0430",
    "qs:la_lc":"*",
    "qs:level":"locality",
    "qs:loc":"\u0406\u0432\u0430\u043d\u043e\u043f\u0456\u043b\u043b\u044f",
    "qs:loc_alt":"Ivanopillia",
    "qs:pop":0,
    "qs:type":"buffered point",
    "wof:name":"\u0406\u0432\u0430\u043d\u043e\u043f\u0456\u043b\u043b\u044f",
    "wof:placetype":"locality"
},
  "geometry": {"coordinates":[37.758115,48.48878],"type":"Point"}
}