{
  "type": "Feature",
  "properties": {
    "gn:admin1_code":"7.0",
    "gn:asciiname":"Lochinov",
    "gn:country_code":"UA",
    "gn:dem":162,
    "gn:feature_class":"P",
    "gn:feature_code":"PPL",
    "gn:name":"Lochinov",
    "gn:population":0,
    "gn:timezone":"Europe/Kiev",
    "iso:country":"UA",
    "name:und_x_variant":[
        "Lochinovo",
        "Lochinov"
    ],
    "wof:name":"Lochinov",
    "wof:placetype":"locality"
},
  "geometry": {"coordinates":[36.78331,48.94154],"type":"Point"}
}