{
  "type": "Feature",
  "properties": {
    "gn:admin1_code":"23.0",
    "gn:asciiname":"Vugrinivka",
    "gn:country_code":"UA",
    "gn:dem":247,
    "gn:feature_class":"P",
    "gn:feature_code":"PPL",
    "gn:name":"Vugrinivka",
    "gn:population":0,
    "gn:timezone":"Europe/Kiev",
    "iso:country":"UA",
    "wof:name":"Vugrinivka",
    "wof:placetype":"locality"
},
  "geometry": {"coordinates":[27.95,49.55],"type":"Point"}
}