{
  "type": "Feature",
  "properties": {
    "gn:admin1_code":"24.0",
    "gn:asciiname":"Kryvlyn",
    "gn:country_code":"UA",
    "gn:dem":170,
    "gn:feature_class":"P",
    "gn:feature_code":"PPL",
    "gn:name":"Kryvlyn",
    "gn:population":0,
    "gn:timezone":"Europe/Kiev",
    "iso:country":"UA",
    "name:ukr_x_preferred":[
        "Kryvlyn"
    ],
    "name:ukr_x_variant":[
        "\u041a\u0440\u0438\u0432\u043b\u0438\u043d"
    ],
    "name:und_x_variant":[
        "Krivlin"
    ],
    "wof:name":"Kryvlyn",
    "wof:placetype":"locality"
},
  "geometry": {"coordinates":[25.11604,51.17628],"type":"Point"}
}