{
  "type": "Feature",
  "properties": {
    "gn:admin1_code":"9.0",
    "gn:asciiname":"Besidky",
    "gn:country_code":"UA",
    "gn:dem":231,
    "gn:feature_class":"P",
    "gn:feature_code":"PPL",
    "gn:name":"Besidky",
    "gn:population":0,
    "gn:timezone":"Europe/Kiev",
    "iso:country":"UA",
    "name:ukr_x_preferred":[
        "Besidky"
    ],
    "name:ukr_x_variant":[
        "\u0411\u0435\u0441\u0456\u0434\u043a\u0438"
    ],
    "name:und_x_variant":[
        "Besedki"
    ],
    "wof:name":"Besidky",
    "wof:placetype":"locality"
},
  "geometry": {"coordinates":[27.2231,50.50832],"type":"Point"}
}