{
  "type": "Feature",
  "properties": {
    "gn:admin1_code":"23.0",
    "gn:asciiname":"Maloye Kutyshche",
    "gn:country_code":"UA",
    "gn:dem":284,
    "gn:feature_class":"P",
    "gn:feature_code":"PPL",
    "gn:name":"Maloye Kutyshche",
    "gn:population":0,
    "gn:timezone":"Europe/Kiev",
    "iso:country":"UA",
    "name:und_x_variant":[
        "Maloye Kutishche",
        "Maloye Kutyshche"
    ],
    "wof:name":"Maloye Kutyshche",
    "wof:placetype":"locality"
},
  "geometry": {"coordinates":[28.41643,49.63766],"type":"Point"}
}