{
  "type": "Feature",
  "properties": {
    "gn:admin1_code":"16.0",
    "gn:asciiname":"Shostakove",
    "gn:country_code":"UA",
    "gn:dem":74,
    "gn:feature_class":"P",
    "gn:feature_code":"PPL",
    "gn:name":"Shostakove",
    "gn:population":0,
    "gn:timezone":"Europe/Kiev",
    "iso:country":"UA",
    "wof:name":"Shostakove",
    "wof:placetype":"locality"
},
  "geometry": {"coordinates":[31.72045,47.217],"type":"Point"}
}