{
  "type": "Feature",
  "properties": {
    "gn:admin1_code":"7.0",
    "gn:asciiname":"Popel'ne",
    "gn:country_code":"UA",
    "gn:dem":193,
    "gn:feature_class":"P",
    "gn:feature_code":"PPL",
    "gn:name":"Popel\u2019ne",
    "gn:population":0,
    "gn:timezone":"Europe/Kiev",
    "iso:country":"UA",
    "name:rus_x_preferred":[
        "\u041f\u043e\u043f\u0435\u043b\u044c\u043d\u043e\u0435"
    ],
    "name:ukr_x_preferred":[
        "Popel\u2019ne"
    ],
    "name:ukr_x_variant":[
        "\u041f\u043e\u043f\u0435\u043b\u044c\u043d\u0435"
    ],
    "name:und_x_variant":[
        "Popel\u2019noye",
        "Popel\u2019nyy"
    ],
    "wof:name":"Popel'ne",
    "wof:placetype":"locality"
},
  "geometry": {"coordinates":[37.5223,50.27423],"type":"Point"}
}