{
  "type": "Feature",
  "properties": {
    "gn:admin1_code":"13.0",
    "gn:asciiname":"Bezuhlivka",
    "gn:country_code":"UA",
    "gn:dem":124,
    "gn:feature_class":"P",
    "gn:feature_code":"PPL",
    "gn:name":"Bezuhlivka",
    "gn:population":0,
    "gn:timezone":"Europe/Kiev",
    "iso:country":"UA",
    "name:ukr_x_preferred":[
        "Bezuhlivka"
    ],
    "name:ukr_x_variant":[
        "\u0411\u0435\u0437\u0443\u0433\u043b\u0456\u0432\u043a\u0430"
    ],
    "name:und_x_variant":[
        "Bezuglovka"
    ],
    "wof:name":"Bezuhlivka",
    "wof:placetype":"locality"
},
  "geometry": {"coordinates":[31.75687000000001,50.41841],"type":"Point"}
}