{
  "type": "Feature",
  "properties": {
    "gn:admin1_code":"7.0",
    "gn:asciiname":"Danyl'chyn Kut",
    "gn:country_code":"UA",
    "gn:dem":175,
    "gn:feature_class":"P",
    "gn:feature_code":"PPL",
    "gn:name":"Danyl\u2019chyn Kut",
    "gn:population":0,
    "gn:timezone":"Europe/Kiev",
    "iso:country":"UA",
    "name:ukr_x_preferred":[
        "Danyl\u2019chyn Kut"
    ],
    "name:ukr_x_variant":[
        "\u0414\u0430\u043d\u0438\u043b\u044c\u0447\u0438\u043d \u041a\u0443\u0442"
    ],
    "wof:name":"Danyl'chyn Kut",
    "wof:placetype":"locality"
},
  "geometry": {"coordinates":[35.64635,49.8015],"type":"Point"}
}