{
  "type": "Feature",
  "properties": {
    "iso:country":"UA",
    "name:rus_x_preferred":[
        "Velikaya Rubl\u00ebvka"
    ],
    "name:ukr_x_preferred":[
        "\u0412\u0435\u043b\u0438\u043a\u0430 \u0420\u0443\u0431\u043b\u0456\u0432\u043a\u0430"
    ],
    "name:unk_x_variant":[
        "Bol\u2019shaya Rubl\u00ebvka"
    ],
    "qs:a0":"\u0423\u043a\u0440\u0430\u0457\u043d\u0430",
    "qs:a1":"*\u041f\u043e\u043b\u0442\u0430\u0432\u0441\u044c\u043a\u0430",
    "qs:a1_alt":"Poltavs'ka",
    "qs:a1r":"0",
    "qs:a2":"\u041a\u043e\u0442\u0435\u043b\u0435\u0432\u0441\u044c\u043a\u0438\u0439",
    "qs:a2_alt":"Kotelevs'kyi",
    "qs:adm0":"\u0423\u043a\u0440\u0430\u0457\u043d\u0430",
    "qs:la_lc":"*",
    "qs:level":"locality",
    "qs:loc":"\u0412\u0435\u043b\u0438\u043a\u0430 \u0420\u0443\u0431\u043b\u0456\u0432\u043a\u0430",
    "qs:loc_alt":"Velyka Rublivka",
    "qs:pop":0,
    "qs:type":"buffered point",
    "wof:name":"\u0412\u0435\u043b\u0438\u043a\u0430 \u0420\u0443\u0431\u043b\u0456\u0432\u043a\u0430",
    "wof:placetype":"locality"
},
  "geometry": {"coordinates":[34.802723,49.896951],"type":"Point"}
}