{
  "type": "Feature",
  "properties": {
    "gn:admin1_code":"19.0",
    "gn:asciiname":"Mykhalkivtsi",
    "gn:country_code":"UA",
    "gn:dem":200,
    "gn:feature_class":"P",
    "gn:feature_code":"PPL",
    "gn:name":"Mykhalkivtsi",
    "gn:population":0,
    "gn:timezone":"Europe/Kiev",
    "iso:country":"UA",
    "name:ukr_x_preferred":[
        "Mykhalkivtsi"
    ],
    "name:ukr_x_variant":[
        "\u041c\u0438\u0445\u0430\u043b\u043a\u0456\u0432\u0446\u0456"
    ],
    "name:und_x_variant":[
        "Mikchalkovtse",
        "Mikhalkovtsy"
    ],
    "wof:name":"Mykhalkivtsi",
    "wof:placetype":"locality"
},
  "geometry": {"coordinates":[26.56431,50.49100000000001],"type":"Point"}
}