{
  "type": "Feature",
  "properties": {
    "gn:admin1_code":"7.0",
    "gn:asciiname":"Enehgetykiv",
    "gn:country_code":"UA",
    "gn:dem":198,
    "gn:feature_class":"P",
    "gn:feature_code":"PPL",
    "gn:name":"Enehgetykiv",
    "gn:population":0,
    "gn:timezone":"Europe/Kiev",
    "iso:country":"UA",
    "name:ukr_x_preferred":[
        "Enehgetykiv"
    ],
    "name:ukr_x_variant":[
        "\u0415\u043d\u0435\u0440\u0433\u0435\u0442\u0438\u043a\u0456\u0432"
    ],
    "name:und_x_variant":[
        "Energetikov"
    ],
    "wof:name":"Enehgetykiv",
    "wof:placetype":"locality"
},
  "geometry": {"coordinates":[36.68016,48.82391],"type":"Point"}
}