{
  "type": "Feature",
  "properties": {
    "gn:admin1_code":"9.0",
    "gn:asciiname":"Hubyn",
    "gn:country_code":"UA",
    "gn:dem":268,
    "gn:feature_class":"P",
    "gn:feature_code":"PPL",
    "gn:name":"Hubyn",
    "gn:population":0,
    "gn:timezone":"Europe/Kiev",
    "iso:country":"UA",
    "name:ukr_x_preferred":[
        "Hubyn"
    ],
    "name:ukr_x_variant":[
        "\u0413\u0443\u0431\u0438\u043d"
    ],
    "name:und_x_variant":[
        "Gubin"
    ],
    "wof:name":"Hubyn",
    "wof:placetype":"locality"
},
  "geometry": {"coordinates":[27.45264,49.77757],"type":"Point"}
}