{
  "type": "Feature",
  "properties": {
    "gn:admin1_code":"21.0",
    "gn:asciiname":"Pryvillya",
    "gn:country_code":"UA",
    "gn:dem":167,
    "gn:feature_class":"P",
    "gn:feature_code":"PPL",
    "gn:name":"Pryvillya",
    "gn:population":0,
    "gn:timezone":"Europe/Kiev",
    "iso:country":"UA",
    "name:rus_x_preferred":[
        "Privol\u2019ye"
    ],
    "name:ukr_x_preferred":[
        "Pryvillya"
    ],
    "name:ukr_x_variant":[
        "\u041f\u0440\u0438\u0432\u0456\u043b\u043b\u044f"
    ],
    "name:und_x_variant":[
        "Frevgal\u2019tovo",
        "Freygol\u2019tovo"
    ],
    "wof:name":"Pryvillya",
    "wof:placetype":"locality"
},
  "geometry": {"coordinates":[34.0175,51.70639],"type":"Point"}
}