{
  "type": "Feature",
  "properties": {
    "gn:admin1_code":"7.0",
    "gn:asciiname":"Petrivs'ke",
    "gn:country_code":"UA",
    "gn:dem":107,
    "gn:feature_class":"P",
    "gn:feature_code":"PPL",
    "gn:name":"Petrivs\u2019ke",
    "gn:population":0,
    "gn:timezone":"Europe/Kiev",
    "iso:country":"UA",
    "name:ukr_x_preferred":[
        "Petrivs\u2019ke"
    ],
    "name:ukr_x_variant":[
        "\u041f\u0435\u0442\u0440\u0456\u0432\u0441\u044c\u043a\u0435"
    ],
    "wof:name":"Petrivs'ke",
    "wof:placetype":"locality"
},
  "geometry": {"coordinates":[35.17163,50.04782],"type":"Point"}
}