{
  "type": "Feature",
  "properties": {
    "gn:admin1_code":"27.0",
    "gn:asciiname":"Smokivka",
    "gn:country_code":"UA",
    "gn:dem":219,
    "gn:feature_class":"P",
    "gn:feature_code":"PPL",
    "gn:name":"Smokivka",
    "gn:population":0,
    "gn:timezone":"Europe/Kiev",
    "iso:country":"UA",
    "name:ukr_x_preferred":[
        "Smokivka"
    ],
    "name:ukr_x_variant":[
        "\u0421\u043c\u043e\u043a\u0456\u0432\u043a\u0430"
    ],
    "name:und_x_variant":[
        "Tsmokovka",
        "Tsmokivka",
        "Smokovka"
    ],
    "wof:name":"Smokivka",
    "wof:placetype":"locality"
},
  "geometry": {"coordinates":[28.73368,50.2857],"type":"Point"}
}