{
  "type": "Feature",
  "properties": {
    "gn:admin1_code":"4.0",
    "gn:asciiname":"Kotlyarivka",
    "gn:country_code":"UA",
    "gn:dem":120,
    "gn:feature_class":"P",
    "gn:feature_code":"PPL",
    "gn:name":"Kotlyarivka",
    "gn:population":0,
    "gn:timezone":"Europe/Kiev",
    "iso:country":"UA",
    "name:ukr_x_preferred":[
        "Kotlyarivka"
    ],
    "name:ukr_x_variant":[
        "\u041a\u043e\u0442\u043b\u044f\u0440\u0456\u0432\u043a\u0430"
    ],
    "wof:name":"Kotlyarivka",
    "wof:placetype":"locality"
},
  "geometry": {"coordinates":[34.5595,48.10283],"type":"Point"}
}