{
  "type": "Feature",
  "properties": {
    "gn:admin1_code":"27.0",
    "gn:asciiname":"Zhad'ky",
    "gn:country_code":"UA",
    "gn:dem":196,
    "gn:feature_class":"P",
    "gn:feature_code":"PPL",
    "gn:name":"Zhad\u2019ky",
    "gn:population":0,
    "gn:timezone":"Europe/Kiev",
    "iso:country":"UA",
    "name:rus_x_preferred":[
        "Zhad\u2019ki"
    ],
    "name:ukr_x_preferred":[
        "Zhad\u2019ky"
    ],
    "name:ukr_x_variant":[
        "\u0416\u0430\u0434\u044c\u043a\u0438"
    ],
    "wof:name":"Zhad'ky",
    "wof:placetype":"locality"
},
  "geometry": {"coordinates":[28.80407,50.60822],"type":"Point"}
}