{
  "type": "Feature",
  "properties": {
    "gn:admin1_code":"15.0",
    "gn:asciiname":"Kovynichi",
    "gn:country_code":"UA",
    "gn:dem":273,
    "gn:feature_class":"P",
    "gn:feature_code":"PPL",
    "gn:name":"Kovynichi",
    "gn:population":0,
    "gn:timezone":"Europe/Kiev",
    "iso:country":"UA",
    "name:und_x_variant":[
        "Kovenitse",
        "Kovynichi"
    ],
    "wof:name":"Kovynichi",
    "wof:placetype":"locality"
},
  "geometry": {"coordinates":[23.23336,49.62194],"type":"Point"}
}