{
  "type": "Feature",
  "properties": {
    "gn:admin1_code":"24.0",
    "gn:asciiname":"Kholoniv",
    "gn:country_code":"UA",
    "gn:dem":192,
    "gn:feature_class":"P",
    "gn:feature_code":"PPL",
    "gn:name":"Kholoniv",
    "gn:population":0,
    "gn:timezone":"Europe/Kiev",
    "iso:country":"UA",
    "name:ukr_x_preferred":[
        "Kholoniv"
    ],
    "name:ukr_x_variant":[
        "\u0425\u043e\u043b\u043e\u043d\u0456\u0432"
    ],
    "name:und_x_variant":[
        "Cho\u0142oni\u00f3w",
        "Kholonyuv",
        "Kholonev"
    ],
    "wof:name":"Kholoniv",
    "wof:placetype":"locality"
},
  "geometry": {"coordinates":[24.83839,50.48541],"type":"Point"}
}