{
  "type": "Feature",
  "properties": {
    "iso:country":"UA",
    "name:ceb_x_preferred":[
        "Zavydovo"
    ],
    "name:eng_x_preferred":[
        "Zavydovo"
    ],
    "name:epo_x_preferred":[
        "Zavidovo"
    ],
    "name:fra_x_preferred":[
        "Zavydovo"
    ],
    "name:hun_x_preferred":[
        "D\u00e1vidfalva"
    ],
    "name:hye_x_preferred":[
        "\u0536\u0561\u057e\u056b\u0564\u0578\u057e\u0578"
    ],
    "name:nld_x_preferred":[
        "Zavydovo"
    ],
    "name:ron_x_preferred":[
        "Zav\u00eedovo"
    ],
    "name:rus_x_preferred":[
        "\u0417\u0430\u0432\u0438\u0434\u043e\u0432\u043e"
    ],
    "name:ukr_x_preferred":[
        "\u0417\u0430\u0432\u0438\u0434\u043e\u0432\u043e"
    ],
    "name:unk_x_variant":[
        "Zavydove"
    ],
    "name:zho_x_preferred":[
        "\u624e\u7dad\u591a\u6c83"
    ],
    "qs:a0":"\u0423\u043a\u0440\u0430\u0457\u043d\u0430",
    "qs:a1":"*\u0417\u0430\u043a\u0430\u0440\u043f\u0430\u0442\u0441\u044c\u043a\u0430",
    "qs:a1_alt":"Zakarpats'ka",
    "qs:a1r":"0",
    "qs:a2":"\u041c\u0443\u043a\u0430\u0447\u0456\u0432\u0441\u044c\u043a\u0438\u0439",
    "qs:a2_alt":"Mukachivs'kyi",
    "qs:adm0":"\u0423\u043a\u0440\u0430\u0457\u043d\u0430",
    "qs:la_lc":"*",
    "qs:level":"locality",
    "qs:loc":"\u0417\u0430\u0432\u0438\u0434\u043e\u0432\u043e",
    "qs:loc_alt":"Zavydovo",
    "qs:pop":0,
    "qs:type":"buffered point",
    "wd:wordcount":59,
    "wof:name":"\u0417\u0430\u0432\u0438\u0434\u043e\u0432\u043e",
    "wof:placetype":"locality"
},
  "geometry": {"coordinates":[22.90319,48.391429],"type":"Point"}
}