{
  "type": "Feature",
  "properties": {
    "gn:admin1_code":"7.0",
    "gn:asciiname":"Hlazunivka",
    "gn:country_code":"UA",
    "gn:dem":142,
    "gn:feature_class":"P",
    "gn:feature_code":"PPL",
    "gn:name":"Hlazunivka",
    "gn:population":0,
    "gn:timezone":"Europe/Kiev",
    "iso:country":"UA",
    "name:ukr_x_preferred":[
        "Hlazunivka"
    ],
    "name:ukr_x_variant":[
        "\u0413\u043b\u0430\u0437\u0443\u043d\u0456\u0432\u043a\u0430"
    ],
    "name:und_x_variant":[
        "Glazunovka"
    ],
    "wof:name":"Hlazunivka",
    "wof:placetype":"locality"
},
  "geometry": {"coordinates":[36.62714,49.40955],"type":"Point"}
}