{
  "type": "Feature",
  "properties": {
    "gn:admin1_code":"23.0",
    "gn:asciiname":"Sopyn",
    "gn:country_code":"UA",
    "gn:dem":290,
    "gn:feature_class":"P",
    "gn:feature_code":"PPL",
    "gn:name":"Sopyn",
    "gn:population":0,
    "gn:timezone":"Europe/Kiev",
    "iso:country":"UA",
    "name:rus_x_preferred":[
        "\u0421\u043e\u043f\u0438\u043d"
    ],
    "name:ukr_x_preferred":[
        "\u0421\u043e\u043f\u0438\u043d"
    ],
    "wof:name":"Sopyn",
    "wof:placetype":"locality"
},
  "geometry": {"coordinates":[28.94187,49.42686],"type":"Point"}
}