{
  "type": "Feature",
  "properties": {
    "gn:admin1_code":"11.0",
    "gn:admin2_code":"710690",
    "gn:admin3_code":"11153138.0",
    "gn:asciiname":"Snezhnoye",
    "gn:country_code":"UA",
    "gn:dem":26,
    "gn:elevation":"31.0",
    "gn:feature_class":"P",
    "gn:feature_code":"PPL",
    "gn:name":"Snezhnoye",
    "gn:population":83,
    "gn:timezone":"Europe/Simferopol",
    "iso:country":"UA",
    "name:eng_x_preferred":[
        "Snezhnoye"
    ],
    "name:rus_x_historical":[
        "\u041a\u0430\u0440\u043b\u0430\u0301\u0432 \u0420\u0443\u0301\u0441\u0441\u043a\u0438\u0439"
    ],
    "name:rus_x_preferred":[
        "\u0421\u043d\u0435\u0436\u043d\u043e\u0435"
    ],
    "name:rus_x_variant":[
        "\u041a\u0430\u0440\u043b\u0430\u0301\u0432 \u0420\u0443\u0301\u0441\u0441\u043a\u0438\u0439"
    ],
    "name:ukr_x_preferred":[
        "\u0421\u043d\u0456\u0436\u043d\u0435"
    ],
    "wof:name":"Snezhnoye",
    "wof:placetype":"locality",
    "wof:population":83
},
  "geometry": {"coordinates":[32.83774,45.52733],"type":"Point"}
}