{
  "type": "Feature",
  "properties": {
    "gn:admin1_code":"7.0",
    "gn:asciiname":"Horyane",
    "gn:country_code":"UA",
    "gn:dem":175,
    "gn:feature_class":"P",
    "gn:feature_code":"PPL",
    "gn:name":"Horyane",
    "gn:population":0,
    "gn:timezone":"Europe/Kiev",
    "iso:country":"UA",
    "name:ukr_x_preferred":[
        "Horyane"
    ],
    "name:ukr_x_variant":[
        "\u0413\u043e\u0440\u044f\u043d\u0435"
    ],
    "name:und_x_variant":[
        "Goryanov"
    ],
    "wof:name":"Horyane",
    "wof:placetype":"locality"
},
  "geometry": {"coordinates":[37.3748,50.07505],"type":"Point"}
}