{
  "type": "Feature",
  "properties": {
    "gn:admin1_code":"10.0",
    "gn:asciiname":"Novo-Kiyevka",
    "gn:country_code":"UA",
    "gn:dem":121,
    "gn:feature_class":"P",
    "gn:feature_code":"PPL",
    "gn:name":"Novo-Kiyevka",
    "gn:population":0,
    "gn:timezone":"Europe/Kiev",
    "iso:country":"UA",
    "wof:name":"Novo-Kiyevka",
    "wof:placetype":"locality"
},
  "geometry": {"coordinates":[32.35,47.93333],"type":"Point"}
}