{
  "type": "Feature",
  "properties": {
    "iso:country":"UA",
    "name:ukr_x_preferred":[
        "Andriyivka"
    ],
    "name:ukr_x_variant":[
        "\u0410\u043d\u0434\u0440\u0456\u0457\u0432\u043a\u0430"
    ],
    "name:und_x_variant":[
        "Andreyevka"
    ],
    "qs:a0":"\u0423\u043a\u0440\u0430\u0457\u043d\u0430",
    "qs:a1":"*\u041a\u0438\u0457\u0432\u0441\u044c\u043a\u0430",
    "qs:a1_alt":"Kyivs'ka",
    "qs:a1r":"0",
    "qs:a2":"\u041c\u0430\u043a\u0430\u0440\u0456\u0432\u0441\u044c\u043a\u0438\u0439",
    "qs:a2_alt":"Makarivs'kyi",
    "qs:adm0":"\u0423\u043a\u0440\u0430\u0457\u043d\u0430",
    "qs:la_lc":"*",
    "qs:level":"locality",
    "qs:loc":"\u0410\u043d\u0434\u0440\u0456\u0457\u0432\u043a\u0430",
    "qs:loc_alt":"Andriivka",
    "qs:pop":0,
    "qs:type":"buffered point",
    "wd:wordcount":103,
    "wof:name":"\u0410\u043d\u0434\u0440\u0456\u0457\u0432\u043a\u0430",
    "wof:placetype":"locality"
},
  "geometry": {"coordinates":[29.826579,50.542978],"type":"Point"}
}