{
  "type": "Feature",
  "properties": {
    "gn:admin1_code":"21.0",
    "gn:asciiname":"Stepove",
    "gn:country_code":"UA",
    "gn:dem":165,
    "gn:feature_class":"P",
    "gn:feature_code":"PPL",
    "gn:name":"Stepove",
    "gn:population":0,
    "gn:timezone":"Europe/Kiev",
    "iso:country":"UA",
    "name:deu_x_preferred":[
        "Stepowe"
    ],
    "name:hye_x_preferred":[
        "\u054d\u057f\u0565\u057a\u0578\u057e\u0578\u0565"
    ],
    "name:rus_x_preferred":[
        "\u0421\u0442\u0435\u043f\u043e\u0432\u043e\u0435"
    ],
    "name:ukr_x_preferred":[
        "Zhovtneve"
    ],
    "name:ukr_x_variant":[
        "\u0416\u043e\u0432\u0442\u043d\u0435\u0432\u0435",
        "Stepove",
        "\u0421\u0442\u0435\u043f\u043e\u0432\u0435"
    ],
    "name:und_x_variant":[
        "Kholodnyaki"
    ],
    "wof:name":"Stepove",
    "wof:placetype":"locality"
},
  "geometry": {"coordinates":[34.19977,50.73612],"type":"Point"}
}