{
  "type": "Feature",
  "properties": {
    "gn:admin1_code":"23.0",
    "gn:asciiname":"Pilyava",
    "gn:country_code":"UA",
    "gn:dem":277,
    "gn:feature_class":"P",
    "gn:feature_code":"PPL",
    "gn:name":"Pilyava",
    "gn:population":0,
    "gn:timezone":"Europe/Kiev",
    "iso:country":"UA",
    "wof:name":"Pilyava",
    "wof:placetype":"locality"
},
  "geometry": {"coordinates":[28.52326,49.07142],"type":"Point"}
}