{
  "type": "Feature",
  "properties": {
    "gn:admin1_code":"23.0",
    "gn:asciiname":"Voznivtsi",
    "gn:country_code":"UA",
    "gn:dem":313,
    "gn:feature_class":"P",
    "gn:feature_code":"PPL",
    "gn:name":"Voznivtsi",
    "gn:population":0,
    "gn:timezone":"Europe/Kiev",
    "iso:country":"UA",
    "name:ukr_x_preferred":[
        "\u0412\u043e\u0437\u043d\u0456\u0432\u0446\u0456"
    ],
    "name:und_x_variant":[
        "Voznivtsy"
    ],
    "wof:name":"Voznivtsi",
    "wof:placetype":"locality"
},
  "geometry": {"coordinates":[28.21395,48.89962],"type":"Point"}
}