{
  "type": "Feature",
  "properties": {
    "gn:admin1_code":"5.0",
    "gn:asciiname":"Yelyzavetivka",
    "gn:country_code":"UA",
    "gn:dem":189,
    "gn:feature_class":"P",
    "gn:feature_code":"PPL",
    "gn:name":"Yelyzavetivka",
    "gn:population":0,
    "gn:timezone":"Europe/Kiev",
    "iso:country":"UA",
    "name:ukr_x_preferred":[
        "Yelyzavetivka"
    ],
    "name:ukr_x_variant":[
        "\u0404\u043b\u0438\u0437\u0430\u0432\u0435\u0442\u0456\u0432\u043a\u0430"
    ],
    "name:und_x_variant":[
        "Yelizavetovka"
    ],
    "wof:name":"Yelyzavetivka",
    "wof:placetype":"locality"
},
  "geometry": {"coordinates":[36.85174,48.77571],"type":"Point"}
}