{
  "type": "Feature",
  "properties": {
    "gn:admin1_code":"7.0",
    "gn:asciiname":"Luchky",
    "gn:country_code":"UA",
    "gn:dem":191,
    "gn:feature_class":"P",
    "gn:feature_code":"PPL",
    "gn:name":"Luchky",
    "gn:population":0,
    "gn:timezone":"Europe/Kiev",
    "iso:country":"UA",
    "name:ukr_x_preferred":[
        "Luchky"
    ],
    "name:ukr_x_variant":[
        "\u041b\u0443\u0447\u043a\u0438"
    ],
    "wof:name":"Luchky",
    "wof:placetype":"locality"
},
  "geometry": {"coordinates":[35.16149,50.14365],"type":"Point"}
}