{
  "type": "Feature",
  "properties": {
    "gn:admin1_code":"4.0",
    "gn:asciiname":"Rakshivka",
    "gn:country_code":"UA",
    "gn:dem":88,
    "gn:feature_class":"P",
    "gn:feature_code":"PPL",
    "gn:name":"Rakshivka",
    "gn:population":0,
    "gn:timezone":"Europe/Kiev",
    "iso:country":"UA",
    "name:ukr_x_preferred":[
        "Rakshivka"
    ],
    "name:ukr_x_variant":[
        "\u0420\u0430\u043a\u0448\u0456\u0432\u043a\u0430"
    ],
    "wof:name":"Rakshivka",
    "wof:placetype":"locality"
},
  "geometry": {"coordinates":[35.10733,48.32673],"type":"Point"}
}