{
  "type": "Feature",
  "properties": {
    "gn:admin1_code":"22.0",
    "gn:asciiname":"Zlochuvka",
    "gn:country_code":"UA",
    "gn:dem":340,
    "gn:feature_class":"P",
    "gn:feature_code":"PPL",
    "gn:name":"Zlochuvka",
    "gn:population":0,
    "gn:timezone":"Europe/Kiev",
    "iso:country":"UA",
    "wof:name":"Zlochuvka",
    "wof:placetype":"locality"
},
  "geometry": {"coordinates":[25.21667,49.56667],"type":"Point"}
}