{
  "type": "Feature",
  "properties": {
    "gn:admin1_code":"18.0",
    "gn:asciiname":"Reshetniki",
    "gn:country_code":"UA",
    "gn:dem":88,
    "gn:feature_class":"P",
    "gn:feature_code":"PPL",
    "gn:name":"Resh\u00ebtniki",
    "gn:population":0,
    "gn:timezone":"Europe/Kiev",
    "iso:country":"UA",
    "name:eng_x_preferred":[
        "Resh\u00ebtniki"
    ],
    "name:rus_x_preferred":[
        "\u0420\u0435\u0448\u0435\u0442\u043d\u0438\u043a\u0438"
    ],
    "name:und_x_variant":[
        "Staryye Senzhary",
        "Resh\u00ebtniki"
    ],
    "wof:name":"Reshetniki",
    "wof:placetype":"locality"
},
  "geometry": {"coordinates":[34.45305,49.42516],"type":"Point"}
}