{
  "type": "Feature",
  "properties": {
    "gn:admin1_code":"9.0",
    "gn:asciiname":"Dzelentsy",
    "gn:country_code":"UA",
    "gn:dem":333,
    "gn:feature_class":"P",
    "gn:feature_code":"PPL",
    "gn:name":"Dzelentsy",
    "gn:population":0,
    "gn:timezone":"Europe/Kiev",
    "iso:country":"UA",
    "name:und_x_variant":[
        "Dzelinche",
        "Dzelentsy"
    ],
    "wof:name":"Dzelentsy",
    "wof:placetype":"locality"
},
  "geometry": {"coordinates":[26.61667000000001,49.45603],"type":"Point"}
}