{
  "type": "Feature",
  "properties": {
    "gn:country":"UA",
    "gn:fcode":"PPL",
    "gn:population":1541,
    "iso:country":"UA",
    "name:eng_x_preferred":[
        "Molodizhne"
    ],
    "name:rus_x_preferred":[
        "\u041c\u043e\u043b\u043e\u0434\u0435\u0436\u043d\u043e\u0435"
    ],
    "name:rus_x_variant":[
        "\u041c\u043e\u043b\u043e\u0434\u0456\u0436\u043d\u0435"
    ],
    "name:ukr_x_preferred":[
        "\u041c\u043e\u043b\u043e\u0434\u0456\u0436\u043d\u0435"
    ],
    "name:und_x_variant":[
        "Molod\u00ebzhnoye"
    ],
    "qs_pg:aaroncc":"UA",
    "qs_pg:gn_country":"UA",
    "qs_pg:gn_fcode":"PPL",
    "qs_pg:gn_pop":1541,
    "qs_pg:name":"Molodizhne",
    "qs_pg:photos_9r":0,
    "qs_pg:photos_sr":0,
    "qs_pg:pop_sr":3,
    "qs_pg:qs_pg_placetype":"locality",
    "wof:name":"Molodizhne",
    "wof:placetype":"locality",
    "wof:population":1541
},
  "geometry": {"coordinates":[32.66015,48.17732],"type":"Point"}
}