{
  "type": "Feature",
  "properties": {
    "gn:admin1_code":"13.0",
    "gn:asciiname":"Gayvoron",
    "gn:country_code":"UA",
    "gn:dem":178,
    "gn:feature_class":"P",
    "gn:feature_code":"PPL",
    "gn:name":"Gayvoron",
    "gn:population":0,
    "gn:timezone":"Europe/Kiev",
    "iso:country":"UA",
    "wof:name":"Gayvoron",
    "wof:placetype":"locality"
},
  "geometry": {"coordinates":[29.83323,49.5739],"type":"Point"}
}