{
  "type": "Feature",
  "properties": {
    "gn:admin1_code":"26.0",
    "gn:asciiname":"Burlats'ke",
    "gn:country_code":"UA",
    "gn:dem":162,
    "gn:feature_class":"P",
    "gn:feature_code":"PPL",
    "gn:name":"Burlats\u2019ke",
    "gn:population":0,
    "gn:timezone":"Europe/Zaporozhye",
    "iso:country":"UA",
    "name:ukr_x_preferred":[
        "Burlats\u2019ke"
    ],
    "name:ukr_x_variant":[
        "\u0411\u0443\u0440\u043b\u0430\u0446\u044c\u043a\u0435"
    ],
    "name:und_x_variant":[
        "Burlatskiy"
    ],
    "wof:name":"Burlats'ke",
    "wof:placetype":"locality"
},
  "geometry": {"coordinates":[36.61666,47.57544],"type":"Point"}
}