{
  "type": "Feature",
  "properties": {
    "gn:admin1_code":"18.0",
    "gn:asciiname":"Yehorivka",
    "gn:country_code":"UA",
    "gn:dem":103,
    "gn:feature_class":"P",
    "gn:feature_code":"PPL",
    "gn:name":"Yehorivka",
    "gn:population":0,
    "gn:timezone":"Europe/Kiev",
    "iso:country":"UA",
    "name:ukr_x_preferred":[
        "Yehorivka"
    ],
    "name:ukr_x_variant":[
        "\u0404\u0433\u043e\u0440\u0456\u0432\u043a\u0430"
    ],
    "wof:name":"Yehorivka",
    "wof:placetype":"locality"
},
  "geometry": {"coordinates":[33.20144000000001,49.5537],"type":"Point"}
}