{
  "type": "Feature",
  "properties": {
    "gn:gn_country":"UA",
    "gn:gn_fcode":"PPL",
    "gn:gn_pop":6894,
    "gn:population":6894,
    "iso:country":"UA",
    "name:eng_x_preferred":[
        "Peresichna"
    ],
    "name:rus_x_preferred":[
        "\u041f\u0435\u0440\u0435\u0441\u0435\u0447\u043d\u0430\u044f"
    ],
    "name:ukr_x_preferred":[
        "\u041f\u0435\u0440\u0435\u0441\u0456\u0447\u043d\u0430"
    ],
    "name:unk_x_variant":[
        "Peresechnoye"
    ],
    "qs_pg:aaroncc":"UA",
    "qs_pg:gn_country":"UA",
    "qs_pg:gn_fcode":"PPL",
    "qs_pg:gn_pop":6894,
    "qs_pg:name":"Peresechnaya",
    "qs_pg:name_adm0":"Ukraine",
    "qs_pg:name_adm1":"Kharkivs\u00b4ka Oblast\u00b4",
    "qs_pg:photos_9r":0,
    "qs_pg:photos_sr":0,
    "qs_pg:pop_sr":5,
    "qs_pg:qs_pg_placetype":"locality",
    "qs_pg:qs_pg_placetype_gp":"Town",
    "qs_pg:woe_adm0":23424976,
    "woe:adm0_id":23424976,
    "woe:name_adm0":"Ukraine",
    "woe:name_adm1":"Kharkivs\u00b4ka Oblast\u00b4",
    "woe:placetype":"Town",
    "wof:name":"Peresechnaya",
    "wof:placetype":"locality",
    "wof:population":6894
},
  "geometry": {"coordinates":[35.98259,50.02413],"type":"Point"}
}