{
  "type": "Feature",
  "properties": {
    "gn:admin1_code":"11.0",
    "gn:admin2_code":"693058",
    "gn:admin3_code":"11153123.0",
    "gn:asciiname":"Shakhtino",
    "gn:country_code":"UA",
    "gn:dem":37,
    "gn:elevation":"38.0",
    "gn:feature_class":"P",
    "gn:feature_code":"PPL",
    "gn:name":"Shakhtino",
    "gn:population":463,
    "gn:timezone":"Europe/Simferopol",
    "iso:country":"UA",
    "name:crh_x_historical":[
        "Aq K\u00f6bek"
    ],
    "name:crh_x_preferred":[
        "Aq K\u00f6bek"
    ],
    "name:eng_x_preferred":[
        "Shakhtino"
    ],
    "name:rus_x_historical":[
        "\u0410\u043a-\u041a\u043e\u0431\u0435\u0301\u043a"
    ],
    "name:rus_x_preferred":[
        "\u0428\u0430\u0445\u0442\u0438\u043d\u043e"
    ],
    "name:rus_x_variant":[
        "\u0410\u043a-\u041a\u043e\u0431\u0435\u0301\u043a"
    ],
    "name:ukr_x_preferred":[
        "\u0428\u0430\u0445\u0442\u0438\u043d\u0435"
    ],
    "wof:name":"Shakhtino",
    "wof:placetype":"locality",
    "wof:population":463
},
  "geometry": {"coordinates":[35.02385,45.2533],"type":"Point"}
}