{
  "type": "Feature",
  "properties": {
    "gn:admin1_code":"15.0",
    "gn:asciiname":"Mikolayuv",
    "gn:cc2":"UA",
    "gn:country_code":"UA",
    "gn:dem":195,
    "gn:feature_class":"P",
    "gn:feature_code":"PPL",
    "gn:name":"Mikolayuv",
    "gn:population":0,
    "gn:timezone":"Europe/Kiev",
    "iso:country":"UA",
    "name:und_x_variant":[
        "Miko\u0142aj\u00f3w",
        "Mikolayuv"
    ],
    "wof:name":"Mikolayuv",
    "wof:placetype":"locality"
},
  "geometry": {"coordinates":[24.98333,50.35],"type":"Point"}
}