{
  "type": "Feature",
  "properties": {
    "gn:admin1_code":"27.0",
    "gn:asciiname":"Mezhyrichka",
    "gn:country_code":"UA",
    "gn:dem":151,
    "gn:feature_class":"P",
    "gn:feature_code":"PPL",
    "gn:name":"Mezhyrichka",
    "gn:population":0,
    "gn:timezone":"Europe/Kiev",
    "iso:country":"UA",
    "name:ukr_x_preferred":[
        "Mezhyrichka"
    ],
    "name:ukr_x_variant":[
        "\u041c\u0435\u0436\u0438\u0440\u0456\u0447\u043a\u0430"
    ],
    "name:und_x_variant":[
        "Mezhirichka",
        "Mezhirechka"
    ],
    "wof:name":"Mezhyrichka",
    "wof:placetype":"locality"
},
  "geometry": {"coordinates":[28.77256,51.07494000000001],"type":"Point"}
}