{
  "type": "Feature",
  "properties": {
    "gn:admin1_code":"18.0",
    "gn:asciiname":"Vil'shanka",
    "gn:country_code":"UA",
    "gn:dem":111,
    "gn:feature_class":"P",
    "gn:feature_code":"PPL",
    "gn:name":"Vil\u2019shanka",
    "gn:population":0,
    "gn:timezone":"Europe/Kiev",
    "iso:country":"UA",
    "name:ukr_x_preferred":[
        "\u0412\u0456\u043b\u044c\u0448\u0430\u043d\u043a\u0430"
    ],
    "name:und_x_variant":[
        "Vil\u2019shanka",
        "Ol\u2019shanka"
    ],
    "wof:name":"Vil'shanka",
    "wof:placetype":"locality"
},
  "geometry": {"coordinates":[33.02296,50.04146],"type":"Point"}
}