{
  "type": "Feature",
  "properties": {
    "gn:admin1_code":"21.0",
    "gn:asciiname":"Bilovyshneve",
    "gn:country_code":"UA",
    "gn:dem":137,
    "gn:feature_class":"P",
    "gn:feature_code":"PPL",
    "gn:name":"Bilovyshneve",
    "gn:population":0,
    "gn:timezone":"Europe/Kiev",
    "iso:country":"UA",
    "name:ukr_x_preferred":[
        "Bilovyshneve"
    ],
    "name:ukr_x_variant":[
        "\u0411\u0456\u043b\u043e\u0432\u0438\u0448\u043d\u0435\u0432\u0435"
    ],
    "name:und_x_variant":[
        "Belovishnevoye"
    ],
    "wof:name":"Bilovyshneve",
    "wof:placetype":"locality"
},
  "geometry": {"coordinates":[34.35006,51.09197],"type":"Point"}
}