{
  "type": "Feature",
  "properties": {
    "gn:admin1_code":"27.0",
    "gn:asciiname":"Stara Radcha",
    "gn:country_code":"UA",
    "gn:dem":142,
    "gn:feature_class":"P",
    "gn:feature_code":"PPL",
    "gn:name":"Stara Radcha",
    "gn:population":0,
    "gn:timezone":"Europe/Kiev",
    "iso:country":"UA",
    "name:ukr_x_preferred":[
        "Stara Radcha"
    ],
    "name:ukr_x_variant":[
        "\u0421\u0442\u0430\u0440\u0430 \u0420\u0430\u0434\u0447\u0430"
    ],
    "name:und_x_variant":[
        "Staraya Radcha"
    ],
    "wof:name":"Stara Radcha",
    "wof:placetype":"locality"
},
  "geometry": {"coordinates":[29.2987,51.38146],"type":"Point"}
}