{
  "type": "Feature",
  "properties": {
    "gn:admin1_code":"17.0",
    "gn:asciiname":"Sadove",
    "gn:country_code":"UA",
    "gn:dem":114,
    "gn:feature_class":"P",
    "gn:feature_code":"PPL",
    "gn:name":"Sadove",
    "gn:population":0,
    "gn:timezone":"Europe/Kiev",
    "iso:country":"UA",
    "name:rus_x_preferred":[
        "\u0421\u0430\u0434\u043e\u0432\u0435"
    ],
    "name:ukr_x_preferred":[
        "\u0421\u0430\u0434\u043e\u0432\u0435"
    ],
    "name:ukr_x_variant":[
        "Sadove"
    ],
    "name:und_x_variant":[
        "Pos\u00eblok Sadovo",
        "Sadovoye",
        "Sadovo"
    ],
    "wof:name":"Sadove",
    "wof:placetype":"locality"
},
  "geometry": {"coordinates":[29.46505,47.32953],"type":"Point"}
}