{
  "type": "Feature",
  "properties": {
    "gn:admin1_code":"17.0",
    "gn:asciiname":"Stari Troyany",
    "gn:country_code":"UA",
    "gn:dem":52,
    "gn:feature_class":"P",
    "gn:feature_code":"PPL",
    "gn:name":"Stari Troyany",
    "gn:population":0,
    "gn:timezone":"Europe/Kiev",
    "iso:country":"UA",
    "name:ukr_x_preferred":[
        "Stari Troyany"
    ],
    "name:ukr_x_variant":[
        "\u0421\u0442\u0430\u0440\u0456 \u0422\u0440\u043e\u044f\u043d\u0438"
    ],
    "name:und_x_variant":[
        "Trayanu-Vek\u2019",
        "Staro-Trayany",
        "Traian",
        "Staryy Troyan",
        "Traianul-Vechiu",
        "Staro-Troyany",
        "Staryye Troyany"
    ],
    "wof:name":"Stari Troyany",
    "wof:placetype":"locality"
},
  "geometry": {"coordinates":[29.17007000000001,45.67584],"type":"Point"}
}