{
  "type": "Feature",
  "properties": {
    "gn:admin1_code":"7.0",
    "gn:asciiname":"Khatnye",
    "gn:country_code":"UA",
    "gn:dem":156,
    "gn:feature_class":"P",
    "gn:feature_code":"PPL",
    "gn:name":"Khatnye",
    "gn:population":0,
    "gn:timezone":"Europe/Kiev",
    "iso:country":"UA",
    "name:eng_x_preferred":[
        "Khatneye"
    ],
    "name:rus_x_preferred":[
        "\u0425\u0430\u0442\u043d\u0435\u0435"
    ],
    "name:rus_x_variant":[
        "\u0425\u0430\u0442\u043d\u043e\u0435"
    ],
    "name:ukr_x_preferred":[
        "Khatnye"
    ],
    "name:ukr_x_variant":[
        "\u0425\u0430\u0442\u043d\u0454"
    ],
    "name:und_x_variant":[
        "Khatnee",
        "Khatne",
        "Khatnoye"
    ],
    "wof:name":"Khatnye",
    "wof:placetype":"locality"
},
  "geometry": {"coordinates":[37.56545,50.12248],"type":"Point"}
}