{
  "type": "Feature",
  "properties": {
    "gn:admin1_code":"18.0",
    "gn:asciiname":"Mala Rudka",
    "gn:country_code":"UA",
    "gn:dem":146,
    "gn:feature_class":"P",
    "gn:feature_code":"PPL",
    "gn:name":"Mala Rudka",
    "gn:population":0,
    "gn:timezone":"Europe/Kiev",
    "iso:country":"UA",
    "name:ukr_x_preferred":[
        "Mala Rudka"
    ],
    "name:ukr_x_variant":[
        "\u041c\u0430\u043b\u0430 \u0420\u0443\u0434\u043a\u0430"
    ],
    "name:und_x_variant":[
        "Malaya Rudka"
    ],
    "wof:name":"Mala Rudka",
    "wof:placetype":"locality"
},
  "geometry": {"coordinates":[34.44586,49.73009],"type":"Point"}
}