{
  "type": "Feature",
  "properties": {
    "gn:admin1_code":"2.0",
    "gn:asciiname":"Chepeliv",
    "gn:country_code":"UA",
    "gn:dem":122,
    "gn:feature_class":"P",
    "gn:feature_code":"PPL",
    "gn:name":"Chepeliv",
    "gn:population":0,
    "gn:timezone":"Europe/Kiev",
    "iso:country":"UA",
    "name:ukr_x_preferred":[
        "Chepeliv"
    ],
    "name:ukr_x_variant":[
        "\u0427\u0435\u043f\u0435\u043b\u0456\u0432"
    ],
    "name:und_x_variant":[
        "Chepelev",
        "Chepelevka",
        "Chepel\u00ebvo"
    ],
    "wof:name":"Chepeliv",
    "wof:placetype":"locality"
},
  "geometry": {"coordinates":[32.07607,51.86911],"type":"Point"}
}