{
  "type": "Feature",
  "properties": {
    "iso:country":"UA",
    "name:ceb_x_preferred":[
        "Severinovca"
    ],
    "name:dan_x_preferred":[
        "Severinovca"
    ],
    "name:deu_x_preferred":[
        "Severinovca"
    ],
    "name:eng_x_preferred":[
        "Severinovca"
    ],
    "name:eus_x_preferred":[
        "Severinovca"
    ],
    "name:fra_x_preferred":[
        "Severinovca"
    ],
    "name:ita_x_preferred":[
        "Severinovca"
    ],
    "name:nld_x_preferred":[
        "Severinovca"
    ],
    "name:nno_x_preferred":[
        "Severinovca"
    ],
    "name:nob_x_preferred":[
        "Severinovca"
    ],
    "name:pol_x_preferred":[
        "\u041d\u043e\u0432\u043e\u044f\u0432\u043e\u0440\u0456\u0432\u0441\u044c\u043a\u0435"
    ],
    "name:pol_x_variant":[
        "Severinovca"
    ],
    "name:por_x_preferred":[
        "Severinovca"
    ],
    "name:ron_x_preferred":[
        "Severinovca"
    ],
    "name:rus_x_preferred":[
        "\u0421\u0435\u0432\u0435\u0440\u0438\u043d\u043e\u0432\u043a\u0430"
    ],
    "name:spa_x_preferred":[
        "Severinovca"
    ],
    "name:swe_x_preferred":[
        "Severinovca"
    ],
    "name:tur_x_preferred":[
        "Severinovca"
    ],
    "name:ukr_x_preferred":[
        "\u0421\u0435\u0432\u0435\u0440\u0438\u043d\u0456\u0432\u043a\u0430"
    ],
    "qs:a0":"\u0423\u043a\u0440\u0430\u0457\u043d\u0430",
    "qs:a1":"*\u0412\u0456\u043d\u043d\u0438\u0446\u044c\u043a\u0430",
    "qs:a1_alt":"Vinnyts'ka",
    "qs:a1r":"0",
    "qs:a2":"\u0416\u043c\u0435\u0440\u0438\u043d\u0441\u044c\u043a\u0438\u0439",
    "qs:a2_alt":"Zhmeryns'kyi",
    "qs:adm0":"\u0423\u043a\u0440\u0430\u0457\u043d\u0430",
    "qs:la_lc":"*",
    "qs:level":"locality",
    "qs:loc":"\u0421\u0435\u0432\u0435\u0440\u0438\u043d\u0456\u0432\u043a\u0430",
    "qs:loc_alt":"Severynivka",
    "qs:pop":0,
    "qs:type":"buffered point",
    "wd:wordcount":65,
    "wof:name":"\u0421\u0435\u0432\u0435\u0440\u0438\u043d\u0456\u0432\u043a\u0430",
    "wof:placetype":"locality"
},
  "geometry": {"coordinates":[27.955043,49.054304],"type":"Point"}
}