{
  "type": "Feature",
  "properties": {
    "iso:country":"UA",
    "name:chi_x_preferred":[
        "\u59c6\u6c99\u7d0d"
    ],
    "name:eng_x_preferred":[
        "Mshana"
    ],
    "name:pol_x_preferred":[
        "Mszana"
    ],
    "name:rum_x_preferred":[
        "M\u0219ana"
    ],
    "name:rus_x_preferred":[
        "\u041c\u0448\u0430\u043d\u0430"
    ],
    "name:ukr_x_preferred":[
        "\u041c\u0448\u0430\u043d\u0430"
    ],
    "qs:a0":"\u0423\u043a\u0440\u0430\u0457\u043d\u0430",
    "qs:a1":"*\u041b\u044c\u0432\u0456\u0432\u0441\u044c\u043a\u0430",
    "qs:a1_alt":"L'vivs'ka",
    "qs:a1r":"0",
    "qs:a2":"\u0413\u043e\u0440\u043e\u0434\u043e\u0446\u044c\u043a\u0438\u0439",
    "qs:a2_alt":"Horodots'kyi",
    "qs:adm0":"\u0423\u043a\u0440\u0430\u0457\u043d\u0430",
    "qs:la_lc":"*",
    "qs:level":"locality",
    "qs:loc":"\u041c\u0448\u0430\u043d\u0430",
    "qs:loc_alt":"Mshana",
    "qs:pop":0,
    "qs:type":"buffered point",
    "wd:wordcount":110,
    "wof:name":"\u041c\u0448\u0430\u043d\u0430",
    "wof:placetype":"locality"
},
  "geometry": {"coordinates":[23.795968,49.82974],"type":"Point"}
}