{
  "type": "Feature",
  "properties": {
    "gn:admin1_code":"21.0",
    "gn:asciiname":"Komarivka",
    "gn:country_code":"UA",
    "gn:dem":157,
    "gn:feature_class":"P",
    "gn:feature_code":"PPL",
    "gn:name":"Komarivka",
    "gn:population":0,
    "gn:timezone":"Europe/Kiev",
    "iso:country":"UA",
    "name:bel_x_preferred":[
        "\u041a\u0430\u043c\u0430\u0440\u043e\u045e\u043a\u0430"
    ],
    "name:deu_x_preferred":[
        "Komariwka"
    ],
    "name:hye_x_preferred":[
        "\u053f\u0578\u0574\u0561\u0580\u0578\u057e\u056f\u0561"
    ],
    "name:kaz_x_preferred":[
        "\u041a\u043e\u043c\u0430\u0440\u043e\u0432\u043a\u0430"
    ],
    "name:rus_x_preferred":[
        "\u041a\u043e\u043c\u0430\u0440\u043e\u0432\u043a\u0430"
    ],
    "name:tat_x_preferred":[
        "\u041a\u043e\u043c\u0430\u0440\u043e\u0432\u043a\u0430"
    ],
    "name:ukr_x_preferred":[
        "Komarivka"
    ],
    "name:ukr_x_variant":[
        "\u041a\u043e\u043c\u0430\u0440\u0456\u0432\u043a\u0430"
    ],
    "name:und_x_variant":[
        "Komarovka"
    ],
    "wof:name":"Komarivka",
    "wof:placetype":"locality"
},
  "geometry": {"coordinates":[34.2981,51.717],"type":"Point"}
}