{
  "type": "Feature",
  "properties": {
    "gn:admin1_code":"5.0",
    "gn:asciiname":"Prelestne",
    "gn:country_code":"UA",
    "gn:dem":80,
    "gn:feature_class":"P",
    "gn:feature_code":"PPL",
    "gn:name":"Prelestne",
    "gn:population":0,
    "gn:timezone":"Europe/Kiev",
    "iso:country":"UA",
    "name:eng_x_preferred":[
        "Prelestnoye"
    ],
    "name:rus_x_preferred":[
        "\u041f\u0440\u0435\u043b\u0435\u0441\u0442\u043d\u043e\u0435"
    ],
    "name:ukr_x_preferred":[
        "Prelestne"
    ],
    "name:ukr_x_variant":[
        "\u041f\u0440\u0435\u043b\u0435\u0441\u0442\u043d\u0435"
    ],
    "name:und_x_variant":[
        "Bantyshevo",
        "Prelestnoye"
    ],
    "wof:name":"Prelestne",
    "wof:placetype":"locality"
},
  "geometry": {"coordinates":[37.29526,48.83281],"type":"Point"}
}