{
  "type": "Feature",
  "properties": {
    "gn:admin1_code":"26.0",
    "gn:admin2_code":"691467",
    "gn:asciiname":"Mays'ke",
    "gn:country_code":"UA",
    "gn:dem":64,
    "gn:feature_class":"P",
    "gn:feature_code":"PPL",
    "gn:name":"Mays'ke",
    "gn:population":0,
    "gn:timezone":"Europe/Zaporozhye",
    "iso:country":"UA",
    "name:rus_x_preferred":[
        "Mayskoye"
    ],
    "name:rus_x_variant":[
        "\u041c\u0430\u0439\u0441\u043a\u043e\u0435"
    ],
    "name:ukr_x_preferred":[
        "Maiske"
    ],
    "name:ukr_x_variant":[
        "Mays'ke",
        "Majs'ke",
        "\u041c\u0430\u0439\u0441\u044c\u043a\u0435"
    ],
    "name:und_x_variant":[
        "Libenau"
    ],
    "wof:name":"Mays'ke",
    "wof:placetype":"locality"
},
  "geometry": {"coordinates":[35.88333,47.25],"type":"Point"}
}