{
  "type": "Feature",
  "properties": {
    "gn:admin1_code":"16.0",
    "gn:asciiname":"Andriyivka",
    "gn:cc2":"UA",
    "gn:country_code":"UA",
    "gn:dem":4,
    "gn:feature_class":"P",
    "gn:feature_code":"PPL",
    "gn:name":"Andriyivka",
    "gn:population":0,
    "gn:timezone":"Europe/Kiev",
    "iso:country":"UA",
    "name:und_x_variant":[
        "Andreevka",
        "Andriyivka"
    ],
    "wof:name":"Andriyivka",
    "wof:placetype":"locality"
},
  "geometry": {"coordinates":[31.49167000000001,46.75],"type":"Point"}
}