{
  "type": "Feature",
  "properties": {
    "iso:country":"UA",
    "name:deu_x_preferred":[
        "Djakowe"
    ],
    "name:eng_x_preferred":[
        "Dyakove"
    ],
    "name:eng_x_variant":[
        "Diakove"
    ],
    "name:est_x_preferred":[
        "Djakove"
    ],
    "name:lav_x_preferred":[
        "Djakove"
    ],
    "name:nld_x_preferred":[
        "Deakove"
    ],
    "name:ron_x_preferred":[
        "Deakove"
    ],
    "name:rus_x_preferred":[
        "\u0414\u044c\u044f\u043a\u043e\u0432\u043e"
    ],
    "name:ukr_x_preferred":[
        "\u0414\u044f\u043a\u043e\u0432\u0435"
    ],
    "name:und_x_variant":[
        "D\u2019yakovo"
    ],
    "name:zho_x_preferred":[
        "\u5b63\u4e9e\u79d1\u97cb"
    ],
    "qs:a0":"\u0423\u043a\u0440\u0430\u0457\u043d\u0430",
    "qs:a1":"*\u041b\u0443\u0433\u0430\u043d\u0441\u044c\u043a\u0430",
    "qs:a1_alt":"Luhans'ka",
    "qs:a1r":"0",
    "qs:a2":"\u0410\u043d\u0442\u0440\u0430\u0446\u0438\u0442\u0456\u0432\u0441\u044c\u043a\u0438\u0439",
    "qs:a2_alt":"Antratsytivs'kyi",
    "qs:adm0":"\u0423\u043a\u0440\u0430\u0457\u043d\u0430",
    "qs:la_lc":"*",
    "qs:level":"locality",
    "qs:loc":"\u0414\u044f\u043a\u043e\u0432\u0435",
    "qs:loc_alt":"Diakove",
    "qs:pop":0,
    "qs:type":"buffered point",
    "wof:name":"\u0414\u044f\u043a\u043e\u0432\u0435",
    "wof:placetype":"locality"
},
  "geometry": {"coordinates":[39.134663,47.941266],"type":"Point"}
}