{
  "type": "Feature",
  "properties": {
    "gn:admin1_code":"5.0",
    "gn:admin2_code":"699674",
    "gn:asciiname":"Oleksandrivs'ke",
    "gn:country_code":"UA",
    "gn:dem":13,
    "gn:feature_class":"P",
    "gn:feature_code":"PPL",
    "gn:name":"Oleksandrivs'ke",
    "gn:population":0,
    "gn:timezone":"Europe/Kiev",
    "iso:country":"UA",
    "name:bel_x_historical":[
        "\u0420\u043e\u0437\u044b \u041b\u044e\u043a\u0441\u044d\u043c\u0431\u0443\u0440\u0433"
    ],
    "name:bel_x_preferred":[
        "\u0410\u043b\u044f\u043a\u0441\u0430\u043d\u0434\u0440\u0430\u045e\u0441\u043a\u0430\u0435"
    ],
    "name:bel_x_variant":[
        "\u0420\u043e\u0437\u044b \u041b\u044e\u043a\u0441\u044d\u043c\u0431\u0443\u0440\u0433"
    ],
    "name:deu_x_preferred":[
        "Olexandriwske"
    ],
    "name:deu_x_variant":[
        "Olexandriwsske"
    ],
    "name:eng_x_historical":[
        "Rozy Lyuksemburh"
    ],
    "name:eng_x_preferred":[
        "Rozy Lyuksemburh"
    ],
    "name:hye_x_colloquial":[
        "\u0531\u056c\u0565\u0584\u057d\u0561\u0576\u0564\u0580\u0578\u057e\u057d\u056f\u0578\u0565"
    ],
    "name:hye_x_historical":[
        "\u054c\u0578\u0566\u056b \u053c\u0575\u0578\u0582\u056f\u057d\u0565\u0574\u0562\u0578\u0582\u0580\u0563"
    ],
    "name:hye_x_preferred":[
        "\u054c\u0578\u0566\u056b \u053c\u0575\u0578\u0582\u056f\u057d\u0565\u0574\u0562\u0578\u0582\u0580\u0563"
    ],
    "name:hye_x_variant":[
        "\u0548\u056c\u0565\u056f\u057d\u0561\u0576\u0564\u0580\u056b\u057e\u057d\u056f\u0565",
        "\u0531\u056c\u0565\u0584\u057d\u0561\u0576\u0564\u0580\u0578\u057e\u057d\u056f\u0578\u0565"
    ],
    "name:rus_x_historical":[
        "Rozy Lyuksemburg",
        "\u0420\u043e\u0437\u044b \u041b\u044e\u043a\u0441\u0435\u043c\u0431\u0443\u0440\u0433"
    ],
    "name:rus_x_preferred":[
        "Rozy Lyuksemburg"
    ],
    "name:rus_x_variant":[
        "\u0420\u043e\u0437\u044b \u041b\u044e\u043a\u0441\u0435\u043c\u0431\u0443\u0440\u0433",
        "\u0410\u043b\u0435\u043a\u0441\u0430\u043d\u0434\u0440\u043e\u0432\u0441\u043a\u043e\u0435"
    ],
    "name:ukr_x_historical":[
        "\u0420\u043e\u0437\u0438 \u041b\u044e\u043a\u0441\u0435\u043c\u0431\u0443\u0440\u0433"
    ],
    "name:ukr_x_preferred":[
        "\u041e\u043b\u0435\u043a\u0441\u0430\u043d\u0434\u0440\u0456\u0432\u0441\u044c\u043a\u0435"
    ],
    "name:ukr_x_variant":[
        "\u0420\u043e\u0437\u0438 \u041b\u044e\u043a\u0441\u0435\u043c\u0431\u0443\u0440\u0433"
    ],
    "name:und_x_variant":[
        "Rozy Liuksemburh",
        "Oleksandriwske",
        "Olekssandriwsske"
    ],
    "name:zho_x_preferred":[
        "\u5967\u5217\u514b\u6851\u5fb7\u91cc\u592b\u897f\u514b"
    ],
    "wof:name":"Oleksandrivs'ke",
    "wof:placetype":"locality"
},
  "geometry": {"coordinates":[38.11126,47.20674],"type":"Point"}
}