{
  "type": "Feature",
  "properties": {
    "iso:country":"UA",
    "name:eng_x_preferred":[
        "Leninskoye"
    ],
    "name:rus_x_historical":[
        "\u041f\u0435\u0442\u0440\u043e\u0301\u0432\u0441\u043a\u043e\u0435"
    ],
    "name:rus_x_preferred":[
        "\u041f\u0435\u0442\u0440\u043e\u0301\u0432\u0441\u043a\u043e\u0435"
    ],
    "name:rus_x_variant":[
        "\u041b\u0435\u043d\u0438\u043d\u0441\u043a\u043e\u0435"
    ],
    "name:ukr_x_preferred":[
        "\u041b\u0435\u043d\u0456\u043d\u0441\u044c\u043a\u0435"
    ],
    "qs:a0":"\u0423\u043a\u0440\u0430\u0457\u043d\u0430",
    "qs:a1":"*\u041a\u0440\u0438\u043c",
    "qs:a1_alt":"Krym",
    "qs:a1r":"0",
    "qs:a2":"\u041b\u0435\u043d\u0456\u043d\u0441\u044c\u043a\u0438\u0439",
    "qs:a2_alt":"Lenins'kyi",
    "qs:adm0":"\u0423\u043a\u0440\u0430\u0457\u043d\u0430",
    "qs:la_lc":"*",
    "qs:level":"locality",
    "qs:loc":"\u041b\u0435\u043d\u0456\u043d\u0441\u044c\u043a\u0435",
    "qs:loc_alt":"Lenins'ke",
    "qs:pop":0,
    "qs:type":"buffered point",
    "wof:name":"\u041b\u0435\u043d\u0456\u043d\u0441\u044c\u043a\u0435",
    "wof:placetype":"locality"
},
  "geometry": {"coordinates":[35.92497,45.248051],"type":"Point"}
}