{
  "type": "Feature",
  "properties": {
    "gn:admin1_code":"5.0",
    "gn:asciiname":"Manuylivka",
    "gn:country_code":"UA",
    "gn:dem":106,
    "gn:feature_class":"P",
    "gn:feature_code":"PPL",
    "gn:name":"Manuylivka",
    "gn:population":0,
    "gn:timezone":"Europe/Kiev",
    "iso:country":"UA",
    "name:ukr_x_preferred":[
        "\u041c\u0430\u043d\u0443\u0439\u043b\u0456\u0432\u043a\u0430"
    ],
    "name:und_x_variant":[
        "Manuylovo",
        "Manuylovka",
        "Manuilovo",
        "Manuylivka"
    ],
    "wof:name":"Manuylivka",
    "wof:placetype":"locality"
},
  "geometry": {"coordinates":[38.67074,47.96448],"type":"Point"}
}