{
  "type": "Feature",
  "properties": {
    "gn:admin1_code":"17.0",
    "gn:asciiname":"Yakova",
    "gn:country_code":"UA",
    "gn:dem":78,
    "gn:feature_class":"P",
    "gn:feature_code":"PPL",
    "gn:name":"Yakova",
    "gn:population":0,
    "gn:timezone":"Europe/Kiev",
    "iso:country":"UA",
    "name:ukr_x_preferred":[
        "\u042f\u043a\u043e\u0432\u0430"
    ],
    "name:und_x_variant":[
        "Khutor Yakova",
        "Yakova"
    ],
    "wof:name":"Yakova",
    "wof:placetype":"locality"
},
  "geometry": {"coordinates":[30.76849,46.88802],"type":"Point"}
}