{
  "type": "Feature",
  "properties": {
    "gn:admin1_code":"5.0",
    "gn:asciiname":"Stavky",
    "gn:country_code":"UA",
    "gn:dem":175,
    "gn:feature_class":"P",
    "gn:feature_code":"PPL",
    "gn:name":"Stavky",
    "gn:population":0,
    "gn:timezone":"Europe/Kiev",
    "iso:country":"UA",
    "name:ukr_x_preferred":[
        "Stavky"
    ],
    "name:ukr_x_variant":[
        "\u0421\u0442\u0430\u0432\u043a\u0438"
    ],
    "wof:name":"Stavky",
    "wof:placetype":"locality"
},
  "geometry": {"coordinates":[37.93917,48.24951],"type":"Point"}
}