{
  "type": "Feature",
  "properties": {
    "gn:admin1_code":"9.0",
    "gn:asciiname":"Malyshivka",
    "gn:country_code":"UA",
    "gn:dem":294,
    "gn:feature_class":"P",
    "gn:feature_code":"PPL",
    "gn:name":"Malyshivka",
    "gn:population":0,
    "gn:timezone":"Europe/Kiev",
    "iso:country":"UA",
    "name:ukr_x_preferred":[
        "Malyshivka"
    ],
    "name:ukr_x_variant":[
        "\u041c\u0430\u043b\u0438\u0448\u0456\u0432\u043a\u0430"
    ],
    "name:und_x_variant":[
        "Malysheyevka",
        "Malyshevka"
    ],
    "wof:name":"Malyshivka",
    "wof:placetype":"locality"
},
  "geometry": {"coordinates":[27.42374,49.82738],"type":"Point"}
}