{
  "type": "Feature",
  "properties": {
    "gn:admin1_code":"5.0",
    "gn:asciiname":"Ocheretyne",
    "gn:country_code":"UA",
    "gn:dem":178,
    "gn:feature_class":"P",
    "gn:feature_code":"PPL",
    "gn:name":"Ocheretyne",
    "gn:population":0,
    "gn:timezone":"Europe/Kiev",
    "iso:country":"UA",
    "name:ukr_x_preferred":[
        "Ocheretyne"
    ],
    "name:ukr_x_variant":[
        "\u041e\u0447\u0435\u0440\u0435\u0442\u0438\u043d\u0435"
    ],
    "name:und_x_variant":[
        "Ocheretino"
    ],
    "wof:name":"Ocheretyne",
    "wof:placetype":"locality"
},
  "geometry": {"coordinates":[37.12138,48.74202],"type":"Point"}
}