{
  "type": "Feature",
  "properties": {
    "gn:population":7513,
    "iso:country":"UA",
    "name:bel_x_preferred":[
        "\u041d\u0430\u0432\u0430 \u041f\u0440\u0430\u0433\u0430"
    ],
    "name:ceb_x_preferred":[
        "Nova Praha"
    ],
    "name:ces_x_preferred":[
        "Nowa Praha"
    ],
    "name:crh_x_preferred":[
        "Nova Praga"
    ],
    "name:deu_x_preferred":[
        "Nowa Praha"
    ],
    "name:eng_x_preferred":[
        "Nova Praha"
    ],
    "name:hye_x_preferred":[
        "\u0546\u0578\u057e\u0561\u0575\u0561 \u054a\u0580\u0561\u0563\u0561"
    ],
    "name:ron_x_preferred":[
        "Nova Praha"
    ],
    "name:rus_x_preferred":[
        "\u041d\u043e\u0432.\u041f\u0440\u0430\u0433\u0430"
    ],
    "name:rus_x_variant":[
        "\u041d\u043e\u0432\u0430 \u041f\u0440\u0430\u0433\u0430",
        "\u041d\u043e\u0432\u0430\u044f \u041f\u0440\u0430\u0433\u0430"
    ],
    "name:ukr_x_preferred":[
        "\u041d\u043e\u0432\u0430 \u041f\u0440\u0430\u0433\u0430"
    ],
    "name:und_x_variant":[
        "Novaya Praga"
    ],
    "name:zho_x_preferred":[
        "\u65b0\u666e\u62c9\u52a0"
    ],
    "qs:a0":"\u0423\u043a\u0440\u0430\u0457\u043d\u0430",
    "qs:a1":"*\u041a\u0456\u0440\u043e\u0432\u043e\u0433\u0440\u0430\u0434\u0441\u044c\u043a\u0430",
    "qs:a1_alt":"Kirovohrads'ka",
    "qs:a1r":"0",
    "qs:a2":"\u041e\u043b\u0435\u043a\u0441\u0430\u043d\u0434\u0440\u0456\u0439\u0441\u044c\u043a\u0438\u0439",
    "qs:a2_alt":"Oleksandriis'kyi",
    "qs:adm0":"\u0423\u043a\u0440\u0430\u0457\u043d\u0430",
    "qs:la_lc":"*",
    "qs:level":"locality",
    "qs:loc":"\u041d\u043e\u0432\u0430 \u041f\u0440\u0430\u0433\u0430",
    "qs:loc_alt":"Nova Praha",
    "qs:pop":0,
    "qs:type":"buffered point",
    "wof:name":"\u041d\u043e\u0432\u0430 \u041f\u0440\u0430\u0433\u0430",
    "wof:placetype":"locality",
    "wof:population":7513
},
  "geometry": {"coordinates":[32.896757,48.542519],"type":"Point"}
}