{
  "type": "Feature",
  "properties": {
    "gn:admin1_code":"6.0",
    "gn:asciiname":"Banya",
    "gn:country_code":"UA",
    "gn:dem":394,
    "gn:feature_class":"P",
    "gn:feature_code":"PPL",
    "gn:name":"Banya",
    "gn:population":0,
    "gn:timezone":"Europe/Kiev",
    "iso:country":"UA",
    "name:aze_x_preferred":[
        "Banya"
    ],
    "name:bel_x_preferred":[
        "\u0411\u0430\u043d\u044f"
    ],
    "name:bul_x_preferred":[
        "\u0411\u0430\u043d\u044f"
    ],
    "name:ceb_x_preferred":[
        "Banya"
    ],
    "name:chv_x_preferred":[
        "\u041c\u0443\u043d\u0447\u0430"
    ],
    "name:fra_x_preferred":[
        "Banya"
    ],
    "name:kor_x_preferred":[
        "\ubc18\uc57c"
    ],
    "name:ron_x_preferred":[
        "Banea"
    ],
    "name:rus_x_preferred":[
        "\u0411\u0430\u043d\u044f"
    ],
    "name:spa_x_preferred":[
        "Banya"
    ],
    "name:swe_x_preferred":[
        "Banya"
    ],
    "name:tur_x_preferred":[
        "Banya"
    ],
    "name:ukr_x_preferred":[
        "\u0411\u0430\u043d\u044f"
    ],
    "wof:name":"Banya",
    "wof:placetype":"locality"
},
  "geometry": {"coordinates":[24.55,48.68333],"type":"Point"}
}