{
  "type": "Feature",
  "properties": {
    "gn:admin1_code":"11.0",
    "gn:admin2_code":"712968",
    "gn:admin3_code":"11152817.0",
    "gn:asciiname":"Bol'shoye Sadovoye",
    "gn:country_code":"UA",
    "gn:dem":134,
    "gn:elevation":"255.0",
    "gn:feature_class":"P",
    "gn:feature_code":"PPL",
    "gn:name":"Bol\u2019shoye Sadovoye",
    "gn:population":397,
    "gn:timezone":"Europe/Simferopol",
    "iso:country":"UA",
    "name:eng_x_preferred":[
        "Bol\u2019shoye Sadovoye"
    ],
    "name:rus_x_historical":[
        "\u0422\u0430\u0448-\u0411\u0430\u0441\u0442\u044b\u0301"
    ],
    "name:rus_x_preferred":[
        "\u0411\u043e\u043b\u044c\u0448\u043e\u0435 \u0421\u0430\u0434\u043e\u0432\u043e\u0435"
    ],
    "name:rus_x_variant":[
        "\u0422\u0430\u0448-\u0411\u0430\u0441\u0442\u044b\u0301"
    ],
    "name:ukr_x_preferred":[
        "\u0412\u0435\u043b\u0438\u043a\u0435 \u0421\u0430\u0434\u043e\u0432\u0435"
    ],
    "wof:name":"Bol'shoye Sadovoye",
    "wof:placetype":"locality",
    "wof:population":397
},
  "geometry": {"coordinates":[33.82854,44.63948],"type":"Point"}
}