{
  "type": "Feature",
  "properties": {
    "gn:admin1_code":"24.0",
    "gn:asciiname":"Raymisto",
    "gn:country_code":"UA",
    "gn:dem":185,
    "gn:feature_class":"P",
    "gn:feature_code":"PPL",
    "gn:name":"Raymisto",
    "gn:population":0,
    "gn:timezone":"Europe/Kiev",
    "iso:country":"UA",
    "name:ukr_x_preferred":[
        "Raymisto"
    ],
    "name:ukr_x_variant":[
        "\u0420\u0430\u0439\u043c\u0456\u0441\u0442\u043e"
    ],
    "wof:name":"Raymisto",
    "wof:placetype":"locality"
},
  "geometry": {"coordinates":[24.97063,51.00367],"type":"Point"}
}