{
  "type": "Feature",
  "properties": {
    "gn:admin1_code":"17.0",
    "gn:asciiname":"Hirzhove",
    "gn:country_code":"UA",
    "gn:dem":54,
    "gn:feature_class":"P",
    "gn:feature_code":"PPL",
    "gn:name":"Hirzhove",
    "gn:population":0,
    "gn:timezone":"Europe/Kiev",
    "iso:country":"UA",
    "name:ukr_x_preferred":[
        "Hirzhove"
    ],
    "name:und_x_variant":[
        "Girzhovo",
        "Girzhevo"
    ],
    "wof:name":"Hirzhove",
    "wof:placetype":"locality"
},
  "geometry": {"coordinates":[29.81563,47.10378],"type":"Point"}
}