{
  "type": "Feature",
  "properties": {
    "iso:country":"UA",
    "qs:a0":"\u0423\u043a\u0440\u0430\u0457\u043d\u0430",
    "qs:a1":"*\u0422\u0435\u0440\u043d\u043e\u043f\u0456\u043b\u044c\u0441\u044c\u043a\u0430",
    "qs:a1_alt":"Ternopil's'ka",
    "qs:a1r":"0",
    "qs:a2":"\u0417\u0431\u0430\u0440\u0430\u0437\u044c\u043a\u0438\u0439",
    "qs:a2_alt":"Zbaraz'kyi",
    "qs:adm0":"\u0423\u043a\u0440\u0430\u0457\u043d\u0430",
    "qs:la_lc":"*",
    "qs:level":"locality",
    "qs:loc":"\u0412\u0438\u0449\u0456 \u041b\u0443\u0431'\u044f\u043d\u043a\u0438",
    "qs:loc_alt":"Vyschi Lubianky",
    "qs:pop":0,
    "qs:type":"buffered point",
    "wof:name":"\u0412\u0438\u0449\u0456 \u041b\u0443\u0431'\u044f\u043d\u043a\u0438",
    "wof:placetype":"locality"
},
  "geometry": {"coordinates":[25.867588,49.654887],"type":"Point"}
}