{
  "type": "Feature",
  "properties": {
    "gn:admin1_code":"15.0",
    "gn:asciiname":"Kotovane",
    "gn:country_code":"UA",
    "gn:dem":310,
    "gn:feature_class":"P",
    "gn:feature_code":"PPL",
    "gn:name":"Kotovane",
    "gn:population":0,
    "gn:timezone":"Europe/Kiev",
    "iso:country":"UA",
    "name:ukr_x_preferred":[
        "Kotovane"
    ],
    "name:ukr_x_variant":[
        "\u041a\u043e\u0442\u043e\u0432\u0430\u043d\u0435"
    ],
    "name:und_x_variant":[
        "Kotovanya",
        "Kotovaniya"
    ],
    "wof:name":"Kotovane",
    "wof:placetype":"locality"
},
  "geometry": {"coordinates":[23.34671,49.44441],"type":"Point"}
}