{
  "type": "Feature",
  "properties": {
    "gn:population":2573,
    "iso:country":"UA",
    "name:azb_x_preferred":[
        "\u0645\u06cc\u06a9\u0648\u0644\u0627\u06cc\u0648\u06a9\u0627"
    ],
    "name:bel_x_preferred":[
        "\u041c\u044b\u043a\u0430\u043b\u0430\u0456\u045e\u043a\u0430"
    ],
    "name:cat_x_preferred":[
        "Nikol\u00e0ievka"
    ],
    "name:ceb_x_preferred":[
        "Mykolayivka"
    ],
    "name:crh_x_preferred":[
        "Nikolayevka"
    ],
    "name:deu_x_preferred":[
        "Mykolaiwka"
    ],
    "name:eng_x_preferred":[
        "Nikolayevka"
    ],
    "name:eng_x_variant":[
        "Mykolaivka"
    ],
    "name:epo_x_preferred":[
        "Nikolajevko"
    ],
    "name:fra_x_preferred":[
        "Mykola\u00efvka"
    ],
    "name:hye_x_preferred":[
        "\u0546\u056b\u056f\u0578\u056c\u0561\u0587\u056f\u0561"
    ],
    "name:nld_x_preferred":[
        "Nikolaevka"
    ],
    "name:ron_x_preferred":[
        "M\u00eekolaiivka"
    ],
    "name:rus_x_preferred":[
        "\u041d\u0438\u043a\u043e\u043b\u0430\u0435\u0432\u043a\u0430"
    ],
    "name:swe_x_preferred":[
        "Mykolajivka"
    ],
    "name:ukr_x_preferred":[
        "\u041c\u0438\u043a\u043e\u043b\u0430\u0457\u0432\u043a\u0430"
    ],
    "name:urd_x_preferred":[
        "\u0645\u0626\u06a9\u0648\u0644\u0627\u06cc\u0648\u06a9\u0627"
    ],
    "name:zho_x_preferred":[
        "\u7c73\u79d1\u62c9\u4f0a\u592b\u5361"
    ],
    "qs:a0":"\u0423\u043a\u0440\u0430\u0457\u043d\u0430",
    "qs:a1":"*\u041a\u0440\u0438\u043c",
    "qs:a1_alt":"Krym",
    "qs:a1r":"0",
    "qs:a2":"\u0421\u0456\u043c\u0444\u0435\u0440\u043e\u043f\u043e\u043b\u044c\u0441\u044c\u043a\u0438\u0439",
    "qs:a2_alt":"Simferopol's'kyi",
    "qs:adm0":"\u0423\u043a\u0440\u0430\u0457\u043d\u0430",
    "qs:la_lc":"*",
    "qs:level":"locality",
    "qs:loc":"\u041c\u0438\u043a\u043e\u043b\u0430\u0457\u0432\u043a\u0430",
    "qs:loc_alt":"Mykolaivka",
    "qs:pop":0,
    "qs:type":"buffered point",
    "wd:wordcount":110,
    "wof:lang":[
        "eng"
    ],
    "wof:name":"\u041c\u0438\u043a\u043e\u043b\u0430\u0457\u0432\u043a\u0430",
    "wof:placetype":"locality",
    "wof:population":2573
},
  "geometry": {"coordinates":[33.605652,44.968612],"type":"Point"}
}