{
  "type": "Feature",
  "properties": {
    "gn:admin1_code":"26.0",
    "gn:asciiname":"Pryvil'ne",
    "gn:country_code":"UA",
    "gn:dem":83,
    "gn:feature_class":"P",
    "gn:feature_code":"PPL",
    "gn:name":"Pryvil\u2019ne",
    "gn:population":0,
    "gn:timezone":"Europe/Zaporozhye",
    "iso:country":"UA",
    "name:rus_x_preferred":[
        "Privol\u2019noye"
    ],
    "name:ukr_x_preferred":[
        "Pryvil\u2019ne"
    ],
    "name:ukr_x_variant":[
        "\u041f\u0440\u0438\u0432\u0456\u043b\u044c\u043d\u0435"
    ],
    "name:und_x_variant":[
        "Privol\u2019ny",
        "Privol\u2019nyy"
    ],
    "wof:name":"Pryvil'ne",
    "wof:placetype":"locality"
},
  "geometry": {"coordinates":[35.35194,47.11472],"type":"Point"}
}