{
  "type": "Feature",
  "properties": {
    "gn:admin1_code":"24.0",
    "gn:asciiname":"Dibrova",
    "gn:country_code":"UA",
    "gn:dem":154,
    "gn:feature_class":"P",
    "gn:feature_code":"PPL",
    "gn:name":"Dibrova",
    "gn:population":0,
    "gn:timezone":"Europe/Kiev",
    "iso:country":"UA",
    "name:ukr_x_preferred":[
        "Dibrova"
    ],
    "name:ukr_x_variant":[
        "\u0414\u0456\u0431\u0440\u043e\u0432\u0430"
    ],
    "name:und_x_variant":[
        "Donbrova",
        "Dubrova"
    ],
    "wof:name":"Dibrova",
    "wof:placetype":"locality"
},
  "geometry": {"coordinates":[25.12983,51.7377],"type":"Point"}
}