{
  "type": "Feature",
  "properties": {
    "iso:country":"UA",
    "name:eng_x_preferred":[
        "Marfovka"
    ],
    "name:rus_x_historical":[
        "\u0414\u0430\u0443\u0301\u0442-\u042d\u043b\u0438\u0301"
    ],
    "name:rus_x_preferred":[
        "\u0414\u0430\u0443\u0301\u0442-\u042d\u043b\u0438\u0301"
    ],
    "name:rus_x_variant":[
        "\u041c\u0430\u0440\u0444\u043e\u0432\u043a\u0430"
    ],
    "name:ukr_x_preferred":[
        "\u041c\u0430\u0440\u0444\u0456\u0432\u043a\u0430"
    ],
    "qs:a0":"\u0423\u043a\u0440\u0430\u0457\u043d\u0430",
    "qs:a1":"*\u041a\u0440\u0438\u043c",
    "qs:a1_alt":"Krym",
    "qs:a1r":"0",
    "qs:a2":"\u041b\u0435\u043d\u0456\u043d\u0441\u044c\u043a\u0438\u0439",
    "qs:a2_alt":"Lenins'kyi",
    "qs:adm0":"\u0423\u043a\u0440\u0430\u0457\u043d\u0430",
    "qs:la_lc":"*",
    "qs:level":"locality",
    "qs:loc":"\u041c\u0430\u0440\u0444\u0456\u0432\u043a\u0430",
    "qs:loc_alt":"Marfivka",
    "qs:pop":0,
    "qs:type":"buffered point",
    "wof:name":"\u041c\u0430\u0440\u0444\u0456\u0432\u043a\u0430",
    "wof:placetype":"locality"
},
  "geometry": {"coordinates":[36.083353,45.199808],"type":"Point"}
}