{
  "type": "Feature",
  "properties": {
    "gn:admin1_code":"4.0",
    "gn:asciiname":"Zatyshne",
    "gn:country_code":"UA",
    "gn:dem":101,
    "gn:feature_class":"P",
    "gn:feature_code":"PPL",
    "gn:name":"Zatyshne",
    "gn:population":0,
    "gn:timezone":"Europe/Kiev",
    "iso:country":"UA",
    "name:eng_x_preferred":[
        "Zatishnyy"
    ],
    "name:rus_x_preferred":[
        "\u0417\u0430\u0442\u0438\u0448\u043d\u043e\u0435"
    ],
    "name:ukr_x_preferred":[
        "Zatyshne"
    ],
    "name:ukr_x_variant":[
        "\u0417\u0430\u0442\u0438\u0448\u043d\u0435"
    ],
    "name:und_x_variant":[
        "Zatish\u2019ye",
        "Zatishnoye"
    ],
    "wof:name":"Zatyshne",
    "wof:placetype":"locality"
},
  "geometry": {"coordinates":[35.92958,48.81245],"type":"Point"}
}