{
  "type": "Feature",
  "properties": {
    "gn:admin1_code":"21.0",
    "gn:asciiname":"Terekhove",
    "gn:country_code":"UA",
    "gn:dem":158,
    "gn:feature_class":"P",
    "gn:feature_code":"PPL",
    "gn:name":"Terekhove",
    "gn:population":0,
    "gn:timezone":"Europe/Kiev",
    "iso:country":"UA",
    "name:ukr_x_preferred":[
        "Terekhove"
    ],
    "name:ukr_x_variant":[
        "\u0422\u0435\u0440\u0435\u0445\u043e\u0432\u0435"
    ],
    "name:und_x_variant":[
        "Terekhovo"
    ],
    "wof:name":"Terekhove",
    "wof:placetype":"locality"
},
  "geometry": {"coordinates":[33.22778,51.50621],"type":"Point"}
}