{
  "type": "Feature",
  "properties": {
    "gn:admin1_code":"4.0",
    "gn:asciiname":"Mazhary",
    "gn:country_code":"UA",
    "gn:dem":169,
    "gn:feature_class":"P",
    "gn:feature_code":"PPL",
    "gn:name":"Mazhary",
    "gn:population":0,
    "gn:timezone":"Europe/Kiev",
    "iso:country":"UA",
    "name:ukr_x_preferred":[
        "Mazhary"
    ],
    "name:ukr_x_variant":[
        "\u041c\u0430\u0436\u0430\u0440\u0438"
    ],
    "wof:name":"Mazhary",
    "wof:placetype":"locality"
},
  "geometry": {"coordinates":[35.55649000000001,48.17281],"type":"Point"}
}