{
  "type": "Feature",
  "properties": {
    "iso:country":"UA",
    "name:ara_x_preferred":[
        "\u0647\u0641\u0627\u0631\u062f\u064a\u064a\u0633\u0643\u064a"
    ],
    "name:crh_x_preferred":[
        "Gvardiyske"
    ],
    "name:deu_x_preferred":[
        "Hwardijske"
    ],
    "name:eng_x_preferred":[
        "Hvardiys'ke"
    ],
    "name:eng_x_variant":[
        "Gvardeyskoye",
        "Gvardiiske",
        "Spat",
        "Hvardiiske"
    ],
    "name:fra_x_preferred":[
        "Hvardi\u00efske"
    ],
    "name:hye_x_preferred":[
        "\u0533\u057e\u0561\u0580\u0564\u0565\u0575\u057d\u056f\u0578\u0565"
    ],
    "name:ita_x_preferred":[
        "Gvardijs'ke"
    ],
    "name:lav_x_preferred":[
        "Hvardijske"
    ],
    "name:ron_x_preferred":[
        "Hvardiiske"
    ],
    "name:rus_x_historical":[
        "\u0410\u043a\u0447\u043e\u0440\u0430\u0301"
    ],
    "name:rus_x_preferred":[
        "\u0413\u0432\u0430\u0440\u0434\u0435\u0439\u0441\u043a\u043e\u0435"
    ],
    "name:rus_x_variant":[
        "\u0410\u043a\u0447\u043e\u0440\u0430\u0301"
    ],
    "name:ukr_x_preferred":[
        "\u0413\u0432\u0430\u0440\u0434\u0456\u0439\u0441\u044c\u043a\u0435"
    ],
    "name:zho_x_preferred":[
        "\u683c\u74e6\u723e\u5b63\u897f\u514b"
    ],
    "qs:a0":"\u0423\u043a\u0440\u0430\u0457\u043d\u0430",
    "qs:a1":"*\u041a\u0440\u0438\u043c",
    "qs:a1_alt":"Krym",
    "qs:a1r":"0",
    "qs:a2":"\u041f\u0435\u0440\u0432\u043e\u043c\u0430\u0439\u0441\u044c\u043a\u0438\u0439",
    "qs:a2_alt":"Pervomais'kyi",
    "qs:adm0":"\u0423\u043a\u0440\u0430\u0457\u043d\u0430",
    "qs:la_lc":"*",
    "qs:level":"locality",
    "qs:loc":"\u0413\u0432\u0430\u0440\u0434\u0456\u0439\u0441\u044c\u043a\u0435",
    "qs:loc_alt":"Hvardiis'ke",
    "qs:pop":0,
    "qs:type":"buffered point",
    "wd:wordcount":99,
    "wof:name":"\u0413\u0432\u0430\u0440\u0434\u0456\u0439\u0441\u044c\u043a\u0435",
    "wof:placetype":"locality"
},
  "geometry": {"coordinates":[33.980234,45.586702],"type":"Point"}
}