{
  "type": "Feature",
  "properties": {
    "gn:admin1_code":"4.0",
    "gn:asciiname":"Nazarenky",
    "gn:country_code":"UA",
    "gn:dem":71,
    "gn:feature_class":"P",
    "gn:feature_code":"PPL",
    "gn:name":"Nazarenky",
    "gn:population":0,
    "gn:timezone":"Europe/Kiev",
    "iso:country":"UA",
    "name:ukr_x_preferred":[
        "Nazarenky"
    ],
    "name:ukr_x_variant":[
        "\u041d\u0430\u0437\u0430\u0440\u0435\u043d\u043a\u0438"
    ],
    "wof:name":"Nazarenky",
    "wof:placetype":"locality"
},
  "geometry": {"coordinates":[34.35278,48.9911],"type":"Point"}
}