{
  "type": "Feature",
  "properties": {
    "iso:country":"UA",
    "name:eng_x_preferred":[
        "Ul'yanovka"
    ],
    "name:rus_x_preferred":[
        "\u0423\u043b\u044c\u044f\u043d\u043e\u0432\u043a\u0430"
    ],
    "name:ukr_x_preferred":[
        "Ulyanivka"
    ],
    "name:ukr_x_variant":[
        "\u0423\u043b\u044f\u043d\u0456\u0432\u043a\u0430"
    ],
    "name:und_x_variant":[
        "Ul\u2019yanovka"
    ],
    "qs:a0":"\u0423\u043a\u0440\u0430\u0457\u043d\u0430",
    "qs:a1":"*\u0421\u0443\u043c\u0441\u044c\u043a\u0430",
    "qs:a1_alt":"Sums'ka",
    "qs:a1r":"0",
    "qs:a2":"\u0411\u0456\u043b\u043e\u043f\u0456\u043b\u044c\u0441\u044c\u043a\u0438\u0439",
    "qs:a2_alt":"Bilopil's'kyi",
    "qs:adm0":"\u0423\u043a\u0440\u0430\u0457\u043d\u0430",
    "qs:la_lc":"*",
    "qs:level":"locality",
    "qs:loc":"\u0423\u043b\u044f\u043d\u0456\u0432\u043a\u0430",
    "qs:loc_alt":"Ulianivka",
    "qs:pop":0,
    "qs:type":"buffered point",
    "wof:name":"\u0423\u043b\u044f\u043d\u0456\u0432\u043a\u0430",
    "wof:placetype":"locality"
},
  "geometry": {"coordinates":[34.306938,50.982041],"type":"Point"}
}