{
  "type": "Feature",
  "properties": {
    "gn:admin1_code":"5.0",
    "gn:asciiname":"Vasyukivka",
    "gn:country_code":"UA",
    "gn:dem":85,
    "gn:feature_class":"P",
    "gn:feature_code":"PPL",
    "gn:name":"Vasyukivka",
    "gn:population":0,
    "gn:timezone":"Europe/Kiev",
    "iso:country":"UA",
    "name:ukr_x_preferred":[
        "Vasyukivka"
    ],
    "name:ukr_x_variant":[
        "\u0412\u0430\u0441\u044e\u043a\u0456\u0432\u043a\u0430"
    ],
    "name:und_x_variant":[
        "Voroshilovka",
        "Vasyukovka"
    ],
    "wof:name":"Vasyukivka",
    "wof:placetype":"locality"
},
  "geometry": {"coordinates":[37.99574000000001,48.74089],"type":"Point"}
}