{
  "type": "Feature",
  "properties": {
    "gn:admin1_code":"21.0",
    "gn:asciiname":"Atynsk",
    "gn:country_code":"UA",
    "gn:dem":134,
    "gn:feature_class":"P",
    "gn:feature_code":"PPL",
    "gn:name":"Atynsk",
    "gn:population":0,
    "gn:timezone":"Europe/Kiev",
    "iso:country":"UA",
    "wof:name":"Atynsk",
    "wof:placetype":"locality"
},
  "geometry": {"coordinates":[34.21167,51.22389],"type":"Point"}
}