{
  "type": "Feature",
  "properties": {
    "gn:admin1_code":"18.0",
    "gn:asciiname":"Poteryayky",
    "gn:country_code":"UA",
    "gn:dem":96,
    "gn:feature_class":"P",
    "gn:feature_code":"PPL",
    "gn:name":"Poteryayky",
    "gn:population":0,
    "gn:timezone":"Europe/Kiev",
    "iso:country":"UA",
    "name:ukr_x_preferred":[
        "Poteryayky"
    ],
    "name:ukr_x_variant":[
        "\u041f\u043e\u0442\u0435\u0440\u044f\u0439\u043a\u0438"
    ],
    "name:und_x_variant":[
        "Poteryayevka",
        "Poteryayki"
    ],
    "wof:name":"Poteryayky",
    "wof:placetype":"locality"
},
  "geometry": {"coordinates":[34.08821,49.70177],"type":"Point"}
}