{
  "type": "Feature",
  "properties": {
    "gn:admin1_code":"14.0",
    "gn:asciiname":"Krasnyy Kavkaz",
    "gn:cc2":"UA",
    "gn:country_code":"UA",
    "gn:dem":139,
    "gn:feature_class":"P",
    "gn:feature_code":"PPL",
    "gn:name":"Krasnyy Kavkaz",
    "gn:population":0,
    "gn:timezone":"Europe/Zaporozhye",
    "iso:country":"UA",
    "name:und_x_variant":[
        "Krasny Kavkaz",
        "Krasnyy Kavkaz"
    ],
    "wof:name":"Krasnyy Kavkaz",
    "wof:placetype":"locality"
},
  "geometry": {"coordinates":[39.65972,48.74028],"type":"Point"}
}